Workbook

Sheet 总报价表
A1: SIM-CATALOG-WORKFLOW 两款共用零件＋球壳模拟 混装内部报价明细
A2: 客户：TEST 数量：1000 创建：2026-09-30 02:03:24
A6: 二、注塑部分
A7: 模号 | B7: 零件名称 | C7: 材质 | D7: 啤净重(g) | E7: 料损耗 0% | F7: 料价 HK$/g | G7: 原料单价 HK$ | H7: 机台 | I7: 啤价 HK$/啤 | J7: 套数 | K7: 机型 | L7: 目标数 | M7: 周期(秒) | N7: 成品金额 HK$ | O7: 日费用 HKD | P7: 日产啤次 | Q7: 出模数 | R7: 需求量（手填） | S7: 完成啤次 | T7: 阶段每穴费用 | U7: 累计啤工 HKD | V7: 每件啤工 HKD | W7: 每啤价 HKD | X7: 上一阶段完成啤次
A8: M1 | B8: 共用盒子 | C8: PP | D8: 2.06 | E8: =('总报价表'!D8)*1 -> 2.06 | F8: =45.4/454 -> 0.1 | G8: =('总报价表'!E8)*('总报价表'!F8) -> 0.206 | I8: ='啤机明细'!I2 -> 0.1 | J8: ='啤机明细'!J2 -> 1 | L8: ='啤机明细'!L2 -> 100 | N8: ='啤机明细'!N2 -> 0.306 | O8: 40 | P8: 100 | Q8: 4 | R8: 100 | S8: =('总报价表'!R8)/('总报价表'!Q8) -> 25 | T8: =IF('总报价表'!S8=0,0,('总报价表'!S8-'总报价表'!X8)*'总报价表'!W8/(IF('总报价表'!S8>='总报价表'!S8,('总报价表'!Q8),0))/(IF('总报价表'!S8='总报价表'!S8,1,0))) -> 2.5 | U8: =(IF('总报价表'!S8<='总报价表'!S8,'总报价表'!T8,0))*('总报价表'!Q8) -> 10 | V8: =IFERROR('总报价表'!U8/('总报价表'!R8),0) -> 0.1 | W8: =('总报价表'!O8)/('总报价表'!P8) -> 0.4 | X8: =MAX(0,IF('总报价表'!S8<'总报价表'!S8,'总报价表'!S8,0)) -> 0
A9: M2 | B9: A主体 | C9: PVC | D9: 1.03 | E9: =('总报价表'!D9)*1 -> 1.03 | F9: =90.8/454 -> 0.2 | G9: =('总报价表'!E9)*('总报价表'!F9) -> 0.206 | I9: ='啤机明细'!I3 -> 0.2 | J9: ='啤机明细'!J3 -> 1 | L9: ='啤机明细'!L3 -> 100 | N9: ='啤机明细'!N3 -> 0.406 | O9: 40 | P9: 100 | Q9: 2 | R9: 100 | S9: =('总报价表'!R9)/('总报价表'!Q9) -> 50 | T9: =IF('总报价表'!S9=0,0,('总报价表'!S9-'总报价表'!X9)*'总报价表'!W9/(IF('总报价表'!S9>='总报价表'!S9,('总报价表'!Q9),0))/(IF('总报价表'!S9='总报价表'!S9,1,0))) -> 10 | U9: =(IF('总报价表'!S9<='总报价表'!S9,'总报价表'!T9,0))*('总报价表'!Q9) -> 20 | V9: =IFERROR('总报价表'!U9/('总报价表'!R9),0) -> 0.2 | W9: =('总报价表'!O9)/('总报价表'!P9) -> 0.4 | X9: =MAX(0,IF('总报价表'!S9<'总报价表'!S9,'总报价表'!S9,0)) -> 0
A10: M3 | B10: B主体 | C10: PVC | D10: 3.09 | E10: =('总报价表'!D10)*1 -> 3.09 | F10: =45.4/454 -> 0.1 | G10: =('总报价表'!E10)*('总报价表'!F10) -> 0.309 | I10: ='啤机明细'!I4 -> 0.3 | J10: ='啤机明细'!J4 -> 1 | L10: ='啤机明细'!L4 -> 100 | N10: ='啤机明细'!N4 -> 0.609 | O10: 180 | P10: 100 | Q10: 6 | R10: 100 | S10: =('总报价表'!R10)/('总报价表'!Q10) -> 16.666667 | T10: =IF('总报价表'!S10=0,0,('总报价表'!S10-'总报价表'!X10)*'总报价表'!W10/(IF('总报价表'!S10>='总报价表'!S10,('总报价表'!Q10),0))/(IF('总报价表'!S10='总报价表'!S10,1,0))) -> 5 | U10: =(IF('总报价表'!S10<='总报价表'!S10,'总报价表'!T10,0))*('总报价表'!Q10) -> 30 | V10: =IFERROR('总报价表'!U10/('总报价表'!R10),0) -> 0.3 | W10: =('总报价表'!O10)/('总报价表'!P10) -> 1.8 | X10: =MAX(0,IF('总报价表'!S10<'总报价表'!S10,'总报价表'!S10,0)) -> 0
A11: M4 | B11: 球壳 | C11: PP | D11: 5 | E11: =('总报价表'!D11)*1 -> 5 | F11: =45.4/454 -> 0.1 | G11: =('总报价表'!E11)*('总报价表'!F11) -> 0.5 | I11: ='啤机明细'!I5 -> 0.1 | J11: ='啤机明细'!J5 -> 1 | L11: ='啤机明细'!L5 -> 100 | N11: ='啤机明细'!N5 -> 0.6 | O11: 20 | P11: 100 | Q11: 2 | R11: 0 | S11: =('总报价表'!R11)/('总报价表'!Q11) -> 0 | T11: =IF('总报价表'!S11=0,0,('总报价表'!S11-'总报价表'!X11)*'总报价表'!W11/(IF('总报价表'!S11>='总报价表'!S11,('总报价表'!Q11),0))/(IF('总报价表'!S11='总报价表'!S11,1,0))) -> 0 | U11: =(IF('总报价表'!S11<='总报价表'!S11,'总报价表'!T11,0))*('总报价表'!Q11) -> 0 | V11: ='总报价表'!W11/('总报价表'!Q11) -> 0.1 | W11: =('总报价表'!O11)/('总报价表'!P11) -> 0.2 | X11: =MAX(0,IF('总报价表'!S11<'总报价表'!S11,'总报价表'!S11,0)) -> 0
A12: 总合计 | B12: 零件单价合计 | G12: ='啤机明细'!G6 -> 1.221 | I12: ='啤机明细'!I6 -> 0.7 | N12: ='啤机明细'!N6 -> 1.921
A15: 纸箱 / 运费计算
A16: 名称 | B16: L (inch) | C16: W | D16: H
A17: 产品尺寸（英寸） | E17: CU.FT | F17: 箱价 (HK$) | G17: 数量
A18: 主纸箱 | E18: =IF(COUNT(B18:D18)=3,B18*C18*D18/1728,0) -> 0 | G18: 1
A19: 主平卡
A20: 运输方案 | B20: 每箱箱积 CUFT | C20: 每箱包装数 | D20: 货柜容量 CUFT | E20: 整柜费用 HKD | F20: 运费占比 | G20: 吊柜费占比 | H20: 每柜箱数 | I20: 运费 HKD / 包装 | J20: 吊柜费 HKD / 包装 | K20: 合计 HKD / 包装
A21: 出厂价 | B21: =E18 -> 0 | C21: =G18 -> 1 | D21: 0 | E21: 0 | F21: 0.48 | G21: 0.52 | H21: =IFERROR(MAX(ROUND(D21/B21,0),1),0) -> 0 | I21: =IFERROR(E21/H21/C21*F21,0) -> 0 | J21: =IFERROR(E21/H21/C21*G21,0) -> 0 | K21: =SUM(I21:J21) -> 0
A22: 纸箱尺寸、纸质及单价尚未填写；上表箱积和装箱数用于运输分摊。
A25: 各小产品费用明细及合计（HKD）
A28: 金额单位：HKD ｜ 分类金额为原始成本；NA后金额＝成本合计×NA比例；共有费用每包装计一次。
A29: 货号 | B29: 品名 | C29: 进口料 | D29: 国内料 | E29: 啤工 | F29: 喷工 | G29: 油漆 | H29: 装工＋ 入纸袋／包装 | I29: 五金 | J29: 马达 | K29: 吸塑 | L29: 胶袋 | M29: 彩盒/内咭 | N29: 电池 | O29: 产品利宝 | P29: 彩盒利宝 | Q29: 电镀 | R29: 其他外购 | S29: 纸箱 | T29: 电子 | U29: 吹气 | V29: 搪胶 | W29: 车发 | X29: 车衣 | Y29: 成本合计 HKD | Z29: NA比例 | AA29: NA比例后合计 HKD
A30: A | B30: 产品A | C30: =((('总报价表'!G8)*1)) -> 0.206 | D30: =((('总报价表'!G9)*1)) -> 0.206 | E30: =((('总报价表'!V8*1)+('总报价表'!V9*1))) -> 0.3 | F30: =0*0.7 -> 0 | G30: =0*0.3 -> 0 | H30: =0+0 -> 0 | I30: =0 -> 0 | J30: =0 -> 0 | K30: =0 -> 0 | L30: =0 -> 0 | M30: =0 -> 0 | N30: =0 -> 0 | O30: =0-P30 -> 0 | P30: 0 | Q30: =0 -> 0 | R30: =0 -> 0 | S30: =0 -> 0 | T30: =0 -> 0 | U30: =0 -> 0 | V30: =0 -> 0 | W30: =0 -> 0 | X30: =0-'总报价表'!W30 -> 0 | Y30: =SUM(C30:X30) -> 0.712 | Z30: 0.5 | AA30: =Y30*Z30 -> 0.356
A31: B | B31: 产品B | C31: =((('总报价表'!G8)*1)) -> 0.206 | D31: =((('总报价表'!G10)*2)) -> 0.618 | E31: =((('总报价表'!V8*1)+('总报价表'!V10*2))) -> 0.7 | F31: =0*0.7 -> 0 | G31: =0*0.3 -> 0 | H31: =0+0 -> 0 | I31: =0 -> 0 | J31: =0 -> 0 | K31: =0 -> 0 | L31: =0 -> 0 | M31: =0 -> 0 | N31: =0 -> 0 | O31: =0-P31 -> 0 | P31: 0 | Q31: =0 -> 0 | R31: =0 -> 0 | S31: =0 -> 0 | T31: =0 -> 0 | U31: =0 -> 0 | V31: =0 -> 0 | W31: =0 -> 0 | X31: =0-'总报价表'!W31 -> 0 | Y31: =SUM(C31:X31) -> 1.524 | Z31: 0.5 | AA31: =Y31*Z31 -> 0.762
A32: 小产品合计 | B32: 2款，不含共有费用 | C32: =SUM(C30:C31) -> 0.412 | D32: =SUM(D30:D31) -> 0.824 | E32: =SUM(E30:E31) -> 1 | F32: =SUM(F30:F31) -> 0 | G32: =SUM(G30:G31) -> 0 | H32: =SUM(H30:H31) -> 0 | I32: =SUM(I30:I31) -> 0 | J32: =SUM(J30:J31) -> 0 | ... Y32: =SUM(Y30:Y31) -> 2.236 | AA32: =SUM(AA30:AA31) -> 1.118
A33: 全部小产品平均价（NA） | B33: 各款分类金额×NA比例，再求和 | C33: =SUMPRODUCT(C30:C31,Z30:Z31) -> 0.206 | D33: =SUMPRODUCT(D30:D31,Z30:Z31) -> 0.412 | E33: =SUMPRODUCT(E30:E31,Z30:Z31) -> 0.5 | F33: =SUMPRODUCT(F30:F31,Z30:Z31) -> 0 | G33: =SUMPRODUCT(G30:G31,Z30:Z31) -> 0 | H33: =SUMPRODUCT(H30:H31,Z30:Z31) -> 0 | I33: =SUMPRODUCT(I30:I31,Z30:Z31) -> 0 | J33: =SUMPRODUCT(J30:J31,Z30:Z31) -> 0 | K33: =SUMPRODUCT(K30:K31,Z30:Z31) -> 0 | L33: =SUMPRODUCT(L30:L31,Z30:Z31) -> 0 | M33: =SUMPRODUCT(M30:M31,Z30:Z31) -> 0 | N33: =SUMPRODUCT(N30:N31,Z30:Z31) -> 0 | O33: =SUMPRODUCT(O30:O31,Z30:Z31) -> 0 | P33: =SUMPRODUCT(P30:P31,Z30:Z31) -> 0 | Q33: =SUMPRODUCT(Q30:Q31,Z30:Z31) -> 0 | R33: =SUMPRODUCT(R30:R31,Z30:Z31) -> 0 | S33: =SUMPRODUCT(S30:S31,Z30:Z31) -> 0 | T33: =SUMPRODUCT(T30:T31,Z30:Z31) -> 0 | U33: =SUMPRODUCT(U30:U31,Z30:Z31) -> 0 | V33: =SUMPRODUCT(V30:V31,Z30:Z31) -> 0 | W33: =SUMPRODUCT(W30:W31,Z30:Z31) -> 0 | X33: =SUMPRODUCT(X30:X31,Z30:Z31) -> 0 | Y33: =SUMPRODUCT(Y30:Y31,Z30:Z31) -> 1.118 | AA33: =SUM(AA30:AA31) -> 1.118
A34: 共有费用 | B34: 每包装共有项目 | C34: =((('总报价表'!G11)*1)) -> 0.5 | D34: =0 -> 0 | E34: =((('总报价表'!V11*1))) -> 0.1 | F34: =0*0.7 -> 0 | G34: =0*0.3 -> 0 | H34: =0+0 -> 0 | I34: =0 -> 0 | J34: =0 -> 0 | K34: =0 -> 0 | L34: =0 -> 0 | M34: =0 -> 0 | N34: =0 -> 0 | O34: =0-P34 -> 0 | P34: 0 | Q34: =0 -> 0 | R34: =0 -> 0 | S34: =0 -> 0 | T34: =0 -> 0 | U34: =0 -> 0 | V34: =0 -> 0 | W34: =0 -> 0 | X34: =0-'总报价表'!W34 -> 0 | Y34: =SUM(C34:X34) -> 0.6 | Z34: 每包装一次 | AA34: =Y34 -> 0.6
A35: 合计 | B35: NA平均价＋共有费用 | C35: =C33*2+C34 -> 0.912 | D35: =D33*2+D34 -> 0.824 | E35: =E33*2+E34 -> 1.1 | F35: =F33*2+F34 -> 0 | G35: =G33*2+G34 -> 0 | H35: =H33*2+H34 -> 0 | I35: =I33*2+I34 -> 0 | J35: =J33*2+J34 -> 0 | ... Y35: =Y33*2+Y34 -> 2.836 | AA35: =AA33*2+AA34 -> 2.836
A38: 十一、出货价算价
A39: 金额按每包装计算 · 蓝色列为报客方案
A43: 报价计算 · HKD / USD | G43: 运输方案对比 · HKD / 包装
A44: 项目 | B44: 参数 | C44: 出厂价（报客方案） | G44: 运输方案 | I44: 运费 HKD | J44: 吊柜费 HKD | K44: 合计 HKD / 包装
A45: 主体小计 HKD（不含车缝、电子） | C45: =('总报价表'!E35)+('总报价表'!H35)+('总报价表'!F35)+('总报价表'!G35)+('总报价表'!C35)+('总报价表'!D35)+('总报价表'!U35)+('总报价表'!V35)+('总报价表'!I35)+('总报价表'!J35)+('总报价表'!K35)+('总报价表'!L35)+('总报价表'!M35)+('总报价表'!N35)+('总报价表'!O35+'总报价表'!P35)+('总报价表'!Q35)+('总报价表'!R35)+('总报价表'!S35)+(((((((((0*30%*0)))+0)))*'总报价表'!C97)+(((((((0*30%*0)))+0)))*'总报价表'!C98))*2+((((((0*30%*0)))+0)))) -> 2.836 | G45: YT 40柜 | K45: 参数未齐
A46: 运费 HKD | C46: ='总报价表'!I21 -> 0 | G46: YT 20柜 | K46: 参数未齐
A47: 吊柜费 HKD | C47: ='总报价表'!J21 -> 0 | G47: HK 40柜 | K47: 参数未齐
A48: 含运 HKD | C48: =SUM(C45:C47) -> 2.836 | G48: HK 20柜 | K48: 参数未齐
A49: 主体码点 × | B49: =1.1 -> 1.1 | C49: =C48*$B$49 -> 3.1196 | G49: YT 5吨车 | K49: 参数未齐
A50: 车缝 HKD | C50: =('总报价表'!W35)+('总报价表'!X35) -> 0 | G50: YT 10吨车 | K50: 参数未齐
A51: 车缝码点 × | B51: =1.1 -> 1.1 | C51: =C50*$B$51 -> 0 | G51: HK 5吨车 | K51: 参数未齐
A52: 电子 HKD | C52: ='总报价表'!T35 -> 0 | G52: HK 10吨车 | K52: 参数未齐
A53: 电子码点 × | B53: =1.1 -> 1.1 | C53: =C52*$B$53 -> 0
A54: 码点后合计 HKD | C54: =C49+C51+C53 -> 3.1196
A55: 统一找数 ÷ | B55: =0.99 -> 0.99 | C55: =C54/$B$55 -> 3.1511111 | G55: 费用摊分（USD / 包装）
A56: TOTAL USD（HKD ÷ 汇率） | B56: =7.75 -> 7.75 | C56: =C55/$B$56 -> 0.40659498 | G56: 模具、手办及测试摊费 | K56: =C57 -> 0
A57: 模具、手办及测试摊费 USD | C57: =((0*'总报价表'!C97)+(0*'总报价表'!C98))*2+0 -> 0 | G57: 额外摊费 | K57: =C58 -> 0
A58: 额外摊费 USD | B58: =0 -> 0 | C58: =$B$58 -> 0
A59: TOTAL USD | C59: =SUM(C56:C58) -> 0.40659498
A60: 附加税 % | B60: =0 -> 0 | C60: =C59*$B$60/100 -> 0
A61: 附加税码点 × | B61: =1.1 -> 1.1 | C61: =C60*$B$61 -> 0
A62: 附加税找数 ÷ | B62: =0.99 -> 0.99 | C62: =C61/$B$62 -> 0
A63: TOTAL 报客价 USD | C63: =C59+C62 -> 0.40659498
A67: 十二、减税明细 / 成本汇总
A69: 一、出厂货价核
A70: 货价 | B70: 进口料 | C70: 国内料 | D70: 吹气 | E70: 搪胶 | F70: 车发 | G70: 车衣 | H70: 五金 | I70: 电子 | J70: 马达 | K70: 吸塑 | L70: 胶袋
A71: =C63*$B$56 -> 3.1511111 | B71: ='总报价表'!C35 -> 0.912 | C71: ='总报价表'!D35 -> 0.824 | D71: ='总报价表'!U35 -> 0 | E71: ='总报价表'!V35 -> 0 | F71: ='总报价表'!W35 -> 0 | G71: ='总报价表'!X35 -> 0 | H71: ='总报价表'!I35 -> 0 | I71: ='总报价表'!T35 -> 0 | J71: ='总报价表'!J35 -> 0 | K71: ='总报价表'!K35 -> 0 | L71: ='总报价表'!L35 -> 0
A73: 二、包装 / 外购
A74: 彩盒/内咭 | B74: 未减税前码数 | C74: 减税后码数 | D74: 电池 | E74: 利宝 | F74: 电镀 | G74: 其他外购 | H74: 纸箱 | I74: 运费 | J74: 吊柜费 | K74: 杂项
A75: ='总报价表'!M35 -> 0 | B75: =IFERROR(A71/K79,0) -> 1.1111111 | C75: =IFERROR(A71/(K79-J85),0) -> 1.1495203 | D75: ='总报价表'!N35 -> 0 | E75: ='总报价表'!O35+'总报价表'!P35 -> 0 | F75: ='总报价表'!Q35 -> 0 | G75: ='总报价表'!R35 -> 0 | H75: ='总报价表'!S35 -> 0 | I75: =C46 -> 0 | J75: =C47 -> 0 | K75: ='总报价表'!AA99*2+((((((0*30%*0)))+0)))+C60*$B$56 -> 0
A77: 三、人工 & 成本汇总
A78: 啤工 | B78: 喷油工 | C78: 油漆 | D78: 装配工 | E78: 不含人工成本 | F78: 人工比例 | G78: 毛利 | H78: 毛利率 | I78: 利润 | J78: 利润率 | K78: 总成本
A79: ='总报价表'!E35 -> 1.1 | B79: ='总报价表'!F35 -> 0 | C79: ='总报价表'!G35 -> 0 | D79: ='总报价表'!H35 -> 0 | E79: =B71+C71+D71+E71+F71+G71+H71+I71+J71+K71+L71+A75+D75+E75+F75+G75+H75+I75+J75+K75+C79 -> 1.736 | F79: =IFERROR((A79+B79+D79)/A71,0) -> 0.34908322 | G79: =A71-E79 -> 1.4151111 | H79: =IFERROR(G79/A71,0) -> 0.44908322 | I79: =A71-K79 -> 0.31511111 | J79: =IFERROR(I79/A71,0) -> 0.1 | K79: =E79+A79+B79+D79 -> 2.836
A81: 四、减税明细
A82: 含税13%类成本 | B82: 纸箱类 | C82: 含税1% | D82: 搪胶类3% | E82: 车发类13% | F82: 车衣类13% | G82: 吸塑类6% | H82: 运费类9% | I82: 含税13%类 | J82: 合计减税
A83: =C71+H71+J71+A75+D75+E75+G75+C79+L71 -> 0.824 | B83: =H75 -> 0 | C83: =F75 -> 0 | D83: =E71 -> 0 | E83: =F71 -> 0 | F83: =G71 -> 0 | G83: =K71 -> 0 | H83: =I75 -> 0 | I83: =A83 -> 0.824
B84: 0.1 | C84: 0.0099 | D84: 0.03 | E84: 0.115 | F84: 0.115 | G84: 0.06 | H84: 0.0826 | I84: 0.115 | J84: 税率 %
A85: — | B85: =B83*B84 -> 0 | C85: =C83*C84 -> 0 | D85: =D83*D84 -> 0 | E85: =E83*E84 -> 0 | F85: =F83*F84 -> 0 | G85: =G83*G84 -> 0 | H85: =H83*H84 -> 0 | I85: =I83*I84 -> 0.09476 | J85: =SUM(B85:I85) -> 0.09476
A87: 合计减税 | G87: =J85 -> 0.09476
A88: 减税后成本 | G88: =K79-J85 -> 2.74124
A89: 减税后毛利 | G89: =G79+J85 -> 1.5098711
A90: 减税后毛利率 | G90: =IFERROR((G79+J85)/A71,0) -> 0.47915515
A91: 减税后利润 | G91: =I79+J85 -> 0.40987111
A92: 减税后利润率 | G92: =IFERROR((I79+J85)/A71,0) -> 0.13007193
A95: 附录：NA加权成本明细
A96: 货号 | B96: 小产品 | C96: NA比例 | D96: 啤工 HKD | E96: 装配人工 HKD | F96: 喷油人工 HKD | G96: 油料 HKD | H96: 进口塑胶 HKD | I96: 国产塑胶 HKD | J96: 吹气 HKD | K96: 搪胶 HKD | L96: 车发 HKD | M96: 车衣 HKD | N96: 五金 HKD | O96: 电子 HKD | P96: 马达 HKD | Q96: 吸塑 HKD | R96: 胶袋 HKD | S96: 彩盒/内咭 HKD | T96: 电池 HKD | U96: 利宝 HKD | V96: 电镀 HKD | W96: 其他外购 HKD | X96: 纸箱 HKD | Y96: 运费 HKD | Z96: 吊柜 HKD | AA96: 印尼运费 HKD | AB96: 合计 HKD
A97: A | B97: 产品A | C97: ='总报价表'!Z30 -> 0.5 | D97: =('总报价表'!E30)*$C97 -> 0.15 | E97: =('总报价表'!H30)*$C97 -> 0 | F97: =('总报价表'!F30)*$C97 -> 0 | G97: =('总报价表'!G30)*$C97 -> 0 | H97: =((('总报价表'!G8)*1))*$C97 -> 0.103 | I97: =((('总报价表'!G9)*1))*$C97 -> 0.103 | J97: =('总报价表'!U30)*$C97 -> 0 | K97: =('总报价表'!V30)*$C97 -> 0 | L97: =('总报价表'!W30)*$C97 -> 0 | M97: =('总报价表'!X30)*$C97 -> 0 | N97: =('总报价表'!I30)*$C97 -> 0 | O97: =('总报价表'!T30)*$C97 -> 0 | P97: =('总报价表'!J30)*$C97 -> 0 | Q97: =('总报价表'!K30)*$C97 -> 0 | R97: =('总报价表'!L30)*$C97 -> 0 | S97: =('总报价表'!M30)*$C97 -> 0 | T97: =('总报价表'!N30)*$C97 -> 0 | U97: =0*$C97 -> 0 | V97: =('总报价表'!Q30)*$C97 -> 0 | W97: =('总报价表'!R30)*$C97 -> 0 | X97: =('总报价表'!S30)*$C97 -> 0 | Y97: =0*$C97 -> 0 | Z97: =0*$C97 -> 0 | AA97: =((((((0*30%*0)))+0)))*$C97 -> 0 | AB97: =SUM(D97:AA97) -> 0.356
A98: B | B98: 产品B | C98: ='总报价表'!Z31 -> 0.5 | D98: =('总报价表'!E31)*$C98 -> 0.35 | E98: =('总报价表'!H31)*$C98 -> 0 | F98: =('总报价表'!F31)*$C98 -> 0 | G98: =('总报价表'!G31)*$C98 -> 0 | H98: =((('总报价表'!G8)*1))*$C98 -> 0.103 | I98: =((('总报价表'!G10)*2))*$C98 -> 0.309 | J98: =('总报价表'!U31)*$C98 -> 0 | K98: =('总报价表'!V31)*$C98 -> 0 | L98: =('总报价表'!W31)*$C98 -> 0 | M98: =('总报价表'!X31)*$C98 -> 0 | N98: =('总报价表'!I31)*$C98 -> 0 | O98: =('总报价表'!T31)*$C98 -> 0 | P98: =('总报价表'!J31)*$C98 -> 0 | Q98: =('总报价表'!K31)*$C98 -> 0 | R98: =('总报价表'!L31)*$C98 -> 0 | S98: =('总报价表'!M31)*$C98 -> 0 | T98: =('总报价表'!N31)*$C98 -> 0 | U98: =0*$C98 -> 0 | V98: =('总报价表'!Q31)*$C98 -> 0 | W98: =('总报价表'!R31)*$C98 -> 0 | X98: =('总报价表'!S31)*$C98 -> 0 | Y98: =0*$C98 -> 0 | Z98: =0*$C98 -> 0 | AA98: =((((((0*30%*0)))+0)))*$C98 -> 0 | AB98: =SUM(D98:AA98) -> 0.762
A99: 分类平均价 | B99: 共有费用另计 | C99: =SUM(C97:C98) -> 1 | D99: =SUM(D97:D98) -> 0.5 | E99: =SUM(E97:E98) -> 0 | F99: =SUM(F97:F98) -> 0 | G99: =SUM(G97:G98) -> 0 | H99: =SUM(H97:H98) -> 0.206 | I99: =SUM(I97:I98) -> 0.412 | J99: =SUM(J97:J98) -> 0 | ... AB99: =SUM(AB97:AB98) -> 1.118

Sheet 模具报价
A1: SIM-CATALOG-WORKFLOW 两款共用零件＋球壳模拟 混装模具报价
A2: 客户：TEST 数量：1000 创建：2026-09-30 02:03:24
A4: 货号 | B4: 品名 | C4: 序号 | D4: 模具名称 | E4: 模号 | F4: 模胚类型 | G4: 材质 | H4: 出模数 | I4: 套数 | J4: 周期(秒) | K4: 模具尺寸 | L4: 图 片 | N4: 模具价格（RMB） | O4: 模具价格（USD） | P4: 模价 HKD

Sheet 啤机明细
A1: 模号 | B1: 零件名称 | C1: 材质 | D1: 啤净重(g) | E1: 料损耗 0% | F1: 料价 HK$/g | G1: 原料单价 HK$ | H1: 机台 | I1: 啤价 HK$/啤 | J1: 套数 | K1: 机型 | L1: 目标数 | M1: 周期(秒) | N1: 成品金额 HK$
A2: M1 | B2: 共用盒子 | C2: PP | D2: ='总报价表'!D8 -> 2.06 | E2: ='总报价表'!E8 -> 2.06 | F2: ='总报价表'!F8 -> 0.1 | G2: ='总报价表'!G8 -> 0.206 | I2: =('总报价表'!V8*1)/1 -> 0.1 | J2: 1 | L2: 100 | N2: =G2+I2 -> 0.306
A3: M2 | B3: A主体 | C3: PVC | D3: ='总报价表'!D9 -> 1.03 | E3: ='总报价表'!E9 -> 1.03 | F3: ='总报价表'!F9 -> 0.2 | G3: ='总报价表'!G9 -> 0.206 | I3: =('总报价表'!V9*1)/1 -> 0.2 | J3: 1 | L3: 100 | N3: =G3+I3 -> 0.406
A4: M3 | B4: B主体 | C4: PVC | D4: ='总报价表'!D10 -> 3.09 | E4: ='总报价表'!E10 -> 3.09 | F4: ='总报价表'!F10 -> 0.1 | G4: ='总报价表'!G10 -> 0.309 | I4: =('总报价表'!V10*2)/2 -> 0.3 | J4: 1 | L4: 100 | N4: =G4+I4 -> 0.609
A5: M4 | B5: 球壳 | C5: PP | D5: ='总报价表'!D11 -> 5 | E5: ='总报价表'!E11 -> 5 | F5: ='总报价表'!F11 -> 0.1 | G5: ='总报价表'!G11 -> 0.5 | I5: =('总报价表'!V11*1)/1 -> 0.1 | J5: 1 | L5: 100 | N5: =G5+I5 -> 0.6
A6: 总合计 | B6: 零件单价合计 | G6: =SUM(G2:G5) -> 1.221 | I6: =SUM(I2:I5) -> 0.7 | N6: =SUM(N2:N5) -> 1.921

Sheet 吹气明细
A1: 货号 | B1: 小产品名称 | C1: 部门费用 HKD（未乘NA） | D1: NA比例 | E1: NA后金额 HKD
A2: A | B2: 产品A | C2: =0 -> 0 | D2: ='总报价表'!Z30 -> 0.5 | E2: =C2*D2 -> 0
A3: B | B3: 产品B | C3: =0 -> 0 | D3: ='总报价表'!Z31 -> 0.5 | E3: =C3*D3 -> 0
A4: 共有 | B4: 每包装共有项目 | C4: =0 -> 0 | D4: 1 | E4: =C4*D4 -> 0
A7: A · 产品A
A8: 啤机部·吹气明细
A11: B · 产品B
A12: 啤机部·吹气明细
A15: 共有 · 每包装共有项目
A16: 啤机部·吹气明细

Sheet 电子明细
A1: 货号 | B1: 小产品名称 | C1: 部门费用 HKD（未乘NA） | D1: NA比例 | E1: NA后金额 HKD
A2: A | B2: 产品A | C2: =0 -> 0 | D2: ='总报价表'!Z30 -> 0.5 | E2: =C2*D2 -> 0
A3: B | B3: 产品B | C3: =0 -> 0 | D3: ='总报价表'!Z31 -> 0.5 | E3: =C3*D3 -> 0
A4: 共有 | B4: 每包装共有项目 | C4: =0 -> 0 | D4: 1 | E4: =C4*D4 -> 0

Sheet 车缝明细
A1: 货号 | B1: 小产品名称 | C1: 部门费用 HKD（未乘NA） | D1: NA比例 | E1: NA后金额 HKD
A2: A | B2: 产品A | C2: =('总报价表'!W30)+('总报价表'!X30) -> 0 | D2: ='总报价表'!Z30 -> 0.5 | E2: =C2*D2 -> 0
A3: B | B3: 产品B | C3: =('总报价表'!W31)+('总报价表'!X31) -> 0 | D3: ='总报价表'!Z31 -> 0.5 | E3: =C3*D3 -> 0
A4: 共有 | B4: 每包装共有项目 | C4: =('总报价表'!W34)+('总报价表'!X34) -> 0 | D4: 1 | E4: =C4*D4 -> 0

Sheet 装配明细
A1: 货号 | B1: 小产品名称 | C1: 部门费用 HKD（未乘NA） | D1: NA比例 | E1: NA后金额 HKD
A2: A | B2: 产品A | C2: =0+0 -> 0 | D2: ='总报价表'!Z30 -> 0.5 | E2: =C2*D2 -> 0
A3: B | B3: 产品B | C3: =0+0 -> 0 | D3: ='总报价表'!Z31 -> 0.5 | E3: =C3*D3 -> 0
A4: 共有 | B4: 每包装共有项目 | C4: =0+0 -> 0 | D4: 1 | E4: =C4*D4 -> 0

Sheet 喷油明细
A1: 货号 | B1: 小产品名称 | C1: 部门费用 HKD（未乘NA） | D1: NA比例 | E1: NA后金额 HKD
A2: A | B2: 产品A | C2: =('总报价表'!F30)+('总报价表'!G30) -> 0 | D2: ='总报价表'!Z30 -> 0.5 | E2: =C2*D2 -> 0
A3: B | B3: 产品B | C3: =('总报价表'!F31)+('总报价表'!G31) -> 0 | D3: ='总报价表'!Z31 -> 0.5 | E3: =C3*D3 -> 0
A4: 共有 | B4: 每包装共有项目 | C4: =('总报价表'!F34)+('总报价表'!G34) -> 0 | D4: 1 | E4: =C4*D4 -> 0

Sheet 搪胶明细
A1: 货号 | B1: 小产品名称 | C1: 部门费用 HKD（未乘NA） | D1: NA比例 | E1: NA后金额 HKD
A2: A | B2: 产品A | C2: =0 -> 0 | D2: ='总报价表'!Z30 -> 0.5 | E2: =C2*D2 -> 0
A3: B | B3: 产品B | C3: =0 -> 0 | D3: ='总报价表'!Z31 -> 0.5 | E3: =C3*D3 -> 0
A4: 共有 | B4: 每包装共有项目 | C4: =0 -> 0 | D4: 1 | E4: =C4*D4 -> 0
