Workbook

Sheet 77425包装MA 
A1: 迷你衣柜装MA明细
A2: 放MA日期 | B2: PO号码 | C2: MA订单号码 | D2: 货号 | E2: 数量 | F2: 名称 | G2: 版本号 | H2: 彩盒 1L | I2: 说明书 5L | K2: 彩盒 3L | L2: 中文说明书 | N2: 备注
A3: 44930 | B3: 77200 77361 Dino Strike S4, S5 & 77349 Fashion S2 包材放订 | C3: 1000012977 | D3: 77425 | E3: 20000 | F3: Color box | G3: A | H3: 20000
A4: 44930 | B4: 77200 77361 Dino Strike S4, S5 & 77349 Fashion S2 包材放订 | C4: 1000012978 | D4: 77425 | E4: 20000 | F4: Instruction Book | G4: A | I4: 20000
A5: 44991 | B5: 77200 77361 Dino Strike S4, S5 & 77349 Fashion S2 包材放订 | C5: 1000013388 | D5: 77425 | E5: 5000 | F5: Color box | G5: A | K5: 5000
D6: 77425 | E6: 订单备料 | L6: 3000
A7: 45023 | B7: 77200 77361 Dino Strike S4, S5 & 77349 Fashion S2 包材放订 | C7: 1000013765 | D7: 77425 | E7: 10000 | F7: Color box | G7: A | H7: 10000
A8: 45023 | B8: 77200 77361 Dino Strike S4, S5 & 77349 Fashion S2 包材放订 | C8: 1000013766 | D8: 77425 | E8: 20000 | F8: Instruction Book | G8: A | I8: 20000
A9: 45034 | B9: 77200 77361 Dino Strike S4, S5 & 77349 Fashion S2 包材放订 | C9: 1000013938 | D9: 77425 | E9: 10000 | F9: Color box | G9: A | H9: 10000
A10: 45034 | B10: 77200 77361 Dino Strike S4, S5 & 77349 Fashion S2 包材放订 | C10: 1000013939 | D10: 77425 | E10: 10000 | F10: Instruction Book | G10: A | I10: 10000
A11: 45043 | B11: 77200 77361 Dino Strike S4, S5 & 77349 Fashion S2 包材放订 | C11: 1000014135 | D11: 77425 | E11: 20000 | F11: Color box | G11: A | H11: 20000
A12: 45043 | B12: 77200 77361 Dino Strike S4, S5 & 77349 Fashion S2 包材放订 | C12: 1000014136 | D12: 77425 | E12: 10000 | F12: Color box | G12: A | K12: 10000
A13: 45043 | B13: 77200 77361 Dino Strike S4, S5 & 77349 Fashion S2 包材放订 | C13: 1000014137 | D13: 77425 | E13: 25000 | F13: Instruction Book | G13: A | I13: 25000
A14: 45111 | B14: 77200 77361 Dino Strike S4, S5 & 77349 Fashion S2 包材放订 | C14: 1000015246 | D14: 77425 | E14: 20000 | F14: Color box | G14: A | H14: 20000
A15: 45111 | B15: 77200 77361 Dino Strike S4, S5 & 77349 Fashion S2 包材放订 | C15: 1000015247 | D15: 77425 | E15: 15000 | F15: Instruction Book | G15: A | I15: 15000
A16: 45111 | B16: 77200 77361 Dino Strike S4, S5 & 77349 Fashion S2 包材放订 | C16: 1000015248 | D16: 77425 | E16: 5000 | F16: Color box | G16: A | K16: 5000
A17: 45128 | B17: 77200 77361 Dino Strike S4, S5 & 77349 Fashion S2 包材放订 | C17: 1000015524 | D17: 77425 | E17: 10000 | F17: Instruction Book | G17: A | I17: 10000
A18: 45142 | B18: 77200 77361 Dino Strike S4, S5 & 77349 Fashion S2 包材放订 | C18: 1000015842 | D18: 77425 | E18: 15000 | F18: Color box | G18: A | H18: 15000
A19: 45142 | B19: 77200 77361 Dino Strike S4, S5 & 77349 Fashion S2 包材放订 | C19: 1000015843 | D19: 77425 | E19: 10000 | F19: Instruction Book | G19: A | I19: 10000
A20: 45475 | B20: 77200 77361 Dino Strike S4, S5 & 77349 Fashion S2 包材放订 | C20: 1000021482 | D20: 77425 | E20: 2000 | F20: Color box | G20: A | K20: 2000
A21: 45490 | B21: 77200 77361 Dino Strike S4, S5 & 77349 Fashion S2 包材放订 | C21: 1000021895 | D21: 77425 | E21: 5000 | F21: Instruction Book | G21: A | I21: 5000
A22: 45559 | B22: 77200 77361 Dino Strike S4, S5 & 77349 Fashion S2 包材放订 | C22: 1000023322 | D22: 77425 | E22: 3436 | F22: Color box | G22: A | H22: 3436
A23: 45559 | B23: 77200 77361 Dino Strike S4, S5 & 77349 Fashion S2 包材放订 | C23: 1000023323 | D23: 77425 | E23: 2456 | F23: Instruction Book | G23: A | I23: 2456 | N23: 最后一次放订，按照实际订单数量采购
N24: 最后一次放订，按照实际订单数量采购
A27: 包材合计 | H27: =SUM(H3:H26) -> 98436 | I27: =SUM(I3:I26) -> 117456 | J27: =SUM(J3:J26) -> 0 | K27: =SUM(K3:K26) -> 22000 | L27: =SUM(L3:L26) -> 3000
A29: 接单汇总数 | H29: ='77425明细 '!AK20+H32 -> 95060 | I29: ='77425明细 '!AL20+I32 -> 115160 | K29: ='77425明细 '!AM20+K32 -> 22020 | L29: ='77425明细 '!AN20+L32 -> 3000
A31: 欠数 | H31: =H27-H29 -> 3376 | I31: =I27-I29 -> 2296 | J31: =J27-J29 -> 0 | K31: =K27-K29 -> -20 | L31: =L27-L29 -> 0
F32: 2024年删除数 | H32: 93316 | I32: 113416 | J32: 0 | K32: 22020 | L32: 3000

Sheet 77425明细 
A1: 香港接单日期 | B1: 第三方客户名称 | C1: 走货国家 | D1: ZURU PO NO# | E1: 第三方客户 PO NO# | F1: SKU | G1: ITEM# | H1: 货品名称 | I1: PO数量(只) | J1: 内箱装箱数量(只) | K1: 外箱装箱数量(只) | L1: 总箱数 | M1: 计划出货期 | N1: 计划验货期 | O1: 第三方客户公证行验货 | P1: 验货结果 | Q1: S/O(截仓期) | R1: 箱唛 (收到日期) | S1: 外箱贴纸 | T1: 贴纸资料 (收到日期及订购日期) | U1: 备注 | V1: ZURU跟单组员 | W1: 单价USD | X1: 金额USD | Y1: 发票号 | Z1: 系统货号 | AA1: 是否入系统 | AB1: 下单情况 | AC1: 生产情况 | AD1: 已回数量 | AE1: 欠数 | AF1: HN回复完成时间 | AG1: 贴纸 | AH1: 纸箱 | AI1: 77425 有香味 | AJ1: 77425 无香味 | AK1: 彩盒 A/B版 MA 1L | AL1: 说明书 5L A/B版本 | AM1: 彩盒 MA 3L | AN1: 中文版说明书
A2: 45614 | B2: Amazon Mexico, S. DE R.L. DE CV | C2: 墨西哥 | D2: 4500151559 | E2: 64SP3ZYY | F2: 4500151559-20 | G2: 77425-S001 | H2: 迷你衣柜 | I2: 24 | J2: 0 | K2: 4 | L2: =I2/K2 -> 6 | M2: 45649 | N2: 45645 | P2: PASS | R2: 空白外箱加印ZURU Logo+MADE IN CHINA+SSCC LABEL(客供贴纸），无shipping mark,日期使用ZURU 标准版本 | S2: 有 | T2: 欠 | U2: 日期码格式：ZURU INC(BVI) 标准格式 日期：按实际生产日期 Packaging Info: 77425: MA 1L+进口商贴纸+SSCC贴纸 Remark: Amazon FOB订单，出口Mexico，外箱最长边不能超过25" （超过了，case pack只能为1），不符合要求的大货，一律不接受。 1.空白外箱加印ZURU Logo+MADE IN CHINA+SSCC LABEL(客供贴纸），无shipping mark,日期使用ZURU 标准版本。SSCC Label显示的是客人自己的item#，SSCC Lab el 贴在外箱正面的正中间，贴一面即可，跟单订购，贴纸离外箱距必须至少3cm,每一张SSCC Label都是唯一且有不同流水及条码的，没有损耗，绝对不可贴错，否 则贴错或损坏一张会导致全部都错，千万要注意！ 2. 日期码使用ZURU标准版 3. 客户PO备注在remark处 5.77425: 3PCS AAA Batteries (Not included) | V2: Zoe Luo | W2: 8.2879 | X2: =I2*W2 -> 198.9096 | Y2: 88897-1.6 | Z2: 77425-S001 | AA2: 已入 | AB2: 系统出单 | AD2: 24 | AE2: =AD2-I2 -> 0 | AG2: OK | AI2: =I2 -> 24 | AK2: =I2 -> 24 | AL2: =I2 -> 24
A3: 45631 | D3: ZMPO24913 | G3: 77425-S001 | H3: 迷你衣柜 | I3: 60 | J3: 0 | K3: 4 | L3: =I3/K3 -> 15 | M3: 45649 | N3: 45645 | R3: 周转箱 | S3: 无 | T3: 无 | U3: Remark:大货最新ZURU Logo版本/请用大货标准箱装箱4PCS/箱共15箱/箱唛请参照邮件附件 备注：收到样品订单后尽快安排 ，注意样板品质质量要求要高于大货品质要求 ，送货时必须要附带送货单(没有送货单和QC检验合格报告的仓库一律拒绝收货)，请知悉，谢谢！ | V3: Angus | Y3: 94902-4.30 | Z3: 77425-S001 | AA3: 已入 | AB3: 系统出单 | AD3: 60 | AE3: =AD3-I3 -> 0 | AI3: =I3 -> 60 | AK3: =I3 -> 60 | AL3: =I3 -> 60
A4: 45702 | B4: TJX UK | C4: 英国 | D4: 4500157680 | E4: TJX UK: PO#50047489 | F4: 4500157680-50 | G4: 77425-S001 | H4: 迷你衣柜 | I4: 548 | J4: 0 | K4: 4 | L4: =I4/K4 -> 137 | M4: 45741 | N4: 45737 | P4: PASS | R4: 45712 | S4: 无 | T4: 45707 | U4: 日期码格式：ZURU INC(BVI) 标准格式 日期：按实际生产日期 Packaging Info: TJX UK: PO#50047540(71101)---TJX UK: PO#50047545(71101)---TJX UK: PO#50047483(71101)---TJX UK: PO#50047488(71101)---TJX UK: PO#50047489(77425) SLOB ITEM消耗库存： 77425: MA1L (1L warning) 最新UPC包装 Remark: 1. 出往UK的产品+包装务必打上UKCA logo ，否则客人会退货且当地会有罚款； 2. 订单必须经过ZURU QC验货并且通过后方可出货； 3. 订单每行对应客人不同的PO， 箱唛也有不同，做货的时候请分开堆放； 4. 包装条码请按包装备注上的对应的警示语语种包装，出德国的订单(订单备注为TJX Europe-DE)需要确保有英语+德语+荷兰语+波兰语警示语； 5. 订单每行对应客人不同的PO，即同款item的价格贴纸都不相同，请注意收到贴纸后不要弄混!（客人PO号请参考PO最后一栏remark）； 6. 客供价格贴纸位置为产品正面右上角，不能遮住产品信息，大货生产前，请把贴纸位置先发给跟单确认 7. 涉及到相关款式会有闪粉的或者微塑料的，请统一默认出无闪粉或者不含微塑料版本; 8. 外箱封箱必须是工字型封箱方式； | V4: Sandy Shao | W4: 7.6428 | X4: =W4*I4 -> 4188.2544 | Y4: 94634-3.25 | Z4: 77425-S001 | AA4: 已入 | AB4: 系统出单 | AD4: 548 | AE4: =AD4-I4 -> 0 | AG4: 无 | AI4: =I4 -> 548 | AK4: =I4 -> 548 | AL4: =I4 -> 548
A5: 45702 | B5: TJX UK c/o TJX Distribution Ltd & C | C5: 德国 | D5: 4500157675 | E5: TJX Europe-DE: PO#55047520 | F5: 4500157675-60 | G5: 77425-S001 | H5: 迷你衣柜 | I5: 548 | J5: 0 | K5: 4 | L5: =I5/K5 -> 137 | M5: 45741 | N5: 45737 | P5: PASS | R5: 45712 | S5: 无 | T5: 45707 | U5: 日期码格式：ZURU INC(BVI) 标准格式 日期：按实际生产日期 Packaging Info: TJX Europe-DE: PO#55047501(71101)---TJX Europe-DE: PO#55047502(71101)---TJX Europe-DE: PO#55047504(71101)---TJX Europe-DE: PO#55047514(71101)--- TJX Europe-DE: PO#55047516(71101)---TJX Europe-DE: PO#55047520(77425) SLOB ITEM 消耗库存： 77425: MA1L (1L warning) 最新UPC包装+1张贴纸（含德语<(>&<)>荷兰语<(>&<)>波兰语警告语） Remark: 1. 出往UK的产品+包装务必打上UKCA logo ，否则客人会退货且当地会有罚款； 2. 订单必须经过ZURU QC验货并且通过后方可出货； 3. 订单每行对应客人不同的PO， 箱唛也有不同，做货的时候请分开堆放； 4. 包装条码请按包装备注上的对应的警示语语种包装，出德国的订单(订单备注为TJX Europe-DE)需要确保有英语+德语+荷兰语+波兰语警示语； 5. 订单每行对应客人不同的PO，即同款item的价格贴纸都不相同，请注意收到贴纸后不要弄混!（客人PO号请参考PO最后一栏remark）； 6. 客供价格贴纸位置为产品正面右上角，不能遮住产品信息，大货生产前，请把贴纸位置先发给跟单确认 7. 涉及到相关款式会有闪粉的或者微塑料的，请统一默认出无闪粉或者不含微塑料版本; 8. 外箱封箱必须是工字型封箱方式； | V5: Sandy Shao | W5: 7.339 | X5: =W5*I5 -> 4021.772 | Y5: 94645-3.26 | Z5: 77425-S001 | AA5: 已入 | AB5: 系统出单 | AD5: 548 | AE5: =AD5-I5 -> 0 | AG5: OK | AI5: =I5 -> 548 | AK5: =I5 -> 548 | AL5: =I5 -> 548
A6: 45756 | B6: Amazon Mexico, S. DE R.L. DE CV | C6: 墨西哥 | D6: 4500163057 | E6: 5K7XXSZF | F6: 4500163057-50 | G6: 77425-S001 | H6: 迷你衣柜 | I6: 92 | J6: 0 | K6: 4 | L6: =I6/K6 -> 23 | M6: 45812 | N6: =M6-4 -> 45808 | P6: PASS | R6: 空白外箱加印ZURU Logo+MADE IN CHINA+SSCC LABEL(客供贴纸），无shipping mark,日期使用ZURU 标准版本。SSCC Label显示的是客人自己的item#，SSCC Lab | S6: 有 | T6: 欠 | U6: 日期码格式：ZURU INC(BVI) 标准格式 日期：按实际生产日期 5. 77425：MA 1L UPC包装+MA 多语说明书+进口商贴纸+SSCC label Remark: 1. Amazon FOB订单，出口Mexico，外箱最长边不能超过25" （超过了，case pack只能为1），不符合要求的大货，一律不接受。 2. 空白外箱加印ZURU Logo+MADE IN CHINA+SSCC LABEL(客供贴纸），无shipping mark,日期使用ZURU 标准版本。SSCC Label显示的是客人自己的item#，SSCC Lab el 贴在外箱正面的正中间，贴一面即可，跟单订购，贴纸离外箱距必须至少3cm,每一张SSCC Label都是唯一且有不同流水及条码的，没有损耗，绝对不可贴错，否 则贴错或损坏一张会导致全部都错，千万要注意！ 3. 日期码使用ZURU标准版 4. 9543D:2PCS AAA BATTERIES(NOT INCLUDED) 5. 77425: 3PCS AAA BATTERIES(NOT INCLUDED) | V6: Ever Li | W6: 8.1164 | X6: =W6*I6 -> 746.7088 | Y6: 95288-6.10 | Z6: 77425-S001 | AA6: 已入 | AB6: 系统出单 | AD6: 92 | AE6: =AD6-I6 -> 0 | AG6: OK | AI6: =I6 -> 92 | AK6: =I6 -> 92 | AL6: =I6 -> 92
A7: 45756 | B7: Amazon Mexico, S. DE R.L. DE CV | C7: 墨西哥 | D7: 4500163057 | E7: 34P65IJU | F7: 4500163057-80 | G7: 774225-S001 | H7: 迷你衣柜 | I7: 64 | J7: 0 | K7: 4 | L7: =I7/K7 -> 16 | M7: 45812 | N7: =M7-4 -> 45808 | P7: PASS | R7: 空白外箱加印ZURU Logo+MADE IN CHINA+SSCC LABEL(客供贴纸），无shipping mark,日期使用ZURU 标准版本。SSCC Label显示的是客人自己的item#，SSCC Lab | S7: 有 | T7: 欠 | U7: 日期码格式：ZURU INC(BVI) 标准格式 日期：按实际生产日期 5. 77425：MA 1L UPC包装+MA 多语说明书+进口商贴纸+SSCC label Remark: 1. Amazon FOB订单，出口Mexico，外箱最长边不能超过25" （超过了，case pack只能为1），不符合要求的大货，一律不接受。 2. 空白外箱加印ZURU Logo+MADE IN CHINA+SSCC LABEL(客供贴纸），无shipping mark,日期使用ZURU 标准版本。SSCC Label显示的是客人自己的item#，SSCC Lab el 贴在外箱正面的正中间，贴一面即可，跟单订购，贴纸离外箱距必须至少3cm,每一张SSCC Label都是唯一且有不同流水及条码的，没有损耗，绝对不可贴错，否 则贴错或损坏一张会导致全部都错，千万要注意！ 3. 日期码使用ZURU标准版 4. 9543D:2PCS AAA BATTERIES(NOT INCLUDED) 5. 77425: 3PCS AAA BATTERIES(NOT INCLUDED) | V7: Ever Li | W7: 8.1164 | X7: =W7*I7 -> 519.4496 | Y7: 95288-6.10 | Z7: 77425-S001 | AA7: 已入 | AB7: 系统出单 | AD7: 64 | AE7: =AD7-I7 -> 0 | AG7: OK | AI7: =I7 -> 64 | AK7: =I7 -> 64 | AL7: =I7 -> 64
A8: 45818 | B8: ZURU LLC | C8: 美国 | D8: 4500169495 | E8: B0BS8LM6R6 | F8: 4500169495-120 | G8: 77425-S001-MTS | H8: 迷你衣柜 | I8: 212 | J8: 0 | K8: 4 | L8: =I8/K8 -> 53 | M8: 45855 | N8: 45852 | P8: PASS | R8: 45818 | S8: 无 | T8: 无 | U8: 日期码格式：ZURU INC(BVI) 标准格式 日期：按实际生产日期 Packaging Info: #77425 MA 1L UPC版本 Remark: 1.Amazon domestic 订单。出口美国。外箱最长边不能超过25" （超过了，case pack只能为1），不符合要求的大货，一律不接受。 2.无第三方验货/测试要求。 3.日期码使用ZURU标准版本。 4.邮包盒要印刷日期码。 | V8: Kelly Shen/Mia Pan/P | W8: 4.4908 | X8: =W8*I8 -> 952.0496 | Y8: ZB01104R1-8.6 | Z8: 77425-S001 | AA8: 已入 | AB8: 系统出单 | AD8: 212 | AE8: =AD8-I8 -> 0 | AG8: 无 | AI8: =I8 -> 212 | AK8: =I8 -> 212 | AL8: =I8 -> 212
A9: 45744 | B9: YOYO LLC | C9: 吉尔吉斯斯坦 | D9: 4500161685 | F9: 4500161685-10 | G9: 77425-S001 | H9: 迷你衣柜 | I9: 100 | J9: 0 | K9: 4 | L9: =I9/K9 -> 25 | M9: 45880 | N9: 45876 | P9: PASS | R9: 45784 | S9: 无 | T9: 45856 | U9: 日期码格式：ZURU INC(BVI) 标准格式 日期：按实际生产日期 Packaging Info: 1L MA UPC 包装+ 进口商贴纸 ， MA PDQ /说明书/指南（如有） Remark: 标准配比 | V9: Ann | W9: 7.1871 | X9: =W9*I9 -> 718.71 | Y9: 96119-8.22 | Z9: 77425-S001 | AA9: 已入 | AB9: 系统出单 | AD9: 100 | AE9: =AD9-I9 -> 0 | AG9: OK | AI9: =I9 -> 100 | AK9: =I9 -> 100 | AL9: =I9 -> 100
A10: 45840 | B10: TJX UK | C10: 英国 | D10: 4500172515 | E10: TJX UK PO#50687573 | F10: 4500172515-60 | G10: 77425-S001 | H10: 迷你衣柜 | I10: 96 | J10: 0 | K10: 4 | L10: =I10/K10 -> 24 | M10: 45880 | N10: 45876 | P10: PASS | R10: 45840 | S10: 无 | T10: 45861 | U10: 日期码格式：ZURU INC(BVI) 标准格式 日期：按实际生产日期 Packaging Info: 77425 MA1L (1L warning) 最新UPC包装+1张客供价格贴纸 Remark: 1. 出往UK的产品+包装务必打上UKCA logo ，否则客人会退货且当地会有罚款； 2. 订单必须经过ZURU QC验货并且通过后方可出货； 3. 订单每行对应客人不同的PO， 箱唛也有不同，做货的时候请分开堆放； 4. 包装条码请按包装备注上的对应的警示语语种包装，出德国的订单(订单备注为TJX Europe-DE)需要确保有英语+德语+荷兰语+波兰语警示语； 5. 订单每行对应客人不同的PO，即同款item的价格贴纸都不相同，请注意收到贴纸后不要弄混!（客人PO号请参考PO最后一栏remark）； 6. 客供价格贴纸位置为产品正面右上角，不能遮住产品信息，大货生产前，请把贴纸位置先发给跟单确认 7. 涉及到相关款式会有闪粉的或者微塑料的，请统一默认出无闪粉或者不含微塑料版本; 8. 外箱封箱必须是工字型封箱方式； | V10: Sandy Shao | W10: 7.4847 | X10: =W10*I10 -> 718.5312 | Y10: 96093-8.19 | Z10: 77425-S001 | AA10: 已入 | AB10: 系统出单 | AD10: 96 | AE10: =AD10-I10 -> 0 | AG10: OK | AI10: =I10 -> 96 | AK10: =I10 -> 96 | AL10: =I10 -> 96
G20: 接单汇总 | I20: =SUM(I2:I19) -> 1744 | AI20: =SUM(AI2:AI19) -> 1744 | AJ20: =SUM(AJ2:AJ19) -> 0 | AK20: =SUM(AK2:AK19) -> 1744 | AL20: =SUM(AL2:AL19) -> 1744 | AM20: =SUM(AM2:AM19) -> 0 | AN20: =SUM(AN2:AN19) -> 0 | AO20: =SUM(AO2:AO19) -> 0 | AP20: =SUM(AP2:AP19) -> 0 | ... AX20: =SUM(AX2:AX19) -> 0 | AZ20: =SUM(AZ2:AZ19) -> 0 | BA20: =SUM(BA2:BA19) -> 0 | BB20: =SUM(BB2:BB19) -> 0 | BC20: =SUM(BC2:BC19) -> 0 | BD20: =SUM(BD2:BD19) -> 0 | BE20: =SUM(BE2:BE19) -> 0 | BF20: =SUM(BF2:BF19) -> 0 | BG20: =SUM(BG2:BG19) -> 0 | ... BJ20: =SUM(BJ2:BJ19) -> 0

Sheet 77485 S3 明细
A1: 香港接单日期 | B1: 第三方客户名称 | C1: 走货国家 | D1: ZURU PO NO# | E1: 第三方客户 PO NO# | F1: SKU | G1: ITEM# | H1: 货品名称 | I1: PO数量(只) | J1: 内箱装箱数量(只) | K1: 外箱装箱数量(只) | L1: 总箱数 | M1: 计划出货期 | N1: 计划验货期 | O1: 第三方客户公证行验货 | P1: 验货结果 | Q1: S/O(截仓期) | R1: 箱唛 (收到日期) | S1: 外箱贴纸 | T1: 贴纸资料 (收到日期及订购日期) | U1: 样板 | V1: 备注 | W1: ZURU跟单组员 | X1: 单价USD | Y1: 金额USD | Z1: 是否收到客版包装资料 | AA1: 发票号 | AB1: 系统货号 | AC1: 是否入系统 | AD1: 下单情况 | AE1: 生产情况 | AF1: 已回数量 | AG1: 欠数 | AH1: HN回复完成时间 | AI1: 贴纸 | AJ1: 纸箱 | AK1: 77485 有香味 | AL1: 77485 无香味 | AM1: MA 1L A/B收缩膜 | AN1: MA 1L 收缩膜 无条码 | AO1: MA 3L 收缩膜 无条码 | AP1: MA 3L 收缩膜 | AQ1: 客版收缩膜 | AR1: MA 5L 收藏指南 | AS1: MA 5L B版收藏指南 | AT1: 客版收藏指南 | AU1: WM 客版收藏指南 | AV1: 客版 1L 8pcs GQ1-S001 | AW1: 1L 21pcs GQ2-S001 | AX1: 3L 21pcs GQ2-S001 | AY1: 1L 12PCS GQ3-S001 | AZ1: 1L B 12PCS GQ3-S001 | BA1: 3L 12PCS GQ3-S001 | BB1: 1L 12PCS GQ4-S001 | BC1: 1L 13PCS GQ6-S001 | BD1: 13PCS GQ6-S001 3L | BE1: 25PCS GQ7-S001 | BF1: 25PCS GQ7-S001 3L | BG1: 客版 SK-S001 不含底座 | BH1: 客版 1L SK-S001 不含底座 | BI1: 3L SK-S002 含底座 60pcs | BJ1: 3L SK1-S001 30pcs | BK1: MSLD104展示架 | BL1: 客版不含鞋子 收缩膜 | BM1: 客版不含鞋子 收藏指南 | BN1: 77486 圆筒 | BO1: 77486 3L彩纸 | BP1: 77486 TJX版本 彩纸 | BQ1: 77486 贴纸 | BR1: 77601 圆筒 | BS1: 776016 3L彩纸 | BT1: 77601 贴纸 | BU1: 合计数量 | BV1: 累计数量 | BW1: MA 数量 | BX1: 820000 | BY1: 300000 | BZ1: 300000 | CA1: 200000 | CB1: =400000+500000+300000 -> 1200000 | CC1: GQ2/GQ7 | CD1: 累计数量 | CE1: MA 数量 | CF1: 2000 | CG1: 13970 | CH1: 11700 | CI1: =22330+10000 -> 32330
A2: 45604 | B2: THE ENTERTAINER | C2: 英国 | D2: 4500150141 | E2: 4500150141-2 | F2: 4500150141-80 | G2: 77485GQ6-S001 | H2: 3代迷你小手袋 | I2: 3120 | J2: 0 | K2: 52 | L2: =I2/K2 -> 60 | M2: 45657 | N2: 45653 | P2: PASS | R2: 45610 | S2: 无 | T2: 客户EAN条码贴一张覆盖ZURU 原条码，条码贴翻订单4500148687 | V2: 日期码格式：ZURU INC(BVI) 标准格式 日期：按实际生产日期 Packaging Info: 77485GQ6：MA最新1L配套包装+客户EAN条码贴一张覆盖ZURU 原条码，条码贴翻订单4500148687。 Remark: *MA版本按工厂现有最新库存即可，订单出英国，请注意检查产品及包装应带UKCA图标，包装显示ZURU UK LTD信息，QC同事请查核，如有问题与跟单确认。 *生产日期按实际（法定工作日），按ZURU标准格式即可 ，但是请知悉包装日期码需要早于或者等于外箱日期码 ，不能晚于外箱日期码 *请注意所有订单都需要经过ZURU QC验货并且通过后方可出货 *条码以订单显示为准 ，请安排生产前先核对 ，有问题请提出。 *所有产品按符合欧洲标准走货，需要是不含微塑料版本 。 *涉及到硼的，如可选择情况下应使用低硼版本 （slime 类别低硼一般低于300ppm)，无选择的应与跟单复核再安排 。 | W2: Sherry Lu | X2: 1.8967 | Y2: =I2*X2 -> 5917.704 | AA2: 88877-1.4 | AB2: 77485GQ6-S001 | AC2: 已入 | AD2: 系统出单 | AF2: =52+3068 -> 3120 | AG2: =AF2-I2 -> 0 | AI2: OK | AK2: =I2 -> 3120 | AM2: =I2 -> 3120 | AS2: =I2 -> 3120 | BC2: =AK2/13 -> 240 | BU2: =AK2+AL2 -> 3120 | BV2: =2188428+BU2 -> 2191548 | CA2: =SUM(BX$1:CB$1)-BV2 -> 628452 | CC2: =AW2+AX2+BE2+BF2 -> 0 | CD2: =46986.5714285714+CC2 -> 46986.571 | CH2: =$CF$1+$CG$1+$CH$1+$CI$1-CD2 -> 13013.429
A3: 45586 | B3: ROSS PROCUREMENT.INC | C3: 美国 | D3: 4500148421 | E3: 60190475 | F3: 4500148421-20 | G3: 77486-S001 | H3: 3代迷你小手袋 圆筒装 | I3: 3000 | J3: 0 | K3: 12 | L3: =I3/K3 -> 250 | M3: 45653 | N3: 45649 | P3: PASS | R3: 通用模板 | S3: 无 | T3: 欠客供价格贴纸 | V3: 日期码格式： 标准格式 日期：按实际生产日期 Packaging Info: URU MA UPC 收缩膜+客版铜版纸+PVC桶 + 客供价格贴纸，出口美国 , 优先使用MA 1L 最新版本 。 Remark: 1.ZURU MA UPC 收缩膜+客版铜版纸+PVC桶 + 客供价格贴纸，出口美国 , 优先使用MA 1L 最新版本 。 2.价格贴纸位于包装正面右下角，不挡住重要信息即可，可适当调整 ，价格贴纸由跟单提供。 3.标准日期码格式，产品和包装必须有日期码 。 4.同个产品同个货期不可出现不同的包装。 5. PVC 桶中球不能出现完全相同的ASSORTMENT ， 即同一个PVC 中球里的ASSORTMENT 需要不同。 以免消费者失望。 6.PVC 桶上加上 MINI BRANDS 的LOGO 贴纸 （ ZURU 统一要求的） 7.收缩膜可使用标版带UPC条码MA，无需白色贴纸覆盖。 | W3: Sophia Zhou | X3: 4.0635 | Y3: =I3*X3 -> 12190.5 | AA3: 88928-1.7 | AB3: 77486-S001 | AC3: 已入 | AD3: 系统出单 | AF3: =2988+12 -> 3000 | AG3: =AF3-I3 -> 0 | AI3: OK | AK3: =I3*2 -> 6000 | AM3: =I3*2 -> 6000 | AS3: =I3*2 -> 6000 | BN3: =I3 -> 3000 | BO3: =I3 -> 3000 | BQ3: =I3 -> 3000 | BU3: =AK3+AL3 -> 6000 | BV3: =BV2+BU3 -> 2197548 | CA3: =SUM(BX$1:CB$1)-BV3 -> 622452 | CC3: =AW3+AX3+BE3+BF3 -> 0 | CD3: =CD2+CC3 -> 46986.571 | CH3: =$CF$1+$CG$1+$CH$1+$CI$1-CD3 -> 13013.429
A4: 45615 | B4: COMERCIALIZADORA MEXICO AMERICANA S | C4: 墨西哥 | D4: 4500151611 | E4: 5251213810 | F4: 4500151611-80 | G4: 77485GQ7-S001 | H4: 3代迷你小手袋 | I4: 15700 | J4: 0 | K4: 50 | L4: =I4/K4 -> 314 | M4: 45650 | N4: 45652 | O4: 客版日期码要求：LOT+ZURU标准日期码格式。东莞生产的格式：LOTDGYYYYMMDD, DG是东莞拼音首字母， YYYYMMDD是实际的年月日，例如(LOTDG20240920) | P4: PASS | R4: 45631 | S4: 无 | T4: 进口商贴纸翻单PO4500120342 | V4: 日期码格式：LOTDGYYYYMMDD 日期：按实际生产日期 Packaging Info: 77485GQ7: 3L MA EAN 收缩膜+新UPC条码贴纸+进口商贴纸+MA 5L 收藏指南+MA 3L PDQ+箱唛；进口商贴纸翻单PO4500120342，条码贴纸不翻单 Remark: 1. 客版日期码要求：LOT+ZURU标准日期码格式。东莞生产的格式：LOTDGYYYYMMDD, DG是东莞拼音首字母， YYYYMMDD是实际的年月日，例如(LOTDG20240920) 3. 此单有第三方监柜，至少多备一套完整的物料用于监柜，请多备料。 4. WM墨西哥防霉的新要求:货物必须在出货主箱和集装箱中按要求放置干燥剂，干燥剂指定品牌干霸 77485GQ7： 需要在每箱放入6小包干燥剂，每包干燥剂重量2g 如走柜货等loading plan 确认后再通知集装箱干燥剂数量 | W4: Ever Li | X4: 1.9784 | Y4: =X4*I4 -> 31060.88 | AA4: 88845-1.2 | AB4: 77485GQ7-S001-3L-1 | AC4: 已入 | AD4: 系统出单 | AF4: =15700 -> 15700 | AG4: =AF4-I4 -> 0 | AI4: OK | AK4: =I4 -> 15700 | AP4: =I4 -> 15700 | AS4: =I4 -> 15700 | BF4: =I4/25 -> 628 | BU4: =AK4+AL4 -> 15700 | BV4: =BV3+BU4 -> 2213248 | CA4: =SUM(BX$1:CB$1)-BV4 -> 606752 | CC4: =AW4+AX4+BE4+BF4 -> 628 | CD4: =CD3+CC4 -> 47614.571 | CH4: =$CF$1+$CG$1+$CH$1+$CI$1-CD4 -> 12385.429
A5: 45644 | B5: WALGREEN CO. | C5: 美国 | D5: MPO03152 | G5: 77485-S001 | H5: 3代迷你小手袋 | I5: 42616 | J5: 0 | K5: 24 | L5: =I5/K5 -> 1775.6667 | M5: 45667 | N5: 45663 | O5: 此MPO订单替换原手工单MPOWAL034 | P5: PASS | R5: 周转箱 | S5: 无 | T5: WIC贴纸（WIC # 795592） | V5: Remark:1.此MPO订单替换原手工单MPOWAL034 2.订单要求参考MPOWAL034 3.分三批送货 第-批 77485-8528pcs 77555-8528pcs(已送货)第二批77485-25584pcs77555-25584pcs(已送货)第三批 77485-8504pcs77555-8504pcs(待安排送货) | W5: Cara Li | X5: 1.8043 | Y5: =X5*I5 -> 76892.049 | AA5: 94402-2.27 94410-2.28 | AB5: 77485-S001 | AC5: 已入 | AD5: 消耗取消单 | AF5: =34112+8520 -> 42632 | AG5: =AF5-I5 -> 16 | AI5: OK | AK5: =I5 -> 42616 | AM5: =I5 -> 42616 | AS5: =I5 -> 42616 | BU5: =AK5+AL5 -> 42616 | BV5: =BV4+BU5 -> 2255864 | CA5: =SUM(BX$1:CB$1)-BV5 -> 564136 | CC5: =AW5+AX5+BE5+BF5 -> 0 | CD5: =CD4+CC5 -> 47614.571 | CH5: =$CF$1+$CG$1+$CH$1+$CI$1-CD5 -> 12385.429
A6: 45573 | B6: Ansaldo Chile | C6: 智利 | D6: 4500146540 | F6: 4500146540-40 | G6: 77485GQ7-S001 | H6: 3代迷你小手袋 | I6: 3200 | J6: 0 | K6: 50 | L6: =I6/K6 -> 64 | M6: 45659 | N6: 45654 | P6: PASS | R6: 45580 | S6: 无 | T6: 进口商贴纸翻单PO4500146361 | V6: 日期码格式：ZURU INC(BVI) 标准格式 日期：按实际生产日期 Packaging Info: 77485GQ7:MA 1L包装+进口商贴纸+箱唛,进口商贴纸翻单PO4500146361 Remark: | W6: Ava Liang | X6: 1.9961 | Y6: =X6*I6 -> 6387.52 | AA6: 88980-1.10 | AB6: 77485GQ7-S001 | AC6: 已入 | AD6: 系统出单 | AF6: 3200 | AG6: =AF6-I6 -> 0 | AI6: OK | AK6: =I6 -> 3200 | AM6: =I6 -> 3200 | AS6: =I6 -> 3200 | BE6: =I6/25 -> 128 | BU6: =AK6+AL6 -> 3200 | BV6: =BV5+BU6 -> 2259064 | CA6: =SUM(BX$1:CB$1)-BV6 -> 560936 | CC6: =AW6+AX6+BE6+BF6 -> 128 | CD6: =CD5+CC6 -> 47742.571 | CH6: =$CF$1+$CG$1+$CH$1+$CI$1-CD6 -> 12257.429
A7: 45621 | B7: London Supply Group SA | C7: 乌拉圭 | D7: 4500152280 | F7: 4500152280-60 | G7: 77485GQ7-S001 | H7: 3代迷你小手袋 | I7: 250 | J7: 0 | K7: 50 | L7: =I7/K7 -> 5 | M7: 45660 | N7: 45656 | P7: PASS | R7: 45623 | S7: 无 | T7: 无 | V7: 日期码格式：ZURU INC(BVI) 标准格式 日期：按实际生产日期 Tracking Code: Packaging Info: 77485GQ7:MA 1L包装+箱唛，无进口商贴纸 Remark: | W7: Ava Liang | X7: 2.0019 | Y7: =X7*I7 -> 500.475 | AA7: 88896-1.6 | AB7: 77485GQ7-S001 | AC7: 已入 | AD7: 系统出单 | AF7: 250 | AG7: =AF7-I7 -> 0 | AI7: 无 | AK7: =I7 -> 250 | AM7: =I7 -> 250 | AS7: =I7 -> 250 | BE7: =I7/25 -> 10 | BU7: =AK7+AL7 -> 250 | BV7: =BV6+BU7 -> 2259314 | CA7: =SUM(BX$1:CB$1)-BV7 -> 560686 | CC7: =AW7+AX7+BE7+BF7 -> 10 | CD7: =CD6+CC7 -> 47752.571 | CH7: =$CF$1+$CG$1+$CH$1+$CI$1-CD7 -> 12247.429
A8: 45615 | B8: VM INTERNATIONAL | C8: 美国 | D8: 4500151779 | F8: 4500151779-70 | G8: 77485GQ6-S003 | H8: 3代迷你小手袋 | I8: 1092 | J8: 0 | K8: 13 | L8: =I8/K8 -> 84 | M8: 45666 | N8: 45296 | O8: 2025/1/6 第三方验货 | P8: PASS | Q8: 1/12 出货 | R8: 45638 | S8: 无 | T8: 无 | V8: 日期码格式：ZURU INC(BVI) 标准格式 日期：按实际生产日期 Packaging Info: 1.ZURU 标准日期码格式， 2.无第三方测试和验货，ZURU 内部QC验货即可出货 Remark: 3. 优先 MA 1L UPC包装; 4. 纸箱印ZURU LOGO，出口美国； | W8: Iris Yuan | X8: 1.9068 | Y8: =I8*X8 -> 2082.2256 | AA8: 94112-1.18 | AB8: 77485GQ6-S003 | AC8: 已入 | AD8: 系统出单 | AF8: 1092 | AG8: =AF8-I8 -> 0 | AI8: 无 | AK8: =I8 -> 1092 | AM8: =I8 -> 1092 | AS8: =I8 -> 1092 | BC8: =I8/13 -> 84 | BU8: =AK8+AL8 -> 1092 | BV8: =BV7+BU8 -> 2260406 | CA8: =SUM(BX$1:CB$1)-BV8 -> 559594 | CC8: =AW8+AX8+BE8+BF8 -> 0 | CD8: =CD7+CC8 -> 47752.571 | CH8: =$CF$1+$CG$1+$CH$1+$CI$1-CD8 -> 12247.429
A9: 45621 | B9: WAL-MART STORES INC. USA | C9: 美国 | D9: 4500152202 | E9: 0877286348 ELWOOD | F9: 4500152202-10 | G9: 77485SLB-S004 | H9: 3代迷你小手袋 | I9: 3456 | J9: 0 | K9: 1152 | L9: =I9/K9 -> 3 | M9: 45300 | N9: 45296 | O9: 2025/1/6 自检 | P9: PASS | R9: 45621 | S9: 无 | T9: 12/20 RFID贴纸 艾利贴纸（不干胶贴纸）和一张普通贴纸（A4纸） | V9: 日期码格式：ZURU DGYYYYMMDD CHINA(日期避开周末和法定节假日即可） 日期：按实际生产日期 Tracking Code: Packaging Info: 77485SLB-S004 1.包装要求： MA 1L收缩膜+ 客版 收藏指南B版+MA 纸袋+客版 1L PDQ，翻单：4500128976 每pcs产品上要贴1张RFID贴纸，贴纸由ZURU提供，贴纸位置请严格按照我们签回的签板； Remark: 77485SLB-S004 1.包装要求： MA 1L收缩膜+ 客版 收藏指南B版+MA 纸袋+客版 1L PDQ，翻单：4500128976 每pcs产品上要贴1张RFID贴纸，贴纸由ZURU提供，贴纸位置请严格按照我们签回的签板； 2. 外箱印刷带条码的RFID箱唛：RFID紫色色带+WM Dept.图标+RFID图标+ITF-14条码，四面右下角印刷ZURU logo, ITFF条码只印刷在正唛一面，在加印的时候确保 条形码能扫描出来，外箱侧面任一角落加印："MADE IN CHINA" 字样； 3. 每个slip sheet上面贴一张艾利贴纸（不干胶贴纸）和一张普通贴纸（A4纸），slip sheet打印的普通贴纸的尺寸不能比艾利贴纸小，普通贴纸内容见附件； 4. 在产品上和包装上要有日期码、以及要有MADE IN CHINA和ZURU字样； 5. 产品如有扎带口要剪平，不能刮手。 6. 此单需要验货，请多备料 7. 此单以slip sheet出货，77485：1152pcs/96CTN/Slip Sheet | W9: Maggie Xie | X9: 2182.1336 | Y9: 6546.4008 | AA9: 94397-2.27 | AB9: 77485SLB-S004 | AC9: 已入 | AD9: 系统出单 | AF9: 3456 | AG9: =AF9-I9 -> 0 | AK9: =I9 -> 3456 | AM9: =I9 -> 3456 | AU9: 3456 | AZ9: =I9/12 -> 288 | BU9: =AK9+AL9 -> 3456 | BV9: =BV8+BU9 -> 2263862 | CA9: =SUM(BX$1:CB$1)-BV9 -> 556138 | CC9: =AW9+AX9+BE9+BF9 -> 0 | CD9: =CD8+CC9 -> 47752.571 | CH9: =$CF$1+$CG$1+$CH$1+$CI$1-CD9 -> 12247.429
A10: 45621 | B10: WAL-MART STORES INC. USA | C10: 美国 | D10: 4500152202 | E10: 0877286379 RIDGEVILLE SC | F10: 4500152202-20 | G10: 77485SLB-S004 | H10: 3代迷你小手袋 | I10: 3456 | J10: 0 | K10: 1152 | L10: =I10/K10 -> 3 | M10: 45300 | N10: 45296 | O10: 2025/1/6 自检 | P10: PASS | R10: 45621 | S10: 无 | T10: 12/20 RFID贴纸 艾利贴纸（不干胶贴纸）和一张普通贴纸（A4纸） | V10: 日期码格式：ZURU DGYYYYMMDD CHINA(日期避开周末和法定节假日即可） 日期：按实际生产日期 Tracking Code: Packaging Info: 77485SLB-S004 1.包装要求： MA 1L收缩膜+ 客版 收藏指南B版+MA 纸袋+客版 1L PDQ，翻单：4500128976 每pcs产品上要贴1张RFID贴纸，贴纸由ZURU提供，贴纸位置请严格按照我们签回的签板； Remark: 77485SLB-S004 1.包装要求： MA 1L收缩膜+ 客版 收藏指南B版+MA 纸袋+客版 1L PDQ，翻单：4500128976 每pcs产品上要贴1张RFID贴纸，贴纸由ZURU提供，贴纸位置请严格按照我们签回的签板； 2. 外箱印刷带条码的RFID箱唛：RFID紫色色带+WM Dept.图标+RFID图标+ITF-14条码，四面右下角印刷ZURU logo, ITFF条码只印刷在正唛一面，在加印的时候确保 条形码能扫描出来，外箱侧面任一角落加印："MADE IN CHINA" 字样； 3. 每个slip sheet上面贴一张艾利贴纸（不干胶贴纸）和一张普通贴纸（A4纸），slip sheet打印的普通贴纸的尺寸不能比艾利贴纸小，普通贴纸内容见附件； 4. 在产品上和包装上要有日期码、以及要有MADE IN CHINA和ZURU字样； 5. 产品如有扎带口要剪平，不能刮手。 6. 此单需要验货，请多备料 7. 此单以slip sheet出货，77485：1152pcs/96CTN/Slip Sheet | W10: Maggie Xie | X10: 2182.1336 | Y10: 6546.4008 | AA10: 94397-2.27 | AB10: 77485SLB-S004 | AC10: 已入 | AD10: 系统出单 | AG10: =AF10-I10 -> -3456 | AK10: =I10 -> 3456 | AM10: =I10 -> 3456 | AU10: 3456 | AZ10: =I10/12 -> 288 | BU10: =AK10+AL10 -> 3456 | BV10: =BV9+BU10 -> 2267318 | CA10: =SUM(BX$1:CB$1)-BV10 -> 552682 | CC10: =AW10+AX10+BE10+BF10 -> 0 | CD10: =CD9+CC10 -> 47752.571 | CH10: =$CF$1+$CG$1+$CH$1+$CI$1-CD10 -> 12247.429
A11: 45621 | B11: WAL-MART STORES INC. USA | C11: 美国 | D11: 4500152202 | E11: 0877286391 EASTVALE | F11: 4500152202-30 | G11: 77485SLB-S004 | H11: 3代迷你小手袋 | I11: 5760 | J11: 0 | K11: 1152 | L11: =I11/K11 -> 5 | M11: 45300 | N11: 45296 | O11: 2025/1/6 自检 | P11: PASS | R11: 45621 | S11: 无 | T11: 12/20 RFID贴纸 艾利贴纸（不干胶贴纸）和一张普通贴纸（A4纸） | V11: 日期码格式：ZURU DGYYYYMMDD CHINA(日期避开周末和法定节假日即可） 日期：按实际生产日期 Tracking Code: Packaging Info: 77485SLB-S004 1.包装要求： MA 1L收缩膜+ 客版 收藏指南B版+MA 纸袋+客版 1L PDQ，翻单：4500128976 每pcs产品上要贴1张RFID贴纸，贴纸由ZURU提供，贴纸位置请严格按照我们签回的签板； Remark: 77485SLB-S004 1.包装要求： MA 1L收缩膜+ 客版 收藏指南B版+MA 纸袋+客版 1L PDQ，翻单：4500128976 每pcs产品上要贴1张RFID贴纸，贴纸由ZURU提供，贴纸位置请严格按照我们签回的签板； 2. 外箱印刷带条码的RFID箱唛：RFID紫色色带+WM Dept.图标+RFID图标+ITF-14条码，四面右下角印刷ZURU logo, ITFF条码只印刷在正唛一面，在加印的时候确保 条形码能扫描出来，外箱侧面任一角落加印："MADE IN CHINA" 字样； 3. 每个slip sheet上面贴一张艾利贴纸（不干胶贴纸）和一张普通贴纸（A4纸），slip sheet打印的普通贴纸的尺寸不能比艾利贴纸小，普通贴纸内容见附件； 4. 在产品上和包装上要有日期码、以及要有MADE IN CHINA和ZURU字样； 5. 产品如有扎带口要剪平，不能刮手。 6. 此单需要验货，请多备料 7. 此单以slip sheet出货，77485：1152pcs/96CTN/Slip Sheet | W11: Maggie Xie | X11: 2182.1336 | Y11: 10910.668 | AA11: 94052-1.15 | AB11: 77485SLB-S004 | AC11: 已入 | AD11: 系统出单 | AF11: 5760 | AG11: =AF11-I11 -> 0 | AK11: =I11 -> 5760 | AM11: =I11 -> 5760 | AU11: 5760 | AZ11: =I11/12 -> 480 | BU11: =AK11+AL11 -> 5760 | BV11: =BV10+BU11 -> 2273078 | CA11: =SUM(BX$1:CB$1)-BV11 -> 546922 | CC11: =AW11+AX11+BE11+BF11 -> 0 | CD11: =CD10+CC11 -> 47752.571 | CH11: =$CF$1+$CG$1+$CH$1+$CI$1-CD11 -> 12247.429
A12: 45621 | B12: WAL-MART STORES INC. USA | C12: 美国 | D12: 4500152202 | E12: 0877286395 STATESBORO | F12: 4500152202-40 | G12: 77485SLB-S004 | H12: 3代迷你小手袋 | I12: 1152 | J12: 0 | K12: 1152 | L12: =I12/K12 -> 1 | M12: 45300 | N12: 45296 | O12: 2025/1/6 自检 | P12: PASS | R12: 45621 | S12: 无 | T12: 12/20 RFID贴纸 艾利贴纸（不干胶贴纸）和一张普通贴纸（A4纸） | V12: 日期码格式：ZURU DGYYYYMMDD CHINA(日期避开周末和法定节假日即可） 日期：按实际生产日期 Tracking Code: Packaging Info: 77485SLB-S004 1.包装要求： MA 1L收缩膜+ 客版 收藏指南B版+MA 纸袋+客版 1L PDQ，翻单：4500128976 每pcs产品上要贴1张RFID贴纸，贴纸由ZURU提供，贴纸位置请严格按照我们签回的签板； Remark: 77485SLB-S004 1.包装要求： MA 1L收缩膜+ 客版 收藏指南B版+MA 纸袋+客版 1L PDQ，翻单：4500128976 每pcs产品上要贴1张RFID贴纸，贴纸由ZURU提供，贴纸位置请严格按照我们签回的签板； 2. 外箱印刷带条码的RFID箱唛：RFID紫色色带+WM Dept.图标+RFID图标+ITF-14条码，四面右下角印刷ZURU logo, ITFF条码只印刷在正唛一面，在加印的时候确保 条形码能扫描出来，外箱侧面任一角落加印："MADE IN CHINA" 字样； 3. 每个slip sheet上面贴一张艾利贴纸（不干胶贴纸）和一张普通贴纸（A4纸），slip sheet打印的普通贴纸的尺寸不能比艾利贴纸小，普通贴纸内容见附件； 4. 在产品上和包装上要有日期码、以及要有MADE IN CHINA和ZURU字样； 5. 产品如有扎带口要剪平，不能刮手。 6. 此单需要验货，请多备料 7. 此单以slip sheet出货，77485：1152pcs/96CTN/Slip Sheet | W12: Maggie Xie | X12: 2182.1336 | Y12: 2182.1336 | AA12: 94052-1.15 | AB12: 77485SLB-S004 | AC12: 已入 | AD12: 系统出单 | AF12: 1152 | AG12: =AF12-I12 -> 0 | AK12: =I12 -> 1152 | AM12: =I12 -> 1152 | AU12: 1152 | AZ12: =I12/12 -> 96 | BU12: =AK12+AL12 -> 1152 | BV12: =BV11+BU12 -> 2274230 | CA12: =SUM(BX$1:CB$1)-BV12 -> 545770 | CC12: =AW12+AX12+BE12+BF12 -> 0 | CD12: =CD11+CC12 -> 47752.571 | CH12: =$CF$1+$CG$1+$CH$1+$CI$1-CD12 -> 12247.429
A13: 45621 | B13: WAL-MART STORES INC. USA | C13: 美国 | D13: 4500152202 | E13: 0877286401 SUFFOLK | F13: 4500152202-50 | G13: 77485SLB-S004 | H13: 3代迷你小手袋 | I13: 4608 | J13: 0 | K13: 1152 | L13: =I13/K13 -> 4 | M13: 45300 | N13: 45296 | O13: 2025/1/6 自检 | P13: PASS | R13: 45621 | S13: 无 | T13: 12/20 RFID贴纸 艾利贴纸（不干胶贴纸）和一张普通贴纸（A4纸） | V13: 日期码格式：ZURU DGYYYYMMDD CHINA(日期避开周末和法定节假日即可） 日期：按实际生产日期 Tracking Code: Packaging Info: 77485SLB-S004 1.包装要求： MA 1L收缩膜+ 客版 收藏指南B版+MA 纸袋+客版 1L PDQ，翻单：4500128976 每pcs产品上要贴1张RFID贴纸，贴纸由ZURU提供，贴纸位置请严格按照我们签回的签板； Remark: 77485SLB-S004 1.包装要求： MA 1L收缩膜+ 客版 收藏指南B版+MA 纸袋+客版 1L PDQ，翻单：4500128976 每pcs产品上要贴1张RFID贴纸，贴纸由ZURU提供，贴纸位置请严格按照我们签回的签板； 2. 外箱印刷带条码的RFID箱唛：RFID紫色色带+WM Dept.图标+RFID图标+ITF-14条码，四面右下角印刷ZURU logo, ITFF条码只印刷在正唛一面，在加印的时候确保 条形码能扫描出来，外箱侧面任一角落加印："MADE IN CHINA" 字样； 3. 每个slip sheet上面贴一张艾利贴纸（不干胶贴纸）和一张普通贴纸（A4纸），slip sheet打印的普通贴纸的尺寸不能比艾利贴纸小，普通贴纸内容见附件； 4. 在产品上和包装上要有日期码、以及要有MADE IN CHINA和ZURU字样； 5. 产品如有扎带口要剪平，不能刮手。 6. 此单需要验货，请多备料 7. 此单以slip sheet出货，77485：1152pcs/96CTN/Slip Sheet | W13: Maggie Xie | X13: 2182.1336 | Y13: 8728.5344 | AA13: 94018-1.13 | AB13: 77485SLB-S004 | AC13: 已入 | AD13: 系统出单 | AF13: 4608 | AG13: =AF13-I13 -> 0 | AK13: =I13 -> 4608 | AM13: =I13 -> 4608 | AU13: 4608 | AZ13: =I13/12 -> 384 | BU13: =AK13+AL13 -> 4608 | BV13: =BV12+BU13 -> 2278838 | CA13: =SUM(BX$1:CB$1)-BV13 -> 541162 | CC13: =AW13+AX13+BE13+BF13 -> 0 | CD13: =CD12+CC13 -> 47752.571 | CH13: =$CF$1+$CG$1+$CH$1+$CI$1-CD13 -> 12247.429
A14: 45621 | B14: WAL-MART STORES INC. USA | C14: 美国 | D14: 4500152202 | E14: 0877286405 HOUSTON | F14: 4500152202-60 | G14: 77485SLB-S004 | H14: 3代迷你小手袋 | I14: 5760 | J14: 0 | K14: 1152 | L14: =I14/K14 -> 5 | M14: 45300 | N14: 45296 | O14: 2025/1/6 自检 | P14: PASS | R14: 45621 | S14: 无 | T14: 12/20 RFID贴纸 艾利贴纸（不干胶贴纸）和一张普通贴纸（A4纸） | V14: 日期码格式：ZURU DGYYYYMMDD CHINA(日期避开周末和法定节假日即可） 日期：按实际生产日期 Tracking Code: Packaging Info: 77485SLB-S004 1.包装要求： MA 1L收缩膜+ 客版 收藏指南B版+MA 纸袋+客版 1L PDQ，翻单：4500128976 每pcs产品上要贴1张RFID贴纸，贴纸由ZURU提供，贴纸位置请严格按照我们签回的签板； Remark: 77485SLB-S004 1.包装要求： MA 1L收缩膜+ 客版 收藏指南B版+MA 纸袋+客版 1L PDQ，翻单：4500128976 每pcs产品上要贴1张RFID贴纸，贴纸由ZURU提供，贴纸位置请严格按照我们签回的签板； 2. 外箱印刷带条码的RFID箱唛：RFID紫色色带+WM Dept.图标+RFID图标+ITF-14条码，四面右下角印刷ZURU logo, ITFF条码只印刷在正唛一面，在加印的时候确保 条形码能扫描出来，外箱侧面任一角落加印："MADE IN CHINA" 字样； 3. 每个slip sheet上面贴一张艾利贴纸（不干胶贴纸）和一张普通贴纸（A4纸），slip sheet打印的普通贴纸的尺寸不能比艾利贴纸小，普通贴纸内容见附件； 4. 在产品上和包装上要有日期码、以及要有MADE IN CHINA和ZURU字样； 5. 产品如有扎带口要剪平，不能刮手。 6. 此单需要验货，请多备料 7. 此单以slip sheet出货，77485：1152pcs/96CTN/Slip Sheet | W14: Maggie Xie | X14: 2182.1336 | Y14: 10910.668 | AA14: 94397-2.27 | AB14: 77485SLB-S004 | AC14: 已入 | AD14: 系统出单 | AF14: 5760 | AG14: =AF14-I14 -> 0 | AK14: =I14 -> 5760 | AM14: =I14 -> 5760 | AU14: 5760 | AZ14: =I14/12 -> 480 | BU14: =AK14+AL14 -> 5760 | BV14: =BV13+BU14 -> 2284598 | CA14: =SUM(BX$1:CB$1)-BV14 -> 535402 | CC14: =AW14+AX14+BE14+BF14 -> 0 | CD14: =CD13+CC14 -> 47752.571 | CH14: =$CF$1+$CG$1+$CH$1+$CI$1-CD14 -> 12247.429
A15: 45621 | B15: WAL-MART STORES INC. USA | C15: 美国 | D15: 4500152202 | E15: 0877286409 MOBILE | F15: 4500152202-70 | G15: 77485SLB-S004 | H15: 3代迷你小手袋 | I15: 2304 | J15: 0 | K15: 1152 | L15: =I15/K15 -> 2 | M15: 45300 | N15: 45296 | O15: 2025/1/6 自检 | P15: PASS | R15: 45621 | S15: 无 | T15: 12/20 RFID贴纸 艾利贴纸（不干胶贴纸）和一张普通贴纸（A4纸） | V15: 日期码格式：ZURU DGYYYYMMDD CHINA(日期避开周末和法定节假日即可） 日期：按实际生产日期 Tracking Code: Packaging Info: 77485SLB-S004 1.包装要求： MA 1L收缩膜+ 客版 收藏指南B版+MA 纸袋+客版 1L PDQ，翻单：4500128976 每pcs产品上要贴1张RFID贴纸，贴纸由ZURU提供，贴纸位置请严格按照我们签回的签板； Remark: 77485SLB-S004 1.包装要求： MA 1L收缩膜+ 客版 收藏指南B版+MA 纸袋+客版 1L PDQ，翻单：4500128976 每pcs产品上要贴1张RFID贴纸，贴纸由ZURU提供，贴纸位置请严格按照我们签回的签板； 2. 外箱印刷带条码的RFID箱唛：RFID紫色色带+WM Dept.图标+RFID图标+ITF-14条码，四面右下角印刷ZURU logo, ITFF条码只印刷在正唛一面，在加印的时候确保 条形码能扫描出来，外箱侧面任一角落加印："MADE IN CHINA" 字样； 3. 每个slip sheet上面贴一张艾利贴纸（不干胶贴纸）和一张普通贴纸（A4纸），slip sheet打印的普通贴纸的尺寸不能比艾利贴纸小，普通贴纸内容见附件； 4. 在产品上和包装上要有日期码、以及要有MADE IN CHINA和ZURU字样； 5. 产品如有扎带口要剪平，不能刮手。 6. 此单需要验货，请多备料 7. 此单以slip sheet出货，77485：1152pcs/96CTN/Slip Sheet | W15: Maggie Xie | X15: 2182.1336 | Y15: 4364.2672 | AA15: 94052-1.15 | AB15: 77485SLB-S004 | AC15: 已入 | AD15: 系统出单 | AF15: 2304 | AG15: =AF15-I15 -> 0 | AK15: =I15 -> 2304 | AM15: =I15 -> 2304 | AU15: 2304 | AZ15: =I15/12 -> 192 | BU15: =AK15+AL15 -> 2304 | BV15: =BV14+BU15 -> 2286902 | CA15: =SUM(BX$1:CB$1)-BV15 -> 533098 | CC15: =AW15+AX15+BE15+BF15 -> 0 | CD15: =CD14+CC15 -> 47752.571 | CH15: =$CF$1+$CG$1+$CH$1+$CI$1-CD15 -> 12247.429
A16: 45618 | B16: CRG | C16: 哥斯达黎加 | D16: 4500152087 | E16: ZU01-25 | F16: 4500152087-100 | G16: 77485GQ7-S001 | H16: 3代迷你小手袋 | I16: 2000 | J16: 0 | K16: 50 | L16: =I16/K16 -> 40 | M16: 45660 | N16: 45656 | P16: PASS | R16: 45623 | S16: 无 | T16: 45636 | V16: 日期码格式：ZURU INC(BVI) 标准格式 日期：按实际生产日期 Packaging Info: 77485GQ7:MA 1L包装+进口商贴纸+箱唛 Remark: | W16: Ava Liang | X16: 2.0019 | Y16: =X16*I16 -> 4003.8 | AA16: 88961-1.9 | AB16: 77485GQ7-S001 | AC16: 已入 | AD16: 系统出单 | AF16: 2000 | AG16: =AF16-I16 -> 0 | AI16: OK | AK16: =I16 -> 2000 | AM16: =I16 -> 2000 | AS16: =I16 -> 2000 | BE16: =I16/25 -> 80 | BU16: =AK16+AL16 -> 2000 | BV16: =BV15+BU16 -> 2288902 | CA16: =SUM(BX$1:CB$1)-BV16 -> 531098 | CC16: =AW16+AX16+BE16+BF16 -> 80 | CD16: =CD15+CC16 -> 47832.571 | CH16: =$CF$1+$CG$1+$CH$1+$CI$1-CD16 -> 12167.429
A17: 45587 | B17: WALGREEN CO. | C17: 美国 | D17: MPOWAL034 | G17: 77485-S001 | H17: 3代迷你小手袋 | I17: 0 | J17: 0 | K17: 24 | L17: =I17/K17 -> 0 | M17: 45656 | N17: 45652 | R17: 周转箱 | S17: 无 | T17: WIC贴纸（WIC # 795592） | V17: Remark:1. 2% 损耗 2. 送货前必需通知我司安排验货 3.77485：MA 1L包装 + WIC贴纸（WIC # 795592） 4.产品和包装上要有ZURU 标准格式 tracking code DG20241122 4.先安排CRD 11/22的数量，CRD 12/10的数量等通知后再安排 5.11/22完成23452PCS, 11/23抽板测试，抽板后才可以安排送货。所有来料都要测试符合美国联邦法规和州法规后才可以做大货。如因测试问题延期造成罚款需由工厂承担。 6. 装箱方式需另外跟PM确认，用周转箱/周转框，出货前需提供装箱清单 7.收到PO后请寄出每款1个球和全套散件给实验室。大货样77515 12PCS，77555 16PCS,7748516PCS, 待通知后再寄出。 | W17: Cara Li | X17: 1.7942 | Y17: =X17*I17 -> 0 | AB17: 77485-S001 | AC17: 已入 | AD17: 系统出单 | AG17: =AF17-I17 -> 0 | AI17: OK | AK17: =I17 -> 0 | AM17: =I17 -> 0 | AS17: =I17 -> 0 | BU17: =AK17+AL17 -> 0 | BV17: =BV16+BU17 -> 2288902 | CA17: =SUM(BX$1:CB$1)-BV17 -> 531098 | CC17: =AW17+AX17+BE17+BF17 -> 0 | CD17: =CD16+CC17 -> 47832.571 | CH17: =$CF$1+$CG$1+$CH$1+$CI$1-CD17 -> 12167.429
A18: 45604 | B18: Inventive Toys | C18: 俄罗斯联邦 | D18: 4500150836 | F18: 4500150836-20 | G18: 77485GQ6-S001 | H18: 3代迷你小手袋 | I18: 2028 | J18: 0 | K18: 52 | L18: =I18/K18 -> 39 | M18: 45657 | N18: 45653 | O18: 注意 ：外包装 (指: 收缩膜/彩卡/铝箔袋/挂卡/PDQ) /外箱不要打ZURU标准日期码！胶件可以打日期码。 | P18: PASS | R18: 45622 | S18: 无 | T18: 进口商贴纸+EAN条码贴纸 | V18: 日期码格式：外包装/外箱不要打ZURU标准日期码 日期： Packaging Info: 注意 ：外包装 (指: 收缩膜/彩卡/铝箔袋/挂卡/PDQ) /外箱不要打ZURU标准日期码！胶件可以打日期码。 外包装（包括收缩膜/彩卡/PDQ）都不能含Instagram and facebook logo等社交logo; 1L MA 收缩膜 或者彩卡+ 进口商贴纸； MA PDQ + EAN条码贴纸 ， MA指南/说明书（如有）; Remark: 标准配比 ；整单货期2025年1月3 | W18: Ann Zhang | X18: 1.9026 | Y18: =I18*X18 -> 3858.4728 | AA18: 94071-1.16 | AB18: 77485GQ6-S001 | AC18: 已入 | AD18: 系统出单 | AF18: =1976+52 -> 2028 | AG18: =AF18-I18 -> 0 | AI18: OK | AK18: =I18 -> 2028 | AM18: =I18 -> 2028 | AS18: =I18 -> 2028 | BC18: =AK18/13 -> 156 | BU18: =AK18+AL18 -> 2028 | BV18: =BV17+BU18 -> 2290930 | CA18: =SUM(BX$1:CB$1)-BV18 -> 529070 | CC18: =AW18+AX18+BE18+BF18 -> 0 | CD18: =CD17+CC18 -> 47832.571 | CH18: =$CF$1+$CG$1+$CH$1+$CI$1-CD18 -> 12167.429
A19: 45614 | B19: BURLINGTON COAT FACTORY | C19: 美国 | D19: 4500151472 | E19: 客户PO#383017 506 | F19: 4500151472-50 | G19: 77486-S001 | H19: 3代迷你小手袋 圆筒装 | I19: 1800 | J19: 0 | K19: 12 | L19: =I19/K19 -> 150 | M19: 45663 | N19: 45659 | P19: PASS | R19: 45614 | S19: 有 | T19: 45638 | V19: 日期码格式：ZURU INC(BVI) 标准格式 日期：按实际生产日期 Packaging Info: 1，ZURU MA （首选1L）UPC版本+客供价格贴纸+外箱贴纸，出口美国 有PVC桶的价格贴纸贴在PVC桶上面 Remark: 2，产品和包装上印刷ZURU 标准日期码； 3，纸箱中间靠上沿印刷ZURU LOGO，见箱唛资料 4、外箱UCC 条码贴纸，尺寸: 4*6inch，贴在其中一面正唛右下角，贴纸距离外箱底部3.5cm, 侧边距离3.5cm。外箱贴纸由跟单提供电子版, 工厂自行安排，不可用 封箱胶覆盖贴纸条码，贴纸需要可以扫描且无损坏. 5，每个产品有一个价格贴纸， 价格贴纸覆盖UPC条码上 （若UPC 条码太大，可以露出ITEM#, 覆盖条码即可），若价格贴纸覆盖UPC 会挡住文字/图案，在产品背面 找空白处粘贴价格贴纸即可。贴的时候要是会覆盖包装上重要的信息和图案，需要告知跟单。 | W19: Jessi Xu | X19: 4.1259 | Y19: =I19*X19 -> 7426.62 | AA19: 88988-1.11 | AB19: 77486-S001 | AC19: 已入 | AD19: 系统出单 | AF19: 1800 | AG19: =AF19-I19 -> 0 | AI19: OK | AK19: =I19*2 -> 3600 | AM19: =I19*2 -> 3600 | AS19: =I19*2 -> 3600 | BN19: =I19 -> 1800 | BO19: =I19 -> 1800 | BQ19: =I19 -> 1800 | BU19: =AK19+AL19 -> 3600 | BV19: =BV18+BU19 -> 2294530 | CA19: =SUM(BX$1:CB$1)-BV19 -> 525470 | CC19: =AW19+AX19+BE19+BF19 -> 0 | CD19: =CD18+CC19 -> 47832.571 | CH19: =$CF$1+$CG$1+$CH$1+$CI$1-CD19 -> 12167.429
A20: 45614 | B20: BURLINGTON COAT FACTORY | C20: 美国 | D20: 4500151472 | E20: 客户PO#383019 406 | F20: 4500151472-100 | G20: 77486-S001 | H20: 3代迷你小手袋 圆筒装 | I20: 3600 | J20: 0 | K20: 12 | L20: =I20/K20 -> 300 | M20: 45663 | N20: 45659 | P20: PASS | R20: 45614 | S20: 有 | T20: 45638 | V20: 日期码格式：ZURU INC(BVI) 标准格式 日期：按实际生产日期 Packaging Info: 1，ZURU MA （首选1L）UPC版本+客供价格贴纸+外箱贴纸，出口美国 有PVC桶的价格贴纸贴在PVC桶上面 Remark: 2，产品和包装上印刷ZURU 标准日期码； 3，纸箱中间靠上沿印刷ZURU LOGO，见箱唛资料 4、外箱UCC 条码贴纸，尺寸: 4*6inch，贴在其中一面正唛右下角，贴纸距离外箱底部3.5cm, 侧边距离3.5cm。外箱贴纸由跟单提供电子版, 工厂自行安排，不可用 封箱胶覆盖贴纸条码，贴纸需要可以扫描且无损坏. 5，每个产品有一个价格贴纸， 价格贴纸覆盖UPC条码上 （若UPC 条码太大，可以露出ITEM#, 覆盖条码即可），若价格贴纸覆盖UPC 会挡住文字/图案，在产品背面 找空白处粘贴价格贴纸即可。贴的时候要是会覆盖包装上重要的信息和图案，需要告知跟单。 | W20: Jessi Xu | X20: 4.1024 | Y20: =I20*X20 -> 14768.64 | AA20: 88981-1.10 | AB20: 77486-S001 | AC20: 已入 | AD20: 系统出单 | AF20: 3600 | AG20: =AF20-I20 -> 0 | AI20: OK | AK20: =I20*2 -> 7200 | AM20: =I20*2 -> 7200 | AS20: =I20*2 -> 7200 | BN20: =I20 -> 3600 | BO20: =I20 -> 3600 | BQ20: =I20 -> 3600 | BU20: =AK20+AL20 -> 7200 | BV20: =BV19+BU20 -> 2301730 | CA20: =SUM(BX$1:CB$1)-BV20 -> 518270 | CC20: =AW20+AX20+BE20+BF20 -> 0 | CD20: =CD19+CC20 -> 47832.571 | CH20: =$CF$1+$CG$1+$CH$1+$CI$1-CD20 -> 12167.429
A21: 45603 | B21: DD’S DISCOUNTS | C21: 美国 | D21: 4500150308 | E21: 70054030 | F21: 4500150308-10 | G21: 77486-S001 | H21: 3代迷你小手袋 圆筒装 | I21: 600 | J21: 0 | K21: 12 | L21: =I21/K21 -> 50 | M21: 45670 | N21: 45666 | P21: PASS | R21: 45610 | S21: 无 | T21: 欠客供价格贴纸 | V21: 日期码格式： 标准格式 日期：按实际生产日期 Packaging Info: 1.ZURU MA UPC 收缩膜+客版铜版纸+PVC桶 + 客供价格贴纸，出口美国 , 优先使用MA 1L 最新版本 。 Remark: 1.ZURU MA UPC 收缩膜+客版铜版纸+PVC桶 + 客供价格贴纸，出口美国 , 优先使用MA 1L 最新版本 。 2.价格贴纸位于包装正面右下角，不挡住重要信息即可，可适当调整 ，价格贴纸由跟单提供。 3.标准日期码格式，产品和包装必须有日期码 。 4.同个产品同个货期不可出现不同的包装。 5. PVC 桶中球不能出现完全相同的ASSORTMENT ， 即同一个PVC 中球里的ASSORTMENT 需要不同。 以免消费者失望。 6.PVC 桶上加上 MINI BRANDS 的LOGO 贴纸 （ ZURU 统一要求的） 7.收缩膜可使用标版带UPC条码MA，无需白色贴纸覆盖。 8. #77516 收缩膜用3L+空白贴纸 | W21: Taylor Liao | X21: 4.1259 | Y21: =I21*X21 -> 2475.54 | AA21: 94145-1.21 | AB21: 77486-S001 | AC21: 已入 | AD21: 系统出单 | AF21: 600 | AG21: =AF21-I21 -> 0 | AI21: OK | AK21: =I21*2 -> 1200 | AM21: =I21*2 -> 1200 | AS21: =I21*2 -> 1200 | BN21: =I21 -> 600 | BO21: =I21 -> 600 | BQ21: =I21 -> 600 | BU21: =AK21+AL21 -> 1200 | BV21: =BV20+BU21 -> 2302930 | CA21: =SUM(BX$1:CB$1)-BV21 -> 517070 | CC21: =AW21+AX21+BE21+BF21 -> 0 | CD21: =CD20+CC21 -> 47832.571 | CH21: =$CF$1+$CG$1+$CH$1+$CI$1-CD21 -> 12167.429
A22: 45637 | B22: WAL-MART STORES INC. USA | C22: 美国 | D22: 4500153681 | E22: 0881410086 STATESBORO | F22: 4500153681-10 | G22: 77485SLB-S004 | H22: 3代迷你小手袋 | I22: 1152 | J22: 0 | K22: 1152 | L22: =I22/K22 -> 1 | M22: 45671 | N22: 45667 | O22: 2025/1/14第三方验货 | P22: PASS | R22: 外箱印刷带条码的RFID箱唛：RFID紫色色带+WM Dept.图标+RFID图标+ITF-14条码，四面右下角印刷ZURU logo, ITFF条码只印刷在正唛一面，在加印的时候确保 条形码能扫描出来，外箱侧面任一角落加印："MADE IN CHINA" 字样； | S22: 无 | T22: 12/20 寄出RFID贴纸 | V22: 日期码格式：ZURU DGYYYYMMDD CHINA(日期避开周末和法定节假日即可） 日期：按实际生产日期 Packaging Info: 77485SLB-S004 1.包装要求： MA 1L收缩膜+ 客版 收藏指南B版+MA 纸袋+客版 1L PDQ，翻单：4500128976 每pcs产品上要贴1张RFID贴纸，贴纸由ZURU提供，贴纸位置请严格按照我们签回的签板； Remark: 77485SLB-S004 1.包装要求： MA 1L收缩膜+ 客版 收藏指南B版+MA 纸袋+客版 1L PDQ，翻单：4500128976 每pcs产品上要贴1张RFID贴纸，贴纸由ZURU提供，贴纸位置请严格按照我们签回的签板； 2. 外箱印刷带条码的RFID箱唛：RFID紫色色带+WM Dept.图标+RFID图标+ITF-14条码，四面右下角印刷ZURU logo, ITFF条码只印刷在正唛一面，在加印的时候确保 条形码能扫描出来，外箱侧面任一角落加印："MADE IN CHINA" 字样； 3. 每个slip sheet上面贴一张艾利贴纸（不干胶贴纸）和一张普通贴纸（A4纸），slip sheet打印的普通贴纸的尺寸不能比艾利贴纸小，普通贴纸内容见附件； 4. 在产品上和包装上要有日期码、以及要有MADE IN CHINA和ZURU字样； 5. 产品如有扎带口要剪平，不能刮手。 6. 此单需要验货，请多备料 7. 此单以slip sheet出货，77485：1152pcs/96CTN/Slip Sheet | W22: Maggie Xie | X22: 2206.6131 | Y22: 4364.2672 | AA22: 94124-1.20 | AB22: 77485SLB-S004 | AC22: 已入 | AD22: 系统出单 | AF22: 1152 | AG22: =AF22-I22 -> 0 | AK22: =I22 -> 1152 | AM22: =I22 -> 1152 | AU22: =I22 -> 1152 | AZ22: =I22/12 -> 96 | BU22: =AK22+AL22 -> 1152 | BV22: =BV21+BU22 -> 2304082 | CA22: =SUM(BX$1:CB$1)-BV22 -> 515918 | CC22: =AW22+AX22+BE22+BF22 -> 0 | CD22: =CD21+CC22 -> 47832.571 | CH22: =$CF$1+$CG$1+$CH$1+$CI$1-CD22 -> 12167.429
A23: 45637 | B23: WAL-MART STORES INC. USA | C23: 美国 | D23: 4500153681 | E23: 0881410104 ELWOOD | F23: 4500153681-20 | G23: 77485SLB-S004 | H23: 3代迷你小手袋 | I23: 3456 | J23: 0 | K23: 1152 | L23: =I23/K23 -> 3 | M23: 45671 | N23: 45667 | O23: 2025/1/14第三方验货 | P23: PASS | R23: 外箱印刷带条码的RFID箱唛：RFID紫色色带+WM Dept.图标+RFID图标+ITF-14条码，四面右下角印刷ZURU logo, ITFF条码只印刷在正唛一面，在加印的时候确保 条形码能扫描出来，外箱侧面任一角落加印："MADE IN CHINA" 字样； | S23: 无 | T23: 12/20 寄出RFID贴纸 | V23: 日期码格式：ZURU DGYYYYMMDD CHINA(日期避开周末和法定节假日即可） 日期：按实际生产日期 Packaging Info: 77485SLB-S004 1.包装要求： MA 1L收缩膜+ 客版 收藏指南B版+MA 纸袋+客版 1L PDQ，翻单：4500128976 每pcs产品上要贴1张RFID贴纸，贴纸由ZURU提供，贴纸位置请严格按照我们签回的签板； Remark: 77485SLB-S004 1.包装要求： MA 1L收缩膜+ 客版 收藏指南B版+MA 纸袋+客版 1L PDQ，翻单：4500128976 每pcs产品上要贴1张RFID贴纸，贴纸由ZURU提供，贴纸位置请严格按照我们签回的签板； 2. 外箱印刷带条码的RFID箱唛：RFID紫色色带+WM Dept.图标+RFID图标+ITF-14条码，四面右下角印刷ZURU logo, ITFF条码只印刷在正唛一面，在加印的时候确保 条形码能扫描出来，外箱侧面任一角落加印："MADE IN CHINA" 字样； 3. 每个slip sheet上面贴一张艾利贴纸（不干胶贴纸）和一张普通贴纸（A4纸），slip sheet打印的普通贴纸的尺寸不能比艾利贴纸小，普通贴纸内容见附件； 4. 在产品上和包装上要有日期码、以及要有MADE IN CHINA和ZURU字样； 5. 产品如有扎带口要剪平，不能刮手。 6. 此单需要验货，请多备料 7. 此单以slip sheet出货，77485：1152pcs/96CTN/Slip Sheet | W23: Maggie Xie | X23: 2206.6131 | Y23: 4364.2672 | AA23: 94051-1.15 | AB23: 77485SLB-S004 | AC23: 已入 | AD23: 系统出单 | AF23: 3456 | AG23: =AF23-I23 -> 0 | AK23: =I23 -> 3456 | AM23: =I23 -> 3456 | AU23: =I23 -> 3456 | AZ23: =I23/12 -> 288 | BU23: =AK23+AL23 -> 3456 | BV23: =BV22+BU23 -> 2307538 | CA23: =SUM(BX$1:CB$1)-BV23 -> 512462 | CC23: =AW23+AX23+BE23+BF23 -> 0 | CD23: =CD22+CC23 -> 47832.571 | CH23: =$CF$1+$CG$1+$CH$1+$CI$1-CD23 -> 12167.429
A24: 45637 | B24: WAL-MART STORES INC. USA | C24: 美国 | D24: 4500153681 | E24: 0881410110 EASTVALE | F24: 4500153681-30 | G24: 77485SLB-S004 | H24: 3代迷你小手袋 | I24: 1152 | J24: 0 | K24: 1152 | L24: =I24/K24 -> 1 | M24: 45671 | N24: 45667 | O24: 2025/1/14第三方验货 | P24: PASS | R24: 外箱印刷带条码的RFID箱唛：RFID紫色色带+WM Dept.图标+RFID图标+ITF-14条码，四面右下角印刷ZURU logo, ITFF条码只印刷在正唛一面，在加印的时候确保 条形码能扫描出来，外箱侧面任一角落加印："MADE IN CHINA" 字样； | S24: 无 | T24: 12/20 寄出RFID贴纸 | V24: 日期码格式：ZURU DGYYYYMMDD CHINA(日期避开周末和法定节假日即可） 日期：按实际生产日期 Packaging Info: 77485SLB-S004 1.包装要求： MA 1L收缩膜+ 客版 收藏指南B版+MA 纸袋+客版 1L PDQ，翻单：4500128976 每pcs产品上要贴1张RFID贴纸，贴纸由ZURU提供，贴纸位置请严格按照我们签回的签板； Remark: 77485SLB-S004 1.包装要求： MA 1L收缩膜+ 客版 收藏指南B版+MA 纸袋+客版 1L PDQ，翻单：4500128976 每pcs产品上要贴1张RFID贴纸，贴纸由ZURU提供，贴纸位置请严格按照我们签回的签板； 2. 外箱印刷带条码的RFID箱唛：RFID紫色色带+WM Dept.图标+RFID图标+ITF-14条码，四面右下角印刷ZURU logo, ITFF条码只印刷在正唛一面，在加印的时候确保 条形码能扫描出来，外箱侧面任一角落加印："MADE IN CHINA" 字样； 3. 每个slip sheet上面贴一张艾利贴纸（不干胶贴纸）和一张普通贴纸（A4纸），slip sheet打印的普通贴纸的尺寸不能比艾利贴纸小，普通贴纸内容见附件； 4. 在产品上和包装上要有日期码、以及要有MADE IN CHINA和ZURU字样； 5. 产品如有扎带口要剪平，不能刮手。 6. 此单需要验货，请多备料 7. 此单以slip sheet出货，77485：1152pcs/96CTN/Slip Sheet | W24: Maggie Xie | X24: 2206.6131 | Y24: 4364.2672 | AA24: 94124-1.20 | AB24: 77485SLB-S004 | AC24: 已入 | AD24: 系统出单 | AF24: 1152 | AG24: =AF24-I24 -> 0 | AK24: =I24 -> 1152 | AM24: =I24 -> 1152 | AU24: =I24 -> 1152 | AZ24: =I24/12 -> 96 | BU24: =AK24+AL24 -> 1152 | BV24: =BV23+BU24 -> 2308690 | CA24: =SUM(BX$1:CB$1)-BV24 -> 511310 | CC24: =AW24+AX24+BE24+BF24 -> 0 | CD24: =CD23+CC24 -> 47832.571 | CH24: =$CF$1+$CG$1+$CH$1+$CI$1-CD24 -> 12167.429
A25: 45637 | B25: WAL-MART STORES INC. USA | C25: 美国 | D25: 4500153681 | E25: 0881410111 HOUSTON | F25: 4500153681-40 | G25: 77485SLB-S004 | H25: 3代迷你小手袋 | I25: 2304 | J25: 0 | K25: 1152 | L25: =I25/K25 -> 2 | M25: 45671 | N25: 45667 | O25: 2025/1/14第三方验货 | P25: PASS | R25: 外箱印刷带条码的RFID箱唛：RFID紫色色带+WM Dept.图标+RFID图标+ITF-14条码，四面右下角印刷ZURU logo, ITFF条码只印刷在正唛一面，在加印的时候确保 条形码能扫描出来，外箱侧面任一角落加印："MADE IN CHINA" 字样； | S25: 无 | T25: 12/20 寄出RFID贴纸 | V25: 日期码格式：ZURU DGYYYYMMDD CHINA(日期避开周末和法定节假日即可） 日期：按实际生产日期 Packaging Info: 77485SLB-S004 1.包装要求： MA 1L收缩膜+ 客版 收藏指南B版+MA 纸袋+客版 1L PDQ，翻单：4500128976 每pcs产品上要贴1张RFID贴纸，贴纸由ZURU提供，贴纸位置请严格按照我们签回的签板； Remark: 77485SLB-S004 1.包装要求： MA 1L收缩膜+ 客版 收藏指南B版+MA 纸袋+客版 1L PDQ，翻单：4500128976 每pcs产品上要贴1张RFID贴纸，贴纸由ZURU提供，贴纸位置请严格按照我们签回的签板； 2. 外箱印刷带条码的RFID箱唛：RFID紫色色带+WM Dept.图标+RFID图标+ITF-14条码，四面右下角印刷ZURU logo, ITFF条码只印刷在正唛一面，在加印的时候确保 条形码能扫描出来，外箱侧面任一角落加印："MADE IN CHINA" 字样； 3. 每个slip sheet上面贴一张艾利贴纸（不干胶贴纸）和一张普通贴纸（A4纸），slip sheet打印的普通贴纸的尺寸不能比艾利贴纸小，普通贴纸内容见附件； 4. 在产品上和包装上要有日期码、以及要有MADE IN CHINA和ZURU字样； 5. 产品如有扎带口要剪平，不能刮手。 6. 此单需要验货，请多备料 7. 此单以slip sheet出货，77485：1152pcs/96CTN/Slip Sheet | W25: Maggie Xie | X25: 2206.6131 | Y25: 4364.2672 | AA25: 94124-1.20 | AB25: 77485SLB-S004 | AC25: 已入 | AD25: 系统出单 | AF25: 2304 | AG25: =AF25-I25 -> 0 | AK25: =I25 -> 2304 | AM25: =I25 -> 2304 | AU25: =I25 -> 2304 | AZ25: =I25/12 -> 192 | BU25: =AK25+AL25 -> 2304 | BV25: =BV24+BU25 -> 2310994 | CA25: =SUM(BX$1:CB$1)-BV25 -> 509006 | CC25: =AW25+AX25+BE25+BF25 -> 0 | CD25: =CD24+CC25 -> 47832.571 | CH25: =$CF$1+$CG$1+$CH$1+$CI$1-CD25 -> 12167.429
A26: 45637 | B26: WAL-MART STORES INC. USA | C26: 美国 | D26: 4500153681 | E26: 0881410114 SUFFOLK | F26: 4500153681-50 | G26: 77485SLB-S004 | H26: 3代迷你小手袋 | I26: 2304 | J26: 0 | K26: 1152 | L26: =I26/K26 -> 2 | M26: 45671 | N26: 45667 | O26: 2025/1/14第三方验货 | P26: PASS | R26: 外箱印刷带条码的RFID箱唛：RFID紫色色带+WM Dept.图标+RFID图标+ITF-14条码，四面右下角印刷ZURU logo, ITFF条码只印刷在正唛一面，在加印的时候确保 条形码能扫描出来，外箱侧面任一角落加印："MADE IN CHINA" 字样； | S26: 无 | T26: 12/20 寄出RFID贴纸 | V26: 日期码格式：ZURU DGYYYYMMDD CHINA(日期避开周末和法定节假日即可） 日期：按实际生产日期 Packaging Info: 77485SLB-S004 1.包装要求： MA 1L收缩膜+ 客版 收藏指南B版+MA 纸袋+客版 1L PDQ，翻单：4500128976 每pcs产品上要贴1张RFID贴纸，贴纸由ZURU提供，贴纸位置请严格按照我们签回的签板； Remark: 77485SLB-S004 1.包装要求： MA 1L收缩膜+ 客版 收藏指南B版+MA 纸袋+客版 1L PDQ，翻单：4500128976 每pcs产品上要贴1张RFID贴纸，贴纸由ZURU提供，贴纸位置请严格按照我们签回的签板； 2. 外箱印刷带条码的RFID箱唛：RFID紫色色带+WM Dept.图标+RFID图标+ITF-14条码，四面右下角印刷ZURU logo, ITFF条码只印刷在正唛一面，在加印的时候确保 条形码能扫描出来，外箱侧面任一角落加印："MADE IN CHINA" 字样； 3. 每个slip sheet上面贴一张艾利贴纸（不干胶贴纸）和一张普通贴纸（A4纸），slip sheet打印的普通贴纸的尺寸不能比艾利贴纸小，普通贴纸内容见附件； 4. 在产品上和包装上要有日期码、以及要有MADE IN CHINA和ZURU字样； 5. 产品如有扎带口要剪平，不能刮手。 6. 此单需要验货，请多备料 7. 此单以slip sheet出货，77485：1152pcs/96CTN/Slip Sheet | W26: Maggie Xie | X26: 2206.6131 | Y26: 4364.2672 | AA26: 94124-1.20 | AB26: 77485SLB-S004 | AC26: 已入 | AD26: 系统出单 | AG26: =AF26-I26 -> -2304 | AK26: =I26 -> 2304 | AM26: =I26 -> 2304 | AU26: =I26 -> 2304 | AZ26: =I26/12 -> 192 | BU26: =AK26+AL26 -> 2304 | BV26: =BV25+BU26 -> 2313298 | CA26: =SUM(BX$1:CB$1)-BV26 -> 506702 | CC26: =AW26+AX26+BE26+BF26 -> 0 | CD26: =CD25+CC26 -> 47832.571 | CH26: =$CF$1+$CG$1+$CH$1+$CI$1-CD26 -> 12167.429
A27: 45637 | B27: WAL-MART STORES INC. USA | C27: 美国 | D27: 4500153681 | E27: 0881410121 MOBILE | F27: 4500153681-60 | G27: 77485SLB-S004 | H27: 3代迷你小手袋 | I27: 3456 | J27: 0 | K27: 1152 | L27: =I27/K27 -> 3 | M27: 45671 | N27: 45667 | O27: 2025/1/14第三方验货 | P27: PASS | R27: 外箱印刷带条码的RFID箱唛：RFID紫色色带+WM Dept.图标+RFID图标+ITF-14条码，四面右下角印刷ZURU logo, ITFF条码只印刷在正唛一面，在加印的时候确保 条形码能扫描出来，外箱侧面任一角落加印："MADE IN CHINA" 字样； | S27: 无 | T27: 12/20 寄出RFID贴纸 | V27: 日期码格式：ZURU DGYYYYMMDD CHINA(日期避开周末和法定节假日即可） 日期：按实际生产日期 Packaging Info: 77485SLB-S004 1.包装要求： MA 1L收缩膜+ 客版 收藏指南B版+MA 纸袋+客版 1L PDQ，翻单：4500128976 每pcs产品上要贴1张RFID贴纸，贴纸由ZURU提供，贴纸位置请严格按照我们签回的签板； Remark: 77485SLB-S004 1.包装要求： MA 1L收缩膜+ 客版 收藏指南B版+MA 纸袋+客版 1L PDQ，翻单：4500128976 每pcs产品上要贴1张RFID贴纸，贴纸由ZURU提供，贴纸位置请严格按照我们签回的签板； 2. 外箱印刷带条码的RFID箱唛：RFID紫色色带+WM Dept.图标+RFID图标+ITF-14条码，四面右下角印刷ZURU logo, ITFF条码只印刷在正唛一面，在加印的时候确保 条形码能扫描出来，外箱侧面任一角落加印："MADE IN CHINA" 字样； 3. 每个slip sheet上面贴一张艾利贴纸（不干胶贴纸）和一张普通贴纸（A4纸），slip sheet打印的普通贴纸的尺寸不能比艾利贴纸小，普通贴纸内容见附件； 4. 在产品上和包装上要有日期码、以及要有MADE IN CHINA和ZURU字样； 5. 产品如有扎带口要剪平，不能刮手。 6. 此单需要验货，请多备料 7. 此单以slip sheet出货，77485：1152pcs/96CTN/Slip Sheet | W27: Maggie Xie | X27: 2206.6131 | Y27: 4364.2672 | AA27: 94084-1.17 | AB27: 77485SLB-S004 | AC27: 已入 | AD27: 系统出单 | AF27: 3456 | AG27: =AF27-I27 -> 0 | AK27: =I27 -> 3456 | AM27: =I27 -> 3456 | AU27: =I27 -> 3456 | AZ27: =I27/12 -> 288 | BU27: =AK27+AL27 -> 3456 | BV27: =BV26+BU27 -> 2316754 | CA27: =SUM(BX$1:CB$1)-BV27 -> 503246 | CC27: =AW27+AX27+BE27+BF27 -> 0 | CD27: =CD26+CC27 -> 47832.571 | CH27: =$CF$1+$CG$1+$CH$1+$CI$1-CD27 -> 12167.429
A28: 45637 | B28: WAL-MART STORES INC. USA | C28: 美国 | D28: 4500153681 | E28: 0881410134 RIDGEVILLE SC | F28: 4500153681-70 | G28: 77485SLB-S004 | H28: 3代迷你小手袋 | I28: 1152 | J28: 0 | K28: 1152 | L28: =I28/K28 -> 1 | M28: 45671 | N28: 45667 | P28: PASS | R28: 外箱印刷带条码的RFID箱唛：RFID紫色色带+WM Dept.图标+RFID图标+ITF-14条码，四面右下角印刷ZURU logo, ITFF条码只印刷在正唛一面，在加印的时候确保 条形码能扫描出来，外箱侧面任一角落加印："MADE IN CHINA" 字样； | S28: 无 | T28: 12/20 寄出RFID贴纸 | V28: 日期码格式：ZURU DGYYYYMMDD CHINA(日期避开周末和法定节假日即可） 日期：按实际生产日期 Packaging Info: 77485SLB-S004 1.包装要求： MA 1L收缩膜+ 客版 收藏指南B版+MA 纸袋+客版 1L PDQ，翻单：4500128976 每pcs产品上要贴1张RFID贴纸，贴纸由ZURU提供，贴纸位置请严格按照我们签回的签板； Remark: 77485SLB-S004 1.包装要求： MA 1L收缩膜+ 客版 收藏指南B版+MA 纸袋+客版 1L PDQ，翻单：4500128976 每pcs产品上要贴1张RFID贴纸，贴纸由ZURU提供，贴纸位置请严格按照我们签回的签板； 2. 外箱印刷带条码的RFID箱唛：RFID紫色色带+WM Dept.图标+RFID图标+ITF-14条码，四面右下角印刷ZURU logo, ITFF条码只印刷在正唛一面，在加印的时候确保 条形码能扫描出来，外箱侧面任一角落加印："MADE IN CHINA" 字样； 3. 每个slip sheet上面贴一张艾利贴纸（不干胶贴纸）和一张普通贴纸（A4纸），slip sheet打印的普通贴纸的尺寸不能比艾利贴纸小，普通贴纸内容见附件； 4. 在产品上和包装上要有日期码、以及要有MADE IN CHINA和ZURU字样； 5. 产品如有扎带口要剪平，不能刮手。 6. 此单需要验货，请多备料 7. 此单以slip sheet出货，77485：1152pcs/96CTN/Slip Sheet | W28: Maggie Xie | X28: 2206.6131 | Y28: 4364.2672 | AA28: 94124-1.20 | AB28: 77485SLB-S004 | AC28: 已入 | AD28: 系统出单 | AF28: 1152 | AG28: =AF28-I28 -> 0 | AK28: =I28 -> 1152 | AM28: =I28 -> 1152 | AU28: =I28 -> 1152 | AZ28: =I28/12 -> 96 | BU28: =AK28+AL28 -> 1152 | BV28: =BV27+BU28 -> 2317906 | CA28: =SUM(BX$1:CB$1)-BV28 -> 502094 | CC28: =AW28+AX28+BE28+BF28 -> 0 | CD28: =CD27+CC28 -> 47832.571 | CH28: =$CF$1+$CG$1+$CH$1+$CI$1-CD28 -> 12167.429
A29: 45586 | B29: TJX COMPANIES, INC | C29: 美国 | D29: 4500147801 | E29: TJ MAXX DC#891-120PCS , DC#894-96PCS, DC#896-96PCS, DC#897-192PCS , DC#898-96PCS | F29: 4500147801-40 | G29: 77486-S001 | H29: 3代迷你小手袋 圆筒装 | I29: 600 | J29: 0 | K29: 12 | L29: =I29/K29 -> 50 | M29: 45677 | N29: 45673 | P29: PASS | R29: 45600 | S29: 无 | T29: 欠客供价格贴纸+空白贴纸 | V29: 日期码格式：ZURU INC(BVI) 标准格式 日期：按实际生产日期 Packaging Info: MA UPC包装+价格贴纸，价格贴纸客供。#77486 球的收缩膜用无条码版本或者加空白贴纸覆盖条码信息。 Remark: 1. 产品和包装上印刷tracking code信息，格式为ZURU常规格式。 2. 分5个DC出货，每款产品每个DC的箱唛资料不同。具体分DC数量，请参考后面行项目备注。 3. ZURU QC验货。 | W29: Emily Wu | X29: 4.1259 | Y29: =I29*X29 -> 2475.54 | AA29: 94280-2.18 | AB29: 77486-S001 | AC29: 已入 | AD29: 系统出单 | AF29: 600 | AG29: =AF29-I29 -> 0 | AI29: OK | AK29: =I29*2 -> 1200 | AM29: =I29*2 -> 1200 | AS29: =I29*2 -> 1200 | BN29: =I29 -> 600 | BO29: =I29 -> 600 | BQ29: =I29 -> 600 | BU29: =AK29+AL29 -> 1200 | BV29: =BV28+BU29 -> 2319106 | CA29: =SUM(BX$1:CB$1)-BV29 -> 500894 | CC29: =AW29+AX29+BE29+BF29 -> 0 | CD29: =CD28+CC29 -> 47832.571 | CH29: =$CF$1+$CG$1+$CH$1+$CI$1-CD29 -> 12167.429
A30: 45586 | B30: TJX COMPANIES, INC | C30: 美国 | D30: 4500147799 | E30: Marshalls DC#881-120PCS , DC#884-96PCS, DC#886-132PCS , DC#887-120PCS , DC#888-132PCS | F30: 4500147799-40 | G30: 77486-S001 | H30: 3代迷你小手袋 圆筒装 | I30: 600 | J30: 0 | K30: 12 | L30: =I30/K30 -> 50 | M30: 45677 | N30: 45673 | P30: PASS | R30: 45600 | S30: 无 | T30: 欠客供价格贴纸+空白贴纸 | V30: 日期码格式：ZURU INC(BVI) 标准格式 日期：按实际生产日期 Packaging Info: MA UPC包装+价格贴纸，价格贴纸客供。#77486 球的收缩膜用无条码版本或者加空白贴纸覆盖条码信息。 Remark: 1. 产品和包装上印刷tracking code信息，格式为ZURU常规格式。 2. 分5个DC出货，每款产品每个DC的箱唛资料不同。具体分DC数量，请参考后面行项目备注。 3. ZURU QC验货。 | W30: Emily Wu | X30: 4.087 | Y30: =I30*X30 -> 2452.2 | AA30: 94278-2.18 | AB30: 77486-S001 | AC30: 已入 | AD30: 系统出单 | AG30: =AF30-I30 -> -600 | AI30: OK | AK30: =I30*2 -> 1200 | AM30: =I30*2 -> 1200 | AS30: =I30*2 -> 1200 | BN30: =I30 -> 600 | BO30: =I30 -> 600 | BQ30: =I30 -> 600 | BU30: =AK30+AL30 -> 1200 | BV30: =BV29+BU30 -> 2320306 | CA30: =SUM(BX$1:CB$1)-BV30 -> 499694 | CC30: =AW30+AX30+BE30+BF30 -> 0 | CD30: =CD29+CC30 -> 47832.571 | CH30: =$CF$1+$CG$1+$CH$1+$CI$1-CD30 -> 12167.429
A31: 45603 | B31: ROSS PROCUREMENT.INC | C31: 美国 | D31: 4500150464 | E31: 60190494 | F31: 4500150464-30 | G31: 77486-S001 | H31: 3代迷你小手袋 圆筒装 | I31: 2400 | J31: 0 | K31: 12 | L31: =I31/K31 -> 200 | M31: 45672 | N31: 45668 | P31: pass | R31: 45610 | S31: 无 | T31: 欠客供价格贴纸 | V31: 日期码格式：ZURU INC(BVI) 标准格式 日期：按实际生产日期 Packaging Info: 1.ZURU MA UPC 收缩膜+客版铜版纸+PVC桶 + 客供价格贴纸，出口美国 , 优先使用MA 1L 最新版本 。 Remark: 1.ZURU MA UPC 收缩膜+客版铜版纸+PVC桶 + 客供价格贴纸，出口美国 , 优先使用MA 1L 最新版本 。 2.价格贴纸位于包装正面右下角，不挡住重要信息即可，可适当调整 ，价格贴纸由跟单提供。 3.标准日期码格式，产品和包装必须有日期码 。 4.同个产品同个货期不可出现不同的包装。 5. PVC 桶中球不能出现完全相同的ASSORTMENT ， 即同一个PVC 中球里的ASSORTMENT 需要不同。 以免消费者失望。 6.PVC 桶上加上 MINI BRANDS 的LOGO 贴纸 （ ZURU 统一要求的） 7.收缩膜可使用标版带UPC条码MA，无需白色贴纸覆盖。 | W31: Sophia Zhou | X31: 4.1142 | Y31: =I31*X31 -> 9874.08 | AA31: 94486-3.7 | AB31: 77486-S001 | AC31: 已入 | AD31: 系统出单 | AF31: =2388+12 -> 2400 | AG31: =AF31-I31 -> 0 | AI31: OK | AK31: =I31*2 -> 4800 | AM31: =I31*2 -> 4800 | AS31: =I31*2 -> 4800 | BN31: =I31 -> 2400 | BO31: =I31 -> 2400 | BQ31: =I31 -> 2400 | BU31: =AK31+AL31 -> 4800 | BV31: =BV30+BU31 -> 2325106 | CA31: =SUM(BX$1:CB$1)-BV31 -> 494894 | CC31: =AW31+AX31+BE31+BF31 -> 0 | CD31: =CD30+CC31 -> 47832.571 | CH31: =$CF$1+$CG$1+$CH$1+$CI$1-CD31 -> 12167.429
A32: 45632 | B32: Cladellas 2000 S.L | C32: 西班牙 | D32: 4500153372 | F32: 4500153372-60 | G32: 77485GQ7-S001 | H32: 3代迷你小手袋 | I32: 1000 | J32: 0 | K32: 50 | L32: =I32/K32 -> 20 | M32: 45672 | N32: 45668 | P32: pass | Q32: 1/15 出货 | R32: 45638 | S32: 无 | T32: 45638 | V32: 日期码格式：ZURU INC(BVI) 标准格式 日期：按实际生产日期 Packaging Info: 6.77485GQ7：最新MA 3L EAN 版本包装+一张客户警语贴纸（含环保标）+MA 5L 收藏指南+MA 3L PDQ； Remark: 产品均符合EU微塑料法规要求：不含有微塑料，不含有闪粉； 此单需要在年前出货，请注意安排装柜人员； | W32: Sherry Chen | X32: 2.0019 | Y32: =I32*X32 -> 2001.9 | AA32: 94203-2.10 | AB32: 77485GQ7-S001-3L-1 | AC32: 已入 | AD32: 系统出单 | AF32: 1000 | AG32: =AF32-I32 -> 0 | AI32: OK | AK32: =I32 -> 1000 | AP32: =I32 -> 1000 | AS32: =I32 -> 1000 | BF32: =I32/25 -> 40 | BU32: =AK32+AL32 -> 1000 | BV32: =BV31+BU32 -> 2326106 | CA32: =SUM(BX$1:CB$1)-BV32 -> 493894 | CC32: =AW32+AX32+BE32+BF32 -> 40 | CD32: =CD31+CC32 -> 47872.571 | CH32: =$CF$1+$CG$1+$CH$1+$CI$1-CD32 -> 12127.429
A33: 45632 | B33: MILLS FLEET FARM | C33: 美国 | D33: MPO03108 | G33: 77485-S001 | H33: 3代迷你小手袋 | I33: 640 | J33: 0 | K33: 24 | L33: =I33/K33 -> 26.666667 | M33: 45674 | N33: 45670 | P33: pass | Q33: 子件于2025年1月21日送到库有混装 | R33: 周转箱 | S33: 无 | T33: 无 | V33: Remark:1.包装:ZURU MA 1L UPC最新包装;出口美国2.日期跟踪码:产品外包装及产品本身都必须有日期跟踪码，并且确保两者的日期跟踪码要一致;2URU标准格式日期码(请自行调整具体年月日生产期,但不能为周末)该单是多工厂混装，为了统一，日期可以统一打2025年1月16日 3.按照Zuru MA 标板配比 4.子件于2025年1月21日送到库有混装,产品包菠上需做好标识,以便组装厂识别组装时避免重复字,送货到库有厂时送货单请备注上:客供子件给Mils Fleet Farm p4500153457 #MSLD121-S001混装用。 | W33: Mila Yao | X33: 1.8342 | Y33: =X33*I33 -> 1173.888 | AA33: 94409-2.28 | AB33: 77485-S001 | AC33: 已入 | AD33: 系统出单 | AF33: 640 | AG33: =AF33-I33 -> 0 | AI33: 无 | AK33: =I33 -> 640 | AM33: =I33 -> 640 | AS33: =I33 -> 640 | BU33: =AK33+AL33 -> 640 | BV33: =BV32+BU33 -> 2326746 | CA33: =SUM(BX$1:CB$1)-BV33 -> 493254 | CC33: =AW33+AX33+BE33+BF33 -> 0 | CD33: =CD32+CC33 -> 47872.571 | CH33: =$CF$1+$CG$1+$CH$1+$CI$1-CD33 -> 12127.429
A34: 45639 | B34: CORPORACION FAVORITA C.A. | C34: 厄瓜多尔 | D34: 4500153836 | E34: 24-1067174JEC | F34: 4500153836-20 | G34: 77485GQ7-S001 | H34: 3代迷你小手袋 | I34: 4600 | J34: 0 | K34: 50 | L34: =I34/K34 -> 92 | M34: 45677 | N34: 45673 | P34: pass | R34: 45639 | S34: 无 | T34: 45643 | V34: 日期码格式：LOTE 格式：例如2025-01 日期： Packaging Info: 77485GQ7：MA 5L 收藏指南+MA 3L 包装+UPC 贴纸+MA 3L PDQ 包装+进口商贴纸+箱唛 Remark: 客户有LOTE 格式：例如2025-01. ，外箱箱唛，产品批号需要与进口商贴纸保持一致。 | W34: Zoe Luo | X34: 1.9961 | Y34: =I34*X34 -> 9182.06 | AA34: 94144-1.21 | AB34: 77485GQ7-S001-3L-1 | AC34: 已入 | AD34: 系统出单 | AF34: =2100+2500 -> 4600 | AG34: =AF34-I34 -> 0 | AI34: OK | AK34: =I34 -> 4600 | AP34: =I34 -> 4600 | AS34: =I34 -> 4600 | BF34: =I34/25 -> 184 | BU34: =AK34+AL34 -> 4600 | BV34: =BV33+BU34 -> 2331346 | CA34: =SUM(BX$1:CB$1)-BV34 -> 488654 | CC34: =AW34+AX34+BE34+BF34 -> 184 | CD34: =CD33+CC34 -> 48056.571 | CH34: =$CF$1+$CG$1+$CH$1+$CI$1-CD34 -> 11943.429
A35: 45639 | B35: CENTRO CUESTA NACIONAL | C35: 多米尼加共和国 | D35: 4500153864 | F35: 4500153864-80 | G35: 77485GQ7-S001 | H35: 3代迷你小手袋 | I35: 750 | J35: 0 | K35: 50 | L35: =I35/K35 -> 15 | M35: 45677 | N35: 45673 | P35: pass | R35: 45639 | S35: 无 | T35: 45644 | V35: 日期码格式：2025-01 日期： Packaging Info: 77485GQ7：MA 5L 收藏指南+MA 3L 包装+UPC 贴纸+MA 3L PDQ 包装+箱唛 Remark: | W35: Zoe Luo | X35: 2.0019 | Y35: =I35*X35 -> 1501.425 | AA35: 94113-1.18 | AB35: 77485GQ7-S001-3L-1 | AC35: 已入 | AD35: 系统出单 | AF35: 750 | AG35: =AF35-I35 -> 0 | AI35: OK | AK35: =I35 -> 750 | AP35: =I35 -> 750 | AS35: =I35 -> 750 | BF35: =I35/25 -> 30 | BU35: =AK35+AL35 -> 750 | BV35: =BV34+BU35 -> 2332096 | CA35: =SUM(BX$1:CB$1)-BV35 -> 487904 | CC35: =AW35+AX35+BE35+BF35 -> 30 | CD35: =CD34+CC35 -> 48086.571 | CH35: =$CF$1+$CG$1+$CH$1+$CI$1-CD35 -> 11913.429
A36: 45624 | B36: WALGREEN CO. | C36: 美国 | D36: 4500152749 | E36: 4550103326 | F36: 4500152749-10 | G36: 77485GQ4-S002 | H36: 3代迷你小手袋 | I36: 2226 | J36: 0 | K36: 6 | L36: =I36/K36 -> 371 | M36: 45695 | N36: 45691 | P36: pass | R36: 45624 | S36: 无 | T36: WIC贴纸（WIC#744431） | V36: 日期码格式：ZURU INC(BVI) 标准格式:DG20250207 日期：02-07-2025 Tracking Code: Packaging Info: Remark: 客版1L PDQ +MA 1L包装 + WIC贴纸（WIC#744431）+ MA 收藏指南 + PDQ折页 （同PO 4500142744） 产品和包装上面要有ZURU 标准格式TRACKING CODE， DG20250207 | W36: Cara Li | X36: 1.9361 | Y36: =I36*X36 -> 4309.7586 | AA36: 94189-2.8 | AB36: 待定 | AC36: 已入 | AD36: 系统出单 | AF36: 2226 | AG36: =AF36-I36 -> 0 | AI36: OK | AK36: =I36 -> 2226 | AM36: =I36 -> 2226 | AS36: =I36 -> 2226 | BB36: =I36/6 -> 371 | BU36: =AK36+AL36 -> 2226 | BV36: =BV35+BU36 -> 2334322 | CA36: =SUM(BX$1:CB$1)-BV36 -> 485678 | CC36: =AW36+AX36+BE36+BF36 -> 0 | CD36: =CD35+CC36 -> 48086.571 | CH36: =$CF$1+$CG$1+$CH$1+$CI$1-CD36 -> 11913.429
A37: 45624 | B37: WALGREEN CO. | C37: 美国 | D37: 4500152749 | E37: 4550102988 | F37: 4500152749-20 | G37: 77485GQ4-S002 | H37: 3代迷你小手袋 | I37: 708 | J37: 0 | K37: 6 | L37: =I37/K37 -> 118 | M37: 45695 | N37: 45691 | P37: pass | R37: 45624 | S37: 无 | T37: WIC贴纸（WIC#744431） | V37: 日期码格式：ZURU INC(BVI) 标准格式:DG20250207 日期：02-07-2025 Tracking Code: Packaging Info: Remark: 客版1L PDQ +MA 1L包装 + WIC贴纸（WIC#744431）+ MA 收藏指南 + PDQ折页 （同PO 4500142744） 产品和包装上面要有ZURU 标准格式TRACKING CODE， DG20250207 | W37: Cara Li | X37: 1.9361 | Y37: =I37*X37 -> 1370.7588 | AA37: 94189-2.8 | AB37: 待定 | AC37: 已入 | AD37: 系统出单 | AF37: 708 | AG37: =AF37-I37 -> 0 | AK37: =I37 -> 708 | AM37: =I37 -> 708 | AS37: =I37 -> 708 | BB37: =I37/6 -> 118 | BU37: =AK37+AL37 -> 708 | BV37: =BV36+BU37 -> 2335030 | CA37: =SUM(BX$1:CB$1)-BV37 -> 484970 | CC37: =AW37+AX37+BE37+BF37 -> 0 | CD37: =CD36+CC37 -> 48086.571 | CH37: =$CF$1+$CG$1+$CH$1+$CI$1-CD37 -> 11913.429
A38: 45624 | B38: WALGREEN CO. | C38: 美国 | D38: 4500152749 | E38: 4550103356 | F38: 4500152749-30 | G38: 77485GQ4-S002 | H38: 3代迷你小手袋 | I38: 942 | J38: 0 | K38: 6 | L38: =I38/K38 -> 157 | M38: 45695 | N38: 45691 | P38: pass | R38: 45624 | S38: 无 | T38: WIC贴纸（WIC#744431） | V38: 日期码格式：ZURU INC(BVI) 标准格式:DG20250207 日期：02-07-2025 Tracking Code: Packaging Info: Remark: 客版1L PDQ +MA 1L包装 + WIC贴纸（WIC#744431）+ MA 收藏指南 + PDQ折页 （同PO 4500142744） 产品和包装上面要有ZURU 标准格式TRACKING CODE， DG20250207 | W38: Cara Li | X38: 1.9361 | Y38: =I38*X38 -> 1823.8062 | AA38: 94189-2.8 | AB38: 待定 | AC38: 已入 | AD38: 系统出单 | AF38: 942 | AG38: =AF38-I38 -> 0 | AK38: =I38 -> 942 | AM38: =I38 -> 942 | AS38: =I38 -> 942 | BB38: =I38/6 -> 157 | BU38: =AK38+AL38 -> 942 | BV38: =BV37+BU38 -> 2335972 | CA38: =SUM(BX$1:CB$1)-BV38 -> 484028 | CC38: =AW38+AX38+BE38+BF38 -> 0 | CD38: =CD37+CC38 -> 48086.571 | CH38: =$CF$1+$CG$1+$CH$1+$CI$1-CD38 -> 11913.429
A39: 45624 | B39: WALGREEN CO. | C39: 美国 | D39: 4500152749 | E39: 4550102986 | F39: 4500152749-40 | G39: 77485GQ4-S002 | H39: 3代迷你小手袋 | I39: 1416 | J39: 0 | K39: 6 | L39: =I39/K39 -> 236 | M39: 45695 | N39: 45691 | P39: pass | R39: 45624 | S39: 无 | T39: WIC贴纸（WIC#744431） | V39: 日期码格式：ZURU INC(BVI) 标准格式:DG20250207 日期：02-07-2025 Tracking Code: Packaging Info: Remark: 客版1L PDQ +MA 1L包装 + WIC贴纸（WIC#744431）+ MA 收藏指南 + PDQ折页 （同PO 4500142744） 产品和包装上面要有ZURU 标准格式TRACKING CODE， DG20250207 | W39: Cara Li | X39: 1.9361 | Y39: =I39*X39 -> 2741.5176 | AA39: 94189-2.8 | AB39: 待定 | AC39: 已入 | AD39: 系统出单 | AF39: 1416 | AG39: =AF39-I39 -> 0 | AK39: =I39 -> 1416 | AM39: =I39 -> 1416 | AS39: =I39 -> 1416 | BB39: =I39/6 -> 236 | BU39: =AK39+AL39 -> 1416 | BV39: =BV38+BU39 -> 2337388 | CA39: =SUM(BX$1:CB$1)-BV39 -> 482612 | CC39: =AW39+AX39+BE39+BF39 -> 0 | CD39: =CD38+CC39 -> 48086.571 | CH39: =$CF$1+$CG$1+$CH$1+$CI$1-CD39 -> 11913.429
A40: 45624 | B40: WALGREEN CO. | C40: 美国 | D40: 4500152749 | E40: 4550103369 | F40: 4500152749-50 | G40: 77485GQ4-S002 | H40: 3代迷你小手袋 | I40: 2010 | J40: 0 | K40: 6 | L40: =I40/K40 -> 335 | M40: 45695 | N40: 45691 | P40: pass | R40: 45624 | S40: 无 | T40: WIC贴纸（WIC#744431） | V40: 日期码格式：ZURU INC(BVI) 标准格式:DG20250207 日期：02-07-2025 Tracking Code: Packaging Info: Remark: 客版1L PDQ +MA 1L包装 + WIC贴纸（WIC#744431）+ MA 收藏指南 + PDQ折页 （同PO 4500142744） 产品和包装上面要有ZURU 标准格式TRACKING CODE， DG20250207 | W40: Cara Li | X40: 1.9361 | Y40: =I40*X40 -> 3891.561 | AA40: 94189-2.8 | AB40: 待定 | AC40: 已入 | AD40: 系统出单 | AF40: 2010 | AG40: =AF40-I40 -> 0 | AK40: =I40 -> 2010 | AM40: =I40 -> 2010 | AS40: =I40 -> 2010 | BB40: =I40/6 -> 335 | BU40: =AK40+AL40 -> 2010 | BV40: =BV39+BU40 -> 2339398 | CA40: =SUM(BX$1:CB$1)-BV40 -> 480602 | CC40: =AW40+AX40+BE40+BF40 -> 0 | CD40: =CD39+CC40 -> 48086.571 | CH40: =$CF$1+$CG$1+$CH$1+$CI$1-CD40 -> 11913.429
A41: 45624 | B41: WALGREEN CO. | C41: 美国 | D41: 4500152749 | E41: 4550103370 | F41: 4500152749-60 | G41: 77485GQ4-S002 | H41: 3代迷你小手袋 | I41: 768 | J41: 0 | K41: 6 | L41: =I41/K41 -> 128 | M41: 45695 | N41: 45691 | P41: pass | R41: 45624 | S41: 无 | T41: WIC贴纸（WIC#744431） | V41: 日期码格式：ZURU INC(BVI) 标准格式:DG20250207 日期：02-07-2025 Tracking Code: Packaging Info: Remark: 客版1L PDQ +MA 1L包装 + WIC贴纸（WIC#744431）+ MA 收藏指南 + PDQ折页 （同PO 4500142744） 产品和包装上面要有ZURU 标准格式TRACKING CODE， DG20250207 | W41: Cara Li | X41: 1.9361 | Y41: =I41*X41 -> 1486.9248 | AA41: 94189-2.8 | AB41: 待定 | AC41: 已入 | AD41: 系统出单 | AF41: 768 | AG41: =AF41-I41 -> 0 | AK41: =I41 -> 768 | AM41: =I41 -> 768 | AS41: =I41 -> 768 | BB41: =I41/6 -> 128 | BU41: =AK41+AL41 -> 768 | BV41: =BV40+BU41 -> 2340166 | CA41: =SUM(BX$1:CB$1)-BV41 -> 479834 | CC41: =AW41+AX41+BE41+BF41 -> 0 | CD41: =CD40+CC41 -> 48086.571 | CH41: =$CF$1+$CG$1+$CH$1+$CI$1-CD41 -> 11913.429
A42: 45624 | B42: WALGREEN CO. | C42: 美国 | D42: 4500152749 | E42: 4550103376 | F42: 4500152749-70 | G42: 77485GQ4-S002 | H42: 3代迷你小手袋 | I42: 1266 | J42: 0 | K42: 6 | L42: =I42/K42 -> 211 | M42: 45695 | N42: 45691 | P42: pass | R42: 45624 | S42: 无 | T42: WIC贴纸（WIC#744431） | V42: 日期码格式：ZURU INC(BVI) 标准格式:DG20250207 日期：02-07-2025 Tracking Code: Packaging Info: Remark: 客版1L PDQ +MA 1L包装 + WIC贴纸（WIC#744431）+ MA 收藏指南 + PDQ折页 （同PO 4500142744） 产品和包装上面要有ZURU 标准格式TRACKING CODE， DG20250207 | W42: Cara Li | X42: 1.9361 | Y42: =I42*X42 -> 2451.1026 | AA42: 94189-2.8 | AB42: 待定 | AC42: 已入 | AD42: 系统出单 | AF42: 1266 | AG42: =AF42-I42 -> 0 | AK42: =I42 -> 1266 | AM42: =I42 -> 1266 | AS42: =I42 -> 1266 | BB42: =I42/6 -> 211 | BU42: =AK42+AL42 -> 1266 | BV42: =BV41+BU42 -> 2341432 | CA42: =SUM(BX$1:CB$1)-BV42 -> 478568 | CC42: =AW42+AX42+BE42+BF42 -> 0 | CD42: =CD41+CC42 -> 48086.571 | CH42: =$CF$1+$CG$1+$CH$1+$CI$1-CD42 -> 11913.429
A43: 45623 | B43: THE ENTERTAINER | C43: 英国 | D43: 4500152538 | E43: 4500152538-2: FB12127 | F43: 4500152538-60 | G43: 77485GQ6-S001 | H43: 3代迷你小手袋 | I43: 2600 | J43: 0 | K43: 52 | L43: =I43/K43 -> 50 | M43: 45696 | N43: 45692 | P43: pass | R43: 45624 | S43: 无 | T43: 条码贴翻订单4500148687 | V43: 日期码格式：ZURU INC(BVI) 标准格式 日期：按实际生产日期 Packaging Info: 77485GQ6：MA最新1L配套包装+客户EAN条码贴一张覆盖ZURU 原条码，条码贴翻订单4500148687。 Remark: *MA版本按工厂现有最新库存即可，订单出英国，请注意检查产品及包装应带UKCA图标，包装显示ZURU UK LTD信息，QC同事请查核，如有问题与跟单确认。 *生产日期按实际（法定工作日），按ZURU标准格式即可 ，但是请知悉包装日期码需要早于或者等于外箱日期码 ，不能晚于外箱日期码 *请注意所有订单都需要经过ZURU QC验货并且通过后方可出货 *条码以订单显示为准 ，请安排生产前先核对 ，有问题请提出。 *所有产品按符合欧洲标准走货，需要是不含微塑料版本 。 *涉及到硼的，如可选择情况下应使用低硼版本 （slime 类别低硼一般低于300ppm)，无选择的应与跟单复核再安排 。 | W43: Amy Ding | X43: 1.9026 | Y43: =I43*X43 -> 4946.76 | AA43: 94275-2.18 | AB43: 77485GQ6-S001 | AC43: 已入 | AD43: 系统出单 | AF43: 2600 | AG43: =AF43-I43 -> 0 | AI43: OK | AK43: =I43 -> 2600 | AM43: =I43 -> 2600 | AS43: =I43 -> 2600 | BC43: =I43/13 -> 200 | BU43: =AK43+AL43 -> 2600 | BV43: =BV42+BU43 -> 2344032 | CA43: =SUM(BX$1:CB$1)-BV43 -> 475968 | CC43: =AW43+AX43+BE43+BF43 -> 0 | CD43: =CD42+CC43 -> 48086.571 | CH43: =$CF$1+$CG$1+$CH$1+$CI$1-CD43 -> 11913.429
A44: 45623 | B44: THE ENTERTAINER | C44: 英国 | D44: 4500152538 | E44: 4500152538-3: FB12155 | F44: 4500152538-150 | G44: 77485GQ6-S001 | H44: 3代迷你小手袋 | I44: 1456 | J44: 0 | K44: 52 | L44: =I44/K44 -> 28 | M44: 45696 | N44: 45692 | P44: pass | R44: 45624 | S44: 无 | T44: 条码贴翻订单4500148687 | V44: 日期码格式：ZURU INC(BVI) 标准格式 日期：按实际生产日期 Packaging Info: 77485GQ6：MA最新1L配套包装+客户EAN条码贴一张覆盖ZURU 原条码，条码贴翻订单4500148687。 Remark: *MA版本按工厂现有最新库存即可，订单出英国，请注意检查产品及包装应带UKCA图标，包装显示ZURU UK LTD信息，QC同事请查核，如有问题与跟单确认。 *生产日期按实际（法定工作日），按ZURU标准格式即可 ，但是请知悉包装日期码需要早于或者等于外箱日期码 ，不能晚于外箱日期码 *请注意所有订单都需要经过ZURU QC验货并且通过后方可出货 *条码以订单显示为准 ，请安排生产前先核对 ，有问题请提出。 *所有产品按符合欧洲标准走货，需要是不含微塑料版本 。 *涉及到硼的，如可选择情况下应使用低硼版本 （slime 类别低硼一般低于300ppm)，无选择的应与跟单复核再安排 。 | W44: Amy Ding | X44: 1.9026 | Y44: =I44*X44 -> 2770.1856 | AA44: 94275-2.18 | AB44: 77485GQ6-S001 | AC44: 已入 | AD44: 系统出单 | AF44: 1456 | AG44: =AF44-I44 -> 0 | AK44: =I44 -> 1456 | AM44: =I44 -> 1456 | AS44: =I44 -> 1456 | BC44: =I44/13 -> 112 | BU44: =AK44+AL44 -> 1456 | BV44: =BV43+BU44 -> 2345488 | CA44: =SUM(BX$1:CB$1)-BV44 -> 474512 | CC44: =AW44+AX44+BE44+BF44 -> 0 | CD44: =CD43+CC44 -> 48086.571 | CH44: =$CF$1+$CG$1+$CH$1+$CI$1-CD44 -> 11913.429
A45: 45586 | B45: TJX COMPANIES, INC | C45: 美国 | D45: 4500147804 | E45: Marshalls DC#881-120PCS , DC#884-96PCS, DC#886-132PCS , DC#887-120PCS , DC#888-132PCS | F45: 4500147804-50 | G45: 77486-S001 | H45: 3代迷你小手袋 圆筒装 | I45: 600 | J45: 0 | K45: 12 | L45: =I45/K45 -> 50 | M45: 45698 | N45: 45694 | P45: pass | R45: 45600 | S45: 无 | T45: 欠客供价格贴纸+空白贴纸 | V45: 日期码格式：ZURU INC(BVI) 标准格式 日期：按实际生产日期 Packaging Info: MA UPC包装+价格贴纸，价格贴纸客供。#77486 球的收缩膜用无条码版本或者加空白贴纸覆盖条码信息。 Remark: 1. 产品和包装上印刷tracking code信息，格式为ZURU常规格式。 2. 分5个DC出货，每款产品每个DC的箱唛资料不同。具体分DC数量，请参考后面行项目备注。 3. ZURU QC验货。 | W45: Emily Wu | X45: 4.1259 | Y45: =I45*X45 -> 2475.54 | AA45: 94381-2.27 | AB45: 77486-S001 | AC45: 已入 | AD45: 系统出单 | AF45: 600 | AG45: =AF45-I45 -> 0 | AI45: OK | AK45: =I45*2 -> 1200 | AM45: =I45*2 -> 1200 | AS45: =I45*2 -> 1200 | BN45: =I45 -> 600 | BO45: =I45 -> 600 | BQ45: =I45 -> 600 | BU45: =AK45+AL45 -> 1200 | BV45: =BV44+BU45 -> 2346688 | CA45: =SUM(BX$1:CB$1)-BV45 -> 473312 | CC45: =AW45+AX45+BE45+BF45 -> 0 | CD45: =CD44+CC45 -> 48086.571 | CH45: =$CF$1+$CG$1+$CH$1+$CI$1-CD45 -> 11913.429
A46: 45586 | B46: TJX COMPANIES, INC | C46: 美国 | D46: 4500147806 | E46: TJ MAXX DC#891-120PCS , DC#894-96PCS, DC#896-96PCS, DC#897-192PCS , DC#898-96PCS | F46: 4500147806-50 | G46: 77486-S001 | H46: 3代迷你小手袋 圆筒装 | I46: 600 | J46: 0 | K46: 12 | L46: =I46/K46 -> 50 | M46: 45698 | N46: 45694 | P46: pass | R46: 45600 | S46: 无 | T46: 欠客供价格贴纸+空白贴纸 | V46: 日期码格式：ZURU INC(BVI) 标准格式 日期：按实际生产日期 Packaging Info: MA UPC包装+价格贴纸，价格贴纸客供。#77486 球的收缩膜用无条码版本或者加空白贴纸覆盖条码信息。 Remark: 1. 产品和包装上印刷tracking code信息，格式为ZURU常规格式。 2. 分5个DC出货，每款产品每个DC的箱唛资料不同。具体分DC数量，请参考后面行项目备注。 3. ZURU QC验货。 | W46: Emily Wu | X46: 4.1259 | Y46: =I46*X46 -> 2475.54 | AA46: 94380-2.27 | AB46: 77486-S001 | AC46: 已入 | AD46: 系统出单 | AG46: =AF46-I46 -> -600 | AK46: =I46*2 -> 1200 | AM46: =I46*2 -> 1200 | AS46: =I46*2 -> 1200 | BN46: =I46 -> 600 | BO46: =I46 -> 600 | BQ46: =I46 -> 600 | BU46: =AK46+AL46 -> 1200 | BV46: =BV45+BU46 -> 2347888 | CA46: =SUM(BX$1:CB$1)-BV46 -> 472112 | CC46: =AW46+AX46+BE46+BF46 -> 0 | CD46: =CD45+CC46 -> 48086.571 | CH46: =$CF$1+$CG$1+$CH$1+$CI$1-CD46 -> 11913.429
A47: 45644 | B47: TJX Australia Pty Limited | C47: 澳大利亚 | D47: 4500154316 | E47: CUS PO#885182 | F47: 4500154316-10 | G47: 77486-S001 | H47: 3代迷你小手袋 圆筒装 | I47: 336 | J47: 0 | K47: 12 | L47: =I47/K47 -> 28 | M47: 45698 | N47: 45694 | P47: pass | R47: 45655 | S47: 无 | T47: 欠客供价格贴纸+空白贴纸 | V47: 日期码格式：ZURU INC(BVI) 标准格式 日期：按实际生产日期 Packaging Info: 包装： 77486: 客版PVC桶_UPC版本+MA收缩膜和收藏指南（UPC条码用1张空白贴纸盖住）+箱唛+1张客供贴纸；（首选1L，无1L可用多L含英语） Ratio： Remark: 1.箱唛不可出现任何手写内容，重量与实际须一致且不可手写; 2.产品上贴客供价格贴纸，贴纸位置为产品正面右上角，不能遮住产品信息；请与跟单确认贴纸位置后再生产大货； 3.订单每行对应客人不同的PO，即同款item的价格贴纸都不相同，请注意收到贴纸后不要弄混!（CUS PO号请参考行项目Remark） 4. 此单去澳大利亚，请按相应澳新标准生产并满足当地法规要求; 5.ZURU QC验货。 6.产品和包装上要有tracking label信息：日期码格式为Zuru标准格式； | W47: Christine Liao | X47: 4.1259 | Y47: =I47*X47 -> 1386.3024 | AA47: 94276-2.18 | AB47: 77486-S001 | AC47: 已入 | AD47: 系统出单 | AF47: 336 | AG47: =AF47-I47 -> 0 | AK47: =I47*2 -> 672 | AM47: =I47 -> 336 | AS47: =I47*2 -> 672 | BN47: =I47 -> 336 | BO47: =I47 -> 336 | BQ47: =I47 -> 336 | BU47: =AK47+AL47 -> 672 | BV47: =BV46+BU47 -> 2348560 | CA47: =SUM(BX$1:CB$1)-BV47 -> 471440 | CC47: =AW47+AX47+BE47+BF47 -> 0 | CD47: =CD46+CC47 -> 48086.571 | CH47: =$CF$1+$CG$1+$CH$1+$CI$1-CD47 -> 11913.429
A48: 45644 | B48: TJX Australia Pty Limited | C48: 澳大利亚 | D48: 4500154316 | E48: CUS PO#885186 | F48: 4500154316-50 | G48: 77486-S001 | H48: 3代迷你小手袋 圆筒装 | I48: 336 | J48: 0 | K48: 12 | L48: =I48/K48 -> 28 | M48: 45698 | N48: 45694 | P48: pass | R48: 45655 | S48: 无 | T48: 欠客供价格贴纸+空白贴纸 | V48: 日期码格式：ZURU INC(BVI) 标准格式 日期：按实际生产日期 Packaging Info: 包装： 77486: 客版PVC桶_UPC版本+MA收缩膜和收藏指南（UPC条码用1张空白贴纸盖住）+箱唛+1张客供贴纸；（首选1L，无1L可用多L含英语） Ratio： Remark: 1.箱唛不可出现任何手写内容，重量与实际须一致且不可手写; 2.产品上贴客供价格贴纸，贴纸位置为产品正面右上角，不能遮住产品信息；请与跟单确认贴纸位置后再生产大货； 3.订单每行对应客人不同的PO，即同款item的价格贴纸都不相同，请注意收到贴纸后不要弄混!（CUS PO号请参考行项目Remark） 4. 此单去澳大利亚，请按相应澳新标准生产并满足当地法规要求; 5.ZURU QC验货。 6.产品和包装上要有tracking label信息：日期码格式为Zuru标准格式； | W48: Christine Liao | X48: 4.1259 | Y48: =I48*X48 -> 1386.3024 | AA48: 94276-2.18 | AB48: 77486-S001 | AC48: 已入 | AD48: 系统出单 | AG48: =AF48-I48 -> -336 | AK48: =I48*2 -> 672 | AM48: =I48 -> 336 | AS48: =I48*2 -> 672 | BN48: =I48 -> 336 | BO48: =I48 -> 336 | BQ48: =I48 -> 336 | BU48: =AK48+AL48 -> 672 | BV48: =BV47+BU48 -> 2349232 | CA48: =SUM(BX$1:CB$1)-BV48 -> 470768 | CC48: =AW48+AX48+BE48+BF48 -> 0 | CD48: =CD47+CC48 -> 48086.571 | CH48: =$CF$1+$CG$1+$CH$1+$CI$1-CD48 -> 11913.429
A49: 45644 | B49: TJX Australia Pty Limited | C49: 澳大利亚 | D49: 4500154316 | E49: CUS PO#885190 | F49: 4500154316-90 | G49: 77486-S001 | H49: 3代迷你小手袋 圆筒装 | I49: 336 | J49: 0 | K49: 12 | L49: =I49/K49 -> 28 | M49: 45698 | N49: 45694 | P49: pass | R49: 45655 | S49: 无 | T49: 欠客供价格贴纸+空白贴纸 | V49: 日期码格式：ZURU INC(BVI) 标准格式 日期：按实际生产日期 Packaging Info: 包装： 77486: 客版PVC桶_UPC版本+MA收缩膜和收藏指南（UPC条码用1张空白贴纸盖住）+箱唛+1张客供贴纸；（首选1L，无1L可用多L含英语） Ratio： Remark: 1.箱唛不可出现任何手写内容，重量与实际须一致且不可手写; 2.产品上贴客供价格贴纸，贴纸位置为产品正面右上角，不能遮住产品信息；请与跟单确认贴纸位置后再生产大货； 3.订单每行对应客人不同的PO，即同款item的价格贴纸都不相同，请注意收到贴纸后不要弄混!（CUS PO号请参考行项目Remark） 4. 此单去澳大利亚，请按相应澳新标准生产并满足当地法规要求; 5.ZURU QC验货。 6.产品和包装上要有tracking label信息：日期码格式为Zuru标准格式； | W49: Christine Liao | X49: 4.1259 | Y49: =I49*X49 -> 1386.3024 | AA49: 94276-2.18 | AB49: 77486-S001 | AC49: 已入 | AD49: 系统出单 | AG49: =AF49-I49 -> -336 | AK49: =I49*2 -> 672 | AM49: =I49 -> 336 | AS49: =I49*2 -> 672 | BN49: =I49 -> 336 | BO49: =I49 -> 336 | BQ49: =I49 -> 336 | BU49: =AK49+AL49 -> 672 | BV49: =BV48+BU49 -> 2349904 | CA49: =SUM(BX$1:CB$1)-BV49 -> 470096 | CC49: =AW49+AX49+BE49+BF49 -> 0 | CD49: =CD48+CC49 -> 48086.571 | CH49: =$CF$1+$CG$1+$CH$1+$CI$1-CD49 -> 11913.429
A50: 45615 | B50: DD’S DISCOUNTS | C50: 美国 | D50: 4500151537 | E50: 70054036 | F50: 4500151537-10 | G50: 77486-S001 | H50: 3代迷你小手袋 圆筒装 | I50: 600 | J50: 0 | K50: 12 | L50: =I50/K50 -> 50 | M50: 45705 | N50: 45701 | P50: pass | R50: ROSS通用排版 | S50: 无 | T50: 客供价格贴纸 | V50: 日期码格式： 标准格式 日期：按实际生产日期 Packaging Info: 1.ZURU MA UPC 收缩膜+客版铜版纸+PVC桶 + 客供价格贴纸，出口美国 , 优先使用MA 1L 最新版本 。 Remark: 1.ZURU MA UPC 收缩膜+客版铜版纸+PVC桶 + 客供价格贴纸，出口美国 , 优先使用MA 1L 最新版本 。 2.价格贴纸位于包装正面右下角，不挡住重要信息即可，可适当调整 ，价格贴纸由跟单提供。 3.标准日期码格式，产品和包装必须有日期码 。 4.同个产品同个货期不可出现不同的包装。 5. PVC 桶中球不能出现完全相同的ASSORTMENT ， 即同一个PVC 中球里的ASSORTMENT 需要不同。 以免消费者失望。 6.PVC 桶上加上 MINI BRANDS 的LOGO 贴纸 （ ZURU 统一要求的） 7.收缩膜可使用标版带UPC条码MA，无需白色贴纸覆盖。 | W50: Taylor Liao | X50: 4.1259 | Y50: =I50*X50 -> 2475.54 | AA50: ZB00019-3.20 | AB50: 77486-S001 | AC50: 已入 | AD50: 系统出单 | AF50: 600 | AG50: =AF50-I50 -> 0 | AK50: =I50*2 -> 1200 | AM50: =I50*2 -> 1200 | AS50: =I50*2 -> 1200 | BN50: =I50 -> 600 | BO50: =I50 -> 600 | BQ50: =I50 -> 600 | BU50: =AK50+AL50 -> 1200 | BV50: =BV49+BU50 -> 2351104 | CA50: =SUM(BX$1:CB$1)-BV50 -> 468896 | CC50: =AW50+AX50+BE50+BF50 -> 0 | CD50: =CD49+CC50 -> 48086.571 | CH50: =$CF$1+$CG$1+$CH$1+$CI$1-CD50 -> 11913.429
A51: 45649 | B51: WAL-MART STORES INC. USA | C51: 美国 | D51: 4500154532 | E51: 0885773823 SUFFOLK | F51: 4500154532-10 | G51: 77485SLB-S004 | H51: 3代迷你小手袋 | I51: 2304 | J51: 0 | K51: 1152 | L51: =I51/K51 -> 2 | M51: 45705 | N51: 45701 | P51: pass | Q51: 3/4 SI | R51: 外箱印刷带条码的RFID箱唛：RFID紫色色带+WM Dept.图标+RFID图标+ITF-14条码，四面右下角印刷ZURU logo, ITFF条码只印刷在正唛一面，在加印的时候确保 条形码能扫描出来，外箱侧面任一角落加印："MADE IN CHINA" 字样； | S51: 无 | T51: 欠RFID贴纸 | V51: 日期码格式：ZURU DGYYYYMMDD CHINA(日期避开周末和法定节假日即可） 日期：按实际生产日期 Packaging Info: 77485SLB-S004 1.包装要求： MA 1L收缩膜+ 客版 收藏指南B版+MA 纸袋+客版 1L PDQ，翻单：4500128976 每pcs产品上要贴1张RFID贴纸，贴纸由ZURU提供，贴纸位置请严格按照我们签回的签板； Remark: 77485SLB-S004 1.包装要求： MA 1L收缩膜+ 客版 收藏指南B版+MA 纸袋+客版 1L PDQ，翻单：4500128976 每pcs产品上要贴1张RFID贴纸，贴纸由ZURU提供，贴纸位置请严格按照我们签回的签板； 2. 外箱印刷带条码的RFID箱唛：RFID紫色色带+WM Dept.图标+RFID图标+ITF-14条码，四面右下角印刷ZURU logo, ITFF条码只印刷在正唛一面，在加印的时候确保 条形码能扫描出来，外箱侧面任一角落加印："MADE IN CHINA" 字样； 3. 每个slip sheet上面贴一张艾利贴纸（不干胶贴纸）和一张普通贴纸（A4纸），slip sheet打印的普通贴纸的尺寸不能比艾利贴纸小，普通贴纸内容见附件； 4. 在产品上和包装上要有日期码、以及要有MADE IN CHINA和ZURU字样； 5. 产品如有扎带口要剪平，不能刮手。 6. 此单需要验货，请多备料 7. 此单以slip sheet出货，77485：1152pcs/96CTN/Slip Sheet | W51: Maggie Xie | X51: 2206.6131 | Y51: =X51*L51 -> 4413.2262 | AA51: 94290-2.19 | AB51: 77485SLB-S004 | AC51: 已入 | AD51: 系统出单 | AF51: 2304 | AG51: =AF51-I51 -> 0 | AK51: =I51 -> 2304 | AM51: =I51 -> 2304 | AU51: =I51 -> 2304 | AZ51: =I51/12 -> 192 | BU51: =AK51+AL51 -> 2304 | BV51: =BV50+BU51 -> 2353408 | CA51: =SUM(BX$1:CB$1)-BV51 -> 466592 | CC51: =AW51+AX51+BE51+BF51 -> 0 | CD51: =CD50+CC51 -> 48086.571 | CH51: =$CF$1+$CG$1+$CH$1+$CI$1-CD51 -> 11913.429
A52: 45649 | B52: WAL-MART STORES INC. USA | C52: 美国 | D52: 4500154532 | E52: 0885773840 STATESBORO | F52: 4500154532-20 | G52: 77485SLB-S004 | H52: 3代迷你小手袋 | I52: 1152 | J52: 0 | K52: 1152 | L52: =I52/K52 -> 1 | M52: 45705 | N52: 45701 | P52: pass | R52: 外箱印刷带条码的RFID箱唛：RFID紫色色带+WM Dept.图标+RFID图标+ITF-14条码，四面右下角印刷ZURU logo, ITFF条码只印刷在正唛一面，在加印的时候确保 条形码能扫描出来，外箱侧面任一角落加印："MADE IN CHINA" 字样； | S52: 无 | T52: 欠RFID贴纸 | V52: 日期码格式：ZURU DGYYYYMMDD CHINA(日期避开周末和法定节假日即可） 日期：按实际生产日期 Packaging Info: 77485SLB-S004 1.包装要求： MA 1L收缩膜+ 客版 收藏指南B版+MA 纸袋+客版 1L PDQ，翻单：4500128976 每pcs产品上要贴1张RFID贴纸，贴纸由ZURU提供，贴纸位置请严格按照我们签回的签板； Remark: 77485SLB-S004 1.包装要求： MA 1L收缩膜+ 客版 收藏指南B版+MA 纸袋+客版 1L PDQ，翻单：4500128976 每pcs产品上要贴1张RFID贴纸，贴纸由ZURU提供，贴纸位置请严格按照我们签回的签板； 2. 外箱印刷带条码的RFID箱唛：RFID紫色色带+WM Dept.图标+RFID图标+ITF-14条码，四面右下角印刷ZURU logo, ITFF条码只印刷在正唛一面，在加印的时候确保 条形码能扫描出来，外箱侧面任一角落加印："MADE IN CHINA" 字样； 3. 每个slip sheet上面贴一张艾利贴纸（不干胶贴纸）和一张普通贴纸（A4纸），slip sheet打印的普通贴纸的尺寸不能比艾利贴纸小，普通贴纸内容见附件； 4. 在产品上和包装上要有日期码、以及要有MADE IN CHINA和ZURU字样； 5. 产品如有扎带口要剪平，不能刮手。 6. 此单需要验货，请多备料 7. 此单以slip sheet出货，77485：1152pcs/96CTN/Slip Sheet | W52: Maggie Xie | X52: 2206.6131 | Y52: =X52*L52 -> 2206.6131 | AA52: 94268-2.17 | AB52: 77485SLB-S004 | AC52: 已入 | AD52: 系统出单 | AF52: 1152 | AG52: =AF52-I52 -> 0 | AK52: =I52 -> 1152 | AM52: =I52 -> 1152 | AU52: =I52 -> 1152 | AZ52: =I52/12 -> 96 | BU52: =AK52+AL52 -> 1152 | BV52: =BV51+BU52 -> 2354560 | CA52: =SUM(BX$1:CB$1)-BV52 -> 465440 | CC52: =AW52+AX52+BE52+BF52 -> 0 | CD52: =CD51+CC52 -> 48086.571 | CH52: =$CF$1+$CG$1+$CH$1+$CI$1-CD52 -> 11913.429
A53: 45649 | B53: WAL-MART STORES INC. USA | C53: 美国 | D53: 4500154532 | E53: 0885773843 HOUSTON | F53: 4500154532-30 | G53: 77485SLB-S004 | H53: 3代迷你小手袋 | I53: 3456 | J53: 0 | K53: 1152 | L53: =I53/K53 -> 3 | M53: 45705 | N53: 45701 | P53: pass | R53: 外箱印刷带条码的RFID箱唛：RFID紫色色带+WM Dept.图标+RFID图标+ITF-14条码，四面右下角印刷ZURU logo, ITFF条码只印刷在正唛一面，在加印的时候确保 条形码能扫描出来，外箱侧面任一角落加印："MADE IN CHINA" 字样； | S53: 无 | T53: 欠RFID贴纸 | V53: 日期码格式：ZURU DGYYYYMMDD CHINA(日期避开周末和法定节假日即可） 日期：按实际生产日期 Packaging Info: 77485SLB-S004 1.包装要求： MA 1L收缩膜+ 客版 收藏指南B版+MA 纸袋+客版 1L PDQ，翻单：4500128976 每pcs产品上要贴1张RFID贴纸，贴纸由ZURU提供，贴纸位置请严格按照我们签回的签板； Remark: 77485SLB-S004 1.包装要求： MA 1L收缩膜+ 客版 收藏指南B版+MA 纸袋+客版 1L PDQ，翻单：4500128976 每pcs产品上要贴1张RFID贴纸，贴纸由ZURU提供，贴纸位置请严格按照我们签回的签板； 2. 外箱印刷带条码的RFID箱唛：RFID紫色色带+WM Dept.图标+RFID图标+ITF-14条码，四面右下角印刷ZURU logo, ITFF条码只印刷在正唛一面，在加印的时候确保 条形码能扫描出来，外箱侧面任一角落加印："MADE IN CHINA" 字样； 3. 每个slip sheet上面贴一张艾利贴纸（不干胶贴纸）和一张普通贴纸（A4纸），slip sheet打印的普通贴纸的尺寸不能比艾利贴纸小，普通贴纸内容见附件； 4. 在产品上和包装上要有日期码、以及要有MADE IN CHINA和ZURU字样； 5. 产品如有扎带口要剪平，不能刮手。 6. 此单需要验货，请多备料 7. 此单以slip sheet出货，77485：1152pcs/96CTN/Slip Sheet | W53: Maggie Xie | X53: 2206.6131 | Y53: =X53*L53 -> 6619.8393 | AA53: 94336-2.24 94474-3.6 | AB53: 77485SLB-S004 | AC53: 已入 | AD53: 系统出单 | AF53: 3456 | AG53: =AF53-I53 -> 0 | AK53: =I53 -> 3456 | AM53: =I53 -> 3456 | AU53: =I53 -> 3456 | AZ53: =I53/12 -> 288 | BU53: =AK53+AL53 -> 3456 | BV53: =BV52+BU53 -> 2358016 | CA53: =SUM(BX$1:CB$1)-BV53 -> 461984 | CC53: =AW53+AX53+BE53+BF53 -> 0 | CD53: =CD52+CC53 -> 48086.571 | CH53: =$CF$1+$CG$1+$CH$1+$CI$1-CD53 -> 11913.429
A54: 45649 | B54: WAL-MART STORES INC. USA | C54: 美国 | D54: 4500154532 | E54: 0885773844 RIDGEVILLE SC | F54: 4500154532-40 | G54: 77485SLB-S004 | H54: 3代迷你小手袋 | I54: 1152 | J54: 0 | K54: 1152 | L54: =I54/K54 -> 1 | M54: 45705 | N54: 45701 | P54: pass | R54: 外箱印刷带条码的RFID箱唛：RFID紫色色带+WM Dept.图标+RFID图标+ITF-14条码，四面右下角印刷ZURU logo, ITFF条码只印刷在正唛一面，在加印的时候确保 条形码能扫描出来，外箱侧面任一角落加印："MADE IN CHINA" 字样； | S54: 无 | T54: 欠RFID贴纸 | V54: 日期码格式：ZURU DGYYYYMMDD CHINA(日期避开周末和法定节假日即可） 日期：按实际生产日期 Packaging Info: 77485SLB-S004 1.包装要求： MA 1L收缩膜+ 客版 收藏指南B版+MA 纸袋+客版 1L PDQ，翻单：4500128976 每pcs产品上要贴1张RFID贴纸，贴纸由ZURU提供，贴纸位置请严格按照我们签回的签板； Remark: 77485SLB-S004 1.包装要求： MA 1L收缩膜+ 客版 收藏指南B版+MA 纸袋+客版 1L PDQ，翻单：4500128976 每pcs产品上要贴1张RFID贴纸，贴纸由ZURU提供，贴纸位置请严格按照我们签回的签板； 2. 外箱印刷带条码的RFID箱唛：RFID紫色色带+WM Dept.图标+RFID图标+ITF-14条码，四面右下角印刷ZURU logo, ITFF条码只印刷在正唛一面，在加印的时候确保 条形码能扫描出来，外箱侧面任一角落加印："MADE IN CHINA" 字样； 3. 每个slip sheet上面贴一张艾利贴纸（不干胶贴纸）和一张普通贴纸（A4纸），slip sheet打印的普通贴纸的尺寸不能比艾利贴纸小，普通贴纸内容见附件； 4. 在产品上和包装上要有日期码、以及要有MADE IN CHINA和ZURU字样； 5. 产品如有扎带口要剪平，不能刮手。 6. 此单需要验货，请多备料 7. 此单以slip sheet出货，77485：1152pcs/96CTN/Slip Sheet | W54: Maggie Xie | X54: 2206.6131 | Y54: =X54*L54 -> 2206.6131 | AA54: 94336-2.24 | AB54: 77485SLB-S004 | AC54: 已入 | AD54: 系统出单 | AF54: 1152 | AG54: =AF54-I54 -> 0 | AK54: =I54 -> 1152 | AM54: =I54 -> 1152 | AU54: =I54 -> 1152 | AZ54: =I54/12 -> 96 | BU54: =AK54+AL54 -> 1152 | BV54: =BV53+BU54 -> 2359168 | CA54: =SUM(BX$1:CB$1)-BV54 -> 460832 | CC54: =AW54+AX54+BE54+BF54 -> 0 | CD54: =CD53+CC54 -> 48086.571 | CH54: =$CF$1+$CG$1+$CH$1+$CI$1-CD54 -> 11913.429
A55: 45649 | B55: WAL-MART STORES INC. USA | C55: 美国 | D55: 4500154532 | E55: 0885773845 EASTVALE | F55: 4500154532-50 | G55: 77485SLB-S004 | H55: 3代迷你小手袋 | I55: 1152 | J55: 0 | K55: 1152 | L55: =I55/K55 -> 1 | M55: 45705 | N55: 45701 | P55: pass | R55: 外箱印刷带条码的RFID箱唛：RFID紫色色带+WM Dept.图标+RFID图标+ITF-14条码，四面右下角印刷ZURU logo, ITFF条码只印刷在正唛一面，在加印的时候确保 条形码能扫描出来，外箱侧面任一角落加印："MADE IN CHINA" 字样； | S55: 无 | T55: 欠RFID贴纸 | V55: 日期码格式：ZURU DGYYYYMMDD CHINA(日期避开周末和法定节假日即可） 日期：按实际生产日期 Packaging Info: 77485SLB-S004 1.包装要求： MA 1L收缩膜+ 客版 收藏指南B版+MA 纸袋+客版 1L PDQ，翻单：4500128976 每pcs产品上要贴1张RFID贴纸，贴纸由ZURU提供，贴纸位置请严格按照我们签回的签板； Remark: 77485SLB-S004 1.包装要求： MA 1L收缩膜+ 客版 收藏指南B版+MA 纸袋+客版 1L PDQ，翻单：4500128976 每pcs产品上要贴1张RFID贴纸，贴纸由ZURU提供，贴纸位置请严格按照我们签回的签板； 2. 外箱印刷带条码的RFID箱唛：RFID紫色色带+WM Dept.图标+RFID图标+ITF-14条码，四面右下角印刷ZURU logo, ITFF条码只印刷在正唛一面，在加印的时候确保 条形码能扫描出来，外箱侧面任一角落加印："MADE IN CHINA" 字样； 3. 每个slip sheet上面贴一张艾利贴纸（不干胶贴纸）和一张普通贴纸（A4纸），slip sheet打印的普通贴纸的尺寸不能比艾利贴纸小，普通贴纸内容见附件； 4. 在产品上和包装上要有日期码、以及要有MADE IN CHINA和ZURU字样； 5. 产品如有扎带口要剪平，不能刮手。 6. 此单需要验货，请多备料 7. 此单以slip sheet出货，77485：1152pcs/96CTN/Slip Sheet | W55: Maggie Xie | X55: 2206.6131 | Y55: =X55*L55 -> 2206.6131 | AA55: 94362-2.26 | AB55: 77485SLB-S004 | AC55: 已入 | AD55: 系统出单 | AG55: =AF55-I55 -> -1152 | AK55: =I55 -> 1152 | AM55: =I55 -> 1152 | AU55: =I55 -> 1152 | AZ55: =I55/12 -> 96 | BU55: =AK55+AL55 -> 1152 | BV55: =BV54+BU55 -> 2360320 | CA55: =SUM(BX$1:CB$1)-BV55 -> 459680 | CC55: =AW55+AX55+BE55+BF55 -> 0 | CD55: =CD54+CC55 -> 48086.571 | CH55: =$CF$1+$CG$1+$CH$1+$CI$1-CD55 -> 11913.429
A56: 45649 | B56: WAL-MART STORES INC. USA | C56: 美国 | D56: 4500154532 | E56: 0885773895 MOBILE | F56: 4500154532-60 | G56: 77485SLB-S004 | H56: 3代迷你小手袋 | I56: 1152 | J56: 0 | K56: 1152 | L56: =I56/K56 -> 1 | M56: 45705 | N56: 45701 | P56: pass | R56: 外箱印刷带条码的RFID箱唛：RFID紫色色带+WM Dept.图标+RFID图标+ITF-14条码，四面右下角印刷ZURU logo, ITFF条码只印刷在正唛一面，在加印的时候确保 条形码能扫描出来，外箱侧面任一角落加印："MADE IN CHINA" 字样； | S56: 无 | T56: 欠RFID贴纸 | V56: 日期码格式：ZURU DGYYYYMMDD CHINA(日期避开周末和法定节假日即可） 日期：按实际生产日期 Packaging Info: 77485SLB-S004 1.包装要求： MA 1L收缩膜+ 客版 收藏指南B版+MA 纸袋+客版 1L PDQ，翻单：4500128976 每pcs产品上要贴1张RFID贴纸，贴纸由ZURU提供，贴纸位置请严格按照我们签回的签板； Remark: 77485SLB-S004 1.包装要求： MA 1L收缩膜+ 客版 收藏指南B版+MA 纸袋+客版 1L PDQ，翻单：4500128976 每pcs产品上要贴1张RFID贴纸，贴纸由ZURU提供，贴纸位置请严格按照我们签回的签板； 2. 外箱印刷带条码的RFID箱唛：RFID紫色色带+WM Dept.图标+RFID图标+ITF-14条码，四面右下角印刷ZURU logo, ITFF条码只印刷在正唛一面，在加印的时候确保 条形码能扫描出来，外箱侧面任一角落加印："MADE IN CHINA" 字样； 3. 每个slip sheet上面贴一张艾利贴纸（不干胶贴纸）和一张普通贴纸（A4纸），slip sheet打印的普通贴纸的尺寸不能比艾利贴纸小，普通贴纸内容见附件； 4. 在产品上和包装上要有日期码、以及要有MADE IN CHINA和ZURU字样； 5. 产品如有扎带口要剪平，不能刮手。 6. 此单需要验货，请多备料 7. 此单以slip sheet出货，77485：1152pcs/96CTN/Slip Sheet | W56: Maggie Xie | X56: 2206.6131 | Y56: =X56*L56 -> 2206.6131 | AA56: 94362-2.26 | AB56: 77485SLB-S004 | AC56: 已入 | AD56: 系统出单 | AG56: =AF56-I56 -> -1152 | AK56: =I56 -> 1152 | AM56: =I56 -> 1152 | AU56: =I56 -> 1152 | AZ56: =I56/12 -> 96 | BU56: =AK56+AL56 -> 1152 | BV56: =BV55+BU56 -> 2361472 | CA56: =SUM(BX$1:CB$1)-BV56 -> 458528 | CC56: =AW56+AX56+BE56+BF56 -> 0 | CD56: =CD55+CC56 -> 48086.571 | CH56: =$CF$1+$CG$1+$CH$1+$CI$1-CD56 -> 11913.429
A57: 45652 | B57: KOTRYNA GROUP, UAB | C57: 立陶宛 | D57: 4500154811 | F57: 4500154811-20 | G57: 77485GQ6-S001 | H57: 3代迷你小手袋 | I57: 520 | J57: 0 | K57: 52 | L57: =I57/K57 -> 10 | M57: 45705 | N57: 45701 | P57: PASS | R57: 45652 | S57: 无 | T57: 进口商贴纸（贴纸翻4500135326 <(>&<)> 4500135339） | V57: 日期码格式：ZURU INC(BVI) 标准格式 日期：按实际生产日期 Packaging Info: 77485GQ6：B 版 1L MA 收缩膜+进口商贴纸（贴纸翻4500135326 <(>&<)> 4500135339）；A 版 1L MA PDQ/ B 版 5L MA 收藏指南 Remark: 1、若产品有比例使用ZURU STD 比例 2、所有item 均用MA UPC 条码，若包装不是UPC 条码的请告知 3、此单出欧洲需满足EU测试标准要求。另外若产品本身含闪粉则需要出符合欧洲微塑料版本的产品 | W57: Snowy | X57: 1.9026 | Y57: =I57*X57 -> 989.352 | AA57: 94291-2.19 | AB57: 77485GQ6-S001 | AC57: 已入 | AD57: 系统出单 | AF57: 520 | AG57: =AF57-I57 -> 0 | AI57: OK | AK57: =I57 -> 520 | AM57: =I57 -> 520 | AS57: =I57 -> 520 | BC57: =I57/13 -> 40 | BU57: =AK57+AL57 -> 520 | BV57: =BV56+BU57 -> 2361992 | CA57: =SUM(BX$1:CB$1)-BV57 -> 458008 | CC57: =AW57+AX57+BE57+BF57 -> 0 | CD57: =CD56+CC57 -> 48086.571 | CH57: =$CF$1+$CG$1+$CH$1+$CI$1-CD57 -> 11913.429
A58: 45642 | B58: AMAZON.COM.DEDC,LLC | C58: 美国 | D58: 4500153992 | E58: 58SRIN4E | F58: 4500153992-30 | G58: 77486-S001 | H58: 3代迷你小手袋 圆筒装 | I58: 12 | J58: 0 | K58: 12 | L58: =I58/K58 -> 1 | M58: 45707 | N58: 45703 | P58: PASS | R58: 45655 | S58: 有 | T58: 45670 | V58: 日期码格式： 标准格式 日期：按实际生产日期 Packaging Info: #77486：2PK #77485入PVC圆筒。收藏指南用MA 5L，收缩膜用MA 1L不带UPC版。2PK铜版纸图稿翻单4500141223(两个球的配比不能重复)。 Remark: 1.Amazon FOB订单，出口US。外箱最长边不能超过25" （超过了，case pack只能为1），不符合要求的大货，一律不接受。 2. 外箱正面印ZURU Logo+SSCC LABEL（客供贴纸), 侧面印item#（订单上显示的SKU#)+carton size(以工厂实际尺寸为准,单位: inch) +MADE IN CHINA,日期使用Z URU 标准版本 SSCC Label 显示的是客人自己的item#, SSCC Label 贴在外箱正面的正中间，贴一面即可，跟单订购，贴纸离外箱距必须至少3cm, 每一张SSCC labe l 都是唯一且有不同流水及条码的，没有损耗，绝对不可贴错 ，否则贴错或损坏一张会导致全部都错，千万要注意. SSCC 贴纸务必要在正中间(可以覆盖Logo <(>&<)> 箱唛), 否则会影响到仓库扫描识别 3.日期码使用ZURU标准版本 邮包盒上要打上日期码 LCL散货， 直接送货到CDS保税仓 | W58: kelly/Mia | X58: 4.087 | Y58: =I58*X58 -> 49.044 | AA58: 94376-2.27 | AB58: 77486-S001 | AC58: 已入 | AD58: 系统出单 | AF58: 12 | AG58: =AF58-I58 -> 0 | AI58: OK | AK58: =I58*2 -> 24 | AN58: =I58*2 -> 24 | AS58: =I58*2 -> 24 | BN58: =I58 -> 12 | BO58: =I58 -> 12 | BQ58: =I58 -> 12 | BU58: =AK58+AL58 -> 24 | BV58: =BV57+BU58 -> 2362016 | CA58: =SUM(BX$1:CB$1)-BV58 -> 457984 | CC58: =AW58+AX58+BE58+BF58 -> 0 | CD58: =CD57+CC58 -> 48086.571 | CH58: =$CF$1+$CG$1+$CH$1+$CI$1-CD58 -> 11913.429
A59: 45642 | B59: AMAZON.COM.DEDC,LLC | C59: 美国 | D59: 4500154101 | E59: 4AOAWCYU | F59: 4500154101-140 | G59: 77486-S001 | H59: 3代迷你小手袋 圆筒装 | I59: 144 | J59: 0 | K59: 12 | L59: =I59/K59 -> 12 | M59: 45707 | N59: 45703 | P59: PASS | R59: 45655 | S59: 有 | T59: 45670 | V59: 日期码格式： 标准格式 日期：按实际生产日期 Packaging Info: #77486：2PK #77485入PVC圆筒。收藏指南用MA 5L，收缩膜用MA 1L不带UPC版。2PK铜版纸图稿翻单4500141223。(两个球的配比不能重复)。 Remark: 1. Amazon FOB订单，出口US。 2. 日期码使用ZURU标准版本。 3. 如果大货有要求入邮包盒，则对应的邮包盒上面要打上日期码。 4. 箱尺寸要求：外箱最长边不能超过25"(超过了，case pack只能为1)，不符合要求的大货，一律不接受。 5. 外箱箱唛要求： ①外箱正面印ZURU Logo+SSCC Label(客供贴纸，由跟单订购)。关于 SSCC Label 请注意： SSCC Label显示的是客人自己的item#。每一张SSCC label都是唯一且有不同流水及条码的，没有损耗，绝对不可贴错。如果贴错或损坏任何一张，都会导致全部都 错，千万要注意！SSCC Label必须贴在外箱正面的正中间位置(贴一面即可)，并且贴纸离外箱边距必须至少3cm(可以覆盖Logo<(>&<)>箱唛)，否则会影响到客户那边 仓库的扫描识别。 ②外箱侧面印item#(订单上显示的SKU#)+carton size(以工厂实际尺寸为准，单位: inch)+MADE IN CHINA，日期使用ZURU 标准版本。 6. 装柜要求：按照客户PO#装柜/箱号顺序装柜，跟单会提前给到装柜计划。 在大货生产/仓库存放时，请留意该装柜要求，以便装柜时不混乱(避免装错/装漏/找不到货号等)。 | W59: kelly/Mia | X59: 4.1259 | Y59: =I59*X59 -> 594.1296 | AA59: 94337-2.24 | AB59: 77486-S001 | AC59: 已入 | AD59: 系统出单 | AF59: 144 | AG59: =AF59-I59 -> 0 | AI59: OK | AK59: =I59*2 -> 288 | AN59: =I59*2 -> 288 | AS59: =I59*2 -> 288 | BN59: =I59 -> 144 | BO59: =I59 -> 144 | BQ59: =I59 -> 144 | BU59: =AK59+AL59 -> 288 | BV59: =BV58+BU59 -> 2362304 | CA59: =SUM(BX$1:CB$1)-BV59 -> 457696 | CC59: =AW59+AX59+BE59+BF59 -> 0 | CD59: =CD58+CC59 -> 48086.571 | CH59: =$CF$1+$CG$1+$CH$1+$CI$1-CD59 -> 11913.429
A60: 45594 | B60: Distribuidora Liverpool S.A de C.V. | C60: 墨西哥 | D60: 4500149460 | E60: 61900883 | F60: 4500149460-150 | G60: 77485GQ7-S001 | H60: 3代迷你小手袋 | I60: 1350 | J60: 0 | K60: 50 | L60: =I60/K60 -> 27 | M60: 45712 | N60: =M60-4 -> 45708 | P60: PASS | R60: 45660 | S60: 无 | T60: 进口商贴纸翻单之前PO#4500137056 | V60: 日期码格式：ZURU INC(BVI) 标准格式 日期：按实际生产日期 Packaging Info:77485GQ7:MA 3LEAN包装+UPC贴纸+进口商贴纸+价标贴纸+箱唛，UPC贴纸/进口商贴纸翻单PO4500137056 Remark: 1. 此单价格贴纸（ZURU定购). 2.此单有第三方监柜，不用额外准备备品，会在大货中每款拆1pc，拆了包装的产品会由监装员用客供胶带封好或在外箱上写上""opened by telescope” | W60: Ava Liang | X60: 2.0019 | Y60: =X60*I60 -> 2702.565 | AA60: 94382-2.27 | AB60: 77485GQ7-S001-3L-1 | AC60: 已入 | AD60: 系统出单 | AF60: 1350 | AG60: =AF60-I60 -> 0 | AI60: OK | AK60: =I60 -> 1350 | AP60: =I60 -> 1350 | AS60: =I60 -> 1350 | BF60: =I60/25 -> 54 | BU60: =AK60+AL60 -> 1350 | BV60: =BV59+BU60 -> 2363654 | CA60: =SUM(BX$1:CB$1)-BV60 -> 456346 | CC60: =AW60+AX60+BE60+BF60 -> 54 | CD60: =CD59+CC60 -> 48140.571 | CH60: =$CF$1+$CG$1+$CH$1+$CI$1-CD60 -> 11859.429
A61: 45611 | B61: Distribuidora Liverpool S.A de C.V. | C61: 墨西哥 | D61: 4500151307 | F61: 4500151307-90 | G61: 77485GQ7-S001 | H61: 3代迷你小手袋 | I61: 750 | J61: 0 | K61: 50 | L61: =I61/K61 -> 15 | M61: 45712 | N61: 45708 | P61: PASS | R61: 45666 | S61: 无 | T61: UPC贴纸+进口商贴纸+客供价标贴纸 | V61: 日期码格式：ZURU INC(BVI) 标准格式 日期：按实际生产日期 Packaging Info: 77485GQ7:MA 3LEAN包装+UPC贴纸+进口商贴纸+价标贴纸+箱唛，UPC贴纸/进口商贴纸翻单PO4500137056 Remark: 1. 此单价格贴纸（ZURU定购). 2.此单有第三方监柜，不用额外准备备品，会在大货中每款拆1pc，拆了包装的产品会由监装员用客供胶带封好或在外箱上写上""opened by telescope” | W61: Ava Liang | X61: 2.0019 | Y61: =X61*I61 -> 1501.425 | AA61: 94352-2.25 | AB61: 77485GQ7-S001-3L-1 | AC61: 已入 | AD61: 系统出单 | AF61: 750 | AG61: =AF61-I61 -> 0 | AI61: OK | AK61: =I61 -> 750 | AP61: =I61 -> 750 | AS61: =I61 -> 750 | BF61: =I61/25 -> 30 | BU61: =AK61+AL61 -> 750 | BV61: =BV60+BU61 -> 2364404 | CA61: =SUM(BX$1:CB$1)-BV61 -> 455596 | CC61: =AW61+AX61+BE61+BF61 -> 30 | CD61: =CD60+CC61 -> 48170.571 | CH61: =$CF$1+$CG$1+$CH$1+$CI$1-CD61 -> 11829.429
A62: 45651 | B62: AMIC TRADING (PTY) LTD | C62: 南非 | D62: 4500154694 | E62: PO#6006-00522 6PI#110002571 5-2 | F62: 4500154694-40 | G62: 77485GQ6-S001 | H62: 3代迷你小手袋 | I62: 416 | J62: 0 | K62: 52 | L62: =I62/K62 -> 8 | M62: 45713 | N62: =M62-4 -> 45709 | P62: PASS | R62: 45651 | S62: 无 | T62: 45659 | V62: 日期码格式：ZURU INC(BVI) 标准格式 日期：按实际生产日期 Packaging Info: MA PKG, 优先1L +1张进口商贴纸（贴条码附近空白处，不得遮挡日期码） 该客户只有一款进口商贴纸，所有款通用，进口商贴纸AW可翻此客户旧订单 Remark: | W62: Doris Shou | X62: 1.8868 | Y62: =I62*X62 -> 784.9088 | AA62: 94351-2.25 | AB62: 77485GQ6-S001 | AC62: 已入 | AD62: 系统出单 | AF62: 416 | AG62: =AF62-I62 -> 0 | AI62: OK | AK62: =I62 -> 416 | AM62: =I62 -> 416 | AS62: =I62 -> 416 | BC62: =I62/13 -> 32 | BU62: =AK62+AL62 -> 416 | BV62: =BV61+BU62 -> 2364820 | CA62: =SUM(BX$1:CB$1)-BV62 -> 455180 | CC62: =AW62+AX62+BE62+BF62 -> 0 | CD62: =CD61+CC62 -> 48170.571 | CH62: =$CF$1+$CG$1+$CH$1+$CI$1-CD62 -> 11829.429
A63: 45651 | B63: TOYS "R" US – JAPAN, LTD | C63: 日本 | D63: 4500154656 | E63: 47:0003113849 | F63: 4500154656-10 | G63: 77485GQ7-S001 | H63: 3代迷你小手袋 | I63: 5000 | J63: 0 | K63: 50 | L63: =I63/K63 -> 100 | M63: 45716 | N63: 45712 | P63: PASS | R63: 45651 | S63: 无 | T63: 45677 | V63: 日期码格式：ZURU INC(BVI) 标准格式 日期：按实际生产日期 Packaging Info: 77485GQ7：MA 1L PKG+1张日语警语贴纸 Remark: 出日本首单需安排样板测试， 请按邮件要求先寄出MA包装的样板做测试。 大货的产品内容和MA包装版本以及产品品质需严格跟到寄出的测试版。 | W63: Doris Shou | X63: 1.9731 | Y63: =I63*X63 -> 9865.5 | AA63: 94602-3.21 | AB63: 77485GQ7-S001 | AC63: 已入 | AD63: 系统出单 | AF63: 5000 | AG63: =AF63-I63 -> 0 | AI63: OK | AK63: =I63 -> 5000 | AM63: =I63 -> 5000 | AS63: =I63 -> 5000 | BE63: =I63/25 -> 200 | BU63: =AK63+AL63 -> 5000 | BV63: =BV62+BU63 -> 2369820 | CA63: =SUM(BX$1:CB$1)-BV63 -> 450180 | CC63: =AW63+AX63+BE63+BF63 -> 200 | CD63: =CD62+CC63 -> 48370.571 | CH63: =$CF$1+$CG$1+$CH$1+$CI$1-CD63 -> 11629.429
A64: 45660 | B64: THE ENTERTAINER | C64: 英国 | D64: 4500154847 | E64: FB12131 | F64: 4500154847-60 | G64: 77485GQ6-S001 | H64: 3代迷你小手袋 | I64: 3224 | J64: 0 | K64: 52 | L64: =I64/K64 -> 62 | M64: 45716 | N64: 45712 | P64: PASS | R64: 45663 | S64: 无 | T64: 客户EAN条码（翻单4500148687） | V64: 日期码格式：ZURU INC(BVI) 标准格式 日期：按实际生产日期 Packaging Info: 77485GQ6: MA最新1L配套包装+客户EAN条码（翻单4500148687）覆盖ZURU 原条码，MA PDQ Remark: *MA版本按工厂现有最新库存即可，订单出英国，请注意检查产品及包装应带UKCA图标，包装显示ZURU UK LTD信息，QC同事请查核，如有问题与跟单确认 *生产日期按实际（法定工作日），按ZURU标准格式即可 ，但是请知悉包装日期码需要早于或者等于外箱日期码 ，不能晚于外箱日期码 *请注意所有订单都需要经过ZURU QC验货并且通过后方可出货 *条码以订单显示为准 ，请安排生产前先核对 ，有问题请提出。 *所有产品按符合欧洲标准走货，需要是不含微塑料版本 。 *涉及到硼的，如可选择情况下应使用低硼版本 （slime 类别低硼一般低于300ppm)，无选择的应与跟单复核再安排 。 *条码以订单显示为准 ，请安排生产前先核对 ，有问题请提出。 *订单对应客户2个PO号 ，备注有显示 ，注意分开做货/验货/装柜 ，混装有罚款。 *样板： 请在1/20前每款寄出2pcs大货样到罗湖办公室 7B Sandy Shao收 | W64: Sandy Shao | X64: 1.8809 | Y64: =I64*X64 -> 6064.0216 | AA64: 94436-3.4 | AB64: 77485GQ6-S001 | AC64: 已入 | AD64: 系统出单 | AF64: 3224 | AG64: =AF64-I64 -> 0 | AI64: OK | AK64: =I64 -> 3224 | AM64: =I64 -> 3224 | AS64: =I64 -> 3224 | BC64: =I64/13 -> 248 | BU64: =AK64+AL64 -> 3224 | BV64: =BV63+BU64 -> 2373044 | CA64: =SUM(BX$1:CB$1)-BV64 -> 446956 | CC64: =AW64+AX64+BE64+BF64 -> 0 | CD64: =CD63+CC64 -> 48370.571 | CH64: =$CF$1+$CG$1+$CH$1+$CI$1-CD64 -> 11629.429
A65: 45649 | B65: WAL-MART STORES INC. USA | C65: 美国 | D65: 4500154533 | E65: 0885773851 EASTVALE | F65: 4500154533-10 | G65: 77485SLB-S004 | H65: 3代迷你小手袋 | I65: 2304 | J65: 0 | K65: 1152 | L65: =I65/K65 -> 2 | M65: 45719 | N65: 45715 | P65: PASS | R65: 外箱印刷带条码的RFID箱唛：RFID紫色色带+WM Dept.图标+RFID图标+ITF-14条码，四面右下角印刷ZURU logo, ITFF条码只印刷在正唛一面，在加印的时候确保 条形码能扫描出来，外箱侧面任一角落加印："MADE IN CHINA" 字样； | S65: 无 | T65: 欠RFID贴纸 | V65: 日期码格式：ZURU DGYYYYMMDD CHINA(日期避开周末和法定节假日即可） 日期：按实际生产日期 Packaging Info: 77485SLB-S004 1.包装要求： MA 1L收缩膜+ 客版 收藏指南B版+MA 纸袋+客版 1L PDQ，翻单：4500128976 每pcs产品上要贴1张RFID贴纸，贴纸由ZURU提供，贴纸位置请严格按照我们签回的签板 Remark: 77485SLB-S004 1.包装要求： MA 1L收缩膜+ 客版 收藏指南B版+MA 纸袋+客版 1L PDQ，翻单：4500128976 每pcs产品上要贴1张RFID贴纸，贴纸由ZURU提供，贴纸位置请严格按照我们签回的签板； 2. 外箱印刷带条码的RFID箱唛：RFID紫色色带+WM Dept.图标+RFID图标+ITF-14条码，四面右下角印刷ZURU logo, ITFF条码只印刷在正唛一面，在加印的时候确保 条形码能扫描出来，外箱侧面任一角落加印："MADE IN CHINA" 字样； 3. 每个slip sheet上面贴一张艾利贴纸（不干胶贴纸）和一张普通贴纸（A4纸），slip sheet打印的普通贴纸的尺寸不能比艾利贴纸小，普通贴纸内容见附件； 4. 在产品上和包装上要有日期码、以及要有MADE IN CHINA和ZURU字样； 5. 产品如有扎带口要剪平，不能刮手。 6. 此单需要验货，请多备料 7. 此单以slip sheet出货，77485：1152pcs/96CTN/Slip Sheet | W65: Maggie Xie | X65: 2220.2067 | Y65: =X65*L65 -> 4440.4134 | AA65: 94543-3.13 | AB65: 77485SLB-S004 | AC65: 已入 | AD65: 系统出单 | AF65: 2304 | AG65: =AF65-I65 -> 0 | AK65: =I65 -> 2304 | AM65: =I65 -> 2304 | AU65: =I65 -> 2304 | AZ65: =I65/12 -> 192 | BU65: =AK65+AL65 -> 2304 | BV65: =BV64+BU65 -> 2375348 | CA65: =SUM(BX$1:CB$1)-BV65 -> 444652 | CC65: =AW65+AX65+BE65+BF65 -> 0 | CD65: =CD64+CC65 -> 48370.571 | CH65: =$CF$1+$CG$1+$CH$1+$CI$1-CD65 -> 11629.429
A66: 45649 | B66: WAL-MART STORES INC. USA | C66: 美国 | D66: 4500154533 | E66: 0885773855 MOBILE | F66: 4500154533-20 | G66: 77485SLB-S004 | H66: 3代迷你小手袋 | I66: 1152 | J66: 0 | K66: 1152 | L66: =I66/K66 -> 1 | M66: 45719 | N66: 45715 | P66: PASS | R66: 外箱印刷带条码的RFID箱唛：RFID紫色色带+WM Dept.图标+RFID图标+ITF-14条码，四面右下角印刷ZURU logo, ITFF条码只印刷在正唛一面，在加印的时候确保 条形码能扫描出来，外箱侧面任一角落加印："MADE IN CHINA" 字样； | S66: 无 | T66: 欠RFID贴纸 | V66: 日期码格式：ZURU DGYYYYMMDD CHINA(日期避开周末和法定节假日即可） 日期：按实际生产日期 Packaging Info: 77485SLB-S004 1.包装要求： MA 1L收缩膜+ 客版 收藏指南B版+MA 纸袋+客版 1L PDQ，翻单：4500128976 每pcs产品上要贴1张RFID贴纸，贴纸由ZURU提供，贴纸位置请严格按照我们签回的签板 Remark: 77485SLB-S004 1.包装要求： MA 1L收缩膜+ 客版 收藏指南B版+MA 纸袋+客版 1L PDQ，翻单：4500128976 每pcs产品上要贴1张RFID贴纸，贴纸由ZURU提供，贴纸位置请严格按照我们签回的签板； 2. 外箱印刷带条码的RFID箱唛：RFID紫色色带+WM Dept.图标+RFID图标+ITF-14条码，四面右下角印刷ZURU logo, ITFF条码只印刷在正唛一面，在加印的时候确保 条形码能扫描出来，外箱侧面任一角落加印："MADE IN CHINA" 字样； 3. 每个slip sheet上面贴一张艾利贴纸（不干胶贴纸）和一张普通贴纸（A4纸），slip sheet打印的普通贴纸的尺寸不能比艾利贴纸小，普通贴纸内容见附件； 4. 在产品上和包装上要有日期码、以及要有MADE IN CHINA和ZURU字样； 5. 产品如有扎带口要剪平，不能刮手。 6. 此单需要验货，请多备料 7. 此单以slip sheet出货，77485：1152pcs/96CTN/Slip Sheet | W66: Maggie Xie | X66: 2220.2067 | Y66: =X66*L66 -> 2220.2067 | AA66: 94451-3.5 | AB66: 77485SLB-S004 | AC66: 已入 | AD66: 系统出单 | AF66: 1152 | AG66: =AF66-I66 -> 0 | AK66: =I66 -> 1152 | AM66: =I66 -> 1152 | AU66: =I66 -> 1152 | AZ66: =I66/12 -> 96 | BU66: =AK66+AL66 -> 1152 | BV66: =BV65+BU66 -> 2376500 | CA66: =SUM(BX$1:CB$1)-BV66 -> 443500 | CC66: =AW66+AX66+BE66+BF66 -> 0 | CD66: =CD65+CC66 -> 48370.571 | CH66: =$CF$1+$CG$1+$CH$1+$CI$1-CD66 -> 11629.429
A67: 45649 | B67: WAL-MART STORES INC. USA | C67: 美国 | D67: 4500154533 | E67: 0885773864 STATESBORO | F67: 4500154533-30 | G67: 77485SLB-S004 | H67: 3代迷你小手袋 | I67: 1152 | J67: 0 | K67: 1152 | L67: =I67/K67 -> 1 | M67: 45719 | N67: 45715 | P67: PASS | R67: 外箱印刷带条码的RFID箱唛：RFID紫色色带+WM Dept.图标+RFID图标+ITF-14条码，四面右下角印刷ZURU logo, ITFF条码只印刷在正唛一面，在加印的时候确保 条形码能扫描出来，外箱侧面任一角落加印："MADE IN CHINA" 字样； | S67: 无 | T67: 欠RFID贴纸 | V67: 日期码格式：ZURU DGYYYYMMDD CHINA(日期避开周末和法定节假日即可） 日期：按实际生产日期 Packaging Info: 77485SLB-S004 1.包装要求： MA 1L收缩膜+ 客版 收藏指南B版+MA 纸袋+客版 1L PDQ，翻单：4500128976 每pcs产品上要贴1张RFID贴纸，贴纸由ZURU提供，贴纸位置请严格按照我们签回的签板 Remark: 77485SLB-S004 1.包装要求： MA 1L收缩膜+ 客版 收藏指南B版+MA 纸袋+客版 1L PDQ，翻单：4500128976 每pcs产品上要贴1张RFID贴纸，贴纸由ZURU提供，贴纸位置请严格按照我们签回的签板； 2. 外箱印刷带条码的RFID箱唛：RFID紫色色带+WM Dept.图标+RFID图标+ITF-14条码，四面右下角印刷ZURU logo, ITFF条码只印刷在正唛一面，在加印的时候确保 条形码能扫描出来，外箱侧面任一角落加印："MADE IN CHINA" 字样； 3. 每个slip sheet上面贴一张艾利贴纸（不干胶贴纸）和一张普通贴纸（A4纸），slip sheet打印的普通贴纸的尺寸不能比艾利贴纸小，普通贴纸内容见附件； 4. 在产品上和包装上要有日期码、以及要有MADE IN CHINA和ZURU字样； 5. 产品如有扎带口要剪平，不能刮手。 6. 此单需要验货，请多备料 7. 此单以slip sheet出货，77485：1152pcs/96CTN/Slip Sheet | W67: Maggie Xie | X67: 2220.2067 | Y67: =X67*L67 -> 2220.2067 | AA67: 94490-3.7 | AB67: 77485SLB-S004 | AC67: 已入 | AD67: 系统出单 | AG67: =AF67-I67 -> -1152 | AK67: =I67 -> 1152 | AM67: =I67 -> 1152 | AU67: =I67 -> 1152 | AZ67: =I67/12 -> 96 | BU67: =AK67+AL67 -> 1152 | BV67: =BV66+BU67 -> 2377652 | CA67: =SUM(BX$1:CB$1)-BV67 -> 442348 | CC67: =AW67+AX67+BE67+BF67 -> 0 | CD67: =CD66+CC67 -> 48370.571 | CH67: =$CF$1+$CG$1+$CH$1+$CI$1-CD67 -> 11629.429
A68: 45649 | B68: WAL-MART STORES INC. USA | C68: 美国 | D68: 4500154533 | E68: 0885773871 SUFFOLK | F68: 4500154533-40 | G68: 77485SLB-S004 | H68: 3代迷你小手袋 | I68: 1152 | J68: 0 | K68: 1152 | L68: =I68/K68 -> 1 | M68: 45719 | N68: 45715 | P68: PASS | R68: 外箱印刷带条码的RFID箱唛：RFID紫色色带+WM Dept.图标+RFID图标+ITF-14条码，四面右下角印刷ZURU logo, ITFF条码只印刷在正唛一面，在加印的时候确保 条形码能扫描出来，外箱侧面任一角落加印："MADE IN CHINA" 字样； | S68: 无 | T68: 欠RFID贴纸 | V68: 日期码格式：ZURU DGYYYYMMDD CHINA(日期避开周末和法定节假日即可） 日期：按实际生产日期 Packaging Info: 77485SLB-S004 1.包装要求： MA 1L收缩膜+ 客版 收藏指南B版+MA 纸袋+客版 1L PDQ，翻单：4500128976 每pcs产品上要贴1张RFID贴纸，贴纸由ZURU提供，贴纸位置请严格按照我们签回的签板 Remark: 77485SLB-S004 1.包装要求： MA 1L收缩膜+ 客版 收藏指南B版+MA 纸袋+客版 1L PDQ，翻单：4500128976 每pcs产品上要贴1张RFID贴纸，贴纸由ZURU提供，贴纸位置请严格按照我们签回的签板； 2. 外箱印刷带条码的RFID箱唛：RFID紫色色带+WM Dept.图标+RFID图标+ITF-14条码，四面右下角印刷ZURU logo, ITFF条码只印刷在正唛一面，在加印的时候确保 条形码能扫描出来，外箱侧面任一角落加印："MADE IN CHINA" 字样； 3. 每个slip sheet上面贴一张艾利贴纸（不干胶贴纸）和一张普通贴纸（A4纸），slip sheet打印的普通贴纸的尺寸不能比艾利贴纸小，普通贴纸内容见附件； 4. 在产品上和包装上要有日期码、以及要有MADE IN CHINA和ZURU字样； 5. 产品如有扎带口要剪平，不能刮手。 6. 此单需要验货，请多备料 7. 此单以slip sheet出货，77485：1152pcs/96CTN/Slip Sheet | W68: Maggie Xie | X68: 2220.2067 | Y68: =X68*L68 -> 2220.2067 | AA68: 94543-3.13 | AB68: 77485SLB-S004 | AC68: 已入 | AD68: 系统出单 | AG68: =AF68-I68 -> -1152 | AK68: =I68 -> 1152 | AM68: =I68 -> 1152 | AU68: =I68 -> 1152 | AZ68: =I68/12 -> 96 | BU68: =AK68+AL68 -> 1152 | BV68: =BV67+BU68 -> 2378804 | CA68: =SUM(BX$1:CB$1)-BV68 -> 441196 | CC68: =AW68+AX68+BE68+BF68 -> 0 | CD68: =CD67+CC68 -> 48370.571 | CH68: =$CF$1+$CG$1+$CH$1+$CI$1-CD68 -> 11629.429
A69: 45649 | B69: WAL-MART STORES INC. USA | C69: 美国 | D69: 4500154533 | E69: 0885773885 HOUSTON | F69: 4500154533-50 | G69: 77485SLB-S004 | H69: 3代迷你小手袋 | I69: 1152 | J69: 0 | K69: 1152 | L69: =I69/K69 -> 1 | M69: 45719 | N69: 45715 | P69: PASS | R69: 外箱印刷带条码的RFID箱唛：RFID紫色色带+WM Dept.图标+RFID图标+ITF-14条码，四面右下角印刷ZURU logo, ITFF条码只印刷在正唛一面，在加印的时候确保 条形码能扫描出来，外箱侧面任一角落加印："MADE IN CHINA" 字样； | S69: 无 | T69: 欠RFID贴纸 | V69: 日期码格式：ZURU DGYYYYMMDD CHINA(日期避开周末和法定节假日即可） 日期：按实际生产日期 Packaging Info: 77485SLB-S004 1.包装要求： MA 1L收缩膜+ 客版 收藏指南B版+MA 纸袋+客版 1L PDQ，翻单：4500128976 每pcs产品上要贴1张RFID贴纸，贴纸由ZURU提供，贴纸位置请严格按照我们签回的签板 Remark: 77485SLB-S004 1.包装要求： MA 1L收缩膜+ 客版 收藏指南B版+MA 纸袋+客版 1L PDQ，翻单：4500128976 每pcs产品上要贴1张RFID贴纸，贴纸由ZURU提供，贴纸位置请严格按照我们签回的签板； 2. 外箱印刷带条码的RFID箱唛：RFID紫色色带+WM Dept.图标+RFID图标+ITF-14条码，四面右下角印刷ZURU logo, ITFF条码只印刷在正唛一面，在加印的时候确保 条形码能扫描出来，外箱侧面任一角落加印："MADE IN CHINA" 字样； 3. 每个slip sheet上面贴一张艾利贴纸（不干胶贴纸）和一张普通贴纸（A4纸），slip sheet打印的普通贴纸的尺寸不能比艾利贴纸小，普通贴纸内容见附件； 4. 在产品上和包装上要有日期码、以及要有MADE IN CHINA和ZURU字样； 5. 产品如有扎带口要剪平，不能刮手。 6. 此单需要验货，请多备料 7. 此单以slip sheet出货，77485：1152pcs/96CTN/Slip Sheet | W69: Maggie Xie | X69: 2220.2067 | Y69: =X69*L69 -> 2220.2067 | AA69: 94571-3.17 | AB69: 77485SLB-S004 | AC69: 已入 | AD69: 系统出单 | AG69: =AF69-I69 -> -1152 | AK69: =I69 -> 1152 | AM69: =I69 -> 1152 | AU69: =I69 -> 1152 | AZ69: =I69/12 -> 96 | BU69: =AK69+AL69 -> 1152 | BV69: =BV68+BU69 -> 2379956 | CA69: =SUM(BX$1:CB$1)-BV69 -> 440044 | CC69: =AW69+AX69+BE69+BF69 -> 0 | CD69: =CD68+CC69 -> 48370.571 | CH69: =$CF$1+$CG$1+$CH$1+$CI$1-CD69 -> 11629.429
A70: 45649 | B70: WAL-MART STORES INC. USA | C70: 美国 | D70: 4500154533 | E70: 0885773894 RIDGEVILLE SC | F70: 4500154533-60 | G70: 77485SLB-S004 | H70: 3代迷你小手袋 | I70: 1152 | J70: 0 | K70: 1152 | L70: =I70/K70 -> 1 | M70: 45719 | N70: 45715 | P70: PASS | R70: 外箱印刷带条码的RFID箱唛：RFID紫色色带+WM Dept.图标+RFID图标+ITF-14条码，四面右下角印刷ZURU logo, ITFF条码只印刷在正唛一面，在加印的时候确保 条形码能扫描出来，外箱侧面任一角落加印："MADE IN CHINA" 字样； | S70: 无 | T70: 欠RFID贴纸 | V70: 日期码格式：ZURU DGYYYYMMDD CHINA(日期避开周末和法定节假日即可） 日期：按实际生产日期 Packaging Info: 77485SLB-S004 1.包装要求： MA 1L收缩膜+ 客版 收藏指南B版+MA 纸袋+客版 1L PDQ，翻单：4500128976 每pcs产品上要贴1张RFID贴纸，贴纸由ZURU提供，贴纸位置请严格按照我们签回的签板 Remark: 77485SLB-S004 1.包装要求： MA 1L收缩膜+ 客版 收藏指南B版+MA 纸袋+客版 1L PDQ，翻单：4500128976 每pcs产品上要贴1张RFID贴纸，贴纸由ZURU提供，贴纸位置请严格按照我们签回的签板； 2. 外箱印刷带条码的RFID箱唛：RFID紫色色带+WM Dept.图标+RFID图标+ITF-14条码，四面右下角印刷ZURU logo, ITFF条码只印刷在正唛一面，在加印的时候确保 条形码能扫描出来，外箱侧面任一角落加印："MADE IN CHINA" 字样； 3. 每个slip sheet上面贴一张艾利贴纸（不干胶贴纸）和一张普通贴纸（A4纸），slip sheet打印的普通贴纸的尺寸不能比艾利贴纸小，普通贴纸内容见附件； 4. 在产品上和包装上要有日期码、以及要有MADE IN CHINA和ZURU字样； 5. 产品如有扎带口要剪平，不能刮手。 6. 此单需要验货，请多备料 7. 此单以slip sheet出货，77485：1152pcs/96CTN/Slip Sheet | W70: Maggie Xie | X70: 2220.2067 | Y70: =X70*L70 -> 2220.2067 | AA70: 94512-3.11 | AB70: 77485SLB-S004 | AC70: 已入 | AD70: 系统出单 | AG70: =AF70-I70 -> -1152 | AK70: =I70 -> 1152 | AM70: =I70 -> 1152 | AU70: =I70 -> 1152 | AZ70: =I70/12 -> 96 | BU70: =AK70+AL70 -> 1152 | BV70: =BV69+BU70 -> 2381108 | CA70: =SUM(BX$1:CB$1)-BV70 -> 438892 | CC70: =AW70+AX70+BE70+BF70 -> 0 | CD70: =CD69+CC70 -> 48370.571 | CH70: =$CF$1+$CG$1+$CH$1+$CI$1-CD70 -> 11629.429
A71: 45649 | B71: PPTOYS PTE LTD (SG) | C71: 新加坡 | D71: 4500154572 | E71: ZU24120901SG | F71: 4500154572-40 | G71: 77485GQ6-S001 | H71: 3代迷你小手袋 | I71: 2080 | J71: 0 | K71: 52 | L71: =I71/K71 -> 40 | M71: 45723 | N71: 45719 | P71: PASS | R71: 45663 | S71: 无 | T71: 贴纸AW、位置图翻单如下： 77485-4500131403 | V71: 日期码格式：ZURU INC(BVI) 标准格式 日期：按实际生产日期 Packaging Info: MA UPC包装（优先1L)+1张进口商贴纸 贴纸AW、位置图翻单如下： 77485-4500131403 所有item的贴纸图稿一模一样，请一起订购节省成本。 Remark: | W71: Emma Wu | X71: 1.8868 | Y71: =I71*X71 -> 3924.544 | AA71: 94491-3.7 | AB71: 77485GQ6-S001 | AC71: 已入 | AD71: 系统出单 | AF71: =2028+52 -> 2080 | AG71: =AF71-I71 -> 0 | AI71: OK | AK71: =I71 -> 2080 | AM71: =I71 -> 2080 | AS71: =I71 -> 2080 | BC71: =I71/13 -> 160 | BU71: =AK71+AL71 -> 2080 | BV71: =BV70+BU71 -> 2383188 | CA71: =SUM(BX$1:CB$1)-BV71 -> 436812 | CC71: =AW71+AX71+BE71+BF71 -> 0 | CD71: =CD70+CC71 -> 48370.571 | CH71: =$CF$1+$CG$1+$CH$1+$CI$1-CD71 -> 11629.429
A72: 45651 | B72: Distribuidora Liverpool S.A de C.V. | C72: 墨西哥 | D72: 4500154604 | E72: 61900884 | F72: 4500154604-140 | G72: 77485GQ7-S001 | H72: 3代迷你小手袋 | I72: 1350 | J72: 0 | K72: 50 | L72: =I72/K72 -> 27 | M72: 45721 | N72: 45717 | P72: PASS | R72: 45695 | S72: 无 | T72: UPC贴纸/进口商贴纸翻单PO4500137056 | V72: 日期码格式：ZURU INC(BVI) 标准格式 日期：按实际生产日期 Packaging Info: 77485GQ7:MA 3LEAN包装+UPC贴纸+进口商贴纸+价标贴纸+箱唛，UPC贴纸/进口商贴纸翻单PO4500137056 Remark: 1. 此单价格贴纸（ZURU定购). 2.此单有第三方监柜，不用额外准备备品，会在大货中每款拆1pc，拆了包装的产品会由监装员用客供胶带封好或在外箱上写上""opened by telescope” | W72: Ava Liang | X72: 2.0019 | Y72: =I72*X72 -> 2702.565 | AA72: 94525-3.12 | AB72: 77485GQ7-S001-3L-1 | AC72: 已入 | AD72: 系统出单 | AF72: 1350 | AG72: =AF72-I72 -> 0 | AI72: OK | AK72: =I72 -> 1350 | AP72: =I72 -> 1350 | AS72: =I72 -> 1350 | BF72: =I72/25 -> 54 | BU72: =AK72+AL72 -> 1350 | BV72: =BV71+BU72 -> 2384538 | CA72: =SUM(BX$1:CB$1)-BV72 -> 435462 | CC72: =AW72+AX72+BE72+BF72 -> 54 | CD72: =CD71+CC72 -> 48424.571 | CH72: =$CF$1+$CG$1+$CH$1+$CI$1-CD72 -> 11575.429
A73: 45672 | B73: Fratello (PTY) Ltd | C73: 南非 | D73: 4500155828 | F73: 4500155828-30 | G73: 77485SK1-S002 | H73: 3代迷你小手袋 展示架/带底座 | I73: 360 | J73: 0 | K73: 30 | L73: =I73/K73 -> 12 | M73: 45723 | N73: 45719 | P73: PASS | R73: 45672 | S73: 无 | T73: 无 | V73: 日期码格式：ZURU INC(BVI) 标准格式 日期：按实际生产日期 Packaging Info: 77485SK1: 展架MA 3L PKG, 收缩膜MA 1L PKG, 收藏指南MA 5L PKG Remark: | W73: Doris Shou | X73: 73.6896 | Y73: =X73*L73 -> 884.2752 | AA73: 94513-3.11 | AB73: 77485SK1-S002 | AC73: 已入 | AD73: 系统出单 | AF73: 360 | AG73: =AF73-I73 -> 0 | AI73: 无 | AK73: =I73 -> 360 | AM73: =I73 -> 360 | AS73: =I73 -> 360 | BJ73: =I73/30 -> 12 | BU73: =AK73+AL73 -> 360 | BV73: =BV72+BU73 -> 2384898 | CA73: =SUM(BX$1:CB$1)-BV73 -> 435102 | CC73: =AW73+AX73+BE73+BF73 -> 0 | CD73: =CD72+CC73 -> 48424.571 | CH73: =$CF$1+$CG$1+$CH$1+$CI$1-CD73 -> 11575.429
A74: 45630 | B74: SEARS MEXICO | C74: 墨西哥 | D74: 4500153293 | F74: 4500153293-10 | G74: 77485GQ7-S001 | H74: 3代迷你小手袋 | I74: 1600 | J74: 0 | K74: 50 | L74: =I74/K74 -> 32 | M74: 45723 | N74: 45719 | P74: PASS | R74: 45651 | S74: 无 | T74: 45678 | V74: 日期码格式：ZURU INC(BVI) 标准格式 日期：按实际生产日期 Packaging Info: 77485GQ7：MA 5L 收藏指南+MA 3L 包装+UPC 贴纸+MA 3L PDQ 包装+进口商贴纸+箱唛 Remark: | W74: Zoe Luo | X74: 1.9849 | Y74: =X74*I74 -> 3175.84 | AA74: 94489-3.7 | AB74: 77485GQ7-S001-3L-1 | AC74: 已入 | AD74: 系统出单 | AF74: =1550+50 -> 1600 | AG74: =AF74-I74 -> 0 | AI74: OK | AK74: =I74 -> 1600 | AP74: =I74 -> 1600 | AS74: =I74 -> 1600 | BF74: =I74/25 -> 64 | BU74: =AK74+AL74 -> 1600 | BV74: =BV73+BU74 -> 2386498 | CA74: =SUM(BX$1:CB$1)-BV74 -> 433502 | CC74: =AW74+AX74+BE74+BF74 -> 64 | CD74: =CD73+CC74 -> 48488.571 | CH74: =$CF$1+$CG$1+$CH$1+$CI$1-CD74 -> 11511.429
A75: 45694 | B75: WAL-MART STORES INC. USA | C75: 美国 | D75: 4500156777 | E75: 893502858 | F75: 4500156777-10 | G75: 77485SLB-S004 | H75: 3代迷你小手袋 | I75: 1152 | J75: 0 | K75: 1152 | L75: =I75/K75 -> 1 | M75: 45723 | N75: 45719 | P75: PASS | R75: 外箱印刷带条码的RFID箱唛：RFID紫色色带+WM Dept.图标+RFID图标+ITF-14条码，四面右下角印刷ZURU logo, ITFF条码只印刷在正唛一面，在加印的时候确保 条形码能扫描出来，外箱侧面任一角落加印："MADE IN CHINA" 字样； | S75: 无 | T75: 欠RFID贴纸 | V75: 日期码格式：ZURU DGYYYYMMDD CHINA(日期避开周末和法定节假日即可） 日期：按实际生产日期 Packaging Info: 77485SLB-S004 1.包装要求： MA 1L收缩膜+ 客版 收藏指南B版+MA 纸袋+客版 1L PDQ，翻单：4500128976 每pcs产品上要贴1张RFID贴纸，贴纸由ZURU提供，贴纸位置请严格按照我们签回的签板； Remark: 77485SLB-S004 1.包装要求： MA 1L收缩膜+ 客版 收藏指南B版+MA 纸袋+客版 1L PDQ，翻单：4500128976 每pcs产品上要贴1张RFID贴纸，贴纸由ZURU提供，贴纸位置请严格按照我们签回的签板； 2. 外箱印刷带条码的RFID箱唛：RFID紫色色带+WM Dept.图标+RFID图标+ITF-14条码，四面右下角印刷ZURU logo, ITFF条码只印刷在正唛一面，在加印的时候确保 条形码能扫描出来，外箱侧面任一角落加印："MADE IN CHINA" 字样； 3. 每个slip sheet上面贴一张艾利贴纸（不干胶贴纸）和一张普通贴纸（A4纸），slip sheet打印的普通贴纸的尺寸不能比艾利贴纸小，普通贴纸内容见附件； 4. 在产品上和包装上要有日期码、以及要有MADE IN CHINA和ZURU字样； 5. 产品如有扎带口要剪平，不能刮手。 6. 此单需要验货，请多备料 7. 此单以slip sheet出货，77485：1152pcs/96CTN/Slip Sheet | W75: Maggie Xie | X75: 2211.8489 | Y75: =X75*L75 -> 2211.8489 | AA75: 94542-3.13 | AB75: 77485SLB-S004 | AC75: 已入 | AD75: 系统出单 | AF75: =1140+12 -> 1152 | AG75: =AF75-I75 -> 0 | AK75: =I75 -> 1152 | AM75: =I75 -> 1152 | AU75: =I75 -> 1152 | AZ75: =I75/12 -> 96 | BU75: =AK75+AL75 -> 1152 | BV75: =BV74+BU75 -> 2387650 | CA75: =SUM(BX$1:CB$1)-BV75 -> 432350 | CC75: =AW75+AX75+BE75+BF75 -> 0 | CD75: =CD74+CC75 -> 48488.571 | CH75: =$CF$1+$CG$1+$CH$1+$CI$1-CD75 -> 11511.429
A76: 45678 | B76: DISTRIBUIDORA JUGUETRON S.A. DE C.V | C76: 墨西哥 | D76: 4500156374 | F76: 4500156374-80 | G76: 77485GQ7-S001 | H76: 3代迷你小手袋 | I76: 2500 | J76: 0 | K76: 50 | L76: =I76/K76 -> 50 | M76: 45726 | N76: 45729 | O76: 此单有第三方监柜，需要每款多备1套完整物料 | P76: PASS | R76: 45678 | S76: 有 | T76: 45713 | V76: 日期码格式：ZURU INC(BVI) 标准格式 日期：按实际生产日期 Packaging Info: 77485GQ7:MA 3L EAN包装+UPC贴纸+MA 3L PDQ+外箱贴纸+进口商贴纸+箱唛 Remark: 此单有第三方监柜，需要每款多备1套完整物料 | W76: Ava Liang | X76: 2.0019 | Y76: =X76*I76 -> 5004.75 | AA76: 94515-3.11 | AB76: 77485GQ7-S001-3L-1 | AC76: 已入 | AD76: 系统出单 | AF76: 2500 | AG76: =AF76-I76 -> 0 | AI76: OK | AK76: =I76 -> 2500 | AP76: =I76 -> 2500 | AS76: =I76 -> 2500 | BF76: =I76/25 -> 100 | BU76: =AK76+AL76 -> 2500 | BV76: =BV75+BU76 -> 2390150 | CA76: =SUM(BX$1:CB$1)-BV76 -> 429850 | CC76: =AW76+AX76+BE76+BF76 -> 100 | CD76: =CD75+CC76 -> 48588.571 | CH76: =$CF$1+$CG$1+$CH$1+$CI$1-CD76 -> 11411.429
A77: 45651 | B77: Distribuidora Liverpool S.A de C.V. | C77: 墨西哥 | D77: 4500154624 | E77: 61900885 | F77: 4500154624-140 | G77: 77485GQ7-S001 | H77: 3代迷你小手袋 | I77: 1300 | J77: 0 | K77: 50 | L77: =I77/K77 -> 26 | M77: 45730 | N77: 45726 | P77: PASS | R77: 45698 | S77: 无 | T77: UPC贴纸/进口商贴纸翻单PO4500137056 | V77: 日期码格式：ZURU INC(BVI) 标准格式 日期：按实际生产日期 Packaging Info: 77485GQ7:MA 3LEAN包装+UPC贴纸+进口商贴纸+价标贴纸+箱唛，UPC贴纸/进口商贴纸翻单PO4500137056 Remark: 1. 此单价格贴纸（ZURU定购). 2.此单有第三方监柜，不用额外准备备品，会在大货中每款拆1pc，拆了包装的产品会由监装员用客供胶带封好或在外箱上写上""opened by telescope” | W77: Ava Liang | X77: 2.0019 | Y77: =I77*X77 -> 2602.47 | AA77: 94698-4.3 | AB77: 77485GQ7-S001-3L-1 | AC77: 已入 | AD77: 系统出单 | AF77: =1250+50 -> 1300 | AG77: =AF77-I77 -> 0 | AI77: OK | AK77: =I77 -> 1300 | AP77: =I77 -> 1300 | AS77: =I77 -> 1300 | BF77: =I77/25 -> 52 | BU77: =AK77+AL77 -> 1300 | BV77: =BV76+BU77 -> 2391450 | CA77: =SUM(BX$1:CB$1)-BV77 -> 428550 | CC77: =AW77+AX77+BE77+BF77 -> 52 | CD77: =CD76+CC77 -> 48640.571 | CH77: =$CF$1+$CG$1+$CH$1+$CI$1-CD77 -> 11359.429
A78: 45679 | B78: WAL-MART STORES INC. USA | C78: 美国 | D78: 4500156438 | E78: 0891979243 ELWOOD | F78: 4500156438-10 | G78: 77485SLB-S004 | H78: 3代迷你小手袋 | I78: 1152 | J78: 0 | K78: 1152 | L78: =I78/K78 -> 1 | M78: 45733 | N78: 45729 | P78: PASS | R78: 外箱印刷带条码的RFID箱唛：RFID紫色色带+WM Dept.图标+RFID图标+ITF-14条码，四面右下角印刷ZURU logo, ITFF条码只印刷在正唛一面，在加印的时候确保 条形码能扫描出来，外箱侧面任一角落加印："MADE IN CHINA" 字样； | S78: 无 | T78: 欠RFID贴纸 | V78: 日期码格式：ZURU DGYYYYMMDD CHINA(日期避开周末和法定节假日即可） 日期：按实际生产日期 Packaging Info: 77485SLB-S004 1.包装要求： MA 1L收缩膜+ 客版 收藏指南B版+MA 纸袋+客版 1L PDQ，翻单：4500128976 每pcs产品上要贴1张RFID贴纸，贴纸由ZURU提供，贴纸位置请严格按照我们签回的签板； Remark: 77485SLB-S004 1.包装要求： MA 1L收缩膜+ 客版 收藏指南B版+MA 纸袋+客版 1L PDQ，翻单：4500128976 每pcs产品上要贴1张RFID贴纸，贴纸由ZURU提供，贴纸位置请严格按照我们签回的签板； 2. 外箱印刷带条码的RFID箱唛：RFID紫色色带+WM Dept.图标+RFID图标+ITF-14条码，四面右下角印刷ZURU logo, ITFF条码只印刷在正唛一面，在加印的时候确保 条形码能扫描出来，外箱侧面任一角落加印："MADE IN CHINA" 字样； 3. 每个slip sheet上面贴一张艾利贴纸（不干胶贴纸）和一张普通贴纸（A4纸），slip sheet打印的普通贴纸的尺寸不能比艾利贴纸小，普通贴纸内容见附件； 4. 在产品上和包装上要有日期码、以及要有MADE IN CHINA和ZURU字样； 5. 产品如有扎带口要剪平，不能刮手。 6. 此单需要验货，请多备料 7. 此单以slip sheet出货，77485：1152pcs/96CTN/Slip Sheet | W78: Maggie Xie | X78: 2220.2067 | Y78: =X78*L78 -> 2220.2067 | AA78: ZB00011-3.19 | AB78: 77485SLB-S004 | AC78: 已入 | AD78: 系统出单 | AF78: 1152 | AG78: =AF78-I78 -> 0 | AK78: =I78 -> 1152 | AM78: =I78 -> 1152 | AU78: =I78 -> 1152 | AZ78: =I78/12 -> 96 | BU78: =AK78+AL78 -> 1152 | BV78: =BV77+BU78 -> 2392602 | CA78: =SUM(BX$1:CB$1)-BV78 -> 427398 | CC78: =AW78+AX78+BE78+BF78 -> 0 | CD78: =CD77+CC78 -> 48640.571 | CH78: =$CF$1+$CG$1+$CH$1+$CI$1-CD78 -> 11359.429
A79: 45679 | B79: WAL-MART STORES INC. USA | C79: 美国 | D79: 4500156438 | E79: 0891979244 RIDGEVILLE SC | F79: 4500156438-20 | G79: 77485SLB-S004 | H79: 3代迷你小手袋 | I79: 1152 | J79: 0 | K79: 1152 | L79: =I79/K79 -> 1 | M79: 45733 | N79: 45729 | P79: PASS | R79: 外箱印刷带条码的RFID箱唛：RFID紫色色带+WM Dept.图标+RFID图标+ITF-14条码，四面右下角印刷ZURU logo, ITFF条码只印刷在正唛一面，在加印的时候确保 条形码能扫描出来，外箱侧面任一角落加印："MADE IN CHINA" 字样； | S79: 无 | T79: 欠RFID贴纸 | V79: 日期码格式：ZURU DGYYYYMMDD CHINA(日期避开周末和法定节假日即可） 日期：按实际生产日期 Packaging Info: 77485SLB-S004 1.包装要求： MA 1L收缩膜+ 客版 收藏指南B版+MA 纸袋+客版 1L PDQ，翻单：4500128976 每pcs产品上要贴1张RFID贴纸，贴纸由ZURU提供，贴纸位置请严格按照我们签回的签板； Remark: 77485SLB-S004 1.包装要求： MA 1L收缩膜+ 客版 收藏指南B版+MA 纸袋+客版 1L PDQ，翻单：4500128976 每pcs产品上要贴1张RFID贴纸，贴纸由ZURU提供，贴纸位置请严格按照我们签回的签板； 2. 外箱印刷带条码的RFID箱唛：RFID紫色色带+WM Dept.图标+RFID图标+ITF-14条码，四面右下角印刷ZURU logo, ITFF条码只印刷在正唛一面，在加印的时候确保 条形码能扫描出来，外箱侧面任一角落加印："MADE IN CHINA" 字样； 3. 每个slip sheet上面贴一张艾利贴纸（不干胶贴纸）和一张普通贴纸（A4纸），slip sheet打印的普通贴纸的尺寸不能比艾利贴纸小，普通贴纸内容见附件； 4. 在产品上和包装上要有日期码、以及要有MADE IN CHINA和ZURU字样； 5. 产品如有扎带口要剪平，不能刮手。 6. 此单需要验货，请多备料 7. 此单以slip sheet出货，77485：1152pcs/96CTN/Slip Sheet | W79: Maggie Xie | X79: 2220.2067 | Y79: =X79*L79 -> 2220.2067 | AA79: ZB00036 | AB79: 77485SLB-S004 | AC79: 已入 | AD79: 系统出单 | AG79: =AF79-I79 -> -1152 | AK79: =I79 -> 1152 | AM79: =I79 -> 1152 | AU79: =I79 -> 1152 | AZ79: =I79/12 -> 96 | BU79: =AK79+AL79 -> 1152 | BV79: =BV78+BU79 -> 2393754 | CA79: =SUM(BX$1:CB$1)-BV79 -> 426246 | CC79: =AW79+AX79+BE79+BF79 -> 0 | CD79: =CD78+CC79 -> 48640.571 | CH79: =$CF$1+$CG$1+$CH$1+$CI$1-CD79 -> 11359.429
A80: 45679 | B80: WAL-MART STORES INC. USA | C80: 美国 | D80: 4500156438 | E80: 0891979249 MOBILE | F80: 4500156438-30 | G80: 77485SLB-S004 | H80: 3代迷你小手袋 | I80: 3456 | J80: 0 | K80: 1152 | L80: =I80/K80 -> 3 | M80: 45733 | N80: 45729 | P80: PASS | R80: 外箱印刷带条码的RFID箱唛：RFID紫色色带+WM Dept.图标+RFID图标+ITF-14条码，四面右下角印刷ZURU logo, ITFF条码只印刷在正唛一面，在加印的时候确保 条形码能扫描出来，外箱侧面任一角落加印："MADE IN CHINA" 字样； | S80: 无 | T80: 欠RFID贴纸 | V80: 日期码格式：ZURU DGYYYYMMDD CHINA(日期避开周末和法定节假日即可） 日期：按实际生产日期 Packaging Info: 77485SLB-S004 1.包装要求： MA 1L收缩膜+ 客版 收藏指南B版+MA 纸袋+客版 1L PDQ，翻单：4500128976 每pcs产品上要贴1张RFID贴纸，贴纸由ZURU提供，贴纸位置请严格按照我们签回的签板； Remark: 77485SLB-S004 1.包装要求： MA 1L收缩膜+ 客版 收藏指南B版+MA 纸袋+客版 1L PDQ，翻单：4500128976 每pcs产品上要贴1张RFID贴纸，贴纸由ZURU提供，贴纸位置请严格按照我们签回的签板； 2. 外箱印刷带条码的RFID箱唛：RFID紫色色带+WM Dept.图标+RFID图标+ITF-14条码，四面右下角印刷ZURU logo, ITFF条码只印刷在正唛一面，在加印的时候确保 条形码能扫描出来，外箱侧面任一角落加印："MADE IN CHINA" 字样； 3. 每个slip sheet上面贴一张艾利贴纸（不干胶贴纸）和一张普通贴纸（A4纸），slip sheet打印的普通贴纸的尺寸不能比艾利贴纸小，普通贴纸内容见附件； 4. 在产品上和包装上要有日期码、以及要有MADE IN CHINA和ZURU字样； 5. 产品如有扎带口要剪平，不能刮手。 6. 此单需要验货，请多备料 7. 此单以slip sheet出货，77485：1152pcs/96CTN/Slip Sheet | W80: Maggie Xie | X80: 2220.2067 | Y80: =X80*L80 -> 6660.6201 | AA80: ZB00032 | AB80: 77485SLB-S004 | AC80: 已入 | AD80: 系统出单 | AF80: 3456 | AG80: =AF80-I80 -> 0 | AK80: =I80 -> 3456 | AM80: =I80 -> 3456 | AU80: =I80 -> 3456 | AZ80: =I80/12 -> 288 | BU80: =AK80+AL80 -> 3456 | BV80: =BV79+BU80 -> 2397210 | CA80: =SUM(BX$1:CB$1)-BV80 -> 422790 | CC80: =AW80+AX80+BE80+BF80 -> 0 | CD80: =CD79+CC80 -> 48640.571 | CH80: =$CF$1+$CG$1+$CH$1+$CI$1-CD80 -> 11359.429
A81: 45679 | B81: WAL-MART STORES INC. USA | C81: 美国 | D81: 4500156438 | E81: 0891979260 HOUSTON | F81: 4500156438-40 | G81: 77485SLB-S004 | H81: 3代迷你小手袋 | I81: 2304 | J81: 0 | K81: 1152 | L81: =I81/K81 -> 2 | M81: 45733 | N81: 45729 | P81: PASS | R81: 外箱印刷带条码的RFID箱唛：RFID紫色色带+WM Dept.图标+RFID图标+ITF-14条码，四面右下角印刷ZURU logo, ITFF条码只印刷在正唛一面，在加印的时候确保 条形码能扫描出来，外箱侧面任一角落加印："MADE IN CHINA" 字样； | S81: 无 | T81: 欠RFID贴纸 | V81: 日期码格式：ZURU DGYYYYMMDD CHINA(日期避开周末和法定节假日即可） 日期：按实际生产日期 Packaging Info: 77485SLB-S004 1.包装要求： MA 1L收缩膜+ 客版 收藏指南B版+MA 纸袋+客版 1L PDQ，翻单：4500128976 每pcs产品上要贴1张RFID贴纸，贴纸由ZURU提供，贴纸位置请严格按照我们签回的签板； Remark: 77485SLB-S004 1.包装要求： MA 1L收缩膜+ 客版 收藏指南B版+MA 纸袋+客版 1L PDQ，翻单：4500128976 每pcs产品上要贴1张RFID贴纸，贴纸由ZURU提供，贴纸位置请严格按照我们签回的签板； 2. 外箱印刷带条码的RFID箱唛：RFID紫色色带+WM Dept.图标+RFID图标+ITF-14条码，四面右下角印刷ZURU logo, ITFF条码只印刷在正唛一面，在加印的时候确保 条形码能扫描出来，外箱侧面任一角落加印："MADE IN CHINA" 字样； 3. 每个slip sheet上面贴一张艾利贴纸（不干胶贴纸）和一张普通贴纸（A4纸），slip sheet打印的普通贴纸的尺寸不能比艾利贴纸小，普通贴纸内容见附件； 4. 在产品上和包装上要有日期码、以及要有MADE IN CHINA和ZURU字样； 5. 产品如有扎带口要剪平，不能刮手。 6. 此单需要验货，请多备料 7. 此单以slip sheet出货，77485：1152pcs/96CTN/Slip Sheet | W81: Maggie Xie | X81: 2220.2067 | Y81: =X81*L81 -> 4440.4134 | AA81: ZB00036 | AB81: 77485SLB-S004 | AC81: 已入 | AD81: 系统出单 | AF81: 2304 | AG81: =AF81-I81 -> 0 | AK81: =I81 -> 2304 | AM81: =I81 -> 2304 | AU81: =I81 -> 2304 | AZ81: =I81/12 -> 192 | BU81: =AK81+AL81 -> 2304 | BV81: =BV80+BU81 -> 2399514 | CA81: =SUM(BX$1:CB$1)-BV81 -> 420486 | CC81: =AW81+AX81+BE81+BF81 -> 0 | CD81: =CD80+CC81 -> 48640.571 | CH81: =$CF$1+$CG$1+$CH$1+$CI$1-CD81 -> 11359.429
A82: 45679 | B82: WAL-MART STORES INC. USA | C82: 美国 | D82: 4500156438 | E82: 0891979261 STATESBORO | F82: 4500156438-50 | G82: 77485SLB-S004 | H82: 3代迷你小手袋 | I82: 1152 | J82: 0 | K82: 1152 | L82: =I82/K82 -> 1 | M82: 45733 | N82: 45729 | P82: PASS | R82: 外箱印刷带条码的RFID箱唛：RFID紫色色带+WM Dept.图标+RFID图标+ITF-14条码，四面右下角印刷ZURU logo, ITFF条码只印刷在正唛一面，在加印的时候确保 条形码能扫描出来，外箱侧面任一角落加印："MADE IN CHINA" 字样； | S82: 无 | T82: 欠RFID贴纸 | V82: 日期码格式：ZURU DGYYYYMMDD CHINA(日期避开周末和法定节假日即可） 日期：按实际生产日期 Packaging Info: 77485SLB-S004 1.包装要求： MA 1L收缩膜+ 客版 收藏指南B版+MA 纸袋+客版 1L PDQ，翻单：4500128976 每pcs产品上要贴1张RFID贴纸，贴纸由ZURU提供，贴纸位置请严格按照我们签回的签板； Remark: 77485SLB-S004 1.包装要求： MA 1L收缩膜+ 客版 收藏指南B版+MA 纸袋+客版 1L PDQ，翻单：4500128976 每pcs产品上要贴1张RFID贴纸，贴纸由ZURU提供，贴纸位置请严格按照我们签回的签板； 2. 外箱印刷带条码的RFID箱唛：RFID紫色色带+WM Dept.图标+RFID图标+ITF-14条码，四面右下角印刷ZURU logo, ITFF条码只印刷在正唛一面，在加印的时候确保 条形码能扫描出来，外箱侧面任一角落加印："MADE IN CHINA" 字样； 3. 每个slip sheet上面贴一张艾利贴纸（不干胶贴纸）和一张普通贴纸（A4纸），slip sheet打印的普通贴纸的尺寸不能比艾利贴纸小，普通贴纸内容见附件； 4. 在产品上和包装上要有日期码、以及要有MADE IN CHINA和ZURU字样； 5. 产品如有扎带口要剪平，不能刮手。 6. 此单需要验货，请多备料 7. 此单以slip sheet出货，77485：1152pcs/96CTN/Slip Sheet | W82: Maggie Xie | X82: 2220.2067 | Y82: =X82*L82 -> 2220.2067 | AA82: ZB00072 | AB82: 77485SLB-S004 | AC82: 已入 | AD82: 系统出单 | AF82: 1152 | AG82: =AF82-I82 -> 0 | AK82: =I82 -> 1152 | AM82: =I82 -> 1152 | AU82: =I82 -> 1152 | AZ82: =I82/12 -> 96 | BU82: =AK82+AL82 -> 1152 | BV82: =BV81+BU82 -> 2400666 | CA82: =SUM(BX$1:CB$1)-BV82 -> 419334 | CC82: =AW82+AX82+BE82+BF82 -> 0 | CD82: =CD81+CC82 -> 48640.571 | CH82: =$CF$1+$CG$1+$CH$1+$CI$1-CD82 -> 11359.429
A83: 45679 | B83: WAL-MART STORES INC. USA | C83: 美国 | D83: 4500156438 | E83: 0891979269 SUFFOLK | F83: 4500156438-60 | G83: 77485SLB-S004 | H83: 3代迷你小手袋 | I83: 1152 | J83: 0 | K83: 1152 | L83: =I83/K83 -> 1 | M83: 45733 | N83: 45729 | P83: PASS | R83: 外箱印刷带条码的RFID箱唛：RFID紫色色带+WM Dept.图标+RFID图标+ITF-14条码，四面右下角印刷ZURU logo, ITFF条码只印刷在正唛一面，在加印的时候确保 条形码能扫描出来，外箱侧面任一角落加印："MADE IN CHINA" 字样； | S83: 无 | T83: 欠RFID贴纸 | V83: 日期码格式：ZURU DGYYYYMMDD CHINA(日期避开周末和法定节假日即可） 日期：按实际生产日期 Packaging Info: 77485SLB-S004 1.包装要求： MA 1L收缩膜+ 客版 收藏指南B版+MA 纸袋+客版 1L PDQ，翻单：4500128976 每pcs产品上要贴1张RFID贴纸，贴纸由ZURU提供，贴纸位置请严格按照我们签回的签板； Remark: 77485SLB-S004 1.包装要求： MA 1L收缩膜+ 客版 收藏指南B版+MA 纸袋+客版 1L PDQ，翻单：4500128976 每pcs产品上要贴1张RFID贴纸，贴纸由ZURU提供，贴纸位置请严格按照我们签回的签板； 2. 外箱印刷带条码的RFID箱唛：RFID紫色色带+WM Dept.图标+RFID图标+ITF-14条码，四面右下角印刷ZURU logo, ITFF条码只印刷在正唛一面，在加印的时候确保 条形码能扫描出来，外箱侧面任一角落加印："MADE IN CHINA" 字样； 3. 每个slip sheet上面贴一张艾利贴纸（不干胶贴纸）和一张普通贴纸（A4纸），slip sheet打印的普通贴纸的尺寸不能比艾利贴纸小，普通贴纸内容见附件； 4. 在产品上和包装上要有日期码、以及要有MADE IN CHINA和ZURU字样； 5. 产品如有扎带口要剪平，不能刮手。 6. 此单需要验货，请多备料 7. 此单以slip sheet出货，77485：1152pcs/96CTN/Slip Sheet | W83: Maggie Xie | X83: 2220.2067 | Y83: =X83*L83 -> 2220.2067 | AA83: ZB00077 | AB83: 77485SLB-S004 | AC83: 已入 | AD83: 系统出单 | AG83: =AF83-I83 -> -1152 | AK83: =I83 -> 1152 | AM83: =I83 -> 1152 | AU83: =I83 -> 1152 | AZ83: =I83/12 -> 96 | BU83: =AK83+AL83 -> 1152 | BV83: =BV82+BU83 -> 2401818 | CA83: =SUM(BX$1:CB$1)-BV83 -> 418182 | CC83: =AW83+AX83+BE83+BF83 -> 0 | CD83: =CD82+CC83 -> 48640.571 | CH83: =$CF$1+$CG$1+$CH$1+$CI$1-CD83 -> 11359.429
A84: 45700 | B84: WAL-MART STORES INC. USA | C84: 美国 | D84: 4500157306 | E84: 0897254649 | F84: 4500157306-10 | G84: 77485SLB-S004 | H84: 3代迷你小手袋 | I84: 1152 | J84: 0 | K84: 1152 | L84: =I84/K84 -> 1 | M84: 45733 | N84: 45729 | P84: PASS | R84: 外箱印刷带条码的RFID箱唛：RFID紫色色带+WM Dept.图标+RFID图标+ITF-14条码，四面右下角印刷ZURU logo, ITFF条码只印刷在正唛一面，在加印的时候确保 条形码能扫描出来，外箱侧面任一角落加印："MADE IN CHINA" 字样； | S84: 无 | T84: 欠RFID贴纸 | V84: 日期码格式：ZURU DGYYYYMMDD CHINA(日期避开周末和法定节假日即可） 日期：按实际生产日期 Packaging Info: 77485SLB-S004 1.包装要求： MA 1L收缩膜+ 客版 收藏指南B版+MA 纸袋+客版 1L PDQ，翻单：4500128976 每pcs产品上要贴1张RFID贴纸，贴纸由ZURU提供，贴纸位置请严格按照我们签回的签板； Remark: 77485SLB-S004 1.包装要求： MA 1L收缩膜+ 客版 收藏指南B版+MA 纸袋+客版 1L PDQ，翻单：4500128976 每pcs产品上要贴1张RFID贴纸，贴纸由ZURU提供，贴纸位置请严格按照我们签回的签板； 2. 外箱印刷带条码的RFID箱唛：RFID紫色色带+WM Dept.图标+RFID图标+ITF-14条码，四面右下角印刷ZURU logo, ITFF条码只印刷在正唛一面，在加印的时候确保 条形码能扫描出来，外箱侧面任一角落加印："MADE IN CHINA" 字样； 3. 每个slip sheet上面贴一张艾利贴纸（不干胶贴纸）和一张普通贴纸（A4纸），slip sheet打印的普通贴纸的尺寸不能比艾利贴纸小，普通贴纸内容见附件； 4. 在产品上和包装上要有日期码、以及要有MADE IN CHINA和ZURU字样； 5. 产品如有扎带口要剪平，不能刮手。 6. 此单需要验货，请多备料 7. 此单以slip sheet出货，77485：1152pcs/96CTN/Slip Sheet | W84: Maggie Xie | X84: 2233.8003 | Y84: =X84*L84 -> 2233.8003 | AA84: ZB00014-3.19 | AB84: 77485SLB-S004 | AC84: 已入 | AD84: 系统出单 | AG84: =AF84-I84 -> -1152 | AK84: =I84 -> 1152 | AM84: =I84 -> 1152 | AU84: =I84 -> 1152 | AZ84: =I84/12 -> 96 | BU84: =AK84+AL84 -> 1152 | BV84: =BV83+BU84 -> 2402970 | CA84: =SUM(BX$1:CB$1)-BV84 -> 417030 | CC84: =AW84+AX84+BE84+BF84 -> 0 | CD84: =CD83+CC84 -> 48640.571 | CH84: =$CF$1+$CG$1+$CH$1+$CI$1-CD84 -> 11359.429
A85: 45698 | B85: Ambiental Paraguay | C85: 巴拉圭 | D85: 4500156544 | F85: 4500156544-60 | G85: 77485GQ6-S001 | H85: 3代迷你小手袋 | I85: 1196 | J85: 0 | K85: 52 | L85: =I85/K85 -> 23 | M85: 45737 | N85: 45734 | P85: PASS | R85: 45696 | S85: 无 | T85: 45707 | V85: 日期码格式：ZURU INC(BVI) 标准格式 日期：按实际生产日期 Packaging Info: 77485GQ6:MA 3L EAN包装+进口商贴纸（进口商贴纸+UPC贴纸合并为一张）+箱唛 Remark: | W85: Ava Liang | X85: 1.9026 | Y85: =I85*X85 -> 2275.5096 | AA85: 94726-4.8 | AB85: 77485GQ6-S001-3L | AC85: 已入 | AD85: 系统出单 | AF85: =1196 -> 1196 | AG85: =AF85-I85 -> 0 | AI85: OK | AK85: =I85 -> 1196 | AP85: =I85 -> 1196 | AS85: =I85 -> 1196 | BD85: =I85/13 -> 92 | BU85: =AK85+AL85 -> 1196 | BV85: =BV84+BU85 -> 2404166 | CA85: =SUM(BX$1:CB$1)-BV85 -> 415834 | CC85: =AW85+AX85+BE85+BF85 -> 0 | CD85: =CD84+CC85 -> 48640.571 | CH85: =$CF$1+$CG$1+$CH$1+$CI$1-CD85 -> 11359.429
A86: 45712 | B86: IMPORTADORA CHICOCOS | C86: 玻利维亚 | D86: 4500158356 | F86: 4500158356-110 | G86: 77485GQ7-S001 | H86: 3代迷你小手袋 | I86: 750 | J86: 0 | K86: 50 | L86: =I86/K86 -> 15 | M86: 45744 | N86: 45740 | P86: PASS | R86: 45713 | S86: 无 | T86: 45712 | V86: 日期码格式：ZURU INC(BVI) 标准格式 日期：按实际生产日期 Packaging Info: 77485GQ7: MA多语EAN包装+UPC贴纸+MA PDQ包装+箱唛 Remark: | W86: Ava Liang | X86: 2.0019 | Y86: =I86*X86 -> 1501.425 | AA86: 94687-4.1 | AB86: 77485GQ7-S001-3L-1 | AC86: 已入 | AD86: 系统出单 | AF86: 750 | AG86: =AF86-I86 -> 0 | AI86: OK | AK86: =I86 -> 750 | AP86: =I86 -> 750 | AS86: =I86 -> 750 | BF86: =I86/25 -> 30 | BU86: =AK86+AL86 -> 750 | BV86: =BV85+BU86 -> 2404916 | CA86: =SUM(BX$1:CB$1)-BV86 -> 415084 | CC86: =AW86+AX86+BE86+BF86 -> 30 | CD86: =CD85+CC86 -> 48670.571 | CH86: =$CF$1+$CG$1+$CH$1+$CI$1-CD86 -> 11329.429
A87: 45740 | D87: ZMPO250257 | G87: 77485-S001 | H87: 3代迷你小手袋 | I87: 142空球 | J87: 0 | K87: 24 | L87: =I87/K87 -> #VALUE! | M87: 45749 | N87: =M87-4 -> 45745 | R87: 45740 | S87: 无 | T87: 无 | V87: Remark:大货最新版本/142PCS空球要用大货收缩膜收缩好;备注： 收到样品订单后尽快安排 ，注意样板品质质量要求要高于大货品质质量 ，送货时必须要附带送货单(没有送货单和QC检验合格报告的仓库一律拒绝收货)，请知悉，谢谢！ | W87: Angus | AA87: 95977 | AC87: * | AF87: 142 | AG87: 0 | BU87: =AK87+AL87 -> 0 | BV87: =BV86+BU87 -> 2404916 | CA87: =SUM(BX$1:CB$1)-BV87 -> 415084 | CC87: =AW87+AX87+BE87+BF87 -> 0 | CD87: =CD86+CC87 -> 48670.571 | CH87: =$CF$1+$CG$1+$CH$1+$CI$1-CD87 -> 11329.429
A88: 45740 | D88: ZMPO250257 | G88: 77485-S001 | H88: 3代迷你小手袋 | I88: 7套散件 | J88: 0 | K88: 24 | L88: =I88/K88 -> #VALUE! | M88: 45749 | N88: =M88-4 -> 45745 | R88: 45740 | S88: 无 | T88: 无 | V88: Remark:大货最新版本/只需要齐全套散件，每款散件不要用纸袋子装，用透明塑胶袋装即可/麻烦用胶袋分装好一套为一袋;备注： 收到样品订单后尽快安排 ，注意样板品质质量要求要高于大货品质质量 ，送货时必须要附带送货单(没有送货单和QC检验合格报告的仓库一律拒绝收货)，请知悉，谢谢！ | W88: Angus | AA88: 95977 | AC88: * | AF88: 7 | AG88: 0 | BU88: =AK88+AL88 -> 0 | BV88: =BV87+BU88 -> 2404916 | CA88: =SUM(BX$1:CB$1)-BV88 -> 415084 | CC88: =AW88+AX88+BE88+BF88 -> 0 | CD88: =CD87+CC88 -> 48670.571 | CH88: =$CF$1+$CG$1+$CH$1+$CI$1-CD88 -> 11329.429
A89: 45721 | B89: CatchMe.lk (PVT) LTD | C89: 斯里兰卡 | D89: 4500159239 | F89: 4500159239-10 | G89: 77485GQ6-S001 | H89: 3代迷你小手袋 | I89: 416 | J89: 0 | K89: 52 | L89: =I89/K89 -> 8 | M89: 45758 | N89: =M89-4 -> 45754 | P89: PASS | R89: 45721 | S89: 无 | T89: 无 | V89: 日期码格式：ZURU INC(BVI) 标准格式 日期：按实际生产日期 Packaging Info: MA PKG, 优先1L(UPC 条码） Remark: 出斯里兰卡，需送货到汕头仓库 | W89: Doris Shou | X89: 1.8868 | Y89: =I89*X89 -> 784.9088 | AA89: 94841-4.25 | AB89: 77485GQ6-S001 | AC89: 已入 | AD89: 系统出单 | AF89: 416 | AG89: =AF89-I89 -> 0 | AI89: 无 | AK89: =I89 -> 416 | AM89: =I89 -> 416 | AS89: =I89 -> 416 | BC89: =I89/13 -> 32 | BU89: =AK89+AL89 -> 416 | BV89: =BV88+BU89 -> 2405332 | CA89: =SUM(BX$1:CB$1)-BV89 -> 414668 | CC89: =AW89+AX89+BE89+BF89 -> 0 | CD89: =CD88+CC89 -> 48670.571 | CH89: =$CF$1+$CG$1+$CH$1+$CI$1-CD89 -> 11329.429
A90: 45712 | B90: Walmart Central America | C90: 萨尔瓦多 | D90: 4500158302 | F90: 4500158302-40 | G90: 77485GQ7-S001 | H90: 3代迷你小手袋 | I90: 350 | J90: 0 | K90: 50 | L90: =I90/K90 -> 7 | M90: 45763 | N90: 45759 | P90: PASS | R90: 3/24，使用双坑外箱 | S90: 无 | T90: 45737 | V90: 日期码格式：ZURU INC(BVI) 标准格式 日期：按实际生产日期 Packaging Info: 1. 77485GQ7：MA 3L EAN包装+UPC贴纸+MA 3L PDQ包装+MA多语收藏指南+进口商贴纸+箱唛 Remark: 1.使用双坑外箱 2.请注意产品包装条形码必须是UPC 3.无第三方验货 | W90: Ever Li | X90: 2.0019 | Y90: =I90*X90 -> 700.665 | AA90: 94865-4.28 | AB90: 77485GQ7-S001-3L-1 | AC90: 已入 | AD90: 系统出单 | AF90: 350 | AG90: =AF90-I90 -> 0 | AI90: OK | AK90: =I90 -> 350 | AP90: =I90 -> 350 | AS90: =I90 -> 350 | BF90: =I90/25 -> 14 | BU90: =AK90+AL90 -> 350 | BV90: =BV89+BU90 -> 2405682 | CA90: =SUM(BX$1:CB$1)-BV90 -> 414318 | CC90: =AW90+AX90+BE90+BF90 -> 14 | CD90: =CD89+CC90 -> 48684.571 | CH90: =$CF$1+$CG$1+$CH$1+$CI$1-CD90 -> 11315.429
A91: 45712 | B91: Walmart Central America-NI | C91: 尼加拉瓜 | D91: 4500158358 | F91: 4500158358-20 | G91: 77485GQ7-S001 | H91: 3代迷你小手袋 | I91: 200 | J91: 0 | K91: 50 | L91: =I91/K91 -> 4 | M91: 45763 | N91: 45759 | P91: PASS | R91: 3/24，使用双坑外箱 | S91: 无 | T91: 45737 | V91: 日期码格式：ZURU INC(BVI) 标准格式 日期：按实际生产日期 Packaging Info: 1. 77485GQ7：MA 3L EAN包装+UPC贴纸+MA 3L PDQ包装+MA多语收藏指南+进口商贴纸+箱唛 所有贴纸翻单PO 4500158302 Remark: 1.使用双坑外箱 2.请注意产品包装条形码必须是UPC 3.无第三方验货 | W91: Ever Li | X91: 2.0019 | Y91: =I91*X91 -> 400.38 | AA91: 94934-5.6 | AB91: 77485GQ7-S001-3L-1 | AC91: 已入 | AD91: 系统出单 | AF91: 200 | AG91: =AF91-I91 -> 0 | AK91: =I91 -> 200 | AP91: =I91 -> 200 | AS91: =I91 -> 200 | BF91: =I91/25 -> 8 | BU91: =AK91+AL91 -> 200 | BV91: =BV90+BU91 -> 2405882 | CA91: =SUM(BX$1:CB$1)-BV91 -> 414118 | CC91: =AW91+AX91+BE91+BF91 -> 8 | CD91: =CD90+CC91 -> 48692.571 | CH91: =$CF$1+$CG$1+$CH$1+$CI$1-CD91 -> 11307.429
A92: 45712 | B92: Walmart Central America-HN | C92: 洪都拉斯 | D92: 4500158415 | F92: 4500158415-40 | G92: 77485GQ7-S001 | H92: 3代迷你小手袋 | I92: 250 | J92: 0 | K92: 50 | L92: =I92/K92 -> 5 | M92: 45763 | N92: 45759 | P92: PASS | R92: 3/24，使用双坑外箱 | S92: 无 | T92: 45737 | V92: 日期码格式：ZURU INC(BVI) 标准格式 日期：按实际生产日期 Packaging Info: 1. 77485GQ7：MA 3L EAN包装+UPC贴纸+MA 3L PDQ包装+MA多语收藏指南+进口商贴纸+箱唛 以上所有贴纸翻单PO4500158302 Remark: 1.使用双坑外箱 2.请注意产品包装条形码必须是UPC 3.无第三方验货 | W92: Ever Li | X92: 2.0019 | Y92: =I92*X92 -> 500.475 | AA92: 94891-4.30 | AB92: 77485GQ7-S001-3L-1 | AC92: 已入 | AD92: 系统出单 | AF92: 250 | AG92: =AF92-I92 -> 0 | AK92: =I92 -> 250 | AP92: =I92 -> 250 | AS92: =I92 -> 250 | BF92: =I92/25 -> 10 | BU92: =AK92+AL92 -> 250 | BV92: =BV91+BU92 -> 2406132 | CA92: =SUM(BX$1:CB$1)-BV92 -> 413868 | CC92: =AW92+AX92+BE92+BF92 -> 10 | CD92: =CD91+CC92 -> 48702.571 | CH92: =$CF$1+$CG$1+$CH$1+$CI$1-CD92 -> 11297.429
A93: 45714 | B93: Walmart Central America-CR | C93: 哥斯达黎加 | D93: 4500158535 | F93: 4500158535-40 | G93: 77485GQ7-S001 | H93: 3代迷你小手袋 | I93: 900 | J93: 0 | K93: 50 | L93: =I93/K93 -> 18 | M93: 45763 | N93: 45759 | P93: PASS | R93: 3/24，使用双坑外箱 | S93: 无 | T93: 45737 | V93: 日期码格式：ZURU INC(BVI) 标准格式 日期：按实际生产日期 Packaging Info: 1.77485GQ7：MA 3L EAN包装+UPC贴纸+MA 3L PDQ包装+MA多语收藏指南+进口商贴纸+箱唛 以上贴纸翻单PO 4500158302 Remark: 1.使用双坑外箱 2.请注意产品包装条形码必须是UPC 3.无第三方验货 | W93: Ever Li | X93: 2.0019 | Y93: =I93*X93 -> 1801.71 | AA93: 94882-4.29 | AB93: 77485GQ7-S001-3L-1 | AC93: 已入 | AD93: 系统出单 | AF93: 900 | AG93: =AF93-I93 -> 0 | AK93: =I93 -> 900 | AP93: =I93 -> 900 | AS93: =I93 -> 900 | BF93: =I93/25 -> 36 | BU93: =AK93+AL93 -> 900 | BV93: =BV92+BU93 -> 2407032 | CA93: =SUM(BX$1:CB$1)-BV93 -> 412968 | CC93: =AW93+AX93+BE93+BF93 -> 36 | CD93: =CD92+CC93 -> 48738.571 | CH93: =$CF$1+$CG$1+$CH$1+$CI$1-CD93 -> 11261.429
A94: 45714 | B94: Walmart Central America-GT | C94: 危地马拉 | D94: 4500158447 | F94: 4500158447-40 | G94: 77485GQ7-S001 | H94: 3代迷你小手袋 | I94: 1000 | J94: 0 | K94: 50 | L94: =I94/K94 -> 20 | M94: 45763 | N94: 45759 | P94: PASS | R94: 3/24，使用双坑外箱 | S94: 无 | T94: 45737 | V94: 日期码格式：ZURU INC(BVI) 标准格式 日期：按实际生产日期 Packaging Info: 1. 77485GQ7：MA 3L EAN包装+UPC贴纸+MA 3L PDQ包装+MA多语收藏指南+进口商贴纸+箱唛 以上所有贴纸翻单PO4500158302 Remark: 1.使用双坑外箱 2.请注意产品包装条形码必须是UPC 3.无第三方验货 | W94: Ever Li | X94: 2.0019 | Y94: =I94*X94 -> 2001.9 | AA94: 94923-5.5 | AB94: 77485GQ7-S001-3L-1 | AC94: 已入 | AD94: 系统出单 | AF94: =950+50 -> 1000 | AG94: =AF94-I94 -> 0 | AK94: =I94 -> 1000 | AP94: =I94 -> 1000 | AS94: =I94 -> 1000 | BF94: =I94/25 -> 40 | BU94: =AK94+AL94 -> 1000 | BV94: =BV93+BU94 -> 2408032 | CA94: =SUM(BX$1:CB$1)-BV94 -> 411968 | CC94: =AW94+AX94+BE94+BF94 -> 40 | CD94: =CD93+CC94 -> 48778.571 | CH94: =$CF$1+$CG$1+$CH$1+$CI$1-CD94 -> 11221.429
A95: 45733 | B95: Distruibuciones Universales, SA - D | C95: 洪都拉斯 | D95: 4500160421 | F95: 4500160421-90 | G95: 77485GQ7-S001 | H95: 3代迷你小手袋 | I95: 200 | J95: 0 | K95: 50 | L95: =I95/K95 -> 4 | M95: 45768 | N95: 45764 | P95: PASS | R95: 45736 | S95: 无 | T95: 45741 | V95: 日期码格式：ZURU INC(BVI) 标准格式 日期：按实际生产日期 Packaging Info: 77485GQ7: MA多语EAN包装+UPC贴纸+MA多语收藏指南+MA多语PDQ+箱唛 Remark: | W95: Ava Liang | X95: 1.9605 | Y95: =I95*X95 -> 392.1 | AA95: 94795-4.18 | AB95: 77485GQ7-S001 | AC95: 已入 | AD95: 系统出单 | AF95: 200 | AG95: =AF95-I95 -> 0 | AI95: OK | AK95: =I95 -> 200 | AM95: =I95 -> 200 | AS95: =I95 -> 200 | BE95: =I95/25 -> 8 | BU95: =AK95+AL95 -> 200 | BV95: =BV94+BU95 -> 2408232 | CA95: =SUM(BX$1:CB$1)-BV95 -> 411768 | CC95: =AW95+AX95+BE95+BF95 -> 8 | CD95: =CD94+CC95 -> 48786.571 | CH95: =$CF$1+$CG$1+$CH$1+$CI$1-CD95 -> 11213.429
A96: 45743 | B96: WALMART INC. | C96: 美国 | D96: 4500161593 | E96: 0906735630 EASTVALE | F96: 4500161593-10 | G96: 77485SLB-S004 | H96: 3代迷你小手袋 | I96: 2304 | J96: 0 | K96: 1152 | L96: =I96/K96 -> 2 | M96: 45771 | N96: 45768 | O96: 4/29 第三方验货 | P96: PASS | R96: 外箱印刷带条码的RFID箱唛：RFID紫色色带+WM Dept.图标+RFID图标+ITF-14条码，四面右下角印刷ZURU logo, ITFF条码只印刷在正唛一面，在加印的时候确保 条形码能扫描出来，外箱侧面任一角落加印："MADE IN CHINA" 字样； | S96: 无 | T96: RFID贴纸 | V96: 日期码格式：ZURU DGYYYYMMDD CHINA(日期避开周末和法定节假日即可） 日期：按实际生产日期 Packaging Info: 77485SLB-S004 1.包装要求： MA 1L收缩膜+ 客版 收藏指南B版+MA 纸袋+客版 1L PDQ，翻单：4500128976 每pcs产品上要贴1张RFID贴纸，贴纸由ZURU提供，贴纸位置请严格按照我们签回的签板； Remark: 77485SLB-S004 1.包装要求： MA 1L收缩膜+ 客版 收藏指南B版+MA 纸袋+客版 1L PDQ，翻单：4500128976 每pcs产品上要贴1张RFID贴纸，贴纸由ZURU提供，贴纸位置请严格按照我们签回的签板； 2. 外箱印刷带条码的RFID箱唛：RFID紫色色带+WM Dept.图标+RFID图标+ITF-14条码，四面右下角印刷ZURU logo, ITFF条码只印刷在正唛一面，在加印的时候确保 条形码能扫描出来，外箱侧面任一角落加印："MADE IN CHINA" 字样； 3. 每个slip sheet上面贴一张艾利贴纸（不干胶贴纸）和一张普通贴纸（A4纸），slip sheet打印的普通贴纸的尺寸不能比艾利贴纸小，普通贴纸内容见附件； 4. 在产品上和包装上要有日期码、以及要有MADE IN CHINA和ZURU字样； 5. 产品如有扎带口要剪平，不能刮手。 6. 此单需要验货，请多备料 7. 此单以slip sheet出货，77485：1152pcs/96CTN/Slip Sheet | W96: Maggie Xie | X96: 2180.9506 | Y96: =X96*L96 -> 4361.9012 | AA96: ZB00227-5.9 | AB96: 77485SLB-S004 | AC96: 已入 | AD96: 系统出单 | AF96: 2304 | AG96: =AF96-I96 -> 0 | AI96: OK | AK96: =I96 -> 2304 | AM96: =I96 -> 2304 | AU96: =I96 -> 2304 | AZ96: =I96/12 -> 192 | BU96: =AK96+AL96 -> 2304 | BV96: =BV95+BU96 -> 2410536 | CA96: =SUM(BX$1:CB$1)-BV96 -> 409464 | CC96: =AW96+AX96+BE96+BF96 -> 0 | CD96: =CD95+CC96 -> 48786.571 | CH96: =$CF$1+$CG$1+$CH$1+$CI$1-CD96 -> 11213.429
A97: 45743 | B97: WALMART INC. | C97: 美国 | D97: 4500161593 | E97: 0906735634 HOUSTON | F97: 4500161593-20 | G97: 77485SLB-S004 | H97: 3代迷你小手袋 | I97: 1152 | J97: 0 | K97: 1152 | L97: =I97/K97 -> 1 | M97: 45771 | N97: 45768 | O97: 4/29 第三方验货 | P97: PASS | R97: 外箱印刷带条码的RFID箱唛：RFID紫色色带+WM Dept.图标+RFID图标+ITF-14条码，四面右下角印刷ZURU logo, ITFF条码只印刷在正唛一面，在加印的时候确保 条形码能扫描出来，外箱侧面任一角落加印："MADE IN CHINA" 字样； | S97: 无 | T97: RFID贴纸 | V97: 日期码格式：ZURU DGYYYYMMDD CHINA(日期避开周末和法定节假日即可） 日期：按实际生产日期 Packaging Info: 77485SLB-S004 1.包装要求： MA 1L收缩膜+ 客版 收藏指南B版+MA 纸袋+客版 1L PDQ，翻单：4500128976 每pcs产品上要贴1张RFID贴纸，贴纸由ZURU提供，贴纸位置请严格按照我们签回的签板； Remark: 77485SLB-S004 1.包装要求： MA 1L收缩膜+ 客版 收藏指南B版+MA 纸袋+客版 1L PDQ，翻单：4500128976 每pcs产品上要贴1张RFID贴纸，贴纸由ZURU提供，贴纸位置请严格按照我们签回的签板； 2. 外箱印刷带条码的RFID箱唛：RFID紫色色带+WM Dept.图标+RFID图标+ITF-14条码，四面右下角印刷ZURU logo, ITFF条码只印刷在正唛一面，在加印的时候确保 条形码能扫描出来，外箱侧面任一角落加印："MADE IN CHINA" 字样； 3. 每个slip sheet上面贴一张艾利贴纸（不干胶贴纸）和一张普通贴纸（A4纸），slip sheet打印的普通贴纸的尺寸不能比艾利贴纸小，普通贴纸内容见附件； 4. 在产品上和包装上要有日期码、以及要有MADE IN CHINA和ZURU字样； 5. 产品如有扎带口要剪平，不能刮手。 6. 此单需要验货，请多备料 7. 此单以slip sheet出货，77485：1152pcs/96CTN/Slip Sheet | W97: Maggie Xie | X97: 2180.9506 | Y97: =X97*L97 -> 2180.9506 | AA97: ZB00226-5.9 | AB97: 77485SLB-S004 | AC97: 已入 | AD97: 系统出单 | AF97: 1152 | AG97: =AF97-I97 -> 0 | AI97: OK | AK97: =I97 -> 1152 | AM97: =I97 -> 1152 | AU97: =I97 -> 1152 | AZ97: =I97/12 -> 96 | BU97: =AK97+AL97 -> 1152 | BV97: =BV96+BU97 -> 2411688 | CA97: =SUM(BX$1:CB$1)-BV97 -> 408312 | CC97: =AW97+AX97+BE97+BF97 -> 0 | CD97: =CD96+CC97 -> 48786.571 | CH97: =$CF$1+$CG$1+$CH$1+$CI$1-CD97 -> 11213.429
A98: 45735 | B98: MTA Trade | C98: 哈萨克斯坦 | D98: 4500160671 | F98: 4500160671-80 | G98: 77485GQ6-S001 | H98: 3代迷你小手袋 | I98: 260 | J98: 0 | K98: 52 | L98: =I98/K98 -> 5 | M98: 45772 | N98: 45768 | P98: PASS | R98: 45735 | S98: 无 | T98: 进口商贴纸(翻PO4500148660) | V98: 日期码格式：ZURU INC(BVI) 标准格式 日期：按实际生产日期 Packaging Info: 77485GQ6：MA UPC 收缩膜（优先1L)+进口商贴纸(翻PO4500148660);MA指南;MA PDQ(优先1L) Remark: 标准配比 | W98: Cora Zhou | X98: 1.8632 | Y98: =I98*X98 -> 484.432 | AA98: 94843-4.25 | AB98: 77485GQ6-S001 | AC98: 已入 | AD98: 系统出单 | AF98: 260 | AG98: =AF98-I98 -> 0 | AI98: OK | AK98: =I98 -> 260 | AM98: =I98 -> 260 | AS98: =I98 -> 260 | BC98: =I98/13 -> 20 | BU98: =AK98+AL98 -> 260 | BV98: =BV97+BU98 -> 2411948 | CA98: =SUM(BX$1:CB$1)-BV98 -> 408052 | CC98: =AW98+AX98+BE98+BF98 -> 0 | CD98: =CD97+CC98 -> 48786.571 | CH98: =$CF$1+$CG$1+$CH$1+$CI$1-CD98 -> 11213.429
A99: 45735 | B99: AMAZON UK | C99: 英国 | D99: 4500160662 | E99: Amazon UK:5VZ9DDZU | F99: 4500160662-20 | G99: 77486-S001 | H99: 3代迷你小手袋 圆筒装 | I99: 1008 | J99: 0 | K99: 12 | L99: =I99/K99 -> 84 | M99: 45777 | N99: 45773 | P99: PASS | R99: 空白外箱（加印带Zuru字样的最新logo，除了邮包盒直接做外箱的产品） + SSCC LABEL一张, 无箱唛，MADE IN CHINA 外箱只印一正一侧。箱唛资料按照给定的 标准去做即可，无需发回我方再行审批(新标准将另行通知)。 | S99: 有 | T99: 45754 | V99: 日期码格式：ZURU INC(BVI) 标准格式 日期：按实际生产日期 Packaging Info: Amazon UK(15701A/15711B/71109D/71126/77486/92104H/9296A/9548)/FR(77555)/DE(9258G) 5. 77486：2pcs 77485入PVC tube, 12tubes/ctn; MA 1L收缩膜包装(无barcode)+MA 3L(5L warning)C收藏指南+其他最新版MA包装，客版 3L(5L warning)彩卡包装 +1张贴纸(IT环保标); capsule need to use "no barcode"shrink wrap version 参考翻单PO#4500114776; 11. 最迟验货不得晚于2025/4/30; Remark: 1.空白外箱（加印带Zuru字样的最新logo，除了邮包盒直接做外箱的产品） + SSCC LABEL一张, 无箱唛，MADE IN CHINA 外箱只印一正一侧。箱唛资料按照给定的 标准去做即可，无需发回我方再行审批(新标准将另行通知)。 (SSCC LABEL竖贴在外箱正面的正中间，贴一面即可,贴纸离外箱边距必须至少3.2CM。如竖贴无法满足要求，则横贴。如横贴也无法满足要求，则竖贴，遮到ZURU lo go无影响), SSCC贴纸由工厂直接跟勤得采购或者工厂自行采购，每一张SSCC Label都是唯一且有不同流水及条码，且需要检查条码是否能正常扫描，另外，此贴纸 印刷不可出现模糊，溢出及粘胶不牢易脱落等现象，如工厂不按此要求导致贴纸有任何问题产生的罚款将由工厂承担一切责任 。 2.出往UK的产品+包装务必打上UKCA logo ，否则客人会退货且当地会有罚款。 3.订单必须经过ZURU QC验货并且通过后方可出货。 4.法国订单要求包装不使用矿物油，请按要求提供以下其中一份文件再出货 ，产品出到法国被相关部门抽检出现包装不符合此要求的，供应商需要为此承担责任， 故此请严格把关。 -油墨物质""由1 ~ 7个芳香环组成的MOAH""的包装检测报告，要求限值≤1.0%； -包装材料清单，包括包装油墨或物质的信息； -油墨制造商的证书； 5.每一批次出货只能有一个生产日期，不可多个生产日期混在同一批次出货；且邮包盒上必须统一加上日期码；外箱对于日期码没有硬性规定； 6.涉及到相关款式会有闪粉的或者微塑料的，请统一默认出无闪粉或者不含微塑料版本； 7.邮包盒及外箱封箱必须是工字型封箱方式； 8.5 Surprise or Mini Brands涉及包装是2个及2个以上的球入PVC桶包装时，单个球上若有UPC#或者EAN#，请用白色贴纸覆盖住； | W99: Crystal Chen | X99: 4.0406 | Y99: =I99*X99 -> 4072.9248 | AA99: 95011-5.17 | AB99: 77486-S001 | AC99: 已入 | AD99: 系统出单 | AF99: 1008 | AG99: =AF99-I99 -> 0 | AI99: OK | AK99: =I99*2 -> 2016 | AN99: =I99 -> 1008 | AS99: =I99 -> 1008 | BN99: =I99 -> 1008 | BO99: =I99 -> 1008 | BQ99: =I99 -> 1008 | BU99: =AK99+AL99 -> 2016 | BV99: =BV98+BU99 -> 2413964 | CA99: =SUM(BX$1:CB$1)-BV99 -> 406036 | CC99: =AW99+AX99+BE99+BF99 -> 0 | CD99: =CD98+CC99 -> 48786.571 | CH99: =$CF$1+$CG$1+$CH$1+$CI$1-CD99 -> 11213.429
A100: 45737 | B100: TOY KINGDOM (PTY) LTD | C100: 南非 | D100: 4500161136 | F100: 4500161136-40 | G100: 77485GQ7-S001 | H100: 3代迷你小手袋 | I100: 800 | J100: 0 | K100: 50 | L100: =I100/K100 -> 16 | M100: 45770 | N100: 45766 | P100: PASS | R100: 45737 | S100: 无 | T100: 无 | V100: 日期码格式：ZURU INC(BVI) 标准格式 日期：按实际生产日期 Packaging Info: MA PKG ,优先1L Remark: | W100: Doris Shou | X100: 1.9438 | Y100: =I100*X100 -> 1555.04 | AA100: 94837-4.24 | AB100: 77485GQ7-S001 | AC100: 已入 | AD100: 系统出单 | AF100: 800 | AG100: =AF100-I100 -> 0 | AI100: 无 | AK100: =I100 -> 800 | AM100: =I100 -> 800 | AS100: =I100 -> 800 | BE100: =I100/25 -> 32 | BU100: =AK100+AL100 -> 800 | BV100: =BV99+BU100 -> 2414764 | CA100: =SUM(BX$1:CB$1)-BV100 -> 405236 | CC100: =AW100+AX100+BE100+BF100 -> 32 | CD100: =CD99+CC100 -> 48818.571 | CH100: =$CF$1+$CG$1+$CH$1+$CI$1-CD100 -> 11181.429
...

Sheet 77770 S4 明细
A1: 香港接单日期 | B1: 第三方客户名称 | C1: 走货国家 | D1: ZURU PO NO# | E1: 第三方客户 PO NO# | F1: SKU | G1: ITEM# | H1: 货品名称 | I1: PO数量(只) | J1: 内箱装箱数量(只) | K1: 外箱装箱数量(只) | L1: 总箱数 | M1: 计划出货期 | N1: 计划验货期 | O1: 第三方客户公证行验货 | P1: 验货结果 | Q1: S/O(截仓期) | R1: 箱唛 (收到日期) | S1: 外箱贴纸 | T1: 贴纸资料 (收到日期及订购日期) | U1: 样板 | V1: 备注 | W1: ZURU跟单组员 | X1: 单价USD | Y1: 金额USD | Z1: 是否收到客版包装资料 | AA1: 发票号 | AB1: 系统货号 | AC1: 是否入系统 | AD1: 下单情况 | AE1: 生产情况 | AF1: 已回数量 | AG1: 欠数 | AH1: HN回复完成时间 | AI1: 贴纸 | AJ1: 纸箱 | AK1: 球数 | AL1: MA 1L A收缩膜 | AM1: MA 3L 收缩膜 无条码 | AN1: MA 3L 收缩膜 | AO1: MA 5L 收藏指南 | AP1: WM 客版收藏指南 | AQ1: 中文吊牌 | AR1: 1L 13pcs GQ1 | AS1: 3L 13pcs GQ1 | AT1: 1L 25pcs GQ2 | AU1: 3L 25pcs GQ2-S001 | AV1: 1L 12PCS GQ3-S001 | AW1: 1L B 12PCS GQ3-S001 | AX1: 3L 12PCS GQ3-S001 | AY1: 1L 16PCS GQ4-S001 | AZ1: 1L 13PCS GQ6-S001 | BA1: 13PCS GQ6-S001 3L | BB1: 26PCS TARGET-客版SQ1 | BC1: 25PCS GQ7-S001 3L | BD1: 客版 SK-S001 不含底座 | BE1: 客版 1L SK-S001 不含底座 | BF1: 3L SK-S002 含底座 60pcs | BG1: 3L SK1-S002 30pcs | BH1: 1L SK1-S001 30pcs | BI1: 1L SK1-S002 30pcs | BJ1: 77806 圆筒 | BK1: 77806 彩纸 | BL1: 77806 贴纸 | BN1: 合计数量 | BO1: 累计数量 | BP1: MA 数量 | BQ1: 820000 | BR1: 300000 | BS1: 300000 | BT1: 200000 | BU1: =400000+500000 -> 900000 | BV1: GQ2/GQ4 | BW1: SK1/SK | BX1: 累计数量 | BY1: MA 数量 | BZ1: 420000 | CA1: 440000 | CB1: 440000
A2: 45828 | D2: ZPO2506009 | G2: 77770GQ2-S001 | H2: 迷你包包S4 | I2: 530 | J2: 0 | K2: 24 | L2: =I2/K2 -> 22.083333 | M2: 45841 | N2: =M2-3 -> 45838 | O2: 第三方客户公证行验货 | R2: 无 | S2: 无 | T2: 无 | V2: Remark:跟PP订单一起安排/大货标准箱装箱/箱唛请参照邮件附件;备注：收到样品订单后尽快安排 ，注意样板品质质量要求要高于大货品质要求 ，送货时必须要附带送货单(没有送货单和QC检验合格报告的仓库一律拒绝收货)，请知悉，谢谢！ | W2: Lynn | AB2: N/A | AC2: N/A | AG2: =AF2-I2 -> -530 | AK2: =I2 -> 530 | BV2: =AT2+AU2+AY2 -> 0 | BW2: =BF2+BG2+BI2 -> 0 | BX2: =AK2 -> 530 | BZ2: =$BZ$1-BX2 -> 419470
A3: 45828 | D3: ZMPO250496 | G3: 77770-S001 | H3: 迷你包包S4 | I3: 504 | J3: 0 | K3: 24 | L3: =I3/K3 -> 21 | M3: 45845 | N3: 45841 | R3: 无 | S3: 无 | T3: 无 | V3: Remark:跟PP订单一起安排/大货标准箱装箱/箱唛请参照邮件附件;备注：收到样品订单后尽快安排 ，注意样板品质质量要求要高于大货品质要求 ，送货时必须要附带送货单(没有送货单和QC检验合格报告的仓库一律拒绝收货)，请知悉，谢谢！ | W3: Angus | AB3: N/A | AC3: N/A | AG3: =AF3-I3 -> -504 | AK3: =I3 -> 504 | AL3: =I3 -> 504 | AO3: =I3 -> 504 | BV3: =AT3+AU3+AY3 -> 0 | BW3: =BF3+BG3+BI3 -> 0 | BX3: =AK3+BX2 -> 1034 | BZ3: =$BZ$1-BX3 -> 418966
A4: 45828 | D4: ZMPO250496 | G4: 77770-S001 | H4: 迷你包包S4套散件 | I4: 5 | J4: 0 | K4: 24 | L4: =I4/K4 -> 0.20833333 | M4: 45845 | N4: 45841 | R4: 无 | S4: 无 | T4: 无 | V4: Remark:跟PP订单一起安排/只需要齐全套三散件/麻烦用胶袋分装好一套为一袋/箱唛请参照邮件附件;备注：收到样品订单后尽快安排 ，注意样板品质质量要求要高于大货品质要求 ，送货时必须要附带送货单(没有送货单和QC检验合格报告的仓库一律拒绝收货)，请知悉，谢谢！ | W4: Angus | AB4: N/A | AC4: N/A | AG4: =AF4-I4 -> -5 | AK4: =I4 -> 5 | BV4: =AT4+AU4+AY4 -> 0 | BW4: =BF4+BG4+BI4 -> 0 | BX4: =AK4+BX3 -> 1039 | BZ4: =$BZ$1-BX4 -> 418961
A5: 45828 | D5: ZMPO250496 | G5: 77770GQ1-S001 | H5: 迷你包包S4个空PDQ | I5: 20 | J5: 0 | K5: 24 | L5: =I5/K5 -> 0.83333333 | M5: 45845 | N5: 45841 | R5: 无 | S5: 无 | T5: 无 | V5: Remark:跟PP订单一起安排/请配齐PDQ上原有的Demo+吸塑;备注：收到样品订单后尽快安排 ，注意样板品质质量要求要高于大货品质要求 ，送货时必须要附带送货单(没有送货单和QC检验合格报告的仓库一律拒绝收货)，请知悉，谢谢！ | W5: Angus | AB5: N/A | AC5: N/A | AK5: =I5 -> 20 | AR5: 20 | BV5: =AT5+AU5+AY5 -> 0 | BW5: =BF5+BG5+BI5 -> 0 | BX5: =AK5+BX4 -> 1059 | BZ5: =$BZ$1-BX5 -> 418941
A6: 45828 | D6: ZMPO250496 | G6: 77770GQ2-S001 | H6: 迷你包包S4个空PDQ | I6: 20 | J6: 0 | K6: 24 | L6: =I6/K6 -> 0.83333333 | M6: 45845 | N6: 45841 | R6: 无 | S6: 无 | T6: 无 | V6: Remark:跟PP订单一起安排/请配齐PDQ上原有的Demo+吸塑;备注：收到样品订单后尽快安排 ，注意样板品质质量要求要高于大货品质要求 ，送货时必须要附带送货单(没有送货单和QC检验合格报告的仓库一律拒绝收货)，请知悉，谢谢！ | W6: Angus | AB6: N/A | AC6: N/A | AK6: =I6 -> 20 | AT6: 20 | BV6: =AT6+AU6+AY6 -> 20 | BW6: =BF6+BG6+BI6 -> 0 | BX6: =AK6+BX5 -> 1079 | BZ6: =$BZ$1-BX6 -> 418921
A7: 45866 | B7: KMART AUSTRALIA LTD | C7: 澳大利亚 | D7: 4500173688 | E7: 21056035 | F7: 4500173688-20 | G7: 77770GQ1-S002 | H7: 迷你包包S4 13pcs/箱 | I7: 6370 | J7: 0 | K7: 13 | L7: =I7/K7 -> 490 | M7: 45898 | N7: 45894 | P7: PASS | R7: 45866 | S7: 有 | T7: 45876 | V7: 日期码格式：ZURU INC(BVI) 标准格式 日期：按实际生产日期 Packaging Info: 77770GQ1:MA英语UPC版本包装（收缩膜和说明书, MA首选1L，如无1L可用多语且含英语的配套多语包装) + 1张防盗贴纸+箱唛 + 外箱SSCC Label Remark: 1.请务必按时完货，验货。并且按期送货入货代指定仓库，如果晚了导致船期Delay将会有罚金产生或者客户要求空运，所产生的罚金和空运费由工厂承担。 2.SSCC 外箱贴纸请同纸箱瓦楞纸方向（竖纹向）垂直，即外箱贴纸横着贴(注意条码不要被胶带粘住），贴1pc，贴1面正唛，封箱胶纸不能挡住贴纸内容。外箱贴纸 离外箱边距离不少于2cm。 3.外箱材质为ZURU标准； 4.此单需使用KMART封箱胶上下工字型封箱;从2019年6月开始，要用KMART 新版封箱胶带，此单要用"ANKO"封箱胶带 5.此单出口澳大利亚，请按相应的澳新标准生产； 6.产品和包装上生产批号的显示格式ZURU标准日期码格式 7.外箱信息不可手写，重量和体积需要与实际的一致(不可手写） 8. 每款item装箱后的G.W.超过10KG或者CBM超过0.13,(9.5KG或者以上，四舍五入后也属于10KG) 需在外箱上加印超 重或者Bulky LOGO，若发现我们资料没有，请 帮忙提醒 1)重量超过10kg但不超过16kg且CBM不超过0.13,10-16kg 超重logo 2）CBM超过0.13且重量少于17kg，bulky logo 3）不属于以上两种情况，需要使用相应重量范围内的超重logo 4）超重logo需要在外箱四面都印刷(箱唛右上角，两面侧唛超重logo需要尽量靠近毛重)，尺寸为:110mm height* 95mm width 9. 实际外箱重量跟印在箱唛上的数据差异不能超3%，尺寸按实际数据印刷 | W7: Lydia Wu | X7: 2.4275 | Y7: =I7*X7 -> 15463.175 | AA7: A96798-10.31 | AB7: 77770GQ1-S002 | AC7: 已入 | AD7: 东莞生产 | AF7: =4852+107+1411 -> 6370 | AG7: =AF7-I7 -> 0 | AI7: OK | AK7: =I7 -> 6370 | AL7: =I7 -> 6370 | AO7: =I7 -> 6370 | AR7: =I7/13 -> 490 | BV7: =AT7+AU7+AY7 -> 0 | BW7: =BF7+BG7+BI7 -> 0 | BX7: =AK7+BX6 -> 7449 | BZ7: =$BZ$1-BX7 -> 412551
A8: 45866 | B8: KMART AUSTRALIA LTD(NEW ZEALAND) | C8: 新西兰 | D8: 4500173689 | E8: 21056038 | F8: 4500173689-20 | G8: 77770GQ1-S002 | H8: 迷你包包S4 13pcs/箱 | I8: 702 | J8: 0 | K8: 13 | L8: =I8/K8 -> 54 | M8: 45898 | N8: 45894 | P8: PASS | R8: 45866 | S8: 有 | T8: 45876 | V8: 日期码格式：ZURU INC(BVI) 标准格式 日期：按实际生产日期 Packaging Info: 77770GQ1:MA英语UPC版本包装（收缩膜和说明书, MA首选1L，如无1L可用多语且含英语的配套多语包装) + 1张防盗贴纸+箱唛 + 外箱SSCC Label (贴纸以及位置图翻单PO#4500173688） Remark: 1.请务必按时完货，验货。并且按期送货入货代指定仓库，如果晚了导致船期Delay将会有罚金产生或者客户要求空运，所产生的罚金和空运费由工厂承担。 2.SSCC 外箱贴纸请同纸箱瓦楞纸方向（竖纹向）垂直，即外箱贴纸横着贴(注意条码不要被胶带粘住），贴1pc，贴1面正唛，封箱胶纸不能挡住贴纸内容。外箱贴纸 离外箱边距离不少于2cm。 3.外箱材质为ZURU标准； 4.此单需使用KMART封箱胶上下工字型封箱;从2019年6月开始，要用KMART 新版封箱胶带，此单要用"ANKO"封箱胶带 5.此单出口新西兰，请按相应的澳新标准生产； 6.产品和包装上生产批号的显示格式ZURU标准日期码格式 7.外箱信息不可手写，重量和体积需要与实际的一致(不可手写） 8. 每款item装箱后的G.W.超过10KG或者CBM超过0.13,(9.5KG或者以上，四舍五入后也属于10KG) 需在外箱上加印超 重或者Bulky LOGO，若发现我们资料没有，请 帮忙提醒 1)重量超过10kg但不超过16kg且CBM不超过0.13,10-16kg 超重logo 2）CBM超过0.13且重量少于17kg，bulky logo 3）不属于以上两种情况，需要使用相应重量范围内的超重logo 4）超重logo需要在外箱四面都印刷(箱唛右上角，两面侧唛超重logo需要尽量靠近毛重)，尺寸为:110mm height* 95mm width 9. 实际外箱重量跟印在箱唛上的数据差异不能超3%，尺寸按实际数据印刷 | W8: Lydia Wu | X8: 2.4275 | Y8: =I8*X8 -> 1704.105 | AA8: A96799-10.31 | AB8: 77770GQ1-S002 | AC8: 已入 | AD8: 东莞生产 | AF8: =300+402 -> 702 | AG8: =AF8-I8 -> 0 | AI8: OK | AK8: =I8 -> 702 | AL8: =I8 -> 702 | AO8: =I8 -> 702 | AR8: =I8/13 -> 54 | BV8: =AT8+AU8+AY8 -> 0 | BW8: =BF8+BG8+BI8 -> 0 | BX8: =AK8+BX7 -> 8151 | BZ8: =$BZ$1-BX8 -> 411849
A9: 45853 | B9: TARGET US | C9: 美国 | D9: 4500173932 | E9: Draft PO-77770SQ1 | F9: 4500173932-10 | G9: 77770SQ1-S001 | H9: 迷你包包S4 26 pcs/PDQ/箱 | I9: 108004 | J9: 0 | K9: 26 | L9: =I9/K9 -> 4154 | M9: 45908 | N9: 45904 | P9: PASS | R9: 45875 | S9: 有 | T9: 45875 | V9: 日期码格式：ZURU INC(BVI) 标准格式 日期：按实际生产日期 Packaging Info: 产品包装(UPC 版) MA 1L收缩膜 + MA 5L 收藏指南/说明书+客版 PDQ(PDQ中需放置一张折卡，印有Remove信息)+背身UPC贴纸； Remark: 1. 77770SQ1-S001-MINI BRANDS-FASHION MINI BRANDS-SERIES 4-CAPSULE,26PCS/PDQ,26PCS/PDQ/CTN 2. 产品包装(UPC 版) MA 1L收缩膜 + MA 5L 收藏指南/说明书+客版 PDQ(PDQ中需放置一张折卡，印有Remove信息)+背身UPC贴纸；收缩膜上的UPC显示193052089465 ；客版PDQ背面居中位置需要贴背身贴纸，背身贴纸内容显示客户的 DPCI: 086-02-6519，UPC：193052097507； 3. 外箱正唛左上角位置粘贴条码箱贴纸，每箱只贴一张，由ZURU订购。来料贴纸上显示的客户DPCI# 086-02-1748, UPC显示193052097514; 4. 外箱正唛信息右侧空白位置粘贴一张Event label贴纸，贴纸内容显示：Christmas Morning Magic Rear Seasonal Set Date: 11/30/2025 ；由工厂自己订购； 5. 产品和包装上印刷 tracking code信息，格式为ZURU常规格式; 6. 出货方式：货代自提 | W9: Holly Zheng | X9: 1.5191 | Y9: =I9*X9 -> 164068.88 | AA9: ZB02193(REV1)-9.27 ZB02253(REV1)-9.30 | AB9: 77770SQ1-S001 | AC9: 已入 | AD9: 系统出单 | AF9: =22464+11232+56160+18148 -> 108004 | AG9: =AF9-I9 -> 0 | AI9: OK | AK9: =I9 -> 108004 | AL9: =I9 -> 108004 | AO9: =I9 -> 108004 | BB9: =I9/26 -> 4154 | BV9: =AT9+AU9+AY9 -> 0 | BW9: =BF9+BG9+BI9 -> 0 | BX9: =AK9+BX8 -> 116155 | BZ9: =$BZ$1-BX9 -> 303845
A10: 45873 | B10: KMART AUSTRALIA LTD | C10: 澳大利亚 | D10: 4500175924 | E10: 21012356 | F10: 4500175924-130 | G10: 77770GQ1-S002 | H10: 迷你包包S4 13pcs/箱 | I10: 1508 | J10: 0 | K10: 13 | L10: =I10/K10 -> 116 | M10: 45915 | N10: 45911 | P10: PASS | Q10: 45917 | R10: 45883 | S10: 有 | T10: 45877 | V10: 日期码格式：ZURU INC(BVI) 标准格式 日期：按实际生产日期 Packaging Info: 77770GQ1:MA英语UPC版本包装（收缩膜和说明书, MA首选1L，如无1L可用多语且含英语的配套多语包装) + 1张防盗贴纸+箱唛 + 外箱SSCC Label (贴纸以及位置图翻单PO#4500173688） Remark: 1.请务必按时完货，验货。并且按期送货入货代指定仓库，如果晚了导致船期Delay将会有罚金产生或者客户要求空运，所产生的罚金和空运费由工厂承担。 2.SSCC 外箱贴纸请同纸箱瓦楞纸方向（竖纹向）垂直，即外箱贴纸横着贴(注意条码不要被胶带粘住），贴1pc，贴1面正唛，封箱胶纸不能挡住贴纸内容。外箱贴纸 离外箱边距离不少于2cm。 3.外箱材质为ZURU标准； 4.此单需使用KMART封箱胶上下工字型封箱;从2019年6月开始，要用KMART 新版封箱胶带，此单要用"ANKO"封箱胶带 5.此单出口澳大利亚，请按相应的澳新标准生产； 6.产品和包装上生产批号的显示格式ZURU标准日期码格式 7.外箱信息不可手写，重量和体积需要与实际的一致(不可手写） 8. 每款item装箱后的G.W.超过10KG或者CBM超过0.13,(9.5KG或者以上，四舍五入后也属于10KG) 需在外箱上加印超 重或者Bulky LOGO，若发现我们资料没有，请 帮忙提醒 1)重量超过10kg但不超过16kg且CBM不超过0.13,10-16kg 超重logo 2）CBM超过0.13且重量少于17kg，bulky logo 3）不属于以上两种情况，需要使用相应重量范围内的超重logo 4）超重logo需要在外箱四面都印刷(箱唛右上角，两面侧唛超重logo需要尽量靠近毛重)，尺寸为:110mm height* 95mm width 9. 实际外箱重量跟印在箱唛上的数据差异不能超3%，尺寸按实际数据印刷 | W10: Lydia Wu | X10: 2.4275 | Y10: =X10*I10 -> 3660.67 | AA10: A96807-2-10.31 | AB10: 77770GQ1-S002 | AC10: 已入 | AD10: 系统出单 | AF10: 1508 | AG10: =AF10-I10 -> 0 | AI10: OK | AK10: =I10 -> 1508 | AL10: =I10 -> 1508 | AO10: =I10 -> 1508 | AR10: =I10/13 -> 116 | BV10: =AT10+AU10+AY10 -> 0 | BW10: =BF10+BG10+BI10 -> 0 | BX10: =AK10+BX9 -> 117663 | BZ10: =$BZ$1-BX10 -> 302337
A11: 45880 | B11: KMART AUSTRALIA LTD | C11: 澳大利亚 | D11: 4500175924 | E11: 21089022 | F11: 4500175924-140 | G11: 77770GQ1-S002 | H11: 迷你包包S4 13pcs/箱 | I11: 3094 | J11: 0 | K11: 13 | L11: =I11/K11 -> 238 | M11: 45915 | N11: 45911 | P11: PASS | Q11: 45917 | R11: 45883 | S11: 有 | T11: 45877 | V11: 日期码格式：ZURU INC(BVI) 标准格式 日期：按实际生产日期 Packaging Info: 77770GQ1:MA英语UPC版本包装（收缩膜和说明书, MA首选1L，如无1L可用多语且含英语的配套多语包装) + 1张防盗贴纸+箱唛 + 外箱SSCC Label (贴纸以及位置图翻单PO#4500173688） Remark: 1.请务必按时完货，验货。并且按期送货入货代指定仓库，如果晚了导致船期Delay将会有罚金产生或者客户要求空运，所产生的罚金和空运费由工厂承担。 2.SSCC 外箱贴纸请同纸箱瓦楞纸方向（竖纹向）垂直，即外箱贴纸横着贴(注意条码不要被胶带粘住），贴1pc，贴1面正唛，封箱胶纸不能挡住贴纸内容。外箱贴纸 离外箱边距离不少于2cm。 3.外箱材质为ZURU标准； 4.此单需使用KMART封箱胶上下工字型封箱;从2019年6月开始，要用KMART 新版封箱胶带，此单要用"ANKO"封箱胶带 5.此单出口澳大利亚，请按相应的澳新标准生产； 6.产品和包装上生产批号的显示格式ZURU标准日期码格式 7.外箱信息不可手写，重量和体积需要与实际的一致(不可手写） 8. 每款item装箱后的G.W.超过10KG或者CBM超过0.13,(9.5KG或者以上，四舍五入后也属于10KG) 需在外箱上加印超 重或者Bulky LOGO，若发现我们资料没有，请 帮忙提醒 1)重量超过10kg但不超过16kg且CBM不超过0.13,10-16kg 超重logo 2）CBM超过0.13且重量少于17kg，bulky logo 3）不属于以上两种情况，需要使用相应重量范围内的超重logo 4）超重logo需要在外箱四面都印刷(箱唛右上角，两面侧唛超重logo需要尽量靠近毛重)，尺寸为:110mm height* 95mm width 9. 实际外箱重量跟印在箱唛上的数据差异不能超3%，尺寸按实际数据印刷 | W11: Lydia Wu | X11: 2.4275 | Y11: =X11*I11 -> 7510.685 | AA11: A96807-2-10.31 A96808-2-10.31 | AB11: 77770GQ1-S002 | AC11: 已入 | AD11: 系统出单 | AF11: 3094 | AG11: =AF11-I11 -> 0 | AI11: OK | AK11: =I11 -> 3094 | AL11: =I11 -> 3094 | AO11: =I11 -> 3094 | AR11: =I11/13 -> 238 | BV11: =AT11+AU11+AY11 -> 0 | BW11: =BF11+BG11+BI11 -> 0 | BX11: =AK11+BX10 -> 120757 | BZ11: =$BZ$1-BX11 -> 299243
A12: 45880 | B12: KMART AUSTRALIA LTD(NEW ZEALAND) | C12: 新西兰 | D12: 4500175925 | E12: 21089023 | F12: 4500175925-130 | G12: 77770GQ1-S002 | H12: 迷你包包S4 13pcs/箱 | I12: 130 | J12: 0 | K12: 13 | L12: =I12/K12 -> 10 | M12: 45915 | N12: 45911 | P12: PASS | Q12: 45917 | R12: 45883 | S12: 有 | T12: 45877 | V12: 日期码格式：ZURU INC(BVI) 标准格式 日期：按实际生产日期 Packaging Info: 77770GQ1:MA英语UPC版本包装（收缩膜和说明书, MA首选1L，如无1L可用多语且含英语的配套多语包装) + 1张防盗贴纸+箱唛 + 外箱SSCC Label (贴纸以及位置图翻单PO#4500173688） Remark: 1.请务必按时完货，验货。并且按期送货入货代指定仓库，如果晚了导致船期Delay将会有罚金产生或者客户要求空运，所产生的罚金和空运费由工厂承担。 2.SSCC 外箱贴纸请同纸箱瓦楞纸方向（竖纹向）垂直，即外箱贴纸横着贴(注意条码不要被胶带粘住），贴1pc，贴1面正唛，封箱胶纸不能挡住贴纸内容。外箱贴纸 离外箱边距离不少于2cm。 3.外箱材质为ZURU标准； 4.此单需使用KMART封箱胶上下工字型封箱;从2019年6月开始，要用KMART 新版封箱胶带，此单要用"ANKO"封箱胶带 5.此单出口新西兰，请按相应的澳新标准生产； 6.产品和包装上生产批号的显示格式ZURU标准日期码格式 7.外箱信息不可手写，重量和体积需要与实际的一致(不可手写） 8. 每款item装箱后的G.W.超过10KG或者CBM超过0.13,(9.5KG或者以上，四舍五入后也属于10KG) 需在外箱上加印超 重或者Bulky LOGO，若发现我们资料没有，请 帮忙提醒 1)重量超过10kg但不超过16kg且CBM不超过0.13,10-16kg 超重logo 2）CBM超过0.13且重量少于17kg，bulky logo 3）不属于以上两种情况，需要使用相应重量范围内的超重logo 4）超重logo需要在外箱四面都印刷(箱唛右上角，两面侧唛超重logo需要尽量靠近毛重)，尺寸为:110mm height* 95mm width 9. 实际外箱重量跟印在箱唛上的数据差异不能超3%，尺寸按实际数据印刷 | W12: Lydia Wu | X12: 2.4275 | Y12: =X12*I12 -> 315.575 | AA12: 96808-9.19 | AB12: 77770GQ1-S002 | AC12: 已入 | AD12: 系统出单 | AF12: 130 | AG12: =AF12-I12 -> 0 | AI12: OK | AK12: =I12 -> 130 | AL12: =I12 -> 130 | AO12: =I12 -> 130 | AR12: =I12/13 -> 10 | BV12: =AT12+AU12+AY12 -> 0 | BW12: =BF12+BG12+BI12 -> 0 | BX12: =AK12+BX11 -> 120887 | BZ12: =$BZ$1-BX12 -> 299113
A13: 45877 | B13: TOYS "R" US – JAPAN, LTD | C13: 日本 | D13: 4500176402 | E13: 47:0003158165 | F13: 4500176402-10 | G13: 77770GQ2-S001 | H13: 迷你包包S4 | I13: 3750 | J13: 0 | K13: 50 | L13: =I13/K13 -> 75 | M13: 45915 | N13: 45911 | P13: PASS | R13: 45880 | S13: 无 | T13: 45896 | V13: 日期码格式：ZURU INC(BVI) 标准格式 日期：按实际生产日期 Packaging Info: MA 1L UPC PKG+1张日语警语贴纸(贴纸不能遮挡日期码) Remark: 1. 出日本 2. 77770GQ2请安排寄3 套样板到SGS 实验室安排测试，测试pass 后才能出货。大货样需严格跟到测试样。 3. 请多备1-2个外箱出货，避免外箱到仓库后出现破损情况。 | W13: Doris Shou | X13: 2.35 | Y13: =X13*I13 -> 8812.5 | AA13: A96794-10.31 | AB13: 77770GQ2-S001 | AC13: 已入 | AD13: 系统出单 | AF13: 3750 | AG13: =AF13-I13 -> 0 | AI13: OK | AK13: =I13 -> 3750 | AL13: =I13 -> 3750 | AO13: =I13 -> 3750 | AT13: =L13*2 -> 150 | BV13: =AT13+AU13+AY13 -> 150 | BW13: =BF13+BG13+BI13 -> 0 | BX13: =AK13+BX12 -> 124637 | BZ13: =$BZ$1-BX13 -> 295363
A14: 45869 | B14: ALL BRANDS TOYS PTY LTD | C14: 澳大利亚 | D14: 4500175512 | E14: 84457 | F14: 4500175512-10 | G14: 77770GQ2-S002 | H14: 迷你包包S4 25pcs/箱 | I14: 1250 | J14: 0 | K14: 25 | L14: =I14/K14 -> 50 | M14: 45918 | N14: 45915 | P14: PASS | R14: 45869 | S14: 无 | T14: 45869 | V14: 日期码格式：ZURU INC(BVI) 标准格式 日期：按实际生产日期 Packaging Info: MA 1L PKG +1张客人通用进口商贴纸，贴于包装背面空白处， 请提供位置图确认。 Remark: 1.按实际生产日期; 2.出澳大利亚，请按照相应标准生产; | W14: Doris Shou | X14: 2.61 | Y14: =I14*X14 -> 3262.5 | AA14: A96793-10.31 | AB14: 77770GQ2-S002 | AC14: 已入 | AD14: 系统出单 | AF14: 1250 | AG14: =AF14-I14 -> 0 | AI14: OK | AK14: =I14 -> 1250 | AL14: =I14 -> 1250 | AO14: =I14 -> 1250 | AT14: =I14/25 -> 50 | BV14: =AT14+AU14+AY14 -> 50 | BW14: =BF14+BG14+BI14 -> 0 | BX14: =AK14+BX13 -> 125887 | BZ14: =$BZ$1-BX14 -> 294113
A15: 45877 | B15: MEIJER DISTRIBUTION, INC. | C15: 美国 | D15: 4500176410 | E15: 217985641 | F15: 4500176410-10 | G15: 77770GQ1-S002 | H15: 迷你包包S4 13pcs/箱 | I15: 2691 | J15: 0 | K15: 13 | L15: =I15/K15 -> 207 | M15: 45920 | N15: 45916 | P15: PASS | Q15: 截SI 9/22 | R15: 45887 | S15: 无 | T15: 无 | V15: 日期码格式：ZURU INC(BVI) 标准格式 日期： Packaging Info: 1. MA 1L 包装 2. 客人指定箱唛排版 Remark: 出货前 Zuru QC 验货 | W15: Agnes Zheng | X15: 1.4565 | Y15: =X15*I15 -> 3919.4415 | AA15: ZB02464-10.16 | AB15: 77770GQ1-S002 | AC15: 已入 | AD15: 系统出单 | AF15: 2691 | AG15: =AF15-I15 -> 0 | AI15: 无 | AK15: =I15 -> 2691 | AL15: =I15 -> 2691 | AO15: =I15 -> 2691 | AR15: =I15/13 -> 207 | BV15: =AT15+AU15+AY15 -> 0 | BW15: =BF15+BG15+BI15 -> 0 | BX15: =AK15+BX14 -> 128578 | BZ15: =$BZ$1-BX15 -> 291422
A16: 45877 | B16: MEIJER DISTRIBUTION, INC. | C16: 美国 | D16: 4500176411 | E16: 217985572 | F16: 4500176411-10 | G16: 77770GQ1-S002 | H16: 迷你包包S4 13pcs/箱 | I16: 4784 | J16: 0 | K16: 13 | L16: =I16/K16 -> 368 | M16: 45920 | N16: 45916 | P16: PASS | Q16: 截SI 9/22 | R16: 45887 | S16: 无 | T16: 无 | V16: 日期码格式：ZURU INC(BVI) 标准格式 日期： Packaging Info: 1. MA 1L 包装 2. 客人指定箱唛排版 Remark: 出货前 Zuru QC 验货 | W16: Agnes Zheng | X16: 1.4565 | Y16: =X16*I16 -> 6967.896 | AA16: ZB02465-10.16 | AB16: 77770GQ1-S002 | AC16: 已入 | AD16: 系统出单 | AF16: 4784 | AG16: =AF16-I16 -> 0 | AI16: 无 | AK16: =I16 -> 4784 | AL16: =I16 -> 4784 | AO16: =I16 -> 4784 | AR16: =I16/13 -> 368 | BV16: =AT16+AU16+AY16 -> 0 | BW16: =BF16+BG16+BI16 -> 0 | BX16: =AK16+BX15 -> 133362 | BZ16: =$BZ$1-BX16 -> 286638
A17: 45884 | B17: WALMART INC. | C17: 美国 | D17: 4500177086 | E17: 0938210290 | F17: 4500177086-10 | G17: 77770GQ4-S001 | H17: 迷你包包S4 16pcs/箱 | I17: 960 | J17: 0 | K17: 16 | L17: =I17/K17 -> 60 | M17: 45922 | N17: 45918 | O17: 9/22预计安排抽板，2025/10/9第三方验货 | P17: PASS | Q17: 抽板订单的球上加贴布标贴纸 | R17: 45884 | S17: 无 | T17: 45902 | V17: 日期码格式：ZURU DGYYYYMMDD CHINA(日期避开周末和法定节假日即可） 日期：按实际生产日期 Packaging Info: 77770GQ4-S001 1. 包装要求： 77770：MA 1L A版收缩膜+MA 5L A版收藏指南+MA A版纸袋+客版 1L A版PDQ 需加贴布标贴纸 每pcs产品要贴一张RFID贴纸，RFID贴纸由ZURU提供，贴纸位置要严格按照客人签板 Remark: 77770GQ4-S001 1. 包装要求： 77770：MA 1L A版收缩膜+MA 5L A版收藏指南+MA A版纸袋+客版 1L A版PDQ 需加贴布标贴纸 每pcs产品要贴一张RFID贴纸，RFID贴纸由ZURU提供，贴纸位置要严格按照客人签板 2. 外箱印刷带条码的RFID箱唛：RFID紫色色带+WM Dept.图标+RFID图标+ITF-14条码，四面右下角印刷ZURU logo, ITFF条码只印刷在正唛一面，在加印的时候确保 条形码能扫描出来，外箱侧面任一角落加印："MADE IN CHINA" 字样； 3. 在产品上和包装上要有日期码、以及要有MADE IN CHINA和ZURU字样； 4. 产品如有扎带口要剪平，不能刮手。 5. 此单需要抽板和验货，抽板时间预计9/22，请多备料 6. 此单以loose carton出货，16pcs/PDQ/CTN | W17: Maggie Xie | X17: 1.596 | Y17: =X17*I17 -> 1532.16 | AA17: ZB02491-10.17 | AB17: 77770GQ4-S001 | AC17: 已入 | AD17: 系统出单 | AF17: 960 | AG17: =AF17-I17 -> 0 | AI17: OK | AK17: =I17 -> 960 | AL17: =I17 -> 960 | AO17: =I17 -> 960 | AY17: =I17/16 -> 60 | BV17: =AT17+AU17+AY17 -> 60 | BW17: =BF17+BG17+BI17 -> 0 | BX17: =AK17+BX16 -> 134322 | BZ17: =$BZ$1-BX17 -> 285678
A18: 45889 | B18: BRICKLAND LLC | C18: 蒙古 | D18: 4500177281 | E18: Zuru.2025Q3 | F18: 4500177281-80 | G18: 77770GQ1-S001 | H18: 迷你包包S4 | I18: 520 | J18: 0 | K18: 52 | L18: =I18/K18 -> 10 | M18: 45923 | N18: 45919 | P18: PASS | R18: 45891 | S18: 无 | T18: 45895 | V18: 日期码格式：ZURU INC(BVI) 标准格式 日期：按实际生产日期 Packaging Info: MA UPC包装(优先1L)+1张进口商贴纸,贴纸资料及位置图翻单如下 其他items待提供 Remark: | W18: Emma Wu | X18: 2.15 | Y18: =X18*I18 -> 1118 | AA18: 96896-2-11.8 | AB18: 77770GQ1-S001 | AC18: 已入 | AD18: 系统出单 | AF18: 520 | AG18: =AF18-I18 -> 0 | AI18: OK | AK18: =I18 -> 520 | AL18: =I18 -> 520 | AO18: =I18 -> 520 | AR18: =I18/13 -> 40 | BV18: =AT18+AU18+AY18 -> 0 | BW18: =BF18+BG18+BI18 -> 0 | BX18: =AK18+BX17 -> 134842 | BZ18: =$BZ$1-BX18 -> 285158
A19: 45889 | B19: PT. STAKOM TRIJAYA ANDALA | C19: 印度尼西亚 | D19: 4500177396 | E19: SS26 | F19: 4500177396-10 | G19: 77770GQ1-S001 | H19: 迷你包包S4 | I19: 520 | J19: 0 | K19: 52 | L19: =I19/K19 -> 10 | M19: 45923 | N19: 45919 | O19: 玩具订单一般都是第三方视频验货,实际不会有第三方的人到厂验货; 需按照客人要求提供2轮照片; 第一轮是产品包装/纸箱/堆码等情况下的照片; 第二轮是VO number打印出来,站在货物前的照片;待提供VO number,靠近货期才有; 照片标准待提供,做完货请帮忙同步提供照片; | P19: PASS | R19: 45895 | S19: 无 | T19: 无 | V19: 日期码格式：ZURU INC(BVI) 标准格式 日期：按实际生产日期 Packaging Info: 1.MA UPC(优先1L,所有包装仅需英文语言即可;) package, 无需任何贴纸; 2.可能会有测试样品需求,待确认被抽中的款, 请多备料; 3.玩具订单一般都是第三方视频验货,实际不会有第三方的人到厂验货; 需按照客人要求提供2轮照片; 第一轮是产品包装/纸箱/堆码等情况下的照片; 第二轮是VO number打印出来,站在货物前的照片;待提供VO number,靠近货期才有; 照片标准待提供,做完货请帮忙同步提供照片; Remark: | W19: Emma Wu | X19: 2.15 | Y19: =X19*I19 -> 1118 | AA19: A96792-10.31 | AB19: 77770GQ1-S001 | AC19: 已入 | AD19: 系统出单 | AF19: 520 | AG19: =AF19-I19 -> 0 | AI19: 无 | AK19: =I19 -> 520 | AL19: =I19 -> 520 | AO19: =I19 -> 520 | AR19: =I19/13 -> 40 | BV19: =AT19+AU19+AY19 -> 0 | BW19: =BF19+BG19+BI19 -> 0 | BX19: =AK19+BX18 -> 135362 | BZ19: =$BZ$1-BX19 -> 284638
A20: 45884 | D20: ZMPO250719 | G20: 77770GQ1-S001 | H20: 迷你包包S4 | I20: 390 | J20: 0 | K20: 52 | L20: =I20/K20 -> 7.5 | M20: 45909 | N20: 45905 | P20: PASS | R20: 周转箱 | S20: 无 | T20: 无 | V20: Remark：大货最新版本/产品按大货比例入PDQ/大货标准箱装箱/箱唛参照邮件附件；备注：收到样品订单后尽快安排 ，注意样板品质质量要求要高于大货品质要求 ，送货时必须要附带送货单(没有送货单和QC检验合格报告的仓库一律拒绝收货)，请知悉，谢谢！ | W20: Angus | AA20: 96835-10.31 | AB20: 77770GQ1-S001 | AC20: 已入 | AD20: 系统出单 | AF20: 390 | AG20: =AF20-I20 -> 0 | AK20: =I20 -> 390 | AL20: =I20 -> 390 | AO20: =I20 -> 390 | AR20: =I20/13 -> 30 | BV20: =AT20+AU20+AY20 -> 0 | BW20: =BF20+BG20+BI20 -> 0 | BX20: =AK20+BX19 -> 135752 | BZ20: =$BZ$1-BX20 -> 284248
A21: 45884 | D21: ZMPO250719 | G21: 77770GQ2-S001 | H21: 迷你包包S4 | I21: 1500 | J21: 0 | K21: 25 | L21: =I21/K21 -> 60 | M21: 45909 | N21: 45905 | P21: PASS | R21: 周转箱 | S21: 无 | T21: 无 | V21: Remark：大货最新版本/产品按大货比例入PDQ/大货标准箱装箱/箱唛参照邮件附件；备注：收到样品订单后尽快安排 ，注意样板品质质量要求要高于大货品质要求 ，送货时必须要附带送货单(没有送货单和QC检验合格报告的仓库一律拒绝收货)，请知悉，谢谢！ | W21: Angus | AA21: 96835-10.31 | AB21: 77770GQ2-S001 | AC21: 已入 | AD21: 系统出单 | AF21: 1500 | AG21: =AF21-I21 -> 0 | AK21: =I21 -> 1500 | AL21: =I21 -> 1500 | AO21: =I21 -> 1500 | AT21: =I21/K21 -> 60 | BV21: =AT21+AU21+AY21 -> 60 | BW21: =BF21+BG21+BI21 -> 0 | BX21: =AK21+BX20 -> 137252 | BZ21: =$BZ$1-BX21 -> 282748
A22: 45894 | B22: ZURU NEW ZEALAND LIMITED | C22: 新西兰 | D22: 4500179435 | E22: 5200007745 | F22: 77770GQ1-S 001-MTS | G22: 77770GQ1-S001 | H22: 迷你包包S4 | I22: 208 | J22: 0 | K22: 52 | L22: =I22/K22 -> 4 | M22: 45915 | N22: 45911 | P22: PASS | R22: 外箱除常规箱唛外，需要贴一张黄色A4贴纸，印“test order". | S22: 有 | T22: 更换试销订单专用UPC贴纸 | V22: Date code format：ZURU Standard format Date：Manufactory DateMA 1L UPC包装，每箱需要增加黄色A4贴纸，印“Test Order"字样，每个产品需要更换UPC贴纸，用试销专用的UPC条码 | W22: SD92 | AA22: A96791-10.31 | AB22: 77770GQ1-S001 | AC22: 已入 | AD22: 系统出单 | AF22: 208 | AG22: =AF22-I22 -> 0 | AI22: OK | AK22: =I22 -> 208 | AL22: =I22 -> 208 | AO22: =I22 -> 208 | AR22: =I22/13 -> 16 | BV22: =AT22+AU22+AY22 -> 0 | BW22: =BF22+BG22+BI22 -> 0 | BX22: =AK22+BX21 -> 137460 | BZ22: =$BZ$1-BX22 -> 282540
A23: 45868 | B23: ZURU GERMANY GMBH | C23: 德国 | D23: 4500175551 | E23: 5200007337 | F23: 4500175551-20 | G23: 77770GQ1-S002-MTS | H23: 迷你包包S4 13pcs/箱-MTS | I23: 3601 | J23: 0 | K23: 13 | L23: =I23/K23 -> 277 | M23: 45919 | N23: 45915 | P23: PASS | R23: 45868 | S23: 无 | T23: 45869 | V23: 日期码格式：ZURU INC(BVI) 标准格式 日期：按实际生产日期 Packaging Info: 2. 77770GQ1：MA 3L EAN收缩膜+1*多语折叠警语贴纸+MA 5L收藏指南+MA 纸袋+其他MA包装。 Remark: 1.德国内销单，需要通过ZURU 验货结果后才能出货 (工厂需要主动提前同ZURU QC预约验货避免延期出货造成不必要麻烦)； 2.产品如含有化学品（slime 等），需要无硼无香。需要无微塑料版本。 3.所有出口欧洲的产品, 法规规定禁止在包装和共公众用的印刷品中使用矿物油中含有的物质, 包装印刷油墨中含有的MOAH/MOSH的质量浓度不能超过1%, 否则出货 到法国被抽检出现问题, 供应商需要对此负责; 4. date code: 外箱日期码要晚于或等于产品日期码，不能早于产品的日期码； 5. 所有电子产品身上需要加字唛，为ZURU FRANCE 地址 (如无电子产品，或者产品布标有此地址，可忽略此信息) 如产品太小，也可忽略。如无法加字唛，可以用贴纸的形式加在产品身上。 ZURU France 1/3, Rue d'Argenteuil 95210 SAINT-GRATIEN, FRANCE 6.所有出往德国订单的电子产品需增加一张欧洲通用WEEE声明说明书，区分带电池和不带电池版本, 如已做客版说明书可忽略此要求。 7.装柜时需要按照款式号码从小到大一款款依次装,避免终端仓库卸货混乱.若一个柜子涉及到几个不同国家内销单,装柜时需要一个国家装完后再装另一个国家的 产品,依次装柜,避免终端仓库因不同国家不同库位位置卸货混乱. (此点需要同工厂装柜人员强调)" 8.ratio 同MA 9. 若有特定款有特殊外箱条码要求时,需要明确列出产品款对应的具体外箱条码号码/条码类型 (若无,可以忽略此需求). | W23: Bella Wang | X23: 2.39 | Y23: =I23*X23 -> 8606.39 | AA23: A96790-10.31 | AB23: 77770GQ1-S002-MTS | AC23: 已入 | AD23: 系统出单 | AF23: 3601 | AG23: =AF23-I23 -> 0 | AI23: OK | AK23: =I23 -> 3601 | AN23: =I23 -> 3601 | AO23: =I23 -> 3601 | AS23: =I23/13 -> 277 | BV23: =AT23+AU23+AY23 -> 0 | BW23: =BF23+BG23+BI23 -> 0 | BX23: =AK23+BX22 -> 141061 | BZ23: =$BZ$1-BX23 -> 278939
A24: 45894 | B24: WONDERLAND TOYS, INC. | C24: 美国 | D24: 4500177726 | E24: 4758 | F24: 4500177726-40 | G24: 77770GQ2-S001 | H24: 迷你包包S4 | I24: 700 | J24: 0 | K24: 50 | L24: =I24/K24 -> 14 | M24: 45930 | N24: 45926 | P24: PASS | R24: 45896 | S24: 无 | T24: 无 | V24: 日期码格式：ZURU INC(BVI) 标准格式 日期：按实际生产日期 Packaging Info: 1. 出口美国，MA UPC 版本包装，优先1L。 Remark: 2. Zuru QC 验货即可。 | W24: Abby Mai,Lluvia Zeng | X24: 1.41 | Y24: =X24*I24 -> 987 | AA24: ZB02466-10.16 | AB24: 77770GQ2-S001 | AC24: 已入 | AD24: 系统出单 | AF24: 700 | AG24: =AF24-I24 -> 0 | AI24: 无 | AK24: =I24 -> 700 | AL24: =I24 -> 700 | AO24: =I24 -> 700 | AT24: =L24*2 -> 28 | BV24: =AT24+AU24+AY24 -> 28 | BW24: =BF24+BG24+BI24 -> 0 | BX24: =AK24+BX23 -> 141761 | BZ24: =$BZ$1-BX24 -> 278239
A25: 45888 | B25: TARGET US | C25: 美国 | D25: 4500177334 | E25: 10001444618-3891 | F25: 4500177334-10 | G25: 77770GQ2-S002 | H25: 迷你包包S4 25pcs/箱 | I25: 21975 | J25: 0 | K25: 25 | L25: =I25/K25 -> 879 | M25: 45930 | N25: 45926 | P25: PASS | R25: 45891 | S25: 有 | T25: 45891 | V25: 日期码格式：ZURU INC(BVI) 标准格式 日期：按实际生产日期 Packaging Info: 77770GQ2: 产品包装(UPC 版) MA 1L收缩膜 +MA 1L PDQ； Remark: 77770GQ2: 1. 77770GQ2-S002-MINI BRANDS-FASHION MINI BRANDS-SERIES 4-CAPSULE,WITH DEMO,25PCS/Gravity PDQ,25PCS/PDQ/CTN 2. 产品包装(UPC 版) MA 1L收缩膜+MA 1L PDQ；收缩膜上的UPC显示193052089465； 3. 外箱正唛左上角位置粘贴条码箱贴纸，每箱只贴一张，由ZURU订购。来料贴纸上显示的客户DPCI# 086-02-9624, UPC显示10193052089462; 4. 外箱正唛信息右侧空白位置粘贴一张Event label贴纸，贴纸内容显示：Toys Set Date：1/11/2026；由工厂自己订购； 5. 产品和包装上印刷 tracking code信息，格式为ZURU常规格式; 6. 出货方式：货代自提 | W25: Holly Zheng | X25: 1.5848 | Y25: =I25*X25 -> 34825.98 | AA25: ZB02960-11.19 | AB25: 77770GQ2-S002 | AC25: 已入 | AD25: 系统出单 | AF25: 21975 | AG25: =AF25-I25 -> 0 | AI25: OK | AK25: =I25 -> 21975 | AL25: =I25 -> 21975 | AO25: =I25 -> 21975 | AT25: =I25/25 -> 879 | BV25: =AT25+AU25+AY25 -> 879 | BW25: =BF25+BG25+BI25 -> 0 | BX25: =AK25+BX24 -> 163736 | BZ25: =$BZ$1-BX25 -> 256264
A26: 45891 | B26: WALMART INC. | C26: 美国 | D26: 4500177643 | E26: 0938210281 | F26: 4500177643-10 | G26: 77770GQ4-S001 | H26: 迷你包包S4 16pcs/箱 | I26: 960 | J26: 0 | K26: 16 | L26: =I26/K26 -> 60 | M26: 45938 | N26: 45934 | O26: 45943 | P26: PASS | R26: 外箱印刷带条码的RFID箱唛：RFID紫色色带+WM Dept.图标+RFID图标+ITF-14条码，四面右下角印刷ZURU logo, ITFF条码只印刷在正唛一面，在加印的时候确保 条形码能扫描出来，外箱侧面任一角落加印："MADE IN CHINA" 字样； | S26: 无 | T26: 45902 | V26: 日期码格式：ZURU DGYYYYMMDD CHINA(日期避开周末和法定节假日即可） 日期：按实际生产日期 Packaging Info: 77770 1. 包装要求： 77770：MA 1L A版收缩膜+MA 5L A版收藏指南+MA A版纸袋+客版 1L A版PDQ，翻单：4500177086 每pcs产品要贴一张RFID贴纸，RFID贴纸由ZURU提供，贴纸位置要严格按照客人签板 Remark: 77770 1. 包装要求： 77770：MA 1L A版收缩膜+MA 5L A版收藏指南+MA A版纸袋+客版 1L A版PDQ，翻单：4500177086 每pcs产品要贴一张RFID贴纸，RFID贴纸由ZURU提供，贴纸位置要严格按照客人签板 2. 外箱印刷带条码的RFID箱唛：RFID紫色色带+WM Dept.图标+RFID图标+ITF-14条码，四面右下角印刷ZURU logo, ITFF条码只印刷在正唛一面，在加印的时候确保 条形码能扫描出来，外箱侧面任一角落加印："MADE IN CHINA" 字样； 3. 在产品上和包装上要有日期码、以及要有MADE IN CHINA和ZURU字样； 4. 产品如有扎带口要剪平，不能刮手。 5. 此单需要验货，请多备料 6. 此单以loose carton出货，16pcs/PDQ/CTN | W26: Maggie Xie | X26: 1.596 | Y26: =X26*I26 -> 1532.16 | AA26: ZB02551-10.22 | AB26: 77770GQ4-S001 | AC26: 已入 | AD26: 系统出单 | AF26: 960 | AG26: =AF26-I26 -> 0 | AK26: =I26 -> 960 | AL26: =I26 -> 960 | AO26: =I26 -> 960 | AY26: =I26/16 -> 60 | BV26: =AT26+AU26+AY26 -> 60 | BW26: =BF26+BG26+BI26 -> 0 | BX26: =AK26+BX25 -> 164696 | BZ26: =$BZ$1-BX26 -> 255304
A27: 45891 | B27: WALMART INC. | C27: 美国 | D27: 4500177643 | E27: 0938210340 | F27: 4500177643-20 | G27: 77770GQ4-S001 | H27: 迷你包包S4 16pcs/箱 | I27: 960 | J27: 0 | K27: 16 | L27: =I27/K27 -> 60 | M27: 45938 | N27: 45934 | O27: 45943 | P27: PASS | R27: 外箱印刷带条码的RFID箱唛：RFID紫色色带+WM Dept.图标+RFID图标+ITF-14条码，四面右下角印刷ZURU logo, ITFF条码只印刷在正唛一面，在加印的时候确保 条形码能扫描出来，外箱侧面任一角落加印："MADE IN CHINA" 字样； | S27: 无 | T27: 45902 | V27: 日期码格式：ZURU DGYYYYMMDD CHINA(日期避开周末和法定节假日即可） 日期：按实际生产日期 Packaging Info: 77770 1. 包装要求： 77770：MA 1L A版收缩膜+MA 5L A版收藏指南+MA A版纸袋+客版 1L A版PDQ，翻单：4500177086 每pcs产品要贴一张RFID贴纸，RFID贴纸由ZURU提供，贴纸位置要严格按照客人签板 Remark: 77770 1. 包装要求： 77770：MA 1L A版收缩膜+MA 5L A版收藏指南+MA A版纸袋+客版 1L A版PDQ，翻单：4500177086 每pcs产品要贴一张RFID贴纸，RFID贴纸由ZURU提供，贴纸位置要严格按照客人签板 2. 外箱印刷带条码的RFID箱唛：RFID紫色色带+WM Dept.图标+RFID图标+ITF-14条码，四面右下角印刷ZURU logo, ITFF条码只印刷在正唛一面，在加印的时候确保 条形码能扫描出来，外箱侧面任一角落加印："MADE IN CHINA" 字样； 3. 在产品上和包装上要有日期码、以及要有MADE IN CHINA和ZURU字样； 4. 产品如有扎带口要剪平，不能刮手。 5. 此单需要验货，请多备料 6. 此单以loose carton出货，16pcs/PDQ/CTN | W27: Maggie Xie | X27: 1.596 | Y27: =X27*I27 -> 1532.16 | AA27: ZB02602-10.24 | AB27: 77770GQ4-S001 | AC27: 已入 | AD27: 系统出单 | AF27: 960 | AG27: =AF27-I27 -> 0 | AK27: =I27 -> 960 | AL27: =I27 -> 960 | AO27: =I27 -> 960 | AY27: =I27/16 -> 60 | BV27: =AT27+AU27+AY27 -> 60 | BW27: =BF27+BG27+BI27 -> 0 | BX27: =AK27+BX26 -> 165656 | BZ27: =$BZ$1-BX27 -> 254344
A28: 45891 | B28: WALMART INC. | C28: 美国 | D28: 4500177643 | E28: 0938210382 | F28: 4500177643-30 | G28: 77770GQ4-S001 | H28: 迷你包包S4 16pcs/箱 | I28: 960 | J28: 0 | K28: 16 | L28: =I28/K28 -> 60 | M28: 45938 | N28: 45934 | O28: 45943 | P28: PASS | R28: 外箱印刷带条码的RFID箱唛：RFID紫色色带+WM Dept.图标+RFID图标+ITF-14条码，四面右下角印刷ZURU logo, ITFF条码只印刷在正唛一面，在加印的时候确保 条形码能扫描出来，外箱侧面任一角落加印："MADE IN CHINA" 字样； | S28: 无 | T28: 45902 | V28: 日期码格式：ZURU DGYYYYMMDD CHINA(日期避开周末和法定节假日即可） 日期：按实际生产日期 Packaging Info: 77770 1. 包装要求： 77770：MA 1L A版收缩膜+MA 5L A版收藏指南+MA A版纸袋+客版 1L A版PDQ，翻单：4500177086 每pcs产品要贴一张RFID贴纸，RFID贴纸由ZURU提供，贴纸位置要严格按照客人签板 Remark: 77770 1. 包装要求： 77770：MA 1L A版收缩膜+MA 5L A版收藏指南+MA A版纸袋+客版 1L A版PDQ，翻单：4500177086 每pcs产品要贴一张RFID贴纸，RFID贴纸由ZURU提供，贴纸位置要严格按照客人签板 2. 外箱印刷带条码的RFID箱唛：RFID紫色色带+WM Dept.图标+RFID图标+ITF-14条码，四面右下角印刷ZURU logo, ITFF条码只印刷在正唛一面，在加印的时候确保 条形码能扫描出来，外箱侧面任一角落加印："MADE IN CHINA" 字样； 3. 在产品上和包装上要有日期码、以及要有MADE IN CHINA和ZURU字样； 4. 产品如有扎带口要剪平，不能刮手。 5. 此单需要验货，请多备料 6. 此单以loose carton出货，16pcs/PDQ/CTN | W28: Maggie Xie | X28: 1.596 | Y28: =X28*I28 -> 1532.16 | AA28: ZB02603-10.24 | AB28: 77770GQ4-S001 | AC28: 已入 | AD28: 系统出单 | AF28: 960 | AG28: =AF28-I28 -> 0 | AK28: =I28 -> 960 | AL28: =I28 -> 960 | AO28: =I28 -> 960 | AY28: =I28/16 -> 60 | BV28: =AT28+AU28+AY28 -> 60 | BW28: =BF28+BG28+BI28 -> 0 | BX28: =AK28+BX27 -> 166616 | BZ28: =$BZ$1-BX28 -> 253384
A29: 45884 | B29: WALMART INC. | C29: 美国 | D29: 4500177088 | E29: 0936942375 | F29: 4500177088-10 | G29: 77770GQ4-S001 | H29: 迷你包包S4 16pcs/箱 | I29: 11296 | J29: 0 | K29: 16 | L29: =I29/K29 -> 706 | M29: 45938 | N29: 45934 | O29: 45943 | P29: PASS | R29: 45884 | S29: 无 | T29: 45902 | V29: 日期码格式：ZURU DGYYYYMMDD CHINA(日期避开周末和法定节假日即可） 日期：按实际生产日期 Packaging Info: 77770GQ4-S001 1. 包装要求： 77770：MA 1L A版收缩膜+MA 5L A版收藏指南+MA A版纸袋+客版 1L A版PDQ 每pcs产品要贴一张RFID贴纸，RFID贴纸由ZURU提供，贴纸位置要严格按照客人签板 Remark: 77770GQ4-S001 1. 包装要求： 77770：MA 1L A版收缩膜+MA 5L A版收藏指南+MA A版纸袋+客版 1L A版PDQ 每pcs产品要贴一张RFID贴纸，RFID贴纸由ZURU提供，贴纸位置要严格按照客人签板 2. 外箱印刷带条码的RFID箱唛：RFID紫色色带+WM Dept.图标+RFID图标+ITF-14条码+粉色艾利贴纸（不干胶打印），四面右下角印刷ZURU logo, ITFF条码只印刷在 正唛一面，在加印的时候确保条形码能扫描出来，1张粉红色贴纸贴在正唛对角线，外箱侧面任一角落加印："MADE IN CHINA" 字样； 3. 在产品上和包装上要有日期码、以及要有MADE IN CHINA和ZURU字样； 4. 产品如有扎带口要剪平，不能刮手。 5. 此单需要验货，请多备料 6. 此单以loose carton出货，16pcs/PDQ/CTN | W29: Maggie Xie | X29: 1.596 | Y29: =X29*I29 -> 18028.416 | AA29: ZB02693-10.29 | AB29: 77770GQ4-S001 | AC29: 已入 | AD29: 系统出单 | AF29: 11296 | AG29: =AF29-I29 -> 0 | AK29: =I29 -> 11296 | AL29: =I29 -> 11296 | AO29: =I29 -> 11296 | AY29: =I29/16 -> 706 | BV29: =AT29+AU29+AY29 -> 706 | BW29: =BF29+BG29+BI29 -> 0 | BX29: =AK29+BX28 -> 177912 | BZ29: =$BZ$1-BX29 -> 242088
A30: 45887 | B30: KMART AUSTRALIA LTD(NEW ZEALAND) | C30: 新西兰 | D30: 4500177240 | E30: 21105444 | F30: 4500177240-40 | G30: 77770GQ1-S002 | H30: 迷你包包S4 13pcs/箱 | I30: 117 | J30: 0 | K30: 13 | L30: =I30/K30 -> 9 | M30: 45939 | N30: 45936 | P30: PASS | R30: 45898 | S30: 有 | T30: 外箱SSCC Label (贴纸以及位置图翻单PO#4500173688） | V30: 日期码格式：ZURU INC(BVI) 标准格式 日期：按实际生产日期 Packaging Info: 77770GQ1:MA英语UPC版本包装（收缩膜和说明书, MA首选1L，如无1L可用多语且含英语的配套多语包装) + 1张防盗贴纸+箱唛 + 外箱SSCC Label (贴纸以及位置图翻单PO#4500173688） Remark: 1.请务必按时完货，验货。并且按期送货入货代指定仓库，如果晚了导致船期Delay将会有罚金产生或者客户要求空运，所产生的罚金和空运费由工厂承担。 2.SSCC 外箱贴纸请同纸箱瓦楞纸方向（竖纹向）垂直，即外箱贴纸横着贴(注意条码不要被胶带粘住），贴1pc，贴1面正唛，封箱胶纸不能挡住贴纸内容。外箱贴纸 离外箱边距离不少于2cm。 3.外箱材质为ZURU标准； 4.此单需使用KMART封箱胶上下工字型封箱;从2019年6月开始，要用KMART 新版封箱胶带，此单要用"ANKO"封箱胶带 5.此单出口新西兰，请按相应的澳新标准生产； 6.产品和包装上生产批号的显示格式ZURU标准日期码格式 7.外箱信息不可手写，重量和体积需要与实际的一致(不可手写） 8. 每款item装箱后的G.W.超过10KG或者CBM超过0.13,(9.5KG或者以上，四舍五入后也属于10KG) 需在外箱上加印超 重或者Bulky LOGO，若发现我们资料没有，请 帮忙提醒 1)重量超过10kg但不超过16kg且CBM不超过0.13,10-16kg 超重logo 2）CBM超过0.13且重量少于17kg，bulky logo 3）不属于以上两种情况，需要使用相应重量范围内的超重logo 4）超重logo需要在外箱四面都印刷(箱唛右上角，两面侧唛超重logo需要尽量靠近毛重)，尺寸为:110mm height* 95mm width 9. 实际外箱重量跟印在箱唛上的数据差异不能超3%，尺寸按实际数据印刷 | W30: Lydia Wu | X30: 2.4275 | Y30: =X30*I30 -> 284.0175 | AA30: 96626-10.10 | AB30: 77770GQ1-S002 | AC30: 已入 | AD30: 系统出单 | AF30: 117 | AG30: =AF30-I30 -> 0 | AK30: =I30 -> 117 | AL30: =I30 -> 117 | AO30: =I30 -> 117 | AR30: =I30/13 -> 9 | BV30: =AT30+AU30+AY30 -> 0 | BW30: =BF30+BG30+BI30 -> 0 | BX30: =AK30+BX29 -> 178029 | BZ30: =$BZ$1-BX30 -> 241971
A31: 45887 | B31: KMART AUSTRALIA LTD | C31: 澳大利亚 | D31: 4500177236 | E31: 21105443 | F31: 4500177236-40 | G31: 77770GQ1-S002 | H31: 迷你包包S4 13pcs/箱 | I31: 3900 | J31: 0 | K31: 13 | L31: =I31/K31 -> 300 | M31: 45939 | N31: 45936 | P31: PASS | R31: 45898 | S31: 有 | T31: 外箱SSCC Label (贴纸以及位置图翻单PO#4500173688） | V31: 日期码格式：ZURU INC(BVI) 标准格式 日期：按实际生产日期 Packaging Info: 77770GQ1:MA英语UPC版本包装（收缩膜和说明书, MA首选1L，如无1L可用多语且含英语的配套多语包装) + 1张防盗贴纸+箱唛 + 外箱SSCC Label (贴纸以及位置图翻单PO#4500173688） Remark: 1.请务必按时完货，验货。并且按期送货入货代指定仓库，如果晚了导致船期Delay将会有罚金产生或者客户要求空运，所产生的罚金和空运费由工厂承担。 2.SSCC 外箱贴纸请同纸箱瓦楞纸方向（竖纹向）垂直，即外箱贴纸横着贴(注意条码不要被胶带粘住），贴1pc，贴1面正唛，封箱胶纸不能挡住贴纸内容。外箱贴纸 离外箱边距离不少于2cm。 3.外箱材质为ZURU标准； 4.此单需使用KMART封箱胶上下工字型封箱;从2019年6月开始，要用KMART 新版封箱胶带，此单要用"ANKO"封箱胶带 5.此单出口澳大利亚，请按相应的澳新标准生产； 6.产品和包装上生产批号的显示格式ZURU标准日期码格式 7.外箱信息不可手写，重量和体积需要与实际的一致(不可手写） 8. 每款item装箱后的G.W.超过10KG或者CBM超过0.13,(9.5KG或者以上，四舍五入后也属于10KG) 需在外箱上加印超 重或者Bulky LOGO，若发现我们资料没有，请 帮忙提醒 1)重量超过10kg但不超过16kg且CBM不超过0.13,10-16kg 超重logo 2）CBM超过0.13且重量少于17kg，bulky logo 3）不属于以上两种情况，需要使用相应重量范围内的超重logo 4）超重logo需要在外箱四面都印刷(箱唛右上角，两面侧唛超重logo需要尽量靠近毛重)，尺寸为:110mm height* 95mm width 9. 实际外箱重量跟印在箱唛上的数据差异不能超3%，尺寸按实际数据印刷 | W31: Lydia Wu | X31: 2.4275 | Y31: =X31*I31 -> 9467.25 | AA31: 96625-10.10 | AB31: 77770GQ1-S002 | AC31: 已入 | AD31: 系统出单 | AF31: 3900 | AG31: =AF31-I31 -> 0 | AK31: =I31 -> 3900 | AL31: =I31 -> 3900 | AO31: =I31 -> 3900 | AR31: =I31/13 -> 300 | BV31: =AT31+AU31+AY31 -> 0 | BW31: =BF31+BG31+BI31 -> 0 | BX31: =AK31+BX30 -> 181929 | BZ31: =$BZ$1-BX31 -> 238071
A32: 45896 | B32: KMART AUSTRALIA LTD(NEW ZEALAND) | C32: 新西兰 | D32: 4500177974 | E32: 21105440 | F32: 4500177974-80 | G32: 77770GQ1-S002 | H32: 迷你包包S4 13pcs/箱 | I32: 143 | J32: 0 | K32: 13 | L32: =I32/K32 -> 11 | M32: 45943 | N32: 45939 | P32: PASS | R32: 45911 | S32: 有 | T32: 45923 | V32: 日期码格式：ZURU INC(BVI) 标准格式 日期：按实际生产日期 Packaging Info: 77770GQ1:MA英语UPC版本包装（收缩膜和说明书, MA首选1L，如无1L可用多语且含英语的配套多语包装) + 1张防盗贴纸+箱唛 + 外箱SSCC Label (贴纸以及位置图翻单PO#4500173688） Remark: 1.请务必按时完货，验货。并且按期送货入货代指定仓库，如果晚了导致船期Delay将会有罚金产生或者客户要求空运，所产生的罚金和空运费由工厂承担。 2.SSCC 外箱贴纸请同纸箱瓦楞纸方向（竖纹向）垂直，即外箱贴纸横着贴(注意条码不要被胶带粘住），贴1pc，贴1面正唛，封箱胶纸不能挡住贴纸内容。外箱贴纸 离外箱边距离不少于2cm。 3.外箱材质为ZURU标准； 4.此单需使用KMART封箱胶上下工字型封箱;从2019年6月开始，要用KMART 新版封箱胶带，此单要用"ANKO"封箱胶带 5.此单出口新西兰，请按相应的澳新标准生产； 6.产品和包装上生产批号的显示格式ZURU标准日期码格式 7.外箱信息不可手写，重量和体积需要与实际的一致(不可手写） 8. 每款item装箱后的G.W.超过10KG或者CBM超过0.13,(9.5KG或者以上，四舍五入后也属于10KG) 需在外箱上加印超 重或者Bulky LOGO，若发现我们资料没有，请 帮忙提醒 1)重量超过10kg但不超过16kg且CBM不超过0.13,10-16kg 超重logo 2）CBM超过0.13且重量少于17kg，bulky logo 3）不属于以上两种情况，需要使用相应重量范围内的超重logo 4）超重logo需要在外箱四面都印刷(箱唛右上角，两面侧唛超重logo需要尽量靠近毛重)，尺寸为:110mm height* 95mm width 9. 实际外箱重量跟印在箱唛上的数据差异不能超3%，尺寸按实际数据印刷 | W32: Lydia Wu | X32: 2.4275 | Y32: =X32*I32 -> 347.1325 | AA32: 96681-2-10.17 | AB32: 77770GQ1-S002 | AC32: 已入 | AD32: 系统出单 | AF32: 143 | AG32: =AF32-I32 -> 0 | AK32: =I32 -> 143 | AL32: =I32 -> 143 | AO32: =I32 -> 143 | AR32: =I32/13 -> 11 | BV32: =AT32+AU32+AY32 -> 0 | BW32: =BF32+BG32+BI32 -> 0 | BX32: =AK32+BX31 -> 182072 | BZ32: =$BZ$1-BX32 -> 237928
A33: 45896 | B33: KMART AUSTRALIA LTD | C33: 澳大利亚 | D33: 4500177972 | E33: 21105437 | F33: 4500177972-80 | G33: 77770GQ1-S002 | H33: 迷你包包S4 13pcs/箱 | I33: 2223 | J33: 0 | K33: 13 | L33: =I33/K33 -> 171 | M33: 45943 | N33: 45939 | P33: PASS | R33: 45896 | S33: 有 | T33: 45912 | V33: 日期码格式：ZURU INC(BVI) 标准格式 日期：按实际生产日期 Packaging Info: 77770GQ1:MA英语UPC版本包装（收缩膜和说明书, MA首选1L，如无1L可用多语且含英语的配套多语包装) + 1张防盗贴纸+箱唛 + 外箱SSCC Label (贴纸以及位置图翻单PO#4500173688） Remark: 1.请务必按时完货，验货。并且按期送货入货代指定仓库，如果晚了导致船期Delay将会有罚金产生或者客户要求空运，所产生的罚金和空运费由工厂承担。 2.SSCC 外箱贴纸请同纸箱瓦楞纸方向（竖纹向）垂直，即外箱贴纸横着贴(注意条码不要被胶带粘住），贴1pc，贴1面正唛，封箱胶纸不能挡住贴纸内容。外箱贴纸 离外箱边距离不少于2cm。 3.外箱材质为ZURU标准； 4.此单需使用KMART封箱胶上下工字型封箱;从2019年6月开始，要用KMART 新版封箱胶带，此单要用"ANKO"封箱胶带 5.此单出口澳大利亚，请按相应的澳新标准生产； 6.产品和包装上生产批号的显示格式ZURU标准日期码格式 7.外箱信息不可手写，重量和体积需要与实际的一致(不可手写） 8. 每款item装箱后的G.W.超过10KG或者CBM超过0.13,(9.5KG或者以上，四舍五入后也属于10KG) 需在外箱上加印超 重或者Bulky LOGO，若发现我们资料没有，请 帮忙提醒 1)重量超过10kg但不超过16kg且CBM不超过0.13,10-16kg 超重logo 2）CBM超过0.13且重量少于17kg，bulky logo 3）不属于以上两种情况，需要使用相应重量范围内的超重logo 4）超重logo需要在外箱四面都印刷(箱唛右上角，两面侧唛超重logo需要尽量靠近毛重)，尺寸为:110mm height* 95mm width 9. 实际外箱重量跟印在箱唛上的数据差异不能超3%，尺寸按实际数据印刷 | W33: Lydia Wu | X33: 2.4275 | Y33: =X33*I33 -> 5396.3325 | AA33: 96680-2-10.17 | AB33: 77770GQ1-S002 | AC33: 已入 | AD33: 系统出单 | AF33: 2223 | AG33: =AF33-I33 -> 0 | AH33: 45938 | AK33: =I33 -> 2223 | AL33: =I33 -> 2223 | AO33: =I33 -> 2223 | AR33: =I33/13 -> 171 | BV33: =AT33+AU33+AY33 -> 0 | BW33: =BF33+BG33+BI33 -> 0 | BX33: =AK33+BX32 -> 184295 | BZ33: =$BZ$1-BX33 -> 235705
A34: 45884 | B34: WALMART INC. | C34: 美国 | D34: 4500177091 | E34: 0936942331 | F34: 4500177091-10 | G34: 77770GQ4-S001 | H34: 迷你包包S4 16pcs/箱 | I34: 13728 | J34: 0 | K34: 16 | L34: =I34/K34 -> 858 | M34: 45943 | N34: 45939 | O34: 45946 | P34: PASS | R34: 45884 | S34: 无 | T34: 45902 | V34: 日期码格式：ZURU DGYYYYMMDD CHINA(日期避开周末和法定节假日即可） 日期：按实际生产日期 Packaging Info: 77770GQ4-S001 1. 包装要求： 77770：MA 1L A版收缩膜+MA 5L A版收藏指南+MA A版纸袋+客版 1L A版PDQ 每pcs产品要贴一张RFID贴纸，RFID贴纸由ZURU提供，贴纸位置要严格按照客人签板 Remark: 77770GQ4-S001 1. 包装要求： 77770：MA 1L A版收缩膜+MA 5L A版收藏指南+MA A版纸袋+客版 1L A版PDQ 每pcs产品要贴一张RFID贴纸，RFID贴纸由ZURU提供，贴纸位置要严格按照客人签板 2. 外箱印刷带条码的RFID箱唛：RFID紫色色带+WM Dept.图标+RFID图标+ITF-14条码+粉色艾利贴纸（不干胶打印），四面右下角印刷ZURU logo, ITFF条码只印刷在 正唛一面，在加印的时候确保条形码能扫描出来，1张粉红色贴纸贴在正唛对角线，外箱侧面任一角落加印："MADE IN CHINA" 字样； 3. 在产品上和包装上要有日期码、以及要有MADE IN CHINA和ZURU字样； 4. 产品如有扎带口要剪平，不能刮手。 5. 此单需要验货，请多备料 6. 此单以loose carton出货，16pcs/PDQ/CTN | W34: Maggie Xie | X34: 1.596 | Y34: =X34*I34 -> 21909.888 | AA34: ZB02807-11.4 | AB34: 77770GQ4-S001 | AC34: 已入 | AD34: 系统出单 | AF34: =13056+672 -> 13728 | AG34: =AF34-I34 -> 0 | AH34: 45944 | AK34: =I34 -> 13728 | AL34: =I34 -> 13728 | AO34: =I34 -> 13728 | AY34: =I34/16 -> 858 | BV34: =AT34+AU34+AY34 -> 858 | BW34: =BF34+BG34+BI34 -> 0 | BX34: =AK34+BX33 -> 198023 | BZ34: =$BZ$1-BX34 -> 221977
A35: 45884 | B35: WALMART INC. | C35: 美国 | D35: 4500177091 | E35: 0936942359 | F35: 4500177091-20 | G35: 77770GQ4-S001 | H35: 迷你包包S4 16pcs/箱 | I35: 14368 | J35: 0 | K35: 16 | L35: =I35/K35 -> 898 | M35: 45943 | N35: 45939 | O35: 45946 | P35: PASS | R35: 45884 | S35: 无 | T35: 45902 | V35: 日期码格式：ZURU DGYYYYMMDD CHINA(日期避开周末和法定节假日即可） 日期：按实际生产日期 Packaging Info: 77770GQ4-S001 1. 包装要求： 77770：MA 1L A版收缩膜+MA 5L A版收藏指南+MA A版纸袋+客版 1L A版PDQ 每pcs产品要贴一张RFID贴纸，RFID贴纸由ZURU提供，贴纸位置要严格按照客人签板 Remark: 77770GQ4-S001 1. 包装要求： 77770：MA 1L A版收缩膜+MA 5L A版收藏指南+MA A版纸袋+客版 1L A版PDQ 每pcs产品要贴一张RFID贴纸，RFID贴纸由ZURU提供，贴纸位置要严格按照客人签板 2. 外箱印刷带条码的RFID箱唛：RFID紫色色带+WM Dept.图标+RFID图标+ITF-14条码+粉色艾利贴纸（不干胶打印），四面右下角印刷ZURU logo, ITFF条码只印刷在 正唛一面，在加印的时候确保条形码能扫描出来，1张粉红色贴纸贴在正唛对角线，外箱侧面任一角落加印："MADE IN CHINA" 字样； 3. 在产品上和包装上要有日期码、以及要有MADE IN CHINA和ZURU字样； 4. 产品如有扎带口要剪平，不能刮手。 5. 此单需要验货，请多备料 6. 此单以loose carton出货，16pcs/PDQ/CTN | W35: Maggie Xie | X35: 1.596 | Y35: =X35*I35 -> 22931.328 | AA35: ZB02806-11.4 | AB35: 77770GQ4-S001 | AC35: 已入 | AD35: 系统出单 | AF35: =8160+6208 -> 14368 | AG35: =AF35-I35 -> 0 | AH35: 45944 | AK35: =I35 -> 14368 | AL35: =I35 -> 14368 | AO35: =I35 -> 14368 | AY35: =I35/16 -> 898 | BV35: =AT35+AU35+AY35 -> 898 | BW35: =BF35+BG35+BI35 -> 0 | BX35: =AK35+BX34 -> 212391 | BZ35: =$BZ$1-BX35 -> 207609
A36: 45891 | B36: WALMART INC. | C36: 美国 | D36: 4500177644 | E36: 0938210337 | F36: 4500177644-10 | G36: 77770GQ4-S001 | H36: 迷你包包S4 16pcs/箱 | I36: 960 | J36: 0 | K36: 16 | L36: =I36/K36 -> 60 | M36: 45943 | N36: 45939 | O36: 45946 | P36: PASS | R36: 外箱印刷带条码的RFID箱唛：RFID紫色色带+WM Dept.图标+RFID图标+ITF-14条码，四面右下角印刷ZURU logo, ITFF条码只印刷在正唛一面，在加印的时候确保 条形码能扫描出来，外箱侧面任一角落加印："MADE IN CHINA" 字样； | S36: 无 | T36: 45902 | V36: 日期码格式：ZURU DGYYYYMMDD CHINA(日期避开周末和法定节假日即可） 日期：按实际生产日期 Packaging Info: 77770 1. 包装要求： 77770：MA 1L A版收缩膜+MA 5L A版收藏指南+MA A版纸袋+客版 1L A版PDQ，翻单：4500177086 每pcs产品要贴一张RFID贴纸，RFID贴纸由ZURU提供，贴纸位置要严格按照客人签板 Remark: 77770 1. 包装要求： 77770：MA 1L A版收缩膜+MA 5L A版收藏指南+MA A版纸袋+客版 1L A版PDQ，翻单：4500177086 每pcs产品要贴一张RFID贴纸，RFID贴纸由ZURU提供，贴纸位置要严格按照客人签板 2. 外箱印刷带条码的RFID箱唛：RFID紫色色带+WM Dept.图标+RFID图标+ITF-14条码，四面右下角印刷ZURU logo, ITFF条码只印刷在正唛一面，在加印的时候确保 条形码能扫描出来，外箱侧面任一角落加印："MADE IN CHINA" 字样； 3. 在产品上和包装上要有日期码、以及要有MADE IN CHINA和ZURU字样； 4. 产品如有扎带口要剪平，不能刮手。 5. 此单需要验货，请多备料 6. 此单以loose carton出货，16pcs/PDQ/CTN | W36: Maggie Xie | X36: 1.596 | Y36: =X36*I36 -> 1532.16 | AA36: ZB02963-11.19 | AB36: 77770GQ4-S001 | AC36: 已入 | AD36: 系统出单 | AF36: 960 | AG36: =AF36-I36 -> 0 | AH36: 45944 | AK36: =I36 -> 960 | AL36: =I36 -> 960 | AO36: =I36 -> 960 | AY36: =I36/16 -> 60 | BV36: =AT36+AU36+AY36 -> 60 | BW36: =BF36+BG36+BI36 -> 0 | BX36: =AK36+BX35 -> 213351 | BZ36: =$BZ$1-BX36 -> 206649
A37: 45898 | B37: ALL BRANDS TOYS PTY LTD | C37: 澳大利亚 | D37: 4500178243 | E37: 84521 | F37: 4500178243-10 | G37: 77770GQ2-S002 | H37: 迷你包包S4 25pcs/箱 | I37: 2500 | J37: 0 | K37: 25 | L37: =I37/K37 -> 100 | M37: 45944 | N37: 45940 | P37: PASS | Q37: 10/18送库有拼柜 | R37: 45898 | S37: 无 | T37: 1张客人通用进口商贴纸(翻单4500175512） | V37: 日期码格式：ZURU INC(BVI) 标准格式 日期：按实际生产日期 Packaging Info: 77770GQ2: MA 1L PKG +1张客人通用进口商贴纸(翻单4500175512） Remark: 1.按实际生产日期; 2.出澳大利亚，请按照相应标准生产; | W37: Doris Shou | X37: 2.66 | Y37: =I37*X37 -> 6650 | AA37: 96676-10.17 | AB37: 77770GQ2-S002 | AC37: 已入 | AD37: 系统出单 | AF37: 2500 | AG37: =AF37-I37 -> 0 | AH37: 45947 | AI37: OK | AK37: =I37 -> 2500 | AL37: =I37 -> 2500 | AO37: =I37 -> 2500 | AT37: =I37/25 -> 100 | BV37: =AT37+AU37+AY37 -> 100 | BW37: =BF37+BG37+BI37 -> 0 | BX37: =AK37+BX36 -> 215851 | BZ37: =$BZ$1-BX37 -> 204149
A38: 45888 | B38: TARGET US | C38: 美国 | D38: 4500177333 | E38: 10001444616-3890 | F38: 4500177333-10 | G38: 77770GQ2-S002 | H38: 迷你包包S4 25pcs/箱 | I38: 30275 | J38: 0 | K38: 25 | L38: =I38/K38 -> 1211 | M38: 45940 | N38: 45938 | P38: PASS | Q38: 10/20客上柜 | R38: 45891 | S38: 有 | T38: 45891 | V38: 日期码格式：ZURU INC(BVI) 标准格式 日期：按实际生产日期 Packaging Info: 77770GQ2: 产品包装(UPC 版) MA 1L收缩膜 +MA 1L PDQ； Remark: 77770GQ2: 1. 77770GQ2-S002-MINI BRANDS-FASHION MINI BRANDS-SERIES 4-CAPSULE,WITH DEMO,25PCS/Gravity PDQ,25PCS/PDQ/CTN 2. 产品包装(UPC 版) MA 1L收缩膜+MA 1L PDQ；收缩膜上的UPC显示193052089465； 3. 外箱正唛左上角位置粘贴条码箱贴纸，每箱只贴一张，由ZURU订购。来料贴纸上显示的客户DPCI# 086-02-9624, UPC显示10193052089462; 4. 外箱正唛信息右侧空白位置粘贴一张Event label贴纸，贴纸内容显示：Toys Set Date：1/11/2026；由工厂自己订购； 5. 产品和包装上印刷 tracking code信息，格式为ZURU常规格式; 6. 出货方式：货代自提 | W38: Holly Zheng | X38: 1.5848 | Y38: =I38*X38 -> 47979.82 | AA38: ZB02961-11.19 | AB38: 77770GQ2-S002 | AC38: 已入 | AD38: 系统出单 | AF38: =22500+7775 -> 30275 | AG38: =AF38-I38 -> 0 | AH38: 45943 | AK38: =I38 -> 30275 | AL38: =I38 -> 30275 | AO38: =I38 -> 30275 | AT38: =I38/25 -> 1211 | BV38: =AT38+AU38+AY38 -> 1211 | BW38: =BF38+BG38+BI38 -> 0 | BX38: =AK38+BX37 -> 246126 | BZ38: =$BZ$1-BX38 -> 173874
A39: 45896 | B39: TARGET US | C39: 美国 | D39: 4500177938 | E39: 10001493622-3891 | F39: 4500177938-20 | G39: 77770GQ2-S002 | H39: 迷你包包S4 25pcs/箱 | I39: 21600 | J39: 0 | K39: 25 | L39: =I39/K39 -> 864 | M39: 45943 | N39: 45939 | P39: PASS | Q39: 10/22预提货 | R39: 45904 | S39: 有 | T39: 45916 | V39: 日期码格式：ZURU INC(BVI) 标准格式 日期：按实际生产日期 Packaging Info: 77770GQ2 产品包装(UPC 版) MA 1L收缩膜+MA 1L PDQ； Remark: 77770GQ2 1. 77770GQ2-S002-MINI BRANDS-FASHION MINI BRANDS-SERIES 4-CAPSULE,WITH DEMO,25PCS/Gravity PDQ,25PCS/PDQ/CTN 2. 产品包装(UPC 版) MA 1L收缩膜+MA 1L PDQ；收缩膜上的UPC显示193052089465； 3. 外箱正唛左上角位置粘贴条码箱贴纸，每箱只贴一张，由ZURU订购。来料贴纸上显示的客户DPCI# 086-02-9624, UPC显示10193052089462; 以上所以item均： 1. 产品和包装上均要印刷tracking code信息，格式为ZURU常规格式; 2. 出货方式：货代自提 | W39: Holly Zheng | X39: 1.5848 | Y39: =I39*X39 -> 34231.68 | AA39: ZB02562-10.23 zb02957-11.19 | AB39: 77770GQ2-S002 | AC39: 已入 | AD39: 系统出单 | AF39: =6750+14850 -> 21600 | AG39: =AF39-I39 -> 0 | AH39: 45945 | AI39: OK | AK39: =I39 -> 21600 | AL39: =I39 -> 21600 | AO39: =I39 -> 21600 | AT39: =I39/25 -> 864 | BV39: =AT39+AU39+AY39 -> 864 | BW39: =BF39+BG39+BI39 -> 0 | BX39: =AK39+BX38 -> 267726 | BZ39: =$BZ$1-BX39 -> 152274
A40: 45905 | B40: KMART AUSTRALIA LTD(NEW ZEALAND) | C40: 新西兰 | D40: 4500178926 | E40: 21105441 | F40: 4500178926-40 | G40: 77770GQ1-S002 | H40: 迷你包包S4 13pcs/箱 | I40: 169 | J40: 0 | K40: 13 | L40: =I40/K40 -> 13 | M40: 45946 | N40: 45943 | P40: PASS | Q40: 10/22-24交仓 | R40: 45905 | S40: 有 | T40: 外箱SSCC Label (贴纸以及位置图翻单PO#4500173688） | V40: 日期码格式：ZURU INC(BVI) 标准格式 日期：按实际生产日期 Packaging Info: 77770GQ1:MA英语UPC版本包装（收缩膜和说明书, MA首选1L，如无1L可用多语且含英语的配套多语包装) + 1张防盗贴纸+箱唛 + 外箱SSCC Label (贴纸以及位置图翻单PO#4500173688） Remark: 1.请务必按时完货，验货。并且按期送货入货代指定仓库，如果晚了导致船期Delay将会有罚金产生或者客户要求空运，所产生的罚金和空运费由工厂承担。 2.SSCC 外箱贴纸请同纸箱瓦楞纸方向（竖纹向）垂直，即外箱贴纸横着贴(注意条码不要被胶带粘住），贴1pc，贴1面正唛，封箱胶纸不能挡住贴纸内容。外箱贴纸 离外箱边距离不少于2cm。 3.外箱材质为ZURU标准； 4.此单需使用KMART封箱胶上下工字型封箱;从2019年6月开始，要用KMART 新版封箱胶带，此单要用"ANKO"封箱胶带 5.此单出口新西兰，请按相应的澳新标准生产； 6.产品和包装上生产批号的显示格式ZURU标准日期码格式 7.外箱信息不可手写，重量和体积需要与实际的一致(不可手写） 8. 每款item装箱后的G.W.超过10KG或者CBM超过0.13,(9.5KG或者以上，四舍五入后也属于10KG) 需在外箱上加印超 重或者Bulky LOGO，若发现我们资料没有，请 帮忙提醒 1)重量超过10kg但不超过16kg且CBM不超过0.13,10-16kg 超重logo 2）CBM超过0.13且重量少于17kg，bulky logo 3）不属于以上两种情况，需要使用相应重量范围内的超重logo 4）超重logo需要在外箱四面都印刷(箱唛右上角，两面侧唛超重logo需要尽量靠近毛重)，尺寸为:110mm height* 95mm width 9. 实际外箱重量跟印在箱唛上的数据差异不能超3%，尺寸按实际数据印刷 | W40: Lydia Wu | X40: 2.4275 | Y40: =X40*I40 -> 410.2475 | AA40: 96678-10.17 | AB40: 77770GQ1-S002 | AC40: 已入 | AD40: 系统出单 | AF40: 169 | AG40: =AF40-I40 -> 0 | AH40: 欠11号鞋子 | AK40: =I40 -> 169 | AL40: =I40 -> 169 | AO40: =I40 -> 169 | AR40: =I40/13 -> 13 | BV40: =AT40+AU40+AY40 -> 0 | BW40: =BF40+BG40+BI40 -> 0 | BX40: =AK40+BX39 -> 267895 | BZ40: =$BZ$1-BX40 -> 152105
A41: 45902 | B41: TARGET US | C41: 美国 | D41: 4500178501 | E41: 10001502358-3891 | F41: 4500178501-20 | G41: 77770GQ2-S002 | H41: 迷你包包S4 25pcs/箱 | I41: 59150 | J41: 0 | K41: 25 | L41: =I41/K41 -> 2366 | M41: 45947 | N41: 45945 | P41: PASS | Q41: 10/21客上柜 | R41: 45909 | S41: 粘贴条码箱贴纸，每箱只贴一张，由ZURU订购 | T41: 45919 | V41: 日期码格式：ZURU INC(BVI) 标准格式 日期：按实际生产日期 Packaging Info: 77770GQ2: 产品包装(UPC 版) MA 1L收缩膜 +MA 1L PDQ； Remark: 77770GQ2: 1. 77770GQ2-S002-MINI BRANDS-FASHION MINI BRANDS-SERIES 4-CAPSULE,WITH DEMO,25PCS/Gravity PDQ,25PCS/PDQ/CTN 2. 产品包装(UPC 版) MA 1L收缩膜+MA 1L PDQ；收缩膜上的UPC显示193052089465； 3. 外箱正唛左上角位置粘贴条码箱贴纸，每箱只贴一张，由ZURU订购。来料贴纸上显示的客户DPCI# 086-02-9624, UPC显示10193052089462; 4. 产品和包装上印刷 tracking code信息，格式为ZURU常规格式; 5. 出货方式：货代自提 | W41: Holly Zheng | X41: 1.5848 | Y41: =I41*X41 -> 93740.92 | AA41: ZB02537-10.21 | AB41: 77770GQ2-S002 | AC41: 已入 | AD41: 系统出单 | AF41: =13500+45650 -> 59150 | AG41: =AF41-I41 -> 0 | AI41: OK | AK41: =I41 -> 59150 | AL41: =I41 -> 59150 | AO41: =I41 -> 59150 | AT41: =I41/25 -> 2366 | BV41: =AT41+AU41+AY41 -> 2366 | BW41: =BF41+BG41+BI41 -> 0 | BX41: =AK41+BX40 -> 327045 | BZ41: =$BZ$1-BX41 -> 92955
A42: 45905 | B42: KMART AUSTRALIA LTD | C42: 澳大利亚 | D42: 4500178925 | E42: 21105438 | F42: 4500178925-40 | G42: 77770GQ1-S002 | H42: 迷你包包S4 13pcs/箱 | I42: 4550 | J42: 0 | K42: 13 | L42: =I42/K42 -> 350 | M42: 45946 | N42: 45943 | P42: PASS | Q42: 10/22-24交仓 | R42: 45905 | S42: 有 | T42: 外箱SSCC Label (贴纸以及位置图翻单PO#4500173688） | V42: 日期码格式：ZURU INC(BVI) 标准格式 日期：按实际生产日期 Packaging Info: 77770GQ1:MA英语UPC版本包装（收缩膜和说明书, MA首选1L，如无1L可用多语且含英语的配套多语包装) + 1张防盗贴纸+箱唛 + 外箱SSCC Label (贴纸以及位置图翻单PO#4500173688） Remark: 1.请务必按时完货，验货。并且按期送货入货代指定仓库，如果晚了导致船期Delay将会有罚金产生或者客户要求空运，所产生的罚金和空运费由工厂承担。 2.SSCC 外箱贴纸请同纸箱瓦楞纸方向（竖纹向）垂直，即外箱贴纸横着贴(注意条码不要被胶带粘住），贴1pc，贴1面正唛，封箱胶纸不能挡住贴纸内容。外箱贴纸 离外箱边距离不少于2cm。 3.外箱材质为ZURU标准； 4.此单需使用KMART封箱胶上下工字型封箱;从2019年6月开始，要用KMART 新版封箱胶带，此单要用"ANKO"封箱胶带 5.此单出口澳大利亚，请按相应的澳新标准生产； 6.产品和包装上生产批号的显示格式ZURU标准日期码格式 7.外箱信息不可手写，重量和体积需要与实际的一致(不可手写） 8. 每款item装箱后的G.W.超过10KG或者CBM超过0.13,(9.5KG或者以上，四舍五入后也属于10KG) 需在外箱上加印超 重或者Bulky LOGO，若发现我们资料没有，请 帮忙提醒 1)重量超过10kg但不超过16kg且CBM不超过0.13,10-16kg 超重logo 2）CBM超过0.13且重量少于17kg，bulky logo 3）不属于以上两种情况，需要使用相应重量范围内的超重logo 4）超重logo需要在外箱四面都印刷(箱唛右上角，两面侧唛超重logo需要尽量靠近毛重)，尺寸为:110mm height* 95mm width 9. 实际外箱重量跟印在箱唛上的数据差异不能超3%，尺寸按实际数据印刷 | W42: Lydia Wu | X42: 2.4275 | Y42: =X42*I42 -> 11045.125 | AA42: 96677-10.17 | AB42: 77770GQ1-S002 | AC42: 已入 | AD42: 系统出单 | AF42: 4550 | AG42: =AF42-I42 -> 0 | AH42: 欠11号鞋子 | AK42: =I42 -> 4550 | AL42: =I42 -> 4550 | AO42: =I42 -> 4550 | AR42: =I42/13 -> 350 | BV42: =AT42+AU42+AY42 -> 0 | BW42: =BF42+BG42+BI42 -> 0 | BX42: =AK42+BX41 -> 331595 | BZ42: =$BZ$1-BX42 -> 88405
A43: 45884 | B43: WALMART INC. | C43: 美国 | D43: 4500177093 | E43: 0936942305 | F43: 4500177093-10 | G43: 77770GQ4-S001 | H43: 迷你包包S4 16pcs/箱 | I43: 16544 | J43: 0 | K43: 16 | L43: =I43/K43 -> 1034 | M43: 45946 | N43: 45943 | O43: BV验货转自检10/24 | P43: PASS | R43: 45884 | S43: 无 | T43: 45902 | V43: 日期码格式：ZURU DGYYYYMMDD CHINA(日期避开周末和法定节假日即可） 日期：按实际生产日期 Packaging Info: 77770GQ4-S001 1. 包装要求： 77770：MA 1L A版收缩膜+MA 5L A版收藏指南+MA A版纸袋+客版 1L A版PDQ 每pcs产品要贴一张RFID贴纸，RFID贴纸由ZURU提供，贴纸位置要严格按照客人签板 Remark: 77770GQ4-S001 1. 包装要求： 77770：MA 1L A版收缩膜+MA 5L A版收藏指南+MA A版纸袋+客版 1L A版PDQ 每pcs产品要贴一张RFID贴纸，RFID贴纸由ZURU提供，贴纸位置要严格按照客人签板 2. 外箱印刷带条码的RFID箱唛：RFID紫色色带+WM Dept.图标+RFID图标+ITF-14条码+粉色艾利贴纸（不干胶打印），四面右下角印刷ZURU logo, ITFF条码只印刷在 正唛一面，在加印的时候确保条形码能扫描出来，1张粉红色贴纸贴在正唛对角线，外箱侧面任一角落加印："MADE IN CHINA" 字样； 3. 在产品上和包装上要有日期码、以及要有MADE IN CHINA和ZURU字样； 4. 产品如有扎带口要剪平，不能刮手。 5. 此单需要验货，请多备料 6. 此单以loose carton出货，16pcs/PDQ/CTN | W43: Maggie Xie | X43: 1.596 | Y43: =X43*I43 -> 26404.224 | AA43: ZB02601-10.24 | AB43: 77770GQ4-S001 | AC43: 已入 | AD43: 系统出单 | AF43: 16544 | AG43: =AF43-I43 -> 0 | AH43: 45947 | AK43: =I43 -> 16544 | AL43: =I43 -> 16544 | AO43: =I43 -> 16544 | AY43: =I43/16 -> 1034 | BV43: =AT43+AU43+AY43 -> 1034 | BW43: =BF43+BG43+BI43 -> 0 | BX43: =AK43+BX42 -> 348139 | BZ43: =$BZ$1-BX43 -> 71861
A44: 45884 | B44: WALMART INC. | C44: 美国 | D44: 4500177093 | E44: 0936942326 | F44: 4500177093-20 | G44: 77770GQ4-S001 | H44: 迷你包包S4 16pcs/箱 | I44: 20480 | J44: 0 | K44: 16 | L44: =I44/K44 -> 1280 | M44: 45946 | N44: 45943 | O44: BV验货转自检10/24 | P44: PASS | R44: 45884 | S44: 无 | T44: 45902 | V44: 日期码格式：ZURU DGYYYYMMDD CHINA(日期避开周末和法定节假日即可） 日期：按实际生产日期 Packaging Info: 77770GQ4-S001 1. 包装要求： 77770：MA 1L A版收缩膜+MA 5L A版收藏指南+MA A版纸袋+客版 1L A版PDQ 每pcs产品要贴一张RFID贴纸，RFID贴纸由ZURU提供，贴纸位置要严格按照客人签板 Remark: 77770GQ4-S001 1. 包装要求： 77770：MA 1L A版收缩膜+MA 5L A版收藏指南+MA A版纸袋+客版 1L A版PDQ 每pcs产品要贴一张RFID贴纸，RFID贴纸由ZURU提供，贴纸位置要严格按照客人签板 2. 外箱印刷带条码的RFID箱唛：RFID紫色色带+WM Dept.图标+RFID图标+ITF-14条码+粉色艾利贴纸（不干胶打印），四面右下角印刷ZURU logo, ITFF条码只印刷在 正唛一面，在加印的时候确保条形码能扫描出来，1张粉红色贴纸贴在正唛对角线，外箱侧面任一角落加印："MADE IN CHINA" 字样； 3. 在产品上和包装上要有日期码、以及要有MADE IN CHINA和ZURU字样； 4. 产品如有扎带口要剪平，不能刮手。 5. 此单需要验货，请多备料 6. 此单以loose carton出货，16pcs/PDQ/CTN | W44: Maggie Xie | X44: 1.596 | Y44: =X44*I44 -> 32686.08 | AA44: ZB02771-11.3 | AB44: 77770GQ4-S001 | AC44: 已入 | AD44: 系统出单 | AF44: =16640+3840 -> 20480 | AG44: =AF44-I44 -> 0 | AH44: 欠11号鞋子 | AK44: =I44 -> 20480 | AL44: =I44 -> 20480 | AO44: =I44 -> 20480 | AY44: =I44/16 -> 1280 | BV44: =AT44+AU44+AY44 -> 1280 | BW44: =BF44+BG44+BI44 -> 0 | BX44: =AK44+BX43 -> 368619 | BZ44: =$BZ$1-BX44 -> 51381
A45: 45897 | B45: WALMART INC. | C45: 美国 | D45: 4500178134 | E45: 0938210279 | F45: 4500178134-10 | G45: 77770GQ4-S001 | H45: 迷你包包S4 16pcs/箱 | I45: 960 | J45: 0 | K45: 16 | L45: =I45/K45 -> 60 | M45: 45951 | N45: 45947 | O45: 验货10/24转自检 | P45: PASS | R45: 外箱印刷带条码的RFID箱唛：RFID紫色色带+WM Dept.图标+RFID图标+ITF-14条码，四面右下角印刷ZURU logo, ITFF条码只印刷在正唛一面，在加印的时候确保 条形码能扫描出来，外箱侧面任一角落加印："MADE IN CHINA" 字样； | S45: 无 | T45: 45908 | V45: 日期码格式：ZURU DGYYYYMMDD CHINA(日期避开周末和法定节假日即可） 日期：按实际生产日期 Packaging Info: 77770 1. 包装要求： 77770：MA 1L A版收缩膜+MA 5L A版收藏指南+MA A版纸袋+客版 1L A版PDQ，翻单：4500177086 每pcs产品要贴一张RFID贴纸，RFID贴纸由ZURU提供，贴纸位置要严格按照客人签板 Remark: 77770 1. 包装要求： 77770：MA 1L A版收缩膜+MA 5L A版收藏指南+MA A版纸袋+客版 1L A版PDQ，翻单：4500177086 每pcs产品要贴一张RFID贴纸，RFID贴纸由ZURU提供，贴纸位置要严格按照客人签板 2. 外箱印刷带条码的RFID箱唛：RFID紫色色带+WM Dept.图标+RFID图标+ITF-14条码，四面右下角印刷ZURU logo, ITFF条码只印刷在正唛一面，在加印的时候确保 条形码能扫描出来，外箱侧面任一角落加印："MADE IN CHINA" 字样； 3. 在产品上和包装上要有日期码、以及要有MADE IN CHINA和ZURU字样； 4. 产品如有扎带口要剪平，不能刮手。 5. 此单需要验货，请多备料 6. 此单以loose carton出货，16pcs/PDQ/CTN | W45: Maggie Xie | X45: 1.596 | Y45: =X45*I45 -> 1532.16 | AA45: ZB02977-11.19 | AB45: 77770GQ4-S001 | AC45: 已入 | AD45: 系统出单 | AF45: 960 | AG45: =AF45-I45 -> 0 | AK45: =I45 -> 960 | AL45: =I45 -> 960 | AO45: =I45 -> 960 | AY45: =I45/16 -> 60 | BV45: =AT45+AU45+AY45 -> 60 | BW45: =BF45+BG45+BI45 -> 0 | BX45: =AK45+BX44 -> 369579 | BZ45: =$BZ$1-BX45 -> 50421
A46: 45897 | B46: WALMART INC. | C46: 美国 | D46: 4500178134 | E46: 0938210352 | F46: 4500178134-20 | G46: 77770GQ4-S001 | H46: 迷你包包S4 16pcs/箱 | I46: 960 | J46: 0 | K46: 16 | L46: =I46/K46 -> 60 | M46: 45951 | N46: 45947 | O46: 验货10/24转自检 | P46: PASS | R46: 外箱印刷带条码的RFID箱唛：RFID紫色色带+WM Dept.图标+RFID图标+ITF-14条码，四面右下角印刷ZURU logo, ITFF条码只印刷在正唛一面，在加印的时候确保 条形码能扫描出来，外箱侧面任一角落加印："MADE IN CHINA" 字样； | S46: 无 | T46: 45908 | V46: 日期码格式：ZURU DGYYYYMMDD CHINA(日期避开周末和法定节假日即可） 日期：按实际生产日期 Packaging Info: 77770 1. 包装要求： 77770：MA 1L A版收缩膜+MA 5L A版收藏指南+MA A版纸袋+客版 1L A版PDQ，翻单：4500177086 每pcs产品要贴一张RFID贴纸，RFID贴纸由ZURU提供，贴纸位置要严格按照客人签板 Remark: 77770 1. 包装要求： 77770：MA 1L A版收缩膜+MA 5L A版收藏指南+MA A版纸袋+客版 1L A版PDQ，翻单：4500177086 每pcs产品要贴一张RFID贴纸，RFID贴纸由ZURU提供，贴纸位置要严格按照客人签板 2. 外箱印刷带条码的RFID箱唛：RFID紫色色带+WM Dept.图标+RFID图标+ITF-14条码，四面右下角印刷ZURU logo, ITFF条码只印刷在正唛一面，在加印的时候确保 条形码能扫描出来，外箱侧面任一角落加印："MADE IN CHINA" 字样； 3. 在产品上和包装上要有日期码、以及要有MADE IN CHINA和ZURU字样； 4. 产品如有扎带口要剪平，不能刮手。 5. 此单需要验货，请多备料 6. 此单以loose carton出货，16pcs/PDQ/CTN | W46: Maggie Xie | X46: 1.596 | Y46: =X46*I46 -> 1532.16 | AA46: ZB02980-11.19 | AB46: 77770GQ4-S001 | AC46: 已入 | AD46: 系统出单 | AF46: 960 | AG46: =AF46-I46 -> 0 | AK46: =I46 -> 960 | AL46: =I46 -> 960 | AO46: =I46 -> 960 | AY46: =I46/16 -> 60 | BV46: =AT46+AU46+AY46 -> 60 | BW46: =BF46+BG46+BI46 -> 0 | BX46: =AK46+BX45 -> 370539 | BZ46: =$BZ$1-BX46 -> 49461
A47: 45905 | B47: ASIA GOAL LIMITED TAIWAN BRANCH (H. | C47: 台湾 | D47: 4500178971 | E47: AG250201-TW | F47: 4500178971-10 | G47: 77770GQ1-S001 | H47: 迷你包包S4 | I47: 364 | J47: 0 | K47: 52 | L47: =I47/K47 -> 7 | M47: 45957 | N47: 45958 | P47: PASS | Q47: 45959 | R47: 45905 | S47: 无 | T47: 45925 | V47: 日期码格式：ZURU INC(BVI) 标准格式 日期：按实际生产日期 Packaging Info: 此单出TW 77770GQ1 ： MA PKG 优先1L +1张警语贴纸 Remark: | W47: Chelsea Luo | X47: 2.15 | Y47: =X47*I47 -> 782.6 | AA47: 96738-10.27 | AB47: 77770GQ1-S001 | AC47: 已入 | AD47: 系统出单 | AF47: 364 | AG47: =AF47-I47 -> 0 | AI47: OK | AK47: =I47 -> 364 | AL47: =I47 -> 364 | AO47: =I47 -> 364 | AR47: =I47/13 -> 28 | BV47: =AT47+AU47+AY47 -> 0 | BW47: =BF47+BG47+BI47 -> 0 | BX47: =AK47+BX46 -> 370903 | BZ47: =$BZ$1-BX47 -> 49097 | CA47: 414825
A48: 45912 | B48: KMART AUSTRALIA LTD(NEW ZEALAND) | C48: 新西兰 | D48: 4500179341 | E48: 21105442 | F48: 4500179341-90 | G48: 77770GQ1-S002 | H48: 迷你包包S4 13pcs/箱 | I48: 78 | J48: 0 | K48: 13 | L48: =I48/K48 -> 6 | M48: 45957 | N48: 45958 | P48: PASS | Q48: 10月29日-10月31日交仓 | R48: 45925 | S48: 有 | T48: 1张防盗贴纸+箱唛 + 外箱SSCC Label (贴纸以及位置图翻单PO#4500173688） | V48: 日期码格式：ZURU INC(BVI) 标准格式 日期：按实际生产日期 Packaging Info: 77770GQ1:MA英语UPC版本包装（收缩膜和说明书, MA首选1L，如无1L可用多语且含英语的配套多语包装) + 1张防盗贴纸+箱唛 + 外箱SSCC Label (贴纸以及位置图翻单PO#4500173688） Remark: 1.请务必按时完货，验货。并且按期送货入货代指定仓库，如果晚了导致船期Delay将会有罚金产生或者客户要求空运，所产生的罚金和空运费由工厂承担。 2.SSCC 外箱贴纸请同纸箱瓦楞纸方向（竖纹向）垂直，即外箱贴纸横着贴(注意条码不要被胶带粘住），贴1pc，贴1面正唛，封箱胶纸不能挡住贴纸内容。外箱贴纸 离外箱边距离不少于2cm。 3.外箱材质为ZURU标准； 4.此单需使用KMART封箱胶上下工字型封箱;从2019年6月开始，要用KMART 新版封箱胶带，此单要用"ANKO"封箱胶带 5.此单出口新西兰，请按相应的澳新标准生产； 6.产品和包装上生产批号的显示格式ZURU标准日期码格式 7.外箱信息不可手写，重量和体积需要与实际的一致(不可手写） 8. 每款item装箱后的G.W.超过10KG或者CBM超过0.13,(9.5KG或者以上，四舍五入后也属于10KG) 需在外箱上加印超 重或者Bulky LOGO，若发现我们资料没有，请 帮忙提醒 1)重量超过10kg但不超过16kg且CBM不超过0.13,10-16kg 超重logo 2）CBM超过0.13且重量少于17kg，bulky logo 3）不属于以上两种情况，需要使用相应重量范围内的超重logo 4）超重logo需要在外箱四面都印刷(箱唛右上角，两面侧唛超重logo需要尽量靠近毛重)，尺寸为:110mm height* 95mm width 9. 实际外箱重量跟印在箱唛上的数据差异不能超3%，尺寸按实际数据印刷 | W48: Lydia Wu | X48: 2.4275 | Y48: =X48*I48 -> 189.345 | AA48: A96772-2-10.30 | AB48: 77770GQ1-S002 | AC48: 已入 | AD48: 系统出单 | AF48: 78 | AG48: =AF48-I48 -> 0 | AI48: OK | AK48: =I48 -> 78 | AL48: =I48 -> 78 | AO48: =I48 -> 78 | AR48: =I48/13 -> 6 | BV48: =AT48+AU48+AY48 -> 0 | BW48: =BF48+BG48+BI48 -> 0 | BX48: =AK48+BX47 -> 370981 | BZ48: =$BZ$1-BX48 -> 49019 | CA48: 413967
A49: 45912 | B49: KMART AUSTRALIA LTD | C49: 澳大利亚 | D49: 4500179340 | E49: 21105439 | F49: 4500179340-90 | G49: 77770GQ1-S002 | H49: 迷你包包S4 13pcs/箱 | I49: 1482 | J49: 0 | K49: 13 | L49: =I49/K49 -> 114 | M49: 45957 | N49: 45958 | P49: PASS | Q49: 10 月 29 日 入裕泰仓 | R49: 45925 | S49: 有 | T49: 1张防盗贴纸+箱唛 + 外箱SSCC Label (贴纸以及位置图翻单PO#4500173688） | V49: 日期码格式：ZURU INC(BVI) 标准格式 日期：按实际生产日期 Packaging Info: 77770GQ1:MA英语UPC版本包装（收缩膜和说明书, MA首选1L，如无1L可用多语且含英语的配套多语包装) + 1张防盗贴纸+箱唛 + 外箱SSCC Label (贴纸以及位置图翻单PO#4500173688） Remark: 1.请务必按时完货，验货。并且按期送货入货代指定仓库，如果晚了导致船期Delay将会有罚金产生或者客户要求空运，所产生的罚金和空运费由工厂承担。 2.SSCC 外箱贴纸请同纸箱瓦楞纸方向（竖纹向）垂直，即外箱贴纸横着贴(注意条码不要被胶带粘住），贴1pc，贴1面正唛，封箱胶纸不能挡住贴纸内容。外箱贴纸 离外箱边距离不少于2cm。 3.外箱材质为ZURU标准； 4.此单需使用KMART封箱胶上下工字型封箱;从2019年6月开始，要用KMART 新版封箱胶带，此单要用"ANKO"封箱胶带 5.此单出口澳大利亚，请按相应的澳新标准生产； 6.产品和包装上生产批号的显示格式ZURU标准日期码格式 7.外箱信息不可手写，重量和体积需要与实际的一致(不可手写） 8. 每款item装箱后的G.W.超过10KG或者CBM超过0.13,(9.5KG或者以上，四舍五入后也属于10KG) 需在外箱上加印超 重或者Bulky LOGO，若发现我们资料没有，请 帮忙提醒 1)重量超过10kg但不超过16kg且CBM不超过0.13,10-16kg 超重logo 2）CBM超过0.13且重量少于17kg，bulky logo 3）不属于以上两种情况，需要使用相应重量范围内的超重logo 4）超重logo需要在外箱四面都印刷(箱唛右上角，两面侧唛超重logo需要尽量靠近毛重)，尺寸为:110mm height* 95mm width 9. 实际外箱重量跟印在箱唛上的数据差异不能超3%，尺寸按实际数据印刷 | W49: Lydia Wu | X49: 2.4275 | Y49: =X49*I49 -> 3597.555 | AA49: A96773-2-10.30 | AB49: 77770GQ1-S002 | AC49: 已入 | AD49: 系统出单 | AF49: 1482 | AG49: =AF49-I49 -> 0 | AI49: OK | AK49: =I49 -> 1482 | AL49: =I49 -> 1482 | AO49: =I49 -> 1482 | AR49: =I49/13 -> 114 | BV49: =AT49+AU49+AY49 -> 0 | BW49: =BF49+BG49+BI49 -> 0 | BX49: =AK49+BX48 -> 372463 | BZ49: =$BZ$1-BX49 -> 47537 | CA49: 412485
A50: 45884 | B50: WALMART INC. | C50: 美国 | D50: 4500177094 | E50: 0936942198 | F50: 4500177094-10 | G50: 77770GQ4-S001 | H50: 迷你包包S4 16pcs/箱 | I50: 13536 | J50: 0 | K50: 16 | L50: =I50/K50 -> 846 | M50: 45957 | N50: 45960 | O50: 转自检10/30 | P50: PASS | Q50: 45960 | R50: 45884 | S50: 无 | T50: 45902 | V50: 日期码格式：ZURU DGYYYYMMDD CHINA(日期避开周末和法定节假日即可） 日期：按实际生产日期 Packaging Info: 77770GQ4-S001 1. 包装要求： 77770：MA 1L A版收缩膜+MA 5L A版收藏指南+MA A版纸袋+客版 1L A版PDQ 每pcs产品要贴一张RFID贴纸，RFID贴纸由ZURU提供，贴纸位置要严格按照客人签板 Remark: 77770GQ4-S001 1. 包装要求： 77770：MA 1L A版收缩膜+MA 5L A版收藏指南+MA A版纸袋+客版 1L A版PDQ 每pcs产品要贴一张RFID贴纸，RFID贴纸由ZURU提供，贴纸位置要严格按照客人签板 2. 外箱印刷带条码的RFID箱唛：RFID紫色色带+WM Dept.图标+RFID图标+ITF-14条码+粉色艾利贴纸（不干胶打印），四面右下角印刷ZURU logo, ITFF条码只印刷在 正唛一面，在加印的时候确保条形码能扫描出来，1张粉红色贴纸贴在正唛对角线，外箱侧面任一角落加印："MADE IN CHINA" 字样； 3. 在产品上和包装上要有日期码、以及要有MADE IN CHINA和ZURU字样； 4. 产品如有扎带口要剪平，不能刮手。 5. 此单需要验货，请多备料 6. 此单以loose carton出货，16pcs/PDQ/CTN | W50: Maggie Xie | X50: 1.596 | Y50: =X50*I50 -> 21603.456 | AA50: ZB02913-11.14 | AB50: 77770GQ4-S001 | AC50: 已入 | AD50: 系统出单 | AF50: =7776+5760 -> 13536 | AG50: =AF50-I50 -> 0 | AK50: =I50 -> 13536 | AL50: =I50 -> 13536 | AO50: =I50 -> 13536 | AY50: =I50/16 -> 846 | BV50: =AT50+AU50+AY50 -> 846 | BW50: =BF50+BG50+BI50 -> 0 | BX50: =AK50+BX49 -> 385999 | BZ50: =$BZ$1-BX50 -> 34001 | CA50: =$BZ$1+$CA$1-BX50 -> 474001
A51: 45884 | B51: WALMART INC. | C51: 美国 | D51: 4500177094 | E51: 0936942303 | F51: 4500177094-20 | G51: 77770GQ4-S001 | H51: 迷你包包S4 16pcs/箱 | I51: 13376 | J51: 0 | K51: 16 | L51: =I51/K51 -> 836 | M51: 45957 | N51: 45960 | O51: 转自检10/30 | P51: PASS | Q51: 45960 | R51: 45884 | S51: 无 | T51: 45902 | V51: 日期码格式：ZURU DGYYYYMMDD CHINA(日期避开周末和法定节假日即可） 日期：按实际生产日期 Packaging Info: 77770GQ4-S001 1. 包装要求： 77770：MA 1L A版收缩膜+MA 5L A版收藏指南+MA A版纸袋+客版 1L A版PDQ 每pcs产品要贴一张RFID贴纸，RFID贴纸由ZURU提供，贴纸位置要严格按照客人签板 Remark: 77770GQ4-S001 1. 包装要求： 77770：MA 1L A版收缩膜+MA 5L A版收藏指南+MA A版纸袋+客版 1L A版PDQ 每pcs产品要贴一张RFID贴纸，RFID贴纸由ZURU提供，贴纸位置要严格按照客人签板 2. 外箱印刷带条码的RFID箱唛：RFID紫色色带+WM Dept.图标+RFID图标+ITF-14条码+粉色艾利贴纸（不干胶打印），四面右下角印刷ZURU logo, ITFF条码只印刷在 正唛一面，在加印的时候确保条形码能扫描出来，1张粉红色贴纸贴在正唛对角线，外箱侧面任一角落加印："MADE IN CHINA" 字样； 3. 在产品上和包装上要有日期码、以及要有MADE IN CHINA和ZURU字样； 4. 产品如有扎带口要剪平，不能刮手。 5. 此单需要验货，请多备料 6. 此单以loose carton出货，16pcs/PDQ/CTN | W51: Maggie Xie | X51: 1.596 | Y51: =X51*I51 -> 21348.096 | AA51: ZB02808-11.4 | AB51: 77770GQ4-S001 | AC51: 已入 | AD51: 系统出单 | AF51: 13376 | AG51: =AF51-I51 -> 0 | AK51: =I51 -> 13376 | AL51: =I51 -> 13376 | AO51: =I51 -> 13376 | AY51: =I51/16 -> 836 | BV51: =AT51+AU51+AY51 -> 836 | BW51: =BF51+BG51+BI51 -> 0 | BX51: =AK51+BX50 -> 399375 | BZ51: =$BZ$1-BX51 -> 20625 | CA51: =$BZ$1+$CA$1-BX51 -> 460625
A52: 45897 | B52: WALMART INC. | C52: 美国 | D52: 4500178135 | E52: 0938210349 | F52: 4500178135-10 | G52: 77770GQ4-S001 | H52: 迷你包包S4 16pcs/箱 | I52: 960 | J52: 0 | K52: 16 | L52: =I52/K52 -> 60 | M52: 45957 | N52: 45960 | O52: BV验货转自检10/30 | P52: PASS | R52: 外箱印刷带条码的RFID箱唛：RFID紫色色带+WM Dept.图标+RFID图标+ITF-14条码，四面右下角印刷ZURU logo, ITFF条码只印刷在正唛一面，在加印的时候确保 条形码能扫描出来，外箱侧面任一角落加印："MADE IN CHINA" 字样； | S52: 无 | T52: 45908 | V52: 日期码格式：ZURU DGYYYYMMDD CHINA(日期避开周末和法定节假日即可） 日期：按实际生产日期 Packaging Info: 77770 1. 包装要求： 77770：MA 1L A版收缩膜+MA 5L A版收藏指南+MA A版纸袋+客版 1L A版PDQ，翻单：4500177086 每pcs产品要贴一张RFID贴纸，RFID贴纸由ZURU提供，贴纸位置要严格按照客人签板 Remark: 77770 1. 包装要求： 77770：MA 1L A版收缩膜+MA 5L A版收藏指南+MA A版纸袋+客版 1L A版PDQ，翻单：4500177086 每pcs产品要贴一张RFID贴纸，RFID贴纸由ZURU提供，贴纸位置要严格按照客人签板 2. 外箱印刷带条码的RFID箱唛：RFID紫色色带+WM Dept.图标+RFID图标+ITF-14条码，四面右下角印刷ZURU logo, ITFF条码只印刷在正唛一面，在加印的时候确保 条形码能扫描出来，外箱侧面任一角落加印："MADE IN CHINA" 字样； 3. 在产品上和包装上要有日期码、以及要有MADE IN CHINA和ZURU字样； 4. 产品如有扎带口要剪平，不能刮手。 5. 此单需要验货，请多备料 6. 此单以loose carton出货，16pcs/PDQ/CTN | W52: Maggie Xie | X52: 1.596 | Y52: =X52*I52 -> 1532.16 | AA52: ZB02878-11.11 | AB52: 77770GQ4-S001 | AC52: 已入 | AD52: 系统出单 | AF52: 960 | AG52: =AF52-I52 -> 0 | AK52: =I52 -> 960 | AL52: =I52 -> 960 | AO52: =I52 -> 960 | AY52: =I52/16 -> 60 | BV52: =AT52+AU52+AY52 -> 60 | BW52: =BF52+BG52+BI52 -> 0 | BX52: =AK52+BX51 -> 400335 | BZ52: =$BZ$1-BX52 -> 19665 | CA52: =$BZ$1+$CA$1-BX52 -> 459665
A53: 45904 | B53: BINGO GLOBAL GROUP FOR TRADING SUPP | C53: 埃及 | D53: 4500178799 | F53: 4500178799-40 | G53: 77770GQ2-S001 | H53: 迷你包包S4 | I53: 1000 | J53: 0 | K53: 50 | L53: =I53/K53 -> 20 | M53: 45947 | N53: 45945 | P53: PASS | R53: 45910 | S53: 无 | T53: 进口商贴纸 | V53: 日期码格式：ZURU INC(BVI) 标准格式 日期：按实际生产日期 Packaging Info: 77770GQ2: 包装MA EAN收缩膜+进口商贴纸，MA PDQ，收缩膜EAN条码显示4894680050518，产品年龄3+； 客人箱唛排版，印4面，条码内容4894680050518; Remark: | W53: Nora Pan | X53: 2.35 | Y53: =X53*I53 -> 2350 | AA53: A97467-1.7 | AB53: 77770GQ2-S001-3L | AC53: 已入 | AD53: 系统出单 | AF53: 1000 | AG53: =AF53-I53 -> 0 | AI53: OK | AK53: =I53 -> 1000 | AN53: =I53 -> 1000 | AO53: =I53 -> 1000 | AT53: =L53*2 -> 40 | BV53: =AT53+AU53+AY53 -> 40 | BW53: =BF53+BG53+BI53 -> 0 | BX53: =AK53+BX52 -> 401335 | BZ53: =$BZ$1-BX53 -> 18665 | CA53: =$BZ$1+$CA$1-BX53 -> 458665
A54: 45896 | B54: TARGET US | C54: 美国 | D54: 4500177942 | E54: 10001493620-3890 | F54: 4500177942-20 | G54: 77770GQ2-S002 | H54: 迷你包包S4 25pcs/箱 | I54: 29750 | J54: 0 | K54: 25 | L54: =I54/K54 -> 1190 | M54: 45954 | N54: 45950 | P54: PASS | Q54: 2025/11/3提货 | R54: 45904 | S54: 有 | T54: 45919 | V54: 日期码格式：ZURU INC(BVI) 标准格式 日期：按实际生产日期 Packaging Info: ； 77770GQ2 产品包装(UPC 版) MA 1L收缩膜+MA 1L PDQ； Remark: 77770GQ2 1. 77770GQ2-S002-MINI BRANDS-FASHION MINI BRANDS-SERIES 4-CAPSULE,WITH DEMO,25PCS/Gravity PDQ,25PCS/PDQ/CTN 2. 产品包装(UPC 版) MA 1L收缩膜+MA 1L PDQ；收缩膜上的UPC显示193052089465； 3. 外箱正唛左上角位置粘贴条码箱贴纸，每箱只贴一张，由ZURU订购。来料贴纸上显示的客户DPCI# 086-02-9624, UPC显示10193052089462; 以上所以item均： 1. 产品和包装上均要印刷tracking code信息，格式为ZURU常规格式; 2. 出货方式：货代自提 | W54: Holly Zheng | X54: 1.5848 | Y54: =I54*X54 -> 47147.8 | AA54: ZB02956-11.19 | AB54: 77770GQ2-S002 | AC54: 已入 | AD54: 系统出单 | AF54: 29750 | AG54: =AF54-I54 -> 0 | AI54: OK | AK54: =I54 -> 29750 | AL54: =I54 -> 29750 | AO54: =I54 -> 29750 | AT54: =I54/25 -> 1190 | BV54: =AT54+AU54+AY54 -> 1190 | BW54: =BF54+BG54+BI54 -> 0 | BX54: =AK54+BX53 -> 431085 | CA54: =$BZ$1+$CA$1-BX54 -> 428915
A55: 45908 | B55: TARGET US | C55: 美国 | D55: 4500179008 | E55: 10001493848-3891 | F55: 4500179008-20 | G55: 77770GQ2-S002 | H55: 迷你包包S4 25pcs/箱 | I55: 12600 | J55: 0 | K55: 25 | L55: =I55/K55 -> 504 | M55: 45956 | N55: 45952 | P55: PASS | Q55: 2025/11/6提货 | R55: 45919 | S55: 有 | T55: 粘贴条码箱贴纸 | V55: 日期码格式：ZURU INC(BVI) 标准格式 日期：按实际生产日期 Packaging Info: 77770GQ2 产品包装(UPC 版) MA 1L收缩膜+MA 1L PDQ； Remark: 77770GQ2 1. 77770GQ2-S002-MINI BRANDS-FASHION MINI BRANDS-SERIES 4-CAPSULE,WITH DEMO,25PCS/Gravity PDQ,25PCS/PDQ/CTN 2. 产品包装(UPC 版) MA 1L收缩膜+MA 1L PDQ；收缩膜上的UPC显示193052089465； 3. 外箱正唛左上角位置粘贴条码箱贴纸，每箱只贴一张，由ZURU订购。来料贴纸上显示的客户DPCI# 086-02-9624, UPC显示10193052089462; 以上所有item均： 1. 产品和包装上均要印刷tracking code信息，格式为ZURU常规格式; 2. 出货方式：货代自提 | W55: Holly Zheng | X55: 1.5848 | Y55: =I55*X55 -> 19968.48 | AA55: ZB02958-11.19 | AB55: 77770GQ2-S002 | AC55: 已入 | AD55: 系统出单 | AF55: 12600 | AG55: =AF55-I55 -> 0 | AI55: OK | AK55: =I55 -> 12600 | AL55: =I55 -> 12600 | AO55: =I55 -> 12600 | AT55: =I55/25 -> 504 | BV55: =AT55+AU55+AY55 -> 504 | BW55: =BF55+BG55+BI55 -> 0 | BX55: =AK55+BX54 -> 443685 | CA55: =$BZ$1+$CA$1-BX55 -> 416315
A56: 45919 | B56: KMART AUSTRALIA LTD | C56: 澳大利亚 | D56: 4500179977 | E56: 21169559 | F56: 4500179977-20 | G56: 77770GQ1-S002 | H56: 迷你包包S4 13pcs/箱 | I56: 1638 | J56: 0 | K56: 13 | L56: =I56/K56 -> 126 | M56: 45964 | N56: 45965 | P56: PASS | Q56: 11/5-11/7交仓 | R56: 45930 | S56: 有 | T56: 1张防盗贴纸+箱唛 + 外箱SSCC Label (贴纸以及位置图翻单PO#4500173688） | V56: 日期码格式：ZURU INC(BVI) 标准格式 日期：按实际生产日期 Packaging Info: 77770GQ1:MA英语UPC版本包装（收缩膜和说明书, MA首选1L，如无1L可用多语且含英语的配套多语包装) + 1张防盗贴纸+箱唛 + 外箱SSCC Label (贴纸以及位置图翻单PO#4500173688） Remark: 1.请务必按时完货，验货。并且按期送货入货代指定仓库，如果晚了导致船期Delay将会有罚金产生或者客户要求空运，所产生的罚金和空运费由工厂承担。 2.SSCC 外箱贴纸请同纸箱瓦楞纸方向（竖纹向）垂直，即外箱贴纸横着贴(注意条码不要被胶带粘住），贴1pc，贴1面正唛，封箱胶纸不能挡住贴纸内容。外箱贴纸 离外箱边距离不少于2cm。 3.外箱材质为ZURU标准； 4.此单需使用KMART封箱胶上下工字型封箱;从2019年6月开始，要用KMART 新版封箱胶带，此单要用"ANKO"封箱胶带 5.此单出口澳大利亚，请按相应的澳新标准生产； 6.产品和包装上生产批号的显示格式ZURU标准日期码格式 7.外箱信息不可手写，重量和体积需要与实际的一致(不可手写） 8. 每款item装箱后的G.W.超过10KG或者CBM超过0.13,(9.5KG或者以上，四舍五入后也属于10KG) 需在外箱上加印超 重或者Bulky LOGO，若发现我们资料没有，请 帮忙提醒 1)重量超过10kg但不超过16kg且CBM不超过0.13,10-16kg 超重logo 2）CBM超过0.13且重量少于17kg，bulky logo 3）不属于以上两种情况，需要使用相应重量范围内的超重logo 4）超重logo需要在外箱四面都印刷(箱唛右上角，两面侧唛超重logo需要尽量靠近毛重)，尺寸为:110mm height* 95mm width 9. 实际外箱重量跟印在箱唛上的数据差异不能超3%，尺寸按实际数据印刷 | W56: Lydia Wu | X56: 2.4275 | Y56: =X56*I56 -> 3976.245 | AA56: 96880-11.6 | AB56: 77770GQ1-S002 | AC56: 已入 | AD56: 系统出单 | AF56: 1638 | AG56: =AF56-I56 -> 0 | AI56: OK | AK56: =I56 -> 1638 | AL56: =I56 -> 1638 | AO56: =I56 -> 1638 | AR56: =I56/13 -> 126 | BV56: =AT56+AU56+AY56 -> 0 | BW56: =BF56+BG56+BI56 -> 0 | BX56: =AK56+BX55 -> 445323 | CA56: =$BZ$1+$CA$1-BX56 -> 414677
A57: 45919 | B57: KMART AUSTRALIA LTD(NEW ZEALAND) | C57: 新西兰 | D57: 4500179979 | E57: 21169560 | F57: 4500179979-20 | G57: 77770GQ1-S002 | H57: 迷你包包S4 13pcs/箱 | I57: 130 | J57: 0 | K57: 13 | L57: =I57/K57 -> 10 | M57: 45964 | N57: 45965 | P57: PASS | Q57: 11/5-11/7交仓 | R57: 45930 | S57: 有 | T57: 1张防盗贴纸+箱唛 + 外箱SSCC Label (贴纸以及位置图翻单PO#4500173688） | V57: 日期码格式：ZURU INC(BVI) 标准格式 日期：按实际生产日期 Packaging Info: 77770GQ1:MA英语UPC版本包装（收缩膜和说明书, MA首选1L，如无1L可用多语且含英语的配套多语包装) + 1张防盗贴纸+箱唛 + 外箱SSCC Label (贴纸以及位置图翻单PO#4500173688） Remark: 1.请务必按时完货，验货。并且按期送货入货代指定仓库，如果晚了导致船期Delay将会有罚金产生或者客户要求空运，所产生的罚金和空运费由工厂承担。 2.SSCC 外箱贴纸请同纸箱瓦楞纸方向（竖纹向）垂直，即外箱贴纸横着贴(注意条码不要被胶带粘住），贴1pc，贴1面正唛，封箱胶纸不能挡住贴纸内容。外箱贴纸 离外箱边距离不少于2cm。 3.外箱材质为ZURU标准； 4.此单需使用KMART封箱胶上下工字型封箱;从2019年6月开始，要用KMART 新版封箱胶带，此单要用"ANKO"封箱胶带 5.此单出口新西兰，请按相应的澳新标准生产； 6.产品和包装上生产批号的显示格式ZURU标准日期码格式 7.外箱信息不可手写，重量和体积需要与实际的一致(不可手写） 8. 每款item装箱后的G.W.超过10KG或者CBM超过0.13,(9.5KG或者以上，四舍五入后也属于10KG) 需在外箱上加印超 重或者Bulky LOGO，若发现我们资料没有，请 帮忙提醒 1)重量超过10kg但不超过16kg且CBM不超过0.13,10-16kg 超重logo 2）CBM超过0.13且重量少于17kg，bulky logo 3）不属于以上两种情况，需要使用相应重量范围内的超重logo 4）超重logo需要在外箱四面都印刷(箱唛右上角，两面侧唛超重logo需要尽量靠近毛重)，尺寸为:110mm height* 95mm width 9. 实际外箱重量跟印在箱唛上的数据差异不能超3%，尺寸按实际数据印刷 | W57: Lydia Wu | X57: 2.4275 | Y57: =X57*I57 -> 315.575 | AA57: 96881-11.6 | AB57: 77770GQ1-S002 | AC57: 已入 | AD57: 系统出单 | AF57: 130 | AG57: =AF57-I57 -> 0 | AI57: OK | AK57: =I57 -> 130 | AL57: =I57 -> 130 | AO57: =I57 -> 130 | AR57: =I57/13 -> 10 | BV57: =AT57+AU57+AY57 -> 0 | BW57: =BF57+BG57+BI57 -> 0 | BX57: =AK57+BX56 -> 445453 | CA57: =$BZ$1+$CA$1-BX57 -> 414547
A58: 45918 | B58: AMAZON.COM SERVICES LLC | C58: 美国 | D58: 4500179751 | E58: 7KBRJIJB | F58: 4500179751-10 | G58: 77806-S001 | H58: 迷你包包S4 2PK 圆筒装 | I58: 3000 | J58: 0 | K58: 12 | L58: =I58/K58 -> 250 | M58: 45953 | N58: 45950 | O58: 原domestic PO4500177327转FOB单 | P58: PASS | Q58: 10/31-11/1 | R58: 45918 | S58: 有 | T58: 外箱正面印ZURU Logo+SSCC Label(客供贴纸，由跟单订购 | V58: 日期码格式：ZURU INC(BVI) 标准格式 日期：按实际生产日期 Packaging Info: #77806: 2PK STD #77770入PVC筒,客版3L无UPC版收缩膜，客版3L铜版纸（跟单提供）。收藏指南和说明书为MA版本。（两个球的配比不能重复）。 （原domestic PO4500177327转FOB单） Remark: 1. Amazon MDDP订单，出口US。 2. 日期码使用ZURU标准版本。 3. 如果大货有要求入邮包盒，则对应的邮包盒上面要打上日期码。 4. 箱尺寸要求：外箱最长边不能超过25"(超过了，case pack只能为1)，不符合要求的大货，一律不接受。 5. 外箱箱唛要求： ①外箱正面印ZURU Logo+SSCC Label(客供贴纸，由跟单订购)。关于 SSCC Label 请注意： SSCC Label显示的是客人自己的item#。每一张SSCC label都是唯一且有不同流水及条码的，没有损耗，绝对不可贴错。如果贴错或损坏任何一张，都会导致全部都 错，千万要注意！SSCC Label必须贴在外箱正面的正中间位置(贴一面即可)，并且贴纸离外箱边距必须至少3cm(可以覆盖Logo<(>&<)>箱唛)，否则会影响到客户那边 仓库的扫描识别。 ②外箱侧面印item#(订单上显示的SKU#)+carton size(以工厂实际尺寸为准，单位: inch)+MADE IN CHINA，日期使用ZURU 标准版本。 6. 装柜要求：按照客户PO#装柜/箱号顺序装柜，跟单会提前给到装柜计划。 在大货生产/仓库存放时，请留意该装柜要求，以便装柜时不混乱(避免装错/装漏/找不到货号等)。 | W58: Kelly Shen/Mia Pan/P | X58: 2.892 | Y58: =X58*I58 -> 8676 | AA58: ZB02994-11.19 | AB58: 77806-S001 | AC58: 已入 | AD58: 系统出单 | AF58: 3000 | AG58: =AF58-I58 -> 0 | AI58: OK | AK58: =I58*2 -> 6000 | AM58: =I58*2 -> 6000 | AO58: =I58*2 -> 6000 | BJ58: =I58 -> 3000 | BK58: =I58 -> 3000 | BL58: =I58 -> 3000 | BV58: =AT58+AU58+AY58 -> 0 | BW58: =BF58+BG58+BI58 -> 0 | BX58: =AK58+BX57 -> 451453 | CA58: =$BZ$1+$CA$1-BX58 -> 408547
