Workbook

Sheet 77685旧排期 
A1: ZURU 5 surprise Dino （混搭恐龙）生产排期表 #77685 | H1: 3L及共用包材上的logo为英法2L，纸袋底纹为5S通用logo（为应对加拿大魁北克新规，3L及共用包材上的logo增加法语或改为5S logo以减少翻译）。口水胶、纸袋、说明书、收藏指南从1L Logo变更3L Logo，GQ21L/3L各库存2000PCS，后续切换B版本，注意走加拿大魁北克订单不能用A版本.同一个单不能出现两个版本 | AH1: 无硼 口水胶 | AK1: 收缩膜 | AN1: 收藏指南 | AP1: 外挂中文收藏指南+中文说明书 | AQ1: GQ2 | AT1: GQ1 | AV1: GQ4 | AW1: GQ5 | AX1: GQ7 | AZ1: SK展示架 | BC1: SK1展示架 | BF1: 2PK | BJ1: 腕龙 | BK1: 双脊龙 | BL1: 镰刀龙 | BM1: 甲龙 | BN1: 戟龙 | BO1: 棘龙 | BP1: 沧龙 | BQ1: 霸王龙 | BR1: 特殊款霸王龙 | BT1: =生产MA!G4 -> 腕龙 | BU1: =生产MA!H4 -> 双脊龙 | BV1: =生产MA!I4 -> 镰刀龙 | BW1: =生产MA!J4 -> 甲龙 | BX1: =生产MA!K4 -> 戟龙 | BY1: =生产MA!L4 -> 棘龙 | BZ1: =生产MA!M4 -> 沧龙 | CA1: =生产MA!N4 -> 霸王龙 | CB1: =生产MA!O4 -> 特殊款霸王龙
A2: 香港接单日期 | B2: 第三方客户名称 | C2: 走货国家 | D2: PO号 | E2: 第三方客户 PO NO# | F2: SKU | G2: ITEM# | H2: 中文名 | I2: PO数量 (pcs) | J2: 内箱装箱数量(pcs) | K2: 外箱装箱数量(pcs) | L2: 总箱数 | M2: 客PO期 | N2: 验货期 | O2: 第三方验货时间 | P2: 验货结果 | Q2: 船期 | R2: 箱唛资料(收到日期) | S2: 外箱贴纸 | T2: 客供贴纸AI(收到日期) | U2: 样板 | V2: 备注 | W2: ZURU 跟单 | X2: 单价USD | Y2: 金额USD | Z2: 发票号 | AA2: 送回数量 | AB2: 欠数 | AC2: 贴纸情况 | AD2: 下单情况 | AE2: 系统货号 | AF2: 是否入系统 | AG2: 球数 | AH2: MA | AI2: B MA | AJ2: 客版 | AK2: MA 1L | AL2: MA 3L | AM2: Smyths客版 | AN2: MA 5L | AO2: B MA 5L | AP2: 客版 | AQ2: MA 1L | AR2: MA 3L | AS2: MA B3L | AT2: MA 1L | AU2: MA 3L | AV2: WM 客版 | AW2: Big 客版 | AX2: WM M客版 | AY2: IMP 3L 客版 | AZ2: MA 1L | BA2: MA 3L | BB2: 3L底座 | BC2: MA 1L | BD2: MA 3L | BE2: 底座 | BF2: 圆筒 | BG2: logo英法语彩纸/贴纸 条码UPC | BJ2: 0.12239583 | BK2: 0.12239583 | BL2: 0.12239583 | BM2: 0.12239583 | BN2: 0.12239583 | BO2: 0.12239583 | BP2: 0.12239583 | BQ2: 0.12239583 | BR2: 0.020833333 | BS2: MA扣数 | BT2: =生产MA!G12 -> 134028 | BU2: =生产MA!H12 -> 134028 | BV2: =生产MA!I12 -> 134028 | BW2: =生产MA!J12 -> 134028 | BX2: =生产MA!K12 -> 134028 | BY2: =生产MA!L12 -> 134028 | BZ2: =生产MA!M12 -> 134028 | CA2: =生产MA!N12 -> 134028 | CB2: =生产MA!O12 -> 22815
A3: 45617 | B3: ZURU | C3: 深圳 | D3: ZPO2411012 | E3: PP订单 | G3: 77685GQ2-S001 | H3: 混搭恐龙27pcs/GQ2*2/箱 | I3: 1135 | J3: 0 | K3: 54 | L3: =I3/K3 -> 21.018519 | M3: 45639 | N3: 45635 | R3: 无 | S3: 无 | T3: 无 | V3: 如何同意以上交货期到ZURU但是最后由于供应商原因无法交货，ZURU保留以下的罚款条款 不按期出货罚款如下： 1-7（含第七天）天内延迟出货罚款为合同总金额的百分之五 7-14（含第十四天）天内延迟出货罚款为合同总金额的百分之七 如果超过14天将扣合同金额的百分之十或者由客人提出预计运费方案 如果因为质量不符合雨禾要求的标准，供应商必须改进产品并达到标准并支付返工费用和出货延迟费用 订单细节会不时进行修改，如果订单做了修改要及时通知供应商，修改和特殊指引在生产过程中要由邮件或者电话确认 | Z3: 年存 | BT3: =BT2-BJ3 -> 134028 | BU3: =BU2-BK3 -> 134028 | BV3: =BV2-BL3 -> 134028 | BW3: =BW2-BM3 -> 134028 | BX3: =BX2-BN3 -> 134028 | BY3: =BY2-BO3 -> 134028 | BZ3: =BZ2-BP3 -> 134028 | CA3: =CA2-BQ3 -> 134028 | CB3: =CB2-BR3 -> 22815
A4: 45618 | B4: ZURU | C4: 库有 | D4: ZMPO24875 | E4: 同PP单一起做 | G4: 77685-S001 | H4: 混搭恐龙 | I4: 1008 | J4: 0 | K4: 24 | L4: =I4/K4 -> 42 | M4: 45639 | N4: 45635 | R4: 无 | S4: 无 | T4: 无 | V4: Remark：跟PP订单一起安排/标准箱装箱/箱唛参照邮件附件 备注：收到样品订单后尽快安排 ，注意样板品质质量要求要高于大货品质要求 ，送货时必须要附带送货单(没有送货单和QC检验合格报告的仓库一律拒绝收货)，请知悉，谢谢！ | W4: Angus | Z4: 97427-12.31 | BT4: =BT3-BJ4 -> 134028 | BU4: =BU3-BK4 -> 134028 | BV4: =BV3-BL4 -> 134028 | BW4: =BW3-BM4 -> 134028 | BX4: =BX3-BN4 -> 134028 | BY4: =BY3-BO4 -> 134028 | BZ4: =BZ3-BP4 -> 134028 | CA4: =CA3-BQ4 -> 134028 | CB4: =CB3-BR4 -> 22815
A5: 45618 | B5: ZURU | C5: 库有 | D5: ZMPO24875 | E5: 同PP单一起做 | G5: 77685-S001 | H5: 10套散件 | I5: 10 | J5: 0 | K5: 10 | L5: =I5/K5 -> 1 | M5: 45639 | N5: 45635 | R5: 无 | S5: 无 | T5: 无 | V5: Remark：跟PP订单一起安排/只需要齐全套散件/麻烦用胶袋分装好一套为一袋/箱唛参照邮件附件 备注：收到样品订单后尽快安排 ，注意样板品质质量要求要高于大货品质要求 ，送货时必须要附带送货单(没有送货单和QC检验合格报告的仓库一律拒绝收货)，请知悉，谢谢！ | W5: Angus | Z5: 97427-12.31 | AE5: # | BT5: =BT4-BJ5 -> 134028 | BU5: =BU4-BK5 -> 134028 | BV5: =BV4-BL5 -> 134028 | BW5: =BW4-BM5 -> 134028 | BX5: =BX4-BN5 -> 134028 | BY5: =BY4-BO5 -> 134028 | BZ5: =BZ4-BP5 -> 134028 | CA5: =CA4-BQ5 -> 134028 | CB5: =CB4-BR5 -> 22815
A6: 45618 | B6: ZURU | C6: 库有 | D6: ZMPO24875 | E6: 同PP单一起做 | G6: 77685GQ1-S001 | H6: GQ1空PDQ搭配Demo零件 | I6: 20 | J6: 0 | K6: 20 | L6: =I6/K6 -> 1 | M6: 45639 | N6: 45635 | R6: 无 | S6: 无 | T6: 无 | V6: Remark：跟PP订单一起安排/只需要空PDQ(PDQ可打平包/需配齐PDQ上原有的配件（列如-Demo-吸塑) 备注：收到样品订单后尽快安排 ，注意样板品质质量要求要高于大货品质要求 ，送货时必须要附带送货单(没有送货单和QC检验合格报告的仓库一律拒绝收货)，请知悉，谢谢！ | W6: Angus | Z6: 97427-12.31 | AE6: # | BT6: =BT5-BJ6 -> 134028 | BU6: =BU5-BK6 -> 134028 | BV6: =BV5-BL6 -> 134028 | BW6: =BW5-BM6 -> 134028 | BX6: =BX5-BN6 -> 134028 | BY6: =BY5-BO6 -> 134028 | BZ6: =BZ5-BP6 -> 134028 | CA6: =CA5-BQ6 -> 134028 | CB6: =CB5-BR6 -> 22815
A7: 45618 | B7: ZURU | C7: 库有 | D7: ZMPO24875 | E7: 同PP单一起做 | G7: 77685GQ2-S001 | H7: GQ2空PDQ搭配Demo零件 | I7: 20 | J7: 0 | K7: 20 | L7: =I7/K7 -> 1 | M7: 45639 | N7: 45635 | R7: 无 | S7: 无 | T7: 无 | V7: Remark：跟PP订单一起安排/只需要空PDQ(PDQ可打平包/需配齐PDQ上原有的配件（列如-Demo-吸塑) 备注：收到样品订单后尽快安排 ，注意样板品质质量要求要高于大货品质要求 ，送货时必须要附带送货单(没有送货单和QC检验合格报告的仓库一律拒绝收货)，请知悉，谢谢！ | W7: Angus | Z7: 97427-12.31 | AE7: # | BT7: =BT6-BJ7 -> 134028 | BU7: =BU6-BK7 -> 134028 | BV7: =BV6-BL7 -> 134028 | BW7: =BW6-BM7 -> 134028 | BX7: =BX6-BN7 -> 134028 | BY7: =BY6-BO7 -> 134028 | BZ7: =BZ6-BP7 -> 134028 | CA7: =CA6-BQ7 -> 134028 | CB7: =CB6-BR7 -> 22815
A8: 45714 | D8: ZMPO250144 | G8: 77685GQ1-S001 | H8: 40个空PDQ | I8: 40 | J8: 0 | K8: 40 | L8: =I8/K8 -> 1 | M8: 45726 | N8: 45722 | R8: 45714 | S8: 无 | T8: 无 | V8: Remark:大货最新版本/只需要空PDQ(PDQ可打平包/需配齐PDQ上原有的配件（列如-Demo-吸塑);备注：收到样品订单后尽快安排 ，注意样板品质质量要求要高于大货品质要求 ，送货时必须要附带送货单(没有送货单和QC检验合格报告的仓库一律拒绝收货)，请知悉，谢谢！ | W8: Angus | Z8: 94917-4.30 | AA8: 40 | AB8: =AA8-I8 -> 0 | AE8: # | AT8: =I8 -> 40 | BT8: =BT7-BJ8 -> 134028 | BU8: =BU7-BK8 -> 134028 | BV8: =BV7-BL8 -> 134028 | BW8: =BW7-BM8 -> 134028 | BX8: =BX7-BN8 -> 134028 | BY8: =BY7-BO8 -> 134028 | BZ8: =BZ7-BP8 -> 134028 | CA8: =CA7-BQ8 -> 134028 | CB8: =CB7-BR8 -> 22815
A9: 45714 | D9: ZMPO250144 | G9: 77685GQ2-S001 | H9: 40个空PDQ | I9: 40 | J9: 0 | K9: 40 | L9: =I9/K9 -> 1 | M9: 45726 | N9: 45722 | R9: 45714 | S9: 无 | T9: 无 | V9: Remark:大货最新版本/只需要空PDQ(PDQ可打平包/需配齐PDQ上原有的配件（列如-Demo-吸塑);备注：收到样品订单后尽快安排 ，注意样板品质质量要求要高于大货品质要求 ，送货时必须要附带送货单(没有送货单和QC检验合格报告的仓库一律拒绝收货)，请知悉，谢谢！ | W9: Angus | Z9: 94917-4.30 | AA9: 40 | AB9: =AA9-I9 -> 0 | AE9: # | AQ9: =I9 -> 40 | BT9: =BT8-BJ9 -> 134028 | BU9: =BU8-BK9 -> 134028 | BV9: =BV8-BL9 -> 134028 | BW9: =BW8-BM9 -> 134028 | BX9: =BX8-BN9 -> 134028 | BY9: =BY8-BO9 -> 134028 | BZ9: =BZ8-BP9 -> 134028 | CA9: =CA8-BQ9 -> 134028 | CB9: =CB8-BR9 -> 22815
A10: 45680 | B10: ALL BRANDS TOYS PTY LTD | C10: 澳大利亚 | D10: 4500156526 | E10: 83574 | F10: 4500156526-20 | G10: 77685GQ2-S001 | H10: 混搭恐龙27pcs/GQ2*2/箱 | I10: 3618 | J10: 0 | K10: 54 | L10: =I10/K10 -> 67 | M10: 45730 | N10: 45726 | O10: 东莞生产 | P10: pass | Q10: 3/26 截SI | R10: 45680 | S10: 无 | T10: 2/20进口商贴纸 | V10: 日期码格式：ZURU INC(BVI) 标准格式 日期：按实际生产日期 Packaging Info: 77685GQ2：MA_UPC版本包装（收缩膜和说明书, MA首选1L，如无1L可用多语且含英语的配套多语UPC包装）+ 1张客人通用进口商贴纸 Remark: 1.按实际生产日期; 2.出澳大利亚，请按照相应标准生产; | W10: Lydia Wu | X10: 0.9779 | Y10: =X10*I10 -> 3538.0422 | Z10: 94636-3.25 | AA10: =3101+75 -> 3176 | AB10: =AA10-I10 -> -442 | AC10: OK | AD10: 系统出单 | AE10: 77685GQ2-S001 | AF10: 已入 | AG10: =I10 -> 3618 | AH10: =I10 -> 3618 | AK10: =I10 -> 3618 | AN10: =I10 -> 3618 | AQ10: =I10/27 -> 134 | BJ10: =$I10*BJ$2 -> 442.82812 | BK10: =$I10*BK$2 -> 442.82812 | BL10: =$I10*BL$2 -> 442.82812 | BM10: =$I10*BM$2 -> 442.82812 | BN10: =$I10*BN$2 -> 442.82812 | BO10: =$I10*BO$2 -> 442.82812 | BP10: =$I10*BP$2 -> 442.82812 | BQ10: =$I10*BQ$2 -> 442.82812 | BR10: =$I10*BR$2 -> 75.375 | BT10: =BT9-BJ10 -> 133585.17 | BU10: =BU9-BK10 -> 133585.17 | BV10: =BV9-BL10 -> 133585.17 | BW10: =BW9-BM10 -> 133585.17 | BX10: =BX9-BN10 -> 133585.17 | BY10: =BY9-BO10 -> 133585.17 | BZ10: =BZ9-BP10 -> 133585.17 | CA10: =CA9-BQ10 -> 133585.17 | CB10: =CB9-BR10 -> 22739.625
A11: 45701 | B11: ZURU LLC | C11: 美国 | D11: 4500157378 | E11: 5200006139 | F11: 4500157378-20 | G11: 77723-S001-MTS | H11: 混搭恐龙2PK圆筒装 | I11: 492 | J11: 0 | K11: 12 | L11: =I11/K11 -> 41 | M11: 45734 | N11: 45730 | P11: pass | Q11: 3/28 交仓 | R11: 2/13外箱最长边不能超过25" （超过了，case pack只能为1） | S11: 无 | T11: 2/21空白贴纸 | V11: 日期码格式：ZURU INC(BVI) 标准格式 日期：按实际生产日期 Packaging Info: #77723=2PK STD #77685 PVC Tube. #77685 收缩膜MA 1L+空白贴纸覆盖UPC，空白贴纸图稿跟单提供。2PK铜板纸，收藏指南，说明书均为MA 5L标版。（两个球的配 比不能重复）。 Remark: 1.Amazon domestic 订单。出口美国。外箱最长边不能超过25" （超过了，case pack只能为1），不符合要求的大货，一律不接受。 2.无第三方验货/测试要求。 3.日期码使用ZURU标准版本。 | W11: SD24 | X11: 2.09 | Y11: =X11*I11 -> 1028.28 | Z11: ZB00056 | AA11: 492 | AB11: =AA11-I11 -> 0 | AC11: OK | AD11: 系统出单 | AE11: 77723-S001-MTS | AF11: 已入 | AG11: =I11*2 -> 984 | AH11: =I11*2 -> 984 | AK11: =I11*2 -> 984 | AN11: =I11*2 -> 984 | BF11: =I11 -> 492 | BG11: =I11 -> 492 | BJ11: =$I11*BJ$2*2 -> 120.4375 | BK11: =$I11*BK$2*2 -> 120.4375 | BL11: =$I11*BL$2*2 -> 120.4375 | BM11: =$I11*BM$2*2 -> 120.4375 | BN11: =$I11*BN$2*2 -> 120.4375 | BO11: =$I11*BO$2*2 -> 120.4375 | BP11: =$I11*BP$2*2 -> 120.4375 | BQ11: =$I11*BQ$2*2 -> 120.4375 | BR11: =$I11*BR$2*2 -> 20.5 | BT11: =BT10-BJ11 -> 133464.73 | BU11: =BU10-BK11 -> 133464.73 | BV11: =BV10-BL11 -> 133464.73 | BW11: =BW10-BM11 -> 133464.73 | BX11: =BX10-BN11 -> 133464.73 | BY11: =BY10-BO11 -> 133464.73 | BZ11: =BZ10-BP11 -> 133464.73 | CA11: =CA10-BQ11 -> 133464.73 | CB11: =CB10-BR11 -> 22719.125 | CD11: 2/17 已放MA 圆筒/彩纸/贴纸 | CE11: 10000 | CF11: 5000 | CH11: =CE11-I11 -> 9508 | CI11: =CF11-I11 -> 4508
A12: 45674 | B12: Smyths Toys EU HQ UC | C12: 德国 | D12: 4500156119 | F12: 4500156119-10 | G12: 77685GQ2-S002 | H12: 混搭恐龙27pcs/GQ2/箱 | I12: 10017 | J12: 0 | K12: 27 | L12: =I12/K12 -> 371 | M12: 45741 | N12: 45737 | P12: pass | Q12: 3/31 截SI | R12: 45674 | S12: 无 | T12: 无 | V12: 日期码格式：ZURU INC(BVI) 标准格式 日期：按实际生产日期 Packaging Info: 客版收缩膜(英法德意荷)翻单#4500155619 +客版5L slime bag 翻单#4500155619+MA 3L PDQ+MA5L(23L Warning)收藏指南+MA23L说明书+MA内袋 EAN # 4894680042612 Remark: 1. 此单出德国，需要满足Zuru Standard欧洲标准测试要求； 2. 请准时出货，推期会有罚款； 3. 出口欧洲，微塑料需符合法规； 4. 所有电子产品身上需要加字唛，为ZURU FRANCE 地址 (如无电子产品，或者产品布标有此地址，可忽略此信息) ZURU France 1/3, Rue d'Argenteuil 95210 SAINT-GRATIEN, FRANCE 5. 标准配比 | W12: Shirley Zhou | X12: 0.89 | Y12: =I12*X12 -> 8915.13 | Z12: 94676-3.31 | AA12: 10017 | AB12: =AA12-I12 -> 0 | AC12: 无 | AD12: 系统出单 | AE12: 77685GQ2-S002-客 | AF12: 已入 | AG12: =I12 -> 10017 | AJ12: =I12 -> 10017 | AM12: =I12 -> 10017 | AN12: =I12 -> 10017 | AR12: =I12/27 -> 371 | BJ12: =$I12*BJ$2 -> 1226.0391 | BK12: =$I12*BK$2 -> 1226.0391 | BL12: =$I12*BL$2 -> 1226.0391 | BM12: =$I12*BM$2 -> 1226.0391 | BN12: =$I12*BN$2 -> 1226.0391 | BO12: =$I12*BO$2 -> 1226.0391 | BP12: =$I12*BP$2 -> 1226.0391 | BQ12: =$I12*BQ$2 -> 1226.0391 | BR12: =$I12*BR$2 -> 208.6875 | BT12: =BT11-BJ12 -> 132238.7 | BU12: =BU11-BK12 -> 132238.7 | BV12: =BV11-BL12 -> 132238.7 | BW12: =BW11-BM12 -> 132238.7 | BX12: =BX11-BN12 -> 132238.7 | BY12: =BY11-BO12 -> 132238.7 | BZ12: =BZ11-BP12 -> 132238.7 | CA12: =CA11-BQ12 -> 132238.7 | CB12: =CB11-BR12 -> 22510.438
A13: 45670 | B13: Smyths Toys HQ UC UK | C13: 爱尔兰 | D13: 4500155619 | E13: PO4400458973 | F13: 4500155619-10 | G13: 77685GQ2-S002 | H13: 混搭恐龙27pcs/GQ2/箱 | I13: 8046 | J13: 0 | K13: 27 | L13: 298 | M13: 45741 | N13: 45737 | P13: pass | Q13: 3/27 截SI | R13: 45670 | S13: 无 | T13: 无 | V13: 日期码格式：ZURU INC(BVI) 标准格式 日期：按实际生产日期 Packaging Info: 77685GQ2：客版收缩膜(英法德意荷)+客版5L slime bag+MA 3L PDQ+MA5L(23L Warning)收藏指南+MA23L说明书 客户PO号码请参考remark Remark: 1）包装日期码按ZURU格式即可，请确保不迟于外箱日期码，可等于或者早于外箱日期码，必须为法定工作日，印刷前请先检查外箱日期码。 2）订单出英国，请注意检查产品及包装应带UKCA图标（14+产品除外），包装显示ZURU UK LTD/ZURU France地址信息，QC部门请查核，如有问题与跟单确认 3) 需要完全符合欧洲标准(符合微塑料法规)，否则不合法规会有客诉产生 | W13: Ula Zhao | X13: 0.89 | Y13: =I13*X13 -> 7160.94 | Z13: 94640-3.26 | AA13: =7452+594 -> 8046 | AB13: =AA13-I13 -> 0 | AC13: 无 | AD13: 系统出单 | AE13: 77685GQ2-S002-客 | AF13: 已入 | AG13: =I13 -> 8046 | AJ13: =I13 -> 8046 | AM13: =I13 -> 8046 | AN13: =I13 -> 8046 | AR13: =I13/27 -> 298 | BJ13: =$I13*BJ$2 -> 984.79687 | BK13: =$I13*BK$2 -> 984.79687 | BL13: =$I13*BL$2 -> 984.79687 | BM13: =$I13*BM$2 -> 984.79687 | BN13: =$I13*BN$2 -> 984.79687 | BO13: =$I13*BO$2 -> 984.79687 | BP13: =$I13*BP$2 -> 984.79687 | BQ13: =$I13*BQ$2 -> 984.79687 | BR13: =$I13*BR$2 -> 167.625 | BT13: =BT12-BJ13 -> 131253.9 | BU13: =BU12-BK13 -> 131253.9 | BV13: =BV12-BL13 -> 131253.9 | BW13: =BW12-BM13 -> 131253.9 | BX13: =BX12-BN13 -> 131253.9 | BY13: =BY12-BO13 -> 131253.9 | BZ13: =BZ12-BP13 -> 131253.9 | CA13: =CA12-BQ13 -> 131253.9 | CB13: =CB12-BR13 -> 22342.812
A14: 45670 | B14: Smyths Toys HQ UC UK | C14: 爱尔兰 | D14: 4500155619 | E14: PO4400458974 | F14: 4500155619-20 | G14: 77685GQ2-S002 | H14: 混搭恐龙27pcs/GQ2/箱 | I14: 2052 | J14: 0 | K14: 27 | L14: =I14/K14 -> 76 | M14: 45741 | N14: 45737 | P14: pass | Q14: 3/31 截SI | R14: 45670 | S14: 无 | T14: 无 | V14: 日期码格式：ZURU INC(BVI) 标准格式 日期：按实际生产日期 Packaging Info: 77685GQ2：客版收缩膜(英法德意荷)+客版5L slime bag+MA 3L PDQ+MA5L(23L Warning)收藏指南+MA23L说明书 客户PO号码请参考remark Remark: 1）包装日期码按ZURU格式即可，请确保不迟于外箱日期码，可等于或者早于外箱日期码，必须为法定工作日，印刷前请先检查外箱日期码。 2）订单出英国，请注意检查产品及包装应带UKCA图标（14+产品除外），包装显示ZURU UK LTD/ZURU France地址信息，QC部门请查核，如有问题与跟单确认 3) 需要完全符合欧洲标准(符合微塑料法规)，否则不合法规会有客诉产生 | W14: Ula Zhao | X14: 0.89 | Y14: =I14*X14 -> 1826.28 | Z14: 94667-3.29 | AA14: 2052 | AB14: =AA14-I14 -> 0 | AC14: 无 | AD14: 系统出单 | AE14: 77685GQ2-S002-客 | AF14: 已入 | AG14: =I14 -> 2052 | AJ14: =I14 -> 2052 | AM14: =I14 -> 2052 | AN14: =I14 -> 2052 | AR14: =I14/27 -> 76 | BJ14: =$I14*BJ$2 -> 251.15625 | BK14: =$I14*BK$2 -> 251.15625 | BL14: =$I14*BL$2 -> 251.15625 | BM14: =$I14*BM$2 -> 251.15625 | BN14: =$I14*BN$2 -> 251.15625 | BO14: =$I14*BO$2 -> 251.15625 | BP14: =$I14*BP$2 -> 251.15625 | BQ14: =$I14*BQ$2 -> 251.15625 | BR14: =$I14*BR$2 -> 42.75 | BT14: =BT13-BJ14 -> 131002.74 | BU14: =BU13-BK14 -> 131002.74 | BV14: =BV13-BL14 -> 131002.74 | BW14: =BW13-BM14 -> 131002.74 | BX14: =BX13-BN14 -> 131002.74 | BY14: =BY13-BO14 -> 131002.74 | BZ14: =BZ13-BP14 -> 131002.74 | CA14: =CA13-BQ14 -> 131002.74 | CB14: =CB13-BR14 -> 22300.062
A15: 45705 | B15: TARGET US | C15: 美国 | D15: 4500157763 | E15: 10001232830-0581 | F15: 4500157763-10 | G15: 77685GQ1-S002 | H15: 混搭恐龙13pcs/GQ1/箱 | I15: 18720 | J15: 0 | K15: 13 | L15: =I15/K15 -> 1440 | M15: 45770 | N15: 45766 | P15: pass | Q15: 6/9 客上柜 | R15: 45705 | S15: 无 | T15: 2/26条码箱贴纸客供+2/17 Event label贴纸 | U15: 已出样板 | V15: 日期码格式：ZURU INC(BVI) 标准格式 日期：按实际生产日期 Packaging Info: MA 1L 收缩膜+说明书, MA PDQ Remark: 1.77685GQ1-S002-5 SURPRISE-DINO MIX AND MATCH-SERIES 1-CAPSULE,13PCS/Gravity PDQ, 13PCS/PDQ/CTN。MA 1L 收缩膜+说明书, MA PDQ，产品UPC19305207905 2. 外箱正唛左上角位置粘贴条码箱贴纸，每箱只贴一张由ZURU订购,来料显示DPCI-087-26-6460, UPC 10193052079050. 3. 产品和包装上均要印刷tracking code信息，格式为ZURU常规格式。 4 .外箱正唛右侧空白位置粘贴一张Event label贴纸，由工厂自己订购。 5. 出货方式：货代自提，兴信出货。 | W15: Holly Zheng | X15: 0.765 | Y15: =X15*I15 -> 14320.8 | Z15: ZB00436-6.9 | AA15: 18720 | AB15: =AA15-I15 -> 0 | AC15: OK | AD15: 系统出单 | AE15: 77685GQ1-S002 | AF15: 已入 | AG15: =I15 -> 18720 | AH15: =I15 -> 18720 | AK15: =I15 -> 18720 | AN15: =I15 -> 18720 | AT15: =I15/13 -> 1440 | BJ15: =$I15*BJ$2 -> 2291.25 | BK15: =$I15*BK$2 -> 2291.25 | BL15: =$I15*BL$2 -> 2291.25 | BM15: =$I15*BM$2 -> 2291.25 | BN15: =$I15*BN$2 -> 2291.25 | BO15: =$I15*BO$2 -> 2291.25 | BP15: =$I15*BP$2 -> 2291.25 | BQ15: =$I15*BQ$2 -> 2291.25 | BR15: =$I15*BR$2 -> 390 | BT15: =BT14-BJ15 -> 128711.49 | BU15: =BU14-BK15 -> 128711.49 | BV15: =BV14-BL15 -> 128711.49 | BW15: =BW14-BM15 -> 128711.49 | BX15: =BX14-BN15 -> 128711.49 | BY15: =BY14-BO15 -> 128711.49 | BZ15: =BZ14-BP15 -> 128711.49 | CA15: =CA14-BQ15 -> 128711.49 | CB15: =CB14-BR15 -> 21910.062
A16: 45713 | B16: Ramp-s Corporation | C16: 菲律宾 | D16: 4500158563 | E16: PO-25-0003 | F16: 4500158563-10 | G16: 77685GQ2-S001 | H16: 混搭恐龙27pcs/GQ2*2/箱 | I16: 2052 | J16: 0 | K16: 54 | L16: =I16/K16 -> 38 | M16: 45749 | N16: 45745 | P16: pass | Q16: 4/3 截SI | R16: 45719 | S16: 无 | T16: 3/5 进口商贴纸 | V16: 日期码格式：ZURU INC(BVI) 标准格式 日期：按实际生产日期 Packaging Info: MA UPC包装+进口商贴纸,贴纸资料待提供 Remark | W16: Emma Wu | X16: 0.8048 | Y16: =X16*I16 -> 1651.4496 | Z16: 94696-4.3 | AA16: 2052 | AB16: =AA16-I16 -> 0 | AC16: OK | AD16: 系统出单 | AE16: 77685GQ2-S001 | AF16: 已入 | AG16: =I16 -> 2052 | AH16: =I16 -> 2052 | AK16: =I16 -> 2052 | AN16: =I16 -> 2052 | AQ16: =I16/27 -> 76 | BJ16: =$I16*BJ$2 -> 251.15625 | BK16: =$I16*BK$2 -> 251.15625 | BL16: =$I16*BL$2 -> 251.15625 | BM16: =$I16*BM$2 -> 251.15625 | BN16: =$I16*BN$2 -> 251.15625 | BO16: =$I16*BO$2 -> 251.15625 | BP16: =$I16*BP$2 -> 251.15625 | BQ16: =$I16*BQ$2 -> 251.15625 | BR16: =$I16*BR$2 -> 42.75 | BT16: =BT15-BJ16 -> 128460.34 | BU16: =BU15-BK16 -> 128460.34 | BV16: =BV15-BL16 -> 128460.34 | BW16: =BW15-BM16 -> 128460.34 | BX16: =BX15-BN16 -> 128460.34 | BY16: =BY15-BO16 -> 128460.34 | BZ16: =BZ15-BP16 -> 128460.34 | CA16: =CA15-BQ16 -> 128460.34 | CB16: =CB15-BR16 -> 21867.312
A17: 45719 | B17: THE WAREHOUSE LIMITED | C17: 新西兰 | D17: 4500159004 | E17: 28854700/1 | F17: 4500159004-10 | G17: 77685SK-S002 | H17: 混搭恐龙展示架带底座 | I17: 2508 | J17: 0 | K17: 66 | L17: =I17/K17 -> 38 | M17: 45756 | N17: 45751 | P17: PASS | Q17: 4/16 截SI | R17: 45719 | S17: 无 | T17: 无 | V17: 日期码格式：ZURU INC(BVI) 标准格式 日期：按实际生产日期 Packaging Info: MA UPC 英语包装（优先1L英语版本，或者3L/5L含英语都可） 此客人不接受易掉落或者剥落或者可直接触碰的闪粉，可降解也不行，但可以接受符合欧洲微塑料标准的珠光粉或者闪片。 Remark: | W17: Abby Liang | X17: 59.55 | Y17: =X17*L17 -> 2262.9 | Z17: 94964-5.10 | AA17: 2508 | AB17: =AA17-I17 -> 0 | AC17: 无 | AD17: 系统出单 | AE17: 77685SK-S002 | AF17: 已入 | AG17: =I17 -> 2508 | AH17: =I17 -> 2508 | AK17: =I17 -> 2508 | AN17: =I17 -> 2508 | BA17: =I17/66 -> 38 | BB17: =BA17 -> 38 | BJ17: =$I17*BJ$2 -> 306.96875 | BK17: =$I17*BK$2 -> 306.96875 | BL17: =$I17*BL$2 -> 306.96875 | BM17: =$I17*BM$2 -> 306.96875 | BN17: =$I17*BN$2 -> 306.96875 | BO17: =$I17*BO$2 -> 306.96875 | BP17: =$I17*BP$2 -> 306.96875 | BQ17: =$I17*BQ$2 -> 306.96875 | BR17: =$I17*BR$2 -> 52.25 | BT17: =BT16-BJ17 -> 128153.37 | BU17: =BU16-BK17 -> 128153.37 | BV17: =BV16-BL17 -> 128153.37 | BW17: =BW16-BM17 -> 128153.37 | BX17: =BX16-BN17 -> 128153.37 | BY17: =BY16-BO17 -> 128153.37 | BZ17: =BZ16-BP17 -> 128153.37 | CA17: =CA16-BQ17 -> 128153.37 | CB17: =CB16-BR17 -> 21815.062
A18: 45719 | B18: THE WAREHOUSE LIMITED | C18: 新西兰 | D18: 4500159005 | E18: 28854701/1 | F18: 4500159005-10 | G18: 77685SK-S002 | H18: 混搭恐龙展示架带底座 | I18: 792 | J18: 0 | K18: 66 | L18: =I18/K18 -> 12 | M18: 45756 | N18: 45751 | P18: PASS | R18: 45719 | S18: 无 | T18: 无 | V18: 日期码格式：ZURU INC(BVI) 标准格式 日期：按实际生产日期 Packaging Info: MA UPC 英语包装（优先1L英语版本，或者3L/5L含英语都可） 此客人不接受易掉落或者剥落或者可直接触碰的闪粉，可降解也不行，但可以接受符合欧洲微塑料标准的珠光粉或者闪片。 Remark: | W18: Abby Liang | X18: 59.55 | Y18: =X18*L18 -> 714.6 | Z18: 94965-5.10 | AA18: 792 | AB18: =AA18-I18 -> 0 | AC18: 无 | AD18: 系统出单 | AE18: 77685SK-S002 | AF18: 已入 | AG18: =I18 -> 792 | AH18: =I18 -> 792 | AK18: =I18 -> 792 | AN18: =I18 -> 792 | BA18: =I18/66 -> 12 | BB18: =BA18 -> 12 | BJ18: =$I18*BJ$2 -> 96.9375 | BK18: =$I18*BK$2 -> 96.9375 | BL18: =$I18*BL$2 -> 96.9375 | BM18: =$I18*BM$2 -> 96.9375 | BN18: =$I18*BN$2 -> 96.9375 | BO18: =$I18*BO$2 -> 96.9375 | BP18: =$I18*BP$2 -> 96.9375 | BQ18: =$I18*BQ$2 -> 96.9375 | BR18: =$I18*BR$2 -> 16.5 | BT18: =BT17-BJ18 -> 128056.43 | BU18: =BU17-BK18 -> 128056.43 | BV18: =BV17-BL18 -> 128056.43 | BW18: =BW17-BM18 -> 128056.43 | BX18: =BX17-BN18 -> 128056.43 | BY18: =BY17-BO18 -> 128056.43 | BZ18: =BZ17-BP18 -> 128056.43 | CA18: =CA17-BQ18 -> 128056.43 | CB18: =CB17-BR18 -> 21798.562
A19: 45713 | B19: Amazon ES | C19: 西班牙 | D19: 4500158469 | E19: Amazon ES: 4EASJCSI | F19: 4500158469-10 | G19: 77723-S001 | H19: 混搭恐龙2PK圆筒装 | I19: 492 | J19: 0 | K19: 12 | L19: =I19/K19 -> 41 | M19: 45757 | N19: 45754 | P19: PASS | Q19: 4/21 截SI | R19: 空白外箱（加印带Zuru字样的最新logo，除了邮包盒直接做外箱的产品） | S19: 有 | T19: 3/21 SSCC贴纸+空白贴纸 | V19: 日期码格式：ZURU INC(BVI) 标准格式 日期：按实际生产日期 Packaging Info: Amazon ES(77723) 1. 77723：2pk 77685 into pvc tube, 12tubes/ctn; MA 3L(3L warning EAN)A收缩膜+MA 1L(23L warning)A说明书+MA 1L A内袋+MA 5L(23L warning)A收藏指南+M A 5L A Slime胶袋+客版3L（5L warning UPC)PVC筒彩卡(含英法德意西警告语+UPC#+邮箱地址+FR/ES/IT环保标) 2. 最迟验货不得晚于2025/4/11; Remark: 1.空白外箱（加印带Zuru字样的最新logo，除了邮包盒直接做外箱的产品） + SSCC LABEL一张, 无箱唛，MADE IN CHINA 外箱只印一正一侧。箱唛资料按照给定的 标准去做即可，无需发回我方再行审批(新标准将另行通知)。 (SSCC LABEL竖贴在外箱正面的正中间，贴一面即可,贴纸离外箱边距必须至少3.2CM。如竖贴无法满足要求，则横贴。如横贴也无法满足要求，则竖贴，遮到ZURU lo go无影响), SSCC贴纸由工厂直接跟勤得采购或者工厂自行采购，每一张SSCC Label都是唯一且有不同流水及条码，且需要检查条码是否能正常扫描，另外，此贴纸 印刷不可出现模糊，溢出及粘胶不牢易脱落等现象，如工厂不按此要求导致贴纸有任何问题产生的罚款将由工厂承担一切责任 。 2.出往UK的产品+包装务必打上UKCA logo ，否则客人会退货且当地会有罚款。 3.订单必须经过ZURU QC验货并且通过后方可出货。 4.法国订单要求包装不使用矿物油，请按要求提供以下其中一份文件再出货 ，产品出到法国被相关部门抽检出现包装不符合此要求的，供应商需要为此承担责任， 故此请严格把关。 -油墨物质""由1 ~ 7个芳香环组成的MOAH""的包装检测报告，要求限值≤1.0%； -包装材料清单，包括包装油墨或物质的信息； -油墨制造商的证书； 5.每一批次出货只能有一个生产日期，不可多个生产日期混在同一批次出货；且邮包盒上必须统一加上日期码；外箱对于日期码没有硬性规定； 6.涉及到相关款式会有闪粉的或者微塑料的，请统一默认出无闪粉或者不含微塑料版本； 7.邮包盒及外箱封箱必须是工字型封箱方式； 8.5 Surprise or Mini Brands涉及包装是2个及2个以上的球入PVC桶包装时，单个球上若有UPC#或者EAN#，请用白色贴纸覆盖住； | W19: Crystal Chen | X19: 1.8938 | Y19: =X19*I19 -> 931.7496 | Z19: 94786-4.17 | AA19: 492 | AB19: =AA19-I19 -> 0 | AC19: OK | AD19: 系统出单 | AE19: 77723-S001 | AF19: 已入 | AG19: =I19*2 -> 984 | AH19: =I19*2 -> 984 | AL19: =I19*2 -> 984 | AN19: =I19*2 -> 984 | BF19: =I19 -> 492 | BG19: =I19 -> 492 | BJ19: =$I19*BJ$2*2 -> 120.4375 | BK19: =$I19*BK$2*2 -> 120.4375 | BL19: =$I19*BL$2*2 -> 120.4375 | BM19: =$I19*BM$2*2 -> 120.4375 | BN19: =$I19*BN$2*2 -> 120.4375 | BO19: =$I19*BO$2*2 -> 120.4375 | BP19: =$I19*BP$2*2 -> 120.4375 | BQ19: =$I19*BQ$2*2 -> 120.4375 | BR19: =$I19*BR$2*2 -> 20.5 | BT19: =BT18-BJ19 -> 127935.99 | BU19: =BU18-BK19 -> 127935.99 | BV19: =BV18-BL19 -> 127935.99 | BW19: =BW18-BM19 -> 127935.99 | BX19: =BX18-BN19 -> 127935.99 | BY19: =BY18-BO19 -> 127935.99 | BZ19: =BZ18-BP19 -> 127935.99 | CA19: =CA18-BQ19 -> 127935.99 | CB19: =CB18-BR19 -> 21778.062 | CD19: 2/17 已放MA 圆筒/彩纸/贴纸 | CH19: =CH11-I19 -> 9016 | CI19: =CI11-I19 -> 4016
A20: 45720 | B20: AMAZON UK | C20: 德国 | D20: 4500158578 | E20: Amazon DE: 1WYS31BD | F20: 4500158578-160 | G20: 77723-S001 | H20: 混搭恐龙2PK圆筒装 | I20: 744 | J20: 0 | K20: 12 | L20: =I20/K20 -> 62 | M20: 45757 | N20: 45754 | P20: PASS | Q20: 4/27 截SI | R20: 空白外箱（加印带Zuru字样的最新logo，除了邮包盒直接做外箱的产品） | S20: 有 | T20: 3/18 SSCC贴纸+空白贴纸 | V20: 日期码格式：ZURU INC(BVI) 标准格式 日期：按实际生产日期 Packaging Info: Amazon UK(15726BEK/15728BEG/15762ABDE)/DE(15726EK/15728B/15762A/77723)/FR(77723) 4. 77723: 2pk 77685 into pvc tube, 12tubes/ctn; MA 3L(3L warning EAN)A收缩膜+MA 1L(23L warning)A说明书+MA 1L A内袋+MA 5L(23L warning)A收藏指南+M A 5L A Slime胶袋+客版PVC筒彩卡(含英法德意西5L警告语+UPC#+邮箱地址+FR/ES/IT环保标，参考翻单PO#4500158469)； 5. 验货时间不迟于2025/4/11. Remark: 1.空白外箱（加印带Zuru字样的最新logo，除了邮包盒直接做外箱的产品） + SSCC LABEL一张, 无箱唛，MADE IN CHINA 外箱只印一正一侧。箱唛资料按照给定的 标准去做即可，无需发回我方再行审批(新标准将另行通知)。 (SSCC LABEL竖贴在外箱正面的正中间，贴一面即可,贴纸离外箱边距必须至少3.2CM。如竖贴无法满足要求，则横贴。如横贴也无法满足要求，则竖贴，遮到ZURU lo go无影响), SSCC贴纸由工厂直接跟勤得采购或者工厂自行采购，每一张SSCC Label都是唯一且有不同流水及条码，且需要检查条码是否能正常扫描，另外，此贴纸 印刷不可出现模糊，溢出及粘胶不牢易脱落等现象，如工厂不按此要求导致贴纸有任何问题产生的罚款将由工厂承担一切责任 。 2.出往UK的产品+包装务必打上UKCA logo ，否则客人会退货且当地会有罚款。 3.订单必须经过ZURU QC验货并且通过后方可出货。 4.法国订单要求包装不使用矿物油，请按要求提供以下其中一份文件再出货 ，产品出到法国被相关部门抽检出现包装不符合此要求的，供应商需要为此承担责任， 故此请严格把关。 -油墨物质""由1 ~ 7个芳香环组成的MOAH""的包装检测报告，要求限值≤1.0%； -包装材料清单，包括包装油墨或物质的信息； -油墨制造商的证书； 5.每一批次出货只能有一个生产日期，不可多个生产日期混在同一批次出货；且邮包盒上必须统一加上日期码；外箱对于日期码没有硬性规定； 6.涉及到相关款式会有闪粉的或者微塑料的，请统一默认出无闪粉或者不含微塑料版本； 7.邮包盒及外箱封箱必须是工字型封箱方式； 8.5 Surprise or Mini Brands涉及包装是2个及2个以上的球入PVC桶包装时，单个球上若有UPC#或者EAN#，请用白色贴纸覆盖住 | W20: Crystal Chen | X20: 1.8626 | Y20: =X20*I20 -> 1385.7744 | Z20: 94813-4.22 | AA20: 744 | AB20: =AA20-I20 -> 0 | AC20: OK | AD20: 系统出单 | AE20: 77723-S001 | AF20: 已入 | AG20: =I20*2 -> 1488 | AH20: =I20*2 -> 1488 | AL20: =I20*2 -> 1488 | AN20: =I20*2 -> 1488 | BF20: =I20 -> 744 | BG20: =I20 -> 744 | BJ20: =$I20*BJ$2*2 -> 182.125 | BK20: =$I20*BK$2*2 -> 182.125 | BL20: =$I20*BL$2*2 -> 182.125 | BM20: =$I20*BM$2*2 -> 182.125 | BN20: =$I20*BN$2*2 -> 182.125 | BO20: =$I20*BO$2*2 -> 182.125 | BP20: =$I20*BP$2*2 -> 182.125 | BQ20: =$I20*BQ$2*2 -> 182.125 | BR20: =$I20*BR$2*2 -> 31 | BT20: =BT19-BJ20 -> 127753.87 | BU20: =BU19-BK20 -> 127753.87 | BV20: =BV19-BL20 -> 127753.87 | BW20: =BW19-BM20 -> 127753.87 | BX20: =BX19-BN20 -> 127753.87 | BY20: =BY19-BO20 -> 127753.87 | BZ20: =BZ19-BP20 -> 127753.87 | CA20: =CA19-BQ20 -> 127753.87 | CB20: =CB19-BR20 -> 21747.062 | CD20: 2/17 已放MA 圆筒/彩纸/贴纸 | CH20: =CH19-I20 -> 8272 | CI20: =CI19-I20 -> 3272
A21: 45720 | B21: AMAZON UK | C21: 法国 | D21: 4500158578 | E21: Amazon FR: 1YINQXLS | F21: 4500158578-180 | G21: 77723-S001 | H21: 混搭恐龙2PK圆筒装 | I21: 492 | J21: 0 | K21: 12 | L21: =I21/K21 -> 41 | M21: 45757 | N21: 45754 | P21: PASS | Q21: 4/27 截SI | R21: 空白外箱（加印带Zuru字样的最新logo，除了邮包盒直接做外箱的产品） | S21: 有 | T21: 3/18 SSCC贴纸+空白贴纸 | V21: 日期码格式：ZURU INC(BVI) 标准格式 日期：按实际生产日期 Packaging Info: Amazon UK(15726BEK/15728BEG/15762ABDE)/DE(15726EK/15728B/15762A/77723)/FR(77723) 4. 77723: 2pk 77685 into pvc tube, 12tubes/ctn; MA 3L(3L warning EAN)A收缩膜+MA 1L(23L warning)A说明书+MA 1L A内袋+MA 5L(23L warning)A收藏指南+M A 5L A Slime胶袋+客版PVC筒彩卡(含英法德意西5L警告语+UPC#+邮箱地址+FR/ES/IT环保标，参考翻单PO#4500158469)； 5. 验货时间不迟于2025/4/11. Remark: 1.空白外箱（加印带Zuru字样的最新logo，除了邮包盒直接做外箱的产品） + SSCC LABEL一张, 无箱唛，MADE IN CHINA 外箱只印一正一侧。箱唛资料按照给定的 标准去做即可，无需发回我方再行审批(新标准将另行通知)。 (SSCC LABEL竖贴在外箱正面的正中间，贴一面即可,贴纸离外箱边距必须至少3.2CM。如竖贴无法满足要求，则横贴。如横贴也无法满足要求，则竖贴，遮到ZURU lo go无影响), SSCC贴纸由工厂直接跟勤得采购或者工厂自行采购，每一张SSCC Label都是唯一且有不同流水及条码，且需要检查条码是否能正常扫描，另外，此贴纸 印刷不可出现模糊，溢出及粘胶不牢易脱落等现象，如工厂不按此要求导致贴纸有任何问题产生的罚款将由工厂承担一切责任 。 2.出往UK的产品+包装务必打上UKCA logo ，否则客人会退货且当地会有罚款。 3.订单必须经过ZURU QC验货并且通过后方可出货。 4.法国订单要求包装不使用矿物油，请按要求提供以下其中一份文件再出货 ，产品出到法国被相关部门抽检出现包装不符合此要求的，供应商需要为此承担责任， 故此请严格把关。 -油墨物质""由1 ~ 7个芳香环组成的MOAH""的包装检测报告，要求限值≤1.0%； -包装材料清单，包括包装油墨或物质的信息； -油墨制造商的证书； 5.每一批次出货只能有一个生产日期，不可多个生产日期混在同一批次出货；且邮包盒上必须统一加上日期码；外箱对于日期码没有硬性规定； 6.涉及到相关款式会有闪粉的或者微塑料的，请统一默认出无闪粉或者不含微塑料版本； 7.邮包盒及外箱封箱必须是工字型封箱方式； 8.5 Surprise or Mini Brands涉及包装是2个及2个以上的球入PVC桶包装时，单个球上若有UPC#或者EAN#，请用白色贴纸覆盖住 | W21: Crystal Chen | X21: 1.8626 | Y21: =X21*I21 -> 916.3992 | Z21: 94834-4.24 | AA21: 492 | AB21: =AA21-I21 -> 0 | AC21: OK | AD21: 系统出单 | AE21: 77723-S001 | AF21: 已入 | AG21: =I21*2 -> 984 | AH21: =I21*2 -> 984 | AL21: =I21*2 -> 984 | AN21: =I21*2 -> 984 | BF21: =I21 -> 492 | BG21: =I21 -> 492 | BJ21: =$I21*BJ$2*2 -> 120.4375 | BK21: =$I21*BK$2*2 -> 120.4375 | BL21: =$I21*BL$2*2 -> 120.4375 | BM21: =$I21*BM$2*2 -> 120.4375 | BN21: =$I21*BN$2*2 -> 120.4375 | BO21: =$I21*BO$2*2 -> 120.4375 | BP21: =$I21*BP$2*2 -> 120.4375 | BQ21: =$I21*BQ$2*2 -> 120.4375 | BR21: =$I21*BR$2*2 -> 20.5 | BT21: =BT20-BJ21 -> 127633.43 | BU21: =BU20-BK21 -> 127633.43 | BV21: =BV20-BL21 -> 127633.43 | BW21: =BW20-BM21 -> 127633.43 | BX21: =BX20-BN21 -> 127633.43 | BY21: =BY20-BO21 -> 127633.43 | BZ21: =BZ20-BP21 -> 127633.43 | CA21: =CA20-BQ21 -> 127633.43 | CB21: =CB20-BR21 -> 21726.562 | CD21: 2/17 已放MA 圆筒/彩纸/贴纸 | CH21: =CH20-I21 -> 7780 | CI21: =CI20-I21 -> 2780
A22: 45737 | B22: ASIA GOAL LIMITED | C22: 香港 | D22: 4500160929 | E22: AG240425-HK | F22: 4500160929-20 | G22: 77685GQ1-S001 | H22: 混搭恐龙13pcs/GQ1*4/箱 | I22: 780 | J22: 0 | K22: 52 | L22: =I22/K22 -> 15 | M22: 45761 | N22: 45757 | P22: pass | Q22: 4/16 截SI | R22: 45737 | S22: 无 | T22: 4/3客供警语贴纸 | V22: 日期码格式：ZURU INC(BVI) 标准格式 日期：按实际生产日期 Packaging Info: 71152：MA 1L PKG， MA 说明书+客供警语贴纸 77685GQ1：MA 1L PKG, MA PDQ, MA 收藏指南+4张客供警语贴纸 (1张贴球底部，1张贴收藏指南，1张贴说明书上，1张贴口水胶袋子上) Remark: 此单出香港 | W22: Doris Shou | X22: 0.8533 | Y22: =X22*I22 -> 665.574 | Z22: 94777-4.16 | AA22: 780 | AB22: =AA22-I22 -> 0 | AC22: OK | AD22: 系统出单 | AE22: 77685GQ1-S001 | AF22: 已入 | AG22: =I22 -> 780 | AH22: =I22 -> 780 | AK22: =I22 -> 780 | AN22: =I22 -> 780 | AT22: =I22/13 -> 60 | BJ22: =$I22*BJ$2 -> 95.46875 | BK22: =$I22*BK$2 -> 95.46875 | BL22: =$I22*BL$2 -> 95.46875 | BM22: =$I22*BM$2 -> 95.46875 | BN22: =$I22*BN$2 -> 95.46875 | BO22: =$I22*BO$2 -> 95.46875 | BP22: =$I22*BP$2 -> 95.46875 | BQ22: =$I22*BQ$2 -> 95.46875 | BR22: =$I22*BR$2 -> 16.25 | BT22: =BT21-BJ22 -> 127537.96 | BU22: =BU21-BK22 -> 127537.96 | BV22: =BV21-BL22 -> 127537.96 | BW22: =BW21-BM22 -> 127537.96 | BX22: =BX21-BN22 -> 127537.96 | BY22: =BY21-BO22 -> 127537.96 | BZ22: =BZ21-BP22 -> 127537.96 | CA22: =CA21-BQ22 -> 127537.96 | CB22: =CB21-BR22 -> 21710.312
A23: 45720 | B23: HARVEY WHOLESALE LTD | C23: 新西兰 | D23: 4500159074 | E23: 3002 | F23: 4500159074-10 | G23: 77685GQ2-S002 | H23: 混搭恐龙27pcs/GQ2/箱 | I23: 1350 | J23: 0 | K23: 27 | L23: =I23/K23 -> 50 | M23: 45763 | N23: 45758 | P23: pass | Q23: 4/17 截SI | R23: 45720 | S23: 无 | T23: 无 | V23: 日期码格式：ZURU INC(BVI) 标准格式 日期：按实际生产日期 Packaging Info: Remark: MA UPC 英语包装（优先1L英语版本,或者3L/L含英语即可 | W23: Abby Liang | X23: 0.89 | Y23: =X23*I23 -> 1201.5 | Z23: 94768-4.15 | AA23: 1350 | AB23: =AA23-I23 -> 0 | AC23: 无 | AD23: 系统出单 | AE23: 77685GQ2-S002 | AF23: 已入 | AG23: =I23 -> 1350 | AH23: =I23 -> 1350 | AK23: =I23 -> 1350 | AN23: =I23 -> 1350 | AQ23: =I23/27 -> 50 | BJ23: =$I23*BJ$2 -> 165.23438 | BK23: =$I23*BK$2 -> 165.23438 | BL23: =$I23*BL$2 -> 165.23438 | BM23: =$I23*BM$2 -> 165.23438 | BN23: =$I23*BN$2 -> 165.23438 | BO23: =$I23*BO$2 -> 165.23438 | BP23: =$I23*BP$2 -> 165.23438 | BQ23: =$I23*BQ$2 -> 165.23438 | BR23: =$I23*BR$2 -> 28.125 | BT23: =BT22-BJ23 -> 127372.73 | BU23: =BU22-BK23 -> 127372.73 | BV23: =BV22-BL23 -> 127372.73 | BW23: =BW22-BM23 -> 127372.73 | BX23: =BX22-BN23 -> 127372.73 | BY23: =BY22-BO23 -> 127372.73 | BZ23: =BZ22-BP23 -> 127372.73 | CA23: =CA22-BQ23 -> 127372.73 | CB23: =CB22-BR23 -> 21682.188
A24: 45733 | B24: Distruibuciones Universales, SA - D | C24: 洪都拉斯 | D24: 4500160421 | F24: 4500160421-120 | G24: 77685GQ2-S001 | H24: 混搭恐龙27pcs/GQ2*2/箱 | I24: 378 | J24: 0 | K24: 54 | L24: =I24/K24 -> 7 | M24: 45768 | N24: 45764 | P24: 自检 | Q24: 4/22 截SI | R24: 45736 | S24: 无 | T24: 3/25 UPC贴纸 | V24: 日期码格式：ZURU INC(BVI) 标准格式 日期：按实际生产日期 Packaging Info: 77685GQ2: MA多语EAN包装+UPC贴纸+MA多语收藏指南+MA多语PDQ+箱唛 Remark: | W24: Ava Liang | X24: 0.9779 | Y24: =X24*I24 -> 369.6462 | Z24: 94795-4.18 | AA24: 378 | AB24: =AA24-I24 -> 0 | AC24: OK | AD24: 系统出单 | AE24: 77685GQ2-S001-3L | AF24: 已入 | AG24: =I24 -> 378 | AH24: =I24 -> 378 | AL24: =I24 -> 378 | AN24: =I24 -> 378 | AR24: =I24/27 -> 14 | BJ24: =$I24*BJ$2 -> 46.265625 | BK24: =$I24*BK$2 -> 46.265625 | BL24: =$I24*BL$2 -> 46.265625 | BM24: =$I24*BM$2 -> 46.265625 | BN24: =$I24*BN$2 -> 46.265625 | BO24: =$I24*BO$2 -> 46.265625 | BP24: =$I24*BP$2 -> 46.265625 | BQ24: =$I24*BQ$2 -> 46.265625 | BR24: =$I24*BR$2 -> 7.875 | BT24: =BT23-BJ24 -> 127326.46 | BU24: =BU23-BK24 -> 127326.46 | BV24: =BV23-BL24 -> 127326.46 | BW24: =BW23-BM24 -> 127326.46 | BX24: =BX23-BN24 -> 127326.46 | BY24: =BY23-BO24 -> 127326.46 | BZ24: =BZ23-BP24 -> 127326.46 | CA24: =CA23-BQ24 -> 127326.46 | CB24: =CB23-BR24 -> 21674.312
A25: 45749 | D25: ZMPO250285 | G25: 77685-S001 | H25: 60套散件 | I25: 60 | J25: 0 | K25: 24 | L25: =I25/K25 -> 2.5 | M25: 45768 | N25: 45764 | P25: # | R25: 45749 | S25: 无 | T25: 无 | V25: Remark:大货最新版本/只需要齐全套散件/麻烦用胶袋分装好一套为一袋/箱唛参照邮件附件;备注：收到样品订单后尽快安排 ，注意样板品质质量要求要高于大货品质要求 ，送货时必须要附带送货单(没有送货单和QC检验合格报告的仓库一律拒绝收货)，请知悉，谢谢！ | W25: Angus | Z25: 94916-4.30 | AA25: 60 | AB25: =AA25-I25 -> 0 | AC25: 无 | AE25: # | BJ25: 60 | BK25: 60 | BL25: 60 | BM25: 60 | BN25: 60 | BO25: 60 | BP25: 60 | BQ25: 60 | BR25: 60 | BT25: =BT24-BJ25 -> 127266.46 | BU25: =BU24-BK25 -> 127266.46 | BV25: =BV24-BL25 -> 127266.46 | BW25: =BW24-BM25 -> 127266.46 | BX25: =BX24-BN25 -> 127266.46 | BY25: =BY24-BO25 -> 127266.46 | BZ25: =BZ24-BP25 -> 127266.46 | CA25: =CA24-BQ25 -> 127266.46 | CB25: =CB24-BR25 -> 21614.312
A26: 45749 | D26: ZMPO250285 | G26: 77685GQ1-S001 | H26: 50个满PDQ(650PCS) | I26: 650 | J26: 0 | K26: 52 | L26: =I26/K26 -> 12.5 | M26: 45768 | N26: 45764 | P26: pass | R26: 45749 | S26: 无 | T26: 无 | V26: Remark:大货最新版本/产品按大货比例/大货标准箱装箱/箱唛参照邮件附件;备注：收到样品订单后尽快安排 ，注意样板品质质量要求要高于大货品质要求 ，送货时必须要附带送货单(没有送货单和QC检验合格报告的仓库一律拒绝收货)，请知悉，谢谢！ | W26: Angus | Z26: 94916-4.30 | AA26: 650 | AB26: =AA26-I26 -> 0 | AC26: 无 | AD26: 系统出单 | AE26: 77685GQ1-S001 | AF26: 已入 | AG26: =I26 -> 650 | AH26: =I26 -> 650 | AK26: =I26 -> 650 | AN26: =I26 -> 650 | AT26: =I26/13 -> 50 | BJ26: =$I26*BJ$2 -> 79.557292 | BK26: =$I26*BK$2 -> 79.557292 | BL26: =$I26*BL$2 -> 79.557292 | BM26: =$I26*BM$2 -> 79.557292 | BN26: =$I26*BN$2 -> 79.557292 | BO26: =$I26*BO$2 -> 79.557292 | BP26: =$I26*BP$2 -> 79.557292 | BQ26: =$I26*BQ$2 -> 79.557292 | BR26: =$I26*BR$2 -> 13.541667 | BT26: =BT25-BJ26 -> 127186.9 | BU26: =BU25-BK26 -> 127186.9 | BV26: =BV25-BL26 -> 127186.9 | BW26: =BW25-BM26 -> 127186.9 | BX26: =BX25-BN26 -> 127186.9 | BY26: =BY25-BO26 -> 127186.9 | BZ26: =BZ25-BP26 -> 127186.9 | CA26: =CA25-BQ26 -> 127186.9 | CB26: =CB25-BR26 -> 21600.771
A27: 45749 | D27: ZMPO250285 | G27: 77685GQ2-S001 | H27: 50个满PDQ(1350PCS) | I27: 1350 | J27: 0 | K27: 54 | L27: =I27/K27 -> 25 | M27: 45768 | N27: 45764 | P27: pass | R27: 45749 | S27: 无 | T27: 无 | V27: Remark:大货最新版本/产品按大货比例/大货标准箱装箱/箱唛参照邮件附件;备注：收到样品订单后尽快安排 ，注意样板品质质量要求要高于大货品质要求 ，送货时必须要附带送货单(没有送货单和QC检验合格报告的仓库一律拒绝收货)，请知悉，谢谢！ | W27: Angus | Z27: 94916-4.30 | AA27: 1350 | AB27: =AA27-I27 -> 0 | AC27: 无 | AD27: 系统出单 | AE27: 77685GQ2-S001 | AF27: 已入 | AG27: =I27 -> 1350 | AH27: =I27 -> 1350 | AK27: =I27 -> 1350 | AN27: =I27 -> 1350 | AQ27: =I27/27 -> 50 | BJ27: =$I27*BJ$2 -> 165.23438 | BK27: =$I27*BK$2 -> 165.23438 | BL27: =$I27*BL$2 -> 165.23438 | BM27: =$I27*BM$2 -> 165.23438 | BN27: =$I27*BN$2 -> 165.23438 | BO27: =$I27*BO$2 -> 165.23438 | BP27: =$I27*BP$2 -> 165.23438 | BQ27: =$I27*BQ$2 -> 165.23438 | BR27: =$I27*BR$2 -> 28.125 | BT27: =BT26-BJ27 -> 127021.67 | BU27: =BU26-BK27 -> 127021.67 | BV27: =BV26-BL27 -> 127021.67 | BW27: =BW26-BM27 -> 127021.67 | BX27: =BX26-BN27 -> 127021.67 | BY27: =BY26-BO27 -> 127021.67 | BZ27: =BZ26-BP27 -> 127021.67 | CA27: =CA26-BQ27 -> 127021.67 | CB27: =CB26-BR27 -> 21572.646
A28: 45729 | B28: Babyhouse | C28: 乌兹别克斯坦 | D28: 4500159866 | F28: 4500159866-10 | G28: 77685GQ1-S001 | H28: 混搭恐龙13pcs/GQ1*4/箱 | I28: 208 | J28: 0 | K28: 52 | L28: =I28/K28 -> 4 | M28: 45769 | N28: 45765 | P28: 自检 | Q28: 4/22 客上柜 | R28: 45729 | S28: 无 | T28: 3/14 进口商贴纸 | V28: 日期码格式：ZURU INC(BVI) 标准格式 日期：按实际生产日期 Packaging Info: 77685: 1L MA 收缩膜 + 进口商贴纸 ; MA 说明书/指南（如有）; Remark: 标准配比 | W28: Ann Zhang | X28: 0.945 | Y28: =X28*I28 -> 196.56 | Z28: 94879-4.29 | AA28: 208 | AB28: =AA28-I28 -> 0 | AC28: OK | AD28: 系统出单 | AE28: 77685GQ1-S001 | AF28: 已入 | AG28: =I28 -> 208 | AH28: =I28 -> 208 | AK28: =I28 -> 208 | AN28: =I28 -> 208 | AT28: =I28/13 -> 16 | BJ28: =$I28*BJ$2 -> 25.458333 | BK28: =$I28*BK$2 -> 25.458333 | BL28: =$I28*BL$2 -> 25.458333 | BM28: =$I28*BM$2 -> 25.458333 | BN28: =$I28*BN$2 -> 25.458333 | BO28: =$I28*BO$2 -> 25.458333 | BP28: =$I28*BP$2 -> 25.458333 | BQ28: =$I28*BQ$2 -> 25.458333 | BR28: =$I28*BR$2 -> 4.3333333 | BT28: =BT27-BJ28 -> 126996.21 | BU28: =BU27-BK28 -> 126996.21 | BV28: =BV27-BL28 -> 126996.21 | BW28: =BW27-BM28 -> 126996.21 | BX28: =BX27-BN28 -> 126996.21 | BY28: =BY27-BO28 -> 126996.21 | BZ28: =BZ27-BP28 -> 126996.21 | CA28: =CA27-BQ28 -> 126996.21 | CB28: =CB27-BR28 -> 21568.312
A29: 45737 | B29: ASIA GOAL LIMITED TAIWAN BRANCH (H. | C29: 台湾 | D29: 4500160940 | E29: AG240426-TW | F29: 4500160940-10 | G29: 77685GQ1-S001 | H29: 混搭恐龙13pcs/GQ1*4/箱 | I29: 780 | J29: 0 | K29: 52 | L29: =I29/K29 -> 15 | M29: 45772 | N29: 45768 | P29: pass | Q29: 4/29 截SI | R29: 45737 | S29: 无 | T29: 3.28警语贴纸 | V29: 日期码格式：ZURU INC(BVI) 标准格式 日期：按实际生产日期 Packaging Info: MA 1L PKG, MA 1L PDQ +MA 收藏指南说明书+1张警语贴纸（贴球底部） Remark: 此单出台湾 | W29: Doris Shou | X29: 0.945 | Y29: =X29*I29 -> 737.1 | Z29: 94842-4.25 | AA29: 780 | AB29: =AA29-I29 -> 0 | AC29: OK | AD29: 系统出单 | AE29: 77685GQ1-S001 | AF29: 已入 | AG29: =I29 -> 780 | AH29: =I29 -> 780 | AK29: =I29 -> 780 | AN29: =I29 -> 780 | AT29: =I29/13 -> 60 | BJ29: =$I29*BJ$2 -> 95.46875 | BK29: =$I29*BK$2 -> 95.46875 | BL29: =$I29*BL$2 -> 95.46875 | BM29: =$I29*BM$2 -> 95.46875 | BN29: =$I29*BN$2 -> 95.46875 | BO29: =$I29*BO$2 -> 95.46875 | BP29: =$I29*BP$2 -> 95.46875 | BQ29: =$I29*BQ$2 -> 95.46875 | BR29: =$I29*BR$2 -> 16.25 | BT29: =BT28-BJ29 -> 126900.74 | BU29: =BU28-BK29 -> 126900.74 | BV29: =BV28-BL29 -> 126900.74 | BW29: =BW28-BM29 -> 126900.74 | BX29: =BX28-BN29 -> 126900.74 | BY29: =BY28-BO29 -> 126900.74 | BZ29: =BZ28-BP29 -> 126900.74 | CA29: =CA28-BQ29 -> 126900.74 | CB29: =CB28-BR29 -> 21552.062
A30: 45726 | B30: WAL-MART STORES INC. USA | C30: 美国 | D30: 4500159701 | E30: 0904512381 | F30: 4500159701-10 | G30: 77685SLB-S001 | H30: 混搭恐龙卡板装12pcs/GQ4/CTN**96/Slip Sheet | I30: 1152 | J30: 0 | K30: 1152 | L30: =I30/K30 -> 1 | M30: 45770 | N30: 45768 | O30: 4/23 第三方抽办+验货 | P30: pass | Q30: 5/15 截SI | R30: 首单，3/25 | S30: 有 | T30: 3/21 RFID+艾利贴纸（不干胶贴纸）和一张普通贴纸（A4纸） | V30: 日期码格式：ZURU DGYYYYMMDD CHINA(日期避开周末和法定节假日即可） 日期：按实际生产日期 Packaging Info: 77685SLB-S001： 1.包装要求： MA 1L A版收缩膜+MA A版纸袋+MA 5L A版收藏指南+MA A版slime bag+客版1L PDQ 每pcs产品上要贴1张RFID贴纸，贴纸由ZURU提供，贴纸位置请严格按照我们签回的签板； Remark: 77685SLB-S001： 1.包装要求： MA 1L A版收缩膜+MA A版纸袋+MA 5L A版收藏指南+MA A版slime bag+客版1L PDQ 每pcs产品上要贴1张RFID贴纸，贴纸由ZURU提供，贴纸位置请严格按照我们签回的签板； 2. 外箱印刷带条码的RFID箱唛：RFID紫色色带+WM Dept.图标+RFID图标+ITF-14条码，四面右下角印刷ZURU logo, ITFF条码只印刷在正唛一面，在加印的时候确保 条形码能扫描出来，外箱侧面任一角落加印："MADE IN CHINA" 字样； 3. 每个slip sheet上面贴一张艾利贴纸（不干胶贴纸）和一张普通贴纸（A4纸），slip sheet打印的普通贴纸的尺寸不能比艾利贴纸小，普通贴纸内容见附件； 4. 在产品上和包装上要有日期码、以及要有MADE IN CHINA和ZURU字样； 5. 产品如有扎带口要剪平，不能刮手。 6. 此单需要抽板和验货，抽板时间预计4/23，请多备料 7. 此单以slip sheet出货，77685：1152pcs/96CTN/Slip Sheet | W30: Maggie Xie | X30: 903.2128 | Y30: =X30*L30 -> 903.2128 | Z30: ZB00268-5.16 | AA30: 1152 | AB30: =AA30-I30 -> 0 | AD30: 系统出单 | AE30: 77685SLB-S001 | AF30: 已入 | AG30: =I30 -> 1152 | AH30: =I30 -> 1152 | AK30: =I30 -> 1152 | AN30: =I30 -> 1152 | AV30: =I30/12 -> 96 | BJ30: =$I30*BJ$2 -> 141 | BK30: =$I30*BK$2 -> 141 | BL30: =$I30*BL$2 -> 141 | BM30: =$I30*BM$2 -> 141 | BN30: =$I30*BN$2 -> 141 | BO30: =$I30*BO$2 -> 141 | BP30: =$I30*BP$2 -> 141 | BQ30: =$I30*BQ$2 -> 141 | BR30: =$I30*BR$2 -> 24 | BT30: =BT29-BJ30 -> 126759.74 | BU30: =BU29-BK30 -> 126759.74 | BV30: =BV29-BL30 -> 126759.74 | BW30: =BW29-BM30 -> 126759.74 | BX30: =BX29-BN30 -> 126759.74 | BY30: =BY29-BO30 -> 126759.74 | BZ30: =BZ29-BP30 -> 126759.74 | CA30: =CA29-BQ30 -> 126759.74 | CB30: =CB29-BR30 -> 21528.062
A31: 45735 | B31: MTA Trade | C31: 哈萨克斯坦 | D31: 4500160671 | F31: 4500160671-90 | G31: 77685GQ1-S001 | H31: 混搭恐龙13pcs/GQ1*4/箱 | I31: 312 | J31: 0 | K31: 52 | L31: =I31/K31 -> 6 | M31: 45772 | N31: 45768 | P31: 自检 | Q31: 4/25 客自提 | R31: 45735 | S31: 无 | T31: 3/28进口商贴纸 | V31: 日期码格式：ZURU INC(BVI) 标准格式 日期：按实际生产日期 Packaging Info: 77685GQ1:MA UPC 收缩膜（优先1L)+进口商贴纸;MA指南;MA PDQ(优先1L) Remark: 77685GQ1 Rare ratio:1/48 标准配比 | W31: Cora Zhou | X31: 0.7909 | Y31: =X31*I31 -> 246.7608 | Z31: 94843-4.25 | AA31: 312 | AB31: =AA31-I31 -> 0 | AC31: OK | AD31: 系统出单 | AE31: 77685GQ1-S001 | AF31: 已入 | AG31: =I31 -> 312 | AH31: =I31 -> 312 | AK31: =I31 -> 312 | AN31: =I31 -> 312 | AT31: =I31/13 -> 24 | BJ31: =$I31*BJ$2 -> 38.1875 | BK31: =$I31*BK$2 -> 38.1875 | BL31: =$I31*BL$2 -> 38.1875 | BM31: =$I31*BM$2 -> 38.1875 | BN31: =$I31*BN$2 -> 38.1875 | BO31: =$I31*BO$2 -> 38.1875 | BP31: =$I31*BP$2 -> 38.1875 | BQ31: =$I31*BQ$2 -> 38.1875 | BR31: =$I31*BR$2 -> 6.5 | BT31: =BT30-BJ31 -> 126721.55 | BU31: =BU30-BK31 -> 126721.55 | BV31: =BV30-BL31 -> 126721.55 | BW31: =BW30-BM31 -> 126721.55 | BX31: =BX30-BN31 -> 126721.55 | BY31: =BY30-BO31 -> 126721.55 | BZ31: =BZ30-BP31 -> 126721.55 | CA31: =CA30-BQ31 -> 126721.55 | CB31: =CB30-BR31 -> 21521.562
A32: 45695 | B32: SMYTHS TOYS HQ UC | C32: 法国 | D32: 4500156863 | E32: 4400463048 | F32: 4500156863-10 | G32: 77685GQ2-S002 | H32: 混搭恐龙27pcs/GQ2/箱 | I32: 4023 | J32: 0 | K32: 27 | L32: =I32/K32 -> 149 | M32: 45775 | N32: 45771 | P32: pass | Q32: 5/20 截SI | R32: 45696 | S32: 无 | T32: 无 | V32: 日期码格式：ZURU INC(BVI) 标准格式 日期：按实际生产日期 Packaging Info: 77685GQ2：客版收缩膜(英法德意荷)+客版5L slime bag+MA 3L PDQ+MA5L(23L Warning)收藏指南+MA23L说明书(客版翻4500155619) Remark: 1. 此单出法国，所有包装都需要含有法语，需要满足Zuru Standard欧洲标准测试要求； 2. 请准时出货，推期会有罚款； 3. 所有出口法国的产品, 法规规定禁止在包装和共公众用的印刷品中使用矿物油中含有的物质, 包装印刷油墨中含有的MOAH/MOSH的质量浓度不能超过1%, 否则出 货到法国被抽检出现问题, 供应商需要对此负责; | W32: Ula Zhao | X32: 0.89 | Y32: =X32*I32 -> 3580.47 | Z32: 94996-5.16 | AA32: 4023 | AB32: =AA32-I32 -> 0 | AC32: 无 | AD32: 系统出单 | AE32: 77685GQ2-S002-客 | AF32: 已入 | AG32: =I32 -> 4023 | AJ32: =I32 -> 4023 | AM32: =I32 -> 4023 | AN32: =I32 -> 4023 | AR32: =I32/27 -> 149 | BJ32: =$I32*BJ$2 -> 492.39844 | BK32: =$I32*BK$2 -> 492.39844 | BL32: =$I32*BL$2 -> 492.39844 | BM32: =$I32*BM$2 -> 492.39844 | BN32: =$I32*BN$2 -> 492.39844 | BO32: =$I32*BO$2 -> 492.39844 | BP32: =$I32*BP$2 -> 492.39844 | BQ32: =$I32*BQ$2 -> 492.39844 | BR32: =$I32*BR$2 -> 83.8125 | BT32: =BT31-BJ32 -> 126229.16 | BU32: =BU31-BK32 -> 126229.16 | BV32: =BV31-BL32 -> 126229.16 | BW32: =BW31-BM32 -> 126229.16 | BX32: =BX31-BN32 -> 126229.16 | BY32: =BY31-BO32 -> 126229.16 | BZ32: =BZ31-BP32 -> 126229.16 | CA32: =CA31-BQ32 -> 126229.16 | CB32: =CB31-BR32 -> 21437.75
A33: 45730 | B33: Andrés Dauhajre SA (LA NOVIA DE VIL | C33: 多米尼加共和国 | D33: 4500160345 | F33: 4500160345-90 | G33: 77685GQ2-S001 | H33: 混搭恐龙27pcs/GQ2*2/箱 | I33: 108 | J33: 0 | K33: 54 | L33: =I33/K33 -> 2 | M33: 45776 | N33: 45772 | P33: 自检 | R33: 45743 | S33: 无 | T33: 3/31 UPC贴纸 | V33: 日期码格式：ZURU INC(BVI) 标准格式 日期：按实际生产日期 Packaging Info: 77685GQ2: MA多语EAN包装+UPC贴纸+MA多语收藏指南+MA多语PDQ+箱唛 Remark: | W33: Ava Liang | X33: 0.7967 | Y33: =X33*I33 -> 86.0436 | Z33: 94881-4.29 | AA33: 108 | AB33: =AA33-I33 -> 0 | AC33: OK | AD33: 系统出单 | AE33: 77685GQ2-S001-3L | AF33: 已入 | AG33: =I33 -> 108 | AH33: =I33 -> 108 | AL33: =I33 -> 108 | AN33: =I33 -> 108 | AR33: =I33/27 -> 4 | BJ33: =$I33*BJ$2 -> 13.21875 | BK33: =$I33*BK$2 -> 13.21875 | BL33: =$I33*BL$2 -> 13.21875 | BM33: =$I33*BM$2 -> 13.21875 | BN33: =$I33*BN$2 -> 13.21875 | BO33: =$I33*BO$2 -> 13.21875 | BP33: =$I33*BP$2 -> 13.21875 | BQ33: =$I33*BQ$2 -> 13.21875 | BR33: =$I33*BR$2 -> 2.25 | BT33: =BT32-BJ33 -> 126215.94 | BU33: =BU32-BK33 -> 126215.94 | BV33: =BV32-BL33 -> 126215.94 | BW33: =BW32-BM33 -> 126215.94 | BX33: =BX32-BN33 -> 126215.94 | BY33: =BY32-BO33 -> 126215.94 | BZ33: =BZ32-BP33 -> 126215.94 | CA33: =CA32-BQ33 -> 126215.94 | CB33: =CB32-BR33 -> 21435.5
A34: 45734 | B34: ZURU LLC | C34: 美国 | D34: 4500160498 | E34: B0DS4YBF4S | F34: 4500160498-60 | G34: 77723-S001-MTS | H34: 混搭恐龙2PK圆筒装 | I34: 756 | J34: 0 | K34: 12 | L34: =I34/K34 -> 63 | M34: 45777 | N34: 45773 | P34: 自检 | Q34: 4/30 客上柜 | R34: 3/18 外箱最长边不能超过25" （超过了，case pack只能为1） | S34: 无 | T34: 2/21空白贴纸 | V34: 日期码格式：ZURU INC(BVI) 标准格式 日期：按实际生产日期 Packaging Info: #77723：2PK STD 77685 PVC Tube. MA 1L UPC版本+空白UPC贴纸，3L 铜版纸和空白贴纸跟翻单#4500157378。收藏指南，说明书均为MA 5L标版。（两个球的配比不 能重复）。 Remark: 1.Amazon domestic 订单。出口美国。外箱最长边不能超过25" （超过了，case pack只能为1），不符合要求的大货，一律不接受。 2.无第三方验货/测试要求。 3.日期码使用ZURU标准版本。 4.邮包盒要印刷日期码。 | W34: Kelly Shen/Mia Pan/P | X34: 2.09 | Y34: =X34*I34 -> 1580.04 | Z34: ZB00241-5.13 | AA34: 756 | AB34: =AA34-I34 -> 0 | AC34: OK | AD34: 系统出单 | AE34: 77723-S001-MTS | AF34: 已入 | AG34: =I34*2 -> 1512 | AH34: =I34*2 -> 1512 | AK34: =I34*2 -> 1512 | AN34: =I34*2 -> 1512 | BF34: =I34 -> 756 | BG34: =I34 -> 756 | BJ34: =$I34*BJ$2*2 -> 185.0625 | BK34: =$I34*BK$2*2 -> 185.0625 | BL34: =$I34*BL$2*2 -> 185.0625 | BM34: =$I34*BM$2*2 -> 185.0625 | BN34: =$I34*BN$2*2 -> 185.0625 | BO34: =$I34*BO$2*2 -> 185.0625 | BP34: =$I34*BP$2*2 -> 185.0625 | BQ34: =$I34*BQ$2*2 -> 185.0625 | BR34: =$I34*BR$2*2 -> 31.5 | BT34: =BT33-BJ34 -> 126030.88 | BU34: =BU33-BK34 -> 126030.88 | BV34: =BV33-BL34 -> 126030.88 | BW34: =BW33-BM34 -> 126030.88 | BX34: =BX33-BN34 -> 126030.88 | BY34: =BY33-BO34 -> 126030.88 | BZ34: =BZ33-BP34 -> 126030.88 | CA34: =CA33-BQ34 -> 126030.88 | CB34: =CB33-BR34 -> 21404 | CD34: 2/17 已放MA 圆筒/彩纸/贴纸 | CH34: =CH21-I34 -> 7024 | CI34: =CI21-I34 -> 2024
A35: 45735 | B35: MILLS FLEET FARM | C35: 美国 | D35: 4500160726 | E35: PO#4647602 | F35: 4500160726-190 | G35: 77685GQ1-S001 | H35: 混搭恐龙13pcs/GQ1*4/箱 | I35: 988 | J35: 0 | K35: 52 | L35: =I35/K35 -> 19 | M35: 45818 | N35: 45814 | P35: pass | Q35: 6/16 截SI | R35: 45742 | S35: 有 | T35: 3/26外箱贴纸 | V35: 日期码格式：ZURU INC(BVI) 标准格式 日期：按实际生产日期 Packaging Info: 1. 包材：ZURU 最新 MA 1L UPC 版本，出口美国;| Remark: 2.日期跟踪码：产品包装及产品本身都必须有日期跟踪码，并且确保两者的日期跟踪码要一致；ZURU标准格式日期码(请自行调整具体年月日生产期，但不能为末). 3. 此单不同客户PO对应不同交期，PO详情看侧边remark ，交期请看PO上面的delivery date； 4. 外箱贴纸(请务必先发箱唛排版给跟单确认后再做印刷) 5. 出货配比：ZURU 标版配比 | W35: Mila Yao | X35: 0.945 | Y35: =X35*I35 -> 933.66 | Z35: ZB00483-6.16 | AA35: 988 | AB35: =AA35-I35 -> 0 | AD35: 系统出单 | AE35: 77685GQ1-S001 | AF35: 已入 | AG35: =I35 -> 988 | AH35: =I35 -> 988 | AK35: =I35 -> 988 | AN35: =I35 -> 988 | AT35: =I35/13 -> 76 | BJ35: =$I35*BJ$2 -> 120.92708 | BK35: =$I35*BK$2 -> 120.92708 | BL35: =$I35*BL$2 -> 120.92708 | BM35: =$I35*BM$2 -> 120.92708 | BN35: =$I35*BN$2 -> 120.92708 | BO35: =$I35*BO$2 -> 120.92708 | BP35: =$I35*BP$2 -> 120.92708 | BQ35: =$I35*BQ$2 -> 120.92708 | BR35: =$I35*BR$2 -> 20.583333 | BT35: =BT34-BJ35 -> 125909.95 | BU35: =BU34-BK35 -> 125909.95 | BV35: =BV34-BL35 -> 125909.95 | BW35: =BW34-BM35 -> 125909.95 | BX35: =BX34-BN35 -> 125909.95 | BY35: =BY34-BO35 -> 125909.95 | BZ35: =BZ34-BP35 -> 125909.95 | CA35: =CA34-BQ35 -> 125909.95 | CB35: =CB34-BR35 -> 21383.417
A36: 45730 | B36: CORPORACION FAVORITA C.A. | C36: 厄多瓜尔 | D36: 4500160092 | E36: 25-2101100JEC | F36: 4500160092-240 | G36: 77685GQ2-S001 | H36: 混搭恐龙27pcs/GQ2*2/箱 | I36: 2700 | J36: 0 | K36: 54 | L36: =I36/K36 -> 50 | M36: 45775 | N36: 45775 | O36: 指定日期码：2025-05 外箱/产品/包装/进口商贴纸 日期码要一致 | P36: pass | Q36: 5/12 截SI | R36: 45740 | S36: 无 | T36: 4/15 UPC贴纸+进口商贴纸 | V36: 日期码格式：2025-05 日期： Packaging Info: 77685GQ2: MA多语EAN包装+UPC贴纸+MA多语收藏指南+MA多语PDQ+进口商贴纸+箱唛 Remark: 1.指定日期码：2025-05（外箱/产品/包装/进口商贴纸 日期码要一致。 如果部分半成品已打ZURU 标准日期码，满足不了指定日期码的要求，可以接受标准日期码，不用重复确认。) 2.所有item的包装上的条码必须是UPC，如果后续提供的贴纸资料已将进口商贴纸和UPC条码合并到一张， 则不需要额外再订购UPC贴纸资料，仅需要订购一张进口商贴纸 | W36: Ava Liang | X36: 0.9779 | Y36: =X36*I36 -> 2640.33 | Z36: 94973-5.12 | AA36: =2700 -> 2700 | AB36: =AA36-I36 -> 0 | AC36: OK | AD36: 系统出单 | AE36: 77685GQ2-S001-3L | AF36: 已入 | AG36: =I36 -> 2700 | AH36: =I36 -> 2700 | AL36: =I36 -> 2700 | AN36: =I36 -> 2700 | AR36: =I36/27 -> 100 | BJ36: =$I36*BJ$2 -> 330.46875 | BK36: =$I36*BK$2 -> 330.46875 | BL36: =$I36*BL$2 -> 330.46875 | BM36: =$I36*BM$2 -> 330.46875 | BN36: =$I36*BN$2 -> 330.46875 | BO36: =$I36*BO$2 -> 330.46875 | BP36: =$I36*BP$2 -> 330.46875 | BQ36: =$I36*BQ$2 -> 330.46875 | BR36: =$I36*BR$2 -> 56.25 | BT36: =BT35-BJ36 -> 125579.48 | BU36: =BU35-BK36 -> 125579.48 | BV36: =BV35-BL36 -> 125579.48 | BW36: =BW35-BM36 -> 125579.48 | BX36: =BX35-BN36 -> 125579.48 | BY36: =BY35-BO36 -> 125579.48 | BZ36: =BZ35-BP36 -> 125579.48 | CA36: =CA35-BQ36 -> 125579.48 | CB36: =CB35-BR36 -> 21327.167
A37: 45754 | B37: ZURU Denmark ApS | C37: 丹麦 | D37: 4500162346 | E37: 5200006527 | F37: 4500162346-10 | G37: 77685GQ1-S002-MTS | H37: 混搭恐龙13pcs/GQ1/箱 | I37: 3315 | J37: 0 | K37: 13 | L37: =I37/K37 -> 255 | M37: 45783 | N37: 45782 | P37: pass | Q37: 5/6截SI | R37: 45757 | S37: 无 | T37: 4/16警告语贴纸 | V37: 日期码格式：ZURU INC(BVI) 标准格式 日期：按实际生产日期 Packaging Info: 77685GQ1: MA 3L A版PDQ + 3L警语 EAN A版收缩膜 +1*多语折叠警告语贴纸+ 1L+23L警语说明书 + 5L+23L警语收藏指南 + 5L Slime袋子 + 北欧五语通用Slime黑 白说明书 Remark: 1.北欧内销单，需要通过ZURU 验货结果后才能出货 (工厂需要主动提前同ZURU QC预约验货避免延期出货造成不必要麻烦)； 2. 产品如含有化学品，需要无硼无香， 3.包装不能含有PVC，使用PET 4. date code: 外箱日期码要晚于产品日期码 5. 装柜时需要按照款式号码从小到大一款款依次装,避免终端仓库卸货混乱.若一个柜子涉及到几个不同国家内销单,装柜时需要一个国家装完后再装另一个国家的 产品,依次装柜,避免终端仓库因不同国家不同库位位置卸货混乱. (此点需要同工厂装柜人员强调)" 6.若有特定款有特殊外箱条码要求时,需要明确列出产品款对应的具体外箱条码号码/条码类型 (若无,可以忽略此需求) 7.所有出口欧洲的产品, 法规规定禁止在包装和共公众用的印刷品中使用矿物油中含有的物质, 包装印刷油墨中含有的MOAH/MOSH的质量浓度不能超过1%, 否则出货 到法国被抽检出现问题, 供应商需要对此负责; 8.带电池出货的产品所用到的电池需要符合欧洲电池新规(EU) 2023-1542。 9.ratio 同MA | W37: SD04 | X37: 0.7931 | Y37: =X37*I37 -> 2629.1265 | Z37: 94941-5.7 | AA37: 3315 | AB37: =AA37-I37 -> 0 | AC37: OK | AD37: 系统出单 | AE37: 77685GQ1-S002-3L | AF37: 已入 | AG37: =I37 -> 3315 | AH37: =I37 -> 3315 | AL37: =I37 -> 3315 | AN37: =I37 -> 3315 | AU37: =I37/13 -> 255 | BJ37: =$I37*BJ$2 -> 405.74219 | BK37: =$I37*BK$2 -> 405.74219 | BL37: =$I37*BL$2 -> 405.74219 | BM37: =$I37*BM$2 -> 405.74219 | BN37: =$I37*BN$2 -> 405.74219 | BO37: =$I37*BO$2 -> 405.74219 | BP37: =$I37*BP$2 -> 405.74219 | BQ37: =$I37*BQ$2 -> 405.74219 | BR37: =$I37*BR$2 -> 69.0625 | BT37: =BT36-BJ37 -> 125173.74 | BU37: =BU36-BK37 -> 125173.74 | BV37: =BV36-BL37 -> 125173.74 | BW37: =BW36-BM37 -> 125173.74 | BX37: =BX36-BN37 -> 125173.74 | BY37: =BY36-BO37 -> 125173.74 | BZ37: =BZ36-BP37 -> 125173.74 | CA37: =CA36-BQ37 -> 125173.74 | CB37: =CB36-BR37 -> 21258.104
A38: 45740 | B38: Signature Marketing N.Z Limited | C38: 新西兰 | D38: 4500161244 | E38: SMNZZU2503 | F38: 4500161244-10 | G38: 77685GQ1-S001 | H38: 混搭恐龙13pcs/GQ1*4/箱 | I38: 1456 | J38: 0 | K38: 52 | L38: =I38/K38 -> 28 | M38: 45784 | N38: 45782 | P38: pass | Q38: 待SO出货 | R38: 45747 | S38: 无 | T38: 无 | V38: 日期码格式：ZURU INC(BVI) 标准格式 日期：按实际生产日期 Packaging Info: 77685GQ1:Rare ratio:1/48 Remark: MA UPC 英语包装（优先1L英语版本,或者3L/L含英语即可） | W38: Abby Liang | X38: 0.945 | Y38: =X38*I38 -> 1375.92 | Z38: 94957-5.10 | AA38: 1456 | AB38: =AA38-I38 -> 0 | AC38: 无 | AD38: 系统出单 | AE38: 77685GQ1-S001 | AF38: 已入 | AG38: =I38 -> 1456 | AH38: =I38 -> 1456 | AK38: =I38 -> 1456 | AN38: =I38 -> 1456 | AT38: =I38/13 -> 112 | BJ38: =$I38*BJ$2 -> 178.20833 | BK38: =$I38*BK$2 -> 178.20833 | BL38: =$I38*BL$2 -> 178.20833 | BM38: =$I38*BM$2 -> 178.20833 | BN38: =$I38*BN$2 -> 178.20833 | BO38: =$I38*BO$2 -> 178.20833 | BP38: =$I38*BP$2 -> 178.20833 | BQ38: =$I38*BQ$2 -> 178.20833 | BR38: =$I38*BR$2 -> 30.333333 | BT38: =BT37-BJ38 -> 124995.53 | BU38: =BU37-BK38 -> 124995.53 | BV38: =BV37-BL38 -> 124995.53 | BW38: =BW37-BM38 -> 124995.53 | BX38: =BX37-BN38 -> 124995.53 | BY38: =BY37-BO38 -> 124995.53 | BZ38: =BZ37-BP38 -> 124995.53 | CA38: =CA37-BQ38 -> 124995.53 | CB38: =CB37-BR38 -> 21227.771
A39: 45744 | B39: WALMART INC. | C39: 美国 | D39: 4500161693 | E39: 0904512406 STATESBORO | F39: 4500161693-10 | G39: 77685SLB-S001 | H39: 混搭恐龙卡板装12pcs/GQ4/CTN**96/Slip Sheet | I39: 1152 | J39: 0 | K39: 1152 | L39: =I39/K39 -> 1 | M39: 45785 | N39: 45782 | O39: 5/9 BV | P39: pass | Q39: 5/15 交仓 | R39: 翻单 | S39: 有 | T39: 4/14 RFID | V39: 日期码格式：ZURU DGYYYYMMDD CHINA(日期避开周末和法定节假日即可） 日期：按实际生产日期 Packaging Info: 77685SLB-S001： 1.包装要求： MA 1L A版收缩膜+MA A版纸袋+MA 5L A版收藏指南+MA A版slime bag+客版1L PDQ,翻单：4500159701 每pcs产品上要贴1张RFID贴纸，贴纸由ZURU提供，贴纸位置请严格按照我们签回的签板； Remark: 77685SLB-S001： 1.包装要求： MA 1L A版收缩膜+MA A版纸袋+MA 5L A版收藏指南+MA A版slime bag+客版1L PDQ,翻单：4500159701 每pcs产品上要贴1张RFID贴纸，贴纸由ZURU提供，贴纸位置请严格按照我们签回的签板； 2. 外箱印刷带条码的RFID箱唛：RFID紫色色带+WM Dept.图标+RFID图标+ITF-14条码，四面右下角印刷ZURU logo, ITFF条码只印刷在正唛一面，在加印的时候确保 条形码能扫描出来，外箱侧面任一角落加印："MADE IN CHINA" 字样； 3. 每个slip sheet上面贴一张艾利贴纸（不干胶贴纸）和一张普通贴纸（A4纸），slip sheet打印的普通贴纸的尺寸不能比艾利贴纸小，普通贴纸内容见附件； 4. 在产品上和包装上要有日期码、以及要有MADE IN CHINA和ZURU字样； 5. 产品如有扎带口要剪平，不能刮手。 6. 此单需要验货，请多备料 7. 此单以slip sheet出货，77685：1152pcs/96CTN/Slip Sheet | W39: Maggie Xie | X39: 903.2128 | Y39: =X39*L39 -> 903.2128 | Z39: ZB00249-5.14 | AA39: 1152 | AB39: =AA39-I39 -> 0 | AD39: 系统出单 | AE39: 77685SLB-S001 | AF39: 已入 | AG39: =I39 -> 1152 | AH39: =I39 -> 1152 | AK39: =I39 -> 1152 | AN39: =I39 -> 1152 | AV39: =I39/12 -> 96 | BJ39: =$I39*BJ$2 -> 141 | BK39: =$I39*BK$2 -> 141 | BL39: =$I39*BL$2 -> 141 | BM39: =$I39*BM$2 -> 141 | BN39: =$I39*BN$2 -> 141 | BO39: =$I39*BO$2 -> 141 | BP39: =$I39*BP$2 -> 141 | BQ39: =$I39*BQ$2 -> 141 | BR39: =$I39*BR$2 -> 24 | BT39: =BT38-BJ39 -> 124854.53 | BU39: =BU38-BK39 -> 124854.53 | BV39: =BV38-BL39 -> 124854.53 | BW39: =BW38-BM39 -> 124854.53 | BX39: =BX38-BN39 -> 124854.53 | BY39: =BY38-BO39 -> 124854.53 | BZ39: =BZ38-BP39 -> 124854.53 | CA39: =CA38-BQ39 -> 124854.53 | CB39: =CB38-BR39 -> 21203.771
A40: 45744 | B40: WALMART INC. | C40: 美国 | D40: 4500161693 | E40: 0904512349 SUFFOLK | F40: 4500161693-20 | G40: 77685SLB-S001 | H40: 混搭恐龙卡板装12pcs/GQ4/CTN**96/Slip Sheet | I40: 1152 | J40: 0 | K40: 1152 | L40: =I40/K40 -> 1 | M40: 45785 | N40: 45782 | O40: 5/9 BV | P40: pass | Q40: 5/10 交仓 | R40: 翻单 | S40: 有 | T40: 4/14 RFID | V40: 日期码格式：ZURU DGYYYYMMDD CHINA(日期避开周末和法定节假日即可） 日期：按实际生产日期 Packaging Info: 77685SLB-S001： 1.包装要求： MA 1L A版收缩膜+MA A版纸袋+MA 5L A版收藏指南+MA A版slime bag+客版1L PDQ,翻单：4500159701 每pcs产品上要贴1张RFID贴纸，贴纸由ZURU提供，贴纸位置请严格按照我们签回的签板； Remark: 77685SLB-S001： 1.包装要求： MA 1L A版收缩膜+MA A版纸袋+MA 5L A版收藏指南+MA A版slime bag+客版1L PDQ,翻单：4500159701 每pcs产品上要贴1张RFID贴纸，贴纸由ZURU提供，贴纸位置请严格按照我们签回的签板； 2. 外箱印刷带条码的RFID箱唛：RFID紫色色带+WM Dept.图标+RFID图标+ITF-14条码，四面右下角印刷ZURU logo, ITFF条码只印刷在正唛一面，在加印的时候确保 条形码能扫描出来，外箱侧面任一角落加印："MADE IN CHINA" 字样； 3. 每个slip sheet上面贴一张艾利贴纸（不干胶贴纸）和一张普通贴纸（A4纸），slip sheet打印的普通贴纸的尺寸不能比艾利贴纸小，普通贴纸内容见附件； 4. 在产品上和包装上要有日期码、以及要有MADE IN CHINA和ZURU字样； 5. 产品如有扎带口要剪平，不能刮手。 6. 此单需要验货，请多备料 7. 此单以slip sheet出货，77685：1152pcs/96CTN/Slip Sheet | W40: Maggie Xie | X40: 903.2128 | Y40: =X40*L40 -> 903.2128 | Z40: ZB00240-5.13 | AA40: 1152 | AB40: =AA40-I40 -> 0 | AD40: 系统出单 | AE40: 77685SLB-S001 | AF40: 已入 | AG40: =I40 -> 1152 | AH40: =I40 -> 1152 | AK40: =I40 -> 1152 | AN40: =I40 -> 1152 | AV40: =I40/12 -> 96 | BJ40: =$I40*BJ$2 -> 141 | BK40: =$I40*BK$2 -> 141 | BL40: =$I40*BL$2 -> 141 | BM40: =$I40*BM$2 -> 141 | BN40: =$I40*BN$2 -> 141 | BO40: =$I40*BO$2 -> 141 | BP40: =$I40*BP$2 -> 141 | BQ40: =$I40*BQ$2 -> 141 | BR40: =$I40*BR$2 -> 24 | BT40: =BT39-BJ40 -> 124713.53 | BU40: =BU39-BK40 -> 124713.53 | BV40: =BV39-BL40 -> 124713.53 | BW40: =BW39-BM40 -> 124713.53 | BX40: =BX39-BN40 -> 124713.53 | BY40: =BY39-BO40 -> 124713.53 | BZ40: =BZ39-BP40 -> 124713.53 | CA40: =CA39-BQ40 -> 124713.53 | CB40: =CB39-BR40 -> 21179.771
A41: 45744 | B41: WALMART INC. | C41: 美国 | D41: 4500161749 | E41: 0904512397 | F41: 4500161749-10 | G41: 77685SLB-S001 | H41: 混搭恐龙卡板装12pcs/GQ4/CTN**96/Slip Sheet | I41: 1152 | J41: 0 | K41: 1152 | L41: =I41/K41 -> 1 | M41: 45789 | N41: 45785 | O41: 5/14 BV | P41: pass | Q41: 5/26 截SI | R41: 翻单 | S41: 有 | T41: 4/14 RFID | V41: 日期码格式：ZURU DGYYYYMMDD CHINA(日期避开周末和法定节假日即可） 日期：按实际生产日期 Packaging Info: 77685SLB-S001： 1.包装要求： MA 1L A版收缩膜+MA A版纸袋+MA 5L A版收藏指南+MA A版slime bag+客版1L PDQ,翻单：4500159701 每pcs产品上要贴1张RFID贴纸，贴纸由ZURU提供，贴纸位置请严格按照我们签回的签板； Remark: 77685SLB-S001： 1.包装要求： MA 1L A版收缩膜+MA A版纸袋+MA 5L A版收藏指南+MA A版slime bag+客版1L PDQ,翻单：4500159701 每pcs产品上要贴1张RFID贴纸，贴纸由ZURU提供，贴纸位置请严格按照我们签回的签板； 2. 外箱印刷带条码的RFID箱唛：RFID紫色色带+WM Dept.图标+RFID图标+ITF-14条码，四面右下角印刷ZURU logo, ITFF条码只印刷在正唛一面，在加印的时候确保 条形码能扫描出来，外箱侧面任一角落加印："MADE IN CHINA" 字样； 3. 每个slip sheet上面贴一张艾利贴纸（不干胶贴纸）和一张普通贴纸（A4纸），slip sheet打印的普通贴纸的尺寸不能比艾利贴纸小，普通贴纸内容见附件； 4. 在产品上和包装上要有日期码、以及要有MADE IN CHINA和ZURU字样； 5. 产品如有扎带口要剪平，不能刮手。 6. 此单需要验货，请多备料 7. 此单以slip sheet出货，77685：1152pcs/96CTN/Slip Sheet | W41: Maggie Xie | X41: 903.2128 | Y41: =X41*L41 -> 903.2128 | AA41: 1152 | AB41: =AA41-I41 -> 0 | AD41: 系统出单 | AE41: 77685SLB-S001 | AF41: 已入 | AG41: =I41 -> 1152 | AH41: =I41 -> 1152 | AK41: =I41 -> 1152 | AN41: =I41 -> 1152 | AV41: =I41/12 -> 96 | BJ41: =$I41*BJ$2 -> 141 | BK41: =$I41*BK$2 -> 141 | BL41: =$I41*BL$2 -> 141 | BM41: =$I41*BM$2 -> 141 | BN41: =$I41*BN$2 -> 141 | BO41: =$I41*BO$2 -> 141 | BP41: =$I41*BP$2 -> 141 | BQ41: =$I41*BQ$2 -> 141 | BR41: =$I41*BR$2 -> 24 | BT41: =BT40-BJ41 -> 124572.53 | BU41: =BU40-BK41 -> 124572.53 | BV41: =BV40-BL41 -> 124572.53 | BW41: =BW40-BM41 -> 124572.53 | BX41: =BX40-BN41 -> 124572.53 | BY41: =BY40-BO41 -> 124572.53 | BZ41: =BZ40-BP41 -> 124572.53 | CA41: =CA40-BQ41 -> 124572.53 | CB41: =CB40-BR41 -> 21155.771
A42: 45749 | B42: WALMART INC. | C42: 美国 | D42: 4500162369 | E42: 0902421363 SAVANNAH | F42: 4500162369-10 | G42: 77685GQ4-S001 | H42: 混搭恐龙12pcs/GQ4/箱 | I42: 5064 | J42: 0 | K42: 12 | L42: =I42/K42 -> 422 | M42: 45789 | N42: 45785 | O42: 5/14 BV | P42: pass | Q42: 5/20 截SI | R42: 45749 | S42: 有 | T42: 4/14 RFID | V42: 日期码格式：ZURU DGYYYYMMDD CHINA(日期避开周末和法定节假日即可） 日期：按实际生产日期 Packaging Info: 77685GQ4-S001： 1.包装要求： MA 1L A版收缩膜+MA A版纸袋+MA 5L A版收藏指南+MA A版slime bag+客版1L PDQ, 翻单：4500159701 每pcs产品上要贴1张RFID贴纸，贴纸由ZURU提供，贴纸位置请严格按照我们签回的签板； Remark: 77685GQ4-S001： 1.包装要求： MA 1L A版收缩膜+MA A版纸袋+MA 5L A版收藏指南+MA A版slime bag+客版1L PDQ, 翻单：4500159701 每pcs产品上要贴1张RFID贴纸，贴纸由ZURU提供，贴纸位置请严格按照我们签回的签板； 2. 外箱印刷带条码的RFID箱唛：RFID紫色色带+WM Dept.图标+RFID图标+ITF-14条码+粉色艾利贴纸（不干胶打印），四面右下角印刷ZURU logo, ITFF条码只印刷在 正唛一面，在加印的时候确保条形码能扫描出来，1张粉红色贴纸贴在正唛对角线，外箱侧面任一角落加印："MADE IN CHINA" 字样； 3. 在产品上和包装上要有日期码、以及要有MADE IN CHINA和ZURU字样； 4. 产品如有扎带口要剪平，不能刮手。 5. 此单需要验货，请多备料 6. 此单以loose carton出货，77685：12pcs/PDQ/CTN | W42: Maggie Xie | X42: 0.945 | Y42: =X42*I42 -> 4785.48 | AA42: 5064 | AB42: =AA42-I42 -> 0 | AD42: 系统出单 | AE42: 77685GQ4-S001 | AF42: 已入 | AG42: =I42 -> 5064 | AH42: =I42 -> 5064 | AK42: =I42 -> 5064 | AN42: =I42 -> 5064 | AV42: =I42/12 -> 422 | BJ42: =$I42*BJ$2 -> 619.8125 | BK42: =$I42*BK$2 -> 619.8125 | BL42: =$I42*BL$2 -> 619.8125 | BM42: =$I42*BM$2 -> 619.8125 | BN42: =$I42*BN$2 -> 619.8125 | BO42: =$I42*BO$2 -> 619.8125 | BP42: =$I42*BP$2 -> 619.8125 | BQ42: =$I42*BQ$2 -> 619.8125 | BR42: =$I42*BR$2 -> 105.5 | BT42: =BT41-BJ42 -> 123952.72 | BU42: =BU41-BK42 -> 123952.72 | BV42: =BV41-BL42 -> 123952.72 | BW42: =BW41-BM42 -> 123952.72 | BX42: =BX41-BN42 -> 123952.72 | BY42: =BY41-BO42 -> 123952.72 | BZ42: =BZ41-BP42 -> 123952.72 | CA42: =CA41-BQ42 -> 123952.72 | CB42: =CB41-BR42 -> 21050.271
A43: 45749 | B43: WALMART INC. | C43: 美国 | D43: 4500162369 | E43: 0902421367 SUFFOLK | F43: 4500162369-20 | G43: 77685GQ4-S001 | H43: 混搭恐龙12pcs/GQ4/箱 | I43: 6684 | J43: 0 | K43: 12 | L43: =I43/K43 -> 557 | M43: 45789 | N43: 45785 | O43: 5/14 BV | P43: pass | Q43: 5/15 截SI | R43: 45749 | S43: 有 | T43: 4/14 RFID | V43: 日期码格式：ZURU DGYYYYMMDD CHINA(日期避开周末和法定节假日即可） 日期：按实际生产日期 Packaging Info: 77685GQ4-S001： 1.包装要求： MA 1L A版收缩膜+MA A版纸袋+MA 5L A版收藏指南+MA A版slime bag+客版1L PDQ, 翻单：4500159701 每pcs产品上要贴1张RFID贴纸，贴纸由ZURU提供，贴纸位置请严格按照我们签回的签板； Remark: 77685GQ4-S001： 1.包装要求： MA 1L A版收缩膜+MA A版纸袋+MA 5L A版收藏指南+MA A版slime bag+客版1L PDQ, 翻单：4500159701 每pcs产品上要贴1张RFID贴纸，贴纸由ZURU提供，贴纸位置请严格按照我们签回的签板； 2. 外箱印刷带条码的RFID箱唛：RFID紫色色带+WM Dept.图标+RFID图标+ITF-14条码+粉色艾利贴纸（不干胶打印），四面右下角印刷ZURU logo, ITFF条码只印刷在 正唛一面，在加印的时候确保条形码能扫描出来，1张粉红色贴纸贴在正唛对角线，外箱侧面任一角落加印："MADE IN CHINA" 字样； 3. 在产品上和包装上要有日期码、以及要有MADE IN CHINA和ZURU字样； 4. 产品如有扎带口要剪平，不能刮手。 5. 此单需要验货，请多备料 6. 此单以loose carton出货，77685：12pcs/PDQ/CTN | W43: Maggie Xie | X43: 0.945 | Y43: =X43*I43 -> 6316.38 | AA43: 6684 | AB43: =AA43-I43 -> 0 | AD43: 系统出单 | AE43: 77685GQ4-S001 | AF43: 已入 | AG43: =I43 -> 6684 | AH43: =I43 -> 6684 | AK43: =I43 -> 6684 | AN43: =I43 -> 6684 | AV43: =I43/12 -> 557 | BJ43: =$I43*BJ$2 -> 818.09375 | BK43: =$I43*BK$2 -> 818.09375 | BL43: =$I43*BL$2 -> 818.09375 | BM43: =$I43*BM$2 -> 818.09375 | BN43: =$I43*BN$2 -> 818.09375 | BO43: =$I43*BO$2 -> 818.09375 | BP43: =$I43*BP$2 -> 818.09375 | BQ43: =$I43*BQ$2 -> 818.09375 | BR43: =$I43*BR$2 -> 139.25 | BT43: =BT42-BJ43 -> 123134.62 | BU43: =BU42-BK43 -> 123134.62 | BV43: =BV42-BL43 -> 123134.62 | BW43: =BW42-BM43 -> 123134.62 | BX43: =BX42-BN43 -> 123134.62 | BY43: =BY42-BO43 -> 123134.62 | BZ43: =BZ42-BP43 -> 123134.62 | CA43: =CA42-BQ43 -> 123134.62 | CB43: =CB42-BR43 -> 20911.021
A44: 45749 | B44: WALMART INC. | C44: 美国 | D44: 4500162369 | E44: 0902421371 RIDGEVILLE SC | F44: 4500162369-30 | G44: 77685GQ4-S001 | H44: 混搭恐龙12pcs/GQ4/箱 | I44: 5820 | J44: 0 | K44: 12 | L44: =I44/K44 -> 485 | M44: 45789 | N44: 45785 | O44: 5/14 BV | P44: pass | Q44: 5/16 截SI | R44: 45749 | S44: 有 | T44: 4/14 RFID | V44: 日期码格式：ZURU DGYYYYMMDD CHINA(日期避开周末和法定节假日即可） 日期：按实际生产日期 Packaging Info: 77685GQ4-S001： 1.包装要求： MA 1L A版收缩膜+MA A版纸袋+MA 5L A版收藏指南+MA A版slime bag+客版1L PDQ, 翻单：4500159701 每pcs产品上要贴1张RFID贴纸，贴纸由ZURU提供，贴纸位置请严格按照我们签回的签板； Remark: 77685GQ4-S001： 1.包装要求： MA 1L A版收缩膜+MA A版纸袋+MA 5L A版收藏指南+MA A版slime bag+客版1L PDQ, 翻单：4500159701 每pcs产品上要贴1张RFID贴纸，贴纸由ZURU提供，贴纸位置请严格按照我们签回的签板； 2. 外箱印刷带条码的RFID箱唛：RFID紫色色带+WM Dept.图标+RFID图标+ITF-14条码+粉色艾利贴纸（不干胶打印），四面右下角印刷ZURU logo, ITFF条码只印刷在 正唛一面，在加印的时候确保条形码能扫描出来，1张粉红色贴纸贴在正唛对角线，外箱侧面任一角落加印："MADE IN CHINA" 字样； 3. 在产品上和包装上要有日期码、以及要有MADE IN CHINA和ZURU字样； 4. 产品如有扎带口要剪平，不能刮手。 5. 此单需要验货，请多备料 6. 此单以loose carton出货，77685：12pcs/PDQ/CTN | W44: Maggie Xie | X44: 0.945 | Y44: =X44*I44 -> 5499.9 | AA44: 5820 | AB44: =AA44-I44 -> 0 | AD44: 系统出单 | AE44: 77685GQ4-S001 | AF44: 已入 | AG44: =I44 -> 5820 | AH44: =I44 -> 5820 | AK44: =I44 -> 5820 | AN44: =I44 -> 5820 | AV44: =I44/12 -> 485 | BJ44: =$I44*BJ$2 -> 712.34375 | BK44: =$I44*BK$2 -> 712.34375 | BL44: =$I44*BL$2 -> 712.34375 | BM44: =$I44*BM$2 -> 712.34375 | BN44: =$I44*BN$2 -> 712.34375 | BO44: =$I44*BO$2 -> 712.34375 | BP44: =$I44*BP$2 -> 712.34375 | BQ44: =$I44*BQ$2 -> 712.34375 | BR44: =$I44*BR$2 -> 121.25 | BT44: =BT43-BJ44 -> 122422.28 | BU44: =BU43-BK44 -> 122422.28 | BV44: =BV43-BL44 -> 122422.28 | BW44: =BW43-BM44 -> 122422.28 | BX44: =BX43-BN44 -> 122422.28 | BY44: =BY43-BO44 -> 122422.28 | BZ44: =BZ43-BP44 -> 122422.28 | CA44: =CA43-BQ44 -> 122422.28 | CB44: =CB43-BR44 -> 20789.771
A45: 45747 | B45: TARGET US | C45: 美国 | D45: 4500162016 | E45: 10001269475-3890 | F45: 4500162016-10 | G45: 77685GQ1-S002 | H45: 混搭恐龙13pcs/GQ1/箱 | I45: 10530 | J45: 0 | K45: 13 | L45: =I45/K45 -> 810 | M45: 45790 | N45: 45790 | P45: pass | Q45: 5/26 截SI | R45: 45761 | S45: 无 | T45: 4/16条码箱贴纸客供 | V45: 日期码格式：ZURU INC(BVI) 标准格式 日期：按实际生产日期 Packaging Info: MA 1L 收缩膜+ MA 1L PDQ Remark: 1.77685GQ1-S002-5 SURPRISE-DINO MIX AND MATCH-SERIES 1-CAPSULE,13PCS/Gravity PDQ, 13PCS/PDQ/CTN 2. MA 1L 收缩膜+ MA 1L PDQ，收缩膜上的UPC193052079053. 3. 每个外箱正唛箱唛信息左上方位置粘贴条码箱贴纸，每箱只贴一张,由ZURU订购，来料显示DPCI-087-26-6460, UPC 10193052079050. 4. 产品和包装上印刷 tracking code信息，格式为ZURU常规格式; 5. 出货方式：货代自提 | W45: Holly Zheng | X45: 0.765 | Y45: =X45*I45 -> 8055.45 | AA45: =10491+39 -> 10530 | AB45: =AA45-I45 -> 0 | AC45: OK | AD45: 系统出单 | AE45: 77685GQ1-S002 | AF45: 已入 | AG45: =I45 -> 10530 | AH45: =I45 -> 10530 | AK45: =I45 -> 10530 | AO45: =I45 -> 10530 | AT45: =I45/13 -> 810 | BJ45: =$I45*BJ$2 -> 1288.8281 | BK45: =$I45*BK$2 -> 1288.8281 | BL45: =$I45*BL$2 -> 1288.8281 | BM45: =$I45*BM$2 -> 1288.8281 | BN45: =$I45*BN$2 -> 1288.8281 | BO45: =$I45*BO$2 -> 1288.8281 | BP45: =$I45*BP$2 -> 1288.8281 | BQ45: =$I45*BQ$2 -> 1288.8281 | BR45: =$I45*BR$2 -> 219.375 | BT45: =BT44-BJ45 -> 121133.45 | BU45: =BU44-BK45 -> 121133.45 | BV45: =BV44-BL45 -> 121133.45 | BW45: =BW44-BM45 -> 121133.45 | BX45: =BX44-BN45 -> 121133.45 | BY45: =BY44-BO45 -> 121133.45 | BZ45: =BZ44-BP45 -> 121133.45 | CA45: =CA44-BQ45 -> 121133.45 | CB45: =CB44-BR45 -> 20570.396
A46: 45744 | B46: WALMART INC. | C46: 美国 | D46: 4500161750 | E46: 904512454 | F46: 4500161750-10 | G46: 77685SLB-S001 | H46: 混搭恐龙12pcs/GQ4/CTN**96/卡板装 | I46: 1152 | J46: 0 | K46: 1152 | L46: =I46/K46 -> 1 | M46: 45793 | N46: 45789 | O46: 5/19 BV | P46: pass | Q46: 5/27 截SI | R46: 翻单 | S46: 有 | T46: 4/14 RFID | V46: 日期码格式：ZURU DGYYYYMMDD CHINA(日期避开周末和法定节假日即可） 日期：按实际生产日期 Packaging Info: 77685SLB-S001： 1.包装要求： MA 1L A版收缩膜+MA A版纸袋+MA 5L A版收藏指南+MA A版slime bag+客版1L PDQ,翻单：4500159701 每pcs产品上要贴1张RFID贴纸，贴纸由ZURU提供，贴纸位置请严格按照我们签回的签板； Remark: 77685SLB-S001： 1.包装要求： MA 1L A版收缩膜+MA A版纸袋+MA 5L A版收藏指南+MA A版slime bag+客版1L PDQ,翻单：4500159701 每pcs产品上要贴1张RFID贴纸，贴纸由ZURU提供，贴纸位置请严格按照我们签回的签板； 2. 外箱印刷带条码的RFID箱唛：RFID紫色色带+WM Dept.图标+RFID图标+ITF-14条码，四面右下角印刷ZURU logo, ITFF条码只印刷在正唛一面，在加印的时候确保 条形码能扫描出来，外箱侧面任一角落加印："MADE IN CHINA" 字样； 3. 每个slip sheet上面贴一张艾利贴纸（不干胶贴纸）和一张普通贴纸（A4纸），slip sheet打印的普通贴纸的尺寸不能比艾利贴纸小，普通贴纸内容见附件； 4. 在产品上和包装上要有日期码、以及要有MADE IN CHINA和ZURU字样； 5. 产品如有扎带口要剪平，不能刮手。 6. 此单需要验货，请多备料 7. 此单以slip sheet出货，77685：1152pcs/96CTN/Slip Sheet | W46: Maggie Xie | X46: 903.2128 | Y46: =X46*L46 -> 903.2128 | AA46: 1152 | AB46: =AA46-I46 -> 0 | AD46: 系统出单 | AE46: 77685SLB-S001 | AF46: 已入 | AG46: =I46 -> 1152 | AH46: =I46 -> 1152 | AK46: =I46 -> 1152 | AN46: =I46 -> 1152 | AV46: =I46/12 -> 96 | BJ46: =$I46*BJ$2 -> 141 | BK46: =$I46*BK$2 -> 141 | BL46: =$I46*BL$2 -> 141 | BM46: =$I46*BM$2 -> 141 | BN46: =$I46*BN$2 -> 141 | BO46: =$I46*BO$2 -> 141 | BP46: =$I46*BP$2 -> 141 | BQ46: =$I46*BQ$2 -> 141 | BR46: =$I46*BR$2 -> 24 | BT46: =BT45-BJ46 -> 120992.45 | BU46: =BU45-BK46 -> 120992.45 | BV46: =BV45-BL46 -> 120992.45 | BW46: =BW45-BM46 -> 120992.45 | BX46: =BX45-BN46 -> 120992.45 | BY46: =BY45-BO46 -> 120992.45 | BZ46: =BZ45-BP46 -> 120992.45 | CA46: =CA45-BQ46 -> 120992.45 | CB46: =CB45-BR46 -> 20546.396
A47: 45741 | B47: Big Ideas Marketing | C47: 美国 | D47: 4500161373 | E47: 22425 | F47: 4500161373-10 | G47: MGQ15-77685-S001 | H47: 混搭恐龙24pcs/GQ5+外厂#83183GQ5/箱 | I47: 12840 | J47: 0 | K47: 24 | L47: =I47/K47 -> 535 | M47: 45797 | N47: 45793 | O47: 按标准格式，指定日期为2025年5月15日，为了同外厂的球日期一致 | P47: PASS | Q47: 5/26 截SI | R47: 45741 | S47: 无 | T47: 无 | V47: 日期码格式：ZURU INC(BVI) 标准格式 日期：按实际生产日期 Tracking Code: Packaging Info: 1、包装方式：MA UPC优先1L+客版PDQ（客版AW邮件提供），出口美国 其中#MGQ15为混厂混Brand产品，混的产品为#77685GQ5-兴信与#83183GQ5-高德斯（最终组装工厂为兴信), 高德斯工厂的#83183GQ5会在2025/05/13送到 #77685GQ5：193052079053 #83183GQ5：193052069092 Remark: 2、无第三方测试与验货要求。 3、纸箱4面印ZURU LOGO + 箱唛 任何外箱最长的边不得大于48" 4、日期码请按ZURU标准版执行即可。 5、ZURU QC验货。 6、Ratio: #MGQ15/CTN=1 PDQ#77685GQ5(5 SURPRISE-DINO MIX AND MATCH-SERIES 1-CAPSULE,2Facing24pcs/Gravity PDQ,24pcs/PDQ/CTN)+1 PDQ#83183GQ5(MAX-MA X PREMIUM-SERIES 1-GARDEN POT PLANTS-CAPSULE,15PCS/Gravity PDQ,Facing at short side,15PCS/PDQ/CTN) | W47: Annie Huang | X47: 18.4169 | Y47: =X47*L47 -> 9853.0415 | AA47: =12792+48 -> 12840 | AB47: =AA47-I47 -> 0 | AC47: 无 | AD47: 系统出单 | AE47: MGQ15-77685-S001 | AF47: 已入 | AG47: =I47 -> 12840 | AH47: =I47 -> 12840 | AK47: =I47 -> 12840 | AO47: =I47 -> 12840 | AW47: =I47/24 -> 535 | BJ47: =$I47*BJ$2 -> 1571.5625 | BK47: =$I47*BK$2 -> 1571.5625 | BL47: =$I47*BL$2 -> 1571.5625 | BM47: =$I47*BM$2 -> 1571.5625 | BN47: =$I47*BN$2 -> 1571.5625 | BO47: =$I47*BO$2 -> 1571.5625 | BP47: =$I47*BP$2 -> 1571.5625 | BQ47: =$I47*BQ$2 -> 1571.5625 | BR47: =$I47*BR$2 -> 267.5 | BT47: =BT46-BJ47 -> 119420.89 | BU47: =BU46-BK47 -> 119420.89 | BV47: =BV46-BL47 -> 119420.89 | BW47: =BW46-BM47 -> 119420.89 | BX47: =BX46-BN47 -> 119420.89 | BY47: =BY46-BO47 -> 119420.89 | BZ47: =BZ46-BP47 -> 119420.89 | CA47: =CA46-BQ47 -> 119420.89 | CB47: =CB46-BR47 -> 20278.896
A48: 45744 | B48: WALMART INC. | C48: 美国 | D48: 4500161751 | E48: 0904512405 EASTVALE | F48: 4500161751-10 | G48: 77685SLB-S001 | H48: 混搭恐龙卡板装12pcs/GQ4/CTN**96/Slip Sheet | I48: 1152 | J48: 0 | K48: 1152 | L48: =I48/K48 -> 1 | M48: 45797 | N48: 45793 | O48: 5/22 BV | P48: pass | Q48: 5/30 交仓 | R48: 翻单 | S48: 有 | T48: 4/14 RFID | V48: 日期码格式：ZURU DGYYYYMMDD CHINA(日期避开周末和法定节假日即可） 日期：按实际生产日期 Packaging Info: 77685SLB-S001： 1.包装要求： MA 1L A版收缩膜+MA A版纸袋+MA 5L A版收藏指南+MA A版slime bag+客版1L PDQ,翻单：4500159701 每pcs产品上要贴1张RFID贴纸，贴纸由ZURU提供，贴纸位置请严格按照我们签回的签板； Remark: 77685SLB-S001： 1.包装要求： MA 1L A版收缩膜+MA A版纸袋+MA 5L A版收藏指南+MA A版slime bag+客版1L PDQ,翻单：4500159701 每pcs产品上要贴1张RFID贴纸，贴纸由ZURU提供，贴纸位置请严格按照我们签回的签板； 2. 外箱印刷带条码的RFID箱唛：RFID紫色色带+WM Dept.图标+RFID图标+ITF-14条码，四面右下角印刷ZURU logo, ITFF条码只印刷在正唛一面，在加印的时候确保 条形码能扫描出来，外箱侧面任一角落加印："MADE IN CHINA" 字样； 3. 每个slip sheet上面贴一张艾利贴纸（不干胶贴纸）和一张普通贴纸（A4纸），slip sheet打印的普通贴纸的尺寸不能比艾利贴纸小，普通贴纸内容见附件； 4. 在产品上和包装上要有日期码、以及要有MADE IN CHINA和ZURU字样； 5. 产品如有扎带口要剪平，不能刮手。 6. 此单需要验货，请多备料 7. 此单以slip sheet出货，77685：1152pcs/96CTN/Slip Sheet | W48: Maggie Xie | X48: 903.2128 | Y48: =X48*L48 -> 903.2128 | Z48: ZB00394-6.3 | AA48: 1152 | AB48: =AA48-I48 -> 0 | AD48: 系统出单 | AE48: 77685SLB-S001 | AF48: 已入 | AG48: =I48 -> 1152 | AH48: =I48 -> 1152 | AK48: =I48 -> 1152 | AO48: =I48 -> 1152 | AV48: =I48/12 -> 96 | BJ48: =$I48*BJ$2 -> 141 | BK48: =$I48*BK$2 -> 141 | BL48: =$I48*BL$2 -> 141 | BM48: =$I48*BM$2 -> 141 | BN48: =$I48*BN$2 -> 141 | BO48: =$I48*BO$2 -> 141 | BP48: =$I48*BP$2 -> 141 | BQ48: =$I48*BQ$2 -> 141 | BR48: =$I48*BR$2 -> 24 | BT48: =BT47-BJ48 -> 119279.89 | BU48: =BU47-BK48 -> 119279.89 | BV48: =BV47-BL48 -> 119279.89 | BW48: =BW47-BM48 -> 119279.89 | BX48: =BX47-BN48 -> 119279.89 | BY48: =BY47-BO48 -> 119279.89 | BZ48: =BZ47-BP48 -> 119279.89 | CA48: =CA47-BQ48 -> 119279.89 | CB48: =CB47-BR48 -> 20254.896
A49: 45744 | B49: WALMART INC. | C49: 美国 | D49: 4500161751 | E49: 0904512393 ELWOOD | F49: 4500161751-20 | G49: 77685SLB-S001 | H49: 混搭恐龙卡板装12pcs/GQ4/CTN**96/Slip Sheet | I49: 1152 | J49: 0 | K49: 1152 | L49: =I49/K49 -> 1 | M49: 45797 | N49: 45793 | O49: 5/22 BV | P49: pass | Q49: 5/30 交仓 | R49: 翻单 | S49: 有 | T49: 4/14 RFID | V49: 日期码格式：ZURU DGYYYYMMDD CHINA(日期避开周末和法定节假日即可） 日期：按实际生产日期 Packaging Info: 77685SLB-S001： 1.包装要求： MA 1L A版收缩膜+MA A版纸袋+MA 5L A版收藏指南+MA A版slime bag+客版1L PDQ,翻单：4500159701 每pcs产品上要贴1张RFID贴纸，贴纸由ZURU提供，贴纸位置请严格按照我们签回的签板； Remark: 77685SLB-S001： 1.包装要求： MA 1L A版收缩膜+MA A版纸袋+MA 5L A版收藏指南+MA A版slime bag+客版1L PDQ,翻单：4500159701 每pcs产品上要贴1张RFID贴纸，贴纸由ZURU提供，贴纸位置请严格按照我们签回的签板； 2. 外箱印刷带条码的RFID箱唛：RFID紫色色带+WM Dept.图标+RFID图标+ITF-14条码，四面右下角印刷ZURU logo, ITFF条码只印刷在正唛一面，在加印的时候确保 条形码能扫描出来，外箱侧面任一角落加印："MADE IN CHINA" 字样； 3. 每个slip sheet上面贴一张艾利贴纸（不干胶贴纸）和一张普通贴纸（A4纸），slip sheet打印的普通贴纸的尺寸不能比艾利贴纸小，普通贴纸内容见附件； 4. 在产品上和包装上要有日期码、以及要有MADE IN CHINA和ZURU字样； 5. 产品如有扎带口要剪平，不能刮手。 6. 此单需要验货，请多备料 7. 此单以slip sheet出货，77685：1152pcs/96CTN/Slip Sheet | W49: Maggie Xie | X49: 903.2128 | Y49: =X49*L49 -> 903.2128 | Z49: ZB00430-6.7 | AA49: =1140+12 -> 1152 | AB49: =AA49-I49 -> 0 | AD49: 系统出单 | AE49: 77685SLB-S001 | AF49: 已入 | AG49: =I49 -> 1152 | AH49: =I49 -> 1152 | AK49: =I49 -> 1152 | AO49: =I49 -> 1152 | AV49: =I49/12 -> 96 | BJ49: =$I49*BJ$2 -> 141 | BK49: =$I49*BK$2 -> 141 | BL49: =$I49*BL$2 -> 141 | BM49: =$I49*BM$2 -> 141 | BN49: =$I49*BN$2 -> 141 | BO49: =$I49*BO$2 -> 141 | BP49: =$I49*BP$2 -> 141 | BQ49: =$I49*BQ$2 -> 141 | BR49: =$I49*BR$2 -> 24 | BT49: =BT48-BJ49 -> 119138.89 | BU49: =BU48-BK49 -> 119138.89 | BV49: =BV48-BL49 -> 119138.89 | BW49: =BW48-BM49 -> 119138.89 | BX49: =BX48-BN49 -> 119138.89 | BY49: =BY48-BO49 -> 119138.89 | BZ49: =BZ48-BP49 -> 119138.89 | CA49: =CA48-BQ49 -> 119138.89 | CB49: =CB48-BR49 -> 20230.896
A50: 45744 | B50: WALMART INC. | C50: 美国 | D50: 4500161751 | E50: 0904512355 STATESBORO | F50: 4500161751-30 | G50: 77685SLB-S001 | H50: 混搭恐龙卡板装12pcs/GQ4/CTN**96/Slip Sheet | I50: 1152 | J50: 0 | K50: 1152 | L50: =I50/K50 -> 1 | M50: 45797 | N50: 45793 | O50: 5/22 BV | P50: pass | Q50: 6/9 截SI | R50: 翻单 | S50: 有 | T50: 4/14 RFID | V50: 日期码格式：ZURU DGYYYYMMDD CHINA(日期避开周末和法定节假日即可） 日期：按实际生产日期 Packaging Info: 77685SLB-S001： 1.包装要求： MA 1L A版收缩膜+MA A版纸袋+MA 5L A版收藏指南+MA A版slime bag+客版1L PDQ,翻单：4500159701 每pcs产品上要贴1张RFID贴纸，贴纸由ZURU提供，贴纸位置请严格按照我们签回的签板； Remark: 77685SLB-S001： 1.包装要求： MA 1L A版收缩膜+MA A版纸袋+MA 5L A版收藏指南+MA A版slime bag+客版1L PDQ,翻单：4500159701 每pcs产品上要贴1张RFID贴纸，贴纸由ZURU提供，贴纸位置请严格按照我们签回的签板； 2. 外箱印刷带条码的RFID箱唛：RFID紫色色带+WM Dept.图标+RFID图标+ITF-14条码，四面右下角印刷ZURU logo, ITFF条码只印刷在正唛一面，在加印的时候确保 条形码能扫描出来，外箱侧面任一角落加印："MADE IN CHINA" 字样； 3. 每个slip sheet上面贴一张艾利贴纸（不干胶贴纸）和一张普通贴纸（A4纸），slip sheet打印的普通贴纸的尺寸不能比艾利贴纸小，普通贴纸内容见附件； 4. 在产品上和包装上要有日期码、以及要有MADE IN CHINA和ZURU字样； 5. 产品如有扎带口要剪平，不能刮手。 6. 此单需要验货，请多备料 7. 此单以slip sheet出货，77685：1152pcs/96CTN/Slip Sheet | W50: Maggie Xie | X50: 903.2128 | Y50: =X50*L50 -> 903.2128 | AA50: 1152 | AB50: =AA50-I50 -> 0 | AD50: 系统出单 | AE50: 77685SLB-S001 | AF50: 已入 | AG50: =I50 -> 1152 | AH50: =I50 -> 1152 | AK50: =I50 -> 1152 | AO50: =I50 -> 1152 | AV50: =I50/12 -> 96 | BJ50: =$I50*BJ$2 -> 141 | BK50: =$I50*BK$2 -> 141 | BL50: =$I50*BL$2 -> 141 | BM50: =$I50*BM$2 -> 141 | BN50: =$I50*BN$2 -> 141 | BO50: =$I50*BO$2 -> 141 | BP50: =$I50*BP$2 -> 141 | BQ50: =$I50*BQ$2 -> 141 | BR50: =$I50*BR$2 -> 24 | BT50: =BT49-BJ50 -> 118997.89 | BU50: =BU49-BK50 -> 118997.89 | BV50: =BV49-BL50 -> 118997.89 | BW50: =BW49-BM50 -> 118997.89 | BX50: =BX49-BN50 -> 118997.89 | BY50: =BY49-BO50 -> 118997.89 | BZ50: =BZ49-BP50 -> 118997.89 | CA50: =CA49-BQ50 -> 118997.89 | CB50: =CB49-BR50 -> 20206.896
A51: 45744 | B51: WALMART INC. | C51: 美国 | D51: 4500161751 | E51: 0904512380 SUFFOLK | F51: 4500161751-40 | G51: 77685SLB-S001 | H51: 混搭恐龙卡板装12pcs/GQ4/CTN**96/Slip Sheet | I51: 1152 | J51: 0 | K51: 1152 | L51: =I51/K51 -> 1 | M51: 45797 | N51: 45793 | O51: 5/22 BV | P51: pass | Q51: 5/30 交仓 | R51: 翻单 | S51: 有 | T51: 4/14 RFID | V51: 日期码格式：ZURU DGYYYYMMDD CHINA(日期避开周末和法定节假日即可） 日期：按实际生产日期 Packaging Info: 77685SLB-S001： 1.包装要求： MA 1L A版收缩膜+MA A版纸袋+MA 5L A版收藏指南+MA A版slime bag+客版1L PDQ,翻单：4500159701 每pcs产品上要贴1张RFID贴纸，贴纸由ZURU提供，贴纸位置请严格按照我们签回的签板； Remark: 77685SLB-S001： 1.包装要求： MA 1L A版收缩膜+MA A版纸袋+MA 5L A版收藏指南+MA A版slime bag+客版1L PDQ,翻单：4500159701 每pcs产品上要贴1张RFID贴纸，贴纸由ZURU提供，贴纸位置请严格按照我们签回的签板； 2. 外箱印刷带条码的RFID箱唛：RFID紫色色带+WM Dept.图标+RFID图标+ITF-14条码，四面右下角印刷ZURU logo, ITFF条码只印刷在正唛一面，在加印的时候确保 条形码能扫描出来，外箱侧面任一角落加印："MADE IN CHINA" 字样； 3. 每个slip sheet上面贴一张艾利贴纸（不干胶贴纸）和一张普通贴纸（A4纸），slip sheet打印的普通贴纸的尺寸不能比艾利贴纸小，普通贴纸内容见附件； 4. 在产品上和包装上要有日期码、以及要有MADE IN CHINA和ZURU字样； 5. 产品如有扎带口要剪平，不能刮手。 6. 此单需要验货，请多备料 7. 此单以slip sheet出货，77685：1152pcs/96CTN/Slip Sheet | W51: Maggie Xie | X51: 903.2128 | Y51: =X51*L51 -> 903.2128 | AA51: =1128+24 -> 1152 | AB51: =AA51-I51 -> 0 | AD51: 系统出单 | AE51: 77685SLB-S001 | AF51: 已入 | AG51: =I51 -> 1152 | AH51: =I51 -> 1152 | AK51: =I51 -> 1152 | AO51: =I51 -> 1152 | AV51: =I51/12 -> 96 | BJ51: =$I51*BJ$2 -> 141 | BK51: =$I51*BK$2 -> 141 | BL51: =$I51*BL$2 -> 141 | BM51: =$I51*BM$2 -> 141 | BN51: =$I51*BN$2 -> 141 | BO51: =$I51*BO$2 -> 141 | BP51: =$I51*BP$2 -> 141 | BQ51: =$I51*BQ$2 -> 141 | BR51: =$I51*BR$2 -> 24 | BT51: =BT50-BJ51 -> 118856.89 | BU51: =BU50-BK51 -> 118856.89 | BV51: =BV50-BL51 -> 118856.89 | BW51: =BW50-BM51 -> 118856.89 | BX51: =BX50-BN51 -> 118856.89 | BY51: =BY50-BO51 -> 118856.89 | BZ51: =BZ50-BP51 -> 118856.89 | CA51: =CA50-BQ51 -> 118856.89 | CB51: =CB50-BR51 -> 20182.896
A52: 45744 | B52: WALMART INC. | C52: 美国 | D52: 4500161751 | E52: 0904512390 RIDGEVILLE SC | F52: 4500161751-50 | G52: 77685SLB-S001 | H52: 混搭恐龙卡板装12pcs/GQ4/CTN**96/Slip Sheet | I52: 1152 | J52: 0 | K52: 1152 | L52: =I52/K52 -> 1 | M52: 45797 | N52: 45793 | O52: 5/22 BV | P52: pass | Q52: 5/30 交仓 | R52: 翻单 | S52: 有 | T52: 4/14 RFID | V52: 日期码格式：ZURU DGYYYYMMDD CHINA(日期避开周末和法定节假日即可） 日期：按实际生产日期 Packaging Info: 77685SLB-S001： 1.包装要求： MA 1L A版收缩膜+MA A版纸袋+MA 5L A版收藏指南+MA A版slime bag+客版1L PDQ,翻单：4500159701 每pcs产品上要贴1张RFID贴纸，贴纸由ZURU提供，贴纸位置请严格按照我们签回的签板； Remark: 77685SLB-S001： 1.包装要求： MA 1L A版收缩膜+MA A版纸袋+MA 5L A版收藏指南+MA A版slime bag+客版1L PDQ,翻单：4500159701 每pcs产品上要贴1张RFID贴纸，贴纸由ZURU提供，贴纸位置请严格按照我们签回的签板； 2. 外箱印刷带条码的RFID箱唛：RFID紫色色带+WM Dept.图标+RFID图标+ITF-14条码，四面右下角印刷ZURU logo, ITFF条码只印刷在正唛一面，在加印的时候确保 条形码能扫描出来，外箱侧面任一角落加印："MADE IN CHINA" 字样； 3. 每个slip sheet上面贴一张艾利贴纸（不干胶贴纸）和一张普通贴纸（A4纸），slip sheet打印的普通贴纸的尺寸不能比艾利贴纸小，普通贴纸内容见附件； 4. 在产品上和包装上要有日期码、以及要有MADE IN CHINA和ZURU字样； 5. 产品如有扎带口要剪平，不能刮手。 6. 此单需要验货，请多备料 7. 此单以slip sheet出货，77685：1152pcs/96CTN/Slip Sheet | W52: Maggie Xie | X52: 903.2128 | Y52: =X52*L52 -> 903.2128 | AA52: 1152 | AB52: =AA52-I52 -> 0 | AD52: 系统出单 | AE52: 77685SLB-S001 | AF52: 已入 | AG52: =I52 -> 1152 | AH52: =I52 -> 1152 | AK52: =I52 -> 1152 | AO52: =I52 -> 1152 | AV52: =I52/12 -> 96 | BJ52: =$I52*BJ$2 -> 141 | BK52: =$I52*BK$2 -> 141 | BL52: =$I52*BL$2 -> 141 | BM52: =$I52*BM$2 -> 141 | BN52: =$I52*BN$2 -> 141 | BO52: =$I52*BO$2 -> 141 | BP52: =$I52*BP$2 -> 141 | BQ52: =$I52*BQ$2 -> 141 | BR52: =$I52*BR$2 -> 24 | BT52: =BT51-BJ52 -> 118715.89 | BU52: =BU51-BK52 -> 118715.89 | BV52: =BV51-BL52 -> 118715.89 | BW52: =BW51-BM52 -> 118715.89 | BX52: =BX51-BN52 -> 118715.89 | BY52: =BY51-BO52 -> 118715.89 | BZ52: =BZ51-BP52 -> 118715.89 | CA52: =CA51-BQ52 -> 118715.89 | CB52: =CB51-BR52 -> 20158.896
A53: 45749 | B53: WALMART INC. | C53: 美国 | D53: 4500162370 | E53: 0902421360 HOUSTON | F53: 4500162370-10 | G53: 77685GQ4-S001 | H53: 混搭恐龙12pcs/GQ4/箱 | I53: 9108 | J53: 0 | K53: 12 | L53: =I53/K53 -> 759 | M53: 45797 | N53: 45793 | O53: 5/22 BV | P53: pass | Q53: 5/27 截SI | R53: 45749 | S53: 有 | T53: 4/14 RFID | V53: 日期码格式：ZURU DGYYYYMMDD CHINA(日期避开周末和法定节假日即可） 日期：按实际生产日期 Packaging Info: 77685GQ4-S001： 1.包装要求： MA 1L A版收缩膜+MA A版纸袋+MA 5L A版收藏指南+MA A版slime bag+客版1L PDQ,翻单：4500159701 每pcs产品上要贴1张RFID贴纸，贴纸由ZURU提供，贴纸位置请严格按照我们签回的签板； Remark: 77685GQ4-S001： 1.包装要求： MA 1L A版收缩膜+MA A版纸袋+MA 5L A版收藏指南+MA A版slime bag+客版1L PDQ,翻单：4500159701 每pcs产品上要贴1张RFID贴纸，贴纸由ZURU提供，贴纸位置请严格按照我们签回的签板； 2. 外箱印刷带条码的RFID箱唛：RFID紫色色带+WM Dept.图标+RFID图标+ITF-14条码+粉色艾利贴纸（不干胶打印），四面右下角印刷ZURU logo, ITF条码只印刷在 正唛一面，在加印的时候确保条形码能扫描出来，1张粉红色贴纸贴在正唛对角线，外箱侧面任一角落加印："MADE IN CHINA" 字样； 3. 在产品上和包装上要有日期码、以及要有MADE IN CHINA和ZURU字样； 4. 产品如有扎带口要剪平，不能刮手。 5. 此单需要验货，请多备料 6. 此单以loose carton出货，77685：12pcs/PDQ/CTN | W53: Maggie Xie | X53: 0.945 | Y53: =X53*I53 -> 8607.06 | AA53: =8928+180 -> 9108 | AB53: =AA53-I53 -> 0 | AD53: 系统出单 | AE53: 77685GQ4-S001 | AF53: 已入 | AG53: =I53 -> 9108 | AH53: =I53 -> 9108 | AK53: =I53 -> 9108 | AO53: =I53 -> 9108 | AV53: =I53/12 -> 759 | BJ53: =$I53*BJ$2 -> 1114.7812 | BK53: =$I53*BK$2 -> 1114.7812 | BL53: =$I53*BL$2 -> 1114.7812 | BM53: =$I53*BM$2 -> 1114.7812 | BN53: =$I53*BN$2 -> 1114.7812 | BO53: =$I53*BO$2 -> 1114.7812 | BP53: =$I53*BP$2 -> 1114.7812 | BQ53: =$I53*BQ$2 -> 1114.7812 | BR53: =$I53*BR$2 -> 189.75 | BT53: =BT52-BJ53 -> 117601.11 | BU53: =BU52-BK53 -> 117601.11 | BV53: =BV52-BL53 -> 117601.11 | BW53: =BW52-BM53 -> 117601.11 | BX53: =BX52-BN53 -> 117601.11 | BY53: =BY52-BO53 -> 117601.11 | BZ53: =BZ52-BP53 -> 117601.11 | CA53: =CA52-BQ53 -> 117601.11 | CB53: =CB52-BR53 -> 19969.146
A54: 45749 | B54: WALMART INC. | C54: 美国 | D54: 4500162370 | E54: 0902421364 MOBILE | F54: 4500162370-20 | G54: 77685GQ4-S001 | H54: 混搭恐龙12pcs/GQ4/箱 | I54: 7860 | J54: 0 | K54: 12 | L54: =I54/K54 -> 655 | M54: 45797 | N54: 45793 | O54: 5/22 BV | P54: pass | Q54: 5/27 截SI | R54: 45749 | S54: 有 | T54: 4/14 RFID | V54: 日期码格式：ZURU DGYYYYMMDD CHINA(日期避开周末和法定节假日即可） 日期：按实际生产日期 Packaging Info: 77685GQ4-S001： 1.包装要求： MA 1L A版收缩膜+MA A版纸袋+MA 5L A版收藏指南+MA A版slime bag+客版1L PDQ,翻单：4500159701 每pcs产品上要贴1张RFID贴纸，贴纸由ZURU提供，贴纸位置请严格按照我们签回的签板； Remark: 77685GQ4-S001： 1.包装要求： MA 1L A版收缩膜+MA A版纸袋+MA 5L A版收藏指南+MA A版slime bag+客版1L PDQ,翻单：4500159701 每pcs产品上要贴1张RFID贴纸，贴纸由ZURU提供，贴纸位置请严格按照我们签回的签板； 2. 外箱印刷带条码的RFID箱唛：RFID紫色色带+WM Dept.图标+RFID图标+ITF-14条码+粉色艾利贴纸（不干胶打印），四面右下角印刷ZURU logo, ITF条码只印刷在 正唛一面，在加印的时候确保条形码能扫描出来，1张粉红色贴纸贴在正唛对角线，外箱侧面任一角落加印："MADE IN CHINA" 字样； 3. 在产品上和包装上要有日期码、以及要有MADE IN CHINA和ZURU字样； 4. 产品如有扎带口要剪平，不能刮手。 5. 此单需要验货，请多备料 6. 此单以loose carton出货，77685：12pcs/PDQ/CTN | W54: Maggie Xie | X54: 0.945 | Y54: =X54*I54 -> 7427.7 | AA54: =7752+108 -> 7860 | AB54: =AA54-I54 -> 0 | AD54: 系统出单 | AE54: 77685GQ4-S001 | AF54: 已入 | AG54: =I54 -> 7860 | AH54: =I54 -> 7860 | AK54: =I54 -> 7860 | AO54: =I54 -> 7860 | AV54: =I54/12 -> 655 | BJ54: =$I54*BJ$2 -> 962.03125 | BK54: =$I54*BK$2 -> 962.03125 | BL54: =$I54*BL$2 -> 962.03125 | BM54: =$I54*BM$2 -> 962.03125 | BN54: =$I54*BN$2 -> 962.03125 | BO54: =$I54*BO$2 -> 962.03125 | BP54: =$I54*BP$2 -> 962.03125 | BQ54: =$I54*BQ$2 -> 962.03125 | BR54: =$I54*BR$2 -> 163.75 | BT54: =BT53-BJ54 -> 116639.08 | BU54: =BU53-BK54 -> 116639.08 | BV54: =BV53-BL54 -> 116639.08 | BW54: =BW53-BM54 -> 116639.08 | BX54: =BX53-BN54 -> 116639.08 | BY54: =BY53-BO54 -> 116639.08 | BZ54: =BZ53-BP54 -> 116639.08 | CA54: =CA53-BQ54 -> 116639.08 | CB54: =CB53-BR54 -> 19805.396
A55: 45758 | B55: TOYS "R" US (CANADA) LTD. | C55: 加拿大 | D55: 4500163438 | E55: 3501527805 | F55: 4500163438-20 | G55: 77685GQ1-S002 | H55: 混搭恐龙13pcs/GQ1/箱 | I55: 1716 | J55: 0 | K55: 13 | L55: =I55/K55 -> 132 | M55: 45796 | N55: 45793 | O55: 5/27第三方 | P55: 自检 | Q55: 6/6 截SI | R55: 45764 | S55: 无 | T55: 4/17 UPC 贴纸 | V55: 日期码格式：ZURU INC(BVI) 标准格式 日期：按实际生产日期 Packaging Info: 1. 出口加拿大市场，MA UPC版本包装。 #77685GQ1: MA 3L EAN_A版本 +UPC 贴纸；UPC#193052079053 2. 产品、包装、外箱上面tracking code的时间格式需要一致 Remark: 3. 需要第三方SGS验货，验货时间2025/05/19，每款每色请备1PC完整带包装样品供验货人员参考。用完后若无损坏可以放回大货里。 | W55: Abby Mai,Lluvia Zeng | X55: 0.7931 | Y55: =X55*I55 -> 1360.9596 | AA55: =1547+169 -> 1716 | AB55: =AA55-I55 -> 0 | AC55: OK | AD55: 系统出单 | AE55: 77685GQ1-S002-3L | AF55: 已入 | AG55: =I55 -> 1716 | AI55: =I55 -> 1716 | AL55: =I55 -> 1716 | AO55: =I55 -> 1716 | AU55: =I55/13 -> 132 | BJ55: =$I55*BJ$2 -> 210.03125 | BK55: =$I55*BK$2 -> 210.03125 | BL55: =$I55*BL$2 -> 210.03125 | BM55: =$I55*BM$2 -> 210.03125 | BN55: =$I55*BN$2 -> 210.03125 | BO55: =$I55*BO$2 -> 210.03125 | BP55: =$I55*BP$2 -> 210.03125 | BQ55: =$I55*BQ$2 -> 210.03125 | BR55: =$I55*BR$2 -> 35.75 | BT55: =BT54-BJ55 -> 116429.04 | BU55: =BU54-BK55 -> 116429.04 | BV55: =BV54-BL55 -> 116429.04 | BW55: =BW54-BM55 -> 116429.04 | BX55: =BX54-BN55 -> 116429.04 | BY55: =BY54-BO55 -> 116429.04 | BZ55: =BZ54-BP55 -> 116429.04 | CA55: =CA54-BQ55 -> 116429.04 | CB55: =CB54-BR55 -> 19769.646
A56: 45720 | B56: AMAZON UK | C56: 英国 | D56: 4500158581 | E56: Amazon UK: 19EG6O9K | F56: 4500158581-10 | G56: 77723-S001 | H56: 混搭恐龙2PK圆筒装 | I56: 600 | J56: 0 | K56: 12 | L56: =I56/K56 -> 50 | M56: 45799 | N56: 45793 | P56: 自检 | Q56: 5/27 截SI | R56: 空白外箱（加印带Zuru字样的最新logo，除了邮包盒直接做外箱的产品） | S56: 有 | T56: 4/27SSCC贴纸+空白贴纸 | V56: 日期码格式：ZURU INC(BVI) 标准格式 日期：按实际生产日期 Packaging Info: Amazon UK(77723) 1. 77723:2pk 77685 into pvc tube, 12tubes/ctn; MA 3L(3L warning EAN)A收缩膜+MA 1L(23L warning)A说明书+MA 1L A内袋+MA 5L(23L warning)A收藏指南+M A 5L A Slime胶袋+客版PVC筒彩卡(含英法德意西5L警告语+UPC#+邮箱地址+FR/ES/IT环保标，参考翻单PO#4500158469)； 2. 验货时间不迟于2025/5/23. Remark: 1.空白外箱（加印带Zuru字样的最新logo，除了邮包盒直接做外箱的产品） + SSCC LABEL一张, 无箱唛，MADE IN CHINA 外箱只印一正一侧。箱唛资料按照给定的 标准去做即可，无需发回我方再行审批(新标准将另行通知)。 (SSCC LABEL竖贴在外箱正面的正中间，贴一面即可,贴纸离外箱边距必须至少3.2CM。如竖贴无法满足要求，则横贴。如横贴也无法满足要求，则竖贴，遮到ZURU lo go无影响), SSCC贴纸由工厂直接跟勤得采购或者工厂自行采购，每一张SSCC Label都是唯一且有不同流水及条码，且需要检查条码是否能正常扫描，另外，此贴纸 印刷不可出现模糊，溢出及粘胶不牢易脱落等现象，如工厂不按此要求导致贴纸有任何问题产生的罚款将由工厂承担一切责任 。 2.出往UK的产品+包装务必打上UKCA logo ，否则客人会退货且当地会有罚款。 3.订单必须经过ZURU QC验货并且通过后方可出货。 4.法国订单要求包装不使用矿物油，请按要求提供以下其中一份文件再出货 ，产品出到法国被相关部门抽检出现包装不符合此要求的，供应商需要为此承担责任， 故此请严格把关。 -油墨物质""由1 ~ 7个芳香环组成的MOAH""的包装检测报告，要求限值≤1.0%； -包装材料清单，包括包装油墨或物质的信息； -油墨制造商的证书； 5.每一批次出货只能有一个生产日期，不可多个生产日期混在同一批次出货；且邮包盒上必须统一加上日期码；外箱对于日期码没有硬性规定； 6.涉及到相关款式会有闪粉的或者微塑料的，请统一默认出无闪粉或者不含微塑料版本； 7.邮包盒及外箱封箱必须是工字型封箱方式； 8.5 Surprise or Mini Brands涉及包装是2个及2个以上的球入PVC桶包装时，单个球上若有UPC#或者EAN#，请用白色贴纸覆盖住； | W56: Crystal Chen | X56: 1.8626 | Y56: =X56*I56 -> 1117.56 | AA56: 600 | AB56: =AA56-I56 -> 0 | AC56: OK | AD56: 系统出单 | AE56: 77723-S001 | AF56: 已入 | AG56: =I56*2 -> 1200 | AH56: =I56*2 -> 1200 | AL56: =I56*2 -> 1200 | AO56: =I56*2 -> 1200 | BF56: =I56 -> 600 | BG56: =I56 -> 600 | BJ56: =$I56*BJ$2*2 -> 146.875 | BK56: =$I56*BK$2*2 -> 146.875 | BL56: =$I56*BL$2*2 -> 146.875 | BM56: =$I56*BM$2*2 -> 146.875 | BN56: =$I56*BN$2*2 -> 146.875 | BO56: =$I56*BO$2*2 -> 146.875 | BP56: =$I56*BP$2*2 -> 146.875 | BQ56: =$I56*BQ$2*2 -> 146.875 | BR56: =$I56*BR$2*2 -> 25 | BT56: =BT55-BJ56 -> 116282.17 | BU56: =BU55-BK56 -> 116282.17 | BV56: =BV55-BL56 -> 116282.17 | BW56: =BW55-BM56 -> 116282.17 | BX56: =BX55-BN56 -> 116282.17 | BY56: =BY55-BO56 -> 116282.17 | BZ56: =BZ55-BP56 -> 116282.17 | CA56: =CA55-BQ56 -> 116282.17 | CB56: =CB55-BR56 -> 19744.646 | CD56: 2/17 已放MA 圆筒/彩纸/贴纸 | CH56: =CH34-I56 -> 6424 | CI56: =CI34-I56 -> 1424
A57: 45768 | B57: UPD, INC. | C57: 美国 | D57: 4500164375 | E57: PO# 34499 | F57: 4500164375-10 | G57: 77685GQ2-S001 | H57: 混搭恐龙27pcs/GQ2*2/箱 | I57: 2160 | J57: 0 | K57: 54 | L57: =I57/K57 -> 40 | M57: 45799 | N57: 45803 | P57: pass | Q57: 5/28 截SI | R57: 45771 | S57: 无 | T57: 无 | V57: 日期码格式：ZURU INC(BVI) 标准格式 日期：按实际生产日期 Packaging Info: 1. 包装方式：MA UPC 优先1L 最新包装，出口美国 Remark: 2. 外箱箱唛红色和黑色双色印刷 3. 产品和包装上印刷tracking code信息，格式为ZURU常规 4. 需要ZURU QC 验货合格后方可出货 5. 整柜出货。 | W57: Sia Liu | X57: 0.4748 | Y57: =X57*I57 -> 1025.568 | AA57: =108+2052 -> 2160 | AB57: =AA57-I57 -> 0 | AC57: 无 | AD57: 系统出单 | AE57: 77685GQ2-S001-3L | AF57: 已入 | AG57: =I57 -> 2160 | AH57: =I57 -> 2160 | AL57: =I57 -> 2160 | AO57: =I57 -> 2160 | AQ57: =I57/27 -> 80 | BJ57: =$I57*BJ$2 -> 264.375 | BK57: =$I57*BK$2 -> 264.375 | BL57: =$I57*BL$2 -> 264.375 | BM57: =$I57*BM$2 -> 264.375 | BN57: =$I57*BN$2 -> 264.375 | BO57: =$I57*BO$2 -> 264.375 | BP57: =$I57*BP$2 -> 264.375 | BQ57: =$I57*BQ$2 -> 264.375 | BR57: =$I57*BR$2 -> 45 | BT57: =BT56-BJ57 -> 116017.79 | BU57: =BU56-BK57 -> 116017.79 | BV57: =BV56-BL57 -> 116017.79 | BW57: =BW56-BM57 -> 116017.79 | BX57: =BX56-BN57 -> 116017.79 | BY57: =BY56-BO57 -> 116017.79 | BZ57: =BZ56-BP57 -> 116017.79 | CA57: =CA56-BQ57 -> 116017.79 | CB57: =CB56-BR57 -> 19699.646
A58: 45722 | B58: BINGO GLOBAL GROUP FOR TRADING SUPP | C58: 埃及 | D58: 4500159286 | F58: 4500159286-10 | G58: 77685GQ1-S001 | H58: 混搭恐龙13pcs/GQ1*4/箱 | I58: 1040 | J58: 0 | K58: 52 | L58: =I58/K58 -> 20 | M58: 45800 | N58: 45803 | P58: 自检 | Q58: 6/22 截SI | R58: 45762 | S58: 无 | T58: 4/23进口商贴纸 | V58: 日期码格式：ZURU INC(BVI) 标准格式 日期：按实际生产日期 Packaging Info: 77685GQ1: MA 3L EAN 收缩膜+ 进口商贴纸 +MA收藏指南和说明书；MA PDQ Remark: 77685GQ1: Rare ratio:1/48 | W58: Lena Huang | X58: 0.945 | Y58: =X58*I58 -> 982.8 | AA58: 1040 | AB58: =AA58-I58 -> 0 | AC58: OK | AD58: 系统出单 | AE58: 77685GQ1-S001-3L | AF58: 已入 | AG58: =I58 -> 1040 | AH58: =I58 -> 1040 | AL58: =I58 -> 1040 | AO58: =I58 -> 1040 | AU58: =I58/13 -> 80 | BJ58: =$I58*BJ$2 -> 127.29167 | BK58: =$I58*BK$2 -> 127.29167 | BL58: =$I58*BL$2 -> 127.29167 | BM58: =$I58*BM$2 -> 127.29167 | BN58: =$I58*BN$2 -> 127.29167 | BO58: =$I58*BO$2 -> 127.29167 | BP58: =$I58*BP$2 -> 127.29167 | BQ58: =$I58*BQ$2 -> 127.29167 | BR58: =$I58*BR$2 -> 21.666667 | BT58: =BT57-BJ58 -> 115890.5 | BU58: =BU57-BK58 -> 115890.5 | BV58: =BV57-BL58 -> 115890.5 | BW58: =BW57-BM58 -> 115890.5 | BX58: =BX57-BN58 -> 115890.5 | BY58: =BY57-BO58 -> 115890.5 | BZ58: =BZ57-BP58 -> 115890.5 | CA58: =CA57-BQ58 -> 115890.5 | CB58: =CB57-BR58 -> 19677.979
A59: 45727 | B59: THE ENTERTAINER | C59: 英国 | D59: 4500159575 | E59: FB12980 | F59: 4500159575-10 | G59: 77685GQ1-S001 | H59: 混搭恐龙13pcs/GQ1*4/箱 | I59: 21216 | J59: 0 | K59: 52 | L59: =I59/K59 -> 408 | M59: 45800 | N59: 45803 | P59: pass | Q59: 5/28 截SI | R59: 45727 | S59: 无 | T59: 无 | U59: 已出样板 | V59: 日期码格式：ZURU INC(BVI) 标准格式 日期：按实际生产日期 Packaging Info: *MA版本按工厂现有最新库存即可，订单出英国，请注意检查产品及包装应带UKCA图标，包装显示ZURU UK LTD信息，QC同事请查核，如有问题与跟单确认 *生产日期按实际（法定工作日），按ZURU标准格式即可 ，但是请知悉包装日期码需要早于或者等于外箱日期码 ，不能晚于外箱日期码 *请注意所有订单都需要经过ZURU QC验货并且通过后方可出货 *所有产品按符合欧洲标准走货，需要是不含微塑料版本 。 *涉及到硼的，如可选择情况下应使用低硼版本 （slime 类别低硼一般低于300ppm)，无选择的应与跟单复核再安排 。 *条码如下，请核查 77685GQ1-S001 193052079053 * 大货样： 请在5/10 前寄出每款1整套大货样到罗湖办公室7B Sandy Shao 收。 Remark: 77685GQ1-S001 MA-1L 配套包装 | W59: Sandy Shao | X59: 0.7835 | Y59: =X59*I59 -> 16622.736 | AA59: =21216 -> 21216 | AB59: =AA59-I59 -> 0 | AC59: 无 | AD59: 系统出单 | AE59: 77685GQ1-S001 | AF59: 已入 | AG59: =I59 -> 21216 | AH59: =I59 -> 21216 | AK59: =I59 -> 21216 | AO59: =I59 -> 21216 | AT59: =I59/13 -> 1632 | BJ59: =$I59*BJ$2 -> 2596.75 | BK59: =$I59*BK$2 -> 2596.75 | BL59: =$I59*BL$2 -> 2596.75 | BM59: =$I59*BM$2 -> 2596.75 | BN59: =$I59*BN$2 -> 2596.75 | BO59: =$I59*BO$2 -> 2596.75 | BP59: =$I59*BP$2 -> 2596.75 | BQ59: =$I59*BQ$2 -> 2596.75 | BR59: =$I59*BR$2 -> 442 | BT59: =BT58-BJ59 -> 113293.75 | BU59: =BU58-BK59 -> 113293.75 | BV59: =BV58-BL59 -> 113293.75 | BW59: =BW58-BM59 -> 113293.75 | BX59: =BX58-BN59 -> 113293.75 | BY59: =BY58-BO59 -> 113293.75 | BZ59: =BZ58-BP59 -> 113293.75 | CA59: =CA58-BQ59 -> 113293.75 | CB59: =CB58-BR59 -> 19235.979
A60: 45764 | B60: SHOPRITE CHECKERS (PTY) LTD | C60: 南非 | D60: 4500163743 | E60: BRK1177100734 | F60: 4500163743-40 | G60: 77685SK1-S002 | H60: 混搭恐龙展示架带底座 | I60: 4950 | J60: 0 | K60: 33 | L60: =I60/K60 -> 150 | M60: 45800 | N60: 45803 | P60: pass | Q60: 5/29 截SI | R60: 45762 | S60: 无 | T60: 无 | V60: 日期码格式：ZURU INC(BVI) 标准格式 日期：按实际生产日期 Packaging Info: MA PKG, 优先1L Remark: 请留意箱唛色带高度为40mm, 色带顶部需留出10mm高空白地方 客户PO#BRK1177100734 | W60: Doris Shou | X60: 38.1703 | Y60: =X60*L60 -> 5725.545 | AA60: =33+4917 -> 4950 | AB60: =AA60-I60 -> 0 | AC60: 无 | AD60: 系统出单 | AE60: 77685SK1-S002 | AF60: 已入 | AG60: =I60 -> 4950 | AH60: =I60 -> 4950 | AK60: =I60 -> 4950 | AO60: =I60 -> 4950 | BC60: =I60/33 -> 150 | BE60: =BC60 -> 150 | BJ60: =$I60*BJ$2 -> 605.85937 | BK60: =$I60*BK$2 -> 605.85937 | BL60: =$I60*BL$2 -> 605.85937 | BM60: =$I60*BM$2 -> 605.85937 | BN60: =$I60*BN$2 -> 605.85937 | BO60: =$I60*BO$2 -> 605.85937 | BP60: =$I60*BP$2 -> 605.85937 | BQ60: =$I60*BQ$2 -> 605.85937 | BR60: =$I60*BR$2 -> 103.125 | BT60: =BT59-BJ60 -> 112687.89 | BU60: =BU59-BK60 -> 112687.89 | BV60: =BV59-BL60 -> 112687.89 | BW60: =BW59-BM60 -> 112687.89 | BX60: =BX59-BN60 -> 112687.89 | BY60: =BY59-BO60 -> 112687.89 | BZ60: =BZ59-BP60 -> 112687.89 | CA60: =CA59-BQ60 -> 112687.89 | CB60: =CB59-BR60 -> 19132.854
A61: 45749 | B61: K􀃤rkk􀃤inen Oy /Centrawla rehouse | C61: 芬兰 | D61: 4500161573 | E61: 4100411993 | F61: 4500161573-140 | G61: 77685GQ2-S002 | H61: 混搭恐龙27pcs/GQ2/箱 | I61: 162 | J61: 0 | K61: 27 | L61: =I61/K61 -> 6 | M61: 45803 | N61: 45803 | P61: 自检 | Q61: 6/4 截SI | R61: 45770 | S61: 无 | T61: 4/28瑞典芬兰警告语贴纸 | V61: 日期码格式：ZURU INC(BVI) 标准格式 日期：按实际生产日期 Packaging Info: 14. 77685GQ2: MA 3L EAN版收缩膜+瑞典芬兰警告语贴纸+北欧五语通用Slime黑白说明书+MA 5L slime bag+MA B1L(23L warning)说明书+MA 3L PDQ 2. 配比跟MA Remark: 1. 包装如含PVC,请改为PET并第一时间通知跟单 2. 产品/包装要求无硼无香，出欧洲，微塑料需合规。 3.带电池出货的产品所用到的电池需要符合欧洲电池新规(EU) 2023-1542 4.有胶袋的产品：要求产品的胶袋厚度要大于等于0.05mm 5.关于贴纸，如果贴纸位置图的包装版本与大货不一致，请工厂第一时间提前提出。跟单会重新调整确认是否更新贴纸或调整位置图 6.产品/包装不含PFAS成分 7.产品条码如下: 请先检查条码是否正确再安排做货，如有问题请告知 ZURU ITEM#<(>&<)>EAN: 77685GQ2:4894680042612 | W61: Sheba | X61: 0.7792 | Y61: =X61*I61 -> 126.2304 | AA61: 162 | AB61: =AA61-I61 -> 0 | AC61: OK | AD61: 系统出单 | AE61: 77685GQ2-S002-3L | AF61: 已入 | AG61: =I61 -> 162 | AH61: =I61 -> 162 | AL61: =I61 -> 162 | AO61: =I61 -> 162 | AR61: =I61/27 -> 6 | BJ61: =$I61*BJ$2 -> 19.828125 | BK61: =$I61*BK$2 -> 19.828125 | BL61: =$I61*BL$2 -> 19.828125 | BM61: =$I61*BM$2 -> 19.828125 | BN61: =$I61*BN$2 -> 19.828125 | BO61: =$I61*BO$2 -> 19.828125 | BP61: =$I61*BP$2 -> 19.828125 | BQ61: =$I61*BQ$2 -> 19.828125 | BR61: =$I61*BR$2 -> 3.375 | BT61: =BT60-BJ61 -> 112668.07 | BU61: =BU60-BK61 -> 112668.07 | BV61: =BV60-BL61 -> 112668.07 | BW61: =BW60-BM61 -> 112668.07 | BX61: =BX60-BN61 -> 112668.07 | BY61: =BY60-BO61 -> 112668.07 | BZ61: =BZ60-BP61 -> 112668.07 | CA61: =CA60-BQ61 -> 112668.07 | CB61: =CB60-BR61 -> 19129.479
A62: 45744 | B62: WALMART INC. | C62: 美国 | D62: 4500161752 | E62: 0904512463 | F62: 4500161752-10 | G62: 77685SLB-S001 | H62: 混搭恐龙卡板装12pcs/GQ4/CTN**96/Slip Sheet | I62: 1152 | J62: 0 | K62: 1152 | L62: =I62/K62 -> 1 | M62: 45803 | N62: 45803 | O62: 5/30 BV | P62: pass | Q62: 6/3 交仓 | R62: 翻单 | S62: 有 | T62: 4/14 RFID | V62: 日期码格式：ZURU DGYYYYMMDD CHINA(日期避开周末和法定节假日即可） 日期：按实际生产日期 Packaging Info: 77685SLB-S001： 1.包装要求： MA 1L A版收缩膜+MA A版纸袋+MA 5L A版收藏指南+MA A版slime bag+客版1L PDQ,翻单：4500159701 每pcs产品上要贴1张RFID贴纸，贴纸由ZURU提供，贴纸位置请严格按照我们签回的签板； Remark: 77685SLB-S001： 1.包装要求： MA 1L A版收缩膜+MA A版纸袋+MA 5L A版收藏指南+MA A版slime bag+客版1L PDQ,翻单：4500159701 每pcs产品上要贴1张RFID贴纸，贴纸由ZURU提供，贴纸位置请严格按照我们签回的签板； 2. 外箱印刷带条码的RFID箱唛：RFID紫色色带+WM Dept.图标+RFID图标+ITF-14条码，四面右下角印刷ZURU logo, ITFF条码只印刷在正唛一面，在加印的时候确保 条形码能扫描出来，外箱侧面任一角落加印："MADE IN CHINA" 字样； 3. 每个slip sheet上面贴一张艾利贴纸（不干胶贴纸）和一张普通贴纸（A4纸），slip sheet打印的普通贴纸的尺寸不能比艾利贴纸小，普通贴纸内容见附件； 4. 在产品上和包装上要有日期码、以及要有MADE IN CHINA和ZURU字样； 5. 产品如有扎带口要剪平，不能刮手。 6. 此单需要验货，请多备料 7. 此单以slip sheet出货，77685：1152pcs/96CTN/Slip Sheet | W62: Maggie Xie | X62: 903.2128 | Y62: =X62*L62 -> 903.2128 | Z62: ZB00404-6.3 | AA62: =1140+12 -> 1152 | AB62: =AA62-I62 -> 0 | AD62: 系统出单 | AE62: 77685SLB-S001 | AF62: 已入 | AG62: =I62 -> 1152 | AH62: =I62 -> 1152 | AK62: =I62 -> 1152 | AO62: =I62 -> 1152 | AV62: =I62/12 -> 96 | BJ62: =$I62*BJ$2 -> 141 | BK62: =$I62*BK$2 -> 141 | BL62: =$I62*BL$2 -> 141 | BM62: =$I62*BM$2 -> 141 | BN62: =$I62*BN$2 -> 141 | BO62: =$I62*BO$2 -> 141 | BP62: =$I62*BP$2 -> 141 | BQ62: =$I62*BQ$2 -> 141 | BR62: =$I62*BR$2 -> 24 | BT62: =BT61-BJ62 -> 112527.07 | BU62: =BU61-BK62 -> 112527.07 | BV62: =BV61-BL62 -> 112527.07 | BW62: =BW61-BM62 -> 112527.07 | BX62: =BX61-BN62 -> 112527.07 | BY62: =BY61-BO62 -> 112527.07 | BZ62: =BZ61-BP62 -> 112527.07 | CA62: =CA61-BQ62 -> 112527.07 | CB62: =CB61-BR62 -> 19105.479
A63: 45749 | B63: WALMART INC. | C63: 美国 | D63: 4500162371 | E63: 0902421348 EASTVALE | F63: 4500162371-10 | G63: 77685GQ4-S001 | H63: 混搭恐龙12pcs/GQ4/箱 | I63: 6276 | J63: 0 | K63: 12 | L63: =I63/K63 -> 523 | M63: 45803 | N63: 45803 | O63: 5/27 BV | P63: pass | Q63: 6/6 截SI | R63: 45749 | S63: 有 | T63: 4/14 RFID | V63: 日期码格式：ZURU DGYYYYMMDD CHINA(日期避开周末和法定节假日即可） 日期：按实际生产日期 Packaging Info: 77685GQ4-S001： 1.包装要求： MA 1L A版收缩膜+MA A版纸袋+MA 5L A版收藏指南+MA A版slime bag+客版1L PDQ,翻单：4500159701 每pcs产品上要贴1张RFID贴纸，贴纸由ZURU提供，贴纸位置请严格按照我们签回的签板； Remark: 77685GQ4-S001： 1.包装要求： MA 1L A版收缩膜+MA A版纸袋+MA 5L A版收藏指南+MA A版slime bag+客版1L PDQ,翻单：4500159701 每pcs产品上要贴1张RFID贴纸，贴纸由ZURU提供，贴纸位置请严格按照我们签回的签板； 2. 外箱印刷带条码的RFID箱唛：RFID紫色色带+WM Dept.图标+RFID图标+ITF-14条码+粉色艾利贴纸（不干胶打印），四面右下角印刷ZURU logo, ITF条码只印刷在 正唛一面，在加印的时候确保条形码能扫描出来，1张粉红色贴纸贴在正唛对角线，外箱侧面任一角落加印："MADE IN CHINA" 字样； 3. 在产品上和包装上要有日期码、以及要有MADE IN CHINA和ZURU字样； 4. 产品如有扎带口要剪平，不能刮手。 5. 此单需要验货，请多备料 6. 此单以loose carton出货，77685：12pcs/PDQ/CTN | W63: Maggie Xie | X63: 0.945 | Y63: =X63*I63 -> 5930.82 | Z63: ZB00412-6.5 | AA63: 6276 | AB63: =AA63-I63 -> 0 | AD63: 系统出单 | AE63: 77685GQ4-S001 | AF63: 已入 | AG63: =I63 -> 6276 | AH63: =I63 -> 6276 | AK63: =I63 -> 6276 | AO63: =I63 -> 6276 | AV63: =I63/12 -> 523 | BJ63: =$I63*BJ$2 -> 768.15625 | BK63: =$I63*BK$2 -> 768.15625 | BL63: =$I63*BL$2 -> 768.15625 | BM63: =$I63*BM$2 -> 768.15625 | BN63: =$I63*BN$2 -> 768.15625 | BO63: =$I63*BO$2 -> 768.15625 | BP63: =$I63*BP$2 -> 768.15625 | BQ63: =$I63*BQ$2 -> 768.15625 | BR63: =$I63*BR$2 -> 130.75 | BT63: =BT62-BJ63 -> 111758.91 | BU63: =BU62-BK63 -> 111758.91 | BV63: =BV62-BL63 -> 111758.91 | BW63: =BW62-BM63 -> 111758.91 | BX63: =BX62-BN63 -> 111758.91 | BY63: =BY62-BO63 -> 111758.91 | BZ63: =BZ62-BP63 -> 111758.91 | CA63: =CA62-BQ63 -> 111758.91 | CB63: =CB62-BR63 -> 18974.729
A64: 45749 | B64: WALMART INC. | C64: 美国 | D64: 4500162371 | E64: 0902421356 ELWOOD | F64: 4500162371-20 | G64: 77685GQ4-S001 | H64: 混搭恐龙12pcs/GQ4/箱 | I64: 6000 | J64: 0 | K64: 12 | L64: =I64/K64 -> 500 | M64: 45803 | N64: 45803 | O64: 5/27 BV | P64: pass | Q64: 6/6 截SI | R64: 45749 | S64: 有 | T64: 4/14 RFID | V64: 日期码格式：ZURU DGYYYYMMDD CHINA(日期避开周末和法定节假日即可） 日期：按实际生产日期 Packaging Info: 77685GQ4-S001： 1.包装要求： MA 1L A版收缩膜+MA A版纸袋+MA 5L A版收藏指南+MA A版slime bag+客版1L PDQ,翻单：4500159701 每pcs产品上要贴1张RFID贴纸，贴纸由ZURU提供，贴纸位置请严格按照我们签回的签板； Remark: 77685GQ4-S001： 1.包装要求： MA 1L A版收缩膜+MA A版纸袋+MA 5L A版收藏指南+MA A版slime bag+客版1L PDQ,翻单：4500159701 每pcs产品上要贴1张RFID贴纸，贴纸由ZURU提供，贴纸位置请严格按照我们签回的签板； 2. 外箱印刷带条码的RFID箱唛：RFID紫色色带+WM Dept.图标+RFID图标+ITF-14条码+粉色艾利贴纸（不干胶打印），四面右下角印刷ZURU logo, ITF条码只印刷在 正唛一面，在加印的时候确保条形码能扫描出来，1张粉红色贴纸贴在正唛对角线，外箱侧面任一角落加印："MADE IN CHINA" 字样； 3. 在产品上和包装上要有日期码、以及要有MADE IN CHINA和ZURU字样； 4. 产品如有扎带口要剪平，不能刮手。 5. 此单需要验货，请多备料 6. 此单以loose carton出货，77685：12pcs/PDQ/CTN | W64: Maggie Xie | X64: 0.945 | Y64: =X64*I64 -> 5670 | Z64: ZB00413-6.5 | AA64: =5976+24 -> 6000 | AB64: =AA64-I64 -> 0 | AD64: 系统出单 | AE64: 77685GQ4-S001 | AF64: 已入 | AG64: =I64 -> 6000 | AH64: =I64 -> 6000 | AK64: =I64 -> 6000 | AO64: =I64 -> 6000 | AV64: =I64/12 -> 500 | BJ64: =$I64*BJ$2 -> 734.375 | BK64: =$I64*BK$2 -> 734.375 | BL64: =$I64*BL$2 -> 734.375 | BM64: =$I64*BM$2 -> 734.375 | BN64: =$I64*BN$2 -> 734.375 | BO64: =$I64*BO$2 -> 734.375 | BP64: =$I64*BP$2 -> 734.375 | BQ64: =$I64*BQ$2 -> 734.375 | BR64: =$I64*BR$2 -> 125 | BT64: =BT63-BJ64 -> 111024.53 | BU64: =BU63-BK64 -> 111024.53 | BV64: =BV63-BL64 -> 111024.53 | BW64: =BW63-BM64 -> 111024.53 | BX64: =BX63-BN64 -> 111024.53 | BY64: =BY63-BO64 -> 111024.53 | BZ64: =BZ63-BP64 -> 111024.53 | CA64: =CA63-BQ64 -> 111024.53 | CB64: =CB63-BR64 -> 18849.729
A65: 45749 | B65: COOP NORGE HANDEL AS - DOM | C65: 挪威 | D65: 4500162231 | E65: 32578104 | F65: 4500162231-20 | G65: 77685GQ1-S002 | H65: 混搭恐龙13pcs/GQ1/箱 | I65: 2600 | J65: 0 | K65: 13 | L65: =I65/K65 -> 200 | M65: 45803 | N65: 45803 | O65: 5/26-5/27第三方 | P65: pass | Q65: 6/3 截SI | R65: 45750 | S65: 无 | T65: 4/30挪威语警语贴纸 | U65: 已出样板 | V65: 日期码格式：ZURU INC(BVI) 标准格式 日期：按实际生产日期 Packaging Info: 77685GQ1:MA EAN 3L 收缩膜+MA-B COLLECTOR GUIDE+MA 说明书+MA SLIME BAG<(><<)>(><(>&<)><(><<)>)> INNER BAG++MA 3L 展示盒+挪威语警语贴纸 Remark: 1/产品和包装要求无硼无香，包装不能含有PVC； 2/如有微塑料，必须合规欧洲标准，闪粉也是微塑料的一种，目前仅接受三张方式1.去除，2.用可降解材料，和3.永久封印在固体； 3/此订单有第三方验货，请准备三套大货样并不迟于5-14寄出给ZURU 深圳办公室； 4/带电池出货的产品所用到的电池需要符合欧洲电池新规(EU)2023-1542； 5/工厂货号-客户货号彩盒条码-外箱条码 77685GQ1-7254586-4894680042612-10193052079050 6/配比: 77685GQ1:Rare ratio:1/48 | W65: Zoe Zhou | X65: 0.7931 | Y65: =X65*I65 -> 2062.06 | AA65: =2548+39+13 -> 2600 | AB65: =AA65-I65 -> 0 | AC65: OK | AD65: 系统出单 | AE65: 77685GQ1-S002-3L | AF65: 已入 | AG65: =I65 -> 2600 | AH65: =I65 -> 2600 | AL65: =I65 -> 2600 | AO65: =I65 -> 2600 | AU65: =I65/13 -> 200 | BJ65: =$I65*BJ$2 -> 318.22917 | BK65: =$I65*BK$2 -> 318.22917 | BL65: =$I65*BL$2 -> 318.22917 | BM65: =$I65*BM$2 -> 318.22917 | BN65: =$I65*BN$2 -> 318.22917 | BO65: =$I65*BO$2 -> 318.22917 | BP65: =$I65*BP$2 -> 318.22917 | BQ65: =$I65*BQ$2 -> 318.22917 | BR65: =$I65*BR$2 -> 54.166667 | BT65: =BT64-BJ65 -> 110706.3 | BU65: =BU64-BK65 -> 110706.3 | BV65: =BV64-BL65 -> 110706.3 | BW65: =BW64-BM65 -> 110706.3 | BX65: =BX64-BN65 -> 110706.3 | BY65: =BY64-BO65 -> 110706.3 | BZ65: =BZ64-BP65 -> 110706.3 | CA65: =CA64-BQ65 -> 110706.3 | CB65: =CB64-BR65 -> 18795.562
A66: 45755 | B66: Coop Danmark A/S | C66: 丹麦 | D66: 4500160515 | E66: 4508281081 | F66: 4500160515-80 | G66: 77685GQ1-S002 | H66: 混搭恐龙13pcs/GQ1/箱 | I66: 3510 | J66: 0 | K66: 13 | L66: =I66/K66 -> 270 | M66: 45803 | N66: 45803 | P66: 自检 | Q66: 6/3 截SI | R66: 45755 | S66: 无 | T66: 4/21北欧四语警告语贴纸 | U66: 已出样板 | V66: 日期码格式：ZURU INC(BVI) 标准格式 日期：按实际生产日期 Packaging Info: 6. 77685GQ1: MA 3L EAN版收缩膜+丹麦瑞典挪威芬兰语警告语贴纸+北欧五语通用Slime黑白说明书+MA 5L slime bag+MA B1L(23L warning)说明书+MA 3L PDQ+MA 5 L-23L warning收藏指南 Remark: 1. 包装如含PVC,请改为PET 2. 产品/包装要求无硼无香； 3. 出欧洲，微塑料需合规。 4.带电池出货的产品所用到的电池需要符合欧洲电池新规(EU) 2023-1542 5.关于贴纸，如果贴纸位置图的包装版本与大货不一致，请工厂提前提出。跟单会重新调整确认是否更新贴纸或调整位置图 6.产品/包装不含PFAS成分 7. ITEM-COOP ITEM-EAN-GTIN 77685GQ1-1000492570-4894680042612-10193052079050 9. 验货注意，警告语需要包含丹麦语 10，要求样品，寄出时间5/15前， 77685GQ1 各3pcs球+2套散件 其它产品各2套 | W66: Luna Lin | X66: 0.7758 | Y66: =X66*I66 -> 2723.058 | AA66: 3510 | AB66: =AA66-I66 -> 0 | AC66: OK | AD66: 系统出单 | AE66: 77685GQ1-S002-3L | AF66: 已入 | AG66: =I66 -> 3510 | AH66: =I66 -> 3510 | AL66: =I66 -> 3510 | AO66: =I66 -> 3510 | AU66: =I66/13 -> 270 | BJ66: =$I66*BJ$2 -> 429.60937 | BK66: =$I66*BK$2 -> 429.60937 | BL66: =$I66*BL$2 -> 429.60937 | BM66: =$I66*BM$2 -> 429.60937 | BN66: =$I66*BN$2 -> 429.60937 | BO66: =$I66*BO$2 -> 429.60937 | BP66: =$I66*BP$2 -> 429.60937 | BQ66: =$I66*BQ$2 -> 429.60937 | BR66: =$I66*BR$2 -> 73.125 | BT66: =BT65-BJ66 -> 110276.7 | BU66: =BU65-BK66 -> 110276.7 | BV66: =BV65-BL66 -> 110276.7 | BW66: =BW65-BM66 -> 110276.7 | BX66: =BX65-BN66 -> 110276.7 | BY66: =BY65-BO66 -> 110276.7 | BZ66: =BZ65-BP66 -> 110276.7 | CA66: =CA65-BQ66 -> 110276.7 | CB66: =CB65-BR66 -> 18722.438
A67: 45756 | B67: AB Gee of Ripley Ltd. | C67: 英国 | D67: 4500162622 | E67: 777 2MAY25 | F67: 4500162622-20 | G67: 77685GQ2-S003 | H67: 混搭恐龙27pcs/GQ2/内箱*2 | I67: 540 | J67: 27 | K67: 54 | L67: =I67/K67 -> 10 | M67: 45804 | N67: 45803 | P67: 自检 | Q67: 5/30 截SI | R67: 45761 | S67: 无 | T67: 无 | V67: 日期码格式：ZURU INC(BVI) 标准格式 日期：按实际生产日期 Packaging Info: MA 最新UPC包装，各款的条码如下，请先检查条码是否正确再安排做货，如有问题请告知,配比跟MA 77685GQ2：193052079053 Remark: 1.产品及包装需要印UKCA图标，包装需要有ZURU UK LTD/ZURU France地址信息，QC同事请核查，如有问题与跟单确认。 2. 需要符合欧洲标准不能含有闪粉和微塑料，否则不和法规会有客诉产生 | W67: Yoga Huang | X67: 0.9779 | Y67: =X67*I67 -> 528.066 | AA67: 540 | AB67: =AA67-I67 -> 0 | AC67: 无 | AD67: 系统出单 | AE67: 77685GQ2-S003 | AF67: 已入 | AG67: =I67 -> 540 | AH67: =I67 -> 540 | AK67: =I67 -> 540 | AO67: =I67 -> 540 | AQ67: =I67/27 -> 20 | BJ67: =$I67*BJ$2 -> 66.09375 | BK67: =$I67*BK$2 -> 66.09375 | BL67: =$I67*BL$2 -> 66.09375 | BM67: =$I67*BM$2 -> 66.09375 | BN67: =$I67*BN$2 -> 66.09375 | BO67: =$I67*BO$2 -> 66.09375 | BP67: =$I67*BP$2 -> 66.09375 | BQ67: =$I67*BQ$2 -> 66.09375 | BR67: =$I67*BR$2 -> 11.25 | BT67: =BT66-BJ67 -> 110210.6 | BU67: =BU66-BK67 -> 110210.6 | BV67: =BV66-BL67 -> 110210.6 | BW67: =BW66-BM67 -> 110210.6 | BX67: =BX66-BN67 -> 110210.6 | BY67: =BY66-BO67 -> 110210.6 | BZ67: =BZ66-BP67 -> 110210.6 | CA67: =CA66-BQ67 -> 110210.6 | CB67: =CB66-BR67 -> 18711.188
A68: 45771 | B68: ZURU Germany GMBH | C68: 德国 | D68: 4500164783 | E68: 5200006663 | F68: 4500164783-10 | G68: 77685GQ2-S002-MTS | H68: 混搭恐龙27pcs/GQ2/箱 | I68: 1458 | J68: 0 | K68: 27 | L68: =I68/K68 -> 54 | M68: 45804 | N68: 45803 | P68: pass | Q68: 5/29 截SI | R68: 45772 | S68: 无 | T68: 无 | V68: 日期码格式：ZURU INC(BVI) 标准格式 日期：按实际生产日期 Packaging Info: 1.77685GQ2：MA 3L EAN 最新版收缩膜+1张多语警告语贴纸+MA 说明书+MA 最新版PDQ； Remark: 1.波兰内销单，需要通过ZURU 验货结果后才能出货 (工厂需要主动提前同ZURU QC预约验货避免延期出货造成不必要麻烦)； 2. 若有特定款有特殊外箱条码要求时,需要明确列出产品款对应的具体外箱条码号码/条码类型 (若无,可以忽略此需求) 3.所有出口欧洲的产品, 法规规定禁止在包装和共公众用的印刷品中使用矿物油中含有的物质, 包装印刷油墨中含有的MOAH/MOSH的质量浓度不能超过1%, 否则出货 到法国被抽检出现问题, 供应商需要对此负责; 4. date code: 外箱日期码要晚于或等于产品日期码，不能早于产品的日期码 5. 所有电子产品身上需要加字唛，为ZURU FRANCE 地址 (如无电子产品，或者产品布标有此地址，可忽略此信息) ZURU France 1/3, Rue d'Argenteuil 95210 SAINT-GRATIEN, FRANCE 6. 装柜时需要按照款式号码从小到大一款款依次装,避免终端仓库卸货混乱.若一个柜子涉及到几个不同国家内销单,装柜时需要一个国家装完后再装另一个国家的 产品,依次装柜,避免终端仓库因不同国家不同库位位置卸货混乱. (此点需要同工厂装柜人员强调) | W68: Amy Xiao | X68: 0.7581 | Y68: =X68*I68 -> 1105.3098 | AA68: =1458 -> 1458 | AB68: =AA68-I68 -> 0 | AC68: OK | AD68: 系统出单 | AE68: 77685GQ2-S002-3L | AF68: 已入 | AG68: =I68 -> 1458 | AH68: =I68 -> 1458 | AL68: =I68 -> 1458 | AO68: =I68 -> 1458 | AR68: =I68/27 -> 54 | BJ68: =$I68*BJ$2 -> 178.45312 | BK68: =$I68*BK$2 -> 178.45312 | BL68: =$I68*BL$2 -> 178.45312 | BM68: =$I68*BM$2 -> 178.45312 | BN68: =$I68*BN$2 -> 178.45312 | BO68: =$I68*BO$2 -> 178.45312 | BP68: =$I68*BP$2 -> 178.45312 | BQ68: =$I68*BQ$2 -> 178.45312 | BR68: =$I68*BR$2 -> 30.375 | BT68: =BT67-BJ68 -> 110032.15 | BU68: =BU67-BK68 -> 110032.15 | BV68: =BV67-BL68 -> 110032.15 | BW68: =BW67-BM68 -> 110032.15 | BX68: =BX67-BN68 -> 110032.15 | BY68: =BY67-BO68 -> 110032.15 | BZ68: =BZ67-BP68 -> 110032.15 | CA68: =CA67-BQ68 -> 110032.15 | CB68: =CB67-BR68 -> 18680.812
A69: 45765 | B69: Lekia AB | C69: 瑞典 | D69: 4500164226 | E69: 156653-2 | F69: 4500164226-120 | G69: 77685GQ2-S002 | H69: 混搭恐龙27pcs/GQ2/箱 | I69: 729 | J69: 0 | K69: 27 | L69: =I69/K69 -> 27 | M69: 45811 | N69: 45807 | O69: 北欧五语通用Slime黑白说明书 | P69: 自检 | Q69: 6/3 待SO出货 | R69: 45772 | S69: 无 | T69: 5/9警告语/进口商贴纸 | V69: 日期码格式：ZURU INC(BVI) 标准格式 日期：按实际生产日期 Packaging Info: 77685GQ2-S002:MA 3L EAN版收缩膜+北欧五语通用Slime黑白说明书+MA 5L slime bag+MA B1L(23L warning)说明书+MA 3L PDQ+警告语/进口商贴纸 北欧五语通用Slime黑白说明书 带纽扣电池走货北欧六语通用黑白电池说明书 不带电池走货北欧六语通用黑白电池说明书 上述说明书翻单4500162375,之前已通知按照MA采购，不要重复订购 Remark: "1. 包装如含PVC,请改为PET 2. 产品/包装要求无硼无香； 3. 出欧洲，微塑料需合规。 4.带电池出货的产品所用到的电池需要符合欧洲电池新规(EU) 2023-1542 5.关于贴纸，如果贴纸位置图的包装版本与大货不一致，请工厂提前提出。跟单会重新调整确认是否更新贴纸或调整位置图 6.产品/包装不含PFAS成分 7. 产品信息： 77685GQ2-S002//100-222011469//4894680042612 | W69: Luna Lin | X69: 0.7792 | Y69: =X69*I69 -> 568.0368 | AA69: 729 | AB69: =AA69-I69 -> 0 | AC69: OK | AD69: 系统出单 | AE69: 77685GQ2-S002-3L | AF69: 已入 | AG69: =I69 -> 729 | AH69: =I69 -> 729 | AL69: =I69 -> 729 | AO69: =I69 -> 729 | AR69: =I69/27 -> 27 | BJ69: =$I69*BJ$2 -> 89.226562 | BK69: =$I69*BK$2 -> 89.226562 | BL69: =$I69*BL$2 -> 89.226562 | BM69: =$I69*BM$2 -> 89.226562 | BN69: =$I69*BN$2 -> 89.226562 | BO69: =$I69*BO$2 -> 89.226562 | BP69: =$I69*BP$2 -> 89.226562 | BQ69: =$I69*BQ$2 -> 89.226562 | BR69: =$I69*BR$2 -> 15.1875 | BT69: =BT68-BJ69 -> 109942.92 | BU69: =BU68-BK69 -> 109942.92 | BV69: =BV68-BL69 -> 109942.92 | BW69: =BW68-BM69 -> 109942.92 | BX69: =BX68-BN69 -> 109942.92 | BY69: =BY68-BO69 -> 109942.92 | BZ69: =BZ68-BP69 -> 109942.92 | CA69: =CA68-BQ69 -> 109942.92 | CB69: =CB68-BR69 -> 18665.625
A70: 45765 | B70: Lekia AB | C70: 瑞典 | D70: 4500164226 | E70: 156653-2 | F70: 4500164226-210 | G70: 77685SK1-S002 | H70: 混搭恐龙展示架带底座 | I70: 462 | J70: 0 | K70: 33 | L70: =I70/K70 -> 14 | M70: 45811 | N70: 45807 | O70: 北欧五语通用Slime黑白说明书 | P70: 自检 | Q70: 6/3 待SO出货 | R70: 45772 | S70: 无 | T70: 5/9警告语/进口商贴纸+EAN贴纸 | V70: 日期码格式：ZURU INC(BVI) 标准格式 日期：按实际生产日期 Packaging Info: 77685SK1-S002:MA 3L EAN版收缩膜+北欧五语通用Slime黑白说明书+MA 5L slime bag+MA B1L(23L warning)说明书+MA 3L 展示架+警告语/进口商贴纸+EAN贴纸 北欧五语通用Slime黑白说明书 带纽扣电池走货北欧六语通用黑白电池说明书 不带电池走货北欧六语通用黑白电池说明书 上述说明书翻单4500162375,之前已通知按照MA采购，不要重复订购 Remark: "1. 包装如含PVC,请改为PET 2. 产品/包装要求无硼无香； 3. 出欧洲，微塑料需合规。 4.带电池出货的产品所用到的电池需要符合欧洲电池新规(EU) 2023-1542 5.关于贴纸，如果贴纸位置图的包装版本与大货不一致，请工厂提前提出。跟单会重新调整确认是否更新贴纸或调整位置图 6.产品/包装不含PFAS成分 7. 产品信息： 77685SK1-S002//100-222011468//4894680054363 | W70: Luna Lin | X70: 38.3485 | Y70: =X70*L70 -> 536.879 | AA70: 462 | AB70: =AA70-I70 -> 0 | AC70: OK | AD70: 系统出单 | AE70: 77685SK1-S002-3L | AF70: 已入 | AG70: =I70 -> 462 | AH70: =I70 -> 462 | AL70: =I70 -> 462 | AO70: =I70 -> 462 | BD70: =I70/33 -> 14 | BE70: =BD70 -> 14 | BJ70: =$I70*BJ$2 -> 56.546875 | BK70: =$I70*BK$2 -> 56.546875 | BL70: =$I70*BL$2 -> 56.546875 | BM70: =$I70*BM$2 -> 56.546875 | BN70: =$I70*BN$2 -> 56.546875 | BO70: =$I70*BO$2 -> 56.546875 | BP70: =$I70*BP$2 -> 56.546875 | BQ70: =$I70*BQ$2 -> 56.546875 | BR70: =$I70*BR$2 -> 9.625 | BT70: =BT69-BJ70 -> 109886.38 | BU70: =BU69-BK70 -> 109886.38 | BV70: =BV69-BL70 -> 109886.38 | BW70: =BW69-BM70 -> 109886.38 | BX70: =BX69-BN70 -> 109886.38 | BY70: =BY69-BO70 -> 109886.38 | BZ70: =BZ69-BP70 -> 109886.38 | CA70: =CA69-BQ70 -> 109886.38 | CB70: =CB69-BR70 -> 18656
A71: 45701 | B71: THE WAREHOUSE LIMITED | C71: 新西兰 | D71: 4500157534 | E71: 从PP ZP02411012中扣数 | F71: 4500157534-10 | G71: 77685GQ1-S002 | H71: 混搭恐龙13pcs/GQ1/箱 | I71: 156 | J71: 0 | K71: 13 | L71: =I71/K71 -> 12 | M71: 45731 | N71: 45813 | P71: 自检 | Q71: 6/5 出货 | R71: 5/27 箱唛资料， 箱唛资料会在货期前一天提供，外箱上都要贴一张大黄贴："ZURU Product for NZ test " | S71: 有 | T71: 2/14 UPC贴纸+大黄贴 | V71: 日期码格式：ZURU INC(BVI) 标准格式 日期：按实际生产日期 Packaging Info: MA UPC 英语包装（优先1L英语版本，或者3L/5L含英语都可） 此客人不接受易掉落或者剥落或者可直接触碰的闪粉，可降解也不行，但可以接受符合欧洲微塑料标准的珠光粉或者闪片。 77685GQ1: 要加UPC贴纸 所有外箱上都要贴一张大黄贴："ZURU Product for NZ test " Remark: 77685GQ1: Rare ratio:1/48 | W71: Abby Liang | X71: 0.7812 | Y71: =X71*I71 -> 121.8672 | AA71: 156 | AB71: =AA71-I71 -> 0 | AC71: OK | AD71: 消耗PP | AE71: 77685GQ1-S002 | AF71: 已入 | BJ71: =$I71*BJ$2 -> 19.09375 | BK71: =$I71*BK$2 -> 19.09375 | BL71: =$I71*BL$2 -> 19.09375 | BM71: =$I71*BM$2 -> 19.09375 | BN71: =$I71*BN$2 -> 19.09375 | BO71: =$I71*BO$2 -> 19.09375 | BP71: =$I71*BP$2 -> 19.09375 | BQ71: =$I71*BQ$2 -> 19.09375 | BR71: =$I71*BR$2 -> 3.25 | BT71: =BT70-BJ71 -> 109867.28 | BU71: =BU70-BK71 -> 109867.28 | BV71: =BV70-BL71 -> 109867.28 | BW71: =BW70-BM71 -> 109867.28 | BX71: =BX70-BN71 -> 109867.28 | BY71: =BY70-BO71 -> 109867.28 | BZ71: =BZ70-BP71 -> 109867.28 | CA71: =CA70-BQ71 -> 109867.28 | CB71: =CB70-BR71 -> 18652.75
A72: 45775 | B72: Bol.com | C72: 荷兰 | D72: 4500164939 | E72: P2505497 | F72: 4500164939-20 | G72: 77723-S001 | H72: 混搭恐龙2PK圆筒装 | I72: 744 | J72: 0 | K72: 12 | L72: =I72/K72 -> 62 | M72: 45806 | N72: 45811 | P72: 自检 | Q72: 6/12截SI | R72: 45777 | S72: 有 | T72: 5/6EAN+NL警告语+空白贴纸 | V72: 日期码格式：ZURU INC(BVI) 标准格式 日期：按实际生产日期 Packaging Info: BOL NL(9548/77723/92119ABDEH) 2. 77723：2pk 77685 into pvc tube, 12tubes/ctn; MA 3L(3L warning EAN)A收缩膜+MA 1L(23L warning)A说明书+MA 1L A内袋+MA 5L(23L warning)A收藏指南+M A 5L A Slime胶袋+客版PVC筒彩卡(含英法德意西5L警告语+UPC#+邮箱地址+FR/ES/IT环保标，参考翻单PO#4500158469)+2张贴纸(1张EAN#，1张NL警告语，贴在彩卡) ； 4.最迟验货不得晚于2025/5/30; Remark: 1. 出欧洲产品不可含闪粉或者微塑料，若所涉产品无闪粉或不含微塑料可忽略此点； 2. 5 Surprise or Mini Brands涉及包装是2个及2个以上的球入PVC桶包装时，单个球上若有UPC#或者EAN#，请用白色贴纸覆盖住； 3. 箱唛资料按照提供的要求去做即可，无需再发回我方确认； 4.柜货产品务必拉网且要拉紧，拉网要求： A: 网要结实同时网格要细，纸箱不能从网格处跌落下来 B: 打网固定8-10个点。请提供拉网的装柜照片给船务确认 后柜子再离厂。 | W72: Crystal Chen | X72: 1.8228 | Y72: =X72*I72 -> 1356.1632 | AA72: 744 | AB72: =AA72-I72 -> 0 | AC72: OK | AD72: 系统出单 | AE72: 77723-S001 | AF72: 已入 | AG72: =I72*2 -> 1488 | AH72: =I72*2 -> 1488 | AL72: =I72*2 -> 1488 | AO72: =I72*2 -> 1488 | BF72: =I72 -> 744 | BG72: =I72 -> 744 | BJ72: =$I72*BJ$2*2 -> 182.125 | BK72: =$I72*BK$2*2 -> 182.125 | BL72: =$I72*BL$2*2 -> 182.125 | BM72: =$I72*BM$2*2 -> 182.125 | BN72: =$I72*BN$2*2 -> 182.125 | BO72: =$I72*BO$2*2 -> 182.125 | BP72: =$I72*BP$2*2 -> 182.125 | BQ72: =$I72*BQ$2*2 -> 182.125 | BR72: =$I72*BR$2*2 -> 31 | BT72: =BT71-BJ72 -> 109685.16 | BU72: =BU71-BK72 -> 109685.16 | BV72: =BV71-BL72 -> 109685.16 | BW72: =BW71-BM72 -> 109685.16 | BX72: =BX71-BN72 -> 109685.16 | BY72: =BY71-BO72 -> 109685.16 | BZ72: =BZ71-BP72 -> 109685.16 | CA72: =CA71-BQ72 -> 109685.16 | CB72: =CB71-BR72 -> 18621.75 | CD72: 4/23 已放MA 圆筒/彩纸/贴纸 | CH72: =CH94-I72 -> 8752 | CI72: =CI94-I72 -> 3752
A73: 45740 | B73: GLOBUS Logistik GmbH and Co KG | C73: 德国 | D73: 4500161168 | E73: 10349100 | F73: 4500161168-10 | G73: 77685GQ2-S001 | H73: 混搭恐龙27pcs/GQ2*2/箱 | I73: 2754 | J73: 0 | K73: 54 | L73: =I73/K73 -> 51 | M73: 45807 | N73: 45811 | P73: pass | Q73: 6/10 截SI | R73: 45772 | S73: 无 | T73: 4/28德语警告语贴纸 | U73: 已出样板 | V73: 日期码格式：ZURU INC(BVI) 标准格式 日期：按实际生产日期 Packaging Info: "77685GQ2: MA EAN 收缩膜3L-A版本 +德语警告语贴纸+ MA纸袋1L-A版本 +MA贴纸+MA口水胶5L-A版本 + MA收藏指南5+23L-A版本 + MA产品组装说明书23L-A版本+MA PDQ3L-A版本+PDQ GTIN 贴纸 EAN:4894680042612" Remark: "1. 此单出德国，需准时出货。无须客户第三方验货但是需要在6-2 提供验货图片(含不良图）。待客人放货后才能安排走货。 2. 外箱正唛需要贴产品图片贴纸，（外箱印4面-2*正唛+2*侧唛） 3. 外箱正唛需要印GTIN, 请保证GTIN条码能扫描。 4. 需要在货期前一个月安排2套样品给客户评估（非测试，包装无要求）" | W73: Claire Wang | X73: 0.7913 | Y73: =X73*I73 -> 2179.2402 | AA73: 2754 | AB73: =AA73-I73 -> 0 | AC73: OK | AD73: 系统出单 | AE73: 77685GQ2-S001 | AF73: 已入 | AG73: =I73 -> 2754 | AH73: =I73 -> 2754 | AL73: =I73 -> 2754 | AO73: =I73 -> 2754 | AR73: =I73/27 -> 102 | BJ73: =$I73*BJ$2 -> 337.07812 | BK73: =$I73*BK$2 -> 337.07812 | BL73: =$I73*BL$2 -> 337.07812 | BM73: =$I73*BM$2 -> 337.07812 | BN73: =$I73*BN$2 -> 337.07812 | BO73: =$I73*BO$2 -> 337.07812 | BP73: =$I73*BP$2 -> 337.07812 | BQ73: =$I73*BQ$2 -> 337.07812 | BR73: =$I73*BR$2 -> 57.375 | BT73: =BT72-BJ73 -> 109348.08 | BU73: =BU72-BK73 -> 109348.08 | BV73: =BV72-BL73 -> 109348.08 | BW73: =BW72-BM73 -> 109348.08 | BX73: =BX72-BN73 -> 109348.08 | BY73: =BY72-BO73 -> 109348.08 | BZ73: =BZ72-BP73 -> 109348.08 | CA73: =CA72-BQ73 -> 109348.08 | CB73: =CB72-BR73 -> 18564.375
A74: 45776 | B74: G.T. WHOLESALE LIMITED | C74: 加拿大 | D74: 4500165393 | E74: 2924737-00 | F74: 4500165393-10 | G74: 77685GQ1-S002 | H74: 混搭恐龙13pcs/GQ1/箱 | I74: 2314 | J74: 0 | K74: 13 | L74: =I74/K74 -> 178 | M74: 45807 | N74: 45811 | P74: pass | Q74: 6/5 截SI | R74: 45777 | S74: 无 | T74: 5/8 UPC贴纸+进口商贴纸 | U74: 已出大货样 | V74: 日期码格式： 标准格式 日期：按实际生产日期 Packaging Info: 77685GQ1 MA 多语EAN版本+UPC贴纸 UPC号码193052079053 Remark: 出口加拿大， 有 进口商贴纸 5/23前寄出大货样2套 Zuru验货 需要单个产品称重的图片和整箱产品称重的图片，还需要产品上made in China的晒字图片，包装上的警告语的清晰图片，以及单个产品的尺寸测量图片 和外箱的尺寸测量图片 日期跟踪码：产品外包装必须有日期跟踪码，ZURU标准格式日期码 | W74: Summer Mo | X74: 0.7931 | Y74: =X74*I74 -> 1835.2334 | AA74: 2314 | AB74: =AA74-I74 -> 0 | AC74: OK | AD74: 系统出单 | AE74: 77685GQ1-S002-3L | AF74: 已入 | AG74: =I74 -> 2314 | AH74: =I74 -> 2314 | AL74: =I74 -> 2314 | AO74: =I74 -> 2314 | AU74: =I74/13 -> 178 | BJ74: =$I74*BJ$2 -> 283.22396 | BK74: =$I74*BK$2 -> 283.22396 | BL74: =$I74*BL$2 -> 283.22396 | BM74: =$I74*BM$2 -> 283.22396 | BN74: =$I74*BN$2 -> 283.22396 | BO74: =$I74*BO$2 -> 283.22396 | BP74: =$I74*BP$2 -> 283.22396 | BQ74: =$I74*BQ$2 -> 283.22396 | BR74: =$I74*BR$2 -> 48.208333 | BT74: =BT73-BJ74 -> 109064.85 | BU74: =BU73-BK74 -> 109064.85 | BV74: =BV73-BL74 -> 109064.85 | BW74: =BW73-BM74 -> 109064.85 | BX74: =BX73-BN74 -> 109064.85 | BY74: =BY73-BO74 -> 109064.85 | BZ74: =BZ73-BP74 -> 109064.85 | CA74: =CA73-BQ74 -> 109064.85 | CB74: =CB73-BR74 -> 18516.167
A75: 45763 | B75: NORWEGIAN TOY IMPORT AS - DOM | C75: 挪威 | D75: 4500163205 | E75: 14675 | F75: 4500163205-160 | G75: 77685GQ2-S002 | H75: 混搭恐龙27pcs/GQ2/箱 | I75: 135 | J75: 0 | K75: 27 | L75: =I75/K75 -> 5 | M75: 45811 | N75: 45811 | P75: 自检 | Q75: 6/9 截SI | R75: 45763 | S75: 无 | T75: 5/12进口商贴纸 | V75: 日期码格式：ZURU INC(BVI) 标准格式 日期：按实际生产日期 Packaging Info: 77685GQ2：MA-A EAN 3L收缩膜+MA 3L A展示盒+进口商贴纸 Remark: 1/配比： 2/产品和包装要求无硼无香，包装不能含有PVC; 如有微塑料，必须合规欧洲标准，闪粉也是微塑料的一种，目前仅接受三张方式1.去除，2.用可降解材料，和3. 永久封印在固体。 3/带电池出货的产品,电池需要符合欧洲电池新规(EU) 2023-1542. | W75: Zoe Zhou | X75: 0.7792 | Y75: =X75*I75 -> 105.192 | AA75: 135 | AB75: =AA75-I75 -> 0 | AC75: OK | AD75: 系统出单 | AE75: 77685GQ2-S002-3L | AF75: 已入 | AG75: =I75 -> 135 | AI75: =I75 -> 135 | AL75: =I75 -> 135 | AO75: =I75 -> 135 | AR75: =I75/27 -> 5 | BJ75: =$I75*BJ$2 -> 16.523438 | BK75: =$I75*BK$2 -> 16.523438 | BL75: =$I75*BL$2 -> 16.523438 | BM75: =$I75*BM$2 -> 16.523438 | BN75: =$I75*BN$2 -> 16.523438 | BO75: =$I75*BO$2 -> 16.523438 | BP75: =$I75*BP$2 -> 16.523438 | BQ75: =$I75*BQ$2 -> 16.523438 | BR75: =$I75*BR$2 -> 2.8125 | BT75: =BT74-BJ75 -> 109048.33 | BU75: =BU74-BK75 -> 109048.33 | BV75: =BV74-BL75 -> 109048.33 | BW75: =BW74-BM75 -> 109048.33 | BX75: =BX74-BN75 -> 109048.33 | BY75: =BY74-BO75 -> 109048.33 | BZ75: =BZ74-BP75 -> 109048.33 | CA75: =CA74-BQ75 -> 109048.33 | CB75: =CB74-BR75 -> 18513.354
A76: 45771 | B76: NORWEGIAN TOY IMPORT AS - DOM | C76: 挪威 | D76: 4500163205 | E76: 14675 | F76: 4500163205-230 | G76: 77685SK1-S002 | H76: 混搭恐龙展示架带底座 | I76: 165 | J76: 0 | K76: 33 | L76: =I76/K76 -> 5 | M76: 45811 | N76: 45811 | P76: 自检 | Q76: 6/9 截SI | R76: 45763 | S76: 无 | T76: 5/12进口商贴纸 | V76: 日期码格式：ZURU INC(BVI) 标准格式 日期：按实际生产日期 Packaging Info: 77685SK1：MA-A EAN 3L收缩膜+MA 说明书+MA-A 3L展示架+进口商贴纸 Remark: 1/配比： 2/产品和包装要求无硼无香，包装不能含有PVC; 如有微塑料，必须合规欧洲标准，闪粉也是微塑料的一种，目前仅接受三张方式1.去除，2.用可降解材料，和3. 永久封印在固体。 3/带电池出货的产品,电池需要符合欧洲电池新规(EU) 2023-1542. | W76: Zoe Zhou | X76: 38.3485 | Y76: =X76*L76 -> 191.7425 | AA76: 165 | AB76: =AA76-I76 -> 0 | AD76: 系统出单 | AE76: 77685SK1-S002-3L | AF76: 已入 | AG76: =I76 -> 165 | AH76: =I76 -> 165 | AL76: =I76 -> 165 | AO76: =I76 -> 165 | BD76: =I76/33 -> 5 | BE76: =BD76 -> 5 | BJ76: =$I76*BJ$2 -> 20.195312 | BK76: =$I76*BK$2 -> 20.195312 | BL76: =$I76*BL$2 -> 20.195312 | BM76: =$I76*BM$2 -> 20.195312 | BN76: =$I76*BN$2 -> 20.195312 | BO76: =$I76*BO$2 -> 20.195312 | BP76: =$I76*BP$2 -> 20.195312 | BQ76: =$I76*BQ$2 -> 20.195312 | BR76: =$I76*BR$2 -> 3.4375 | BT76: =BT75-BJ76 -> 109028.14 | BU76: =BU75-BK76 -> 109028.14 | BV76: =BV75-BL76 -> 109028.14 | BW76: =BW75-BM76 -> 109028.14 | BX76: =BX75-BN76 -> 109028.14 | BY76: =BY75-BO76 -> 109028.14 | BZ76: =BZ75-BP76 -> 109028.14 | CA76: =CA75-BQ76 -> 109028.14 | CB76: =CB75-BR76 -> 18509.917
A77: 45775 | B77: JSC «Grand-Trade» | C77: 俄罗斯联邦 | D77: MPO03508 | E77: 4500165114-母件PO | G77: 77685-S001-MEC348 | H77: 混搭恐龙4pcs/胶袋*6/箱-同一胶袋内球不重复 | I77: 4944 | J77: 0 | K77: 24 | L77: =I77/K77 -> 206 | M77: 45811 | N77: 45815 | O77: 按照标准配比，4个球一组入一个胶袋，一组球不能有重复 请留意收缩膜和指南需要覆盖recycled material | P77: pass | Q77: 6/10 送丹尼 组装MEC348 | R77: 周转箱 | S77: 无 | T77: 5/13进口商贴纸+EAN条码贴纸+空白贴纸 | V77: Product Requirement Remark: 注意： 注 此客户不允许包装 此 /产品产 /PDQ 上显示 上 recycled material 字眼，如有请告知跟单需要加贴纸覆盖； 字 1. 包装要求如下 包 ： 77685 MA UPC 1L收缩膜 收 +进口商贴纸（覆盖内膜上的 进 recycled material）+EAN条码贴纸， 条 MA收藏指南 收 + 加空白贴纸覆盖 加 recycled material ， MA产品组装说明书 产 2. 标准配比 仓库联系人 丹尼 丹尼玩具（龙川）有限公司 中国广东河源广东省 河源市 龙川县 登云镇 深圳宝安（龙川）产业转移工业园6-2号地块 | W77: Claire Wang/Cora Zhou/Ann Zhang | X77: 0.8 | Y77: =X77*I77 -> 3955.2 | Z77: 95833-7.31 | AA77: 4944 | AB77: =AA77-I77 -> 0 | AC77: OK | AD77: 系统出单 | AE77: 77685-S001-MEC348 | AF77: 已入 | AG77: =I77 -> 4944 | AH77: =I77 -> 4944 | AK77: =I77 -> 4944 | AO77: =I77 -> 4944 | BJ77: =$I77*BJ$2 -> 605.125 | BK77: =$I77*BK$2 -> 605.125 | BL77: =$I77*BL$2 -> 605.125 | BM77: =$I77*BM$2 -> 605.125 | BN77: =$I77*BN$2 -> 605.125 | BO77: =$I77*BO$2 -> 605.125 | BP77: =$I77*BP$2 -> 605.125 | BQ77: =$I77*BQ$2 -> 605.125 | BR77: =$I77*BR$2 -> 103 | BT77: =BT76-BJ77 -> 108423.01 | BU77: =BU76-BK77 -> 108423.01 | BV77: =BV76-BL77 -> 108423.01 | BW77: =BW76-BM77 -> 108423.01 | BX77: =BX76-BN77 -> 108423.01 | BY77: =BY76-BO77 -> 108423.01 | BZ77: =BZ76-BP77 -> 108423.01 | CA77: =CA76-BQ77 -> 108423.01 | CB77: =CB76-BR77 -> 18406.917
A78: 45775 | B78: JSC «Grand-Trade» | C78: 俄罗斯联邦 | D78: MPO03508 | E78: 4500165114-母件PO | G78: 77685-S001-MEC348 | H78: 混搭恐龙4pcs/胶袋*6/箱-同一胶袋内球不重复 | I78: 7168 | J78: 0 | K78: 24 | L78: =I78/K78 -> 298.66667 | M78: 45811 | N78: 45815 | O78: 按照标准配比，4个球一组入一个胶袋，一组球不能有重复 请留意收缩膜和指南需要覆盖recycled material | P78: pass | Q78: 6/10 送丹尼 组装MEC348 | R78: 周转箱 | S78: 无 | T78: 5/13进口商贴纸+EAN条码贴纸+空白贴纸 | V78: Product Requirement Remark: 注意： 注 此客户不允许包装 此 /产品产 /PDQ 上显示 上 recycled material 字眼，如有请告知跟单需要加贴纸覆盖； 字 1. 包装要求如下 包 ： 77685 MA UPC 1L收缩膜 收 +进口商贴纸（覆盖内膜上的 进 recycled material）+EAN条码贴纸， 条 MA收藏指南 收 + 加空白贴纸覆盖 加 recycled material ， MA产品组装说明书 产 2. 标准配比 仓库联系人 丹尼 丹尼玩具（龙川）有限公司 中国广东河源广东省 河源市 龙川县 登云镇 深圳宝安（龙川）产业转移工业园6-2号地块 | W78: Claire Wang/Cora Zhou/Ann Zhang | X78: 0.8 | Y78: =X78*I78 -> 5734.4 | Z78: 95833-7.31 | AA78: 7168 | AB78: =AA78-I78 -> 0 | AD78: 系统出单 | AE78: 77685-S001-MEC348 | AF78: 已入 | AG78: =I78 -> 7168 | AH78: =I78 -> 7168 | AK78: =I78 -> 7168 | AO78: =I78 -> 7168 | BJ78: =$I78*BJ$2 -> 877.33333 | BK78: =$I78*BK$2 -> 877.33333 | BL78: =$I78*BL$2 -> 877.33333 | BM78: =$I78*BM$2 -> 877.33333 | BN78: =$I78*BN$2 -> 877.33333 | BO78: =$I78*BO$2 -> 877.33333 | BP78: =$I78*BP$2 -> 877.33333 | BQ78: =$I78*BQ$2 -> 877.33333 | BR78: =$I78*BR$2 -> 149.33333 | BT78: =BT77-BJ78 -> 107545.68 | BU78: =BU77-BK78 -> 107545.68 | BV78: =BV77-BL78 -> 107545.68 | BW78: =BW77-BM78 -> 107545.68 | BX78: =BX77-BN78 -> 107545.68 | BY78: =BY77-BO78 -> 107545.68 | BZ78: =BZ77-BP78 -> 107545.68 | CA78: =CA77-BQ78 -> 107545.68 | CB78: =CB77-BR78 -> 18257.583
A79: 45775 | B79: WALMART INC. | C79: 美国 | D79: 4500162784 | E79: 0904512394EAS TVALE | F79: 4500162784-10 | G79: 77685SLB-S001 | H79: 混搭恐龙卡板装12pcs/GQ4/CTN**96/Slip Sheet | I79: 1152 | J79: 0 | K79: 1152 | L79: =I79/K79 -> 1 | M79: 45811 | N79: 45815 | O79: 6/9 BV | P79: 自检 | Q79: 6/14 截SI | R79: 翻单 | S79: 有 | T79: 5/12 RFID | V79: 日期码格式：ZURU DGYYYYMMDD CHINA(日期避开周末和法定节假日即可） 日期：按实际生产日期 Packaging Info: 77685SLB-S001： 1.包装要求： MA 1L A版收缩膜+MA A版纸袋+MA 5L A版收藏指南+MA A版slime bag+客版1L PDQ,翻单：4500159701 每pcs产品上要贴1张RFID贴纸，贴纸由ZURU提供，贴纸位置请严格按照我们签回的签板 Remark: 77685SLB-S001： 1.包装要求： MA 1L A版收缩膜+MA A版纸袋+MA 5L A版收藏指南+MA A版slime bag+客版1L PDQ,翻单：4500159701 每pcs产品上要贴1张RFID贴纸，贴纸由ZURU提供，贴纸位置请严格按照我们签回的签板； 2. 外箱印刷带条码的RFID箱唛：RFID紫色色带+WM Dept.图标+RFID图标+ITF-14条码，四面右下角印刷ZURU logo, ITFF条码只印刷在正唛一面，在加印的时候确保 条形码能扫描出来，外箱侧面任一角落加印："MADE IN CHINA" 字样； 3. 每个slip sheet上面贴一张艾利贴纸（不干胶贴纸）和一张普通贴纸（A4纸），slip sheet打印的普通贴纸的尺寸不能比艾利贴纸小，普通贴纸内容见附件； 4. 在产品上和包装上要有日期码、以及要有MADE IN CHINA和ZURU字样； 5. 产品如有扎带口要剪平，不能刮手。 6.此单以slip sheet出货，77685：1152pcs/96CTN/Slip Sheet | W79: Maggie Xie | X79: 555.88 | Y79: =X79*L79 -> 555.88 | Z79: ZB00475-6.14 | AA79: 1152 | AB79: =AA79-I79 -> 0 | AD79: 系统出单 | AE79: 77685SLB-S001 | AF79: 已入 | AG79: =I79 -> 1152 | AH79: =I79 -> 1152 | AK79: =I79 -> 1152 | AO79: =I79 -> 1152 | AV79: =I79/12 -> 96 | BJ79: =$I79*BJ$2 -> 141 | BK79: =$I79*BK$2 -> 141 | BL79: =$I79*BL$2 -> 141 | BM79: =$I79*BM$2 -> 141 | BN79: =$I79*BN$2 -> 141 | BO79: =$I79*BO$2 -> 141 | BP79: =$I79*BP$2 -> 141 | BQ79: =$I79*BQ$2 -> 141 | BR79: =$I79*BR$2 -> 24 | BT79: =BT78-BJ79 -> 107404.68 | BU79: =BU78-BK79 -> 107404.68 | BV79: =BV78-BL79 -> 107404.68 | BW79: =BW78-BM79 -> 107404.68 | BX79: =BX78-BN79 -> 107404.68 | BY79: =BY78-BO79 -> 107404.68 | BZ79: =BZ78-BP79 -> 107404.68 | CA79: =CA78-BQ79 -> 107404.68 | CB79: =CB78-BR79 -> 18233.583
A80: 45775 | B80: WALMART INC. | C80: 美国 | D80: 4500162784 | E80: 0904512384ELW OOD | F80: 4500162784-20 | G80: 77685SLB-S001 | H80: 混搭恐龙卡板装12pcs/GQ4/CTN**96/Slip Sheet | I80: 1152 | J80: 0 | K80: 1152 | L80: =I80/K80 -> 1 | M80: 45811 | N80: 45815 | O80: 6/9 BV | P80: 自检 | Q80: 6/20 截SI | R80: 翻单 | S80: 有 | T80: 5/12 RFID | V80: 日期码格式：ZURU DGYYYYMMDD CHINA(日期避开周末和法定节假日即可） 日期：按实际生产日期 Packaging Info: 77685SLB-S001： 1.包装要求： MA 1L A版收缩膜+MA A版纸袋+MA 5L A版收藏指南+MA A版slime bag+客版1L PDQ,翻单：4500159701 每pcs产品上要贴1张RFID贴纸，贴纸由ZURU提供，贴纸位置请严格按照我们签回的签板 Remark: 77685SLB-S001： 1.包装要求： MA 1L A版收缩膜+MA A版纸袋+MA 5L A版收藏指南+MA A版slime bag+客版1L PDQ,翻单：4500159701 每pcs产品上要贴1张RFID贴纸，贴纸由ZURU提供，贴纸位置请严格按照我们签回的签板； 2. 外箱印刷带条码的RFID箱唛：RFID紫色色带+WM Dept.图标+RFID图标+ITF-14条码，四面右下角印刷ZURU logo, ITFF条码只印刷在正唛一面，在加印的时候确保 条形码能扫描出来，外箱侧面任一角落加印："MADE IN CHINA" 字样； 3. 每个slip sheet上面贴一张艾利贴纸（不干胶贴纸）和一张普通贴纸（A4纸），slip sheet打印的普通贴纸的尺寸不能比艾利贴纸小，普通贴纸内容见附件； 4. 在产品上和包装上要有日期码、以及要有MADE IN CHINA和ZURU字样； 5. 产品如有扎带口要剪平，不能刮手。 6.此单以slip sheet出货，77685：1152pcs/96CTN/Slip Sheet | W80: Maggie Xie | X80: 555.88 | Y80: =X80*L80 -> 555.88 | Z80: ZB00505-6.18 | AA80: 1152 | AB80: =AA80-I80 -> 0 | AD80: 系统出单 | AE80: 77685SLB-S001 | AF80: 已入 | AG80: =I80 -> 1152 | AH80: =I80 -> 1152 | AK80: =I80 -> 1152 | AO80: =I80 -> 1152 | AV80: =I80/12 -> 96 | BJ80: =$I80*BJ$2 -> 141 | BK80: =$I80*BK$2 -> 141 | BL80: =$I80*BL$2 -> 141 | BM80: =$I80*BM$2 -> 141 | BN80: =$I80*BN$2 -> 141 | BO80: =$I80*BO$2 -> 141 | BP80: =$I80*BP$2 -> 141 | BQ80: =$I80*BQ$2 -> 141 | BR80: =$I80*BR$2 -> 24 | BT80: =BT79-BJ80 -> 107263.68 | BU80: =BU79-BK80 -> 107263.68 | BV80: =BV79-BL80 -> 107263.68 | BW80: =BW79-BM80 -> 107263.68 | BX80: =BX79-BN80 -> 107263.68 | BY80: =BY79-BO80 -> 107263.68 | BZ80: =BZ79-BP80 -> 107263.68 | CA80: =CA79-BQ80 -> 107263.68 | CB80: =CB79-BR80 -> 18209.583
A81: 45774 | B81: UNFI WHOLESALE INC | C81: 美国 | D81: 4500165209 | E81: PO# 43359476 | F81: 4500165209-40 | G81: 77685GQ2-S001 | H81: 混搭恐龙27pcs/GQ2*2/箱 | I81: 5130 | J81: 0 | K81: 54 | L81: =I81/K81 -> 95 | M81: 45817 | N81: 45815 | P81: pass | Q81: 6/18 交仓 | R81: 45784 | S81: 无 | T81: 无 | V81: 日期码格式：ZURU INC(BVI) 标准格式 日期：按实际生产日期 Packaging Info: 优先ZURU MA 1L包装，显示ZURU UPC条码，出口美国 Remark: 1、无第三方测试和验货；Zuru QC 验货即可出货； 2、如果产品含塑胶袋，厚度小于1/1000 inch（0.0254 毫米），需印警告语 | W81: Sia Liu | X81: 0.4715 | Y81: =X81*I81 -> 2418.795 | Z81: ZB00564-6.24 | AA81: =5076+54 -> 5130 | AB81: =AA81-I81 -> 0 | AC81: 无 | AD81: 系统出单 | AE81: 77685GQ2-S001 | AF81: 已入 | AG81: =I81 -> 5130 | AH81: =I81 -> 5130 | AK81: =I81 -> 5130 | AO81: =I81 -> 5130 | AQ81: =I81/27 -> 190 | BJ81: =$I81*BJ$2 -> 627.89062 | BK81: =$I81*BK$2 -> 627.89062 | BL81: =$I81*BL$2 -> 627.89062 | BM81: =$I81*BM$2 -> 627.89062 | BN81: =$I81*BN$2 -> 627.89062 | BO81: =$I81*BO$2 -> 627.89062 | BP81: =$I81*BP$2 -> 627.89062 | BQ81: =$I81*BQ$2 -> 627.89062 | BR81: =$I81*BR$2 -> 106.875 | BT81: =BT80-BJ81 -> 106635.79 | BU81: =BU80-BK81 -> 106635.79 | BV81: =BV80-BL81 -> 106635.79 | BW81: =BW80-BM81 -> 106635.79 | BX81: =BX80-BN81 -> 106635.79 | BY81: =BY80-BO81 -> 106635.79 | BZ81: =BZ80-BP81 -> 106635.79 | CA81: =CA80-BQ81 -> 106635.79 | CB81: =CB80-BR81 -> 18102.708
A82: 45774 | B82: UNFI WHOLESALE INC | C82: 美国 | D82: 4500165209 | E82: PO# 91157512 | F82: 4500165209-90 | G82: 77685GQ2-S001 | H82: 混搭恐龙27pcs/GQ2*2/箱 | I82: 270 | J82: 0 | K82: 54 | L82: =I82/K82 -> 5 | M82: 45817 | N82: 45815 | P82: pass | Q82: 6/18 交仓 | R82: 45784 | S82: 无 | T82: 无 | V82: 日期码格式：ZURU INC(BVI) 标准格式 日期：按实际生产日期 Packaging Info: 优先ZURU MA 1L包装，显示ZURU UPC条码，出口美国 Remark: 1、无第三方测试和验货；Zuru QC 验货即可出货； 2、如果产品含塑胶袋，厚度小于1/1000 inch（0.0254 毫米），需印警告语 | W82: Sia Liu | X82: 0.478 | Y82: =X82*I82 -> 129.06 | Z82: ZB00564-6.24 | AA82: 270 | AB82: =AA82-I82 -> 0 | AC82: 无 | AD82: 系统出单 | AE82: 77685GQ2-S001 | AF82: 已入 | AG82: =I82 -> 270 | AH82: =I82 -> 270 | AK82: =I82 -> 270 | AO82: =I82 -> 270 | AQ82: =I82/27 -> 10 | BJ82: =$I82*BJ$2 -> 33.046875 | BK82: =$I82*BK$2 -> 33.046875 | BL82: =$I82*BL$2 -> 33.046875 | BM82: =$I82*BM$2 -> 33.046875 | BN82: =$I82*BN$2 -> 33.046875 | BO82: =$I82*BO$2 -> 33.046875 | BP82: =$I82*BP$2 -> 33.046875 | BQ82: =$I82*BQ$2 -> 33.046875 | BR82: =$I82*BR$2 -> 5.625 | BT82: =BT81-BJ82 -> 106602.74 | BU82: =BU81-BK82 -> 106602.74 | BV82: =BV81-BL82 -> 106602.74 | BW82: =BW81-BM82 -> 106602.74 | BX82: =BX81-BN82 -> 106602.74 | BY82: =BY81-BO82 -> 106602.74 | BZ82: =BZ81-BP82 -> 106602.74 | CA82: =CA81-BQ82 -> 106602.74 | CB82: =CB81-BR82 -> 18097.083
A83: 45774 | B83: UNFI WHOLESALE INC | C83: 美国 | D83: 4500165209 | E83: PO# 96103059 | F83: 4500165209-140 | G83: 77685GQ2-S001 | H83: 混搭恐龙27pcs/GQ2*2/箱 | I83: 648 | J83: 0 | K83: 54 | L83: =I83/K83 -> 12 | M83: 45817 | N83: 45815 | P83: pass | Q83: 6/18 交仓 | R83: 45784 | S83: 无 | T83: 无 | V83: 日期码格式：ZURU INC(BVI) 标准格式 日期：按实际生产日期 Packaging Info: 优先ZURU MA 1L包装，显示ZURU UPC条码，出口美国 Remark: 1、无第三方测试和验货；Zuru QC 验货即可出货； 2、如果产品含塑胶袋，厚度小于1/1000 inch（0.0254 毫米），需印警告语 | W83: Sia Liu | X83: 0.478 | Y83: =X83*I83 -> 309.744 | Z83: ZB00564-6.24 | AA83: 648 | AB83: =AA83-I83 -> 0 | AC83: 无 | AD83: 系统出单 | AE83: 77685GQ2-S001 | AF83: 已入 | AG83: =I83 -> 648 | AH83: =I83 -> 648 | AK83: =I83 -> 648 | AO83: =I83 -> 648 | AQ83: =I83/27 -> 24 | BJ83: =$I83*BJ$2 -> 79.3125 | BK83: =$I83*BK$2 -> 79.3125 | BL83: =$I83*BL$2 -> 79.3125 | BM83: =$I83*BM$2 -> 79.3125 | BN83: =$I83*BN$2 -> 79.3125 | BO83: =$I83*BO$2 -> 79.3125 | BP83: =$I83*BP$2 -> 79.3125 | BQ83: =$I83*BQ$2 -> 79.3125 | BR83: =$I83*BR$2 -> 13.5 | BT83: =BT82-BJ83 -> 106523.43 | BU83: =BU82-BK83 -> 106523.43 | BV83: =BV82-BL83 -> 106523.43 | BW83: =BW82-BM83 -> 106523.43 | BX83: =BX82-BN83 -> 106523.43 | BY83: =BY82-BO83 -> 106523.43 | BZ83: =BZ82-BP83 -> 106523.43 | CA83: =CA82-BQ83 -> 106523.43 | CB83: =CB82-BR83 -> 18083.583
A84: 45777 | B84: Salling Group A/S | C84: 丹麦 | D84: MPO03527 | E84: 4500165363-母件PO | G84: 77685-S001-MEC299 | H84: 混搭恐龙30pcs/周装箱 | I84: 1530 | J84: 0 | K84: 30 | L84: =I84/K84 -> 51 | M84: 45818 | N84: 45817 | P84: 自检 | Q84: 送丹尼组装展示架MEC299 | R84: 周转箱 | S84: 无 | T84: 丹麦语警告语贴纸翻4500160515+北欧五语通用Slime黑白说明书 | U84: 已出样板 | V84: Remark: 1. ##77685: MA 3L EAN版收缩膜+丹麦语警告语贴纸--贴纸和位置图翻Coop PO#4500160515+北欧五语通用Slime黑白说明书+MA 5L slime bag+MA B1L(23L warning)说明书+MA 5L-23L warning收藏指南; 产品条码EAN#4894680042612: 请先检查条码是否正确再安排做货，如有问题请告知 2. 包装如含PVC,请改为PET,产品/包装要求无硼无香' 3. 出欧洲，微塑料需合规。 4.带电池出货的产品所用到的电池需要符合欧洲电池新规(EU) 2023-1542 5.关于贴纸，如果贴纸位置图的包装版本与大货不一致，请工厂提前提出。跟单会重新调整确认是否更新贴纸或调整位置图 6.产品/包装不含PFAS成分 7. 每座展示架包含30个#77685，请工厂务必按照每座展示架数量配好每个assortment的配比，方便组装厂直接组装展示架，配比跟MA标准款，如有不清楚的请找PM和跟 单核查 8. 外箱可以直接用周转箱或者其他，工厂自行安排即可，请在外箱上写好每箱装多少和总箱数方便点数 9. 送货到永茂时请在送货单上备注客供子件给Salling Group PO#4500165363/#MEC299混装展示架用 10. 组装厂会安排最终验货，请准备好备品，验货后需要马上安排补货，届时请务必按时送货到永茂厂 | W84: Sheba Ye | X84: 0.8 | Y84: =X84*I84 -> 1224 | AA84: 1530 | AB84: =AA84-I84 -> 0 | AC84: OK | AD84: 系统出单 | AE84: 77685-S001-MEC299 | AF84: 已入 | AG84: =I84 -> 1530 | AH84: =I84 -> 1530 | AL84: =I84 -> 1530 | AO84: =I84 -> 1530 | BJ84: =$I84*BJ$2 -> 187.26562 | BK84: =$I84*BK$2 -> 187.26562 | BL84: =$I84*BL$2 -> 187.26562 | BM84: =$I84*BM$2 -> 187.26562 | BN84: =$I84*BN$2 -> 187.26562 | BO84: =$I84*BO$2 -> 187.26562 | BP84: =$I84*BP$2 -> 187.26562 | BQ84: =$I84*BQ$2 -> 187.26562 | BR84: =$I84*BR$2 -> 31.875 | BT84: =BT83-BJ84 -> 106336.16 | BU84: =BU83-BK84 -> 106336.16 | BV84: =BV83-BL84 -> 106336.16 | BW84: =BW83-BM84 -> 106336.16 | BX84: =BX83-BN84 -> 106336.16 | BY84: =BY83-BO84 -> 106336.16 | BZ84: =BZ83-BP84 -> 106336.16 | CA84: =CA83-BQ84 -> 106336.16 | CB84: =CB83-BR84 -> 18051.708
A85: 45744 | B85: MEIJER DISTRIBUTION, INC. | C85: 美国 | D85: 4500161803 | E85: 客户PO：21688 8482 | F85: 4500161803-40 | G85: 77685GQ1-S002 | H85: 混搭恐龙13pcs/GQ1/箱 | I85: 2249 | J85: 0 | K85: 13 | L85: =I85/K85 -> 173 | M85: 45819 | N85: 45817 | P85: pass | Q85: 6/13 截仓 | R85: 45748 | S85: 无 | T85: 无 | V85: 日期码格式：ZURU INC(BVI) 标准格式 日期： Packaging Info: 1. MA 1L 包装 2. 客人指定箱唛排版 Remark: 出货前 Zuru QC 验货 | W85: Cherie Li | X85: 0.7931 | Y85: =X85*I85 -> 1783.6819 | Z85: ZB00469-6.13 | AA85: 2249 | AB85: =AA85-I85 -> 0 | AC85: 无 | AD85: 系统出单 | AE85: 77685GQ1-S002 | AF85: 已入 | AG85: =I85 -> 2249 | AH85: =I85 -> 2249 | AK85: =I85 -> 2249 | AN85: =I85 -> 2249 | AT85: =I85/13 -> 173 | BJ85: =$I85*BJ$2 -> 275.26823 | BK85: =$I85*BK$2 -> 275.26823 | BL85: =$I85*BL$2 -> 275.26823 | BM85: =$I85*BM$2 -> 275.26823 | BN85: =$I85*BN$2 -> 275.26823 | BO85: =$I85*BO$2 -> 275.26823 | BP85: =$I85*BP$2 -> 275.26823 | BQ85: =$I85*BQ$2 -> 275.26823 | BR85: =$I85*BR$2 -> 46.854167 | BT85: =BT84-BJ85 -> 106060.89 | BU85: =BU84-BK85 -> 106060.89 | BV85: =BV84-BL85 -> 106060.89 | BW85: =BW84-BM85 -> 106060.89 | BX85: =BX84-BN85 -> 106060.89 | BY85: =BY84-BO85 -> 106060.89 | BZ85: =BZ84-BP85 -> 106060.89 | CA85: =CA84-BQ85 -> 106060.89 | CB85: =CB84-BR85 -> 18004.854
A86: 45744 | B86: MEIJER DISTRIBUTION, INC. | C86: 美国 | D86: 4500161694 | E86: 216888483 | F86: 4500161694-10 | G86: 77685GQ1-S002 | H86: 混搭恐龙13pcs/GQ1/箱 | I86: 1209 | J86: 0 | K86: 13 | L86: =I86/K86 -> 93 | M86: 45819 | N86: 45815 | P86: pass | Q86: 6/13 截仓 | R86: 45748 | S86: 无 | T86: 无 | V86: 日期码格式：ZURU INC(BVI) 标准格式 日期： Packaging Info: 1. MA 1L 包装 2. 客人指定箱唛排版 Remark: 出货前 Zuru QC 验货 | W86: Cherie Li | X86: 0.83 | Y86: =X86*I86 -> 1003.47 | Z86: ZB00468-6.13 | AA86: 1209 | AB86: =AA86-I86 -> 0 | AC86: 无 | AD86: 系统出单 | AE86: 77685GQ1-S002 | AF86: 已入 | AG86: =I86 -> 1209 | AH86: =I86 -> 1209 | AK86: =I86 -> 1209 | AN86: =I86 -> 1209 | AT86: =I86/13 -> 93 | BJ86: =$I86*BJ$2 -> 147.97656 | BK86: =$I86*BK$2 -> 147.97656 | BL86: =$I86*BL$2 -> 147.97656 | BM86: =$I86*BM$2 -> 147.97656 | BN86: =$I86*BN$2 -> 147.97656 | BO86: =$I86*BO$2 -> 147.97656 | BP86: =$I86*BP$2 -> 147.97656 | BQ86: =$I86*BQ$2 -> 147.97656 | BR86: =$I86*BR$2 -> 25.1875 | BT86: =BT85-BJ86 -> 105912.92 | BU86: =BU85-BK86 -> 105912.92 | BV86: =BV85-BL86 -> 105912.92 | BW86: =BW85-BM86 -> 105912.92 | BX86: =BX85-BN86 -> 105912.92 | BY86: =BY85-BO86 -> 105912.92 | BZ86: =BZ85-BP86 -> 105912.92 | CA86: =CA85-BQ86 -> 105912.92 | CB86: =CB85-BR86 -> 17979.667
A87: 45757 | B87: SUBURBIA S DE R. L. DE C. V. | C87: 墨西哥 | D87: 4500162850 | E87: 6000056637 | F87: 4500162850-60 | G87: 77685GQ2-S001 | H87: 混搭恐龙27pcs/GQ2*2/箱 | I87: 486 | J87: 0 | K87: 54 | L87: =I87/K87 -> 9 | M87: 45821 | N87: 45819 | O87: 有监柜要求，需要每款多准备一套完整物料 | P87: 自检 | Q87: 6/13 截SI | R87: 外箱只需四面印Zuru logo | S87: 有 | T87: 5/9进口商贴纸+价标贴纸+说明书贴纸+5/26 HU贴纸和ASN贴纸客供 | V87: 日期码格式：ZURU INC(BVI) 标准格式 日期：按实际生产日期 Packaging Info: 77685GQ2：MA 3L EAN 包装+MA 多语PDQ+MA多语说明书+进口商贴纸+价标贴纸+说明书贴纸 1. 外箱只需四面印Zuru logo，再加2张贴纸，1张Hu贴纸（条码贴），1张ASN贴纸（尺寸6.5cm*6.3cm,潘通色号2597C），都贴于侧唛，只需贴1面(HU贴纸和ASN贴 纸客供） 2. 一个外箱对应一个HU’S(条形码),不可以混条码包装 3.含有说明书需要增加说明书贴纸 4.价格贴纸覆盖原有包装的条形码 Remark: 此单有监柜要求，需要每款多准备一套完整物料，用于监柜，不可以随大货走 | W87: Ever Li | X87: 0.7967 | Y87: =X87*I87 -> 387.1962 | AA87: 486 | AB87: =AA87-I87 -> 0 | AD87: 系统出单 | AE87: 77685GQ2-S001-3L | AF87: 已入 | AG87: =I87 -> 486 | AH87: =I87 -> 486 | AL87: =I87 -> 486 | AO87: =I87 -> 486 | AR87: =I87/27 -> 18 | BJ87: =$I87*BJ$2 -> 59.484375 | BK87: =$I87*BK$2 -> 59.484375 | BL87: =$I87*BL$2 -> 59.484375 | BM87: =$I87*BM$2 -> 59.484375 | BN87: =$I87*BN$2 -> 59.484375 | BO87: =$I87*BO$2 -> 59.484375 | BP87: =$I87*BP$2 -> 59.484375 | BQ87: =$I87*BQ$2 -> 59.484375 | BR87: =$I87*BR$2 -> 10.125 | BT87: =BT86-BJ87 -> 105853.43 | BU87: =BU86-BK87 -> 105853.43 | BV87: =BV86-BL87 -> 105853.43 | BW87: =BW86-BM87 -> 105853.43 | BX87: =BX86-BN87 -> 105853.43 | BY87: =BY86-BO87 -> 105853.43 | BZ87: =BZ86-BP87 -> 105853.43 | CA87: =CA86-BQ87 -> 105853.43 | CB87: =CB86-BR87 -> 17969.542
A88: 45758 | B88: THE KROGER CO. | C88: 美国 | D88: 4500163428 | E88: PO#500-23710 | F88: 4500163428-30 | G88: 77685GQ1-S002 | H88: 混搭恐龙13pcs/GQ1/箱 | I88: 2600 | J88: 0 | K88: 13 | L88: =I88/K88 -> 200 | M88: 45824 | N88: 45822 | P88: pass | Q88: 7/4 截SI | R88: 45758 | S88: 无 | T88: 无 | V88: 日期码格式：ZURU INC(BVI) 标准格式 日期：按实际生产日期 Packaging Info: 1、包装方式: MA UPC 优先1L最新版，出口美国 Remark: 2、无测试无验货要求 3、纸箱4面印ZURU LOGO + 箱唛 4、日期码请按ZURU标准版执行即可 5、ZURU OQC验货 | W88: Vicky Wu | X88: 0.7931 | Y88: =X88*I88 -> 2062.06 | Z88: ZXB00622-7.1 | AA88: =2470+130 -> 2600 | AB88: =AA88-I88 -> 0 | AC88: 无 | AD88: 系统出单 | AE88: 77685GQ1-S002 | AF88: 已入 | AG88: =I88 -> 2600 | AH88: =I88 -> 2600 | AK88: =I88 -> 2600 | AO88: =I88 -> 2600 | AT88: =I88/13 -> 200 | BJ88: =$I88*BJ$2 -> 318.22917 | BK88: =$I88*BK$2 -> 318.22917 | BL88: =$I88*BL$2 -> 318.22917 | BM88: =$I88*BM$2 -> 318.22917 | BN88: =$I88*BN$2 -> 318.22917 | BO88: =$I88*BO$2 -> 318.22917 | BP88: =$I88*BP$2 -> 318.22917 | BQ88: =$I88*BQ$2 -> 318.22917 | BR88: =$I88*BR$2 -> 54.166667 | BT88: =BT87-BJ88 -> 105535.2 | BU88: =BU87-BK88 -> 105535.2 | BV88: =BV87-BL88 -> 105535.2 | BW88: =BW87-BM88 -> 105535.2 | BX88: =BX87-BN88 -> 105535.2 | BY88: =BY87-BO88 -> 105535.2 | BZ88: =BZ87-BP88 -> 105535.2 | CA88: =CA87-BQ88 -> 105535.2 | CB88: =CB87-BR88 -> 17915.375
A89: 45758 | B89: THE KROGER CO. | C89: 美国 | D89: 4500163428 | E89: PO#600-59500 | F89: 4500163428-60 | G89: 77685GQ1-S002 | H89: 混搭恐龙13pcs/GQ1/箱 | I89: 4680 | J89: 0 | K89: 13 | L89: =I89/K89 -> 360 | M89: 45824 | N89: 45822 | P89: pass | Q89: 7/4 截SI | R89: 45758 | S89: 无 | T89: 无 | V89: 日期码格式：ZURU INC(BVI) 标准格式 日期：按实际生产日期 Packaging Info: 1、包装方式: MA UPC 优先1L最新版，出口美国 Remark: 2、无测试无验货要求 3、纸箱4面印ZURU LOGO + 箱唛 4、日期码请按ZURU标准版执行即可 5、ZURU OQC验货 | W89: Vicky Wu | X89: 0.7931 | Y89: =X89*I89 -> 3711.708 | Z89: ZB00627-7.2 | AA89: =4667+13 -> 4680 | AB89: =AA89-I89 -> 0 | AC89: 无 | AD89: 系统出单 | AE89: 77685GQ1-S002 | AF89: 已入 | AG89: =I89 -> 4680 | AH89: =I89 -> 4680 | AK89: =I89 -> 4680 | AO89: =I89 -> 4680 | AT89: =I89/13 -> 360 | BJ89: =$I89*BJ$2 -> 572.8125 | BK89: =$I89*BK$2 -> 572.8125 | BL89: =$I89*BL$2 -> 572.8125 | BM89: =$I89*BM$2 -> 572.8125 | BN89: =$I89*BN$2 -> 572.8125 | BO89: =$I89*BO$2 -> 572.8125 | BP89: =$I89*BP$2 -> 572.8125 | BQ89: =$I89*BQ$2 -> 572.8125 | BR89: =$I89*BR$2 -> 97.5 | BT89: =BT88-BJ89 -> 104962.39 | BU89: =BU88-BK89 -> 104962.39 | BV89: =BV88-BL89 -> 104962.39 | BW89: =BW88-BM89 -> 104962.39 | BX89: =BX88-BN89 -> 104962.39 | BY89: =BY88-BO89 -> 104962.39 | BZ89: =BZ88-BP89 -> 104962.39 | CA89: =CA88-BQ89 -> 104962.39 | CB89: =CB88-BR89 -> 17817.875
A90: 45777 | B90: BRICKLAND LLC | C90: 蒙古 | D90: 4500165462 | E90: Zuru.2025Q2(June.addon) | F90: 4500165462-20 | G90: 77685GQ1-S001 | H90: 混搭恐龙13pcs/GQ1*4/箱 | I90: 1040 | J90: 0 | K90: 52 | L90: =I90/K90 -> 20 | M90: 45812 | N90: 45815 | P90: 自检 | Q90: 客上柜 | R90: 45786 | S90: 无 | T90: 5/13进口商贴纸 | V90: 日期码格式：ZURU INC(BVI) 标准格式 日期：按实际生产日期 Packaging Info: MA UPC packages(优先1L)+1张进口商贴纸;贴纸aw及位置图待提供 Remark: 77685GQ1-Rare ratio:1/48 | W90: Emma Wu | X90: 0.7855 | Y90: =X90*I90 -> 816.92 | AA90: 1040 | AB90: =AA90-I90 -> 0 | AC90: OK | AD90: 系统出单 | AE90: 77685GQ1-S001 | AF90: 已入 | AG90: =I90 -> 1040 | AH90: =I90 -> 1040 | AK90: =I90 -> 1040 | AO90: =I90 -> 1040 | AT90: =I90/13 -> 80 | BJ90: =$I90*BJ$2 -> 127.29167 | BK90: =$I90*BK$2 -> 127.29167 | BL90: =$I90*BL$2 -> 127.29167 | BM90: =$I90*BM$2 -> 127.29167 | BN90: =$I90*BN$2 -> 127.29167 | BO90: =$I90*BO$2 -> 127.29167 | BP90: =$I90*BP$2 -> 127.29167 | BQ90: =$I90*BQ$2 -> 127.29167 | BR90: =$I90*BR$2 -> 21.666667 | BT90: =BT89-BJ90 -> 104835.1 | BU90: =BU89-BK90 -> 104835.1 | BV90: =BV89-BL90 -> 104835.1 | BW90: =BW89-BM90 -> 104835.1 | BX90: =BX89-BN90 -> 104835.1 | BY90: =BY89-BO90 -> 104835.1 | BZ90: =BZ89-BP90 -> 104835.1 | CA90: =CA89-BQ90 -> 104835.1 | CB90: =CB89-BR90 -> 17796.208
A91: 45792 | B91: WALMART INC. | C91: 美国 | D91: 4500166538 | E91: 0907594855 | F91: 4500166538-10 | G91: 77685SLB-S001 | H91: 混搭恐龙卡板装12pcs/GQ4/CTN**96/Slip Sheet | I91: 1152 | J91: 0 | K91: 1152 | L91: =I91/K91 -> 1 | M91: 45817 | N91: 45815 | O91: 6/17 BV | P91: pass | Q91: 6/23 截SI | R91: 翻单 | S91: 有 | T91: 5/27 RFID | V91: 日期码格式：ZURU DGYYYYMMDD CHINA(日期避开周末和法定节假日即可） 日期：按实际生产日期 Packaging Info: 77685SLB-S001： 1.包装要求： MA 1L A版收缩膜+MA A版纸袋+MA 5L B版收藏指南+MA A版slime bag+客版1L PDQ 每pcs产品上要贴1张RFID贴纸，贴纸由ZURU提供，贴纸位置请严格按照我们签回的签板； Remark: 77685SLB-S001： 1.包装要求： MA 1L A版收缩膜+MA A版纸袋+MA 5L B版收藏指南+MA A版slime bag+客版1L PDQ 每pcs产品上要贴1张RFID贴纸，贴纸由ZURU提供，贴纸位置请严格按照我们签回的签板； 2. 外箱印刷带条码的RFID箱唛：RFID紫色色带+WM Dept.图标+RFID图标+ITF-14条码，四面右下角印刷ZURU logo, ITFF条码只印刷在正唛一面，在加印的时候确保 条形码能扫描出来，外箱侧面任一角落加印："MADE IN CHINA" 字样； 3. 每个slip sheet上面贴一张艾利贴纸（不干胶贴纸）和一张普通贴纸（A4纸），slip sheet打印的普通贴纸的尺寸不能比艾利贴纸小，普通贴纸内容见附件； 4. 在产品上和包装上要有日期码、以及要有MADE IN CHINA和ZURU字样； 5. 产品如有扎带口要剪平，不能刮手。 6. 此单需要验货，请多备料 7. 此单以slip sheet出货，77685：1152pcs/96CTN/Slip Sheet | W91: Maggie Xie | X91: 555.88 | Y91: =X91*L91 -> 555.88 | Z91: ZB00535-6.21 | AA91: =1092+60 -> 1152 | AB91: =AA91-I91 -> 0 | AD91: 系统出单 | AE91: 77685SLB-S001 | AF91: 已入 | AG91: =I91 -> 1152 | AH91: =I91 -> 1152 | AK91: =I91 -> 1152 | AO91: =I91 -> 1152 | AV91: =I91/12 -> 96 | BJ91: =$I91*BJ$2 -> 141 | BK91: =$I91*BK$2 -> 141 | BL91: =$I91*BL$2 -> 141 | BM91: =$I91*BM$2 -> 141 | BN91: =$I91*BN$2 -> 141 | BO91: =$I91*BO$2 -> 141 | BP91: =$I91*BP$2 -> 141 | BQ91: =$I91*BQ$2 -> 141 | BR91: =$I91*BR$2 -> 24 | BT91: =BT90-BJ91 -> 104694.1 | BU91: =BU90-BK91 -> 104694.1 | BV91: =BV90-BL91 -> 104694.1 | BW91: =BW90-BM91 -> 104694.1 | BX91: =BX90-BN91 -> 104694.1 | BY91: =BY90-BO91 -> 104694.1 | BZ91: =BZ90-BP91 -> 104694.1 | CA91: =CA90-BQ91 -> 104694.1 | CB91: =CB90-BR91 -> 17772.208
A92: 45775 | B92: WALMART INC. | C92: 美国 | D92: 4500162798 | E92: 0904512441HOU STON | F92: 4500162798-10 | G92: 77685SLB-S001 | H92: 混搭恐龙卡板装12pcs/GQ4/CTN**96/Slip Sheet | I92: 1152 | J92: 0 | K92: 1152 | L92: =I92/K92 -> 1 | M92: 45819 | N92: 45817 | O92: 6/13 BV | P92: pass | Q92: 6/23 截SI | R92: 翻单 | S92: 有 | T92: 5/12 RFID | V92: 日期码格式：ZURU DGYYYYMMDD CHINA(日期避开周末和法定节假日即可） 日期：按实际生产日期 Packaging Info: 77685SLB-S001： 1.包装要求： MA 1L A版收缩膜+MA A版纸袋+MA 5L A版收藏指南+MA A版slime bag+客版1L PDQ,翻单：4500159701 每pcs产品上要贴1张RFID贴纸，贴纸由ZURU提供，贴纸位置请严格按照我们签回的签板 Remark: 77685SLB-S001： 1.包装要求： MA 1L A版收缩膜+MA A版纸袋+MA 5L A版收藏指南+MA A版slime bag+客版1L PDQ,翻单：4500159701 每pcs产品上要贴1张RFID贴纸，贴纸由ZURU提供，贴纸位置请严格按照我们签回的签板； 2. 外箱印刷带条码的RFID箱唛：RFID紫色色带+WM Dept.图标+RFID图标+ITF-14条码，四面右下角印刷ZURU logo, ITFF条码只印刷在正唛一面，在加印的时候确保 条形码能扫描出来，外箱侧面任一角落加印："MADE IN CHINA" 字样； 3. 每个slip sheet上面贴一张艾利贴纸（不干胶贴纸）和一张普通贴纸（A4纸），slip sheet打印的普通贴纸的尺寸不能比艾利贴纸小，普通贴纸内容见附件； 4. 在产品上和包装上要有日期码、以及要有MADE IN CHINA和ZURU字样； 5. 产品如有扎带口要剪平，不能刮手。 6.此单以slip sheet出货，77685：1152pcs/96CTN/Slip Sheet | W92: Maggie Xie | X92: 555.88 | Y92: =X92*L92 -> 555.88 | Z92: ZB00544-6.23 | AA92: 1152 | AB92: =AA92-I92 -> 0 | AD92: 系统出单 | AE92: 77685SLB-S001 | AF92: 已入 | AG92: =I92 -> 1152 | AH92: =I92 -> 1152 | AK92: =I92 -> 1152 | AO92: =I92 -> 1152 | AV92: =I92/12 -> 96 | BJ92: =$I92*BJ$2 -> 141 | BK92: =$I92*BK$2 -> 141 | BL92: =$I92*BL$2 -> 141 | BM92: =$I92*BM$2 -> 141 | BN92: =$I92*BN$2 -> 141 | BO92: =$I92*BO$2 -> 141 | BP92: =$I92*BP$2 -> 141 | BQ92: =$I92*BQ$2 -> 141 | BR92: =$I92*BR$2 -> 24 | BT92: =BT91-BJ92 -> 104553.1 | BU92: =BU91-BK92 -> 104553.1 | BV92: =BV91-BL92 -> 104553.1 | BW92: =BW91-BM92 -> 104553.1 | BX92: =BX91-BN92 -> 104553.1 | BY92: =BY91-BO92 -> 104553.1 | BZ92: =BZ91-BP92 -> 104553.1 | CA92: =CA91-BQ92 -> 104553.1 | CB92: =CB91-BR92 -> 17748.208
A93: 45785 | B93: COLIMPO LTD | C93: 比利时 | D93: 4500165739 | E93: F7010986 | F93: 4500165739-10 | G93: 77685GQ1-S001 | H93: 混搭恐龙13pcs/GQ1*4/箱 | I93: 2444 | J93: 0 | K93: 52 | L93: =I93/K93 -> 47 | M93: 45821 | N93: 45817 | P93: 自检 | Q93: 6/13 出货 | R93: 45786 | S93: 无 | T93: 5/9NL 警语贴纸 | V93: 日期码格式：ZURU INC(BVI) 标准格式 日期：按实际生产日期 Packaging Info: 77685GQ1:MA 3L A版 EAN收缩膜+DE、NL警语贴纸+法国环保标（做在一起），MA 1L B版内袋，MA 5L+23L B版收藏指南，MA 5L A版slime 袋子+NL 警语贴纸，MA 1L B版说明书，MA A版 PDQ; L 珠子袋子+NL 警语贴纸; Remark: 1.此单走LC,货期不可延迟，否则有罚款 2.产品上必须打上日期码，ZURU格式即可，无特殊要求； 3.如MA 产品中有大于10*10cm的塑料袋，必须有德语/法语/荷兰语/英语的警告语，印刷内容请与跟单确认 4.所有塑料袋的厚度不小于0.038mm 5.订单出比利时，产品及包装需要印CE图标，包装需要有ZURU France地址信息，QC同事请核查，如有问题与跟单确认； 6.外箱上有条码要求，排版时请留意，并请确保条码清晰可扫描； 7.出欧洲，微塑料需合规（如item本身不含微塑料，则忽略此要求） 8. STD配比 9.确保产品和包装中SVHC的含量低于0.1% 10. 客人款号 77685GQ1：135636 | W93: Max kong | X93: 0.8186 | Y93: =X93*I93 -> 2000.6584 | AA93: 2444 | AB93: =AA93-I93 -> 0 | AC93: OK | AD93: 系统出单 | AE93: 77685GQ1-S001-3L | AF93: 已入 | AG93: =I93 -> 2444 | AH93: =I93 -> 2444 | AL93: =I93 -> 2444 | AO93: =I93 -> 2444 | AU93: =I93/13 -> 188 | BJ93: =$I93*BJ$2 -> 299.13542 | BK93: =$I93*BK$2 -> 299.13542 | BL93: =$I93*BL$2 -> 299.13542 | BM93: =$I93*BM$2 -> 299.13542 | BN93: =$I93*BN$2 -> 299.13542 | BO93: =$I93*BO$2 -> 299.13542 | BP93: =$I93*BP$2 -> 299.13542 | BQ93: =$I93*BQ$2 -> 299.13542 | BR93: =$I93*BR$2 -> 50.916667 | BT93: =BT92-BJ93 -> 104253.96 | BU93: =BU92-BK93 -> 104253.96 | BV93: =BV92-BL93 -> 104253.96 | BW93: =BW92-BM93 -> 104253.96 | BX93: =BX92-BN93 -> 104253.96 | BY93: =BY92-BO93 -> 104253.96 | BZ93: =BZ92-BP93 -> 104253.96 | CA93: =CA92-BQ93 -> 104253.96 | CB93: =CB92-BR93 -> 17697.292
A94: 45765 | B94: Amazon EU SARL, Ndl Deutschland | C94: 英国 | D94: 4500164250 | E94: Amazon UK:3P5HOGHS | F94: 4500164250-80 | G94: 77723-S001 | H94: 混搭恐龙2PK圆筒装 | I94: 504 | J94: 0 | K94: 12 | L94: =I94/K94 -> 42 | M94: 45814 | N94: 45815 | P94: 自检 | Q94: 6/17 截SI | R94: 空白外箱（加印带Zuru字样的最新logo，除了邮包盒直接做外箱的产品） | S94: 有 | T94: 5/14SSCC贴纸+空白贴纸 | V94: 日期码格式：ZURU INC(BVI) 标准格式 日期：按实际生产日期 Packaging Info: Amazon UK(15714K/7150B/77673/77723/92119AH/9279B/9561)/FR(9543D)/DE(71126/77555/77731/92104G/9543E) 4. 77723：2pk 77685 into pvc tube, 12tubes/ctn; MA 3L(3L warning EAN)A收缩膜+MA 1L(23L warning)A说明书+MA 1L A内袋+MA 5L(23L warning)A收藏指南+M A 5L A Slime胶袋+客版PVC筒彩卡(含英法德意西5L警告语+UPC#+邮箱地址+FR/ES/IT环保标，参考翻单PO#4500158469)； 14. 最迟验货不得晚于2025/6/6 & 2025/6/9; Remark: 1.空白外箱（加印带Zuru字样的最新logo，除了邮包盒直接做外箱的产品） + SSCC LABEL一张, 无箱唛，MADE IN CHINA 外箱只印一正一侧。箱唛资料按照给定的 标准去做即可，无需发回我方再行审批(新标准将另行通知)。 (SSCC LABEL竖贴在外箱正面的正中间，贴一面即可,贴纸离外箱边距必须至少3.2CM。如竖贴无法满足要求，则横贴。如横贴也无法满足要求，则竖贴，遮到ZURU lo go无影响), SSCC贴纸由工厂直接跟勤得采购或者工厂自行采购，每一张SSCC Label都是唯一且有不同流水及条码，且需要检查条码是否能正常扫描，另外，此贴纸 印刷不可出现模糊，溢出及粘胶不牢易脱落等现象，如工厂不按此要求导致贴纸有任何问题产生的罚款将由工厂承担一切责任 。 2.出往UK的产品+包装务必打上UKCA logo ，否则客人会退货且当地会有罚款。 3.订单必须经过ZURU QC验货并且通过后方可出货。 4.法国订单要求包装不使用矿物油，请按要求提供以下其中一份文件再出货 ，产品出到法国被相关部门抽检出现包装不符合此要求的，供应商需要为此承担责任， 故此请严格把关。 -油墨物质""由1 ~ 7个芳香环组成的MOAH""的包装检测报告，要求限值≤1.0%； -包装材料清单，包括包装油墨或物质的信息； -油墨制造商的证书； 5.每一批次出货只能有一个生产日期，不可多个生产日期混在同一批次出货；且邮包盒上必须统一加上日期码；外箱对于日期码没有硬性规定； 6.涉及到相关款式会有闪粉的或者微塑料的，请统一默认出无闪粉或者不含微塑料版本； 7.邮包盒及外箱封箱必须是工字型封箱方式； 8.5 Surprise or Mini Brands涉及包装是2个及2个以上的球入PVC桶包装时，单个球上若有UPC#或者EAN#，请用白色贴纸覆盖住； | W94: Crystal Chen | X94: 1.8626 | Y94: =X94*I94 -> 938.7504 | AA94: 504 | AB94: =AA94-I94 -> 0 | AD94: 系统出单 | AE94: 77723-S001 | AF94: 已入 | AG94: =I94*2 -> 1008 | AH94: =I94*2 -> 1008 | AL94: =I94*2 -> 1008 | AO94: =I94*2 -> 1008 | BF94: =I94 -> 504 | BG94: =I94 -> 504 | BJ94: =$I94*BJ$2*2 -> 123.375 | BK94: =$I94*BK$2*2 -> 123.375 | BL94: =$I94*BL$2*2 -> 123.375 | BM94: =$I94*BM$2*2 -> 123.375 | BN94: =$I94*BN$2*2 -> 123.375 | BO94: =$I94*BO$2*2 -> 123.375 | BP94: =$I94*BP$2*2 -> 123.375 | BQ94: =$I94*BQ$2*2 -> 123.375 | BR94: =$I94*BR$2*2 -> 21 | BT94: =BT93-BJ94 -> 104130.59 | BU94: =BU93-BK94 -> 104130.59 | BV94: =BV93-BL94 -> 104130.59 | BW94: =BW93-BM94 -> 104130.59 | BX94: =BX93-BN94 -> 104130.59 | BY94: =BY93-BO94 -> 104130.59 | BZ94: =BZ93-BP94 -> 104130.59 | CA94: =CA93-BQ94 -> 104130.59 | CB94: =CB93-BR94 -> 17676.292 | CD94: 4/23 已放MA 圆筒/彩纸/贴纸 | CE94: 10000 | CF94: 5000 | CH94: =CE94-I94 -> 9496 | CI94: =CF94-I94 -> 4496
A95: 45786 | B95: TIENDAS CHEDRAUI, S.A. DE C.V. | C95: 墨西哥 | D95: 4500165810 | F95: 4500165810-10 | G95: 77685GQ2-S001 | H95: 混搭恐龙27pcs/GQ2*2/箱 | I95: 7236 | J95: 0 | K95: 54 | L95: =I95/K95 -> 134 | M95: 45820 | N95: 45817 | P95: pass | Q95: 7/2 截SI | R95: 45790 | S95: 无 | T95: 5/19 UPC贴纸+进口商贴纸 | V95: 日期码格式：ZURU INC(BVI) 标准格式 日期：按实际生产日期 Packaging Info: 1. 77685GQ2：MA 3L EAN包装+UPC条码贴纸+MA 3L PDQ包装+MA 说明书+进口商贴纸+箱唛 Remark: | W95: Ever Li | X95: 0.7687 | Y95: =X95*I95 -> 5562.3132 | Z95: 95529-7.2 | AA95: 7236 | AB95: =AA95-I95 -> 0 | AC95: OK | AD95: 系统出单 | AE95: 77685GQ2-S001-3L | AF95: 已入 | AG95: =I95 -> 7236 | AH95: =I95 -> 7236 | AL95: =I95 -> 7236 | AO95: =I95 -> 7236 | AR95: =I95/27 -> 268 | BJ95: =$I95*BJ$2 -> 885.65625 | BK95: =$I95*BK$2 -> 885.65625 | BL95: =$I95*BL$2 -> 885.65625 | BM95: =$I95*BM$2 -> 885.65625 | BN95: =$I95*BN$2 -> 885.65625 | BO95: =$I95*BO$2 -> 885.65625 | BP95: =$I95*BP$2 -> 885.65625 | BQ95: =$I95*BQ$2 -> 885.65625 | BR95: =$I95*BR$2 -> 150.75 | BT95: =BT94-BJ95 -> 103244.93 | BU95: =BU94-BK95 -> 103244.93 | BV95: =BV94-BL95 -> 103244.93 | BW95: =BW94-BM95 -> 103244.93 | BX95: =BX94-BN95 -> 103244.93 | BY95: =BY94-BO95 -> 103244.93 | BZ95: =BZ94-BP95 -> 103244.93 | CA95: =CA94-BQ95 -> 103244.93 | CB95: =CB94-BR95 -> 17525.542
A96: 45758 | B96: SEARS MEXICO | C96: 墨西哥 | D96: 4500163238 | F96: 4500163238-20 | G96: 77685GQ2-S001 | H96: 混搭恐龙27pcs/GQ2*2/箱 | I96: 540 | J96: 0 | K96: 54 | L96: =I96/K96 -> 10 | M96: 45821 | N96: 45817 | P96: 自检 | Q96: 6/19 截SI | R96: 45786 | S96: 无 | T96: 5/15UPC条码贴纸+进口商贴纸 | V96: 日期码格式：ZURU INC(BVI) 标准格式 日期：按实际生产日期 Packaging Info: 2. 77685GQ2：MA 3L EAN包装+UPC条码贴纸+MA 3L PDQ包装+MA 说明书+进口商贴纸+箱唛 Remark: | W96: Ever Li | X96: 0.7967 | Y96: =X96*I96 -> 430.218 | AA96: 540 | AB96: =AA96-I96 -> 0 | AC96: OK | AD96: 系统出单 | AE96: 77685GQ2-S001-3L | AF96: 已入 | AG96: =I96 -> 540 | AH96: =I96 -> 540 | AL96: =I96 -> 540 | AO96: =I96 -> 540 | AR96: =I96/27 -> 20 | BJ96: =$I96*BJ$2 -> 66.09375 | BK96: =$I96*BK$2 -> 66.09375 | BL96: =$I96*BL$2 -> 66.09375 | BM96: =$I96*BM$2 -> 66.09375 | BN96: =$I96*BN$2 -> 66.09375 | BO96: =$I96*BO$2 -> 66.09375 | BP96: =$I96*BP$2 -> 66.09375 | BQ96: =$I96*BQ$2 -> 66.09375 | BR96: =$I96*BR$2 -> 11.25 | BT96: =BT95-BJ96 -> 103178.84 | BU96: =BU95-BK96 -> 103178.84 | BV96: =BV95-BL96 -> 103178.84 | BW96: =BW95-BM96 -> 103178.84 | BX96: =BX95-BN96 -> 103178.84 | BY96: =BY95-BO96 -> 103178.84 | BZ96: =BZ95-BP96 -> 103178.84 | CA96: =CA95-BQ96 -> 103178.84 | CB96: =CB95-BR96 -> 17514.292
A97: 45775 | B97: WALMART INC. | C97: 美国 | D97: 4500162823 | E97: 0907594714RID GEVILLE SC | F97: 4500162823-10 | G97: 77685SLB-S001 | H97: 混搭恐龙卡板装12pcs/GQ4/CTN**96/Slip Sheet | I97: 1152 | J97: 0 | K97: 1152 | L97: =I97/K97 -> 1 | M97: 45825 | N97: 45821 | O97: 6/19 BV | P97: pass | Q97: 7/9 截SI | R97: 翻单 | S97: 有 | T97: 5/12 RFID | V97: 日期码格式：ZURU DGYYYYMMDD CHINA(日期避开周末和法定节假日即可） 日期：按实际生产日期 Packaging Info: 77685SLB-S001： 1.包装要求： MA 1L A版收缩膜+MA A版纸袋+MA 5L A版收藏指南+MA A版slime bag+客版1L PDQ,翻单：4500159701 每pcs产品上要贴1张RFID贴纸，贴纸由ZURU提供，贴纸位置请严格按照我们签回的签板 Remark: 77685SLB-S001： 1.包装要求： MA 1L A版收缩膜+MA A版纸袋+MA 5L A版收藏指南+MA A版slime bag+客版1L PDQ,翻单：4500159701 每pcs产品上要贴1张RFID贴纸，贴纸由ZURU提供，贴纸位置请严格按照我们签回的签板； 2. 外箱印刷带条码的RFID箱唛：RFID紫色色带+WM Dept.图标+RFID图标+ITF-14条码，四面右下角印刷ZURU logo, ITFF条码只印刷在正唛一面，在加印的时候确保 条形码能扫描出来，外箱侧面任一角落加印："MADE IN CHINA" 字样； 3. 每个slip sheet上面贴一张艾利贴纸（不干胶贴纸）和一张普通贴纸（A4纸），slip sheet打印的普通贴纸的尺寸不能比艾利贴纸小，普通贴纸内容见附件； 4. 在产品上和包装上要有日期码、以及要有MADE IN CHINA和ZURU字样； 5. 产品如有扎带口要剪平，不能刮手。 6.此单以slip sheet出货，77685：1152pcs/96CTN/Slip Sheet | W97: Maggie Xie | X97: 555.88 | Y97: =X97*L97 -> 555.88 | Z97: ZB00684-7.8 | AA97: =1152 -> 1152 | AB97: =AA97-I97 -> 0 | AD97: 系统出单 | AE97: 77685SLB-S001 | AF97: 已入 | AG97: =I97 -> 1152 | AH97: =I97 -> 1152 | AK97: =I97 -> 1152 | AO97: =I97 -> 1152 | AV97: =I97/12 -> 96 | BJ97: =$I97*BJ$2 -> 141 | BK97: =$I97*BK$2 -> 141 | BL97: =$I97*BL$2 -> 141 | BM97: =$I97*BM$2 -> 141 | BN97: =$I97*BN$2 -> 141 | BO97: =$I97*BO$2 -> 141 | BP97: =$I97*BP$2 -> 141 | BQ97: =$I97*BQ$2 -> 141 | BR97: =$I97*BR$2 -> 24 | BT97: =BT96-BJ97 -> 103037.84 | BU97: =BU96-BK97 -> 103037.84 | BV97: =BV96-BL97 -> 103037.84 | BW97: =BW96-BM97 -> 103037.84 | BX97: =BX96-BN97 -> 103037.84 | BY97: =BY96-BO97 -> 103037.84 | BZ97: =BZ96-BP97 -> 103037.84 | CA97: =CA96-BQ97 -> 103037.84 | CB97: =CB96-BR97 -> 17490.292
A98: 45775 | B98: WALMART INC. | C98: 美国 | D98: 4500162823 | E98: 0907594769SUF FOLK | F98: 4500162823-20 | G98: 77685SLB-S001 | H98: 混搭恐龙卡板装12pcs/GQ4/CTN**96/Slip Sheet | I98: 1152 | J98: 0 | K98: 1152 | L98: =I98/K98 -> 1 | M98: 45825 | N98: 45821 | O98: 6/23 BV | P98: pass | Q98: 6/25 截SI | R98: 翻单 | S98: 有 | T98: 5/12 RFID | V98: 日期码格式：ZURU DGYYYYMMDD CHINA(日期避开周末和法定节假日即可） 日期：按实际生产日期 Packaging Info: 77685SLB-S001： 1.包装要求： MA 1L A版收缩膜+MA A版纸袋+MA 5L A版收藏指南+MA A版slime bag+客版1L PDQ,翻单：4500159701 每pcs产品上要贴1张RFID贴纸，贴纸由ZURU提供，贴纸位置请严格按照我们签回的签板 Remark: 77685SLB-S001： 1.包装要求： MA 1L A版收缩膜+MA A版纸袋+MA 5L A版收藏指南+MA A版slime bag+客版1L PDQ,翻单：4500159701 每pcs产品上要贴1张RFID贴纸，贴纸由ZURU提供，贴纸位置请严格按照我们签回的签板； 2. 外箱印刷带条码的RFID箱唛：RFID紫色色带+WM Dept.图标+RFID图标+ITF-14条码，四面右下角印刷ZURU logo, ITFF条码只印刷在正唛一面，在加印的时候确保 条形码能扫描出来，外箱侧面任一角落加印："MADE IN CHINA" 字样； 3. 每个slip sheet上面贴一张艾利贴纸（不干胶贴纸）和一张普通贴纸（A4纸），slip sheet打印的普通贴纸的尺寸不能比艾利贴纸小，普通贴纸内容见附件； 4. 在产品上和包装上要有日期码、以及要有MADE IN CHINA和ZURU字样； 5. 产品如有扎带口要剪平，不能刮手。 6.此单以slip sheet出货，77685：1152pcs/96CTN/Slip Sheet | W98: Maggie Xie | X98: 555.88 | Y98: =X98*L98 -> 555.88 | Z98: ZB00607-6.30 | AA98: =1116+36 -> 1152 | AB98: =AA98-I98 -> 0 | AD98: 系统出单 | AE98: 77685SLB-S001 | AF98: 已入 | AG98: =I98 -> 1152 | AH98: =I98 -> 1152 | AK98: =I98 -> 1152 | AO98: =I98 -> 1152 | AV98: =I98/12 -> 96 | BJ98: =$I98*BJ$2 -> 141 | BK98: =$I98*BK$2 -> 141 | BL98: =$I98*BL$2 -> 141 | BM98: =$I98*BM$2 -> 141 | BN98: =$I98*BN$2 -> 141 | BO98: =$I98*BO$2 -> 141 | BP98: =$I98*BP$2 -> 141 | BQ98: =$I98*BQ$2 -> 141 | BR98: =$I98*BR$2 -> 24 | BT98: =BT97-BJ98 -> 102896.84 | BU98: =BU97-BK98 -> 102896.84 | BV98: =BV97-BL98 -> 102896.84 | BW98: =BW97-BM98 -> 102896.84 | BX98: =BX97-BN98 -> 102896.84 | BY98: =BY97-BO98 -> 102896.84 | BZ98: =BZ97-BP98 -> 102896.84 | CA98: =CA97-BQ98 -> 102896.84 | CB98: =CB97-BR98 -> 17466.292
A99: 45775 | B99: WALMART INC. | C99: 美国 | D99: 4500162823 | E99: 0907594791STA TESBORO | F99: 4500162823-30 | G99: 77685SLB-S001 | H99: 混搭恐龙卡板装12pcs/GQ4/CTN**96/Slip Sheet | I99: 1152 | J99: 0 | K99: 1152 | L99: =I99/K99 -> 1 | M99: 45825 | N99: 45821 | O99: 6/23 BV | P99: pass | Q99: 7/9 截SI | R99: 翻单 | S99: 有 | T99: 5/12 RFID | V99: 日期码格式：ZURU DGYYYYMMDD CHINA(日期避开周末和法定节假日即可） 日期：按实际生产日期 Packaging Info: 77685SLB-S001： 1.包装要求： MA 1L A版收缩膜+MA A版纸袋+MA 5L A版收藏指南+MA A版slime bag+客版1L PDQ,翻单：4500159701 每pcs产品上要贴1张RFID贴纸，贴纸由ZURU提供，贴纸位置请严格按照我们签回的签板 Remark: 77685SLB-S001： 1.包装要求： MA 1L A版收缩膜+MA A版纸袋+MA 5L A版收藏指南+MA A版slime bag+客版1L PDQ,翻单：4500159701 每pcs产品上要贴1张RFID贴纸，贴纸由ZURU提供，贴纸位置请严格按照我们签回的签板； 2. 外箱印刷带条码的RFID箱唛：RFID紫色色带+WM Dept.图标+RFID图标+ITF-14条码，四面右下角印刷ZURU logo, ITFF条码只印刷在正唛一面，在加印的时候确保 条形码能扫描出来，外箱侧面任一角落加印："MADE IN CHINA" 字样； 3. 每个slip sheet上面贴一张艾利贴纸（不干胶贴纸）和一张普通贴纸（A4纸），slip sheet打印的普通贴纸的尺寸不能比艾利贴纸小，普通贴纸内容见附件； 4. 在产品上和包装上要有日期码、以及要有MADE IN CHINA和ZURU字样； 5. 产品如有扎带口要剪平，不能刮手。 6.此单以slip sheet出货，77685：1152pcs/96CTN/Slip Sheet | W99: Maggie Xie | X99: 555.88 | Y99: =X99*L99 -> 555.88 | Z99: ZB00713-7.10 | AA99: =1140+12 -> 1152 | AB99: =AA99-I99 -> 0 | AD99: 系统出单 | AE99: 77685SLB-S001 | AF99: 已入 | AG99: =I99 -> 1152 | AH99: =I99 -> 1152 | AK99: =I99 -> 1152 | AO99: =I99 -> 1152 | AV99: =I99/12 -> 96 | BJ99: =$I99*BJ$2 -> 141 | BK99: =$I99*BK$2 -> 141 | BL99: =$I99*BL$2 -> 141 | BM99: =$I99*BM$2 -> 141 | BN99: =$I99*BN$2 -> 141 | BO99: =$I99*BO$2 -> 141 | BP99: =$I99*BP$2 -> 141 | BQ99: =$I99*BQ$2 -> 141 | BR99: =$I99*BR$2 -> 24 | BT99: =BT98-BJ99 -> 102755.84 | BU99: =BU98-BK99 -> 102755.84 | BV99: =BV98-BL99 -> 102755.84 | BW99: =BW98-BM99 -> 102755.84 | BX99: =BX98-BN99 -> 102755.84 | BY99: =BY98-BO99 -> 102755.84 | BZ99: =BZ98-BP99 -> 102755.84 | CA99: =CA98-BQ99 -> 102755.84 | CB99: =CB98-BR99 -> 17442.292
A100: 45772 | B100: LLC SALUS | C100: 俄罗斯联邦 | D100: 4500164723 | F100: 4500164723-130 | G100: 77685GQ1-S001 | H100: 混搭恐龙13pcs/GQ1*4/箱 | I100: 624 | J100: 0 | K100: 52 | L100: =I100/K100 -> 12 | M100: 45828 | N100: 45824 | P100: 自检 | Q100: 6/21 客上柜 | R100: 45772 | S100: 无 | T100: 5/7 进口商贴纸 | V100: 日期码格式：ZURU INC(BVI) 标准格式 日期：按实际生产日期 Packaging Info: Fuggler : MA UPC 彩盒 + 进口商贴纸， MA PDQ ； 77685GQ1 ： 1L MA UPC 包装+ 进口商贴纸 ， MA 指南/说明书（如有） Remark: 标准配比 | W100: Ann | X100: 0.8094 | Y100: =X100*I100 -> 505.0656 | AA100: 624 | AB100: =AA100-I100 -> 0 | AC100: OK | AD100: 系统出单 | AE100: 77685GQ1-S001 | AF100: 已入 | AG100: =I100 -> 624 | AH100: =I100 -> 624 | AK100: =I100 -> 624 | AO100: =I100 -> 624 | AT100: =I100/13 -> 48 | BJ100: =$I100*BJ$2 -> 76.375 | BK100: =$I100*BK$2 -> 76.375 | BL100: =$I100*BL$2 -> 76.375 | BM100: =$I100*BM$2 -> 76.375 | BN100: =$I100*BN$2 -> 76.375 | BO100: =$I100*BO$2 -> 76.375 | BP100: =$I100*BP$2 -> 76.375 | BQ100: =$I100*BQ$2 -> 76.375 | BR100: =$I100*BR$2 -> 13 | BT100: =BT99-BJ100 -> 102679.46 | BU100: =BU99-BK100 -> 102679.46 | BV100: =BV99-BL100 -> 102679.46 | BW100: =BW99-BM100 -> 102679.46 | BX100: =BX99-BN100 -> 102679.46 | BY100: =BY99-BO100 -> 102679.46 | BZ100: =BZ99-BP100 -> 102679.46 | CA100: =CA99-BQ100 -> 102679.46 | CB100: =CB99-BR100 -> 17429.292
...

Sheet 77685排期
A1: ZURU 5 surprise Dino （混搭恐龙）生产排期表 #77685 | H1: 3L及共用包材上的logo为英法2L，纸袋底纹为5S通用logo（为应对加拿大魁北克新规，3L及共用包材上的logo增加法语或改为5S logo以减少翻译）。口水胶、纸袋、说明书、收藏指南从1L Logo变更3L Logo，GQ21L/3L各库存2000PCS，后续切换B版本，注意走加拿大魁北克订单不能用A版本.同一个单不能出现两个版本 | AJ1: 无硼 口水胶 | AM1: 收缩膜 | AP1: 收藏指南 | AR1: 外挂中文收藏指南+中文说明书 | AS1: GQ2 | AV1: GQ1 | AX1: GQ4 | AY1: GQ5 | AZ1: GQ7 | BB1: SK展示架 | BE1: SK1展示架 | BH1: 2PK | BL1: 腕龙 | BM1: 双脊龙 | BN1: 镰刀龙 | BO1: 甲龙 | BP1: 戟龙 | BQ1: 棘龙 | BR1: 沧龙 | BS1: 霸王龙 | BT1: 特殊款霸王龙 | BV1: =生产MA!G4 -> 腕龙 | BW1: =生产MA!H4 -> 双脊龙 | BX1: =生产MA!I4 -> 镰刀龙 | BY1: =生产MA!J4 -> 甲龙 | BZ1: =生产MA!K4 -> 戟龙 | CA1: =生产MA!L4 -> 棘龙 | CB1: =生产MA!M4 -> 沧龙 | CC1: =生产MA!N4 -> 霸王龙 | CD1: =生产MA!O4 -> 特殊款霸王龙
A2: 香港接单日期 | B2: 第三方客户名称 | C2: 走货国家 | D2: PO号 | E2: 第三方客户 PO NO# | F2: SKU | G2: ITEM# | H2: 中文名 | I2: PO数量 (pcs) | J2: 内箱装箱数量(pcs) | K2: 外箱装箱数量(pcs) | L2: 总箱数 | M2: 客PO期 | N2: 验货期 | O2: 第三方验货时间 | P2: 验货结果 | Q2: 船期 | R2: 箱唛资料(收到日期) | S2: 外箱贴纸 | T2: 客供贴纸AI(收到日期) | U2: 样板 | V2: 日期 | W2: 额外说明书/保证书 | X2: 备注 | Y2: ZURU 跟单 | Z2: 单价USD | AA2: 金额USD | AB2: 发票号 | AC2: 送回数量 | AD2: 欠数 | AE2: 贴纸情况 | AF2: 下单情况 | AG2: 系统货号 | AH2: ZURU | AI2: 球数 | AJ2: MA | AK2: B MA | AL2: 客版 | AM2: MA 1L | AN2: MA 3L | AO2: Smyths客版 | AP2: MA 5L | AQ2: B MA 5L | AR2: 客版 | AS2: MA 1L | AT2: MA 3L | AU2: MA B3L | AV2: MA 1L | AW2: MA 3L | AX2: WM 客版 | AY2: Big 客版 | AZ2: WM M客版 | BA2: IMP 3L 客版 | BB2: MA 1L | BC2: MA 3L | BD2: 3L底座 | BE2: MA 1L | BF2: MA 3L | BG2: 底座 | BH2: 圆筒 | BI2: logo英法语彩纸/贴纸 157378 | BL2: 0.12239583 | BM2: 0.12239583 | BN2: 0.12239583 | BO2: 0.12239583 | BP2: 0.12239583 | BQ2: 0.12239583 | BR2: 0.12239583 | BS2: 0.12239583 | BT2: 0.020833333 | BU2: MA扣数 | BV2: =生产MA!G12 -> 134028 | BW2: =生产MA!H12 -> 134028 | BX2: =生产MA!I12 -> 134028 | BY2: =生产MA!J12 -> 134028 | BZ2: =生产MA!K12 -> 134028 | CA2: =生产MA!L12 -> 134028 | CB2: =生产MA!M12 -> 134028 | CC2: =生产MA!N12 -> 134028 | CD2: =生产MA!O12 -> 22815
A3: 45617 | B3: ZURU | C3: 深圳 | D3: ZPO2411012 | E3: PP订单 | G3: 77685GQ2-S001 | H3: 混搭恐龙27pcs/GQ2*2/箱 | I3: 1135 | J3: 0 | K3: 54 | L3: =I3/K3 -> 21.018519 | M3: 45639 | N3: 45635 | R3: 无 | S3: 无 | T3: 无 | X3: 如何同意以上交货期到ZURU但是最后由于供应商原因无法交货，ZURU保留以下的罚款条款 不按期出货罚款如下： 1-7（含第七天）天内延迟出货罚款为合同总金额的百分之五 7-14（含第十四天）天内延迟出货罚款为合同总金额的百分之七 如果超过14天将扣合同金额的百分之十或者由客人提出预计运费方案 如果因为质量不符合雨禾要求的标准，供应商必须改进产品并达到标准并支付返工费用和出货延迟费用 订单细节会不时进行修改，如果订单做了修改要及时通知供应商，修改和特殊指引在生产过程中要由邮件或者电话确认 | AB3: 年存 | AH3: # | BV3: =BV2-BL3-BL129 -> 46090.729 | BW3: =BW2-BM3-BM129 -> 46090.729 | BX3: =BX2-BN3-BN129 -> 46090.729 | BY3: =BY2-BO3-BO129 -> 46090.729 | BZ3: =BZ2-BP3-BP129 -> 46090.729 | CA3: =CA2-BQ3-BQ129 -> 46090.729 | CB3: =CB2-BR3-BR129 -> 46090.729 | CC3: =CC2-BS3-BS129 -> 46090.729 | CD3: =CD2-BT3-BT129 -> 7797.1667
A4: 45952 | B4: DISTRIBUIDORA LIVERPOOL S.A DE C.V. | C4: 墨西哥 | D4: 4500182578 | E4: 62050798 | F4: 4500182578-130 | G4: 77685GQ2-S001 | H4: 混搭恐龙27pcs/GQ2*2/箱 | I4: 972 | J4: 0 | K4: 54 | L4: =I4/K4 -> 18 | M4: 46006 | N4: 46004 | P4: 自检 | Q4: 1/15 截SI | R4: 45971 | S4: 无 | T4: 11/28 UPC贴纸+进口商贴纸+12/1价标贴纸 | X4: 日期码格式：ZURU INC(BVI) 标准格式 日期：按实际生产日期 Packaging Info:77685GQ2:MA 多语 EAN 包装+UPC贴纸+进口商贴纸+价标贴纸+箱唛 Remark: 1.此单价格贴纸（ZURU定购).-无位置图，价标贴纸贴于产品背面右上角空白处（不遮挡西班牙语处），如有特殊情况，请重新确认位置图。 2.此单有第三方监柜，不用额外准备备品，会在大货中每款拆1pc，拆了包装的产品会由监装员用客供胶带封好或在外箱上写上""opened by telescope” MOTHER UPC Barcode: | Y4: Ava Liang | Z4: 0.7795 | AA4: =Z4*I4 -> 757.674 | AB4: A97534-1.14 | AC4: 972 | AD4: =AC4-I4 -> 0 | AF4: 系统出单 | AG4: 77685GQ2-S001-3L | AH4: 已入 | AI4: =I4 -> 972 | AK4: =I4 -> 972 | AN4: =I4 -> 972 | AQ4: =I4 -> 972 | AU4: =I4/27 -> 36 | BL4: =$I4*BL$2 -> 118.96875 | BM4: =$I4*BM$2 -> 118.96875 | BN4: =$I4*BN$2 -> 118.96875 | BO4: =$I4*BO$2 -> 118.96875 | BP4: =$I4*BP$2 -> 118.96875 | BQ4: =$I4*BQ$2 -> 118.96875 | BR4: =$I4*BR$2 -> 118.96875 | BS4: =$I4*BS$2 -> 118.96875 | BT4: =$I4*BT$2 -> 20.25 | BV4: =BV3-BL4 -> 45971.76 | BW4: =BW3-BM4 -> 45971.76 | BX4: =BX3-BN4 -> 45971.76 | BY4: =BY3-BO4 -> 45971.76 | BZ4: =BZ3-BP4 -> 45971.76 | CA4: =CA3-BQ4 -> 45971.76 | CB4: =CB3-BR4 -> 45971.76 | CC4: =CC3-BS4 -> 45971.76 | CD4: =CD3-BT4 -> 7776.9167
A5: 45964 | B5: ESAL TRADING L.L.C. | C5: 阿拉伯联合酋长国 | D5: 4500180717 | E5: UAE | F5: 4500180717-210 | G5: 77685GQ2-S001 | H5: 混搭恐龙27pcs/GQ2*2/箱 | I5: 2916 | J5: 0 | K5: 54 | L5: =I5/K5 -> 54 | M5: 46006 | N5: 46006 | P5: pass | R5: 45973 | S5: 无 | T5: 11/28进口商贴纸 | X5: 日期码格式：ZURU INC(BVI) 标准格式 日期：按实际生产日期 Packaging Info: 77685GQ2: MA 收缩膜+进口商贴纸 (含G Mark, QR code, 阿拉伯警语); 贴纸上的QR code需微信可扫，扫描结果另外通知; 收缩膜上UPC条码为193052079053；MA P DQ+进口商贴纸; 产品年龄3+； 客人箱唛排版，印4面，条码内容193052079053； Remark: | Y5: Nora Pan | Z5: 0.7913 | AA5: =Z5*I5 -> 2307.4308 | AB5: A97533-1.14 | AC5: 2916 | AD5: =AC5-I5 -> 0 | AE5: OK | AF5: 系统出单 | AG5: 77685GQ2-S001 | AH5: 已入 | AI5: =I5 -> 2916 | AK5: =I5 -> 2916 | AM5: =I5 -> 2916 | AQ5: =I5 -> 2916 | AS5: =I5/27 -> 108 | BL5: =$I5*BL$2 -> 356.90625 | BM5: =$I5*BM$2 -> 356.90625 | BN5: =$I5*BN$2 -> 356.90625 | BO5: =$I5*BO$2 -> 356.90625 | BP5: =$I5*BP$2 -> 356.90625 | BQ5: =$I5*BQ$2 -> 356.90625 | BR5: =$I5*BR$2 -> 356.90625 | BS5: =$I5*BS$2 -> 356.90625 | BT5: =$I5*BT$2 -> 60.75 | BV5: =BV4-BL5 -> 45614.854 | BW5: =BW4-BM5 -> 45614.854 | BX5: =BX4-BN5 -> 45614.854 | BY5: =BY4-BO5 -> 45614.854 | BZ5: =BZ4-BP5 -> 45614.854 | CA5: =CA4-BQ5 -> 45614.854 | CB5: =CB4-BR5 -> 45614.854 | CC5: =CC4-BS5 -> 45614.854 | CD5: =CD4-BT5 -> 7716.1667
A6: 45964 | B6: ESAL TRADING L.L.C. | C6: 阿拉伯联合酋长国 | D6: 4500180735 | E6: QAT | F6: 4500180735-190 | G6: 77685GQ2-S001 | H6: 混搭恐龙27pcs/GQ2*2/箱 | I6: 1080 | J6: 0 | K6: 54 | L6: =I6/K6 -> 20 | M6: 46006 | N6: 46006 | P6: pass | Q6: 1/12 截SI | R6: 45973 | S6: 无 | T6: 11/28进口商贴纸 | X6: 日期码格式：ZURU INC(BVI) 标准格式 日期：按实际生产日期 Packaging Info: 77685GQ2: MA 收缩膜+进口商贴纸 (含G Mark, QR code, 阿拉伯警语); 贴纸上的QR code需微信可扫，扫描结果另外通知; 收缩膜上UPC条码为193052079053；MA P DQ+进口商贴纸; 产品年龄3+； 客人箱唛排版，印4面，条码内容193052079053； Remark: | Y6: Nora Pan | Z6: 0.7913 | AA6: =Z6*I6 -> 854.604 | AB6: A97503-1.12 | AC6: 1080 | AD6: =AC6-I6 -> 0 | AE6: OK | AF6: 系统出单 | AG6: 77685GQ2-S001 | AH6: 已入 | AI6: =I6 -> 1080 | AK6: =I6 -> 1080 | AM6: =I6 -> 1080 | AQ6: =I6 -> 1080 | AS6: =I6/27 -> 40 | BL6: =$I6*BL$2 -> 132.1875 | BM6: =$I6*BM$2 -> 132.1875 | BN6: =$I6*BN$2 -> 132.1875 | BO6: =$I6*BO$2 -> 132.1875 | BP6: =$I6*BP$2 -> 132.1875 | BQ6: =$I6*BQ$2 -> 132.1875 | BR6: =$I6*BR$2 -> 132.1875 | BS6: =$I6*BS$2 -> 132.1875 | BT6: =$I6*BT$2 -> 22.5 | BV6: =BV5-BL6 -> 45482.667 | BW6: =BW5-BM6 -> 45482.667 | BX6: =BX5-BN6 -> 45482.667 | BY6: =BY5-BO6 -> 45482.667 | BZ6: =BZ5-BP6 -> 45482.667 | CA6: =CA5-BQ6 -> 45482.667 | CB6: =CB5-BR6 -> 45482.667 | CC6: =CC5-BS6 -> 45482.667 | CD6: =CD5-BT6 -> 7693.6667
A7: 45964 | B7: ESAL TRADING L.L.C. | C7: 阿拉伯联合酋长国 | D7: 4500180758 | E7: KSA | F7: 4500180758-400 | G7: 77685GQ2-S001 | H7: 混搭恐龙27pcs/GQ2*2/箱 | I7: 1080 | J7: 0 | K7: 54 | L7: =I7/K7 -> 20 | M7: 46006 | N7: 46006 | P7: pass | Q7: 2/24 ETD | R7: 45973 | S7: 无 | T7: 11/28进口商贴纸 | X7: 日期码格式：ZURU INC(BVI) 标准格式 日期：按实际生产日期 Packaging Info: 77685GQ2: MA 收缩膜+进口商贴纸 (含G Mark, QR code, 阿拉伯警语); 贴纸上的QR code需微信可扫，扫描结果另外通知; 收缩膜上UPC条码为193052079053；MA P DQ+进口商贴纸; 产品年龄3+； 客人箱唛排版，印4面，条码内容193052079053； Remark: | Y7: Nora Pan | Z7: 0.7913 | AA7: =Z7*I7 -> 854.604 | AB7: 年存 | AC7: 1080 | AD7: =AC7-I7 -> 0 | AE7: OK | AF7: 系统出单 | AG7: 77685GQ2-S001 | AH7: 已入 | AI7: =I7 -> 1080 | AK7: =I7 -> 1080 | AM7: =I7 -> 1080 | AQ7: =I7 -> 1080 | AS7: =I7/27 -> 40 | BL7: =$I7*BL$2 -> 132.1875 | BM7: =$I7*BM$2 -> 132.1875 | BN7: =$I7*BN$2 -> 132.1875 | BO7: =$I7*BO$2 -> 132.1875 | BP7: =$I7*BP$2 -> 132.1875 | BQ7: =$I7*BQ$2 -> 132.1875 | BR7: =$I7*BR$2 -> 132.1875 | BS7: =$I7*BS$2 -> 132.1875 | BT7: =$I7*BT$2 -> 22.5 | BV7: =BV6-BL7 -> 45350.479 | BW7: =BW6-BM7 -> 45350.479 | BX7: =BX6-BN7 -> 45350.479 | BY7: =BY6-BO7 -> 45350.479 | BZ7: =BZ6-BP7 -> 45350.479 | CA7: =CA6-BQ7 -> 45350.479 | CB7: =CB6-BR7 -> 45350.479 | CC7: =CC6-BS7 -> 45350.479 | CD7: =CD6-BT7 -> 7671.1667
A8: 45972 | B8: ZHUYU(SHENZHEN)TRADING CO.,LTD. | C8: 中国 | D8: 4500185221 | E8: 5000002057 | F8: 4500185221-60 | G8: 77685GQ1-S002 | H8: 混搭恐龙13pcs/GQ1/箱 | I8: 2600 | J8: 0 | K8: 13 | L8: =I8/K8 -> 200 | M8: 46008 | N8: 46006 | P8: pass | Q8: 12/19 装柜 | R8: 翻单：4500178603 | S8: 无 | T8: 年龄贴（8+）+12/9 防串码 | X8: 日期码格式：ZURU INC(BVI) 标准格式 日期：按实际生产日期 Packaging Info: 物料要求 SKU 6 77685 MA PDQ +外挂中文收藏指南+中文说明书+收缩膜年龄贴（8+） 翻单： 4500178603 Remark: 2.外箱材质如下： 1）毛重小于5kg 外箱纸质 K=B 爆破:1000Kpa 边压:4400N/M; 2）毛重大于5kg 外箱纸质 K636K 爆破:1400Kpa 边压:6300N/M; 3. 产品/销售包装/外箱日期码要一致， 4.此产品务必满足国内6P 测试标准，因为可能会被市场监督局抽查，如有问题产生，工厂要负全责 5. 这张订单做出厂价，我司自行安排车辆去贵司提货，贵司需要配合提供出口报关 6. 此单所有产品启用防窜码贴纸 : 位置产品和箱唛对应贴好 | Y8: Dona Tang | Z8: 0.7758 | AA8: =Z8*I8 -> 2017.08 | AB8: 年存 | AC8: 2600 | AD8: =AC8-I8 -> 0 | AE8: OK | AF8: 系统出单 | AG8: 77685GQ1-S002-中 | AH8: 已入 | AI8: =I8 -> 2600 | AK8: =I8 -> 2600 | AM8: =I8 -> 2600 | AR8: =I8 -> 2600 | AV8: =I8/13 -> 200 | BL8: =$I8*BL$2 -> 318.22917 | BM8: =$I8*BM$2 -> 318.22917 | BN8: =$I8*BN$2 -> 318.22917 | BO8: =$I8*BO$2 -> 318.22917 | BP8: =$I8*BP$2 -> 318.22917 | BQ8: =$I8*BQ$2 -> 318.22917 | BR8: =$I8*BR$2 -> 318.22917 | BS8: =$I8*BS$2 -> 318.22917 | BT8: =$I8*BT$2 -> 54.166667 | BV8: =BV7-BL8 -> 45032.25 | BW8: =BW7-BM8 -> 45032.25 | BX8: =BX7-BN8 -> 45032.25 | BY8: =BY7-BO8 -> 45032.25 | BZ8: =BZ7-BP8 -> 45032.25 | CA8: =CA7-BQ8 -> 45032.25 | CB8: =CB7-BR8 -> 45032.25 | CC8: =CC7-BS8 -> 45032.25 | CD8: =CD7-BT8 -> 7617
A9: 45995 | B9: WALMART INC. | C9: 美国 | D9: 4500188055 | E9: 0963642005 | F9: 4500188055-10 | G9: 77685SLB-S001 | H9: 混搭恐龙卡板装12pcs/GQ4/CTN**96/Slip Sheet | I9: 9216 | J9: 0 | K9: 1152 | L9: =I9/K9 -> 8 | M9: 46027 | N9: 46027 | O9: 1/20 BV | P9: pass | Q9: 1/26 截SI | R9: 翻单 | S9: 有 | T9: 12/16 RFID | X9: 日期码格式：ZURU DGYYYYMMDD CHINA(日期避开周末和法定节假日即可） 日期：按实际生产日期 Packaging Info: 77685SLB-S001： 1.包装要求： MA 1L A版收缩膜+MA B版纸袋+MA 5L B版收藏指南+MA B版slime bag+ MA 1L B版说明书+客版1L PDQ 每pcs产品上要贴1张RFID贴纸，贴纸由ZURU提供，贴纸位置请严格按照我们签回的签板； Remark: 77685SLB-S001： 1.包装要求： MA 1L A版收缩膜+MA B版纸袋+MA 5L B版收藏指南+MA B版slime bag+ MA 1L B版说明书+客版1L PDQ 每pcs产品上要贴1张RFID贴纸，贴纸由ZURU提供，贴纸位置请严格按照我们签回的签板； 2. 外箱印刷带条码的RFID箱唛：RFID紫色色带+WM Dept.图标+RFID图标+ITF-14条码，四面右下角印刷ZURU logo, ITFF条码只印刷在正唛一面，在加印的时候确保 条形码能扫描出来，外箱侧面任一角落加印："MADE IN CHINA" 字样； 3. 每个slip sheet上面贴一张艾利贴纸（不干胶贴纸）和一张普通贴纸（A4纸），slip sheet打印的普通贴纸的尺寸不能比艾利贴纸小，普通贴纸内容见附件； 4. 在产品上和包装上要有日期码、以及要有MADE IN CHINA和ZURU字样； 5. 产品如有扎带口要剪平，不能刮手。 6. 此单需要验货，请多备料 7. 此单以slip sheet出货，77685：1152pcs/96CTN/Slip Sheet | Y9: Maggie Xie | Z9: 62.7125 | AA9: =Z9*L9 -> 501.7 | AB9: 年存 | AC9: =9180+36 -> 9216 | AD9: =AC9-I9 -> 0 | AE9: OK | AF9: 系统出单 | AG9: 77685SLB-S001 | AH9: 已入 | AI9: =I9 -> 9216 | AK9: =I9 -> 9216 | AM9: =I9 -> 9216 | AQ9: =I9 -> 9216 | AX9: =I9/12 -> 768 | BL9: =$I9*BL$2 -> 1128 | BM9: =$I9*BM$2 -> 1128 | BN9: =$I9*BN$2 -> 1128 | BO9: =$I9*BO$2 -> 1128 | BP9: =$I9*BP$2 -> 1128 | BQ9: =$I9*BQ$2 -> 1128 | BR9: =$I9*BR$2 -> 1128 | BS9: =$I9*BS$2 -> 1128 | BT9: =$I9*BT$2 -> 192 | BV9: =BV8-BL9 -> 43904.25 | BW9: =BW8-BM9 -> 43904.25 | BX9: =BX8-BN9 -> 43904.25 | BY9: =BY8-BO9 -> 43904.25 | BZ9: =BZ8-BP9 -> 43904.25 | CA9: =CA8-BQ9 -> 43904.25 | CB9: =CB8-BR9 -> 43904.25 | CC9: =CC8-BS9 -> 43904.25 | CD9: =CD8-BT9 -> 7425
A10: 45968 | B10: CRG | C10: 哥斯达黎加 | D10: 4500183616 | E10: ZU02-26 | F10: 4500183616-190 | G10: 77685GQ2-S001 | H10: 混搭恐龙27pcs/GQ2*2/箱 | I10: 1782 | J10: 0 | K10: 54 | L10: =I10/K10 -> 33 | M10: 46031 | N10: 46027 | P10: 自检 | Q10: 1/13截SI | R10: 45982 | S10: 无 | T10: 12/10 进口商贴纸+UPC贴纸 | X10: 日期码格式：ZURU INC(BVI) 标准格式 日期：按实际生产日期 Packaging Info: 其余item：MA 多语EAN包装+进口商贴纸+UPC贴纸+箱唛 Remark: | Y10: Ava Liang | Z10: 0.7913 | AA10: =Z10*I10 -> 1410.0966 | AB10: 年存 | AC10: 1782 | AD10: =AC10-I10 -> 0 | AE10: OK | AF10: 系统出单 | AG10: 77685GQ2-S001-3L | AH10: 已入 | AI10: =I10 -> 1782 | AK10: =I10 -> 1782 | AN10: =I10 -> 1782 | AQ10: =I10 -> 1782 | AU10: =I10/27 -> 66 | BL10: =$I10*BL$2 -> 218.10937 | BM10: =$I10*BM$2 -> 218.10937 | BN10: =$I10*BN$2 -> 218.10937 | BO10: =$I10*BO$2 -> 218.10937 | BP10: =$I10*BP$2 -> 218.10937 | BQ10: =$I10*BQ$2 -> 218.10937 | BR10: =$I10*BR$2 -> 218.10937 | BS10: =$I10*BS$2 -> 218.10937 | BT10: =$I10*BT$2 -> 37.125 | BV10: =BV9-BL10 -> 43686.141 | BW10: =BW9-BM10 -> 43686.141 | BX10: =BX9-BN10 -> 43686.141 | BY10: =BY9-BO10 -> 43686.141 | BZ10: =BZ9-BP10 -> 43686.141 | CA10: =CA9-BQ10 -> 43686.141 | CB10: =CB9-BR10 -> 43686.141 | CC10: =CC9-BS10 -> 43686.141 | CD10: =CD9-BT10 -> 7387.875
A11: 45978 | B11: IMPORTADORA SUDAMERICANA & | C11: 阿根廷 | D11: 4500185782 | F11: 4500185782-30 | G11: 77685GQ7-S001 | H11: 混搭恐龙8pcs/GQ7/箱 | I11: 5000 | J11: 0 | K11: 8 | L11: =I11/K11 -> 625 | M11: 46027 | N11: 46030 | P11: pass | Q11: 2/3 截SI | R11: 45999 | S11: 无 | T11: 12/15进口商贴纸+UPC贴纸 | X11: 日期码格式：ZURU INC(BVI) 标准格式 日期：按实际生产日期 Packaging Info: 77685GQ7： MA 3L EAN包装+进口商贴纸+UPC贴纸+箱唛,, Remark: 请确保包装上的条形码是UPC，如果是babyUPC，需要用mother UPC 覆盖，如有不一致，请及时提出。谢谢! | Y11: Aimee Huang | Z11: 0.8485 | AA11: =Z11*I11 -> 4242.5 | AB11: 年存 | AC11: =4976+24 -> 5000 | AD11: =AC11-I11 -> 0 | AE11: OK | AF11: 系统出单 | AG11: 77685GQ7-S001 | AH11: 已入 | AI11: =I11 -> 5000 | AK11: =I11 -> 5000 | AN11: =I11 -> 5000 | AQ11: =I11 -> 5000 | BA11: =I11/8 -> 625 | BL11: =$I11*BL$2 -> 611.97917 | BM11: =$I11*BM$2 -> 611.97917 | BN11: =$I11*BN$2 -> 611.97917 | BO11: =$I11*BO$2 -> 611.97917 | BP11: =$I11*BP$2 -> 611.97917 | BQ11: =$I11*BQ$2 -> 611.97917 | BR11: =$I11*BR$2 -> 611.97917 | BS11: =$I11*BS$2 -> 611.97917 | BT11: =$I11*BT$2 -> 104.16667 | BV11: =BV10-BL11 -> 43074.161 | BW11: =BW10-BM11 -> 43074.161 | BX11: =BX10-BN11 -> 43074.161 | BY11: =BY10-BO11 -> 43074.161 | BZ11: =BZ10-BP11 -> 43074.161 | CA11: =CA10-BQ11 -> 43074.161 | CB11: =CB10-BR11 -> 43074.161 | CC11: =CC10-BS11 -> 43074.161 | CD11: =CD10-BT11 -> 7283.7083
A12: 45992 | B12: ASDA STORES LTD | C12: 英国 | D12: 4500187528 | E12: 2950867457 | F12: 4500187528-60 | G12: 77685SLB-S002 | H12: 混搭恐龙13pcs/GQ1/CTN**80/卡板装 | I12: 2080 | J12: 0 | K12: 1040 | L12: =I12/K12 -> 2 | M12: 46034 | N12: 46030 | P12: 自检 | Q12: 1/21 截SI | R12: 45992 | S12: 无 | T12: 贴一张slip sheet贴纸自行打印 | X12: 日期码格式：ZURU INC(BVI) 标准格式 日期：按实际生产日期 Packaging Info: 77685SLB-S002, MA最新UPC包装，UPC :193052079053，请先检查条码是否正确再安排做货。 Slip sheet: 77685GQ1-S002 13pcs/PDQ/CTN 20*4H=80CTN/SLB=1040pcs/Slip Sheet; 一共需要2个slip sheet； Slip Sheet打包好后，需要在正唛、侧唛右下角各贴一张slip sheet贴纸，直接用A4纸打印出来即可，贴纸尺寸160mm width x 140mm high； Slip Sheet尺寸限制为100*115*130CM，一旦实际SLIP SHEET尺寸超过这个尺寸，请提前通知ZURU跟单，需同客人确认才能量产和出货.""" 7151SLB-S002, MA最新UPC包装+WEEE带电池走货30语通用说明书，UPC :193052033482，请先检查条码是否正确再安排做货。 Slip sheet: 7151-S005 3PCS(CTN SIZE: 30.5*20*13CM), (5*7+7)*4H=168CTN=504PCS/SLIP SHEET；一共需要3个slip sheet； Slip Sheet打包好后，需要在正唛、侧唛右下角各贴一张slip sheet贴纸，直接用A4纸打印出来即可，贴纸尺寸160mm width x 140mm high； Slip Sheet尺寸限制为100*115*130CM，一旦实际SLIP SHEET尺寸超过这个尺寸，请提前通知ZURU跟单，需同客人确认才能量产和出货.""" 77711SLB-S001-INT, MA最新UPC包装，UPC :193052080127，请先检查条码是否正确再安排做货。 Slip sheet: 77711GQ1-S002-INT 13pcs/PDQ/CTN 15*5H=75CTN/SLB=975pcs/Slip Sheet;；一共需要3个slip sheet； Slip Sheet打包好后，需要在正唛、侧唛右下角各贴一张slip sheet贴纸，直接用A4纸打印出来即可，贴纸尺寸160mm width x 140mm high； Slip Sheet尺寸限制为100*115*130CM，一旦实际SLIP SHEET尺寸超过这个尺寸，请提前通知ZURU跟单，需同客人确认才能量产和出货.""" Remark: 1. 产品及包装需要印UKCA图标，包装需要有ZURU UK LTD/ZURU France地址信息，QC同事请核查，如有问题与跟单确认 2. 产品/包装/外箱都需要打ZURU格式日期码，日期必须为法定工作日。 3. 需要符合欧洲标准不能含有闪粉和微塑料，否则不合法规会有客诉产生 | Y12: Meyya Liu | Z12: 82.6221 | AA12: =Z12*L12 -> 165.2442 | AB12: 年存 | AC12: 2080 | AD12: =AC12-I12 -> 0 | AE12: 无 | AF12: 系统出单 | AG12: 77685SLB-S002 | AH12: 已入 | AI12: =I12 -> 2080 | AK12: =I12 -> 2080 | AM12: =I12 -> 2080 | AQ12: =I12 -> 2080 | AV12: =I12/13 -> 160 | BL12: =$I12*BL$2 -> 254.58333 | BM12: =$I12*BM$2 -> 254.58333 | BN12: =$I12*BN$2 -> 254.58333 | BO12: =$I12*BO$2 -> 254.58333 | BP12: =$I12*BP$2 -> 254.58333 | BQ12: =$I12*BQ$2 -> 254.58333 | BR12: =$I12*BR$2 -> 254.58333 | BS12: =$I12*BS$2 -> 254.58333 | BT12: =$I12*BT$2 -> 43.333333 | BV12: =BV11-BL12 -> 42819.578 | BW12: =BW11-BM12 -> 42819.578 | BX12: =BX11-BN12 -> 42819.578 | BY12: =BY11-BO12 -> 42819.578 | BZ12: =BZ11-BP12 -> 42819.578 | CA12: =CA11-BQ12 -> 42819.578 | CB12: =CB11-BR12 -> 42819.578 | CC12: =CC11-BS12 -> 42819.578 | CD12: =CD11-BT12 -> 7240.375
A13: 46003 | B13: T.J.MORRIS LTD | C13: 英国 | D13: 4500188811 | E13: 11519265 | F13: 4500188811-10 | G13: 77685GQ2-S001 | H13: 混搭恐龙27pcs/GQ2*2/箱 | I13: 25272 | J13: 202901 | K13: 54 | L13: =I13/K13 -> 468 | M13: 46038 | N13: 46034 | P13: pass | Q13: 2/2 截SI | R13: 46003 | S13: 无 | T13: 无 | X13: 日期码格式：ZURU INC(BVI) 标准格式 日期：按实际生产日期 Packaging Info: 1L MA UPC 包装; MA说明书/指南; MA PDQ Remark: 1.产品及包装需要印UKCA图标，包装需要有ZURU UK LTD/ZURU France地址信息，QC同事请核查，如有问题与跟单确认。 2. 需要符合欧洲标准不能含有闪粉和微塑料，否则不和法规会有客诉产生 | Y13: Lena Huang | Z13: 0.7751 | AA13: =Z13*I13 -> 19588.327 | AB13: 年存 | AC13: 25272 | AD13: =AC13-I13 -> 0 | AE13: 无 | AF13: 系统出单 | AG13: 77685GQ2-S001 | AH13: 已入 | AI13: =I13 -> 25272 | AK13: =I13 -> 25272 | AM13: =I13 -> 25272 | AQ13: =I13 -> 25272 | AS13: =I13/27 -> 936 | BL13: =$I13*BL$2 -> 3093.1875 | BM13: =$I13*BM$2 -> 3093.1875 | BN13: =$I13*BN$2 -> 3093.1875 | BO13: =$I13*BO$2 -> 3093.1875 | BP13: =$I13*BP$2 -> 3093.1875 | BQ13: =$I13*BQ$2 -> 3093.1875 | BR13: =$I13*BR$2 -> 3093.1875 | BS13: =$I13*BS$2 -> 3093.1875 | BT13: =$I13*BT$2 -> 526.5 | BV13: =BV12-BL13 -> 39726.391 | BW13: =BW12-BM13 -> 39726.391 | BX13: =BX12-BN13 -> 39726.391 | BY13: =BY12-BO13 -> 39726.391 | BZ13: =BZ12-BP13 -> 39726.391 | CA13: =CA12-BQ13 -> 39726.391 | CB13: =CB12-BR13 -> 39726.391 | CC13: =CC12-BS13 -> 39726.391 | CD13: =CD12-BT13 -> 6713.875
A14: 45996 | B14: MINISO DEPOT CA INC. | C14: 美国 | D14: 4500188208 | E14: 4353960671 | F14: 4500188208-10 | G14: 77685GQ1-S002 | H14: 混搭恐龙13pcs/GQ1/箱 | I14: 1807 | J14: 0 | K14: 13 | L14: =I14/K14 -> 139 | M14: 46044 | N14: 46041 | P14: pass | R14: 46009 | S14: 无 | T14: 12/18UPC 条码贴纸 | X14: 日期码格式：ZURU INC(BVI) 标准格式 日期：按实际生产日期 Packaging Info: 1. 包装方式：MA UPC优先1L最新包装，出口美国； 2. 产品和包装上印刷tracking code信息，格式为ZURU常规； 3. ZURU QC 验货合格后即可出货. Remark: 4. 77685GQ1-S002 PDQ上需要贴一张UPC 条码贴纸,UPC显示：193052079053，贴纸AW跟单提供，工厂自行采购； | Y14: Iris Yuan | Z14: 0.4655 | AA14: =Z14*I14 -> 841.1585 | AB14: 年存 | AC14: 1807 | AD14: =AC14-I14 -> 0 | AE14: OK | AF14: 系统出单 | AG14: 77685GQ1-S002 | AH14: 已入 | AI14: =I14 -> 1807 | AK14: =I14 -> 1807 | AM14: =I14 -> 1807 | AQ14: =I14 -> 1807 | AV14: =I14/13 -> 139 | BL14: =$I14*BL$2 -> 221.16927 | BM14: =$I14*BM$2 -> 221.16927 | BN14: =$I14*BN$2 -> 221.16927 | BO14: =$I14*BO$2 -> 221.16927 | BP14: =$I14*BP$2 -> 221.16927 | BQ14: =$I14*BQ$2 -> 221.16927 | BR14: =$I14*BR$2 -> 221.16927 | BS14: =$I14*BS$2 -> 221.16927 | BT14: =$I14*BT$2 -> 37.645833 | BV14: =BV13-BL14 -> 39505.221 | BW14: =BW13-BM14 -> 39505.221 | BX14: =BX13-BN14 -> 39505.221 | BY14: =BY13-BO14 -> 39505.221 | BZ14: =BZ13-BP14 -> 39505.221 | CA14: =CA13-BQ14 -> 39505.221 | CB14: =CB13-BR14 -> 39505.221 | CC14: =CC13-BS14 -> 39505.221 | CD14: =CD13-BT14 -> 6676.2292
A15: 45995 | B15: MINISO DEPOT CA INC. | C15: 美国 | D15: 4500187984 | E15: 4353960389 | F15: 4500187984-10 | G15: 77685GQ1-S002 | H15: 混搭恐龙13pcs/GQ1/箱 | I15: 2223 | J15: 0 | K15: 13 | L15: =I15/K15 -> 171 | M15: 46044 | N15: 46041 | P15: pass | Q15: 1/23 截SI | R15: 46009 | S15: 无 | T15: 12/18UPC 条码贴纸 | X15: 日期码格式：ZURU INC(BVI) 标准格式 日期：按实际生产日期 Packaging Info: 1. 包装方式：MA UPC优先1L最新包装，出口美国； 2. 产品和包装上印刷tracking code信息，格式为ZURU常规； 3. ZURU QC 验货合格后即可出货. Remark: 4. 77685GQ1-S002 PDQ上需要贴一张UPC 条码贴纸,UPC显示：193052079053，贴纸AW跟单提供，工厂自行采购； | Y15: Iris Yuan | Z15: 0.4759 | AA15: =Z15*I15 -> 1057.9257 | AB15: 年存 | AC15: =2171+52 -> 2223 | AD15: =AC15-I15 -> 0 | AE15: OK | AF15: 系统出单 | AG15: 77685GQ1-S002 | AH15: 已入 | AI15: =I15 -> 2223 | AK15: =I15 -> 2223 | AM15: =I15 -> 2223 | AQ15: =I15 -> 2223 | AV15: =I15/13 -> 171 | BL15: =$I15*BL$2 -> 272.08594 | BM15: =$I15*BM$2 -> 272.08594 | BN15: =$I15*BN$2 -> 272.08594 | BO15: =$I15*BO$2 -> 272.08594 | BP15: =$I15*BP$2 -> 272.08594 | BQ15: =$I15*BQ$2 -> 272.08594 | BR15: =$I15*BR$2 -> 272.08594 | BS15: =$I15*BS$2 -> 272.08594 | BT15: =$I15*BT$2 -> 46.3125 | BV15: =BV14-BL15 -> 39233.135 | BW15: =BW14-BM15 -> 39233.135 | BX15: =BX14-BN15 -> 39233.135 | BY15: =BY14-BO15 -> 39233.135 | BZ15: =BZ14-BP15 -> 39233.135 | CA15: =CA14-BQ15 -> 39233.135 | CB15: =CB14-BR15 -> 39233.135 | CC15: =CC14-BS15 -> 39233.135 | CD15: =CD14-BT15 -> 6629.9167
A16: 45987 | B16: COMERCIALIZADORA MEXICO AMERICANA S | C16: 墨西哥 | D16: 4500187084 | E16: 5251218604 | F16: 4500187084-10 | G16: 77685GQ2-S002 | H16: 混搭恐龙27pcs/GQ2/箱-干燥剂 | I16: 1269 | J16: 0 | K16: 27 | L16: =I16/K16 -> 47 | M16: 46045 | N16: 46041 | P16: 自检 | Q16: 2/6 截SI | R16: 45987 | S16: 无 | T16: UPC贴纸+进口商贴纸 贴纸翻单PO4500167348 | U16: 日期码格式：LOTDGYYYYMMDD | X16: 日期码格式：LOTDGYYYYMMDD 日期：按实际生产日期 Packaging Info: 1. 77685GQ2 :3L EAN收缩膜+ UPC贴纸+ 3LPDQ+MA多语收藏指南+MA多语说明书+进口商贴纸+箱唛，进口商贴纸分别贴在球和说明书上，贴纸翻单PO4500167348 Remark: 1：客版日期码要求：LOT+ZURU标准日期码格式。东莞生产的格式：LOTDGYYYYMMDD, DG是东莞拼音首字母，YYYYMMDD是实际的年月日 3. 此单有第三方监柜，至少多备一套完整的物料用于监柜，请多备料。 4. WM墨西哥防霉的新要求:货物必须在出货主箱和集装箱中按要求放置干燥剂，干燥剂指定品牌干霸 77685GQ2：每箱需放置6小包干燥剂, 每包重2-3g 5. 如走柜货等loading plan 确认后再通知集装箱干燥剂数量 | Y16: Ever Li | Z16: 0.89 | AA16: =Z16*I16 -> 1129.41 | AB16: 年存 | AC16: =1242+27 -> 1269 | AD16: =AC16-I16 -> 0 | AE16: OK | AF16: 系统出单 | AG16: 77685GQ2-S002-3L | AH16: 已入 | AI16: =I16 -> 1269 | AK16: =I16 -> 1269 | AN16: =I16 -> 1269 | AQ16: =I16 -> 1269 | AU16: =I16/27 -> 47 | BL16: =$I16*BL$2 -> 155.32031 | BM16: =$I16*BM$2 -> 155.32031 | BN16: =$I16*BN$2 -> 155.32031 | BO16: =$I16*BO$2 -> 155.32031 | BP16: =$I16*BP$2 -> 155.32031 | BQ16: =$I16*BQ$2 -> 155.32031 | BR16: =$I16*BR$2 -> 155.32031 | BS16: =$I16*BS$2 -> 155.32031 | BT16: =$I16*BT$2 -> 26.4375 | BV16: =BV15-BL16 -> 39077.815 | BW16: =BW15-BM16 -> 39077.815 | BX16: =BX15-BN16 -> 39077.815 | BY16: =BY15-BO16 -> 39077.815 | BZ16: =BZ15-BP16 -> 39077.815 | CA16: =CA15-BQ16 -> 39077.815 | CB16: =CB15-BR16 -> 39077.815 | CC16: =CC15-BS16 -> 39077.815 | CD16: =CD15-BT16 -> 6603.4792
A17: 46014 | B17: NASA PANAMA | C17: 巴拿马 | D17: 4500189691 | F17: 4500189691-70 | G17: 77685GQ2-S001 | H17: 混搭恐龙27pcs/GQ2*2/箱 | I17: 540 | J17: 0 | K17: 54 | L17: =I17/K17 -> 10 | M17: 46052 | N17: 46046 | P17: 自检 | Q17: 2/3 截SI | R17: 46021 | S17: 无 | T17: 1/6UPC贴纸 | X17: 日期码格式：ZURU INC(BVI) 标准格式 日期：按实际生产日期 Packaging Info: 请确保包装上的条形码是UPC，如果是babyUPC，需要用mother UPC覆盖，如有不一致，请及时提出。谢谢! 77685GQ2,,MA 多语EAN包装+UPC贴纸+MA B版本说明书+MA PDQ 包装+箱唛,, Remark: Common: Equal ratio,, | Y17: Aimee Huang | Z17: 0.7967 | AA17: =Z17*I17 -> 430.218 | AB17: 年存 | AC17: =486+54 -> 540 | AD17: =AC17-I17 -> 0 | AE17: OK | AF17: 系统出单 | AG17: 77685GQ2-S001-3L | AH17: 已入 | AI17: =I17 -> 540 | AK17: =I17 -> 540 | AN17: =I17 -> 540 | AQ17: =I17 -> 540 | AU17: =I17/27 -> 20 | BL17: =$I17*BL$2 -> 66.09375 | BM17: =$I17*BM$2 -> 66.09375 | BN17: =$I17*BN$2 -> 66.09375 | BO17: =$I17*BO$2 -> 66.09375 | BP17: =$I17*BP$2 -> 66.09375 | BQ17: =$I17*BQ$2 -> 66.09375 | BR17: =$I17*BR$2 -> 66.09375 | BS17: =$I17*BS$2 -> 66.09375 | BT17: =$I17*BT$2 -> 11.25 | BV17: =BV16-BL17 -> 39011.721 | BW17: =BW16-BM17 -> 39011.721 | BX17: =BX16-BN17 -> 39011.721 | BY17: =BY16-BO17 -> 39011.721 | BZ17: =BZ16-BP17 -> 39011.721 | CA17: =CA16-BQ17 -> 39011.721 | CB17: =CB16-BR17 -> 39011.721 | CC17: =CC16-BS17 -> 39011.721 | CD17: =CD16-BT17 -> 6592.2292
A18: 45999 | B18: NASA PANAMA | C18: 巴拿马 | D18: 4500188248 | F18: 4500188248-100 | G18: 77685GQ2-S001 | H18: 混搭恐龙27pcs/GQ2*2/箱 | I18: 540 | J18: 0 | K18: 54 | L18: =I18/K18 -> 10 | M18: 46052 | N18: 46046 | P18: 自检 | Q18: 2/5 截SI | R18: 46021 | S18: 无 | T18: 1/6UPC贴纸 | X18: 日期码格式：ZURU INC(BVI) 标准格式 日期：按实际生产日期 Packaging Info: 请确保包装上的条形码是UPC，如果是babyUPC，需要用mother UPC覆盖，如有不一致，请及时提出。谢谢! 77685GQ2,,MA 多语EAN包装+UPC贴纸+MA B版本说明书+MA PDQ 包装+箱唛,, Remark： | Y18: Aimee Huang | Z18: 0.7967 | AA18: =Z18*I18 -> 430.218 | AB18: 年存 | AC18: 540 | AD18: =AC18-I18 -> 0 | AE18: OK | AF18: 系统出单 | AG18: 77685GQ2-S001-3L | AH18: 已入 | AI18: =I18 -> 540 | AK18: =I18 -> 540 | AN18: =I18 -> 540 | AQ18: =I18 -> 540 | AU18: =I18/27 -> 20 | BL18: =$I18*BL$2 -> 66.09375 | BM18: =$I18*BM$2 -> 66.09375 | BN18: =$I18*BN$2 -> 66.09375 | BO18: =$I18*BO$2 -> 66.09375 | BP18: =$I18*BP$2 -> 66.09375 | BQ18: =$I18*BQ$2 -> 66.09375 | BR18: =$I18*BR$2 -> 66.09375 | BS18: =$I18*BS$2 -> 66.09375 | BT18: =$I18*BT$2 -> 11.25 | BV18: =BV17-BL18 -> 38945.628 | BW18: =BW17-BM18 -> 38945.628 | BX18: =BX17-BN18 -> 38945.628 | BY18: =BY17-BO18 -> 38945.628 | BZ18: =BZ17-BP18 -> 38945.628 | CA18: =CA17-BQ18 -> 38945.628 | CB18: =CB17-BR18 -> 38945.628 | CC18: =CC17-BS18 -> 38945.628 | CD18: =CD17-BT18 -> 6580.9792
A19: 46016 | B19: AMAZON CA (VENDOR CENTER) | C19: 加拿大 | D19: 4500190061 | E19: 3MIKTQSU | F19: 4500190061-330 | G19: 77723-S001 | H19: 混搭恐龙2PK圆筒装 | I19: 12 | J19: 0 | K19: 12 | L19: =I19/K19 -> 1 | M19: 46059 | N19: 46055 | P19: 自检 | Q19: 3/2 截SI | R19: 46016 | S19: 有 | T19: 12/30空白UPC贴纸 | X19: 日期码格式：ZURU INC(BVI) 标准格式 日期：按实际生产日期 Packaging Info: 出口加拿大，包装需要至少2/3L UPC版，无硼版本。 #77723：2PK STD 77685 PVC Tube. MA 3L EAN版本+空白UPC贴纸，3L 铜版纸跟翻单#4500157378,空白贴纸跟单提供。收藏指南，说明书均为MA 5L标版。（两个球 的配比不能重复）。 Remark: 1. Amazon FOB订单，出口CA。外箱最长边不能超过25" （超过了，case pack只能为1），不符合要求的大货，一律不接受。 2. 外箱正面印ZURU Logo + SSCC LABEL（客供贴纸)，侧面印item#（订单上显示的SKU#) + carton size(以工厂实际尺寸为准，单位: inch) + MADE IN CHINA， 日期使用ZURU 标准版本 SSCC Label 显示的是客人自己的item#，SSCC Label 贴在外箱正面的正中间，贴一面即可，跟单订购，贴纸离外箱距必须至少3cm，每一 张SSCC label 都是唯一且有不同流水及条码的，没有损耗，绝对不可贴错 ，否则贴错或损坏一张会导致全部都错，千万要注意: SSCC 贴纸务必要在正中间(可以覆 盖Logo <(>&<)> 箱唛)，否则会影响到仓库扫描识别。 3. 日期码使用ZURU标准版本。 4. 如果大货有要求入邮包盒，则对应的邮包盒上面要打上日期码。 5. 按照客户PO# 装柜/箱号顺序装柜，跟单会提前给到装柜计划。在大货生产/仓库存放时，请留意该装柜要求，以便装柜时不混乱（避免装错/装漏/找不到货号等 ）。 6. 出口加拿大，包装需要至少2/3L UPC版，无硼版本。 7.邮包盒上要印刷日期码 | Y19: Kelly Shen | Z19: 1.9471 | AA19: =Z19*I19 -> 23.3652 | AB19: 年存 | AC19: 12 | AD19: =AC19-I19 -> 0 | AE19: OK | AF19: 系统出单 | AG19: 77723-S001 | AH19: 已入 | AI19: =I19*2 -> 24 | AK19: =I19*2 -> 24 | AN19: =I19*2 -> 24 | AQ19: =I19*2 -> 24 | BH19: =I19 -> 12 | BI19: =I19 -> 12 | BL19: =$I19*BL$2*2 -> 2.9375 | BM19: =$I19*BM$2*2 -> 2.9375 | BN19: =$I19*BN$2*2 -> 2.9375 | BO19: =$I19*BO$2*2 -> 2.9375 | BP19: =$I19*BP$2*2 -> 2.9375 | BQ19: =$I19*BQ$2*2 -> 2.9375 | BR19: =$I19*BR$2*2 -> 2.9375 | BS19: =$I19*BS$2*2 -> 2.9375 | BT19: =$I19*BT$2*2 -> 0.5 | BV19: =BV18-BL19 -> 38942.69 | BW19: =BW18-BM19 -> 38942.69 | BX19: =BX18-BN19 -> 38942.69 | BY19: =BY18-BO19 -> 38942.69 | BZ19: =BZ18-BP19 -> 38942.69 | CA19: =CA18-BQ19 -> 38942.69 | CB19: =CB18-BR19 -> 38942.69 | CC19: =CC18-BS19 -> 38942.69 | CD19: =CD18-BT19 -> 6580.4792
A20: 46035 | B20: VM INTERNATIONAL | C20: 美国 | D20: 4500191213 | E20: 33826 | F20: 4500191213-70 | G20: 77685GQ4-S001 | H20: 混搭恐龙12pcs/GQ4/箱 | I20: 1200 | J20: 0 | K20: 12 | L20: =I20/K20 -> 100 | M20: 46083 | N20: =M20-4 -> 46079 | P20: pass | Q20: 3/9 截SI | R20: 46041 | S20: 无 | T20: 无 | X20: 日期码格式：ZURU INC(BVI) 标准格式 日期：按实际生产日期 Packaging Info: 1. ZURU 标准日期码格式， 2. 无第三方测试和验货，ZURU 内部QC验货即可出货 Remark: 3. 优先 MA 1L UPC包装; 4. 纸箱印ZURU LOGO，出口美国； | Y20: Angel Lin | Z20: 0.4802 | AA20: =Z20*I20 -> 576.24 | AC20: =1188+12 -> 1200 | AD20: =AC20-I20 -> 0 | AE20: 无 | AF20: 系统出单 | AG20: 77685GQ4-S001 | AH20: 已入 | AI20: =I20 -> 1200 | AK20: =I20 -> 1200 | AM20: =I20 -> 1200 | AQ20: =I20 -> 1200 | AX20: =I20/12 -> 100 | BL20: =$I20*BL$2 -> 146.875 | BM20: =$I20*BM$2 -> 146.875 | BN20: =$I20*BN$2 -> 146.875 | BO20: =$I20*BO$2 -> 146.875 | BP20: =$I20*BP$2 -> 146.875 | BQ20: =$I20*BQ$2 -> 146.875 | BR20: =$I20*BR$2 -> 146.875 | BS20: =$I20*BS$2 -> 146.875 | BT20: =$I20*BT$2 -> 25 | BV20: =BV19-BL20 -> 38795.815 | BW20: =BW19-BM20 -> 38795.815 | BX20: =BX19-BN20 -> 38795.815 | BY20: =BY19-BO20 -> 38795.815 | BZ20: =BZ19-BP20 -> 38795.815 | CA20: =CA19-BQ20 -> 38795.815 | CB20: =CB19-BR20 -> 38795.815 | CC20: =CC19-BS20 -> 38795.815 | CD20: =CD19-BT20 -> 6555.4792
A21: 46014 | B21: JSC 􀂫GRAND-TRADE􀂻 | C21: 俄罗斯联邦 | D21: 4500189587 | E21: PGT-720385 | F21: 4500189587-10 | G21: 77685GQ1-S002 | H21: 混搭恐龙13pcs/GQ1/箱 | I21: 676 | J21: 0 | K21: 13 | L21: =I21/K21 -> 52 | M21: 46092 | N21: 46088 | O21: 有监柜 | P21: 自检 | Q21: 3/18截SI | R21: 46015 | S21: 有 | T21: 1/13进口商贴纸+外箱贴纸+EAN条码+1/19 QR code贴纸 | X21: 日期码格式：ZURU INC(BVI) 标准格式 日期：按实际生产日期 Packaging Info: 77685GQ1:MA收缩膜+进口商贴纸+EAN条码+QR code贴纸;MA PDQ+1张空白帖覆盖recycle字样；MA指南+1张空白帖覆盖recycle字样 外箱侧面右上角各1张箱唛； 有监柜验货； 需要打印序号1-5的二维码拍照给客户确认后再批量打印；做大货时也提供几张二维码贴产品上的照片 QRcode要求：贴纸上客户PO号及序号一起打印。尺寸（客户建议18*18mm非强制）根据产品调整，最小接受10*10mm,要清晰可扫描，2年不褪色。 需提供application report追中QR code到箱/柜 Remark: | Y21: Cora Zhou | Z21: 0.7985 | AA21: =Z21*I21 -> 539.786 | AB21: 年存 | AC21: 676 | AD21: =AC21-I21 -> 0 | AE21: OK | AF21: 系统出单 | AG21: 77685GQ1-S002 | AH21: 已入 | AI21: =I21 -> 676 | AK21: =I21 -> 676 | AM21: =I21 -> 676 | AQ21: =I21 -> 676 | AV21: =I21/13 -> 52 | BL21: =$I21*BL$2 -> 82.739583 | BM21: =$I21*BM$2 -> 82.739583 | BN21: =$I21*BN$2 -> 82.739583 | BO21: =$I21*BO$2 -> 82.739583 | BP21: =$I21*BP$2 -> 82.739583 | BQ21: =$I21*BQ$2 -> 82.739583 | BR21: =$I21*BR$2 -> 82.739583 | BS21: =$I21*BS$2 -> 82.739583 | BT21: =$I21*BT$2 -> 14.083333 | BV21: =BV20-BL21 -> 38713.076 | BW21: =BW20-BM21 -> 38713.076 | BX21: =BX20-BN21 -> 38713.076 | BY21: =BY20-BO21 -> 38713.076 | BZ21: =BZ20-BP21 -> 38713.076 | CA21: =CA20-BQ21 -> 38713.076 | CB21: =CB20-BR21 -> 38713.076 | CC21: =CC20-BS21 -> 38713.076 | CD21: =CD20-BT21 -> 6541.3958
A22: 45993 | B22: IMPORTADORA SUDAMERICANA & | C22: 阿根廷 | D22: 4500187691 | E22: LEGAJO 4610 | F22: 4500187691-30 | G22: 77685GQ7-S001 | H22: 混搭恐龙8pcs/GQ7/箱 | I22: 5000 | J22: 0 | K22: 8 | L22: =I22/K22 -> 625 | M22: 46132 | N22: 46128 | P22: pass | Q22: 4/29 截SI | R22: 翻单185782 | S22: 无 | T22: 12/15进口商贴纸+UPC贴纸 | X22: 日期码格式：ZURU INC(BVI) 标准格式 日期：按实际生产日期 Packaging Info: 77685GQ7： MA 3L EAN包装+进口商贴纸+UPC贴纸+箱唛 Remark: 请确保包装上的条形码是UPC，如果是babyUPC，需要用mother UPC 覆盖，如有不一致，请及时提出。谢谢! | Y22: Aimee Huang | Z22: 0.7932 | AA22: =Z22*I22 -> 3966 | AB22: 年存 | AC22: 5000 | AD22: =AC22-I22 -> 0 | AE22: OK | AF22: 系统出单 | AG22: 77685GQ7-S001 | AH22: 已入 | AI22: =I22 -> 5000 | AK22: =I22 -> 5000 | AN22: =I22 -> 5000 | AQ22: =I22 -> 5000 | BA22: =I22/8 -> 625 | BL22: =$I22*BL$2 -> 611.97917 | BM22: =$I22*BM$2 -> 611.97917 | BN22: =$I22*BN$2 -> 611.97917 | BO22: =$I22*BO$2 -> 611.97917 | BP22: =$I22*BP$2 -> 611.97917 | BQ22: =$I22*BQ$2 -> 611.97917 | BR22: =$I22*BR$2 -> 611.97917 | BS22: =$I22*BS$2 -> 611.97917 | BT22: =$I22*BT$2 -> 104.16667 | BV22: =BV21-BL22 -> 38101.096 | BW22: =BW21-BM22 -> 38101.096 | BX22: =BX21-BN22 -> 38101.096 | BY22: =BY21-BO22 -> 38101.096 | BZ22: =BZ21-BP22 -> 38101.096 | CA22: =CA21-BQ22 -> 38101.096 | CB22: =CB21-BR22 -> 38101.096 | CC22: =CC21-BS22 -> 38101.096 | CD22: =CD21-BT22 -> 6437.2292
A23: 46065 | B23: TJX COMPANIES, INC | C23: 美国 | D23: 4500193766 | E23: 272587 | F23: 4500193766-80 | G23: 77723-S001 | H23: 混搭恐龙2PK圆筒装 | I23: 4404 | J23: 0 | K23: 12 | L23: =I23/K23 -> 367 | M23: 46113 | N23: =M23-4 -> 46109 | P23: pass | Q23: 4/2 装柜 | R23: 46081 | S23: 无 | T23: 3/9价格贴纸+空白贴纸 | X23: 日期码格式：ZURU INC(BVI) 标准格式 日期：按实际生产日期 Packaging Info: MA UPC包装(优先1L)+价格贴纸，价格贴纸客供。2PK的球用无条码收缩膜或加空白贴纸覆盖原条码。 Remark: 1. 产品和包装上印刷tracking code信息，格式为ZURU常规格式。 2. ZURU QC验货。 3. 分5个DC出货，每款产品每个DC的箱唛资料不同，具体DC数量如下： item#77723: Marshalls PO#272592,SKU#913011 DC#881-216PCS, DC#884-156PCS, DC#886-228PCS, DC#887-192PCS, DC#888-204PCS | Y23: Emily Wu | Z23: 0.9082 | AA23: =Z23*I23 -> 3999.7128 | AC23: 4404 | AD23: =AC23-I23 -> 0 | AE23: OK | AF23: 系统出单 | AG23: 77723-S001-MTS | AH23: 已入 | AI23: =I23*2 -> 8808 | AK23: =I23*2 -> 8808 | AM23: =I23*2 -> 8808 | AQ23: =I23*2 -> 8808 | BH23: =I23 -> 4404 | BI23: =I23 -> 4404 | BL23: =$I23*BL$2*2 -> 1078.0625 | BM23: =$I23*BM$2*2 -> 1078.0625 | BN23: =$I23*BN$2*2 -> 1078.0625 | BO23: =$I23*BO$2*2 -> 1078.0625 | BP23: =$I23*BP$2*2 -> 1078.0625 | BQ23: =$I23*BQ$2*2 -> 1078.0625 | BR23: =$I23*BR$2*2 -> 1078.0625 | BS23: =$I23*BS$2*2 -> 1078.0625 | BT23: =$I23*BT$2*2 -> 183.5 | BV23: =BV22-BL23 -> 37023.034 | BW23: =BW22-BM23 -> 37023.034 | BX23: =BX22-BN23 -> 37023.034 | BY23: =BY22-BO23 -> 37023.034 | BZ23: =BZ22-BP23 -> 37023.034 | CA23: =CA22-BQ23 -> 37023.034 | CB23: =CB22-BR23 -> 37023.034 | CC23: =CC22-BS23 -> 37023.034 | CD23: =CD22-BT23 -> 6253.7292
A24: 46065 | B24: TJX COMPANIES, INC | C24: 美国 | D24: 4500193767 | E24: 272590 | F24: 4500193767-80 | G24: 77723-S001 | H24: 混搭恐龙2PK圆筒装 | I24: 4596 | J24: 0 | K24: 12 | L24: =I24/K24 -> 383 | M24: 46113 | N24: =M24-4 -> 46109 | P24: 自检 | Q24: 4/1装柜 | R24: 46081 | S24: 无 | T24: 3/9价格贴纸+空白贴纸 | X24: 日期码格式：ZURU INC(BVI) 标准格式 日期：按实际生产日期 Packaging Info: MA UPC包装(优先1L)+价格贴纸，价格贴纸客供。2PK的球用无条码收缩膜或加空白贴纸覆盖原条码。 Remark: 1. 产品和包装上印刷tracking code信息，格式为ZURU常规格式。 2. ZURU QC验货。 3. 分5个DC出货，每款产品每个DC的箱唛资料不同，具体DC数量如下： item#77723: Marshalls PO#272592,SKU#913011 DC#881-216PCS, DC#884-156PCS, DC#886-228PCS, DC#887-192PCS, DC#888-204PCS | Y24: Emily Wu | Z24: 0.9082 | AA24: =Z24*I24 -> 4174.0872 | AC24: 4596 | AD24: =AC24-I24 -> 0 | AE24: OK | AF24: 系统出单 | AG24: 77723-S001-MTS | AH24: 已入 | AI24: =I24*2 -> 9192 | AK24: =I24*2 -> 9192 | AM24: =I24*2 -> 9192 | AQ24: =I24*2 -> 9192 | BH24: =I24 -> 4596 | BI24: =I24 -> 4596 | BL24: =$I24*BL$2*2 -> 1125.0625 | BM24: =$I24*BM$2*2 -> 1125.0625 | BN24: =$I24*BN$2*2 -> 1125.0625 | BO24: =$I24*BO$2*2 -> 1125.0625 | BP24: =$I24*BP$2*2 -> 1125.0625 | BQ24: =$I24*BQ$2*2 -> 1125.0625 | BR24: =$I24*BR$2*2 -> 1125.0625 | BS24: =$I24*BS$2*2 -> 1125.0625 | BT24: =$I24*BT$2*2 -> 191.5 | BV24: =BV23-BL24 -> 35897.971 | BW24: =BW23-BM24 -> 35897.971 | BX24: =BX23-BN24 -> 35897.971 | BY24: =BY23-BO24 -> 35897.971 | BZ24: =BZ23-BP24 -> 35897.971 | CA24: =CA23-BQ24 -> 35897.971 | CB24: =CB23-BR24 -> 35897.971 | CC24: =CC23-BS24 -> 35897.971 | CD24: =CD23-BT24 -> 6062.2292
A25: 46065 | B25: TJX COMPANIES, INC | C25: 美国 | D25: 4500193770 | E25: 272592 | F25: 4500193770-40 | G25: 77723-S001 | H25: 混搭恐龙2PK圆筒装 | I25: 996 | J25: 0 | K25: 12 | L25: =I25/K25 -> 83 | M25: 46122 | N25: 46118 | P25: pass | Q25: 4/16 装柜 | R25: 46081 | S25: 无 | T25: 3/9价格贴纸+空白贴纸 | X25: 日期码格式：ZURU INC(BVI) 标准格式 日期：按实际生产日期 Packaging Info: MA UPC包装(优先1L)+价格贴纸，价格贴纸客供。2PK的球用无条码收缩膜或加空白贴纸覆盖原条码。 Remark: 1. 产品和包装上印刷tracking code信息，格式为ZURU常规格式。 2. ZURU QC验货。 3. 分5个DC出货，每款产品每个DC的箱唛资料不同，具体DC数量如下： item#77723: Marshalls PO#272592,SKU#913011 DC#881-216PCS, DC#884-156PCS, DC#886-228PCS, DC#887-192PCS, DC#888-204PCS | Y25: Emily Wu | Z25: 1.1176 | AA25: =Z25*I25 -> 1113.1296 | AC25: 996 | AD25: =AC25-I25 -> 0 | AE25: OK | AF25: 系统出单 | AG25: 77723-S001-MTS | AH25: 已入 | AI25: =I25*2 -> 1992 | AK25: =I25*2 -> 1992 | AM25: =I25*2 -> 1992 | AQ25: =I25*2 -> 1992 | BH25: =I25 -> 996 | BI25: =I25 -> 996 | BL25: =$I25*BL$2*2 -> 243.8125 | BM25: =$I25*BM$2*2 -> 243.8125 | BN25: =$I25*BN$2*2 -> 243.8125 | BO25: =$I25*BO$2*2 -> 243.8125 | BP25: =$I25*BP$2*2 -> 243.8125 | BQ25: =$I25*BQ$2*2 -> 243.8125 | BR25: =$I25*BR$2*2 -> 243.8125 | BS25: =$I25*BS$2*2 -> 243.8125 | BT25: =$I25*BT$2*2 -> 41.5 | BV25: =BV24-BL25 -> 35654.159 | BW25: =BW24-BM25 -> 35654.159 | BX25: =BX24-BN25 -> 35654.159 | BY25: =BY24-BO25 -> 35654.159 | BZ25: =BZ24-BP25 -> 35654.159 | CA25: =CA24-BQ25 -> 35654.159 | CB25: =CB24-BR25 -> 35654.159 | CC25: =CC24-BS25 -> 35654.159 | CD25: =CD24-BT25 -> 6020.7292
A26: 46065 | B26: TJX COMPANIES, INC | C26: 美国 | D26: 4500193771 | E26: 272596 | F26: 4500193771-40 | G26: 77723-S001 | H26: 混搭恐龙2PK圆筒装 | I26: 1200 | J26: 0 | K26: 12 | L26: =I26/K26 -> 100 | M26: 46122 | N26: 46118 | P26: pass | Q26: 4/17 截SI | R26: 46081 | S26: 无 | T26: 3/9价格贴纸+空白贴纸 | X26: 日期码格式：ZURU INC(BVI) 标准格式 日期：按实际生产日期 Packaging Info: MA UPC包装(优先1L)+价格贴纸，价格贴纸客供。2PK的球用无条码收缩膜或加空白贴纸覆盖原条码。 Remark: 1. 产品和包装上印刷tracking code信息，格式为ZURU常规格式。 2. ZURU QC验货。 3. 分5个DC出货，每款产品每个DC的箱唛资料不同，具体DC数量如下： item#77723: TJ MAXX PO#272596,SKU#192376 DC#891-252PCS, DC#894-204PCS, DC#896-168PCS, DC#897-336PCS, DC#898-240PCS | Y26: Emily Wu | Z26: 0.9147 | AA26: =Z26*I26 -> 1097.64 | AC26: 1200 | AD26: =AC26-I26 -> 0 | AE26: OK | AF26: 系统出单 | AG26: 77723-S001-MTS | AH26: 已入 | AI26: =I26*2 -> 2400 | AK26: =I26*2 -> 2400 | AM26: =I26*2 -> 2400 | AQ26: =I26*2 -> 2400 | BH26: =I26 -> 1200 | BI26: =I26 -> 1200 | BL26: =$I26*BL$2*2 -> 293.75 | BM26: =$I26*BM$2*2 -> 293.75 | BN26: =$I26*BN$2*2 -> 293.75 | BO26: =$I26*BO$2*2 -> 293.75 | BP26: =$I26*BP$2*2 -> 293.75 | BQ26: =$I26*BQ$2*2 -> 293.75 | BR26: =$I26*BR$2*2 -> 293.75 | BS26: =$I26*BS$2*2 -> 293.75 | BT26: =$I26*BT$2*2 -> 50 | BV26: =BV25-BL26 -> 35360.409 | BW26: =BW25-BM26 -> 35360.409 | BX26: =BX25-BN26 -> 35360.409 | BY26: =BY25-BO26 -> 35360.409 | BZ26: =BZ25-BP26 -> 35360.409 | CA26: =CA25-BQ26 -> 35360.409 | CB26: =CB25-BR26 -> 35360.409 | CC26: =CC25-BS26 -> 35360.409 | CD26: =CD25-BT26 -> 5970.7292
A27: 46065 | B27: MIGROS-GENOSSENSCHAFTS-BUND | C27: 瑞士 | D27: 4500193874 | E27: 21214261 | F27: 4500193874-10 | G27: 77685GQ1-S002 | H27: 混搭恐龙13pcs/GQ1/箱 | I27: 2405 | J27: 0 | K27: 13 | L27: =I27/K27 -> 185 | M27: 46125 | N27: 46121 | P27: 自检 | Q27: 4/13-17 截仓 | R27: 46078 | S27: 无 | T27: 德意警告语贴纸(翻单:4500185407) | U27: 已出 样板 | X27: 日期码格式：ZURU INC(BVI) 标准格式 日期：按实际生产日期 Packaging Info: 77685-S001: MA 3L EAN包装+德意警告语贴纸(翻单:4500185407)+MA B版 5L+23L警语收藏指南+MA B版5L Slime 袋+MA B版 多语说明书 Remark: "1. 价格贴纸要求为可移动贴纸（包装备注有则需要满足要求，没有则忽略） 2.一套大货样品/item，请多备料。 3.延期出货会有罚款，请务必按时完货。 4.客人要求飞机孔的尺寸为3.0-3.2 cm（包装备注有则需要满足要求，没有则忽略） 5.所有包装材料禁止使用PVC，需改用PET材料 6. 出口欧洲 微塑料需合规 7. 请确保产品不含任何俄罗斯生产，或从俄罗斯进口的钢铁材料 8.所有出往欧洲订单的电子产品需增加一张客版WEEE声明说明书，区分带电池(WEEE 带电池走货 通用30L 说明书)和不带电池版本(WEEE 不带电池走货 通用30L 说 明书) 9.所有出往GAS市场(德国/奥地利/瑞士)的电子产品身上需要加字唛，为ZURU FRANCE 地址，需跟包装上的地址一致 (如无电子产品，产品布标有此地址，或产品太 小无法增加可忽略此信息。如产品无法加字唛，需让对应跟单提供产品贴纸资料) 新地址：ZURU France 33 rue Paul Meurice 75020 Paris, France 旧地址：ZURU France 1/3, Rue d'Argenteuil 95210 SAINT-GRATIEN, FRANCE" | Y27: Winnie zhong | Z27: 0.7931 | AA27: =Z27*I27 -> 1907.4055 | AC27: =2379+26 -> 2405 | AD27: =AC27-I27 -> 0 | AE27: OK | AF27: 系统出单 | AG27: 77685GQ1-S002-3L | AH27: 已入 | AI27: =I27 -> 2405 | AK27: =I27 -> 2405 | AN27: =I27 -> 2405 | AQ27: =I27 -> 2405 | AW27: =I27/13 -> 185 | BL27: =$I27*BL$2 -> 294.36198 | BM27: =$I27*BM$2 -> 294.36198 | BN27: =$I27*BN$2 -> 294.36198 | BO27: =$I27*BO$2 -> 294.36198 | BP27: =$I27*BP$2 -> 294.36198 | BQ27: =$I27*BQ$2 -> 294.36198 | BR27: =$I27*BR$2 -> 294.36198 | BS27: =$I27*BS$2 -> 294.36198 | BT27: =$I27*BT$2 -> 50.104167 | BV27: =BV26-BL27 -> 35066.047 | BW27: =BW26-BM27 -> 35066.047 | BX27: =BX26-BN27 -> 35066.047 | BY27: =BY26-BO27 -> 35066.047 | BZ27: =BZ26-BP27 -> 35066.047 | CA27: =CA26-BQ27 -> 35066.047 | CB27: =CB26-BR27 -> 35066.047 | CC27: =CC26-BS27 -> 35066.047 | CD27: =CD26-BT27 -> 5920.625
A28: 46041 | B28: B&M FRANCE SAS | C28: 法国 | D28: 4500191695 | E28: 2026001079 | F28: 4500191695-10 | G28: 77685GQ2-S002 | H28: 混搭恐龙27pcs/GQ2/箱-干燥剂 | I28: 4590 | J28: 0 | K28: 27 | L28: =I28/K28 -> 170 | M28: 46129 | N28: 46125 | P28: pass | Q28: 4/22 截SI | R28: 46048 | S28: 无 | T28: 1/26客户货号贴纸 | U28: 已出 样板 | X28: 日期码格式：ZURU INC(BVI) 标准格式 日期：按实际生产日期 Packaging Info: MA3L EAN最新版收缩膜+1张客户货号贴纸(含法国回收标)+MA 23L最新版说明书+MA 3L最新版PDQ Remark: 1. 此票无需第三方验货，通过ZURU OQC验货即可； 2. 请多备料一套大货样； 3. 此票出法国，包装需含有法国回收logo，产品符合EU标准； 4. 此票全部用EAN条码 5. 所有出口法国的产品, 法规规定禁止在包装和公众用的印刷品中使用矿物油中含有的物质, 包装印刷油墨中含有的MOAH/MOSH的质量浓度不能超过1%, 否则出货 到法国被抽检出现问题, 供应商需要对此负责; | Y28: Ula Zhao | Z28: 0.7581 | AA28: =Z28*I28 -> 3479.679 | AC28: 4590 | AD28: =AC28-I28 -> 0 | AE28: OK | AF28: 系统出单 | AG28: 77685GQ2-S002-3L | AH28: 已入 | AI28: =I28 -> 4590 | AK28: =I28 -> 4590 | AN28: =I28 -> 4590 | AQ28: =I28 -> 4590 | AU28: =I28/27 -> 170 | BL28: =$I28*BL$2 -> 561.79687 | BM28: =$I28*BM$2 -> 561.79687 | BN28: =$I28*BN$2 -> 561.79687 | BO28: =$I28*BO$2 -> 561.79687 | BP28: =$I28*BP$2 -> 561.79687 | BQ28: =$I28*BQ$2 -> 561.79687 | BR28: =$I28*BR$2 -> 561.79687 | BS28: =$I28*BS$2 -> 561.79687 | BT28: =$I28*BT$2 -> 95.625 | BV28: =BV27-BL28 -> 34504.25 | BW28: =BW27-BM28 -> 34504.25 | BX28: =BX27-BN28 -> 34504.25 | BY28: =BY27-BO28 -> 34504.25 | BZ28: =BZ27-BP28 -> 34504.25 | CA28: =CA27-BQ28 -> 34504.25 | CB28: =CB27-BR28 -> 34504.25 | CC28: =CC27-BS28 -> 34504.25 | CD28: =CD27-BT28 -> 5825
A29: 46091 | B29: SIMBA TOYS VN | C29: 越南 | D29: 4500195981 | F29: 4500195981-10 | G29: 77685GQ2-S001 | H29: 混搭恐龙27pcs/GQ2*2/箱 | I29: 540 | J29: 0 | K29: 54 | L29: =I29/K29 -> 10 | M29: 46126 | N29: 46126 | P29: 自检 | Q29: 4/21 截SI | R29: 46094 | S29: 无 | T29: 3/30进口商贴纸 | X29: 日期码格式：ZURU INC(BVI) 标准格式 日期：按实际生产日期 Packaging Info: MA EAN 3L收缩膜 +1L PDQ,其他包材配件使用1L+1张进口商贴纸,待提供贴纸资料 Remark: | Y29: Emma Wu | Z29: 0.8296 | AA29: =Z29*I29 -> 447.984 | AC29: 540 | AD29: =AC29-I29 -> 0 | AE29: OK | AF29: 系统出单 | AG29: 77685GQ2-S001-3L | AH29: 已入 | AI29: =I29 -> 540 | AK29: =I29 -> 540 | AN29: =I29 -> 540 | AQ29: =I29 -> 540 | AS29: =I29/27 -> 20 | BL29: =$I29*BL$2 -> 66.09375 | BM29: =$I29*BM$2 -> 66.09375 | BN29: =$I29*BN$2 -> 66.09375 | BO29: =$I29*BO$2 -> 66.09375 | BP29: =$I29*BP$2 -> 66.09375 | BQ29: =$I29*BQ$2 -> 66.09375 | BR29: =$I29*BR$2 -> 66.09375 | BS29: =$I29*BS$2 -> 66.09375 | BT29: =$I29*BT$2 -> 11.25 | BV29: =BV28-BL29 -> 34438.156 | BW29: =BW28-BM29 -> 34438.156 | BX29: =BX28-BN29 -> 34438.156 | BY29: =BY28-BO29 -> 34438.156 | BZ29: =BZ28-BP29 -> 34438.156 | CA29: =CA28-BQ29 -> 34438.156 | CB29: =CB28-BR29 -> 34438.156 | CC29: =CC28-BS29 -> 34438.156 | CD29: =CD28-BT29 -> 5813.75
A30: 46087 | B30: TJX COMPANIES, INC | C30: 美国 | D30: 4500195559 | E30: 332427 | F30: 4500195559-20 | G30: 77723-S001 | H30: 混搭恐龙2PK圆筒装 | I30: 996 | J30: 0 | K30: 12 | L30: =I30/K30 -> 83 | M30: 46141 | N30: 46137 | P30: 自检 | Q30: 5/8 截SI | R30: 46090 | S30: 无 | T30: 3/18 价格贴纸+空白贴纸 | X30: 日期码格式：ZURU INC(BVI) 标准格式 日期：按实际生产日期 Packaging Info: MA UPC包装(优先1L)+价格贴纸，价格贴纸客供。2PK的球用无条码收缩膜或加空白贴纸覆盖原条码。 价格贴纸贴在产品正面无遮挡任何文字或图案的地方，优先正面右上角。如有疑问/位置不够，请找我们确认位置。之前确认过的款就无需再重复确认了。 Remark: 1. 产品和包装上印刷tracking code信息，格式为ZURU常规格式。 2. ZURU QC验货。 3. 分5个DC出货，每款产品每个DC的箱唛资料不同，具体DC数量如下： item#77723: Marshalls PO#332427,SKU#918882 DC#881-324PCS, DC#884-168PCS, DC#886-300PCS, DC#887-144PCS, DC#888-60PCS | Y30: Emily Wu | Z30: 1.1176 | AA30: =Z30*I30 -> 1113.1296 | AC30: 996 | AD30: =AC30-I30 -> 0 | AF30: 系统出单 | AG30: 77723-S001-MTS | AH30: 已入 | AI30: =I30*2 -> 1992 | AK30: =I30*2 -> 1992 | AM30: =I30*2 -> 1992 | AQ30: =I30*2 -> 1992 | BH30: =I30 -> 996 | BI30: =I30 -> 996 | BL30: =$I30*BL$2*2 -> 243.8125 | BM30: =$I30*BM$2*2 -> 243.8125 | BN30: =$I30*BN$2*2 -> 243.8125 | BO30: =$I30*BO$2*2 -> 243.8125 | BP30: =$I30*BP$2*2 -> 243.8125 | BQ30: =$I30*BQ$2*2 -> 243.8125 | BR30: =$I30*BR$2*2 -> 243.8125 | BS30: =$I30*BS$2*2 -> 243.8125 | BT30: =$I30*BT$2*2 -> 41.5 | BV30: =BV29-BL30 -> 34194.344 | BW30: =BW29-BM30 -> 34194.344 | BX30: =BX29-BN30 -> 34194.344 | BY30: =BY29-BO30 -> 34194.344 | BZ30: =BZ29-BP30 -> 34194.344 | CA30: =CA29-BQ30 -> 34194.344 | CB30: =CB29-BR30 -> 34194.344 | CC30: =CC29-BS30 -> 34194.344 | CD30: =CD29-BT30 -> 5772.25
A31: 46087 | B31: TJX COMPANIES, INC | C31: 美国 | D31: 4500195560 | E31: 332429 | F31: 4500195560-20 | G31: 77723-S001 | H31: 混搭恐龙2PK圆筒装 | I31: 1200 | J31: 0 | K31: 12 | L31: =I31/K31 -> 100 | M31: 46141 | N31: 46137 | P31: 自检 | Q31: 5/7 截SI | R31: 46090 | S31: 无 | T31: 3/9价格贴纸+空白贴纸 | X31: 日期码格式：ZURU INC(BVI) 标准格式 日期：按实际生产日期 Packaging Info: MA UPC包装(优先1L)+价格贴纸，价格贴纸客供。2PK的球用无条码收缩膜或加空白贴纸覆盖原条码。 价格贴纸贴在产品正面无遮挡任何文字或图案的地方，优先正面右上角。如有疑问/位置不够，请找我们确认位置。之前确认过的款就无需再重复确认了。 Remark: 1. 产品和包装上印刷tracking code信息，格式为ZURU常规格式。 2. ZURU QC验货。 3. 分5个DC出货，每款产品每个DC的箱唛资料不同，具体DC数量如下： item#77723: TJ MAXX PO#332429,SKU#197992 DC#891-252PCS, DC#894-204PCS, DC#896-180PCS, DC#897-372PCS, DC#898-192PCS | Y31: Emily Wu | Z31: 0.8908 | AA31: =Z31*I31 -> 1068.96 | AC31: 1200 | AD31: =AC31-I31 -> 0 | AE31: OK | AF31: 系统出单 | AG31: 77723-S001-MTS | AH31: 已入 | AI31: =I31*2 -> 2400 | AK31: =I31*2 -> 2400 | AM31: =I31*2 -> 2400 | AQ31: =I31*2 -> 2400 | BH31: =I31 -> 1200 | BI31: =I31 -> 1200 | BL31: =$I31*BL$2*2 -> 293.75 | BM31: =$I31*BM$2*2 -> 293.75 | BN31: =$I31*BN$2*2 -> 293.75 | BO31: =$I31*BO$2*2 -> 293.75 | BP31: =$I31*BP$2*2 -> 293.75 | BQ31: =$I31*BQ$2*2 -> 293.75 | BR31: =$I31*BR$2*2 -> 293.75 | BS31: =$I31*BS$2*2 -> 293.75 | BT31: =$I31*BT$2*2 -> 50 | BV31: =BV30-BL31 -> 33900.594 | BW31: =BW30-BM31 -> 33900.594 | BX31: =BX30-BN31 -> 33900.594 | BY31: =BY30-BO31 -> 33900.594 | BZ31: =BZ30-BP31 -> 33900.594 | CA31: =CA30-BQ31 -> 33900.594 | CB31: =CB30-BR31 -> 33900.594 | CC31: =CC30-BS31 -> 33900.594 | CD31: =CD30-BT31 -> 5722.25
A32: 46093 | B32: WONDERLAND TOYS, INC. | C32: 美国 | D32: 4500196264 | E32: 5167 | F32: 4500196264-50 | G32: 77685GQ2-S001 | H32: 混搭恐龙27pcs/GQ2*2/箱 | I32: 1026 | J32: 0 | K32: 54 | L32: =I32/K32 -> 19 | M32: 46142 | N32: 46139 | P32: 自检 | Q32: 5/12 截SI | R32: 46098 | S32: 无 | T32: 3/25 UPC贴纸 | X32: 日期码格式：ZURU INC(BVI) 标准格式 日期：按实际生产日期 Tracking Code: Packaging Info: 1. 出口美国，MA UPC 版本包装，优先1L。 6. 77685GQ2 UPC#193052079053. MA 3L 收缩 膜 + UPC贴纸 + MA 3L PDQ。 Remark: 8. ZURU QC 验货即可。 | Y32: Abby Mai,Lluvia Zeng | Z32: 0.4862 | AA32: =Z32*I32 -> 498.8412 | AC32: 1026 | AD32: =AC32-I32 -> 0 | AF32: 系统出单 | AG32: 77685GQ2-S001-3L | AH32: 已入 | AI32: =I32 -> 1026 | AK32: =I32 -> 1026 | AN32: =I32 -> 1026 | AQ32: =I32 -> 1026 | AU32: =I32/27 -> 38 | BL32: =$I32*BL$2 -> 125.57812 | BM32: =$I32*BM$2 -> 125.57812 | BN32: =$I32*BN$2 -> 125.57812 | BO32: =$I32*BO$2 -> 125.57812 | BP32: =$I32*BP$2 -> 125.57812 | BQ32: =$I32*BQ$2 -> 125.57812 | BR32: =$I32*BR$2 -> 125.57812 | BS32: =$I32*BS$2 -> 125.57812 | BT32: =$I32*BT$2 -> 21.375 | BV32: =BV31-BL32 -> 33775.016 | BW32: =BW31-BM32 -> 33775.016 | BX32: =BX31-BN32 -> 33775.016 | BY32: =BY31-BO32 -> 33775.016 | BZ32: =BZ31-BP32 -> 33775.016 | CA32: =CA31-BQ32 -> 33775.016 | CB32: =CB31-BR32 -> 33775.016 | CC32: =CC31-BS32 -> 33775.016 | CD32: =CD31-BT32 -> 5700.875
A33: 46105 | B33: PLANET OF TOYS LTD | C33: 吉尔吉吉斯坦 | D33: 4500198237 | F33: 4500198237-50 | G33: 77685GQ1-S001 | H33: 混搭恐龙13pcs/GQ1*4/箱 | I33: 208 | J33: 0 | K33: 52 | L33: =I33/K33 -> 4 | M33: 46148 | N33: 46146 | P33: 自检 | Q33: 待SO 出货 | R33: 46106 | S33: 无 | T33: 3/25通用贴纸 | X33: 日期码格式：ZURU INC(BVI) 标准格式 日期：按实际生产日期 Packaging Info: 1L MA UPC 包装 + 通用贴纸 ， MA 说明书/指南/PDQ （如有）； Remark: 标准配比； | Y33: Ann | Z33: 0.8099 | AA33: =Z33*I33 -> 168.4592 | AC33: 208 | AD33: =AC33-I33 -> 0 | AF33: 系统出单 | AG33: 77685GQ1-S001 | AH33: 已入 | AI33: =I33 -> 208 | AK33: =I33 -> 208 | AM33: =I33 -> 208 | AQ33: =I33 -> 208 | AV33: =I33/13 -> 16 | BL33: =$I33*BL$2 -> 25.458333 | BM33: =$I33*BM$2 -> 25.458333 | BN33: =$I33*BN$2 -> 25.458333 | BO33: =$I33*BO$2 -> 25.458333 | BP33: =$I33*BP$2 -> 25.458333 | BQ33: =$I33*BQ$2 -> 25.458333 | BR33: =$I33*BR$2 -> 25.458333 | BS33: =$I33*BS$2 -> 25.458333 | BT33: =$I33*BT$2 -> 4.3333333 | BV33: =BV32-BL33 -> 33749.557 | BW33: =BW32-BM33 -> 33749.557 | BX33: =BX32-BN33 -> 33749.557 | BY33: =BY32-BO33 -> 33749.557 | BZ33: =BZ32-BP33 -> 33749.557 | CA33: =CA32-BQ33 -> 33749.557 | CB33: =CB32-BR33 -> 33749.557 | CC33: =CC32-BS33 -> 33749.557 | CD33: =CD32-BT33 -> 5696.5417
A34: 46092 | B34: SIGNATURE MARKETING N.Z LIMITED | C34: 新西兰 | D34: 4500196294 | E34: SMNZZU2602 | F34: 4500196294-10 | G34: 77685GQ1-S001 | H34: 混搭恐龙13pcs/GQ1*4/箱 | I34: 1196 | J34: 0 | K34: 52 | L34: =I34/K34 -> 23 | M34: 46156 | N34: 46153 | P34: 自检 | Q34: 5/18 截SO | R34: 46106 | S34: 无 | T34: 无 | X34: 日期码格式：ZURU INC(BVI) 标准格式 日期：按实际生产日期 Packaging Info: 􏁬 MA UPC 英语包装（优先1L英语版本，或者3L/5L含英语都可） Remark: Rare ratio:1/48 | Y34: Ivy Li | Z34: 0.8233 | AA34: =Z34*I34 -> 984.6668 | AC34: 1196 | AD34: =AC34-I34 -> 0 | AF34: 系统出单 | AG34: 77685GQ1-S001 | AH34: 已入 | AI34: =I34 -> 1196 | AK34: =I34 -> 1196 | AM34: =I34 -> 1196 | AQ34: =I34 -> 1196 | AV34: =I34/13 -> 92 | BL34: =$I34*BL$2 -> 146.38542 | BM34: =$I34*BM$2 -> 146.38542 | BN34: =$I34*BN$2 -> 146.38542 | BO34: =$I34*BO$2 -> 146.38542 | BP34: =$I34*BP$2 -> 146.38542 | BQ34: =$I34*BQ$2 -> 146.38542 | BR34: =$I34*BR$2 -> 146.38542 | BS34: =$I34*BS$2 -> 146.38542 | BT34: =$I34*BT$2 -> 24.916667 | BV34: =BV33-BL34 -> 33603.172 | BW34: =BW33-BM34 -> 33603.172 | BX34: =BX33-BN34 -> 33603.172 | BY34: =BY33-BO34 -> 33603.172 | BZ34: =BZ33-BP34 -> 33603.172 | CA34: =CA33-BQ34 -> 33603.172 | CB34: =CB33-BR34 -> 33603.172 | CC34: =CC33-BS34 -> 33603.172 | CD34: =CD33-BT34 -> 5671.625
A35: 46108 | B35: SARL SOREDIM | C35: 法国 | D35: 4500198533 | E35: 2026-027 | F35: 4500198533-10 | G35: 77685GQ1-S001 | H35: 混搭恐龙13pcs/GQ1*4/箱 | I35: 520 | J35: 0 | K35: 52 | L35: =I35/K35 -> 10 | M35: 46162 | N35: 46158 | P35: 自检 | R35: 46108 | S35: 无 | T35: 4/13 sorting logo贴纸 | X35: 日期码格式：ZURU INC(BVI) 标准格式 日期：按实际生产日期 Packaging Info: 77685GQ1：MA3L EAN收缩膜+1张法国sorting logo贴纸+MA B版收藏指南+MA3L PDQ 77711GQ1：MA3L EAN收缩膜+1张法国sorting logo贴纸+MA5L收藏指南/说明书+MA23L说明书+MA3L PDQ 9565GQ1：MA3L EAN收缩膜+MA6L收藏指南+WEEE 29L C版说明书_不带电池走货版本+MA3LPDQ Remark: 1. 此票无需第三方验货，通过ZURU OQC验货即可； 2. 此票出法国，包装需含有两个法国回收logo，产品符合EU标准； 3. 此票全部用EAN条码, assortment产品需用mother EAN条码 | Y35: Ula Zhao | Z35: 0.8099 | AA35: =Z35*I35 -> 421.148 | AC35: 520 | AD35: =AC35-I35 -> 0 | AE35: OK | AF35: 系统出单 | AG35: 77685GQ1-S001-3L | AH35: 已入 | AI35: =I35 -> 520 | AK35: =I35 -> 520 | AN35: =I35 -> 520 | AQ35: =I35 -> 520 | AW35: =I35/13 -> 40 | BL35: =$I35*BL$2 -> 63.645833 | BM35: =$I35*BM$2 -> 63.645833 | BN35: =$I35*BN$2 -> 63.645833 | BO35: =$I35*BO$2 -> 63.645833 | BP35: =$I35*BP$2 -> 63.645833 | BQ35: =$I35*BQ$2 -> 63.645833 | BR35: =$I35*BR$2 -> 63.645833 | BS35: =$I35*BS$2 -> 63.645833 | BT35: =$I35*BT$2 -> 10.833333 | BV35: =BV34-BL35 -> 33539.526 | BW35: =BW34-BM35 -> 33539.526 | BX35: =BX34-BN35 -> 33539.526 | BY35: =BY34-BO35 -> 33539.526 | BZ35: =BZ34-BP35 -> 33539.526 | CA35: =CA34-BQ35 -> 33539.526 | CB35: =CB34-BR35 -> 33539.526 | CC35: =CC34-BS35 -> 33539.526 | CD35: =CD34-BT35 -> 5660.7917
A36: 46119 | B36: TJX COMPANIES, INC | C36: 美国 | D36: 4500200298 | E36: 130350 | F36: 4500200298-20 | G36: 77723-S001 | H36: 混搭恐龙2PK圆筒装 | I36: 996 | J36: 0 | K36: 12 | L36: =I36/K36 -> 83 | M36: 46167 | N36: 46165 | P36: 自检 | Q36: 5/28 截IS | R36: 46121 | S36: 无 | T36: 4/20 价格贴纸+空白贴纸 | X36: 日期码格式：ZURU INC(BVI) 标准格式 日期：按实际生产日期 Packaging Info: MA UPC包装(优先1L)+价格贴纸，价格贴纸客供。2PK的球用无条码收缩膜或加空白贴纸覆盖原条码。 价格贴纸贴在产品正面无遮挡任何文字或图案的地方，优先正面右上角。如有疑问/位置不够，请找我们确认位置。之前确认过的款就无需再重复确认了。 Remark: 1. 产品和包装上印刷tracking code信息，格式为ZURU常规格式。 2. ZURU QC验货。 3. 分3-4个DC出货，每款产品每个DC的箱唛资料不同，具体DC数量如下： item#9298: Marshalls PO#130350,SKU#925696 DC#881-336PCS, DC#884-918PCS, DC#886-384PCS, DC#888-564PCS item#77723: Marshalls PO#130350,SKU#925714 DC#884-420PCS, DC#886-96PCS, DC#887-180PCS, DC#888-300PCS item#92104: Marshalls PO#130350,SKU#925744 DC#884-336PCS, DC#886-120PCS, DC#888-336PCS item#71137: Marshalls PO#130350,SKU#925749 DC#881-264PCS, DC#884-192PCS, DC#886-300PCS, DC#888-240PCS | Y36: Emily Wu | Z36: 1.1176 | AA36: =Z36*I36 -> 1113.1296 | AC36: 996 | AD36: =AC36-I36 -> 0 | AE36: OK | AF36: 系统出单 | AG36: 77723-S001-MTS | AH36: 已入 | AI36: =I36*2 -> 1992 | AK36: =I36*2 -> 1992 | AM36: =I36*2 -> 1992 | AQ36: =I36*2 -> 1992 | BH36: =I36 -> 996 | BI36: =I36 -> 996 | BL36: =$I36*BL$2*2 -> 243.8125 | BM36: =$I36*BM$2*2 -> 243.8125 | BN36: =$I36*BN$2*2 -> 243.8125 | BO36: =$I36*BO$2*2 -> 243.8125 | BP36: =$I36*BP$2*2 -> 243.8125 | BQ36: =$I36*BQ$2*2 -> 243.8125 | BR36: =$I36*BR$2*2 -> 243.8125 | BS36: =$I36*BS$2*2 -> 243.8125 | BT36: =$I36*BT$2*2 -> 41.5 | BV36: =BV35-BL36 -> 33295.714 | BW36: =BW35-BM36 -> 33295.714 | BX36: =BX35-BN36 -> 33295.714 | BY36: =BY35-BO36 -> 33295.714 | BZ36: =BZ35-BP36 -> 33295.714 | CA36: =CA35-BQ36 -> 33295.714 | CB36: =CB35-BR36 -> 33295.714 | CC36: =CC35-BS36 -> 33295.714 | CD36: =CD35-BT36 -> 5619.2917
