Workbook
Name _CER10: #REF!
Name _CER10: #REF!
Name _CER10: #REF!

Sheet 名称
A1: 货号 | B1: 名称 | C1: 装箱数 | D1: 彩盒UPC条码
A2: T01535 | B2: 恐龙公园 | C2: 12
A3: JW-RV-RPGE | B3: 恐龙游戏盘 | C3: 6
A4: T01453 | B4: 恐龙游戏盘 | C4: 2
A5: T01685 | B5: 手术游戏盘 | C5: 6
A6: T01685-S | B6: 手术游戏盘 | C6: 6
A7: JW-RV-RPGE-3PK | B7: 恐龙游戏盘 | C7: 3
A8: JW-RV-RPGEA | B8: 恐龙游戏盘(邮包盒装) | C8: 6
A9: T01453 | B9: 恐龙游戏盘 | C9: 2
A10: T01685 | B10: 手术游戏盘 | C10: 6
A11: T02444 | B11: 恐龙公园二代 | C11: 12
A12: T02943 | B12: 9.5寸粉红熊公仔（移印） | C12: 2
A13: T02943-2 | B13: 9.5寸粉红熊公仔（移印） | C13: 2
... A29: T03942-DS | B29: 恐龙公园二代--实验室 | C29: 12

Sheet 总接单
A1: 接单期 | B1: 国家 | C1: 客户 | D1: Customer | E1: PO号 | F1: 货号 | G1: 数量 | H1: 出货日期 | I1: JW-RV-RPGE | J1: JW-RV-RPGEA | K1: T01453 | L1: T01535 | M1: T02444 | N1: T03804 | O1: T01685-S | P1: T01685A | Q1: T02428 | V1: T02945-2 | X1: T02943-2 | Y1: T03190 | Z1: T03191 | AA1: T03192 | AB1: T03900-9.5寸漫画系列 | AF1: T03349-3寸可爱系列 | AM1: T03980 | AO1: T03937-DS | AP1: T03938-DS | AQ1: T03939-DS | AR1: T03940-DS | AS1: T03941-DS | AT1: T03942-DS | AX1: 单价USD$ | AY1: 金额USD$ | AZ1: 金额HK$ | BA1: 国家 | BB1: =C1 -> 客户
I2: 恐龙游戏盘 | J2: 恐龙游戏盘 | K2: 恐龙游戏盘 | L2: 恐龙公园 | M2: 恐龙公园S2 | N2: 恐龙公园S2 | O2: 手术游戏盘 | Q2: 涂鸦公仔 | R2: 格力奇公仔 | S2: 绿色油淋公仔 | T2: 粉红熊公仔 | U2: 涂鸦公仔（移印办） | V2: 格力奇公仔（移印办） | W2: 绿色油淋公仔（移印办） | X2: 粉红熊公仔（移印办） | Y2: 弗莱尔 | Z2: 前锋 | AA2: 大心脏 | AB2: 漫画熊 | AC2: 战士熊 | AD2: 小女孩 | AE2: 大眼睛 | AF2: 寿司狗 | AG2: 柯基 | AH2: 爱心柴犬 | AI2: 爱心猫 | AJ2: 仙人掌 | AK2: 鸡尾酒 | AL2: 可爱熊猫 | AM2: 9.5寸绿色淋油公仔 | AN2: 9.5寸涂鸦公仔 | AO2: 一代陆地 | AP2: 一代海洋 | AQ2: 一代天空 | AR2: 二代海滩 | AS2: 二代雨林 | AT2: 二代实验室
A3: 45967 | B3: 越南 | C3: Viet Tinh Anh Joint Stock Company | D3: Viet-TM110225 | E3: PO211348 | F3: T02444 | G3: 1680 | H3: 46021 | M3: =G3 -> 1680 | AX3: 2.1 | AY3: =SUM(I3:AW3)*AX3 -> 3528 | AZ3: =AY3*7.75 -> 27342 | BA3: =B3 -> 越南 | BB3: =C3 -> Viet Tinh Anh Joint Stock Company
A4: 45981 | B4: 乌克兰 | C4: AMIGO & F Ltd | D4: Kuma Paw 0126 | E4: PO211615 | F4: T02943-2 | G4: 800 | H4: 46047 | X4: =G4 -> 800 | AX4: 6.2 | AY4: =SUM(I4:AW4)*AX4 -> 4960 | AZ4: =AY4*7.75 -> 38440 | BA4: =B4 -> 乌克兰 | BB4: =C4 -> AMIGO & F Ltd
A5: 45981 | B5: 乌克兰 | C5: AMIGO & F Ltd | D5: Kuma Paw 0126 | E5: PO211615 | F5: T02945-2 | G5: 800 | H5: 46047 | V5: =G5 -> 800 | AX5: 6.5 | AY5: =SUM(I5:AW5)*AX5 -> 5200 | AZ5: =AY5*7.75 -> 40300 | BA5: =B5 -> 乌克兰 | BB5: =C5 -> AMIGO & F Ltd
A6: 45986 | B6: 美国 | C6: Monster Group LLC | D6: WM Domestic Order | E6: PO211734 | F6: T02943-2 | G6: 2304 | H6: 46047 | X6: =G6 -> 2304 | AX6: 6.2 | AY6: =SUM(I6:AW6)*AX6 -> 14284.8 | AZ6: =AY6*7.75 -> 110707.2 | BA6: =B6 -> 美国 | BB6: =C6 -> Monster Group LLC
A7: 45986 | B7: 美国 | C7: Monster Group LLC | D7: WM Domestic Order | E7: PO211734 | F7: T02945-2 | G7: 2304 | H7: 46047 | V7: =G7 -> 2304 | AX7: 6.5 | AY7: =SUM(I7:AW7)*AX7 -> 14976 | AZ7: =AY7*7.75 -> 116064 | BA7: =B7 -> 美国 | BB7: =C7 -> Monster Group LLC
A8: 45986 | B8: 美国 | C8: Monster Group LLC | D8: WM Domestic Order | E8: PO212369 | F8: T02943-2 | G8: 2500 | H8: 46086 | X8: =G8 -> 2500 | AX8: 6.2 | AY8: =SUM(I8:AW8)*AX8 -> 15500 | AZ8: =AY8*7.75 -> 120125 | BA8: =B8 -> 美国 | BB8: =C8 -> Monster Group LLC
A9: 45986 | B9: 美国 | C9: Monster Group LLC | D9: WM Domestic Order | E9: PO212369 | F9: T02945-2 | G9: 2500 | H9: 46086 | V9: =G9 -> 2500 | AX9: 6.5 | AY9: =SUM(I9:AW9)*AX9 -> 16250 | AZ9: =AY9*7.75 -> 125937.5 | BA9: =B9 -> 美国 | BB9: =C9 -> Monster Group LLC
A10: 45989 | B10: 澳大利亚 | C10: Woolworths Group Limited t/a Big W | D10: 47895690 | E10: PO211747 | F10: JW-RV-RPGE | G10: 1014 | H10: 46040 | I10: =G10 -> 1014 | AX10: 4.5 | AY10: =SUM(I10:AW10)*AX10 -> 4563 | AZ10: =AY10*7.75 -> 35363.25 | BA10: =B10 -> 澳大利亚 | BB10: =C10 -> Woolworths Group Limited t/a Big W
A11: 45989 | B11: 澳大利亚 | C11: Woolworths Group Limited t/a Big W | D11: 47896520 | E11: PO211748 | F11: JW-RV-RPGE | G11: 624 | H11: 46040 | I11: =G11 -> 624 | AX11: 4.5 | AY11: =SUM(I11:AW11)*AX11 -> 2808 | AZ11: =AY11*7.75 -> 21762 | BA11: =B11 -> 澳大利亚 | BB11: =C11 -> Woolworths Group Limited t/a Big W
A12: 45993 | B12: 新加坡 | C12: Sheng Tai Toys Pty Ltd | D12: Shengtai-TM110464 | E12: PO211605 | F12: T02444 | G12: 1200 | H12: 46083 | M12: =G12 -> 1200 | AX12: 2.1 | AY12: =SUM(I12:AW12)*AX12 -> 2520 | AZ12: =AY12*7.75 -> 19530 | BA12: =B12 -> 新加坡 | BB12: =C12 -> Sheng Tai Toys Pty Ltd
A13: 45996 | B13: 香港 | C13: Asia Goal Limited | D13: PO-AG250344 | E13: PO211794 | F13: T02444 | G13: 720 | H13: 46037 | M13: =G13 -> 720 | AX13: 2.1 | AY13: =SUM(I13:AW13)*AX13 -> 1512 | AZ13: =AY13*7.75 -> 11718 | BA13: =B13 -> 香港 | BB13: =C13 -> Asia Goal Limited
A14: 46010 | B14: 美国 | C14: Monster Group LLC | D14: WM Domestic Order | E14: PO212104 | F14: T03190 | G14: 4676 | H14: 46058 | Y14: =G14 -> 4676 | AX14: 6.15 | AY14: =SUM(I14:AW14)*AX14 -> 28757.4 | AZ14: =AY14*7.75 -> 222869.85 | BA14: =B14 -> 美国 | BB14: =C14 -> Monster Group LLC
A15: 46010 | B15: 美国 | C15: Monster Group LLC | D15: WM Domestic Order | E15: PO212104 | F15: T03191 | G15: 4376 | H15: 46058 | Z15: =G15 -> 4376 | AX15: 6.47 | AY15: =SUM(I15:AW15)*AX15 -> 28312.72 | AZ15: =AY15*7.75 -> 219423.58 | BA15: =B15 -> 美国 | BB15: =C15 -> Monster Group LLC
A16: 46010 | B16: 美国 | C16: Monster Group LLC | D16: WM Domestic Order | E16: PO212104 | F16: T03192 | G16: 4476 | H16: 46058 | AA16: =G16 -> 4476 | AX16: 5.59 | AY16: =SUM(I16:AW16)*AX16 -> 25020.84 | AZ16: =AY16*7.75 -> 193911.51 | BA16: =B16 -> 美国 | BB16: =C16 -> Monster Group LLC
A17: 46010 | B17: 澳大利亚 | C17: Woolworths Group Limited t/a Big W | D17: 47905042 | E17: PO212018 | F17: JW-RV-RPGE | G17: 1200 | H17: 46048 | I17: =G17 -> 1200 | AX17: 4.5 | AY17: =SUM(I17:AW17)*AX17 -> 5400 | AZ17: =AY17*7.75 -> 41850 | BA17: =B17 -> 澳大利亚 | BB17: =C17 -> Woolworths Group Limited t/a Big W
A18: 46030 | B18: 中国台湾 | C18: Asia Goal Limited | D18: PO-AG250418 | E18: PO212218 | F18: T02444 | G18: 780 | H18: 46101 | M18: =G18 -> 780 | AX18: 2.1 | AY18: =SUM(I18:AW18)*AX18 -> 1638 | AZ18: =AY18*7.75 -> 12694.5 | BA18: =B18 -> 中国台湾 | BB18: =C18 -> Asia Goal Limited
A19: 46030 | B19: 中国台湾 | C19: Asia Goal Limited | D19: PO-AG250418 | E19: PO212218 | F19: JW-RV-RPGE | G19: 180 | H19: 46101 | I19: =G19 -> 180 | AX19: 4.5 | AY19: =SUM(I19:AW19)*AX19 -> 810 | AZ19: =AY19*7.75 -> 6277.5 | BA19: =B19 -> 中国台湾 | BB19: =C19 -> Asia Goal Limited
A20: 46030 | B20: 中国台湾 | C20: Asia Goal Limited | D20: PO-AG250418 | E20: PO212218 | F20: T01685 | G20: 180 | H20: 46101 | O20: =G20 -> 180 | AM20: =AC20 -> 0 | AO20: =Z20 -> 0 | AP20: =AA20 -> 0 | AQ20: =AB20 -> 0 | AR20: =AC20 -> 0 | AS20: =AD20 -> 0 | AT20: =AE20 -> 0 | AX20: 4.43 | AY20: =SUM(I20:AW20)*AX20 -> 797.4 | AZ20: =AY20*7.75 -> 6179.85 | BA20: =B20 -> 中国台湾 | BB20: =C20 -> Asia Goal Limited
A21: 46038 | B21: 美国 | C21: Meijer LANSING | D21: 218955615 | E21: PO212267 | F21: T01453 | G21: 1000 | H21: 46092 | K21: =G21 -> 1000 | AX21: 4.5 | AY21: =SUM(I21:AW21)*AX21 -> 4500 | AZ21: =AY21*7.75 -> 34875 | BA21: =B21 -> 美国 | BB21: =C21 -> Meijer LANSING
A22: 46038 | B22: 美国 | C22: Meijer LANSING | D22: 218955627 | E22: PO212268 | F22: T01453 | G22: 500 | H22: 46092 | K22: =G22 -> 500 | AX22: 4.5 | AY22: =SUM(I22:AW22)*AX22 -> 2250 | AZ22: =AY22*7.75 -> 17437.5 | BA22: =B22 -> 美国 | BB22: =C22 -> Meijer LANSING
A23: 46049 | B23: 澳大利亚 | C23: Woolworths Group Limited t/a Big W | D23: 47908798 | E23: PO212336 | F23: JW-RV-RPGE | G23: 1200 | H23: 46100 | I23: 1200 | AX23: 4.5 | AY23: =SUM(I23:AW23)*AX23 -> 5400 | AZ23: =AY23*7.75 -> 41850 | BA23: =B23 -> 澳大利亚 | BB23: =C23 -> Woolworths Group Limited t/a Big W
A24: 46051 | B24: 美国 | C24: Meijer LANSING | D24: 219021251 | E24: PO212355 | F24: T01453 | G24: 1000 | H24: 46106 | K24: 1000 | AX24: 4.5 | AY24: =SUM(I24:AW24)*AX24 -> 4500 | AZ24: =AY24*7.75 -> 34875 | BA24: =B24 -> 美国 | BB24: =C24 -> Meijer LANSING
A25: 46051 | B25: 美国 | C25: Meijer LANSING | D25: 219021257 | E25: PO212356 | F25: T01453 | G25: 500 | H25: 46106 | K25: 500 | AX25: 4.5 | AY25: =SUM(I25:AW25)*AX25 -> 2250 | AZ25: =AY25*7.75 -> 17437.5 | BA25: =B25 -> 美国 | BB25: =C25 -> Meijer LANSING
A26: 46062 | B26: 英国 | C26: Smyths Toys HQ UC | D26: 4400542038 | E26: PO212408 | F26: JW-RV-RPGE | G26: 6306 | H26: 46111 | I26: 6306 | AX26: 4.5 | AY26: =SUM(I26:AW26)*AX26 -> 28377 | AZ26: =AY26*7.75 -> 219921.75 | BA26: =B26 -> 英国 | BB26: =C26 -> Smyths Toys HQ UC
A27: 46077 | B27: 美国 | C27: Monster Group LLC | D27: Kuma Paw 9.5 inch for WM Domestic Order | E27: PO212438 | F27: T03204 | G27: 5400 | H27: 46141 | V27: =G27/2 -> 2700 | X27: =G27/2 -> 2700 | AX27: 6.67 | AY27: =SUM(I27:AW27)*AX27 -> 36018 | AZ27: =AY27*7.75 -> 279139.5 | BA27: =B27 -> 美国 | BB27: =C27 -> Monster Group LLC
A28: 46083 | B28: 新西兰 | C28: Kmart Australia & NZ Holding Limited | D28: 21559600 | E28: PO212479 | F28: T02444 | G28: 564 | H28: 46122 | M28: =G28 -> 564 | AX28: 2.1 | AY28: =SUM(I28:AW28)*AX28 -> 1184.4 | AZ28: =AY28*7.75 -> 9179.1 | BA28: =B28 -> 新西兰 | BB28: =C28 -> Kmart Australia & NZ Holding Limited
A29: 46083 | B29: 澳大利亚 | C29: Kmart Australia & NZ Holding Limited | D29: 21559598 | E29: PO212478 | F29: T02444 | G29: 6156 | H29: 46122 | M29: =G29 -> 6156 | AX29: 2.1 | AY29: =SUM(I29:AW29)*AX29 -> 12927.6 | AZ29: =AY29*7.75 -> 100188.9 | BA29: =B29 -> 澳大利亚 | BB29: =C29 -> Kmart Australia & NZ Holding Limited
A30: 46086 | B30: 美国 | C30: Flybar Inc | D30: FB-7504 | E30: PO212516 | F30: JW-RV-RPGEA | G30: 504 | H30: 46127 | K30: 504 | AX30: 4.9 | AY30: =SUM(I30:AW30)*AX30 -> 2469.6 | AZ30: =AY30*7.75 -> 19139.4 | BA30: =B30 -> 美国 | BB30: =C30 -> Flybar Inc
A31: 46102 | B31: 加拿大 | C31: Lachine | D31: 004980 | E31: PO212541 | F31: T03804 | G31: 2964 | H31: 46157 | N31: =G31 -> 2964 | AX31: 2.1 | AY31: =SUM(I31:AW31)*AX31 -> 6224.4 | AZ31: =AY31*7.75 -> 48239.1 | BA31: =B31 -> 加拿大 | BB31: =C31 -> Lachine
A32: 46101 | B32: 澳大利亚 | C32: Kmart Australia & NZ Holding Limited | D32: 21657135 | E32: PO212624 | F32: T02444 | G32: 6288 | H32: 46135 | M32: =G32 -> 6288 | AX32: 2.1 | AY32: =SUM(I32:AW32)*AX32 -> 13204.8 | AZ32: =AY32*7.75 -> 102337.2 | BA32: =B32 -> 澳大利亚 | BB32: =C32 -> Kmart Australia & NZ Holding Limited
A33: 46101 | B33: 澳大利亚 | C33: Kmart Australia & NZ Holding Limited | D33: 21602319 | E33: PO212625 | F33: T02444 | G33: 432 | H33: 46129 | M33: =G33 -> 432 | AX33: 2.1 | AY33: =SUM(I33:AW33)*AX33 -> 907.2 | AZ33: =AY33*7.75 -> 7030.8 | BA33: =B33 -> 澳大利亚 | BB33: =C33 -> Kmart Australia & NZ Holding Limited
A34: 46101 | B34: 澳大利亚 | C34: Target Australia Pty Ltd | D34: 2617376 | E34: PO212775 | F34: T02444 | G34: 1800 | H34: 46135 | M34: =G34 -> 1800 | AX34: 2.1 | AY34: =SUM(I34:AW34)*AX34 -> 3780 | AZ34: =AY34*7.75 -> 29295 | BA34: =B34 -> 澳大利亚 | BB34: =C34 -> Target Australia Pty Ltd
A35: 46101 | B35: 澳大利亚 | C35: Target Australia Pty Ltd | D35: 2617377 | E35: PO213307 | F35: T02444 | G35: 1800 | H35: 46176 | M35: =G35 -> 1800 | AX35: 2.1 | AY35: =SUM(I35:AW35)*AX35 -> 3780 | AZ35: =AY35*7.75 -> 29295 | BA35: =B35 -> 澳大利亚 | BB35: =C35 -> Target Australia Pty Ltd
A36: 46101 | B36: 澳大利亚 | C36: Target Australia Pty Ltd | D36: 2617378 | E36: PO213308 | F36: T02444 | G36: 1200 | H36: 46211 | M36: =G36 -> 1200 | AX36: 2.1 | AY36: =SUM(I36:AW36)*AX36 -> 2520 | AZ36: =AY36*7.75 -> 19530 | BA36: =B36 -> 澳大利亚 | BB36: =C36 -> Target Australia Pty Ltd
A37: 46101 | B37: 澳大利亚 | C37: Target Australia Pty Ltd | D37: 2617379 | E37: PO213309 | F37: T02444 | G37: 1500 | H37: 46245 | M37: =G37 -> 1500 | AX37: 2.1 | AY37: =SUM(I37:AW37)*AX37 -> 3150 | AZ37: =AY37*7.75 -> 24412.5 | BA37: =B37 -> 澳大利亚 | BB37: =C37 -> Target Australia Pty Ltd
A38: 46101 | B38: 澳大利亚 | C38: Target Australia Pty Ltd | D38: 2617380 | E38: PO213310 | F38: T02444 | G38: 1200 | H38: 46267 | M38: =G38 -> 1200 | AX38: 2.1 | AY38: =SUM(I38:AW38)*AX38 -> 2520 | AZ38: =AY38*7.75 -> 19530 | BA38: =B38 -> 澳大利亚 | BB38: =C38 -> Target Australia Pty Ltd
A39: 46114 | B39: 美国 | C39: Flybar Inc | D39: FB-7781 | E39: PO212868 | F39: JW-RV-RPGEA | G39: 1002 | H39: 46160 | J39: =G39 -> 1002 | AX39: 4.9 | AY39: =SUM(I39:AW39)*AX39 -> 4909.8 | AZ39: =AY39*7.75 -> 38050.95 | BA39: =B39 -> 美国 | BB39: =C39 -> Flybar Inc
A40: 46114 | B40: 美国 | C40: Flybar Inc | D40: FB-7782 | E40: PO212869 | F40: JW-RV-RPGEA | G40: 1002 | H40: 46160 | J40: =G40 -> 1002 | AX40: 4.9 | AY40: =SUM(I40:AW40)*AX40 -> 4909.8 | AZ40: =AY40*7.75 -> 38050.95 | BA40: =B40 -> 美国 | BB40: =C40 -> Flybar Inc
A41: 46114 | B41: 美国 | C41: Flybar Inc | D41: FB-7783 | E41: PO212870 | F41: JW-RV-RPGEA | G41: 1002 | H41: 46160 | J41: =G41 -> 1002 | AX41: 4.9 | AY41: =SUM(I41:AW41)*AX41 -> 4909.8 | AZ41: =AY41*7.75 -> 38050.95 | BA41: =B41 -> 美国 | BB41: =C41 -> Flybar Inc
A42: 46119 | B42: 加拿大 | C42: Canada Inc./dba Red Planet Group | D42: 005065 | E42: PO212771 | F42: JW-RV-RPGE | G42: 1800 | H42: 46164 | I42: =G42 -> 1800 | AX42: 4.5 | AY42: =SUM(I42:AW42)*AX42 -> 8100 | AZ42: =AY42*7.75 -> 62775 | BA42: =B42 -> 加拿大 | BB42: =C42 -> Canada Inc./dba Red Planet Group
A43: 46119 | B43: 澳大利亚 | C43: Woolworths Group Limited t/a Big W | D43: 47946690 | E43: PO212950 | F43: JW-RV-RPGE | G43: 1200 | H43: 46171 | I43: =G43 -> 1200 | AX43: 4.5 | AY43: =SUM(I43:AW43)*AX43 -> 5400 | AZ43: =AY43*7.75 -> 41850 | BA43: =B43 -> 澳大利亚 | BB43: =C43 -> Woolworths Group Limited t/a Big W
A44: 46121 | B44: 越南 | C44: Viet Tinh Anh Joint Stock Company | D44: Viet-TM111631 | E44: PO212874 | F44: T02444 | G44: 1656 | H44: 46175 | M44: =G44 -> 1656 | AX44: 2.1 | AY44: =SUM(I44:AW44)*AX44 -> 3477.6 | AZ44: =AY44*7.75 -> 26951.4 | BA44: =B44 -> 越南 | BB44: =C44 -> Viet Tinh Anh Joint Stock Company
A45: 46122 | B45: 新西兰 | C45: Kmart Australia & NZ Holding Limited | D45: 21688244 | E45: PO213046 | F45: T02444 | G45: 5496 | H45: 46170 | M45: =G45 -> 5496 | AX45: 2.1 | AY45: =SUM(I45:AW45)*AX45 -> 11541.6 | AZ45: =AY45*7.75 -> 89447.4 | BA45: =B45 -> 新西兰 | BB45: =C45 -> Kmart Australia & NZ Holding Limited
A46: 46122 | B46: 澳大利亚 | C46: Kmart Australia & NZ Holding Limited | D46: 21688246 | E46: PO213048 | F46: T02444 | G46: 1224 | H46: 46170 | M46: =G46 -> 1224 | AX46: 2.1 | AY46: =SUM(I46:AW46)*AX46 -> 2570.4 | AZ46: =AY46*7.75 -> 19920.6 | BA46: =B46 -> 澳大利亚 | BB46: =C46 -> Kmart Australia & NZ Holding Limited
A47: 46127 | B47: 澳大利亚 | C47: Kmart Australia & NZ Holding Limited | D47: 21700273 | E47: PO213168 | F47: T03900 | G47: 3600 | H47: 46188 | AB47: =G47/4 -> 900 | AC47: =G47/4 -> 900 | AD47: =G47/4 -> 900 | AE47: =G47/4 -> 900 | AX47: 6.35 | AY47: =SUM(I47:AW47)*AX47 -> 22860 | AZ47: =AY47*7.75 -> 177165 | BA47: =B47 -> 澳大利亚 | BB47: =C48 -> Kmart Australia & NZ Holding Limited
A48: 46127 | B48: 澳大利亚 | C48: Kmart Australia & NZ Holding Limited | D48: 21700273 | E48: PO213168 | F48: T03349 | G48: 7200 | H48: 46188 | AF48: =G48*11/72 -> 1100 | AG48: =G48*11/72 -> 1100 | AH48: =G48*11/72 -> 1100 | AI48: =G48*11/72 -> 1100 | AJ48: =G48*11/72 -> 1100 | AK48: =G48*11/72 -> 1100 | AL48: =G48*6/72 -> 600 | AX48: 1.95 | AY48: =SUM(I48:AW48)*AX48 -> 14040 | AZ48: =AY48*7.75 -> 108810 | BA48: =B48 -> 澳大利亚 | BB48: =C49 -> Kmart Australia & NZ Holding Limited
A49: 46127 | B49: 澳大利亚 | C49: Kmart Australia & NZ Holding Limited | D49: 21700276 | E49: PO213170 | F49: T03900 | G49: 400 | H49: 46188 | AB49: =G49/4 -> 100 | AC49: =G49/4 -> 100 | AD49: =G49/4 -> 100 | AE49: =G49/4 -> 100 | AX49: 6.35 | AY49: =SUM(I49:AW49)*AX49 -> 2540 | AZ49: =AY49*7.75 -> 19685 | BA49: =B49 -> 澳大利亚 | BB49: =C49 -> Kmart Australia & NZ Holding Limited
A50: 46127 | B50: 澳大利亚 | C50: Kmart Australia & NZ Holding Limited | D50: 21700276 | E50: PO213170 | F50: T03349 | G50: 792 | H50: 46188 | AF50: =G50*11/72 -> 121 | AG50: =G50*11/72 -> 121 | AH50: =G50*11/72 -> 121 | AI50: =G50*11/72 -> 121 | AJ50: =G50*11/72 -> 121 | AK50: =G50*11/72 -> 121 | AL50: =G50*6/72 -> 66 | AX50: 1.95 | AY50: =SUM(I50:AW50)*AX50 -> 1544.4 | AZ50: =AY50*7.75 -> 11969.1 | BA50: =B50 -> 澳大利亚 | BB50: =C50 -> Kmart Australia & NZ Holding Limited
A51: 46129 | B51: 澳大利亚 | C51: Kmart Australia & NZ Holding Limited | D51: 21711859 | E51: PO213271 | F51: T02444 | G51: 6720 | H51: 46175 | M51: =G51 -> 6720 | AX51: 2.1 | AY51: =SUM(I51:AW51)*AX51 -> 14112 | AZ51: =AY51*7.75 -> 109368 | BA51: =B51 -> 澳大利亚 | BB51: =C51 -> Kmart Australia & NZ Holding Limited
A52: 46134 | B52: 泰国 | C52: Kiddo Pacific Co. Ltd | D52: Kiddo-TM11353 | E52: PO212633 | F52: T02444 | G52: 1404 | H52: 46168 | M52: =G52 -> 1404 | AX52: 2.1 | AY52: =SUM(I52:AW52)*AX52 -> 2948.4 | AZ52: =AY52*7.75 -> 22850.1 | BA52: =B52 -> 泰国 | BB52: =C52 -> Kiddo Pacific Co. Ltd
A53: 46134 | B53: 韩国 | C53: BomNamu Co. Ltd | D53: BNM_TM260403 | E53: PO213297 | F53: T01535 | G53: 540 | H53: 46174 | L53: =G53 -> 540 | AX53: 2.1 | AY53: =SUM(I53:AW53)*AX53 -> 1134 | AZ53: =AY53*7.75 -> 8788.5 | BA53: =B53 -> 韩国 | BB53: =C53 -> BomNamu Co. Ltd
A54: 46154 | B54: 宁波 | C54: Aliss- Panama | D54: Aliss | E54: PO213496 | F54: T03900 | G54: 1440 | H54: 46191 | AB54: =G54/4 -> 360 | AC54: =G54/4 -> 360 | AD54: =G54/4 -> 360 | AE54: =G54/4 -> 360 | AX54: 6.35 | AY54: =SUM(I54:AW54)*AX54 -> 9144 | AZ54: =AY54*7.75 -> 70866 | BA54: =B54 -> 宁波 | BB54: =C54 -> Aliss- Panama
A55: 46154 | B55: 宁波 | C55: Aliss- Panama | D55: Aliss | E55: PO213496 | F55: T03349 | G55: 1392 | H55: 46191 | AF55: 212 | AG55: 212 | AH55: 213 | AI55: 213 | AJ55: 213 | AK55: 213 | AL55: 116 | AX55: 1.95 | AY55: =SUM(I55:AW55)*AX55 -> 2714.4 | AZ55: =AY55*7.75 -> 21036.6 | BA55: =B55 -> 宁波 | BB55: =C55 -> Aliss- Panama
A56: 46164 | B56: 美国 | C56: Monster Group LLC | D56: Kuma Paw T03980 WM Domestic | E56: PO213866 | F56: T03980 | G56: 2474 | H56: 46210 | AM56: =G56/2 -> 1237 | AN56: =G56/2 -> 1237 | AX56: 5.6 | AY56: =SUM(I56:AW56)*AX56 -> 13854.4 | AZ56: =AY56*7.75 -> 107371.6 | BA56: =B56 -> 美国 | BB56: =C56 -> Monster Group LLC
A57: 46164 | B57: 美国 | C57: Monster Group LLC | D57: Kuma Paw T03980 WM Domestic | E57: PO213866 | F57: T03980 | G57: =9568-2474 -> 7094 | H57: 46210 | AM57: =G57/2 -> 3547 | AN57: =G57/2 -> 3547 | AX57: 5.6 | AY57: =SUM(I57:AW57)*AX57 -> 39726.4 | AZ57: =AY57*7.75 -> 307879.6 | BA57: =B57 -> 美国 | BB57: =C57 -> Monster Group LLC
A58: 46167 | B58: 美国 | C58: Flybar Inc | D58: FB-7937 | E58: PO213850 | F58: T03937-DS | G58: 144 | H58: 46229 | AO58: =G58 -> 144 | AX58: 2.1 | AY58: =SUM(I58:AW58)*AX58 -> 302.4 | AZ58: =AY58*7.75 -> 2343.6 | BA58: =B58 -> 美国 | BB58: =C58 -> Flybar Inc
A59: 46167 | B59: 美国 | C59: Flybar Inc | D59: FB-7937 | E59: PO213850 | F59: T03938-DS | G59: 144 | H59: 46229 | AP59: =G59 -> 144 | AX59: 2.1 | AY59: =SUM(I59:AW59)*AX59 -> 302.4 | AZ59: =AY59*7.75 -> 2343.6 | BA59: =B59 -> 美国 | BB59: =C59 -> Flybar Inc
A60: 46167 | B60: 美国 | C60: Flybar Inc | D60: FB-7937 | E60: PO213850 | F60: T03939-DS | G60: 144 | H60: 46229 | AQ60: =G60 -> 144 | AX60: 2.1 | AY60: =SUM(I60:AW60)*AX60 -> 302.4 | AZ60: =AY60*7.75 -> 2343.6 | BA60: =B60 -> 美国 | BB60: =C60 -> Flybar Inc
A61: 46167 | B61: 美国 | C61: Flybar Inc | D61: FB-7937 | E61: PO213850 | F61: T03940-DS | G61: 144 | H61: 46229 | AR61: =G61 -> 144 | AX61: 2.1 | AY61: =SUM(I61:AW61)*AX61 -> 302.4 | AZ61: =AY61*7.75 -> 2343.6 | BA61: =B61 -> 美国 | BB61: =C61 -> Flybar Inc
A62: 46167 | B62: 美国 | C62: Flybar Inc | D62: FB-7937 | E62: PO213850 | F62: T03941-DS | G62: 144 | H62: 46229 | AS62: =G62 -> 144 | AX62: 2.1 | AY62: =SUM(I62:AW62)*AX62 -> 302.4 | AZ62: =AY62*7.75 -> 2343.6 | BA62: =B62 -> 美国 | BB62: =C62 -> Flybar Inc
A63: 46167 | B63: 美国 | C63: Flybar Inc | D63: FB-7937 | E63: PO213850 | F63: T03942-DS | G63: 144 | H63: 46229 | AT63: =G63 -> 144 | AX63: 2.1 | AY63: =SUM(I63:AW63)*AX63 -> 302.4 | AZ63: =AY63*7.75 -> 2343.6 | BA63: =B63 -> 美国 | BB63: =C63 -> Flybar Inc
A64: 46167 | B64: 美国 | C64: Flybar Inc | D64: FB-7937 | E64: PO213850 | F64: T03937-DS | G64: =408-144 -> 264 | H64: 46229 | AO64: =G64 -> 264 | AX64: 2.1 | AY64: =SUM(I64:AW64)*AX64 -> 554.4 | AZ64: =AY64*7.75 -> 4296.6 | BA64: =B64 -> 美国 | BB64: =C64 -> Flybar Inc
A65: 46167 | B65: 美国 | C65: Flybar Inc | D65: FB-7937 | E65: PO213850 | F65: T03938-DS | G65: =408-144 -> 264 | H65: 46229 | AP65: =G65 -> 264 | AX65: 2.1 | AY65: =SUM(I65:AW65)*AX65 -> 554.4 | AZ65: =AY65*7.75 -> 4296.6 | BA65: =B65 -> 美国 | BB65: =C65 -> Flybar Inc
A66: 46167 | B66: 美国 | C66: Flybar Inc | D66: FB-7937 | E66: PO213850 | F66: T03939-DS | G66: =408-144 -> 264 | H66: 46229 | AQ66: =G66 -> 264 | AX66: 2.1 | AY66: =SUM(I66:AW66)*AX66 -> 554.4 | AZ66: =AY66*7.75 -> 4296.6 | BA66: =B66 -> 美国 | BB66: =C66 -> Flybar Inc
A67: 46167 | B67: 美国 | C67: Flybar Inc | D67: FB-7937 | E67: PO213850 | F67: T03940-DS | G67: =408-144 -> 264 | H67: 46229 | AR67: =G67 -> 264 | AX67: 2.1 | AY67: =SUM(I67:AW67)*AX67 -> 554.4 | AZ67: =AY67*7.75 -> 4296.6 | BA67: =B67 -> 美国 | BB67: =C67 -> Flybar Inc
A68: 46167 | B68: 美国 | C68: Flybar Inc | D68: FB-7937 | E68: PO213850 | F68: T03941-DS | G68: =408-144 -> 264 | H68: 46229 | AS68: =G68 -> 264 | AX68: 2.1 | AY68: =SUM(I68:AW68)*AX68 -> 554.4 | AZ68: =AY68*7.75 -> 4296.6 | BA68: =B68 -> 美国 | BB68: =C68 -> Flybar Inc
A69: 46167 | B69: 美国 | C69: Flybar Inc | D69: FB-7937 | E69: PO213850 | F69: T03942-DS | G69: =408-144 -> 264 | H69: 46229 | AT69: =G69 -> 264 | AX69: 2.1 | AY69: =SUM(I69:AW69)*AX69 -> 554.4 | AZ69: =AY69*7.75 -> 4296.6 | BA69: =B69 -> 美国 | BB69: =C69 -> Flybar Inc
A70: 46167 | B70: 美国 | C70: Flybar Inc | D70: FB-7938 | E70: PO213891 | F70: T03937-DS | G70: 600 | H70: 46261 | AO70: =G70 -> 600 | AX70: 2.1 | AY70: =SUM(I70:AW70)*AX70 -> 1260 | AZ70: =AY70*7.75 -> 9765 | BA70: =B70 -> 美国 | BB70: =C70 -> Flybar Inc
A71: 46167 | B71: 美国 | C71: Flybar Inc | D71: FB-7938 | E71: PO213891 | F71: T03938-DS | G71: 600 | H71: 46261 | AP71: =G71 -> 600 | AX71: 2.1 | AY71: =SUM(I71:AW71)*AX71 -> 1260 | AZ71: =AY71*7.75 -> 9765 | BA71: =B71 -> 美国 | BB71: =C71 -> Flybar Inc
A72: 46167 | B72: 美国 | C72: Flybar Inc | D72: FB-7938 | E72: PO213891 | F72: T03939-DS | G72: 600 | H72: 46261 | AQ72: =G72 -> 600 | AX72: 2.1 | AY72: =SUM(I72:AW72)*AX72 -> 1260 | AZ72: =AY72*7.75 -> 9765 | BA72: =B72 -> 美国 | BB72: =C72 -> Flybar Inc
A73: 46167 | B73: 美国 | C73: Flybar Inc | D73: FB-7938 | E73: PO213891 | F73: T03940-DS | G73: 600 | H73: 46261 | AR73: =G73 -> 600 | AX73: 2.1 | AY73: =SUM(I73:AW73)*AX73 -> 1260 | AZ73: =AY73*7.75 -> 9765 | BA73: =B73 -> 美国 | BB73: =C73 -> Flybar Inc
A74: 46167 | B74: 美国 | C74: Flybar Inc | D74: FB-7938 | E74: PO213891 | F74: T03941-DS | G74: 600 | H74: 46261 | AS74: =G74 -> 600 | AX74: 2.1 | AY74: =SUM(I74:AW74)*AX74 -> 1260 | AZ74: =AY74*7.75 -> 9765 | BA74: =B74 -> 美国 | BB74: =C74 -> Flybar Inc
A75: 46167 | B75: 美国 | C75: Flybar Inc | D75: FB-7938 | E75: PO213891 | F75: T03942-DS | G75: 600 | H75: 46261 | AT75: =G75 -> 600 | AX75: 2.1 | AY75: =SUM(I75:AW75)*AX75 -> 1260 | AZ75: =AY75*7.75 -> 9765 | BA75: =B75 -> 美国 | BB75: =C75 -> Flybar Inc
A76: 46191 | B76: 马来西亚 | C76: Litt Tak Sdn Bhd | D76: TMI-LT112962 | E76: PO214234 | F76: T02444 | G76: 720 | H76: 46238 | M76: =G76 -> 720 | AX76: 2.1 | AY76: =SUM(I76:AW76)*AX76 -> 1512 | AZ76: =AY76*7.75 -> 11718 | BA76: =B76 -> 马来西亚 | BB76: =C76 -> Litt Tak Sdn Bhd
A77: 46195 | B77: 澳大利亚 | C77: Kmart Australia & NZ Holding Limited | D77: 21848574 | E77: PO214263 | F77: T02444 | G77: 5004 | H77: 46233 | M77: =G77 -> 5004 | AX77: 2.1 | AY77: =SUM(I77:AW77)*AX77 -> 10508.4 | AZ77: =AY77*7.75 -> 81440.1 | BA77: =B77 -> 澳大利亚 | BB77: =C77 -> Kmart Australia & NZ Holding Limited
A78: 46195 | B78: 美国 | C78: Flybar Inc | D78: FB-8224 | E78: PO214370 | F78: JW-RV-RPGEA | G78: 1002 | H78: 46249 | J78: =G78 -> 1002 | AX78: 4.9 | AY78: =SUM(I78:AW78)*AX78 -> 4909.8 | AZ78: =AY78*7.75 -> 38050.95 | BA78: =B78 -> 美国 | BB78: =C78 -> Flybar Inc
A79: 46195 | B79: 美国 | C79: Flybar Inc | D79: FB-8223 | E79: PO214369 | F79: JW-RV-RPGEA | G79: 1002 | H79: 46249 | J79: =G79 -> 1002 | AX79: 4.9 | AY79: =SUM(I79:AW79)*AX79 -> 4909.8 | AZ79: =AY79*7.75 -> 38050.95 | BA79: =B79 -> 美国 | BB79: =C79 -> Flybar Inc
A80: 46195 | B80: 美国 | C80: Flybar Inc | D80: FB-8225 | E80: PO214371 | F80: JW-RV-RPGEA | G80: 498 | H80: 46249 | J80: =G80 -> 498 | AX80: 4.9 | AY80: =SUM(I80:AW80)*AX80 -> 2440.2 | AZ80: =AY80*7.75 -> 18911.55 | BA80: =B80 -> 美国 | BB80: =C80 -> Flybar Inc
A81: 46226 | B81: 美国 | C81: Meijer LANSING | D81: 219664389 | E81: PO214790 | F81: T01453 | G81: 574 | H81: 46267 | J81: =G81 -> 574 | AX81: 4.5 | AY81: =SUM(I81:AW81)*AX81 -> 2583 | AZ81: =AY81*7.75 -> 20018.25 | BA81: =B81 -> 美国 | BB81: =C81 -> Meijer LANSING
A82: 46226 | B82: 美国 | C82: Meijer LANSING | D82: 219664388 | E82: PO214789 | F82: T01453 | G82: 1300 | H82: 46266 | J82: =G82 -> 1300 | AX82: 4.5 | AY82: =SUM(I82:AW82)*AX82 -> 5850 | AZ82: =AY82*7.75 -> 45337.5 | BA82: =B82 -> 美国 | BB82: =C82 -> Meijer LANSING
A83: 46240 | B83: 上海 | D83: 47981637 | E83: PO214938 | F83: JW-RV-RPGE | G83: 198 | H83: 46277 | J83: =G83 -> 198 | AX83: 4.5 | AY83: =SUM(I83:AW83)*AX83 -> 891 | AZ83: =AY83*7.75 -> 6905.25 | BA83: =B83 -> 上海 | BB83: =C83 -> 0
A84: 46240 | B84: 上海 | D84: 47981746 | E84: PO214939 | F84: JW-RV-RPGE | G84: 942 | H84: 46277 | J84: =G84 -> 942 | AX84: 4.5 | AY84: =SUM(I84:AW84)*AX84 -> 4239 | AZ84: =AY84*7.75 -> 32852.25 | BA84: =B84 -> 上海 | BB84: =C84 -> 0
A85: 46240 | B85: 上海 | D85: 47982010 | E85: PO214940 | F85: JW-RV-RPGE | G85: 432 | H85: 46277 | J85: =G85 -> 432 | AX85: 4.5 | AY85: =SUM(I85:AW85)*AX85 -> 1944 | AZ85: =AY85*7.75 -> 15066 | BA85: =B85 -> 上海 | BB85: =C85 -> 0
A86: 46240 | B86: 上海 | D86: 47982383 | E86: PO214941 | F86: JW-RV-RPGE | G86: 924 | H86: 46277 | J86: =G86 -> 924 | AX86: 4.5 | AY86: =SUM(I86:AW86)*AX86 -> 4158 | AZ86: =AY86*7.75 -> 32224.5 | BA86: =B86 -> 上海 | BB86: =C86 -> 0
A87: 46245 | B87: 上海 | D87: 26-3202009JUS | E87: PO215033 | F87: T01535 | G87: 132 | H87: 46285 | L87: =G87 -> 132 | AX87: 2.1 | AY87: =SUM(I87:AW87)*AX87 -> 277.2 | AZ87: =AY87*7.75 -> 2148.3 | BA87: =B87 -> 上海 | BB87: =C87 -> 0
A88: 46245 | B88: 上海 | D88: 26-3202009JUS | E88: PO215033 | F88: T02444 | G88: 120 | H88: 46285 | M88: =G88 -> 120 | AX88: 2.1 | AY88: =SUM(I88:AW88)*AX88 -> 252 | AZ88: =AY88*7.75 -> 1953 | BA88: =B88 -> 上海 | BB88: =C88 -> 0
A89: 46245 | B89: 上海 | D89: 26-3202008JDO | E89: PO215031 | F89: T01535 | G89: 144 | H89: 46265 | L89: =G89 -> 144 | AX89: 2.1 | AY89: =SUM(I89:AW89)*AX89 -> 302.4 | AZ89: =AY89*7.75 -> 2343.6 | BA89: =B89 -> 上海 | BB89: =C89 -> 0
A90: 46245 | B90: 上海 | D90: 26-3202008JDO | E90: PO215031 | F90: T02444 | G90: 144 | H90: 46265 | M90: =G90 -> 144 | AX90: 2.1 | AY90: =SUM(I90:AW90)*AX90 -> 302.4 | AZ90: =AY90*7.75 -> 2343.6 | BA90: =B90 -> 上海 | BB90: =C90 -> 0
A91: 46245 | B91: 上海 | D91: 26-3202007JEC | E91: PO215029 | F91: T01535 | G91: 504 | H91: 46285 | L91: =G91 -> 504 | AX91: 2.1 | AY91: =SUM(I91:AW91)*AX91 -> 1058.4 | AZ91: =AY91*7.75 -> 8202.6 | BA91: =B91 -> 上海 | BB91: =C91 -> 0
A92: 46245 | B92: 上海 | D92: 26-3202007JEC | E92: PO215029 | F92: T02444 | G92: 504 | H92: 46285 | M92: =G92 -> 504 | AX92: 2.1 | AY92: =SUM(I92:AW92)*AX92 -> 1058.4 | AZ92: =AY92*7.75 -> 8202.6 | BA92: =B92 -> 上海 | BB92: =C92 -> 0
AY93: =SUM(I93:AW93)*AX93 -> 0 | AZ93: =AY93*7.75 -> 0 | BA93: =B93 -> 0 | BB93: =C93 -> 0
AY94: =SUM(I94:AW94)*AX94 -> 0 | AZ94: =AY94*7.75 -> 0 | BA94: =B94 -> 0 | BB94: =C94 -> 0
AY95: =SUM(I95:AW95)*AX95 -> 0 | AZ95: =AY95*7.75 -> 0 | BA95: =B95 -> 0 | BB95: =C95 -> 0
AY96: =SUM(I96:AW96)*AX96 -> 0 | AZ96: =AY96*7.75 -> 0 | BA96: =B96 -> 0 | BB96: =C96 -> 0
AY97: =SUM(I97:AW97)*AX97 -> 0 | AZ97: =AY97*7.75 -> 0 | BA97: =B97 -> 0 | BB97: =C97 -> 0
AY98: =SUM(I98:AW98)*AX98 -> 0 | AZ98: =AY98*7.75 -> 0 | BA98: =B98 -> 0 | BB98: =C98 -> 0
AY99: =SUM(I99:AW99)*AX99 -> 0 | AZ99: =AY99*7.75 -> 0 | BA99: =B99 -> 0 | BB99: =C99 -> 0
G100: =SUM(G3:G99) -> 140258 | H100: =G100-AX100 -> 0 | I100: =SUM(I3:I99) -> 13524 | J100: =SUM(J3:J99) -> 9878 | K100: =SUM(K3:K99) -> 3504 | L100: =SUM(L3:L99) -> 1320 | M100: =SUM(M3:M99) -> 48312 | N100: =SUM(N3:N99) -> 2964 | O100: =SUM(O3:O99) -> 180 | P100: =SUM(P3:P99) -> 0 | ... AW100: =SUM(AW3:AW99) -> 0 | AX100: =SUM(I100:AW100) -> 140258 | AY100: =SUM(AY1:AY99) -> 543134.96 | AZ100: =SUM(AZ1:AZ99) -> 4209295.9
...

Sheet 正在做货
A1: 接单期 | B1: 国家 | C1: 客跟单 | D1: 客户 | E1: Customer PO | F1: PO号 | G1: 货号 | H1: 名称 | I1: 数量 | J1: 装箱数 | K1: 总箱数 | L1: 客PO期 | M1: 出货期 | N1: 验货期 | O1: 是否约验货 | P1: 验货结果 | Q1: 船期SO | R1: 吨车/柜货 | S1: 生产车间 | T1: 箱唛资料 | U1: 客贴纸 | V1: 是否寄出签办 | W1: 是否打卡板 | X1: 彩盒UPC条码 | Y1: 彩盒版本 | Z1: 说明书版本 | AA1: 日期码 | AB1: 备注 | AC1: 单价 | AD1: 金额USD | AE1: 金额HKD | AF1: 发票号 | AG1: 走柜/散货 | AH1: 出货日期 | AI1: 是否入系统 | AJ1: 下单情况 | AK1: 贴纸情况 | AL1: 首期扣数
A2: 46101 | B2: 澳大利亚 | C2: Rachel | D2: Target Australia Pty Ltd | E2: 2617379 | F2: PO213309 | G2: T02444 | H2: =VLOOKUP(G2,名称!A:B,2,0) -> 恐龙公园二代 | I2: 1500 | J2: =VLOOKUP(G2,名称!A:C,3,FALSE) -> 12 | K2: =I2/J2 -> 125 | L2: 46247 | M2: 46241 | N2: 46241 | O2: 已约 | P2: pass | Q2: Extra Costs：$6.875 | T2: OK | U2: SSCC贴纸 | X2: 草地套装：0840148226203 海滩滩套装：0840148226210 实验室套装：0840148226227 | Y2: 标准美文版本 （13位数UPC条码） | Z2: 美文版本说明书 | AA2: 46260 | AB2: 普通透明胶带封箱，外箱不需要盖日期码 | AC2: 2.1 | AD2: =AC2*I2 -> 3150 | AE2: =AD2*7.75 -> 24412.5 | AI2: 已入系统 | AK2: SSCC贴纸4/23给到佩玲 | AL2: =IFERROR(VLOOKUP(G2,'已打发票扣数（26年5月开始）'!$A$1:$C$17,3,0)*I2*0.3,"") -> 945
A3: 46101 | B3: 澳大利亚 | C3: Rachel | D3: Target Australia Pty Ltd | E3: 2617380 | F3: PO213310 | G3: T02444 | H3: =VLOOKUP(G3,名称!A:B,2,0) -> 恐龙公园二代 | I3: 1200 | J3: =VLOOKUP(G3,名称!A:C,3,FALSE) -> 12 | K3: =I3/J3 -> 100 | L3: 46274 | M3: =L3-7 -> 46267 | N3: =M3 -> 46267 | Q3: Extra Costs：$5.5 | T3: OK | U3: SSCC贴纸 | X3: 草地套装：0840148226203 海滩滩套装：0840148226210 实验室套装：0840148226227 | Y3: 标准美文版本 （13位数UPC条码） | Z3: 美文版本说明书 | AA3: 46291 | AB3: 普通透明胶带封箱，外箱不需要盖日期码 | AC3: 2.1 | AD3: =AC3*I3 -> 2520 | AE3: =AD3*7.75 -> 19530 | AI3: 已入系统 | AK3: SSCC贴纸4/23给到佩玲 | AL3: =IFERROR(VLOOKUP(G3,'已打发票扣数（26年5月开始）'!$A$1:$C$17,3,0)*I3*0.3,"") -> 756
A4: 46114 | B4: 美国-亚马逊 | C4: Elaine | D4: Flybar Inc | E4: FB-7783 | F4: PO212870 | G4: JW-RV-RPGEA | H4: =VLOOKUP(G4,名称!A:B,2,0) -> 恐龙游戏盘(邮包盒装) | I4: 1002 | J4: =VLOOKUP(G4,名称!A:C,3,FALSE) -> 6 | K4: =I4/J4 -> 167 | L4: 46167 | M4: 46163 | N4: 46163 | O4: 已约 | P4: pass | Q4: Extra Costs：$20.04 船期8/26 | T4: OK | X4: 0840148227217 | Y4: 亚马逊版本 （12位数UPC条码） | Z4: 美文版本说明书 | AA4: 46235 | AB4: 外箱不需要盖日期码 | AC4: 4.9 | AD4: =AC4*I4 -> 4909.8 | AE4: =AD4*7.75 -> 38050.95 | AI4: 已入系统 | AK4: 客追踪贴纸 | AL4: =IFERROR(VLOOKUP(G4,'已打发票扣数（26年5月开始）'!$A$1:$C$17,3,0)*I4*0.3,"") -> 1352.7
A5: 46167 | B5: 美国-亚马逊 | C5: Elaine | D5: Flybar Inc | E5: FB-7937 | F5: PO213850 | G5: T03937-DS | H5: =VLOOKUP(G5,名称!A:B,2,0) -> 恐龙公园一代--陆地 | I5: =408-144 -> 264 | J5: =VLOOKUP(G5,名称!A:C,3,FALSE) -> 12 | K5: =I5/J5 -> 22 | L5: 46232 | M5: =L5-5 -> 46227 | N5: 46232 | O5: 已约 | P5: pass | T5: OK | X5: 0840148231382 | Y5: 沃尔玛版本彩盒 （12位数UPC条码） | Z5: 美文版本说明书 | AA5: / | AB5: 用取消单PO211192返工，条形码上已有日期码，不需要另外打日期，产品上的RFID贴纸要撕掉 | AC5: 2.1 | AD5: =AC5*I5 -> 554.4 | AE5: =AD5*7.75 -> 4296.6 | AK5: 条形码贴纸/客追踪贴纸6/18给到佩玲 | AL5: =(I5*AC5)*0.3 -> 166.32
A6: 46167 | B6: 美国-亚马逊 | C6: Elaine | D6: Flybar Inc | E6: FB-7937 | F6: PO213850 | G6: T03938-DS | H6: =VLOOKUP(G6,名称!A:B,2,0) -> 恐龙公园一代--海洋 | I6: =408-144 -> 264 | J6: =VLOOKUP(G6,名称!A:C,3,FALSE) -> 12 | K6: =I6/J6 -> 22 | L6: 46232 | M6: =L6-5 -> 46227 | N6: 46232 | O6: 已约 | P6: pass | T6: OK | X6: 0840148231399 | Y6: 沃尔玛版本彩盒 （12位数UPC条码） | Z6: 美文版本说明书 | AA6: / | AB6: 用取消单PO211192返工，条形码上已有日期码，不需要另外打日期，产品上的RFID贴纸要撕掉 | AC6: 2.1 | AD6: =AC6*I6 -> 554.4 | AE6: =AD6*7.75 -> 4296.6 | AK6: 条形码贴纸/客追踪贴纸6/18给到佩玲 | AL6: =(I6*AC6)*0.3 -> 166.32
A7: 46167 | B7: 美国-亚马逊 | C7: Elaine | D7: Flybar Inc | E7: FB-7937 | F7: PO213850 | G7: T03939-DS | H7: =VLOOKUP(G7,名称!A:B,2,0) -> 恐龙公园一代--天空 | I7: =408-144 -> 264 | J7: =VLOOKUP(G7,名称!A:C,3,FALSE) -> 12 | K7: =I7/J7 -> 22 | L7: 46232 | M7: =L7-5 -> 46227 | N7: 46232 | O7: 已约 | P7: pass | T7: OK | X7: 0840148231405 | Y7: 沃尔玛版本彩盒 （12位数UPC条码） | Z7: 美文版本说明书 | AA7: / | AB7: 用取消单PO211192返工，条形码上已有日期码，不需要另外打日期，产品上的RFID贴纸要撕掉 | AC7: 2.1 | AD7: =AC7*I7 -> 554.4 | AE7: =AD7*7.75 -> 4296.6 | AK7: 条形码贴纸/客追踪贴纸6/18给到佩玲 | AL7: =(I7*AC7)*0.3 -> 166.32
A8: 46167 | B8: 美国-亚马逊 | C8: Elaine | D8: Flybar Inc | E8: FB-7937 | F8: PO213850 | G8: T03940-DS | H8: =VLOOKUP(G8,名称!A:B,2,0) -> 恐龙公园二代--海滩 | I8: =408-144 -> 264 | J8: =VLOOKUP(G8,名称!A:C,3,FALSE) -> 12 | K8: =I8/J8 -> 22 | L8: 46232 | M8: =L8-5 -> 46227 | N8: 46232 | O8: 已约 | P8: pass | T8: OK | X8: 0840148231412 | Y8: 沃尔玛版本彩盒 （12位数UPC条码） | Z8: 美文版本说明书 | AA8: / | AB8: 条形码上已有日期码，不需要另外打日期 | AC8: 2.1 | AD8: =AC8*I8 -> 554.4 | AE8: =AD8*7.75 -> 4296.6 | AK8: 条形码贴纸/客追踪贴纸6/18给到佩玲 | AL8: =(I8*AC8)*0.3 -> 166.32
A9: 46167 | B9: 美国-亚马逊 | C9: Elaine | D9: Flybar Inc | E9: FB-7937 | F9: PO213850 | G9: T03941-DS | H9: =VLOOKUP(G9,名称!A:B,2,0) -> 恐龙公园二代--雨林 | I9: =408-144 -> 264 | J9: =VLOOKUP(G9,名称!A:C,3,FALSE) -> 12 | K9: =I9/J9 -> 22 | L9: 46232 | M9: =L9-5 -> 46227 | N9: 46232 | O9: 已约 | P9: pass | T9: OK | X9: 0840148231429 | Y9: 沃尔玛版本彩盒 （12位数UPC条码） | Z9: 美文版本说明书 | AA9: / | AB9: 条形码上已有日期码，不需要另外打日期 | AC9: 2.1 | AD9: =AC9*I9 -> 554.4 | AE9: =AD9*7.75 -> 4296.6 | AK9: 条形码贴纸/客追踪贴纸6/18给到佩玲 | AL9: =(I9*AC9)*0.3 -> 166.32
A10: 46167 | B10: 美国-亚马逊 | C10: Elaine | D10: Flybar Inc | E10: FB-7937 | F10: PO213850 | G10: T03942-DS | H10: =VLOOKUP(G10,名称!A:B,2,0) -> 恐龙公园二代--实验室 | I10: =408-144 -> 264 | J10: =VLOOKUP(G10,名称!A:C,3,FALSE) -> 12 | K10: =I10/J10 -> 22 | L10: 46232 | M10: =L10-5 -> 46227 | N10: 46232 | O10: 已约 | P10: pass | T10: OK | X10: 0840148231436 | Y10: 沃尔玛版本彩盒 （12位数UPC条码） | Z10: 美文版本说明书 | AA10: / | AB10: 条形码上已有日期码，不需要另外打日期 | AC10: 2.1 | AD10: =AC10*I10 -> 554.4 | AE10: =AD10*7.75 -> 4296.6 | AK10: 条形码贴纸/客追踪贴纸6/18给到佩玲 | AL10: =(I10*AC10)*0.3 -> 166.32
A11: 46167 | B11: 美国-亚马逊 | C11: Elaine | D11: Flybar Inc | E11: FB-7938 | F11: PO213891 | G11: T03937-DS | H11: =VLOOKUP(G11,名称!A:B,2,0) -> 恐龙公园一代--陆地 | I11: 600 | J11: =VLOOKUP(G11,名称!A:C,3,FALSE) -> 12 | K11: =I11/J11 -> 50 | L11: 46262 | M11: =L11-3 -> 46259 | N11: =L11-3 -> 46259 | Q11: Extra Costs：$468 | T11: OK | X11: 0840148231382 | Y11: 沃尔玛版本彩盒 （12位数UPC条码） | Z11: 美文版本说明书 | AA11: / | AB11: 用取消单PO211192、P0210601返工，条形码上已有日期码，不需要另外打日期，产品上的RFID贴纸要撕掉 | AC11: 2.1 | AD11: =AC11*I11 -> 1260 | AE11: =AD11*7.75 -> 9765 | AK11: 条形码贴纸/客追踪贴纸6/18给到佩玲 | AL11: =(I11*AC11)*0.3 -> 378
A12: 46167 | B12: 美国-亚马逊 | C12: Elaine | D12: Flybar Inc | E12: FB-7938 | F12: PO213891 | G12: T03938-DS | H12: =VLOOKUP(G12,名称!A:B,2,0) -> 恐龙公园一代--海洋 | I12: 600 | J12: =VLOOKUP(G12,名称!A:C,3,FALSE) -> 12 | K12: =I12/J12 -> 50 | L12: 46262 | M12: =L12-3 -> 46259 | N12: =L12-3 -> 46259 | T12: OK | X12: 0840148231399 | Y12: 沃尔玛版本彩盒 （12位数UPC条码） | Z12: 美文版本说明书 | AA12: / | AB12: 用取消单PO211192、P0210601返工，条形码上已有日期码，不需要另外打日期，产品上的RFID贴纸要撕掉 | AC12: 2.1 | AD12: =AC12*I12 -> 1260 | AE12: =AD12*7.75 -> 9765 | AK12: 条形码贴纸/客追踪贴纸6/18给到佩玲 | AL12: =(I12*AC12)*0.3 -> 378
A13: 46167 | B13: 美国-亚马逊 | C13: Elaine | D13: Flybar Inc | E13: FB-7938 | F13: PO213891 | G13: T03939-DS | H13: =VLOOKUP(G13,名称!A:B,2,0) -> 恐龙公园一代--天空 | I13: 600 | J13: =VLOOKUP(G13,名称!A:C,3,FALSE) -> 12 | K13: =I13/J13 -> 50 | L13: 46262 | M13: =L13-3 -> 46259 | N13: =L13-3 -> 46259 | T13: OK | X13: 0840148231405 | Y13: 沃尔玛版本彩盒 （12位数UPC条码） | Z13: 美文版本说明书 | AA13: / | AB13: 用取消单PO211192、P0210601返工，条形码上已有日期码，不需要另外打日期，产品上的RFID贴纸要撕掉 | AC13: 2.1 | AD13: =AC13*I13 -> 1260 | AE13: =AD13*7.75 -> 9765 | AK13: 条形码贴纸/客追踪贴纸6/18给到佩玲 | AL13: =(I13*AC13)*0.3 -> 378
A14: 46167 | B14: 美国-亚马逊 | C14: Elaine | D14: Flybar Inc | E14: FB-7938 | F14: PO213891 | G14: T03940-DS | H14: =VLOOKUP(G14,名称!A:B,2,0) -> 恐龙公园二代--海滩 | I14: 600 | J14: =VLOOKUP(G14,名称!A:C,3,FALSE) -> 12 | K14: =I14/J14 -> 50 | L14: 46262 | M14: =L14-3 -> 46259 | N14: =L14-3 -> 46259 | T14: OK | X14: 0840148231412 | Y14: 沃尔玛版本彩盒 （12位数UPC条码） | Z14: 美文版本说明书 | AA14: / | AB14: 条形码上已有日期码，不需要另外打日期 | AC14: 2.1 | AD14: =AC14*I14 -> 1260 | AE14: =AD14*7.75 -> 9765 | AK14: 条形码贴纸/客追踪贴纸6/18给到佩玲 | AL14: =(I14*AC14)*0.3 -> 378
A15: 46167 | B15: 美国-亚马逊 | C15: Elaine | D15: Flybar Inc | E15: FB-7938 | F15: PO213891 | G15: T03941-DS | H15: =VLOOKUP(G15,名称!A:B,2,0) -> 恐龙公园二代--雨林 | I15: 600 | J15: =VLOOKUP(G15,名称!A:C,3,FALSE) -> 12 | K15: =I15/J15 -> 50 | L15: 46262 | M15: =L15-3 -> 46259 | N15: =L15-3 -> 46259 | T15: OK | X15: 0840148231429 | Y15: 沃尔玛版本彩盒 （12位数UPC条码） | Z15: 美文版本说明书 | AA15: / | AB15: 条形码上已有日期码，不需要另外打日期 | AC15: 2.1 | AD15: =AC15*I15 -> 1260 | AE15: =AD15*7.75 -> 9765 | AK15: 条形码贴纸/客追踪贴纸6/18给到佩玲 | AL15: =(I15*AC15)*0.3 -> 378
A16: 46167 | B16: 美国-亚马逊 | C16: Elaine | D16: Flybar Inc | E16: FB-7938 | F16: PO213891 | G16: T03942-DS | H16: =VLOOKUP(G16,名称!A:B,2,0) -> 恐龙公园二代--实验室 | I16: 600 | J16: =VLOOKUP(G16,名称!A:C,3,FALSE) -> 12 | K16: =I16/J16 -> 50 | L16: 46262 | M16: =L16-3 -> 46259 | N16: =L16-3 -> 46259 | T16: OK | X16: 0840148231436 | Y16: 沃尔玛版本彩盒 （12位数UPC条码） | Z16: 美文版本说明书 | AA16: / | AB16: 条形码上已有日期码，不需要另外打日期 | AC16: 2.1 | AD16: =AC16*I16 -> 1260 | AE16: =AD16*7.75 -> 9765 | AK16: 条形码贴纸/客追踪贴纸6/18给到佩玲 | AL16: =(I16*AC16)*0.3 -> 378
A17: 46195 | B17: 美国-亚马逊 | C17: Elaine | D17: Flybar Inc | E17: FB-8224 | F17: PO214370 | G17: JW-RV-RPGEA | H17: =VLOOKUP(G17,名称!A:B,2,0) -> 恐龙游戏盘(邮包盒装) | I17: 1002 | J17: =VLOOKUP(G17,名称!A:C,3,FALSE) -> 6 | K17: =I17/J17 -> 167 | L17: 46248 | M17: 46247 | N17: 46247 | O17: 已约 | P17: pass | Q17: Extra Costs：$30.06 2026/8/29 | T17: OK | U17: 追踪贴纸 | X17: 0840148227217 | Y17: 亚马逊版本 （12位数UPC条码） | Z17: 美文版本说明书 | AA17: 46235 | AB17: 外箱不需要盖日期码 | AC17: 4.9 | AD17: =AC17*I17 -> 4909.8 | AE17: =AD17*7.75 -> 38050.95 | AI17: 已入系统 | AL17: =IFERROR(VLOOKUP(G17,'已打发票扣数（26年5月开始）'!$A$1:$C$17,3,0)*I17*0.3,"") -> 1352.7
A18: 46195 | B18: 美国-亚马逊 | C18: Elaine | D18: Flybar Inc | E18: FB-8223 | F18: PO214369 | G18: JW-RV-RPGEA | H18: =VLOOKUP(G18,名称!A:B,2,0) -> 恐龙游戏盘(邮包盒装) | I18: 1002 | J18: =VLOOKUP(G18,名称!A:C,3,FALSE) -> 6 | K18: =I18/J18 -> 167 | L18: 46248 | M18: 46247 | N18: 46247 | O18: 已约 | P18: pass | Q18: Extra Costs：$30.06 2026/9/21 | T18: OK | U18: 追踪贴纸 | X18: 0840148227217 | Y18: 亚马逊版本 （12位数UPC条码） | Z18: 美文版本说明书 | AA18: 46235 | AB18: 外箱不需要盖日期码 | AC18: 4.9 | AD18: =AC18*I18 -> 4909.8 | AE18: =AD18*7.75 -> 38050.95 | AI18: 已入系统 | AL18: =IFERROR(VLOOKUP(G18,'已打发票扣数（26年5月开始）'!$A$1:$C$17,3,0)*I18*0.3,"") -> 1352.7
A19: 46195 | B19: 美国-亚马逊 | C19: Elaine | D19: Flybar Inc | E19: FB-8225 | F19: PO214371 | G19: JW-RV-RPGEA | H19: =VLOOKUP(G19,名称!A:B,2,0) -> 恐龙游戏盘(邮包盒装) | I19: 498 | J19: =VLOOKUP(G19,名称!A:C,3,FALSE) -> 6 | K19: =I19/J19 -> 83 | L19: 46248 | M19: 46247 | N19: 46247 | O19: 已约 | P19: pass | Q19: Extra Costs：$24.9 2026/10/21 | T19: OK | U19: 追踪贴纸 | X19: 0840148227217 | Y19: 亚马逊版本 （12位数UPC条码） | Z19: 美文版本说明书 | AA19: 46235 | AB19: 外箱不需要盖日期码 | AC19: 4.9 | AD19: =AC19*I19 -> 2440.2 | AE19: =AD19*7.75 -> 18911.55 | AI19: 已入系统 | AL19: =IFERROR(VLOOKUP(G19,'已打发票扣数（26年5月开始）'!$A$1:$C$17,3,0)*I19*0.3,"") -> 672.3
A20: 46226 | B20: 美国 | C20: Jennifer | D20: Meijer LANSING | E20: 219664389 | F20: PO214790 | G20: T01453 | H20: =VLOOKUP(G20,名称!A:B,2,0) -> 恐龙游戏盘 | I20: 574 | J20: =VLOOKUP(G20,名称!A:C,3,FALSE) -> 2 | K20: =I20/J20 -> 287 | L20: 46269 | M20: =L20-7 -> 46262 | N20: 46262 | T20: OK | X20: 840148207301 | Y20: 标准美文12位条形码 | Z20: 沃尔玛版本说明书 | AA20: RR23726 | AB20: 该订单与沃尔玛订单相似，但外箱箱唛不同请注意不要订错外箱，外箱不用加盖日期码。 | AC20: 4.5 | AD20: =AC20*I20 -> 2583 | AE20: =AD20*7.75 -> 20018.25 | AI20: 已入系统 | AL20: =IFERROR(VLOOKUP(G20,'已打发票扣数（26年5月开始）'!$A$1:$C$17,3,0)*I20*0.3,"") -> 774.9
A21: 46226 | B21: 美国 | C21: Jennifer | D21: Meijer LANSING | E21: 219664388 | F21: PO214789 | G21: T01453 | H21: =VLOOKUP(G21,名称!A:B,2,0) -> 恐龙游戏盘 | I21: 1300 | J21: =VLOOKUP(G21,名称!A:C,3,FALSE) -> 2 | K21: =I21/J21 -> 650 | L21: 46269 | M21: =L21-7 -> 46262 | N21: 46262 | T21: OK | X21: 840148207301 | Y21: 标准美文12位条形码 | Z21: 沃尔玛版本说明书 | AA21: RR23726 | AB21: 该订单与沃尔玛订单相似，但外箱箱唛不同请注意不要订错外箱，外箱不用加盖日期码。 | AC21: 4.5 | AD21: =AC21*I21 -> 5850 | AE21: =AD21*7.75 -> 45337.5 | AI21: 已入系统 | AL21: =IFERROR(VLOOKUP(G21,'已打发票扣数（26年5月开始）'!$A$1:$C$17,3,0)*I21*0.3,"") -> 1755
A22: 46240 | B22: 上海 | C22: Carol | D22: BIG W | E22: 47981637 | F22: PO214938 | G22: JW-RV-RPGE | H22: =VLOOKUP(G22,名称!A:B,2,0) -> 恐龙游戏盘 | I22: 198 | J22: =VLOOKUP(G22,名称!A:C,3,FALSE) -> 6 | K22: =I22/J22 -> 33 | L22: 46280 | M22: =L22-7 -> 46273 | N22: 46273 | Q22: Extra Costs：$300 | T22: OK | X22: 0840148207301 | Y22: 标准美文版本 （13位数UPC条码） | Z22: 美文版本说明书 | AA22: 150926 | AB22: 外箱不需要盖日期码 | AC22: 4.5 | AD22: =AC22*I22 -> 891 | AE22: =AD22*7.75 -> 6905.25 | AI22: 已入系统 | AL22: =IFERROR(VLOOKUP(G22,'已打发票扣数（26年5月开始）'!$A$1:$C$17,3,0)*I22*0.3,"") -> 267.3
A23: 46240 | B23: 上海 | C23: Carol | D23: BIG W | E23: 47981746 | F23: PO214939 | G23: JW-RV-RPGE | H23: =VLOOKUP(G23,名称!A:B,2,0) -> 恐龙游戏盘 | I23: 942 | J23: =VLOOKUP(G23,名称!A:C,3,FALSE) -> 6 | K23: =I23/J23 -> 157 | L23: 46280 | M23: =L23-7 -> 46273 | N23: 46273 | T23: OK | X23: 0840148207301 | Y23: 标准美文版本 （13位数UPC条码） | Z23: 美文版本说明书 | AA23: 150926 | AB23: 外箱不需要盖日期码 | AC23: 4.5 | AD23: =AC23*I23 -> 4239 | AE23: =AD23*7.75 -> 32852.25 | AI23: 已入系统 | AL23: =IFERROR(VLOOKUP(G23,'已打发票扣数（26年5月开始）'!$A$1:$C$17,3,0)*I23*0.3,"") -> 1271.7
A24: 46240 | B24: 上海 | C24: Carol | D24: BIG W | E24: 47982010 | F24: PO214940 | G24: JW-RV-RPGE | H24: =VLOOKUP(G24,名称!A:B,2,0) -> 恐龙游戏盘 | I24: 432 | J24: =VLOOKUP(G24,名称!A:C,3,FALSE) -> 6 | K24: =I24/J24 -> 72 | L24: 46280 | M24: =L24-7 -> 46273 | N24: 46273 | Q24: Extra Costs：$300 | T24: OK | X24: 0840148207301 | Y24: 标准美文版本 （13位数UPC条码） | Z24: 美文版本说明书 | AA24: 150926 | AB24: 外箱不需要盖日期码 | AC24: 4.5 | AD24: =AC24*I24 -> 1944 | AE24: =AD24*7.75 -> 15066 | AI24: 已入系统 | AL24: =IFERROR(VLOOKUP(G24,'已打发票扣数（26年5月开始）'!$A$1:$C$17,3,0)*I24*0.3,"") -> 583.2
A25: 46240 | B25: 上海 | C25: Carol | D25: BIG W | E25: 47982383 | F25: PO214941 | G25: JW-RV-RPGE | H25: =VLOOKUP(G25,名称!A:B,2,0) -> 恐龙游戏盘 | I25: 924 | J25: =VLOOKUP(G25,名称!A:C,3,FALSE) -> 6 | K25: =I25/J25 -> 154 | L25: 46280 | M25: =L25-7 -> 46273 | N25: =M25 -> 46273 | T25: OK | X25: 0840148207301 | Y25: 标准美文版本 （13位数UPC条码） | Z25: 美文版本说明书 | AA25: 150926 | AB25: 外箱不需要盖日期码 | AC25: 4.5 | AD25: =AC25*I25 -> 4158 | AE25: =AD25*7.75 -> 32224.5 | AI25: 已入系统 | AL25: =IFERROR(VLOOKUP(G25,'已打发票扣数（26年5月开始）'!$A$1:$C$17,3,0)*I25*0.3,"") -> 1247.4
A26: 46245 | B26: 上海 | C26: Elaine | D26: WRT | E26: 26-3202009JUS | F26: PO215033 | G26: T01535 | H26: =VLOOKUP(G26,名称!A:B,2,0) -> 恐龙公园 | I26: 132 | J26: =VLOOKUP(G26,名称!A:C,3,FALSE) -> 12 | K26: =I26/J26 -> 11 | L26: 46286 | M26: =L26-7 -> 46279 | N26: =M26 -> 46279 | Q26: Extra Costs：$7.56 | X26: 0840148215733 | Y26: 标准美文版本 （13位数UPC条码） | Z26: 美文版本说明书 | AA26: RR25226 | AB26: 外箱不需要盖日期码 | AC26: 2.1 | AD26: =AC26*I26 -> 277.2 | AE26: =AD26*7.75 -> 2148.3 | AI26: 已入系统 | AL26: =IFERROR(VLOOKUP(G26,'已打发票扣数（26年5月开始）'!$A$1:$C$17,3,0)*I26*0.3,"") -> 83.16
A27: 46245 | B27: 上海 | C27: Elaine | D27: WRT | E27: 26-3202009JUS | F27: PO215033 | G27: T02444 | H27: =VLOOKUP(G27,名称!A:B,2,0) -> 恐龙公园二代 | I27: 120 | J27: =VLOOKUP(G27,名称!A:C,3,FALSE) -> 12 | K27: =I27/J27 -> 10 | L27: 46286 | M27: =L27-7 -> 46279 | N27: =M27 -> 46279 | X27: 0840148221734 | Y27: 标准美文版本 （13位数UPC条码） | Z27: 美文版本说明书 | AA27: RR25226 | AB27: 外箱不需要盖日期码 | AC27: 2.1 | AD27: =AC27*I27 -> 252 | AE27: =AD27*7.75 -> 1953 | AI27: 已入系统 | AL27: =IFERROR(VLOOKUP(G27,'已打发票扣数（26年5月开始）'!$A$1:$C$17,3,0)*I27*0.3,"") -> 75.6
A28: 46245 | B28: 上海 | C28: Elaine | D28: WRT | E28: 26-3202008JDO | F28: PO215031 | G28: T01535 | H28: =VLOOKUP(G28,名称!A:B,2,0) -> 恐龙公园 | I28: 144 | J28: =VLOOKUP(G28,名称!A:C,3,FALSE) -> 12 | K28: =I28/J28 -> 12 | L28: 46286 | M28: =L28-7 -> 46279 | N28: =M28 -> 46279 | Q28: Extra Costs：$8.64 | X28: 0840148215733 | Y28: 标准美文版本 （13位数UPC条码） | Z28: 美文版本说明书 | AA28: RR25226 | AB28: 外箱不需要盖日期码 | AC28: 2.1 | AD28: =AC28*I28 -> 302.4 | AE28: =AD28*7.75 -> 2343.6 | AI28: 已入系统 | AL28: =IFERROR(VLOOKUP(G28,'已打发票扣数（26年5月开始）'!$A$1:$C$17,3,0)*I28*0.3,"") -> 90.72
A29: 46245 | B29: 上海 | C29: Elaine | D29: WRT | E29: 26-3202008JDO | F29: PO215031 | G29: T02444 | H29: =VLOOKUP(G29,名称!A:B,2,0) -> 恐龙公园二代 | I29: 144 | J29: =VLOOKUP(G29,名称!A:C,3,FALSE) -> 12 | K29: =I29/J29 -> 12 | L29: 46286 | M29: =L29-7 -> 46279 | N29: =M29 -> 46279 | X29: 0840148221734 | Y29: 标准美文版本 （13位数UPC条码） | Z29: 美文版本说明书 | AA29: RR25226 | AB29: 外箱不需要盖日期码 | AC29: 2.1 | AD29: =AC29*I29 -> 302.4 | AE29: =AD29*7.75 -> 2343.6 | AI29: 已入系统 | AL29: =IFERROR(VLOOKUP(G29,'已打发票扣数（26年5月开始）'!$A$1:$C$17,3,0)*I29*0.3,"") -> 90.72
A30: 46245 | B30: 上海 | C30: Elaine | D30: WRT | E30: 26-3202007JEC | F30: PO215029 | G30: T01535 | H30: =VLOOKUP(G30,名称!A:B,2,0) -> 恐龙公园 | I30: 504 | J30: =VLOOKUP(G30,名称!A:C,3,FALSE) -> 12 | K30: =I30/J30 -> 42 | L30: 46286 | M30: =L30-7 -> 46279 | N30: =M30 -> 46279 | Q30: Extra Costs：$30.24 | X30: 0840148215733 | Y30: 标准美文版本 （13位数UPC条码） | Z30: 美文版本说明书 | AA30: RR25226 | AB30: 外箱不需要盖日期码 | AC30: 2.1 | AD30: =AC30*I30 -> 1058.4 | AE30: =AD30*7.75 -> 8202.6 | AI30: 已入系统 | AL30: =IFERROR(VLOOKUP(G30,'已打发票扣数（26年5月开始）'!$A$1:$C$17,3,0)*I30*0.3,"") -> 317.52
A31: 46245 | B31: 上海 | C31: Elaine | D31: WRT | E31: 26-3202007JEC | F31: PO215029 | G31: T02444 | H31: =VLOOKUP(G31,名称!A:B,2,0) -> 恐龙公园二代 | I31: 504 | J31: =VLOOKUP(G31,名称!A:C,3,FALSE) -> 12 | K31: =I31/J31 -> 42 | L31: 46286 | M31: =L31-7 -> 46279 | N31: =M31 -> 46279 | X31: 0840148221734 | Y31: 标准美文版本 （13位数UPC条码） | Z31: 美文版本说明书 | AA31: RR25226 | AB31: 外箱不需要盖日期码 | AC31: 2.1 | AD31: =AC31*I31 -> 1058.4 | AE31: =AD31*7.75 -> 8202.6 | AI31: 已入系统 | AL31: =IFERROR(VLOOKUP(G31,'已打发票扣数（26年5月开始）'!$A$1:$C$17,3,0)*I31*0.3,"") -> 317.52
AD32: =AC32*I32 -> 0 | AE32: =AD32*7.75 -> 0 | AL32: =IFERROR(VLOOKUP(G32,'已打发票扣数（26年5月开始）'!$A$1:$C$17,3,0)*I32*0.3,"")
AD33: =AC33*I33 -> 0 | AE33: =AD33*7.75 -> 0 | AL33: =IFERROR(VLOOKUP(G33,'已打发票扣数（26年5月开始）'!$A$1:$C$17,3,0)*I33*0.3,"")
AD34: =AC34*I34 -> 0 | AE34: =AD34*7.75 -> 0 | AL34: =IFERROR(VLOOKUP(G34,'已打发票扣数（26年5月开始）'!$A$1:$C$17,3,0)*I34*0.3,"")
AD35: =AC35*I35 -> 0 | AE35: =AD35*7.75 -> 0 | AL35: =IFERROR(VLOOKUP(G35,'已打发票扣数（26年5月开始）'!$A$1:$C$17,3,0)*I35*0.3,"")
AD36: =AC36*I36 -> 0 | AE36: =AD36*7.75 -> 0 | AL36: =IFERROR(VLOOKUP(G36,'已打发票扣数（26年5月开始）'!$A$1:$C$17,3,0)*I36*0.3,"")
AD37: =AC37*I37 -> 0 | AE37: =AD37*7.75 -> 0 | AL37: =IFERROR(VLOOKUP(G37,'已打发票扣数（26年5月开始）'!$A$1:$C$17,3,0)*I37*0.3,"")
AD38: =AC38*I38 -> 0 | AE38: =AD38*7.75 -> 0 | AL38: =IFERROR(VLOOKUP(G38,'已打发票扣数（26年5月开始）'!$A$1:$C$17,3,0)*I38*0.3,"")
AD39: =AC39*I39 -> 0 | AE39: =AD39*7.75 -> 0 | AL39: =IFERROR(VLOOKUP(G39,'已打发票扣数（26年5月开始）'!$A$1:$C$17,3,0)*I39*0.3,"")
I40: =SUM(I2:I39) -> 17306 | AD40: =SUM(AD2:AD39) -> 56641.8 | AE40: =SUM(AE2:AE39) -> 438973.95

Sheet 已出货
A1: 接单期 | B1: 国家 | C1: 客跟单 | D1: 客户 | E1: Customer | F1: PO号 | G1: 货号 | H1: 名称 | I1: 数量 | J1: 装箱数 | K1: 总箱数 | L1: 客PO期 | M1: 出货期 | N1: 验货期 | O1: 是否验货 | P1: 验货结果 | Q1: 船期SO | R1: 吨车/柜货 | S1: 生产车间 | T1: 箱唛资料 | U1: 客贴纸 | V1: 是否寄出签办 | W1: 是否打卡板 | X1: 彩盒UPC条码 | Y1: 彩盒版本 | Z1: 说明书版本 | AA1: 日期码 | AB1: 备注 | AC1: 单价 | AD1: 金额USD | AE1: 金额HKD | AF1: 发票号 | AG1: 走柜/散货 | AH1: 出货日期 | AI1: 是否入系统 | AJ1: 下单情况 | AK1: 贴纸情况 | AL1: 首期扣数30%
A2: 45967 | B2: 越南 | C2: Elaine | D2: Viet Tinh Anh Joint Stock Company | E2: Viet-TM110225 | F2: PO211348 | G2: T02444 | H2: =VLOOKUP(G2,名称!A:B,2,0) -> 恐龙公园二代 | I2: 1680 | J2: =VLOOKUP(G2,名称!A:C,3,FALSE) -> 12 | K2: =I2/J2 -> 140 | L2: 46021 | M2: 46021 | N2: 46021 | O2: 已约 | Q2: 1/6 extra costs:$300 | R2: 5吨车 | T2: OK | X2: 草地套装：0840148226203 海滩滩套装：0840148226210 实验室套装：0840148226227 | Y2: 标准美文版本 （13位数UPC条码） | Z2: 美文版本说明书 | AA2: RR35925 | AC2: 2.1 | AD2: =AC2*I2 -> 3528 | AE2: =AD2*7.75 -> 27342 | AF2: 83213 | AG2: =VLOOKUP(AF2,'[2]Toy Monster'!$L:$M,2,0) -> RR02车 | AH2: =VLOOKUP(AF2,'[2]Toy Monster'!$L:$T,9,FALSE) -> 46027 | AI2: 已入系统 | AL2: =IFERROR(VLOOKUP(G2,'已打发票扣数（26年5月开始）'!$A$1:$C$17,3,0)*I2*0.3,"") -> 1058.4
A3: 45989 | B3: 澳大利亚 | C3: Rachel | D3: Woolworths Group Limited t/a Big W | E3: 47895690 | F3: PO211747 | G3: JW-RV-RPGE | H3: =VLOOKUP(G3,名称!A:B,2,0) -> 恐龙游戏盘 | I3: 1014 | J3: =VLOOKUP(G3,名称!A:C,3,FALSE) -> 6 | K3: =I3/J3 -> 169 | L3: 46041 | M3: 46036 | N3: 46036 | O3: 已约 | P3: OK | T3: OK | X3: 0840148207301 | Y3: 标准美文版本 （13位数UPC条码） | Z3: 美文版本说明书 | AA3: 090126 | AC3: 4.5 | AD3: =AC3*I3 -> 4563 | AE3: =AD3*7.75 -> 35363.25 | AF3: 83218 | AG3: =VLOOKUP(AF3,'[2]Toy Monster'!$L:$M,2,0) -> RR19车 | AH3: =VLOOKUP(AF3,'[2]Toy Monster'!$L:$T,9,FALSE) -> 46048 | AI3: 已入系统 | AL3: =IFERROR(VLOOKUP(G3,'已打发票扣数（26年5月开始）'!$A$1:$C$17,3,0)*I3*0.3,"") -> 1368.9
A4: 45989 | B4: 澳大利亚 | C4: Rachel | D4: Woolworths Group Limited t/a Big W | E4: 47896520 | F4: PO211748 | G4: JW-RV-RPGE | H4: =VLOOKUP(G4,名称!A:B,2,0) -> 恐龙游戏盘 | I4: 624 | J4: =VLOOKUP(G4,名称!A:C,3,FALSE) -> 6 | K4: =I4/J4 -> 104 | L4: 46041 | M4: 46036 | N4: 46036 | O4: 已约 | P4: OK | Q4: Extra Costs:$200 | T4: OK | X4: 0840148207301 | Y4: 标准美文版本 （13位数UPC条码） | Z4: 美文版本说明书 | AA4: 090126 | AC4: 4.5 | AD4: =AC4*I4 -> 2808 | AE4: =AD4*7.75 -> 21762 | AF4: 83219 | AG4: =VLOOKUP(AF4,'[2]Toy Monster'!$L:$M,2,0) -> RR19车 | AH4: =VLOOKUP(AF4,'[2]Toy Monster'!$L:$T,9,FALSE) -> 46048 | AI4: 已入系统 | AL4: =IFERROR(VLOOKUP(G4,'已打发票扣数（26年5月开始）'!$A$1:$C$17,3,0)*I4*0.3,"") -> 842.4
A5: 46010 | B5: 澳大利亚 | C5: Rachel | D5: Woolworths Group Limited t/a Big W | E5: 47905042 | F5: PO212018 | G5: JW-RV-RPGE | H5: =VLOOKUP(G5,名称!A:B,2,0) -> 恐龙游戏盘 | I5: 1200 | J5: =VLOOKUP(G5,名称!A:C,3,FALSE) -> 6 | K5: =I5/J5 -> 200 | L5: 46041 | M5: 46036 | N5: 46036 | O5: 已约 | P5: OK | T5: OK | X5: 0840148207301 | Y5: 标准美文版本 （13位数UPC条码） | Z5: 美文版本说明书 | AA5: 090126 | AC5: 4.5 | AD5: =AC5*I5 -> 5400 | AE5: =AD5*7.75 -> 41850 | AF5: 83220 | AG5: =VLOOKUP(AF5,'[2]Toy Monster'!$L:$M,2,0) -> RR19车 | AH5: =VLOOKUP(AF5,'[2]Toy Monster'!$L:$T,9,FALSE) -> 46048 | AI5: 已入系统 | AL5: =IFERROR(VLOOKUP(G5,'已打发票扣数（26年5月开始）'!$A$1:$C$17,3,0)*I5*0.3,"") -> 1620
A6: 45996 | B6: 香港 | C6: Elaine | D6: Asia Goal Limited | E6: PO-AG250344 | F6: PO211794 | G6: T02444 | H6: =VLOOKUP(G6,名称!A:B,2,0) -> 恐龙公园二代 | I6: 720 | J6: =VLOOKUP(G6,名称!A:C,3,FALSE) -> 12 | K6: =I6/J6 -> 60 | L6: 46043 | M6: 46043 | N6: 46043 | O6: 已约 | P6: OK | R6: EXW | T6: OK | X6: 草地套装：0840148226203 海滩滩套装：0840148226210 实验室套装：0840148226227 | Y6: 标准美文版本 （13位数UPC条码） | Z6: 美文版本说明书 | AA6: RR35925 | AC6: 2.1 | AD6: =AC6*I6 -> 1512 | AE6: =AD6*7.75 -> 11718 | AF6: 83221 | AG6: =VLOOKUP(AF6,'[2]Toy Monster'!$L:$M,2,0) -> RR27客上车 | AH6: =VLOOKUP(AF6,'[2]Toy Monster'!$L:$T,9,FALSE) -> 46052 | AI6: 已入系统 | AK6: 客贴纸12/29给到佩玲 | AL6: =IFERROR(VLOOKUP(G6,'已打发票扣数（26年5月开始）'!$A$1:$C$17,3,0)*I6*0.3,"") -> 453.6
A7: 45981 | B7: 乌克兰 | C7: Rainbow | D7: AMIGO & F Ltd | E7: Kuma Paw 0126 | F7: PO211615 | G7: T02943 | H7: =VLOOKUP(G7,名称!A:B,2,0) -> 9.5寸粉红熊公仔（移印） | I7: 800 | J7: =VLOOKUP(G7,名称!A:C,3,FALSE) -> 2 | K7: =I7/J7 -> 400 | L7: 46045 | M7: 46036 | N7: 46036 | O7: 已约 | P7: OK | Q7: extra costs:$16 | R7: 20GP | T7: OK | X7: 840148224445 | Y7: 沃尔玛版本彩盒 （12位数UPC条码） | Z7: / | AA7: RR00526 | AC7: 6.2 | AD7: =AC7*I7 -> 4960 | AE7: =AD7*7.75 -> 38440 | AF7: 83222 | AG7: =VLOOKUP(AF7,'[2]Toy Monster'!$L:$M,2,0) -> RR103柜 | AH7: =VLOOKUP(AF7,'[2]Toy Monster'!$L:$T,9,FALSE) -> 46052 | AI7: 已入系统 | AK7: 客贴纸/条形码贴纸 | AL7: =IFERROR(VLOOKUP(G7,'已打发票扣数（26年5月开始）'!$A$1:$C$17,3,0)*I7*0.3,"") -> 1521.6
A8: 45981 | B8: 乌克兰 | C8: Rainbow | D8: AMIGO & F Ltd | E8: Kuma Paw 0126 | F8: PO211615 | G8: T02945 | H8: =VLOOKUP(G8,名称!A:B,2,0) -> 9.5寸格力奇公仔 （移印） | I8: 800 | J8: =VLOOKUP(G8,名称!A:C,3,FALSE) -> 2 | K8: =I8/J8 -> 400 | L8: 46045 | M8: 46036 | N8: 46036 | O8: 已约 | P8: OK | Q8: extra costs:$16 | R8: 20GP | T8: OK | X8: 840148224469 | Y8: 沃尔玛版本彩盒 （12位数UPC条码） | Z8: / | AA8: RR00526 | AC8: 6.5 | AD8: =AC8*I8 -> 5200 | AE8: =AD8*7.75 -> 40300 | AF8: 83222 | AG8: =VLOOKUP(AF8,'[2]Toy Monster'!$L:$M,2,0) -> RR103柜 | AH8: =VLOOKUP(AF8,'[2]Toy Monster'!$L:$T,9,FALSE) -> 46052 | AI8: 已入系统 | AK8: 客贴纸/条形码贴纸 | AL8: =IFERROR(VLOOKUP(G8,'已打发票扣数（26年5月开始）'!$A$1:$C$17,3,0)*I8*0.3,"") -> 1593.6
A9: 45986 | B9: 美国 | C9: Jennifer | D9: Monster Group LLC | E9: WM Domestic Order | F9: PO211734 | G9: T02943 | H9: =VLOOKUP(G9,名称!A:B,2,0) -> 9.5寸粉红熊公仔（移印） | I9: 2304 | J9: =VLOOKUP(G9,名称!A:C,3,FALSE) -> 2 | K9: =I9/J9 -> 1152 | L9: 46037 | M9: 46036 | N9: 46036 | O9: 已约 | P9: OK | Q9: 46053 | R9: 10吨车 | T9: OK | X9: 840148224445 | Y9: 沃尔玛版本彩盒 （12位数UPC条码） | Z9: / | AA9: RR00526 | AB9: 出货后PO号跟改为：212368 | AC9: 6.2 | AD9: =AC9*I9 -> 14284.8 | AE9: =AD9*7.75 -> 110707.2 | AF9: 83223 | AG9: =VLOOKUP(AF9,'[2]Toy Monster'!$L:$M,2,0) -> RR21车 | AH9: =VLOOKUP(AF9,'[2]Toy Monster'!$L:$T,9,FALSE) -> 46059 | AI9: 已入系统 | AK9: RFID贴纸12/10日给到佩玲 | AL9: =IFERROR(VLOOKUP(G9,'已打发票扣数（26年5月开始）'!$A$1:$C$17,3,0)*I9*0.3,"") -> 4382.21
A10: 45986 | B10: 美国 | C10: Jennifer | D10: Monster Group LLC | E10: WM Domestic Order | F10: PO211734 | G10: T02945 | H10: =VLOOKUP(G10,名称!A:B,2,0) -> 9.5寸格力奇公仔 （移印） | I10: 2304 | J10: =VLOOKUP(G10,名称!A:C,3,FALSE) -> 2 | K10: =I10/J10 -> 1152 | L10: 46037 | M10: 46036 | N10: 46036 | O10: 已约 | P10: OK | Q10: 46053 | R10: 10吨车 | T10: OK | X10: 840148224469 | Y10: 沃尔玛版本彩盒 （12位数UPC条码） | Z10: / | AA10: RR00526 | AB10: 出货后PO号跟改为：212368 | AC10: 6.5 | AD10: =AC10*I10 -> 14976 | AE10: =AD10*7.75 -> 116064 | AF10: 83223 | AG10: =VLOOKUP(AF10,'[2]Toy Monster'!$L:$M,2,0) -> RR21车 | AH10: =VLOOKUP(AF10,'[2]Toy Monster'!$L:$T,9,FALSE) -> 46059 | AI10: 已入系统 | AK10: RFID贴纸12/10日给到佩玲 | AL10: =IFERROR(VLOOKUP(G10,'已打发票扣数（26年5月开始）'!$A$1:$C$17,3,0)*I10*0.3,"") -> 4589.57
A11: 46010 | B11: 美国 | C11: Jennifer | D11: Monster Group LLC | E11: WM Domestic Order | F11: PO212104 | G11: T03190 | H11: =VLOOKUP(G11,名称!A:B,2,0) -> FLiar | I11: 4676 | J11: =VLOOKUP(G11,名称!A:C,3,FALSE) -> 2 | K11: =I11/J11 -> 2338 | L11: 46052 | M11: =L11-4 -> 46048 | N11: 46056 | O11: 已约 | P11: OK | Q11: 2/7-2/9 | R11: 40HQ | T11: OK | X11: 840148226241 | Y11: 沃尔玛版本彩盒 （12位数UPC条码） | Z11: / | AA11: RR02126 | AC11: 6.15 | AD11: =AC11*I11 -> 28757.4 | AE11: =AD11*7.75 -> 222869.85 | AF11: 83224 | AG11: =VLOOKUP(AF11,'[2]Toy Monster'!$L:$M,2,0) -> RR131-132柜 | AH11: =VLOOKUP(AF11,'[2]Toy Monster'!$L:$T,9,FALSE) -> 46062 | AI11: 已入系统 | AK11: RFID贴纸12/29给到佩玲 | AL11: =IFERROR(VLOOKUP(G11,'已打发票扣数（26年5月开始）'!$A$1:$C$17,3,0)*I11*0.3,"")
A12: 46010 | B12: 美国 | C12: Jennifer | D12: Monster Group LLC | E12: WM Domestic Order | F12: PO212104 | G12: T03191 | H12: =VLOOKUP(G12,名称!A:B,2,0) -> Striker | I12: 4376 | J12: =VLOOKUP(G12,名称!A:C,3,FALSE) -> 2 | K12: =I12/J12 -> 2188 | L12: 46052 | M12: =L12-4 -> 46048 | N12: 46056 | O12: 已约 | P12: OK | Q12: 2/7-2/9 | R12: 40HQ | T12: OK | X12: 840148226258 | Y12: 沃尔玛版本彩盒 （12位数UPC条码） | Z12: / | AA12: RR02126 | AC12: 6.47 | AD12: =AC12*I12 -> 28312.72 | AE12: =AD12*7.75 -> 219423.58 | AF12: 83224 | AG12: =VLOOKUP(AF12,'[2]Toy Monster'!$L:$M,2,0) -> RR131-132柜 | AH12: =VLOOKUP(AF12,'[2]Toy Monster'!$L:$T,9,FALSE) -> 46062 | AI12: 已入系统 | AK12: RFID贴纸12/29给到佩玲 | AL12: =IFERROR(VLOOKUP(G12,'已打发票扣数（26年5月开始）'!$A$1:$C$17,3,0)*I12*0.3,"")
A13: 46010 | B13: 美国 | C13: Jennifer | D13: Monster Group LLC | E13: WM Domestic Order | F13: PO212104 | G13: T03192 | H13: =VLOOKUP(G13,名称!A:B,2,0) -> Clutch | I13: 4476 | J13: =VLOOKUP(G13,名称!A:C,3,FALSE) -> 2 | K13: =I13/J13 -> 2238 | L13: 46052 | M13: =L13-4 -> 46048 | N13: 46056 | O13: 已约 | P13: OK | Q13: 2/7-2/9 | R13: 40HQ | T13: OK | X13: 840148226265 | Y13: 沃尔玛版本彩盒 （12位数UPC条码） | Z13: / | AA13: RR02126 | AC13: 5.59 | AD13: =AC13*I13 -> 25020.84 | AE13: =AD13*7.75 -> 193911.51 | AF13: 83224 | AG13: =VLOOKUP(AF13,'[2]Toy Monster'!$L:$M,2,0) -> RR131-132柜 | AH13: =VLOOKUP(AF13,'[2]Toy Monster'!$L:$T,9,FALSE) -> 46062 | AI13: 已入系统 | AK13: RFID贴纸12/29给到佩玲 | AL13: =IFERROR(VLOOKUP(G13,'已打发票扣数（26年5月开始）'!$A$1:$C$17,3,0)*I13*0.3,"")
A14: 45993 | B14: 新加坡 | C14: Elaine | D14: Sheng Tai Toys Pty Ltd | E14: Shengtai-TM110464 | F14: PO211605 | G14: T02444 | H14: =VLOOKUP(G14,名称!A:B,2,0) -> 恐龙公园二代 | I14: 1200 | J14: =VLOOKUP(G14,名称!A:C,3,FALSE) -> 12 | K14: =I14/J14 -> 100 | L14: 46087 | M14: 46087 | N14: 46087 | O14: 已约 | P14: OK | Q14: 2026/3/10，Extra Costs:$300 | R14: 20GP | T14: OK | X14: 草地套装：0840148226203 海滩滩套装：0840148226210 实验室套装：0840148226227 | Y14: 标准美文版本 （13位数UPC条码） | Z14: 美文版本说明书 | AA14: RR35925 | AC14: 2.1 | AD14: =AC14*I14 -> 2520 | AE14: =AD14*7.75 -> 19530 | AF14: 83229REV1 | AG14: =VLOOKUP(AF14,'[2]Toy Monster'!$L:$M,2,0) -> RR155柜 | AH14: =VLOOKUP(AF14,'[2]Toy Monster'!$L:$T,9,FALSE) -> 46094 | AI14: 已入系统 | AL14: =IFERROR(VLOOKUP(G14,'已打发票扣数（26年5月开始）'!$A$1:$C$17,3,0)*I14*0.3,"") -> 756
A15: 46049 | B15: 澳大利亚 | C15: Rachel | D15: Woolworths Group Limited t/a Big W | E15: 47908798 | F15: PO212336 | G15: JW-RV-RPGE | H15: =VLOOKUP(G15,名称!A:B,2,0) -> 恐龙游戏盘 | I15: 1200 | J15: =VLOOKUP(G15,名称!A:C,3,FALSE) -> 6 | K15: =I15/J15 -> 200 | L15: 46107 | M15: 46107 | N15: 46107 | O15: 已约 | P15: OK | Q15: 46109 | T15: OK | X15: 0840148207301 | Y15: 标准美文版本 （13位数UPC条码） | Z15: 美文版本说明书 | AA15: 170326 | AB15: 生产彩盒时不要印日期码，日期码由湖南生产大货时打在彩盒上，注意不要漏打！ 包装以及说明书均为美文 | AC15: 4.5 | AD15: =AC15*I15 -> 5400 | AE15: =AD15*7.75 -> 41850 | AF15: 83230 | AG15: =VLOOKUP(AF15,'[2]Toy Monster'!$L:$M,2,0) -> RR80车 | AH15: =VLOOKUP(AF15,'[2]Toy Monster'!$L:$T,9,FALSE) -> 46111 | AI15: 已入系统 | AL15: =IFERROR(VLOOKUP(G15,'已打发票扣数（26年5月开始）'!$A$1:$C$17,3,0)*I15*0.3,"") -> 1620
A16: 46038 | B16: 美国 | C16: Jennifer | D16: Meijer LANSING | E16: 218955615 | F16: PO212267 | G16: T01453 | H16: =VLOOKUP(G16,名称!A:B,2,0) -> 恐龙游戏盘 | I16: 1000 | J16: =VLOOKUP(G16,名称!A:C,3,FALSE) -> 2 | K16: =I16/J16 -> 500 | L16: 46099 | M16: 46099 | N16: =M16 -> 46099 | O16: 已约 | P16: OK | Q16: 46100 | T16: OK | X16: 840148207301 | Y16: 沃尔玛版本彩盒 （12位数UPC条码） | Z16: 沃尔玛版本说明书 | AA16: RR07026 | AB16: 该订单与沃尔玛订单相似，但外箱箱唛不同请注意不要订错外箱，外箱不用加盖日期码。 | AC16: 4.5 | AD16: =AC16*I16 -> 4500 | AE16: =AD16*7.75 -> 34875 | AF16: 83231 | AG16: =VLOOKUP(AF16,'[2]Toy Monster'!$L:$M,2,0) -> RR70车 | AH16: =VLOOKUP(AF16,'[2]Toy Monster'!$L:$T,9,FALSE) -> 46111 | AI16: 已入系统 | AL16: =IFERROR(VLOOKUP(G16,'已打发票扣数（26年5月开始）'!$A$1:$C$17,3,0)*I16*0.3,"") -> 1350
A17: 46038 | B17: 美国 | C17: Jennifer | D17: Meijer LANSING | E17: 218955627 | F17: PO212268 | G17: T01453 | H17: =VLOOKUP(G17,名称!A:B,2,0) -> 恐龙游戏盘 | I17: 500 | J17: =VLOOKUP(G17,名称!A:C,3,FALSE) -> 2 | K17: =I17/J17 -> 250 | L17: 46099 | M17: 46099 | N17: =M17 -> 46099 | O17: 已约 | P17: OK | Q17: 46100 | T17: OK | X17: 840148207301 | Y17: 沃尔玛版本彩盒 （12位数UPC条码） | Z17: 沃尔玛版本说明书 | AA17: RR07026 | AB17: 该订单与沃尔玛订单相似，但外箱箱唛不同请注意不要订错外箱，外箱不用加盖日期码。 | AC17: 4.5 | AD17: =AC17*I17 -> 2250 | AE17: =AD17*7.75 -> 17437.5 | AF17: 83232 | AG17: =VLOOKUP(AF17,'[2]Toy Monster'!$L:$M,2,0) -> RR70车 | AH17: =VLOOKUP(AF17,'[2]Toy Monster'!$L:$T,9,FALSE) -> 46111 | AI17: 已入系统 | AL17: =IFERROR(VLOOKUP(G17,'已打发票扣数（26年5月开始）'!$A$1:$C$17,3,0)*I17*0.3,"") -> 675
A18: 45986 | B18: 美国 | C18: Jennifer | D18: Monster Group LLC | E18: WM Domestic Order | F18: PO212369 | G18: T02943 | H18: =VLOOKUP(G18,名称!A:B,2,0) -> 9.5寸粉红熊公仔（移印） | I18: 2500 | J18: =VLOOKUP(G18,名称!A:C,3,FALSE) -> 2 | K18: =I18/J18 -> 1250 | L18: 46086 | M18: =L18-7 -> 46079 | N18: 46056 | O18: 已约 | P18: OK | Q18: Extra Costs:$350 | R18: 10吨车 | T18: OK | X18: 840148224445 | Y18: 沃尔玛版本彩盒 （12位数UPC条码） | Z18: / | AA18: RR00526 | AB18: 原PO号：PO211734 | AC18: 6.2 | AD18: =AC18*I18 -> 15500 | AE18: =AD18*7.75 -> 120125 | AF18: 83233 | AG18: =VLOOKUP(AF18,'[2]Toy Monster'!$L:$M,2,0) -> RR86-87车 | AH18: =VLOOKUP(AF18,'[2]Toy Monster'!$L:$T,9,FALSE) -> 46112 | AI18: 已入系统 | AK18: RFID贴纸12/10日给到佩玲 | AL18: =IFERROR(VLOOKUP(G18,'已打发票扣数（26年5月开始）'!$A$1:$C$17,3,0)*I18*0.3,"") -> 4755
A19: 45986 | B19: 美国 | C19: Jennifer | D19: Monster Group LLC | E19: WM Domestic Order | F19: PO212369 | G19: T02945 | H19: =VLOOKUP(G19,名称!A:B,2,0) -> 9.5寸格力奇公仔 （移印） | I19: 2500 | J19: =VLOOKUP(G19,名称!A:C,3,FALSE) -> 2 | K19: =I19/J19 -> 1250 | L19: 46086 | M19: =L19-7 -> 46079 | N19: 46056 | O19: 已约 | P19: OK | Q19: Extra Costs:$350 | R19: 10吨车 | T19: OK | X19: 840148224469 | Y19: 沃尔玛版本彩盒 （12位数UPC条码） | Z19: / | AA19: RR00526 | AB19: 原PO号：PO211734 | AC19: 6.5 | AD19: =AC19*I19 -> 16250 | AE19: =AD19*7.75 -> 125937.5 | AF19: 83233 | AG19: =VLOOKUP(AF19,'[2]Toy Monster'!$L:$M,2,0) -> RR86-87车 | AH19: =VLOOKUP(AF19,'[2]Toy Monster'!$L:$T,9,FALSE) -> 46112 | AI19: 已入系统 | AK19: RFID贴纸12/10日给到佩玲 | AL19: =IFERROR(VLOOKUP(G19,'已打发票扣数（26年5月开始）'!$A$1:$C$17,3,0)*I19*0.3,"") -> 4980
A20: 46051 | B20: 美国 | C20: Jennifer | D20: Meijer LANSING | E20: 219021251 | F20: PO212355 | G20: T01453 | H20: =VLOOKUP(G20,名称!A:B,2,0) -> 恐龙游戏盘 | I20: 1000 | J20: =VLOOKUP(G20,名称!A:C,3,FALSE) -> 2 | K20: =I20/J20 -> 500 | L20: 46113 | M20: 46107 | N20: 46107 | O20: 已约 | P20: OK | Q20: 46112 | T20: OK | X20: 840148207301 | Y20: 沃尔玛版本彩盒 （12位数UPC条码） | Z20: 沃尔玛版本说明书 | AA20: RR08426 | AB20: 该订单与沃尔玛订单相似，但外箱箱唛不同请注意不要订错外箱，外箱不用加盖日期码。 | AC20: 4.5 | AD20: =AC20*I20 -> 4500 | AE20: =AD20*7.75 -> 34875 | AF20: 83234 | AG20: =VLOOKUP(AF20,'[2]Toy Monster'!$L:$M,2,0) -> RR82车 | AH20: =VLOOKUP(AF20,'[2]Toy Monster'!$L:$T,9,FALSE) -> 46112 | AI20: 已入系统 | AL20: =IFERROR(VLOOKUP(G20,'已打发票扣数（26年5月开始）'!$A$1:$C$17,3,0)*I20*0.3,"") -> 1350
A21: 46051 | B21: 美国 | C21: Jennifer | D21: Meijer LANSING | E21: 219021257 | F21: PO212356 | G21: T01453 | H21: =VLOOKUP(G21,名称!A:B,2,0) -> 恐龙游戏盘 | I21: 500 | J21: =VLOOKUP(G21,名称!A:C,3,FALSE) -> 2 | K21: =I21/J21 -> 250 | L21: 46113 | M21: 46107 | N21: 46107 | O21: 已约 | P21: OK | Q21: 46112 | T21: OK | X21: 840148207301 | Y21: 沃尔玛版本彩盒 （12位数UPC条码） | Z21: 沃尔玛版本说明书 | AA21: RR08426 | AB21: 该订单与沃尔玛订单相似，但外箱箱唛不同请注意不要订错外箱，外箱不用加盖日期码。 | AC21: 4.5 | AD21: =AC21*I21 -> 2250 | AE21: =AD21*7.75 -> 17437.5 | AF21: 83235 | AG21: =VLOOKUP(AF21,'[2]Toy Monster'!$L:$M,2,0) -> RR82车 | AH21: =VLOOKUP(AF21,'[2]Toy Monster'!$L:$T,9,FALSE) -> 46112 | AI21: 已入系统 | AL21: =IFERROR(VLOOKUP(G21,'已打发票扣数（26年5月开始）'!$A$1:$C$17,3,0)*I21*0.3,"") -> 675
A22: 46062 | B22: 英国 | C22: Rainbow Peng | D22: Smyths Toys HQ UC | E22: 4400542038 | F22: PO212408 | G22: JW-RV-RPGE | H22: =VLOOKUP(G22,名称!A:B,2,0) -> 恐龙游戏盘 | I22: 6306 | J22: =VLOOKUP(G22,名称!A:C,3,FALSE) -> 6 | K22: =I22/J22 -> 1051 | L22: 46118 | M22: 46113 | N22: =M22 -> 46113 | O22: 已约 | P22: OK | Q22: 46120 | R22: 40GP | T22: OK | X22: 0840148207301 | Y22: Smyths客版彩盒 （13位数UPC条码） | Z22: 5国语言客版说明书 | AA22: 042026 | AB22: 生产彩盒时不要印日期码，日期码由湖南生产大货时打在彩盒上，注意不要漏打！ 包装以及说明书均为5国语 | AC22: 4.5 | AD22: =AC22*I22 -> 28377 | AE22: =AD22*7.75 -> 219921.75 | AF22: 83236 | AG22: =VLOOKUP(AF22,'[2]Toy Monster'!$L:$M,2,0) -> RR169柜 | AH22: =VLOOKUP(AF22,'[2]Toy Monster'!$L:$T,9,FALSE) -> 46122 | AI22: 已入系统 | AL22: =IFERROR(VLOOKUP(G22,'已打发票扣数（26年5月开始）'!$A$1:$C$17,3,0)*I22*0.3,"") -> 8513.1
A23: 46083 | B23: 新西兰 | C23: Rachel | D23: Kmart Australia & NZ Holding Limited | E23: 21559600 | F23: PO212479 | G23: T02444 | H23: =VLOOKUP(G23,名称!A:B,2,0) -> 恐龙公园二代 | I23: 564 | J23: =VLOOKUP(G23,名称!A:C,3,FALSE) -> 12 | K23: =I23/J23 -> 47 | L23: 46122 | M23: 46122 | N23: 46122 | O23: 已约 | Q23: 4/11 extra costs:$2.585 | R23: 5吨车 | T23: OK | X23: 草地套装：0840148226203 海滩滩套装：0840148226210 实验室套装：0840148226227 | Y23: 标准美文版本 （13位数UPC条码） | Z23: 美文版本说明书 | AA23: 46138 | AB23: 外箱上面两面都需要工字形ANKO胶带封箱 | AC23: 2.1 | AD23: =AC23*I23 -> 1184.4 | AE23: =AD23*7.75 -> 9179.1 | AF23: 83237 | AG23: =VLOOKUP(AF23,'[2]Toy Monster'!$L:$M,2,0) -> RR94车 | AH23: =VLOOKUP(AF23,'[2]Toy Monster'!$L:$T,9,FALSE) -> 46127 | AI23: 已入系统 | AK23: SSCC贴纸3/30给到佩玲 | AL23: =IFERROR(VLOOKUP(G23,'已打发票扣数（26年5月开始）'!$A$1:$C$17,3,0)*I23*0.3,"") -> 355.32
A24: 46083 | B24: 澳大利亚 | C24: Rachel | D24: Kmart Australia & NZ Holding Limited | E24: 21559598 | F24: PO212478 | G24: T02444 | H24: =VLOOKUP(G24,名称!A:B,2,0) -> 恐龙公园二代 | I24: 6156 | J24: =VLOOKUP(G24,名称!A:C,3,FALSE) -> 12 | K24: =I24/J24 -> 513 | L24: 46122 | M24: 46122 | N24: 46122 | O24: 已约 | Q24: 4/11 extra costs:$28.215 | R24: 5吨车 | T24: OK | X24: 草地套装：0840148226203 海滩滩套装：0840148226210 实验室套装：0840148226227 | Y24: 标准美文版本 （13位数UPC条码） | Z24: 美文版本说明书 | AA24: 46138 | AB24: 外箱上面两面都需要工字形ANKO胶带封箱 | AC24: 2.1 | AD24: =AC24*I24 -> 12927.6 | AE24: =AD24*7.75 -> 100188.9 | AF24: 83238 | AG24: =VLOOKUP(AF24,'[2]Toy Monster'!$L:$M,2,0) -> RR94车 | AH24: =VLOOKUP(AF24,'[2]Toy Monster'!$L:$T,9,FALSE) -> 46127 | AI24: 已入系统 | AK24: SSCC贴纸3/30给到佩玲 | AL24: =IFERROR(VLOOKUP(G24,'已打发票扣数（26年5月开始）'!$A$1:$C$17,3,0)*I24*0.3,"") -> 3878.28
A25: 46030 | B25: 中国台湾 | C25: Elaine | D25: Asia Goal Limited | E25: PO-AG250418 | F25: PO212218 | G25: T02444 | H25: =VLOOKUP(G25,名称!A:B,2,0) -> 恐龙公园二代 | I25: 780 | J25: =VLOOKUP(G25,名称!A:C,3,FALSE) -> 12 | K25: =I25/J25 -> 65 | L25: 46108 | M25: 46107 | N25: 46107 | O25: 已约 | P25: OK | Q25: 46125 | R25: 客自提 | T25: OK | X25: 草地套装：0840148226203 海滩滩套装：0840148226210 实验室套装：0840148226227 | Y25: 标准美文版本 （13位数UPC条码） | Z25: 美文版本说明书 | AA25: RR35925 | AC25: 2.1 | AD25: =AC25*I25 -> 1638 | AE25: =AD25*7.75 -> 12694.5 | AF25: 83239 | AG25: =VLOOKUP(AF25,'[2]Toy Monster'!$L:$M,2,0) -> RR103车 | AH25: =VLOOKUP(AF25,'[2]Toy Monster'!$L:$T,9,FALSE) -> 46127 | AI25: 已入系统 | AK25: 客贴纸2/2日给到佩玲 | AL25: =IFERROR(VLOOKUP(G25,'已打发票扣数（26年5月开始）'!$A$1:$C$17,3,0)*I25*0.3,"") -> 491.4
A26: 46030 | B26: 中国台湾 | C26: Elaine | D26: Asia Goal Limited | E26: PO-AG250418 | F26: PO212218 | G26: JW-RV-RPGE | H26: =VLOOKUP(G26,名称!A:B,2,0) -> 恐龙游戏盘 | I26: 180 | J26: =VLOOKUP(G26,名称!A:C,3,FALSE) -> 6 | K26: =I26/J26 -> 30 | L26: 46108 | M26: 46107 | N26: 46107 | O26: 已约 | P26: OK | Q26: 46125 | R26: 客自提 | T26: OK | X26: 0840148207301 | Y26: 标准美文版本 （13位数UPC条码） | Z26: 美文版本说明书 | AA26: 090126 | AC26: 4.5 | AD26: =AC26*I26 -> 810 | AE26: =AD26*7.75 -> 6277.5 | AF26: 83239 | AG26: =VLOOKUP(AF26,'[2]Toy Monster'!$L:$M,2,0) -> RR103车 | AH26: =VLOOKUP(AF26,'[2]Toy Monster'!$L:$T,9,FALSE) -> 46127 | AI26: 已入系统 | AK26: 客贴纸2/2日给到佩玲 | AL26: =IFERROR(VLOOKUP(G26,'已打发票扣数（26年5月开始）'!$A$1:$C$17,3,0)*I26*0.3,"") -> 243
A27: 46030 | B27: 中国台湾 | C27: Elaine | D27: Asia Goal Limited | E27: PO-AG250418 | F27: PO212218 | G27: T01685 | H27: =VLOOKUP(G27,名称!A:B,2,0) -> 手术游戏盘 | I27: 180 | J27: =VLOOKUP(G27,名称!A:C,3,FALSE) -> 6 | K27: =I27/J27 -> 30 | L27: 46108 | M27: 46107 | N27: 46107 | O27: 已约 | P27: OK | Q27: 4/13 extra costs:$60 | R27: 客自提 | T27: OK | X27: 0840148217751 | Y27: 标准美文版本 （13位数UPC条码） | Z27: 美文版本说明书 | AA27: 03/26 | AC27: 4.43 | AD27: =AC27*I27 -> 797.4 | AE27: =AD27*7.75 -> 6179.85 | AF27: 83239 | AG27: =VLOOKUP(AF27,'[2]Toy Monster'!$L:$M,2,0) -> RR103车 | AH27: =VLOOKUP(AF27,'[2]Toy Monster'!$L:$T,9,FALSE) -> 46127 | AI27: 已入系统 | AK27: 客贴纸2/2日给到佩玲 | AL27: =IFERROR(VLOOKUP(G27,'已打发票扣数（26年5月开始）'!$A$1:$C$17,3,0)*I27*0.3,"") -> 244.08
A28: 46086 | B28: 美国 | C28: Elaine | D28: Flybar Inc | E28: FB-7504 | F28: PO212516 | G28: JW-RV-RPGEA | H28: =VLOOKUP(G28,名称!A:B,2,0) -> 恐龙游戏盘(邮包盒装) | I28: 504 | J28: =VLOOKUP(G28,名称!A:C,3,FALSE) -> 6 | K28: =I28/J28 -> 84 | L28: 46134 | M28: 46122 | N28: 46122 | O28: 已约 | P28: OK | Q28: Extra Costs：$120 | R28: 40GP | T28: OK | X28: 0840148227217 | Y28: 标准美文版本 （12位数UPC条码） | Z28: 美文版本说明书 | AA28: 46113 | AC28: 4.9 | AD28: =AC28*I28 -> 2469.6 | AE28: =AD28*7.75 -> 19139.4 | AF28: 83240 | AG28: =VLOOKUP(AF28,'[2]Toy Monster'!$L:$M,2,0) -> RR201柜 | AH28: =VLOOKUP(AF28,'[2]Toy Monster'!$L:$T,9,FALSE) -> 46141 | AI28: 已入系统 | AK28: 追踪贴纸/条形码贴纸 | AL28: =IFERROR(VLOOKUP(G28,'已打发票扣数（26年5月开始）'!$A$1:$C$17,3,0)*I28*0.3,"") -> 680.4
A29: 46101 | B29: 澳大利亚 | C29: Rachel | D29: Kmart Australia & NZ Holding Limited | E29: 21657135 | F29: PO212624 | G29: T02444 | H29: =VLOOKUP(G29,名称!A:B,2,0) -> 恐龙公园二代 | I29: 6288 | J29: =VLOOKUP(G29,名称!A:C,3,FALSE) -> 12 | K29: =I29/J29 -> 524 | L29: 46142 | M29: 46135 | N29: 46135 | O29: 已约 | P29: OK | Q29: 4/27 Extra Costs：$28.82 | R29: 5吨车 | T29: OK | X29: 草地套装：0840148226203 海滩滩套装：0840148226210 实验室套装：0840148226227 | Y29: 标准美文版本 （13位数UPC条码） | Z29: 美文版本说明书 | AA29: 46138 | AB29: 外箱上下两面都需要工字形ANKO胶带封箱 | AC29: 2.1 | AD29: =AC29*I29 -> 13204.8 | AE29: =AD29*7.75 -> 102337.2 | AF29: 83241 | AG29: =VLOOKUP(AF29,'[2]Toy Monster'!$L:$M,2,0) -> RR128车 | AH29: =VLOOKUP(AF29,'[2]Toy Monster'!$L:$T,9,FALSE) -> 46141 | AI29: 已入系统 | AK29: SSCC贴纸4/2给到佩玲 | AL29: =IFERROR(VLOOKUP(G29,'已打发票扣数（26年5月开始）'!$A$1:$C$17,3,0)*I29*0.3,"") -> 3961.44
A30: 46101 | B30: 澳大利亚 | C30: Rachel | D30: Kmart Australia & NZ Holding Limited | E30: 21602319 | F30: PO212625 | G30: T02444 | H30: =VLOOKUP(G30,名称!A:B,2,0) -> 恐龙公园二代 | I30: 432 | J30: =VLOOKUP(G30,名称!A:C,3,FALSE) -> 12 | K30: =I30/J30 -> 36 | L30: 46136 | M30: 46135 | N30: 46135 | O30: 已约 | P30: OK | Q30: 4/27 Extra Costs：$1.98 | R30: 5吨车 | T30: OK | X30: 草地套装：0840148226203 海滩滩套装：0840148226210 实验室套装：0840148226227 | Y30: 标准美文版本 （13位数UPC条码） | Z30: 美文版本说明书 | AA30: 46138 | AB30: 外箱上下两面都需要工字形ANKO胶带封箱 | AC30: 2.1 | AD30: =AC30*I30 -> 907.2 | AE30: =AD30*7.75 -> 7030.8 | AF30: 83242 | AG30: =VLOOKUP(AF30,'[2]Toy Monster'!$L:$M,2,0) -> RR128车 | AH30: =VLOOKUP(AF30,'[2]Toy Monster'!$L:$T,9,FALSE) -> 46141 | AI30: 已入系统 | AK30: SSCC贴纸4/2给到佩玲 | AL30: =IFERROR(VLOOKUP(G30,'已打发票扣数（26年5月开始）'!$A$1:$C$17,3,0)*I30*0.3,"") -> 272.16
A31: 46077 | B31: 美国 | C31: Jennifer | D31: Monster Group LLC | E31: Kuma Paw 9.5 inch for WM Domestic Order | F31: PO212438 | G31: T03204 | H31: =VLOOKUP(G31,名称!A:B,2,0) -> 9.5寸粉红熊公仔+格力奇熊仔混装 | I31: 5400 | J31: =VLOOKUP(G31,名称!A:C,3,FALSE) -> 2 | K31: =I31/J31 -> 2700 | L31: 46157 | M31: 46153 | N31: 46153 | O31: 已约 | P31: OK | Q31: 46160 | R31: 5吨车 | T31: OK | X31: 840148224445 840148224469 | Y31: 沃尔玛版本彩盒 （12位数UPC条码） | Z31: / | AA31: RR11226 | AB31: 9.5寸粉红色熊仔脚底码货号为：T02943-2，与9.5寸格力奇熊仔混装，配比1:1 | AC31: 6.67 | AD31: =AC31*I31 -> 36018 | AE31: =AD31*7.75 -> 279139.5 | AF31: 83246REV1 | AG31: =VLOOKUP(AF31,'[2]Toy Monster'!$L:$M,2,0) -> RR170-171车 | AH31: =VLOOKUP(AF31,'[2]Toy Monster'!$L:$T,9,FALSE) -> 46161 | AI31: 已入系统 | AK31: RFID贴纸3/16给到佩玲 | AL31: =((896*6.34)+(896*6.64))*0.3 -> 3489.02
A32: 46101 | B32: 澳大利亚 | C32: Rachel | D32: Target Australia Pty Ltd | E32: 2617376 | F32: PO212775 | G32: T02444 | H32: =VLOOKUP(G32,名称!A:B,2,0) -> 恐龙公园二代 | I32: 1800 | J32: =VLOOKUP(G32,名称!A:C,3,FALSE) -> 12 | K32: =I32/J32 -> 150 | L32: 46156 | M32: 46156 | N32: 46156 | O32: 已约 | P32: OK | Q32: 5/23 Extra Costs：$8.25 | R32: 5吨车 | T32: OK | X32: 草地套装：0840148226203 海滩滩套装：0840148226210 实验室套装：0840148226227 | Y32: 标准美文版本 （13位数UPC条码） | Z32: 美文版本说明书 | AA32: 46138 | AB32: 普通透明胶带封箱，外箱不需要盖日期码 | AC32: 2.1 | AD32: =AC32*I32 -> 3780 | AE32: =AD32*7.75 -> 29295 | AF32: 83248 | AG32: =VLOOKUP(AF32,'[2]Toy Monster'!$L:$M,2,0) -> RR187车 | AH32: =VLOOKUP(AF32,'[2]Toy Monster'!$L:$T,9,FALSE) -> 46172 | AI32: 已入系统 | AK32: SSCC贴纸4/23给到佩玲 | AL32: =IFERROR(VLOOKUP(G32,'已打发票扣数（26年5月开始）'!$A$1:$C$17,3,0)*I32*0.3,"") -> 1134
A33: 46114 | B33: 美国 | C33: Elaine | D33: Flybar Inc | E33: FB-7781 | F33: PO212868 | G33: JW-RV-RPGEA | H33: =VLOOKUP(G33,名称!A:B,2,0) -> 恐龙游戏盘(邮包盒装) | I33: 1002 | J33: =VLOOKUP(G33,名称!A:C,3,FALSE) -> 6 | K33: =I33/J33 -> 167 | L33: 46167 | M33: 46163 | N33: 46163 | O33: 已约 | P33: OK | Q33: 5/30 Extra Costs：$20.04 | R33: 40HQ | T33: OK | X33: 0840148227217 | Y33: 亚马逊版本 （12位数UPC条码） | Z33: 美文版本说明书 | AA33: 46174 | AB33: 外箱不需要盖日期码 | AC33: 4.9 | AD33: =AC33*I33 -> 4909.8 | AE33: =AD33*7.75 -> 38050.95 | AF33: 83249 | AG33: =VLOOKUP(AF33,'[2]Toy Monster'!$L:$M,2,0) -> RR293柜 | AH33: =VLOOKUP(AF33,'[2]Toy Monster'!$L:$T,9,FALSE) -> 46172 | AI33: 已入系统 | AK33: 客追踪贴纸 | AL33: =IFERROR(VLOOKUP(G33,'已打发票扣数（26年5月开始）'!$A$1:$C$17,3,0)*I33*0.3,"")+(I33*3.55-I33*1.35) -> 3557.1
A34: 46119 | B34: 加拿大 | C34: Jennifer | D34: Canada Inc./dba Red Planet Group | E34: 005065 | F34: PO212771 | G34: JW-RV-RPGE | H34: =VLOOKUP(G34,名称!A:B,2,0) -> 恐龙游戏盘 | I34: 1800 | J34: =VLOOKUP(G34,名称!A:C,3,FALSE) -> 6 | K34: =I34/J34 -> 300 | L34: 46171 | M34: 46167 | N34: 46167 | O34: 已约 | Q34: 6/2 Extra Costs：$260 | R34: 5吨车 | T34: OK | X34: 0840148207301 | Y34: 客版本英法双语彩盒 (12位数UPC条码) | Z34: 客版英法双语说明书 | AA34: RR14226 | AB34: 外箱不需要盖日期码 | AC34: 4.5 | AD34: =AC34*I34 -> 8100 | AE34: =AD34*7.75 -> 62775 | AF34: 83250 | AG34: =VLOOKUP(AF34,'[2]Toy Monster'!$L:$M,2,0) -> RR172车 | AH34: =VLOOKUP(AF34,'[2]Toy Monster'!$L:$T,9,FALSE) -> 46177 | AI34: 已入系统 | AL34: =IFERROR(VLOOKUP(G34,'已打发票扣数（26年5月开始）'!$A$1:$C$17,3,0)*I34*0.3,"")+(I34*3.55-I34*1.35) -> 6390
A35: 46102 | B35: 加拿大 | C35: Jennifer | D35: Lachine | E35: 004980 | F35: PO212541 | G35: T03804 | H35: =VLOOKUP(G35,名称!A:B,2,0) -> 恐龙公园二代 | I35: 2964 | J35: =VLOOKUP(G35,名称!A:C,3,FALSE) -> 12 | K35: =I35/J35 -> 247 | L35: 46164 | M35: 46167 | N35: 46167 | O35: 已约 | P35: OK | Q35: 6/2 Extra Costs：$660 | R35: 5吨车 | T35: OK | X35: 840148221734 | Y35: 双语版本 （12位数UPC条码） | Z35: 双语版本说明书 | AA35: RR13826 | AB35: 混装只需装实验室和海滩两个场景，外箱不需要打日期码 | AC35: 2.1 | AD35: =AC35*I35 -> 6224.4 | AE35: =AD35*7.75 -> 48239.1 | AF35: 95751 | AG35: =VLOOKUP(AF35,'[2]Toy Monster'!$L:$M,2,0) -> RR172车 | AH35: =VLOOKUP(AF35,'[2]Toy Monster'!$L:$T,9,FALSE) -> 46177 | AI35: 已入系统 | AL35: =IFERROR(VLOOKUP(G35,'已打发票扣数（26年5月开始）'!$A$1:$C$17,3,0)*I35*0.3,"") -> 1867.32
A36: 46121 | B36: 越南 | C36: Elaine | D36: Viet Tinh Anh Joint Stock Company | E36: Viet-TM111631 | F36: PO212874 | G36: T02444 | H36: =VLOOKUP(G36,名称!A:B,2,0) -> 恐龙公园二代 | I36: 1656 | J36: =VLOOKUP(G36,名称!A:C,3,FALSE) -> 12 | K36: =I36/J36 -> 138 | L36: 46175 | M36: 46174 | N36: 46174 | O36: 已约 | P36: OK | Q36: 6/6 Extra Costs：$300 | R36: 5吨车 | T36: OK | X36: 草地套装：0840148226203 海滩滩套装：0840148226210 实验室套装：0840148226227 | Y36: 标准美文版本 （13位数UPC条码） | Z36: 美文版本说明书 | AA36: 46162 | AC36: 2.1 | AD36: =AC36*I36 -> 3477.6 | AE36: =AD36*7.75 -> 26951.4 | AF36: 95752 | AG36: =VLOOKUP(AF36,'[2]Toy Monster'!$L:$M,2,0) -> RR245柜 | AH36: =VLOOKUP(AF36,'[2]Toy Monster'!$L:$T,9,FALSE) -> 46183 | AI36: 已入系统 | AL36: =IFERROR(VLOOKUP(G36,'已打发票扣数（26年5月开始）'!$A$1:$C$17,3,0)*I36*0.3,"") -> 1043.28
A37: 46134 | B37: 韩国 | C37: Elaine | D37: BomNamu Co. Ltd | E37: BNM_TM260403 | F37: PO213297 | G37: T01535 | H37: =VLOOKUP(G37,名称!A:B,2,0) -> 恐龙公园 | I37: 540 | J37: =VLOOKUP(G37,名称!A:C,3,FALSE) -> 12 | K37: =I37/J37 -> 45 | L37: 46181 | M37: =L37-7 -> 46174 | N37: =L37-7 -> 46174 | O37: 已约 | P37: OK | Q37: 6/9 Extra Costs：$609 | R37: 5吨车 | T37: OK | U37: 进口贴纸 | X37: 0840148215733 | Y37: 标准美文版本 （13位数UPC条码） | Z37: 美文版本说明书 | AA37: 46162 | AB37: 用取消单P0210601返工 | AC37: 2.1 | AD37: =AC37*I37 -> 1134 | AE37: =AD37*7.75 -> 8788.5 | AF37: 95753 | AG37: =VLOOKUP(AF37,'[2]Toy Monster'!$L:$M,2,0) -> RR254车 | AH37: =VLOOKUP(AF37,'[2]Toy Monster'!$L:$T,9,FALSE) -> 46183 | AI37: 已入系统 | AK37: PDQ贴纸4/29给到佩玲，条形码贴纸、客贴纸5/11给到佩玲 | AL37: =IFERROR(VLOOKUP(G37,'已打发票扣数（26年5月开始）'!$A$1:$C$17,3,0)*I37*0.3,"") -> 340.2
A38: 46122 | B38: 澳大利亚 | C38: Rachel | D38: Kmart Australia & NZ Holding Limited | E38: 21688246 | F38: PO213048 | G38: T02444 | H38: =VLOOKUP(G38,名称!A:B,2,0) -> 恐龙公园二代 | I38: 1224 | J38: =VLOOKUP(G38,名称!A:C,3,FALSE) -> 12 | K38: =I38/J38 -> 102 | L38: 46174 | M38: 46174 | N38: 46174 | O38: 已约 | P38: OK | Q38: 6/10 Extra Costs：$5.61 | R38: 5吨车 | T38: OK | X38: 草地套装：0840148226203 海滩滩套装：0840148226210 实验室套装：0840148226227 | Y38: 标准美文版本 （13位数UPC条码） | Z38: 美文版本说明书 | AA38: 46138 | AB38: 外箱上下两面都需要工字形ANKO胶带封箱 | AC38: 2.1 | AD38: =AC38*I38 -> 2570.4 | AE38: =AD38*7.75 -> 19920.6 | AF38: 95754 | AG38: =VLOOKUP(AF38,'[2]Toy Monster'!$L:$M,2,0) -> RR256车 | AH38: =VLOOKUP(AF38,'[2]Toy Monster'!$L:$T,9,FALSE) -> 46184 | AI38: 已入系统 | AK38: SSCC贴纸5/20给到佩玲 | AL38: =IFERROR(VLOOKUP(G38,'已打发票扣数（26年5月开始）'!$A$1:$C$17,3,0)*I38*0.3,"") -> 771.12
A39: 46122 | B39: 新西兰 | C39: Rachel | D39: Kmart Australia & NZ Holding Limited | E39: 21688244 | F39: PO213046 | G39: T02444 | H39: =VLOOKUP(G39,名称!A:B,2,0) -> 恐龙公园二代 | I39: 5496 | J39: =VLOOKUP(G39,名称!A:C,3,FALSE) -> 12 | K39: =I39/J39 -> 458 | L39: 46174 | M39: 46174 | N39: 46174 | O39: 已约 | P39: OK | Q39: 6/10 Extra Costs:$25.19 | R39: 5吨车 | T39: OK | X39: 草地套装：0840148226203 海滩滩套装：0840148226210 实验室套装：0840148226227 | Y39: 标准美文版本 （13位数UPC条码） | Z39: 美文版本说明书 | AA39: 46138 | AB39: 外箱上下两面都需要工字形ANKO胶带封箱 | AC39: 2.1 | AD39: =AC39*I39 -> 11541.6 | AE39: =AD39*7.75 -> 89447.4 | AF39: 95755 | AG39: =VLOOKUP(AF39,'[2]Toy Monster'!$L:$M,2,0) -> RR256车 | AH39: =VLOOKUP(AF39,'[2]Toy Monster'!$L:$T,9,FALSE) -> 46184 | AI39: 已入系统 | AK39: SSCC贴纸5/20给到佩玲 | AL39: =IFERROR(VLOOKUP(G39,'已打发票扣数（26年5月开始）'!$A$1:$C$17,3,0)*I39*0.3,"") -> 3462.48
A40: 46134 | B40: 泰国 | C40: Elaine | D40: Kiddo Pacific Co. Ltd | E40: Kiddo-TM11353 | F40: PO212633 | G40: T02444 | H40: =VLOOKUP(G40,名称!A:B,2,0) -> 恐龙公园二代 | I40: 1404 | J40: =VLOOKUP(G40,名称!A:C,3,FALSE) -> 12 | K40: =I40/J40 -> 117 | L40: 46175 | M40: 46174 | N40: 46174 | O40: 已约 | P40: OK | Q40: 6/11 Extra Costs：$360 | R40: 5吨车 | T40: OK | U40: 进口贴纸 | X40: 草地套装：0840148226203 海滩滩套装：0840148226210 实验室套装：0840148226227 | Y40: 标准美文版本 （13位数UPC条码） | Z40: 美文版本说明书 | AA40: 46162 | AC40: 2.1 | AD40: =AC40*I40 -> 2948.4 | AE40: =AD40*7.75 -> 22850.1 | AF40: 95756 | AG40: =VLOOKUP(AF40,'[2]Toy Monster'!$L:$M,2,0) -> RR258车 | AH40: =VLOOKUP(AF40,'[2]Toy Monster'!$L:$T,9,FALSE) -> 46184 | AI40: 已入系统 | AK40: 客贴纸4/23给到佩玲 | AL40: =IFERROR(VLOOKUP(G40,'已打发票扣数（26年5月开始）'!$A$1:$C$17,3,0)*I40*0.3,"") -> 884.52
A41: 46119 | B41: 澳大利亚 | C41: Carol | D41: Woolworths Group Limited t/a Big W | E41: 47946690 | F41: PO212950 | G41: JW-RV-RPGE | H41: =VLOOKUP(G41,名称!A:B,2,0) -> 恐龙游戏盘 | I41: 1200 | J41: =VLOOKUP(G41,名称!A:C,3,FALSE) -> 6 | K41: =I41/J41 -> 200 | L41: 46178 | M41: 46174 | N41: 46174 | O41: 已约 | P41: OK | T41: OK | X41: 0840148207301 | Y41: 标准美文版本 （13位数UPC条码） | Z41: 美文版本说明书 | AA41: 050626 | AB41: 外箱不需要盖日期码 | AC41: 4.5 | AD41: =AC41*I41 -> 5400 | AE41: =AD41*7.75 -> 41850 | AF41: 95757 | AG41: =VLOOKUP(AF41,'[2]Toy Monster'!$L:$M,2,0) -> RR242车 | AH41: =VLOOKUP(AF41,'[2]Toy Monster'!$L:$T,9,FALSE) -> 46185 | AI41: 已入系统 | AL41: =IFERROR(VLOOKUP(G41,'已打发票扣数（26年5月开始）'!$A$1:$C$17,3,0)*I41*0.3,"")+(I41*3.55-I41*1.35) -> 4260
A42: 46129 | B42: 澳大利亚 | C42: Rachel | D42: Kmart Australia & NZ Holding Limited | E42: 21711859 | F42: PO213271 | G42: T02444 | H42: =VLOOKUP(G42,名称!A:B,2,0) -> 恐龙公园二代 | I42: 6720 | J42: =VLOOKUP(G42,名称!A:C,3,FALSE) -> 12 | K42: =I42/J42 -> 560 | L42: 46175 | M42: 46174 | N42: 46174 | O42: 已约 | P42: OK | Q42: 6/17 Extra Costs：$30.8 | T42: OK | X42: 草地套装：0840148226203 海滩滩套装：0840148226210 实验室套装：0840148226227 | Y42: 标准美文版本 （13位数UPC条码） | Z42: 美文版本说明书 | AA42: 46174 | AB42: 外箱上下两面都需要工字形ANKO胶带封箱 | AC42: 2.1 | AD42: =AC42*I42 -> 14112 | AE42: =AD42*7.75 -> 109368 | AF42: 95758 | AG42: RR282车 | AH42: 46191 | AI42: 已入系统 | AK42: SSCC贴纸5/20给到佩玲 | AL42: =IFERROR(VLOOKUP(G42,'已打发票扣数（26年5月开始）'!$A$1:$C$17,3,0)*I42*0.3,"") -> 4233.6
A43: 46101 | B43: 澳大利亚 | C43: Rachel | D43: Target Australia Pty Ltd | E43: 2617377 | F43: PO213307 | G43: T02444 | H43: =VLOOKUP(G43,名称!A:B,2,0) -> 恐龙公园二代 | I43: 1800 | J43: =VLOOKUP(G43,名称!A:C,3,FALSE) -> 12 | K43: =I43/J43 -> 150 | L43: 46177 | M43: 46174 | N43: 46174 | O43: 已约 | P43: OK | Q43: 6/25 Extra Costs：$8.25 | R43: 5吨车 | T43: OK | X43: 草地套装：0840148226203 海滩滩套装：0840148226210 实验室套装：0840148226227 | Y43: 标准美文版本 （13位数UPC条码） | Z43: 美文版本说明书 | AA43: 46199 | AB43: 普通透明胶带封箱，外箱不需要盖日期码 | AC43: 2.1 | AD43: =AC43*I43 -> 3780 | AE43: =AD43*7.75 -> 29295 | AF43: 95759 | AG43: RR296车 | AH43: 46203 | AI43: 已入系统 | AK43: SSCC贴纸4/23给到佩玲 | AL43: =IFERROR(VLOOKUP(G43,'已打发票扣数（26年5月开始）'!$A$1:$C$17,3,0)*I43*0.3,"") -> 1134
A44: 46154 | B44: 宁波 | C44: Elaine | D44: Aliss- Panama | E44: Aliss | F44: PO213496 | G44: T03900 | H44: =VLOOKUP(G44,名称!A:B,2,0) -> 9.5寸漫画系列 | I44: 1440 | J44: =VLOOKUP(G44,名称!A:C,3,FALSE) -> 8 | K44: =I44/J44 -> 180 | L44: 46198 | M44: 46202 | N44: 46202 | O44: 已约 | P44: OK | Q44: Extra Costs：$1369.92 船期：7/4 | T44: OK | X44: 0840148230705 | Y44: 标准美文版本 （13位数UPC条码） | Z44: / | AA44: 46174 | AB44: 混装，每款2个，比例为2:2:2:2 | AC44: 6.35 | AD44: =AC44*I44 -> 9144 | AE44: =AD44*7.75 -> 70866 | AF44: 95762 | AG44: RR328车 | AH44: 46206 | AI44: 已入系统 | AK44: 条形码贴纸/进口商贴纸6/22给到佩玲 | AL44: =IFERROR(VLOOKUP(G44,'已打发票扣数（26年5月开始）'!$A$1:$C$17,3,0)*I44*0.3,"")
A45: 46154 | B45: 宁波 | C45: Elaine | D45: Aliss- Panama | E45: Aliss | F45: PO213496 | G45: T03349 | H45: =VLOOKUP(G45,名称!A:B,2,0) -> 3寸可爱系列 | I45: 1392 | J45: =VLOOKUP(G45,名称!A:C,3,FALSE) -> 12 | K45: =I45/J45 -> 116 | L45: 46198 | M45: 46202 | N45: 46202 | O45: 已约 | P45: OK | Q45: 船期：7/4 | T45: OK | X45: 0840148227583 | Y45: 标准美文版本 （13位数UPC条码） | Z45: / | AA45: 46174 | AC45: 1.95 | AD45: =AC45*I45 -> 2714.4 | AE45: =AD45*7.75 -> 21036.6 | AF45: 95762 | AG45: RR328车 | AH45: 46206 | AI45: 已入系统 | AK45: 条形码贴纸/进口商贴纸6/22给到佩玲 | AL45: =IFERROR(VLOOKUP(G45,'已打发票扣数（26年5月开始）'!$A$1:$C$17,3,0)*I45*0.3,"")
A46: 46127 | B46: 澳大利亚 | C46: Rachel | D46: Kmart Australia & NZ Holding Limited | E46: 21700273 | F46: PO213168 | G46: T03900 | H46: =VLOOKUP(G46,名称!A:B,2,0) -> 9.5寸漫画系列 | I46: 3600 | J46: =VLOOKUP(G46,名称!A:C,3,FALSE) -> 8 | K46: =I46/J46 -> 450 | L46: 46188 | M46: 46202 | N46: 46202 | O46: 已约 | P46: pass | Q46: 46212 | T46: OK | X46: 0840148230705 | Y46: 标准美文版本 （13位数UPC条码） | Z46: / | AA46: 46174 | AB46: 外箱上下两面都需要工字形ANKO胶带封箱,混装，每款2个，比例为2:2:2:2，每款多做4个，共16个样办 | AC46: 6.35 | AD46: =AC46*I46 -> 22860 | AE46: =AD46*7.75 -> 177165 | AF46: 95763 | AG46: RR336车 | AH46: 46218 | AI46: 已入系统 | AK46: SSCC贴纸6/18给到佩玲 | AL46: =IFERROR(VLOOKUP(G46,'已打发票扣数（26年5月开始）'!$A$1:$C$17,3,0)*I46*0.3,"")
A47: 46127 | B47: 澳大利亚 | C47: Rachel | D47: Kmart Australia & NZ Holding Limited | E47: 21700273 | F47: PO213168 | G47: T03349 | H47: =VLOOKUP(G47,名称!A:B,2,0) -> 3寸可爱系列 | I47: 7200 | J47: =VLOOKUP(G47,名称!A:C,3,FALSE) -> 12 | K47: =I47/J47 -> 600 | L47: 46188 | M47: 46202 | N47: 46202 | O47: 已约 | P47: pass | Q47: 46212 | T47: OK | X47: 0840148227583 | Y47: 标准美文版本 （13位数UPC条码） | Z47: / | AA47: 46174 | AB47: 外箱上下两面都需要工字形ANKO胶带封箱，做4套样办 | AC47: 1.95 | AD47: =AC47*I47 -> 14040 | AE47: =AD47*7.75 -> 108810 | AF47: 95763 | AG47: RR336车 | AH47: 46218 | AI47: 已入系统 | AK47: SSCC贴纸6/18给到佩玲 | AL47: =IFERROR(VLOOKUP(G47,'已打发票扣数（26年5月开始）'!$A$1:$C$17,3,0)*I47*0.3,"")
A48: 46127 | B48: 新西兰 | C48: Rachel | D48: Kmart Australia & NZ Holding Limited | E48: 21700276 | F48: PO213170 | G48: T03900 | H48: =VLOOKUP(G48,名称!A:B,2,0) -> 9.5寸漫画系列 | I48: 400 | J48: =VLOOKUP(G48,名称!A:C,3,FALSE) -> 8 | K48: =I48/J48 -> 50 | L48: 46188 | M48: 46202 | N48: 46202 | O48: 已约 | P48: pass | Q48: 46212 | T48: OK | X48: 0840148230705 | Y48: 标准美文版本 （13位数UPC条码） | Z48: / | AA48: 46174 | AB48: 外箱上下两面都需要工字形ANKO胶带封箱,混装，每款2个，比例为2:2:2:2 | AC48: 6.35 | AD48: =AC48*I48 -> 2540 | AE48: =AD48*7.75 -> 19685 | AF48: 95764 | AG48: RR336车 | AH48: 46218 | AI48: 已入系统 | AK48: SSCC贴纸6/18给到佩玲 | AL48: =IFERROR(VLOOKUP(G48,'已打发票扣数（26年5月开始）'!$A$1:$C$17,3,0)*I48*0.3,"")
A49: 46127 | B49: 新西兰 | C49: Rachel | D49: Kmart Australia & NZ Holding Limited | E49: 21700276 | F49: PO213170 | G49: T03349 | H49: =VLOOKUP(G49,名称!A:B,2,0) -> 3寸可爱系列 | I49: 792 | J49: =VLOOKUP(G49,名称!A:C,3,FALSE) -> 12 | K49: =I49/J49 -> 66 | L49: 46188 | M49: 46202 | N49: 46202 | O49: 已约 | P49: pass | Q49: 46212 | T49: OK | X49: 0840148227583 | Y49: 标准美文版本 （13位数UPC条码） | Z49: / | AA49: 46174 | AB49: 外箱上下两面都需要工字形ANKO胶带封箱 | AC49: 1.95 | AD49: =AC49*I49 -> 1544.4 | AE49: =AD49*7.75 -> 11969.1 | AF49: 95764 | AG49: RR336车 | AH49: 46218 | AI49: 已入系统 | AK49: SSCC贴纸6/18给到佩玲 | AL49: =IFERROR(VLOOKUP(G49,'已打发票扣数（26年5月开始）'!$A$1:$C$17,3,0)*I49*0.3,"")
A50: 46164 | B50: 美国 | C50: Jennifer | D50: Monster Group LLC | E50: Kuma Paw T03980 WM Domestic | F50: PO213866 | G50: T03980 | H50: =VLOOKUP(G50,名称!A:B,2,0) -> 9.5寸绿色淋油公仔+涂鸦公仔混装 | I50: 2474 | J50: =VLOOKUP(G50,名称!A:C,3,FALSE) -> 2 | K50: =I50/J50 -> 1237 | L50: 46213 | M50: =L50-3 -> 46210 | N50: =L50-3 -> 46210 | O50: 已约 | P50: pass | Q50: 46216 | T50: OK | X50: 840148224438 840148224452 | Y50: 沃尔玛版本彩盒 （12位数UPC条码） | Z50: / | AA50: RR18826 | AB50: 9.5寸绿色淋油公仔脚底码货号为：T02942-2，9.5寸涂鸦公仔脚底码货号为：T02944-2，混装比例1:1，彩盒不需要打日期码 | AC50: 5.6 | AD50: =AC50*I50 -> 13854.4 | AE50: =AD50*7.75 -> 107371.6 | AF50: 95765REV1 | AG50: RR347车 | AH50: 46218 | AI50: 已入系统 | AK50: RFID贴纸5/30给到佩玲 | AL50: =IFERROR(VLOOKUP(G50,'已打发票扣数（26年5月开始）'!$A$1:$C$17,3,0)*I50*0.3,"") -> 4156.32
A51: 46164 | B51: 美国 | C51: Jennifer | D51: Monster Group LLC | E51: Kuma Paw T03980 WM Domestic | F51: PO213866 | G51: T03980 | H51: =VLOOKUP(G51,名称!A:B,2,0) -> 9.5寸绿色淋油公仔+涂鸦公仔混装 | I51: =9568-2474 -> 7094 | J51: =VLOOKUP(G51,名称!A:C,3,FALSE) -> 2 | K51: =I51/J51 -> 3547 | L51: 46213 | M51: =L51-3 -> 46210 | N51: =L51-3 -> 46210 | O51: 已约 | P51: pass | Q51: 46216 | T51: OK | X51: 840148224438 840148224452 | Y51: 沃尔玛版本彩盒 （12位数UPC条码） | Z51: / | AA51: RR18826 | AB51: 9.5寸绿色淋油公仔脚底码货号为：T02942-2，9.5寸涂鸦公仔脚底码货号为：T02944-2，混装比例1:1，彩盒不需要打日期码 | AC51: 5.6 | AD51: =AC51*I51 -> 39726.4 | AE51: =AD51*7.75 -> 307879.6 | AF51: 95765REV1 | AG51: RR347车 | AH51: 46218 | AI51: 已入系统 | AK51: RFID贴纸5/30给到佩玲 | AL51: =IFERROR(VLOOKUP(G51,'已打发票扣数（26年5月开始）'!$A$1:$C$17,3,0)*I51*0.3,"") -> 11917.92
A52: 46114 | B52: 美国-亚马逊 | C52: Elaine | D52: Flybar Inc | E52: FB-7782 | F52: PO212869 | G52: JW-RV-RPGEA | H52: =VLOOKUP(G52,名称!A:B,2,0) -> 恐龙游戏盘(邮包盒装) | I52: 1002 | J52: =VLOOKUP(G52,名称!A:C,3,FALSE) -> 6 | K52: =I52/J52 -> 167 | L52: 46167 | M52: 46163 | N52: 46163 | O52: 已约 | P52: pass | Q52: Extra Costs：$20.04 7/13 | T52: OK | X52: 0840148227217 | Y52: 亚马逊版本 （12位数UPC条码） | Z52: 美文版本说明书 | AA52: 46204 | AB52: 外箱不需要盖日期码 | AC52: 4.9 | AD52: =AC52*I52 -> 4909.8 | AE52: =AD52*7.75 -> 38050.95 | AF52: 95766 | AG52: RR444柜 | AH52: 46220 | AI52: 已入系统 | AK52: 客追踪贴纸 | AL52: =IFERROR(VLOOKUP(G52,'已打发票扣数（26年5月开始）'!$A$1:$C$17,3,0)*I52*0.3,"") -> 1352.7
A53: 46101 | B53: 澳大利亚 | C53: Rachel | D53: Target Australia Pty Ltd | E53: 2617378 | F53: PO213308 | G53: T02444 | H53: =VLOOKUP(G53,名称!A:B,2,0) -> 恐龙公园二代 | I53: 1200 | J53: =VLOOKUP(G53,名称!A:C,3,FALSE) -> 12 | K53: =I53/J53 -> 100 | L53: 46212 | M53: =L53-7 -> 46205 | N53: 46212 | O53: 已约 | P53: pass | Q53: Extra Costs：$5.5 | T53: OK | U53: SSCC贴纸 | X53: 草地套装：0840148226203 海滩滩套装：0840148226210 实验室套装：0840148226227 | Y53: 标准美文版本 （13位数UPC条码） | Z53: 美文版本说明书 | AA53: 46229 | AB53: 普通透明胶带封箱，外箱不需要盖日期码 | AC53: 2.1 | AD53: =AC53*I53 -> 2520 | AE53: =AD53*7.75 -> 19530 | AF53: 95767 | AG53: RR399车 | AH53: 46233 | AI53: 已入系统 | AK53: SSCC贴纸4/23给到佩玲 | AL53: =IFERROR(VLOOKUP(G53,'已打发票扣数（26年5月开始）'!$A$1:$C$17,3,0)*I53*0.3,"") -> 756
A54: 46167 | B54: 美国-亚马逊 | C54: Elaine | D54: Flybar Inc | E54: FB-7937 | F54: PO213850 | G54: T03937-DS | H54: =VLOOKUP(G54,名称!A:B,2,0) -> 恐龙公园一代--陆地 | I54: 144 | J54: =VLOOKUP(G54,名称!A:C,3,FALSE) -> 12 | K54: =I54/J54 -> 12 | L54: 46232 | M54: =L54-5 -> 46227 | N54: 46232 | O54: 已约 | P54: pass | Q54: Extra Costs：$318.24 | T54: OK | X54: 0840148231382 | Y54: 沃尔玛版本彩盒 （12位数UPC条码） | Z54: 美文版本说明书 | AA54: / | AB54: 用取消单PO211192返工，条形码上已有日期码，不需要另外打日期，产品上的RFID贴纸要撕掉 | AC54: 2.1 | AD54: =AC54*I54 -> 302.4 | AE54: =AD54*7.75 -> 2343.6 | AF54: 95768 | AG54: RR527柜 | AH54: 46238 | AK54: 条形码贴纸/客追踪贴纸6/18给到佩玲 | AL54: =(I54*AC54)*0.3 -> 90.72
A55: 46167 | B55: 美国-亚马逊 | C55: Elaine | D55: Flybar Inc | E55: FB-7937 | F55: PO213850 | G55: T03938-DS | H55: =VLOOKUP(G55,名称!A:B,2,0) -> 恐龙公园一代--海洋 | I55: 144 | J55: =VLOOKUP(G55,名称!A:C,3,FALSE) -> 12 | K55: =I55/J55 -> 12 | L55: 46232 | M55: =L55-5 -> 46227 | N55: 46232 | O55: 已约 | P55: pass | T55: OK | X55: 0840148231399 | Y55: 沃尔玛版本彩盒 （12位数UPC条码） | Z55: 美文版本说明书 | AA55: / | AB55: 用取消单PO211192返工，条形码上已有日期码，不需要另外打日期，产品上的RFID贴纸要撕掉 | AC55: 2.1 | AD55: =AC55*I55 -> 302.4 | AE55: =AD55*7.75 -> 2343.6 | AF55: 95768 | AG55: RR527柜 | AH55: 46238 | AK55: 条形码贴纸/客追踪贴纸6/18给到佩玲 | AL55: =(I55*AC55)*0.3 -> 90.72
A56: 46167 | B56: 美国-亚马逊 | C56: Elaine | D56: Flybar Inc | E56: FB-7937 | F56: PO213850 | G56: T03939-DS | H56: =VLOOKUP(G56,名称!A:B,2,0) -> 恐龙公园一代--天空 | I56: 144 | J56: =VLOOKUP(G56,名称!A:C,3,FALSE) -> 12 | K56: =I56/J56 -> 12 | L56: 46232 | M56: =L56-5 -> 46227 | N56: 46232 | O56: 已约 | P56: pass | T56: OK | X56: 0840148231405 | Y56: 沃尔玛版本彩盒 （12位数UPC条码） | Z56: 美文版本说明书 | AA56: / | AB56: 用取消单PO211192返工，条形码上已有日期码，不需要另外打日期，产品上的RFID贴纸要撕掉 | AC56: 2.1 | AD56: =AC56*I56 -> 302.4 | AE56: =AD56*7.75 -> 2343.6 | AF56: 95768 | AG56: RR527柜 | AH56: 46238 | AK56: 条形码贴纸/客追踪贴纸6/18给到佩玲 | AL56: =(I56*AC56)*0.3 -> 90.72
A57: 46167 | B57: 美国-亚马逊 | C57: Elaine | D57: Flybar Inc | E57: FB-7937 | F57: PO213850 | G57: T03940-DS | H57: =VLOOKUP(G57,名称!A:B,2,0) -> 恐龙公园二代--海滩 | I57: 144 | J57: =VLOOKUP(G57,名称!A:C,3,FALSE) -> 12 | K57: =I57/J57 -> 12 | L57: 46232 | M57: =L57-5 -> 46227 | N57: 46232 | O57: 已约 | P57: pass | T57: OK | X57: 0840148231412 | Y57: 沃尔玛版本彩盒 （12位数UPC条码） | Z57: 美文版本说明书 | AA57: / | AB57: 条形码上已有日期码，不需要另外打日期 | AC57: 2.1 | AD57: =AC57*I57 -> 302.4 | AE57: =AD57*7.75 -> 2343.6 | AF57: 95768 | AG57: RR527柜 | AH57: 46238 | AK57: 条形码贴纸/客追踪贴纸6/18给到佩玲 | AL57: =(I57*AC57)*0.3 -> 90.72
A58: 46167 | B58: 美国-亚马逊 | C58: Elaine | D58: Flybar Inc | E58: FB-7937 | F58: PO213850 | G58: T03941-DS | H58: =VLOOKUP(G58,名称!A:B,2,0) -> 恐龙公园二代--雨林 | I58: 144 | J58: =VLOOKUP(G58,名称!A:C,3,FALSE) -> 12 | K58: =I58/J58 -> 12 | L58: 46232 | M58: =L58-5 -> 46227 | N58: 46232 | O58: 已约 | P58: pass | T58: OK | X58: 0840148231429 | Y58: 沃尔玛版本彩盒 （12位数UPC条码） | Z58: 美文版本说明书 | AA58: / | AB58: 条形码上已有日期码，不需要另外打日期 | AC58: 2.1 | AD58: =AC58*I58 -> 302.4 | AE58: =AD58*7.75 -> 2343.6 | AF58: 95768 | AG58: RR527柜 | AH58: 46238 | AK58: 条形码贴纸/客追踪贴纸6/18给到佩玲 | AL58: =(I58*AC58)*0.3 -> 90.72
A59: 46167 | B59: 美国-亚马逊 | C59: Elaine | D59: Flybar Inc | E59: FB-7937 | F59: PO213850 | G59: T03942-DS | H59: =VLOOKUP(G59,名称!A:B,2,0) -> 恐龙公园二代--实验室 | I59: 144 | J59: =VLOOKUP(G59,名称!A:C,3,FALSE) -> 12 | K59: =I59/J59 -> 12 | L59: 46232 | M59: =L59-5 -> 46227 | N59: 46232 | O59: 已约 | P59: pass | T59: OK | X59: 0840148231436 | Y59: 沃尔玛版本彩盒 （12位数UPC条码） | Z59: 美文版本说明书 | AA59: / | AB59: 条形码上已有日期码，不需要另外打日期 | AC59: 2.1 | AD59: =AC59*I59 -> 302.4 | AE59: =AD59*7.75 -> 2343.6 | AF59: 95768 | AG59: RR527柜 | AH59: 46238 | AK59: 条形码贴纸/客追踪贴纸6/18给到佩玲 | AL59: =(I59*AC59)*0.3 -> 90.72
A60: 46195 | B60: 澳大利亚 | C60: Rachel | D60: Kmart Australia & NZ Holding Limited | E60: 21848574 | F60: PO214263 | G60: T02444 | H60: =VLOOKUP(G60,名称!A:B,2,0) -> 恐龙公园二代 | I60: 5004 | J60: =VLOOKUP(G60,名称!A:C,3,FALSE) -> 12 | K60: =I60/J60 -> 417 | L60: 46244 | M60: 46241 | N60: 46241 | O60: 已约 | P60: pass | Q60: Extra Costs：$22.935 | T60: OK | U60: SSCC贴纸 | X60: 草地套装：0840148226203 海滩滩套装：0840148226210 实验室套装：0840148226227 | Y60: 标准美文版本 （13位数UPC条码） | Z60: 美文版本说明书 | AA60: 46260 | AB60: 普通透明胶带封箱，外箱不需要盖日期码 | AC60: 2.1 | AD60: =AC60*I60 -> 10508.4 | AE60: =AD60*7.75 -> 81440.1 | AF60: 95770 | AG60: RR428车 | AH60: 46248 | AI60: 已入系统 | AL60: =IFERROR(VLOOKUP(G60,'已打发票扣数（26年5月开始）'!$A$1:$C$17,3,0)*I60*0.3,"") -> 3152.52
A61: 46191 | B61: 马来西亚 | C61: Elaine | D61: Litt Tak Sdn Bhd | E61: TMI-LT112962 | F61: PO214234 | G61: T02444 | H61: =VLOOKUP(G61,名称!A:B,2,0) -> 恐龙公园二代 | I61: 720 | J61: =VLOOKUP(G61,名称!A:C,3,FALSE) -> 12 | K61: =I61/J61 -> 60 | L61: 46241 | M61: 46241 | N61: 46247 | O61: 已约 | P61: pass | Q61: Extra Costs：$321.6 | T61: OK | U61: 客贴纸 | X61: 草地套装：0840148226203 海滩滩套装：0840148226210 实验室套装：0840148226227 | Y61: 标准美文版本 （13位数UPC条码） | Z61: 美文版本说明书 | AA61: RR21526 | AB61: 外箱不需要盖日期码 | AC61: 2.1 | AD61: =AC61*I61 -> 1512 | AE61: =AD61*7.75 -> 11718 | AF61: 95771 | AG61: RR444车 | AH61: 46248 | AI61: 已入系统 | AK61: 进口商贴纸6/23给到佩玲 | AL61: =IFERROR(VLOOKUP(G61,'已打发票扣数（26年5月开始）'!$A$1:$C$17,3,0)*I61*0.3,"") -> 453.6
AD62: =AC62*I62 -> 0 | AE62: =AD62*7.75 -> 0 | AL62: =IFERROR(VLOOKUP(G62,'已打发票扣数（26年5月开始）'!$A$1:$C$17,3,0)*I62*0.3,"")
AD63: =AC63*I63 -> 0 | AE63: =AD63*7.75 -> 0 | AL63: =IFERROR(VLOOKUP(G63,'已打发票扣数（26年5月开始）'!$A$1:$C$17,3,0)*I63*0.3,"")
AD64: =AC64*I64 -> 0 | AE64: =AD64*7.75 -> 0 | AL64: =IFERROR(VLOOKUP(G64,'已打发票扣数（26年5月开始）'!$A$1:$C$17,3,0)*I64*0.3,"")
AD65: =AC65*I65 -> 0 | AE65: =AD65*7.75 -> 0 | AL65: =IFERROR(VLOOKUP(G65,'已打发票扣数（26年5月开始）'!$A$1:$C$17,3,0)*I65*0.3,"")
AD66: =AC66*I66 -> 0 | AE66: =AD66*7.75 -> 0 | AL66: =IFERROR(VLOOKUP(G66,'已打发票扣数（26年5月开始）'!$A$1:$C$17,3,0)*I66*0.3,"")
AD67: =AC67*I67 -> 0 | AE67: =AD67*7.75 -> 0 | AL67: =IFERROR(VLOOKUP(G67,'已打发票扣数（26年5月开始）'!$A$1:$C$17,3,0)*I67*0.3,"")
I68: =SUM(I1:I67) -> 122952 | AD68: =SUM(AD1:AD67) -> 486493.16 | AE68: =SUM(AE1:AE67) -> 3770322 | AL68: =SUM(AL1:AL67) -> 107130.48

Sheet 取消单
A1: 接单期 | B1: 国家 | C1: 客跟单 | D1: 客户 | E1: Customer | F1: PO号 | G1: 货号 | H1: 名称 | I1: 数量 | J1: 装箱数 | K1: 总箱数 | L1: 客PO期 | M1: 出货期 | N1: 验货期 | O1: 是否约验货 | P1: 验货结果 | Q1: 船期SO | R1: 生产车间 | S1: 箱唛资料 | T1: 客贴纸 | U1: 是否寄出签办 | V1: 是否打卡板 | W1: 彩盒UPC条码 | X1: 彩盒版本 | Y1: 说明书版本 | Z1: 日期码 | AA1: 备注 | AB1: 单价 | AC1: 金额USD | AD1: 金额HKD | AE1: 发票号 | AF1: 走柜/散货 | AG1: 出货日期 | AH1: 是否入系统 | AI1: 下单情况 | AJ1: 贴纸情况 | AK1: 首期扣数30%
A2: 45805 | D2: Smyths Toys HQ UC | G2: T01685-S | H2: =VLOOKUP(G2,[1]Sheet1!B:C,2,0) -> 手术游戏盘 | I2: =10002-4998 -> 5004 | J2: 6 | K2: =I2/J2 -> 834 | L2: 45853 | M2: 45846 | N2: 45846 | W2: 0840148217751 | X2: Smyths客版彩盒 （13位数UPC条码） | Y2: 标准版的说明书+四国语言的说明书 | AA2: 生产彩盒时不要印日期码，日期码由湖南生产大货时打在彩盒上，注意不要漏打！ 包装以及说明书均为5国语 | AB2: 4.52 | AC2: =AB2*I2 -> 22618.08 | AD2: =AC2*7.75 -> 175290.12
A3: 45698 | B3: 美国 | C3: Jennifer | D3: Water Sports LLC | E3: 2025023 | F3: PO208167 | G3: JW-RV-RPGE | H3: =VLOOKUP(G3,名称!A:B,2,0) -> 恐龙游戏盘 | I3: 3000 | J3: 6 | K3: =I3/J3 -> 500 | L3: 45736 | M3: 45729 | N3: 45726 | O3: OK | S3: OK | W3: 0840148207301 | X3: 标准美文版本 （13位数UPC条码） | Y3: 美文版本说明书 | Z3: RR05725 | AA3: 生产彩盒时不要印日期码，日期码由湖南生产大货时打在彩盒上，注意不要漏打！ 包装以及说明书均为美文 | AB3: 4.5 | AC3: =AB3*I3 -> 13500 | AD3: =AC3*7.75 -> 104625 | AH3: 已入系统 | AI3: 已下
A4: 45754 | B4: 美国 | C4: Jennifer | D4: Wal-Mart Inc. USA | E4: 0908207820 | F4: PO209044 | G4: T01535 | H4: =VLOOKUP(G4,名称!A:B,2,0) -> 恐龙公园 | I4: 1080 | J4: 12 | K4: =I4/J4 -> 90 | L4: 45919 | M4: 45915 | N4: 45915 | O4: 已约 | S4: OK | T4: 客供彩盒RFID贴纸/客供AD贴纸 | V4: 是 | W4: 天空：840148219519 陆地：840148219496 海洋：840148219502 | X4: 沃尔玛版本彩盒 （12位数UPC条码） | Y4: 美文版本说明书 | Z4: RR23925 | AA4: 90箱包一个卡板, 一个卡板贴一张客供AD贴纸+1张工厂自行打印的A4纸箱唛 订单都需要滑片包装 | AB4: 2.06 | AC4: =AB4*I4 -> 2224.8 | AD4: =AC4*7.75 -> 17242.2 | AE4: 45908 | AH4: 已入系统 | AJ4: 贴纸4/10RFID贴纸4/17给张佩玲 | AK4: =(I4*2.1*7.75)*0.3 -> 5273.1 | AL4: 45908
A5: 45754 | B5: 美国 | C5: Jennifer | D5: Wal-Mart Inc. USA | E5: 0908207753 | F5: PO209045 | G5: T01535 | H5: =VLOOKUP(G5,名称!A:B,2,0) -> 恐龙公园 | I5: 1080 | J5: 12 | K5: =I5/J5 -> 90 | L5: 45925 | M5: 45918 | N5: 45915 | O5: 已约 | S5: OK | T5: 客供彩盒RFID贴纸/客供AD贴纸 | V5: 是 | W5: 天空：840148219519 陆地：840148219496 海洋：840148219502 | X5: 沃尔玛版本彩盒 （12位数UPC条码） | Y5: 美文版本说明书 | Z5: RR23925 | AA5: 90箱包一个卡板, 一个卡板贴一张客供AD贴纸+1张工厂自行打印的A4纸箱唛 订单都需要滑片包装 | AB5: 2.06 | AC5: =AB5*I5 -> 2224.8 | AD5: =AC5*7.75 -> 17242.2 | AE5: 45908 | AH5: 已入系统 | AJ5: 贴纸4/10RFID贴纸4/17给张佩玲 | AK5: =(I5*2.1*7.75)*0.3 -> 5273.1 | AL5: 45908
A6: 45754 | B6: 美国 | C6: Jennifer | D6: Wal-Mart Inc. USA | E6: 0908207829 | F6: PO209046 | G6: T01535 | H6: =VLOOKUP(G6,名称!A:B,2,0) -> 恐龙公园 | I6: 1080 | J6: 12 | K6: =I6/J6 -> 90 | L6: 45933 | M6: 45926 | N6: 45926 | O6: 已约 | S6: OK | T6: 客供彩盒RFID贴纸/客供AD贴纸 | V6: 是 | W6: 天空：840148219519 陆地：840148219496 海洋：840148219502 | X6: 沃尔玛版本彩盒 （12位数UPC条码） | Y6: 美文版本说明书 | Z6: RR23925 | AA6: 90箱包一个卡板, 一个卡板贴一张客供AD贴纸+1张工厂自行打印的A4纸箱唛 订单都需要滑片包装 | AB6: 2.06 | AC6: =AB6*I6 -> 2224.8 | AD6: =AC6*7.75 -> 17242.2 | AE6: 45908 | AH6: 已入系统 | AJ6: 贴纸4/10RFID贴纸4/17给张佩玲 | AK6: =(I6*2.1*7.75)*0.3 -> 5273.1 | AL6: 45908
A7: 45754 | B7: 美国 | C7: Jennifer | D7: Wal-Mart Inc. USA | E7: 0908207736 | F7: PO209047 | G7: T01535 | H7: =VLOOKUP(G7,名称!A:B,2,0) -> 恐龙公园 | I7: 1080 | J7: 12 | K7: =I7/J7 -> 90 | L7: 45937 | M7: 45930 | N7: 45926 | O7: 已约 | S7: OK | T7: 客供彩盒RFID贴纸/客供AD贴纸 | V7: 是 | W7: 天空：840148219519 陆地：840148219496 海洋：840148219502 | X7: 沃尔玛版本彩盒 （12位数UPC条码） | Y7: 美文版本说明书 | Z7: RR23925 | AA7: 90箱包一个卡板, 一个卡板贴一张客供AD贴纸+1张工厂自行打印的A4纸箱唛 订单都需要滑片包装 | AB7: 2.06 | AC7: =AB7*I7 -> 2224.8 | AD7: =AC7*7.75 -> 17242.2 | AE7: 45908 | AH7: 已入系统 | AJ7: 贴纸4/10RFID贴纸4/17给张佩玲 | AK7: =(I7*2.1*7.75)*0.3 -> 5273.1 | AL7: 45908
A8: 45754 | B8: 美国 | C8: Jennifer | D8: Wal-Mart Inc. USA | E8: 0908207813 | F8: PO209048 | G8: T01535 | H8: =VLOOKUP(G8,名称!A:B,2,0) -> 恐龙公园 | I8: 1080 | J8: 12 | K8: =I8/J8 -> 90 | L8: 45937 | M8: 45930 | N8: 45926 | O8: 已约 | S8: OK | T8: 客供彩盒RFID贴纸/客供AD贴纸 | V8: 是 | W8: 天空：840148219519 陆地：840148219496 海洋：840148219502 | X8: 沃尔玛版本彩盒 （12位数UPC条码） | Y8: 美文版本说明书 | Z8: RR23925 | AA8: 90箱包一个卡板, 一个卡板贴一张客供AD贴纸+1张工厂自行打印的A4纸箱唛 订单都需要滑片包装 | AB8: 2.06 | AC8: =AB8*I8 -> 2224.8 | AD8: =AC8*7.75 -> 17242.2 | AE8: 45908 | AH8: 已入系统 | AJ8: 贴纸4/10RFID贴纸4/17给张佩玲 | AK8: =(I8*2.1*7.75)*0.3 -> 5273.1 | AL8: 45908
A9: 45754 | B9: 美国 | C9: Jennifer | D9: Wal-Mart Inc. USA | E9: 0908207783 | F9: PO209050 | G9: T01535 | H9: =VLOOKUP(G9,名称!A:B,2,0) -> 恐龙公园 | I9: 2160 | J9: 12 | K9: =I9/J9 -> 180 | L9: 45945 | M9: 45943 | N9: 45943 | O9: 已约 | S9: OK | T9: 客供彩盒RFID贴纸/客供AD贴纸 | V9: 是 | W9: 天空：840148219519 陆地：840148219496 海洋：840148219502 | X9: 沃尔玛版本彩盒 （12位数UPC条码） | Y9: 美文版本说明书 | Z9: RR23925 | AA9: 90箱包一个卡板, 一个卡板贴一张客供AD贴纸+1张工厂自行打印的A4纸箱唛 订单都需要滑片包装 | AB9: 2.06 | AC9: =AB9*I9 -> 4449.6 | AD9: =AC9*7.75 -> 34484.4 | AE9: 45908 | AH9: 已入系统 | AJ9: 贴纸4/10RFID贴纸4/17给张佩玲 | AK9: =(I9*2.1*7.75)*0.3 -> 10546.2 | AL9: 45908
A10: 45754 | B10: 美国 | C10: Jennifer | D10: Wal-Mart Inc. USA | E10: 0908207781 | F10: PO209051 | G10: T01535 | H10: =VLOOKUP(G10,名称!A:B,2,0) -> 恐龙公园 | I10: 2160 | J10: 12 | K10: =I10/J10 -> 180 | L10: 45950 | M10: 45943 | N10: 45943 | O10: 已约 | S10: OK | T10: 客供彩盒RFID贴纸/客供AD贴纸 | V10: 是 | W10: 天空：840148219519 陆地：840148219496 海洋：840148219502 | X10: 沃尔玛版本彩盒 （12位数UPC条码） | Y10: 美文版本说明书 | Z10: RR23925 | AA10: 90箱包一个卡板, 一个卡板贴一张客供AD贴纸+1张工厂自行打印的A4纸箱唛 订单都需要滑片包装 | AB10: 2.06 | AC10: =AB10*I10 -> 4449.6 | AD10: =AC10*7.75 -> 34484.4 | AE10: 45908 | AH10: 已入系统 | AJ10: 贴纸4/10RFID贴纸4/17给张佩玲 | AK10: =(I10*2.1*7.75)*0.3 -> 10546.2 | AL10: 45908
A11: 45754 | B11: 美国 | C11: Jennifer | D11: Wal-Mart Inc. USA | E11: 0908207802 | F11: PO209052 | G11: T01535 | H11: =VLOOKUP(G11,名称!A:B,2,0) -> 恐龙公园 | I11: 1080 | J11: 12 | K11: =I11/J11 -> 90 | L11: 45950 | M11: 45943 | N11: 45943 | O11: 已约 | S11: OK | T11: 客供彩盒RFID贴纸/客供AD贴纸 | V11: 是 | W11: 天空：840148219519 陆地：840148219496 海洋：840148219502 | X11: 沃尔玛版本彩盒 （12位数UPC条码） | Y11: 美文版本说明书 | Z11: RR23925 | AA11: 90箱包一个卡板, 一个卡板贴一张客供AD贴纸+1张工厂自行打印的A4纸箱唛 订单都需要滑片包装 | AB11: 2.06 | AC11: =AB11*I11 -> 2224.8 | AD11: =AC11*7.75 -> 17242.2 | AE11: 45908 | AH11: 已入系统 | AJ11: 贴纸4/10RFID贴纸4/17给张佩玲 | AK11: =(I11*2.1*7.75)*0.3 -> 5273.1 | AL11: 45908
A12: 45857 | B12: 美国 | C12: Jennifer | D12: Wal-Mart Inc. USA | E12: 0931994883 | F12: PO210597 | G12: T01535 | H12: 恐龙公园 | I12: 5400 | J12: 12 | K12: 450 | L12: 45915 | M12: 45915 | N12: 45915 | O12: 已约 | S12: OK | T12: 客供彩盒RFID贴纸/客供AD贴纸 | V12: 是 | W12: 天空：840148219519 陆地：840148219496 海洋：840148219502 | X12: 沃尔玛版本彩盒 （12位数UPC条码） | Y12: 美文版本说明书 | Z12: RR20225 | AA12: 90箱包一个卡板, 一个卡板贴一张客供AD贴纸+1张工厂自行打印的A4纸箱唛 订单都需要滑片包装 | AB12: 2.06 | AC12: 11124 | AD12: 86211 | AE12: 45908 | AH12: 已入系统 | AJ12: 7/29给张佩玲 | AK12: 26365.5 | AL12: 45908
A13: 45857 | B13: 美国 | C13: Jennifer | D13: Wal-Mart Inc. USA | E13: 0931994886 | F13: PO210599 | G13: T01535 | H13: 恐龙公园 | I13: 8640 | J13: 12 | K13: 720 | L13: 45915 | M13: 45915 | N13: 45915 | O13: 已约 | S13: OK | T13: 客供彩盒RFID贴纸/客供AD贴纸 | V13: 是 | W13: 天空：840148219519 陆地：840148219496 海洋：840148219502 | X13: 沃尔玛版本彩盒 （12位数UPC条码） | Y13: 美文版本说明书 | Z13: RR20225 | AA13: 90箱包一个卡板, 一个卡板贴一张客供AD贴纸+1张工厂自行打印的A4纸箱唛 订单都需要滑片包装 | AB13: 2.06 | AC13: 17798.4 | AD13: 137937.6 | AE13: 45908 | AH13: 已入系统 | AJ13: 7/29给张佩玲 | AK13: 42184.8 | AL13: 45908
A14: 45857 | B14: 美国 | C14: Jennifer | D14: Wal-Mart Inc. USA | E14: 0931994900 | F14: PO210601 | G14: T01535 | H14: 恐龙公园 | I14: 5400 | J14: 12 | K14: 450 | L14: 45915 | M14: 45915 | N14: 45915 | O14: 已约 | S14: OK | T14: 客供彩盒RFID贴纸/客供AD贴纸 | V14: 是 | W14: 天空：840148219519 陆地：840148219496 海洋：840148219502 | X14: 沃尔玛版本彩盒 （12位数UPC条码） | Y14: 美文版本说明书 | Z14: RR20225 | AA14: 90箱包一个卡板, 一个卡板贴一张客供AD贴纸+1张工厂自行打印的A4纸箱唛 订单都需要滑片包装 | AB14: 2.06 | AC14: 11124 | AD14: 86211 | AE14: 45908 | AH14: 已入系统 | AJ14: 7/29给张佩玲 | AK14: 26365.5 | AL14: 45908
A15: 45857 | B15: 美国 | C15: Jennifer | D15: Wal-Mart Inc. USA | E15: 0931994881 | F15: PO210602 | G15: T01535 | H15: 恐龙公园 | I15: 5400 | J15: 12 | K15: 450 | L15: 45926 | M15: 45926 | N15: 45926 | O15: 已约 | S15: OK | T15: 客供彩盒RFID贴纸/客供AD贴纸 | V15: 是 | W15: 天空：840148219519 陆地：840148219496 海洋：840148219502 | X15: 沃尔玛版本彩盒 （12位数UPC条码） | Y15: 美文版本说明书 | Z15: RR20225 | AA15: 90箱包一个卡板, 一个卡板贴一张客供AD贴纸+1张工厂自行打印的A4纸箱唛 订单都需要滑片包装 | AB15: 2.06 | AC15: 11124 | AD15: 86211 | AE15: 45908 | AH15: 已入系统 | AJ15: 7/29给张佩玲 | AK15: 26365.5 | AL15: 45908
A16: 45857 | B16: 美国 | C16: Jennifer | D16: Wal-Mart Inc. USA | E16: 0931994882 | F16: PO210603 | G16: T01535 | H16: 恐龙公园 | I16: 3240 | J16: 12 | K16: 270 | L16: 45926 | M16: 45926 | N16: 45926 | O16: 已约 | S16: OK | T16: 客供彩盒RFID贴纸/客供AD贴纸 | V16: 是 | W16: 天空：840148219519 陆地：840148219496 海洋：840148219502 | X16: 沃尔玛版本彩盒 （12位数UPC条码） | Y16: 美文版本说明书 | Z16: RR20225 | AA16: 90箱包一个卡板, 一个卡板贴一张客供AD贴纸+1张工厂自行打印的A4纸箱唛 订单都需要滑片包装 | AB16: 2.06 | AC16: 6674.4 | AD16: 51726.6 | AE16: 45908 | AH16: 已入系统 | AJ16: 7/29给张佩玲 | AK16: 15819.3 | AL16: 45908
A17: 45857 | B17: 美国 | C17: Jennifer | D17: Wal-Mart Inc. USA | E17: 0931994888 | F17: PO210604 | G17: T01535 | H17: 恐龙公园 | I17: 7560 | J17: 12 | K17: 630 | L17: 45926 | M17: 45926 | N17: 45926 | O17: 已约 | S17: OK | T17: 客供彩盒RFID贴纸/客供AD贴纸 | V17: 是 | W17: 天空：840148219519 陆地：840148219496 海洋：840148219502 | X17: 沃尔玛版本彩盒 （12位数UPC条码） | Y17: 美文版本说明书 | Z17: RR20225 | AA17: 90箱包一个卡板, 一个卡板贴一张客供AD贴纸+1张工厂自行打印的A4纸箱唛 订单都需要滑片包装 | AB17: 2.06 | AC17: 15573.6 | AD17: 120695.4 | AE17: 45908 | AH17: 已入系统 | AJ17: 7/29给张佩玲 | AK17: 36911.7 | AL17: 45908
A18: 45857 | B18: 美国 | C18: Jennifer | D18: Wal-Mart Inc. USA | E18: 0931994890 | F18: PO210605 | G18: T01535 | H18: 恐龙公园 | I18: 1080 | J18: 12 | K18: 90 | L18: 45926 | M18: 45926 | N18: 45926 | O18: 已约 | S18: OK | T18: 客供彩盒RFID贴纸/客供AD贴纸 | V18: 是 | W18: 天空：840148219519 陆地：840148219496 海洋：840148219502 | X18: 沃尔玛版本彩盒 （12位数UPC条码） | Y18: 美文版本说明书 | Z18: RR20225 | AA18: 90箱包一个卡板, 一个卡板贴一张客供AD贴纸+1张工厂自行打印的A4纸箱唛 订单都需要滑片包装 | AB18: 2.06 | AC18: 2224.8 | AD18: 17242.2 | AE18: 45908 | AH18: 已入系统 | AJ18: 7/29给张佩玲 | AK18: 5273.1 | AL18: 45908
A19: 45857 | B19: 美国 | C19: Jennifer | D19: Wal-Mart Inc. USA | E19: 0931994892 | F19: PO210606 | G19: T01535 | H19: 恐龙公园 | I19: 1080 | J19: 12 | K19: 90 | L19: 45926 | M19: 45926 | N19: 45926 | O19: 已约 | S19: OK | T19: 客供彩盒RFID贴纸/客供AD贴纸 | V19: 是 | W19: 天空：840148219519 陆地：840148219496 海洋：840148219502 | X19: 沃尔玛版本彩盒 （12位数UPC条码） | Y19: 美文版本说明书 | Z19: RR20225 | AA19: 90箱包一个卡板, 一个卡板贴一张客供AD贴纸+1张工厂自行打印的A4纸箱唛 订单都需要滑片包装 | AB19: 2.06 | AC19: 2224.8 | AD19: 17242.2 | AE19: 45908 | AH19: 已入系统 | AJ19: 7/29给张佩玲 | AK19: 5273.1 | AL19: 45908
A20: 45857 | B20: 美国 | C20: Jennifer | D20: Wal-Mart Inc. USA | E20: 0931994893 | F20: PO210607 | G20: T01535 | H20: 恐龙公园 | I20: 1080 | J20: 12 | K20: 90 | L20: 45926 | M20: 45926 | N20: 45926 | O20: 已约 | S20: OK | T20: 客供彩盒RFID贴纸/客供AD贴纸 | V20: 是 | W20: 天空：840148219519 陆地：840148219496 海洋：840148219502 | X20: 沃尔玛版本彩盒 （12位数UPC条码） | Y20: 美文版本说明书 | Z20: RR20225 | AA20: 90箱包一个卡板, 一个卡板贴一张客供AD贴纸+1张工厂自行打印的A4纸箱唛 订单都需要滑片包装 | AB20: 2.06 | AC20: 2224.8 | AD20: 17242.2 | AE20: 45908 | AH20: 已入系统 | AJ20: 7/29给张佩玲 | AK20: 5273.1 | AL20: 45908
A21: 45939 | B21: 美国 | C21: Jennifer | D21: Wal-Mart Inc. USA | E21: 0947524640 | F21: PO211192 | G21: T01535 | H21: 恐龙公园 | I21: 1080 | J21: 12 | K21: =I21/J21 -> 90 | L21: 45975 | M21: =L21-7 -> 45968 | N21: 45971 | O21: 已约 | P21: OK | S21: OK | T21: 客供AD贴纸 | V21: 是 | W21: 天空：840148219519 陆地：840148219496 海洋：840148219502 | X21: 沃尔玛版本彩盒 （12位数UPC条码） | Y21: 美文版本说明书 | Z21: RR20225 | AA21: 90箱包一个卡板, 一个卡板贴一张客供AD贴纸+1张工厂自行打印的A4纸箱唛 订单都需要滑片包装 从PO209045取消单中转出，需修改箱唛上的内容 | AB21: 2.06 | AC21: =AB21*I21 -> 2224.8 | AD21: =AC21*7.75 -> 17242.2 | AE21: 45981 | AJ21: AD贴纸10/16给到佩玲 | AK21: =(AC21*7.75)*0.3 -> 5172.66 | AL21: 45972
A22: 45951 | B22: 美国 | C22: Jennifer | D22: Wal-Mart Inc. USA | E22: 0951184673 | F22: PO211346 | G22: T01535 | H22: 恐龙公园 | I22: 4320 | J22: 12 | K22: =I22/J22 -> 360 | L22: 45986 | M22: 45982 | N22: 45982 | T22: 客供AD贴纸 | V22: 是 | W22: 天空：840148219519 陆地：840148219496 海洋：840148219502 | X22: 沃尔玛版本彩盒 （12位数UPC条码） | Y22: 美文版本说明书 | Z22: RR20225 | AA22: 90箱包一个卡板, 一个卡板贴一张客供AD贴纸+1张工厂自行打印的A4纸箱唛 订单都需要滑片包装 从PO210601取消单中转出，需修改箱唛上的内容 | AB22: 2.06 | AC22: =AB22*I22 -> 8899.2 | AD22: =AC22*7.75 -> 68968.8 | AE22: 45981 | AJ22: AD贴纸10/27给到佩玲 | AL22: 45972
AC23: =AB23*I23 -> 0 | AD23: =AC23*7.75 -> 0
AC24: =AB24*I24 -> 0 | AD24: =AC24*7.75 -> 0
AC25: =AB25*I25 -> 0 | AD25: =AC25*7.75 -> 0
AC26: =AB26*I26 -> 0 | AD26: =AC26*7.75 -> 0
I27: =SUM(I2:I26) -> 63084 | AC27: =SUM(AC2:AC26) -> 149582.88 | AD27: =SUM(AD2:AD26) -> 1159267.3

Sheet 已收费半成品及成品
A1: 货号 | B1: 名称 | C1: 产品状态 | D1: 实单扣数单价 | E1: 单价 (半成品单价含30%定金) | F1: 客人剩余MA数量 | G1: 开票金额 Need to pay for Blance MA | H1: 总计开票金额 total | I1: Deposite paid | J1: total Deposite Paid | K1: Need to pay for official order | L1: total | M1: Not Shipped QTY
A2: JW-RV-RPGE | B2: Jurassic World Ravenous Raptors | C2: 半成品 | D2: 3.55 | E2: =2.2+4.5*0.3 -> 3.55 | F2: =9996-504 -> 9492 | G2: =E2*F2-I2 -> 20882.4 | H2: =G2+G3 -> 98516 | I2: =F2*4.5*0.3 -> 12814.2 | J2: =I2+I3 -> 60453 | K2: =4.5*F2-I2-G2 -> 9017.4 | L2: =K2+K3 -> 42541 | M2: 6006 | N2: =3990-1002-1002-498-574-914 -> 0 | O2: =4.52-E2 -> 0.97 | P2: =4.5*0.3 -> 1.35
A3: JW-RV-RPGE | B3: Jurassic World Ravenous Raptors | C3: 半成品 | D3: 3.55 | E3: =2.2+4.5*0.3 -> 3.55 | F3: 35288 | G3: =E3*F3-I3 -> 77633.6 | I3: =F3*4.5*0.3 -> 47638.8 | K3: =4.5*F3-I3-G3 -> 33523.6 | M3: 0 | N3: =34784-386-198-942-432-924 -> 31902 | O3: =4.52-E3 -> 0.97 | P3: =4.5*0.3 -> 1.35
A4: T01685 | B4: Jurassic Dino Epic Quest | C4: 半成品 | D4: 3.91 | E4: 3.66 | F4: 11922 | G4: =E4*F4-I4 -> 27468.29 | H4: =G4+G5 -> 43300.95 | I4: =F4*4.52*0.3 -> 16166.23 | J4: =I4+I5 -> 22951.65 | K4: =4.52*F4-I4-G4 -> 10252.92 | L4: =K4+K5 -> 10252.92 | M4: 0 | O4: =4.52-E4 -> 0.86 | P4: =4.52*0.3 -> 1.356
C5: 成品 | D5: 3.91 | E5: =4.52 -> 4.52 | F5: 5004 | G5: =E5*F5-I5 -> 15832.66 | I5: =F5*4.52*0.3 -> 6785.42 | K5: =4.52*F5-I5-G5 -> 0 | M5: 0 | O5: =4.52-E5 -> 0 | P5: =4.52*0.3 -> 1.356
A6: T01535 | B6: Dinorama S1-sky | C6: 成品 | D6: 0 | E6: =2.1 -> 2.1 | F6: 15924 | G6: =E6*F6-I6 -> 23408.28 | H6: =G6+G7+G8 -> 70224.84 | I6: =F6*2.1*0.3 -> 10032.12 | J6: 30096.36 | K6: =E6*F6-I6-G6 -> 0 | L6: =K6+K7+K8 -> 0 | M6: 540 | N6: =F6-(540+3024+132+144+504)/3 -> 14476 | O6: =2.1-E6 -> 0 | P6: =2.1*0.3 -> 0.63
A7: T01535 | B7: Dinorama S1-land | C7: 成品 | D7: 0 | E7: =2.1 -> 2.1 | F7: 15924 | G7: =E7*F7-I7 -> 23408.28 | I7: =F7*2.1*0.3 -> 10032.12 | K7: =E7*F7-I7-G7 -> 0 | N7: =F7-(540+3024+132+144+504)/3 -> 14476 | O7: =2.1-E7 -> 0 | P7: =2.1*0.3 -> 0.63
A8: T01535 | B8: Dinorama S1-sea | C8: 成品 | D8: 0 | E8: =2.1 -> 2.1 | F8: 15924 | G8: =E8*F8-I8 -> 23408.28 | I8: =F8*2.1*0.3 -> 10032.12 | K8: =E8*F8-I8-G8 -> 0 | N8: =F8-(540+3024+132+144+504)/3 -> 14476 | O8: =2.1-E8 -> 0 | P8: =2.1*0.3 -> 0.63
E9: 总计： | F9: =SUM(F2:F8) -> 109478 | G9: =SUM(G2:G8) -> 212041.79 | H9: =SUM(H2:H8) -> 212041.79 | I9: =SUM(I2:I8) -> 113501.01 | J9: =SUM(J2:J8) -> 113501.01 | K9: =SUM(K2:K8) -> 52793.92 | L9: =SUM(L2:L8) -> 52793.92
A12: Customer | B12: PO# | C12: Item No | D12: Item Name | E12: Status | F12: Start Date | G12: Order Qty | H12: Unit cost | I12: Balance QTY(INCLUDING ALL OPENING ORDERS) | J12: Total Amount | K12: Deposite inSAP | L12: Qty in SAP | M12: Total balance qty(including all opening orders) | N12: Deposite paid | O12: Need to pay | P12: Deduct unit price in future payment
A13: PO000100 | B13: 240059 | C13: JW-RV-RPGE | D13: Jurassic World Ravenous Raptors | E13: semi product | F13: 45362 | G13: 300000 | H13: 3.55 | I13: 9996 | J13: =H13*I13 -> 35485.8 | K13: 2448.9 | L13: 9996 | M13: 44780 | N13: 60453 | O13: =(J13+J14)-N13 -> 98516
A14: PO000100 | B14: 240090 | C14: JW-RV-RPGE | D14: Jurassic World Ravenous Raptors | E14: semi product | F14: 45705 | G14: 150000 | H14: 3.55 | I14: =34784 -> 34784 | J14: =H14*I14 -> 123483.2 | K14: 58684.5 | L14: 37585
A15: P00000114 | B15: 240088 | C15: T01685 | D15: Jurassic Dino Epic Quest | E15: semi product | F15: 45715 | G15: 45000 | H15: 3.66 | I15: 11922 | J15: =H15*I15 -> 43634.52 | K15: 22951.66 | L15: 16926 | M15: 16926 | N15: 22951.66 | O15: =(J15+J16)-N15 -> 43300.94 | P15: =ROUND((O15+N15)/M15,2) -> 3.91
E16: finished product | H16: 4.52 | I16: 5004 | J16: =H16*I16 -> 22618.08
A17: P00000106 | B17: 240117 | C17: T01535 | D17: Dinorama S1-sky | E17: finished product | F17: 45861 | G17: 22128 | H17: =2.1 -> 2.1 | I17: 15924 | J17: =H17*I17 -> 33440.4 | K17: 30096.36 | L17: 12960 | M17: 47772 | N17: 30096.36 | O17: =(J17+J18+J19)-N17 -> 70224.84 | P17: =(O17+N17)/M17 -> 2.1
A18: P00000107 | B18: 240117 | C18: T01535 | D18: Dinorama S1-land | E18: finished product | F18: 45861 | G18: 22128 | H18: =2.1 -> 2.1 | I18: 15924 | J18: =H18*I18 -> 33440.4 | L18: 12960
A19: P00000108 | B19: 240117 | C19: T01535 | D19: Dinorama S1-sea | E19: finished product | F19: 45861 | G19: 22128 | H19: =2.1 -> 2.1 | I19: 15924 | J19: =H19*I19 -> 33440.4 | L19: 12960
I20: =SUM(I13:I19) -> 109478 | J20: =SUM(J13:J19) -> 325542.8
O21: =SUM(O13:O20) -> 212041.78

Sheet MA排期
A1: 接单期 | B1: 国家 | C1: 客跟单 | D1: 客户 | E1: Customer PO | F1: PO号 | G1: 货号 | H1: 名称 | I1: MA数量 | J1: 装箱数 | K1: 总箱数 | L1: 单价 | M1: 金额USD | N1: 金额HKD
F2: 定金 | G2: JW-RV-RPGE | H2: =VLOOKUP(G2,名称!A:B,2,0) -> 恐龙游戏盘 | I2: =44780-1002 -> 43778 | J2: =VLOOKUP(G2,名称!A:C,3,FALSE) -> 6 | K2: =I2/J2 -> 7296.3333 | L2: 4.5 | M2: =L2*I2*0.3 -> 59100.3 | N2: =M2*7.75 -> 458027.33 | O2: =N2-'[2]Toy Monster'!$O$79 -> 458027.33
F3: 定金 | G3: T01535 | H3: =VLOOKUP(G3,名称!A:B,2,0) -> 恐龙公园 | I3: 49452 | J3: =VLOOKUP(G3,名称!A:C,3,FALSE) -> 12 | K3: =I3/J3 -> 4121 | L3: 2.1 | M3: =L3*I3*0.3 -> 31154.76 | N3: =M3*7.75 -> 241449.39 | O3: =N3-'[2]Toy Monster'!$O$83 -> 241449.39
F4: 定金 | G4: T01685 | H4: =VLOOKUP(G4,名称!A:B,2,0) -> 手术游戏盘 | I4: 16926 | J4: =VLOOKUP(G4,名称!A:C,3,FALSE) -> 6 | K4: =I4/J4 -> 2821 | L4: 4.52 | M4: =L4*I4*0.3 -> 22951.66 | N4: =M4*7.75 -> 177875.37 | O4: =N4-'[2]Toy Monster'!$O$84 -> 177875.37
F5: 定金 | G5: T02444 | H5: =VLOOKUP(G5,名称!A:B,2,0) -> 恐龙公园二代 | I5: =42180-1800 -> 40380 | J5: =VLOOKUP(G5,名称!A:C,3,FALSE) -> 12 | K5: =I5/J5 -> 3365 | L5: 2.1 | M5: =L5*I5*0.3 -> 25439.4 | N5: =M5*7.75 -> 197155.35 | O5: =N5-'[2]Toy Monster'!$O$88 -> #VALUE!
F6: 定金 | G6: T03980 | H6: =VLOOKUP(G6,名称!A:B,2,0) -> 9.5寸绿色淋油公仔+涂鸦公仔混装 | I6: 9568 | J6: =VLOOKUP(G6,名称!A:C,3,FALSE) -> 2 | K6: =I6/J6 -> 4784 | L6: 5.6 | M6: =L6*I6*0.3 -> 16074.24 | N6: =M6*7.75 -> 124575.36 | O6: =N6-'[2]Toy Monster'!$O$92 -> 124575.36
F7: 定金 | G7: T03204 | H7: =VLOOKUP(G7,名称!A:B,2,0) -> 9.5寸粉红熊公仔+格力奇熊仔混装 | I7: =896+896-1792 -> 0 | J7: =VLOOKUP(G7,名称!A:C,3,FALSE) -> 2 | K7: =I7/J7 -> 0 | L7: 6.34 | M7: 0 | N7: =M7*7.75 -> 0 | O7: =N7-'[2]Toy Monster'!$O$91 -> 0
M8: =L8*I8*0.3 -> 0 | N8: =M8*7.75 -> 0
M9: =L9*I9*0.3 -> 0 | N9: =M9*7.75 -> 0
M10: =L10*I10*0.3 -> 0 | N10: =M10*7.75 -> 0
M11: =L11*I11*0.3 -> 0 | N11: =M11*7.75 -> 0
M12: =L12*I12*0.3 -> 0 | N12: =M12*7.75 -> 0
I13: =SUM(I2:I12) -> 160104 | M13: =SUM(M2:M12) -> 154720.36 | N13: =SUM(N2:N12) -> 1199082.8 | O13: =N13-'[2]Toy Monster'!$O$94 -> 1021207.5
F15: 尾款 | G15: JW-RV-RPGE | H15: =VLOOKUP(G15,名称!A:B,2,0) -> 恐龙游戏盘 | I15: =44780-1002 -> 43778 | J15: =VLOOKUP(G15,名称!A:C,3,FALSE) -> 6 | K15: =I15/J15 -> 7296.3333 | L15: 4.5 | M15: =I15*3.55-I15*P15 -> 96311.6 | N15: =M15*7.75 -> 746414.9 | O15: 半成品 | P15: =L15*0.3 -> 1.35
F16: 尾款 | G16: T01685 | H16: =VLOOKUP(G16,名称!A:B,2,0) -> 手术游戏盘 | I16: 11922 | J16: =VLOOKUP(G16,名称!A:C,3,FALSE) -> 6 | K16: =I16/J16 -> 1987 | L16: 4.52 | M16: =I16*3.66-I16*P16 -> 27468.29 | N16: =M16*7.75 -> 212879.25 | O16: 半成品 | P16: =L16*0.3 -> 1.356
F17: 尾款 | G17: T01685 | H17: =VLOOKUP(G17,名称!A:B,2,0) -> 手术游戏盘 | I17: 5004 | J17: =VLOOKUP(G17,名称!A:C,3,FALSE) -> 6 | K17: =I17/J17 -> 834 | L17: 4.52 | M17: =I17*4.52-I17*P17 -> 15832.66 | N17: =M17*7.75 -> 122703.12 | O17: 成品 | P17: =L17*0.3 -> 1.356
F18: 尾款 | G18: T01535 | H18: =VLOOKUP(G18,名称!A:B,2,0) -> 恐龙公园 | I18: 47772 | J18: =VLOOKUP(G18,名称!A:C,3,FALSE) -> 12 | K18: =I18/J18 -> 3981 | L18: 2.1 | M18: =I18*2.1-I18*P18 -> 70224.84 | N18: =M18*7.75 -> 544242.51 | O18: 成品 | P18: =L18*0.3 -> 0.63
M19: =I19*L19 -> 0 | N19: =M19*7.75 -> 0
M20: =I20*L20 -> 0 | N20: =M20*7.75 -> 0
M21: =I21*L21 -> 0 | N21: =M21*7.75 -> 0
M22: =I22*L22 -> 0 | N22: =M22*7.75 -> 0
M23: =I23*L23 -> 0 | N23: =M23*7.75 -> 0
M24: =I24*L24 -> 0 | N24: =M24*7.75 -> 0
I25: =SUM(I15:I24) -> 108476 | M25: =SUM(M15:M24) -> 209837.39 | N25: =SUM(N15:N24) -> 1626239.8

Sheet 详细MA表
A1: Toymonster客放MA扣数情况
A2: 释放时间 | B2: Customer | C2: PO号 | D2: 货号 | E2: 名称 | F2: 数量 | H2: 接单数
A3: 45247 | C3: 欠PO2 | D3: JW-RV-RPGE | E3: 恐龙游戏盘 | F3: 5000
A4: 45315 | B4: 443 | C4: 240056 | D4: JW-RV-RPGE | E4: 恐龙游戏盘 | F4: 10000
A5: 45346 | B5: PO000100 | C5: 240059 | D5: JW-RV-RPGE | E5: 恐龙游戏盘 | F5: 70000
A6: 45363 | B6: PO000100 | C6: 240059 | D6: JW-RV-RPGE | E6: 恐龙游戏盘 | F6: 70000
A7: 45401 | B7: PO000100 | C7: 240059 | D7: JW-RV-RPGE | E7: 恐龙游戏盘 | F7: 160000
A8: 45631 | B8: P00000106 | C8: 240076 | D8: T01535 | E8: 恐龙公园 （天空） | F8: 37000
A9: 45631 | B9: P00000107 | C9: 240076 | D9: T01535 | E9: 恐龙公园 （陆地） | F9: 37000
A10: 45631 | B10: P00000108 | C10: 240076 | D10: T01535 | E10: 恐龙公园 （海洋） | F10: 37000
A11: 45666 | B11: P00000106 | C11: 240079 | D11: T01535 | E11: 恐龙公园 （天空） | F11: 16667
A12: 45666 | B12: P00000107 | C12: 240079 | D12: T01535 | E12: 恐龙公园 （陆地） | F12: 16667
A13: 45666 | B13: P00000108 | C13: 240079 | D13: T01535 | E13: 恐龙公园 （海洋） | F13: 16667
A14: 45719 | B14: P00000114 | C14: 240088 | D14: T01685 | E14: 手术游戏盘 | F14: 45000
A15: 45721 | C15: 240090 | D15: JW-RV-RPGE | E15: 恐龙游戏盘 | F15: 150000
A17: Toymonster客放MA扣数情况
A18: 释放时间 | B18: Customer | C18: PO号 | D18: 货号 | E18: 名称 | F18: 数量 | G18: 总计数量 | H18: 已扣MA数量 | I18: 剩余MA数量 | J18: 单价 | K18: 金额USD | L18: 金额HKD | M18: 剩余MA数量金额USD | N18: 剩余MA数量金额HKD
A19: 45247 | C19: 欠PO2 | D19: JW-RV-RPGE | E19: 恐龙游戏盘 | F19: 5000 | G19: =SUM(F19:F24) -> 465338 | H19: 315000 | I19: 0 | J19: 4.5 | K19: =J19*F19 -> 22500 | L19: =K19*7.75 -> 174375 | M19: =I19*J19 -> 0 | N19: =M19*7.75 -> 0
A20: 45315 | B20: 443 | C20: 240056 | D20: JW-RV-RPGE | E20: 恐龙游戏盘 | F20: 10000 | J20: 4.5 | K20: =J20*F20 -> 45000 | L20: =K20*7.75 -> 348750 | M20: =I20*J20 -> 0 | N20: =M20*7.75 -> 0
A21: 45346 | B21: PO000100 | C21: 240059 | D21: JW-RV-RPGE | E21: 恐龙游戏盘 | F21: 70000 | J21: 4.5 | K21: =J21*F21 -> 315000 | L21: =K21*7.75 -> 2441250 | M21: =I21*J21 -> 0 | N21: =M21*7.75 -> 0
A22: 45363 | B22: PO000100 | C22: 240059 | D22: JW-RV-RPGE | E22: 恐龙游戏盘 | F22: =70000+I21 -> 70000 | J22: 4.5 | K22: =J22*F22 -> 315000 | L22: =K22*7.75 -> 2441250 | M22: =I22*J22 -> 0 | N22: =M22*7.75 -> 0
A23: 45401 | B23: PO000100 | C23: 240090 | D23: JW-RV-RPGE | E23: 恐龙游戏盘 | F23: =160000+I22 -> 160000 | J23: 4.5 | K23: =J23*F23 -> 720000 | L23: =K23*7.75 -> 5580000 | M23: =I23*J23 -> 0 | N23: =M23*7.75 -> 0
A24: 45705 | B24: PO000100 | C24: 240059 | D24: JW-RV-RPGE | E24: 恐龙游戏盘 | F24: =150000+338 -> 150338 | H24: =97614+SUM(总接单!I18:K99) -> 121682 | I24: =G19-H19-H24 -> 28656 | J24: 4.5 | K24: =J24*F24 -> 676521 | L24: =K24*7.75 -> 5243037.8 | M24: =I24*J24 -> 128952 | N24: =M24*7.75 -> 999378
A25: 45301 | B25: P00000106 | C25: 240076 | D25: T01535 | E25: 恐龙公园 （天空） | F25: 37000 | G25: =SUM(F25:F39) -> 396924 | H25: 37000 | I25: =F25-H25 -> 0 | J25: 2.1 | K25: =J25*F25 -> 77700 | L25: =K25*7.75 -> 602175 | M25: =I25*J25 -> 0 | N25: =M25*7.75 -> 0
A26: 45301 | B26: P00000107 | C26: 240076 | D26: T01535 | E26: 恐龙公园 （陆地） | F26: 37000 | H26: 37000 | I26: =F26-H26 -> 0 | J26: 2.1 | K26: =J26*F26 -> 77700 | L26: =K26*7.75 -> 602175 | M26: =I26*J26 -> 0 | N26: =M26*7.75 -> 0
A27: 45301 | B27: P00000108 | C27: 240076 | D27: T01535 | E27: 恐龙公园 （海洋） | F27: 37000 | H27: 37000 | I27: =F27-H27 -> 0 | J27: 2.1 | K27: =J27*F27 -> 77700 | L27: =K27*7.75 -> 602175 | M27: =I27*J27 -> 0 | N27: =M27*7.75 -> 0
A28: 45650 | B28: P00000106 | C28: 240079 | D28: T01535 | E28: 恐龙公园 （天空） | F28: 16667 | H28: 16667 | I28: 0 | J28: 2.1 | K28: =J28*F28 -> 35000.7 | L28: =K28*7.75 -> 271255.42 | M28: =I28*J28 -> 0 | N28: =M28*7.75 -> 0
A29: 45650 | B29: P00000107 | C29: 240079 | D29: T01535 | E29: 恐龙公园 （陆地） | F29: 16667 | H29: 16667 | I29: 0 | J29: 2.1 | K29: =J29*F29 -> 35000.7 | L29: =K29*7.75 -> 271255.42 | M29: =I29*J29 -> 0 | N29: =M29*7.75 -> 0
A30: 45650 | B30: P00000108 | C30: 240079 | D30: T01535 | E30: 恐龙公园 （海洋） | F30: 16667 | H30: 16667 | I30: 0 | J30: 2.1 | K30: =J30*F30 -> 35000.7 | L30: =K30*7.75 -> 271255.42 | M30: =I30*J30 -> 0 | N30: =M30*7.75 -> 0
A31: 45748 | B31: P00000106 | C31: 240106 | D31: T01535 | E31: 恐龙公园 （天空） | F31: 28333 | H31: 28333 | I31: =F31-H31 -> 0 | J31: 2.1 | K31: =J31*F31 -> 59499.3 | L31: =K31*7.75 -> 461119.58 | M31: =I31*J31 -> 0 | N31: =M31*7.75 -> 0
A32: 45748 | B32: P00000107 | C32: 240106 | D32: T01535 | E32: 恐龙公园 （陆地） | F32: 28333 | H32: 28333 | I32: =F32-H32 -> 0 | J32: 2.1 | K32: =J32*F32 -> 59499.3 | L32: =K32*7.75 -> 461119.58 | M32: =I32*J32 -> 0 | N32: =M32*7.75 -> 0
A33: 45748 | B33: P00000108 | C33: 240106 | D33: T01535 | E33: 恐龙公园 （海洋） | F33: 28333 | H33: 28333 | I33: =F33-H33 -> 0 | J33: 2.1 | K33: =J33*F33 -> 59499.3 | L33: =K33*7.75 -> 461119.58 | M33: =I33*J33 -> 0 | N33: =M33*7.75 -> 0
A34: 45835 | B34: P00000106 | C34: 240115 | D34: T01535 | E34: 恐龙公园 （天空） | F34: 28180 | H34: 28180 | I34: =F34-H34 -> 0 | J34: 2.1 | K34: =J34*F34 -> 59178 | L34: =K34*7.75 -> 458629.5 | M34: =I34*J34 -> 0 | N34: =M34*7.75 -> 0
A35: 45835 | B35: P00000107 | C35: 240115 | D35: T01535 | E35: 恐龙公园 （陆地） | F35: 28180 | H35: 28180 | I35: =F35-H35 -> 0 | J35: 2.1 | K35: =J35*F35 -> 59178 | L35: =K35*7.75 -> 458629.5 | M35: =I35*J35 -> 0 | N35: =M35*7.75 -> 0
A36: 45835 | B36: P00000108 | C36: 240115 | D36: T01535 | E36: 恐龙公园 （海洋） | F36: 28180 | H36: 28180 | I36: =F36-H36 -> 0 | J36: 2.1 | K36: =J36*F36 -> 59178 | L36: =K36*7.75 -> 458629.5 | M36: =I36*J36 -> 0 | N36: =M36*7.75 -> 0
A37: 45861 | B37: P00000106 | C37: 240117 | D37: T01535 | E37: 恐龙公园 （天空） | F37: 22128 | H37: =5644+(SUM(总接单!L53:L99)/3)+SUM(总接单!AQ2:AQ99) -> 7092 | I37: =F37-H37 -> 15036 | J37: 2.1 | K37: =J37*F37 -> 46468.8 | L37: =K37*7.75 -> 360133.2 | M37: =I37*J37 -> 31575.6 | N37: =M37*7.75 -> 244710.9
A38: 45861 | B38: P00000107 | C38: 240117 | D38: T01535 | E38: 恐龙公园 （陆地） | F38: 22128 | H38: =5644+(SUM(总接单!L53:L99)/3)+SUM(总接单!AO2:AO99) -> 7092 | I38: =F38-H38 -> 15036 | J38: 2.1 | K38: =J38*F38 -> 46468.8 | L38: =K38*7.75 -> 360133.2 | M38: =I38*J38 -> 31575.6 | N38: =M38*7.75 -> 244710.9
A39: 45861 | B39: P00000108 | C39: 240117 | D39: T01535 | E39: 恐龙公园 （海洋） | F39: 22128 | H39: =5644+(SUM(总接单!L53:L99)/3)+SUM(总接单!AP2:AP99) -> 7092 | I39: =F39-H39 -> 15036 | J39: 2.1 | K39: =J39*F39 -> 46468.8 | L39: =K39*7.75 -> 360133.2 | M39: =I39*J39 -> 31575.6 | N39: =M39*7.75 -> 244710.9
A40: 45898 | D40: T02444 | E40: 恐龙公园S2 (海滩) | F40: 20000 | G40: =SUM(F40:F42) -> 60000 | H40: =1200+SUM(总接单!M18:M99)/3+SUM(总接单!N31:N99)/2+SUM(总接单!AR2:AR99) -> 18594 | I40: =F40-H40 -> 1406 | J40: 2.1 | K40: =J40*F40 -> 42000 | L40: =K40*7.75 -> 325500 | M40: =I40*J40 -> 2952.6 | N40: =M40*7.75 -> 22882.65
A41: 45898 | D41: T02444 | E41: 恐龙公园S2 (草地) | F41: 20000 | H41: =1200+SUM(总接单!M18:M99)/3+SUM(总接单!AS2:AS99) -> 17112 | I41: =F41-H41 -> 2888 | J41: 2.1 | K41: =J41*F41 -> 42000 | L41: =K41*7.75 -> 325500 | M41: =I41*J41 -> 6064.8 | N41: =M41*7.75 -> 47002.2
A42: 45898 | D42: T02444 | E42: 恐龙公园S2 (实验室) | F42: 20000 | H42: =1200+SUM(总接单!M18:M99)/3+SUM(总接单!N31:N99)/2+SUM(总接单!AT2:AT99) -> 18594 | I42: =F42-H42 -> 1406 | J42: 2.1 | K42: =J42*F42 -> 42000 | L42: =K42*7.75 -> 325500 | M42: =I42*J42 -> 2952.6 | N42: =M42*7.75 -> 22882.65
A43: 45715 | B43: P00000114 | C43: 240088 | D43: T01685 | E43: 手术游戏盘 | F43: 45000 | G43: =F43 -> 45000 | H43: =27894+SUM(总接单!O18:P99) -> 28074 | I43: =F43-H43 -> 16926 | J43: 4.52 | K43: =J43*F43 -> 203400 | L43: =K43*7.75 -> 1576350 | M43: =I43*J43 -> 76505.52 | N43: =M43*7.75 -> 592917.78
A44: 45972 | B44: P00000133 | C44: 240140 | D44: T02943 | E44: 9.5寸粉红熊公仔（移印） | F44: 6500 | G44: =F44 -> 6500 | H44: =5604+896 -> 6500 | I44: =G44-H44 -> 0 | J44: 6.34 | K44: =J44*F44 -> 41210 | L44: =K44*7.75 -> 319377.5 | M44: =I44*J44 -> 0 | N44: =M44*7.75 -> 0
A45: 45972 | B45: P00000134 | C45: 240140 | D45: T02945 | E45: 9.5寸格力奇公仔 （移印） | F45: 6500 | G45: =F45 -> 6500 | H45: =5604+896 -> 6500 | I45: =G45-H45 -> 0 | J45: 6.64 | K45: =J45*F45 -> 43160 | L45: =K45*7.75 -> 334490 | M45: =I45*J45 -> 0 | N45: =M45*7.75 -> 0
B47: 名称 | C47: MA数量 | D47: 已扣MA数量 | E47: 剩余MA数量
A48: 总计 | B48: 恐龙游戏盘 | C48: =SUMIF(E18:E43,B48,F18:F43) -> 465338 | D48: =SUMIF(E18:E43,B48,H18:H43) -> 436682 | E48: =SUMIF(E18:E43,B48,I18:I43) -> 28656
B49: 恐龙公园 （天空） | C49: =SUMIF(E18:E43,B49,F18:F43) -> 132308 | D49: =SUMIF(E18:E43,B49,H18:H43) -> 117272 | E49: =SUMIF(E18:E43,B49,I18:I43) -> 15036
B50: 恐龙公园 （陆地） | C50: =SUMIF(E18:E43,B50,F18:F43) -> 132308 | D50: =SUMIF(E18:E43,B50,H18:H43) -> 117272 | E50: =SUMIF(E18:E43,B50,I18:I43) -> 15036
B51: 恐龙公园 （海洋） | C51: =SUMIF(E18:E43,B51,F18:F43) -> 132308 | D51: =SUMIF(E18:E43,B51,H18:H43) -> 117272 | E51: =SUMIF(E18:E43,B51,I18:I43) -> 15036
B52: 恐龙公园S2 (海滩) | C52: 20000 | D52: =SUMIF(E19:E44,B52,H19:H44) -> 18594 | E52: =SUMIF(E19:E44,B52,I19:I44) -> 1406
B53: 恐龙公园S2 (草地) | C53: 20000 | D53: =SUMIF(E20:E45,B53,H20:H45) -> 17112 | E53: =SUMIF(E20:E45,B53,I20:I45) -> 2888
B54: 恐龙公园S2 (实验室) | C54: 20000 | D54: =SUMIF(E21:E46,B54,H21:H46) -> 18594 | E54: =SUMIF(E21:E46,B54,I21:I46) -> 1406
B55: 手术游戏盘 | C55: =SUMIF(E18:E43,B55,F18:F43) -> 45000 | D55: =SUMIF(E18:E43,B55,H18:H43) -> 28074 | E55: =SUMIF(E18:E43,B55,I18:I43) -> 16926
B56: 9.5寸粉红熊公仔（移印） | C56: =SUMIF(E19:E45,B56,F19:F45) -> 6500 | D56: =SUMIF(E19:E45,B56,H19:H45) -> 6500 | E56: =SUMIF(E19:E45,B56,I19:I45) -> 0
B57: 9.5寸格力奇公仔 （移印） | C57: =SUMIF(E19:E45,B57,F19:F45) -> 6500 | D57: =SUMIF(E19:E45,B57,H19:H45) -> 6500 | E57: =SUMIF(E19:E45,B57,I19:I45) -> 0

Sheet MA
A1: 接单期 | B1: 国家 | C1: 客跟单 | D1: 客户 | E1: Customer | F1: PO号 | G1: 货号 | H1: 名称 | I1: 客人放MA数量 | J1: 剩余MA数量 | K1: 装箱数 | L1: 总箱数 | M1: 客PO期 | N1: 出货期 | O1: 验货期 | P1: 验货 结果 | Q1: 船期SO | R1: 箱唛资料 | S1: 客贴纸 | T1: 是否寄出签办 | U1: 是否打卡板 | V1: 彩盒UPC条码 | W1: 彩盒版本 | X1: 说明书版本 | Y1: 日期码 | Z1: 备注 | AA1: 单价 | AB1: 金额USD | AC1: 金额HKD | AD1: 发票号 | AE1: 是否入系统
A2: 45401 | E2: PO000100 | F2: 240059 | G2: JW-RV-RPGE | H2: 恐龙游戏盘 | J2: =15232-384-768-2176-2816-1792-1408-1280-1024-3000-246-338 -> 0 | K2: 6 | L2: =J2/K2 -> 0 | M2: 45658 | N2: 45658 | AA2: 4.5 | AB2: =AA2*J2 -> 0 | AC2: =AB2*7.75 -> 0 | AE2: 已收款30%
A3: 45666 | E3: P00000106 | F3: 240079 | G3: T01535 | H3: 恐龙公园 （天空） | I3: 16667 | J3: =16667-((1764+744+1800+240+360+1200+1440+1800+2400+1800+1800+1200+1080+2160+2160+1080+2160+2160+3240+2160+1080+1080+1080+2160+2160+2160+2160+2160+2160+1053)/3) -> 0 | K3: 1 | L3: =J3/K3 -> 0 | M3: 46015 | N3: 46015 | AA3: 2.1 | AB3: =AA3*J3 -> 0 | AC3: =AB3*7.75 -> 0 | AD3: 82948 | AE3: 已收款30%
A4: 45666 | E4: P00000107 | F4: 240079 | G4: T01535 | H4: 恐龙公园 （陆地） | I4: 16667 | J4: =16667-((1764+744+1800+240+360+1200+1440+1800+2400+1800+1800+1200+1080+2160+2160+1080+2160+2160+3240+2160+1080+1080+1080+2160+2160+2160+2160+2160+2160+1053)/3) -> 0 | K4: 1 | L4: =J4/K4 -> 0 | M4: 46015 | N4: 46015 | AA4: 2.1 | AB4: =AA4*J4 -> 0 | AC4: =AB4*7.75 -> 0 | AD4: 82948 | AE4: 已收款30%
A5: 45666 | E5: P00000108 | F5: 240079 | G5: T01535 | H5: 恐龙公园 （海洋） | I5: 16667 | J5: =16667-((1764+744+1800+240+360+1200+1440+1800+2400+1800+1800+1200+1080+2160+2160+1080+2160+2160+3240+2160+1080+1080+1080+2160+2160+2160+2160+2160+2160+1053)/3) -> 0 | K5: 1 | L5: =J5/K5 -> 0 | M5: 46015 | N5: 46015 | AA5: 2.1 | AB5: =AA5*J5 -> 0 | AC5: =AB5*7.75 -> 0 | AD5: 82948 | AE5: 已收款30%
A6: 45719 | E6: P00000114 | F6: 240088 | G6: T01685 | H6: 手术游戏盘 | I6: 45000 | J6: =45000-5004-2610-1392-3252-4998-2130-3006-4998-504-180 -> 16926 | K6: 6 | L6: =J6/K6 -> 2821 | M6: 46080 | N6: 46080 | AA6: 4.52 | AB6: =AA6*J6 -> 76505.52 | AC6: =AB6*7.75 -> 592917.78 | AD6: 82978REV1 | AE6: 已收款30%
A7: 45721 | F7: 240090 | G7: JW-RV-RPGE | H7: 恐龙游戏盘 | I7: 150000 | J7: =150000+338-1002-1002-498-1164-654-930-120-348-324-480-654-696-354-252-2816-1536-240-1002-534-138-216-342-720-512-384-512-384-1152-4224-4224-2316-7200-2520-5832-7200-1230-1014-288-624-768-384-384-512-640-384-640-6702-3000-512-640-384-384-384-768-640-624-564-256-512-640-768-3072-768-3328-726-624-2100-516-892-384-1300-700-1536-384-768-896-896-256-1500-504-1014-624-1200-180-1000-500-1200-1000-500-6306-504-1002-1002-1002-1800-1200-574-1300-198-942-432-924 -> 28656 | K7: 2 | L7: =J7/K7 -> 14328 | M7: 46070 | N7: 46070 | AA7: 4.5 | AB7: =AA7*J7 -> 128952 | AC7: =AB7*7.75 -> 999378 | AD7: 82979 | AE7: 已收款30%
A8: 45768 | F8: PO209007 PO209008 PO209009 PO209010 PO209011 PO209012 PO209013 PO209014 PO209015 PO209016 PO209017 PO209018 PO209019 PO209020 PO209021 PO209022 PO209023 PO209024 PO209025 PO209026 PO209027 PO209028 PO209029 PO209030 PO209031 PO209032 PO209033 PO209035 PO209036 PO209037 PO209038 PO209039 PO209040 PO209041 PO209042 PO209043 PO209044 PO209045 PO209046 PO209047 PO209048 PO209049 PO209050 PO209051 PO209052 PO208985 PO208986 PO208987 PO208988 PO208989 PO209062 | G8: T01535 | H8: 恐龙公园 （天空） | J8: =(144747/3)-48249 -> 0 | K8: 1 | L8: =J8/K8 -> 0 | M8: 45847 | N8: 45847 | AA8: 2.06 | AB8: =AA8*J8 -> 0 | AC8: =AB8*7.75 -> 0 | AD8: 83013取消
A9: 45768 | F9: PO209007 PO209008 PO209009 PO209010 PO209011 PO209012 PO209013 PO209014 PO209015 PO209016 PO209017 PO209018 PO209019 PO209020 PO209021 PO209022 PO209023 PO209024 PO209025 PO209026 PO209027 PO209028 PO209029 PO209030 PO209031 PO209032 PO209033 PO209035 PO209036 PO209037 PO209038 PO209039 PO209040 PO209041 PO209042 PO209043 PO209044 PO209045 PO209046 PO209047 PO209048 PO209049 PO209050 PO209051 PO209052 PO208985 PO208986 PO208987 PO208988 PO208989 PO209062 | G9: T01535 | H9: 恐龙公园 （陆地） | J9: =(144747/3)-48249 -> 0 | K9: 1 | L9: =J9/K9 -> 0 | M9: 45847 | N9: 45847 | AA9: 2.06 | AB9: =AA9*J9 -> 0 | AC9: =AB9*7.75 -> 0 | AD9: 83013取消
A10: 45768 | F10: PO209007 PO209008 PO209009 PO209010 PO209011 PO209012 PO209013 PO209014 PO209015 PO209016 PO209017 PO209018 PO209019 PO209020 PO209021 PO209022 PO209023 PO209024 PO209025 PO209026 PO209027 PO209028 PO209029 PO209030 PO209031 PO209032 PO209033 PO209035 PO209036 PO209037 PO209038 PO209039 PO209040 PO209041 PO209042 PO209043 PO209044 PO209045 PO209046 PO209047 PO209048 PO209049 PO209050 PO209051 PO209052 PO208985 PO208986 PO208987 PO208988 PO208989 PO209062 | G10: T01535 | H10: 恐龙公园 （海洋） | J10: =(144747/3)-48249 -> 0 | K10: 1 | L10: =J10/K10 -> 0 | M10: 45847 | N10: 45847 | AA10: 2.06 | AB10: =AA10*J10 -> 0 | AC10: =AB10*7.75 -> 0 | AD10: 83013取消
A11: 45768 | F11: PO209062 | G11: T01535 | H11: 恐龙公园 （天空） | J11: =1200/3-400 -> 0 | K11: 1 | L11: =J11/K11 -> 0 | M11: 45847 | N11: 45847 | AA11: 2.1 | AB11: =AA11*J11 -> 0 | AC11: =AB11*7.75 -> 0 | AD11: 83013取消
A12: 45768 | F12: PO209062 | G12: T01535 | H12: 恐龙公园 （陆地） | J12: =1200/3-400 -> 0 | K12: 1 | L12: =J12/K12 -> 0 | M12: 45847 | N12: 45847 | AA12: 2.1 | AB12: =AA12*J12 -> 0 | AC12: =AB12*7.75 -> 0 | AD12: 83013取消
A13: 45768 | F13: PO209062 | G13: T01535 | H13: 恐龙公园 （海洋） | J13: =1200/3-400 -> 0 | K13: 1 | L13: =J13/K13 -> 0 | M13: 45847 | N13: 45847 | AA13: 2.1 | AB13: =AA13*J13 -> 0 | AC13: =AB13*7.75 -> 0 | AD13: 83013取消
A14: 45748 | F14: 240106 | G14: T01535 | H14: 恐龙公园 （天空） | I14: 28333 | J14: =28333-((360+1200+2040+360+480+900+600+144+180+348+1107+2160+3240+4320+3240+3240+2160+4320+3240+4320+4320+4320+4320+3240+4320+3240+4320+6480+3240+3240+4320+1680)/3) -> 0 | K14: 1 | L14: =J14/K14 -> 0 | AA14: 2.1 | AB14: =AA14*J14 -> 0 | AC14: =AB14*7.75 -> 0 | AD14: 83041 | AE14: 已收款30%
A15: 45748 | F15: 240106 | G15: T01535 | H15: 恐龙公园 （陆地） | I15: 28333 | J15: =28333-((360+1200+2040+360+480+900+600+144+180+348+1107+2160+3240+4320+3240+3240+2160+4320+3240+4320+4320+4320+4320+3240+4320+3240+4320+6480+3240+3240+4320+1680)/3) -> 0 | K15: 1 | L15: =J15/K15 -> 0 | AA15: 2.1 | AB15: =AA15*J15 -> 0 | AC15: =AB15*7.75 -> 0 | AD15: 83041 | AE15: 已收款30%
A16: 45748 | F16: 240106 | G16: T01535 | H16: 恐龙公园 （海洋） | I16: 28333 | J16: =28333-((360+1200+2040+360+480+900+600+144+180+348+1107+2160+3240+4320+3240+3240+2160+4320+3240+4320+4320+4320+4320+3240+4320+3240+4320+6480+3240+3240+4320+1680)/3) -> 0 | K16: 1 | L16: =J16/K16 -> 0 | AA16: 2.1 | AB16: =AA16*J16 -> 0 | AC16: =AB16*7.75 -> 0 | AD16: 83041 | AE16: 已收款30%
A17: 45835 | F17: 240115 | G17: T01535 | H17: 恐龙公园 （天空） | I17: 28180 | J17: =28180-((2160+2160+2160+2160+2160+1560+3240+4320+4320+3240+3240+3240+3240+2160+3240+4320+2160+3240+1080+1080+1080+1080+1080+1080+1080+1080+2160+2160+1080+1404+5400+6480+4896)/3) -> 0 | K17: 1 | L17: =J17/K17 -> 0 | AA17: 2.1 | AB17: =AA17*J17 -> 0 | AC17: =AB17*7.75 -> 0 | AD17: 83061REV1 | AE17: 已收款30%
A18: 45835 | F18: 240115 | G18: T01535 | H18: 恐龙公园 （陆地） | I18: 28180 | J18: =28180-((2160+2160+2160+2160+2160+1560+3240+4320+4320+3240+3240+3240+3240+2160+3240+4320+2160+3240+1080+1080+1080+1080+1080+1080+1080+1080+2160+2160+1080+1404+5400+6480+4896)/3) -> 0 | K18: 1 | L18: =J18/K18 -> 0 | AA18: 2.1 | AB18: =AA18*J18 -> 0 | AC18: =AB18*7.75 -> 0 | AD18: 83061REV1 | AE18: 已收款30%
A19: 45835 | F19: 240115 | G19: T01535 | H19: 恐龙公园 （海洋） | I19: 28180 | J19: =28180-((2160+2160+2160+2160+2160+1560+3240+4320+4320+3240+3240+3240+3240+2160+3240+4320+2160+3240+1080+1080+1080+1080+1080+1080+1080+1080+2160+2160+1080+1404+5400+6480+4896)/3) -> 0 | K19: 1 | L19: =J19/K19 -> 0 | AA19: 2.1 | AB19: =AA19*J19 -> 0 | AC19: =AB19*7.75 -> 0 | AD19: 83061REV1 | AE19: 已收款30%
A20: 45861 | F20: 240117 | G20: T01535 | H20: 恐龙公园 （天空） | I20: 22128 | J20: =22128-(504+2160+1080+1080+4320+1080+5400+6480+8640+5400+5400+5400+3240+7560+1080+1080+1080+5400-1080-1080-1080-1080-1080-2160-2160-1080-5400-8640-5400-5400-3240-7560-1080-1080-1080+1080+4320+228-1080-4320+540+132+144+504)/3-408-600 -> 15036 | K20: 1 | L20: =J20/K20 -> 15036 | AA20: 2.1 | AB20: =AA20*J20 -> 31575.6 | AC20: =AB20*7.75 -> 244710.9 | AD20: 83090 | AE20: 已收款30%
A21: 45861 | F21: 240117 | G21: T01535 | H21: 恐龙公园 （陆地） | I21: 22128 | J21: =22128-(504+2160+1080+1080+4320+1080+5400+6480+8640+5400+5400+5400+3240+7560+1080+1080+1080+5400-1080-1080-1080-1080-1080-2160-2160-1080-5400-8640-5400-5400-3240-7560-1080-1080-1080+1080+4320+228-1080-4320+540+132+144+504)/3-408-600 -> 15036 | K21: 1 | L21: =J21/K21 -> 15036 | AA21: 2.1 | AB21: =AA21*J21 -> 31575.6 | AC21: =AB21*7.75 -> 244710.9 | AD21: 83090 | AE21: 已收款30%
A22: 45861 | F22: 240117 | G22: T01535 | H22: 恐龙公园 （海洋） | I22: 22128 | J22: =22128-(504+2160+1080+1080+4320+1080+5400+6480+8640+5400+5400+5400+3240+7560+1080+1080+1080+5400-1080-1080-1080-1080-1080-2160-2160-1080-5400-8640-5400-5400-3240-7560-1080-1080-1080+1080+4320+228-1080-4320+540+132+144+504)/3-408-600 -> 15036 | K22: 1 | L22: =J22/K22 -> 15036 | AA22: 2.1 | AB22: =AA22*J22 -> 31575.6 | AC22: =AB22*7.75 -> 244710.9 | AD22: 83090 | AE22: 已收款30%
A23: 45898 | F23: 240128 | G23: T02444 | H23: 恐龙公园S2 (海滩) | I23: 20000 | J23: =20000-(1680+1200+720+780+564+6156+6288+432+1800+1800+1200+1500+1200+1656+5496+1224+6720+1404+720+5004+120+144+504)/3-1482-408-600 -> 1406 | K23: 1 | L23: =J23/K23 -> 1406 | AA23: 2.1 | AB23: =AA23*J23 -> 2952.6 | AC23: =AB23*7.75 -> 22882.65 | AD23: 83137 | AE23: 已收款30%
A24: 45898 | F24: 240128 | G24: T02444 | H24: 恐龙公园S2 (雨林) | I24: 20000 | J24: =20000-(1680+1200+720+780+564+6156+6288+432+1800+1800+1200+1500+1200+1656+5496+1224+6720+1404+720+5004+120+144+504)/3-408-600 -> 2888 | K24: 1 | L24: =J24/K24 -> 2888 | AA24: 2.1 | AB24: =AA24*J24 -> 6064.8 | AC24: =AB24*7.75 -> 47002.2 | AD24: 83137 | AE24: 已收款30%
A25: 45898 | F25: 240128 | G25: T02444 | H25: 恐龙公园S2 (实验室) | I25: 20000 | J25: =20000-(1680+1200+720+780+564+6156+6288+432+1800+1800+1200+1500+1200+1656+5496+1224+6720+1404+720+5004+120+144+504)/3-1482-408-600 -> 1406 | K25: 1 | L25: =J25/K25 -> 1406 | AA25: 2.1 | AB25: =AA25*J25 -> 2952.6 | AC25: =AB25*7.75 -> 22882.65 | AD25: 83137 | AE25: 已收款30%
A26: 45972 | E26: P00000133 | F26: 240140 | G26: T02943 | H26: 9.5寸粉红熊公仔（移印） | I26: 6500 | J26: =I26-800-2304-2500-896 -> 0 | K26: 2 | L26: =J26/K26 -> 0 | AA26: 6.34 | AB26: =AA26*J26 -> 0 | AC26: =AB26*7.75 -> 0 | AD26: 83206 | AE26: 已收款30%
A27: 45972 | E27: P00000134 | F27: 240140 | G27: T02945 | H27: 9.5寸格力奇公仔 （移印） | I27: 6500 | J27: =I27-800-2304-2500-896 -> 0 | K27: 2 | L27: =J27/K27 -> 0 | AA27: 6.64 | AB27: =AA27*J27 -> 0 | AC27: =AB27*7.75 -> 0 | AD27: 83206 | AE27: 已收款30%
A28: 46164 | F28: 240184 | G28: T03980 | H28: 9.5 inch Echo & Knox | I28: 9568 | J28: =I28-9568 -> 0 | K28: 2 | L28: =J28/K28 -> 0 | AA28: 5.6 | AB28: =AA28*J28 -> 0 | AC28: =AB28*7.75 -> 0 | AD28: 83247 | AE28: 已收款30%
A29: 46164 | AB29: =AA29*J29 -> 0 | AC29: =AB29*7.75 -> 0
AB30: =AA30*J30 -> 0 | AC30: =AB30*7.75 -> 0
J31: =SUM(J2:J30) -> 96390 | AB31: =SUM(AB1:AB30) -> 312154.32 | AC31: =SUM(AC3:AC30) -> 2419196
AC32: =AC31*0.7 -> 1693437.2
L33: =J3/4 -> 0 | AB33: 恐龙公园2代剩余MA金额 | AC33: =SUM(AC23:AC25)*0.7 -> 64937.25
L34: =J4/4 -> 0
L35: =J5/4 -> 0
M36: =J31=SUM(详细MA表!I19:I45) -> TRUE
A38: 46056 | E38: 内部释放 | G38: T02943 | H38: 9.5寸粉红熊公仔（移印） | I38: 5000 | J38: =I38-1804 -> 3196 | K38: 2 | L38: =J38/K38 -> 1598 | AA38: 6.24 | AB38: =AA38*J38 -> 19943.04 | AC38: =AB38*7.75 -> 154558.56
A39: 46056 | E39: 内部释放 | G39: T02945 | H39: 9.5寸格力奇公仔 （移印） | I39: 5000 | J39: =I39-1804 -> 3196 | K39: 2 | L39: =J39/K39 -> 1598 | AA39: 6.64 | AB39: =AA39*J39 -> 21221.44 | AC39: =AB39*7.75 -> 164466.16
A40: 46129 | E40: 内部释放 | G40: T03900 | H40: 漫画熊 | I40: 3000 | J40: =I40-1000-总接单!AB54 -> 1640
A41: 46129 | E41: 内部释放 | G41: T03900 | H41: 战士熊 | I41: 3000 | J41: =I41-1000-总接单!AC54 -> 1640
A42: 46129 | E42: 内部释放 | G42: T03900 | H42: 小女孩 | I42: 3000 | J42: =I42-1000-总接单!AD54 -> 1640
A43: 46129 | E43: 内部释放 | G43: T03900 | H43: 大眼睛 | I43: 3000 | J43: =I43-1000-总接单!AE54 -> 1640
A44: 46129 | E44: 内部释放 | G44: T03349 | H44: 寿司狗 | I44: 3003 | J44: =I44-(792+7200)*11/72-总接单!AF55 -> 1570
A45: 46129 | E45: 内部释放 | G45: T03349 | H45: 柯基 | I45: 3003 | J45: =I45-(792+7200)*11/72-总接单!AG55 -> 1570
A46: 46129 | E46: 内部释放 | G46: T03349 | H46: 爱心柴犬 | I46: 3003 | J46: =I46-(792+7200)*11/72-总接单!AH55 -> 1569
A47: 46129 | E47: 内部释放 | G47: T03349 | H47: 爱心猫 | I47: 3003 | J47: =I47-(792+7200)*11/72-总接单!AI55 -> 1569
A48: 46129 | E48: 内部释放 | G48: T03349 | H48: 仙人掌 | I48: 3003 | J48: =I48-(792+7200)*11/72-总接单!AJ55 -> 1569
A49: 46129 | E49: 内部释放 | G49: T03349 | H49: 鸡尾酒 | I49: 3003 | J49: =I49-(792+7200)*11/72-总接单!AK55 -> 1569
A50: 46129 | E50: 内部释放 | G50: T03349 | H50: 可爱熊猫 | I50: 1638 | J50: =I50-(792+7200)*6/72-总接单!AL55 -> 856

Sheet 包装MA
A1: 下单日期 | B1: Item | C1: 包装 | D1: 包装MA数量 | E1: 实单 | F1: 剩余包装数量 | G1: 备注
A2: 46086 | B2: T02444 | C2: PDQ | D2: 5000 | E2: =1000+SUM(正在做货!I2:I3)/12 -> 1225 | F2: =D2-E2 -> 3775
A3: 45996 | B3: T02444 | C3: 小彩盒WM版本(海滩套装)12位数条码 | D3: 3000 | E3: =(1680+720+1200+780)/3+1008 -> 2468 | F3: =D3-E3 -> 532 | G3: 客人放MA5000，PMC实际采购3000 PO211348--1680PCS PO211794--720PCS PO211605--1200PCS PO212218--780PCS PO213850--3024PCS
A4: 45996 | B4: T02444 | C4: 小彩盒WM版本(草地套装)12位数条码 | D4: 3000 | E4: =(1680+720+1200+780)/3+1008 -> 2468 | F4: =D4-E4 -> 532
A5: 45996 | B5: T02444 | C5: 小彩盒WM版本(实验室套装)12位数条码 | D5: 3000 | E5: =(1680+720+1200+780)/3+1008 -> 2468 | F5: =D5-E5 -> 532
A6: 46086 | B6: T02444 | C6: 小彩盒WW版本(海滩套装)13位数条码 | D6: 5000 | E6: =(564+6156+6288+432)/3 -> 4480 | F6: =D6-E6 -> 520 | G6: PO212479--564PCS PO212478--6156PCS PO212624--6288PCS PO212625--432PCS
A7: 46086 | B7: T02444 | C7: 小彩盒WW版本(草地套装)13位数条码 | D7: 5000 | E7: =(564+6156+6288+432)/3 -> 4480 | F7: =D7-E7 -> 520
A8: 46086 | B8: T02444 | C8: 小彩盒WW版本(实验室套装)13位数条码 | D8: 5000 | E8: =(564+6156+6288+432)/3 -> 4480 | F8: =D8-E8 -> 520
A9: 46104 | B9: T02444 | C9: 小彩盒WW版本(海滩套装)13位数条码 | D9: =F6+5000 -> 5520 | E9: =(1800+1800+1200+1500+1200+1656+5496+1224)/3 -> 5292 | F9: =D9-E9 -> 228 | G9: PO212775--1800PCS PO213307--1800PCS PO213308--1200PCS PO213309--1500PCS PO213310--1200PCS PO212874--1656PCS PO213046--5496PCS PO213048--1224PCS
A10: 46104 | B10: T02444 | C10: 小彩盒WW版本(草地套装)13位数条码 | D10: =F7+5000 -> 5520 | E10: =(1800+1800+1200+1500+1200+1656+5496+1224)/3 -> 5292 | F10: =D10-E10 -> 228
A11: 46104 | B11: T02444 | C11: 小彩盒WW版本(实验室套装)13位数条码 | D11: =F8+5000 -> 5520 | E11: =(1800+1800+1200+1500+1200+1656+5496+1224)/3 -> 5292 | F11: =D11-E11 -> 228
A12: 46129 | B12: T02444 | C12: 小彩盒通用版本(海滩套装)13位数条码 | D12: =5000+F9 -> 5228 | E12: =(6720+1404)/3 -> 2708 | F12: =D12-E12 -> 2520 | G12: PO213271--6720PCS PO212633--1404PCS
A13: 46129 | B13: T02444 | C13: 小彩盒通用版本(草地套装)13位数条码 | D13: =5000+F10 -> 5228 | E13: =(6720+1404)/3 -> 2708 | F13: =D13-E13 -> 2520
A14: 46129 | B14: T02444 | C14: 小彩盒通用版本(实验室套装)13位数条码 | D14: =5000+F11 -> 5228 | E14: =(6720+1404)/3 -> 2708 | F14: =D14-E14 -> 2520
A15: 46122 | B15: JW-RV-RPGEA | C15: 亚马逊版本彩盒 | D15: 5000 | E15: =1002+1002+1002+1002+1002+498 -> 5508 | F15: =D15-E15 -> -508 | G15: PO212868--1002PCS PO212869--1002PCS PO212870--1002PCS
B16: JW-RV-RPGEA | C16: 标准美文12位条形码 | D16: 3000 | E16: =504+574+1300 -> 2378 | F16: =D16-E16 -> 622 | G16: PO212516--504PCS
B17: JW-RV-RPGEA | C17: 标准美文13位条形码 | D17: 1650 | E17: =198+942+432+924 -> 2496 | F17: 1650
B18: JW-RV-RPGEA | C18: 沃尔玛版本12位条形码 | F18: 0

Sheet 日期码

Sheet 外箱资料
A1: 名称 | B1: 备注 | C1: 货号 | D1: 货名 | E1: 尺码英寸 | F1: G.W(kg) | G1: N.W(kg) | H1: 报客长 (CM) | I1: 报客宽 (CM) | J1: 报客高 (CM) | K1: G.W （LBS） | L1: N.W （LBS） | M1: 报客长 (inch) | N1: 报客宽 (inch) | O1: 报客高 (inch) | P1: CU.FT | Q1: CBM | R1: 总箱数 | S1: 总CBM
A2: 恐龙游戏盘 | B2: VM版 | C2: T01453 | D2: K4K(150磅) | E2: 27.7x23.7x27.8cm | F2: 1.77 | G2: 1.56 | H2: 28 | I2: 24.2 | J2: 28.3 | K2: =F2*2.2046 -> 3.9 | L2: =G2*2.2046 -> 3.44 | M2: =H2*0.3937 -> 11.02 | N2: =I2*0.3937 -> 9.53 | O2: =J2*0.3937 -> 11.14 | P2: =M2*N2*O2/1728 -> 0.677 | Q2: =P2/35.315 -> 0.0192 | S2: =R2*Q2 -> 0
A3: 恐龙游戏盘 | C3: T01453 | D3: B3B | E3: 26.2X25.8X8cm内卡*2 | K3: =F3*2.2046 -> 0 | L3: =G3*2.2046 -> 0 | M3: =H3*0.3937 -> 0 | N3: =I3*0.3937 -> 0 | O3: =J3*0.3937 -> 0 | P3: =M3*N3*O3/1728 -> 0 | Q3: =P3/35.315 -> 0 | S3: =R3*Q3 -> 0
A4: 恐龙游戏盘 | B4: 64箱/卡板 | C4: T01453 | D4: 牛皮纸 | E4: 111x97x15CM | K4: =F4*2.2046 -> 0 | L4: =G4*2.2046 -> 0 | M4: =H4*0.3937 -> 0 | N4: =I4*0.3937 -> 0 | O4: =J4*0.3937 -> 0 | P4: =M4*N4*O4/1728 -> 0 | Q4: =P4/35.315 -> 0 | S4: =R4*Q4 -> 0
A5: 恐龙游戏盘 | C5: JW-RV-RPGE | D5: K4K(150磅) | E5: 35.6X27.7X55cm | F5: 5.15 | G5: 4.68 | H5: 35.3 | I5: 27.7 | J5: 55.3 | K5: =F5*2.2046 -> 11.35 | L5: =G5*2.2046 -> 10.32 | M5: =H5*0.3937 -> 13.9 | N5: =I5*0.3937 -> 10.91 | O5: =J5*0.3937 -> 21.77 | P5: =M5*N5*O5/1728 -> 1.9105 | Q5: =P5/35.315 -> 0.0541 | R5: 33 | S5: =R5*Q5 -> 1.7853
A6: 恐龙游戏盘 | C6: JW-RV-RPGE | D6: B3B | E6: 26.2X25.8X8cm啤卡*6 | K6: =F6*2.2046 -> 0 | L6: =G6*2.2046 -> 0 | M6: =H6*0.3937 -> 0 | N6: =I6*0.3937 -> 0 | O6: =J6*0.3937 -> 0 | P6: =M6*N6*O6/1728 -> 0 | Q6: =P6/35.315 -> 0 | S6: =R6*Q6 -> 0
A7: 恐龙游戏盘 （亚马逊版本） | B7: 6 | C7: JW-RV-RPGEA | D7: K4K（外箱） | E7: 37*28*57.5cm | K7: =F7*2.2046 -> 0 | L7: =G7*2.2046 -> 0 | M7: =H7*0.3937 -> 0 | N7: =I7*0.3937 -> 0 | O7: =J7*0.3937 -> 0 | P7: =M7*N7*O7/1728 -> 0 | Q7: =P7/35.315 -> 0 | S7: =R7*Q7 -> 0
C8: JW-RV-RPGEA | D8: K4K（邮包盒） | E8: 27.8*11.8*27.8cm | K8: =F8*2.2046 -> 0 | L8: =G8*2.2046 -> 0 | M8: =H8*0.3937 -> 0 | N8: =I8*0.3937 -> 0 | O8: =J8*0.3937 -> 0 | P8: =M8*N8*O8/1728 -> 0 | Q8: =P8/35.315 -> 0 | S8: =R8*Q8 -> 0
A9: 恐龙公园 （天空） | B9: 12 | C9: T01535 | D9: A=A(175磅) | E9: 37.2X15.0X23.8cm | F9: 2.18 | G9: 1.92 | H9: 37.6 | I9: 15.6 | J9: 25.7 | K9: =F9*2.2046 -> 4.81 | L9: =G9*2.2046 -> 4.23 | M9: =H9*0.3937 -> 14.8 | N9: =I9*0.3937 -> 6.14 | O9: =J9*0.3937 -> 10.12 | P9: =M9*N9*O9/1728 -> 0.5322 | Q9: =P9/35.315 -> 0.0151 | R9: =1404/12 -> 117 | S9: =R9*Q9 -> 1.7667
A10: 恐龙公园 （陆地） | C10: T01535 | D10: B3B | E10: 370X220MM压线卡*1 | K10: =F10*2.2046 -> 0 | L10: =G10*2.2046 -> 0 | M10: =H10*0.3937 -> 0 | N10: =I10*0.3937 -> 0 | O10: =J10*0.3937 -> 0 | P10: =M10*N10*O10/1728 -> 0 | Q10: =P10/35.315 -> 0 | S10: =R10*Q10 -> 0
A11: 恐龙公园 （海洋） | B11: 90箱/卡板 | C11: T01535 | D11: 牛皮纸 | E11: 113x96x15CM | S11: =R11*Q11 -> 0
A12: 恐龙游戏盘 | B12: 3 | C12: JW-RV-RPGE-3PK | D12: K4K(150磅) | E12: 35*27.7*28CM | F12: 2.59 | G12: 2.32 | H12: 35 | I12: 28 | J12: 28 | K12: =F12*0.3937 -> 1.02 | L12: =G12*0.3937 -> 0.91 | M12: =H12*0.3937 -> 13.78 | N12: =K12*L12*M12/1728 -> 0.01 | O12: =N12/35.315 -> 0 | P12: =M12*N12*O12/1728 -> 0 | Q12: =P12/35.315 -> 0 | S12: =R12*Q12 -> 0
A13: 手术游戏盘 | B13: 6 | C13: T01685-S | D13: K=K 175磅 双坑 | E13: 315*285*287MM | F13: 3.59 | G13: 3.11 | H13: 32.4 | I13: 29.3 | J13: 30.5 | K13: =F13*2.2046 -> 7.91 | L13: =G13*2.2046 -> 6.86 | M13: =H13*0.3937 -> 12.76 | N13: =I13*0.3937 -> 11.54 | O13: =J13*0.3937 -> 12.01 | P13: =M13*N13*O13/1728 -> 1.0234 | Q13: =P13/35.315 -> 0.029 | R13: =435+232 -> 667 | S13: =R13*Q13 -> 19.343
A14: 手术游戏盘 | C14: T01685-S | D14: K4K | E14: 270*290MM平卡*2 | K14: =F14*2.2046 -> 0 | L14: =G14*2.2046 -> 0 | M14: =H14*0.3937 -> 0 | N14: =I14*0.3937 -> 0 | O14: =J14*0.3937 -> 0 | P14: =M14*N14*O14/1728 -> 0 | Q14: =P14/35.315 -> 0 | S14: =R14*Q14 -> 0
A15: 手术游戏盘 （亚马逊版本） | B15: 6 | C15: T01685-A | D15: K4K(150磅)外箱 | E15: 34*33*29cm | K15: =F15*2.2046 -> 0 | L15: =G15*2.2046 -> 0 | M15: =H15*0.3937 -> 0 | N15: =I15*0.3937 -> 0 | O15: =J15*0.3937 -> 0 | P15: =M15*N15*O15/1728 -> 0 | Q15: =P15/35.315 -> 0 | S15: =R15*Q15 -> 0
D16: K4K | E16: 31.5*5.1*27.6cm | K16: =F16*2.2046 -> 0 | L16: =G16*2.2046 -> 0 | M16: =H16*0.3937 -> 0 | N16: =I16*0.3937 -> 0 | O16: =J16*0.3937 -> 0 | P16: =M16*N16*O16/1728 -> 0 | Q16: =P16/35.315 -> 0 | S16: =R16*Q16 -> 0
A17: 9.5寸暴力熊Echo | C17: T02942 | F17: 4.7 | G17: 3.81 | H17: 50.6 | I17: 32 | J17: 44.2 | K17: 2.13 | L17: 1.73 | M17: 19.92 | N17: 12.6 | O17: 17.4
A18: 9.5寸暴力熊Trixie | C18: T02943 | F18: 4.7 | G18: 3.81 | H18: 50.6 | I18: 32 | J18: 44.2 | K18: 2.13 | L18: 1.73 | M18: 19.92 | N18: 12.6 | O18: 17.4
A19: 9.5寸暴力熊Knox | C19: T02944 | F19: 4.7 | G19: 3.81 | H19: 50.6 | I19: 32 | J19: 44.2 | K19: 2.13 | L19: 1.73 | M19: 19.92 | N19: 12.6 | O19: 17.4
A20: 9.5寸暴力熊Glitch | C20: T02945 | F20: 4.7 | G20: 3.81 | H20: 50.6 | I20: 32 | J20: 44.2 | K20: 2.13 | L20: 1.73 | M20: 19.92 | N20: 12.6 | O20: 17.4
A21: 9.5寸暴力熊Trixie | B21: 2 | C21: T02943-2 | E21: 26 X 23.1 X 32 CM | F21: 1.48 | G21: 1.09 | K21: =F21*2.2046 -> 3.26 | L21: =G21*2.2046 -> 2.4 | M21: =H21*0.3937 -> 0 | N21: =I21*0.3937 -> 0 | O21: =J21*0.3937 -> 0 | P21: =M21*N21*O21/1728 -> 0 | Q21: =P21/35.315 -> 0
A22: 9.5寸暴力熊Glitch | B22: 2 | C22: T02945-2 | E22: 26 X 23.1 X 32 CM | F22: 1.48 | G22: 1.09 | K22: =F22*2.2046 -> 3.26 | L22: =G22*2.2046 -> 2.4 | M22: =H22*0.3937 -> 0 | N22: =I22*0.3937 -> 0 | O22: =J22*0.3937 -> 0 | P22: =M22*N22*O22/1728 -> 0 | Q22: =P22/35.315 -> 0
A23: 9.5寸FLiar | B23: 2 | C23: T03190 | E23: 26 X 23.1 X 32 CM | F23: 1.48 | G23: 1.09 | K23: =F23*2.2046 -> 3.26 | L23: =G23*2.2046 -> 2.4 | M23: =H23*0.3937 -> 0 | N23: =I23*0.3937 -> 0 | O23: =J23*0.3937 -> 0 | P23: =M23*N23*O23/1728 -> 0 | Q23: =P23/35.315 -> 0
A24: 9.5寸Striker | B24: 2 | C24: T03191 | E24: 26 X 23.1 X 32 CM | F24: 1.48 | G24: 1.09 | K24: =F24*2.2046 -> 3.26 | L24: =G24*2.2046 -> 2.4 | M24: =H24*0.3937 -> 0 | N24: =I24*0.3937 -> 0 | O24: =J24*0.3937 -> 0 | P24: =M24*N24*O24/1728 -> 0 | Q24: =P24/35.315 -> 0
A25: 9.5寸Clutch | B25: 2 | C25: T03192 | E25: 26 X 23.1 X 32 CM | F25: 1.48 | G25: 1.09 | K25: =F25*2.2046 -> 3.26 | L25: =G25*2.2046 -> 2.4 | M25: =H25*0.3937 -> 0 | N25: =I25*0.3937 -> 0 | O25: =J25*0.3937 -> 0 | P25: =M25*N25*O25/1728 -> 0 | Q25: =P25/35.315 -> 0

Sheet 产品价格
A1: 货号 | B1: 名称 | C1: 版本 | D1: 装箱数 | E1: 散货价 | F1: 20尺柜价格
A2: JW-RV-RPGE | B2: 恐龙游戏盘 | C2: 标准版/Smyth | D2: 6 | E2: 4.5
A3: T01453 | C3: WM | D3: 2 | E3: 4.5
A4: JW-RV-RPGE-3PK | D4: 3 | E4: 5.05
A5: JW-RV-RPGEA | C5: 邮包盒 | D5: 6 | E5: 4.9
A6: T01685-S | B6: 手术游戏盘 | C6: SMYTH | D6: 6 | E6: 4.52
A7: T01685A | C7: 邮包盒 | D7: 6 | E7: 4.76
A8: T01535 | B8: 恐龙公园1代 | C8: 国际版 | D8: 12 | E8: 2.1
A9: T01535 | C9: WM | D9: 12 | E9: 2.06
A10: T02428 | B10: 9.5寸暴力熊 | C10: 标准版 | D10: 8 | E10: 5.88 | F10: 5.72
A11: T02942 | B11: 9.5寸绿色淋油公仔（移印） | C11: WM | D11: 8 | E11: 6.18 | F11: 6.02
A12: T02943 | B12: 9.5寸粉红熊公仔（移印） | C12: WM | D12: 8 | E12: 6.18 | F12: 6.02
A13: T02944 | B13: 9.5寸涂鸦公仔（移印） | C13: WM | D13: 8 | E13: 4.67 | F13: 4.51
A14: T02945 | B14: 9.5寸格力奇公仔 （移印） | C14: WM | D14: 8 | E14: 6.5 | F14: 6.32
A15: T02943-2 | B15: 9.5寸粉红熊公仔（移印） | C15: WM | D15: 2 | E15: 6.2 | F15: 5.95
A16: T02945-2 | B16: 9.5寸格力奇公仔 （移印） | C16: WM | D16: 2 | E16: 6.5 | F16: 6.25
A17: T02943-2 | B17: 9.5寸粉红熊公仔（移印） | C17: WM | D17: 1 | E17: 6.34 | F17: 6.09
A18: T02945-2 | B18: 9.5寸格力奇公仔 （移印） | C18: WM | D18: 1 | E18: 6.64 | F18: 6.39
A19: T03190 | B19: FLiar | C19: WM | D19: 2 | E19: 6.4 | F19: 6.15
A20: T03191 | B20: Striker | C20: WM | D20: 2 | E20: 6.72 | F20: 6.47
A21: T03192 | B21: Clutch | C21: WM | D21: 2 | E21: 5.84 | F21: 5.59
A22: T03349 | B22: 3寸可爱系列 | C22: 标准版 | D22: 12 | E22: 1.82 | F22: 1.8

Sheet PDQ配比
A2: 3寸可爱系列
D13: 0.15277778 | E13: 0.15277778 | F13: 0.15277778 | G13: 0.15277778 | H13: 0.15277778 | I13: 0.15277778 | J13: 0.083333333
C14: A | D14: 1 | E14: 2 | F14: 2 | G14: 2 | H14: 2 | I14: 2 | J14: 1
C15: E | D15: 2 | E15: 1 | F15: 2 | G15: 2 | H15: 2 | I15: 2 | J15: 1
C16: H | D16: 2 | E16: 2 | F16: 1 | G16: 2 | H16: 2 | I16: 2 | J16: 1
C17: K | D17: 2 | E17: 2 | F17: 2 | G17: 1 | H17: 2 | I17: 2 | J17: 1
C18: N | D18: 2 | E18: 2 | F18: 2 | G18: 2 | H18: 1 | I18: 2 | J18: 1
C19: Q | D19: 2 | E19: 2 | F19: 2 | G19: 2 | H19: 2 | I19: 1 | J19: 1

Sheet 已打发票扣数（26年5月开始）
A1: 货号 | B1: MA数量 | C1: 单价 | D1: 金额USD | E1: 金额HKD | F1: 发票日期 | G1: 货号 | H1: 尾款付款数量 | I1: 单价 | J1: 尾款单价 | K1: 出货应收单价 | L1: 付款金额USD | M1: 付款金额HKD
A2: JW-RV-RPGE | B2: =160000-102664+150000 -> 207336 | C2: 4.5 | D2: =(B2*C2)*0.3 -> 279903.6 | E2: =D2*7.75 -> 2169252.9 | G2: T01685 | H2: 5004 | I2: 4.52 | J2: 4.52 | K2: =I2-J2 -> 0 | L2: =(H2*J2)-(H2*I2*0.3) -> 15832.66 | M2: =L2*7.75 -> 122703.12 | N2: 成品
A3: T01685 | B3: 45000 | C3: 4.52 | D3: =(B3*C3)*0.3 -> 61020 | E3: =D3*7.75 -> 472905 | G3: T01535 | H3: 15924 | I3: 2.1 | J3: 2.1 | K3: =I3-J3 -> 0 | L3: =(H3*J3)-(H3*I3*0.3) -> 23408.28 | M3: =L3*7.75 -> 181414.17 | N3: 成品
A4: T01535 | B4: =84999+40287 -> 125286 | C4: 2.1 | D4: =(B4*C4)*0.3 -> 78930.18 | E4: =D4*7.75 -> 611708.9 | G4: T01535 | H4: 15924 | I4: 2.1 | J4: 2.1 | K4: =I4-J4 -> 0 | L4: =(H4*J4)-(H4*I4*0.3) -> 23408.28 | M4: =L4*7.75 -> 181414.17 | N4: 成品
A5: T01535 | B5: =37000*3 -> 111000 | C5: 2.1 | D5: =(B5*C5)*0.3 -> 69930 | E5: =D5*7.75 -> 541957.5 | G5: T01535 | H5: 15924 | I5: 2.1 | J5: 2.1 | K5: =I5-J5 -> 0 | L5: =(H5*J5)-(H5*I5*0.3) -> 23408.28 | M5: =L5*7.75 -> 181414.17 | N5: 成品
A6: T01535 | B6: =16667*3 -> 50001 | C6: 2.1 | D6: =(B6*C6)*0.3 -> 31500.63 | E6: =D6*7.75 -> 244129.88 | G6: JW-RV-RPGE | H6: 9492 | I6: 4.5 | J6: 3.55 | K6: =I6-J6 -> 0.95 | L6: =(H6*J6)-(H6*I6*0.3) -> 20882.4 | M6: =L6*7.75 -> 161838.6 | N6: 半成品
A7: T01535 | B7: =44253 -> 44253 | C7: 2.1 | D7: =(B7*C7)*0.3 -> 27879.39 | E7: =D7*7.75 -> 216065.27 | G7: JW-RV-RPGE | H7: 35288 | I7: 4.5 | J7: 3.55 | K7: =I7-J7 -> 0.95 | L7: =(H7*J7)-(H7*I7*0.3) -> 77633.6 | M7: =L7*7.75 -> 601660.4 | N7: 半成品
A8: T01535 | B8: 66384 | C8: 2.1 | D8: =(B8*C8)*0.3 -> 41821.92 | E8: =D8*7.75 -> 324119.88 | F8: 45863 | G8: T01685 | H8: 11922 | I8: 4.52 | J8: 3.66 | K8: =I8-J8 -> 0.86 | L8: =(H8*J8)-(H8*I8*0.3) -> 27468.29 | M8: =L8*7.75 -> 212879.25 | N8: 半成品
A9: T02444 | B9: 60000 | C9: 2.1 | D9: =(B9*C9)*0.3 -> 37800 | E9: =D9*7.75 -> 292950 | F9: 45898 | L9: =(H9*J9)-(H9*I9*0.3) -> 0 | M9: =L9*7.75 -> 0
A10: T02943 | B10: 6500 | C10: 6.34 | D10: =(B10*C10)*0.3 -> 12363 | E10: =D10*7.75 -> 95813.25 | F10: 45973 | L10: =(H10*J10)-(H10*I10*0.3) -> 0 | M10: =L10*7.75 -> 0
A11: T02945 | B11: 6500 | C11: 6.64 | D11: =(B11*C11)*0.3 -> 12948 | E11: =D11*7.75 -> 100347 | F11: 45973 | L11: =(H11*J11)-(H11*I11*0.3) -> 0 | M11: =L11*7.75 -> 0
A12: T01453 | C12: 4.5 | D12: =(B12*C12)*0.3 -> 0 | E12: =D12*7.75 -> 0 | L12: =(H12*J12)-(H12*I12*0.3) -> 0 | M12: =L12*7.75 -> 0
A13: JW-RV-RPGEA | C13: 4.5 | D13: =(B13*C13)*0.3 -> 0 | E13: =D13*7.75 -> 0 | G13: 合计： | H13: =SUM(H2:H12) -> 109478 | L13: =SUM(L2:L12) -> 212041.79 | M13: =SUM(M2:M12) -> 1643323.9
A14: JW-RV-RPGE-3PK | C14: 4.5 | D14: =(B14*C14)*0.3 -> 0 | E14: =D14*7.75 -> 0 | H14: =H13-已收费半成品及成品!F9 -> 0 | L14: =L13-已收费半成品及成品!G9 -> 0
A15: T03204 | C15: 6.67 | D15: =(B15*C15)*0.3 -> 0 | E15: =D15*7.75 -> 0
A16: T03980 | B16: 9568 | C16: 5.6 | D16: =(B16*C16)*0.3 -> 16074.24 | E16: =D16*7.75 -> 124575.36 | F16: 46167
A17: T03804 | C17: 2.1 | D17: =(B17*C17)*0.3 -> 0 | E17: =D17*7.75 -> 0
A18: 合计： | B18: =SUM(B2:B17) -> 731828 | D18: =SUM(D2:D17) -> 670170.96 | E18: =SUM(E2:E17) -> 5193824.9
A22: 货号 | B22: 5月剩余MA数量 | C22: 5-12月出货数量 | D22: 剩余数量 | E22: 5月剩余MA金额HK | F22: 扣除金额USD | G22: 扣除金额HK | H22: 定金剩余金额HK | I22: 出货金额HK | J22: 排期扣除金额HK
A23: JW-RV-RPGE | B23: 44780 | C23: =SUMIF(已出货!$G$31:$G$68,A23,已出货!$I$31:$I$68) -> 3000 | D23: =B23-C23-C24-C25-C26 -> 39776 | E23: 468510.65 | F23: =(C23*4.5)*0.3 -> 4050 | G23: =F23*7.75 -> 31387.5 | H23: =E23-G23-G24-G25-G26 -> 416156.3 | I23: =SUMIF(已出货!$G$31:$G$68,A23,已出货!$AE$31:$AE$68) -> 104625 | J23: =SUMIF(已出货!$G$31:$G$68,A23,已出货!$AL$31:$AL$68)*7.75 -> 82537.5
A24: JW-RV-RPGEA | C24: =SUMIF(已出货!$G$31:$G$68,A24,已出货!$I$31:$I$68) -> 2004 | F24: =(C24*4.5)*0.3 -> 2705.4 | G24: =F24*7.75 -> 20966.85 | I24: =SUMIF(已出货!$G$31:$G$68,A24,已出货!$AE$31:$AE$68) -> 76101.9 | J24: =SUMIF(已出货!$G$31:$G$68,A24,已出货!$AL$31:$AL$68)*7.75 -> 38050.95
A25: JW-RV-RPGE-3PK | C25: =SUMIF(已出货!$G$31:$G$68,A25,已出货!$I$31:$I$68) -> 0 | F25: =(C25*4.5)*0.3 -> 0 | G25: =F25*7.75 -> 0 | I25: =SUMIF(已出货!$G$31:$G$68,A25,已出货!$AE$31:$AE$68) -> 0 | J25: =SUMIF(已出货!$G$31:$G$68,A25,已出货!$AL$31:$AL$68)*7.75 -> 0
A26: T01453 | C26: =SUMIF(已出货!$G$31:$G$68,A26,已出货!$I$31:$I$68) -> 0 | F26: =(C26*4.5)*0.3 -> 0 | G26: =F26*7.75 -> 0 | I26: =SUMIF(已出货!$G$31:$G$68,A26,已出货!$AE$31:$AE$68) -> 0 | J26: =SUMIF(已出货!$G$31:$G$68,A26,已出货!$AL$31:$AL$68)*7.75 -> 0
A27: T01535 | B27: 49452 | C27: =SUMIF(已出货!$G$31:$G$68,A27,已出货!$I$31:$I$68) -> 540 | D27: =B27-C27 -> 48912 | E27: 241449.39 | F27: =(C27*2.1)*0.3 -> 340.2 | G27: =F27*7.75 -> 2636.55 | H27: =E27-G27 -> 238812.84 | I27: =SUMIF(已出货!$G$31:$G$68,A27,已出货!$AE$31:$AE$68) -> 8788.5 | J27: =SUMIF(已出货!$G$31:$G$68,A27,已出货!$AL$31:$AL$68)*7.75 -> 2636.55
A28: T01685 | B28: 16926 | C28: =SUMIF(已出货!$G$31:$G$68,A28,已出货!$I$31:$I$68) -> 0 | D28: =B28-C28-C29-C30 -> 16926 | E28: 177875.35 | F28: =(C28*4.52)*0.3 -> 0 | G28: =F28*7.75 -> 0 | H28: =E28-G28-G29-G30 -> 177875.35 | I28: =SUMIF(已出货!$G$31:$G$68,A28,已出货!$AE$31:$AE$68) -> 0 | J28: =SUMIF(已出货!$G$31:$G$68,A28,已出货!$AL$31:$AL$68)*7.75 -> 0
A29: T01685-S | C29: =SUMIF(已出货!$G$31:$G$68,A29,已出货!$I$31:$I$68) -> 0 | F29: =(C29*4.52)*0.3 -> 0 | G29: =F29*7.75 -> 0 | I29: =SUMIF(已出货!$G$31:$G$68,A29,已出货!$AE$31:$AE$68) -> 0 | J29: =SUMIF(已出货!$G$31:$G$68,A29,已出货!$AL$31:$AL$68)*7.75 -> 0
A30: T01685A | C30: =SUMIF(已出货!$G$31:$G$68,A30,已出货!$I$31:$I$68) -> 0 | F30: =(C30*4.52)*0.3 -> 0 | G30: =F30*7.75 -> 0 | I30: =SUMIF(已出货!$G$31:$G$68,A30,已出货!$AE$31:$AE$68) -> 0 | J30: =SUMIF(已出货!$G$31:$G$68,A30,已出货!$AL$31:$AL$68)*7.75 -> 0
A31: T02444 | B31: 42180 | C31: =SUMIF(已出货!$G$31:$G$68,A31,已出货!$I$31:$I$68) -> 27024 | D31: =B31-C31-C32 -> 12192 | E31: 205943.85 | F31: =(C31*2.1)*0.3 -> 17025.12 | G31: =F31*7.75 -> 131944.68 | H31: =E31-G31-G32 -> 59527.44 | I31: =SUMIF(已出货!$G$31:$G$68,A31,已出货!$AE$31:$AE$68) -> 439815.6 | J31: =SUMIF(已出货!$G$31:$G$68,A31,已出货!$AL$31:$AL$68)*7.75 -> 131944.68
A32: T03804 | C32: =SUMIF(已出货!$G$31:$G$68,A32,已出货!$I$31:$I$68) -> 2964 | F32: =(C32*2.1)*0.3 -> 1867.32 | G32: =F32*7.75 -> 14471.73 | I32: =SUMIF(已出货!$G$31:$G$68,A32,已出货!$AE$31:$AE$68) -> 48239.1 | J32: =SUMIF(已出货!$G$31:$G$68,A32,已出货!$AL$31:$AL$68)*7.75 -> 14471.73
A33: T02943 | B33: 0 | C33: =SUMIF(已出货!$G$31:$G$68,A33,已出货!$I$31:$I$68) -> 0 | D33: =B33-C33 -> 0 | E33: 0 | F33: =(C33*6.34)*0.3 -> 0 | G33: =F33*7.75 -> 0 | H33: =E33-G33 -> 0 | I33: =SUMIF(已出货!$G$31:$G$68,A33,已出货!$AE$31:$AE$68) -> 0 | J33: =SUMIF(已出货!$G$31:$G$68,A33,已出货!$AL$31:$AL$68)*7.75 -> 0
A34: T02945 | B34: 0 | C34: =SUMIF(已出货!$G$31:$G$68,A34,已出货!$I$31:$I$68) -> 0 | D34: =B34-C34 -> 0 | E34: 0 | F34: =(C34*6.64)*0.3 -> 0 | G34: =F34*7.75 -> 0 | H34: =E34-G34 -> 0 | I34: =SUMIF(已出货!$G$31:$G$68,A34,已出货!$AE$31:$AE$68) -> 0 | J34: =SUMIF(已出货!$G$31:$G$68,A34,已出货!$AL$31:$AL$68)*7.75 -> 0
A35: T03204 | B35: 1792 | C35: =896+896 -> 1792 | D35: =B35-C35 -> 0 | E35: 27039.91 | F35: =SUMIF('[2]Toy Monster'!$E$49:$E$54,A35,'[2]Toy Monster'!$R$49:$R$54) -> #VALUE! | G35: =F35*7.75 -> #VALUE! | H35: =E35-G35 -> #VALUE! | I35: =SUMIF(已出货!$G$31:$G$68,A35,已出货!$AE$31:$AE$68) -> 279139.5 | J35: =SUMIF(已出货!$G$31:$G$68,A35,已出货!$AL$31:$AL$68)*7.75 -> 27039.91
A36: T03980 | B36: 9568 | C36: =SUMIF(已出货!$G$31:$G$68,A36,已出货!$I$31:$I$68) -> 9568 | D36: =B36-C36 -> 0 | E36: 124575.36 | F36: =(C36*5.6)*0.3 -> 16074.24 | G36: =F36*7.75 -> 124575.36 | H36: =E36-G36 -> 0 | I36: =SUMIF(已出货!$G$31:$G$68,A36,已出货!$AE$31:$AE$68) -> 415251.2 | J36: =SUMIF(已出货!$G$31:$G$68,A36,已出货!$AL$31:$AL$68)*7.75 -> 124575.36
I37: =SUMIF(已出货!$G$31:$G$68,A37,已出货!$AE$31:$AE$68) -> 0 | J37: =SUMIF(已出货!$G$31:$G$68,A37,已出货!$AL$31:$AL$68)*7.75 -> 0
B38: =SUM(B23:B37) -> 164698 | C38: =SUM(C23:C37) -> 46892 | D38: =SUM(D23:D37) -> 117806 | E38: =SUM(E23:E37) -> 1245394.5 | F38: =SUM(F23:F37) -> #VALUE! | G38: =SUM(G23:G37) -> #VALUE! | H38: =SUM(H23:H37) -> #VALUE! | I38: =SUM(I23:I37) -> 1371960.8 | J38: =SUM(J23:J37) -> 421256.68
B39: =B38-'[2]Toy Monster'!$I$94 -> 147772 | C39: =C38-'[2]Toy Monster'!$J$94 -> 46892 | D39: =D38-'[2]Toy Monster'!$K$94 -> 100880 | E39: =E38-'[2]Toy Monster'!$L$94 -> 1067519.2 | F39: =F38-'[2]Toy Monster'!$M$94 -> #VALUE! | G39: =G38-'[2]Toy Monster'!$N$94 -> #VALUE! | H39: =H38-'[2]Toy Monster'!$O$94 -> #VALUE! | I39: =I38-'[2]Toy Monster'!$P$94 -> 1371960.8 | J39: =J38-'[2]Toy Monster'!$Q$94 -> 421256.68
A42: 2026年1-4月
A43: 货号 | B43: 26年剩余MA数量 | C43: 26年剩余MA金额HK | D43: 26年出货数量 | E43: 剩余数量 | F43: 扣除金额HK | G43: 剩余金额HK | H43: 出货金额HK | I43: 排期扣除金额
A44: JW-RV-RPGE | B44: =58808 -> 58808 | C44: 615278.61 | D44: 10524 | E44: 44780 | F44: 110107.36 | G44: 468510.65 | H44: 367024.5 | I44: 14207.4
A45: JW-RV-RPGEA | D45: 504 | F45: 5273.1 | H45: 19139.4 | I45: 680.4
A46: JW-RV-RPGE-3PK | D46: 0 | F46: 0 | H46: 0 | I46: 0
A47: T01453 | D47: 3000 | F47: 31387.5 | H47: 104625 | I47: 4050
A48: T01535 | B48: 49452 | C48: 241449.39 | D48: 0 | E48: 49452 | F48: 0 | G48: 241449.39 | H48: 0 | I48: 0
A49: T01685 | B49: =17076+30 -> 17106 | C49: 179766.97 | D49: 180 | E49: 16926 | F49: 1891.62 | G49: 177875.35 | H49: 6179.85 | I49: 244.08
A50: T01685-S | D50: 0 | F50: 0 | H50: 0 | I50: 0
A51: T01685A | D51: 0 | F51: 0 | H51: 0 | I51: 0
A52: T02444 | B52: 60000 | C52: 292950 | D52: 17820 | E52: 42180 | F52: 87006.15 | G52: 205943.85 | H52: 290020.5 | I52: 11226.6
A53: T02943 | B53: 5604 | C53: 82605.78 | D53: 5604 | E53: 0 | F53: 82605.78 | G53: 0 | H53: 269272.2 | I53: 10658.81
A54: T02945 | B54: 5604 | C54: 86514.57 | D54: 5604 | E54: 0 | F54: 86514.57 | G54: 0 | H54: 282301.5 | I54: 11163.17
A55: T03204 | B55: 1792 | C55: 27039.91 | D55: 0 | E55: 1792 | F55: 0 | G55: 27039.91 | H55: 0 | I55: 0
H56: 0 | I56: 0
H57: 0 | I57: 0
B58: =SUM(B44:B57) -> 198366 | C58: =SUM(C44:C57) -> 1525605.2 | D58: =SUM(D44:D57) -> 43236 | E58: =SUM(E44:E57) -> 155130 | F58: =SUM(F44:F57) -> 404786.08 | G58: =SUM(G44:G57) -> 1120819.1 | H58: =SUM(H44:H57) -> 1338562.9 | I58: =SUM(I44:I57) -> 52230.46

Sheet 已打发票扣数（截止26年4月）
A1: 定金
A2: 货号 | B2: MA数量 | C2: 单价 | D2: 金额USD | E2: 金额HKD | F2: 发票日期
A3: JW-RV-RPGE | B3: 207336 | C3: 4.5 | D3: 279903.6 | E3: 2169252.9
A4: T01685 | B4: 45000 | C4: 4.52 | D4: 61020 | E4: 472905
A5: T01535 | B5: 125286 | C5: 2.1 | D5: 78930.18 | E5: 611708.9
A6: T01535 | B6: 111000 | C6: 2.1 | D6: 69930 | E6: 541957.5
A7: T01535 | B7: 50001 | C7: 2.1 | D7: 31500.63 | E7: 244129.88
A8: T01535 | B8: 44253 | C8: 2.1 | D8: 27879.39 | E8: 216065.27
A9: T01535 | B9: 66384 | C9: 2.1 | D9: 41821.92 | E9: 324119.88 | F9: 45863
A10: T02444 | B10: 60000 | C10: 2.1 | D10: 37800 | E10: 292950 | F10: 45898
A11: T02943 | B11: 6500 | C11: 6.34 | D11: 12363 | E11: 95813.25 | F11: 45973
A12: T02945 | B12: 6500 | C12: 6.64 | D12: 12948 | E12: 100347 | F12: 45973
A13: T01453 | C13: 4.5 | D13: 0 | E13: 0
A14: JW-RV-RPGEA | C14: 4.5 | D14: 0 | E14: 0
A15: JW-RV-RPGE-3PK | C15: 4.5 | D15: 0 | E15: 0
A16: T03204 | C16: 6.67 | D16: 0 | E16: 0
A17: T03980 | B17: 9568 | C17: 5.6 | D17: 12916.8 | E17: 100105.2 | F17: 46167
D18: 0 | E18: 0
D19: 0 | E19: 0
D20: 0 | E20: 0
D21: 0 | E21: 0
D22: 0 | E22: 0
A23: 合计： | B23: 731828 | D23: 667013.52 | E23: 5169354.8
A25: 货号 | B25: 尾款付款数量 | C25: 单价 | D25: 尾款单价 | E25: 出货应收单价 | F25: 付款金额USD | G25: 付款金额HKD | K25: 尾款货号 | L25: 出货数量 | M25: 剩余数量 | N25: 扣除金额HK | O25: 剩余金额USD | P25: 剩余金额HKD
A26: T01685 | B26: 5004 | C26: 4.52 | D26: 4.52 | E26: 0 | F26: 15832.66 | G26: 122703.12 | H26: 成品 | K26: T01685 | L26: 0 | M26: 5004 | N26: 0 | O26: 15832.66 | P26: 122703.12 | Q26: 成品
A27: T01535 | B27: 15924 | C27: 2.1 | D27: 2.1 | E27: 0 | F27: 23408.28 | G27: 181414.17 | H27: 成品 | K27: T01685-S | L27: 0 | N27: 0 | Q27: 成品
A28: T01535 | B28: 15924 | C28: 2.1 | D28: 2.1 | E28: 0 | F28: 23408.28 | G28: 181414.17 | H28: 成品 | K28: T01685A | L28: 0 | N28: 0 | Q28: 成品
A29: T01535 | B29: 15924 | C29: 2.1 | D29: 2.1 | E29: 0 | F29: 23408.28 | G29: 181414.17 | H29: 成品 | K29: T01535 | L29: 0 | M29: 47772 | N29: 0 | O29: 70224.84 | P29: 544242.51 | Q29: 成品
A30: JW-RV-RPGE | B30: 9492 | C30: 4.5 | D30: 3.55 | E30: 0.95 | F30: 20882.4 | G30: 161838.6 | H30: 半成品 | K30: JW-RV-RPGE | L30: 0 | M30: 44780 | N30: 0 | O30: 98516 | P30: 763499 | Q30: 半成品
A31: JW-RV-RPGE | B31: 35288 | C31: 4.5 | D31: 3.55 | E31: 0.95 | F31: 77633.6 | G31: 601660.4 | H31: 半成品 | K31: JW-RV-RPGEA | L31: 0 | N31: 0 | Q31: 半成品
A32: T01685 | B32: 11922 | C32: 4.52 | D32: 3.66 | E32: 0.86 | F32: 27468.29 | G32: 212879.25 | H32: 半成品 | K32: JW-RV-RPGE-3PK | L32: 0 | N32: 0 | Q32: 半成品
F33: 0 | G33: 0 | K33: T01685 | L33: 0 | M33: 11922 | N33: 0 | O33: 27468.29 | P33: 212879.25 | Q33: 半成品
F34: 0 | G34: 0 | L34: 0 | M34: 109478 | N34: 0 | O34: 212041.79 | P34: 1643323.9
F35: 0 | G35: 0
F36: 0 | G36: 0
A37: 合计： | B37: 109478 | F37: 212041.79 | G37: 1643323.9
B38: 0 | F38: 0
A41: 货号 | B41: 26年剩余MA数量 | C41: 26年剩余MA金额HK | D41: 26年出货数量 | E41: 剩余数量 | F41: 扣除金额HK | G41: 剩余金额HK | H41: 出货金额HK | I41: 排期扣除金额HK
A42: JW-RV-RPGE | B42: 58808 | C42: 615278.61 | D42: 10524 | E42: 44780 | F42: 110107.36 | G42: 468510.65 | H42: 367024.5 | I42: 14207.4
A43: JW-RV-RPGEA | D43: 504 | F43: 5273.1 | H43: 19139.4 | I43: 680.4
A44: JW-RV-RPGE-3PK | D44: 0 | F44: 0 | H44: 0 | I44: 0
A45: T01453 | D45: 3000 | F45: 31387.5 | H45: 104625 | I45: 4050
A46: T01535 | B46: 49248 | C46: 241449.39 | D46: 0 | E46: 49248 | F46: 0 | G46: 241449.39 | H46: 0 | I46: 0
A47: T01685 | B47: 17076 | C47: 179766.97 | D47: 180 | E47: 16896 | F47: 1891.62 | G47: 177875.35 | H47: 6179.85 | I47: 244.08
A48: T01685-S | D48: 0 | F48: 0 | H48: 0 | I48: 0
A49: T01685A | D49: 0 | F49: 0 | H49: 0 | I49: 0
A50: T02444 | B50: 60000 | C50: 292950 | D50: 17820 | E50: 42180 | F50: 87006.15 | G50: 205943.85 | H50: 290020.5 | I50: 11226.6
A51: T02943 | B51: 5604 | C51: 82605.78 | D51: 5604 | E51: 0 | F51: 82605.78 | G51: 0 | H51: 269272.2 | I51: 10658.81
A52: T02945 | B52: 5604 | C52: 86514.57 | D52: 5604 | E52: 0 | F52: 86514.57 | G52: 0 | H52: 282301.5 | I52: 11163.17
A53: T03204 | B53: 1792 | C53: 27039.9 | D53: 1792 | E53: 0 | F53: 0 | G53: 27039.9 | H53: 27039.91 | I53: 3489.02
A54: T03980 | B54: 9568 | C54: 100105.2 | D54: 0 | E54: 9568 | F54: 0 | H54: 0 | I54: 0
H55: 0 | I55: 0
B56: 207700 | C56: 1625710.4 | D56: 45028 | E56: 162672 | F56: 404786.08 | G56: 1120819.1 | H56: 1365602.9 | I56: 55719.48
D57: TRUE | F57: TRUE | G57: TRUE | H57: TRUE | I57: TRUE
A60: 2026年1-4月
A61: 货号 | B61: 26年剩余MA数量 | C61: 26年剩余MA金额HK | D61: 26年出货数量 | E61: 剩余数量 | F61: 扣除金额HK | G61: 剩余金额HK | H61: 出货金额HK | I61: 排期扣除金额HK
A62: JW-RV-RPGE | B62: 58808 | C62: 615278.61 | D62: 10524 | E62: 44780 | F62: 110107.36 | G62: 468510.65 | H62: 367024.5 | I62: 14207.4
A63: JW-RV-RPGEA | D63: 504 | F63: 5273.1 | H63: 19139.4 | I63: 680.4
A64: JW-RV-RPGE-3PK | D64: 0 | F64: 0 | H64: 0 | I64: 0
A65: T01453 | D65: 3000 | F65: 31387.5 | H65: 104625 | I65: 4050
A66: T01535 | B66: 49248 | C66: 241449.39 | D66: 0 | E66: 49248 | F66: 0 | G66: 241449.39 | H66: 0 | I66: 0
A67: T01685 | B67: 17076 | C67: 179766.97 | D67: 180 | E67: 16896 | F67: 1891.62 | G67: 177875.35 | H67: 6179.85 | I67: 244.08
A68: T01685-S | D68: 0 | F68: 0 | H68: 0 | I68: 0
A69: T01685A | D69: 0 | F69: 0 | H69: 0 | I69: 0
A70: T02444 | B70: 60000 | C70: 292950 | D70: 17820 | E70: 42180 | F70: 87006.15 | G70: 205943.85 | H70: 290020.5 | I70: 11226.6
A71: T02943 | B71: 5604 | C71: 82605.78 | D71: 5604 | E71: 0 | F71: 82605.78 | G71: 0 | H71: 269272.2 | I71: 10658.81
A72: T02945 | B72: 5604 | C72: 86514.57 | D72: 5604 | E72: 0 | F72: 86514.57 | G72: 0 | H72: 282301.5 | I72: 11163.17
A73: T03204 | B73: 1792 | C73: 27039.9 | D73: 0 | E73: 1792 | F73: 0 | G73: 27039.9 | H73: 0 | I73: 0
H74: 0 | I74: 0
H75: 0 | I75: 0
B76: =SUM(B62:B75) -> 198132 | C76: =SUM(C62:C75) -> 1525605.2 | D76: =SUM(D62:D75) -> 43236 | E76: =SUM(E62:E75) -> 154896 | F76: =SUM(F62:F75) -> 404786.08 | G76: =SUM(G62:G75) -> 1120819.1 | H76: =SUM(H62:H75) -> 1338562.9 | I76: =SUM(I62:I75) -> 52230.46

Sheet Sheet3
D1: T01535 | E1: 恐龙公园 （天空） | F1: =SUM(总接单!#REF!)/3 -> #REF! | H1: =SUM(总接单!#REF!)/3 -> #REF! | I1: =F1-H1 -> #REF! | J1: 2.06 | K1: =J1*F1 -> #REF! | L1: =K1*7.75 -> #REF! | M1: =I1*J1 -> #REF! | N1: =M1*7.75 -> #REF!
D2: T01535 | E2: 恐龙公园 （陆地） | F2: =SUM(总接单!#REF!)/3 -> #REF! | H2: =SUM(总接单!#REF!)/3 -> #REF! | I2: =F2-H2 -> #REF! | J2: 2.06 | K2: =J2*F2 -> #REF! | L2: =K2*7.75 -> #REF! | M2: =I2*J2 -> #REF! | N2: =M2*7.75 -> #REF!
D3: T01535 | E3: 恐龙公园 （海洋） | F3: =SUM(总接单!#REF!)/3 -> #REF! | H3: =SUM(总接单!#REF!)/3 -> #REF! | I3: =F3-H3 -> #REF! | J3: 2.06 | K3: =J3*F3 -> #REF! | L3: =K3*7.75 -> #REF! | M3: =I3*J3 -> #REF! | N3: =M3*7.75 -> #REF!
D4: T01535 | E4: 恐龙公园 （天空） | F4: =SUM(总接单!#REF!)/3 -> #REF! | H4: =SUM(总接单!#REF!)/3 -> #REF! | I4: =F4-H4 -> #REF! | J4: 2.1 | K4: =J4*F4 -> #REF! | L4: =K4*7.75 -> #REF! | M4: =I4*J4 -> #REF! | N4: =M4*7.75 -> #REF!
D5: T01535 | E5: 恐龙公园 （陆地） | F5: =SUM(总接单!#REF!)/3 -> #REF! | H5: =SUM(总接单!#REF!)/3 -> #REF! | I5: =F5-H5 -> #REF! | J5: 2.1 | K5: =J5*F5 -> #REF! | L5: =K5*7.75 -> #REF! | M5: =I5*J5 -> #REF! | N5: =M5*7.75 -> #REF!
D6: T01535 | E6: 恐龙公园 （海洋） | F6: =SUM(总接单!#REF!)/3 -> #REF! | H6: =SUM(总接单!#REF!)/3 -> #REF! | I6: =F6-H6 -> #REF! | J6: 2.1 | K6: =J6*F6 -> #REF! | L6: =K6*7.75 -> #REF! | M6: =I6*J6 -> #REF! | N6: =M6*7.75 -> #REF!
D7: T01535 | E7: 恐龙公园 （天空） | F7: 0 | H7: =SUM(总接单!#REF!)/3 -> #REF! | I7: =F7-H7 -> #REF! | J7: 2.1 | K7: =J7*F7 -> 0 | L7: =K7*7.75 -> 0 | M7: =I7*J7 -> #REF! | N7: =M7*7.75 -> #REF!
D8: T01535 | E8: 恐龙公园 （陆地） | F8: 0 | H8: =SUM(总接单!#REF!)/3 -> #REF! | I8: =F8-H8 -> #REF! | J8: 2.1 | K8: =J8*F8 -> 0 | L8: =K8*7.75 -> 0 | M8: =I8*J8 -> #REF! | N8: =M8*7.75 -> #REF!
D9: T01535 | E9: 恐龙公园 （海洋） | F9: 0 | H9: =SUM(总接单!#REF!)/3 -> #REF! | I9: =F9-H9 -> #REF! | J9: 2.1 | K9: =J9*F9 -> 0 | L9: =K9*7.75 -> 0 | M9: =I9*J9 -> #REF! | N9: =M9*7.75 -> #REF!
A14: Smyths PO# | B14: INSPECTION DATE | C14: Cargo Ready Date | D14: Country | E14: Supplier | F14: Keycode | G14: ITEM NUMBER | H14: PRODUCT DESCRIPTION | I14: QTY(PCS) | J14: CTN
A15: 4400485440 | B15: 45846 | C15: 45859 | D15: UK | E15: R&R | F15: 221243 | G15: JW-RV-RPGE | H15: Jurassic World Ravenous Raptors | I15: 4224 | J15: 704
A16: 4400485441 | B16: 45846 | C16: 45859 | D16: UK | E16: R&R | F16: 221243 | G16: JW-RV-RPGE | H16: Jurassic World Ravenous Raptors | I16: 4224 | J16: 704
A17: 4400485432 | B17: 45839 | C17: 45844 | D17: IRELAND | E17: R&R | F17: 221243 | G17: JW-RV-RPGE | H17: Jurassic World Ravenous Raptors | I17: 2316 | J17: 704
A18: 4400485433 | B18: 45858 | C18: 45869 | D18: UK | E18: R&R | F18: 221243 | G18: JW-RV-RPGE | H18: Jurassic World Ravenous Raptors | I18: 7200 | J18: 1200
A19: 4400486309 | B19: 45833 | C19: 45838 | D19: GERMANY | E19: R&R | F19: 221243 | G19: JW-RV-RPGE | H19: Jurassic World Ravenous Raptors | I19: 2520 | J19: 420
A20: 4400486310 | B20: 45852 | C20: 45866 | D20: GERMANY | E20: R&R | F20: 221243 | G20: JW-RV-RPGE | H20: Jurassic World Ravenous Raptors | I20: 5832 | J20: 972
