Workbook

Sheet 77772
A1: 香港接单日期 | B1: 第三方客户名称 | C1: 走货国家 | D1: ZURU PO NO# | E1: 第三方客户 PO NO# | F1: SKU | G1: ITEM# | H1: 货品名称 | I1: PO数量(只) | J1: 内箱装箱数量(只) | K1: 外箱装箱数量(只) | L1: 总箱数 | M1: 计划出货期 | N1: 计划验货期 | O1: 湖南完成时间 | P1: 第三方客户公证行验货 | Q1: 验货结果 | R1: S/O(截仓期) | S1: 生产情况 | T1: 已回数量 | U1: 欠数 | V1: 贴纸 | W1: 箱唛 (收到日期) | X1: 外箱贴纸 | Y1: 贴纸资料 (收到日期及订购日期) | Z1: 其他物料 | AA1: 额外说明书/保证书 | AB1: 样办 | AC1: 备注 | AD1: ZURU跟单组员 | AE1: 单价USD | AF1: 金额USD | AG1: 发票号 | AH1: 系统货号 | AI1: 是否入系统 | AJ1: 下单情况 | AK1: 77772 MA版本球数 | AL1: 77772 COSTCO球数 | AM1: 77772 Target球数 | AN1: 收缩膜 1L A版本 | AO1: "收缩膜 1L B版本" | AP1: 收缩膜 3L A版本 | AQ1: 客版3L无条码收缩膜（美国） | AR1: 客版3L无条码收缩膜（英法西） | AS1: WM CA客版收缩膜 | AT1: TARGET客版收缩膜 | AU1: 收藏指南 5L A版本 | AV1: 唱片架组装说明书 | AW1: 客版收藏指南（移除21唱片） | AX1: 客版收藏指南（移除21/23唱片） | AY1: 客版收藏指南（移除17款唱片） | AZ1: 中文收藏指南 | BA1: 中文黑白唱片架组装说明书 | BB1: COSTCO客版收缩膜 | BC1: COSTCO客版收藏指南 | BD1: COSTCO客版说明书 | BE1: COSTCO客版彩盒 | BF1: COSTCO客版托盘 | BG1: Smyths客版收缩膜 | BH1: Smyths客版收藏指南 | BI1: TARGET客版收缩膜 | BJ1: TARGET客版收藏指南 | BK1: MA GQ1 1L 13pcs | BL1: MA GQ1 3L 13pcs | BM1: MA GQ8 1L 48pcs | BN1: MA GQ2 1L 24/25pcs | BO1: MA GQ2 3L 24/25pcs | BP1: 客版GQ1 1L | BQ1: 客版GQ2 1L | BR1: 客版GQ3 1L | BS1: 客版GQ3 3L | BT1: 客版GQ4 | BU1: 客版GQ5 | BV1: EMC457 | BW1: MEC473 | BX1: MEC426 | BY1: MEC426 TARGET专属 | BZ1: MSLD188 | CA1: MSLD182 | CB1: SK-S002 | CC1: SK1-S002 | CD1: GQ2/GQ3 Demo | CE1: Target-US Demo | CF1: 77772展示架DOEM SK | CG1: ENDCAP Demo(set)-STD | CH1: 77944彩盒 | CI1: 77944托盘UQ1 | CJ1: 77876圆筒 | CK1: 77876彩纸 | CL1: 77876贴纸
A2: 46037 | D2: ZMPO260055 | F2: ZMPO260055-10 | G2: 77772-S001 | H2: 唱片球24 pcs/箱 | I2: 80套散件 | J2: 0 | K2: 24 | L2: =80/24 -> 3.3333333 | M2: 46052 | N2: 46048 | W2: 周转箱 | X2: 无 | Y2: 无 | AC2: Remark：大货版本/只需要齐全套散件/麻烦用胶袋分装好一套为一袋 备注： 收到样品订单后尽快安排 ，注意样板品质质量要求要高于大货品质要求 ，送货时必须要附带送货单(没有送货单和QC检验合格报告的仓库一律拒绝收货)，请知悉，谢谢！ | AD2: sally Li | AH2: N/A | AI2: # | CD2: =BN2+BO2+BQ2+BS2+BR2 -> 0 | CE2: =BU2 -> 0 | CF2: =CC2 -> 0 | CG2: =BV2+BW2+BX2 -> 0
A3: 46029 | B3: ZURU NEW ZEALAND LIMITED | C3: 新西兰 | D3: 4500190798 | E3: 5200008655 | F3: 4500190798-10 | G3: 77772GQ2-S002-FS | H3: 唱片球25 pcs/PDQ/箱 | I3: 100 | J3: 0 | K3: 25 | L3: =I3/K3 -> 4 | M3: 46059 | N3: 46055 | P3: 试销单 | Q3: PASS | W3: 46029 | X3: 有 | Y3: 每箱需要增加一张黄色A4贴纸，印“fast start"。 | AC3: 日期码格式：ZURU INC(BVI) 标准格式 日期：按实际生产日期 Packaging Info: Remark: NZ Fast start order, 从PP PO中扣除，每款需要更换UPC贴纸，除常规箱唛外，每箱需要增加一张黄色A4贴纸，印“fast start"。 | AD3: SD92 | AE3: 1.27 | AF3: =I3*AE3 -> 127 | AH3: 77772GQ2-S002-3L | AI3: 已入 | AJ3: 系统入单 | AK3: =I3 -> 100 | AP3: =I3 -> 100 | BO3: =I3/25 -> 4 | CD3: =BN3+BO3+BQ3+BS3+BR3 -> 4 | CE3: =BU3 -> 0 | CF3: =CC3 -> 0 | CG3: =BV3+BW3+BX3 -> 0
A4: 46014 | B4: TARGET US | C4: 美国 | D4: 4500189603 | E4: 10001643491-3 890 | F4: 4500189603-10 | G4: 77772GQ5-S001 | H4: 唱片球25 pcs/PDQ/箱 | I4: 48750 | J4: 0 | K4: 25 | L4: =I4/K4 -> 1950 | M4: 46085 | N4: =M4-4 -> 46081 | Q4: PASS | R4: 3/16 提货 | T4: =9500+18000+21250 -> 48750 | U4: =T4-I4 -> 0 | V4: OK | W4: 46027 | X4: 有 | Y4: 1/22寄出 | AC4: 日期码格式：ZURU INC(BVI) 标准格式 日期：按实际生产日期 Packaging Info: 7772GQ5：产品包装MA 1L 收缩膜+MA 5L 收藏指南，客版PDQ Remark: 7772GQ5： 1.77772GQ5-S001-MINI BRANDS-VINYL-SERIES 1-CAPSULE,WITH DEMO,25PCS/GRAVITY PDQ,25PCS/PDQ/CTN； 2.产品包装MA 1L 收缩膜+MA 5L 收藏指南，客版PDQ； 3.产品UPC显示193052090065，Sweet Caroline Neil Diamond是TARGET独家款唱片； 4. 外箱正唛左上角位置粘贴条码箱贴纸，每箱只贴一张，由ZURU订购。来料贴纸上显示的客户DPCI# 086-02-8931, UPC显示10193052090062; 5. 外箱正唛箱唛内容右侧需贴一张EVENT LABEL，内容显示：TOYS SET DATE: 5/31/2026，由工厂自行订购； 6. 产品和包装上印刷 tracking code信息，格式为ZURU常规格式; 7. 出货方式：货代自提 | AD4: Holly Zheng | AE4: 1.29 | AF4: =I4*AE4 -> 62887.5 | AG4: ZB04936-8.17 | AH4: 77772GQ5-S001 | AI4: 已入 | AJ4: 系统入单 | AM4: =I4 -> 48750 | AN4: =I4 -> 48750 | AU4: =I4 -> 48750 | AV4: =I4*0.06 -> 2925 | BU4: =I4/25 -> 1950 | CD4: =BN4+BO4+BQ4+BS4+BR4 -> 0 | CE4: =BU4 -> 1950 | CF4: =CC4 -> 0 | CG4: =BV4+BW4+BX4 -> 0
A5: 46058 | D5: ZMPO260157 | F5: ZMPO260157-10 | G5: 77772-S001 | H5: 唱片球24 pcs/箱 | I5: 10套散件 | J5: 0 | K5: 24 | L5: 1 | M5: 46090 | N5: 46086 | Q5: PASS | U5: =T5-I5 -> #VALUE! | W5: 周转箱 | X5: 无 | Y5: 无 | AC5: Remark：大货最新版本/只需要齐套散件/麻烦用胶袋分装好一套为一袋/箱唛参照邮件附件 备注： 收到订单后请尽快安排，谢谢 | AD5: sally Li | AH5: N/A | AI5: # | CD5: =BN5+BO5+BQ5+BS5+BR5 -> 0 | CE5: =BU5 -> 0 | CF5: =CC5 -> 0 | CG5: =BV5+BW5+BX5 -> 0
A6: 46013 | B6: TARGET US | C6: 美国 | D6: 4500189608 | E6: 10001643496-3 890 | F6: 4500189608-10 | G6: 77772GQ5-S001 | H6: 唱片球25 pcs/PDQ/箱 | I6: 161250 | J6: 0 | K6: 25 | L6: =I6/K6 -> 6450 | M6: 46091 | N6: 46087 | Q6: PASS | R6: 3/23 提货 | T6: 161250 | U6: =T6-I6 -> 0 | V6: OK | W6: 46027 | X6: 有 | Y6: 1/22寄出 | AC6: 日期码格式：ZURU INC(BVI) 标准格式 日期：按实际生产日期 Packaging Info: 7772GQ5：产品包装MA 1L 收缩膜+MA 5L 收藏指南，客版PDQ Remark: 7772GQ5： 1.77772GQ5-S001-MINI BRANDS-VINYL-SERIES 1-CAPSULE,WITH DEMO,25PCS/GRAVITY PDQ,25PCS/PDQ/CTN； 2.产品包装MA 1L 收缩膜+MA 5L 收藏指南，客版PDQ； 3.产品UPC显示193052090065，Sweet Caroline Neil Diamond是TARGET独家款唱片； 4. 外箱正唛左上角位置粘贴条码箱贴纸，每箱只贴一张，由ZURU订购。来料贴纸上显示的客户DPCI# 086-02-8931, UPC显示10193052090062; 5. 产品和包装上印刷 tracking code信息，格式为ZURU常规格式; 6. 出货方式：货代自提 | AD6: Holly Zheng | AE6: 1.29 | AF6: =I6*AE6 -> 208012.5 | AG6: ZB04934-8.17 | AH6: 77772GQ5-S001 | AI6: 已入 | AJ6: 系统入单 | AM6: =I6 -> 161250 | AN6: =I6 -> 161250 | AU6: =I6 -> 161250 | AV6: =I6*0.06 -> 9675 | BU6: =I6/25 -> 6450 | CD6: =BN6+BO6+BQ6+BS6+BR6 -> 0 | CE6: =BU6 -> 6450 | CF6: =CC6 -> 0 | CG6: =BV6+BW6+BX6 -> 0
A7: 46043 | B7: SMYTHS TOYS HQ UC UK | C7: 英国 | D7: 4500191960 | E7: 4400528768 | F7: 4500191960-30 | G7: 77772GQ2-S001-PRODCC | H7: 唱片球50 pcs/2PDQ/箱 | I7: 10000 | J7: 0 | K7: 50 | L7: =I7/K7 -> 200 | M7: 46097 | N7: 46093 | Q7: PASS | R7: 3/23 出货 | T7: 10000 | U7: =T7-I7 -> 0 | V7: 无 | W7: 46044 | X7: 无 | Y7: 无 | Z7: 移除#21唱片 | AC7: 日期码格式：ZURU INC(BVI) 标准格式 日期：按实际生产日期 Packaging Info: 77772GQ2客版5L(英法德意荷)配套包装=MA PDQ (优先多语)+客版3L-5Lwarning收缩膜(翻PO#4500191961)+客版5L收藏指南(翻PO#4500191961)+MA 23L组装说明+MA 复合袋 EAN#4894680051133 77772GQ2必须移除Messy Lola Young (VINYL-S1-021) 这个唱片 ,比例按Una 更新的安排，如未按要求做货被客罚由工厂承担责任。 -------------------------------------------------------------------- Remark: Smyths 英国/爱尔兰 1. 请准时出货，推期会有罚款； 2. 所有产品按符合欧洲标准走货，需要是不含微塑料版本。 3.包装日期码按ZURU格式即可，请确保不迟于外箱日期码，可等于或者早于外箱日期码，必须为法定工作日，印刷前请先检查外箱日期码。 4.请注意检查产品及包装应带UKCA图标（14+产品除外），包装显示ZURU UK LTD/ZURU France地址信息，QC部门请查核，如有问题与跟单确认 5.电子产品需增加一张WEEE声明30L通用黑白说明书(不接受A版本，翻译有误)，区分带电池和不带电池出货版本, 如已做客版说明书可忽略此要求； 6.订单备注显示有分批的（不同仓库/订单号） ，注意分开做货出货，否则会导致罚款 。 7.做货前请先复核包装条码与订单是否一致再安排，对不上的需与ZURU跟单确认再安排。 | AD7: Sherry Lu | AE7: 1.007 | AF7: =I7*AE7 -> 10070 | AH7: 77772GQ2-S001-PRODCC | AI7: 已入 | AJ7: 系统入单 | AK7: =I7 -> 10000 | AV7: =I7*0.06 -> 600 | BG7: =I7 -> 10000 | BH7: =I7 -> 10000 | BO7: =I7/25 -> 400 | CD7: =BN7+BO7+BQ7+BS7+BR7 -> 400 | CE7: =BU7 -> 0 | CF7: =CC7 -> 0 | CG7: =BV7+BW7+BX7 -> 0
A8: 46084 | B8: ZURU NEW ZEALAND LIMITED | C8: 新西兰 | D8: 4500194964 | E8: 5200009119 | F8: 4500194964-10 | G8: 77772GQ2-S002-FS | H8: 唱片球25 pcs/PDQ/箱 | I8: 100 | J8: 0 | K8: 25 | L8: =I8/K8 -> 4 | M8: 46097 | N8: 46093 | Q8: PASS | R8: 3/19 出货 | T8: 100 | U8: =T8-I8 -> 0 | W8: 46029 | X8: 有 | Y8: 每箱需要增加一张黄色A4贴纸，印“fast start"。 | AC8: 日期码格式：ZURU INC(BVI) 标准格式 日期：按实际生产日期 Packaging Info: Remark: NZ Fast start order, 每款需要更换UPC贴纸，除常规箱唛外，每箱需要增加一张黄色A4贴纸，印"fast start"。 | AD8: SD92 | AE8: 1.27 | AF8: =I8*AE8 -> 127 | AH8: 77772GQ2-S002 | AI8: 已入 | AJ8: 系统入单 | AK8: =I8 -> 100 | AN8: =I8 -> 100 | AU8: =I8 -> 100 | AV8: =I8*0.06*2 -> 12 | BN8: =I8/25 -> 4 | CD8: =BN8+BO8+BQ8+BS8+BR8 -> 4 | CE8: =BU8 -> 0 | CF8: =CC8 -> 0 | CG8: =BV8+BW8+BX8 -> 0
A9: 46044 | B9: SMYTHS TOYS EU HQ UNLIMITED COMPANY | C9: 法国 | D9: 4500191989 | E9: 4400528766 | F9: 4500191989-10 | G9: MEC457-77772-S001 | H9: 唱片机+唱片球混装展示架 | I9: 3528 | J9: 0 | K9: 84 | L9: =I9/K9 -> 42 | M9: 46097 | N9: 46093 | Q9: PASS | R9: 4/6 出货 | T9: 3528 | U9: =T9-I9 -> 0 | W9: 46044 | X9: 有 | Y9: UN3481锂电池运输标签 | Z9: 移除#21唱片 | AC9: 日期码格式：ZURU INC(BVI) 标准格式 日期：按实际生产日期 Packaging Info: MEC457: 客版5L(英法德意荷)展示架[84pcs#77772+48pcs#77794; 所有客版资料翻PO#4500191961] 77772: 客版3L-5Lwarning收缩膜+客版5L收藏指南+MA 23L组装说明+MA复合袋 EAN#4894680051133 77794: 客版3L-5Lwarning纸盒底座+客版3L镭射贴纸+客版3L单铜纸贴纸+MA23L游戏说明书+MA23L warning说明书+1张WEEE声明(带电池)走货欧洲通用29L-C版说明 书 EAN#4894680051430 做货前请先核对条码无误 RECHARGEABLE LITHIUM BATTERY(INCLUDED) *#77772必须移除Messy Lola Young (VINYL-S1-021) 这个唱片, 比例按PM更新的安排* *展架上的Demo Box的唱片需要用"A Little Too Much"(VINYL-S1-025)替代原来的"Messy"(VINYL-S1-021)* *外箱需加一张UN3481锂电池运输标签* Remark: Smyths 法国 1. 请准时出货，推期会有罚款； 2. 所有产品按符合欧洲标准走货，需要是不含微塑料版本。 3. 电子产品需增加一张WEEE声明30L通用黑白说明书(不接受A版本，翻译有误)，区分带电池和不带电池出货版本, 如已做客版说明书可忽略此要求； 4. 出口法国的产品, 法规规定禁止在包装和共公众用的印刷品中使用矿物油中含有的物质, 包装印刷油墨中含有的MOAH/MOSH的质量浓度不能超过1%, 否则出货到 法国被抽检出现问题, 供应商需要对此负责; 5.订单备注显示有分批的（不同仓库/订单号） ，注意分开做货出货，否则会导致罚款 。 6.包装日期码按ZURU格式即可，请确保不迟于外箱日期码，可等于或者早于外箱日期码，必须为法定工作日。 7.做货前请先复核包装条码与订单是否一致再安排，对不上的需与ZURU跟单确认再安排。 | AD9: Sherry Lu | AE9: 306.676 | AF9: =L9*AE9 -> 12880.392 | AH9: MEC457-S001-77772 | AI9: 已入 | AJ9: 系统入单 | AK9: =I9 -> 3528 | AV9: =I9*0.06 -> 211.68 | BG9: =I9 -> 3528 | BH9: =I9 -> 3528 | BV9: =I9/K9 -> 42 | CD9: =BN9+BO9+BQ9+BS9+BR9 -> 0 | CE9: =BU9 -> 0 | CF9: =CC9 -> 0 | CG9: =BV9+BW9+BX9 -> 42
A10: 46044 | B10: SMYTHS TOYS EU HQ UNLIMITED COMPANY | C10: 法国 | D10: 4500191989 | E10: 4400528767 | F10: 4500191989-20 | G10: MEC457-77772-S001 | H10: 唱片机+唱片球混装展示架 | I10: 1512 | J10: 0 | K10: 84 | L10: =I10/K10 -> 18 | M10: 46097 | N10: 46093 | Q10: PASS | R10: 4/6 出货 | T10: 1512 | U10: =T10-I10 -> 0 | V10: 无 | W10: 46044 | X10: 无 | Y10: 无 | Z10: 移除#21唱片 | AC10: 日期码格式：ZURU INC(BVI) 标准格式 日期：按实际生产日期 Packaging Info: MEC457: 客版5L(英法德意荷)展示架[84pcs#77772+48pcs#77794; 所有客版资料翻PO#4500191961] 77772: 客版3L-5Lwarning收缩膜+客版5L收藏指南+MA 23L组装说明+MA复合袋 EAN#4894680051133 77794: 客版3L-5Lwarning纸盒底座+客版3L镭射贴纸+客版3L单铜纸贴纸+MA23L游戏说明书+MA23L warning说明书+1张WEEE声明(带电池)走货欧洲通用29L-C版说明 书 EAN#4894680051430 做货前请先核对条码无误 RECHARGEABLE LITHIUM BATTERY(INCLUDED) *#77772必须移除Messy Lola Young (VINYL-S1-021) 这个唱片, 比例按PM更新的安排* *展架上的Demo Box的唱片需要用"A Little Too Much"(VINYL-S1-025)替代原来的"Messy"(VINYL-S1-021)* *外箱需加一张UN3481锂电池运输标签* Remark: Smyths 法国 1. 请准时出货，推期会有罚款； 2. 所有产品按符合欧洲标准走货，需要是不含微塑料版本。 3. 电子产品需增加一张WEEE声明30L通用黑白说明书(不接受A版本，翻译有误)，区分带电池和不带电池出货版本, 如已做客版说明书可忽略此要求； 4. 出口法国的产品, 法规规定禁止在包装和共公众用的印刷品中使用矿物油中含有的物质, 包装印刷油墨中含有的MOAH/MOSH的质量浓度不能超过1%, 否则出货到 法国被抽检出现问题, 供应商需要对此负责; 5.订单备注显示有分批的（不同仓库/订单号） ，注意分开做货出货，否则会导致罚款 。 6.包装日期码按ZURU格式即可，请确保不迟于外箱日期码，可等于或者早于外箱日期码，必须为法定工作日。 7.做货前请先复核包装条码与订单是否一致再安排，对不上的需与ZURU跟单确认再安排。 | AD10: Sherry Lu | AE10: 306.676 | AF10: =L10*AE10 -> 5520.168 | AH10: MEC457-S001-77772 | AI10: 已入 | AJ10: 系统入单 | AK10: =I10 -> 1512 | AV10: =I10*0.06 -> 90.72 | BG10: =I10 -> 1512 | BH10: =I10 -> 1512 | BV10: =I10/K10 -> 18 | CD10: =BN10+BO10+BQ10+BS10+BR10 -> 0 | CE10: =BU10 -> 0 | CF10: =CC10 -> 0 | CG10: =BV10+BW10+BX10 -> 18
A11: 46044 | B11: SMYTHS TOYS EU HQ UNLIMITED COMPANY | C11: 法国 | D11: 4500191990 | E11: 4400528766 | F11: 4500191990-50 | G11: 77772GQ2-S001-PRODCC | H11: 唱片球50 pcs/2PDQ/箱 | I11: 1400 | J11: 0 | K11: 50 | L11: =I11/K11 -> 28 | M11: 46098 | N11: 46094 | Q11: PASS | R11: 4/7 出货 | T11: 1400 | U11: =T11-I11 -> 0 | V11: 无 | W11: 46044 | X11: 无 | Y11: 无 | Z11: 移除#21唱片 | AC11: 日期码格式：ZURU INC(BVI) 标准格式 日期：按实际生产日期 Packaging Info: 77772GQ2客版5L(英法德意荷)配套包装=MA PDQ (优先多语)+客版3L-5Lwarning收缩膜(翻PO#4500191961)+客版5L收藏指南(翻PO#4500191961)+MA 23L组装说明+MA 复合袋 EAN#4894680051133 77772GQ2必须移除Messy Lola Young (VINYL-S1-021) 这个唱片 ,比例按Una 更新的安排，如未按要求做货被客罚由工厂承担责任。 -------------------------------------------------------------------- Remark: Smyths 法国 1. 请准时出货，推期会有罚款； 2. 所有产品按符合欧洲标准走货，需要是不含微塑料版本。 3. 电子产品需增加一张WEEE声明30L通用黑白说明书(不接受A版本，翻译有误)，区分带电池和不带电池出货版本, 如已做客版说明书可忽略此要求； 4. 出口法国的产品, 法规规定禁止在包装和共公众用的印刷品中使用矿物油中含有的物质, 包装印刷油墨中含有的MOAH/MOSH的质量浓度不能超过1%, 否则出货到 法国被抽检出现问题, 供应商需要对此负责; 5.订单备注显示有分批的（不同仓库/订单号） ，注意分开做货出货，否则会导致罚款 。 6.包装日期码按ZURU格式即可，请确保不迟于外箱日期码，可等于或者早于外箱日期码，必须为法定工作日。 7.做货前请先复核包装条码与订单是否一致再安排，对不上的需与ZURU跟单确认再安排。 | AD11: Sherry Lu | AE11: 1.007 | AF11: =I11*AE11 -> 1409.8 | AH11: 77772GQ2-S001-PRODCC | AI11: 已入 | AJ11: 系统入单 | AK11: =I11 -> 1400 | AV11: =I11*0.06 -> 84 | BG11: =I11 -> 1400 | BH11: =I11 -> 1400 | BO11: =I11/25 -> 56 | CD11: =BN11+BO11+BQ11+BS11+BR11 -> 56 | CE11: =BU11 -> 0 | CF11: =CC11 -> 0 | CG11: =BV11+BW11+BX11 -> 0
A12: 46044 | B12: SMYTHS TOYS EU HQ UNLIMITED COMPANY | C12: 法国 | D12: 4500191990 | E12: 4400528767 | F12: 4500191990-60 | G12: 77772GQ2-S001-PRODCC | H12: 唱片球50 pcs/2PDQ/箱 | I12: 600 | J12: 0 | K12: 50 | L12: =I12/K12 -> 12 | M12: 46098 | N12: 46094 | Q12: PASS | R12: 4/7 出货 | T12: 600 | U12: =T12-I12 -> 0 | V12: 无 | W12: 46044 | X12: 无 | Y12: 无 | Z12: 移除#21唱片 | AC12: 日期码格式：ZURU INC(BVI) 标准格式 日期：按实际生产日期 Packaging Info: 77772GQ2客版5L(英法德意荷)配套包装=MA PDQ (优先多语)+客版3L-5Lwarning收缩膜(翻PO#4500191961)+客版5L收藏指南(翻PO#4500191961)+MA 23L组装说明+MA 复合袋 EAN#4894680051133 77772GQ2必须移除Messy Lola Young (VINYL-S1-021) 这个唱片 ,比例按Una 更新的安排，如未按要求做货被客罚由工厂承担责任。 -------------------------------------------------------------------- Remark: Smyths 法国 1. 请准时出货，推期会有罚款； 2. 所有产品按符合欧洲标准走货，需要是不含微塑料版本。 3. 电子产品需增加一张WEEE声明30L通用黑白说明书(不接受A版本，翻译有误)，区分带电池和不带电池出货版本, 如已做客版说明书可忽略此要求； 4. 出口法国的产品, 法规规定禁止在包装和共公众用的印刷品中使用矿物油中含有的物质, 包装印刷油墨中含有的MOAH/MOSH的质量浓度不能超过1%, 否则出货到 法国被抽检出现问题, 供应商需要对此负责; 5.订单备注显示有分批的（不同仓库/订单号） ，注意分开做货出货，否则会导致罚款 。 6.包装日期码按ZURU格式即可，请确保不迟于外箱日期码，可等于或者早于外箱日期码，必须为法定工作日。 7.做货前请先复核包装条码与订单是否一致再安排，对不上的需与ZURU跟单确认再安排。 | AD12: Sherry Lu | AE12: 1.007 | AF12: =I12*AE12 -> 604.2 | AH12: 77772GQ2-S001-PRODCC | AI12: 已入 | AJ12: 系统入单 | AK12: =I12 -> 600 | AV12: =I12*0.06 -> 36 | BG12: =I12 -> 600 | BH12: =I12 -> 600 | BO12: =I12/25 -> 24 | CD12: =BN12+BO12+BQ12+BS12+BR12 -> 24 | CE12: =BU12 -> 0 | CF12: =CC12 -> 0 | CG12: =BV12+BW12+BX12 -> 0
A13: 46043 | B13: SMYTHS TOYS HQ UC UK | C13: 英国 | D13: 4500191961 | E13: 4400528768 | F13: 4500191961-10 | G13: MEC457-77772-S001 | H13: 唱片机+唱片球混装展示架 | I13: 11172 | J13: 0 | K13: 84 | L13: =I13/K13 -> 133 | M13: 46098 | N13: 46094 | Q13: PASS | R13: 4/6 出货 | T13: 11172 | U13: =T13-I13 -> 0 | W13: 46044 | X13: 有 | Y13: UN3481锂电池运输标签 | Z13: 移除#21唱片 | AC13: 日期码格式：ZURU INC(BVI) 标准格式 日期：按实际生产日期 Packaging Info: MEC457: 客版5L(英法德意荷)展示架[84pcs#77772+48pcs#77794; 所有客版资料翻PO#4500191961] 77772: 客版3L-5Lwarning收缩膜+客版5L收藏指南+MA 23L组装说明+MA复合袋 EAN#4894680051133 77794: 客版3L-5Lwarning纸盒底座+客版3L镭射贴纸+客版3L单铜纸贴纸+MA23L游戏说明书+MA23L warning说明书+1张WEEE声明(带电池)走货欧洲通用29L-C版说明 书 EAN#4894680051430 做货前请先核对条码无误 RECHARGEABLE LITHIUM BATTERY(INCLUDED) *#77772必须移除Messy Lola Young (VINYL-S1-021) 这个唱片, 比例按PM更新的安排* *展架上的Demo Box的唱片需要用"A Little Too Much"(VINYL-S1-025)替代原来的"Messy"(VINYL-S1-021)* *外箱需加一张UN3481锂电池运输标签* Remark: Smyths 英国/爱尔兰 1. 请准时出货，推期会有罚款； 2. 所有产品按符合欧洲标准走货，需要是不含微塑料版本。 3.包装日期码按ZURU格式即可，请确保不迟于外箱日期码，可等于或者早于外箱日期码，必须为法定工作日，印刷前请先检查外箱日期码。 4.请注意检查产品及包装应带UKCA图标（14+产品除外），包装显示ZURU UK LTD/ZURU France地址信息，QC部门请查核，如有问题与跟单确认 5.电子产品需增加一张WEEE声明30L通用黑白说明书(不接受A版本，翻译有误)，区分带电池和不带电池出货版本, 如已做客版说明书可忽略此要求； 6.订单备注显示有分批的（不同仓库/订单号） ，注意分开做货出货，否则会导致罚款 。 7.做货前请先复核包装条码与订单是否一致再安排，对不上的需与ZURU跟单确认再安排。 | AD13: Sherry Lu | AE13: 306.676 | AF13: =L13*AE13 -> 40787.908 | AH13: MEC457-S001-77772 | AI13: 已入 | AJ13: 系统入单 | AK13: =I13 -> 11172 | AV13: =I13*0.06 -> 670.32 | BG13: =I13 -> 11172 | BH13: =I13 -> 11172 | BV13: =I13/K13 -> 133 | CD13: =BN13+BO13+BQ13+BS13+BR13 -> 0 | CE13: =BU13 -> 0 | CF13: =CC13 -> 0 | CG13: =BV13+BW13+BX13 -> 133
A14: 46044 | B14: SMYTHS TOYS EU HQ UC | C14: 德国 | D14: 4500191996 | E14: 4400528770 | F14: 4500191996-50 | G14: 77772GQ2-S001-PRODCC | H14: 唱片球50 pcs/2PDQ/箱 | I14: 1700 | J14: 0 | K14: 50 | L14: =I14/K14 -> 34 | M14: 46099 | N14: 46095 | Q14: PASS | R14: 3/24 出货 | T14: 1700 | U14: =T14-I14 -> 0 | V14: 无 | W14: 46044 | X14: 无 | Y14: 无 | Z14: 移除#21唱片 | AC14: 日期码格式：ZURU INC(BVI) 标准格式 日期：按实际生产日期 Packaging Info: 77772GQ2客版5L(英法德意荷)配套包装=MA PDQ (优先多语)+客版3L-5Lwarning收缩膜(翻PO#4500191961)+客版5L收藏指南(翻PO#4500191961)+MA 23L组装说明+MA 复合袋 EAN#4894680051133 77772GQ2必须移除Messy Lola Young (VINYL-S1-021) 这个唱片 ,比例按Una 更新的安排，如未按要求做货被客罚由工厂承担责任。 RECHARGEABLE LITHIUM BATTERY(INCLUDED) Remark: Smyths 德国 1. 请准时出货，推期会有罚款； 2. 所有产品按符合欧洲标准走货，需要是不含微塑料版本。 3. 所有电子产品身上需要加字唛，为ZURU FRANCE 地址 (如无电子产品，产品布标有此地址，或产品太小无法增加可忽略此信息)，新地址ZURU FRANCE.33 rue Pa ul Meurice 75020 Paris, France. 4. 电子产品需增加一张WEEE声明30L通用黑白说明书(不接受A版本，翻译有误)，区分带电池和不带电池出货版本, 如已做客版说明书可忽略此要求； 5.所有出往德国市场有关slime和带香味的都需要出无硼无香版本； 6.订单备注显示有分批的（不同仓库/订单号） ，注意分开做货出货，否则会导致罚款 。 7.包装日期码按ZURU格式即可，请确保不迟于外箱日期码，可等于或者早于外箱日期码，必须为法定工作日。 8.做货前请先复核包装条码与订单是否一致再安排，对不上的需与ZURU跟单确认再安排。 | AD14: Sherry Lu | AE14: 1.007 | AF14: =I14*AE14 -> 1711.9 | AH14: 77772GQ2-S001-PRODCC | AI14: 已入 | AJ14: 系统入单 | AK14: =I14 -> 1700 | AV14: =I14*0.06 -> 102 | BG14: =I14 -> 1700 | BH14: =I14 -> 1700 | BO14: =I14/25 -> 68 | CD14: =BN14+BO14+BQ14+BS14+BR14 -> 68 | CE14: =BU14 -> 0 | CF14: =CC14 -> 0 | CG14: =BV14+BW14+BX14 -> 0
A15: 46044 | B15: SMYTHS TOYS EU HQ UC | C15: 德国 | D15: 4500191996 | E15: 4400528771 | F15: 4500191996-60 | G15: 77772GQ2-S001-PRODCC | H15: 唱片球50 pcs/2PDQ/箱 | I15: 1300 | J15: 0 | K15: 50 | L15: =I15/K15 -> 26 | M15: 46099 | N15: 46095 | Q15: PASS | R15: 3/24 出货 | T15: 1300 | U15: =T15-I15 -> 0 | V15: 无 | W15: 46044 | X15: 无 | Y15: 无 | Z15: 移除#21唱片 | AC15: 日期码格式：ZURU INC(BVI) 标准格式 日期：按实际生产日期 Packaging Info: 77772GQ2客版5L(英法德意荷)配套包装=MA PDQ (优先多语)+客版3L-5Lwarning收缩膜(翻PO#4500191961)+客版5L收藏指南(翻PO#4500191961)+MA 23L组装说明+MA 复合袋 EAN#4894680051133 77772GQ2必须移除Messy Lola Young (VINYL-S1-021) 这个唱片 ,比例按Una 更新的安排，如未按要求做货被客罚由工厂承担责任。 RECHARGEABLE LITHIUM BATTERY(INCLUDED) Remark: Smyths 德国 1. 请准时出货，推期会有罚款； 2. 所有产品按符合欧洲标准走货，需要是不含微塑料版本。 3. 所有电子产品身上需要加字唛，为ZURU FRANCE 地址 (如无电子产品，产品布标有此地址，或产品太小无法增加可忽略此信息)，新地址ZURU FRANCE.33 rue Pa ul Meurice 75020 Paris, France. 4. 电子产品需增加一张WEEE声明30L通用黑白说明书(不接受A版本，翻译有误)，区分带电池和不带电池出货版本, 如已做客版说明书可忽略此要求； 5.所有出往德国市场有关slime和带香味的都需要出无硼无香版本； 6.订单备注显示有分批的（不同仓库/订单号） ，注意分开做货出货，否则会导致罚款 。 7.包装日期码按ZURU格式即可，请确保不迟于外箱日期码，可等于或者早于外箱日期码，必须为法定工作日。 8.做货前请先复核包装条码与订单是否一致再安排，对不上的需与ZURU跟单确认再安排。 | AD15: Sherry Lu | AE15: 1.007 | AF15: =I15*AE15 -> 1309.1 | AH15: 77772GQ2-S001-PRODCC | AI15: 已入 | AJ15: 系统入单 | AK15: =I15 -> 1300 | AV15: =I15*0.06 -> 78 | BG15: =I15 -> 1300 | BH15: =I15 -> 1300 | BO15: =I15/25 -> 52 | CD15: =BN15+BO15+BQ15+BS15+BR15 -> 52 | CE15: =BU15 -> 0 | CF15: =CC15 -> 0 | CG15: =BV15+BW15+BX15 -> 0
A16: 46044 | B16: SMYTHS TOYS EU HQ UC | C16: 德国 | D16: 4500191997 | E16: 4400528770 | F16: 4500191997-10 | G16: MEC457-77772-S001 | H16: 唱片机+唱片球混装展示架 | I16: 4872 | J16: 0 | K16: 84 | L16: =I16/K16 -> 58 | M16: 46100 | N16: 46097 | Q16: PASS | T16: 4872 | U16: =T16-I16 -> 0 | W16: 46044 | X16: 有 | Y16: UN3481锂电池运输标签 | Z16: 移除#21唱片 | AC16: 日期码格式：ZURU INC(BVI) 标准格式 日期：按实际生产日期 Packaging Info: MEC457: 客版5L(英法德意荷)展示架[84pcs#77772+48pcs#77794; 所有客版资料翻PO#4500191961] 77772: 客版3L-5Lwarning收缩膜+客版5L收藏指南+MA 23L组装说明+MA复合袋 EAN#4894680051133 77794: 客版3L-5Lwarning纸盒底座+客版3L镭射贴纸+客版3L单铜纸贴纸+MA23L游戏说明书+MA23L warning说明书+1张WEEE声明(带电池)走货欧洲通用29L-C版说明 书 EAN#4894680051430 做货前请先核对条码无误 RECHARGEABLE LITHIUM BATTERY(INCLUDED) *#77772必须移除Messy Lola Young (VINYL-S1-021) 这个唱片, 比例按PM更新的安排* *展架上的Demo Box的唱片需要用"A Little Too Much"(VINYL-S1-025)替代原来的"Messy"(VINYL-S1-021)* *外箱需加一张UN3481锂电池运输标签* Remark: Smyths 德国 1. 请准时出货，推期会有罚款； 2. 所有产品按符合欧洲标准走货，需要是不含微塑料版本。 3. 所有电子产品身上需要加字唛，为ZURU FRANCE 地址 (如无电子产品，产品布标有此地址，或产品太小无法增加可忽略此信息)，新地址ZURU FRANCE.33 rue Pa ul Meurice 75020 Paris, France. 4. 电子产品需增加一张WEEE声明30L通用黑白说明书(不接受A版本，翻译有误)，区分带电池和不带电池出货版本, 如已做客版说明书可忽略此要求； 5.所有出往德国市场有关slime和带香味的都需要出无硼无香版本； 6.订单备注显示有分批的（不同仓库/订单号） ，注意分开做货出货，否则会导致罚款 。 7.包装日期码按ZURU格式即可，请确保不迟于外箱日期码，可等于或者早于外箱日期码，必须为法定工作日。 8.做货前请先复核包装条码与订单是否一致再安排，对不上的需与ZURU跟单确认再安排。 | AD16: Sherry Lu | AE16: 306.676 | AF16: =L16*AE16 -> 17787.208 | AH16: MEC457-S001-77772 | AI16: 已入 | AJ16: 系统入单 | AK16: =I16 -> 4872 | AV16: =I16*0.06 -> 292.32 | BG16: =I16 -> 4872 | BH16: =I16 -> 4872 | BV16: =I16/K16 -> 58 | CD16: =BN16+BO16+BQ16+BS16+BR16 -> 0 | CE16: =BU16 -> 0 | CF16: =CC16 -> 0 | CG16: =BV16+BW16+BX16 -> 58
A17: 46044 | B17: SMYTHS TOYS EU HQ UC | C17: 德国 | D17: 4500191997 | E17: 4400528771 | F17: 4500191997-20 | G17: MEC457-77772-S001 | H17: 唱片机+唱片球混装展示架 | I17: 5628 | J17: 0 | K17: 84 | L17: =I17/K17 -> 67 | M17: 46100 | N17: 46097 | Q17: PASS | R17: 4/6 出货 | T17: 5628 | U17: =T17-I17 -> 0 | W17: 46044 | X17: 有 | Y17: UN3481锂电池运输标签 | Z17: 移除#21唱片 | AC17: 日期码格式：ZURU INC(BVI) 标准格式 日期：按实际生产日期 Packaging Info: MEC457: 客版5L(英法德意荷)展示架[84pcs#77772+48pcs#77794; 所有客版资料翻PO#4500191961] 77772: 客版3L-5Lwarning收缩膜+客版5L收藏指南+MA 23L组装说明+MA复合袋 EAN#4894680051133 77794: 客版3L-5Lwarning纸盒底座+客版3L镭射贴纸+客版3L单铜纸贴纸+MA23L游戏说明书+MA23L warning说明书+1张WEEE声明(带电池)走货欧洲通用29L-C版说明 书 EAN#4894680051430 做货前请先核对条码无误 RECHARGEABLE LITHIUM BATTERY(INCLUDED) *#77772必须移除Messy Lola Young (VINYL-S1-021) 这个唱片, 比例按PM更新的安排* *展架上的Demo Box的唱片需要用"A Little Too Much"(VINYL-S1-025)替代原来的"Messy"(VINYL-S1-021)* *外箱需加一张UN3481锂电池运输标签* Remark: Smyths 德国 1. 请准时出货，推期会有罚款； 2. 所有产品按符合欧洲标准走货，需要是不含微塑料版本。 3. 所有电子产品身上需要加字唛，为ZURU FRANCE 地址 (如无电子产品，产品布标有此地址，或产品太小无法增加可忽略此信息)，新地址ZURU FRANCE.33 rue Pa ul Meurice 75020 Paris, France. 4. 电子产品需增加一张WEEE声明30L通用黑白说明书(不接受A版本，翻译有误)，区分带电池和不带电池出货版本, 如已做客版说明书可忽略此要求； 5.所有出往德国市场有关slime和带香味的都需要出无硼无香版本； 6.订单备注显示有分批的（不同仓库/订单号） ，注意分开做货出货，否则会导致罚款 。 7.包装日期码按ZURU格式即可，请确保不迟于外箱日期码，可等于或者早于外箱日期码，必须为法定工作日。 8.做货前请先复核包装条码与订单是否一致再安排，对不上的需与ZURU跟单确认再安排。 | AD17: Sherry Lu | AE17: 306.676 | AF17: =L17*AE17 -> 20547.292 | AH17: MEC457-S001-77772 | AI17: 已入 | AJ17: 系统入单 | AK17: =I17 -> 5628 | AV17: =I17*0.06 -> 337.68 | BG17: =I17 -> 5628 | BH17: =I17 -> 5628 | BV17: =I17/K17 -> 67 | CD17: =BN17+BO17+BQ17+BS17+BR17 -> 0 | CE17: =BU17 -> 0 | CF17: =CC17 -> 0 | CG17: =BV17+BW17+BX17 -> 67
A18: 46045 | B18: UPD, INC. | C18: 美国 | D18: 4500192208 | E18: 36244 | F18: 4500192208-10 | G18: 77772GQ1-S001 | H18: 唱片球52pcs/4PDQ/箱 | I18: 936 | J18: 0 | K18: 52 | L18: =I18/K18 -> 18 | M18: 46108 | N18: 46104 | Q18: PASS | R18: 3/30 出货 | T18: 936 | U18: =T18-I18 -> 0 | V18: 无 | W18: 46078 | X18: 无 | Y18: 无 | AC18: 日期码格式：ZURU INC(BVI) 标准格式 日期：按实际生产日期 Packaging Info: 1. 包装方式：MA UPC 优先1L 最新包装，出口美国 Remark: 2. 外箱箱唛红色和黑色双色印刷 3. 产品和包装上印刷tracking code信息，格式为ZURU常规 | AD18: Angel Lin | AE18: 0.6198 | AF18: =I18*AE18 -> 580.1328 | AG18: ZB04945-8.17 | AH18: 77772GQ1-S001 | AI18: 已入 | AJ18: 系统入单 | AK18: =I18 -> 936 | AN18: =I18 -> 936 | AU18: =I18 -> 936 | AV18: =I18*0.06 -> 56.16 | BK18: =I18/13 -> 72 | CD18: =BN18+BO18+BQ18+BS18+BR18 -> 0 | CE18: =BU18 -> 0 | CF18: =CC18 -> 0 | CG18: =BV18+BW18+BX18 -> 0
A19: 46062 | B19: ZURU LLC | C19: 美国 | D19: 4500193475 | E19: 5200009006 | F19: 4500193475-30 | G19: 77772GQ2-S001-FS | H19: 唱片球50 pcs/2PDQ/箱 | I19: 750 | J19: 0 | K19: 50 | L19: =I19/K19 -> 15 | M19: 46108 | N19: 46104 | Q19: PASS | R19: 4/4 出货 | T19: 750 | U19: =T19-I19 -> 0 | V19: OK | W19: 46062 | X19: 有 | Y19: 2/12客版UPC贴纸 | AC19: 日期码格式：ZURU DGYYYYMMDD CHINA(日期避开周末和法定节假日即可） 日期：按实际生产日期 Packaging Info: 1.产品包装要求： 77772GQ2：MA 1L收缩膜+MA 1L PDQ+MA收藏指南+客版UPC贴纸 2.NO RFID – 不需要RFID NEW UPC 与STD 不同， 需加贴NEW UPC贴纸。贴前须用黑色笔将原 UPC 码完全涂黑，使其无法扫描，再粘贴新 UPC 贴纸。 Remark: FAST START 项目要求 1.产品包装要求： 77772GQ2：MA 1L收缩膜+MA 1L PDQ+MA收藏指南+客版UPC贴纸 2.NO RFID – 不需要RFID NEW UPC 与STD 不同， 需加贴NEW UPC贴纸。贴前须用黑色笔将原 UPC 码完全涂黑，使其无法扫描，再粘贴新 UPC 贴纸。 新UPC 如下： SKU Fast Start SPEC# Description UPC GTIN 77772 77772GQ2-S001-FS MINI BRANDS VINYL S1 193052110282 10193052110289 3.外箱唛参考提供的模版，排版供确认后，才能生产。 4.此MTS订单不需要第三方抽板验货，但是要通过ZURU QC验货PASS后才能出货。 空运到3PL仓库。 | AD19: SD62 | AE19: 0.6042 | AF19: =I19*AE19 -> 453.15 | AG19: ZB05281-8.17 | AH19: 77772GQ2-S001 | AI19: 已入 | AJ19: 系统入单 | AK19: =I19 -> 750 | AN19: =I19 -> 750 | AU19: =I19 -> 750 | AV19: =I19*0.06 -> 45 | BN19: =I19/25 -> 30 | CD19: =BN19+BO19+BQ19+BS19+BR19 -> 30 | CE19: =BU19 -> 0 | CF19: =CC19 -> 0 | CG19: =BV19+BW19+BX19 -> 0
A20: 46044 | B20: SMYTHS TOYS HQ UC UK | C20: 英国 | D20: 4500192013 | E20: 4400530471 | F20: 4500192013-20 | G20: 77772GQ2-S001-PRODCC | H20: 唱片球50 pcs/2PDQ/箱 | I20: 10000 | J20: 0 | K20: 50 | L20: =I20/K20 -> 200 | M20: 46112 | N20: 46108 | Q20: PASS | R20: 4/6 出货 | T20: 10000 | U20: =T20-I20 -> 0 | V20: 无 | W20: 46044 | X20: 无 | Y20: 无 | Z20: 移除#21唱片 | AC20: 日期码格式：ZURU INC(BVI) 标准格式 日期：按实际生产日期 Packaging Info: 77772GQ2客版5L(英法德意荷)配套包装=MA PDQ (优先多语)+客版3L-5Lwarning收缩膜(翻PO#4500191961)+客版5L收藏指南(翻PO#4500191961)+MA 23L组装说明+MA 复合袋 EAN#4894680051133 77772GQ2必须移除Messy Lola Young (VINYL-S1-021) 这个唱片 ,比例按Una 更新的安排，如未按要求做货被客罚由工厂承担责任。 Remark: Smyths 英国/爱尔兰 1. 请准时出货，推期会有罚款； 2. 所有产品按符合欧洲标准走货，需要是不含微塑料版本。 3.包装日期码按ZURU格式即可，请确保不迟于外箱日期码，可等于或者早于外箱日期码，必须为法定工作日，印刷前请先检查外箱日期码。 4.请注意检查产品及包装应带UKCA图标（14+产品除外），包装显示ZURU UK LTD/ZURU France地址信息，QC部门请查核，如有问题与跟单确认 5.电子产品需增加一张WEEE声明30L通用黑白说明书(不接受A版本，翻译有误)，区分带电池和不带电池出货版本, 如已做客版说明书可忽略此要求； 6.订单备注显示有分批的（不同仓库/订单号） ，注意分开做货出货，否则会导致罚款 。 7.做货前请先复核包装条码与订单是否一致再安排，对不上的需与ZURU跟单确认再安排。 | AD20: Sherry Lu | AE20: 1.007 | AF20: =I20*AE20 -> 10070 | AH20: 77772GQ2-S001-PRODCC | AI20: 已入 | AJ20: 系统入单 | AK20: =I20 -> 10000 | AV20: =I20*0.06 -> 600 | BG20: =I20 -> 10000 | BH20: =I20 -> 10000 | BO20: =I20/25 -> 400 | CD20: =BN20+BO20+BQ20+BS20+BR20 -> 400 | CE20: =BU20 -> 0 | CF20: =CC20 -> 0 | CG20: =BV20+BW20+BX20 -> 0
A21: 46045 | B21: ZURU GERMANY GMBH | C21: 德国 | D21: 4500192187 | E21: 5200008729 | F21: 4500192187-10 | G21: 77772GQ1-S002-MTS | H21: 唱片球13 pcs/PDQ/箱 | I21: 15600 | J21: 0 | K21: 13 | L21: =I21/K21 -> 1200 | M21: 46112 | N21: 46108 | Q21: PASS | R21: 4/2 出货 | T21: 15600 | U21: =T21-I21 -> 0 | W21: 46364 | X21: 无 | Y21: 46092 | Z21: 外箱日期码要晚于或等于产品日期码，不能早于产品的日期码 | AC21: 日期码格式：ZURU INC(BVI) 标准格式 日期：按实际生产日期 Packaging Info: 77772GQ1：MA 3L PDQ+MA 3L EAN收缩膜+1*多语警语折叠贴纸+MA 23L拼装说明书+MA 5L收藏指南+MA纸卡/复合袋 Remark: 1.德国内销单，需要通过ZURU 验货结果后才能出货 (工厂需要主动提前同ZURU QC预约验货避免延期出货造成不必要麻烦)； 2.产品如含有化学品（slime 等），需要无硼无香。需要无微塑料版本。 3.所有出口欧洲的产品, 法规规定禁止在包装和共公众用的印刷品中使用矿物油中含有的物质, 包装印刷油墨中含有的MOAH/MOSH的质量浓度不能超过1%, 否则出货 到法国被抽检出现问题, 供应商需要对此负责; 4. date code: 外箱日期码要晚于或等于产品日期码，不能早于产品的日期码； 5. 所有出往德国的电子产品身上需要加字唛，为ZURU FRANCE 地址，需跟包装上的地址一致 (如无电子产品，产品布标有此地址，或产品太小无法增加可忽略此信 息。如产品无法加字唛，需让对应跟单提供产品贴纸资料) 新地址：ZURU France 33 rue Paul Meurice 75020 Paris, France 旧地址：ZURU France 1/3, Rue d'Argenteuil 95210 SAINT-GRATIEN, FRANCE 6.所有出往德国订单的电子产品需增加一张欧洲通用WEEE声明说明书，区分带电池和不带电池版本, 如已做客版说明书可忽略此要求。 7.装柜时需要按照款式号码从小到大一款款依次装,避免终端仓库卸货混乱.若一个柜子涉及到几个不同国家内销单,装柜时需要一个国家装完后再装另一个国家的 产品,依次装柜,避免终端仓库因不同国家不同库位位置卸货混乱. (此点需要同工厂装柜人员强调)" 8.ratio 同MA 9. 若有特定款有特殊外箱条码要求时,需要明确列出产品款对应的具体外箱条码号码/条码类型 (若无,可以忽略此需求). | AD21: SD04 | AE21: 2.02 | AF21: =I21*AE21 -> 31512 | AH21: 77772GQ1-S002-3L | AI21: 已入 | AJ21: 系统入单 | AK21: =I21 -> 15600 | AP21: =I21 -> 15600 | AU21: =I21 -> 15600 | AV21: =I21*0.06 -> 936 | BL21: =I21/13 -> 1200 | CD21: =BN21+BO21+BQ21+BS21+BR21 -> 0 | CE21: =BU21 -> 0 | CF21: =CC21 -> 0 | CG21: =BV21+BW21+BX21 -> 0
A22: 46057 | B22: INDIGO CANADA | C22: 加拿大 | D22: 4500193076 | E22: 4552042232 | F22: 4500193076-10 | G22: 77772GQ2-S002 | H22: 唱片球25 pcs/PDQ/箱 | I22: 7500 | J22: 0 | K22: 25 | L22: =I22/K22 -> 300 | M22: 46114 | N22: 46111 | Q22: PASS | R22: 4/6 出货 | S22: 1903076 | T22: 7500 | U22: =T22-I22 -> 0 | V22: OK | W22: 46097 | X22: 有 | Y22: 46098 | AC22: 日期码格式： 标准格式 日期：按实际生产日期 Packaging Info: 77772GQ2 MA 3L EAN版本+UPC贴纸193052090065 Remark: 出加拿大 有价格贴纸 (Low Tack ,must peel off easily without leaving adhesive residue) 有shipping label (贴4面） Zuru验货.日期跟踪码：产品外包装及产品本身都必须有日期跟踪码，ZURU标准格式日期码。 | AD22: Bella Tan | AE22: 1.094 | AF22: =I22*AE22 -> 8205 | AH22: 77772GQ2-S002-3L | AI22: 已入 | AJ22: 系统入单 | AK22: =I22 -> 7500 | AP22: =I22 -> 7500 | AU22: =I22 -> 7500 | AV22: =I22*0.06 -> 450 | BO22: =I22/25 -> 300 | CD22: =BN22+BO22+BQ22+BS22+BR22 -> 300 | CE22: =BU22 -> 0 | CF22: =CC22 -> 0 | CG22: =BV22+BW22+BX22 -> 0
A23: 46081 | B23: TARGET US | C23: 美国 | D23: 4500194699 | E23: 10001764946-0 581 | F23: 4500194699-10 | G23: 77772GQ5-S001 | H23: 唱片球25 pcs/PDQ/箱 | I23: 55000 | J23: 0 | K23: 25 | L23: =I23/K23 -> 2200 | M23: 46118 | N23: 46114 | Q23: PASS | T23: 55000 | U23: =T23-I23 -> 0 | V23: OK | W23: 3/13确认 | X23: 有 | Y23: 3/25寄出 | AC23: 日期码格式：ZURU INC(BVI) 标准格式 日期：按实际生产日期 Packaging Info: 产品包装MA 1L 收缩膜+MA 5L 收藏指南+MA 23L 组装说明+客版PDQ；客版PDQ翻单4500189603 Remark: 1.77772GQ5-S001-MINI BRANDS-VINYL-SERIES 1-CAPSULE,WITH DEMO,25PCS/GRAVITY PDQ,25PCS/PDQ/CTN; 2.产品包装MA 1L 收缩膜+MA 5L 收藏指南+MA 23L 组装说明+客版PDQ；客版PDQ翻单4500189603；收缩膜上的UPC显示193052090065; 4 mini vinyls(1 Target US Exclusive),1 accessory; 3. 外箱正唛左上角位置粘贴条码箱贴纸，每箱只贴一张，由ZURU订购。来料贴纸上显示的客户DPCI# 086-02-8931, UPC显示10193052090062; 4. 产品和包装上均要印刷tracking code信息，格式为ZURU常规格式; 5. 需要我司QC验货之后才能安排出货; 6. 出货方式： 货代自提 | AD23: Holly Zheng | AE23: 1.29 | AF23: =I23*AE23 -> 70950 | AG23: ZB05068-8.17 | AH23: 77772GQ5-S001 | AI23: 已入 | AJ23: 系统入单 | AM23: =I23 -> 55000 | AN23: =I23 -> 55000 | AU23: =I23 -> 55000 | AV23: =I23*0.06 -> 3300 | BU23: =I23/25 -> 2200 | CD23: =BN23+BO23+BQ23+BS23+BR23 -> 0 | CE23: =BU23 -> 2200 | CF23: =CC23 -> 0 | CG23: =BV23+BW23+BX23 -> 0
A24: 46059 | B24: TARGET US | C24: 美国 | D24: 4500190738 | E24: 10001661694-3891 | F24: 4500190738-50 | G24: 77772GQ5-S001 | H24: 唱片球25 pcs/PDQ/箱 | I24: 21375 | J24: 0 | K24: 25 | L24: =I24/K24 -> 855 | M24: 46119 | N24: 46115 | Q24: PASS | T24: 21375 | U24: =T24-I24 -> 0 | W24: 3/2确认 | X24: 有 | Y24: 3/25寄出 | AC24: 日期码格式：ZURU INC(BVI) 标准格式 日期：按实际生产日期 Packaging Info: 77772GQ5：产品包装MA 1L 收缩膜+MA 5L 收藏指南+MA 23L 组装说明+客版PDQ；客版PDQ翻单4500189603；收缩膜上的UPC显示193052090065; 77794UQ1：产品包装 MA 1L黑白警告语说明书+MA 1L 彩盒+MA 1L PDQ; 彩盒上的UPC显示193052090409; Remark: 77772GQ5： 1.77772GQ5-S001-MINI BRANDS-VINYL-SERIES 1-CAPSULE,WITH DEMO,25PCS/GRAVITY PDQ,25PCS/PDQ/CTN; 2.产品包装MA 1L 收缩膜+MA 5L 收藏指南+MA 23L 组装说明+客版PDQ；客版PDQ翻单4500189603；收缩膜上的UPC显示193052090065; 4 mini vinyls(1 Target US Exclusive),1 accessory; 3. 外箱正唛左上角位置粘贴条码箱贴纸，每箱只贴一张，由ZURU订购。来料贴纸上显示的客户DPCI# 086-02-8931, UPC显示10193052090062; 4. 外箱正唛箱唛内容右侧需贴一张EVENT LABEL，内容显示 7/19 TRANSITION TOYS Set Date 7/19/2026，由工厂自行订购； 以上Items： 1. 产品和包装上均要印刷tracking code信息，格式为ZURU常规格式； 2. 需要我司QC验货之后才能安排出货 3. 出货方式： 货代自提 | AD24: Holly Zheng | AE24: 1.29 | AF24: =I24*AE24 -> 27573.75 | AG24: ZB05310-8.17 | AH24: 77772GQ5-S001 | AI24: 已入 | AJ24: 系统入单 | AM24: =I24 -> 21375 | AN24: =I24 -> 21375 | AU24: =I24 -> 21375 | AV24: =I24*0.06 -> 1282.5 | BU24: =I24/25 -> 855 | CD24: =BN24+BO24+BQ24+BS24+BR24 -> 0 | CE24: =BU24 -> 855 | CF24: =CC24 -> 0 | CG24: =BV24+BW24+BX24 -> 0
A25: 46061 | B25: ASIA GOAL LIMITED TAIWAN BRANCH (H. | C25: 台湾 | D25: 4500193384 | E25: AG250405-TW | F25: 4500193384-10 | G25: 77772GQ1-S001 | H25: 唱片球52pcs/4PDQ/箱 | I25: 780 | J25: 0 | K25: 52 | L25: =I25/K25 -> 15 | M25: 46120 | N25: 46116 | Q25: PASS | T25: 780 | U25: =T25-I25 -> 0 | V25: OK | W25: 46067 | X25: 无 | Y25: 3/23 警语贴纸 | AC25: 日期码格式：ZURU INC(BVI) 标准格式 日期：按实际生产日期 Packaging Info: 此单出TW 77772GQ1/77794UQ1: MA PKG,优先1L + 1张警语贴纸 Remark: | AD25: Chelsea Luo | AE25: 1.033 | AF25: =I25*AE25 -> 805.74 | AH25: 77772GQ1-S001 | AI25: 已入 | AJ25: 系统入单 | AK25: =I25 -> 780 | AN25: =I25 -> 780 | AU25: =I25 -> 780 | AV25: =I25*0.06 -> 46.8 | BK25: =I25/13 -> 60 | CD25: =BN25+BO25+BQ25+BS25+BR25 -> 0 | CE25: =BU25 -> 0 | CF25: =CC25 -> 0 | CG25: =BV25+BW25+BX25 -> 0
A26: 46061 | B26: ASIA GOAL LIMITED | C26: 台湾 | D26: 4500193379 | E26: AG250404-HK | F26: 4500193379-10 | G26: 77772GQ1-S001 | H26: 唱片球52pcs/4PDQ/箱 | I26: 780 | J26: 0 | K26: 52 | L26: =I26/K26 -> 15 | M26: 46120 | N26: 46116 | Q26: PASS | T26: 780 | U26: =T26-I26 -> 0 | V26: OK | W26: 46067 | X26: 无 | Y26: 3/23 警语贴纸 | AC26: 日期码格式：ZURU INC(BVI) 标准格式 日期：按实际生产日期 Packaging Info: 77772GQ1: MA 1L PKG ，PDQ , MA 收藏指南，说明书+HK 客供警语贴纸 Remark: 此单出HK | AD26: Chelsea Luo | AE26: 1.033 | AF26: =I26*AE26 -> 805.74 | AH26: 77772GQ1-S001 | AI26: 已入 | AJ26: 系统入单 | AK26: =I26 -> 780 | AN26: =I26 -> 780 | AU26: =I26 -> 780 | AV26: =I26*0.06 -> 46.8 | BK26: =I26/13 -> 60 | CD26: =BN26+BO26+BQ26+BS26+BR26 -> 0 | CE26: =BU26 -> 0 | CF26: =CC26 -> 0 | CG26: =BV26+BW26+BX26 -> 0
A27: 46081 | B27: TARGET US | C27: 美国 | D27: 4500194700 | E27: 10001764947-0 581 | F27: 4500194700-10 | G27: 77772GQ5-S001 | H27: 唱片球25 pcs/PDQ/箱 | I27: 55000 | J27: 0 | K27: 25 | L27: =I27/K27 -> 2200 | M27: 46125 | N27: 46121 | Q27: PASS | T27: 55000 | U27: =T27-I27 -> 0 | W27: 46094 | X27: 有 | Y27: 3/24外箱条码箱贴纸贴纸，2/10提供EVENT LABEL | AC27: 日期码格式：ZURU INC(BVI) 标准格式 日期：按实际生产日期 Packaging Info: 产品包装MA 1L 收缩膜+MA 5L 收藏指南+MA 23L 组装说明+客版PDQ；客版PDQ翻单4500189603 Remark: 1.77772GQ5-S001-MINI BRANDS-VINYL-SERIES 1-CAPSULE,WITH DEMO,25PCS/GRAVITY PDQ,25PCS/PDQ/CTN; 2.产品包装MA 1L 收缩膜+MA 5L 收藏指南+MA 23L 组装说明+客版PDQ；客版PDQ翻单4500189603；收缩膜上的UPC显示193052090065; 4 mini vinyls(1 Target US Exclusive),1 accessory; 3. 外箱正唛左上角位置粘贴条码箱贴纸，每箱只贴一张，由ZURU订购。来料贴纸上显示的客户DPCI# 086-02-8931, UPC显示10193052090062; 4. 产品和包装上均要印刷tracking code信息，格式为ZURU常规格式; 5. 需要我司QC验货之后才能安排出货; 6. 出货方式： 货代自提 | AD27: Holly Zheng | AE27: 1.29 | AF27: =I27*AE27 -> 70950 | AH27: 77772GQ5-S001 | AI27: 已入 | AJ27: 系统入单 | AM27: =I27 -> 55000 | AN27: =I27 -> 55000 | AU27: =I27 -> 55000 | AV27: =I27*0.06 -> 3300 | BU27: =I27/25 -> 2200 | CD27: =BN27+BO27+BQ27+BS27+BR27 -> 0 | CE27: =BU27 -> 2200 | CF27: =CC27 -> 0 | CG27: =BV27+BW27+BX27 -> 0
A28: 46065 | B28: KANDYTOYS LIMITED | C28: 英国 | D28: 4500193688 | E28: AS191225ZUR15 274 | F28: 4500193688-20 | G28: 77772GQ2-S001-PRODCC | H28: 唱片球50 pcs/2PDQ/箱 | I28: 3750 | J28: 0 | K28: 50 | L28: =I28/K28 -> 75 | M28: 46125 | N28: 46121 | Q28: PASS | T28: 3750 | U28: =T28-I28 -> 0 | V28: OK | W28: 3/23确认 | X28: 无 | Y28: 3/25PDQ条码贴纸 | Z28: 移除#21唱片 | AC28: 日期码格式：ZURU INC(BVI) 标准格式 日期：按实际生产日期 Packaging Info: 77772GQ2-S001:MA UPC包装+MA PDQ+一张PDQ条码贴纸(位置:PDQ底部贴一张可扫描的条码贴纸(ZURU 跟单提供模板) 77772GQ2 出UK，配比：4 mini vinyls(去掉 Lola Young vinyl),1 accessory； 其他款配比按MA标准 Remark: 1.订单出英国，请注意检查产品及包装应带UKCA图标，包装需要显示ZURU UK LTD/ZURU France地址信息，QC同事请查核，如有问题与跟单确认。 2.生产日期按实际的（法定工作日），按ZURU标准格式即可 ，并需要在出货前提供每个产品外包上对应的生产日期明细 3.请注意所有订单都需要经过ZURU QC验货并且通过后方可出货 4.一个产品一个条码，单款有多个子件条码的请让跟单提供贴纸覆盖。 5.外箱上的条码请确保清晰可扫描，有PDQ， 需要在PDQ底部贴一张带条码并可扫描的贴纸(ZURU 跟单提供模板）。 6.所有产品按符合欧洲标准走货，微塑料需合规并增加IFUD声明，含电池的需要增加WEEE说明书。 | AD28: Zoe Zhou | AE28: 1.007 | AF28: =I28*AE28 -> 3776.25 | AH28: 77772GQ2-S001 | AI28: 已入 | AJ28: 系统入单 | AK28: =I28 -> 3750 | AN28: =I28 -> 3750 | AU28: =I28 -> 3750 | AV28: =I28*0.06 -> 225 | BN28: =I28/25 -> 150 | CD28: =BN28+BO28+BQ28+BS28+BR28 -> 150 | CE28: =BU28 -> 0 | CF28: =CC28 -> 0 | CG28: =BV28+BW28+BX28 -> 0
A29: 46079 | B29: MINISO DEPOT CA INC. | C29: 美国 | D29: 4500194334 | E29: 4360138834 | F29: 4500194334-60 | G29: 77772GQ2-S002 | H29: 唱片球25 pcs/PDQ/箱 | I29: 9100 | J29: 0 | K29: 25 | L29: =I29/K29 -> 364 | M29: 46126 | N29: 46122 | Q29: PASS | T29: 9100 | U29: =T29-I29 -> 0 | V29: OK | W29: 46094 | X29: 无 | Y29: 3/13提供PDQUPC 条码贴纸 | AC29: 日期码格式：ZURU INC(BVI) 标准格式 日期：按实际生产日期 Packaging Info: 1. 包装方式：MA UPC优先1L最新包装，出口美国； 2. 产品和包装上印刷tracking code信息，格式为ZURU常规； 3. ZURU QC 验货合格后即可出货. Remark: 6. 77772GQ2-S002 PDQ上需要贴一张UPC 条码贴纸,UPC显示：193052090065，贴纸AW跟单提供，工厂自行采购; | AD29: Iris Yuan | AE29: 0.762 | AF29: =I29*AE29 -> 6934.2 | AG29: ZB05283-8.17 | AH29: 77772GQ2-S002 | AI29: 已入 | AJ29: 系统入单 | AK29: =I29 -> 9100 | AN29: =I29 -> 9100 | AU29: =I29 -> 9100 | AV29: =I29*0.06 -> 546 | BN29: =I29/25 -> 364 | CD29: =BN29+BO29+BQ29+BS29+BR29 -> 364 | CE29: =BU29 -> 0 | CF29: =CC29 -> 0 | CG29: =BV29+BW29+BX29 -> 0
A30: 46079 | B30: MINISO DEPOT CA INC. | C30: 美国 | D30: 4500194341 | E30: 4360138853 | F30: 4500194341-60 | G30: 77772GQ2-S002 | H30: 唱片球25 pcs/PDQ/箱 | I30: 7275 | J30: 0 | K30: 25 | L30: =I30/K30 -> 291 | M30: 46126 | N30: 46122 | Q30: PASS | T30: 7275 | U30: =T30-I30 -> 0 | V30: OK | W30: 46094 | X30: 无 | Y30: 3/13提供PDQUPC 条码贴纸 | AC30: 日期码格式：ZURU INC(BVI) 标准格式 日期：按实际生产日期 Packaging Info: 1. 包装方式：MA UPC优先1L最新包装，出口美国； 2. 产品和包装上印刷tracking code信息，格式为ZURU常规； 3. ZURU QC 验货合格后即可出货. Remark: 7. 77772GQ2-S002 PDQ上需要贴一张UPC 条码贴纸,UPC显示：193052090065，贴纸AW跟单提供，工厂自行采购; | AD30: Iris Yuan | AE30: 0.762 | AF30: =I30*AE30 -> 5543.55 | AG30: ZB05205-8.17 | AH30: 77772GQ2-S002 | AI30: 已入 | AJ30: 系统入单 | AK30: =I30 -> 7275 | AN30: =I30 -> 7275 | AU30: =I30 -> 7275 | AV30: =I30*0.06 -> 436.5 | BN30: =I30/25 -> 291 | CD30: =BN30+BO30+BQ30+BS30+BR30 -> 291 | CE30: =BU30 -> 0 | CF30: =CC30 -> 0 | CG30: =BV30+BW30+BX30 -> 0
A31: 46030 | B31: CRACKER BARREL | C31: 美国 | D31: 4500188838 | E31: 277707 | F31: 4500188838-20 | G31: 77772GQ4-S001 | H31: 唱片球6 pcs/PDQ/箱 | I31: 4002 | J31: 0 | K31: 6 | L31: =I31/K31 -> 667 | M31: 46127 | N31: 46123 | P31: 4/3完成25%大货包装第三方抽板测试，4/15完成100%大货 | Q31: PASS | T31: =1008+2958+36 -> 4002 | U31: =T31-I31 -> 0 | V31: OK | W31: 3/5 确认 | X31: 无 | Y31: 3/3客供价格贴纸 | AB31: A.样板抽取12pcs/每款/每色（带包装，大货中抽取）。 B.产品上有涂层的，需额外准备足够的干油墨（每个颜色2个A4尺寸的喷涂样本，涂层喷到同底材，涂满涂厚，至少能刮取30mg的量）。 4. 外箱贴打印常规 4"x6" Standard Label Stock, 只需贴一面(正唛）, 优先贴在纸箱的右上方空白处，不可以盖住外箱上的其他信息及标签，可适当调整位置。 5. 样板需求（77794UQ1 & 77772GQ4）： 1)产前样+Model Store Sample: 请在4/1前寄出每款每色各8pcs大货样（不带PDQ，需贴客版价格贴纸）并寄给深圳跟单Emily Wu/Irene Wang, 我们需寄给客户审 批和拍照。 2)满箱样：请在4/15前寄出各一箱大货满箱样（产品需贴客版价格贴纸，并带大货外箱）寄给深圳跟单Emily Wu/Irene Wang。 Remark：以上所有样板数量不包含在订单数量里，做货需预备样板数量。 | AC31: 日期码格式：ZURU INC(BVI) 标准格式 日期：按实际生产日期 Packaging Info: 1. item#77772GQ4: MA UPC最新版本包装（优先1L) + 客版PDQ + 客版价格贴纸 + 外箱贴； 客版价格贴纸和外箱贴都是跟单提供，工厂自行订购。出口美国。 2. 产品及包装上都要有日期码，日期码是一致的（但不能为周末)，格式为ZURU标准格式。 Remark: 3. 此两款都需在4/2前完成至少25%大货包装，4/3早上进行ITS的25%大货抽样验货。 100%大货可以在4/15前完成。收到PASS的测试报告后，才可安排出货。 25%抽样由客人指定的第三方ITS进行，现场在大货中抽样，具体要求如下所列： A.样板抽取12pcs/每款/每色（带包装，大货中抽取）。 B.产品上有涂层的，需额外准备足够的干油墨（每个颜色2个A4尺寸的喷涂样本，涂层喷到同底材，涂满涂厚，至少能刮取30mg的量）。 4. 外箱贴打印常规 4"x6" Standard Label Stock, 只需贴一面(正唛）, 优先贴在纸箱的右上方空白处，不可以盖住外箱上的其他信息及标签，可适当调整位置。 5. 样板需求（77794UQ1 <(>&<)> 77772GQ4）： 1)产前样+Model Store Sample: 请在4/1前寄出每款每色各8pcs大货样（不带PDQ，需贴客版价格贴纸）并寄给深圳跟单Emily Wu/Irene Wang, 我们需寄给客户审 批和拍照。 2)满箱样：请在4/15前寄出各一箱大货满箱样（产品需贴客版价格贴纸，并带大货外箱）寄给深圳跟单Emily Wu/Irene Wang。 Remark：以上所有样板数量不包含在订单数量里，做货需预备样板数量。 | AD31: Emily Wu | AE31: 1.248 | AF31: =I31*AE31 -> 4994.496 | AG31: ZB05480-8.17 | AH31: 77772GQ2-S001 | AI31: 已入 | AJ31: 系统入单 | AK31: =I31 -> 4002 | AN31: =I31 -> 4002 | AU31: =I31 -> 4002 | AV31: =I31*0.06 -> 240.12 | BT31: =I31/6 -> 667 | CD31: =BN31+BO31+BQ31+BS31+BR31 -> 0 | CE31: =BU31 -> 0 | CF31: =CC31 -> 0 | CG31: =BV31+BW31+BX31 -> 0
A32: 46086 | B32: SIDJ JOUECLUB | C32: 法国 | D32: 4500195260 | F32: 4500195260-10 | G32: 77772GQ2-S001 | H32: 唱片球50 pcs/2PDQ/箱 | I32: 8750 | J32: 0 | K32: 50 | L32: =I32/K32 -> 175 | M32: 46127 | N32: 46123 | P32: 此票无需客户验货，需2套完整大货样球，出货前一周提供给跟单; | Q32: PASS | T32: 8750 | U32: =T32-I32 -> 0 | W32: 3/23确认 | X32: 无 | Y32: 3/31贴纸(含IT<(>&<)>NL<(>&<)>AR警示语+客户订单信息+意大利回收标+CMIM logo) | Z32: 日期码格式：2041526 | AC32: 日期码格式：2041526 日期： Packaging Info: 77772GQ2-S001:MA3L EAN 吸塑膜+1张贴纸(含IT<(>&<)>NL<(>&<)>AR警示语+客户订单信息+意大利回收标+CMIM logo)+MA配件袋子+MA5L收藏指南+MA23L组装说明书 +MA 3L展示盒 Remark: 1.此票无需客户验货，请多备料1套左右 2.请准备每款5pcs包装备品（客版彩盒），和大货一起出（以备到客户仓库后有破损的包装） 3.所有出口法国的产品, 法规规定禁止在包装和共公众用的印刷品中使用矿物油中含有的物质, 包装印刷油墨中含有的MOAH/MOSH的质量浓度不能超过1%, 否则出货 到法国被抽检出现问题, 供应商需要对此负责; 4.出口法国请确保产品符合EU微塑料法规，包装需显示法国回收logo; | AD32: Ula Zhao | AE32: 1.007 | AF32: =I32*AE32 -> 8811.25 | AH32: 77772GQ2-S001 | AI32: 已入 | AJ32: 系统入单 | AK32: =I32 -> 8750 | AP32: =I32 -> 8750 | AU32: =I32 -> 8750 | AV32: =I32*0.06 -> 525 | BO32: =I32/25 -> 350 | CD32: =BN32+BO32+BQ32+BS32+BR32 -> 350 | CE32: =BU32 -> 0 | CF32: =CC32 -> 0 | CG32: =BV32+BW32+BX32 -> 0
A33: 46044 | B33: SMYTHS TOYS HQ UC IE | C33: 爱尔兰 | D33: 4500192014 | E33: 4400530472 | F33: 4500192014-20 | G33: 77772GQ2-S001-PRODCC | H33: 唱片球50 pcs/2PDQ/箱 | I33: 2000 | J33: 0 | K33: 50 | L33: =I33/K33 -> 40 | M33: 46127 | N33: 46123 | Q33: AOD | T33: 2000 | U33: =T33-I33 -> 0 | W33: 46044 | X33: 无 | Y33: 无 | Z33: 移除#21唱片 | AC33: 日期码格式：ZURU INC(BVI) 标准格式 日期：按实际生产日期 Packaging Info: 77772GQ2客版5L(英法德意荷)配套包装=MA PDQ (优先多语)+客版3L-5Lwarning收缩膜(翻PO#4500191961)+客版5L收藏指南(翻PO#4500191961)+MA 23L组装说明+MA 复合袋 EAN#4894680051133 77772GQ2必须移除Messy Lola Young (VINYL-S1-021) 这个唱片 ,比例按Una 更新的安排，如未按要求做货被客罚由工厂承担责任。 Remark: Smyths 英国/爱尔兰 1. 请准时出货，推期会有罚款； 2. 所有产品按符合欧洲标准走货，需要是不含微塑料版本。 3.包装日期码按ZURU格式即可，请确保不迟于外箱日期码，可等于或者早于外箱日期码，必须为法定工作日，印刷前请先检查外箱日期码。 4.请注意检查产品及包装应带UKCA图标（14+产品除外），包装显示ZURU UK LTD/ZURU France地址信息，QC部门请查核，如有问题与跟单确认 5.电子产品需增加一张WEEE声明30L通用黑白说明书(不接受A版本，翻译有误)，区分带电池和不带电池出货版本, 如已做客版说明书可忽略此要求； 6.订单备注显示有分批的（不同仓库/订单号） ，注意分开做货出货，否则会导致罚款 。 7.做货前请先复核包装条码与订单是否一致再安排，对不上的需与ZURU跟单确认再安排。 | AD33: Sherry Lu | AE33: 1.007 | AF33: =I33*AE33 -> 2014 | AH33: 77772GQ2-S001-PRODCC | AI33: 已入 | AJ33: 系统入单 | AK33: =I33 -> 2000 | AV33: =I33*0.06 -> 120 | BG33: =I33 -> 2000 | BH33: =I33 -> 2000 | BO33: =I33/25 -> 80 | CD33: =BN33+BO33+BQ33+BS33+BR33 -> 80 | CE33: =BU33 -> 0 | CF33: =CC33 -> 0 | CG33: =BV33+BW33+BX33 -> 0
A34: 46122 | D34: ZMPO260373 | F34: ZMPO260373-10 | G34: 77772GQ2-S002-PRODCC | I34: 40 | M34: 46127 | N34: 46123 | T34: 40 | U34: =T34-I34 -> 0 | W34: 46122 | X34: 无 | Y34: 无 | AC34: 备注：收到样品订单后尽快安排 ，注意样板品质质量要求要高于大货品质要求 ，送货时必须要附带送货单(没有送货单和QC检验合格报告的仓库一律拒绝收货)，请知悉，谢谢！Remark只需要40个成品球，不需要PDQ,不需要光碟 | AD34: Angus | AH34: 77772GQ2-S002 | AI34: * | AK34: =I34 -> 40 | AN34: =I34 -> 40 | AU34: =I34 -> 40 | AV34: =I34*0.06 -> 2.4 | BN34: 2 | CD34: =BN34+BO34+BQ34+BS34+BR34 -> 2 | CE34: =BU34 -> 0 | CF34: =CC34 -> 0 | CG34: =BV34+BW34+BX34 -> 0
A35: 46080 | B35: UPD, INC. | C35: 美国 | D35: 4500194415 | E35: 36405 | F35: 4500194415-20 | G35: 77772GQ1-S001 | H35: 唱片球52pcs/4PDQ/箱 | I35: 468 | J35: 0 | K35: 52 | L35: =I35/K35 -> 9 | M35: 46128 | N35: 46125 | Q35: PASS | T35: 468 | U35: =T35-I35 -> 0 | W35: 3/17 确认 | X35: 无 | Y35: 无 | AC35: 日期码格式：ZURU INC(BVI) 标准格式 日期：按实际生产日期 Packaging Info: 1. 包装方式：MA UPC 优先1L 最新包装，出口美国 Remark: 2. 外箱箱唛红色和黑色双色印刷 3. 产品和包装上印刷tracking code信息，格式为ZURU常规 | AD35: Angel Lin | AE35: 0.6198 | AF35: =I35*AE35 -> 290.0664 | AG35: ZB05228-8.17 | AH35: 77772GQ1-S001 | AI35: 已入 | AJ35: 系统入单 | AK35: =I35 -> 468 | AN35: =I35 -> 468 | AU35: =I35 -> 468 | AV35: =I35*0.06 -> 28.08 | BK35: =I35/13 -> 36 | CD35: =BN35+BO35+BQ35+BS35+BR35 -> 0 | CE35: =BU35 -> 0 | CF35: =CC35 -> 0 | CG35: =BV35+BW35+BX35 -> 0
A36: 46113 | D36: ZMPO260330 | F36: ZMPO260330-10 | G36: 77772-S001 | H36: 唱片球24 pcs/箱 | I36: 3000 | J36: 0 | K36: 24 | L36: =I36/K36 -> 125 | M36: 46129 | N36: 46125 | Q36: PASS | T36: 3000 | U36: =T36-I36 -> 0 | W36: 46113 | X36: 无 | Y36: 无 | AC36: Remark：大货最新版本/款号平均/麻烦按款号装箱/并在外箱上注明款号/大货标准箱装箱/箱唛参照邮件附件 备注：收到样品订单后尽快安排 ，注意样板品质质量要求要高于大货品质要求 ，送货时必须要附带送货单(没有送货单和QC检验合格报告的仓库一律拒绝收货)，请知悉，谢谢！ | AH36: 77772-S001 | AI36: 已入 | AJ36: 系统入单 | AK36: =I36 -> 3000 | AN36: =I36 -> 3000 | AU36: =I36 -> 3000 | AV36: =I36*0.06*2 -> 360 | CD36: =BN36+BO36+BQ36+BS36+BR36 -> 0 | CE36: =BU36 -> 0 | CF36: =CC36 -> 0 | CG36: =BV36+BW36+BX36 -> 0
A37: 46080 | B37: THE ENTERTAINER | C37: 英国 | D37: 4500194581 | E37: FB14473 | F37: 4500194581-100 | G37: 77772GQ1-S002-PRODCC | H37: 唱片球13 pcs/PDQ/箱 | I37: 15496 | J37: 0 | K37: 13 | L37: =I37/K37 -> 1192 | M37: 46129 | N37: 46125 | P37: 新款请在CRD前10天寄出每款2整套大货样到罗湖办公室7B Meyya Liu 收，翻单不用寄。" | Q37: AOD | R37: 4/29 出货 | T37: =6240+9256 -> 15496 | U37: =T37-I37 -> 0 | W37: 46100 | X37: 无 | Y37: 客户EAN条码贴纸+PDQ数量贴纸 | Z37: 移除#21唱片 | AB37: 新款请在CRD前10天寄出每款2整套大货样到罗湖办公室7B Meyya Liu 收，翻单不用寄。" | AC37: 日期码格式：ZURU INC(BVI) 标准格式 日期：按实际生产日期 Packaging Info: 77772GQ1-S002-PRODCC：1L PDQ+MA A版UPC收缩膜 注意，此为去掉LOLA YANG的特殊版本。请不要出错。 Remark: "MA版本按工厂现有最新库存即可，订单出英国，请注意检查产品及包装应带UKCA以及CE图标，包装显示ZURU UK LTD信息，QC同事请查核，如有问题与跟单确认 *生产日期按实际（法定工作日），按ZURU标准格式即可 ，但是请知悉包装日期码需要早于或者等于外箱日期码 ，不能晚于外箱日期码 *请注意所有订单都需要经过ZURU QC验货并且通过后方可出货 *所有产品按符合欧洲标准走货，需要是不含微塑料版本 。 *涉及到硼的，如可选择情况下应使用低硼版本 （slime 类别低硼一般低于300ppm)，无选择的应与跟单复核再安排 。 *如果出运产品属于电子类产品需要在ZURU 包装基础上额外添加一张ZURU 标准30L通用WEEE 电子产品说明书,带电池出货的加带电池出货版本通用30L的说明书，不 带电池出货的产品用不带电池出货版本的说明书. *根据客人最新的包装要求，所有多个PDQ盒子(TQ,UQ,GQ）入1外箱的都需要在PDQ顶部右上角加上数量贴纸标明里面的数量。最小字体：36pts, 字体：Calibri（bo ld), 具体要求以及位置见文件. *订单对应客户PO号 ，备注有显示 ，注意分开做货/验货/装柜 ，混装有罚款。 * 大货样： 新款请在CRD前10天寄出每款2整套大货样到罗湖办公室7B Meyya Liu 收，翻单不用寄。" | AD37: Meyya Liu | AE37: 1.2 | AF37: =AE37*I37 -> 18595.2 | AH37: 77772GQ1-S002 | AI37: 已入 | AJ37: 系统入单 | AK37: =I37 -> 15496 | AN37: =I37 -> 15496 | AU37: =I37 -> 15496 | AV37: =I37*0.06 -> 929.76 | BK37: =I37/13 -> 1192 | CD37: =BN37+BO37+BQ37+BS37+BR37 -> 0 | CE37: =BU37 -> 0 | CF37: =CC37 -> 0 | CG37: =BV37+BW37+BX37 -> 0
A38: 46078 | B38: DISTRIBUIDORA JUGUETRON S.A. DE C.V | C38: 墨西哥 | D38: 4500194136 | E38: 50212600321 | F38: 4500194136-40 | G38: 77772GQ2-S002 | H38: 唱片球25 pcs/PDQ/箱 | I38: 10000 | J38: 0 | K38: 25 | L38: =I38/K38 -> 400 | M38: 46132 | N38: 46128 | Q38: PASS | T38: 10000 | U38: =T38-I38 -> 0 | V38: OK | W38: 46093 | X38: 有 | Y38: 4/1 进口商贴纸+UPC贴纸+外箱贴纸 | AC38: 日期码格式：ZURU INC(BVI) 标准格式 日期：按实际生产日期 Packaging Info: 77772GQ2:MA 多语包装+进口商贴纸+UPC贴纸+外箱贴纸+箱唛 Remark: 1.此单有第三方监柜，需要每款多备1套完整物料 2.外箱贴纸只要一张，位置是正唛和侧唛的交接处 | AD38: Ava Liang | AE38: 1.27 | AF38: =I38*AE38 -> 12700 | AH38: 77772GQ2-S002-3L | AI38: 已入 | AJ38: 系统入单 | AK38: =I38 -> 10000 | AP38: =I38 -> 10000 | AU38: =I38 -> 10000 | AV38: =I38*0.06 -> 600 | BO38: =I38/25 -> 400 | CD38: =BN38+BO38+BQ38+BS38+BR38 -> 400 | CE38: =BU38 -> 0 | CF38: =CC38 -> 0 | CG38: =BV38+BW38+BX38 -> 0
A39: 46080 | B39: MEIJER DISTRIBUTION, INC. | C39: 美国 | D39: 4500194435 | E39: 219021595 | G39: 77772GQ1-S002 | H39: 唱片球13 pcs/PDQ/箱 | I39: 2964 | J39: 0 | K39: 13 | L39: =I39/K39 -> 228 | M39: 46132 | N39: 46128 | Q39: PASS | T39: 2964 | U39: =T39-I39 -> 0 | V39: 无 | W39: 2/28 确认 | X39: 无 | Y39: 无 | AC39: 日期码格式：ZURU INC(BVI) 标准格式 日期： Packaging Info: 1. 产品MA UPC包装（优先1L）出美国 2. 客人指定箱唛排版 3. 77772GQ1-S002 4 mini vinyls,1 accessory Remark: 出货前 Zuru QC 验货 | AD39: Agnes Zheng | AE39: 0.72 | AF39: =I39*AE39 -> 2134.08 | AG39: ZB05284-8.17 | AH39: 77772GQ1-S002 | AI39: 已入 | AJ39: 系统入单 | AK39: =I39 -> 2964 | AN39: =I39 -> 2964 | AU39: =I39 -> 2964 | AV39: =I39*0.06 -> 177.84 | BK39: =I39/13 -> 228 | CD39: =BN39+BO39+BQ39+BS39+BR39 -> 0 | CE39: =BU39 -> 0 | CF39: =CC39 -> 0 | CG39: =BV39+BW39+BX39 -> 0
A40: 46080 | B40: MEIJER DISTRIBUTION, INC. | C40: 美国 | D40: 4500194435 | E40: 219021651 | F40: 4500194435-20 | G40: 77772GQ1-S002 | H40: 唱片球13 pcs/PDQ/箱 | I40: 1729 | J40: 0 | K40: 13 | L40: =I40/K40 -> 133 | M40: 46132 | N40: 46128 | Q40: PASS | T40: =1729 -> 1729 | U40: =T40-I40 -> 0 | V40: 无 | W40: 2/28 确认 | X40: 无 | Y40: 无 | AC40: 日期码格式：ZURU INC(BVI) 标准格式 日期： Packaging Info: 1. 产品MA UPC包装（优先1L）出美国 2. 客人指定箱唛排版 3. 77772GQ1-S002 4 mini vinyls,1 accessory Remark: 出货前 Zuru QC 验货 | AD40: Agnes Zheng | AE40: 0.72 | AF40: =I40*AE40 -> 1244.88 | AG40: ZB05284-8.17 | AH40: 77772GQ1-S002 | AI40: 已入 | AJ40: 系统入单 | AK40: =I40 -> 1729 | AN40: =I40 -> 1729 | AU40: =I40 -> 1729 | AV40: =I40*0.06 -> 103.74 | BK40: =I40/13 -> 133 | CD40: =BN40+BO40+BQ40+BS40+BR40 -> 0 | CE40: =BU40 -> 0 | CF40: =CC40 -> 0 | CG40: =BV40+BW40+BX40 -> 0
A41: 46090 | B41: TARGET US | C41: 美国 | D41: 4500195757 | E41: 10001764956-0 581 | F41: 4500195757-10 | G41: 77772GQ5-S001 | H41: 唱片球25 pcs/PDQ/箱 | I41: 80000 | J41: 0 | K41: 25 | L41: =I41/K41 -> 3200 | M41: 46132 | N41: 46128 | Q41: PASS | T41: =45825+13125+21050 -> 80000 | U41: =T41-I41 -> 0 | V41: OK | W41: 3/23确认 | X41: 有 | Y41: 3/31寄出 | AC41: 日期码格式：ZURU INC(BVI) 标准格式 日期：按实际生产日期 Packaging Info: 产品包装MA 1L 收缩膜+MA 5L 收藏指南+MA 23L 组装说明+客版PDQ Remark: 1.77772GQ5-S001-MINI BRANDS-VINYL-SERIES 1-CAPSULE,WITH DEMO,25PCS/GRAVITY PDQ,25PCS/PDQ/CTN; 2.产品包装MA 1L 收缩膜+MA 5L 收藏指南+MA 23L 组装说明+客版PDQ；客版PDQ翻单4500189603；收缩膜上的UPC显示193052090065; 4 mini vinyls(1 Target US Exclusive),1 accessory; 3. 外箱正唛左上角位置粘贴条码箱贴纸，每箱只贴一张，由ZURU订购。来料贴纸上显示的客户DPCI# 086-02-8931, UPC显示10193052090062; 4. 产品和包装上均要印刷tracking code信息，格式为ZURU常规格式; 5. 需要我司QC验货之后才能安排出货; 6. 出货方式： 货代自提 | AD41: Holly Zheng | AE41: 1.29 | AF41: =I41*AE41 -> 103200 | AG41: ZB05260/ZB05307 | AH41: 77772GQ5-S001 | AI41: 已入 | AJ41: 系统入单 | AM41: =I41 -> 80000 | AN41: =I41 -> 80000 | AU41: =I41 -> 80000 | AV41: =I41*0.06 -> 4800 | BU41: =I41/25 -> 3200 | CD41: =BN41+BO41+BQ41+BS41+BR41 -> 0 | CE41: =BU41 -> 3200 | CF41: =CC41 -> 0 | CG41: =BV41+BW41+BX41 -> 0
A42: 46092 | B42: CENTRO CUESTA NACIONAL | C42: 多米尼加共和国 | D42: 4500196119 | E42: 26-1073774JDO | F42: 4500196119-150 | G42: 77772GQ2-S001 | H42: 唱片球50 pcs/2PDQ/箱 | I42: 2500 | J42: 0 | K42: 50 | L42: =I42/K42 -> 50 | M42: 46132 | N42: 46128 | Q42: PASS | T42: 2500 | U42: =T42-I42 -> 0 | V42: OK | W42: 46100 | X42: 无 | Y42: 4/1进口商贴纸+UPC贴纸 | AC42: 日期码格式：ZURU INC(BVI) 标准格式 日期：按实际生产日期 Packaging Info: 其余item：MA 多语包装+进口商贴纸+UPC贴纸+箱唛 Remark: 1.进口商贴纸内容会显示日期码为：2026-04，包装/产品/外箱可按照ZURU标准日期码，无需跟回进口商贴纸上的日期码。 2.所有item包装上的条码必须是UPC，如果已将进口商贴纸和UPC条码合并到一张，则不需再订购UPC贴纸，仅订购一张进口商贴纸即 可。 | AD42: Grace Zhang | AE42: 1.007 | AF42: =I42*AE42 -> 2517.5 | AH42: 77772GQ2-S001-3L | AI42: 已入 | AJ42: 系统入单 | AK42: =I42 -> 2500 | AP42: =I42 -> 2500 | AU42: =I42 -> 2500 | AV42: =I42*0.06 -> 150 | BO42: =I42/25 -> 100 | CD42: =BN42+BO42+BQ42+BS42+BR42 -> 100 | CE42: =BU42 -> 0 | CF42: =CC42 -> 0 | CG42: =BV42+BW42+BX42 -> 0
A43: 46079 | B43: TARGET US | C43: 美国 | D43: 4500194297 | E43: 10001661693-3890 | F43: 4500194297-50 | G43: 77772GQ5-S001 | H43: 唱片球25 pcs/PDQ/箱 | I43: 29425 | J43: 0 | K43: 25 | L43: =I43/K43 -> 1177 | M43: 46132 | N43: 46128 | Q43: PASS | T43: =16250+13175 -> 29425 | U43: =T43-I43 -> 0 | V43: OK | W43: 3/23确认 | X43: 有 | Y43: 3/31寄出 | AC43: 日期码格式：ZURU INC(BVI) 标准格式 日期：按实际生产日期 Packaging Info: 77772GQ5：产品包装MA 1L 收缩膜+MA 5L 收藏指南+MA 23L 组装说明+客版PDQ；客版PDQ翻单4500189603； Remark: 77772GQ5： 1.77772GQ5-S001-MINI BRANDS-VINYL-SERIES 1-CAPSULE,WITH DEMO,25PCS/GRAVITY PDQ,25PCS/PDQ/CTN; 2.产品包装MA 1L 收缩膜+MA 5L 收藏指南+MA 23L 组装说明+客版PDQ；客版PDQ翻单4500189603；收缩膜上的UPC显示193052090065; 4 mini vinyls(1 Target US Exclusive),1 accessory; 3. 外箱正唛左上角位置粘贴条码箱贴纸，每箱只贴一张，由ZURU订购。来料贴纸上显示的客户DPCI# 086-02-8931, UPC显示10193052090062; 4. 外箱正唛箱唛内容右侧需贴一张EVENT LABEL，内容显示 7/19 TRANSITION TOYS Set Date 7/19/2026，由工厂自行订购； 以上Items： 1. 产品和包装上均要印刷tracking code信息，格式为ZURU常规格式； 2. 需要我司QC验货之后才能安排出货 3. 出货方式： 货代自提 | AD43: Holly Zheng | AE43: 1.29 | AF43: =I43*AE43 -> 37958.25 | AG43: ZB05445-8.17 | AH43: 77772GQ5-S001 | AI43: 已入 | AJ43: 系统入单 | AM43: =I43 -> 29425 | AN43: =I43 -> 29425 | AU43: =I43 -> 29425 | AV43: =I43*0.06 -> 1765.5 | BU43: =I43/25 -> 1177 | CD43: =BN43+BO43+BQ43+BS43+BR43 -> 0 | CE43: =BU43 -> 1177 | CF43: =CC43 -> 0 | CG43: =BV43+BW43+BX43 -> 0
A44: 46085 | B44: ASIA GOAL LIMITED | C44: 香港 | D44: 4500195223 | E44: AG250500-HK | F44: 4500195223-10 | G44: 77772GQ1-S001 | H44: 唱片球52pcs/4PDQ/箱 | I44: 780 | J44: 0 | K44: 52 | L44: =I44/K44 -> 15 | M44: 46132 | N44: 46128 | Q44: PASS | T44: 780 | U44: =T44-I44 -> 0 | V44: OK | W44: 46086 | X44: 无 | Y44: 3/24警语贴纸 | AC44: 日期码格式：ZURU INC(BVI) 标准格式 日期：按实际生产日期 Packaging Info: 此单出HK 77772GQ1: MA 1L PKG , 1L PDQ , MA 收藏指南，MA 说明书 +HK 客供警语贴纸 (1张客供警语贴纸贴球底部，1张警语贴纸贴收藏指南， 拆件说明书也需贴一张客供警语贴纸（拆件说明书贴纸和收藏指南的贴纸共用），具体参考HK客供贴纸位置图 | AD44: Chelsea Luo | AE44: 1.033 | AF44: =I44*AE44 -> 805.74 | AH44: 77772GQ1-S002 | AI44: 已入 | AJ44: 系统入单 | AK44: =I44 -> 780 | AN44: =I44 -> 780 | AU44: =I44 -> 780 | AV44: =I44*0.06 -> 46.8 | BK44: =I44/13 -> 60 | CD44: =BN44+BO44+BQ44+BS44+BR44 -> 0 | CE44: =BU44 -> 0 | CF44: =CC44 -> 0 | CG44: =BV44+BW44+BX44 -> 0
A45: 46092 | B45: CORPORACION FAVORITA C.A. | C45: 厄瓜多尔 | D45: 4500195950 | E45: 26-1073773JEC | F45: 4500195950-110 | G45: 77772GQ2-S001 | H45: 唱片球50 pcs/2PDQ/箱 | I45: 5000 | J45: 0 | K45: 50 | L45: =I45/K45 -> 100 | M45: 46132 | N45: 46128 | Q45: PASS | T45: 5000 | U45: =T45-I45 -> 0 | V45: OK | W45: 46100 | X45: 无 | Y45: 4/1进口商贴纸+UPC贴纸 | AC45: 日期码格式：ZURU INC(BVI) 标准格式 日期：按实际生产日期 Packaging Info: 其余item：MA 多语包装+进口商贴纸+UPC贴纸+箱唛 Remark: 1.进口商贴纸内容会显示日期码为：2026-04，包装/产品/外箱可按照ZURU标准日期码，无需跟回进口商贴纸上的日期码。 2.所有item包装上的条码必须是UPC，如果已将进口商贴纸和UPC条码合并到一张，则不需再订购UPC贴纸，仅订购一张进口商贴纸即 可。 | AD45: Grace Zhang | AE45: 1.007 | AF45: =I45*AE45 -> 5035 | AH45: 77772GQ2-S001 | AI45: 已入 | AJ45: 系统入单 | AK45: =I45 -> 5000 | AP45: =I45 -> 5000 | AU45: =I45 -> 5000 | AV45: =I45*0.06 -> 300 | BO45: =I45/25 -> 200 | CD45: =BN45+BO45+BQ45+BS45+BR45 -> 200 | CE45: =BU45 -> 0 | CF45: =CC45 -> 0 | CG45: =BV45+BW45+BX45 -> 0
A46: 46092 | B46: JUGUESAL S.A. DE C.V. | C46: 萨尔瓦多 | D46: 4500196056 | E46: 26-1073775JUS | F46: 4500196056-50 | G46: 77772GQ2-S001 | H46: 唱片球50 pcs/2PDQ/箱 | I46: 600 | J46: 0 | K46: 50 | L46: =I46/K46 -> 12 | M46: 46132 | N46: 46128 | Q46: PASS | T46: 600 | U46: =T46-I46 -> 0 | V46: OK | W46: 46100 | X46: 无 | Y46: 4/1进口商贴纸+UPC贴纸 | AC46: 日期码格式：ZURU INC(BVI) 标准格式 日期：按实际生产日期 Packaging Info: 其余item：MA 多语包装+进口商贴纸+UPC贴纸+箱唛 Remark: 1.进口商贴纸内容会显示日期码为：2026-04，包装/产品/外箱可按照ZURU标准日期码，无需跟回进口商贴纸上的日期码。 2.所有item包装上的条码必须是UPC，如果已将进口商贴纸和UPC条码合并到一张，则不需再订购UPC贴纸，仅订购一张进口商贴纸即 可。 | AD46: Grace Zhang | AE46: 1.007 | AF46: =I46*AE46 -> 604.2 | AH46: 77772GQ2-S001-3L | AI46: 已入 | AJ46: 系统入单 | AK46: =I46 -> 600 | AP46: =I46 -> 600 | AU46: =I46 -> 600 | AV46: =I46*0.06 -> 36 | BO46: =I46/25 -> 24 | CD46: =BN46+BO46+BQ46+BS46+BR46 -> 24 | CE46: =BU46 -> 0 | CF46: =CC46 -> 0 | CG46: =BV46+BW46+BX46 -> 0
A47: 46080 | B47: THE ENTERTAINER | C47: 英国 | D47: 4500194581 | E47: FB14535 | F47: 4500194581-70 | G47: 77772GQ1-S002-PRODCC | H47: 唱片球13 pcs/PDQ/箱 | I47: 9997 | J47: 0 | K47: 13 | L47: =I47/K47 -> 769 | M47: 46132 | N47: 46128 | P47: 新款请在CRD前10天寄出每款2整套大货样到罗湖办公室7B Meyya Liu 收，翻单不用寄。" | Q47: AOD | R47: 4/29 出货 | T47: =5707+4290 -> 9997 | U47: =T47-I47 -> 0 | W47: 46100 | X47: 无 | Y47: 客户EAN条码贴纸+PDQ数量贴纸 | Z47: 移除#21唱片 | AB47: 新款请在CRD前10天寄出每款2整套大货样到罗湖办公室7B Meyya Liu 收，翻单不用寄。" | AC47: 日期码格式：ZURU INC(BVI) 标准格式 日期：按实际生产日期 Packaging Info: 77772GQ1-S002-PRODCC：1L PDQ+MA A版UPC收缩膜 注意，此为去掉LOLA YANG的特殊版本。请不要出错。 Remark: "MA版本按工厂现有最新库存即可，订单出英国，请注意检查产品及包装应带UKCA以及CE图标，包装显示ZURU UK LTD信息，QC同事请查核，如有问题与跟单确认 *生产日期按实际（法定工作日），按ZURU标准格式即可 ，但是请知悉包装日期码需要早于或者等于外箱日期码 ，不能晚于外箱日期码 *请注意所有订单都需要经过ZURU QC验货并且通过后方可出货 *所有产品按符合欧洲标准走货，需要是不含微塑料版本 。 *涉及到硼的，如可选择情况下应使用低硼版本 （slime 类别低硼一般低于300ppm)，无选择的应与跟单复核再安排 。 *如果出运产品属于电子类产品需要在ZURU 包装基础上额外添加一张ZURU 标准30L通用WEEE 电子产品说明书,带电池出货的加带电池出货版本通用30L的说明书，不 带电池出货的产品用不带电池出货版本的说明书. *根据客人最新的包装要求，所有多个PDQ盒子(TQ,UQ,GQ）入1外箱的都需要在PDQ顶部右上角加上数量贴纸标明里面的数量。最小字体：36pts, 字体：Calibri（bo ld), 具体要求以及位置见文件. *订单对应客户PO号 ，备注有显示 ，注意分开做货/验货/装柜 ，混装有罚款。 * 大货样： 新款请在CRD前10天寄出每款2整套大货样到罗湖办公室7B Meyya Liu 收，翻单不用寄。" | AD47: Meyya Liu | AE47: 1.2 | AF47: =AE47*I47 -> 11996.4 | AH47: 77772GQ1-S002 | AI47: 已入 | AJ47: 系统入单 | AK47: =I47 -> 9997 | AN47: =I47 -> 9997 | AU47: =I47 -> 9997 | AV47: =I47*0.06 -> 599.82 | BK47: =I47/13 -> 769 | CD47: =BN47+BO47+BQ47+BS47+BR47 -> 0 | CE47: =BU47 -> 0 | CF47: =CC47 -> 0 | CG47: =BV47+BW47+BX47 -> 0
A48: 46066 | B48: ZURU GERMANY GMBH | C48: 德国 | D48: 4500193875 | E48: 5200008771 | F48: 4500193875-40 | G48: 77772GQ1-S002-MTS | H48: 唱片球13 pcs/PDQ/箱 | I48: 9607 | J48: 0 | K48: 13 | L48: =I48/K48 -> 739 | M48: 46132 | N48: 46128 | Q48: AOD | T48: =9607 -> 9607 | U48: =T48-I48 -> 0 | V48: OK | W48: 46098 | X48: 无 | Y48: 多语警语折叠贴纸 | AC48: 日期码格式：ZURU INC(BVI) 标准格式 日期：按实际生产日期 Packaging Info: 77772GQ1: MA 3L PDQ+MA 3L EAN收缩膜+1*多语警语折叠贴纸 Remark: 1.德国内销单，需要通过ZURU 验货结果后才能出货 (工厂需要主动提前同ZURU QC预约验货避免延期出货造成不必要麻烦)； 2.产品如含有化学品（slime 等），需要无硼无香。需要无微塑料版本。 3.所有出口欧洲的产品, 法规规定禁止在包装和共公众用的印刷品中使用矿物油中含有的物质, 包装印刷油墨中含有的MOAH/MOSH的质量浓度不能超过1%, 否则出货 到法国被抽检出现问题, 供应商需要对此负责; 4. date code: 外箱日期码要晚于或等于产品日期码，不能早于产品的日期码； 5. 所有出往德国的电子产品身上需要加字唛，为ZURU FRANCE 地址，需跟包装上的地址一致 (如无电子产品，产品布标有此地址，或产品太小无法增加可忽略此信 息。如产品无法加字唛，需让对应跟单提供产品贴纸资料) 新地址：ZURU France 33 rue Paul Meurice 75020 Paris, France 旧地址：ZURU France 1/3, Rue d'Argenteuil 95210 SAINT-GRATIEN, FRANCE 6.所有出往德国订单的电子产品需增加一张最新版本的欧洲通用WEEE声明说明书，区分带电池和不带电池版本, 如已做客版说明书可忽略此要求。 7.装柜时需要按照款式号码从小到大一款款依次装,避免终端仓库卸货混乱.若一个柜子涉及到几个不同国家内销单,装柜时需要一个国家装完后再装另一个国家的 产品,依次装柜,避免终端仓库因不同国家不同库位位置卸货混乱. (此点需要同工厂装柜人员强调)" 8.ratio 同MA 9. 若有特定款有特殊外箱条码要求时,需要明确列出产品款对应的具体外箱条码号码/条码类型 (若无,可以忽略此需求). | AD48: Niki Chen | AE48: 2.02 | AF48: =I48*AE48 -> 19406.14 | AH48: 77772GQ1-S002-3L | AI48: 已入 | AJ48: 系统入单 | AK48: =I48 -> 9607 | AP48: =I48 -> 9607 | AU48: =I48 -> 9607 | AV48: =I48*0.06 -> 576.42 | BL48: =I48/13 -> 739 | CD48: =BN48+BO48+BQ48+BS48+BR48 -> 0 | CE48: =BU48 -> 0 | CF48: =CC48 -> 0 | CG48: =BV48+BW48+BX48 -> 0
A49: 46091 | B49: B&M RETAIL LIMITED | C49: 英国 | D49: 4500195602 | E49: 02437256/1 | F49: 4500195602-110 | G49: 77772GQ2-S002-PRODCC | H49: 唱片球25 pcs/PDQ/箱 | I49: 17500 | J49: 0 | K49: 25 | L49: =I49/K49 -> 700 | M49: 46132 | N49: 46128 | Q49: AOD | T49: 17500 | U49: =T49-I49 -> 0 | V49: 无 | W49: 3/11确认 | X49: 无 | Y49: 无 | Z49: 移除#21唱片 | AC49: 日期码格式：ZURU INC(BVI) 标准格式 日期：按实际生产日期 Packaging Info: *MA UPC版本按工厂现有最新库存即可，订单出英国，请注意检查产品及包装应带UKCA图标，包装显示ZURU UK LTD信息，QC同事请查核，如有问题与跟单确认。 *生产日期按实际（法定工作日），按ZURU标准格式即可 ，但是请知悉包装日期码需要早于或者等于外箱日期码 ，不能晚于外箱日期码 *请注意所有订单都需要经过ZURU QC验货并且通过后方可出货 *条码以订单显示为准 ，请安排生产前先核对 ，有问题请提出。 *所有产品按符合欧洲标准走货，需要是不含微塑料版本 。 *涉及到硼的，如可选择情况下应使用低硼版本 （slime 类别低硼一般低于300ppm)，无选择的应与跟单复核再安排 。 *大货完成后请及时提供shipment images 供客户批复 ，如未提供照片就直接走柜，有问题由工厂负责 。 *最终出货工厂需要按船务要求为集装箱挂网，如不按要求挂网导致罚款由工厂承担 。 Remark: 9548/9574:WEEE_不带电池走货 _ 说明书欧洲EN+29L_C版 25282/9561/77772GQ2:WEEE_带电池走货 _ 说明书欧洲EN+29L_C版 77772GQ2: 72 此客制款需移除Lola Young vinyl，如做错货导致罚款会由工厂负全责 77711GQ2-S002-INT: MA B版 5L EAN版收缩膜+UPC条码贴纸 | AD49: Ann Zhang | AE49: 1.27 | AF49: =I49*AE49 -> 22225 | AH49: 77772GQ2-S002 | AI49: 已入 | AJ49: 系统入单 | AK49: =I49 -> 17500 | AN49: =I49 -> 17500 | AU49: =I49 -> 17500 | AV49: =I49*0.06 -> 1050 | BN49: =I49/25 -> 700 | CD49: =BN49+BO49+BQ49+BS49+BR49 -> 700 | CE49: =BU49 -> 0 | CF49: =CC49 -> 0 | CG49: =BV49+BW49+BX49 -> 0
A50: 46091 | B50: SMYTHS TOYS EU HQ UC | C50: 德国 | D50: 4500196046 | E50: 4400549000 | F50: 4500196046-10 | G50: 77772GQ2-S001-PRODCC | H50: 唱片球50 pcs/2PDQ/箱 | I50: 1000 | J50: 0 | K50: 50 | L50: =I50/K50 -> 20 | M50: 46132 | N50: 46128 | Q50: AOD | T50: 1000 | U50: =T50-I50 -> 0 | V50: 无 | W50: 46097 | X50: 无 | Y50: 无 | Z50: 移除#21唱片 | AC50: 日期码格式：ZURU INC(BVI) 标准格式 日期：按实际生产日期 Packaging Info: 77772GQ2: MA PDQ (优先多语)+MA 3L-EAN收缩膜+1张含德语callout/德意荷警语/法国sorting label贴纸(本单放稿) EAN#4894680051133 *必须移除Messy Lola Young (VINYL-S1-021) 这个唱片, 比例按PM更新的安排, 如未按要求做货被客罚由工厂承担责任* *外箱需加一张UN3481锂电池运输标签* Remark: Smyths 德国 1. 请准时出货，推期会有罚款； 2. 所有产品按符合欧洲标准走货，需要是不含微塑料版本。 3. 所有电子产品身上需要加字唛，为ZURU FRANCE 地址 (如无电子产品，产品布标有此地址，或产品太小无法增加可忽略此信息)，新地址ZURU FRANCE.33 rue Pa ul Meurice 75020 Paris, France. 4. 电子产品需增加一张C版WEEE声明29L通用黑白说明书(不接受A版本，翻译有误)，区分带电池和不带电池出货版本, 如已做客版说明书可忽略此要求；如包装备注 上缺少此部分信息，请提醒跟单更新备注。 5.所有出往德国市场有关slime和带香味的都需要出无硼无香版本； 6.订单备注显示有分批的(不同仓库/订单号), 一定要区分客户订单号做货出货，否则会导致罚款 。 7.包装日期码按ZURU格式即可，请确保不迟于外箱日期码，可等于或者早于外箱日期码，必须为法定工作日。 8.做货前请先复核包装条码与订单是否一致再安排，对不上的需与ZURU跟单确认再安排。 9.包装必须含法国回收标(Sorting Label)，如没有，请提醒跟单提供贴纸资料。 | AD50: Sherry Lu | AE50: 1.007 | AF50: =I50*AE50 -> 1007 | AH50: 77772GQ2-S001-3L | AI50: 已入 | AJ50: 系统入单 | AK50: =I50 -> 1000 | AP50: =I50 -> 1000 | AU50: =I50 -> 1000 | AV50: =I50*0.06 -> 60 | BO50: =I50/25 -> 40 | CD50: =BN50+BO50+BQ50+BS50+BR50 -> 40 | CE50: =BU50 -> 0 | CF50: =CC50 -> 0 | CG50: =BV50+BW50+BX50 -> 0
A51: 46087 | B51: WALMART INC. | C51: 美国 | D51: 4500195546 | E51: 0983717904 | F51: 4500195546-10 | G51: 77772SLB-S001 | H51: 唱片球16pcs/PDQ/箱/60箱打卡板 | I51: 17280 | J51: 0 | K51: 960 | L51: =I51/K51 -> 18 | M51: 46135 | N51: 46132 | P51: 4/23抽办1728 pcs | Q51: PASS | T51: 17280 | U51: =T51-I51 -> 0 | V51: OK | W51: 46087 | X51: 无 | Y51: 每pcs产品上要贴1张RFID贴纸，贴纸由ZURU提供，贴纸位置请严格按照我们签回的签板； | AC51: 日期码格式：ZURU DGYYYYMMDD CHINA(日期避开周末和法定节假日即可） 日期：按实际生产日期 Packaging Info: 77772SLB-S001 1.包装要求： MA 1L A版收缩膜+MA 5L A版收藏指南+MA 23L A版说明书+MA A版纸袋+客版1L PDQ 每pcs产品上要贴1张RFID贴纸，贴纸由ZURU提供，贴纸位置请严格按照我们签回的签板； Remark: 77772SLB-S001 1.包装要求： MA 1L A版收缩膜+MA 5L A版收藏指南+MA 23L A版说明书+MA A版纸袋+客版1L PDQ 每pcs产品上要贴1张RFID贴纸，贴纸由ZURU提供，贴纸位置请严格按照我们签回的签板； 2. 外箱印刷带条码的RFID箱唛：RFID紫色色带+WM Dept.图标+RFID图标+ITF-14条码，四面右下角印刷ZURU logo, ITFF条码只印刷在正唛一面，在加印的时候确保 条形码能扫描出来，外箱侧面任一角落加印："MADE IN CHINA" 字样； 3. 在产品上和包装上要有日期码、以及要有MADE IN CHINA和ZURU字样； 4. 产品如有扎带口要剪平，不能刮手。 5. 此单需要抽板和验货，请多备料，预计抽板时间4/23 6. 此单以Slip sheet出货，16pcs/PDQ/CTN，960pcs/60CTNS/Slip sheet | AD51: Maggie Xie | AE51: 645.1439 | AF51: =AE51*L51 -> 11612.59 | AG51: ZB06039-8.17 | AH51: 77772SLB-S001-1L | AI51: 已入 | AJ51: 系统入单 | AK51: =I51 -> 17280 | AN51: =I51 -> 17280 | AU51: =I51 -> 17280 | AV51: =I51*0.06 -> 1036.8 | BR51: =I51/16 -> 1080 | CD51: =BN51+BO51+BQ51+BS51+BR51 -> 1080 | CE51: =BU51 -> 0 | CF51: =CC51 -> 0 | CG51: =BV51+BW51+BX51 -> 0
A52: 46094 | B52: ZURU NEW ZEALAND LIMITED | C52: 新西兰 | D52: 4500196745 | E52: 5200009279 | F52: 4500196745-60 | G52: 77772GQ2-S001-FS-PRODCC1 | H52: 唱片球50 pcs/2PDQ/箱 | I52: 750 | J52: 0 | K52: 50 | L52: =I52/K52 -> 15 | M52: 46136 | N52: 46132 | Q52: PASS | T52: 750 | U52: =T52-I52 -> 0 | W52: 46099 | X52: 有 | Y52: fast start专用UPC贴纸+贴一张黄色A4纸，印"fast s tart"内容。（两张贴纸及位置图翻单4500190798) | Z52: 取消21/23号唱片 | AC52: 日期码格式：ZURU INC(BVI) 标准格式 日期：按实际生产日期 Packaging Info: 77772GQ2:MA英语UPC版本包装（收缩膜和说明书, MA首选1L，如无1L可用多语且含英语的配套多语包装) ++两张覆盖PDQ上唱片的贴纸+两张覆盖收藏指南上唱片的贴 纸+一张覆盖PDQ上数字"45"的贴纸+一张覆盖收藏指南上数字"45"的贴纸+ 1张fast start条码贴纸+贴一张印"fast start"内容黄色A4纸，。（两张贴纸及位置图翻 单4500190798)+箱唛 配比信息：4 mini vinyls,1 accessory Removed了 ""Messy & Delicious""两张唱片 Remark: 1.请务必按时完货，验货。并且按期送货入货代指定仓库，如果晚了导致船期Delay将会有罚金产生或者客户要求空运，所产生的罚金和空运费由工厂承担。 2.外箱材质为ZURU标准； 3.此单需使用KMART封箱胶上下工字型封箱;从2019年6月开始，要用KMART 新版封箱胶带，此单要用"ANKO"封箱胶带 4.此单出口新西兰，请按相应的澳新标准生产； 5.产品和包装上生产批号的显示格式ZURU标准日期码格式 6.外箱信息不可手写，重量和体积需要与实际的一致(不可手写） 7. 实际外箱重量跟印在箱唛上的数据差异不能超3%，尺寸按实际数据印刷 77772CRD4/24需完货并完成ZURU验货可以安排当天交仓 | AD52: Louise Lu | AE52: 1.007 | AF52: =I52*AE52 -> 755.25 | AH52: 77772GQ2-S001 | AI52: 已入 | AJ52: 系统入单 | AK52: =I52 -> 750 | AN52: =I52 -> 750 | AU52: =I52 -> 750 | AV52: =I52*0.06 -> 45 | BN52: =I52/25 -> 30 | CD52: =BN52+BO52+BQ52+BS52+BR52 -> 30 | CE52: =BU52 -> 0 | CF52: =CC52 -> 0 | CG52: =BV52+BW52+BX52 -> 0
A53: 46079 | B53: TARGET US | C53: 美国 | D53: 4500194290 | E53: 10001708292-0 581 | F53: 4500194290-30 | G53: 77772GQ5-S001 | H53: 唱片球25 pcs/PDQ/箱 | I53: 4500 | J53: 0 | K53: 25 | L53: =I53/K53 -> 180 | M53: 46136 | N53: 46132 | Q53: PASS | T53: 4500 | U53: =T53-I53 -> 0 | V53: OK | W53: 3/26确认 | X53: 有 | Y53: 4/2寄出 | AC53: 日期码格式：ZURU INC(BVI) 标准格式 日期：按实际生产日期 Packaging Info: 77772GQ5：产品包装MA 1L 收缩膜+MA 5L 收藏指南+MA 23L 组装说明+客版PDQ；客版PDQ翻单4500189603； Remark: 77772GQ5： 1.77772GQ5-S001-MINI BRANDS-VINYL-SERIES 1-CAPSULE,WITH DEMO,25PCS/GRAVITY PDQ,25PCS/PDQ/CTN; 2.产品包装MA 1L 收缩膜+MA 5L 收藏指南+MA 23L 组装说明+客版PDQ；客版PDQ翻单4500189603；收缩膜上的UPC显示193052090065; 4 mini vinyls(1 Target US Exclusive),1 accessory; 3. 外箱正唛左上角位置粘贴条码箱贴纸，每箱只贴一张，由ZURU订购。来料贴纸上显示的客户DPCI# 086-02-8931, UPC显示10193052090062; 以上Items： 1. 产品和包装上均要印刷tracking code信息，格式为ZURU常规格式； 2. 需要我司QC验货之后才能安排出货 3. 出货方式： 货代自提 | AD53: Holly Zheng | AE53: 1.29 | AF53: =I53*AE53 -> 5805 | AG53: ZB05479-8.17 | AH53: 77772GQ5-S001 | AI53: 已入 | AJ53: 系统入单 | AM53: =I53 -> 4500 | AN53: =I53 -> 4500 | AU53: =I53 -> 4500 | AV53: =I53*0.06 -> 270 | BU53: =I53/25 -> 180 | CD53: =BN53+BO53+BQ53+BS53+BR53 -> 0 | CE53: =BU53 -> 180 | CF53: =CC53 -> 0 | CG53: =BV53+BW53+BX53 -> 0
A54: 46084 | B54: FELYX TOYS | C54: 保加利亚 | D54: 4500194955 | F54: 4500194955-10 | G54: 77772GQ1-S001 | H54: 唱片球52pcs/4PDQ/箱 | I54: 624 | J54: 0 | K54: 52 | L54: =I54/K54 -> 12 | M54: 46136 | N54: 46132 | Q54: PASS | T54: 624 | U54: =T54-I54 -> 0 | V54: OK | W54: 3/3 确认 | X54: 无 | Y54: 3/23进口商贴纸+C 版 29L 不带电池走货通用WEEE说明书 | AC54: 日期码格式：ZURU INC(BVI) 标准格式 日期：按实际生产日期 Packaging Info: 77772GQ1：A 版1L MA 收缩膜+进口商贴纸；A 版 5L MA 收藏指南/A 版 23L 组装说明书/A 版 MA PDQ/C 版 29L 不带电池走货通用WEEE说明书 Remark: "1、所有item 均用MA UPC 条码，若包装不是UPC 条码的请告知 2、此单出欧洲需满足EU测试标准要求 3、此单LC 货期不可延 3、电池产品需要使用通用版本WEEE说明书" | AD54: Snowy Wu | AE54: 1.033 | AF54: =AE54*I54 -> 644.592 | AH54: 77772GQ1-S001 | AI54: 已入 | AJ54: 系统入单 | AK54: =I54 -> 624 | AN54: =I54 -> 624 | AU54: =I54 -> 624 | AV54: =I54*0.06 -> 37.44 | BK54: =I54/13 -> 48 | CD54: =BN54+BO54+BQ54+BS54+BR54 -> 0 | CE54: =BU54 -> 0 | CF54: =CC54 -> 0 | CG54: =BV54+BW54+BX54 -> 0
A55: 46084 | B55: FELYX TOYS | C55: 保加利亚 | D55: 4500194955 | F55: 4500194955-20 | G55: 77772GQ2-S001 | H55: 唱片球50 pcs/2PDQ/箱 | I55: 750 | J55: 0 | K55: 50 | L55: =I55/K55 -> 15 | M55: 46136 | N55: 46132 | Q55: PASS | T55: 750 | U55: =T55-I55 -> 0 | V55: OK | W55: 3/3 确认 | X55: 无 | Y55: 3/23进口商贴纸+C 版 29L 不带电池走货通用WEEE说明书 | AC55: 日期码格式：ZURU INC(BVI) 标准格式 日期：按实际生产日期 Packaging Info: 77772GQ2：A 版1L MA 收缩膜+进口商贴纸；A 版 5L MA 收藏指南/A 版 23L 组装说明书/A 版 MA PDQ/C 版 29L 不带电池走货通用WEEE说明书 Remark: "1、所有item 均用MA UPC 条码，若包装不是UPC 条码的请告知 2、此单出欧洲需满足EU测试标准要求 3、此单LC 货期不可延 3、电池产品需要使用通用版本WEEE说明书" | AD55: Snowy Wu | AE55: 1.007 | AF55: =AE55*I55 -> 755.25 | AH55: 77772GQ2-S001 | AI55: 已入 | AJ55: 系统入单 | AK55: =I55 -> 750 | AN55: =I55 -> 750 | AU55: =I55 -> 750 | AV55: =I55*0.06 -> 45 | BN55: =I55/25 -> 30 | CD55: =BN55+BO55+BQ55+BS55+BR55 -> 30 | CE55: =BU55 -> 0 | CF55: =CC55 -> 0 | CG55: =BV55+BW55+BX55 -> 0
A56: 46090 | B56: WAL-MART CANADA CORP. | C56: 加拿大 | D56: 4500195369 | E56: 7000991882 | F56: 4500195369-30 | G56: 77772GQ3-S001 | H56: 唱片球16pcs/PDQ/箱 | I56: 6480 | J56: 0 | K56: 16 | L56: =I56/K56 -> 405 | M56: 46136 | N56: 46132 | P56: 4/27第三方验货，抽办50% | Q56: PASS | T56: 6480 | U56: =T56-I56 -> 0 | W56: 46098 | X56: 无 | Y56: 无 | AC56: 日期码格式：ZURU INC(BVI) 标准格式 日期：按实际生产日期 Packaging Info: #77772 客版3LPDQ(16装)+客版3L收缩膜(UPC:193052090065)+MA5L收藏指南+MA23L拼装说明书+MA5L复合袋+DEMO纸卡 Remark: 1. 此单有箱唛; 2. UPC贴纸：必须在原来错误的条码上用黑色粗头笔涂黑直至不能扫描，再贴上正确的UPC; 3. 此单有第三方验货，烦请多备包装物料； 4. #77794带锂电池出货，使用英法双语电池，外箱需在正唛空白位置贴一张UN3481锂电池标识贴纸； 5. 需4/17前安排签样，签样要求如下： #77772：大货样3PCS+3套齐套散件+空PDQ2PCS； 6.需安排4/24抽板测试，抽板要求如下： #77772：大货4PCS+4套完整散件； ********************* a. 请确保产品符合1999年版本的加拿大环境保护法(CEPA)和2012年禁止某些有毒物质法规的要求。该产品不含任何在加拿大禁用的化学物质，包括但不限于有毒物 质清单中列出的化学物质，并且在为加拿大沃尔玛生产产品期间没有使用任何禁用化学物质。 Supplier certify that the products comply with the requirements of Canadian Environmental Protection Act, 1999 (CEPA), Prohibition of Certain To xic Substances Regulations, 2012. The products do not contain any chemicals that are banned in Canada, including but not limited to those listed in the Toxic Substances List and no banned chemicals were used during the manufacturing of product for Walmart Canada. 附件列表： (1) Letter of Guarantee for Canada banned chemicals - (1-5CA) b. 请确保产品在均质材料中的汞浓度不超过0.1%（按重量计）。 Supplier certify that the WAL-MART vendor products does not have a mercury concentration of more than 0.1% by weight in homogeneous material. 附件列表： (1) Letter of Guarantee for Mercury COC c. 请确保产品的塑料材料不含以下物质（SOR 2011-17 27B): Supplier certify that the plastic materials do not contain the following substances(SOR 2011-17 27B): (a) carbon tetrachloride or any substance that contains it; (b) methyl alcohol or any substance thay contains >1.0%; (c) petroleum distillates or any substance that contains >10% weight to volume of petroleum distillates; (d) benzene; (e) turpentine or any substance that contains >10% weight to volume of turpentine; (f) boric acid or salts of boric acid; or (g) ethyl ether. 附件列表： (1) Letter of Guarantee for WM CA-Other prohibited substances in plastic(less than 3 years) | AD56: Fly Song | AE56: 1.3 | AF56: =AE56*I56 -> 8424 | AH56: 77772GQ3-S001-客版 | AI56: 已入 | AJ56: 系统入单 | AK56: =I56 -> 6480 | AS56: =I56 -> 6480 | AU56: =I56 -> 6480 | AV56: =I56*0.06 -> 388.8 | BS56: =I56/16 -> 405 | CD56: =BN56+BO56+BQ56+BS56+BR56 -> 405 | CE56: =BU56 -> 0 | CF56: =CC56 -> 0 | CG56: =BV56+BW56+BX56 -> 0
A57: 46090 | B57: AMAZON.COM SERVICES LLC | C57: 美国 | D57: 4500195252 | E57: 2DBDSTII | F57: 4500195252-180 | G57: 77876-S001 | H57: 唱片球2PK圆筒装 | I57: 9012 | J57: 0 | K57: 12 | L57: =I57/K57 -> 751 | M57: 46136 | N57: 46132 | Q57: AOD | T57: 9012 | U57: =T57-I57 -> 0 | V57: OK | W57: 46090 | X57: 有 | Y57: 4/7SSCC Label | AC57: 日期码格式：ZURU INC(BVI) 标准格式 日期：按实际生产日期 Packaging Info: #77876:2PK MA 1L UPC版#77772入PVC桶，3L无UPC客版收缩膜，客版收缩膜和3L铜版纸图稿翻单4500192514.（两个球的配比不能重复）。2544PCS由Domestic PO450 0192506转单,6468PCS由Domestic PO4500192514转单。 Remark: 1. Amazon MDDP订单，出口US。 2. 日期码使用ZURU标准版本。 3. 如果大货有要求入邮包盒，则对应的邮包盒上面要打上日期码。 4. 箱尺寸要求：外箱最长边不能超过25"(超过了，case pack只能为1)，不符合要求的大货，一律不接受。 5. 外箱箱唛要求： ①外箱正面印ZURU Logo+SSCC Label(客供贴纸，由跟单订购)。关于 SSCC Label 请注意： SSCC Label显示的是客人自己的item#。每一张SSCC label都是唯一且有不同流水及条码的，没有损耗，绝对不可贴错。如果贴错或损坏任何一张，都会导致全部都 错，千万要注意！SSCC Label必须贴在外箱正面的正中间位置(贴一面即可)，并且贴纸离外箱边距必须至少3cm(可以覆盖Logo<(>&<)>箱唛)，否则会影响到客户那边 仓库的扫描识别。 ②外箱侧面印item#(订单上显示的SKU#)+carton size(以工厂实际尺寸为准，单位: inch)+MADE IN CHINA，日期使用ZURU 标准版本。 6. 装柜要求：按照客户PO#装柜/箱号顺序装柜，跟单会提前给到装柜计划。 在大货生产/仓库存放时，请留意该装柜要求，以便装柜时不混乱(避免装错/装漏/找不到货号等)。 | AD57: Kelly Shen/Mia Pan/P | AE57: 1.374 | AF57: =AE57*I57 -> 12382.488 | AG57: ZB05681-8.17 | AH57: 77876-S001 | AI57: 已入 | AJ57: 系统入单 | AK57: =I57*2 -> 18024 | AQ57: =I57*2 -> 18024 | AU57: =I57*2 -> 18024 | AV57: =I57*0.06*2 -> 1081.44 | CD57: =BN57+BO57+BQ57+BS57+BR57 -> 0 | CE57: =BU57 -> 0 | CF57: =CC57 -> 0 | CG57: =BV57+BW57+BX57 -> 0 | CJ57: =I57 -> 9012 | CK57: =I57 -> 9012 | CL57: =I57 -> 9012
A58: 46090 | B58: AMAZON.COM SERVICES LLC | C58: 美国 | D58: 4500195266 | E58: 1EG43BFL | F58: 4500195266-190 | G58: 77876-S001 | H58: 唱片球2PK圆筒装 | I58: 7116 | J58: 0 | K58: 12 | L58: =I58/K58 -> 593 | M58: 46136 | N58: 46132 | Q58: AOD | T58: 7116 | U58: =T58-I58 -> 0 | V58: OK | W58: 46090 | X58: 有 | Y58: 4/7SSCC Label | AC58: 日期码格式：ZURU INC(BVI) 标准格式 日期：按实际生产日期 Packaging Info: #77876:2PK MA 1L UPC版#77772入PVC桶，3L无UPC客版收缩膜，客版收缩膜和3L铜版纸图稿翻单4500192514.（两个球的配比不能重复）。7116PCS由Domestic PO450 0192521转单。 Remark: 1. Amazon MDDP订单，出口US。 2. 日期码使用ZURU标准版本。 3. 如果大货有要求入邮包盒，则对应的邮包盒上面要打上日期码。 4. 箱尺寸要求：外箱最长边不能超过25"(超过了，case pack只能为1)，不符合要求的大货，一律不接受。 5. 外箱箱唛要求： ①外箱正面印ZURU Logo+SSCC Label(客供贴纸，由跟单订购)。关于 SSCC Label 请注意： SSCC Label显示的是客人自己的item#。每一张SSCC label都是唯一且有不同流水及条码的，没有损耗，绝对不可贴错。如果贴错或损坏任何一张，都会导致全部都 错，千万要注意！SSCC Label必须贴在外箱正面的正中间位置(贴一面即可)，并且贴纸离外箱边距必须至少3cm(可以覆盖Logo<(>&<)>箱唛)，否则会影响到客户那边 仓库的扫描识别。 ②外箱侧面印item#(订单上显示的SKU#)+carton size(以工厂实际尺寸为准，单位: inch)+MADE IN CHINA，日期使用ZURU 标准版本。 6. 装柜要求：按照客户PO#装柜/箱号顺序装柜，跟单会提前给到装柜计划。 在大货生产/仓库存放时，请留意该装柜要求，以便装柜时不混乱(避免装错/装漏/找不到货号等)。 | AD58: Kelly Shen/Mia Pan/P | AE58: 1.374 | AF58: =AE58*I58 -> 9777.384 | AG58: ZB05684-8.17 | AH58: 77876-S001 | AI58: 已入 | AJ58: 系统入单 | AK58: =I58*2 -> 14232 | AQ58: =I58*2 -> 14232 | AU58: =I58*2 -> 14232 | AV58: =I58*0.06*2 -> 853.92 | CD58: =BN58+BO58+BQ58+BS58+BR58 -> 0 | CE58: =BU58 -> 0 | CF58: =CC58 -> 0 | CG58: =BV58+BW58+BX58 -> 0 | CJ58: =I58 -> 7116 | CK58: =I58 -> 7116 | CL58: =I58 -> 7116
A59: 46090 | B59: AMAZON.COM SERVICES LLC | C59: 美国 | D59: 4500195258 | E59: 5PY83HFO | F59: 4500195258-170 | G59: 77876-S001 | H59: 唱片球2PK圆筒装 | I59: 7464 | J59: 0 | K59: 12 | L59: =I59/K59 -> 622 | M59: 46136 | N59: 46132 | Q59: AOD | T59: 7464 | U59: =T59-I59 -> 0 | V59: OK | W59: 46090 | X59: 有 | Y59: 4/7SSCC Label | AC59: 日期码格式：ZURU INC(BVI) 标准格式 日期：按实际生产日期 Packaging Info: #77876:2PK MA 1L UPC版#77772入PVC桶，3L无UPC客版收缩膜，客版收缩膜和3L铜版纸图稿翻单4500192514.（两个球的配比不能重复）。 7464PCS由Domestic PO45 00192506转单。 Remark: 1. Amazon MDDP订单，出口US。 2. 日期码使用ZURU标准版本。 3. 如果大货有要求入邮包盒，则对应的邮包盒上面要打上日期码。 4. 箱尺寸要求：外箱最长边不能超过25"(超过了，case pack只能为1)，不符合要求的大货，一律不接受。 5. 外箱箱唛要求： ①外箱正面印ZURU Logo+SSCC Label(客供贴纸，由跟单订购)。关于 SSCC Label 请注意： SSCC Label显示的是客人自己的item#。每一张SSCC label都是唯一且有不同流水及条码的，没有损耗，绝对不可贴错。如果贴错或损坏任何一张，都会导致全部都 错，千万要注意！SSCC Label必须贴在外箱正面的正中间位置(贴一面即可)，并且贴纸离外箱边距必须至少3cm(可以覆盖Logo<(>&<)>箱唛)，否则会影响到客户那边 仓库的扫描识别。 ②外箱侧面印item#(订单上显示的SKU#)+carton size(以工厂实际尺寸为准，单位: inch)+MADE IN CHINA，日期使用ZURU 标准版本。 6. 装柜要求：按照客户PO#装柜/箱号顺序装柜，跟单会提前给到装柜计划。 在大货生产/仓库存放时，请留意该装柜要求，以便装柜时不混乱(避免装错/装漏/找不到货号等)。 | AD59: Kelly Shen/Mia Pan/P | AE59: 1.374 | AF59: =AE59*I59 -> 10255.536 | AG59: ZB05679-8.17 | AH59: 77876-S001 | AI59: 已入 | AJ59: 系统入单 | AK59: =I59*2 -> 14928 | AQ59: =I59*2 -> 14928 | AU59: =I59*2 -> 14928 | AV59: =I59*0.06*2 -> 895.68 | CD59: =BN59+BO59+BQ59+BS59+BR59 -> 0 | CE59: =BU59 -> 0 | CF59: =CC59 -> 0 | CG59: =BV59+BW59+BX59 -> 0 | CJ59: =I59 -> 7464 | CK59: =I59 -> 7464 | CL59: =I59 -> 7464
A60: 46051 | B60: AMAZON.COM SERVICES LLC | C60: 美国 | D60: 4500195261 | E60: 2NHI8Q6O | F60: 4500195261-170 | G60: 77876-S001 | H60: 唱片球2PK圆筒装 | I60: 9156 | J60: 0 | K60: 12 | L60: =I60/K60 -> 763 | M60: 46136 | N60: =M60-4 -> 46132 | P60: PO4500195261中#77867-9156PCS由Domestic PO4500192514转单 | Q60: AOD | T60: 9156 | U60: =T60-I60 -> 0 | V60: OK | W60: 46051 | X60: 有 | Y60: 4/7SSCC Label | AC60: 日期码格式：ZURU INC(BVI) 标准格式 日期：按实际生产日期 Packaging Info: #77876:2PK MA 1L UPC版#77772入PVC桶，3L无UPC客版收缩膜，客版收缩膜和3L铜版纸图稿翻单4500192514.（两个球的配比不能重复）。9156PCS由Domestic PO450 0192514转单。 Remark: 1. Amazon MDDP订单，出口US。 2. 日期码使用ZURU标准版本。 3. 如果大货有要求入邮包盒，则对应的邮包盒上面要打上日期码。 4. 箱尺寸要求：外箱最长边不能超过25"(超过了，case pack只能为1)，不符合要求的大货，一律不接受。 5. 外箱箱唛要求： ①外箱正面印ZURU Logo+SSCC Label(客供贴纸，由跟单订购)。关于 SSCC Label 请注意： SSCC Label显示的是客人自己的item#。每一张SSCC label都是唯一且有不同流水及条码的，没有损耗，绝对不可贴错。如果贴错或损坏任何一张，都会导致全部都 错，千万要注意！SSCC Label必须贴在外箱正面的正中间位置(贴一面即可)，并且贴纸离外箱边距必须至少3cm(可以覆盖Logo<(>&<)>箱唛)，否则会影响到客户那边 仓库的扫描识别。 ②外箱侧面印item#(订单上显示的SKU#)+carton size(以工厂实际尺寸为准，单位: inch)+MADE IN CHINA，日期使用ZURU 标准版本。 6. 装柜要求：按照客户PO#装柜/箱号顺序装柜，跟单会提前给到装柜计划。 在大货生产/仓库存放时，请留意该装柜要求，以便装柜时不混乱(避免装错/装漏/找不到货号等)。 | AD60: Kelly Shen/Mia Pan/P | AE60: 1.374 | AF60: =I60*AE60 -> 12580.344 | AG60: ZB05699-8.17 | AH60: 77876-S001 | AI60: 已入 | AJ60: 系统入单 | AK60: =I60*2 -> 18312 | AQ60: =I60*2 -> 18312 | AU60: =I60*2 -> 18312 | AV60: =I60*0.06*2 -> 1098.72 | CD60: =BN60+BO60+BQ60+BS60+BR60 -> 0 | CE60: =BU60 -> 0 | CF60: =CC60 -> 0 | CG60: =BV60+BW60+BX60 -> 0 | CJ60: =I60 -> 9156 | CK60: =I60 -> 9156 | CL60: =I60 -> 9156
A61: 46051 | B61: AMAZON.COM SERVICES LLC | C61: 美国 | D61: 4500195264 | E61: 2XYIKTEU | F61: 4500195264-160 | G61: 77876-S001 | H61: 唱片球2PK圆筒装 | I61: 7248 | J61: 0 | K61: 12 | L61: =I61/K61 -> 604 | M61: 46136 | N61: =M61-4 -> 46132 | P61: PO4500195264中#77876-4392PCS由Domestic PO4500192514转单，2856PCS由Domestic PO4500192521转单。 | Q61: AOD | T61: 7248 | U61: =T61-I61 -> 0 | V61: OK | W61: 46051 | X61: 有 | Y61: 4/7SSCC Label | AC61: 日期码格式：ZURU INC(BVI) 标准格式 日期：按实际生产日期 Packaging Info: #77876:2PK MA 1L UPC版#77772入PVC桶，3L无UPC客版收缩膜，客版收缩膜和3L铜版纸图稿翻单4500192514.（两个球的配比不能重复）。4392PCS由Domestic PO450 0192514转单，2856PCS由Domestic PO4500192521转单。 Remark: 1. Amazon MDDP订单，出口US。 2. 日期码使用ZURU标准版本。 3. 如果大货有要求入邮包盒，则对应的邮包盒上面要打上日期码。 4. 箱尺寸要求：外箱最长边不能超过25"(超过了，case pack只能为1)，不符合要求的大货，一律不接受。 5. 外箱箱唛要求： ①外箱正面印ZURU Logo+SSCC Label(客供贴纸，由跟单订购)。关于 SSCC Label 请注意： SSCC Label显示的是客人自己的item#。每一张SSCC label都是唯一且有不同流水及条码的，没有损耗，绝对不可贴错。如果贴错或损坏任何一张，都会导致全部都 错，千万要注意！SSCC Label必须贴在外箱正面的正中间位置(贴一面即可)，并且贴纸离外箱边距必须至少3cm(可以覆盖Logo<(>&<)>箱唛)，否则会影响到客户那边 仓库的扫描识别。 ②外箱侧面印item#(订单上显示的SKU#)+carton size(以工厂实际尺寸为准，单位: inch)+MADE IN CHINA，日期使用ZURU 标准版本。 6. 装柜要求：按照客户PO#装柜/箱号顺序装柜，跟单会提前给到装柜计划。 在大货生产/仓库存放时，请留意该装柜要求，以便装柜时不混乱(避免装错/装漏/找不到货号等)。 | AD61: Kelly Shen/Mia Pan/P | AE61: 1.374 | AF61: =I61*AE61 -> 9958.752 | AG61: ZB05700-8.17 | AH61: 77876-S001 | AI61: 已入 | AJ61: 系统入单 | AK61: =I61*2 -> 14496 | AQ61: =I61*2 -> 14496 | AU61: =I61*2 -> 14496 | AV61: =I61*0.06*2 -> 869.76 | CD61: =BN61+BO61+BQ61+BS61+BR61 -> 0 | CE61: =BU61 -> 0 | CF61: =CC61 -> 0 | CG61: =BV61+BW61+BX61 -> 0 | CJ61: =I61 -> 7248 | CK61: =I61 -> 7248 | CL61: =I61 -> 7248
A62: 46079 | B62: TARGET US | C62: 美国 | D62: 4500194303 | E62: 10001661762-3 891 | F62: 4500194303-30 | G62: 77772GQ5-S001 | H62: 唱片球25 pcs/PDQ/箱 | I62: 20700 | J62: 0 | K62: 25 | L62: =I62/K62 -> 828 | M62: 46141 | N62: 46137 | Q62: PASS | T62: =13125+5275+2300 -> 20700 | U62: =T62-I62 -> 0 | V62: OK | W62: 46108 | X62: 有 | Y62: 4/2寄出外箱条码箱贴纸贴纸，2/10提供EVENT LABEL | AC62: 日期码格式：ZURU INC(BVI) 标准格式 日期：按实际生产日期 Packaging Info: 77772GQ5：产品包装MA 1L 收缩膜+MA 5L 收藏指南+MA 23L 组装说明+客版PDQ；客版PDQ翻单4500189603； Remark: 77772GQ5： 1.77772GQ5-S001-MINI BRANDS-VINYL-SERIES 1-CAPSULE,WITH DEMO,25PCS/GRAVITY PDQ,25PCS/PDQ/CTN; 2.产品包装MA 1L 收缩膜+MA 5L 收藏指南+MA 23L 组装说明+客版PDQ；客版PDQ翻单4500189603；收缩膜上的UPC显示193052090065; 4 mini vinyls(1 Target US Exclusive),1 accessory; 3. 外箱正唛左上角位置粘贴条码箱贴纸，每箱只贴一张，由ZURU订购。来料贴纸上显示的客户DPCI# 086-02-8931, UPC显示10193052090062; 以上Items： 1. 产品和包装上均要印刷tracking code信息，格式为ZURU常规格式； 2. 需要我司QC验货之后才能安排出货 3. 出货方式： 货代自提 | AD62: Holly Zheng | AE62: 1.29 | AF62: =I62*AE62 -> 26703 | AG62: ZB05472/ZB05518 | AH62: 77772GQ5-S001 | AI62: 已入 | AJ62: 系统入单 | AM62: =I62 -> 20700 | AN62: =I62 -> 20700 | AU62: =I62 -> 20700 | AV62: =I62*0.06 -> 1242 | BU62: =I62/25 -> 828 | CD62: =BN62+BO62+BQ62+BS62+BR62 -> 0 | CE62: =BU62 -> 828 | CF62: =CC62 -> 0 | CG62: =BV62+BW62+BX62 -> 0
A63: 46085 | B63: SCHEEL'S ALL SPORTS, INC. | C63: 美国 | D63: 4500195170 | E63: 21870359 | F63: 4500195170-30 | G63: 77772GQ2-S001 | H63: 唱片球50 pcs/2PDQ/箱 | I63: 9000 | J63: 0 | K63: 50 | L63: =I63/K63 -> 180 | M63: 46142 | N63: 46139 | Q63: PASS | T63: 9000 | U63: =T63-I63 -> 0 | V63: 无 | W63: 46104 | X63: 无 | Y63: 无 | AC63: 日期码格式：ZURU INC(BVI) 标准格式 日期：按实际生产日期 Packaging Info: 1. 包装：ZURU MA 1L 最新UPC版本；出口美国<(>&<)>CA； Remark: 2. 日期跟踪码：产品包装及产品本身都必须有日期跟踪码，并且确保两者的日期跟踪码要一致；ZURU标准格式日期码(请自行调整具体年月日生产期，但不能为周 末）。 3.. 出货配比: Zuru 标版配比。 | AD63: Mila Yao | AE63: 0.6042 | AF63: =AE63*I63 -> 5437.8 | AG63: ZB05444-8.17 | AH63: 77772GQ2-S001 | AI63: 已入 | AJ63: 系统入单 | AK63: =I63 -> 9000 | AN63: =I63 -> 9000 | AU63: =I63 -> 9000 | AV63: =I63*0.06 -> 540 | BN63: =I63/25 -> 360 | CD63: =BN63+BO63+BQ63+BS63+BR63 -> 360 | CE63: =BU63 -> 0 | CF63: =CC63 -> 0 | CG63: =BV63+BW63+BX63 -> 0
A64: 46080 | B64: MEIJER DISTRIBUTION, INC. | C64: 美国 | D64: 4500194442 | E64: 219072794 | F64: 4500194442-10 | G64: 77772GQ1-S002 | H64: 唱片球13 pcs/PDQ/箱 | I64: 1755 | J64: 0 | K64: 13 | L64: =I64/K64 -> 135 | M64: 46142 | N64: 46139 | Q64: PASS | T64: 1755 | U64: =T64-I64 -> 0 | V64: 无 | W64: 2/28 确认 | X64: 无 | Y64: 无 | AC64: 日期码格式：ZURU INC(BVI) 标准格式 日期： Packaging Info: 1. 通用PDQ, 产品MA UPC包装（优先1L）出美国 其中 92129TQ5为客版pdq翻单4500180920 2. 客人指定箱唛排版 3. 77772GQ1-S002 4 mini vinyls,1 accessory Remark: 出货前 Zuru QC 验货 | AD64: Agnes Zheng | AE64: 0.72 | AF64: =I64*AE64 -> 1263.6 | AG64: ZB05585-8.17 | AH64: 77772GQ1-S002 | AI64: 已入 | AJ64: 系统入单 | AK64: =I64 -> 1755 | AN64: =I64 -> 1755 | AU64: =I64 -> 1755 | AV64: =I64*0.06 -> 105.3 | BK64: =I64/13 -> 135 | CD64: =BN64+BO64+BQ64+BS64+BR64 -> 0 | CE64: =BU64 -> 0 | CF64: =CC64 -> 0 | CG64: =BV64+BW64+BX64 -> 0
A65: 46080 | B65: MEIJER DISTRIBUTION, INC. | C65: 美国 | D65: 4500194442 | E65: 219072800 | F65: 4500194442-20 | G65: 77772GQ1-S002 | H65: 唱片球13 pcs/PDQ/箱 | I65: 3250 | J65: 0 | K65: 13 | L65: =I65/K65 -> 250 | M65: 46142 | N65: 46139 | Q65: PASS | T65: 3250 | U65: =T65-I65 -> 0 | V65: 无 | W65: 2/28 确认 | X65: 无 | Y65: 无 | AC65: 日期码格式：ZURU INC(BVI) 标准格式 日期： Packaging Info: 1. 通用PDQ, 产品MA UPC包装（优先1L）出美国 其中 92129TQ5为客版pdq翻单4500180920 2. 客人指定箱唛排版 3. 77772GQ1-S002 4 mini vinyls,1 accessory Remark: 出货前 Zuru QC 验货 | AD65: Agnes Zheng | AE65: 2.02 | AF65: =I65*AE65 -> 6565 | AG65: ZB05585-8.17 | AH65: 77772GQ1-S002 | AI65: 已入 | AJ65: 系统入单 | AK65: =I65 -> 3250 | AN65: =I65 -> 3250 | AU65: =I65 -> 3250 | AV65: =I65*0.06 -> 195 | BK65: =I65/13 -> 250 | CD65: =BN65+BO65+BQ65+BS65+BR65 -> 0 | CE65: =BU65 -> 0 | CF65: =CC65 -> 0 | CG65: =BV65+BW65+BX65 -> 0
A66: 46093 | B66: WONDERLAND TOYS, INC. | C66: 美国 | D66: 4500196320 | E66: 5228 | F66: 4500196320-20 | G66: 77772GQ1-S001 | H66: 唱片球52pcs/4PDQ/箱 | I66: 936 | J66: 0 | K66: 52 | L66: =I66/K66 -> 18 | M66: 46142 | N66: 46139 | Q66: PASS | T66: 936 | U66: =T66-I66 -> 0 | V66: 无 | W66: 46114 | X66: 无 | Y66: 无 | AC66: 日期码格式：ZURU,LLC 标准格式 日期：按实际生产日期 Packaging Info: 1. 1. 出口美国MA UPC 版本包装，优先1L。 Remark: 2. ZURU QC 验货即可。 | AD66: Abby Mai,Lluvia Zeng | AE66: 0.6198 | AF66: =AE66*I66 -> 580.1328 | AG66: ZB05543-8.17 | AH66: 77772GQ1-S001 | AI66: 已入 | AJ66: 系统入单 | AK66: =I66 -> 936 | AN66: =I66 -> 936 | AU66: =I66 -> 936 | AV66: =I66*0.06 -> 56.16 | BK66: =I66/13 -> 72 | CD66: =BN66+BO66+BQ66+BS66+BR66 -> 0 | CE66: =BU66 -> 0 | CF66: =CC66 -> 0 | CG66: =BV66+BW66+BX66 -> 0
A67: 46091 | B67: KOTRYNA GROUP, UAB | C67: 立陶宛 | D67: 4500196085 | F67: 4500196085-30 | G67: 77772GQ1-S001 | H67: 唱片球52pcs/4PDQ/箱 | I67: 1300 | J67: 0 | K67: 52 | L67: =I67/K67 -> 25 | M67: 46142 | N67: 46139 | Q67: PASS | T67: 1300 | U67: =T67-I67 -> 0 | V67: OK | W67: 46107 | X67: 无 | Y67: 4/3进口商贴纸 | AC67: 日期码格式：ZURU INC(BVI) 标准格式 日期：按实际生产日期 Packaging Info: 3.77772GQ1:MA UPC 1L A版收缩膜+23L A版组装说明书+5L A版收藏指南+A版复合袋+ 进口商贴纸，加MA PDQ Remark: 1、若产品有比例使用ZURU STD 比例 2、所有item 包装上需要有CE logo，均用MA UPC 条码，若包装不是UPC 条码的请告知 3、此单出欧洲需满足EU测试标准要求，另外不能出闪粉（若产品本身不含闪粉则忽略这句话），电池产品（带电池/不带电池走货）需要添加WEEE通用说明书 | AD67: Sharon Zhao | AE67: 1.033 | AF67: =AE67*I67 -> 1342.9 | AH67: 77772GQ1-S001 | AI67: 已入 | AJ67: 系统入单 | AK67: =I67 -> 1300 | AN67: =I67 -> 1300 | AU67: =I67 -> 1300 | AV67: =I67*0.06 -> 78 | BK67: =I67/13 -> 100 | CD67: =BN67+BO67+BQ67+BS67+BR67 -> 0 | CE67: =BU67 -> 0 | CF67: =CC67 -> 0 | CG67: =BV67+BW67+BX67 -> 0
A68: 46094 | B68: TARGET US | C68: 美国 | D68: 4500196785 | E68: 10001761481-3 891 | F68: 4500196785-10 | G68: 77772GQ5-S001 | H68: 唱片球25 pcs/PDQ/箱 | I68: 28875 | J68: 0 | K68: 25 | L68: =I68/K68 -> 1155 | M68: 46142 | N68: 46139 | Q68: AOD | T68: 28875 | U68: =T68-I68 -> 0 | V68: OK | W68: 46108 | X68: 有 | Y68: 4/8寄出外箱条码箱贴纸贴纸，2/10提供EVENT LABEL | AC68: 日期码格式：ZURU INC(BVI) 标准格式 日期：按实际生产日期 Packaging Info: 产品包装MA 1L 收缩膜+MA 5L 收藏指南+MA 23L 组装说明+客版PDQ；客版PDQ翻单4500189603 Remark: 1.77772GQ5-S001-MINI BRANDS-VINYL-SERIES 1-CAPSULE,WITH DEMO,25PCS/GRAVITY PDQ,25PCS/PDQ/CTN; 2.产品包装MA 1L 收缩膜+MA 5L 收藏指南+MA 23L 组装说明+客版PDQ；客版PDQ翻单4500189603；收缩膜上的UPC显示193052090065; 4 mini vinyls(1 Target US Exclusive),1 accessory; 3. 外箱正唛左上角位置粘贴条码箱贴纸，每箱只贴一张，由ZURU订购。来料贴纸上显示的客户DPCI# 086-02-8931, UPC显示10193052090062; 4. 产品和包装上均要印刷tracking code信息，格式为ZURU常规格式； 5. 需要我司QC验货之后才能安排出货 6. 出货方式： 货代自提 | AD68: Holly Zheng | AE68: 1.29 | AF68: =I68*AE68 -> 37248.75 | AG68: ZB05515-8.17 | AH68: 77772GQ5-S001 | AI68: 已入 | AJ68: 系统入单 | AM68: =I68 -> 28875 | AN68: =I68 -> 28875 | AU68: =I68 -> 28875 | AV68: =I68*0.06 -> 1732.5 | BU68: =I68/25 -> 1155 | CD68: =BN68+BO68+BQ68+BS68+BR68 -> 0 | CE68: =BU68 -> 1155 | CF68: =CC68 -> 0 | CG68: =BV68+BW68+BX68 -> 0
A69: 46065 | B69: JUGUETIBICI, S.A. DE C.V. | C69: 墨西哥 | D69: 4500193910 | F69: 4500193910-40 | G69: 77772GQ2-S001 | H69: 唱片球50 pcs/2PDQ/箱 | I69: 1500 | J69: 0 | K69: 50 | L69: =I69/K69 -> 30 | M69: 46148 | N69: 46144 | Q69: PASS | S69: 需要监柜备品 | T69: 1500 | U69: =T69-I69 -> 0 | V69: OK | W69: 46093 | X69: 无 | Y69: 4/10UPC条码贴纸+进口商贴纸 | AC69: 日期码格式：ZURU INC(BVI) 标准格式 日期：按实际生产日期 Packaging Info: 4. 77772GQ2：MA 3L EAN包装+UPC条码贴纸+MA 3L PDQ包装+进口商贴纸+箱唛 Remark: 1. 此单有监柜，每款请多备1pc样板用于监装 | AD69: Ever Li | AE69: 1.007 | AF69: =I69*AE69 -> 1510.5 | AH69: 77772GQ2-S001-3L | AI69: 已入 | AJ69: 系统入单 | AK69: =I69 -> 1500 | AP69: =I69 -> 1500 | AU69: =I69 -> 1500 | AV69: =I69*0.06 -> 90 | BO69: =I69/25 -> 60 | CD69: =BN69+BO69+BQ69+BS69+BR69 -> 60 | CE69: =BU69 -> 0 | CF69: =CC69 -> 0 | CG69: =BV69+BW69+BX69 -> 0
A70: 46092 | B70: OSIRIS INC. | C70: 加拿大 | D70: 4500196293 | E70: 42349 | F70: 4500196293-10 | G70: 77772GQ2-S001 | H70: 唱片球50 pcs/2PDQ/箱 | I70: 5000 | J70: 0 | K70: 50 | L70: =I70/K70 -> 100 | M70: 46149 | N70: 46146 | Q70: PASS | T70: 5000 | U70: =T70-I70 -> 0 | V70: OK | W70: 46121 | X70: 无 | Y70: 4/14UPC贴纸 | AC70: 日期码格式：ZURU INC(BVI) 标准格式 日期：按实际生产日期 Packaging Info: 77772GQ2: 收缩膜<(>&<)>PDQ： MA 3L， 收缩膜加UPC贴纸 Remark: 出加拿大 Zuru验货.日期跟踪码：产品外包装及产品本身都必须有日期跟踪码，ZURU标准格式日期码 | AD70: Bella Tan | AE70: 1.007 | AF70: =I70*AE70 -> 5035 | AH70: 77772GQ2-S001-3L | AI70: 已入 | AJ70: 系统入单 | AK70: =I70 -> 5000 | AP70: =I70 -> 5000 | AU70: =I70 -> 5000 | AV70: =I70*0.06 -> 300 | BO70: =I70/25 -> 200 | CD70: =BN70+BO70+BQ70+BS70+BR70 -> 200 | CE70: =BU70 -> 0 | CF70: =CC70 -> 0 | CG70: =BV70+BW70+BX70 -> 0
A71: 46106 | B71: WALMART INC. | C71: 美国 | D71: 4500197250 | E71: 0983717983 | F71: 4500197250-10 | G71: 77772SLB-S001 | H71: 唱片球16pcs/PDQ/箱/60箱打卡板 | I71: 14400 | J71: 0 | K71: 960 | L71: =I71/K71 -> 15 | M71: 46149 | N71: 46146 | P71: 5/11第三方验货 | Q71: PASS | T71: 14400 | U71: =T71-I71 -> 0 | V71: OK | W71: 翻单4500195546 | X71: 无 | Y71: RFID贴纸，贴纸由ZURU提供，贴纸位置请严格按照我们签回的签板； | AC71: 日期码格式：ZURU DGYYMMDD CHINA(日期避开周末和法定节假日即可） 日期：按实际生产日期 Packaging Info: 77772SLB-S001 1.包装要求： MA 1L A版收缩膜+MA 5L A版收藏指南+MA 23L A版说明书+MA A版纸袋+客版1L PDQ，翻单：4500195546 每pcs产品上要贴1张RFID贴纸，贴纸由ZURU提供，贴纸位置请严格按照我们签回的签板； Remark: 77772SLB-S001 1.包装要求： MA 1L A版收缩膜+MA 5L A版收藏指南+MA 23L A版说明书+MA A版纸袋+客版1L PDQ，翻单：4500195546 每pcs产品上要贴1张RFID贴纸，贴纸由ZURU提供，贴纸位置请严格按照我们签回的签板； 2. 外箱印刷带条码的RFID箱唛：RFID紫色色带+WM Dept.图标+RFID图标+ITF-14条码，四面右下角印刷ZURU logo, ITFF条码只印刷在正唛一面，在加印的时候确保 条形码能扫描出来，外箱侧面任一角落加印："MADE IN CHINA" 字样； 3. 每个slip sheet上面贴一张艾利贴纸（不干胶贴纸）和一张普通贴纸（A4纸），slip sheet打印的普通贴纸的尺寸不能比艾利贴纸小，普通贴纸内容见附件； 4. 在产品上和包装上要有日期码、以及要有MADE IN CHINA和ZURU字样； 5. 产品如有扎带口要剪平，不能刮手。 6. 此单需要验货，请多备料 7. 此单以slip sheet出货，960pcs/60CTNS/Slip sheet | AD71: Maggie Xie | AE71: 645.144 | AF71: =AE71*L71 -> 9677.16 | AG71: ZB06041-8.17 | AH71: 77772SLB-S001-1L | AI71: 已入 | AJ71: 系统入单 | AK71: =I71 -> 14400 | AN71: =I71 -> 14400 | AU71: =I71 -> 14400 | AV71: =I71*0.06 -> 864 | BR71: =I71/16 -> 900 | CD71: =BN71+BO71+BQ71+BS71+BR71 -> 900 | CE71: =BU71 -> 0 | CF71: =CC71 -> 0 | CG71: =BV71+BW71+BX71 -> 0
A72: 46111 | D72: ZMPO260320 | F72: ZMPO260320-20 | G72: 77772-S001 | H72: 唱片球24 pcs/箱 | I72: 1248 | J72: 0 | K72: 24 | L72: =I72/K72 -> 52 | M72: 46149 | N72: 46146 | Q72: PASS | T72: 1248 | U72: =T72-I72 -> 0 | V72: 无 | W72: 46113 | X72: 无 | Y72: 无 | AC72: 大货最新版本/款号平均/麻烦按款号装箱/并在外箱上注明款号/大货标准箱装箱/箱唛参照邮件附件备注：收到样品订单后尽快安排 ，注意样板品质质量要求要高于大货品质要求 ，送货时必须要附带送货单(没有送货单和QC检验合格报告的仓库一律拒绝收货)，请知悉，谢谢！ | AD72: Angus | AH72: 77772-S001 | AI72: 已入 | AJ72: 系统入单 | AK72: =I72 -> 1248 | AN72: =I72 -> 1248 | AU72: =I72 -> 1248 | AV72: =I72*0.06*2 -> 149.76 | CD72: =BN72+BO72+BQ72+BS72+BR72 -> 0 | CE72: =BU72 -> 0 | CF72: =CC72 -> 0 | CG72: =BV72+BW72+BX72 -> 0
A73: 46080 | B73: CVS PHARMACY INC | C73: 美国 | D73: 4500194421 | E73: 5633896 | F73: 4500194421-10 | G73: 77772GQ4-S001 | H73: 唱片球6 pcs/PDQ/箱 | I73: 1164 | J73: 0 | K73: 6 | L73: =I73/K73 -> 194 | M73: 46150 | N73: 46146 | P73: 此单需要在2026/5/8完成首批数量供UL实验室抽板测试 | Q73: PASS | T73: 1164 | U73: =T73-I73 -> 0 | V73: 无 | W73: 3/27 确认 | X73: 无 | Y73: 无 | AB73: 测试样:每款预计12pcs成品球(抽板人员从大货中随机抽取12pcs)+额外提前备好每款5套完整散件,大货样：每款4整套(1整套是1个PDQ+ 6PCS球), 具 体寄样要求待后续邮件通知再安排寄出。 | AC73: 日期码格式：ZURU INC(BVI) 标准格式 日期：按实际生产日期 Packaging Info: 77772GQ4:ZURU标准MA UPC版本(优先1L)+客版PDQ(AW翻单 PO#4500188838),出口美国。 Remark: 1. 此单需要在2026/5/8完成首批数量供UL实验室抽板测试，剩余数量要求在2026/6/8全部完成。 2. 日期码请按ZURU标准版执行即可。 3. ZURU QC验货。 4. 样板准备：测试样:每款预计12pcs成品球(抽板人员从大货中随机抽取12pcs)+额外提前备好每款5套完整散件,大货样：每款4整套(1整套是1个PDQ+ 6PCS球), 具 体寄样要求待后续邮件通知再安排寄出。 | AD73: Eleven Zhang | AE73: 1.248 | AF73: =I73*AE73 -> 1452.672 | AG73: ZB06238-8.17 | AH73: 77772GQ4-S001 | AI73: 已入 | AJ73: 系统入单 | AK73: =I73 -> 1164 | AN73: =I73 -> 1164 | AU73: =I73 -> 1164 | AV73: =I73*0.06 -> 69.84 | BT73: =I73/6 -> 194 | CD73: =BN73+BO73+BQ73+BS73+BR73 -> 0 | CE73: =BU73 -> 0 | CF73: =CC73 -> 0 | CG73: =BV73+BW73+BX73 -> 0
A74: 46108 | B74: TARGET US | C74: 美国 | D74: 4500199055 | E74: 10001661761-3890 | F74: 4500199055-30 | G74: 77772GQ5-S001 | H74: 唱片球25 pcs/PDQ/箱 | I74: 28525 | J74: 0 | K74: 25 | L74: =I74/K74 -> 1141 | M74: 46150 | N74: 46146 | Q74: PASS | T74: 28525 | U74: =T74-I74 -> 0 | V74: OK | W74: 46120 | X74: 有 | Y74: 4/25SSCC外箱贴纸+锂电池标签纸 | AC74: 日期码格式：ZURU INC(BVI) 标准格式 日期：按实际生产日期 Packaging Info: 77673TQ1：产品包装 客版收缩膜(C版)+客版收藏指南+MA说明书+ MA 1L PDQ；客版收缩膜(C版）翻单4500183607；客版收藏指南翻单4500174008； 77858：产品包装 MA 1L 彩盒； 77772GQ5：产品包装MA 1L 收缩膜+MA 5L 收藏指南+MA 23L 组装说明+客版PDQ；客版PDQ翻单4500189603； 77794UQ1：产品包装 MA 1L黑白警告语说明书+MA 1L 彩盒+MA 1L PDQ+锂电池标签纸 Remark: 77673TQ1： 1. 77673TQ1-S001-CC-MINI BRANDS-FILL THE FRIDGE PLAYSET-SERIES 1-SHRINK WRAP,4PCS/PDQ,4PCS/PDQ/CTN; 2. 产品包装 客版收缩膜(C版)+客版收藏指南+MA说明书+ MA 1L PDQ；客版收缩膜上的UPC显示193052079404；客版收缩膜(C版）翻单4500183607；客版收藏指南翻 单4500174008； 3. 外箱正唛左上角位置粘贴条码箱贴纸，每箱只贴一张，由ZURU订购。来料贴纸上显示的客户DPCI# 086-02-3468， UPC显示10193052079401; 77858： 1. 77858-S001-MINI BRANDS-MAGIC COOK KITCHEN PLAYSET-SERIES 1-WINDOW BOX,3PCS/CTN; 2. 产品包装 MA 1L 彩盒，彩盒上的UPC显示193052100238; 3. 外箱正唛左上角位置粘贴条码箱贴纸，每箱只贴一张，由ZURU订购。来料贴纸上显示的客户DPCI: 086-02-5654, UPC显示10193052100235; 77772GQ5： 1.77772GQ5-S001-MINI BRANDS-VINYL-SERIES 1-CAPSULE,WITH DEMO,25PCS/GRAVITY PDQ,25PCS/PDQ/CTN; 2.产品包装MA 1L 收缩膜+MA 5L 收藏指南+MA 23L 组装说明+客版PDQ；客版PDQ翻单4500189603；收缩膜上的UPC显示193052090065; 4 mini vinyls(1 Target US Exclusive),1 accessory; 3. 外箱正唛左上角位置粘贴条码箱贴纸，每箱只贴一张，由ZURU订购。来料贴纸上显示的客户DPCI# 086-02-8931, UPC显示10193052090062; 77794UQ1： 1.77794UQ1-S002-MINI BRANDS-VINYL-PLAYSET-SERIES 1-CUBE,8PCS/PDQ,8PCS/PDQ/CTN; 2. 产品包装 MA 1L黑白警告语说明书+MA 1L 彩盒+MA 1L PDQ+锂电池标签纸; 彩盒上的UPC显示193052090409; 3. 外箱正唛左上角位置粘贴条码箱贴纸，每箱只贴一张，由ZURU订购。来料贴纸上显示的客户DPCI# 086-02-4085, UPC显示10193052090406; 4. 带锂电池出货，需在外箱正面或者侧面合适位置上加贴一张贴锂电池标签纸，由工厂订购 以上Items： 1. 产品和包装上均要印刷tracking code信息，格式为ZURU常规格式； 2. 需要我司QC验货之后才能安排出货 3. 出货方式： 货代自提 | AD74: Holly Zheng | AE74: 1.29 | AF74: =I74*AE74 -> 36797.25 | AG74: ZB05793-8.17 | AH74: 77772GQ5-S001 | AI74: 已入 | AJ74: 系统入单 | AK74: 28525 | AM74: =I74 -> 28525 | AN74: =I74 -> 28525 | AU74: =I74 -> 28525 | AV74: =I74*0.06 -> 1711.5 | BU74: =I74/25 -> 1141 | CD74: =BN74+BO74+BQ74+BS74+BR74 -> 0 | CE74: =BU74 -> 1141 | CF74: =CC74 -> 0 | CG74: =BV74+BW74+BX74 -> 0
A75: 46084 | B75: COSTCO WHOLESALE COORPERATION | C75: 美国 | D75: 4500194937 | E75: 9600512462 | F75: 4500194937-10 | G75: 77896SLT-77772-S001 | H75: 1pcs唱片机+3pcs球混装彩盒 | I75: 4320 | J75: 0 | K75: 120 | L75: =I75/K75 -> 36 | M75: 46150 | N75: 46146 | P75: 2026/4/27安排做10%抽版测试，最晚2026/5/19完成100%大货安排第三方验货 | Q75: PASS | R75: 已出货 | T75: =456+1176+1529+999+160 -> 4320 | U75: =T75-I75 -> 0 | V75: 无 | W75: 46155 | X75: 有 | Y75: 无 | AB75: 首单10%货好时需要安排第三方抽板测试,一般需要7-10 working day 做测试, 当天ITS会在大货抽大货样,测试所需样品以及封样(第三方验货时要用). 大货 样需由工厂寄到深圳office, 由ZURU跟单再转寄美国客户.待工厂100%完货之后需安排第三方验货, 一般是在ZURU QC验完货之后安排第三方验货(需要同时拿到pass 测试报告方可进行). | AC75: 日期码格式：ZURU INC(BVI) 标准格式 日期：按实际生产日期 Packaging Info: 客版包装: 客版彩盒+ 客版PDQ+客版收缩膜+客版收藏指南+客版说明书+客版纸袋 等其他内包材 Remark: 77896SLT:S001-MINI BRANDS-VINYLS-SERIES 1-1PK PLAYSET AND 3PK CAPSULES-COMBO IN COLOR BOX,120PCS/DISPLAY/SLIP SHEET 1. 所有日期码印在彩盒上，产品上也需要印日期码. 按实际生产日期，ZURU 标准版格式的日期码。 2. 客版包装: 客版彩盒+ 客版PDQ+客版收缩膜+客版收藏指南+客版说明书+客版纸袋 等其他内包材 3. 纸箱唛头：纸箱四面，正唛和背面两面都需印刷，其他2面侧面留空,按照箱唛要求排版。 4. 确保展示架在入外箱的时候一定要正面对着有印刷箱唛的那面,不可以装反。 5. 此单是首单出货数量4320pcs, 2026/4/27安排做10%抽版测试，最晚2026/5/19完成100%大货安排第三方验货 6. 大货样板:工厂需预留至少6整套测试样用于抽板+3pcs封样（1pc工厂留底待第三方验货使用+2pc寄深圳办公室，需给客人留底)+ 1pc大货样寄深圳办公室拍照用 7.Costco 会委托 UL对 锂电池电池包做"Lot Code 可追溯性审核". 需要电池供应商,工厂配合提供相关资料和文件(见附件打包文件). 请仔细阅读并要求下游供应 商提供齐所需资料. 注意在UL发出审核要求之后30 天内若资料不全，直接出不合格报告，导致无法出货. 初次审核费USD 400. 如果初次审核文件不齐全,导致fail, UL会直接出fail报告给Costco QA .供应商在客户系统提交CAP 文件, 如果供应商有新文件提供, 需要UL 再次审核, re audit 收取USD 200.所以最好是首次审核全部资料提供齐全, 避免re audit 产生额外费用. 注意: 首单10%货好时需要安排第三方抽板测试,一般需要7-10 working day 做测试, 当天ITS会在大货抽大货样,测试所需样品以及封样(第三方验货时要用). 大货 样需由工厂寄到深圳office, 由ZURU跟单再转寄美国客户.待工厂100%完货之后需安排第三方验货, 一般是在ZURU QC验完货之后安排第三方验货(需要同时拿到pass 测试报告方可进行). | AD75: Cherish Yao | AE75: 642 | AF75: =L75*AE75 -> 23112 | AG75: ZB06173-8.17 | AH75: 77896SLT-S001 | AI75: 已入 | AJ75: 系统入单 | AL75: =I75*3 -> 12960 | AV75: =I75*0.06*2 -> 518.4 | BB75: =I75*3 -> 12960 | BC75: =I75*3 -> 12960 | BD75: =I75*3 -> 12960 | BE75: =I75 -> 4320 | BF75: =I75/6 -> 720 | CD75: =BN75+BO75+BQ75+BS75+BR75 -> 0 | CE75: =BU75 -> 0 | CF75: =CC75 -> 0 | CG75: =BV75+BW75+BX75 -> 0
A76: 46095 | B76: COOP FAGHANDEL (NON-FOOD) | C76: 挪威 | D76: 4500196870 | E76: 32830058 | F76: 4500196870-70 | G76: 77772GQ1-S002 | H76: 唱片球13 pcs/PDQ/箱 | I76: 1365 | J76: 0 | K76: 13 | L76: =I76/K76 -> 105 | M76: 46150 | N76: 46146 | Q76: PASS | T76: 1365 | U76: =T76-I76 -> 0 | V76: OK | W76: 46119 | X76: 无 | Y76: 3/24警语贴纸 | Z76: WEEE 30L 不带电池说明书 | AC76: 日期码格式：ZURU INC(BVI) 标准格式 日期：按实际生产日期 Packaging Info: 77772GQ1: MA EAN 3L+警语贴纸+MA 收藏指南+WEEE 30L 不带电池说明书 Remark: 1. 产品和包装要求无硼无香，包装不能含有PVC， 成分不能含石棉； 2. 如有微塑料，必须合规欧洲标准，并增加IFUD说明书 3. 此订单有第三方验货, 新品需要准备三套大货样用于签样验货和给客户留底； 4. 所用电池需要符合欧洲电池新规(EU)2023-1542； 5. ZURU货号-客户货号-外箱条码-彩盒条码 77772GQ1-729436010193052090062-4894680051133 | AD76: Zoe Zhou | AE76: 1.2 | AF76: =I76*AE76 -> 1638 | AH76: 77772GQ1-S002-3L | AI76: 已入 | AJ76: 系统入单 | AK76: =I76 -> 1365 | AP76: =I76 -> 1365 | AU76: =I76 -> 1365 | AV76: =I76*0.06 -> 81.9 | BL76: =I76/13 -> 105 | CD76: =BN76+BO76+BQ76+BS76+BR76 -> 0 | CE76: =BU76 -> 0 | CF76: =CC76 -> 0 | CG76: =BV76+BW76+BX76 -> 0
A77: 46107 | D77: ZMPO260306 | F77: ZMPO260306-20 | G77: 77772-S001 | H77: 唱片球24 pcs/箱 | I77: 2904 | J77: 0 | K77: 24 | L77: =I77/K77 -> 121 | M77: 46152 | N77: 46148 | Q77: PASS | T77: 2904 | U77: =T77-I77 -> 0 | V77: 无 | W77: 46107 | X77: 无 | AC77: 大货最新版本/款号平均/麻烦按款号装箱/并在外箱上注明款号/大货标准箱装箱/箱唛参照邮件附件 | AH77: 77772-S001 | AI77: 已入 | AJ77: 系统入单 | AK77: =I77 -> 2904 | AN77: =I77 -> 2904 | AU77: =I77 -> 2904 | AV77: =I77*0.06 -> 174.24 | CD77: =BN77+BO77+BQ77+BS77+BR77 -> 0 | CE77: =BU77 -> 0 | CF77: =CC77 -> 0 | CG77: =BV77+BW77+BX77 -> 0
A78: 46093 | B78: WALMART INC. | C78: 美国 | D78: 4500196503 | E78: 980444077 | F78: 4500196503-10 | G78: 77772GQ3-S001 | H78: 唱片球16pcs/PDQ/箱 | I78: 17792 | J78: 0 | K78: 16 | L78: =I78/K78 -> 1112 | M78: 46153 | N78: 46149 | P78: 5/14第三方验货 | Q78: PASS | T78: 17792 | U78: =T78-I78 -> 0 | V78: OK | W78: 46099 | X78: 无 | Y78: 每pcs产品上要贴1张RFID贴纸，贴纸由ZURU提供，贴纸位置请严格按照我们签回的签板； | AC78: 日期码格式：ZURU DGMMDD CHINA(日期避开周末和法定节假日即可） 日期：按实际生产日期 Packaging Info: 77772GQ3-S001 1. 包装要求： 77772：MA 1L A版收缩膜+MA 5L A版收藏指南+MA 23L A版说明书+MA A版纸袋+客版1L PDQ，翻单：4500195546 每pcs产品要贴一张RFID贴纸，RFID贴纸由ZURU提供，贴纸位置要严格按照客人签板 Remark: 77772GQ3-S001 1. 包装要求： 77772：MA 1L A版收缩膜+MA 5L A版收藏指南+MA 23L A版说明书+MA A版纸袋+客版1L PDQ，翻单：4500195546 每pcs产品要贴一张RFID贴纸，RFID贴纸由ZURU提供，贴纸位置要严格按照客人签板 2. 外箱印刷带条码的RFID箱唛：RFID紫色色带+WM Dept.图标+RFID图标+ITF-14条码+粉色艾利贴纸（不干胶打印），四面右下角印刷ZURU logo, ITFF条码只印刷在 正唛一面，在加印的时候确保条形码能扫描出来，1张粉红色贴纸贴在正唛对角线，外箱侧面任一角落加印："MADE IN CHINA" 字样； 3. 在产品上和包装上要有日期码、以及要有MADE IN CHINA和ZURU字样； 4. 产品如有扎带口要剪平，不能刮手。 5. 此单需要验货，请多备料 6. 此单以loose carton出货，16pcs/PDQ/CTN | AD78: Maggie Xie | AE78: 0.78 | AF78: =AE78*I78 -> 13877.76 | AG78: ZB06047-8.17 | AH78: 77772GQ3-S001 | AI78: 已入 | AJ78: 系统入单 | AK78: =I78 -> 17792 | AN78: =I78 -> 17792 | AU78: =I78 -> 17792 | AV78: =I78*0.06 -> 1067.52 | BR78: =I78/16 -> 1112 | CD78: =BN78+BO78+BQ78+BS78+BR78 -> 1112 | CE78: =BU78 -> 0 | CF78: =CC78 -> 0 | CG78: =BV78+BW78+BX78 -> 0
A79: 46093 | B79: WALMART INC. | C79: 美国 | D79: 4500196503 | E79: 980444112 | F79: 4500196503-20 | G79: 77772GQ3-S001 | H79: 唱片球16pcs/PDQ/箱 | I79: 15680 | J79: 0 | K79: 16 | L79: =I79/K79 -> 980 | M79: 46153 | N79: 46149 | P79: 5/14第三方验货 | Q79: PASS | T79: 15680 | U79: =T79-I79 -> 0 | V79: OK | W79: 46099 | X79: 无 | Y79: 每pcs产品上要贴1张RFID贴纸，贴纸由ZURU提供，贴纸位置请严格按照我们签回的签板； | AC79: 日期码格式：ZURU DGMMDD CHINA(日期避开周末和法定节假日即可） 日期：按实际生产日期 Packaging Info: 77772GQ3-S001 1. 包装要求： 77772：MA 1L A版收缩膜+MA 5L A版收藏指南+MA 23L A版说明书+MA A版纸袋+客版1L PDQ，翻单：4500195546 每pcs产品要贴一张RFID贴纸，RFID贴纸由ZURU提供，贴纸位置要严格按照客人签板 Remark: 77772GQ3-S001 1. 包装要求： 77772：MA 1L A版收缩膜+MA 5L A版收藏指南+MA 23L A版说明书+MA A版纸袋+客版1L PDQ，翻单：4500195546 每pcs产品要贴一张RFID贴纸，RFID贴纸由ZURU提供，贴纸位置要严格按照客人签板 2. 外箱印刷带条码的RFID箱唛：RFID紫色色带+WM Dept.图标+RFID图标+ITF-14条码+粉色艾利贴纸（不干胶打印），四面右下角印刷ZURU logo, ITFF条码只印刷在 正唛一面，在加印的时候确保条形码能扫描出来，1张粉红色贴纸贴在正唛对角线，外箱侧面任一角落加印："MADE IN CHINA" 字样； 3. 在产品上和包装上要有日期码、以及要有MADE IN CHINA和ZURU字样； 4. 产品如有扎带口要剪平，不能刮手。 5. 此单需要验货，请多备料 6. 此单以loose carton出货，16pcs/PDQ/CTN | AD79: Maggie Xie | AE79: 0.78 | AF79: =AE79*I79 -> 12230.4 | AG79: ZB06046-8.17 | AH79: 77772GQ3-S001 | AI79: 已入 | AJ79: 系统入单 | AK79: =I79 -> 15680 | AN79: =I79 -> 15680 | AU79: =I79 -> 15680 | AV79: =I79*0.06 -> 940.8 | BR79: =I79/16 -> 980 | CD79: =BN79+BO79+BQ79+BS79+BR79 -> 980 | CE79: =BU79 -> 0 | CF79: =CC79 -> 0 | CG79: =BV79+BW79+BX79 -> 0
A80: 46095 | B80: TARGET AUSTRALIA PTY LTD | C80: 澳大利亚 | D80: 4500196881 | E80: 2599183 | F80: 4500196881-50 | G80: 77772GQ1-S002-PRODCC1 | H80: 唱片球13 pcs/PDQ/箱 | I80: 5239 | J80: 0 | K80: 13 | L80: =I80/K80 -> 403 | M80: 46153 | N80: =M80-4 -> 46149 | Q80: PASS | T80: 5239 | U80: =T80-I80 -> 0 | W80: 46097 | X80: 有 | Y80: 4/22外箱条码箱贴纸贴纸，2/10提供EVENT LABEL | Z80: 取消21/23号唱片 | AC80: 日期码格式：ZURU INC(BVI) 标准格式 日期：按实际生产日期 Packaging Info: 3. 77772GQ1: MA英语UPC版本包装（收缩膜和说明书, MA首选1L，如无1L可用多语且含英语的配套多语包装) + 两张覆盖PDQ上唱片的贴纸 + 两张覆盖收藏指南上唱片的贴纸 + 一张覆盖PDQ上数字"45"的贴纸 + 一张覆盖收藏指南上数字"45"的贴纸 + 外箱贴纸SSCC Label 配比信息：4 mini vinyls,1 accessory Remark: 1. 客人要求箱唛不可出现任何手写内容，重量与实际一致且不可手写; 2. 此单去澳大利亚，请按相应澳新标准生产; 3. 取消使用TARGET新版封箱胶封顶，外箱全部使用普通透明封箱胶纸(客版胶纸如还有库存，可先消耗库存)； 4. 外箱需要贴Target SSCC LABEL,客供PDF文档，工厂自行订购。请贴在正唛右下角（一箱一张，贴1面正唛右下角,封箱胶纸不能挡住贴纸内容。)；外箱贴纸距离 外箱边缘应在2cm以上。如果正唛无位置可以贴在侧唛； 5. SSCC LABEL要求：贴纸内容，条形码印刷不完整/不清晰或有划痕/缺失，贴纸脏污、破损、条形码折叠、翘起、重复或者丢失，以及封箱胶盖住贴纸任何位置的 ，客户都不能接受，如有发现以上异常，须返工重新贴； 6. 外箱材质为ZURU标准； 7. 产品和包装上要有tracking label信息：格式为Zuru标准格式（可以自行调整具体年月日生产日期,避开节假期日）； 8. SSCC Label 尺寸更新为：4x4 inch。 | AD80: Christine Liao | AE80: 1.2 | AF80: =I80*AE80 -> 6286.8 | AH80: 77772GQ1-S002 | AI80: 已入 | AJ80: 系统入单 | AK80: =I80 -> 5239 | AN80: =I80 -> 5239 | AU80: =I80 -> 5239 | AV80: =I80*0.06 -> 314.34 | BK80: =I80/13 -> 403 | CD80: =BN80+BO80+BQ80+BS80+BR80 -> 0 | CE80: =BU80 -> 0 | CF80: =CC80 -> 0 | CG80: =BV80+BW80+BX80 -> 0
A81: 46106 | B81: WALMART INC. | C81: 美国 | D81: 4500197333 | E81: 0983718088 | F81: 4500197333-10 | G81: 77772SLB-S001 | H81: 唱片球16pcs/PDQ/箱/60箱打卡板 | I81: 15360 | J81: 0 | K81: 960 | L81: =I81/K81 -> 16 | M81: 46153 | N81: 46149 | P81: 5/18第三方验货 | Q81: PASS | T81: 15360 | U81: =T81-I81 -> 0 | V81: OK | W81: 翻单4500195546 | X81: 无 | Y81: RFID贴纸，贴纸由ZURU提供，贴纸位置请严格按照我们签回的签板； | AC81: 日期码格式：ZURU DGYYMMDD CHINA(日期避开周末和法定节假日即可） 日期：按实际生产日期 Packaging Info: 77772SLB-S001 1.包装要求： MA 1L A版收缩膜+MA 5L A版收藏指南+MA 23L A版说明书+MA A版纸袋+客版1L PDQ，翻单：4500195546 每pcs产品上要贴1张RFID贴纸，贴纸由ZURU提供，贴纸位置请严格按照我们签回的签板； Remark: 77772SLB-S001 1.包装要求： MA 1L A版收缩膜+MA 5L A版收藏指南+MA 23L A版说明书+MA A版纸袋+客版1L PDQ，翻单：4500195546 每pcs产品上要贴1张RFID贴纸，贴纸由ZURU提供，贴纸位置请严格按照我们签回的签板； 2. 外箱印刷带条码的RFID箱唛：RFID紫色色带+WM Dept.图标+RFID图标+ITF-14条码，四面右下角印刷ZURU logo, ITFF条码只印刷在正唛一面，在加印的时候确保 条形码能扫描出来，外箱侧面任一角落加印："MADE IN CHINA" 字样； 3. 每个slip sheet上面贴一张艾利贴纸（不干胶贴纸）和一张普通贴纸（A4纸），slip sheet打印的普通贴纸的尺寸不能比艾利贴纸小，普通贴纸内容见附件； 4. 在产品上和包装上要有日期码、以及要有MADE IN CHINA和ZURU字样； 5. 产品如有扎带口要剪平，不能刮手。 6. 此单需要验货，请多备料 7. 此单以slip sheet出货，960pcs/60CTNS/Slip sheet | AD81: Maggie Xie | AE81: 645.1438 | AF81: =AE81*L81 -> 10322.301 | AG81: 已打卡板 | AH81: 77772SLB-S001-1L | AI81: 已入 | AJ81: 系统入单 | AK81: =I81 -> 15360 | AN81: =I81 -> 15360 | AU81: =I81 -> 15360 | AV81: =I81*0.06 -> 921.6 | BR81: =I81/16 -> 960 | CD81: =BN81+BO81+BQ81+BS81+BR81 -> 960 | CE81: =BU81 -> 0 | CF81: =CC81 -> 0 | CG81: =BV81+BW81+BX81 -> 0
A82: 46106 | B82: WALMART INC. | C82: 美国 | D82: 4500197278 | E82: 0983718034 | F82: 4500197278-10 | G82: 77772SLB-S001 | H82: 唱片球16pcs/PDQ/箱/60箱打卡板 | I82: 10560 | J82: 0 | K82: 960 | L82: =I82/K82 -> 11 | M82: 46153 | N82: 46149 | P82: 5/18第三方验货 | Q82: PASS | T82: 10560 | U82: =T82-I82 -> 0 | V82: OK | W82: 翻单4500195546 | X82: 无 | Y82: RFID贴纸，贴纸由ZURU提供，贴纸位置请严格按照我们签回的签板； | AC82: 日期码格式：ZURU DGYYMMDD CHINA(日期避开周末和法定节假日即可） 日期：按实际生产日期 Packaging Info: 77772SLB-S001 1.包装要求： MA 1L A版收缩膜+MA 5L A版收藏指南+MA 23L A版说明书+MA A版纸袋+客版1L PDQ，翻单：4500195546 每pcs产品上要贴1张RFID贴纸，贴纸由ZURU提供，贴纸位置请严格按照我们签回的签板； Remark: 77772SLB-S001 1.包装要求： MA 1L A版收缩膜+MA 5L A版收藏指南+MA 23L A版说明书+MA A版纸袋+客版1L PDQ，翻单：4500195546 每pcs产品上要贴1张RFID贴纸，贴纸由ZURU提供，贴纸位置请严格按照我们签回的签板； 2. 外箱印刷带条码的RFID箱唛：RFID紫色色带+WM Dept.图标+RFID图标+ITF-14条码，四面右下角印刷ZURU logo, ITFF条码只印刷在正唛一面，在加印的时候确保 条形码能扫描出来，外箱侧面任一角落加印："MADE IN CHINA" 字样； 3. 每个slip sheet上面贴一张艾利贴纸（不干胶贴纸）和一张普通贴纸（A4纸），slip sheet打印的普通贴纸的尺寸不能比艾利贴纸小，普通贴纸内容见附件； 4. 在产品上和包装上要有日期码、以及要有MADE IN CHINA和ZURU字样； 5. 产品如有扎带口要剪平，不能刮手。 6. 此单需要验货，请多备料 7. 此单以slip sheet出货，960pcs/60CTNS/Slip sheet | AD82: Maggie Xie | AE82: 645.1436 | AF82: =AE82*L82 -> 7096.5796 | AG82: 已打卡板 | AH82: 77772SLB-S001-1L | AI82: 已入 | AJ82: 系统入单 | AK82: =I82 -> 10560 | AN82: =I82 -> 10560 | AU82: =I82 -> 10560 | AV82: =I82*0.06 -> 633.6 | BR82: =I82/16 -> 660 | CD82: =BN82+BO82+BQ82+BS82+BR82 -> 660 | CE82: =BU82 -> 0 | CF82: =CC82 -> 0 | CG82: =BV82+BW82+BX82 -> 0
A83: 46062 | B83: KMART AUSTRALIA LTD(NEW ZEALAND) | C83: 新西兰 | D83: 4500193541 | E83: 21680609 | F83: 4500193541-50 | G83: 77772GQ1-S002-PRODCC1 | H83: 唱片球13 pcs/PDQ/箱 | I83: 585 | J83: 0 | K83: 13 | L83: =I83/K83 -> 45 | M83: 46153 | N83: =M83-4 -> 46149 | Q83: PASS | T83: 585 | U83: =T83-I83 -> 0 | V83: OK | W83: 46088 | X83: 有 | Y83: 3/16外箱贴纸SSCC Label+防盜贴纸位置图翻单PO#4500193539 | Z83: 取消21/23号唱片 | AC83: 日期码格式：ZURU INC(BVI) 标准格式 日期：按实际生产日期 Packaging Info: 77772GQ1:MA英语UPC版本包装（收缩膜和说明书, MA首选1L，如无1L可用多语且含英语的配套多语包装) +防盜贴纸(贴纸以及防盜贴纸位置图翻单PO#4500193539)+ 两张张覆盖PDQ上唱片的贴纸+两张张覆盖收藏指南上唱片的贴纸+一张覆盖PDQ上数字"45"的贴纸+一张覆盖收藏指南上数字"45"的贴纸+箱唛+外箱贴纸SSCC Label 配比信息：4 mini vinyls,1 accessory Removed了 ""Messy <(>&<)> Delicious""两张唱片 Remark: 1.请务必按时完货，验货。并且按期送货入货代指定仓库，如果晚了导致船期Delay将会有罚金产生或者客户要求空运，所产生的罚金和空运费由工厂承担。 2.SSCC 外箱贴纸请同纸箱瓦楞纸方向（竖纹向）垂直，即外箱贴纸横着贴(注意条码不要被胶带粘住），贴1pc，贴1面正唛，封箱胶纸不能挡住贴纸内容。外箱贴纸 离外箱边距离不少于2cm。 3.外箱材质为ZURU标准； 4.此单需使用KMART封箱胶上下工字型封箱;从2019年6月开始，要用KMART 新版封箱胶带，此单要用"ANKO"封箱胶带 5.此单出口新西兰，请按相应的澳新标准生产； 6.产品和包装上生产批号的显示格式ZURU标准日期码格式 7.外箱信息不可手写，重量和体积需要与实际的一致(不可手写） 8. 每款item装箱后的G.W.超过10KG或者CBM超过0.13,(9.5KG或者以上，四舍五入后也属于10KG) 需在外箱上加印超 重或者Bulky LOGO，若发现我们资料没有，请 帮忙提醒 1)重量超过10kg但不超过16kg且CBM不超过0.13,10-16kg 超重logo 2）CBM超过0.13且重量少于17kg，bulky logo 3）不属于以上两种情况，需要使用相应重量范围内的超重logo 4）超重logo需要在外箱四面都印刷(箱唛右上角，两面侧唛超重logo需要尽量靠近毛重)，尺寸为:110mm height* 95mm width 9. 实际外箱重量跟印在箱唛上的数据差异不能超3%，尺寸按实际数据印刷 71172实际上为LCL散货出柜，请注意此订单与AU po#4500193539一起合并计算 77772务必赶最晚5/11上午交仓 | AD83: Louise Lu | AE83: 2.02 | AF83: =I83*AE83 -> 1181.7 | AH83: 77772GQ1-S002 | AI83: 已入 | AJ83: 系统入单 | AK83: =I83 -> 585 | AN83: =I83 -> 585 | AU83: =I83 -> 585 | AV83: =I83*0.06 -> 35.1 | BK83: =I83/13 -> 45 | CD83: =BN83+BO83+BQ83+BS83+BR83 -> 0 | CE83: =BU83 -> 0 | CF83: =CC83 -> 0 | CG83: =BV83+BW83+BX83 -> 0
A84: 46062 | B84: KMART AUSTRALIA LTD | C84: 澳大利亚 | D84: 4500193539 | E84: 21680608 | F84: 4500193539-50 | G84: 77772GQ1-S002-PRODCC1 | H84: 唱片球13 pcs/PDQ/箱 | I84: 7293 | J84: 0 | K84: 13 | L84: =I84/K84 -> 561 | M84: 46153 | N84: =M84-4 -> 46149 | Q84: PASS | T84: 7293 | U84: =T84-I84 -> 0 | V84: OK | W84: 46088 | X84: 有 | Y84: 46099 | Z84: 取消21/23号唱片 | AC84: 日期码格式：ZURU INC(BVI) 标准格式 日期：按实际生产日期 Packaging Info: 77772GQ1:MA英语UPC版本包装（收缩膜和说明书, MA首选1L，如无1L可用多语且含英语的配套多语包装) +防盜贴纸(贴纸以及防盜贴纸位置图翻单PO#4500193539)+ 两张张覆盖PDQ上唱片的贴纸+两张张覆盖收藏指南上唱片的贴纸+一张覆盖PDQ上数字"45"的贴纸+一张覆盖收藏指南上数字"45"的贴纸+箱唛+外箱贴纸SSCC Label 配比信息：4 mini vinyls,1 accessory Removed了 ""Messy <(>&<)> Delicious""两张唱片 Remark: 1.请务必按时完货，验货。并且按期送货入货代指定仓库，如果晚了导致船期Delay将会有罚金产生或者客户要求空运，所产生的罚金和空运费由工厂承担。 2.SSCC 外箱贴纸请同纸箱瓦楞纸方向（竖纹向）垂直，即外箱贴纸横着贴(注意条码不要被胶带粘住），贴1pc，贴1面正唛，封箱胶纸不能挡住贴纸内容。外箱贴纸 离外箱边距离不少于2cm。 3.外箱材质为ZURU标准； 4.此单需使用KMART封箱胶上下工字型封箱;从2019年6月开始，要用KMART 新版封箱胶带，此单要用"ANKO"封箱胶带 5.此单出口澳大利亚，请按相应的澳新标准生产； 6.产品和包装上生产批号的显示格式ZURU标准日期码格式 7.外箱信息不可手写，重量和体积需要与实际的一致(不可手写） 8. 每款item装箱后的G.W.超过10KG或者CBM超过0.13,(9.5KG或者以上，四舍五入后也属于10KG) 需在外箱上加印超 重或者Bulky LOGO，若发现我们资料没有，请 帮忙提醒 1)重量超过10kg但不超过16kg且CBM不超过0.13,10-16kg 超重logo 2）CBM超过0.13且重量少于17kg，bulky logo 3）不属于以上两种情况，需要使用相应重量范围内的超重logo 4）超重logo需要在外箱四面都印刷(箱唛右上角，两面侧唛超重logo需要尽量靠近毛重)，尺寸为:110mm height* 95mm width 9. 实际外箱重量跟印在箱唛上的数据差异不能超3%，尺寸按实际数据印刷 71172实际上走LCL散货出柜，请注意此订单与NZ po#4500193541一起合并计算 77772务必赶最晚5/11上午交仓 | AD84: Louise Lu | AE84: 2.02 | AF84: =I84*AE84 -> 14731.86 | AH84: 77772GQ1-S002 | AI84: 已入 | AJ84: 系统入单 | AK84: =I84 -> 7293 | AN84: =I84 -> 7293 | AU84: =I84 -> 7293 | AV84: =I84*0.06 -> 437.58 | BK84: =I84/13 -> 561 | CD84: =BN84+BO84+BQ84+BS84+BR84 -> 0 | CE84: =BU84 -> 0 | CF84: =CC84 -> 0 | CG84: =BV84+BW84+BX84 -> 0
A85: 46090 | B85: KMART AUSTRALIA LTD | C85: 澳大利亚 | D85: 4500195654 | E85: 21680610 | F85: 4500193539-50 | G85: 77772GQ1-S002-PRODCC1 | H85: 唱片球13 pcs/PDQ/箱 | I85: 1417 | J85: 0 | K85: 13 | L85: =I85/K85 -> 109 | M85: 46153 | N85: 46149 | Q85: PASS | T85: 1417 | U85: =T85-I85 -> 0 | W85: 46107 | X85: 有 | Y85: 4/14外箱贴纸SSCC Label | Z85: 取消21/23号唱片 | AC85: 日期码格式：ZURU INC(BVI) 标准格式 日期：按实际生产日期 Packaging Info: 77772GQ1:MA英语UPC版本包装（收缩膜和说明书, MA首选1L，如无1L可用多语且含英语的配套多语包装) +防盜贴纸(贴纸以及防盜贴纸位置图翻单PO#4500193539)+ 两张覆盖PDQ上唱片的贴纸+两张覆盖收藏指南上唱片的贴纸+一张覆盖PDQ上数字"45"的贴纸+一张覆盖收藏指南上数字"45"的贴纸（以上6张贴纸以及贴纸位置图翻单 PO#4500193539)+箱唛+外箱贴纸SSCC Label 配比信息：4 mini vinyls,1 accessory Removed了 ""Messy <(>&<)> Delicious""两张唱片 Remark: 1.请务必按时完货，验货。并且按期送货入货代指定仓库，如果晚了导致船期Delay将会有罚金产生或者客户要求空运，所产生的罚金和空运费由工厂承担。 2.SSCC 外箱贴纸请同纸箱瓦楞纸方向（竖纹向）垂直，即外箱贴纸横着贴(注意条码不要被胶带粘住），贴1pc，贴1面正唛，封箱胶纸不能挡住贴纸内容。外箱贴纸 离外箱边距离不少于2cm。 3.外箱材质为ZURU标准； 4.此单需使用KMART封箱胶上下工字型封箱;从2019年6月开始，要用KMART 新版封箱胶带，此单要用"ANKO"封箱胶带 5.此单出口澳大利亚，请按相应的澳新标准生产； 6.产品和包装上生产批号的显示格式ZURU标准日期码格式 7.外箱信息不可手写，重量和体积需要与实际的一致(不可手写） 8. 每款item装箱后的G.W.超过10KG或者CBM超过0.13,(9.5KG或者以上，四舍五入后也属于10KG) 需在外箱上加印超 重或者Bulky LOGO，若发现我们资料没有，请 帮忙提醒 1)重量超过10kg但不超过16kg且CBM不超过0.13,10-16kg 超重logo 2）CBM超过0.13且重量少于17kg，bulky logo 3）不属于以上两种情况，需要使用相应重量范围内的超重logo 4）超重logo需要在外箱四面都印刷(箱唛右上角，两面侧唛超重logo需要尽量靠近毛重)，尺寸为:110mm height* 95mm width 9. 实际外箱重量跟印在箱唛上的数据差异不能超3%，尺寸按实际数据印刷 请注意此订单与NZ PO#4500195655一起合并计算 77772务必赶最晚5/11上午交仓 | AD85: Louise Lu | AE85: 1.2 | AF85: =I85*AE85 -> 1700.4 | AH85: 77772GQ1-S002 | AI85: 已入 | AJ85: 系统入单 | AK85: =I85 -> 1417 | AN85: =I85 -> 1417 | AU85: =I85 -> 1417 | AV85: =I85*0.06 -> 85.02 | BK85: =I85/13 -> 109 | CD85: =BN85+BO85+BQ85+BS85+BR85 -> 0 | CE85: =BU85 -> 0 | CF85: =CC85 -> 0 | CG85: =BV85+BW85+BX85 -> 0
A86: 46112 | B86: WM MORRISON SUPERMARKETS LIMITED | C86: 英国 | D86: 4500199237 | E86: 89006289 | F86: 4500199237-90 | G86: 77772GQ1-S003 | H86: 唱片球13 pcs/PDQ/箱 | I86: 6448 | J86: 13 | K86: 104 | L86: =I86/K86 -> 62 | M86: 46153 | N86: 46149 | Q86: PASS | T86: 6448 | U86: =T86-I86 -> 0 | V86: 无 | W86: 46129 | X86: 无 | Y86: 无 | Z86: 移除#21唱片 | AC86: 日期码格式：ZURU INC(BVI) 标准格式 日期：按实际生产日期 "77772GQ1: MA PDQ+最新MA 1L UPC收缩膜+MA收藏指南+MA组装说明书+MA袋子 Ratio: 8 Assortment=1:1:1:1:1:1:1:1 Barcode: 157117A: 193052105844 157117B: 193052105851 157117D: 193052105868 157117E: 193052105875 157117G: 193052105882 157117H: 193052105899 157117J: 193052105905 157117K: 193052105912" Remark: 1. 请准时出货，推期会有罚款； 2. 所有产品按符合欧洲标准走货，需要是不含微塑料版本。 3.包装日期码按ZURU格式即可，请确保不迟于外箱日期码，可等于或者早于外箱日期码，必须为法定工作日，印刷前请先检查外箱日期码。 4.请注意检查产品及包装应带UKCA图标（14+产品除外），包装显示ZURU UK LTD/ZURU France地址信息，QC部门请查核，如有问题与跟单确认 5.电子产品需增加一张B版WEEE声明30L通用黑白说明书(不接受A版本，翻译有误)，区分带电池和不带电池出货版本, 如已做客版说明书含WEEE信息可忽略此要求； 6.订单备注显示有分批的（不同仓库/订单号） ，注意分开做货出货，否则会导致罚款 。 7.外箱有条码要求，排版时请留意并请确保条码清晰可扫描（封箱胶不要黏到条码上), 否则客人会有罚款。 8.做货前请先复核包装条码与订单是否一致再安排，对不上的需与ZURU跟单确认再安排。 9.最大外箱尺寸和重量 : 600mm x 500mm x 745mm (LxWxH) 以及 G.W. 16 KG，超过的需要客人批准才能出货并且外箱需要印2 man lift标志 。 10.做货前务必核对零售条码是否与订单要求一致 ，对不上到客户仓库需要返工 ，工厂需要承担责任。 | AD86: Sherry Lu | AE86: 1.2 | AF86: =I86*AE86 -> 7737.6 | AH86: 77772GQ1-S003 | AI86: 已入 | AJ86: 系统入单 | AK86: =I86 -> 6448 | AN86: =I86 -> 6448 | AU86: =I86 -> 6448 | AV86: =I86*0.06*2 -> 773.76 | BK86: =I86/13 -> 496 | CD86: =BN86+BO86+BQ86+BS86+BR86 -> 0 | CE86: =BU86 -> 0 | CF86: =CC86 -> 0 | CG86: =BV86+BW86+BX86 -> 0
A87: 46093 | B87: WALMART INC. | C87: 美国 | D87: 4500196504 | E87: 980444116 | F87: 4500196504-10 | G87: 77772GQ3-S001 | H87: 唱片球16pcs/PDQ/箱 | I87: 13440 | J87: 0 | K87: 16 | L87: =I87/K87 -> 840 | M87: 46156 | N87: 46153 | P87: 5/18第三方验货 | Q87: PASS | T87: 13440 | U87: =T87-I87 -> 0 | V87: OK | W87: 46099 | X87: 无 | Y87: 每pcs产品上要贴1张RFID贴纸，贴纸由ZURU提供，贴纸位置请严格按照我们签回的签板； | AC87: 日期码格式：ZURU DGMMDD CHINA(日期避开周末和法定节假日即可） 日期：按实际生产日期 Packaging Info: 77772GQ3-S001 1. 包装要求： 77772：MA 1L A版收缩膜+MA 5L A版收藏指南+MA 23L A版说明书+MA A版纸袋+客版1L PDQ，翻单：4500195546 每pcs产品要贴一张RFID贴纸，RFID贴纸由ZURU提供，贴纸位置要严格按照客人签板 Remark: 77772GQ3-S001 1. 包装要求： 77772：MA 1L A版收缩膜+MA 5L A版收藏指南+MA 23L A版说明书+MA A版纸袋+客版1L PDQ，翻单：4500195546 每pcs产品要贴一张RFID贴纸，RFID贴纸由ZURU提供，贴纸位置要严格按照客人签板 2. 外箱印刷带条码的RFID箱唛：RFID紫色色带+WM Dept.图标+RFID图标+ITF-14条码+粉色艾利贴纸（不干胶打印），四面右下角印刷ZURU logo, ITFF条码只印刷在 正唛一面，在加印的时候确保条形码能扫描出来，1张粉红色贴纸贴在正唛对角线，外箱侧面任一角落加印："MADE IN CHINA" 字样； 3. 在产品上和包装上要有日期码、以及要有MADE IN CHINA和ZURU字样； 4. 产品如有扎带口要剪平，不能刮手。 5. 此单需要验货，请多备料 6. 此单以loose carton出货，16pcs/PDQ/CTN | AD87: Maggie Xie | AE87: 0.78 | AF87: =AE87*I87 -> 10483.2 | AG87: ZB06045-8.17 | AH87: 77772GQ3-S001 | AI87: 已入 | AJ87: 系统入单 | AK87: =I87 -> 13440 | AN87: =I87 -> 13440 | AU87: =I87 -> 13440 | AV87: =I87*0.06 -> 806.4 | BR87: =I87/16 -> 840 | CD87: =BN87+BO87+BQ87+BS87+BR87 -> 840 | CE87: =BU87 -> 0 | CF87: =CC87 -> 0 | CG87: =BV87+BW87+BX87 -> 0
A88: 46093 | B88: WALMART INC. | C88: 美国 | D88: 4500196504 | E88: 980444121 | F88: 4500196504-20 | G88: 77772GQ3-S001 | H88: 唱片球16pcs/PDQ/箱 | I88: 21056 | J88: 0 | K88: 16 | L88: =I88/K88 -> 1316 | M88: 46156 | N88: 46153 | P88: 5/18第三方验货 | Q88: PASS | T88: 21056 | U88: =T88-I88 -> 0 | V88: OK | W88: 46099 | X88: 无 | Y88: 每pcs产品上要贴1张RFID贴纸，贴纸由ZURU提供，贴纸位置请严格按照我们签回的签板； | AC88: 日期码格式：ZURU DGMMDD CHINA(日期避开周末和法定节假日即可） 日期：按实际生产日期 Packaging Info: 77772GQ3-S001 1. 包装要求： 77772：MA 1L A版收缩膜+MA 5L A版收藏指南+MA 23L A版说明书+MA A版纸袋+客版1L PDQ，翻单：4500195546 每pcs产品要贴一张RFID贴纸，RFID贴纸由ZURU提供，贴纸位置要严格按照客人签板 Remark: 77772GQ3-S001 1. 包装要求： 77772：MA 1L A版收缩膜+MA 5L A版收藏指南+MA 23L A版说明书+MA A版纸袋+客版1L PDQ，翻单：4500195546 每pcs产品要贴一张RFID贴纸，RFID贴纸由ZURU提供，贴纸位置要严格按照客人签板 2. 外箱印刷带条码的RFID箱唛：RFID紫色色带+WM Dept.图标+RFID图标+ITF-14条码+粉色艾利贴纸（不干胶打印），四面右下角印刷ZURU logo, ITFF条码只印刷在 正唛一面，在加印的时候确保条形码能扫描出来，1张粉红色贴纸贴在正唛对角线，外箱侧面任一角落加印："MADE IN CHINA" 字样； 3. 在产品上和包装上要有日期码、以及要有MADE IN CHINA和ZURU字样； 4. 产品如有扎带口要剪平，不能刮手。 5. 此单需要验货，请多备料 6. 此单以loose carton出货，16pcs/PDQ/CTN | AD88: Maggie Xie | AE88: 0.78 | AF88: =AE88*I88 -> 16423.68 | AG88: ZB06044-8.17 | AH88: 77772GQ3-S001 | AI88: 已入 | AJ88: 系统入单 | AK88: =I88 -> 21056 | AN88: =I88 -> 21056 | AU88: =I88 -> 21056 | AV88: =I88*0.06 -> 1263.36 | BR88: =I88/16 -> 1316 | CD88: =BN88+BO88+BQ88+BS88+BR88 -> 1316 | CE88: =BU88 -> 0 | CF88: =CC88 -> 0 | CG88: =BV88+BW88+BX88 -> 0
A89: 46112 | B89: AMAZON UK | C89: 英国 | D89: 4500198642 | E89: 5TKIJIXX | F89: 4500198642-180 | G89: 77876-S001 | H89: 唱片球2PK圆筒装 | I89: 5520 | J89: 0 | K89: 12 | L89: =I89/K89 -> 460 | M89: 46156 | N89: 46153 | Q89: PASS | T89: 5520 | U89: =T89-I89 -> 0 | W89: 空白外箱（加印带Zuru字样的最新logo，除了邮包盒直接做外箱的产品） + SSCC LABEL一张, 无箱唛，MADE IN CHINA 外箱只印一正一侧。箱唛资料按照给定的 标准去做即可，无需发回我方再行审批(新标准将另行通知)。 | X89: 有 | Y89: 4/30外箱贴纸 | Z89: 客版3L(3L warning UPC)A彩卡(参考翻单PO#4500198642，新UK地址) | AC89: 日期码格式：ZURU INC(BVI) 标准格式 日期：按实际生产日期 Packaging Info: Amazon UK: 5TKIJIXX/3O77XWME/7N1D8FUG/7H6BABTK/5Z2UXPOL/3UI85QUZ Amazon UK(77858/77876/77878/157124/157142) 2. 77876: 2pk 77772 VINYL into PVC tube,12tubes/ctn; 77772: 客版 3L(3L warning 无条码收缩膜,翻单Amazon US PO#4500192506)+MA5L A版收藏指南+MA 2 3L warning A组装黑白说明书+MA其它最新配套包装+客版3L(3L warning UPC)彩卡(翻单Amazon US PO#4500192506)+1张贴纸(1张含DE/IT警告语+IT环保标, 贴彩卡) +不带电池30L B版 WEEE说明书 6.验货时间不迟于2026/5/15. 注意：77858需将邮包盒尺寸图片<(>&<)>重量图片放进验货报告。 Remark: 1.空白外箱（加印带Zuru字样的最新logo，除了邮包盒直接做外箱的产品） + SSCC LABEL一张, 无箱唛，MADE IN CHINA 外箱只印一正一侧。箱唛资料按照给定的 标准去做即可，无需发回我方再行审批(新标准将另行通知)。 (SSCC LABEL竖贴在外箱正面的正中间，贴一面即可,贴纸离外箱边距必须至少3.2CM。如竖贴无法满足要求，则横贴。如横贴也无法满足要求，则竖贴，遮到ZURU lo go无影响), SSCC贴纸由工厂直接跟勤得采购或者工厂自行采购，每一张SSCC Label都是唯一且有不同流水及条码，且需要检查条码是否能正常扫描，另外，此贴纸 印刷不可出现模糊，溢出及粘胶不牢易脱落等现象，如工厂不按此要求导致贴纸有任何问题产生的罚款将由工厂承担一切责任 ,<(>,<)> 此要求只适用Amazon UK/DE /FR/ES/IT,不适用Amazon GPE，Amazon GPE无SSCC label, 但是有对应箱唛，需印刷到外箱 。 2.出往UK的产品+包装务必打上UKCA logo ，否则客人会退货且当地会有罚款。 3.订单必须经过ZURU QC验货或者工厂自检通过后方可出货，不涉及第三方验货。 4.法国订单要求包装不使用矿物油，请按要求提供以下其中一份文件再出货 ，产品出到法国被相关部门抽检出现包装不符合此要求的，供应商需要为此承担责任， 故此请严格把关。 -油墨物质""""由1 ~ 7个芳香环组成的MOAH""""的包装检测报告，要求限值≤1.0%； -包装材料清单，包括包装油墨或物质的信息； -油墨制造商的证书； 5.每一批次出货只能有一个生产日期，不可多个生产日期混在同一批次出货；且零售包装上必须统一加上日期码；外箱对于日期码没有硬性规定； 6.涉及到相关款式会有闪粉的或者微塑料的，请统一默认出无闪粉或者不含微塑料版本； 7.邮包盒及外箱封箱必须是工字型封箱方式； 8.5 Surprise or Mini Brands涉及包装是2个及2个以上的球入PVC桶包装时，单个球上若有UPC#或者EAN#，请用空白贴纸覆盖住，贴纸尺寸自行测量能覆盖原条码即 可； 9. 无论是工厂自检还是ZURU验货，验货报告中必须有产品6面图(正面/背面/左面/右面/顶部/底部，不带包装); 10. 按空海运鉴定报告的要求，只要带锂电池出货，都需要加贴UN贴纸； 11. 所有出往GAS市场(德国/奥地利/瑞士)的电子产品身上需要加字唛，为ZURU FRANCE 地址，需跟包装上的地址一致 (如无电子产品，产品布标有此地址，或产品 太小无法增加可忽略此信息。如产品无法加字唛，需让对应跟单提供产品贴纸资料); 12. 所有出往GAS德国 (瑞士，奥地利)。水弹枪系列必须使用EN71版本（电子和非电子水弹枪系列都需要符合); 护目镜需打日期码, 格式跟ZURU标准格式一样; 枪 身上增加ZURU FRANCE公司名和地址。使用贴纸和辐射上去都可以。如果有位置，最好增加ZURU Represented by: (此最好翻译德语，如果位置不允许，那么就只增 加ZURU法国和地址)。使用最新的EN71版包装和说明书） | AD89: Luna Lin | AE89: 2.29 | AF89: =I89*AE89 -> 12640.8 | AH89: 77876-S001 | AI89: 已入 | AJ89: 系统入单 | AK89: =I89*2 -> 11040 | AQ89: =I89*2 -> 11040 | AU89: =I89*2 -> 11040 | AV89: =I89*0.06*2 -> 662.4 | CD89: =BN89+BO89+BQ89+BS89+BR89 -> 0 | CE89: =BU89 -> 0 | CF89: =CC89 -> 0 | CG89: =BV89+BW89+BX89 -> 0 | CJ89: =I89 -> 5520 | CK89: =I89 -> 5520 | CL89: =I89 -> 5520
A90: 46112 | B90: AMAZON UK | C90: 英国 | D90: 4500198642 | E90: 3O77XWME | F90: 4500198642-190 | G90: 77876-S001 | H90: 唱片球2PK圆筒装 | I90: 5520 | J90: 0 | K90: 12 | L90: =I90/K90 -> 460 | M90: 46156 | N90: 46153 | Q90: PASS | T90: 5520 | U90: =T90-I90 -> 0 | W90: 空白外箱（加印带Zuru字样的最新logo，除了邮包盒直接做外箱的产品） + SSCC LABEL一张, 无箱唛，MADE IN CHINA 外箱只印一正一侧。箱唛资料按照给定的 标准去做即可，无需发回我方再行审批(新标准将另行通知)。 | X90: 有 | Y90: 4/30外箱贴纸 | Z90: 客版3L(3L warning UPC)A彩卡(参考翻单PO#4500198642，新UK地址) | AC90: 日期码格式：ZURU INC(BVI) 标准格式 日期：按实际生产日期 Packaging Info: Amazon UK: 5TKIJIXX/3O77XWME/7N1D8FUG/7H6BABTK/5Z2UXPOL/3UI85QUZ Amazon UK(77858/77876/77878/157124/157142) 2. 77876: 2pk 77772 VINYL into PVC tube,12tubes/ctn; 77772: 客版 3L(3L warning 无条码收缩膜,翻单Amazon US PO#4500192506)+MA5L A版收藏指南+MA 2 3L warning A组装黑白说明书+MA其它最新配套包装+客版3L(3L warning UPC)彩卡(翻单Amazon US PO#4500192506)+1张贴纸(1张含DE/IT警告语+IT环保标, 贴彩卡) +不带电池30L B版 WEEE说明书 6.验货时间不迟于2026/5/15. 注意：77858需将邮包盒尺寸图片<(>&<)>重量图片放进验货报告。 Remark: 1.空白外箱（加印带Zuru字样的最新logo，除了邮包盒直接做外箱的产品） + SSCC LABEL一张, 无箱唛，MADE IN CHINA 外箱只印一正一侧。箱唛资料按照给定的 标准去做即可，无需发回我方再行审批(新标准将另行通知)。 (SSCC LABEL竖贴在外箱正面的正中间，贴一面即可,贴纸离外箱边距必须至少3.2CM。如竖贴无法满足要求，则横贴。如横贴也无法满足要求，则竖贴，遮到ZURU lo go无影响), SSCC贴纸由工厂直接跟勤得采购或者工厂自行采购，每一张SSCC Label都是唯一且有不同流水及条码，且需要检查条码是否能正常扫描，另外，此贴纸 印刷不可出现模糊，溢出及粘胶不牢易脱落等现象，如工厂不按此要求导致贴纸有任何问题产生的罚款将由工厂承担一切责任 ,<(>,<)> 此要求只适用Amazon UK/DE /FR/ES/IT,不适用Amazon GPE，Amazon GPE无SSCC label, 但是有对应箱唛，需印刷到外箱 。 2.出往UK的产品+包装务必打上UKCA logo ，否则客人会退货且当地会有罚款。 3.订单必须经过ZURU QC验货或者工厂自检通过后方可出货，不涉及第三方验货。 4.法国订单要求包装不使用矿物油，请按要求提供以下其中一份文件再出货 ，产品出到法国被相关部门抽检出现包装不符合此要求的，供应商需要为此承担责任， 故此请严格把关。 -油墨物质""""由1 ~ 7个芳香环组成的MOAH""""的包装检测报告，要求限值≤1.0%； -包装材料清单，包括包装油墨或物质的信息； -油墨制造商的证书； 5.每一批次出货只能有一个生产日期，不可多个生产日期混在同一批次出货；且零售包装上必须统一加上日期码；外箱对于日期码没有硬性规定； 6.涉及到相关款式会有闪粉的或者微塑料的，请统一默认出无闪粉或者不含微塑料版本； 7.邮包盒及外箱封箱必须是工字型封箱方式； 8.5 Surprise or Mini Brands涉及包装是2个及2个以上的球入PVC桶包装时，单个球上若有UPC#或者EAN#，请用空白贴纸覆盖住，贴纸尺寸自行测量能覆盖原条码即 可； 9. 无论是工厂自检还是ZURU验货，验货报告中必须有产品6面图(正面/背面/左面/右面/顶部/底部，不带包装); 10. 按空海运鉴定报告的要求，只要带锂电池出货，都需要加贴UN贴纸； 11. 所有出往GAS市场(德国/奥地利/瑞士)的电子产品身上需要加字唛，为ZURU FRANCE 地址，需跟包装上的地址一致 (如无电子产品，产品布标有此地址，或产品 太小无法增加可忽略此信息。如产品无法加字唛，需让对应跟单提供产品贴纸资料); 12. 所有出往GAS德国 (瑞士，奥地利)。水弹枪系列必须使用EN71版本（电子和非电子水弹枪系列都需要符合); 护目镜需打日期码, 格式跟ZURU标准格式一样; 枪 身上增加ZURU FRANCE公司名和地址。使用贴纸和辐射上去都可以。如果有位置，最好增加ZURU Represented by: (此最好翻译德语，如果位置不允许，那么就只增 加ZURU法国和地址)。使用最新的EN71版包装和说明书） | AD90: Luna Lin | AE90: 2.29 | AF90: =I90*AE90 -> 12640.8 | AH90: 77876-S001 | AI90: 已入 | AJ90: 系统入单 | AK90: =I90*2 -> 11040 | AQ90: =I90*2 -> 11040 | AU90: =I90*2 -> 11040 | AV90: =I90*0.06*2 -> 662.4 | CD90: =BN90+BO90+BQ90+BS90+BR90 -> 0 | CE90: =BU90 -> 0 | CF90: =CC90 -> 0 | CG90: =BV90+BW90+BX90 -> 0 | CJ90: =I90 -> 5520 | CK90: =I90 -> 5520 | CL90: =I90 -> 5520
A91: 46106 | B91: WALMART INC. | C91: 美国 | D91: 4500197336 | E91: 0983717970 | F91: 4500197336-10 | G91: 77772SLB-S001 | H91: 唱片球16pcs/PDQ/箱/60箱打卡板 | I91: 21120 | J91: 0 | K91: 960 | L91: =I91/K91 -> 22 | M91: 46156 | N91: 46153 | P91: 转自检 | Q91: PASS | T91: 21120 | U91: =T91-I91 -> 0 | W91: 翻单4500195546 | X91: 无 | Y91: RFID贴纸，贴纸由ZURU提供，贴纸位置请严格按照我们签回的签板； | AC91: 日期码格式：ZURU DGYYMMDD CHINA(日期避开周末和法定节假日即可） 日期：按实际生产日期 Packaging Info: 77772SLB-S001 1.包装要求： MA 1L A版收缩膜+MA 5L A版收藏指南+MA 23L A版说明书+MA A版纸袋+客版1L PDQ，翻单：4500195546 每pcs产品上要贴1张RFID贴纸，贴纸由ZURU提供，贴纸位置请严格按照我们签回的签板； Remark: 77772SLB-S001 1.包装要求： MA 1L A版收缩膜+MA 5L A版收藏指南+MA 23L A版说明书+MA A版纸袋+客版1L PDQ，翻单：4500195546 每pcs产品上要贴1张RFID贴纸，贴纸由ZURU提供，贴纸位置请严格按照我们签回的签板； 2. 外箱印刷带条码的RFID箱唛：RFID紫色色带+WM Dept.图标+RFID图标+ITF-14条码，四面右下角印刷ZURU logo, ITFF条码只印刷在正唛一面，在加印的时候确保 条形码能扫描出来，外箱侧面任一角落加印："MADE IN CHINA" 字样； 3. 每个slip sheet上面贴一张艾利贴纸（不干胶贴纸）和一张普通贴纸（A4纸），slip sheet打印的普通贴纸的尺寸不能比艾利贴纸小，普通贴纸内容见附件； 4. 在产品上和包装上要有日期码、以及要有MADE IN CHINA和ZURU字样； 5. 产品如有扎带口要剪平，不能刮手。 6. 此单需要验货，请多备料 7. 此单以slip sheet出货，960pcs/60CTNS/Slip sheet | AD91: Maggie Xie | AE91: 645.1441 | AF91: =AE91*L91 -> 14193.17 | AG91: ZB06037-8.17 | AH91: 77772SLB-S001-1L | AI91: 已入 | AJ91: 系统入单 | AK91: =I91 -> 21120 | AN91: =I91 -> 21120 | AU91: =I91 -> 21120 | AV91: =I91*0.06 -> 1267.2 | BR91: =I91/16 -> 1320 | CD91: =BN91+BO91+BQ91+BS91+BR91 -> 1320 | CE91: =BU91 -> 0 | CF91: =CC91 -> 0 | CG91: =BV91+BW91+BX91 -> 0
A92: 46112 | B92: ZURU LLC | C92: 美国 | D92: 4500199498 | E92: 5200009502 | F92: 4500199498-10 | G92: 77876-S001-MTS | H92: 唱片球2PK圆筒装 | I92: 3840 | J92: 0 | K92: 12 | L92: =I92/K92 -> 320 | M92: 46157 | N92: 46153 | Q92: PASS | T92: 3840 | U92: =T92-I92 -> 0 | W92: 4/1 更新 | X92: 无 | Y92: 无 | Z92: 客版收缩膜和3L铜版纸图稿翻单4500192514 | AC92: 日期码格式：ZURU INC(BVI) 标准格式 日期：按实际生产日期 Packaging Info: #77876:2PK MA 1L UPC版#77772入PVC桶，3L无UPC客版收缩膜，客版收缩膜和3L铜版纸图稿翻单4500192514.（两个球的配比不能重复）。 Remark: 1.TikTok US订单。出口美国。外箱尺寸不能超过26*26*26" ，不符合要求的大货，一律不接受。 2.无第三方验货/测试要求。 3. 日期码使用ZURU标准版本。 4.如果大货有要求入邮包盒，则对应的邮包盒上面要打上日期码。 | AD92: Kelly Shen | AE92: 1.374 | AF92: =I92*AE92 -> 5276.16 | AG92: ZB05682-8.17 | AH92: 77876-S001 | AI92: 已入 | AJ92: 系统入单 | AK92: =I92*2 -> 7680 | AQ92: =I92*2 -> 7680 | AU92: =I92*2 -> 7680 | AV92: =I92*0.06*2 -> 460.8 | CD92: =BN92+BO92+BQ92+BS92+BR92 -> 0 | CE92: =BU92 -> 0 | CF92: =CC92 -> 0 | CG92: =BV92+BW92+BX92 -> 0 | CJ92: =I92 -> 3840 | CK92: =I92 -> 3840 | CL92: =I92 -> 3840
A93: 46108 | B93: AMAZON.COM SERVICES LLC | C93: 美国 | D93: 4500198817 | E93: 5A54748W | F93: 4500198817-10 | G93: 77876-S001 | H93: 唱片球2PK圆筒装 | I93: 1728 | J93: 0 | K93: 12 | L93: =I93/K93 -> 144 | M93: 46157 | N93: 46153 | Q93: PASS | T93: 1728 | U93: =T93-I93 -> 0 | V93: OK | W93: 46108 | X93: 有 | Y93: 4/28已寄SSCC Label | AC93: 日期码格式：ZURU INC(BVI) 标准格式 日期：按实际生产日期 Packaging Info: #77876:2PK MA 1L UPC版#77772入PVC桶，3L无UPC客版收缩膜，客版收缩膜和3L铜版纸图稿翻单4500192514.（两个球的配比不能重复）。2544PCS由Domestic PO450 0192506转单,6468PCS由Domestic PO4500192514转单。 Remark: 1. Amazon MDDP订单，出口US。 2. 日期码使用ZURU标准版本。 3. 如果大货有要求入邮包盒，则对应的邮包盒上面要打上日期码。 4. 箱尺寸要求：外箱最长边不能超过25"(超过了，case pack只能为1)，不符合要求的大货，一律不接受。 5. 外箱箱唛要求： ①外箱正面印ZURU Logo+SSCC Label(客供贴纸，由跟单订购)。关于 SSCC Label 请注意： SSCC Label显示的是客人自己的item#。每一张SSCC label都是唯一且有不同流水及条码的，没有损耗，绝对不可贴错。如果贴错或损坏任何一张，都会导致全部都 错，千万要注意！SSCC Label必须贴在外箱正面的正中间位置(贴一面即可)，并且贴纸离外箱边距必须至少3cm(可以覆盖Logo<(>&<)>箱唛)，否则会影响到客户那边 仓库的扫描识别。 ②外箱侧面印item#(订单上显示的SKU#)+carton size(以工厂实际尺寸为准，单位: inch)+MADE IN CHINA，日期使用ZURU 标准版本。 6. 装柜要求：按照客户PO#装柜/箱号顺序装柜，跟单会提前给到装柜计划。 在大货生产/仓库存放时，请留意该装柜要求，以便装柜时不混乱(避免装错/装漏/找不到货号等)。 | AD93: Kelly Shen | AE93: 1.374 | AF93: =AE93*I93 -> 2374.272 | AG93: ZB05721-8.17 | AH93: 77876-S001 | AI93: 已入 | AJ93: 系统入单 | AK93: =I93*2 -> 3456 | AQ93: =I93*2 -> 3456 | AU93: =I93*2 -> 3456 | AV93: =I93*0.06*2 -> 207.36 | CD93: =BN93+BO93+BQ93+BS93+BR93 -> 0 | CE93: =BU93 -> 0 | CF93: =CC93 -> 0 | CG93: =BV93+BW93+BX93 -> 0 | CJ93: =I93 -> 1728 | CK93: =I93 -> 1728 | CL93: =I93 -> 1728
A94: 46108 | B94: AMAZON.COM SERVICES LLC | C94: 美国 | D94: 4500198818 | E94: 8UHJAS7I | F94: 4500198818-10 | G94: 77876-S001 | H94: 唱片球2PK圆筒装 | I94: 3144 | J94: 0 | K94: 12 | L94: =I94/K94 -> 262 | M94: 46157 | N94: 46153 | Q94: PASS | T94: 3144 | U94: =T94-I94 -> 0 | V94: OK | W94: 46108 | X94: 有 | Y94: 4/28已寄SSCC Label | AC94: 日期码格式：ZURU INC(BVI) 标准格式 日期：按实际生产日期 Packaging Info: #77876:2PK MA 1L UPC版#77772入PVC桶，3L无UPC客版收缩膜，客版收缩膜和3L铜版纸图稿翻单4500192514.（两个球的配比不能重复）。2544PCS由Domestic PO450 0192506转单,6468PCS由Domestic PO4500192514转单。 Remark: 1. Amazon MDDP订单，出口US。 2. 日期码使用ZURU标准版本。 3. 如果大货有要求入邮包盒，则对应的邮包盒上面要打上日期码。 4. 箱尺寸要求：外箱最长边不能超过25"(超过了，case pack只能为1)，不符合要求的大货，一律不接受。 5. 外箱箱唛要求： ①外箱正面印ZURU Logo+SSCC Label(客供贴纸，由跟单订购)。关于 SSCC Label 请注意： SSCC Label显示的是客人自己的item#。每一张SSCC label都是唯一且有不同流水及条码的，没有损耗，绝对不可贴错。如果贴错或损坏任何一张，都会导致全部都 错，千万要注意！SSCC Label必须贴在外箱正面的正中间位置(贴一面即可)，并且贴纸离外箱边距必须至少3cm(可以覆盖Logo<(>&<)>箱唛)，否则会影响到客户那边 仓库的扫描识别。 ②外箱侧面印item#(订单上显示的SKU#)+carton size(以工厂实际尺寸为准，单位: inch)+MADE IN CHINA，日期使用ZURU 标准版本。 6. 装柜要求：按照客户PO#装柜/箱号顺序装柜，跟单会提前给到装柜计划。 在大货生产/仓库存放时，请留意该装柜要求，以便装柜时不混乱(避免装错/装漏/找不到货号等)。 | AD94: Kelly Shen | AE94: 1.374 | AF94: =AE94*I94 -> 4319.856 | AG94: ZB06211-8.17 | AH94: 77876-S001 | AI94: 已入 | AJ94: 系统入单 | AK94: =I94*2 -> 6288 | AQ94: =I94*2 -> 6288 | AU94: =I94*2 -> 6288 | AV94: =I94*0.06*2 -> 377.28 | CD94: =BN94+BO94+BQ94+BS94+BR94 -> 0 | CE94: =BU94 -> 0 | CF94: =CC94 -> 0 | CG94: =BV94+BW94+BX94 -> 0 | CJ94: =I94 -> 3144 | CK94: =I94 -> 3144 | CL94: =I94 -> 3144
A95: 46108 | B95: AMAZON.COM SERVICES LLC | C95: 美国 | D95: 4500198819 | E95: 5T99HRPW | F95: 4500198819-10 | G95: 77876-S001 | H95: 唱片球2PK圆筒装 | I95: 1428 | J95: 0 | K95: 12 | L95: =I95/K95 -> 119 | M95: 46157 | N95: 46153 | Q95: PASS | T95: 1428 | U95: =T95-I95 -> 0 | V95: OK | W95: 46108 | X95: 有 | Y95: 4/28已寄SSCC Label | AC95: 日期码格式：ZURU INC(BVI) 标准格式 日期：按实际生产日期 Packaging Info: #77876:2PK MA 1L UPC版#77772入PVC桶，3L无UPC客版收缩膜，客版收缩膜和3L铜版纸图稿翻单4500192514.（两个球的配比不能重复）。2544PCS由Domestic PO450 0192506转单,6468PCS由Domestic PO4500192514转单。 Remark: 1. Amazon MDDP订单，出口US。 2. 日期码使用ZURU标准版本。 3. 如果大货有要求入邮包盒，则对应的邮包盒上面要打上日期码。 4. 箱尺寸要求：外箱最长边不能超过25"(超过了，case pack只能为1)，不符合要求的大货，一律不接受。 5. 外箱箱唛要求： ①外箱正面印ZURU Logo+SSCC Label(客供贴纸，由跟单订购)。关于 SSCC Label 请注意： SSCC Label显示的是客人自己的item#。每一张SSCC label都是唯一且有不同流水及条码的，没有损耗，绝对不可贴错。如果贴错或损坏任何一张，都会导致全部都 错，千万要注意！SSCC Label必须贴在外箱正面的正中间位置(贴一面即可)，并且贴纸离外箱边距必须至少3cm(可以覆盖Logo<(>&<)>箱唛)，否则会影响到客户那边 仓库的扫描识别。 ②外箱侧面印item#(订单上显示的SKU#)+carton size(以工厂实际尺寸为准，单位: inch)+MADE IN CHINA，日期使用ZURU 标准版本。 6. 装柜要求：按照客户PO#装柜/箱号顺序装柜，跟单会提前给到装柜计划。 在大货生产/仓库存放时，请留意该装柜要求，以便装柜时不混乱(避免装错/装漏/找不到货号等)。 | AD95: Kelly Shen | AE95: 1.374 | AF95: =AE95*I95 -> 1962.072 | AG95: ZB05856-8.17 | AH95: 77876-S001 | AI95: 已入 | AJ95: 系统入单 | AK95: =I95*2 -> 2856 | AQ95: =I95*2 -> 2856 | AU95: =I95*2 -> 2856 | AV95: =I95*0.06*2 -> 171.36 | CD95: =BN95+BO95+BQ95+BS95+BR95 -> 0 | CE95: =BU95 -> 0 | CF95: =CC95 -> 0 | CG95: =BV95+BW95+BX95 -> 0 | CJ95: =I95 -> 1428 | CK95: =I95 -> 1428 | CL95: =I95 -> 1428
A96: 46108 | B96: AMAZON.COM SERVICES LLC | C96: 美国 | D96: 4500198821 | E96: 3K2YN21R | F96: 4500198821-10 | G96: 77876-S001 | H96: 唱片球2PK圆筒装 | I96: 1392 | J96: 0 | K96: 12 | L96: =I96/K96 -> 116 | M96: 46157 | N96: 46153 | Q96: PASS | T96: 1392 | U96: =T96-I96 -> 0 | V96: OK | W96: 46108 | X96: 有 | Y96: 4/28已寄SSCC Label | AC96: 日期码格式：ZURU INC(BVI) 标准格式 日期：按实际生产日期 Packaging Info: #77876:2PK MA 1L UPC版#77772入PVC桶，3L无UPC客版收缩膜，客版收缩膜和3L铜版纸图稿翻单4500192514.（两个球的配比不能重复）。 Remark: 1. Amazon MDDP订单，出口US。 2. 日期码使用ZURU标准版本。 3. 如果大货有要求入邮包盒，则对应的邮包盒上面要打上日期码。 4. 箱尺寸要求：外箱最长边不能超过25"(超过了，case pack只能为1)，不符合要求的大货，一律不接受。 5. 外箱箱唛要求： ①外箱正面印ZURU Logo+SSCC Label(客供贴纸，由跟单订购)。关于 SSCC Label 请注意： SSCC Label显示的是客人自己的item#。每一张SSCC label都是唯一且有不同流水及条码的，没有损耗，绝对不可贴错。如果贴错或损坏任何一张，都会导致全部都 错，千万要注意！SSCC Label必须贴在外箱正面的正中间位置(贴一面即可)，并且贴纸离外箱边距必须至少3cm(可以覆盖Logo<(>&<)>箱唛)，否则会影响到客户那边 仓库的扫描识别。 ②外箱侧面印item#(订单上显示的SKU#)+carton size(以工厂实际尺寸为准，单位: inch)+MADE IN CHINA，日期使用ZURU 标准版本。 6. 装柜要求：按照客户PO#装柜/箱号顺序装柜，跟单会提前给到装柜计划。 在大货生产/仓库存放时，请留意该装柜要求，以便装柜时不混乱(避免装错/装漏/找不到货号等)。 | AD96: Kelly Shen/Mia Pan/P | AE96: 1.374 | AF96: =AE96*I96 -> 1912.608 | AG96: ZB05723-8.17 | AH96: 77876-S001 | AI96: 已入 | AJ96: 系统入单 | AK96: =I96*2 -> 2784 | AQ96: =I96*2 -> 2784 | AU96: =I96*2 -> 2784 | AV96: =I96*0.06*2 -> 167.04 | CD96: =BN96+BO96+BQ96+BS96+BR96 -> 0 | CE96: =BU96 -> 0 | CF96: =CC96 -> 0 | CG96: =BV96+BW96+BX96 -> 0 | CJ96: =I96 -> 1392 | CK96: =I96 -> 1392 | CL96: =I96 -> 1392
A97: 46134 | D97: ZMPO260434 | F97: ZMPO260434-20 | G97: 77772-S001 | H97: 唱片球24 pcs/箱 | I97: 2400 | J97: 0 | K97: 24 | L97: =I97/K97 -> 100 | M97: 46157 | N97: 46153 | Q97: PASS | T97: 2400 | U97: =T97-I97 -> 0 | W97: 周转箱 | X97: 无 | Y97: 无 | AC97: Remark；大货最新版本/款号平均/麻烦按款号装箱/并在外箱上注明款号/大货标准箱装箱/箱唛参照邮件附件；备注：收到样品订单后尽快安排 ，注意样板品质质量要求要高于大货品质要求 ，送货时必须要附带送货单(没有送货单和QC检验合格报告的仓库一律拒绝收货)，请知悉，谢谢！ | AD97: Angus | AH97: 77772-S001 | AI97: 已入 | AJ97: 系统入单 | AK97: =I97 -> 2400 | AN97: =I97 -> 2400 | AU97: =I97 -> 2400 | AV97: =I97*0.06*2 -> 288 | CD97: =BN97+BO97+BQ97+BS97+BR97 -> 0 | CE97: =BU97 -> 0 | CF97: =CC97 -> 0 | CG97: =BV97+BW97+BX97 -> 0
A98: 46094 | B98: WONDERLAND TOYS, INC. | C98: 美国 | D98: 4500196710 | E98: 5286 | F98: 4500196710-20 | G98: 77772GQ1-S001 | H98: 唱片球52pcs/4PDQ/箱 | I98: 416 | J98: 0 | K98: 52 | L98: =I98/K98 -> 8 | M98: 46157 | N98: 46153 | Q98: PASS | T98: 416 | U98: =T98-I98 -> 0 | W98: 46119 | X98: 无 | Y98: 无 | AC98: 日期码格式：ZURU INC(BVI) 标准格式 日期：按实际生产日期 Packaging Info: 1. 出口美国MA UPC 版本包装，优先1L。FUGGLER item都可以按工厂实际库存调整装箱比例。 Remark: 8. ZURU QC 验货即可。 | AD98: Abby Mai | AE98: 0.6198 | AF98: =I98*AE98 -> 257.8368 | AG98: ZB05926-8.17 | AH98: 77772GQ1-S001 | AI98: 已入 | AJ98: 系统入单 | AK98: =I98 -> 416 | AN98: =I98 -> 416 | AU98: =I98 -> 416 | AV98: =I98*0.06 -> 24.96 | BK98: =I98/13 -> 32 | CD98: =BN98+BO98+BQ98+BS98+BR98 -> 0 | CE98: =BU98 -> 0 | CF98: =CC98 -> 0 | CG98: =BV98+BW98+BX98 -> 0
A99: 46094 | B99: ASDA STORES LTD | C99: 英国 | D99: 4500196674 | E99: 2950868300 | F99: 4500196674-20 | G99: 77772SLB-S002 | H99: 唱片球1040pcs/80PDQ/80CTN卡板装 | I99: 4160 | J99: 0 | K99: 1040 | L99: =I99/K99 -> 4 | M99: 46157 | N99: =M99-4 -> 46153 | Q99: PASS | S99: 4160 | T99: 4160 | U99: =T99-I99 -> 0 | W99: 46122 | X99: 无 | Y99: Slip Sheet打包好后，需要在正唛、侧唛右下角各贴一张slip sheet贴纸，直接用A4纸打印出来即可，贴纸尺寸160mm width x 140mm high； | Z99: 移除#21唱片 | AC99: 日期码格式：ZURU INC(BVI) 标准格式 日期：按实际生产日期 Packaging Info: 77772SLB-S002 MA最新UPC版本，条码请核对：193052090065 ，做货时请注意需移除LOLA YOUNG唱片 Slip sheet：77772GQ1-S002-PRODCC 13pcs/PDQ/CTN 20*4H=80CTN/SLB=1040pcs/Slip Sheet; 77794UQ1-S002 产品先入外箱再打SLIP SHEET, 客板PDQ+MA最新UPC包装+29L带电池出货WEEE说明书+加欧洲澳新通用Warning instruction 外箱正唛其中1面右上角贴UN3481贴纸，产品UPC :193052090409，请先检查条码是否正确再安排做货。 Slip sheet77794UQ1-S002 8pcs/PDQ/CTN 16*4H=64CTN/SLB=512pcs/Slip Sheet; 9574-S002 产品先入外箱再打SLIP SHEET, MA最新UPC包装+29L不带电池出货WEEE说明书，UPC :193052098436，请先检查条码是否正确再安排做货。 Slip sheet:9574-S002 1pcs/CTN (Carton Size: 31.7x18x25CM); 18*5H=90PCS/90CTN/SLB 77843GQ1-S002 产品先入外箱再打SLIP SHEET, MA最新UPC包装+29L带电池出货WEEE说明书，UPC :193052099105，请先检查条码是否正确再安排做货。 Slip sheet:77843GQ1-S002 13pcs/PDQ/CTN 15*5H=75CTN/SLB=975pcs/Slip Sheet; 92146TQ3-S001 产品先入外箱再打SLIP SHEET, MA_A_1L-UPC配套包装+客版PDQ，产品UPC :193052100375，请先检查条码是否正确再安排做货。 Slip sheet:92146TQ3-S001:2PCS/PDQ/CTN(Carton Size: 27.5x14.5x24.8CM):27*5H=135cartons=135*2pcs=270pcs/Slip Sheet; 92147-S002 产品先入外箱再打SLIP SHEET,MA_A_1L-UPC配套包装，产品UPC :1930521003825，请先检查条码是否正确再安排做货。 Slip sheet:92147-S002:1PCS/CTN(Carton Size: 25.0x22.0x32.0 CM):20*3H=60cartons=60*1pcs=60pcs/Slip Sheet; Slip Sheet打包好后，需要在正唛、侧唛右下角各贴一张slip sheet贴纸，直接用A4纸打印出来即可，贴纸尺寸160mm width x 140mm high； Slip Sheet尺寸限制为100*115*130CM，一旦实际SLIP SHEET尺寸超过这个尺寸，请提前通知ZURU跟单，需同客人确认才能量产和出货. Remark: 1. 产品及包装需要印UKCA图标，包装需要有ZURU UK LTD/ZURU France地址信息，QC同事请核查，如有问题与跟单确认 2. 产品/包装/外箱都需要打ZURU格式日期码，日期必须为法定工作日。 3. 需要符合欧洲标准不能含有闪粉和微塑料，否则不合法规会有客诉产生"" 4.涉及到硼的，如可选择情况下应使用低硼版本 （slime 类别低硼一般低于300ppm)，无选择的应与跟单复核再安排 。 5.如果出运产品属于电子类产品需要在ZURU 包装基础上额外添加一张ZURU 标准29L通用WEEE 电子产品说明书,带电池出货的加带电池出货版本通用29L的说明书，不 带电池出货的产品用不带电池出货版本的说明书 Order | AD99: Meyya Liu | AE99: 90.4614 | AF99: =L99*AE99 -> 361.8456 | AH99: 77772SLB-S002 | AI99: 已入 | AJ99: 系统入单 | AK99: =I99 -> 4160 | AN99: =I99 -> 4160 | AU99: =I99 -> 4160 | AV99: =I99*0.06 -> 249.6 | BK99: =I99/13 -> 320 | CD99: =BN99+BO99+BQ99+BS99+BR99 -> 0 | CE99: =BU99 -> 0 | CF99: =CC99 -> 0 | CG99: =BV99+BW99+BX99 -> 0
A100: 46108 | B100: TARGET US | C100: 美国 | D100: 4500199078 | E100: 1000176495 -0581 | F100: 4500199078-10 | G100: 77772GQ5-S001 | H100: 唱片球25 pcs/PDQ/箱 | I100: 25950 | J100: 0 | K100: 25 | L100: =I100/K100 -> 1038 | M100: 46160 | N100: 46156 | Q100: PASS | T100: 25950 | U100: =T100-I100 -> 0 | V100: OK | W100: 46128 | X100: 有 | Y100: 4/29已寄SSCC外箱贴纸+锂电池标签纸 | AC100: 日期码格式：ZURU INC(BVI) 标准格式 日期：按实际生产日期 Packaging Info: 产品包装MA 1L 收缩膜+MA 5L 收藏指南+MA 23L 组装说明+客版PDQ；客版PDQ翻单4500189603 Remark: 1.77772GQ5-S001-MINI BRANDS-VINYL-SERIES 1-CAPSULE,WITH DEMO,25PCS/GRAVITY PDQ,25PCS/PDQ/CTN; 2.产品包装MA 1L 收缩膜+MA 5L 收藏指南+MA 23L 组装说明+客版PDQ；客版PDQ翻单4500189603；收缩膜上的UPC显示193052090065; 4 mini vinyls(1 Target US Exclusive),1 accessory; 3. 外箱正唛左上角位置粘贴条码箱贴纸，每箱只贴一张，由ZURU订购。来料贴纸上显示的客户DPCI# 086-02-8931, UPC显示10193052090062; 4. 产品和包装上均要印刷tracking code信息，格式为ZURU常规格式； 5. 需要我司QC验货之后才能安排出货 6. 出货方式： 货代自提 | AD100: HollyZheng | AE100: 1.29 | AF100: =I100*AE100 -> 33475.5 | AG100: ZB05792-8.17 | AH100: 77772GQ5-S001 | AI100: 已入 | AJ100: 系统入单 | AM100: =I100 -> 25950 | AN100: =I100 -> 25950 | AU100: =I100 -> 25950 | AV100: =I100*0.06 -> 1557 | BU100: =I100/25 -> 1038 | CD100: =BN100+BO100+BQ100+BS100+BR100 -> 0 | CE100: =BU100 -> 1038 | CF100: =CC100 -> 0 | CG100: =BV100+BW100+BX100 -> 0
...

Sheet 77794
A1: 香港接单日期 | B1: 第三方客户名称 | C1: 走货国家 | D1: ZURU PO NO# | E1: 第三方客户 PO NO# | F1: SKU | G1: ITEM# | H1: 货品名称 | I1: PO数量(只) | J1: 内箱装箱数量(只) | K1: 外箱装箱数量(只) | L1: 总箱数 | M1: 计划出货期 | N1: 计划验货期 | O1: 第三方客户公证行验货 | P1: 验货结果 | Q1: S/O(截仓期) | R1: 箱唛 (收到日期) | S1: 外箱贴纸 | T1: 贴纸资料 (收到日期及订购日期) | U1: 额外说明书/保证书 | V1: 其他物料 | W1: 样办 | X1: 备注 | Y1: ZURU跟单组员 | Z1: 单价USD | AA1: 金额USD | AB1: 发票号 | AC1: 系统货号 | AD1: 是否入系统 | AE1: 订单数 | AF1: 生产情况 | AG1: 已回数量 | AH1: 欠数 | AI1: 贴纸 | AJ1: 下单情况 | AK1: MA 1L A彩盒 | AL1: MA 3L A彩盒 | AM1: 客版彩盒 | AN1: MA 5L 说明书 | AO1: 客版说明书 | AP1: 中文说明书 | AQ1: COSTCO 客版说明书 | AR1: COSTCO 客版彩盒 | AS1: COSTCO 客版PDQ | AT1: UQ1 1L 8pcs | AU1: UQ1 3L 8pcs | AV1: UQ3客版PDQ | AW1: UQ1 客版PDQ 取消17款唱片 | AX1: UQ1 8pcs 客版 PDQ 取消21/23唱片 | AY1: UQ2 6pcs 客版 PDQ | AZ1: UQ3 2pcs 客版 PDQ | BA1: MEC426 （MA 1L） | BB1: 胶袋 | BC1: MEC457 | BD1: MEC473 | BE1: MSLD188 | BF1: MSLD182 | BG1: SK-S001 | BH1: 77897-S001 | BI1: 77869彩盒
A2: 45989 | B2: 库有 | C2: PP | D2: ZPO2511015 | F2: ZPO2511015-20 | G2: 77794-S001 | H2: 唱片机16pcs/箱 | I2: 424 | J2: 0 | K2: 16 | L2: =I2/K2 -> 26.5 | M2: 46048 | N2: 46044 | Y2: Fiona Ouyang | AD2: # | AE2: =I2 -> 424
A3: 46031 | D3: ZMPO260027 | F3: ZMPO260027-10 | G3: 77794-S001 | H3: 唱片机16pcs/箱 | I3: 240 | J3: 0 | K3: 16 | L3: =I3/K3 -> 15 | M3: 46048 | N3: 46044 | P3: PASS | R3: 46031 | S3: 有 | T3: 无 | X3: Remark:大货最新版本/麻烦按款号装箱/并在外箱上注明款号/大货标准箱装箱/箱唛参照邮件附件 备注：收到样品订单后尽快安排 ，注意样板品质质量要求要高于大货品质要求 ，送货时必须要附带送货单(没有送货单和QC检验合格报告的仓库一律拒绝收货)，请知悉，谢谢！ | AD3: # | AE3: =I3 -> 240 | AG3: 240 | AH3: =AG3-I3 -> 0 | AN3: =I3 -> 240
A4: 46031 | D4: ZMPO260027 | F4: ZMPO260027-20 | G4: 77794UQ1-S001 | H4: 唱片机空PDQ | I4: 100个空PDQ | J4: 0 | K4: 16 | M4: 46048 | N4: 46044 | P4: PASS | R4: 46031 | S4: 有 | T4: 无 | X4: Remark:大货最新版本/只需要空PDQ/PDQ可打平包寄出 备注：收到样品订单后尽快安排 ，注意样板品质质量要求要高于大货品质要求 ，送货时必须要附带送货单(没有送货单和QC检验合格报告的仓库一律拒绝收货)，请知悉，谢谢！ | AB4: -9 | AD4: # | AH4: =AG4-I4 -> #VALUE! | AT4: 100
A5: 46029 | B5: ZURU NEW ZEALAND LIMITED | C5: 新西兰 | D5: 4500190798 | E5: 5200008655 | F5: 4500190798-20 | G5: 77794UQ1-S002-FS | H5: 唱片机8pcs/UQ1/箱 | I5: 32 | J5: 0 | K5: 8 | L5: =I5/K5 -> 4 | M5: 46059 | N5: 46055 | O5: 试销单 | R5: 46029 | S5: 有 | T5: 箱需要增加一张黄色A4贴纸，印“fast start"。 | X5: 日期码格式：ZURU INC(BVI) 标准格式 日期：按实际生产日期 Packaging Info: Remark: NZ Fast start order, 从PP PO中扣除，每款需要更换UPC贴纸，除常规箱唛外，每箱需要增加一张黄色A4贴纸，印“fast start"。 | Y5: Holly Zheng | Z5: 5 | AA5: =Z5*I5 -> 160 | AC5: 77794UQ1-S002 | AD5: 已入 | AH5: =AG5-I5 -> -32 | AJ5: 系统出单
A6: 46014 | B6: TARGET US | C6: 美国 | D6: 4500189603 | E6: 10001643491-3 890 | F6: 4500189603-20 | G6: 77794UQ1-S002 | H6: 唱片机8pcs/UQ1/箱 | I6: 15600 | J6: 0 | K6: 8 | L6: =I6/K6 -> 1950 | M6: 46085 | N6: =M6-4 -> 46081 | P6: PASS | Q6: 3/17 出货 | R6: 46027 | S6: 有 | T6: 1/22 寄出 | V6: 客版PDQ | X6: 日期码格式：ZURU INC(BVI) 标准格式 日期：按实际生产日期 Packaging Info: 77794UQ1：产品包装 MA 1L包装，MA 1L PDQ Remark: 77794UQ1： 1.77794UQ1-S002-MINI BRANDS-VINYL-PLAYSET-SERIES 1-CUBE,8PCS/PDQ,8PCS/PDQ/CTN； 2.产品包装 MA 1L包装，MA 1L PDQ； 3.产品UPC显示193052090409； 4. 外箱正唛左上角位置粘贴条码箱贴纸，每箱只贴一张，由ZURU订购。来料贴纸上显示的客户DPCI# 086-02-4085, UPC显示10193052090406; 5. 外箱正唛箱唛内容右侧需贴一张EVENT LABEL，内容显示：TOYS SET DATE: 5/31/2026，由工厂自行订购； 6. 产品和包装上印刷 tracking code信息，格式为ZURU常规格式; 7. 出货方式：货代自提； 8. 带锂电池出货，需在外箱正面或者侧面合适位置上加贴一张贴锂电池标签纸，由工厂订购 | Y6: Holly Zheng | Z6: 2.88 | AA6: =Z6*I6 -> 44928 | AB6: ZB04936/ZB04937 | AC6: 77794UQ1-S002 | AD6: 已入 | AE6: =I6 -> 15600 | AF6: 东莞生产 | AH6: =AG6-I6 -> -15600 | AI6: OK | AJ6: 系统出单 | AK6: =I6 -> 15600 | AN6: =I6 -> 15600 | AT6: =I6/8 -> 1950
A7: 46013 | B7: TARGET US | C7: 美国 | D7: 4500189608 | E7: 10001643496-3 890 | F7: 4500189608-20 | G7: 77794UQ1-S002 | H7: 唱片机8pcs/UQ1/箱 | I7: 34400 | J7: 0 | K7: 8 | L7: =I7/K7 -> 4300 | M7: 46091 | N7: 46087 | P7: PASS | R7: 46027 | S7: 有 | T7: 1/22 寄出 | V7: 客版PDQ | X7: 日期码格式：ZURU INC(BVI) 标准格式 日期：按实际生产日期 Packaging Info: 77794UQ1：产品包装 MA 1L包装，MA 1L PDQ Remark: 77794UQ1： 1.77794UQ1-S002-MINI BRANDS-VINYL-PLAYSET-SERIES 1-CUBE,8PCS/PDQ,8PCS/PDQ/CTN； 2.产品包装 MA 1L包装，MA 1L PDQ； 3.产品UPC显示193052090409； 4. 外箱正唛左上角位置粘贴条码箱贴纸，每箱只贴一张，由ZURU订购。来料贴纸上显示的客户DPCI# 086-02-4085, UPC显示10193052090406; 5. 产品和包装上印刷 tracking code信息，格式为ZURU常规格式; 6. 出货方式：货代自提 7. 带锂电池出货，需在外箱正面或者侧面合适位置上加贴一张贴锂电池标签纸，由工厂订购 | Y7: Holly Zheng | Z7: 2.88 | AA7: =Z7*I7 -> 99072 | AB7: ZB04934/ZB04935 | AC7: 77794UQ1-S002 | AD7: 已入 | AE7: =I7 -> 34400 | AG7: =34400+12296+4848+17856 -> 69400 | AH7: =AG7-I7 -> 35000 | AI7: OK | AJ7: 系统出单 | AK7: =I7 -> 34400 | AN7: =I7 -> 34400 | AT7: =I7/8 -> 4300
A8: 46044 | B8: SMYTHS TOYS EU HQ UNLIMITED COMPANY | C8: 法国 | D8: 4500191989 | E8: 4400528766 | F8: 4500191989-10 | G8: MEC457-77794-S001 | H8: 唱片机+唱片球混装展示架 | I8: 2016 | J8: 0 | K8: 48 | L8: =I8/K8 -> 42 | M8: 46097 | N8: 46093 | P8: PASS | Q8: 4/6 出货 | R8: 46044 | S8: 有 | T8: UN3481锂电池运输标签 | X8: 日期码格式：ZURU INC(BVI) 标准格式 日期：按实际生产日期 Packaging Info: MEC457: 客版5L(英法德意荷)展示架[84pcs#77772+48pcs#77794; 所有客版资料翻PO#4500191961] 77772: 客版3L-5Lwarning收缩膜+客版5L收藏指南+MA 23L组装说明+MA复合袋 EAN#4894680051133 77794: 客版3L-5Lwarning纸盒底座+客版3L镭射贴纸+客版3L单铜纸贴纸+MA23L游戏说明书+MA23L warning说明书+1张WEEE声明(带电池)走货欧洲通用29L-C版说明 书 EAN#4894680051430 做货前请先核对条码无误 RECHARGEABLE LITHIUM BATTERY(INCLUDED) *#77772必须移除Messy Lola Young (VINYL-S1-021) 这个唱片, 比例按PM更新的安排* *展架上的Demo Box的唱片需要用"A Little Too Much"(VINYL-S1-025)替代原来的"Messy"(VINYL-S1-021)* *外箱需加一张UN3481锂电池运输标签* Remark: Smyths 法国 1. 请准时出货，推期会有罚款； 2. 所有产品按符合欧洲标准走货，需要是不含微塑料版本。 3. 电子产品需增加一张WEEE声明30L通用黑白说明书(不接受A版本，翻译有误)，区分带电池和不带电池出货版本, 如已做客版说明书可忽略此要求； 4. 出口法国的产品, 法规规定禁止在包装和共公众用的印刷品中使用矿物油中含有的物质, 包装印刷油墨中含有的MOAH/MOSH的质量浓度不能超过1%, 否则出货到 法国被抽检出现问题, 供应商需要对此负责; 5.订单备注显示有分批的（不同仓库/订单号） ，注意分开做货出货，否则会导致罚款 。 6.包装日期码按ZURU格式即可，请确保不迟于外箱日期码，可等于或者早于外箱日期码，必须为法定工作日。 7.做货前请先复核包装条码与订单是否一致再安排，对不上的需与ZURU跟单确认再安排。 | Y8: Sherry Lu | Z8: 306.676 | AA8: =L8*Z8 -> 12880.392 | AC8: MEC457-S001-77794 | AD8: 已入 | AE8: =I8 -> 2016 | AG8: 2016 | AH8: =AG8-I8 -> 0 | AJ8: 系统出单 | AM8: =I8 -> 2016 | AN8: =I8 -> 2016 | BA8: =I8/K8 -> 42
A9: 46044 | B9: SMYTHS TOYS EU HQ UNLIMITED COMPANY | C9: 法国 | D9: 4500191989 | E9: 4400528767 | F9: 4500191989-20 | G9: MEC457-77794-S001 | H9: 唱片机+唱片球混装展示架 | I9: 864 | J9: 0 | K9: 48 | L9: =I9/K9 -> 18 | M9: 46097 | N9: 46093 | P9: PASS | Q9: 4/7 出货 | R9: 46044 | S9: 有 | T9: UN3481锂电池运输标签 | X9: 日期码格式：ZURU INC(BVI) 标准格式 日期：按实际生产日期 Packaging Info: MEC457: 客版5L(英法德意荷)展示架[84pcs#77772+48pcs#77794; 所有客版资料翻PO#4500191961] 77772: 客版3L-5Lwarning收缩膜+客版5L收藏指南+MA 23L组装说明+MA复合袋 EAN#4894680051133 77794: 客版3L-5Lwarning纸盒底座+客版3L镭射贴纸+客版3L单铜纸贴纸+MA23L游戏说明书+MA23L warning说明书+1张WEEE声明(带电池)走货欧洲通用29L-C版说明 书 EAN#4894680051430 做货前请先核对条码无误 RECHARGEABLE LITHIUM BATTERY(INCLUDED) *#77772必须移除Messy Lola Young (VINYL-S1-021) 这个唱片, 比例按PM更新的安排* *展架上的Demo Box的唱片需要用"A Little Too Much"(VINYL-S1-025)替代原来的"Messy"(VINYL-S1-021)* *外箱需加一张UN3481锂电池运输标签* Remark: Smyths 法国 1. 请准时出货，推期会有罚款； 2. 所有产品按符合欧洲标准走货，需要是不含微塑料版本。 3. 电子产品需增加一张WEEE声明30L通用黑白说明书(不接受A版本，翻译有误)，区分带电池和不带电池出货版本, 如已做客版说明书可忽略此要求； 4. 出口法国的产品, 法规规定禁止在包装和共公众用的印刷品中使用矿物油中含有的物质, 包装印刷油墨中含有的MOAH/MOSH的质量浓度不能超过1%, 否则出货到 法国被抽检出现问题, 供应商需要对此负责; 5.订单备注显示有分批的（不同仓库/订单号） ，注意分开做货出货，否则会导致罚款 。 6.包装日期码按ZURU格式即可，请确保不迟于外箱日期码，可等于或者早于外箱日期码，必须为法定工作日。 7.做货前请先复核包装条码与订单是否一致再安排，对不上的需与ZURU跟单确认再安排。 | Y9: Sherry Lu | Z9: 306.676 | AA9: =L9*Z9 -> 5520.168 | AC9: MEC457-S001-77794 | AD9: 已入 | AE9: =I9 -> 864 | AG9: 864 | AH9: =AG9-I9 -> 0 | AJ9: 系统出单 | AM9: =I9 -> 864 | AN9: =I9 -> 864 | BA9: =I9/K9 -> 18
A10: 46043 | B10: SMYTHS TOYS HQ UC UK | C10: 英国 | D10: 4500191960 | E10: 4400528768 | F10: 4500191960-20 | G10: 77794UQ1-S001 | H10: 唱片机16pcs/2 UQ1/箱 | I10: 5008 | J10: 0 | K10: 16 | L10: =I10/K10 -> 313 | M10: 46097 | N10: 46093 | P10: PASS | Q10: 3/22 截SI | R10: 46044 | S10: 有 | T10: 新地址贴纸ZURU FRANCE.33 rue Paul Meurice 75020 Paris, France.+WEEE声明29L通用黑白说明书+UN3481锂电池运输标签 | X10: 日期码格式：ZURU INC(BVI) 标准格式 日期：按实际生产日期 Packaging Info: 77794UQ1客版5L(英法德意荷)配套包装=MA PDQ (优先多语)+客版3L-5Lwarning纸盒底座(翻PO#4500191961)+MA23L游戏说明书+MA23L warning说明书+1张WEEE声明( 带电池)走货欧洲通用30L-B版说明书 EAN#4894680051430 RECHARGEABLE LITHIUM BATTERY(INCLUDED) Remark: Smyths 英国/爱尔兰 1. 请准时出货，推期会有罚款； 2. 所有产品按符合欧洲标准走货，需要是不含微塑料版本。 3.包装日期码按ZURU格式即可，请确保不迟于外箱日期码，可等于或者早于外箱日期码，必须为法定工作日，印刷前请先检查外箱日期码。 4.请注意检查产品及包装应带UKCA图标（14+产品除外），包装显示ZURU UK LTD/ZURU France地址信息，QC部门请查核，如有问题与跟单确认 5.电子产品需增加一张WEEE声明30L通用黑白说明书(不接受A版本，翻译有误)，区分带电池和不带电池出货版本, 如已做客版说明书可忽略此要求； 6.订单备注显示有分批的（不同仓库/订单号） ，注意分开做货出货，否则会导致罚款 。 7.做货前请先复核包装条码与订单是否一致再安排，对不上的需与ZURU跟单确认再安排。 | Y10: Sherry Lu | Z10: 4.355 | AA10: =I10*Z10 -> 21809.84 | AC10: 77794UQ1-S001-客版 | AD10: 已入 | AE10: =I10 -> 5008 | AG10: 5008 | AH10: =AG10-I10 -> 0 | AI10: OK | AJ10: 系统出单 | AM10: =I10 -> 5008 | AN10: =I10 -> 5008 | AU10: =I10/8 -> 626
A11: 46043 | B11: SMYTHS TOYS HQ UC IE | C11: 爱尔兰 | D11: 4500191968 | E11: 4400528769 | F11: 4500191968-10 | G11: 77794UQ1-S001 | H11: 唱片机16pcs/2 UQ1/箱 | I11: 2512 | J11: 0 | K11: 16 | L11: =I11/K11 -> 157 | M11: 46097 | N11: 46093 | P11: PASS | Q11: 3/18 截SI | R11: 46044 | S11: 有 | T11: UN3481锂电池运输标签 | X11: 日期码格式：ZURU INC(BVI) 标准格式 日期：按实际生产日期 Packaging Info: 77794UQ1客版5L(英法德意荷)配套包装=MA PDQ (优先多语)+客版3L-5Lwarning纸盒底座(翻PO#4500191961)+MA23L游戏说明书+MA23L warning说明书+1张WEEE声明( 带电池)走货欧洲通用30L-B版说明书 EAN#4894680051430 RECHARGEABLE LITHIUM BATTERY(INCLUDED) Remark: Smyths 英国/爱尔兰 1. 请准时出货，推期会有罚款； 2. 所有产品按符合欧洲标准走货，需要是不含微塑料版本。 3.包装日期码按ZURU格式即可，请确保不迟于外箱日期码，可等于或者早于外箱日期码，必须为法定工作日，印刷前请先检查外箱日期码。 4.请注意检查产品及包装应带UKCA图标（14+产品除外），包装显示ZURU UK LTD/ZURU France地址信息，QC部门请查核，如有问题与跟单确认 5.电子产品需增加一张WEEE声明30L通用黑白说明书(不接受A版本，翻译有误)，区分带电池和不带电池出货版本, 如已做客版说明书可忽略此要求； 6.订单备注显示有分批的（不同仓库/订单号） ，注意分开做货出货，否则会导致罚款 。 7.做货前请先复核包装条码与订单是否一致再安排，对不上的需与ZURU跟单确认再安排。 | Y11: Sherry Lu | Z11: 4.355 | AA11: =I11*Z11 -> 10939.76 | AC11: 77794UQ1-S001-客版 | AD11: 已入 | AE11: =I11 -> 2512 | AG11: 2512 | AH11: =AG11-I11 -> 0 | AI11: OK | AJ11: 系统出单 | AM11: =I11 -> 2512 | AN11: =I11 -> 2512 | AU11: =I11/8 -> 314
A12: 46084 | B12: ZURU NEW ZEALAND LIMITED | C12: 新西兰 | D12: 4500194964 | E12: 5200009119 | F12: 4500194964-20 | G12: 77794UQ1-S002-FS | H12: 唱片机8pcs/UQ1/箱 | I12: 32 | J12: 0 | K12: 8 | L12: =I12/K12 -> 4 | M12: 46097 | N12: 46093 | P12: PASS | R12: 46029 | S12: 有 | T12: 箱需要增加一张黄色A4贴纸，印“fast start"。 | X12: 日期码格式：ZURU INC(BVI) 标准格式 日期：按实际生产日期 Packaging Info: Remark: NZ Fast start order, 每款需要更换UPC贴纸，除常规箱唛外，每箱需要增加一张黄色A4贴纸，印"fast start"。 | Y12: SD92 | Z12: 5 | AA12: =I12*Z12 -> 160 | AC12: 77794UQ1-S002 | AD12: 已入 | AE12: =I12 -> 32 | AG12: 32 | AH12: =AG12-I12 -> 0 | AJ12: 系统出单 | AK12: =I12 -> 32 | AN12: =I12 -> 32 | AT12: =I12/8 -> 4
A13: 46044 | B13: SMYTHS TOYS HQ UC | C13: 法国 | D13: 4500191990 | E13: 4400528766 | F13: 4500191990-20 | G13: 77794UQ1-S001 | H13: 唱片机16pcs/2 UQ1/箱 | I13: 560 | J13: 0 | K13: 16 | L13: =I13/K13 -> 35 | M13: 46098 | N13: 46094 | P13: PASS | R13: 46044 | S13: 有 | T13: UN3481锂电池运输标签 | X13: 日期码格式：ZURU INC(BVI) 标准格式 日期：按实际生产日期 Packaging Info: 77794UQ1: MA PDQ (优先多语)+客版5L(英法德意荷)配套包装 (翻PO#4500191961) EAN#4894680051430 RECHARGEABLE LITHIUM BATTERY(INCLUDED) Remark: Smyths 法国 1. 请准时出货，推期会有罚款； 2. 所有产品按符合欧洲标准走货，需要是不含微塑料版本。 3. 电子产品需增加一张WEEE声明30L通用黑白说明书(不接受A版本，翻译有误)，区分带电池和不带电池出货版本, 如已做客版说明书可忽略此要求； 4. 出口法国的产品, 法规规定禁止在包装和共公众用的印刷品中使用矿物油中含有的物质, 包装印刷油墨中含有的MOAH/MOSH的质量浓度不能超过1%, 否则出货到 法国被抽检出现问题, 供应商需要对此负责; 5.订单备注显示有分批的（不同仓库/订单号） ，注意分开做货出货，否则会导致罚款 。 6.包装日期码按ZURU格式即可，请确保不迟于外箱日期码，可等于或者早于外箱日期码，必须为法定工作日。 7.做货前请先复核包装条码与订单是否一致再安排，对不上的需与ZURU跟单确认再安排。 | Y13: Sherry Lu | Z13: 4.355 | AA13: =I13*Z13 -> 2438.8 | AC13: 77794UQ1-S001-客版 | AD13: 已入 | AE13: =I13 -> 560 | AG13: 560 | AH13: =AG13-I13 -> 0 | AI13: OK | AJ13: 系统出单 | AM13: =I13 -> 560 | AN13: =I13 -> 560 | AU13: =I13/8 -> 70
A14: 46044 | B14: SMYTHS TOYS HQ UC | C14: 法国 | D14: 4500191990 | E14: 4400528767 | F14: 4500191990-40 | G14: 77794UQ1-S001 | H14: 唱片机16pcs/2 UQ1/箱 | I14: 240 | J14: 0 | K14: 16 | L14: =I14/K14 -> 15 | M14: 46098 | N14: 46094 | P14: PASS | Q14: 4/6 出货 | R14: 46044 | S14: 有 | T14: UN3481锂电池运输标签 | X14: 日期码格式：ZURU INC(BVI) 标准格式 日期：按实际生产日期 Packaging Info: 77794UQ1: MA PDQ (优先多语)+客版5L(英法德意荷)配套包装 (翻PO#4500191961) EAN#4894680051430 RECHARGEABLE LITHIUM BATTERY(INCLUDED) Remark: Smyths 法国 1. 请准时出货，推期会有罚款； 2. 所有产品按符合欧洲标准走货，需要是不含微塑料版本。 3. 电子产品需增加一张WEEE声明30L通用黑白说明书(不接受A版本，翻译有误)，区分带电池和不带电池出货版本, 如已做客版说明书可忽略此要求； 4. 出口法国的产品, 法规规定禁止在包装和共公众用的印刷品中使用矿物油中含有的物质, 包装印刷油墨中含有的MOAH/MOSH的质量浓度不能超过1%, 否则出货到 法国被抽检出现问题, 供应商需要对此负责; 5.订单备注显示有分批的（不同仓库/订单号） ，注意分开做货出货，否则会导致罚款 。 6.包装日期码按ZURU格式即可，请确保不迟于外箱日期码，可等于或者早于外箱日期码，必须为法定工作日。 7.做货前请先复核包装条码与订单是否一致再安排，对不上的需与ZURU跟单确认再安排。 | Y14: Sherry Lu | Z14: 4.355 | AA14: =I14*Z14 -> 1045.2 | AC14: 77794UQ1-S001-客版 | AD14: 已入 | AE14: =I14 -> 240 | AG14: 240 | AH14: =AG14-I14 -> 0 | AI14: OK | AJ14: 系统出单 | AM14: =I14 -> 240 | AN14: =I14 -> 240 | AU14: =I14/8 -> 30
A15: 46043 | B15: SMYTHS TOYS HQ UC UK | C15: 英国 | D15: 4500191961 | E15: 4400528768 | F15: 4500191961-10 | G15: MEC457-77794-S001 | H15: 唱片机+唱片球混装展示架 | I15: 6384 | J15: 0 | K15: 48 | L15: =I15/K15 -> 133 | M15: 46098 | N15: 46094 | P15: PASS | Q15: 4/6 出货 | R15: 46044 | S15: 有 | T15: 新地址贴纸ZURU FRANCE.33 rue Paul Meurice 75020 Paris, France.+WEEE声明29L通用黑白说明书+UN3481锂电池运输标签 | X15: 日期码格式：ZURU INC(BVI) 标准格式 日期：按实际生产日期 Packaging Info: MEC457: 客版5L(英法德意荷)展示架[84pcs#77772+48pcs#77794; 所有客版资料翻PO#4500191961] 77772: 客版3L-5Lwarning收缩膜+客版5L收藏指南+MA 23L组装说明+MA复合袋 EAN#4894680051133 77794: 客版3L-5Lwarning纸盒底座+客版3L镭射贴纸+客版3L单铜纸贴纸+MA23L游戏说明书+MA23L warning说明书+1张WEEE声明(带电池)走货欧洲通用29L-C版说明 书 EAN#4894680051430 做货前请先核对条码无误 RECHARGEABLE LITHIUM BATTERY(INCLUDED) *#77772必须移除Messy Lola Young (VINYL-S1-021) 这个唱片, 比例按PM更新的安排* *展架上的Demo Box的唱片需要用"A Little Too Much"(VINYL-S1-025)替代原来的"Messy"(VINYL-S1-021)* *外箱需加一张UN3481锂电池运输标签* Remark: Smyths 英国/爱尔兰 1. 请准时出货，推期会有罚款； 2. 所有产品按符合欧洲标准走货，需要是不含微塑料版本。 3.包装日期码按ZURU格式即可，请确保不迟于外箱日期码，可等于或者早于外箱日期码，必须为法定工作日，印刷前请先检查外箱日期码。 4.请注意检查产品及包装应带UKCA图标（14+产品除外），包装显示ZURU UK LTD/ZURU France地址信息，QC部门请查核，如有问题与跟单确认 5.电子产品需增加一张WEEE声明30L通用黑白说明书(不接受A版本，翻译有误)，区分带电池和不带电池出货版本, 如已做客版说明书可忽略此要求； 6.订单备注显示有分批的（不同仓库/订单号） ，注意分开做货出货，否则会导致罚款 。 7.做货前请先复核包装条码与订单是否一致再安排，对不上的需与ZURU跟单确认再安排。 | Y15: Sherry Lu | Z15: 306.676 | AA15: =L15*Z15 -> 40787.908 | AC15: MEC457-S001-77794 | AD15: 已入 | AE15: =I15 -> 6384 | AG15: =3442+2741+201 -> 6384 | AH15: =AG15-I15 -> 0 | AI15: OK | AJ15: 系统出单 | AM15: =I15 -> 6384 | AN15: =I15 -> 6384 | BA15: =I15/K15 -> 133
A16: 46043 | B16: SMYTHS TOYS HQ UC IE | C16: 爱尔兰 | D16: 4500191969 | E16: 4400528769 | F16: 4500191969-20 | G16: MEC457-77794-S001 | H16: 唱片机+唱片球混装展示架 | I16: 1536 | J16: 0 | K16: 48 | L16: =I16/K16 -> 32 | M16: 46099 | N16: 46095 | P16: PASS | Q16: 4/2 出货 | R16: 46044 | S16: 有 | T16: UN3481锂电池运输标签 | X16: 日期码格式：ZURU INC(BVI) 标准格式 日期：按实际生产日期 Packaging Info: ------------------------------------------------------------------- MEC457: 客版5L(英法德意荷)展示架[84pcs#77772+48pcs#77794; 所有客版资料翻PO#4500191961] 77772: 客版3L-5Lwarning收缩膜+客版5L收藏指南+MA 23L组装说明+MA复合袋 EAN#4894680051133 77794: 客版3L-5Lwarning纸盒底座+客版3L镭射贴纸+客版3L单铜纸贴纸+MA23L游戏说明书+MA23L warning说明书+1张WEEE声明(带电池)走货欧洲通用29L-C版说明 书 EAN#4894680051430 做货前请先核对条码无误 RECHARGEABLE LITHIUM BATTERY(INCLUDED) *#77772必须移除Messy Lola Young (VINYL-S1-021) 这个唱片, 比例按PM更新的安排* *展架上的Demo Box的唱片需要用"A Little Too Much"(VINYL-S1-025)替代原来的"Messy"(VINYL-S1-021)* *外箱需加一张UN3481锂电池运输标签* Remark: Smyths 英国/爱尔兰 1. 请准时出货，推期会有罚款； 2. 所有产品按符合欧洲标准走货，需要是不含微塑料版本。 3.包装日期码按ZURU格式即可，请确保不迟于外箱日期码，可等于或者早于外箱日期码，必须为法定工作日，印刷前请先检查外箱日期码。 4.请注意检查产品及包装应带UKCA图标（14+产品除外），包装显示ZURU UK LTD/ZURU France地址信息，QC部门请查核，如有问题与跟单确认 5.电子产品需增加一张WEEE声明30L通用黑白说明书(不接受A版本，翻译有误)，区分带电池和不带电池出货版本, 如已做客版说明书可忽略此要求； 6.订单备注显示有分批的（不同仓库/订单号） ，注意分开做货出货，否则会导致罚款 。 7.做货前请先复核包装条码与订单是否一致再安排，对不上的需与ZURU跟单确认再安排。 | Y16: Sherry Lu | Z16: 306.676 | AA16: =L16*Z16 -> 9813.632 | AC16: MEC457-S001-77794 | AD16: 已入 | AE16: =I16 -> 1536 | AG16: 1536 | AH16: =AG16-I16 -> 0 | AJ16: 系统出单 | AM16: =I16 -> 1536 | AN16: =I16 -> 1536 | BA16: =I16/K16 -> 32
A17: 46044 | B17: SMYTHS TOYS EU HQ UC | C17: 德国 | D17: 4500191996 | E17: 4400528770 | F17: 4500191996-10 | G17: 77794UQ1-S001 | H17: 唱片机16pcs/2 UQ1/箱 | I17: 992 | J17: 0 | K17: 16 | L17: =I17/K17 -> 62 | M17: 46099 | N17: 46095 | P17: PASS | R17: 46044 | S17: 有 | T17: UN3481锂电池运输标签 | V17: 所有电子产品身上需要加字唛，为ZURU FRANCE 地址 (如无电子产品，产品布标有此地址，或产品太小无法增加可忽略此信息)，新地址ZURU FRANCE.33 rue Paul Meurice 75020 Paris, France. | X17: 日期码格式：ZURU INC(BVI) 标准格式 日期：按实际生产日期 Packaging Info: -------------------------------------------------------------------- 77794UQ1客版5L(英法德意荷)配套包装=MA PDQ (优先多语)+客版3L-5Lwarning纸盒底座(翻PO#4500191961)+MA23L游戏说明书+MA23L warning说明书+1张WEEE声明( 带电池)走货欧洲通用30L-B版说明书 EAN#4894680051430 RECHARGEABLE LITHIUM BATTERY(INCLUDED) Remark: Smyths 德国 1. 请准时出货，推期会有罚款； 2. 所有产品按符合欧洲标准走货，需要是不含微塑料版本。 3. 所有电子产品身上需要加字唛，为ZURU FRANCE 地址 (如无电子产品，产品布标有此地址，或产品太小无法增加可忽略此信息)，新地址ZURU FRANCE.33 rue Pa ul Meurice 75020 Paris, France. 4. 电子产品需增加一张WEEE声明30L通用黑白说明书(不接受A版本，翻译有误)，区分带电池和不带电池出货版本, 如已做客版说明书可忽略此要求； 5.所有出往德国市场有关slime和带香味的都需要出无硼无香版本； 6.订单备注显示有分批的（不同仓库/订单号） ，注意分开做货出货，否则会导致罚款 。 7.包装日期码按ZURU格式即可，请确保不迟于外箱日期码，可等于或者早于外箱日期码，必须为法定工作日。 8.做货前请先复核包装条码与订单是否一致再安排，对不上的需与ZURU跟单确认再安排。 | Y17: Sherry Lu | Z17: 4.355 | AA17: =I17*Z17 -> 4320.16 | AC17: 77794UQ1-S001-客版 | AD17: 已入 | AE17: =I17 -> 992 | AG17: 992 | AH17: =AG17-I17 -> 0 | AI17: OK | AJ17: 系统出单 | AM17: =I17 -> 992 | AN17: =I17 -> 992 | AU17: =I17/8 -> 124
A18: 46044 | B18: SMYTHS TOYS EU HQ UC | C18: 德国 | D18: 4500191996 | E18: 4400528771 | F18: 4500191996-30 | G18: 77794UQ1-S001 | H18: 唱片机16pcs/2 UQ1/箱 | I18: 608 | J18: 0 | K18: 16 | L18: =I18/K18 -> 38 | M18: 46099 | N18: 46095 | P18: PASS | Q18: 3/24 出货 | R18: 46044 | S18: 有 | T18: UN3481锂电池运输标签 | V18: 所有电子产品身上需要加字唛，为ZURU FRANCE 地址 (如无电子产品，产品布标有此地址，或产品太小无法增加可忽略此信息)，新地址ZURU FRANCE.33 rue Paul Meurice 75020 Paris, France. | X18: 日期码格式：ZURU INC(BVI) 标准格式 日期：按实际生产日期 Packaging Info: -------------------------------------------------------------------- 77794UQ1客版5L(英法德意荷)配套包装=MA PDQ (优先多语)+客版3L-5Lwarning纸盒底座(翻PO#4500191961)+MA23L游戏说明书+MA23L warning说明书+1张WEEE声明( 带电池)走货欧洲通用30L-B版说明书 EAN#4894680051430 RECHARGEABLE LITHIUM BATTERY(INCLUDED) Remark: Smyths 德国 1. 请准时出货，推期会有罚款； 2. 所有产品按符合欧洲标准走货，需要是不含微塑料版本。 3. 所有电子产品身上需要加字唛，为ZURU FRANCE 地址 (如无电子产品，产品布标有此地址，或产品太小无法增加可忽略此信息)，新地址ZURU FRANCE.33 rue Pa ul Meurice 75020 Paris, France. 4. 电子产品需增加一张WEEE声明30L通用黑白说明书(不接受A版本，翻译有误)，区分带电池和不带电池出货版本, 如已做客版说明书可忽略此要求； 5.所有出往德国市场有关slime和带香味的都需要出无硼无香版本； 6.订单备注显示有分批的（不同仓库/订单号） ，注意分开做货出货，否则会导致罚款 。 7.包装日期码按ZURU格式即可，请确保不迟于外箱日期码，可等于或者早于外箱日期码，必须为法定工作日。 8.做货前请先复核包装条码与订单是否一致再安排，对不上的需与ZURU跟单确认再安排。 | Y18: Sherry Lu | Z18: 4.355 | AA18: =I18*Z18 -> 2647.84 | AC18: 77794UQ1-S001-客版 | AD18: 已入 | AE18: =I18 -> 608 | AG18: 608 | AH18: =AG18-I18 -> 0 | AI18: OK | AJ18: 系统出单 | AM18: =I18 -> 608 | AN18: =I18 -> 608 | AU18: =I18/8 -> 76
A19: 46044 | B19: SMYTHS TOYS EU HQ UC | C19: 德国 | D19: 4500191997 | E19: 4400528770 | F19: 4500191997-10 | G19: MEC457-77794-S001 | H19: 唱片机+唱片球混装展示架 | I19: 2784 | J19: 0 | K19: 48 | L19: =I19/K19 -> 58 | M19: 46100 | N19: 46097 | P19: PASS | R19: 46044 | S19: 有 | T19: UN3481锂电池运输标签 | V19: 所有电子产品身上需要加字唛，为ZURU FRANCE 地址 (如无电子产品，产品布标有此地址，或产品太小无法增加可忽略此信息)，新地址ZURU FRANCE.33 rue Paul Meurice 75020 Paris, France. | X19: 日期码格式：ZURU INC(BVI) 标准格式 日期：按实际生产日期 Packaging Info: MEC457: 客版5L(英法德意荷)展示架[84pcs#77772+48pcs#77794; 所有客版资料翻PO#4500191961] 77772: 客版3L-5Lwarning收缩膜+客版5L收藏指南+MA 23L组装说明+MA复合袋 EAN#4894680051133 77794: 客版3L-5Lwarning纸盒底座+客版3L镭射贴纸+客版3L单铜纸贴纸+MA23L游戏说明书+MA23L warning说明书+1张WEEE声明(带电池)走货欧洲通用29L-C版说明 书 EAN#4894680051430 做货前请先核对条码无误 RECHARGEABLE LITHIUM BATTERY(INCLUDED) *#77772必须移除Messy Lola Young (VINYL-S1-021) 这个唱片, 比例按PM更新的安排* *展架上的Demo Box的唱片需要用"A Little Too Much"(VINYL-S1-025)替代原来的"Messy"(VINYL-S1-021)* *外箱需加一张UN3481锂电池运输标签* Remark: Smyths 德国 1. 请准时出货，推期会有罚款； 2. 所有产品按符合欧洲标准走货，需要是不含微塑料版本。 3. 所有电子产品身上需要加字唛，为ZURU FRANCE 地址 (如无电子产品，产品布标有此地址，或产品太小无法增加可忽略此信息)，新地址ZURU FRANCE.33 rue Pa ul Meurice 75020 Paris, France. 4. 电子产品需增加一张WEEE声明30L通用黑白说明书(不接受A版本，翻译有误)，区分带电池和不带电池出货版本, 如已做客版说明书可忽略此要求； 5.所有出往德国市场有关slime和带香味的都需要出无硼无香版本； 6.订单备注显示有分批的（不同仓库/订单号） ，注意分开做货出货，否则会导致罚款 。 7.包装日期码按ZURU格式即可，请确保不迟于外箱日期码，可等于或者早于外箱日期码，必须为法定工作日。 8.做货前请先复核包装条码与订单是否一致再安排，对不上的需与ZURU跟单确认再安排。 | Y19: Sherry Lu | Z19: 306.676 | AA19: =L19*Z19 -> 17787.208 | AC19: MEC457-S001-77794 | AD19: 已入 | AE19: =I19 -> 2784 | AG19: 2784 | AH19: =AG19-I19 -> 0 | AI19: OK | AJ19: 系统出单 | AM19: =I19 -> 2784 | AN19: =I19 -> 2784 | BA19: =I19/K19 -> 58
A20: 46044 | B20: SMYTHS TOYS EU HQ UC | C20: 德国 | D20: 4500191997 | E20: 4400528771 | F20: 4500191997-20 | G20: MEC457-77794-S001 | H20: 唱片机+唱片球混装展示架 | I20: 3216 | J20: 0 | K20: 48 | L20: =I20/K20 -> 67 | M20: 46100 | N20: 46097 | P20: PASS | R20: 46044 | S20: 有 | T20: UN3481锂电池运输标签 | V20: 所有电子产品身上需要加字唛，为ZURU FRANCE 地址 (如无电子产品，产品布标有此地址，或产品太小无法增加可忽略此信息)，新地址ZURU FRANCE.33 rue Paul Meurice 75020 Paris, France. | X20: 日期码格式：ZURU INC(BVI) 标准格式 日期：按实际生产日期 Packaging Info: MEC457: 客版5L(英法德意荷)展示架[84pcs#77772+48pcs#77794; 所有客版资料翻PO#4500191961] 77772: 客版3L-5Lwarning收缩膜+客版5L收藏指南+MA 23L组装说明+MA复合袋 EAN#4894680051133 77794: 客版3L-5Lwarning纸盒底座+客版3L镭射贴纸+客版3L单铜纸贴纸+MA23L游戏说明书+MA23L warning说明书+1张WEEE声明(带电池)走货欧洲通用29L-C版说明 书 EAN#4894680051430 做货前请先核对条码无误 RECHARGEABLE LITHIUM BATTERY(INCLUDED) *#77772必须移除Messy Lola Young (VINYL-S1-021) 这个唱片, 比例按PM更新的安排* *展架上的Demo Box的唱片需要用"A Little Too Much"(VINYL-S1-025)替代原来的"Messy"(VINYL-S1-021)* *外箱需加一张UN3481锂电池运输标签* Remark: Smyths 德国 1. 请准时出货，推期会有罚款； 2. 所有产品按符合欧洲标准走货，需要是不含微塑料版本。 3. 所有电子产品身上需要加字唛，为ZURU FRANCE 地址 (如无电子产品，产品布标有此地址，或产品太小无法增加可忽略此信息)，新地址ZURU FRANCE.33 rue Pa ul Meurice 75020 Paris, France. 4. 电子产品需增加一张WEEE声明30L通用黑白说明书(不接受A版本，翻译有误)，区分带电池和不带电池出货版本, 如已做客版说明书可忽略此要求； 5.所有出往德国市场有关slime和带香味的都需要出无硼无香版本； 6.订单备注显示有分批的（不同仓库/订单号） ，注意分开做货出货，否则会导致罚款 。 7.包装日期码按ZURU格式即可，请确保不迟于外箱日期码，可等于或者早于外箱日期码，必须为法定工作日。 8.做货前请先复核包装条码与订单是否一致再安排，对不上的需与ZURU跟单确认再安排。 | Y20: Sherry Lu | Z20: 306.676 | AA20: =L20*Z20 -> 20547.292 | AC20: MEC457-S001-77794 | AD20: 已入 | AE20: =I20 -> 3216 | AG20: 3216 | AH20: =AG20-I20 -> 0 | AI20: OK | AJ20: 系统出单 | AM20: =I20 -> 3216 | AN20: =I20 -> 3216 | BA20: =I20/K20 -> 67
A21: 46052 | B21: WALMART INC. | C21: 美国 | D21: 4500192823 | E21: 7137243194 | F21: 4500192823-10 | G21: 77794SK-S001 | H21: 唱片机16pcs/展示架装（不带底座） | I21: 4320 | J21: 0 | K21: 16 | L21: =I21/K21 -> 270 | M21: 46104 | N21: =M21-4 -> 46100 | O21: 4/17 BV验货 | P21: PASS | R21: 46052 | S21: 有 | T21: 2/9 寄出RFID贴纸 | W21: 4个产品+2个SK | X21: 日期码格式：ZURU DGYYYYMMDD CHINA(日期避开周末和法定节假日即可） 日期：按实际生产日期 Packaging Info: 1. 包装要求： 77794SK：MA 1L A版callout纸卡+MA 23L 玩法说明书+MA 23L 警告语说明书+MA USB连接线贴纸+客版 1L sidekick 每pcs产品要贴一张RFID贴纸，RFID贴纸由ZURU提供，贴纸位置要严格按照客人签板 Remark: 1. 包装要求： 77794SK：MA 1L A版callout纸卡+MA 23L 玩法说明书+MA 23L 警告语说明书+MA USB连接线贴纸+客版 1L sidekick 每pcs产品要贴一张RFID贴纸，RFID贴纸由ZURU提供，贴纸位置要严格按照客人签板 2.外箱RFID箱唛（四面右下角需印Zuru Logo)+ ITF-14条码；ITF-14条码印刷在外箱主唛左下角，外箱任一侧面角落备注："MADE IN CHINA" 字样，一张锂电池贴纸 贴在有条码的正唛上，外箱箱唛资料待提供。 3. 在产品上和包装上要有日期码、以及要有MADE IN CHINA和ZURU字样； 4. 产品如有扎带口要剪平，不能刮手。 5. 此单需要抽板和验货，抽板时间预计3/23，请自行多备包装物料。 6. 16pcs/Sidekick/CTN | Y21: Maggie Xie | Z21: 44.256 | AA21: =L21*Z21 -> 11949.12 | AB21: ZB05417-8.17 | AC21: 77794SK-S001 | AD21: 已入 | AE21: =I21 -> 4320 | AF21: DG已完成 | AG21: 4320 | AH21: =AG21-I21 -> 0 | AI21: OK | AJ21: 系统出单 | AK21: =I21 -> 4320 | AN21: =I21 -> 4320 | BG21: =I21/16 -> 270
A22: 46062 | B22: ZURU LLC | C22: 美国 | D22: 4500193475 | E22: 5200009006 | F22: 4500193475-10 | G22: 77794UQ1-S001-FS | H22: 唱片机16pcs/2 UQ1/箱 | I22: 400 | J22: 0 | K22: 16 | L22: =I22/K22 -> 25 | M22: 46108 | N22: =M22-4 -> 46104 | P22: PASS | Q22: 4/4 出货 | R22: 46062 | S22: 有 | T22: 2/12客版UPC贴纸. | X22: 日期码格式：ZURU DGYYYYMMDD CHINA(日期避开周末和法定节假日即可） 日期：按实际生产日期 Packaging Info: 1.产品包装要求： 77794UQ1：MA 1L PDQ+MA 1L 产品彩盒+MA说明书+客版UPC贴纸. 2.NO RFID – 不需要RFID NEW UPC 与STD 不同， 需加贴NEW UPC贴纸。贴前须用黑色笔将原 UPC 码完全涂黑，使其无法扫描，再粘贴新 UPC 贴纸。 Remark: FAST START 项目要求 1.产品包装要求： 77794UQ1：MA 1L PDQ+MA 1L 产品彩盒+MA说明书+客版UPC贴纸. 2.NO RFID – 不需要RFID NEW UPC 与STD 不同， 需加贴NEW UPC贴纸。贴前须用黑色笔将原 UPC 码完全涂黑，使其无法扫描，再粘贴新 UPC 贴纸。 新UPC 如下： SKU Fast Start SPEC# Description UPC GTIN 77794 77794UQ1-S001-FS Mini Vinyl Playset S1 193052112132 10193052112139 3.外箱唛参考提供的模版，排版供确认后，才能生产。 4.此MTS订单不需要第三方抽板验货，但是要通过ZURU QC验货PASS后才能出货。 空运到3PL仓库。 | Y22: SD62 | Z22: 2.613 | AA22: =I22*Z22 -> 1045.2 | AB22: ZB05281-8.17 | AC22: 77794UQ1-S001 | AD22: 已入 | AE22: =I22 -> 400 | AG22: 400 | AH22: =AG22-I22 -> 0 | AI22: OK | AJ22: 系统出单 | AK22: =I22 -> 400 | AN22: =I22 -> 400 | AT22: =I22/8 -> 50
A23: 46045 | B23: ZURU GERMANY GMBH | C23: 德国 | D23: 4500192187 | E23: 5200008729 | F23: 4500192187-20 | G23: 77794UQ1-S002-MTS | H23: 唱片机8pcs/UQ1/箱 | I23: 6400 | J23: 0 | K23: 8 | L23: =I23/K23 -> 800 | M23: 46112 | N23: 46122 | P23: PASS | Q23: 4/17 截SI | R23: 46050 | S23: 有 | T23: 46105 | V23: 所有电子产品身上需要加字唛，为ZURU FRANCE 地址 (如无电子产品，产品布标有此地址，或产品太小无法增加可忽略此信息)，新地址ZURU FRANCE.33 rue Paul Meurice 75020 Paris, France. | X23: 日期码格式：ZURU INC(BVI) 标准格式 日期：按实际生产日期 Packaging Info: 77794UQ1：MA 3L PDQ+MA 3L EAN包装盒+1*多语警语折叠贴纸+MA 23L说明书+MA 23L警语说明书； Remark: 1.德国内销单，需要通过ZURU 验货结果后才能出货 (工厂需要主动提前同ZURU QC预约验货避免延期出货造成不必要麻烦)； 2.产品如含有化学品（slime 等），需要无硼无香。需要无微塑料版本。 3.所有出口欧洲的产品, 法规规定禁止在包装和共公众用的印刷品中使用矿物油中含有的物质, 包装印刷油墨中含有的MOAH/MOSH的质量浓度不能超过1%, 否则出货 到法国被抽检出现问题, 供应商需要对此负责; 4. date code: 外箱日期码要晚于或等于产品日期码，不能早于产品的日期码； 5. 所有出往德国的电子产品身上需要加字唛，为ZURU FRANCE 地址，需跟包装上的地址一致 (如无电子产品，产品布标有此地址，或产品太小无法增加可忽略此信 息。如产品无法加字唛，需让对应跟单提供产品贴纸资料) 新地址：ZURU France 33 rue Paul Meurice 75020 Paris, France 旧地址：ZURU France 1/3, Rue d'Argenteuil 95210 SAINT-GRATIEN, FRANCE 6.所有出往德国订单的电子产品需增加一张欧洲通用WEEE声明说明书，区分带电池和不带电池版本, 如已做客版说明书可忽略此要求。 7.装柜时需要按照款式号码从小到大一款款依次装,避免终端仓库卸货混乱.若一个柜子涉及到几个不同国家内销单,装柜时需要一个国家装完后再装另一个国家的 产品,依次装柜,避免终端仓库因不同国家不同库位位置卸货混乱. (此点需要同工厂装柜人员强调)" 8.ratio 同MA 9. 若有特定款有特殊外箱条码要求时,需要明确列出产品款对应的具体外箱条码号码/条码类型 (若无,可以忽略此需求). | Y23: SD04 | Z23: 5 | AA23: =I23*Z23 -> 32000 | AC23: 77794UQ1-S002-3L | AD23: 已入 | AE23: =I23 -> 6400 | AF23: 4/14验，4/15到DG | AG23: 6400 | AH23: =AG23-I23 -> 0 | AI23: OK | AJ23: 系统出单 | AL23: =I23 -> 6400 | AN23: =I23 -> 6400 | AU23: =I23/8 -> 800
A24: 46052 | B24: 360 SALES SOLUTIONS INC | C24: 加拿大 | D24: 4500192784 | E24: 2026ZURU01 | F24: 4500192784-10 | G24: 77794UQ1-S002 | H24: 唱片机8pcs/UQ1/箱 | I24: 6000 | J24: 0 | K24: 8 | L24: =I24/K24 -> 750 | M24: 46118 | N24: =M24-4 -> 46114 | P24: PASS | R24: 46052 | S24: 有 | T24: 46062 | X24: 日期码格式： 标准格式 日期：按实际生产日期 Packaging Info: 77794UQ1 MA多语包装 EAN版本+UPC贴纸193052090409 Remark: 出加拿大 Zuru验货.日期跟踪码：产品外包装及产品本身都必须有日期跟踪码，ZURU标准格式日期码。（箱唛日期码按跟单提供格式） | Y24: Bella Tan | Z24: 5 | AA24: =Z24*I24 -> 30000 | AC24: 77794UQ1-S002-3L | AD24: 已入 | AE24: =I24 -> 6000 | AG24: 6000 | AH24: =AG24-I24 -> 0 | AJ24: 系统出单 | AL24: =I24 -> 6000 | AN24: =I24 -> 6000 | AU24: =I24/8 -> 750
A25: 46050 | B25: TARGET US | C25: 美国 | D25: 4500192438 | E25: 10001701248-3891 | F25: 4500192438-10 | G25: 77897-S001 | H25: 唱片机展示 | I25: 777 | J25: 0 | K25: 1 | L25: =I25/K25 -> 777 | M25: 46118 | N25: =M25-4 -> 46114 | P25: PASS | R25: 46059 | S25: 有 | T25: 46106 | X25: 日期码格式：ZURU INC(BVI) 标准格式 日期：按实际生产日期 Packaging Info: Remark: 1. 77897-S001-MINI BRANDS-VINYL-SERIES 1-DISPLAY BOX WITH DEMO,1SET/CTN; 2. 每个外箱正唛信息左上方位置粘贴条码箱贴纸，每箱只贴一张，由ZURU订购；对应的外箱贴DPCI#086-94-5923，UPC#显示为193052108142; 3. 每个亚克力盒子的背面中间位置需要贴一张"SAMPLE - Not for Resale" 贴纸，工厂自行订购； 4. 每个外箱正唛箱唛内容右侧需贴一张Event label，内容显示Class 94 Displays Set Date：7/19/2026，工厂自行订购； 5. 每个外箱上需额外印刷 "Contains Display Box. Non-Saleable Unit."信息，字体和大小没有特殊要求, 可以与箱唛信息保持相同即可；外箱四面需要印刷易碎 /向上的LOGO； 6. 每个纸箱需要装一张货架的整体效果图，用A4纸打印即可； 7. 每个纸箱需要装一张demo box组装说明，工厂自行订购； 8. 产品和包装上印刷 tracking code信息，格式为ZURU常规格式; 9. 出货方式：货代自提 | Y25: Holly Zheng | Z25: 12 | AA25: =I25*Z25 -> 9324 | AB25: ZB05312-8.17 | AC25: 77897-S001 | AD25: 已入 | AE25: =I25 -> 777 | AF25: 已完成 | AG25: 777 | AH25: =AG25-I25 -> 0 | AJ25: 系统出单 | BH25: =I25 -> 777
A26: 46052 | B26: WALMART INC. | C26: 美国 | D26: 4500192824 | E26: 7137243190 | F26: 4500192824-10 | G26: 77794SK-S001 | H26: 唱片机16pcs/展示架装（不带底座） | I26: 4560 | J26: 0 | K26: 16 | L26: =I26/K26 -> 285 | M26: 46118 | N26: =M26-4 -> 46114 | O26: 4/17 BV验货 | P26: PASS | R26: 46052 | S26: 有 | T26: 2/9 寄出RFID贴纸 | X26: 日期码格式：ZURU DGYYYYMMDD CHINA(日期避开周末和法定节假日即可） 日期：按实际生产日期 Packaging Info: 1. 包装要求： 77794SK：MA 1L A版callout纸卡+MA 23L 玩法说明书+MA 23L 警告语说明书+MA USB连接线贴纸+客版 1L sidekick 每pcs产品要贴一张RFID贴纸，RFID贴纸由ZURU提供，贴纸位置要严格按照客人签板 Remark: 1. 包装要求： 77794SK：MA 1L A版callout纸卡+MA 23L 玩法说明书+MA 23L 警告语说明书+MA USB连接线贴纸+客版 1L sidekick 每pcs产品要贴一张RFID贴纸，RFID贴纸由ZURU提供，贴纸位置要严格按照客人签板 2.外箱RFID箱唛（四面右下角需印Zuru Logo)+ ITF-14条码；ITF-14条码印刷在外箱主唛左下角，外箱任一侧面角落备注："MADE IN CHINA" 字样，一张锂电池贴纸 贴在有条码的正唛上，外箱箱唛资料待提供。 3. 在产品上和包装上要有日期码、以及要有MADE IN CHINA和ZURU字样； 4. 产品如有扎带口要剪平，不能刮手。 5. 此单需要验货，请自行多备包装物料。 6. 16pcs/Sidekick/CTN | Y26: Maggie Xie | Z26: 44.256 | AA26: =L26*Z26 -> 12612.96 | AB26: ZB05418-8.17 | AC26: 77794SK-S001 | AD26: 已入 | AE26: =I26 -> 4560 | AF26: DG生产 | AG26: 4560 | AH26: =AG26-I26 -> 0 | AI26: OK | AJ26: 系统出单 | AK26: =I26 -> 4560 | AN26: =I26 -> 4560 | BG26: =I26/16 -> 285
A27: 46062 | B27: KMARTAUSTRALIALTD(NEWZEALAND) | C27: 新西兰 | D27: 4500193541 | E27: 21431976 | F27: 4500193541-20 | G27: 77794UQ1-S002 | H27: 唱片机8pcs/UQ1/箱 | I27: 248 | J27: 0 | K27: 8 | L27: =I27/K27 -> 31 | M27: 46119 | N27: 46115 | P27: PASS | R27: 46088 | S27: 有 | T27: 46126 | X27: 日期码格式：ZURU INC(BVI) 标准格式 日期：按实际生产日期 Packaging Info: 77794UQ1:MA英语UPC版本包装（收缩膜和说明书, MA首选1L，如无1L可用多语且含英语的配套多语包装) +1张锂电池黑白警语书纸 + 1张防盗贴纸 (贴纸以及位置图 翻单PO#4500193539）+ 箱唛 + 外箱SSCC Label Remark: 1.请务必按时完货，验货。并且按期送货入货代指定仓库，如果晚了导致船期Delay将会有罚金产生或者客户要求空运，所产生的罚金和空运费由工厂承担。 2.SSCC 外箱贴纸请同纸箱瓦楞纸方向（竖纹向）垂直，即外箱贴纸横着贴(注意条码不要被胶带粘住），贴1pc，贴1面正唛，封箱胶纸不能挡住贴纸内容。外箱贴纸 离外箱边距离不少于2cm。 3.外箱材质为ZURU标准； 4.此单需使用KMART封箱胶上下工字型封箱;从2019年6月开始，要用KMART 新版封箱胶带，此单要用"ANKO"封箱胶带 5.此单出口新西兰，请按相应的澳新标准生产； 6.产品和包装上生产批号的显示格式ZURU标准日期码格式 7.外箱信息不可手写，重量和体积需要与实际的一致(不可手写） 8. 每款item装箱后的G.W.超过10KG或者CBM超过0.13,(9.5KG或者以上，四舍五入后也属于10KG) 需在外箱上加印超 重或者Bulky LOGO，若发现我们资料没有，请 帮忙提醒 1)重量超过10kg但不超过16kg且CBM不超过0.13,10-16kg 超重logo 2）CBM超过0.13且重量少于17kg，bulky logo 3）不属于以上两种情况，需要使用相应重量范围内的超重logo 4）超重logo需要在外箱四面都印刷(箱唛右上角，两面侧唛超重logo需要尽量靠近毛重)，尺寸为:110mm height* 95mm width 9. 实际外箱重量跟印在箱唛上的数据差异不能超3%，尺寸按实际数据印刷 71172实际上为LCL散货出柜，请注意此订单与AU po#4500193539一起合并计算 77772务必赶最晚5/11上午交仓 | Y27: LouiseLu | Z27: 5 | AA27: =Z27*I27 -> 1240 | AC27: 77794UQ1-S002 | AD27: 已入 | AE27: =I27 -> 248 | AG27: 248 | AH27: =AG27-I27 -> 0 | AJ27: 系统出单 | AK27: =I27 -> 248 | AN27: =I27 -> 248 | AT27: =I27/8 -> 31
A28: 46062 | B28: KMART AUSTRALIA LTD | C28: 澳大利亚 | D28: 4500193539 | E28: 21431973 | F28: 4500193539-20 | G28: 77794UQ1-S002 | H28: 唱片机8pcs/UQ1/箱 | I28: 2720 | J28: 0 | K28: 8 | L28: =I28/K28 -> 340 | M28: 46119 | N28: 46121 | P28: PASS | R28: 46088 | S28: 有 | T28: 防盜贴纸(贴纸以及防盜贴纸位置图翻单PO#4500193539)+箱唛+外箱贴纸SSCC Label | X28: 日期码格式：ZURU INC(BVI) 标准格式 日期：按实际生产日期 Packaging Info: 77772GQ1:MA英语UPC版本包装（收缩膜和说明书, MA首选1L，如无1L可用多语且含英语的配套多语包装) +防盜贴纸(贴纸以及防盜贴纸位置图翻单PO#4500193539)+ 两张张覆盖PDQ上唱片的贴纸+两张张覆盖收藏指南上唱片的贴纸+一张覆盖PDQ上数字"45"的贴纸+一张覆盖收藏指南上数字"45"的贴纸+箱唛+外箱贴纸SSCC Label 配比信息：4 mini vinyls,1 accessory Removed了 ""Messy <(>&<)> Delicious""两张唱片 77794UQ1:MA英语UPC版本包装（收缩膜和说明书, MA首选1L，如无1L可用多语且含英语的配套多语包装) +1张锂电池黑白书纸 + 1张防盗贴纸+ 箱唛 + 外箱SSCC La bel 77843GQ1：MA英语UPC版本包装（MA首选1L，如无1L可用多语且含英语的配套多语包装) +箱唛 + 外箱SSCC Label 77843-sushi <(>&<)> rainbow cake: MA sushi <(>&<)> rainbow cake专用黑白说明书+ 1张防盗贴纸 77843-其他款:MA UV灯说明书+1张防盗贴纸+1张说明书上面加警告语贴纸+1张收缩膜纽扣电池警告语贴纸 配比信息：Ratio: PIZZA: HAMBURGER: PANCAKES: BUBBLE TEA: Matcha TEA: TACO: SUSHI: DONUT: Charcuterie Board: RAINBOW CAKE(Rare)=10.88%: 10.88%: 10.88%: 10.88%: 10.88%: 10.88%: 10.88%: 10.88%: 10.88%: 2.08%=68:68:68:68:68:68:68:68:68:13 71172：MA英语UPC版本包装（收缩膜和说明书, MA首选1L，如无1L可用多语且含英语的配套多语包装) + 一张防盗贴纸+箱唛 + 外箱SSCC Label 3PCS AA BATTERIES(INCLUDED) Remark: 1.请务必按时完货，验货。并且按期送货入货代指定仓库，如果晚了导致船期Delay将会有罚金产生或者客户要求空运，所产生的罚金和空运费由工厂承担。 2.SSCC 外箱贴纸请同纸箱瓦楞纸方向（竖纹向）垂直，即外箱贴纸横着贴(注意条码不要被胶带粘住），贴1pc，贴1面正唛，封箱胶纸不能挡住贴纸内容。外箱贴纸 离外箱边距离不少于2cm。 3.外箱材质为ZURU标准； 4.此单需使用KMART封箱胶上下工字型封箱;从2019年6月开始，要用KMART 新版封箱胶带，此单要用"ANKO"封箱胶带 5.此单出口澳大利亚，请按相应的澳新标准生产； 6.产品和包装上生产批号的显示格式ZURU标准日期码格式 7.外箱信息不可手写，重量和体积需要与实际的一致(不可手写） 8. 每款item装箱后的G.W.超过10KG或者CBM超过0.13,(9.5KG或者以上，四舍五入后也属于10KG) 需在外箱上加印超 重或者Bulky LOGO，若发现我们资料没有，请 帮忙提醒 1)重量超过10kg但不超过16kg且CBM不超过0.13,10-16kg 超重logo 2）CBM超过0.13且重量少于17kg，bulky logo 3）不属于以上两种情况，需要使用相应重量范围内的超重logo 4）超重logo需要在外箱四面都印刷(箱唛右上角，两面侧唛超重logo需要尽量靠近毛重)，尺寸为:110mm height* 95mm width 9. 实际外箱重量跟印在箱唛上的数据差异不能超3%，尺寸按实际数据印刷 71172实际上走LCL散货出柜，请注意此订单与NZ po#4500193541一起合并计算 77772务必赶最晚5/11上午交仓 | Y28: Louise Lu | Z28: 5 | AA28: =Z28*I28 -> 13600 | AC28: 77794UQ1-S002 | AD28: 已入 | AE28: =I28 -> 2720 | AF28: 已完成 | AG28: 2720 | AH28: =AG28-I28 -> 0 | AJ28: 系统出单 | AK28: =I28 -> 2720 | AN28: =I28 -> 2720 | AT28: =I28/8 -> 340
A29: 46059 | B29: TARGET US | C29: 美国 | D29: 4500190738 | E29: 10001661694-3891 | F29: 4500190738-60 | G29: 77794UQ1-S002 | H29: 唱片机8pcs/UQ1/箱 | I29: 6840 | J29: 0 | K29: 8 | L29: =I29/K29 -> 855 | M29: 46119 | N29: 46122 | P29: PASS | Q29: 压柜到4/17 | R29: 3/2 确认 | S29: 有 | T29: 3/25外箱条码箱贴纸贴纸 | V29: 外箱锂电池贴纸 | X29: 日期码格式：ZURU INC(BVI) 标准格式 日期：按实际生产日期 Packaging Info: 77794UQ1：产品包装 MA 1L黑白警告语说明书+MA 1L 彩盒+MA 1L PDQ; 彩盒上的UPC显示193052090409; Remark: 77794UQ1： 1.77794UQ1-S002-MINI BRANDS-VINYL-PLAYSET-SERIES 1-CUBE,8PCS/PDQ,8PCS/PDQ/CTN; 2. 产品包装 MA 1L黑白警告语说明书+MA 1L 彩盒+MA 1L PDQ; 彩盒上的UPC显示193052090409; 3. 外箱正唛左上角位置粘贴条码箱贴纸，每箱只贴一张，由ZURU订购。来料贴纸上显示的客户DPCI# 086-02-4085, UPC显示10193052090406; 4. 带锂电池出货，需在外箱正面或者侧面合适位置上加贴一张贴锂电池标签纸，由工厂订购 以上Items： 1. 产品和包装上均要印刷tracking code信息，格式为ZURU常规格式； 2. 需要我司QC验货之后才能安排出货 3. 出货方式： 货代自提 | Y29: Holly Zheng | Z29: 2.88 | AA29: =Z29*I29 -> 19699.2 | AB29: ZB05239/ZB05310 | AC29: 77794UQ1-S002 | AD29: 已入 | AE29: =I29 -> 6840 | AF29: 已完成 | AG29: =6744+96 -> 6840 | AH29: =AG29-I29 -> 0 | AJ29: 系统出单 | AK29: =I29 -> 6840 | AN29: =I29 -> 6840 | AT29: =I29/8 -> 855
A30: 46061 | B30: ASIA GOAL LIMITED | C30: 台湾 | D30: 4500193379 | E30: AG250404-HK | F30: 4500193379-20 | G30: 77794UQ1-S001 | H30: 唱片机16pcs/2 UQ1/箱 | I30: 240 | J30: 0 | K30: 16 | L30: =I30/K30 -> 15 | M30: 46120 | N30: 46122 | P30: PASS | R30: 2/26 确认 | S30: 有 | T30: 46104 | X30: 日期码格式：ZURU INC(BVI) 标准格式 日期：按实际生产日期 Packaging Info: 77794UQ1: MA 1L PKG ，PDQ , MA 收藏指南，说明书+HK 客供警语贴纸 Remark: 此单出HK | Y30: Chelsea Luo | Z30: 4.355 | AA30: =I30*Z30 -> 1045.2 | AC30: 77794UQ1-S001 | AD30: 已入 | AE30: =I30 -> 240 | AF30: 已完成 | AG30: 240 | AH30: =AG30-I30 -> 0 | AI30: OK | AJ30: 系统出单 | AK30: =I30 -> 240 | AN30: =I30 -> 240 | AT30: =I30/8 -> 30
A31: 46061 | B31: ASIA GOAL LIMITED TAIWAN BRANCH (H. | C31: 台湾 | D31: 4500193384 | E31: AG250405-TW | F31: 4500193384-20 | G31: 77794UQ1-S001 | H31: 唱片机16pcs/2 UQ1/箱 | I31: 240 | J31: 0 | K31: 16 | L31: =I31/K31 -> 15 | M31: 46120 | N31: 46122 | P31: PASS | R31: 2/26 确认 | S31: 有 | T31: 46097 | X31: 日期码格式：ZURU INC(BVI) 标准格式 日期：按实际生产日期 Packaging Info: 此单出TW 77794UQ1: MA PKG,优先1L + 1张警语贴纸 Remark: | Y31: Chelsea Luo | Z31: 4.355 | AA31: =I31*Z31 -> 1045.2 | AC31: 77794UQ1-S001 | AD31: 已入 | AE31: =I31 -> 240 | AF31: 已完成 | AG31: 240 | AH31: =AG31-I31 -> 0 | AI31: OK | AJ31: 系统出单 | AK31: =I31 -> 240 | AN31: =I31 -> 240 | AT31: =I31/8 -> 30
A32: 46052 | B32: WALMART INC. | C32: 美国 | D32: 4500192825 | E32: 7137243189 | F32: 4500192825-10 | G32: 77794SK-S001 | H32: 唱片机16pcs/展示架装（不带底座） | I32: 2832 | J32: 0 | K32: 16 | L32: =I32/K32 -> 177 | M32: 46121 | N32: 46122 | O32: 4/20BV验货 | R32: 46052 | S32: 有 | T32: 2/9 寄出RFID贴纸 | X32: 日期码格式：ZURU DGYYYYMMDD CHINA(日期避开周末和法定节假日即可） 日期：按实际生产日期 Packaging Info: 1. 包装要求： 77794SK：MA 1L A版callout纸卡+MA 23L 玩法说明书+MA 23L 警告语说明书+MA USB连接线贴纸+客版 1L sidekick 每pcs产品要贴一张RFID贴纸，RFID贴纸由ZURU提供，贴纸位置要严格按照客人签板 Remark: 1. 包装要求： 77794SK：MA 1L A版callout纸卡+MA 23L 玩法说明书+MA 23L 警告语说明书+MA USB连接线贴纸+客版 1L sidekick 每pcs产品要贴一张RFID贴纸，RFID贴纸由ZURU提供，贴纸位置要严格按照客人签板 2.外箱RFID箱唛（四面右下角需印Zuru Logo)+ ITF-14条码；ITF-14条码印刷在外箱主唛左下角，外箱任一侧面角落备注："MADE IN CHINA" 字样，一张锂电池贴纸 贴在有条码的正唛上，外箱箱唛资料待提供。 3. 在产品上和包装上要有日期码、以及要有MADE IN CHINA和ZURU字样； 4. 产品如有扎带口要剪平，不能刮手。 5. 此单需要验货，请自行多备包装物料。 6. 16pcs/Sidekick/CTN | Y32: Maggie Xie | Z32: 44.256 | AA32: =L32*Z32 -> 7833.312 | AB32: ZB05419-8.17 | AC32: 77794SK-S001 | AD32: 已入 | AE32: =I32 -> 2832 | AF32: DG生产 | AG32: 2832 | AH32: =AG32-I32 -> 0 | AI32: OK | AJ32: 系统出单 | AK32: =I32 -> 2832 | AN32: =I32 -> 2832 | BG32: =I32/16 -> 177
A33: 46052 | B33: WALMART INC. | C33: 美国 | D33: 4500192826 | E33: 7137243192 | F33: 4500192826-10 | G33: 77794SK-S001 | H33: 唱片机16pcs/展示架装（不带底座） | I33: 4272 | J33: 0 | K33: 16 | L33: =I33/K33 -> 267 | M33: 46122 | N33: 46122 | O33: 4/22BV验货 | P33: PASS | R33: 46052 | S33: 有 | T33: 2/9 寄出RFID贴纸 | X33: 日期码格式：ZURU DGYYYYMMDD CHINA(日期避开周末和法定节假日即可） 日期：按实际生产日期 Packaging Info: 1. 包装要求： 77794SK：MA 1L A版callout纸卡+MA 23L 玩法说明书+MA 23L 警告语说明书+MA USB连接线贴纸+客版 1L sidekick 每pcs产品要贴一张RFID贴纸，RFID贴纸由ZURU提供，贴纸位置要严格按照客人签板 Remark: 1. 包装要求： 77794SK：MA 1L A版callout纸卡+MA 23L 玩法说明书+MA 23L 警告语说明书+MA USB连接线贴纸+客版 1L sidekick 每pcs产品要贴一张RFID贴纸，RFID贴纸由ZURU提供，贴纸位置要严格按照客人签板 2.外箱RFID箱唛（四面右下角需印Zuru Logo)+ ITF-14条码；ITF-14条码印刷在外箱主唛左下角，外箱任一侧面角落备注："MADE IN CHINA" 字样，一张锂电池贴纸 贴在有条码的正唛上，外箱箱唛资料待提供。 3. 在产品上和包装上要有日期码、以及要有MADE IN CHINA和ZURU字样； 4. 产品如有扎带口要剪平，不能刮手。 5. 此单需要验货，请自行多备包装物料。 6. 16pcs/Sidekick/CTN | Y33: Maggie Xie | Z33: 44.256 | AA33: =L33*Z33 -> 11816.352 | AB33: ZB05416-8.17 | AC33: 77794SK-S001 | AD33: 已入 | AE33: =I33 -> 4272 | AF33: DG生产 | AG33: 4272 | AH33: =AG33-I33 -> 0 | AI33: OK | AJ33: 系统出单 | AK33: =I33 -> 4272 | AN33: =I33 -> 4272 | BG33: =I33/16 -> 267
A34: 46065 | B34: KANDYTOYS LIMITED | C34: 英国 | D34: 4500193688 | E34: AS191225ZUR15 274 | F34: 4500193688-30 | G34: 77794UQ1-S001 | H34: 唱片机16pcs/2 UQ1/箱 | I34: 1600 | J34: 0 | K34: 16 | L34: =I34/K34 -> 100 | M34: 46125 | N34: 46123 | P34: PASS | R34: 3/23确认 | S34: 有 | T34: 3/25 PDQ条码贴纸(位置:PDQ底部贴一张可扫描的条码贴纸(ZURU 跟单提供模板)+WEEE 29L 带电池说明书 | X34: 日期码格式：ZURU INC(BVI) 标准格式 日期：按实际生产日期 Packaging Info: 77794UQ1-S001:MA UPC包装+MA PDQ+一张PDQ条码贴纸(位置:PDQ底部贴一张可扫描的条码贴纸(ZURU 跟单提供模板)+WEEE 30L 带电池说明书 B 其他款配比按MA标准 Remark: 1.订单出英国，请注意检查产品及包装应带UKCA图标，包装需要显示ZURU UK LTD/ZURU France地址信息，QC同事请查核，如有问题与跟单确认。 2.生产日期按实际的（法定工作日），按ZURU标准格式即可 ，并需要在出货前提供每个产品外包上对应的生产日期明细 3.请注意所有订单都需要经过ZURU QC验货并且通过后方可出货 4.一个产品一个条码，单款有多个子件条码的请让跟单提供贴纸覆盖。 5.外箱上的条码请确保清晰可扫描，有PDQ， 需要在PDQ底部贴一张带条码并可扫描的贴纸(ZURU 跟单提供模板）。 6.所有产品按符合欧洲标准走货，微塑料需合规并增加IFUD声明，含电池的需要增加WEEE说明书。 | Y34: Zoe Zhou | Z34: 4.355 | AA34: =I34*Z34 -> 6968 | AC34: 77794UQ1-S001 | AD34: 已入 | AE34: =I34 -> 1600 | AF34: 4/11验，4/12到DG | AG34: =1520+80 -> 1600 | AH34: =AG34-I34 -> 0 | AJ34: 系统出单 | AK34: =I34 -> 1600 | AN34: =I34 -> 1600 | AT34: =I34/8 -> 200
A35: 46062 | B35: ALL BRANDS TOYS PTY LTD | C35: 澳大利亚 | D35: 4500193524 | E35: 86065 | F35: 4500193524-20 | G35: 77794UQ1-S002 | H35: 唱片机8pcs/UQ1/箱 | I35: 2400 | J35: 0 | K35: 8 | L35: =I35/K35 -> 300 | M35: 46125 | N35: 46126 | P35: PASS | R35: 3/20 确认 | S35: 有 | T35: 3/15客人通用进口商贴纸+MA锂电池警语书纸 | X35: 日期码格式：ZURU INC(BVI) 标准格式 日期：按实际生产日期 Packaging Info: Removed了 ""Messy <(>&<)> Delicious""两张唱片 77794UQ1:MA_UPC版本包装（MA首选1L，如无1L可用多语且含英语的配套多语UPC包装）+1张MA锂电池警语书纸+ 1张客人通用进口商贴纸 Remark: 1.按实际生产日期; 2.出澳大利亚，请按照相应标准生产; | Y35: Louise Lu | Z35: 5 | AA35: =Z35*I35 -> 12000 | AC35: 77794UQ1-S002 | AD35: 已入 | AE35: =I35 -> 2400 | AF35: 4/14验，4/15到DG | AG35: =2360+40 -> 2400 | AH35: =AG35-I35 -> 0 | AI35: OK | AJ35: 系统出单 | AK35: =I35 -> 2400 | AN35: =I35 -> 2400 | AT35: =I35/8 -> 300
A36: 46052 | B36: WALMART INC. | C36: 美国 | D36: 4500192827 | E36: 7137243191 | F36: 4500192827-10 | G36: 77794SK-S001 | H36: 唱片机16pcs/展示架装（不带底座） | I36: 6528 | J36: 0 | K36: 16 | L36: =I36/K36 -> 408 | M36: 46125 | N36: 46127 | O36: 4/22BV验货 | P36: PASS | R36: 46052 | S36: 有 | T36: 2/9 寄出RFID贴纸 | X36: 日期码格式：ZURU DGYYYYMMDD CHINA(日期避开周末和法定节假日即可） 日期：按实际生产日期 Packaging Info: 1. 包装要求： 77794SK：MA 1L A版callout纸卡+MA 23L 玩法说明书+MA 23L 警告语说明书+MA USB连接线贴纸+客版 1L sidekick 每pcs产品要贴一张RFID贴纸，RFID贴纸由ZURU提供，贴纸位置要严格按照客人签板 Remark: 1. 包装要求： 77794SK：MA 1L A版callout纸卡+MA 23L 玩法说明书+MA 23L 警告语说明书+MA USB连接线贴纸+客版 1L sidekick 每pcs产品要贴一张RFID贴纸，RFID贴纸由ZURU提供，贴纸位置要严格按照客人签板 2.外箱RFID箱唛（四面右下角需印Zuru Logo)+ ITF-14条码；ITF-14条码印刷在外箱主唛左下角，外箱任一侧面角落备注："MADE IN CHINA" 字样，一张锂电池贴纸 贴在有条码的正唛上，外箱箱唛资料待提供。 3. 在产品上和包装上要有日期码、以及要有MADE IN CHINA和ZURU字样； 4. 产品如有扎带口要剪平，不能刮手。 5. 此单需要验货，请自行多备包装物料。 6. 16pcs/Sidekick/CTN | Y36: Maggie Xie | Z36: 44.256 | AA36: =L36*Z36 -> 18056.448 | AB36: ZB05415-8.17 | AC36: 77794SK-S001 | AD36: 已入 | AE36: =I36 -> 6528 | AF36: DG生产 | AG36: 6528 | AH36: =AG36-I36 -> 0 | AI36: OK | AJ36: 系统出单 | AK36: =I36 -> 6528 | AN36: =I36 -> 6528 | BG36: =I36/16 -> 408
A37: 46079 | B37: MINISO DEPOT CA INC. | C37: 美国 | D37: 4500194334 | E37: 4360138834 | F37: 4500194334-50 | G37: 77794-S001 | H37: 唱片机16pcs/箱 | I37: 4656 | J37: 0 | K37: 16 | L37: =I37/K37 -> 291 | M37: 46126 | N37: 46127 | P37: PASS | Q37: 4/18 装柜 | R37: 46094 | S37: 有 | T37: 无 | X37: 日期码格式：ZURU INC(BVI) 标准格式 日期：按实际生产日期 Packaging Info: 1. 包装方式：MA UPC优先1L最新包装，出口美国； 2. 产品和包装上印刷tracking code信息，格式为ZURU常规； 3. ZURU QC 验货合格后即可出货. Remark: | Y37: Iris Yuan | Z37: 2.466 | AA37: =I37*Z37 -> 11481.696 | AB37: ZB05283-8.17 | AC37: 77794-S001 | AD37: 已入 | AE37: =I37 -> 4656 | AF37: 已完成 | AG37: =4496+160 -> 4656 | AH37: =AG37-I37 -> 0 | AJ37: 系统出单 | AK37: =I37 -> 4656 | AN37: =I37 -> 4656
A38: 46079 | B38: MINISO DEPOT CA INC. | C38: 美国 | D38: 4500194341 | E38: 4360138853 | F38: 4500194341-50 | G38: 77794-S001 | H38: 唱片机16pcs/箱 | I38: 3744 | J38: 0 | K38: 16 | L38: =I38/K38 -> 234 | M38: 46126 | N38: 46127 | P38: PASS | Q38: 4/16 装柜 | R38: 46094 | S38: 有 | T38: 无 | X38: 日期码格式：ZURU INC(BVI) 标准格式 日期：按实际生产日期 Packaging Info: 1. 包装方式：MA UPC优先1L最新包装，出口美国； 2. 产品和包装上印刷tracking code信息，格式为ZURU常规； 3. ZURU QC 验货合格后即可出货. Remark: | Y38: Iris Yuan | Z38: 2.466 | AA38: =I38*Z38 -> 9232.704 | AB38: ZB05205-8.17 | AC38: 77794-S001 | AD38: 已入 | AE38: =I38 -> 3744 | AF38: 已完成 | AG38: 3744 | AH38: =AG38-I38 -> 0 | AJ38: 系统出单 | AK38: =I38 -> 3744 | AN38: =I38 -> 3744
A39: 46030 | B39: CRACKER BARREL | C39: 美国 | D39: 4500188838 | E39: 277707 | F39: 4500188838-10 | G39: 77794UQ1-S002 | H39: 唱片机8pcs/UQ1/箱 | I39: 4000 | J39: 0 | K39: 8 | L39: =I39/K39 -> 500 | M39: 46127 | N39: 46122 | O39: 4/3完成25%大货包装第三方抽板测试，4/15完成100%大货 | P39: PASS | Q39: 4/19 出货 | R39: 3/27确认 | S39: 有 | T39: 3/3 客供价格贴纸 | W39: 25%抽样由客人指定的第三方ITS进行，现场在大货中抽样，具体要求如下所列： A.样板抽取12pcs/每款/每色（带包装，大货中抽取）。 B.产品上有涂层的，需额外准备足够的干油墨（每个颜色2个A4尺寸的喷涂样本，涂层喷到同底材，涂满涂厚，至少能刮取30mg的量）。 4. 外箱贴打印常规 4"x6" Standard Label Stock, 只需贴一面(正唛）, 优先贴在纸箱的右上方空白处，不可以盖住外箱上的其他信息及标签，可适当调整位置。 5. 样板需求（77794UQ1 & 77772GQ4）： 1)产前样+Model Store Sample: 请在4/1前寄出每款每色各8pcs大货样（不带PDQ，需贴客版价格贴纸）并寄给深圳跟单Emily Wu/Irene Wang, 我们需寄给客户审 批和拍照。 2)满箱样：请在4/15前寄出各一箱大货满箱样（产品需贴客版价格贴纸，并带大货外箱）寄给深圳跟单Emily Wu/Irene Wang。 Remark：以上所有样板数量不包含在订单数量里，做货需预备样板数量。 | X39: 日期码格式：ZURU INC(BVI) 标准格式 日期：按实际生产日期 Packaging Info: 1. item#77794UQ1: MA UPC最新版本包装（优先1L) + 标版PDQ + 客版价格贴纸 + 外箱贴； 客版价格贴纸和外箱贴都是跟单提供，工厂自行订购。出口美国。 2. 产品及包装上都要有日期码，日期码是一致的（但不能为周末)，格式为ZURU标准格式。 Remark: 3. 此两款都需在4/2前完成至少25%大货包装，4/3早上进行ITS的25%大货抽样验货。 100%大货可以在4/15前完成。收到PASS的测试报告后，才可安排出货。 25%抽样由客人指定的第三方ITS进行，现场在大货中抽样，具体要求如下所列： A.样板抽取12pcs/每款/每色（带包装，大货中抽取）。 B.产品上有涂层的，需额外准备足够的干油墨（每个颜色2个A4尺寸的喷涂样本，涂层喷到同底材，涂满涂厚，至少能刮取30mg的量）。 4. 外箱贴打印常规 4"x6" Standard Label Stock, 只需贴一面(正唛）, 优先贴在纸箱的右上方空白处，不可以盖住外箱上的其他信息及标签，可适当调整位置。 5. 样板需求（77794UQ1 <(>&<)> 77772GQ4）： 1)产前样+Model Store Sample: 请在4/1前寄出每款每色各8pcs大货样（不带PDQ，需贴客版价格贴纸）并寄给深圳跟单Emily Wu/Irene Wang, 我们需寄给客户审 批和拍照。 2)满箱样：请在4/15前寄出各一箱大货满箱样（产品需贴客版价格贴纸，并带大货外箱）寄给深圳跟单Emily Wu/Irene Wang。 Remark：以上所有样板数量不包含在订单数量里，做货需预备样板数量。 | Y39: Emily Wu | Z39: 3 | AA39: =Z39*I39 -> 12000 | AB39: ZB05480-8.17 | AC39: 77794UQ1-S002 | AD39: 已入 | AE39: =I39 -> 4000 | AF39: 已完成 | AG39: 4000 | AH39: =AG39-I39 -> 0 | AI39: OK | AJ39: 系统出单 | AK39: =I39 -> 4000 | AN39: =I39 -> 4000 | AT39: =I39/8 -> 500
A40: 46081 | B40: TARGET US | C40: 美国 | D40: 4500194701 | E40: 10001764948-0 581 | F40: 4500194701-10 | G40: 77794UQ1-S002 | H40: 唱片机8pcs/UQ1/箱 | I40: 13000 | J40: 0 | K40: 8 | L40: =I40/K40 -> 1625 | M40: 46127 | N40: 46127 | P40: PASS | Q40: 4/18 货代上门提货 | R40: 3/13 确认 | S40: 有 | T40: 3/24外箱条码箱贴纸贴纸，2/10提供EVENT LABEL | V40: 外箱锂电池贴纸 | X40: 日期码格式：ZURU INC(BVI) 标准格式 日期：按实际生产日期 Packaging Info: 产品包装 MA 1L黑白警告语说明书+MA 1L 彩盒+MA 1L PDQ Remark: 1.77794UQ1-S002-MINI BRANDS-VINYL-PLAYSET-SERIES 1-CUBE,8PCS/PDQ,8PCS/PDQ/CTN; 2. 产品包装 MA 1L黑白警告语说明书+MA 1L 彩盒+MA 1L PDQ; 彩盒上的UPC显示193052090409; 3. 外箱正唛左上角位置粘贴条码箱贴纸，每箱只贴一张，由ZURU订购。来料贴纸上显示的客户DPCI# 086-02-4085, UPC显示10193052090406; 4. 产品和包装上均要印刷tracking code信息，格式为ZURU常规格式; 5. 需要我司QC验货之后才能安排出货; 6. 出货方式： 货代自提； 7. 带锂电池出货，需在外箱正面或者侧面合适位置上加贴一张贴锂电池标签纸，由工厂订购 | Y40: Holly Zheng | Z40: 2.88 | AA40: =Z40*I40 -> 37440 | AB40: ZB05229-8.17 | AC40: 77794UQ1-S002 | AD40: 已入 | AE40: =I40 -> 13000 | AG40: =5856+7144 -> 13000 | AH40: =AG40-I40 -> 0 | AJ40: 系统出单 | AK40: =I40 -> 13000 | AN40: =I40 -> 13000 | AT40: =I40/8 -> 1625
A41: 46114 | D41: ZMPO260342 | F41: ZMPO260342-10 | G41: 77794-S001 | H41: 唱片机16pcs/箱 | I41: 1666 | J41: 0 | K41: 16 | L41: =I41/K41 -> 104.125 | M41: 46129 | N41: =M41-4 -> 46125 | P41: PASS | R41: 46114 | S41: 无 | T41: 无 | X41: Remark；大货最新版本/麻烦按款号装箱/并在外箱上注明款号/大货标准箱装箱/箱唛参照邮件附件；备注：收到样品订单后尽快安排 ，注意样板品质质量要求要高于大货品质要求 ，送货时必须要附带送货单(没有送货单和QC检验合格报告的仓库一律拒绝收货)，请知悉，谢谢！ | Y41: Angus | AC41: 77794-S001 | AD41: 已入 | AE41: =I41 -> 1666 | AG41: 1666 | AH41: =AG41-I41 -> 0 | AI41: 无 | AJ41: 系统出单 | AK41: =I41 -> 1666 | AN41: =I41 -> 1666
A42: 46045 | B42: UPD, INC. | C42: 美国 | D42: 4500192217 | E42: 36244 | F42: 4500192217-40 | G42: 77794UQ1-S001 | H42: 唱片机16pcs/2 UQ1/箱 | I42: 400 | J42: 0 | K42: 16 | L42: =I42/K42 -> 25 | M42: 46129 | N42: 46125 | P42: PASS | Q42: 4/21验货 | R42: 46092 | S42: 有 | T42: 无 | X42: 日期码格式：ZURU INC(BVI) 标准格式 日期：按实际生产日期 Packaging Info: 1. 包装方式：MA UPC 优先1L 最新包装，出口美国 Remark: 2. 外箱箱唛红色和黑色双色印刷 3. 产品和包装上印刷tracking code信息，格式为ZURU常规 | Y42: Angel Lin | Z42: 2.613 | AA42: =I42*Z42 -> 1045.2 | AB42: ZB05242-8.17 | AC42: 77794UQ1-S001 | AD42: 已入 | AE42: =I42 -> 400 | AF42: 按期 | AG42: 400 | AH42: =AG42-I42 -> 0 | AI42: 无 | AJ42: 系统出单 | AK42: =I42 -> 400 | AN42: =I42 -> 400 | AT42: =I42/8 -> 50
A43: 46091 | B43: SMYTHS TOYS EU HQ UC | C43: 德国 | D43: 4500196046 | E43: 4400549000 | F43: 4500196046-20 | G43: 77794UQ1-S001 | H43: 唱片机16pcs/2 UQ1/箱 | I43: 912 | J43: 0 | K43: 16 | L43: =I43/K43 -> 57 | M43: 46132 | N43: 46128 | P43: PASS | R43: 46097 | S43: 有 | T43: UN3481锂电池运输标签 | V43: 所有电子产品身上需要加字唛，为ZURU FRANCE 地址 (如无电子产品，产品布标有此地址，或产品太小无法增加可忽略此信息)，新地址ZURU FRANCE.33 rue Paul Meurice 75020 Paris, France. | X43: 日期码格式：ZURU INC(BVI) 标准格式 日期：按实际生产日期 Packaging Info: 77794UQ1: MA 3L配套包装+1张含德语callout/德意荷警语贴纸(本单放稿) EAN#4894680051430 RECHARGEABLE LITHIUM BATTERY(INCLUDED) *外箱需加一张UN3481锂电池运输标签* Remark: Smyths 德国 1. 请准时出货，推期会有罚款； 2. 所有产品按符合欧洲标准走货，需要是不含微塑料版本。 3. 所有电子产品身上需要加字唛，为ZURU FRANCE 地址 (如无电子产品，产品布标有此地址，或产品太小无法增加可忽略此信息)，新地址ZURU FRANCE.33 rue Pa ul Meurice 75020 Paris, France. 4. 电子产品需增加一张C版WEEE声明29L通用黑白说明书(不接受A版本，翻译有误)，区分带电池和不带电池出货版本, 如已做客版说明书可忽略此要求；如包装备注 上缺少此部分信息，请提醒跟单更新备注。 5.所有出往德国市场有关slime和带香味的都需要出无硼无香版本； 6.订单备注显示有分批的(不同仓库/订单号), 一定要区分客户订单号做货出货，否则会导致罚款 。 7.包装日期码按ZURU格式即可，请确保不迟于外箱日期码，可等于或者早于外箱日期码，必须为法定工作日。 8.做货前请先复核包装条码与订单是否一致再安排，对不上的需与ZURU跟单确认再安排。 9.包装必须含法国回收标(Sorting Label)，如没有，请提醒跟单提供贴纸资料。 | Y43: Sherry Lu | Z43: 4.355 | AA43: =I43*Z43 -> 3971.76 | AC43: 77794UQ1-S001-3L | AD43: 已入 | AE43: =I43 -> 912 | AF43: 新邵生产 | AG43: 912 | AH43: =AG43-I43 -> 0 | AJ43: 系统出单 | AL43: =I43 -> 912 | AN43: =I43 -> 912 | AU43: =I43/8 -> 114
A44: 46066 | B44: ZURU GERMANY GMBH | C44: 德国 | D44: 4500193875 | E44: 5200008771 | F44: 4500193875-50 | G44: 77794UQ1-S002-MTS | H44: 唱片机8pcs/UQ1/箱 | I44: 3600 | J44: 0 | K44: 8 | L44: =I44/K44 -> 450 | M44: 46132 | N44: 46128 | P44: PASS | R44: 46098 | S44: 有 | T44: 3/31多语警语折叠贴纸 | V44: 所有出往德国的电子产品身上需要加字唛，为ZURU FRANCE 地址，需跟包装上的地址一致 (如无电子产品，产品布标有此地址，或产品太小无法增加可忽略此信 息。如产品无法加字唛，需让对应跟单提供产品贴纸资料) 新地址：ZURU France 33 rue Paul Meurice 75020 Paris, France 旧地址：ZURU France 1/3, Rue d'Argenteuil 95210 SAINT-GRATIEN, FRANCE | X44: 日期码格式：ZURU INC(BVI) 标准格式 日期：按实际生产日期 Packaging Info: 77794UQ1: 77794UQ1: MA 3L PDQ+MA 3L EAN收缩膜+1*多语警语折叠贴纸(翻单4500192187）+23L玩法说明书+23L警语说明书+23L锂电池警语说明书+最新版C版WEEE 带电说明书 请注意：77794含锂电池，需在外箱贴一张含锂电池贴纸。 Remark: 1.德国内销单，需要通过ZURU 验货结果后才能出货 (工厂需要主动提前同ZURU QC预约验货避免延期出货造成不必要麻烦)； 2.产品如含有化学品（slime 等），需要无硼无香。需要无微塑料版本。 3.所有出口欧洲的产品, 法规规定禁止在包装和共公众用的印刷品中使用矿物油中含有的物质, 包装印刷油墨中含有的MOAH/MOSH的质量浓度不能超过1%, 否则出货 到法国被抽检出现问题, 供应商需要对此负责; 4. date code: 外箱日期码要晚于或等于产品日期码，不能早于产品的日期码； 5. 所有出往德国的电子产品身上需要加字唛，为ZURU FRANCE 地址，需跟包装上的地址一致 (如无电子产品，产品布标有此地址，或产品太小无法增加可忽略此信 息。如产品无法加字唛，需让对应跟单提供产品贴纸资料) 新地址：ZURU France 33 rue Paul Meurice 75020 Paris, France 旧地址：ZURU France 1/3, Rue d'Argenteuil 95210 SAINT-GRATIEN, FRANCE 6.所有出往德国订单的电子产品需增加一张最新版本的欧洲通用WEEE声明说明书，区分带电池和不带电池版本, 如已做客版说明书可忽略此要求。 7.装柜时需要按照款式号码从小到大一款款依次装,避免终端仓库卸货混乱.若一个柜子涉及到几个不同国家内销单,装柜时需要一个国家装完后再装另一个国家的 产品,依次装柜,避免终端仓库因不同国家不同库位位置卸货混乱. (此点需要同工厂装柜人员强调)" 8.ratio 同MA 9. 若有特定款有特殊外箱条码要求时,需要明确列出产品款对应的具体外箱条码号码/条码类型 (若无,可以忽略此需求). | Y44: Niki Chen | Z44: 5 | AA44: =I44*Z44 -> 18000 | AC44: 77794UQ1-S002-3L | AD44: 已入 | AE44: =I44 -> 3600 | AF44: 新邵生产 | AG44: 3600 | AH44: =AG44-I44 -> 0 | AI44: OK | AJ44: 系统出单 | AL44: =I44 -> 3600 | AN44: =I44 -> 3600 | AU44: =I44/8 -> 450
A45: 46078 | B45: DISTRIBUIDORA JUGUETRON S.A. DE C.V | C45: 墨西哥 | D45: 4500194136 | E45: 50212600321 | F45: 4500194136-50 | G45: 77794UQ1-S002 | H45: 唱片机8pcs/UQ1/箱 | I45: 5520 | J45: 0 | K45: 8 | L45: =I45/K45 -> 690 | M45: 46132 | N45: 46128 | O45: 此单有第三方监柜，需要每款多备1套完整物料 | P45: PASS | R45: 3/23 确认 | S45: 有 | T45: 4/1 外箱贴纸+保证书+进口商贴纸+UPC贴纸+产品/包装/说明书都要贴1张进口商贴纸 | X45: 日期码格式：ZURU INC(BVI) 标准格式 日期：按实际生产日期 Packaging Info: 77794UQ1:MA 多语包装+MA 多语说明书+外箱贴纸+保证书+进口商贴纸+UPC贴纸+箱唛，产品/包装/说明书都要贴1张进口商贴纸 Remark: 1.此单有第三方监柜，需要每款多备1套完整物料 2.外箱贴纸只要一张，位置是正唛和侧唛的交接处 | Y45: Ava Liang | Z45: 5 | AA45: =Z45*I45 -> 27600 | AC45: 77794UQ1-S002 | AD45: 已入 | AE45: =I45 -> 5520 | AG45: 5520 | AH45: =AG45-I45 -> 0 | AI45: OK | AJ45: 系统出单 | AK45: =I45 -> 5520 | AN45: =I45 -> 5520 | AT45: =I45/8 -> 690
A46: 46093 | B46: B&M RETAIL LIMITED | C46: 英国 | D46: 4500196425 | E46: 02436939/1 | F46: 4500196425-20 | G46: 77794UQ1-S001 | H46: 唱片机16pcs/2 UQ1/箱 | I46: 6000 | J46: 0 | K46: 16 | L46: =I46/K46 -> 375 | M46: 46132 | N46: 46128 | P46: PASS | Q46: 4/28 SI | R46: 46099 | S46: 有 | T46: WEEE 带电池走货 通用30L B 版说明书 | X46: 日期码格式：ZURU INC(BVI) 标准格式 日期：按实际生产日期 Packaging Info: 77794UQ1-S001: MA UPC版本+带电池版本WEEE 带电池走货 通用29L C版说明书+23L 锂电池说明书 9565GQ1-S001:MA UPC版本+不带电池版本WEEE 不带电池走货 通用29L C版说明书 Remark: 1) MA UPC版本。订单出英国，请注意检查产品及包装应带UKCA图标，包装显示ZURU UK LTD信息，QC同事请查核，如有问题与跟单确认。 2) 生产日期按实际（法定工作日），按ZURU标准格式即可 ，但是请知悉包装日期码需要早于或者等于外箱日期码 ，不能晚于外箱日期码 3) 请注意所有订单都需要经过ZURU QC验货并且通过后方可出货 4) 条码以订单显示为准 ，请安排生产前先核对 ，有问题请提出。 5) 所有产品按符合欧洲标准走货，需要是不含微塑料版本 。涉及到硼的，如可选择情况下应使用低硼版本 （slime 类别低硼一般低于300ppm)，无选择的应与跟单 复核再安排 。 6) 所有出往欧洲订单的电子产品需增加一张客版WEEE说明书，区分带电池(WEEE 带电池走货 通用29L C 版说明书)和不带电池版本(WEEE 不带电池走货 通用29L C版说明书) 7) 订单若对应多个客户PO， 请分开做货， 不要混装。一个PO一个柜 8) 大货完成后请及时提供shipment images 供客户批复 ，如未提供照片就直接走柜，有问题由工厂负责 。 9） 最终出货工厂需要按船务要求为集装箱挂网，如不按要求挂网导致罚款由工厂承担 。 10）若有锂电池，需在外箱上加锂电池标签。 | Y46: Ann Zhang | Z46: 4.355 | AA46: =I46*Z46 -> 26130 | AC46: 77794UQ1-S001 | AD46: 已入 | AE46: =I46 -> 6000 | AF46: 新邵生产 | AG46: =16+5984 -> 6000 | AH46: =AG46-I46 -> 0 | AI46: OK | AJ46: 系统出单 | AK46: =I46 -> 6000 | AN46: =I46 -> 6000 | AT46: =I46/8 -> 750
A47: 46093 | B47: B&M RETAIL LIMITED | C47: 英国 | D47: 4500196425 | E47: 02436948/1 | F47: 4500196425-30 | G47: 77794UQ1-S001 | H47: 唱片机16pcs/2 UQ1/箱 | I47: 6000 | J47: 0 | K47: 16 | L47: =I47/K47 -> 375 | M47: 46132 | N47: 46128 | P47: PASS | Q47: 4/28 SI | R47: 46099 | S47: 有 | T47: WEEE 带电池走货 通用30L B 版说明书 | X47: 日期码格式：ZURU INC(BVI) 标准格式 日期：按实际生产日期 Packaging Info: 77794UQ1-S001: MA UPC版本+带电池版本WEEE 带电池走货 通用29L C版说明书+23L 锂电池说明书 9565GQ1-S001:MA UPC版本+不带电池版本WEEE 不带电池走货 通用29L C版说明书 Remark: 1) MA UPC版本。订单出英国，请注意检查产品及包装应带UKCA图标，包装显示ZURU UK LTD信息，QC同事请查核，如有问题与跟单确认。 2) 生产日期按实际（法定工作日），按ZURU标准格式即可 ，但是请知悉包装日期码需要早于或者等于外箱日期码 ，不能晚于外箱日期码 3) 请注意所有订单都需要经过ZURU QC验货并且通过后方可出货 4) 条码以订单显示为准 ，请安排生产前先核对 ，有问题请提出。 5) 所有产品按符合欧洲标准走货，需要是不含微塑料版本 。涉及到硼的，如可选择情况下应使用低硼版本 （slime 类别低硼一般低于300ppm)，无选择的应与跟单 复核再安排 。 6) 所有出往欧洲订单的电子产品需增加一张客版WEEE说明书，区分带电池(WEEE 带电池走货 通用29L C 版说明书)和不带电池版本(WEEE 不带电池走货 通用29L C版说明书) 7) 订单若对应多个客户PO， 请分开做货， 不要混装。一个PO一个柜 8) 大货完成后请及时提供shipment images 供客户批复 ，如未提供照片就直接走柜，有问题由工厂负责 。 9） 最终出货工厂需要按船务要求为集装箱挂网，如不按要求挂网导致罚款由工厂承担 。 10）若有锂电池，需在外箱上加锂电池标签。 | Y47: Ann Zhang | Z47: 4.355 | AA47: =I47*Z47 -> 26130 | AC47: 77794UQ1-S001 | AD47: 已入 | AE47: =I47 -> 6000 | AF47: 新邵生产 | AG47: 6000 | AH47: =AG47-I47 -> 0 | AI47: OK | AJ47: 系统出单 | AK47: =I47 -> 6000 | AN47: =I47 -> 6000 | AT47: =I47/8 -> 750
A48: 46079 | B48: TARGET US | C48: 美国 | D48: 4500194297 | E48: 10001661693-3890 | F48: 4500194297-60 | G48: 77794UQ1-S002 | H48: 唱片机8pcs/UQ1/箱 | I48: 9416 | J48: 0 | K48: 8 | L48: =I48/K48 -> 1177 | M48: 46132 | N48: 46128 | P48: PASS | R48: 3/23 确认 | S48: 有 | T48: 3/13 外箱条码箱贴纸贴纸，2/26提供EVENT LABEL | V48: 外箱锂电池贴纸 | X48: 日期码格式：ZURU INC(BVI) 标准格式 日期：按实际生产日期 Packaging Info: 77794UQ1：产品包装 MA 1L黑白警告语说明书+MA 1L 彩盒+MA 1L PDQ Remark: 77794UQ1： 1.77794UQ1-S002-MINI BRANDS-VINYL-PLAYSET-SERIES 1-CUBE,8PCS/PDQ,8PCS/PDQ/CTN; 2. 产品包装 MA 1L黑白警告语说明书+MA 1L 彩盒+MA 1L PDQ; 彩盒上的UPC显示193052090409; 3. 外箱正唛左上角位置粘贴条码箱贴纸，每箱只贴一张，由ZURU订购。来料贴纸上显示的客户DPCI# 086-02-4085, UPC显示10193052090406; 4.带锂电池出货，需在外箱正面或者侧面合适位置上加贴一张贴锂电池标签纸，由工厂订购 以上Items： 1. 产品和包装上均要印刷tracking code信息，格式为ZURU常规格式； 2. 需要我司QC验货之后才能安排出货 3. 出货方式： 货代自提 | Y48: Holly Zheng | Z48: 2.88 | AA48: =Z48*I48 -> 27118.08 | AB48: ZB05445-8.17 | AC48: 77794UQ1-S002 | AD48: 已入 | AE48: =I48 -> 9416 | AF48: 新邵生产 | AG48: =5632+3784 -> 9416 | AH48: =AG48-I48 -> 0 | AJ48: 系统出单 | AK48: =I48 -> 9416 | AN48: =I48 -> 9416 | AT48: =I48/8 -> 1177
A49: 46050 | B49: TARGET US | C49: 美国 | D49: 4500192440 | E49: 10001701246-3890 | F49: 4500192440-10 | G49: 77897-S001 | H49: 唱片机展示 | I49: 1070 | J49: 0 | K49: 1 | L49: =I49/K49 -> 1070 | M49: 46132 | N49: 46128 | P49: PASS | R49: 46059 | S49: 有 | T49: 46056 | V49: 外箱锂电池贴纸 | X49: 日期码格式：ZURU INC(BVI) 标准格式 日期：按实际生产日期 Packaging Info: Remark: 1. 77897-S001-MINI BRANDS-VINYL-SERIES 1-DISPLAY BOX WITH DEMO,1SET/CTN; 2. 每个外箱正唛信息左上方位置粘贴条码箱贴纸，每箱只贴一张，由ZURU订购；对应的外箱贴DPCI#086-94-5923，UPC#显示为193052108142; 3. 每个亚克力盒子的背面中间位置需要贴一张"SAMPLE - Not for Resale" 贴纸，工厂自行订购； 4. 每个外箱正唛箱唛内容右侧需贴一张Event label，内容显示Class 94 Displays Set Date：7/19/2026，工厂自行订购； 5. 每个外箱上需额外印刷 "Contains Display Box. Non-Saleable Unit."信息，字体和大小没有特殊要求, 可以与箱唛信息保持相同即可；外箱四面需要印刷易碎 /向上的LOGO； 6. 每个纸箱需要装一张货架的整体效果图，用A4纸打印即可； 7. 每个纸箱需要装一张demo box组装说明，工厂自行订购； 8. 产品和包装上印刷 tracking code信息，格式为ZURU常规格式; 9. 出货方式：货代自提 | Y49: Holly Zheng | Z49: 12 | AA49: =I49*Z49 -> 12840 | AB49: ZB05478-8.17 | AC49: 77897-S001 | AD49: 已入 | AE49: =I49 -> 1070 | AG49: 1070 | AH49: =AG49-I49 -> 0 | AJ49: 系统出单 | BH49: =I49 -> 1070
A50: 46090 | B50: TARGET US | C50: 美国 | D50: 4500195753 | E50: 10001764949-0 581 | F50: 4500195753-10 | G50: 77794UQ1-S002 | H50: 唱片机8pcs/UQ1/箱 | I50: 20336 | J50: 0 | K50: 8 | L50: =I50/K50 -> 2542 | M50: 46132 | N50: 46128 | P50: PASS | R50: 46105 | S50: 有 | T50: 4/1外箱条码箱贴纸贴纸，2/26提供EVENT LABEL | V50: 外箱锂电池贴纸 | X50: 日期码格式：ZURU INC(BVI) 标准格式 日期：按实际生产日期 Packaging Info: 产品包装 MA 1L黑白警告语说明书+MA 1L 彩盒+MA 1L PDQ+锂电池标签纸 Remark: 1.77794UQ1-S002-MINI BRANDS-VINYL-PLAYSET-SERIES 1-CUBE,8PCS/PDQ,8PCS/PDQ/CTN; 2. 产品包装 MA 1L黑白警告语说明书+MA 1L 彩盒+MA 1L PDQ; 彩盒上的UPC显示193052090409; 3. 外箱正唛左上角位置粘贴条码箱贴纸，每箱只贴一张，由ZURU订购。来料贴纸上显示的客户DPCI# 086-02-4085, UPC显示10193052090406; 4. 产品和包装上均要印刷tracking code信息，格式为ZURU常规格式; 5. 需要我司QC验货之后才能安排出货; 6. 出货方式： 货代自提； 7. 带锂电池出货，需在外箱正面或者侧面合适位置上加贴一张贴锂电池标签纸，由工厂订购 | Y50: Holly Zheng | Z50: 2.88 | AA50: =Z50*I50 -> 58567.68 | AB50: ZB05351-8.17 | AC50: 77794UQ1-S002 | AD50: 已入 | AE50: =I50 -> 20336 | AG50: =3840+16496 -> 20336 | AH50: =AG50-I50 -> 0 | AJ50: 系统出单 | AK50: =I50 -> 20336 | AN50: =I50 -> 20336 | AT50: =I50/8 -> 2542
A51: 46121 | D51: ZMPO260369 | F51: ZMPO260369-10 | G51: 77897-S001 | I51: 2 | M51: 46132 | N51: =M51-4 -> 46128 | R51: 周转箱 | S51: 无 | T51: 无 | X51: Remark；大货版本；备注：收到样品订单后尽快安排 ，注意样板品质质量要求要高于大货品质要求 ，送货时必须要附带送货单(没有送货单和QC检验合格报告的仓库一律拒绝收货)，请知悉，谢谢！ | Y51: Angus | AD51: # | AE51: =I51 -> 2 | AH51: =AG51-I51 -> -2 | BH51: =I51 -> 2
A52: 46086 | B52: ZURU LLC | C52: 美国 | D52: 4500195402 | E52: 5200009175 | F52: 4500195402-30 | G52: 77794-S001-MTS | H52: 唱片机16pcs/箱 | I52: 992 | J52: 0 | K52: 16 | L52: =I52/K52 -> 62 | M52: 46132 | N52: 46128 | P52: 4/22湖南验货AOD | R52: 46086 | S52: 有 | T52: 无 | X52: 日期码格式：ZURU INC(BVI) 标准格式 日期：按实际生产日期 Packaging Info: #77794: MA UPC版包装(1L或3L都可,3L要加UPC条码)，出口美国。 Remark: 1.Amazon domestic 订单。出口美国。外箱最长边不能超过25" （超过了，case pack只能为1），不符合要求的大货，一律不接受。 2.无第三方验货/测试要求。 3.日期码使用ZURU标准版本。 4.如果大货有要求入邮包盒，则对应的邮包盒上面要打上日期码。 | Y52: Kelly Shen/Mia Pan/P | Z52: 2.466 | AA52: =I52*Z52 -> 2446.272 | AB52: ZB05350-8.17 | AC52: 77794-S001 | AD52: 已入 | AE52: =I52 -> 992 | AG52: 992 | AH52: =AG52-I52 -> 0 | AI52: 无 | AJ52: 系统出单 | AK52: =I52 -> 992 | AN52: =I52 -> 992
A53: 46052 | B53: WALMART INC. | C53: 美国 | D53: 4500192828 | E53: 7137243188 | F53: 4500192828-10 | G53: 77794SK-S001 | H53: 唱片机16pcs/展示架装（不带底座） | I53: 5184 | J53: 0 | K53: 16 | L53: =I53/K53 -> 324 | M53: 46132 | N53: 46128 | O53: 4/24 BV验货 | P53: HOLD | R53: 46052 | S53: 有 | T53: 2/9 寄出RFID贴纸 | X53: 日期码格式：ZURU DGYYYYMMDD CHINA(日期避开周末和法定节假日即可） 日期：按实际生产日期 Packaging Info: 1. 包装要求： 77794SK：MA 1L A版callout纸卡+MA 23L 玩法说明书+MA 23L 警告语说明书+MA USB连接线贴纸+客版 1L sidekick 每pcs产品要贴一张RFID贴纸，RFID贴纸由ZURU提供，贴纸位置要严格按照客人签板 Remark: 1. 包装要求： 77794SK：MA 1L A版callout纸卡+MA 23L 玩法说明书+MA 23L 警告语说明书+MA USB连接线贴纸+客版 1L sidekick 每pcs产品要贴一张RFID贴纸，RFID贴纸由ZURU提供，贴纸位置要严格按照客人签板 2.外箱RFID箱唛（四面右下角需印Zuru Logo)+ ITF-14条码；ITF-14条码印刷在外箱主唛左下角，外箱任一侧面角落备注："MADE IN CHINA" 字样，一张锂电池贴纸 贴在有条码的正唛上，外箱箱唛资料待提供。 3. 在产品上和包装上要有日期码、以及要有MADE IN CHINA和ZURU字样； 4. 产品如有扎带口要剪平，不能刮手。 5. 此单需要验货，请自行多备包装物料。 6. 16pcs/Sidekick/CTN | Y53: Maggie Xie | Z53: 44.256 | AA53: =L53*Z53 -> 14338.944 | AB53: ZB05413-8.17 | AC53: 77794SK-S001 | AD53: 已入 | AE53: =I53 -> 5184 | AG53: 5184 | AH53: =AG53-I53 -> 0 | AI53: OK | AJ53: 系统出单 | AK53: =I53 -> 5184 | AN53: =I53 -> 5184 | BG53: =I53/16 -> 324
A54: 46052 | B54: WALMART INC. | C54: 美国 | D54: 4500192828 | E54: 7137243193 | F54: 4500192828-20 | G54: 77794SK-S001 | H54: 唱片机16pcs/展示架装（不带底座） | I54: 4304 | J54: 0 | K54: 16 | L54: =I54/K54 -> 269 | M54: 46132 | N54: 46128 | O54: 4/24 BV验货 | P54: HOLD | R54: 46052 | S54: 有 | T54: 2/9 寄出RFID贴纸 | X54: 日期码格式：ZURU DGYYYYMMDD CHINA(日期避开周末和法定节假日即可） 日期：按实际生产日期 Packaging Info: 1. 包装要求： 77794SK：MA 1L A版callout纸卡+MA 23L 玩法说明书+MA 23L 警告语说明书+MA USB连接线贴纸+客版 1L sidekick 每pcs产品要贴一张RFID贴纸，RFID贴纸由ZURU提供，贴纸位置要严格按照客人签板 Remark: 1. 包装要求： 77794SK：MA 1L A版callout纸卡+MA 23L 玩法说明书+MA 23L 警告语说明书+MA USB连接线贴纸+客版 1L sidekick 每pcs产品要贴一张RFID贴纸，RFID贴纸由ZURU提供，贴纸位置要严格按照客人签板 2.外箱RFID箱唛（四面右下角需印Zuru Logo)+ ITF-14条码；ITF-14条码印刷在外箱主唛左下角，外箱任一侧面角落备注："MADE IN CHINA" 字样，一张锂电池贴纸 贴在有条码的正唛上，外箱箱唛资料待提供。 3. 在产品上和包装上要有日期码、以及要有MADE IN CHINA和ZURU字样； 4. 产品如有扎带口要剪平，不能刮手。 5. 此单需要验货，请自行多备包装物料。 6. 16pcs/Sidekick/CTN | Y54: Maggie Xie | Z54: 44.256 | AA54: =L54*Z54 -> 11904.864 | AB54: ZB05414-8.17 | AC54: 77794SK-S001 | AD54: 已入 | AE54: =I54 -> 4304 | AG54: 4304 | AH54: =AG54-I54 -> 0 | AI54: OK | AJ54: 系统出单 | AK54: =I54 -> 4304 | AN54: =I54 -> 4304 | BG54: =I54/16 -> 269
A55: 46108 | D55: ZMPO260309 | F55: ZMPO260309-10 | G55: 77794-S001 | H55: 唱片机16pcs/箱 | I55: 240 | J55: 0 | K55: 16 | L55: =I55/K55 -> 15 | M55: 46132 | N55: 46128 | R55: 46108 | S55: 有 | T55: 无 | X55: Remark:大货最新版本/麻烦按款号装箱/并在外箱上注明款号/大货标准箱装箱/箱唛参照邮件附件,备注：收到样品订单后尽快安排 ，注意样板品质质量要求要高于大货品质要求 ，送货时必须要附带送货单(没有送货单和QC检验合格报告的仓库一律拒绝收货)，请知悉，谢谢！ 备注：收到样品订单后尽快安排 ，注意样板品质质量要求要高于大货品质要求 ，送货时必须要附带送货单(没有送货单和QC检验合格报告的仓库一律拒绝收货)，请知悉，谢谢！ | Y55: Angus | AC55: 77794-S001 | AD55: 已入 | AE55: =I55 -> 240 | AH55: =AG55-I55 -> -240 | AI55: 无 | AJ55: 系统出单 | AK55: =I55 -> 240 | AN55: =I55 -> 240
A56: 46094 | B56: ZURU NEW ZEALAND LIMITED | C56: 新西兰 | D56: 4500196745 | E56: 5200009279 | F56: 4500196745-10 | G56: 77794UQ1-S001-FS | H56: 唱片机16pcs/2 UQ1/箱 | I56: 400 | J56: 0 | K56: 16 | L56: =I56/K56 -> 25 | M56: 46136 | N56: 46132 | P56: PASS | R56: 46099 | S56: 有 | T56: 锂电池黑白警语书纸 (贴纸以及位置图翻单PO#450019 3539）+ 1张fast start专用UPC贴纸+贴一张黄色A4纸，印"fast start"内容。（两张贴纸及位置图翻单4500190798) | X56: 日期码格式：ZURU INC(BVI) 标准格式 日期：按实际生产日期 Packaging Info: 77794UQ1:MA英语UPC版本包装（收缩膜和说明书, MA首选1L，如无1L可用多语且含英语的配套多语包装) +1张锂电池黑白警语书纸 (贴纸以及位置图翻单PO#450019 3539）+ 1张fast start专用UPC贴纸+贴一张黄色A4纸，印"fast start"内容。（两张贴纸及位置图翻单4500190798)+箱唛 Remark: 1.请务必按时完货，验货。并且按期送货入货代指定仓库，如果晚了导致船期Delay将会有罚金产生或者客户要求空运，所产生的罚金和空运费由工厂承担。 2.外箱材质为ZURU标准； 3.此单需使用KMART封箱胶上下工字型封箱;从2019年6月开始，要用KMART 新版封箱胶带，此单要用"ANKO"封箱胶带 4.此单出口新西兰，请按相应的澳新标准生产； 5.产品和包装上生产批号的显示格式ZURU标准日期码格式 6.外箱信息不可手写，重量和体积需要与实际的一致(不可手写） 7. 实际外箱重量跟印在箱唛上的数据差异不能超3%，尺寸按实际数据印刷 | Y56: Louise Lu | Z56: 4.355 | AA56: =I56*Z56 -> 1742 | AC56: 77794UQ1-S001 | AD56: 已入 | AE56: =I56 -> 400 | AF56: 已完成 | AG56: =368+32 -> 400 | AH56: =AG56-I56 -> 0 | AJ56: 系统出单 | AK56: =I56 -> 400 | AN56: =I56 -> 400 | AT56: =I56/8 -> 50
A57: 46090 | B57: WAL-MART CANADA CORP. | C57: 加拿大 | D57: 4500195369 | E57: 7000991881 | F57: 4500195369-40 | G57: 77794UQ1-S002 | H57: 唱片机8pcs/UQ1/箱 | I57: 3192 | J57: 0 | K57: 8 | L57: =I57/K57 -> 399 | M57: 46136 | N57: 46132 | O57: 4/27第三方验货，抽办50% | P57: PASS | R57: 46098 | S57: 有 | T57: 3/9UPC贴纸(UPC:193052090409) | X57: 日期码格式：ZURU INC(BVI) 标准格式 日期：按实际生产日期 Packaging Info: #77794 MA3LPDQ(8装)+MA3L彩盒+UPC贴纸(UPC:193052090409)+MA23L说明书+MA23L警告语说明书 Remark: 1. 此单有箱唛; 2. UPC贴纸：必须在原来错误的条码上用黑色粗头笔涂黑直至不能扫描，再贴上正确的UPC; 3. 此单有第三方验货，烦请多备包装物料； 4. #77794带锂电池出货，使用英法双语电池，外箱需在正唛空白位置贴一张UN3481锂电池标识贴纸； 5. 需4/17前安排签样，签样要求如下： #77794：大货样3PCS+空PDQ2PCS； 6.需安排4/24抽板测试，抽板要求如下： #77794：大货4PCS； ********************* a. 请确保产品符合1999年版本的加拿大环境保护法(CEPA)和2012年禁止某些有毒物质法规的要求。该产品不含任何在加拿大禁用的化学物质，包括但不限于有毒物 质清单中列出的化学物质，并且在为加拿大沃尔玛生产产品期间没有使用任何禁用化学物质。 Supplier certify that the products comply with the requirements of Canadian Environmental Protection Act, 1999 (CEPA), Prohibition of Certain To xic Substances Regulations, 2012. The products do not contain any chemicals that are banned in Canada, including but not limited to those listed in the Toxic Substances List and no banned chemicals were used during the manufacturing of product for Walmart Canada. 附件列表： (1) Letter of Guarantee for Canada banned chemicals - (1-5CA) b. 请确保产品在均质材料中的汞浓度不超过0.1%（按重量计）。 Supplier certify that the WAL-MART vendor products does not have a mercury concentration of more than 0.1% by weight in homogeneous material. 附件列表： (1) Letter of Guarantee for Mercury COC c. 请确保产品的塑料材料不含以下物质（SOR 2011-17 27B): Supplier certify that the plastic materials do not contain the following substances(SOR 2011-17 27B): (a) carbon tetrachloride or any substance that contains it; (b) methyl alcohol or any substance thay contains >1.0%; (c) petroleum distillates or any substance that contains >10% weight to volume of petroleum distillates; (d) benzene; (e) turpentine or any substance that contains >10% weight to volume of turpentine; (f) boric acid or salts of boric acid; or (g) ethyl ether. 附件列表： (1) Letter of Guarantee for WM CA-Other prohibited substances in plastic(less than 3 years) | Y57: Fly Song | Z57: 5 | AA57: =Z57*I57 -> 15960 | AC57: 77794UQ1-S002-3L | AD57: 已入 | AE57: =I57 -> 3192 | AF57: 新邵生产 | AG57: =3088+104 -> 3192 | AH57: =AG57-I57 -> 0 | AI57: OK | AJ57: 系统出单 | AL57: =I57 -> 3192 | AN57: =I57 -> 3192 | AU57: =I57/8 -> 399
A58: 46079 | B58: TARGET US | C58: 美国 | D58: 4500194290 | E58: 10001708292-0 581 | F58: 4500194290-40 | G58: 77794UQ1-S002 | H58: 唱片机8pcs/UQ1/箱 | I58: 2000 | J58: 0 | K58: 8 | L58: =I58/K58 -> 250 | M58: 46136 | N58: 46132 | P58: PASS | R58: 46105 | S58: 有 | T58: 4/1外箱条码箱贴纸贴纸，2/26提供EVENT LABEL | V58: 外箱锂电池贴纸 | X58: 日期码格式：ZURU INC(BVI) 标准格式 日期：按实际生产日期 Packaging Info: 77794UQ1：产品包装 MA 1L黑白警告语说明书+MA 1L 彩盒+MA 1L PDQ Remark: 77794UQ1： 1.77794UQ1-S002-MINI BRANDS-VINYL-PLAYSET-SERIES 1-CUBE,8PCS/PDQ,8PCS/PDQ/CTN; 2. 产品包装 MA 1L黑白警告语说明书+MA 1L 彩盒+MA 1L PDQ; 彩盒上的UPC显示193052090409; 3. 外箱正唛左上角位置粘贴条码箱贴纸，每箱只贴一张，由ZURU订购。来料贴纸上显示的客户DPCI# 086-02-4085, UPC显示10193052090406; 4. 带锂电池出货，需在外箱正面或者侧面合适位置上加贴一张贴锂电池标签纸，由工厂订购 以上Items： 1. 产品和包装上均要印刷tracking code信息，格式为ZURU常规格式； 2. 需要我司QC验货之后才能安排出货 3. 出货方式： 货代自提 | Y58: Holly Zheng | Z58: 2.88 | AA58: =Z58*I58 -> 5760 | AB58: ZB05479-8.17 | AC58: 77794UQ1-S002 | AD58: 已入 | AE58: =I58 -> 2000 | AF58: 新邵生产 | AG58: 2000 | AH58: =AG58-I58 -> 0 | AI58: OK | AJ58: 系统出单 | AK58: =I58 -> 2000 | AN58: =I58 -> 2000 | AT58: =I58/8 -> 250
A59: 46090 | B59: TARGET US | C59: 美国 | D59: 4500195755 | E59: 10001764950-0 581 | F59: 4500195755-10 | G59: 77794UQ1-S002 | H59: 唱片机8pcs/UQ1/箱 | I59: 14200 | J59: 0 | K59: 8 | L59: =I59/K59 -> 1775 | M59: 46141 | N59: 46137 | P59: PASS | R59: 46105 | S59: 有 | T59: 4/13外箱条码箱贴纸贴纸，2/26提供EVENT LABEL | V59: 外箱锂电池贴纸 | X59: 日期码格式：ZURU INC(BVI) 标准格式 日期：按实际生产日期 Packaging Info: 产品包装 MA 1L黑白警告语说明书+MA 1L 彩盒+MA 1L PDQ+锂电池标签纸 Remark: 1.77794UQ1-S002-MINI BRANDS-VINYL-PLAYSET-SERIES 1-CUBE,8PCS/PDQ,8PCS/PDQ/CTN; 2. 产品包装 MA 1L黑白警告语说明书+MA 1L 彩盒+MA 1L PDQ; 彩盒上的UPC显示193052090409; 3. 外箱正唛左上角位置粘贴条码箱贴纸，每箱只贴一张，由ZURU订购。来料贴纸上显示的客户DPCI# 086-02-4085, UPC显示10193052090406; 4. 产品和包装上均要印刷tracking code信息，格式为ZURU常规格式; 5. 需要我司QC验货之后才能安排出货; 6. 出货方式： 货代自提； 7. 带锂电池出货，需在外箱正面或者侧面合适位置上加贴一张贴锂电池标签纸，由工厂订购 | Y59: Holly Zheng | Z59: 2.88 | AA59: =Z59*I59 -> 40896 | AB59: ZB05514-8.17 | AC59: 77794UQ1-S002 | AD59: 已入 | AE59: =I59 -> 14200 | AF59: 新邵生产 | AG59: =2304+3456+8152+288 -> 14200 | AH59: =AG59-I59 -> 0 | AI59: OK | AJ59: 系统出单 | AK59: =I59 -> 14200 | AN59: =I59 -> 14200 | AT59: =I59/8 -> 1775
A60: 46080 | B60: MEIJER DISTRIBUTION, INC. | C60: 美国 | D60: 4500194444 | E60: 219021593 | F60: 4500194444-10 | G60: 77794UQ1-S002 | H60: 唱片机8pcs/UQ1/箱 | I60: 1824 | J60: 0 | K60: 8 | L60: =I60/K60 -> 228 | M60: 46142 | N60: 46139 | P60: PASS | R60: 46111 | S60: 有 | T60: 无 | X60: 日期码格式：ZURU INC(BVI) 标准格式 日期： Packaging Info: 1. 产品MA UPC包装（优先1L）出美国 2. 客人指定箱唛排版 Remark: 出货前 Zuru QC 验货 | Y60: Agnes Zheng | Z60: 3 | AA60: =Z60*I60 -> 5472 | AB60: ZB05443-8.17 | AC60: 77794UQ1-S002 | AD60: 已入 | AE60: =I60 -> 1824 | AG60: 1824 | AH60: =AG60-I60 -> 0 | AJ60: 系统出单 | AK60: =I60 -> 1824 | AN60: =I60 -> 1824 | AT60: =I60/8 -> 228
A61: 46080 | B61: MEIJER DISTRIBUTION, INC. | C61: 美国 | D61: 4500194444 | E61: 219021652 | F61: 4500194444-20 | G61: 77794UQ1-S002 | H61: 唱片机8pcs/UQ1/箱 | I61: 1064 | J61: 0 | K61: 8 | L61: =I61/K61 -> 133 | M61: 46142 | N61: 46139 | P61: PASS | R61: 46111 | S61: 有 | T61: 无 | X61: 日期码格式：ZURU INC(BVI) 标准格式 日期： Packaging Info: 1. 产品MA UPC包装（优先1L）出美国 2. 客人指定箱唛排版 Remark: 出货前 Zuru QC 验货 | Y61: Agnes Zheng | Z61: 3 | AA61: =Z61*I61 -> 3192 | AB61: ZB05408-8.17 | AC61: 77794UQ1-S002 | AD61: 已入 | AE61: =I61 -> 1064 | AG61: 1064 | AH61: =AG61-I61 -> 0 | AJ61: 系统出单 | AK61: =I61 -> 1064 | AN61: =I61 -> 1064 | AT61: =I61/8 -> 133
A62: 46080 | B62: MEIJER DISTRIBUTION, INC. | C62: 美国 | D62: 4500194442 | E62: 219072777 | F62: 4500194442-30 | G62: 77794UQ1-S002 | H62: 唱片机8pcs/UQ1/箱 | I62: 984 | J62: 0 | K62: 8 | L62: =I62/K62 -> 123 | M62: 46142 | N62: 46139 | P62: PASS | R62: 46111 | S62: 有 | T62: 无 | X62: 日期码格式：ZURU INC(BVI) 标准格式 日期： Packaging Info: 1. 通用PDQ, 产品MA UPC包装（优先1L）出美国 其中 92129TQ5为客版pdq翻单4500180920 2. 客人指定箱唛排版 Remark: 出货前 Zuru QC 验货 | Y62: Agnes Zheng | Z62: 3 | AA62: =Z62*I62 -> 2952 | AB62: ZB05585-8.17 | AC62: 77794UQ1-S002 | AD62: 已入 | AE62: =I62 -> 984 | AG62: 984 | AH62: =AG62-I62 -> 0 | AJ62: 系统出单 | AK62: =I62 -> 984 | AN62: =I62 -> 984 | AT62: =I62/8 -> 123
A63: 46080 | B63: MEIJER DISTRIBUTION, INC. | C63: 美国 | D63: 4500194442 | E63: 219072785 | F63: 4500194442-40 | G63: 77794UQ1-S002 | H63: 唱片机8pcs/UQ1/箱 | I63: 1824 | J63: 0 | K63: 8 | L63: =I63/K63 -> 228 | M63: 46142 | N63: 46139 | P63: PASS | R63: 46111 | S63: 有 | T63: 无 | X63: 日期码格式：ZURU INC(BVI) 标准格式 日期： Packaging Info: 1. 通用PDQ, 产品MA UPC包装（优先1L）出美国 其中 92129TQ5为客版pdq翻单4500180920 2. 客人指定箱唛排版 Remark: 出货前 Zuru QC 验货 | Y63: Agnes Zheng | Z63: 3 | AA63: =Z63*I63 -> 5472 | AB63: ZB05585-8.17 | AC63: 77794UQ1-S002 | AD63: 已入 | AE63: =I63 -> 1824 | AG63: 1824 | AH63: =AG63-I63 -> 0 | AJ63: 系统出单 | AK63: =I63 -> 1824 | AN63: =I63 -> 1824 | AT63: =I63/8 -> 228
A64: 46080 | B64: THE ENTERTAINER | C64: 英国 | D64: 4500194581 | E64: FB14535 | F64: 4500194581-80 | G64: 77794UQ1-S002 | H64: 唱片机8pcs/UQ1/箱 | I64: 3000 | J64: 0 | K64: 8 | L64: =I64/K64 -> 375 | M64: 46142 | N64: =M64-3 -> 46139 | O64: 新款请在CRD前10天寄出每款2整套大货样到罗湖办公室7B Meyya Liu 收，翻单不用寄。" | P64: PASS | Q64: 4/29 出货 | R64: 46093 | S64: 有 | T64: MA锂电池警语书纸 | V64: 此为去掉LOLA YANG的特殊版本 | W64: * 大货样： 新款请在CRD前10天寄出每款2整套大货样到罗湖办公室7B Meyya Liu 收，翻单不用寄。" | X64: 日期码格式：ZURU INC(BVI) 标准格式 日期：按实际生产日期 Packaging Info: 77794UQ1-S002：MA B版1L UPC版本+C版29L含电池出货版本WEEE说明书以及欧洲澳新通用Warning instruction 因产品含有锂电池，需要在外箱加上UN3481的贴纸，贴纸尺寸106*106mm，贴在正唛其中1面右上角 Remark: "MA版本按工厂现有最新库存即可，订单出英国，请注意检查产品及包装应带UKCA以及CE图标，包装显示ZURU UK LTD信息，QC同事请查核，如有问题与跟单确认 *生产日期按实际（法定工作日），按ZURU标准格式即可 ，但是请知悉包装日期码需要早于或者等于外箱日期码 ，不能晚于外箱日期码 *请注意所有订单都需要经过ZURU QC验货并且通过后方可出货 *所有产品按符合欧洲标准走货，需要是不含微塑料版本 。 *涉及到硼的，如可选择情况下应使用低硼版本 （slime 类别低硼一般低于300ppm)，无选择的应与跟单复核再安排 。 *如果出运产品属于电子类产品需要在ZURU 包装基础上额外添加一张ZURU 标准30L通用WEEE 电子产品说明书,带电池出货的加带电池出货版本通用30L的说明书，不 带电池出货的产品用不带电池出货版本的说明书. *根据客人最新的包装要求，所有多个PDQ盒子(TQ,UQ,GQ）入1外箱的都需要在PDQ顶部右上角加上数量贴纸标明里面的数量。最小字体：36pts, 字体：Calibri（bo ld), 具体要求以及位置见文件. *订单对应客户PO号 ，备注有显示 ，注意分开做货/验货/装柜 ，混装有罚款。 * 大货样： 新款请在CRD前10天寄出每款2整套大货样到罗湖办公室7B Meyya Liu 收，翻单不用寄。" | Y64: Meyya Liu | Z64: 5 | AA64: =Z64*I64 -> 15000 | AC64: 77794UQ1-S002 | AD64: 已入 | AE64: =I64 -> 3000 | AF64: 新邵生产 | AG64: 3000 | AH64: =AG64-I64 -> 0 | AJ64: 系统出单 | AK64: =I64 -> 3000 | AN64: =I64 -> 3000 | AT64: =I64/8 -> 375
A65: 46091 | B65: KOTRYNA GROUP, UAB | C65: 立陶宛 | D65: 4500196085 | F65: 4500196085-20 | G65: 77794UQ1-S001 | H65: 唱片机16pcs/2 UQ1/箱 | I65: 800 | J65: 0 | K65: 16 | L65: =I65/K65 -> 50 | M65: 46142 | N65: 46139 | P65: PASS | R65: 46107 | S65: 有 | T65: 29L C 版带电池走货WEEE说明书 | X65: 日期码格式：ZURU INC(BVI) 标准格式 日期：按实际生产日期 Packaging Info: 2.77794UQ1:MA亚克力盒子+透明珑贴纸+23L 说明书+纸卡+支撑内底托+23L 警告说明书+进口商贴纸+MA PDQ+29L C 版带电池走货WEEE说明书 2、所有item 包装上需要有CE logo，均用MA UPC 条码，若包装不是UPC 条码的请告知 3、此单出欧洲需满足EU测试标准要求，另外不能出闪粉（若产品本身不含闪粉则忽略这句话），电池产品（带电池/不带电池走货）需要添加WEEE通用说明书 | Y65: Sharon Zhao | Z65: 4.355 | AA65: =I65*Z65 -> 3484 | AC65: 77794UQ1-S001 | AD65: 已入 | AE65: =I65 -> 800 | AG65: 800 | AH65: =AG65-I65 -> 0 | AI65: OK | AJ65: 系统出单 | AK65: =I65 -> 800 | AN65: =I65 -> 800 | AT65: =I65/8 -> 100
A66: 46093 | B66: WONDERLAND TOYS, INC. | C66: 美国 | D66: 4500196320 | E66: 5228 | F66: 4500196320-10 | G66: 77794UQ1-S001 | H66: 唱片机16pcs/2 UQ1/箱 | I66: 704 | J66: 0 | K66: 16 | L66: =I66/K66 -> 44 | M66: 46142 | N66: 46139 | P66: PASS | R66: 46114 | S66: 有 | T66: 无 | X66: 日期码格式：ZURU,LLC 标准格式 日期：按实际生产日期 Packaging Info: 1. 1. 出口美国MA UPC 版本包装，优先1L。 Remark: 2. ZURU QC 验货即可。 | Y66: Abby Mai,Lluvia Zeng | Z66: 2.613 | AA66: =I66*Z66 -> 1839.552 | AB66: ZB05543-8.17 | AC66: 77794UQ1-S001 | AD66: 已入 | AE66: =I66 -> 704 | AG66: 704 | AH66: =AG66-I66 -> 0 | AI66: 无 | AJ66: 系统出单 | AK66: =I66 -> 704 | AN66: =I66 -> 704 | AT66: =I66/8 -> 88
A67: 46080 | B67: THE ENTERTAINER | C67: 英国 | D67: 4500194581 | E67: FB14471 | F67: 4500194581-90 | G67: 77794UQ1-S002 | H67: 唱片机8pcs/UQ1/箱 | I67: 8000 | J67: 0 | K67: 8 | L67: =I67/K67 -> 1000 | M67: 46142 | N67: =M67-3 -> 46139 | P67: 46142 | R67: 46093 | S67: 有 | T67: C版29L含电池出货版本WEEE说明书 | V67: 此为去掉LOLA YANG的特殊版本 | W67: * 大货样： 新款请在CRD前10天寄出每款2整套大货样到罗湖办公室7B Meyya Liu 收，翻单不用寄。" | X67: 日期码格式：ZURU INC(BVI) 标准格式 日期：按实际生产日期 Packaging Info: 77794UQ1-S002：MA B版1L UPC版本+C版29L含电池出货版本WEEE说明书以及欧洲澳新通用Warning instruction 因产品含有锂电池，需要在外箱加上UN3481的贴纸，贴纸尺寸106*106mm，贴在正唛其中1面右上角 Remark: "MA版本按工厂现有最新库存即可，订单出英国，请注意检查产品及包装应带UKCA以及CE图标，包装显示ZURU UK LTD信息，QC同事请查核，如有问题与跟单确认 *生产日期按实际（法定工作日），按ZURU标准格式即可 ，但是请知悉包装日期码需要早于或者等于外箱日期码 ，不能晚于外箱日期码 *请注意所有订单都需要经过ZURU QC验货并且通过后方可出货 *所有产品按符合欧洲标准走货，需要是不含微塑料版本 。 *涉及到硼的，如可选择情况下应使用低硼版本 （slime 类别低硼一般低于300ppm)，无选择的应与跟单复核再安排 。 *如果出运产品属于电子类产品需要在ZURU 包装基础上额外添加一张ZURU 标准30L通用WEEE 电子产品说明书,带电池出货的加带电池出货版本通用30L的说明书，不 带电池出货的产品用不带电池出货版本的说明书. *根据客人最新的包装要求，所有多个PDQ盒子(TQ,UQ,GQ）入1外箱的都需要在PDQ顶部右上角加上数量贴纸标明里面的数量。最小字体：36pts, 字体：Calibri（bo ld), 具体要求以及位置见文件. *订单对应客户PO号 ，备注有显示 ，注意分开做货/验货/装柜 ，混装有罚款。 * 大货样： 新款请在CRD前10天寄出每款2整套大货样到罗湖办公室7B Meyya Liu 收，翻单不用寄。" | Y67: Meyya Liu | Z67: 4.8 | AA67: =Z67*I67 -> 38400 | AC67: 77794UQ1-S002 | AD67: 已入 | AE67: =I67 -> 8000 | AF67: 新邵生产 | AG67: =880+768+6352 -> 8000 | AH67: =AG67-I67 -> 0 | AJ67: 系统出单 | AK67: =I67 -> 8000 | AN67: =I67 -> 8000 | AT67: =I67/8 -> 1000
A68: 46090 | B68: KMART AUSTRALIA LTD | C68: 澳大利亚 | D68: 4500195654 | E68: 21650903 | F68: 4500195654-20 | G68: 77794UQ1-S002 | H68: 唱片机8pcs/UQ1/箱 | I68: 1416 | J68: 0 | K68: 8 | L68: =I68/K68 -> 177 | M68: 46146 | N68: =M68-4 -> 46142 | P68: PASS | R68: 46107 | S68: 有 | T68: 防盜贴纸(贴纸以及防盜贴纸位置图翻单PO#4500193539)+箱唛+外箱贴纸SSCC Label | X68: 日期码格式：ZURU INC(BVI) 标准格式 日期：按实际生产日期 Packaging Info: 77772GQ1:MA英语UPC版本包装（收缩膜和说明书, MA首选1L，如无1L可用多语且含英语的配套多语包装) +防盜贴纸(贴纸以及防盜贴纸位置图翻单PO#4500193539)+ 两张覆盖PDQ上唱片的贴纸+两张覆盖收藏指南上唱片的贴纸+一张覆盖PDQ上数字"45"的贴纸+一张覆盖收藏指南上数字"45"的贴纸（以上6张贴纸以及贴纸位置图翻单 PO#4500193539)+箱唛+外箱贴纸SSCC Label 配比信息：4 mini vinyls,1 accessory Removed了 ""Messy <(>&<)> Delicious""两张唱片 77794UQ1:MA英语UPC版本包装（收缩膜和说明书, MA首选1L，如无1L可用多语且含英语的配套多语包装) +1张MA的锂电池黑白警语书纸 + 1张防盗贴纸 (贴纸以及位 置图翻单PO#4500193539）+ 箱唛 + 外箱SSCC Label 25282: 全套MA英语UPC包装（首选1L，如果无1L可用多语含英语）+ 箱唛 + 外箱SCC Label，包装材质为PET; 9574: MA英语UPC版本包装（收缩膜和说明书, MA首选1L，如无1L可用多语且含英语的配套多语包装) + 1张防盗贴纸 (贴纸以及位置图翻单PO#4500192690）+ 箱唛 + 外箱SSCC Label 配比信息：2pcs baby capybara: 3pcs baby capybara= 5:1 92129TQ1： 英文MA包装(UPC版本，首选1L，无1L可用多L含英语) + 1张防盗贴纸 (贴纸以及位置图翻单4500182434）+箱唛+SSCC label外箱贴纸； 7 assortmen ts, Ratio: Elephant: Toucan: Zebra: Sloth: Giraffe: Tiger: Peacock=10: 10: 10: 10: 10: 8: 2 Remark: 1.请务必按时完货，验货。并且按期送货入货代指定仓库，如果晚了导致船期Delay将会有罚金产生或者客户要求空运，所产生的罚金和空运费由工厂承担。 2.SSCC 外箱贴纸请同纸箱瓦楞纸方向（竖纹向）垂直，即外箱贴纸横着贴(注意条码不要被胶带粘住），贴1pc，贴1面正唛，封箱胶纸不能挡住贴纸内容。外箱贴纸 离外箱边距离不少于2cm。 3.外箱材质为ZURU标准； 4.此单需使用KMART封箱胶上下工字型封箱;从2019年6月开始，要用KMART 新版封箱胶带，此单要用"ANKO"封箱胶带 5.此单出口澳大利亚，请按相应的澳新标准生产； 6.产品和包装上生产批号的显示格式ZURU标准日期码格式 7.外箱信息不可手写，重量和体积需要与实际的一致(不可手写） 8. 每款item装箱后的G.W.超过10KG或者CBM超过0.13,(9.5KG或者以上，四舍五入后也属于10KG) 需在外箱上加印超 重或者Bulky LOGO，若发现我们资料没有，请 帮忙提醒 1)重量超过10kg但不超过16kg且CBM不超过0.13,10-16kg 超重logo 2）CBM超过0.13且重量少于17kg，bulky logo 3）不属于以上两种情况，需要使用相应重量范围内的超重logo 4）超重logo需要在外箱四面都印刷(箱唛右上角，两面侧唛超重logo需要尽量靠近毛重)，尺寸为:110mm height* 95mm width 9. 实际外箱重量跟印在箱唛上的数据差异不能超3%，尺寸按实际数据印刷 请注意此订单与NZ PO#4500195655一起合并计算 77772务必赶最晚5/11上午交仓 | Y68: Louise Lu | Z68: 5 | AA68: =Z68*I68 -> 7080 | AC68: 77794UQ1-S002 | AD68: 已入 | AE68: =I68 -> 1416 | AG68: 1416 | AH68: =AG68-I68 -> 0 | AJ68: 系统出单 | AK68: =I68 -> 1416 | AN68: =I68 -> 1416 | AT68: =I68/8 -> 177
