Workbook

Sheet 9543
A1: ZURU Hamster Mania 仓鼠生产排期表 #9543
A2: 44887 | H2: （黃色表示更改或增加） | K2: （蓝色表示已完货） | O2: （綠色表示調整貨期） | AI2: 收縮膜 | AL2: 收缩膜 | AT2: 收藏指南 | AW2: PDQ版本 | AX2: PDQ 1L | BA2: PDQ 3L | BW2: GQ1配比： | BX2: 5 | BY2: 6 | BZ2: 6 | CA2: 5
A3: 接单期 | B3: 第三方客户名称 | C3: 国家 | D3: PO | E3: 客户PO号 | F3: SKU号 | G3: 货号 | H3: 名称 | I3: 数量 | J3: 内箱装箱数量(pcs) | K3: 装箱数（PCS） | L3: 总箱数 | M3: 计划出货期 | N3: 计划验货期 | O3: 第三方验货期 | P3: 驗貨結果 | Q3: 船期SO | R3: 箱唛资料(收到日期) | S3: 外箱贴纸 | T3: PMC订购 说明书纸 | U3: 贴纸AI(收到日期) | V3: 客供物料 | W3: 日期码 | X3: 备注 | Y3: ZURU 跟单 | Z3: 单价USD | AA3: 金额USD | AB3: 送回情况 | AC3: 欠数 | AD3: 贴纸 | AE3: 系统货号 | AF3: 是否入系统 | AG3: 系统出单 | AH3: 發票號 | AI3: MA 1語收縮膜 A版本 | AJ3: MA 1語收縮膜 B版本 | AK3: MA 1語收縮膜 C版本 | AL3: MA 1語收縮膜 D版本 | AM3: MA 1語收縮膜 E版本 | AN3: MA 3语收缩膜 | AO3: MA 3語收縮膜 C版本 | AP3: MA 3語收縮膜 D版本 | AQ3: 客版收縮膜 | AR3: MA 9语 收藏指南 A版本 | AS3: MA 9语 收藏指南 B版本 | AT3: MA 5语 收藏指南 A版本 | AU3: MA 5语 收藏指南 B版本 | AV3: 客版收藏指南 | AW3: GQ1-MA 1L | AX3: GQ1-MA 1L-B版本 | AY3: GQ1-MA 1L-C版本 | AZ3: GQ1-MA 3L | BA3: GQ1-MA 3L-B版本 | BB3: GQ1-MA 3L-C版本 | BC3: GQ2-MA 3L KM单+WM-CA-A版本 | BD3: GQ2-MA 3L KM单+WM-CA-B版本 | BE3: GQ2-MA 3L KM单+WM-CA-C版本 | BF3: GQ3- 客版 1L | BG3: GQ3-客版 1L-B版本 | BH3: GQ3-客版 1L-C版本 | BI3: GQ4-MA 1L TG单-A版本 | BJ3: GQ4-MA 1L TG单-B版本 | BK3: GQ4-MA 1L TG单-C版本 | BL3: GQ4-MA 1L TG单-D版本 | BM3: TQ1 WM单 | BN3: TQ2-3PCS | BO3: TQ2-B 版本 | BP3: GQ5-A版本 | BQ3: GQ5-B版本 | BR3: GQ6 | BS3: GQ6-B版本 | BT3: SK-S001-3L 无底座 | BU3: SK-S002 -3L有底座 | BV3: 客版PDQ | BW3: 布標 | BX3: 蓝色仓鼠(Blue)（A) | BY3: 粉色仓鼠(Pink)（B) | BZ3: 紫色仓鼠(Purple)(D) | CA3: 土黄色仓鼠(Orange)(E) | CB3: 透明球 | CC3: 无功能 粉色仓鼠 | CD3: 总数 | CE3: 相差 | XBS3: =SUM(A3:XBR3) -> 0 | XCB3: =SUBTOTAL(9,A3:XCA3) -> 0 | XCS3: =SUM(A3:XCR3) -> 0 | XDA3: =SUBTOTAL(9,A3:XCZ3) -> 0 | XEN3: =SUBTOTAL(9,A3:XEM3) -> 0
A4: 45463 | B4: DM LLC | C4: 俄罗斯 | D4: 4500137881 | E4: Ural | F4: 4500137881-90 | G4: 9543-S001 | H4: 仓鼠 | I4: 792 | J4: 0 | K4: 24 | L4: =I4/K4 -> 33 | M4: 45498 | N4: 45500 | P4: PASS | Q4: 预计7/31出 | R4: 6/26收到 | U4: 7/9收到进口商贴纸+EAN条码贴纸 | X4: 日期码格式：彩卡/收缩膜/PDQ/外箱不要打ZURU标准日期码！ 日期： Packaging Info: 9543 优先1L MA 收缩膜+进口商贴纸+EAN条码贴纸; MA 说明书/指南(如有); 注意 ：彩卡/收缩膜/PDQ/外箱不要打ZURU标准日期码！！ Remark: 1. 出 Bekasovo 2和Ural; | Y4: Ann Zhang | Z4: 2.5721 | AA4: =I4*Z4 -> 2037.1032 | AB4: 792 | AC4: =AB4-I4 -> 0 | AD4: ok | AE4: 9543-S001 | AF4: 已入 | AG4: 系统出单 | AH4: 88869-1.4 | AL4: =I4 -> 792 | AT4: =I4 -> 792 | BW4: 增加移印布标内容 | BX4: =I4/4 -> 198 | BY4: =I4/4 -> 198 | BZ4: =I4/4 -> 198 | CA4: =I4/4 -> 198 | CB4: =I4 -> 792 | CD4: =SUM(BX4:CA4) -> 792 | CE4: =I4-CD4 -> 0
A5: 45593 | D5: ZMPO24801 | G5: 9543GQ1-S001 | H5: 仓鼠 | I5: 220 | J5: 0 | K5: 22 | L5: =I5/K5 -> 10 | M5: 45608 | N5: 45604 | P5: PASS | R5: 周转箱 | U5: 无 | X5: 备注： 收到样品订单后尽快安排 ，注意样板品质质量要求要高于大货品质要求 ，送货时必须要附带送货单(没有送货单和QC检验合格报告的仓库一律拒绝收货)，请知悉，谢谢！ Remark:大货最新ZURU Logo版本/款号平均/请用大货标准箱装箱22PCS/箱共10箱/箱唛请参照邮件附件 | Y5: Angus | AB5: 220 | AC5: =AB5-I5 -> 0 | AE5: 9543GQ1-S001 | AF5: 已入 | AG5: 系统出单 | AL5: =I5 -> 220 | AT5: =I5 -> 220 | AX5: =I5/11 -> 20 | BW5: 增加移印布标内容 | BX5: =I5/22*5 -> 50 | BY5: =I5/22*6 -> 60 | BZ5: =I5/22*6 -> 60 | CA5: =I5/22*5 -> 50 | CB5: =I5 -> 220 | CC5: =I5/11 -> 20 | CD5: =SUM(BX5:CA5) -> 220 | CE5: =I5-CD5 -> 0
A6: 45523 | B6: DM LLC | C6: 俄罗斯 | D6: 4500143263 | E6: 出Bekasovo 2 | F6: 4500143263-10 | G6: 9543-S001 | H6: 仓鼠 | I6: 1608 | J6: 0 | K6: 24 | L6: =I6/K6 -> 67 | M6: 45667 | N6: 45663 | P6: PASS | Q6: 2/10出 | R6: 10/28收到 | U6: 进口商贴纸+EAN条码贴纸（翻4500143236） | W6: 外包装 (指: 收缩膜/彩卡/吊牌/PDQ) /外箱不要打ZURU标准日期码！ | X6: 日期码格式：注意:外包装(指: 收缩膜/彩卡/吊牌/PDQ)/外箱不要打ZURU标准日期码！ 日期： Packaging Info: 出Bekasovo 2 和Ural 2 个港口； LC 货期不可延期有罚款 ； 1. 1L MA 收缩膜 or 彩卡+进口商贴纸（翻4500143236）+EAN条码贴纸（翻4500143236）; MA 说明书/指南（如有）; 注意 ：外包装 (指: 收缩膜/彩卡/吊牌/PDQ) /外箱不要打ZURU标准日期码！ Remark: 标准配比 | Y6: Ann Zhang | Z6: 2.5721 | AA6: =I6*Z6 -> 4135.9368 | AB6: =1584+24 -> 1608 | AC6: =AB6-I6 -> 0 | AD6: OK | AE6: 9543-S001 | AF6: 已入 | AG6: 系统出单 | AH6: 94200-2.10 | AL6: =I6 -> 1608 | AT6: =I6 -> 1608 | BW6: 增加移印布标内容 | BX6: =I6/4 -> 402 | BY6: =I6/4 -> 402 | BZ6: =I6/4 -> 402 | CA6: =I6/4 -> 402 | CB6: =I6 -> 1608 | CD6: =SUM(BX6:CA6) -> 1608 | CE6: =I6-CD6 -> 0
A7: 45523 | B7: DM LLC | C7: 俄罗斯 | D7: 4500143263 | E7: 出Ural | F7: 4500143263-40 | G7: 9543-S001 | H7: 仓鼠 | I7: 816 | J7: 0 | K7: 24 | L7: =I7/K7 -> 34 | M7: 45667 | N7: 45663 | P7: PASS | Q7: 2/10出 | R7: 10/28收到 | U7: 进口商贴纸+EAN条码贴纸（翻4500143236） | W7: 外包装 (指: 收缩膜/彩卡/吊牌/PDQ) /外箱不要打ZURU标准日期码！ | X7: 日期码格式：注意:外包装(指: 收缩膜/彩卡/吊牌/PDQ)/外箱不要打ZURU标准日期码！ 日期： Packaging Info: 出Bekasovo 2 和Ural 2 个港口； LC 货期不可延期有罚款 ； 1.9543 ： 1L MA 收缩膜 or 彩卡+进口商贴纸（翻4500143236）+EAN条码贴纸（翻4500143236）; MA 说明书/指南（如有）; 注意 ：外包装 (指: 收缩膜/彩卡/吊牌/PDQ) /外箱不要打ZURU标准日期码！ Remark: 标准配比 | Y7: Ann Zhang | Z7: 2.5721 | AA7: =I7*Z7 -> 2098.8336 | AB7: 816 | AC7: =AB7-I7 -> 0 | AD7: OK | AE7: 9543-S001 | AF7: 已入 | AG7: 系统出单 | AH7: 94200-2.10 | AL7: =I7 -> 816 | AT7: =I7 -> 816 | BW7: 增加移印布标内容 | BX7: =I7/4 -> 204 | BY7: =I7/4 -> 204 | BZ7: =I7/4 -> 204 | CA7: =I7/4 -> 204 | CB7: =I7 -> 816 | CD7: =SUM(BX7:CA7) -> 816 | CE7: =I7-CD7 -> 0
A8: 45614 | B8: Amazon Mexico, S. DE R.L. DE CV | C8: 墨西哥 | D8: 4500151559 | E8: 64SP3ZYY | F8: 4500151559-30 | G8: 9543A-S001 | H8: 仓鼠 | I8: 96 | J8: 0 | K8: 24 | L8: =I8/K8 -> 4 | M8: 45649 | N8: 45645 | P8: PASS | R8: 空白外箱加印ZURU Logo+MADE IN CHINA+SSCC LABEL(客供贴纸） | U8: UPC贴纸翻4500098824+12/4-进口商贴纸 | V8: 12/6-SSCC贴纸 | X8: 日期码格式：ZURU INC(BVI) 标准格式 日期：按实际生产日期 Packaging Info: 9543: MA 加UPC贴纸， UPC贴纸跟翻单4500098824+进口商贴纸+SSCC贴纸。 Remark: Amazon FOB订单，出口Mexico，外箱最长边不能超过25" （超过了，case pack只能为1），不符合要求的大货，一律不接受。 1.空白外箱加印ZURU Logo+MADE IN CHINA+SSCC LABEL(客供贴纸），无shipping mark,日期使用ZURU 标准版本。SSCC Label显示的是客人自己的item#，SSCC Lab el 贴在外箱正面的正中间，贴一面即可，跟单订购，贴纸离外箱距必须至少3cm,每一张SSCC Label都是唯一且有不同流水及条码的，没有损耗，绝对不可贴错，否 则贴错或损坏一张会导致全部都错，千万要注意！ 2. 日期码使用ZURU标准版 3. 客户PO备注在remark处 6.9543: 2PCS AAA Batteries(Not Include) | Y8: Zoe Luo | Z8: 2.6514 | AA8: =I8*Z8 -> 254.5344 | AB8: 96 | AC8: =AB8-I8 -> 0 | AD8: ok | AE8: 9543A-S001-MTS | AF8: 已入 | AG8: 系统出单 | AH8: 88897-1.6 | AL8: =I8 -> 96 | AT8: =I8 -> 96 | BW8: 增加移印布标内容 | BX8: =I8 -> 96 | CB8: =SUM(BX8:CA8) -> 96 | CD8: =SUM(BX8:CA8) -> 96 | CE8: =CD8-I8 -> 0
A9: 45614 | B9: Amazon Mexico, S. DE R.L. DE CV | C9: 墨西哥 | D9: 4500151559 | E9: 64SP3ZYY | F9: 4500151559-40 | G9: 9543D-S001 | H9: 仓鼠 | I9: 24 | J9: 0 | K9: 24 | L9: =I9/K9 -> 1 | M9: 45649 | N9: 45645 | P9: PASS | R9: 空白外箱加印ZURU Logo+MADE IN CHINA+SSCC LABEL(客供贴纸） | U9: UPC贴纸翻4500098824+12/4-进口商贴纸 | V9: 12/6-SSCC贴纸 | X9: 日期码格式：ZURU INC(BVI) 标准格式 日期：按实际生产日期 Packaging Info: 9543: MA 加UPC贴纸， UPC贴纸跟翻单4500098824+进口商贴纸+SSCC贴纸。 Remark: Amazon FOB订单，出口Mexico，外箱最长边不能超过25" （超过了，case pack只能为1），不符合要求的大货，一律不接受。 1.空白外箱加印ZURU Logo+MADE IN CHINA+SSCC LABEL(客供贴纸），无shipping mark,日期使用ZURU 标准版本。SSCC Label显示的是客人自己的item#，SSCC Lab el 贴在外箱正面的正中间，贴一面即可，跟单订购，贴纸离外箱距必须至少3cm,每一张SSCC Label都是唯一且有不同流水及条码的，没有损耗，绝对不可贴错，否 则贴错或损坏一张会导致全部都错，千万要注意！ 2. 日期码使用ZURU标准版 3. 客户PO备注在remark处 6.9543: 2PCS AAA Batteries(Not Include) | Y9: Zoe Luo | Z9: 2.6514 | AA9: =I9*Z9 -> 63.6336 | AB9: 24 | AC9: =AB9-I9 -> 0 | AD9: ok | AE9: 9543D-S001-MTS | AF9: 已入 | AG9: 系统出单 | AH9: 88897-1.6 | AL9: =I9 -> 24 | AT9: =I9 -> 24 | BW9: 增加移印布标内容 | BZ9: =I9 -> 24 | CB9: =I9 -> 24 | CD9: =SUM(BX9:CA9) -> 24 | CE9: =I9-CD9 -> 0
A10: 45590 | B10: Amazon EU SARL, Ndl Deutschland | C10: 德国 | D10: 4500148999 | E10: 5WJDQBAA | F10: 4500148999-30 | G10: 9543D-S001 | H10: 仓鼠 | I10: 504 | J10: 0 | K10: 24 | L10: =I10/K10 -> 21 | M10: 45651 | N10: 45647 | P10: PASS | Q10: 1/4-1/8出 | R10: 空白外箱（加印带Zuru字样的最新logo，除了邮包盒直接做外箱的产品） + SSCC LABEL一张, 无箱唛’MADE IN CHINA 外箱只印一正一侧。 | U10: UPC+IT sorting labe翻4500120504+ZURU邮箱贴纸翻4500149035 | V10: 11/21收到客供外箱贴纸 | X10: 日期码格式：ZURU INC(BVI) 标准格式 日期：按实际生产日期 Packaging Info: Amazon DE 9543D 3.9543D: 9543D 24pcs/ctn, no inner, purple; MA 3L（9L warning）C版收缩膜+4张贴纸(1张UPC#，参考翻单PO#4500120504；1张IT环保标，参考翻单PO#4500120 504；1张ES回收标, 参考翻单PO#4500149035；1张ZURU邮箱，参考翻单PO#4500149035)+5L(9L warning)说明书； 5. ZURU 验货最迟不得晚于2024/12/26 Remark: 1.空白外箱（加印带Zuru字样的最新logo，除了邮包盒直接做外箱的产品） + SSCC LABEL一张, 无箱唛. (SSCC LABEL贴在外箱正面的正中间，贴一面即可,贴纸离外箱边距必须至少3.2CM),SSCC贴纸由工厂直接跟勤得采购或者工厂自行采购，每一张SSCC Label都是唯一 且有不同流水及条码，且需要检查条码是否能正常扫描，另外，此贴纸印刷不可出现模糊，溢出及粘胶不牢易脱落等现象，如工厂不按此要求导致贴纸有任何问题产 生的罚款将由工厂承担一切责任 。’MADE IN CHINA 外箱只印一正一侧。 2. 出往UK的产品+包装务必打上UKCA logo ，否则客人会退货且当地会有罚款。 3.订单必须经过ZURU QC验货并且通过后方可出货。 4.法国订单要求包装不使用矿物油，请按要求提供以下其中一份文件再出货 ，产品出到法国被相关部门抽检出现包装不符合此要求的，供应商需要为此承担责任， 故此请严格把关 。 -油墨物质""由1 ~ 7个芳香环组成的MOAH""的包装检测报告，要求限值≤1.0%; -包装材料清单，包括包装油墨或物质的信息 -油墨制造商的证书。 5 . 每一批次出货只能有一个生产日期，不可多个生产日期混在同一批次出货；且邮包盒上必须统一加上日期码； 6. 涉及到相关款式会有闪粉的或 者微塑料的，请统一默认出无闪粉或者不含微塑料 版本; 7 .邮包盒及外箱封箱必须是工字型封箱方式； 8 . 5 Surprise or Mini Brands涉及包装是2个及2个以上的球入PVC桶包装时，单个球上若有UPC#或者EAN#，请用白色贴纸覆盖住； | Y10: Zoe Chen | Z10: 2.5958 | AA10: =I10*Z10 -> 1308.2832 | AB10: 504 | AC10: =AB10-I10 -> 0 | AD10: ok | AE10: 9543D-S001-3L | AF10: 已入 | AG10: 系统出单 | AH10: 88946-1.8 | AO10: =I10 -> 504 | AT10: =I10 -> 504 | BW10: 增加移印布标内容 | BZ10: =I10 -> 504 | CB10: =I10 -> 504 | CD10: =SUM(BX10:CA10) -> 504 | CE10: =I10-CD10 -> 0
A11: 45609 | B11: Amazon ES | C11: 西班牙 | D11: 4500151280 | E11: 5KXG56ZT | F11: 4500151280-10 | G11: 9543B-S001 | H11: 仓鼠 | I11: 504 | J11: 0 | K11: 24 | L11: =I11/K11 -> 21 | M11: 45652 | N11: 45649 | P11: PASS | Q11: 1/5-1/9出 | R11: 空白外箱（加印带Zuru字样的最新logo，除了邮包盒直接做外箱的产品） + SSCC LABEL一张, 无箱唛。 | U11: 11/15收到UPC+IT 翻4500120504+ES回收标+ZURU邮箱贴纸 | V11: 11/29-外箱贴纸 | X11: 日期码格式：ZURU INC(BVI) 标准格式 日期：按实际生产日期 Tracking Code: Packaging Info: Amazon ES(9543B, 7150B) 1. 9543B：9543B 24pcs/ctn, no inner, pink; MA 3L（9L warning）C版收缩膜+4张贴纸(1张#UPC+1张IT sorting label，参考翻单PO#4500120504；1张ES回收标 ，参考翻单PO#4500151280；1张ZURU邮箱)+5L(9L warning)A说明书； 3. 最迟验货不得晚于2024/12/27; Remark: 1.空白外箱（加印带Zuru字样的最新logo，除了邮包盒直接做外箱的产品） + SSCC LABEL一张, 无箱唛。 (SSCC LABEL贴在外箱正面的正中间，贴一面即可,贴纸离外箱边距必须至少3.2CM), SSCC贴纸由工厂直接跟勤得采购或者工厂自行采购，每一张SSCC Label都是唯一 且有不同流水及条码，且需要检查条码是否能正常扫描，另外，此贴纸印刷不可出现模糊，溢出及粘胶不牢易脱落等现象，如工厂不按此要求导致贴纸有任何问题产 生的罚款将由工厂承担一切责任 。’MADE IN CHINA 外箱只印一正一侧。 2.出往UK的产品+包装务必打上UKCA logo ，否则客人会退货且当地会有罚款。 3.订单必须经过ZURU QC验货并且通过后方可出货。 4.法国订单要求包装不使用矿物油，请按要求提供以下其中一份文件再出货 ，产品出到法国被相关部门抽检出现包装不符合此要求的，供应商需要为此承担责任， 故此请严格把关。 -油墨物质""由1 ~ 7个芳香环组成的MOAH""的包装检测报告，要求限值≤1.0%； -包装材料清单，包括包装油墨或物质的信息； -油墨制造商的证书； 5.每一批次出货只能有一个生产日期，不可多个生产日期混在同一批次出货；且邮包盒上必须统一加上日期码； 6.涉及到相关款式会有闪粉的或者微塑料的，请统一默认出无闪粉或者不含微塑料版本； 7.邮包盒及外箱封箱必须是工字型封箱方式； 8.5 Surprise or Mini Brands涉及包装是2个及2个以上的球入PVC桶包装时，单个球上若有UPC#或者EAN#，请用白色贴纸覆盖住； 9.箱唛资料按照给定的标准去做即可，无需发回我方再行审批(新标准将另行通知); | Y11: Mandy Hu | Z11: 2.5958 | AA11: =I11*Z11 -> 1308.2832 | AB11: 504 | AC11: =AB11-I11 -> 0 | AD11: ok | AE11: 9543B-S001-3L | AF11: 已入 | AG11: 系统出单 | AH11: 88939-1.8 | AO11: =I11 -> 504 | AT11: =I11 -> 504 | BW11: 增加移印布标内容 | BY11: =I11 -> 504 | CB11: =I11 -> 504 | CD11: =SUM(BX11:CA11) -> 504 | CE11: =I11-CD11 -> 0
A12: 45609 | B12: AMAZON FR | C12: 法国 | D12: 4500151278 | E12: 59XSZYJX | F12: 4500151278-20 | G12: 9543B-S001 | H12: 仓鼠 | I12: 504 | J12: 0 | K12: 24 | L12: =I12/K12 -> 21 | M12: 45652 | N12: 45649 | P12: PASS | Q12: 1/5-1/9出 | R12: 空白外箱（加印带Zuru字样的最新logo，除了邮包盒直接做外箱的产品） + SSCC LABEL一张, 无箱唛。 | U12: UPC+IT翻4500120504 | V12: 12/5-外箱贴纸 | X12: 日期码格式：ZURU INC(BVI) 标准格式 日期：按实际生产日期 Packaging Info: Amazon FR(7150B, 9543B) 2. 9543B：9543B 24pcs/ctn, no inner, pink; MA 3L（9L warning）C版收缩膜+2张贴纸(含1张#UPC；1张IT sorting label)+5L(9L warning)A说明书；参考翻单P O#4500120504； 3. 最迟验货不得晚于2024/12/27; Remark: 1.空白外箱（加印带Zuru字样的最新logo，除了邮包盒直接做外箱的产品） + SSCC LABEL一张, 无箱唛。 (SSCC LABEL贴在外箱正面的正中间，贴一面即可,贴纸离外箱边距必须至少3.2CM), SSCC贴纸由工厂直接跟勤得采购或者工厂自行采购，每一张SSCC Label都是唯一 且有不同流水及条码，且需要检查条码是否能正常扫描，另外，此贴纸印刷不可出现模糊，溢出及粘胶不牢易脱落等现象，如工厂不按此要求导致贴纸有任何问题产 生的罚款将由工厂承担一切责任 。’MADE IN CHINA 外箱只印一正一侧。 2.出往UK的产品+包装务必打上UKCA logo ，否则客人会退货且当地会有罚款。 3.订单必须经过ZURU QC验货并且通过后方可出货。 4.法国订单要求包装不使用矿物油，请按要求提供以下其中一份文件再出货 ，产品出到法国被相关部门抽检出现包装不符合此要求的，供应商需要为此承担责任， 故此请严格把关。 -油墨物质""由1 ~ 7个芳香环组成的MOAH""的包装检测报告，要求限值≤1.0%； -包装材料清单，包括包装油墨或物质的信息； -油墨制造商的证书； 5.每一批次出货只能有一个生产日期，不可多个生产日期混在同一批次出货；且邮包盒上必须统一加上日期码； 6.涉及到相关款式会有闪粉的或者微塑料的，请统一默认出无闪粉或者不含微塑料版本； 7.邮包盒及外箱封箱必须是工字型封箱方式； 8.5 Surprise or Mini Brands涉及包装是2个及2个以上的球入PVC桶包装时，单个球上若有UPC#或者EAN#，请用白色贴纸覆盖住； 9.箱唛资料按照给定的标准去做即可，无需发回我方再行审批(新标准将另行通知); | Y12: Crystal Chen | Z12: 2.5958 | AA12: =I12*Z12 -> 1308.2832 | AB12: 504 | AC12: =AB12-I12 -> 0 | AD12: ok | AE12: 9543B-S001-3L | AF12: 已入 | AG12: 系统出单 | AH12: 88956-1.9 | AO12: =I12 -> 504 | AT12: =I12 -> 504 | BW12: 增加移印布标内容 | BY12: =I12 -> 504 | CB12: =I12 -> 504 | CD12: =SUM(BX12:CA12) -> 504 | CE12: =I12-CD12 -> 0
A13: 45608 | B13: Amazon CA (Vendor Center) | C13: 加拿大 | D13: 4500150978 | E13: 3NHSHWDA | F13: 4500150978-30 | G13: 9543B-S001 | H13: 仓鼠 | I13: 72 | J13: 0 | K13: 24 | L13: =I13/K13 -> 3 | M13: 45653 | N13: 45649 | P13: PASS | Q13: 1/1-1/7出 | R13: 11/12收到 | U13: UPC贴纸跟翻4500098824 | X13: 日期码格式：ZURU INC(BVI) 标准格式 日期：按实际生产日期 Packaging Info: 出口加拿大，包装需要至少2/3L UPC版，无硼版本 #9543: MA 3L UPC版本加UPC贴纸，UPC贴纸跟翻单4500098824。A:193052051776, B:193052051783, E:193052051806,; Remark: 1. Amazon FOB订单，出口CA。外箱最长边不能超过25" （超过了，case pack只能为1），不符合要求的大货，一律不接受。 2. 外箱正面印ZURU Logo + SSCC LABEL（客供贴纸)，侧面印item#（订单上显示的SKU#) + carton size(以工厂实际尺寸为准，单位: inch) + MADE IN CHINA， 日期使用ZURU 标准版本 SSCC Label 显示的是客人自己的item#，SSCC Label 贴在外箱正面的正中间，贴一面即可，跟单订购，贴纸离外箱距必须至少3cm，每一 张SSCC label 都是唯一且有不同流水及条码的，没有损耗，绝对不可贴错 ，否则贴错或损坏一张会导致全部都错，千万要注意: SSCC 贴纸务必要在正中间(可以覆 盖Logo <(>&<)> 箱唛)，否则会影响到仓库扫描识别。 3. 日期码使用ZURU标准版本。 4. 如果大货有要求入邮包盒，则对应的邮包盒上面要打上日期码。 5. 按照客户PO# 装柜/箱号顺序装柜，跟单会提前给到装柜计划。在大货生产/仓库存放时，请留意该装柜要求，以便装柜时不混乱（避免装错/装漏/找不到货号等 ）。 6. 出口加拿大，包装需要至少2/3L UPC版，无硼版本。 7.邮包盒上要印刷日期码 | Y13: Kelly/Mia | Z13: 2.6514 | AA13: =I13*Z13 -> 190.9008 | AB13: 72 | AC13: =AB13-I13 -> 0 | AD13: ok | AE13: 9543B-S001-3L | AF13: 已入 | AG13: 系统出单 | AH13: 88919-1.7 | AO13: =I13 -> 72 | AT13: =I13 -> 72 | BW13: 增加移印布标内容 | BY13: =I13 -> 72 | CB13: =I13 -> 72 | CD13: =SUM(BX13:CA13) -> 72 | CE13: =I13-CD13 -> 0
A14: 45608 | B14: Amazon CA (Vendor Center) | C14: 加拿大 | D14: 4500150978 | E14: 3A8P5CWW | F14: 4500150978-40 | G14: 9543E-S001 | H14: 仓鼠 | I14: 24 | J14: 0 | K14: 24 | L14: =I14/K14 -> 1 | M14: 45653 | N14: 45649 | P14: PASS | Q14: 1/1-1/7出 | R14: 11/12收到 | U14: UPC贴纸跟翻4500098824 | X14: 日期码格式：ZURU INC(BVI) 标准格式 日期：按实际生产日期 Packaging Info: 出口加拿大，包装需要至少2/3L UPC版，无硼版本 #9543: MA 3L UPC版本加UPC贴纸，UPC贴纸跟翻单4500098824。A:193052051776, B:193052051783, E:193052051806,; Remark: 1. Amazon FOB订单，出口CA。外箱最长边不能超过25" （超过了，case pack只能为1），不符合要求的大货，一律不接受。 2. 外箱正面印ZURU Logo + SSCC LABEL（客供贴纸)，侧面印item#（订单上显示的SKU#) + carton size(以工厂实际尺寸为准，单位: inch) + MADE IN CHINA， 日期使用ZURU 标准版本 SSCC Label 显示的是客人自己的item#，SSCC Label 贴在外箱正面的正中间，贴一面即可，跟单订购，贴纸离外箱距必须至少3cm，每一 张SSCC label 都是唯一且有不同流水及条码的，没有损耗，绝对不可贴错 ，否则贴错或损坏一张会导致全部都错，千万要注意: SSCC 贴纸务必要在正中间(可以覆 盖Logo <(>&<)> 箱唛)，否则会影响到仓库扫描识别。 3. 日期码使用ZURU标准版本。 4. 如果大货有要求入邮包盒，则对应的邮包盒上面要打上日期码。 5. 按照客户PO# 装柜/箱号顺序装柜，跟单会提前给到装柜计划。在大货生产/仓库存放时，请留意该装柜要求，以便装柜时不混乱（避免装错/装漏/找不到货号等 ）。 6. 出口加拿大，包装需要至少2/3L UPC版，无硼版本。 7.邮包盒上要印刷日期码 | Y14: Kelly/Mia | Z14: 2.6514 | AA14: =I14*Z14 -> 63.6336 | AB14: 24 | AC14: =AB14-I14 -> 0 | AD14: ok | AE14: 9543E-S001-3L | AF14: 已入 | AG14: 系统出单 | AH14: 88919-1.7 | AO14: =I14 -> 24 | AT14: =I14 -> 24 | BW14: 增加移印布标内容 | CA14: =I14 -> 24 | CB14: =I14 -> 24 | CD14: =SUM(BX14:CA14) -> 24 | CE14: =I14-CD14 -> 0
A15: 45608 | B15: Amazon CA (Vendor Center) | C15: 加拿大 | D15: 4500150978 | E15: 2IK4A3AH | F15: 4500150978-50 | G15: 9543A-S001 | H15: 仓鼠 | I15: 48 | J15: 0 | K15: 24 | L15: =I15/K15 -> 2 | M15: 45653 | N15: 45649 | P15: PASS | Q15: 1/1-1/7出 | R15: 11/12收到 | U15: UPC贴纸跟翻4500098824 | X15: 日期码格式：ZURU INC(BVI) 标准格式 日期：按实际生产日期 Packaging Info: 出口加拿大，包装需要至少2/3L UPC版，无硼版本 #9543: MA 3L UPC版本加UPC贴纸，UPC贴纸跟翻单4500098824。A:193052051776, B:193052051783, E:193052051806,; Remark: 1. Amazon FOB订单，出口CA。外箱最长边不能超过25" （超过了，case pack只能为1），不符合要求的大货，一律不接受。 2. 外箱正面印ZURU Logo + SSCC LABEL（客供贴纸)，侧面印item#（订单上显示的SKU#) + carton size(以工厂实际尺寸为准，单位: inch) + MADE IN CHINA， 日期使用ZURU 标准版本 SSCC Label 显示的是客人自己的item#，SSCC Label 贴在外箱正面的正中间，贴一面即可，跟单订购，贴纸离外箱距必须至少3cm，每一 张SSCC label 都是唯一且有不同流水及条码的，没有损耗，绝对不可贴错 ，否则贴错或损坏一张会导致全部都错，千万要注意: SSCC 贴纸务必要在正中间(可以覆 盖Logo <(>&<)> 箱唛)，否则会影响到仓库扫描识别。 3. 日期码使用ZURU标准版本。 4. 如果大货有要求入邮包盒，则对应的邮包盒上面要打上日期码。 5. 按照客户PO# 装柜/箱号顺序装柜，跟单会提前给到装柜计划。在大货生产/仓库存放时，请留意该装柜要求，以便装柜时不混乱（避免装错/装漏/找不到货号等 ）。 6. 出口加拿大，包装需要至少2/3L UPC版，无硼版本。 7.邮包盒上要印刷日期码 | Y15: Kelly/Mia | Z15: 2.5695 | AA15: =I15*Z15 -> 123.336 | AB15: 48 | AC15: =AB15-I15 -> 0 | AD15: ok | AE15: 9543A-S001-3L | AF15: 已入 | AG15: 系统出单 | AH15: 88919-1.7 | AO15: =I15 -> 48 | AT15: =I15 -> 48 | BW15: 增加移印布标内容 | BX15: =I15 -> 48 | CB15: =I15 -> 48 | CD15: =SUM(BX15:CA15) -> 48 | CE15: =I15-CD15 -> 0
A16: 45602 | B16: Dirk Rossmann GmbH | C16: 德国 | D16: 4500149853 | E16: 30241146A | F16: 4500149853-50 | G16: 9543-S001 | H16: 仓鼠 | I16: 1008 | J16: 0 | K16: 24 | L16: =I16/K16 -> 42 | M16: 45649 | N16: 45645 | O16: 12/25 第三方 | P16: PASS | Q16: 1/2出 | R16: 11/18收到 外箱需要是5层瓦楞纸，厚度在5-9mm。 | U16: EAN条码贴纸翻4500116318+德语callout贴纸翻4500122326+客版黑白WEEE声明说明书纸翻4500145491 | X16: 日期码格式：ZURU INC(BVI) 标准格式 日期：按实际生产日期 Packaging Info:9543: 最新MA 1L+多语收缩膜+EAN条码贴纸(翻单4500116318)+德语callout贴纸(翻单4500122326)+ 5L+9L说明书+客版黑白WEEE声明说明书纸(翻单#4500145491) Remark: 1. 出口欧洲，微塑料需符合法规，电池符合欧洲法规要求(如有) 2. 此客户要求：化学品无硼无香。 3. 外箱上下需加保护卡，以防开箱时产品被划破。（保护卡需要时整面） 4. 此单在出货前4周提供大货样品给Rossmann德国客人安排第三方验货。 请备额外物料。 5. 此单需要第三方验货，验货时间为完货后第二天，验货OK待客人放货后才能安排走货。 6. 所有包装材料都需要用PET材质。 7. 每箱需要放一包干燥剂（不能是silicon) 。品牌SUPER DRY，规格：10g/pc 。 8. 外箱需要是5层瓦楞纸，厚度在5-9mm。 9. 此单出德国，走整柜请知悉。 10.标准配比。 | Y16: Shirley Zhou | Z16: 2.5816 | AA16: =I16*Z16 -> 2602.2528 | AB16: 1008 | AC16: =AB16-I16 -> 0 | AD16: ok | AE16: 9543-S001 | AF16: 已入 | AG16: 系统出单 | AH16: 94159-1.23 | AL16: =I16 -> 1008 | AT16: =I16 -> 1008 | BW16: 增加移印布标内容 | BX16: =I16/4 -> 252 | BY16: =I16/4 -> 252 | BZ16: =I16/4 -> 252 | CA16: =I16/4 -> 252 | CB16: =I16 -> 1008 | CD16: =SUM(BX16:CA16) -> 1008 | CE16: =I16-CD16 -> 0
A17: 45604 | B17: Inventive Toys | C17: 俄罗斯联邦 | D17: 4500150797 | F17: 4500150797-20 | G17: 9543GQ1-S001 | H17: 仓鼠 | I17: 5016 | J17: 0 | K17: 22 | L17: =I17/K17 -> 228 | M17: 45649 | N17: 45645 | P17: PASS | Q17: 1/3出 | R17: 11/26收到 | U17: 12/3-进口商贴纸+EAN 条码贴纸 | W17: 外包装/外箱不要打ZURU标准日期码 | X17: 日期码格式：外包装/外箱不要打ZURU标准日期码 日期： Packaging Info: 注意 ：外包装 (指: 收缩膜/彩卡/铝箔袋/挂卡/PDQ) /外箱不要打ZURU标准日期码！胶件可以打日期码。 外包装（包括收缩膜/彩卡/PDQ）都不能含Instagram and facebook logo等社交logo; 1L MA 收缩膜+ 进口商贴纸； MA PDQ+ EAN 条码贴纸 ， MA 指南/说明书（如有） Remark: 标准配比 ； | Y17: Ann Zhang | Z17: 2.7397 | AA17: =I17*Z17 -> 13742.335 | AB17: =3168+1848 -> 5016 | AC17: =AB17-I17 -> 0 | AD17: ok | AE17: 9543GQ1-S001 | AF17: 已入 | AG17: 系统出单 | AH17: 94064-1.16 | AL17: =I17 -> 5016 | AT17: =I17 -> 5016 | AX17: =I17/11 -> 456 | BW17: 增加移印布标内容 | BX17: =I17/22*5 -> 1140 | BY17: =I17/22*6 -> 1368 | BZ17: =I17/22*6 -> 1368 | CA17: =I17/22*5 -> 1140 | CB17: =I17 -> 5016 | CC17: =I17/11 -> 456 | CD17: =SUM(BX17:CA17) -> 5016 | CE17: =I17-CD17 -> 0
A18: 45601 | B18: DD’S DISCOUNTS | C18: 美国 | D18: 4500150186 | E18: 70054043 | F18: 4500150186-10 | G18: 9543GQ1-S001 | H18: 仓鼠 | I18: 616 | J18: 0 | K18: 22 | L18: =I18/K18 -> 28 | M18: 45653 | N18: 45649 | P18: PASS | Q18: 1/7出 | R18: ROSS指定箱唛格式 | U18: 无 | V18: 11/20-客供价格贴纸 | X18: 日期码格式：ZURU INC(BVI) 标准格式 日期：按实际生产日期 Packaging Info: 1.ZURU MA UPC 现有版本包装 + 客供价格贴纸，出口美国 , 优先使用MA 1L 最新版本 。 Remark: 1.ZURU MA UPC 现有版本包装 + 客供价格贴纸，出口美国 , 优先使用MA 1L 最新版本 。 2.价格贴纸位于包装正面右下角，不挡住重要信息即可，可适当调整 ，价格贴纸由跟单提供。 3.标准日期码格式，产品和包装必须有日期码 。 4.同个产品同个货期不可出现不同的包装。 5. 跟单提供ROSS通用的箱唛模版，工厂按实际45 PO上客户PO/Item号/装箱数 提供箱唛排版来确认。 | Y18: Taylor Liao | Z18: 2.8179 | AA18: =I18*Z18 -> 1735.8264 | AB18: 616 | AC18: =AB18-I18 -> 0 | AD18: ok | AE18: 9543GQ1-S001 | AF18: 已入 | AG18: 系统出单 | AH18: 88920-1.7 | AL18: =I18 -> 616 | AT18: =I18 -> 616 | AX18: =I18/11 -> 56 | BW18: 增加移印布标内容 | BX18: =I18/22*5 -> 140 | BY18: =I18/22*6 -> 168 | BZ18: =I18/22*6 -> 168 | CA18: =I18/22*5 -> 140 | CB18: =I18 -> 616 | CC18: =I18/11 -> 56 | CD18: =SUM(BX18:CA18) -> 616 | CE18: =I18-CD18 -> 0
A19: 45611 | B19: ToyChamp Belgium nv | C19: 比利时 | D19: 4500151401 | E19: 2024101316 | F19: 4500151401-40 | G19: 9543GQ1-S001 | H19: 仓鼠 | I19: 1584 | J19: 0 | K19: 22 | L19: =I19/K19 -> 72 | M19: 45657 | N19: 45653 | P19: PASS | Q19: 1/19出 | R19: 11/21收到 | U19: 11/21收到EAN条码贴纸 | X19: 日期码格式：ZURU INC(BVI) 标准格式 日期：按实际生产日期 Packaging Info: 9543GQ1: MA C版 3L（9L warning）收缩膜+1张EAN条码贴纸，MA 5L说明书（9L warning），MA B版 3L PDQ Remark: 1.外箱需要印条码，请确保条码可以清晰扫描，且条码内容正确 2.出欧洲，微塑料需合规（如item本身不含微塑料,则忽略此要求） 3.STD配比 | Y19: Amber Zhang | Z19: 2.8038 | AA19: =I19*Z19 -> 4441.2192 | AB19: 1584 | AC19: =AB19-I19 -> 0 | AD19: ok | AE19: 9543GQ1-S001-3L | AF19: 已入 | AG19: 系统出单 | AH19: 94107-1.18 | AO19: =I19 -> 1584 | AT19: =I19 -> 1584 | BA19: =I19/11 -> 144 | BW19: 增加移印布标内容 | BX19: =I19/22*5 -> 360 | BY19: =I19/22*6 -> 432 | BZ19: =I19/22*6 -> 432 | CA19: =I19/22*5 -> 360 | CB19: =I19 -> 1584 | CC19: =I19/11 -> 144 | CD19: =SUM(BX19:CA19) -> 1584 | CE19: =I19-CD19 -> 0
A20: 45616 | B20: N.V. DREAMLAND | C20: 比利时 | D20: 4500151832 | E20: 4500054541 | F20: 4500151832-10 | G20: 9543GQ1-S001 | H20: 仓鼠 | I20: 1584 | J20: 0 | K20: 22 | L20: =I20/K20 -> 72 | M20: 45657 | N20: 45653 | P20: PASS | Q20: 1/6出 | R20: 11/20收到 | U20: 11/20收到EAN条码贴纸 | X20: 日期码格式：ZURU INC(BVI) 标准格式 日期：按实际生产日期 Packaging Info: 9543GQ1: MA C版 3L（9L warning）收缩膜+1张EAN条码贴纸，MA 5L说明书（9L warning），MA B版 3L PDQ Remark: 1.外箱需要印条码，请确保条码可以清晰扫描，且条码内容正确 2.出欧洲，微塑料需合规（如item本身不含微塑料,则忽略此要求） 3.STD配比 4. 所有产品符合REACH申明 | Y20: Amber Zhang | Z20: 2.8038 | AA20: =I20*Z20 -> 4441.2192 | AB20: 1584 | AC20: =AB20-I20 -> 0 | AD20: ok | AE20: 9543GQ1-S001-3L | AF20: 已入 | AG20: 系统出单 | AH20: 88874-1.4 | AO20: =I20 -> 1584 | AT20: =I20 -> 1584 | BA20: =I20/11 -> 144 | BW20: 增加移印布标内容 | BX20: =I20/22*5 -> 360 | BY20: =I20/22*6 -> 432 | BZ20: =I20/22*6 -> 432 | CA20: =I20/22*5 -> 360 | CB20: =I20 -> 1584 | CC20: =I20/11 -> 144 | CD20: =SUM(BX20:CA20) -> 1584 | CE20: =I20-CD20 -> 0
A21: 45624 | B21: «Market Group» LLC | C21: 俄罗斯联邦 | D21: 4500152880 | F21: 4500152880-10 | G21: 9543GQ1-S002 | H21: 仓鼠 | I21: 1980 | J21: 0 | K21: 11 | L21: =I21/K21 -> 180 | M21: 45657 | N21: 45653 | P21: PASS | Q21: 1/2出 | R21: 11/29收到 | U21: 12/6-进口商贴纸+ EAN条码贴纸 | X21: 日期码格式：ZURU INC(BVI) 标准格式 日期：按实际生产日期 Packaging Info: 1. 9543GQ1 : 1L MA 收缩膜 or 彩卡 + 进口商贴纸+ EAN条码贴纸，MA 指南 /说明书/PDQ 如有; 2. 货期不能延后，客人有罚金。 3. 需要安排3套大货样，请多备料。 Remark: 标准配比 | Y21: Ann Zhang | Z21: 2.7662 | AA21: =I21*Z21 -> 5477.076 | AB21: 1980 | AC21: =AB21-I21 -> 0 | AD21: ok | AE21: 9543GQ1-S002 | AF21: 已入 | AG21: 系统出单 | AH21: 88935-1.8 | AL21: =I21 -> 1980 | AT21: =I21 -> 1980 | AX21: =I21/11 -> 180 | BW21: 增加移印布标内容 | BX21: =I21/22*5 -> 450 | BY21: =I21/22*6 -> 540 | BZ21: =I21/22*6 -> 540 | CA21: =I21/22*5 -> 450 | CB21: =I21 -> 1980 | CC21: =I21/11 -> 180 | CD21: =SUM(BX21:CA21) -> 1980 | CE21: =I21-CD21 -> 0
A22: 45624 | B22: BIG W | C22: 澳大利亚 | D22: 4500152763 | E22: CUS PO#47779210 SYD | F22: 4500152763-10 | G22: 9543GQ1-S001 | H22: 仓鼠 | I22: 506 | J22: 0 | K22: 22 | L22: =I22/K22 -> 23 | M22: 45657 | N22: 45653 | P22: PASS | Q22: 1/3出 | R22: 11/28收到 | U22: 进口商贴纸翻4500106537 | X22: 日期码格式：ZURU INC(BVI) 标准格式 日期：按实际生产日期 Packaging Info: 1. 包装 9543GQ1：英文MA包装 (UPC版本，首选1L，无1L可用多L含英语)+1张进口商贴纸，贴纸翻单4500106537 2. 产品和包装上的日期码一致，请按要求在包装上打日期码（进口商贴纸不覆盖日期码） 3. 使用ZURU标准日期码 Remark: 1. 共出4港口(SYD, BNE, MEL, FRE), 不同港口数量信息请见订单行项目，并请参考箱唛资料，港口不同，箱唛资料也不同； 2. 箱唛不可出现任何手写内容（箱数除外），重量与实际一致且不可手写; 3. 此单出澳大利亚，请按澳洲标准生产并满足当地法规要求; 4. 出无闪粉版本，需符合欧洲微塑料法规 | Y22: Christine Liao | Z22: 2.8789 | AA22: =I22*Z22 -> 1456.7234 | AB22: 506 | AC22: =AB22-I22 -> 0 | AD22: ok | AE22: 9543GQ1-S001 | AF22: 已入 | AG22: 系统出单 | AH22: 88832-1.2 | AL22: =I22 -> 506 | AT22: =I22 -> 506 | AX22: =I22/11 -> 46 | BW22: 增加移印布标内容 | BX22: =I22/22*5 -> 115 | BY22: =I22/22*6 -> 138 | BZ22: =I22/22*6 -> 138 | CA22: =I22/22*5 -> 115 | CB22: =I22 -> 506 | CC22: =I22/11 -> 46 | CD22: =SUM(BX22:CA22) -> 506 | CE22: =I22-CD22 -> 0
A23: 45624 | B23: BIG W | C23: 澳大利亚 | D23: 4500152763 | E23: CUS PO#47779211 BNE | F23: 4500152763-30 | G23: 9543GQ1-S001 | H23: 仓鼠 | I23: 440 | J23: 0 | K23: 22 | L23: =I23/K23 -> 20 | M23: 45657 | N23: 45653 | P23: PASS | Q23: 1/4出 | R23: 11/28收到 | U23: 进口商贴纸翻4500106537 | X23: 日期码格式：ZURU INC(BVI) 标准格式 日期：按实际生产日期 Packaging Info: 1. 包装 9543GQ1：英文MA包装 (UPC版本，首选1L，无1L可用多L含英语)+1张进口商贴纸，贴纸翻单4500106537 2. 产品和包装上的日期码一致，请按要求在包装上打日期码（进口商贴纸不覆盖日期码） 3. 使用ZURU标准日期码 Remark: 1. 共出4港口(SYD, BNE, MEL, FRE), 不同港口数量信息请见订单行项目，并请参考箱唛资料，港口不同，箱唛资料也不同； 2. 箱唛不可出现任何手写内容（箱数除外），重量与实际一致且不可手写; 3. 此单出澳大利亚，请按澳洲标准生产并满足当地法规要求; 4. 出无闪粉版本，需符合欧洲微塑料法规 | Y23: Christine Liao | Z23: 2.8789 | AA23: =I23*Z23 -> 1266.716 | AB23: 440 | AC23: =AB23-I23 -> 0 | AD23: ok | AE23: 9543GQ1-S001 | AF23: 已入 | AG23: 系统出单 | AH23: 88853-1.3 | AL23: =I23 -> 440 | AT23: =I23 -> 440 | AX23: =I23/11 -> 40 | BW23: 增加移印布标内容 | BX23: =I23/22*5 -> 100 | BY23: =I23/22*6 -> 120 | BZ23: =I23/22*6 -> 120 | CA23: =I23/22*5 -> 100 | CB23: =I23 -> 440 | CC23: =I23/11 -> 40 | CD23: =SUM(BX23:CA23) -> 440 | CE23: =I23-CD23 -> 0
A24: 45624 | B24: BIG W | C24: 澳大利亚 | D24: 4500152763 | E24: CUS PO#47779212 MEL | F24: 4500152763-50 | G24: 9543GQ1-S001 | H24: 仓鼠 | I24: 352 | J24: 0 | K24: 22 | L24: =I24/K24 -> 16 | M24: 45657 | N24: 45653 | P24: PASS | Q24: 1/8出 | R24: 11/28收到 | U24: 进口商贴纸翻4500106537 | X24: 日期码格式：ZURU INC(BVI) 标准格式 日期：按实际生产日期 Packaging Info: 1. 包装 9543GQ1：英文MA包装 (UPC版本，首选1L，无1L可用多L含英语)+1张进口商贴纸，贴纸翻单4500106537 2. 产品和包装上的日期码一致，请按要求在包装上打日期码（进口商贴纸不覆盖日期码） 3. 使用ZURU标准日期码 Remark: 1. 共出4港口(SYD, BNE, MEL, FRE), 不同港口数量信息请见订单行项目，并请参考箱唛资料，港口不同，箱唛资料也不同； 2. 箱唛不可出现任何手写内容（箱数除外），重量与实际一致且不可手写; 3. 此单出澳大利亚，请按澳洲标准生产并满足当地法规要求; 4. 出无闪粉版本，需符合欧洲微塑料法规 | Y24: Christine Liao | Z24: 2.8789 | AA24: =I24*Z24 -> 1013.3728 | AB24: 352 | AC24: =AB24-I24 -> 0 | AD24: ok | AE24: 9543GQ1-S001 | AF24: 已入 | AG24: 系统出单 | AH24: 88887-1.6 | AL24: =I24 -> 352 | AT24: =I24 -> 352 | AX24: =I24/11 -> 32 | BW24: 增加移印布标内容 | BX24: =I24/22*5 -> 80 | BY24: =I24/22*6 -> 96 | BZ24: =I24/22*6 -> 96 | CA24: =I24/22*5 -> 80 | CB24: =I24 -> 352 | CC24: =I24/11 -> 32 | CD24: =SUM(BX24:CA24) -> 352 | CE24: =I24-CD24 -> 0
A25: 45624 | B25: BIG W | C25: 澳大利亚 | D25: 4500152763 | E25: CUS PO#47779213 FRE | F25: 4500152763-70 | G25: 9543GQ1-S001 | H25: 仓鼠 | I25: 220 | J25: 0 | K25: 22 | L25: =I25/K25 -> 10 | M25: 45657 | N25: 45653 | P25: PASS | Q25: 1/4出 | R25: 11/28收到 | U25: 进口商贴纸翻4500106537 | X25: 日期码格式：ZURU INC(BVI) 标准格式 日期：按实际生产日期 Packaging Info: 1. 包装 9543GQ1：英文MA包装 (UPC版本，首选1L，无1L可用多L含英语)+1张进口商贴纸，贴纸翻单4500106537 2. 产品和包装上的日期码一致，请按要求在包装上打日期码（进口商贴纸不覆盖日期码） 3. 使用ZURU标准日期码 Remark: 1. 共出4港口(SYD, BNE, MEL, FRE), 不同港口数量信息请见订单行项目，并请参考箱唛资料，港口不同，箱唛资料也不同； 2. 箱唛不可出现任何手写内容（箱数除外），重量与实际一致且不可手写; 3. 此单出澳大利亚，请按澳洲标准生产并满足当地法规要求; 4. 出无闪粉版本，需符合欧洲微塑料法规 | Y25: Christine Liao | Z25: 2.8789 | AA25: =I25*Z25 -> 633.358 | AB25: 220 | AC25: =AB25-I25 -> 0 | AD25: ok | AE25: 9543GQ1-S001 | AF25: 已入 | AG25: 系统出单 | AH25: 88867-1.4 | AL25: =I25 -> 220 | AT25: =I25 -> 220 | AX25: =I25/11 -> 20 | BW25: 增加移印布标内容 | BX25: =I25/22*5 -> 50 | BY25: =I25/22*6 -> 60 | BZ25: =I25/22*6 -> 60 | CA25: =I25/22*5 -> 50 | CB25: =I25 -> 220 | CC25: =I25/11 -> 20 | CD25: =SUM(BX25:CA25) -> 220 | CE25: =I25-CD25 -> 0
A26: 45615 | B26: THE WAREHOUSE LIMITED | C26: 新西兰 | D26: 4500151669 | E26: 28682677 | F26: 4500151669-10 | G26: 9543GQ1-S001 | H26: 仓鼠 | I26: 1144 | J26: 0 | K26: 22 | L26: =I26/K26 -> 52 | M26: 45660 | N26: 45656 | P26: PASS | Q26: 1/14出 | R26: 11/19收到 | U26: 无 | X26: 日期码格式：ZURU INC(BVI) 标准格式 日期：按实际生产日期 Packaging Info: MA UPC 英语包装（优先1L英语版本，或者3L/5L含英语都可） 此客人不接受易掉落或者剥落或者可直接触碰的闪粉，可降解也不行，但可以接受符合欧洲微塑料标准的珠光粉或者闪片。 Remark: 此单出AKL 9543GQ1: bule/purple/pink/orange =5:6:6:5; 2PCS AAA Batteries(Not Include) | Y26: Abby Liang | Z26: 2.8038 | AA26: =I26*Z26 -> 3207.5472 | AB26: 1144 | AC26: =AB26-I26 -> 0 | AD26: 无 | AE26: 9543GQ1-S001 | AF26: 已入 | AG26: 系统出单 | AH26: 94011-1.13 | AL26: =I26 -> 1144 | AT26: =I26 -> 1144 | AX26: =I26/11 -> 104 | BW26: 增加移印布标内容 | BX26: =I26/22*5 -> 260 | BY26: =I26/22*6 -> 312 | BZ26: =I26/22*6 -> 312 | CA26: =I26/22*5 -> 260 | CB26: =I26 -> 1144 | CC26: =I26/11 -> 104 | CD26: =SUM(BX26:CA26) -> 1144 | CE26: =I26-CD26 -> 0
A27: 45618 | B27: CRG | C27: 哥斯达黎加 | D27: 4500152087 | E27: ZU01-25 | F27: 4500152087-80 | G27: 9543GQ1-S001 | H27: 仓鼠 | I27: 528 | J27: 0 | K27: 22 | L27: =I27/K27 -> 24 | M27: 45660 | N27: 45656 | P27: PASS | Q27: 1/8出 | R27: 11/25收到 | U27: 进口商贴纸翻4500098650 | X27: 日期码格式：ZURU INC(BVI) 标准格式 日期：按实际生产日期 Packaging Info: 9543GQ1:MA 1L包装+MA 5L说明书+进口商贴纸+箱唛，进口商贴纸翻单PO4500098650 Remark: | Y27: Ava Liang | Z27: 2.8179 | AA27: =I27*Z27 -> 1487.8512 | AB27: 528 | AC27: =AB27-I27 -> 0 | AD27: OK | AE27: 9543GQ1-S001 | AF27: 已入 | AG27: 系统出单 | AH27: 88961-1.9 | AL27: =I27 -> 528 | AT27: =I27 -> 528 | AX27: =I27/11 -> 48 | BW27: 增加移印布标内容 | BX27: =I27/22*5 -> 120 | BY27: =I27/22*6 -> 144 | BZ27: =I27/22*6 -> 144 | CA27: =I27/22*5 -> 120 | CB27: =I27 -> 528 | CC27: =I27/11 -> 48 | CD27: =SUM(BX27:CA27) -> 528 | CE27: =I27-CD27 -> 0
A28: 45615 | B28: THE WAREHOUSE LIMITED | C28: 新西兰 | D28: 4500151670 | E28: 28682679 | F28: 4500151670-10 | G28: 9543GQ1-S001 | H28: 仓鼠 | I28: 374 | J28: 0 | K28: 22 | L28: =I28/K28 -> 17 | M28: 45660 | N28: 45656 | P28: PASS | Q28: 1/14出 | R28: 11/19收到 | U28: 无 | X28: 日期码格式：ZURU INC(BVI) 标准格式 日期：按实际生产日期 Packaging Info: MA UPC 英语包装（优先1L英语版本，或者3L/5L含英语都可） 此客人不接受易掉落或者剥落或者可直接触碰的闪粉，可降解也不行，但可以接受符合欧洲微塑料标准的珠光粉或者闪片。 Remark: 此单出LYT 9543GQ1: bule/purple/pink/orange =5:6:6:5; 2PCS AAA Batteries(Not Include) | Y28: Abby Liang | Z28: 2.8179 | AA28: =I28*Z28 -> 1053.8946 | AB28: 374 | AC28: =AB28-I28 -> 0 | AD28: 无 | AE28: 9543GQ1-S001 | AF28: 已入 | AG28: 系统出单 | AH28: 94012-1.13 | AL28: =I28 -> 374 | AT28: =I28 -> 374 | AX28: =I28/11 -> 34 | BW28: 增加移印布标内容 | BX28: =I28/22*5 -> 85 | BY28: =I28/22*6 -> 102 | BZ28: =I28/22*6 -> 102 | CA28: =I28/22*5 -> 85 | CB28: =I28 -> 374 | CC28: =I28/11 -> 34 | CD28: =SUM(BX28:CA28) -> 374 | CE28: =I28-CD28 -> 0
A29: 45625 | B29: FREDMEYER INC | C29: 美国 | D29: 4500152951 | E29: 37333959 | F29: 4500152951-10 | G29: 9543GQ1-S002 | H29: 仓鼠 | I29: 5500 | J29: 0 | K29: 11 | L29: =I29/K29 -> 500 | M29: 45657 | N29: 45653 | P29: PASS | R29: 11/29收到 | U29: 无 | X29: 日期码格式：ZURU INC(BVI) 标准格式 日期：按实际生产日期 Packaging Info: 1、包装方式： MA UPC优先1L最新版，出口美国 Remark: 2、无第三方测试验货要求。 3、纸箱4面印ZURU LOGO + 箱唛。 4、日期码请按ZURU标准版执行即可。 5、ZURU QC验货 6、REMARK: 2pcs *AAA battery not Includedd; Integral single ratio=bule/purple/pink/orange =5:6:6:5; IF Kroger/Fredmeyer need new GTIN:60193052050320 | Y29: Vicky Wu | Z29: 2.7699 | AA29: =I29*Z29 -> 15234.45 | AB29: 5500 | AC29: =AB29-I29 -> 0 | AD29: 无 | AE29: 9543GQ1-S002 | AF29: 已入 | AG29: 系统出单 | AH29: 88886-1.6 | AL29: =I29 -> 5500 | AT29: =I29 -> 5500 | AX29: =I29/11 -> 500 | BW29: 增加移印布标内容 | BX29: =I29/22*5 -> 1250 | BY29: =I29/22*6 -> 1500 | BZ29: =I29/22*6 -> 1500 | CA29: =I29/22*5 -> 1250 | CB29: =I29 -> 5500 | CC29: =I29/11 -> 500 | CD29: =SUM(BX29:CA29) -> 5500 | CE29: =I29-CD29 -> 0
A30: 45621 | B30: ATLAS AMBASSADOR | C30: 摩洛哥 | D30: 4500152205 | F30: 4500152205-10 | G30: 9543GQ1-S001 | H30: 仓鼠 | I30: 506 | J30: 0 | K30: 22 | L30: =I30/K30 -> 23 | M30: 45659 | N30: 45656 | P30: PASS | Q30: 1/15出 | R30: 11/27收到 | U30: 12/11-进口商贴纸+说明书贴纸 | X30: 日期码格式：ZURU INC(BVI) 标准格式 日期：按实际生产日期 Packaging Info: 1.9543GQ1:1L MA UPC收缩膜+进口商贴纸;MA说明书;MA PDQ 2.此客户需要进行COC认证，装柜前在主拼工厂会有第三方验货，每款item需备2pcs 验货备品。 Remark: 标准产品标准配比 | Y30: Lena Huang | Z30: 2.8179 | AA30: =I30*Z30 -> 1425.8574 | AB30: 506 | AC30: =AB30-I30 -> 0 | AD30: ok | AE30: 9543GQ1-S001 | AF30: 已入 | AG30: 系统出单 | AH30: 94106-1.18 | AL30: =I30 -> 506 | AT30: =I30 -> 506 | AX30: =I30/11 -> 46 | BW30: 增加移印布标内容 | BX30: =I30/22*5 -> 115 | BY30: =I30/22*6 -> 138 | BZ30: =I30/22*6 -> 138 | CA30: =I30/22*5 -> 115 | CB30: =I30 -> 506 | CC30: =I30/11 -> 46 | CD30: =SUM(BX30:CA30) -> 506 | CE30: =I30-CD30 -> 0
A31: 45573 | B31: Ansaldo Chile | C31: 智利 | D31: 4500146540 | E31: 2024-HKC0026 | F31: 4500146540-30 | G31: 9543GQ1-S001 | H31: 仓鼠 | I31: 946 | J31: 0 | K31: 22 | L31: =I31/K31 -> 43 | M31: 45659 | N31: 45656 | P31: PASS | Q31: 1/10出 | R31: 10/15收到 | U31: 进口商贴纸翻450014636 | X31: 日期码格式：ZURU INC(BVI) 标准格式 日期：按实际生产日期 Packaging Info: 9543GQ1:MA 3L UPC包装+进口商贴纸+箱唛,进口商贴纸翻单PO4500146361 Remark: | Y31: Ava Liang | Z31: 2.8179 | AA31: =I31*Z31 -> 2665.7334 | AB31: 946 | AC31: =AB31-I31 -> 0 | AD31: ok | AE31: 9543GQ1-S001-3L | AF31: 已入 | AG31: 系统出单 | AH31: 88980-1.10 | AO31: =I31 -> 946 | AT31: =I31 -> 946 | BA31: =I31/11 -> 86 | BW31: 增加移印布标内容 | BX31: =I31/22*5 -> 215 | BY31: =I31/22*6 -> 258 | BZ31: =I31/22*6 -> 258 | CA31: =I31/22*5 -> 215 | CB31: =I31 -> 946 | CC31: =I31/11 -> 86 | CD31: =SUM(BX31:CA31) -> 946 | CE31: =I31-CD31 -> 0
A32: 45615 | B32: Wonderland Toys Inc DBA The Zoofy G | C32: 美国 | D32: 4500151635 | E32: 4357 | F32: 4500151635-10 | G32: 9543GQ1-S002 | H32: 仓鼠 | I32: 3718 | J32: 0 | K32: 11 | L32: =I32/K32 -> 338 | M32: 45665 | N32: 45661 | P32: PASS | Q32: 1/20出 | R32: 11/27收到 | U32: 11/27-价格贴纸+要UCC贴纸 | X32: 日期码格式：ZURU INC(BVI) 标准格式 日期：按实际生产日期 Packaging Info: 1. 出口美国，MA UPC 版本包装，优先1L。 #9543GQ1: PRICER TICK-10.99; Shipped without batteries; operated by 2PCS AAA batteries; 2. 产品需要价格贴纸， 贴纸资料后面提供。 3. 外箱需要UCC贴纸。贴纸资料后面提供。 Remark: 4. Zuru QC 验货即可。 | Y32: Abby Mai, Lluviazeng | Z32: 2.7552 | AA32: =I32*Z32 -> 10243.834 | AB32: 3718 | AC32: =AB32-I32 -> 0 | AD32: ok | AE32: 9543GQ1-S002 | AF32: 已入 | AG32: 系统出单 | AH32: 94108-1.18 | AL32: =I32 -> 3718 | AT32: =I32 -> 3718 | AX32: =I32/11 -> 338 | BW32: 增加移印布标内容 | BX32: =I32/22*5 -> 845 | BY32: =I32/22*6 -> 1014 | BZ32: =I32/22*6 -> 1014 | CA32: =I32/22*5 -> 845 | CB32: =I32 -> 3718 | CC32: =I32/11 -> 338 | CD32: =SUM(BX32:CA32) -> 3718 | CE32: =I32-CD32 -> 0
A33: 45631 | B33: Ambiental Paraguay | C33: 巴拉圭 | D33: 4500153347 | F33: 4500153347-50 | G33: 9543GQ1-S001 | H33: 仓鼠 | I33: 968 | J33: 0 | K33: 22 | L33: =I33/K33 -> 44 | M33: 45667 | N33: 45663 | P33: PASS | Q33: 1/11出 | R33: 12/5收到 | U33: 12/5-进口商贴纸 | X33: 日期码格式：ZURU INC(BVI) 标准格式 日期：按实际生产日期 Packaging Info: 9543GQ1:MA 3L UPC包装+进口商贴纸+箱唛，进口商贴纸贴于位置"B" | Y33: Ava Liang | Z33: 2.8179 | AA33: =I33*Z33 -> 2727.7272 | AB33: 968 | AC33: =AB33-I33 -> 0 | AD33: ok | AE33: 9543GQ1-S001-3L | AF33: 已入 | AG33: 系统出单 | AH33: 94049-1.15 | AO33: =I33 -> 968 | AT33: =I33 -> 968 | BA33: =I33/11 -> 88 | BW33: 增加移印布标内容 | BX33: =I33/22*5 -> 220 | BY33: =I33/22*6 -> 264 | BZ33: =I33/22*6 -> 264 | CA33: =I33/22*5 -> 220 | CB33: =I33 -> 968 | CC33: =I33/11 -> 88 | CD33: =SUM(BX33:CA33) -> 968 | CE33: =I33-CD33 -> 0
A34: 45603 | B34: DD’S DISCOUNTS | C34: 美国 | D34: 4500150314 | E34: 70054056 | F34: 4500150314-10 | G34: 9543GQ1-S001 | H34: 仓鼠 | I34: 616 | J34: 0 | K34: 22 | L34: =I34/K34 -> 28 | M34: 45670 | N34: 45666 | P34: PASS | R34: ROSS指定箱唛格式 | U34: 无 | V34: 12/2-客供价格贴纸 | X34: 日期码格式： 标准格式 日期：按实际生产日期 Packaging Info: 1.ZURU MA UPC 现有版本包装 + 客供价格贴纸，出口美国 , 优先使用MA 1L 最新版本 。 Remark: 1.ZURU MA UPC 现有版本包装 + 客供价格贴纸，出口美国 , 优先使用MA 1L 最新版本 。 2.价格贴纸位于包装正面右下角，不挡住重要信息即可，可适当调整 ，价格贴纸由跟单提供。 3.标准日期码格式，产品和包装必须有日期码 。 4.同个产品同个货期不可出现不同的包装。 5. 跟单提供ROSS通用的箱唛模版，工厂按实际45 PO上客户PO/Item号/装箱数 提供箱唛排版来确认 | Y34: Taylor Liao | Z34: 2.8179 | AA34: =I34*Z34 -> 1735.8264 | AB34: 616 | AC34: =AB34-I34 -> 0 | AD34: ok | AE34: 9543GQ1-S001 | AF34: 已入 | AG34: 系统出单 | AH34: 94127-1.21 | AL34: =I34 -> 616 | AT34: =I34 -> 616 | AX34: =I34/11 -> 56 | BW34: 增加移印布标内容 | BX34: =I34/22*5 -> 140 | BY34: =I34/22*6 -> 168 | BZ34: =I34/22*6 -> 168 | CA34: =I34/22*5 -> 140 | CB34: =I34 -> 616 | CC34: =I34/11 -> 56 | CD34: =SUM(BX34:CA34) -> 616 | CE34: =I34-CD34 -> 0
A35: 45623 | B35: Amazon CA (Vendor Center) | C35: 加拿大 | D35: 4500152544 | E35: 6QVOH9XX | F35: 4500152544-70 | G35: 9543A-S001 | H35: 仓鼠 | I35: 24 | J35: 0 | K35: 24 | L35: =I35/K35 -> 1 | M35: 45670 | N35: 45666 | P35: PASS | Q35: 1/16-1/21出 | R35: 11/27收到 | U35: UPC贴纸跟翻4500098824 | V35: 12/20-客供外箱贴纸 | X35: 日期码格式：ZURU INC(BVI) 标准格式 日期：按实际生产日期 Packaging Info: 出口加拿大，包装需要至少2/3L UPC版，无硼版本。 #9543: MA 3L UPC版本。A:193052051776, B:193052051783, E:193052051806,; Remark: 1. Amazon FOB订单，出口CA。外箱最长边不能超过25" （超过了，case pack只能为1），不符合要求的大货，一律不接受。 2. 外箱正面印ZURU Logo + SSCC LABEL（客供贴纸)，侧面印item#（订单上显示的SKU#) + carton size(以工厂实际尺寸为准，单位: inch) + MADE IN CHINA， 日期使用ZURU 标准版本 SSCC Label 显示的是客人自己的item#，SSCC Label 贴在外箱正面的正中间，贴一面即可，跟单订购，贴纸离外箱距必须至少3cm，每一 张SSCC label 都是唯一且有不同流水及条码的，没有损耗，绝对不可贴错 ，否则贴错或损坏一张会导致全部都错，千万要注意: SSCC 贴纸务必要在正中间(可以覆 盖Logo <(>&<)> 箱唛)，否则会影响到仓库扫描识别。 3. 日期码使用ZURU标准版本。 4. 如果大货有要求入邮包盒，则对应的邮包盒上面要打上日期码。 5. 按照客户PO# 装柜/箱号顺序装柜，跟单会提前给到装柜计划。在大货生产/仓库存放时，请留意该装柜要求，以便装柜时不混乱（避免装错/装漏/找不到货号等 ）。 6. 出口加拿大，包装需要至少2/3L UPC版，无硼版本。 7.邮包盒上要印刷日期码 | Y35: Kelly/Mia | Z35: 2.5695 | AA35: =I35*Z35 -> 61.668 | AB35: 24 | AC35: =AB35-I35 -> 0 | AD35: ok | AE35: 9543A-S001-3L | AF35: 已入 | AG35: 系统出单 | AH35: 94134-1.21 | AO35: =I35 -> 24 | AT35: =I35 -> 24 | BW35: 增加移印布标内容 | BX35: =I35 -> 24 | CB35: =I35 -> 24 | CD35: =SUM(BX35:CA35) -> 24 | CE35: =I35-CD35 -> 0
A36: 45623 | B36: Amazon CA (Vendor Center) | C36: 加拿大 | D36: 4500152544 | E36: 741V7UML | F36: 4500152544-90 | G36: 9543B-S001 | H36: 仓鼠 | I36: 24 | J36: 0 | K36: 24 | L36: =I36/K36 -> 1 | M36: 45670 | N36: 45666 | P36: PASS | Q36: 1/16-1/21出 | R36: 11/27收到 | U36: UPC贴纸跟翻4500098824 | V36: 12/20-客供外箱贴纸 | X36: 日期码格式：ZURU INC(BVI) 标准格式 日期：按实际生产日期 Packaging Info: 出口加拿大，包装需要至少2/3L UPC版，无硼版本。 #9543: MA 3L UPC版本。A:193052051776, B:193052051783, E:193052051806,; Remark: 1. Amazon FOB订单，出口CA。外箱最长边不能超过25" （超过了，case pack只能为1），不符合要求的大货，一律不接受。 2. 外箱正面印ZURU Logo + SSCC LABEL（客供贴纸)，侧面印item#（订单上显示的SKU#) + carton size(以工厂实际尺寸为准，单位: inch) + MADE IN CHINA， 日期使用ZURU 标准版本 SSCC Label 显示的是客人自己的item#，SSCC Label 贴在外箱正面的正中间，贴一面即可，跟单订购，贴纸离外箱距必须至少3cm，每一 张SSCC label 都是唯一且有不同流水及条码的，没有损耗，绝对不可贴错 ，否则贴错或损坏一张会导致全部都错，千万要注意: SSCC 贴纸务必要在正中间(可以覆 盖Logo <(>&<)> 箱唛)，否则会影响到仓库扫描识别。 3. 日期码使用ZURU标准版本。 4. 如果大货有要求入邮包盒，则对应的邮包盒上面要打上日期码。 5. 按照客户PO# 装柜/箱号顺序装柜，跟单会提前给到装柜计划。在大货生产/仓库存放时，请留意该装柜要求，以便装柜时不混乱（避免装错/装漏/找不到货号等 ）。 6. 出口加拿大，包装需要至少2/3L UPC版，无硼版本。 7.邮包盒上要印刷日期码 | Y36: Kelly/Mia | Z36: 2.5695 | AA36: =I36*Z36 -> 61.668 | AB36: 24 | AC36: =AB36-I36 -> 0 | AD36: ok | AE36: 9543B-S001-3L | AF36: 已入 | AG36: 系统出单 | AH36: 94134-1.21 | AO36: =I36 -> 24 | AT36: =I36 -> 24 | BW36: 增加移印布标内容 | BY36: =I36 -> 24 | CB36: =I36 -> 24 | CD36: =SUM(BX36:CA36) -> 24 | CE36: =I36-CD36 -> 0
A37: 45623 | B37: Amazon CA (Vendor Center) | C37: 加拿大 | D37: 4500152544 | E37: 1OGZNF3F | F37: 4500152544-120 | G37: 9543A-S001 | H37: 仓鼠 | I37: 24 | J37: 0 | K37: 24 | L37: =I37/K37 -> 1 | M37: 45670 | N37: 45666 | P37: PASS | Q37: 1/16-1/21出 | R37: 11/27收到 | U37: UPC贴纸跟翻4500098824 | V37: 12/20-客供外箱贴纸 | X37: 日期码格式：ZURU INC(BVI) 标准格式 日期：按实际生产日期 Packaging Info: 出口加拿大，包装需要至少2/3L UPC版，无硼版本。 #9543: MA 3L UPC版本。A:193052051776, B:193052051783, E:193052051806,; Remark: 1. Amazon FOB订单，出口CA。外箱最长边不能超过25" （超过了，case pack只能为1），不符合要求的大货，一律不接受。 2. 外箱正面印ZURU Logo + SSCC LABEL（客供贴纸)，侧面印item#（订单上显示的SKU#) + carton size(以工厂实际尺寸为准，单位: inch) + MADE IN CHINA， 日期使用ZURU 标准版本 SSCC Label 显示的是客人自己的item#，SSCC Label 贴在外箱正面的正中间，贴一面即可，跟单订购，贴纸离外箱距必须至少3cm，每一 张SSCC label 都是唯一且有不同流水及条码的，没有损耗，绝对不可贴错 ，否则贴错或损坏一张会导致全部都错，千万要注意: SSCC 贴纸务必要在正中间(可以覆 盖Logo <(>&<)> 箱唛)，否则会影响到仓库扫描识别。 3. 日期码使用ZURU标准版本。 4. 如果大货有要求入邮包盒，则对应的邮包盒上面要打上日期码。 5. 按照客户PO# 装柜/箱号顺序装柜，跟单会提前给到装柜计划。在大货生产/仓库存放时，请留意该装柜要求，以便装柜时不混乱（避免装错/装漏/找不到货号等 ）。 6. 出口加拿大，包装需要至少2/3L UPC版，无硼版本。 7.邮包盒上要印刷日期码 | Y37: Kelly/Mia | Z37: 2.5695 | AA37: =I37*Z37 -> 61.668 | AB37: 24 | AC37: =AB37-I37 -> 0 | AD37: ok | AE37: 9543A-S001-3L | AF37: 已入 | AG37: 系统出单 | AH37: 94134-1.21 | AO37: =I37 -> 24 | AT37: =I37 -> 24 | BW37: 增加移印布标内容 | BX37: =I37 -> 24 | CB37: =I37 -> 24 | CD37: =SUM(BX37:CA37) -> 24 | CE37: =I37-CD37 -> 0
A38: 45623 | B38: Amazon CA (Vendor Center) | C38: 加拿大 | D38: 4500152544 | E38: 6GPK2DAR | F38: 4500152544-130 | G38: 9543E-S001 | H38: 仓鼠 | I38: 24 | J38: 0 | K38: 24 | L38: =I38/K38 -> 1 | M38: 45670 | N38: 45666 | P38: PASS | Q38: 1/16-1/21出 | R38: 11/27收到 | U38: UPC贴纸跟翻4500098824 | V38: 12/20-客供外箱贴纸 | X38: 日期码格式：ZURU INC(BVI) 标准格式 日期：按实际生产日期 Packaging Info: 出口加拿大，包装需要至少2/3L UPC版，无硼版本。 #9543: MA 3L UPC版本。A:193052051776, B:193052051783, E:193052051806,; Remark: 1. Amazon FOB订单，出口CA。外箱最长边不能超过25" （超过了，case pack只能为1），不符合要求的大货，一律不接受。 2. 外箱正面印ZURU Logo + SSCC LABEL（客供贴纸)，侧面印item#（订单上显示的SKU#) + carton size(以工厂实际尺寸为准，单位: inch) + MADE IN CHINA， 日期使用ZURU 标准版本 SSCC Label 显示的是客人自己的item#，SSCC Label 贴在外箱正面的正中间，贴一面即可，跟单订购，贴纸离外箱距必须至少3cm，每一 张SSCC label 都是唯一且有不同流水及条码的，没有损耗，绝对不可贴错 ，否则贴错或损坏一张会导致全部都错，千万要注意: SSCC 贴纸务必要在正中间(可以覆 盖Logo <(>&<)> 箱唛)，否则会影响到仓库扫描识别。 3. 日期码使用ZURU标准版本。 4. 如果大货有要求入邮包盒，则对应的邮包盒上面要打上日期码。 5. 按照客户PO# 装柜/箱号顺序装柜，跟单会提前给到装柜计划。在大货生产/仓库存放时，请留意该装柜要求，以便装柜时不混乱（避免装错/装漏/找不到货号等 ）。 6. 出口加拿大，包装需要至少2/3L UPC版，无硼版本。 7.邮包盒上要印刷日期码 | Y38: Kelly/Mia | Z38: 2.5695 | AA38: =I38*Z38 -> 61.668 | AB38: 24 | AC38: =AB38-I38 -> 0 | AD38: ok | AE38: 9543E-S001-3L | AF38: 已入 | AG38: 系统出单 | AH38: 94134-1.21 | AO38: =I38 -> 24 | AT38: =I38 -> 24 | BW38: 增加移印布标内容 | CA38: =I38 -> 24 | CB38: =I38 -> 24 | CD38: =SUM(BX38:CA38) -> 24 | CE38: =I38-CD38 -> 0
A39: 45623 | B39: Amazon CA (Vendor Center) | C39: 加拿大 | D39: 4500152544 | E39: 2SPNAMFN | F39: 4500152544-140 | G39: 9543E-S001 | H39: 仓鼠 | I39: 24 | J39: 0 | K39: 24 | L39: =I39/K39 -> 1 | M39: 45670 | N39: 45666 | P39: PASS | Q39: 1/16-1/21出 | R39: 11/27收到 | U39: UPC贴纸跟翻4500098824 | V39: 12/20-客供外箱贴纸 | X39: 日期码格式：ZURU INC(BVI) 标准格式 日期：按实际生产日期 Packaging Info: 出口加拿大，包装需要至少2/3L UPC版，无硼版本。 #9543: MA 3L UPC版本。A:193052051776, B:193052051783, E:193052051806,; Remark: 1. Amazon FOB订单，出口CA。外箱最长边不能超过25" （超过了，case pack只能为1），不符合要求的大货，一律不接受。 2. 外箱正面印ZURU Logo + SSCC LABEL（客供贴纸)，侧面印item#（订单上显示的SKU#) + carton size(以工厂实际尺寸为准，单位: inch) + MADE IN CHINA， 日期使用ZURU 标准版本 SSCC Label 显示的是客人自己的item#，SSCC Label 贴在外箱正面的正中间，贴一面即可，跟单订购，贴纸离外箱距必须至少3cm，每一 张SSCC label 都是唯一且有不同流水及条码的，没有损耗，绝对不可贴错 ，否则贴错或损坏一张会导致全部都错，千万要注意: SSCC 贴纸务必要在正中间(可以覆 盖Logo <(>&<)> 箱唛)，否则会影响到仓库扫描识别。 3. 日期码使用ZURU标准版本。 4. 如果大货有要求入邮包盒，则对应的邮包盒上面要打上日期码。 5. 按照客户PO# 装柜/箱号顺序装柜，跟单会提前给到装柜计划。在大货生产/仓库存放时，请留意该装柜要求，以便装柜时不混乱（避免装错/装漏/找不到货号等 ）。 6. 出口加拿大，包装需要至少2/3L UPC版，无硼版本。 7.邮包盒上要印刷日期码 | Y39: Kelly/Mia | Z39: 2.5695 | AA39: =I39*Z39 -> 61.668 | AB39: 24 | AC39: =AB39-I39 -> 0 | AD39: ok | AE39: 9543E-S001-3L | AF39: 已入 | AG39: 系统出单 | AH39: 94134-1.21 | AO39: =I39 -> 24 | AT39: =I39 -> 24 | BW39: 增加移印布标内容 | CA39: =I39 -> 24 | CB39: =I39 -> 24 | CD39: =SUM(BX39:CA39) -> 24 | CE39: =I39-CD39 -> 0
A40: 45623 | B40: Amazon CA (Vendor Center) | C40: 加拿大 | D40: 4500152544 | E40: 6ZIX89BO | F40: 4500152544-180 | G40: 9543E-S001 | H40: 仓鼠 | I40: 24 | J40: 0 | K40: 24 | L40: =I40/K40 -> 1 | M40: 45670 | N40: 45666 | P40: PASS | Q40: 1/16-1/21出 | R40: 11/27收到 | U40: UPC贴纸跟翻4500098824 | V40: 12/20-客供外箱贴纸 | X40: 日期码格式：ZURU INC(BVI) 标准格式 日期：按实际生产日期 Packaging Info: 出口加拿大，包装需要至少2/3L UPC版，无硼版本。 #9543: MA 3L UPC版本。A:193052051776, B:193052051783, E:193052051806,; Remark: 1. Amazon FOB订单，出口CA。外箱最长边不能超过25" （超过了，case pack只能为1），不符合要求的大货，一律不接受。 2. 外箱正面印ZURU Logo + SSCC LABEL（客供贴纸)，侧面印item#（订单上显示的SKU#) + carton size(以工厂实际尺寸为准，单位: inch) + MADE IN CHINA， 日期使用ZURU 标准版本 SSCC Label 显示的是客人自己的item#，SSCC Label 贴在外箱正面的正中间，贴一面即可，跟单订购，贴纸离外箱距必须至少3cm，每一 张SSCC label 都是唯一且有不同流水及条码的，没有损耗，绝对不可贴错 ，否则贴错或损坏一张会导致全部都错，千万要注意: SSCC 贴纸务必要在正中间(可以覆 盖Logo <(>&<)> 箱唛)，否则会影响到仓库扫描识别。 3. 日期码使用ZURU标准版本。 4. 如果大货有要求入邮包盒，则对应的邮包盒上面要打上日期码。 5. 按照客户PO# 装柜/箱号顺序装柜，跟单会提前给到装柜计划。在大货生产/仓库存放时，请留意该装柜要求，以便装柜时不混乱（避免装错/装漏/找不到货号等 ）。 6. 出口加拿大，包装需要至少2/3L UPC版，无硼版本。 7.邮包盒上要印刷日期码 | Y40: Kelly/Mia | Z40: 2.5695 | AA40: =I40*Z40 -> 61.668 | AB40: 24 | AC40: =AB40-I40 -> 0 | AD40: ok | AE40: 9543E-S001-3L | AF40: 已入 | AG40: 系统出单 | AH40: 94134-1.21 | AO40: =I40 -> 24 | AT40: =I40 -> 24 | BW40: 增加移印布标内容 | CA40: =I40 -> 24 | CB40: =I40 -> 24 | CD40: =SUM(BX40:CA40) -> 24 | CE40: =I40-CD40 -> 0
A41: 45621 | B41: SUCKOT SAC | C41: 秘鲁 | D41: 4500152261 | F41: 4500152261-100 | G41: 9543GQ1-S001 | H41: 仓鼠 | I41: 5940 | J41: 0 | K41: 22 | L41: =I41/K41 -> 270 | M41: 45663 | N41: 45659 | P41: PASS | Q41: 1/6出 | R41: 11/26收到 | U41: 12/19-进口商贴纸 | X41: 日期码格式：ZURU INC(BVI) 标准格式 日期：按实际生产日期 Tracking Code: Packaging Info: 9543GQ1：MA 3L UPC包装+MA PDQ包装+MA 多语说明书+进口商贴纸+箱唛 Remark: 9543GQ1：bule/purple/pink/orange =5:6:6:5; 2PCS AAA Batteries(Not Include) 出货前要提供大货照片给客户确认后才能出货，请按期完货 | Y41: Zoe Luo | Z41: 2.7752 | AA41: =I41*Z41 -> 16484.688 | AB41: =2376+3564 -> 5940 | AC41: =AB41-I41 -> 0 | AD41: ok | AE41: 9543GQ1-S001-3L | AF41: 已入 | AG41: 系统出单 | AH41: 88921-1.7 | AO41: =I41 -> 5940 | AT41: =I41 -> 5940 | BA41: =I41/11 -> 540 | BW41: 增加移印布标内容 | BX41: =I41/22*5 -> 1350 | BY41: =I41/22*6 -> 1620 | BZ41: =I41/22*6 -> 1620 | CA41: =I41/22*5 -> 1350 | CB41: =I41 -> 5940 | CC41: =I41/11 -> 540 | CD41: =SUM(BX41:CA41) -> 5940 | CE41: =I41-CD41 -> 0
A42: 45624 | B42: WABRO | C42: 阿根廷 | D42: 4500152720 | F42: 4500152720-190 | G42: 9543GQ1-S001 | H42: 仓鼠 | I42: 1012 | J42: 0 | K42: 22 | L42: =I42/K42 -> 46 | M42: 45663 | N42: 45659 | P42: PASS | Q42: 1/8出 | R42: 12/3收到 | U42: 12/6-进口商贴纸+ITEM NO.贴纸 | X42: 日期码格式：ZURU INC(BVI) 标准格式 日期：按实际生产日期 Packaging Info: 9543GQ1:MA 3L包装+MA 5L说明书+进口商贴纸+箱唛+ITEM NO.贴纸 Remark: LR44 电池品牌为ONLY | Y42: Ava Liang | Z42: 2.8038 | AA42: =I42*Z42 -> 2837.4456 | AB42: 1012 | AC42: =AB42-I42 -> 0 | AD42: ok | AE42: 9543GQ1-S001-3L | AF42: 已入 | AG42: 系统出单 | AH42: 88958-1.9 | AO42: =I42 -> 1012 | AT42: =I42 -> 1012 | BA42: =I42/11 -> 92 | BW42: 增加移印布标内容 | BX42: =I42/22*5 -> 230 | BY42: =I42/22*6 -> 276 | BZ42: =I42/22*6 -> 276 | CA42: =I42/22*5 -> 230 | CB42: =I42 -> 1012 | CC42: =I42/11 -> 92 | CD42: =SUM(BX42:CA42) -> 1012 | CE42: =I42-CD42 -> 0
A43: 45615 | B43: VM INTERNATIONAL | C43: 美国 | D43: 4500151779 | F43: 4500151779-20 | G43: 9543GQ1-S001 | H43: 仓鼠 | I43: 1760 | J43: 0 | K43: 22 | L43: =I43/K43 -> 80 | M43: 45666 | N43: 45663 | P43: PASS | Q43: 1/13出 | R43: 12/12收到 | U43: 无 | X43: 日期码格式：ZURU INC(BVI) 标准格式 日期：按实际生产日期 Packaging Info: 1.ZURU 标准日期码格式， 2.无第三方测试和验货，ZURU 内部QC验货即可出货 Remark: 3. 优先 MA 1L UPC包装; 4. 纸箱印ZURU LOGO，出口美国； | Y43: Iris Yuan | Z43: 2.8038 | AA43: =I43*Z43 -> 4934.688 | AB43: 1760 | AC43: =AB43-I43 -> 0 | AD43: 无 | AE43: 9543GQ1-S001 | AF43: 已入 | AG43: 系统出单 | AH43: 94112-1.18 | AL43: =I43 -> 1760 | AT43: =I43 -> 1760 | AX43: =I43/11 -> 160 | BW43: 增加移印布标内容 | BX43: =I43/22*5 -> 400 | BY43: =I43/22*6 -> 480 | BZ43: =I43/22*6 -> 480 | CA43: =I43/22*5 -> 400 | CB43: =I43 -> 1760 | CC43: =I43/11 -> 160 | CD43: =SUM(BX43:CA43) -> 1760 | CE43: =I43-CD43 -> 0
A44: 45629 | B44: APOLLO D.O.O. | C44: 斯洛文尼亚 | D44: 4500153179 | F44: 4500153179-10 | G44: 9543GQ1-S001 | H44: 仓鼠 | I44: 1210 | J44: 0 | K44: 22 | L44: =I44/K44 -> 55 | M44: 45667 | N44: 45663 | P44: PASS | Q44: 收到SO | R44: 12/3收到 | U44: 进口商贴纸(翻4500119045 | X44: 日期码格式：ZURU INC(BVI) 标准格式 日期：按实际生产日期 Packaging Info: 9543GQ1: MA最新包装含UPC条码+进口商贴纸(翻4500119045）+MA PDQ Remark: 此单出欧洲斯洛文尼亚， 需满足EU测试标准要求，不能含微塑料，需出无闪粉版本 9543GQ1:bule/purple/pink/orange =5:6:6:5; 2PCS AAA Batteries(Not Include) | Y44: Sharon | Z44: 2.7684 | AA44: =I44*Z44 -> 3349.764 | AB44: 1210 | AC44: =AB44-I44 -> 0 | AD44: ok | AE44: 9543GQ1-S001 | AF44: 已入 | AG44: 系统出单 | AH44: 94148-1.22 | AL44: =I44 -> 1210 | AT44: =I44 -> 1210 | AX44: =I44/11 -> 110 | BW44: 增加移印布标内容 | BX44: =I44/22*5 -> 275 | BY44: =I44/22*6 -> 330 | BZ44: =I44/22*6 -> 330 | CA44: =I44/22*5 -> 275 | CB44: =I44 -> 1210 | CC44: =I44/11 -> 110 | CD44: =SUM(BX44:CA44) -> 1210 | CE44: =I44-CD44 -> 0
A45: 45594 | B45: Gabriel Brothers | C45: 美国 | D45: 4500148873 | E45: 84006305 | F45: 4500148873-10 | G45: 9543GQ1-S001 | H45: 仓鼠 | I45: 1210 | J45: 0 | K45: 22 | L45: =I45/K45 -> 55 | M45: 45677 | N45: 45673 | P45: PASS | Q45: 1/21出 | R45: 10/29收到 | U45: 无 | X45: 日期码格式：ZURU INC(BVI) 标准格式 日期：按实际生产日期 Packaging Info: ZURU MA UPC (首选1L / 多语可以接受)包装, Remark: 1. ZURU MA UPC (首选1L / 多语可以接受)包装, 2. 产品和包装上印刷tracking code信息，格式为ZURU常规 3. 整柜FCL 出货，（装柜工厂）装柜时最后一箱正唛贴上装箱单 (不是装柜工厂忽略即可），装箱单需要用透明的袋子装好， 剩下三面贴上'' PACKING LIST ENC LOSED '' 的字样 （可以用A4 纸打印）- 船务会发出。 4. 需ZURU QC 验货合格后方可出货 | Y45: Jessi Xu | Z45: 2.8038 | AA45: =I45*Z45 -> 3392.598 | AB45: 1210 | AC45: =AB45-I45 -> 0 | AE45: 9543GQ1-S001 | AF45: 已入 | AG45: 系统出单 | AH45: 94092-1.18 | AL45: =I45 -> 1210 | AT45: =I45 -> 1210 | AX45: =I45/11 -> 110 | BW45: 增加移印布标内容 | BX45: =I45/22*5 -> 275 | BY45: =I45/22*6 -> 330 | BZ45: =I45/22*6 -> 330 | CA45: =I45/22*5 -> 275 | CB45: =I45 -> 1210 | CC45: =I45/11 -> 110 | CD45: =SUM(BX45:CA45) -> 1210 | CE45: =I45-CD45 -> 0
A46: 45610 | B46: AMAZON UK | C46: 英国 | D46: 4500151302 | E46: Amazon UK:8VVMR8EI | F46: 4500151302-70 | G46: 9543B-S001-PKC | H46: 仓鼠 1只胶袋装 | I46: 504 | J46: 0 | K46: 24 | L46: =I46/K46 -> 21 | M46: 45667 | N46: 45663 | P46: PASS | Q46: 1/22-1/26出 | R46: 空白外箱（加印带Zuru字样的最新logo，除了邮包盒直接做外箱的产品） + SSCC LABEL一张, 无箱唛。 | U46: UPC+IT翻单4500120504+ES回收标翻4500151280+1/10-胶袋UPC贴纸 | V46: 12/9-外箱贴纸 | X46: 日期码格式：ZURU INC(BVI) 标准格式 日期：按实际生产日期 Packaging Info: Amazon UK(9543B, 71126, 71109B)/DE(9543B, 7150B) 1. 9543B：9543B 24pcs/ctn, no inner, pink; MA 3L（9L warning）C版收缩膜+4张贴纸(1张#UPC+1张IT sorting label，参考翻单PO#4500120504；1张ES回收标 ，参考翻单PO#4500151280；1张ZURU邮箱，参考翻单PO#4500151280)+5L(9L warning)A说明书+Polybag(含防窒息5L警示语+塑料循环标) +1张贴纸(UPC#，参考翻单P O#4500120504，贴在polybag)； 5. 最迟验货不得晚于2024/1/13; Remark: 1.空白外箱（加印带Zuru字样的最新logo，除了邮包盒直接做外箱的产品） + SSCC LABEL一张, 无箱唛。 (SSCC LABEL贴在外箱正面的正中间，贴一面即可,贴纸离外箱边距必须至少3.2CM), SSCC贴纸由工厂直接跟勤得采购或者工厂自行采购，每一张SSCC Label都是唯一 且有不同流水及条码，且需要检查条码是否能正常扫描，另外，此贴纸印刷不可出现模糊，溢出及粘胶不牢易脱落等现象，如工厂不按此要求导致贴纸有任何问题产 生的罚款将由工厂承担一切责任 。’MADE IN CHINA 外箱只印一正一侧。 2.出往UK的产品+包装务必打上UKCA logo ，否则客人会退货且当地会有罚款。 3.订单必须经过ZURU QC验货并且通过后方可出货。 4.法国订单要求包装不使用矿物油，请按要求提供以下其中一份文件再出货 ，产品出到法国被相关部门抽检出现包装不符合此要求的，供应商需要为此承担责任， 故此请严格把关。 -油墨物质""由1 ~ 7个芳香环组成的MOAH""的包装检测报告，要求限值≤1.0%； -包装材料清单，包括包装油墨或物质的信息； -油墨制造商的证书； 5.每一批次出货只能有一个生产日期，不可多个生产日期混在同一批次出货；且邮包盒上必须统一加上日期码； 6.涉及到相关款式会有闪粉的或者微塑料的，请统一默认出无闪粉或者不含微塑料版本； 7.邮包盒及外箱封箱必须是工字型封箱方式； 8.5 Surprise or Mini Brands涉及包装是2个及2个以上的球入PVC桶包装时，单个球上若有UPC#或者EAN#，请用白色贴纸覆盖住； 9.箱唛资料按照给定的标准去做即可，无需发回我方再行审批(新标准将另行通知); | Y46: Crystal Chen | Z46: 2.4325 | AA46: =I46*Z46 -> 1225.98 | AB46: 504 | AC46: =AB46-I46 -> 0 | AD46: ok | AE46: 9543B-S001-3L | AF46: 已入 | AG46: 系统出单 | AH46: 94154-1.22 | AO46: =I46 -> 504 | AT46: =I46 -> 504 | BW46: 增加移印布标内容 | BY46: =I46 -> 504 | CB46: =I46 -> 504 | CD46: =SUM(BX46:CA46) -> 504 | CE46: =I46-CD46 -> 0
A47: 45610 | B47: AMAZON UK | C47: 英国 | D47: 4500151302 | E47: Amazon DE:6WL9FEON | F47: 4500151302-80 | G47: 9543B-S001-PKC | H47: 仓鼠 1只胶袋装 | I47: 504 | J47: 0 | K47: 24 | L47: =I47/K47 -> 21 | M47: 45667 | N47: 45663 | P47: PASS | Q47: 1/21-1/25出 | R47: 空白外箱（加印带Zuru字样的最新logo，除了邮包盒直接做外箱的产品） + SSCC LABEL一张, 无箱唛。 | U47: UPC+IT翻单4500120504+ES回收标翻4500151280+1/10-胶袋UPC贴纸 | V47: 12/9-外箱贴纸 | X47: 日期码格式：ZURU INC(BVI) 标准格式 日期：按实际生产日期 Packaging Info: Amazon UK(9543B, 71126, 71109B)/DE(9543B, 7150B) 1. 9543B：9543B 24pcs/ctn, no inner, pink; MA 3L（9L warning）C版收缩膜+4张贴纸(1张#UPC+1张IT sorting label，参考翻单PO#4500120504；1张ES回收标 ，参考翻单PO#4500151280；1张ZURU邮箱，参考翻单PO#4500151280)+5L(9L warning)A说明书+Polybag(含防窒息5L警示语+塑料循环标) +1张贴纸(UPC#，参考翻单P O#4500120504，贴在polybag)； 5. 最迟验货不得晚于2024/1/13; Remark: 1.空白外箱（加印带Zuru字样的最新logo，除了邮包盒直接做外箱的产品） + SSCC LABEL一张, 无箱唛。 (SSCC LABEL贴在外箱正面的正中间，贴一面即可,贴纸离外箱边距必须至少3.2CM), SSCC贴纸由工厂直接跟勤得采购或者工厂自行采购，每一张SSCC Label都是唯一 且有不同流水及条码，且需要检查条码是否能正常扫描，另外，此贴纸印刷不可出现模糊，溢出及粘胶不牢易脱落等现象，如工厂不按此要求导致贴纸有任何问题产 生的罚款将由工厂承担一切责任 。’MADE IN CHINA 外箱只印一正一侧。 2.出往UK的产品+包装务必打上UKCA logo ，否则客人会退货且当地会有罚款。 3.订单必须经过ZURU QC验货并且通过后方可出货。 4.法国订单要求包装不使用矿物油，请按要求提供以下其中一份文件再出货 ，产品出到法国被相关部门抽检出现包装不符合此要求的，供应商需要为此承担责任， 故此请严格把关。 -油墨物质""由1 ~ 7个芳香环组成的MOAH""的包装检测报告，要求限值≤1.0%； -包装材料清单，包括包装油墨或物质的信息； -油墨制造商的证书； 5.每一批次出货只能有一个生产日期，不可多个生产日期混在同一批次出货；且邮包盒上必须统一加上日期码； 6.涉及到相关款式会有闪粉的或者微塑料的，请统一默认出无闪粉或者不含微塑料版本； 7.邮包盒及外箱封箱必须是工字型封箱方式； 8.5 Surprise or Mini Brands涉及包装是2个及2个以上的球入PVC桶包装时，单个球上若有UPC#或者EAN#，请用白色贴纸覆盖住； 9.箱唛资料按照给定的标准去做即可，无需发回我方再行审批(新标准将另行通知); | Y47: Crystal Chen | Z47: 2.4325 | AA47: =I47*Z47 -> 1225.98 | AB47: 504 | AC47: =AB47-I47 -> 0 | AD47: ok | AE47: 9543B-S001-3L | AF47: 已入 | AG47: 系统出单 | AH47: 94154-1.22 | AO47: =I47 -> 504 | AT47: =I47 -> 504 | BW47: 增加移印布标内容 | BY47: =I47 -> 504 | CB47: =I47 -> 504 | CD47: =SUM(BX47:CA47) -> 504 | CE47: =I47-CD47 -> 0
A48: 45632 | B48: AMAZON UK | C48: 英国 | D48: 4500153435 | E48: Amazon DE: PO#4HNJ87AR | F48: 4500153435-80 | G48: 9543A-S001-PKC | H48: 仓鼠 1只胶袋装 | I48: 504 | J48: 0 | K48: 24 | L48: =I48/K48 -> 21 | M48: 45681 | N48: 45677 | P48: PASS | Q48: 2/7-2/11出 | R48: 空白外箱（加印带Zuru字样的最新logo，除了邮包盒直接做外箱的产品） + SSCC LABEL一张, 无箱唛. | U48: UPC+IT翻4500120504+ZURU邮箱贴纸翻4500149035）；+1/10-胶袋UPC贴纸 | V48: 12/18-外箱贴纸 | X48: 日期码格式：ZURU INC(BVI) 标准格式 日期：按实际生产日期 Packaging Info: Amazon UK/DE (92104HG/9279B/9296A/9543A) 4. 9543A: 9543A 24pcs/ctn, no inner, blue; MA 3L（9L warning）C版收缩膜+2张贴纸(1张#UPC, 1张IT sorting label<(>,<)> 参考翻单PO#4500120504)+MA 5L (9L warning) A 说明书 +1张ZURU邮箱贴纸（参考翻单PO#4500149035）+Polybag(含防窒息5L警示语+塑料循环标) +1张贴纸(UPC#，参考翻单PO#4500120504，贴在p olybag)； 5. ZURU验货最迟不得晚于2025/1/27 Remark: 1.空白外箱（加印带Zuru字样的最新logo，除了邮包盒直接做外箱的产品） + SSCC LABEL一张, 无箱唛. (SSCC LABEL贴在外箱正面的正中间，贴一面即可,贴纸离外箱边距必须至少3.2CM),SSCC贴纸由工厂直接跟勤得采购或者工厂自行采购，每一张SSCC Label都是唯一 且有不同流水及条码，且需要检查条码是否能正常扫描，另外，此贴纸印刷不可出现模糊，溢出及粘胶不牢易脱落等现象，如工厂不按此要求导致贴纸有任何问题产 生的罚款将由工厂承担一切责任 。’MADE IN CHINA 外箱只印一正一侧。 2. 出往UK的产品+包装务必打上UKCA logo ，否则客人会退货且当地会有罚款。 3.订单必须经过ZURU QC验货并且通过后方可出货。 4.法国订单要求包装不使用矿物油，请按要求提供以下其中一份文件再出货 ，产品出到法国被相关部门抽检出现包装不符合此要求的，供应商需要为此承担责任， 故此请严格把关 。 -油墨物质""由1 ~ 7个芳香环组成的MOAH""的包装检测报告，要求限值≤1.0%; -包装材料清单，包括包装油墨或物质的信息 -油墨制造商的证书。 5 . 每一批次出货只能有一个生产日期，不可多个生产日期混在同一批次出货；且邮包盒上必须统一加上日期码； 6. 涉及到相关款式会有闪粉的或 者微塑料的，请统一默认出无闪粉或者不含微塑料 版本; 7 .邮包盒及外箱封箱必须是工字型封箱方式； 8 . 5 Surprise or Mini Brands涉及包装是2个及2个以上的球入PVC桶包装时，单个球上若有UPC#或者EAN#，请用白色贴纸覆盖住； | Y48: Crystal Chen | Z48: 2.4325 | AA48: =I48*Z48 -> 1225.98 | AB48: 504 | AC48: =AB48-I48 -> 0 | AD48: ok | AE48: 9543A-S001-3L | AF48: 已入 | AG48: 系统出单 | AH48: 94210-2.11 | AO48: =I48 -> 504 | AT48: =I48 -> 504 | BW48: 增加移印布标内容 | BX48: =I48 -> 504 | CB48: =SUM(BX48:CA48) -> 504 | CD48: =SUM(BX48:CA48) -> 504 | CE48: =I48-CD48 -> 0
A49: 45652 | D49: ZMPO24996 | G49: 9543-S001 | H49: 仓鼠 | I49: 600 | J49: 0 | K49: 24 | L49: =I49/K49 -> 25 | M49: 45659 | N49: 45656 | P49: 完成 | X49: 大货版/只需要仓鼠球球壳和里面白色的底托 备注：收到样品订单后尽快安排 ，谢谢！ | Y49: Angus | Z49: 0 | AA49: =I49*Z49 -> 0 | AB49: 600 | AE49: * | AF49: 过渡 | CB49: =I49 -> 600
A50: 45560 | B50: SUBURBIA S DE R. L. DE C. V. | C50: 墨西哥 | D50: 4500145574 | F50: 4500145574-30 | G50: 9543GQ1-S001 | H50: 仓鼠 | I50: 506 | J50: 0 | K50: 22 | L50: =I50/K50 -> 23 | M50: 45649 | N50: 45673 | P50: PASS | Q50: 1/17出 | R50: .外箱只需四面印Zuru logo | U50: 1/2-进口商贴纸+价标贴纸+说明书贴纸 | V50: 11/29-外箱贴纸 | X50: 日期码格式：ZURU INC(BVI) 标准格式 日期：按实际生产日期 Packaging Info: 9543GQ1: MA 3L UPC包装+MA PDQ包装+MA多语说明书+进口商贴纸+价标贴纸+说明书贴纸 1.外箱只需四面印Zuru logo，再加2张贴纸，1张Hu贴纸（条码贴），1张ASN贴纸（尺寸6.5cm*6.3cm,潘通色号2597C），都贴于侧唛，只需贴1面(备注HU'S <(>& <)> ASN贴纸客供） 2. 一个外箱对应一个HU’S(条形码),不可以混条码包装 3.含有说明书需要增加说明书贴纸 4.价格贴纸覆盖原有彩盒的条形码 Remark: 9543GQ1:2PCS AAA Batteries(Not Include) bule/purple/pink/orange =5:6:6:5; 此单有监柜要求，需要每款多准备一套完整物料，用于监柜，不可以随大货走 | Y50: Zoe Luo | Z50: 2.8179 | AA50: =I50*Z50 -> 1425.8574 | AB50: =462+44 -> 506 | AC50: =AB50-I50 -> 0 | AD50: ok | AE50: 9543GQ1-S001-3L | AF50: 已入 | AG50: 系统出单 | AH50: 94085-1.17 | AO50: =I50 -> 506 | AT50: =I50 -> 506 | BA50: =I50/11 -> 46 | BW50: 增加移印布标内容 | BX50: =I50/22*5 -> 115 | BY50: =I50/22*6 -> 138 | BZ50: =I50/22*6 -> 138 | CA50: =I50/22*5 -> 115 | CB50: =I50 -> 506 | CC50: =I50/11 -> 46 | CD50: =SUM(BX50:CA50) -> 506 | CE50: =I50-CD50 -> 0
A51: 45628 | B51: TOYS "R" US – JAPAN, LTD | C51: 日本 | D51: 4500153105 | E51: 47:0003109948 | F51: 4500153105-10 | G51: 9543GQ1-S001 | H51: 仓鼠 | I51: 616 | J51: 0 | K51: 22 | L51: =I51/K51 -> 28 | M51: 45691 | N51: 45687 | P51: PASS | Q51: 2/17出 | R51: 12/2收到 | U51: 12/4-日语贴纸 | X51: 日期码格式：ZURU INC(BVI) 标准格式 日期：按实际生产日期 Packaging Info: 9543GQ1： MA 1L PKG D版包装+MA 说明书+1张日语贴纸（贴纸AW待提供）（位置图翻单4500122471） (9543GQ1)PDQ: MA 1L PDQ PKG B 版包装 Remark: 9543GQ1的大货的产品品质跟内容需跟4500129603这单一致，有任何更新（含包装）需提前告知。 | Y51: Doris Shou | Z51: 2.8179 | AA51: =I51*Z51 -> 1735.8264 | AB51: 616 | AC51: =AB51-I51 -> 0 | AD51: ok | AE51: 9543GQ1-S001 | AF51: 已入 | AG51: 系统出单 | AH51: 94235-2.13 | AL51: =I51 -> 616 | AT51: =I51 -> 616 | AX51: =I51/11 -> 56 | BW51: 增加移印布标内容 | BX51: =I51/22*5 -> 140 | BY51: =I51/22*6 -> 168 | BZ51: =I51/22*6 -> 168 | CA51: =I51/22*5 -> 140 | CB51: =I51 -> 616 | CC51: =I51/11 -> 56 | CD51: =SUM(BX51:CA51) -> 616 | CE51: =I51-CD51 -> 0
A52: 45601 | B52: SAINSBURY'S SUPERMARKET LTD | C52: 英国 | D52: 4500150157 | E52: PO#2700206-SK U#143951840 | F52: 4500150157-10 | G52: 9543GQ3-S001 | H52: 仓鼠 | I52: 1498 | J52: 0 | K52: 7 | L52: =I52/K52 -> 214 | M52: 45695 | N52: 45691 | P52: PASS | Q52: 2/11出 | R52: 12/16收到 | U52: 无 | X52: 日期码格式：ZURU INC(BVI) 标准格式 日期：按实际生产日期 Packaging Info: -9543GQ3: MA-1L包装配套+ ZURU客版PDQ（2Facing7pcs/Gravity PDQ; 参考翻单PO#4500123744） 产品信息: 7product+demo;2pcs *AAA battery not Include; Integral single ratio=bule/purple/pink/orange =1:1:1:1 -订单对应客户1个PO号 ，备注有显示 Remark: *胶带最少宽度要保证6.0CM,厚度最少0.05毫米,外箱不可以打钉/扎带；以工字型封箱； *如果重量超过5KGS，箱唛需加黄色警示图标志 ，有疑问请与ZURU跟单同事联系,十分重要！ *订单出英国，请注意检查产品及包装应带UKCA图标，包装显示ZURU UK LTD信息，QC同事请查核，如有问题与跟单确认。 *MA版本按工厂现有最新库存即可，订单出英国，请注意检查产品及包装应带UKCA图标，包装显示ZURU UK LTD信息，QC同事请查核，如有问题与跟单确认。 *生产日期按实际的（法定工作日），按ZURU标准格式即可 ，但是请知悉包装日期码需要早于或者等于外箱日期码 ，不能晚于外箱日期码 *请注意所有订单都需要经过ZURU QC验货并且通过后方可出货 *产品条码以订单显示为准 ，请安排生产前先核对再生产或者与Sherry 复核再安排 。 *外箱上的条码请确保清晰可扫描 ，否则到目的仓无法扫描入仓由工厂承担责任 。 *所有产品按符合欧洲标准走货，需要是不含微塑料版本 。 *涉及到硼的，请使用低硼版本 *客户不接受PVC材质 | Y52: Zoe Chen | Z52: 2.8304 | AA52: =I52*Z52 -> 4239.9392 | AB52: 1498 | AC52: =AB52-I52 -> 0 | AD52: 无 | AE52: 9543GQ3-S001 | AF52: 已入 | AG52: 系统出单 | AH52: 94208-2.11 | AL52: =I52 -> 1498 | AT52: =I52 -> 1498 | BG52: =I52/7 -> 214 | BW52: 增加移印布标内容 | BX52: =I52/4 -> 374.5 | BY52: =I52/4 -> 374.5 | BZ52: =I52/4 -> 374.5 | CA52: =I52/4 -> 374.5 | CB52: =I52 -> 1498 | CC52: =I52/7 -> 214 | CD52: =SUM(BX52:CA52) -> 1498 | CE52: =CD52-I52 -> 0
A53: 45614 | B53: ARGOS LIMITED | C53: 英国 | D53: 4500150417 | E53: PO#361486-SKU #3428775 | F53: 4500150417-10 | G53: 9543-S001 | H53: 仓鼠 | I53: 1008 | J53: 0 | K53: 24 | L53: =I53/K53 -> 42 | M53: 45702 | N53: 45698 | P53: PASS | Q53: 2/17出 | R53: 12/3收到 | U53: 12/6客人白色Cat.label 1张覆盖ZURU条码 | X53: 日期码格式：ZURU INC(BVI) 标准格式 日期：按实际生产日期 Packaging Info: 9543: MA -1L 包装+客人白色Cat.label 1张覆盖ZURU条码 注意Cat.label (要求易撕类贴纸，但是粘性不能过低），同时此贴纸每个订单都是不相同的(会显示客户对应的订单号），切勿翻旧订单购买，该贴纸由工厂自行 购买。 订单对应客户1个PO号 ，备注有显示 Remark: *MA包装按最新版本安排即可 *包装日期码按ZURU格式即可，请确保不迟于外箱日期码，可等于或者早于外箱日期码，必须为法定工作日。 *外箱尺寸任何一条边长度超过75cm或者每箱重量超过10KG,需要在外箱上加三脚架符号，有问题请与ZURU跟单同事核实。 *订单必须经过ZURU QC验货并且通过后方可出货。 *订单出英国，请注意检查产品及包装应带UKCA图标，包装显示ZURU UK LTD信息，QC同事请查核，如有问题与跟单确认。 *条码扫描会显示客户7位数产品号 ，忽略订单显示的MA条码 *所有产品按符合欧洲标准走货，需要是不含微塑料版本 。 *涉及到硼的，请使用低硼版本 *客户不接受PVC材质包装 | Y53: Zoe Chen | Z53: 2.5816 | AA53: =I53*Z53 -> 2602.2528 | AB53: 1008 | AC53: =AB53-I53 -> 0 | AD53: ok | AE53: 9543-S001 | AF53: 已入 | AG53: 系统出单 | AH53: 94267-2.17 | AL53: =I53 -> 1008 | AT53: =I53 -> 1008 | BW53: 增加移印布标内容 | BX53: =I53/4 -> 252 | BY53: =I53/4 -> 252 | BZ53: =I53/4 -> 252 | CA53: =I53/4 -> 252 | CB53: =I53 -> 1008 | CD53: =SUM(BX53:CA53) -> 1008 | CE53: =I53-CD53 -> 0
A54: 45615 | B54: DD’S DISCOUNTS | C54: 美国 | D54: 4500151558 | E54: 70054059 | F54: 4500151558-10 | G54: 9543GQ1-S001 | H54: 仓鼠 | I54: 616 | J54: 0 | K54: 22 | L54: =I54/K54 -> 28 | M54: 45705 | N54: 45701 | P54: PASS | Q54: 3/21出 | R54: ROSS指定箱唛格式 | U54: 无 | V54: 1/3-客供价格贴纸 | X54: 日期码格式： 标准格式 日期：按实际生产日期 Packaging Info: 1.ZURU MA UPC 现有版本包装 + 客供价格贴纸，出口美国 , 优先使用MA 1L 最新版本 。 Remark: 1.ZURU MA UPC 现有版本包装 + 客供价格贴纸，出口美国 , 优先使用MA 1L 最新版本 。 2.价格贴纸位于包装正面右下角，不挡住重要信息即可，可适当调整 ，价格贴纸由跟单提供。 3.标准日期码格式，产品和包装必须有日期码 。 4.同个产品同个货期不可出现不同的包装。 5. 跟单提供ROSS通用的箱唛模版，工厂按实际45 PO上客户PO/Item号/装箱数 提供箱唛排版来确认 | Y54: Taylor Liao | Z54: 2.8179 | AA54: =I54*Z54 -> 1735.8264 | AB54: 616 | AC54: =AB54-I54 -> 0 | AD54: ok | AE54: 9543GQ1-S001 | AF54: 已入 | AG54: 系统出单 | AH54: ZB00018-3.20 | AL54: =I54 -> 616 | AT54: =I54 -> 616 | AX54: =I54/11 -> 56 | BW54: 增加移印布标内容 | BX54: =I54/22*5 -> 140 | BY54: =I54/22*6 -> 168 | BZ54: =I54/22*6 -> 168 | CA54: =I54/22*5 -> 140 | CB54: =I54 -> 616 | CC54: =I54/11 -> 56 | CD54: =SUM(BX54:CA54) -> 616 | CE54: =I54-CD54 -> 0
A55: 45643 | B55: Toynova GmbH | C55: 德国 | D55: 4500154198 | F55: 4500154198-10 | G55: 9543A-S001 | H55: 仓鼠 | I55: 240 | J55: 0 | K55: 24 | L55: =I55/K55 -> 10 | M55: 45695 | N55: 45691 | P55: PASS | Q55: 2/11出 | R55: 12/18收到 | U55: EAN条码贴纸翻4500137714 | X55: 日期码格式：ZURU INC(BVI) 标准格式 日期：按实际生产日期 Packaging Info: 9543A：MA 1L 收缩膜+EAN条码贴纸(翻单：4500137714）+MA 5L说明书 Remark: "1.需要在完货当天提供验货图片供客人放货 2.此单出德国，需准时出货 3.此单出欧洲需要出无闪粉版本 4.此单符合欧洲 8 PAH 标准即可" | Y55: Amy Xiao | Z55: 2.5958 | AA55: =I55*Z55 -> 622.992 | AB55: 240 | AC55: =AB55-I55 -> 0 | AD55: OK | AE55: 9543A-S001-MTS | AF55: 已入 | AG55: 系统出单 | AH55: 94209-2.11 | AL55: =I55 -> 240 | AT55: =I55 -> 240 | BW55: 增加移印布标内容 | BX55: =I55 -> 240 | CB55: =I55 -> 240 | CD55: =SUM(BX55:CA55) -> 240 | CE55: =I55-CD55 -> 0
A56: 45643 | B56: Toynova GmbH | C56: 德国 | D56: 4500154198 | F56: 4500154198-20 | G56: 9543B-S001 | H56: 仓鼠 | I56: 288 | J56: 0 | K56: 24 | L56: =I56/K56 -> 12 | M56: 45695 | N56: 45691 | P56: PASS | Q56: 2/11出 | R56: 12/18收到 | U56: EAN条码贴纸翻4500137714 | X56: 日期码格式：ZURU INC(BVI) 标准格式 日期：按实际生产日期 Packaging Info: 9543B：MA 1L 收缩膜+EAN条码贴纸(翻单：4500137714）+MA 5L说明书 Remark: "1.需要在完货当天提供验货图片供客人放货 2.此单出德国，需准时出货 3.此单出欧洲需要出无闪粉版本 4.此单符合欧洲 8 PAH 标准即可" | Y56: Amy Xiao | Z56: 2.5958 | AA56: =I56*Z56 -> 747.5904 | AB56: 288 | AC56: =AB56-I56 -> 0 | AD56: OK | AE56: 9543B-S001-MTS | AF56: 已入 | AG56: 系统出单 | AH56: 94209-2.11 | AL56: =I56 -> 288 | AT56: =I56 -> 288 | BW56: 增加移印布标内容 | BY56: =I56 -> 288 | CB56: =I56 -> 288 | CD56: =SUM(BX56:CA56) -> 288 | CE56: =I56-CD56 -> 0
A57: 45643 | B57: Toynova GmbH | C57: 德国 | D57: 4500154198 | F57: 4500154198-30 | G57: 9543D-S001 | H57: 仓鼠 | I57: 288 | J57: 0 | K57: 24 | L57: =I57/K57 -> 12 | M57: 45695 | N57: 45691 | P57: PASS | Q57: 2/11出 | R57: 12/18收到 | U57: EAN条码贴纸翻4500137714 | X57: 日期码格式：ZURU INC(BVI) 标准格式 日期：按实际生产日期 Packaging Info: 9543D：MA 1L 收缩膜+EAN条码贴纸(翻单：4500137714）+MA 5L说明书 Remark: "1.需要在完货当天提供验货图片供客人放货 2.此单出德国，需准时出货 3.此单出欧洲需要出无闪粉版本 4.此单符合欧洲 8 PAH 标准即可" | Y57: Amy Xiao | Z57: 2.5958 | AA57: =I57*Z57 -> 747.5904 | AB57: 288 | AC57: =AB57-I57 -> 0 | AD57: OK | AE57: 9543D-S001-MTS | AF57: 已入 | AG57: 系统出单 | AH57: 94209-2.11 | AL57: =I57 -> 288 | AT57: =I57 -> 288 | BW57: 增加移印布标内容 | BZ57: =I57 -> 288 | CB57: =I57 -> 288 | CD57: =SUM(BX57:CA57) -> 288 | CE57: =I57-CD57 -> 0
A58: 45643 | B58: Toynova GmbH | C58: 德国 | D58: 4500154198 | F58: 4500154198-40 | G58: 9543E-S001 | H58: 仓鼠 | I58: 408 | J58: 0 | K58: 24 | L58: =I58/K58 -> 17 | M58: 45695 | N58: 45691 | P58: PASS | Q58: 2/11出 | R58: 12/18收到 | U58: EAN条码贴纸翻4500137714 | X58: 日期码格式：ZURU INC(BVI) 标准格式 日期：按实际生产日期 Tracking Code: Packaging Info: 9543E：MA 1L 收缩膜+EAN条码贴纸(翻单：4500137714）+MA 5L说明书 Remark: "1.需要在完货当天提供验货图片供客人放货 2.此单出德国，需准时出货 3.此单出欧洲需要出无闪粉版本 4.此单符合欧洲 8 PAH 标准即可" | Y58: Amy Xiao | Z58: 2.5958 | AA58: =I58*Z58 -> 1059.0864 | AB58: 408 | AC58: =AB58-I58 -> 0 | AD58: OK | AE58: 9543E-S001-MTS | AF58: 已入 | AG58: 系统出单 | AH58: 94209-2.11 | AL58: =I58 -> 408 | AT58: =I58 -> 408 | BW58: 增加移印布标内容 | CA58: =I58 -> 408 | CB58: =I58 -> 408 | CD58: =SUM(BX58:CA58) -> 408 | CE58: =I58-CD58 -> 0
A59: 45651 | B59: VEDES Grosshandel | C59: 德国 | D59: 4500153900 | E59: 4500183563 | F59: 4500153900-10 | G59: 9543GQ1-S001 | H59: 仓鼠 | I59: 814 | J59: 0 | K59: 22 | L59: =I59/K59 -> 37 | M59: 45706 | N59: 45702 | P59: PASS | Q59: 2/24出 | R59: 12/25收到- 外箱上下需加隔板 | U59: EAN条码贴纸(翻4500117969)+PDQ条码贴纸+客版黑白WEEE声明说明书纸(翻#4500144419) | W59: 183563/02/2025 | X59: 日期码格式：183563/02/2025 日期： Packaging Info: 9543GQ1：最新MA 3LPDQ+ 3L+9L包装+5L+9L说明书+EAN条码贴纸(翻#4500117969)+1张PDQ条码贴纸(翻#4500144419)+客版黑白WEEE声明说明书纸(翻#4500144419) EAN: 4894680026995, 请先检查条码是否正确再安排做货 Remark: 1，出欧洲，微塑料需符合法规 2，产品，包装，外箱Batch code:183563/02/2025，另外包装上的Batch code位置图在EAN条码位置旁边 如产品位置太小印不下日期码则按照标准即可； 如产品上有足够位置，请把每个item的款号#也印上，如无位置则可不加。 3，塑料袋的厚度（单层）应在0.038～0.042mm之间,如含吸塑材料必须是非邻苯二甲酸酯材料或塑料包装编码的PET 3. 外箱上下需加隔板，以保护开箱时不被划破产品。外箱不可打釘及打帶。 每箱不得超过5立方英尺，重量不得超过15公斤。 4. 封箱胶带不能为PVC材质，需为PP 或者 OPP胶或者non-phthalate材料 5. 此单出货前需要提供两套样品给客人确认放货，需准时寄出避免影响出货。 6. 此单需准时出货，推期会有罚款 7. 任何彩盒及陳列盒一定要用文書膠紙貼於開口的位置 , 不能使用封箱膠紙 8. 外箱不可打釘及打帶 9. 标准配比 | Y59: Shirley Zhou | Z59: 2.7825 | AA59: =I59*Z59 -> 2264.955 | AB59: 814 | AC59: =AB59-I59 -> 0 | AD59: ok | AE59: 9543GQ1-S001-3L | AF59: 已入 | AG59: 系统出单 | AH59: 94316-2.21 | AO59: =I59 -> 814 | AT59: =I59 -> 814 | BA59: =I59/11 -> 74 | BW59: 增加移印布标内容 | BX59: =I59/22*5 -> 185 | BY59: =I59/22*6 -> 222 | BZ59: =I59/22*6 -> 222 | CA59: =I59/22*5 -> 185 | CB59: =I59 -> 814 | CC59: =I59/11 -> 74 | CD59: =SUM(BX59:CA59) -> 814 | CE59: =I59-CD59 -> 0
A60: 45617 | B60: MTA Trade | C60: 哈萨克斯坦 | D60: 4500151799 | F60: 4500151799-50 | G60: 9543GQ1-S001 | H60: 仓鼠 | I60: 396 | J60: 0 | K60: 22 | L60: =I60/K60 -> 18 | M60: 45705 | N60: 45701 | O60: 2/21出 | P60: PASS | Q60: 2/18出 | R60: 11/22收到 | U60: 进口商贴纸翻4500142077 | X60: 日期码格式：ZURU INC(BVI) 标准格式 日期：按实际生产日期 Tracking Code: Packaging Info: 9543GQ1：MA 1L 收缩膜+进口商贴纸（翻4500142077）； MA 说明书/指南（如有）；MA PDQ; Remark: 标准配比 | Y60: Ann Zhang | Z60: 2.7825 | AA60: =I60*Z60 -> 1101.87 | AB60: 396 | AC60: =AB60-I60 -> 0 | AD60: ok | AE60: 9543GQ1-S001 | AF60: 已入 | AG60: 系统出单 | AH60: 94747-4.10 | AL60: =I60 -> 396 | AT60: =I60 -> 396 | AX60: =I60/11 -> 36 | BW60: 增加移印布标内容 | BX60: =I60/22*5 -> 90 | BY60: =I60/22*6 -> 108 | BZ60: =I60/22*6 -> 108 | CA60: =I60/22*5 -> 90 | CB60: =I60 -> 396 | CC60: =I60/11 -> 36 | CD60: =SUM(BX60:CA60) -> 396 | CE60: =I60-CD60 -> 0
A61: 45652 | B61: VEDES Grosshandel | C61: 德国 | D61: 4500154798 | E61: Amazon FR:27YNNSMM | F61: 4500154798-90 | G61: 9543A-S001-PKC | H61: 仓鼠 1只胶袋装 | I61: 504 | J61: 0 | K61: 24 | L61: =I61/K61 -> 21 | M61: 45706 | N61: 45702 | O61: 增加增加胶袋 | P61: PASS | Q61: 2/27-3/3出 | R61: 空白外箱（加印带Zuru字样的最新logo，除了邮包盒直接做外箱的产品） + SSCC LABEL一张, 无箱唛，MADE IN CHINA 外箱只印一正一侧。 | U61: UPC+IT环保标翻单4500120504ES环保标翻4500151280；ZURU邮箱+1/10-胶袋UPC贴纸 | V61: 1/3-外箱贴纸 | X61: 日期码格式：ZURU INC(BVI) 标准格式 日期：按实际生产日期 Packaging Info: Amazon UK(71126/9543A/9297G/71109B)/FR(9543A)/DE(9543A/71126) 1. 9543A：9543A 24pcs/ctn, no inner, blue; MA 3L（9L warning）C版收缩膜+3张贴纸(1张#UPC，1张IT环保标，参考翻单PO#4500120504；1张ES环保标, 参考翻单PO#4500151280；ZURU邮箱)+MA 5L(9L warning) A 说明书+Polybag(含防窒息5L警示语+塑料循环标，参考翻单PO#4500153435) +1张贴纸(UPC#，参考翻单PO#4500120504，贴在polybag)； 5. 最迟验货不得晚于2025/02/18; Remark: 1.空白外箱（加印带Zuru字样的最新logo，除了邮包盒直接做外箱的产品） + SSCC LABEL一张, 无箱唛，MADE IN CHINA 外箱只印一正一侧。箱唛资料按照给定的 标准去做即可，无需发回我方再行审批(新标准将另行通知)。 (SSCC LABEL竖贴在外箱正面的正中间，贴一面即可,贴纸离外箱边距必须至少3.2CM。如竖贴无法满足要求，则横贴。如横贴也无法满足要求，则竖贴，遮到ZURU lo go无影响), SSCC贴纸由工厂直接跟勤得采购或者工厂自行采购，每一张SSCC Label都是唯一且有不同流水及条码，且需要检查条码是否能正常扫描，另外，此贴纸 印刷不可出现模糊，溢出及粘胶不牢易脱落等现象，如工厂不按此要求导致贴纸有任何问题产生的罚款将由工厂承担一切责任 。 2.出往UK的产品+包装务必打上UKCA logo ，否则客人会退货且当地会有罚款。 3.订单必须经过ZURU QC验货并且通过后方可出货。 4.法国订单要求包装不使用矿物油，请按要求提供以下其中一份文件再出货 ，产品出到法国被相关部门抽检出现包装不符合此要求的，供应商需要为此承担责任， 故此请严格把关。 -油墨物质""由1 ~ 7个芳香环组成的MOAH""的包装检测报告，要求限值≤1.0%； -包装材料清单，包括包装油墨或物质的信息； -油墨制造商的证书； 5.每一批次出货只能有一个生产日期，不可多个生产日期混在同一批次出货；且邮包盒上必须统一加上日期码；外箱对于日期码没有硬性规定； 6.涉及到相关款式会有闪粉的或者微塑料的，请统一默认出无闪粉或者不含微塑料版本； 7.邮包盒及外箱封箱必须是工字型封箱方式； 8.5 Surprise or Mini Brands涉及包装是2个及2个以上的球入PVC桶包装时，单个球上若有UPC#或者EAN#，请用白色贴纸覆盖住； | Y61: Crystal Chen | Z61: 2.4325 | AA61: =I61*Z61 -> 1225.98 | AB61: 504 | AC61: =AB61-I61 -> 0 | AD61: ok | AE61: 9543A-S001-3L | AF61: 已入 | AG61: 系统出单 | AH61: 94424-3.4 | AO61: =I61 -> 504 | AT61: =I61 -> 504 | BW61: 增加移印布标内容 | BX61: =I61 -> 504 | CB61: =SUM(BX61:CA61) -> 504 | CD61: =SUM(BX61:CA61) -> 504 | CE61: =I61-CD61 -> 0
A62: 45652 | B62: VEDES Grosshandel | C62: 德国 | D62: 4500154798 | E62: Amazon DE:5N9BLBJF | F62: 4500154798-100 | G62: 9543A-S001-PKC | H62: 仓鼠 1只胶袋装 | I62: 504 | J62: 0 | K62: 24 | L62: =I62/K62 -> 21 | M62: 45706 | N62: 45702 | O62: 增加增加胶袋 | P62: PASS | Q62: 2/27-3/3出 | R62: 空白外箱（加印带Zuru字样的最新logo，除了邮包盒直接做外箱的产品） + SSCC LABEL一张, 无箱唛，MADE IN CHINA 外箱只印一正一侧。 | U62: UPC+IT环保标翻单4500120504ES环保标翻4500151280；ZURU邮箱+1/10-胶袋UPC贴纸 | V62: 1/3-外箱贴纸 | X62: 日期码格式：ZURU INC(BVI) 标准格式 日期：按实际生产日期 Packaging Info: Amazon UK(71126/9543A/9297G/71109B)/FR(9543A)/DE(9543A/71126) 1. 9543A：9543A 24pcs/ctn, no inner, blue; MA 3L（9L warning）C版收缩膜+3张贴纸(1张#UPC，1张IT环保标，参考翻单PO#4500120504；1张ES环保标, 参考翻单PO#4500151280；ZURU邮箱)+MA 5L(9L warning) A 说明书+Polybag(含防窒息5L警示语+塑料循环标，参考翻单PO#4500153435) +1张贴纸(UPC#，参考翻单PO#4500120504，贴在polybag)； 5. 最迟验货不得晚于2025/02/18; Remark: 1.空白外箱（加印带Zuru字样的最新logo，除了邮包盒直接做外箱的产品） + SSCC LABEL一张, 无箱唛，MADE IN CHINA 外箱只印一正一侧。箱唛资料按照给定的 标准去做即可，无需发回我方再行审批(新标准将另行通知)。 (SSCC LABEL竖贴在外箱正面的正中间，贴一面即可,贴纸离外箱边距必须至少3.2CM。如竖贴无法满足要求，则横贴。如横贴也无法满足要求，则竖贴，遮到ZURU lo go无影响), SSCC贴纸由工厂直接跟勤得采购或者工厂自行采购，每一张SSCC Label都是唯一且有不同流水及条码，且需要检查条码是否能正常扫描，另外，此贴纸 印刷不可出现模糊，溢出及粘胶不牢易脱落等现象，如工厂不按此要求导致贴纸有任何问题产生的罚款将由工厂承担一切责任 。 2.出往UK的产品+包装务必打上UKCA logo ，否则客人会退货且当地会有罚款。 3.订单必须经过ZURU QC验货并且通过后方可出货。 4.法国订单要求包装不使用矿物油，请按要求提供以下其中一份文件再出货 ，产品出到法国被相关部门抽检出现包装不符合此要求的，供应商需要为此承担责任， 故此请严格把关。 -油墨物质""由1 ~ 7个芳香环组成的MOAH""的包装检测报告，要求限值≤1.0%； -包装材料清单，包括包装油墨或物质的信息； -油墨制造商的证书； 5.每一批次出货只能有一个生产日期，不可多个生产日期混在同一批次出货；且邮包盒上必须统一加上日期码；外箱对于日期码没有硬性规定； 6.涉及到相关款式会有闪粉的或者微塑料的，请统一默认出无闪粉或者不含微塑料版本； 7.邮包盒及外箱封箱必须是工字型封箱方式； 8.5 Surprise or Mini Brands涉及包装是2个及2个以上的球入PVC桶包装时，单个球上若有UPC#或者EAN#，请用白色贴纸覆盖住； | Y62: Crystal Chen | Z62: 2.4325 | AA62: =I62*Z62 -> 1225.98 | AB62: 504 | AC62: =AB62-I62 -> 0 | AD62: ok | AE62: 9543A-S001-3L | AF62: 已入 | AG62: 系统出单 | AH62: 94424-3.4 | AO62: =I62 -> 504 | AT62: =I62 -> 504 | BW62: 增加移印布标内容 | BX62: =I62 -> 504 | CB62: =SUM(BX62:CA62) -> 504 | CD62: =SUM(BX62:CA62) -> 504 | CE62: =I62-CD62 -> 0
A63: 45652 | B63: VEDES Grosshandel | C63: 德国 | D63: 4500154798 | E63: Amazon UK:5HVCIB6O | F63: 4500154798-110 | G63: 9543A-S001-PKC | H63: 仓鼠 1只胶袋装 | I63: 504 | J63: 0 | K63: 24 | L63: =I63/K63 -> 21 | M63: 45706 | N63: 45702 | O63: 增加增加胶袋 | P63: PASS | Q63: 3/1-3/5出 | R63: 空白外箱（加印带Zuru字样的最新logo，除了邮包盒直接做外箱的产品） + SSCC LABEL一张, 无箱唛，MADE IN CHINA 外箱只印一正一侧。 | U63: UPC+IT环保标翻单4500120504ES环保标翻4500151280；ZURU邮箱+1/10-胶袋UPC贴纸 | V63: 1/3-外箱贴纸 | X63: 日期码格式：ZURU INC(BVI) 标准格式 日期：按实际生产日期 Packaging Info: Amazon UK(71126/9543A/9297G/71109B)/FR(9543A)/DE(9543A/71126) 1. 9543A：9543A 24pcs/ctn, no inner, blue; MA 3L（9L warning）C版收缩膜+3张贴纸(1张#UPC，1张IT环保标，参考翻单PO#4500120504；1张ES环保标, 参考翻单PO#4500151280；ZURU邮箱)+MA 5L(9L warning) A 说明书+Polybag(含防窒息5L警示语+塑料循环标，参考翻单PO#4500153435) +1张贴纸(UPC#，参考翻单PO#4500120504，贴在polybag)； 5. 最迟验货不得晚于2025/02/18; Remark: 1.空白外箱（加印带Zuru字样的最新logo，除了邮包盒直接做外箱的产品） + SSCC LABEL一张, 无箱唛，MADE IN CHINA 外箱只印一正一侧。箱唛资料按照给定的 标准去做即可，无需发回我方再行审批(新标准将另行通知)。 (SSCC LABEL竖贴在外箱正面的正中间，贴一面即可,贴纸离外箱边距必须至少3.2CM。如竖贴无法满足要求，则横贴。如横贴也无法满足要求，则竖贴，遮到ZURU lo go无影响), SSCC贴纸由工厂直接跟勤得采购或者工厂自行采购，每一张SSCC Label都是唯一且有不同流水及条码，且需要检查条码是否能正常扫描，另外，此贴纸 印刷不可出现模糊，溢出及粘胶不牢易脱落等现象，如工厂不按此要求导致贴纸有任何问题产生的罚款将由工厂承担一切责任 。 2.出往UK的产品+包装务必打上UKCA logo ，否则客人会退货且当地会有罚款。 3.订单必须经过ZURU QC验货并且通过后方可出货。 4.法国订单要求包装不使用矿物油，请按要求提供以下其中一份文件再出货 ，产品出到法国被相关部门抽检出现包装不符合此要求的，供应商需要为此承担责任， 故此请严格把关。 -油墨物质""由1 ~ 7个芳香环组成的MOAH""的包装检测报告，要求限值≤1.0%； -包装材料清单，包括包装油墨或物质的信息； -油墨制造商的证书； 5.每一批次出货只能有一个生产日期，不可多个生产日期混在同一批次出货；且邮包盒上必须统一加上日期码；外箱对于日期码没有硬性规定； 6.涉及到相关款式会有闪粉的或者微塑料的，请统一默认出无闪粉或者不含微塑料版本； 7.邮包盒及外箱封箱必须是工字型封箱方式； 8.5 Surprise or Mini Brands涉及包装是2个及2个以上的球入PVC桶包装时，单个球上若有UPC#或者EAN#，请用白色贴纸覆盖住； | Y63: Crystal Chen | Z63: 2.4325 | AA63: =I63*Z63 -> 1225.98 | AB63: 504 | AC63: =AB63-I63 -> 0 | AD63: ok | AE63: 9543A-S001-3L | AF63: 已入 | AG63: 系统出单 | AH63: 94444-3.5 | AO63: =I63 -> 504 | AT63: =I63 -> 504 | BW63: 增加移印布标内容 | BX63: =I63 -> 504 | CB63: =SUM(BX63:CA63) -> 504 | CD63: =SUM(BX63:CA63) -> 504 | CE63: =I63-CD63 -> 0
A64: 45642 | B64: AMAZON.COM.DEDC,LLC | C64: 美国 | D64: 4500153992 | E64: 2ELMN5VZ | F64: 4500153992-20 | G64: 9543A-S001 | H64: 仓鼠 | I64: 72 | J64: 0 | K64: 24 | L64: =I64/K64 -> 3 | M64: 45707 | N64: 45703 | P64: PASS | Q64: 2/21-2/27出 | R64: 12/16收到 | U64: UPC贴纸翻4500098824 | V64: 1/17-客供外箱贴纸 | X64: 日期码格式： 标准格式 日期：按实际生产日期 Packaging Info: #9543：MA 1L 加UPC贴纸，UPC贴纸跟翻单4500098824。A:193052051776。 Remark: 1.Amazon FOB订单，出口US。外箱最长边不能超过25" （超过了，case pack只能为1），不符合要求的大货，一律不接受。 2. 外箱正面印ZURU Logo+SSCC LABEL（客供贴纸), 侧面印item#（订单上显示的SKU#)+carton size(以工厂实际尺寸为准,单位: inch) +MADE IN CHINA,日期使用Z URU 标准版本 SSCC Label 显示的是客人自己的item#, SSCC Label 贴在外箱正面的正中间，贴一面即可，跟单订购，贴纸离外箱距必须至少3cm, 每一张SSCC labe l 都是唯一且有不同流水及条码的，没有损耗，绝对不可贴错 ，否则贴错或损坏一张会导致全部都错，千万要注意. SSCC 贴纸务必要在正中间(可以覆盖Logo <(>&<)> 箱唛), 否则会影响到仓库扫描识别 3.日期码使用ZURU标准版本 邮包盒上要打上日期码 LCL散货， 直接送货到CDS保税仓 | Y64: kelly/Mia | Z64: 2.5695 | AA64: =I64*Z64 -> 185.004 | AB64: 72 | AC64: =AB64-I64 -> 0 | AD64: ok | AE64: 9543A-S001-MTS | AF64: 已入 | AG64: 系统出单 | AH64: 94376-2.27 | AL64: =I64 -> 72 | AT64: =I64 -> 72 | BW64: 增加移印布标内容 | BX64: =I64 -> 72 | CB64: =I64 -> 72 | CD64: =SUM(BX64:CA64) -> 72 | CE64: =I64-CD64 -> 0
A65: 45642 | B65: AMAZON.COM.DEDC,LLC | C65: 美国 | D65: 4500154101 | E65: 57KK746V | F65: 4500154101-80 | G65: 9543B-S001 | H65: 仓鼠 | I65: 1992 | J65: 0 | K65: 24 | L65: =I65/K65 -> 83 | M65: 45707 | N65: 45703 | P65: PASS | Q65: 2/25出 | R65: 12/16收到 | U65: UPC贴纸翻4500098824 | V65: 1/17-客供外箱贴纸 | X65: 日期码格式： 标准格式 日期：按实际生产日期 Packaging Info: #9543：MA 1L 加UPC贴纸，UPC贴纸跟翻单4500098824。A:193052051776，B:193052051783。 Remark: 1. Amazon FOB订单，出口US。 2. 日期码使用ZURU标准版本。 3. 如果大货有要求入邮包盒，则对应的邮包盒上面要打上日期码。 4. 箱尺寸要求：外箱最长边不能超过25"(超过了，case pack只能为1)，不符合要求的大货，一律不接受。 5. 外箱箱唛要求： ①外箱正面印ZURU Logo+SSCC Label(客供贴纸，由跟单订购)。关于 SSCC Label 请注意： SSCC Label显示的是客人自己的item#。每一张SSCC label都是唯一且有不同流水及条码的，没有损耗，绝对不可贴错。如果贴错或损坏任何一张，都会导致全部都 错，千万要注意！SSCC Label必须贴在外箱正面的正中间位置(贴一面即可)，并且贴纸离外箱边距必须至少3cm(可以覆盖Logo<(>&<)>箱唛)，否则会影响到客户那边 仓库的扫描识别。 ②外箱侧面印item#(订单上显示的SKU#)+carton size(以工厂实际尺寸为准，单位: inch)+MADE IN CHINA，日期使用ZURU 标准版本。 6. 装柜要求：按照客户PO#装柜/箱号顺序装柜，跟单会提前给到装柜计划。 在大货生产/仓库存放时，请留意该装柜要求，以便装柜时不混乱(避免装错/装漏/找不到货号等)。 | Y65: kelly/Mia | Z65: 2.5816 | AA65: =I65*Z65 -> 5142.5472 | AB65: 1992 | AC65: =AB65-I65 -> 0 | AD65: ok | AE65: 9543B-S001-MTS | AF65: 已入 | AG65: 系统出单 | AH65: 94337-2.24 | AL65: =I65 -> 1992 | AT65: =I65 -> 1992 | BW65: 增加移印布标内容 | BY65: =I65 -> 1992 | CB65: =I65 -> 1992 | CD65: =SUM(BX65:CA65) -> 1992 | CE65: =I65-CD65 -> 0
A66: 45642 | B66: AMAZON.COM.DEDC,LLC | C66: 美国 | D66: 4500154101 | E66: 53V1YVGR | F66: 4500154101-90 | G66: 9543A-S001 | H66: 仓鼠 | I66: 48 | J66: 0 | K66: 24 | L66: =I66/K66 -> 2 | M66: 45707 | N66: 45703 | P66: PASS | Q66: 2/25出 | R66: 12/16收到 | U66: UPC贴纸翻4500098824 | V66: 1/17-客供外箱贴纸 | X66: 日期码格式： 标准格式 日期：按实际生产日期 Packaging Info: #9543：MA 1L 加UPC贴纸，UPC贴纸跟翻单4500098824。A:193052051776，B:193052051783。 Remark: 1. Amazon FOB订单，出口US。 2. 日期码使用ZURU标准版本。 3. 如果大货有要求入邮包盒，则对应的邮包盒上面要打上日期码。 4. 箱尺寸要求：外箱最长边不能超过25"(超过了，case pack只能为1)，不符合要求的大货，一律不接受。 5. 外箱箱唛要求： ①外箱正面印ZURU Logo+SSCC Label(客供贴纸，由跟单订购)。关于 SSCC Label 请注意： SSCC Label显示的是客人自己的item#。每一张SSCC label都是唯一且有不同流水及条码的，没有损耗，绝对不可贴错。如果贴错或损坏任何一张，都会导致全部都 错，千万要注意！SSCC Label必须贴在外箱正面的正中间位置(贴一面即可)，并且贴纸离外箱边距必须至少3cm(可以覆盖Logo<(>&<)>箱唛)，否则会影响到客户那边 仓库的扫描识别。 ②外箱侧面印item#(订单上显示的SKU#)+carton size(以工厂实际尺寸为准，单位: inch)+MADE IN CHINA，日期使用ZURU 标准版本。 6. 装柜要求：按照客户PO#装柜/箱号顺序装柜，跟单会提前给到装柜计划。 在大货生产/仓库存放时，请留意该装柜要求，以便装柜时不混乱(避免装错/装漏/找不到货号等)。 | Y66: kelly/Mia | Z66: 2.5958 | AA66: =I66*Z66 -> 124.5984 | AB66: 48 | AC66: =AB66-I66 -> 0 | AD66: ok | AE66: 9543A-S001-MTS | AF66: 已入 | AG66: 系统出单 | AH66: 94337-2.24 | AL66: =I66 -> 48 | AT66: =I66 -> 48 | BW66: 增加移印布标内容 | BX66: =I66 -> 48 | CB66: =I66 -> 48 | CD66: =SUM(BX66:CA66) -> 48 | CE66: =I66-CD66 -> 0
A67: 45642 | B67: AMAZON.COM.DEDC,LLC | C67: 美国 | D67: 4500154032 | E67: 5MDMZZ1L | F67: 4500154032-90 | G67: 9543B-S001 | H67: 仓鼠 | I67: 528 | J67: 0 | K67: 24 | L67: =I67/K67 -> 22 | M67: 45707 | N67: 45703 | P67: PASS | Q67: 2/21出 | R67: 12/16收到 | U67: UPC贴纸翻4500098824 | V67: 1/17-客供外箱贴纸 | X67: 日期码格式： 标准格式 日期：按实际生产日期 Packaging Info: #9543：MA 1L 加UPC贴纸，UPC贴纸跟翻单4500098824。B:193052051783。 Remark: 1. Amazon FOB订单，出口US。 2. 日期码使用ZURU标准版本。 3. 如果大货有要求入邮包盒，则对应的邮包盒上面要打上日期码。 4. 箱尺寸要求：外箱最长边不能超过25"(超过了，case pack只能为1)，不符合要求的大货，一律不接受。 5. 外箱箱唛要求： ①外箱正面印ZURU Logo+SSCC Label(客供贴纸，由跟单订购)。关于 SSCC Label 请注意： SSCC Label显示的是客人自己的item#。每一张SSCC label都是唯一且有不同流水及条码的，没有损耗，绝对不可贴错。如果贴错或损坏任何一张，都会导致全部都 错，千万要注意！SSCC Label必须贴在外箱正面的正中间位置(贴一面即可)，并且贴纸离外箱边距必须至少3cm(可以覆盖Logo<(>&<)>箱唛)，否则会影响到客户那边 仓库的扫描识别。 ②外箱侧面印item#(订单上显示的SKU#)+carton size(以工厂实际尺寸为准，单位: inch)+MADE IN CHINA，日期使用ZURU 标准版本。 6. 装柜要求：按照客户PO#装柜/箱号顺序装柜，跟单会提前给到装柜计划。 在大货生产/仓库存放时，请留意该装柜要求，以便装柜时不混乱(避免装错/装漏/找不到货号等)。 | Y67: kelly/Mia | Z67: 2.5695 | AA67: =I67*Z67 -> 1356.696 | AB67: 528 | AC67: =AB67-I67 -> 0 | AD67: ok | AE67: 9543B-S001-MTS | AF67: 已入 | AG67: 系统出单 | AH67: 94313-2.21 | AL67: =I67 -> 528 | AT67: =I67 -> 528 | BW67: 增加移印布标内容 | BY67: =I67 -> 528 | CB67: =I67 -> 528 | CD67: =SUM(BX67:CA67) -> 528 | CE67: =I67-CD67 -> 0
A68: 45642 | B68: AMAZON.COM.DEDC,LLC | C68: 美国 | D68: 4500154144 | E68: 5SZOOR9N | F68: 4500154144-90 | G68: 9543B-S001 | H68: 仓鼠 | I68: 264 | J68: 0 | K68: 24 | L68: =I68/K68 -> 11 | M68: 45707 | N68: 45703 | P68: PASS | Q68: 2/21出 | R68: 12/16收到 | U68: UPC贴纸翻4500098824 | V68: 1/17-客供外箱贴纸 | X68: 日期码格式： 标准格式 日期：按实际生产日期 Packaging Info: #9543：MA 1L 加UPC贴纸，UPC贴纸跟翻单4500098824。A:193052051776，B:193052051783。 Remark: 1. Amazon FOB订单，出口US。 2. 日期码使用ZURU标准版本。 3. 如果大货有要求入邮包盒，则对应的邮包盒上面要打上日期码。 4. 箱尺寸要求：外箱最长边不能超过25"(超过了，case pack只能为1)，不符合要求的大货，一律不接受。 5. 外箱箱唛要求： ①外箱正面印ZURU Logo+SSCC Label(客供贴纸，由跟单订购)。关于 SSCC Label 请注意： SSCC Label显示的是客人自己的item#。每一张SSCC label都是唯一且有不同流水及条码的，没有损耗，绝对不可贴错。如果贴错或损坏任何一张，都会导致全部都 错，千万要注意！SSCC Label必须贴在外箱正面的正中间位置(贴一面即可)，并且贴纸离外箱边距必须至少3cm(可以覆盖Logo<(>&<)>箱唛)，否则会影响到客户那边 仓库的扫描识别。 ②外箱侧面印item#(订单上显示的SKU#)+carton size(以工厂实际尺寸为准，单位: inch)+MADE IN CHINA，日期使用ZURU 标准版本。 6. 装柜要求：按照客户PO#装柜/箱号顺序装柜，跟单会提前给到装柜计划。 在大货生产/仓库存放时，请留意该装柜要求，以便装柜时不混乱(避免装错/装漏/找不到货号等)。 | Y68: kelly/Mia | Z68: 2.5958 | AA68: =I68*Z68 -> 685.2912 | AB68: 264 | AC68: =AB68-I68 -> 0 | AD68: ok | AE68: 9543B-S001-MTS | AF68: 已入 | AG68: 系统出单 | AH68: 94314-2.21 | AL68: =I68 -> 264 | AT68: =I68 -> 264 | BW68: 增加移印布标内容 | BY68: =I68 -> 264 | CB68: =I68 -> 264 | CD68: =SUM(BX68:CA68) -> 264 | CE68: =I68-CD68 -> 0
A69: 45642 | B69: AMAZON.COM.DEDC,LLC | C69: 美国 | D69: 4500154124 | E69: 2MBG7DRK | F69: 4500154124-70 | G69: 9543B-S001 | H69: 仓鼠 | I69: 360 | J69: 0 | K69: 24 | L69: =I69/K69 -> 15 | M69: 45707 | N69: 45703 | P69: PASS | Q69: 2/21出 | R69: 12/16收到 | U69: UPC贴纸翻4500098824 | V69: 1/17-客供外箱贴纸 | X69: 日期码格式：ZURU INC(BVI) 标准格式 日期：按实际生产日期 Packaging Info: #9543：MA 1L 加UPC贴纸，UPC贴纸跟翻单4500098824。A:193052051776，B:193052051783。 Remark: 1. Amazon FOB订单，出口US。 2. 日期码使用ZURU标准版本。 3. 如果大货有要求入邮包盒，则对应的邮包盒上面要打上日期码。 4. 箱尺寸要求：外箱最长边不能超过25"(超过了，case pack只能为1)，不符合要求的大货，一律不接受。 5. 外箱箱唛要求： ①外箱正面印ZURU Logo+SSCC Label(客供贴纸，由跟单订购)。关于 SSCC Label 请注意： SSCC Label显示的是客人自己的item#。每一张SSCC label都是唯一且有不同流水及条码的，没有损耗，绝对不可贴错。如果贴错或损坏任何一张，都会导致全部都 错，千万要注意！SSCC Label必须贴在外箱正面的正中间位置(贴一面即可)，并且贴纸离外箱边距必须至少3cm(可以覆盖Logo<(>&<)>箱唛)，否则会影响到客户那边 仓库的扫描识别。 ②外箱侧面印item#(订单上显示的SKU#)+carton size(以工厂实际尺寸为准，单位: inch)+MADE IN CHINA，日期使用ZURU 标准版本。 6. 装柜要求：按照客户PO#装柜/箱号顺序装柜，跟单会提前给到装柜计划。 在大货生产/仓库存放时，请留意该装柜要求，以便装柜时不混乱(避免装错/装漏/找不到货号等)。 | Y69: kelly/Mia | Z69: 2.5958 | AA69: =I69*Z69 -> 934.488 | AB69: 360 | AC69: =AB69-I69 -> 0 | AD69: ok | AE69: 9543B-S001-MTS | AF69: 已入 | AG69: 系统出单 | AH69: 94315-2.21 | AL69: =I69 -> 360 | AT69: =I69 -> 360 | BW69: 增加移印布标内容 | BY69: =I69 -> 360 | CB69: =I69 -> 360 | CD69: =SUM(BX69:CA69) -> 360 | CE69: =I69-CD69 -> 0
A70: 45653 | B70: Amazon ES | C70: 西班牙 | D70: 4500154883 | E70: Amazon ES: 4X81GPHP | F70: 4500154883-10 | G70: 9543A-S001 | H70: 仓鼠 | I70: 504 | J70: 0 | K70: 24 | L70: =I70/K70 -> 21 | M70: 45706 | N70: 45702 | P70: PASS | Q70: 2/28-3/4出 | R70: 空白外箱（加印带Zuru字样的最新logo，除了邮包盒直接做外箱的产品） + SSCC LABEL一张, 无箱唛，MADE IN CHINA 外箱只印一正一侧。 | U70: UPC+IT环保标翻单4500120504+ES环保标+ZURU邮箱翻4500151280 | V70: 1/2-外箱贴纸 | X70: 日期码格式：ZURU INC(BVI) 标准格式 日期：按实际生产日期 Packaging Info: Amazon ES(9543A/9298A) 1. 9543A：9543A 24pcs/ctn, no inner, blue; MA 3L（9L warning）C版收缩膜+3张贴纸(1张#UPC，1张IT环保标，参考翻单PO#4500120504；1张ES环保标，1张ZUR U邮箱, 参考翻单PO#4500151280)+MA 5L(9L warning) A 说明书； 3. 最迟验货不得晚于2025/02/18; Remark: 1.空白外箱（加印带Zuru字样的最新logo，除了邮包盒直接做外箱的产品） + SSCC LABEL一张, 无箱唛，MADE IN CHINA 外箱只印一正一侧。箱唛资料按照给定的 标准去做即可，无需发回我方再行审批(新标准将另行通知)。 (SSCC LABEL竖贴在外箱正面的正中间，贴一面即可,贴纸离外箱边距必须至少3.2CM。如竖贴无法满足要求，则横贴。如横贴也无法满足要求，则竖贴，遮到ZURU lo go无影响), SSCC贴纸由工厂直接跟勤得采购或者工厂自行采购，每一张SSCC Label都是唯一且有不同流水及条码，且需要检查条码是否能正常扫描，另外，此贴纸 印刷不可出现模糊，溢出及粘胶不牢易脱落等现象，如工厂不按此要求导致贴纸有任何问题产生的罚款将由工厂承担一切责任 。 2.出往UK的产品+包装务必打上UKCA logo ，否则客人会退货且当地会有罚款。 3.订单必须经过ZURU QC验货并且通过后方可出货。 4.法国订单要求包装不使用矿物油，请按要求提供以下其中一份文件再出货 ，产品出到法国被相关部门抽检出现包装不符合此要求的，供应商需要为此承担责任， 故此请严格把关。 -油墨物质""由1 ~ 7个芳香环组成的MOAH""的包装检测报告，要求限值≤1.0%； -包装材料清单，包括包装油墨或物质的信息； -油墨制造商的证书； 5.每一批次出货只能有一个生产日期，不可多个生产日期混在同一批次出货；且邮包盒上必须统一加上日期码；外箱对于日期码没有硬性规定； 6.涉及到相关款式会有闪粉的或者微塑料的，请统一默认出无闪粉或者不含微塑料版本； 7.邮包盒及外箱封箱必须是工字型封箱方式； 8.5 Surprise or Mini Brands涉及包装是2个及2个以上的球入PVC桶包装时，单个球上若有UPC#或者EAN#，请用白色贴纸覆盖住； | Y70: Mandy Hu | Z70: 2.5958 | AA70: =I70*Z70 -> 1308.2832 | AB70: 504 | AC70: =AB70-I70 -> 0 | AD70: ok | AE70: 9543A-S001-3L | AF70: 已入 | AG70: 系统出单 | AH70: 94425-3.4 | AO70: =I70 -> 504 | AT70: =I70 -> 504 | BW70: 增加移印布标内容 | BX70: =I70 -> 504 | CB70: =I70 -> 504 | CD70: =SUM(BX70:CA70) -> 504 | CE70: =I70-CD70 -> 0
A71: 45667 | B71: BIG W | C71: 澳大利亚 | D71: 4500155680 | E71: CUS PO#47786999 SYD | F71: 4500155680-10 | G71: 9543GQ1-S001 | H71: 仓鼠 | I71: 528 | J71: 0 | K71: 22 | L71: =I71/K71 -> 24 | M71: 45708 | N71: 45703 | P71: PASS | Q71: 2/20出 | R71: 1/10收到 | U71: 进口商贴纸翻4500106537 | X71: 日期码格式：ZURU INC(BVI) 标准格式 日期：按实际生产日期 Packaging Info: 1. 9543GQ1：英文MA包装 (UPC版本，首选1L，无1L可用多L含英语)+1张进口商贴纸，贴纸翻单4500106537 2. 产品和包装上的日期码一致，请按要求在包装上打日期码（进口商贴纸不覆盖日期码） 3. 使用ZURU标准日期码 Remark: 1. 共出4港口(SYD, BNE, MEL, FRE), 不同港口数量信息请见订单行项目，并请参考箱唛资料，港口不同，箱唛资料也不同； 2. 箱唛不可出现任何手写内容（箱数除外），重量与实际一致且不可手写; 3. 此单出澳大利亚，请按澳洲标准生产并满足当地法规要求; 4. 出无闪粉版本，需符合欧洲微塑料法规 | Y71: Christine Liao | Z71: 2.8789 | AA71: =I71*Z71 -> 1520.0592 | AB71: 528 | AC71: =AB71-I71 -> 0 | AD71: OK | AE71: 9543GQ1-S001 | AF71: 已入 | AG71: 系统出单 | AH71: 94305-2.20 | AL71: =I71 -> 528 | AT71: =I71 -> 528 | AX71: =I71/11 -> 48 | BW71: 增加移印布标内容 | BX71: =I71/22*5 -> 120 | BY71: =I71/22*6 -> 144 | BZ71: =I71/22*6 -> 144 | CA71: =I71/22*5 -> 120 | CB71: =I71 -> 528 | CC71: =I71/11 -> 48 | CD71: =SUM(BX71:CA71) -> 528 | CE71: =I71-CD71 -> 0
A72: 45667 | B72: BIG W | C72: 澳大利亚 | D72: 4500155680 | E72: CUS PO#47787500 BNE | F72: 4500155680-20 | G72: 9543GQ1-S001 | H72: 仓鼠 | I72: 396 | J72: 0 | K72: 22 | L72: =I72/K72 -> 18 | M72: 45708 | N72: 45703 | P72: PASS | Q72: 2/20出 | R72: 1/10收到 | U72: 进口商贴纸翻4500106537 | X72: 日期码格式：ZURU INC(BVI) 标准格式 日期：按实际生产日期 Packaging Info: 1. 9543GQ1：英文MA包装 (UPC版本，首选1L，无1L可用多L含英语)+1张进口商贴纸，贴纸翻单4500106537 2. 产品和包装上的日期码一致，请按要求在包装上打日期码（进口商贴纸不覆盖日期码） 3. 使用ZURU标准日期码 Remark: 1. 共出4港口(SYD, BNE, MEL, FRE), 不同港口数量信息请见订单行项目，并请参考箱唛资料，港口不同，箱唛资料也不同； 2. 箱唛不可出现任何手写内容（箱数除外），重量与实际一致且不可手写; 3. 此单出澳大利亚，请按澳洲标准生产并满足当地法规要求; 4. 出无闪粉版本，需符合欧洲微塑料法规 | Y72: Christine Liao | Z72: 2.8789 | AA72: =I72*Z72 -> 1140.0444 | AB72: 396 | AC72: =AB72-I72 -> 0 | AD72: OK | AE72: 9543GQ1-S001 | AF72: 已入 | AG72: 系统出单 | AH72: 94317-2.21 | AL72: =I72 -> 396 | AT72: =I72 -> 396 | AX72: =I72/11 -> 36 | BW72: 增加移印布标内容 | BX72: =I72/22*5 -> 90 | BY72: =I72/22*6 -> 108 | BZ72: =I72/22*6 -> 108 | CA72: =I72/22*5 -> 90 | CB72: =I72 -> 396 | CC72: =I72/11 -> 36 | CD72: =SUM(BX72:CA72) -> 396 | CE72: =I72-CD72 -> 0
A73: 45667 | B73: BIG W | C73: 澳大利亚 | D73: 4500155680 | E73: CUS PO#47788295 MEL | F73: 4500155680-30 | G73: 9543GQ1-S001 | H73: 仓鼠 | I73: 418 | J73: 0 | K73: 22 | L73: =I73/K73 -> 19 | M73: 45708 | N73: 45703 | P73: PASS | Q73: 2/20出 | R73: 1/10收到 | U73: 进口商贴纸翻4500106537 | X73: 日期码格式：ZURU INC(BVI) 标准格式 日期：按实际生产日期 Packaging Info: 1. 9543GQ1：英文MA包装 (UPC版本，首选1L，无1L可用多L含英语)+1张进口商贴纸，贴纸翻单4500106537 2. 产品和包装上的日期码一致，请按要求在包装上打日期码（进口商贴纸不覆盖日期码） 3. 使用ZURU标准日期码 Remark: 1. 共出4港口(SYD, BNE, MEL, FRE), 不同港口数量信息请见订单行项目，并请参考箱唛资料，港口不同，箱唛资料也不同； 2. 箱唛不可出现任何手写内容（箱数除外），重量与实际一致且不可手写; 3. 此单出澳大利亚，请按澳洲标准生产并满足当地法规要求; 4. 出无闪粉版本，需符合欧洲微塑料法规 | Y73: Christine Liao | Z73: 2.8789 | AA73: =I73*Z73 -> 1203.3802 | AB73: 418 | AC73: =AB73-I73 -> 0 | AD73: OK | AE73: 9543GQ1-S001 | AF73: 已入 | AG73: 系统出单 | AH73: 94368-2.27 | AL73: =I73 -> 418 | AT73: =I73 -> 418 | AX73: =I73/11 -> 38 | BW73: 增加移印布标内容 | BX73: =I73/22*5 -> 95 | BY73: =I73/22*6 -> 114 | BZ73: =I73/22*6 -> 114 | CA73: =I73/22*5 -> 95 | CB73: =I73 -> 418 | CC73: =I73/11 -> 38 | CD73: =SUM(BX73:CA73) -> 418 | CE73: =I73-CD73 -> 0
A74: 45667 | B74: BIG W | C74: 澳大利亚 | D74: 4500155680 | E74: CUS PO#47788296 FRE | F74: 4500155680-40 | G74: 9543GQ1-S001 | H74: 仓鼠 | I74: 176 | J74: 0 | K74: 22 | L74: =I74/K74 -> 8 | M74: 45708 | N74: 45703 | P74: PASS | Q74: 2/20出 | R74: 1/10收到 | U74: 进口商贴纸翻4500106537 | X74: 日期码格式：ZURU INC(BVI) 标准格式 日期：按实际生产日期 Packaging Info: 1. 9543GQ1：英文MA包装 (UPC版本，首选1L，无1L可用多L含英语)+1张进口商贴纸，贴纸翻单4500106537 2. 产品和包装上的日期码一致，请按要求在包装上打日期码（进口商贴纸不覆盖日期码） 3. 使用ZURU标准日期码 Remark: 1. 共出4港口(SYD, BNE, MEL, FRE), 不同港口数量信息请见订单行项目，并请参考箱唛资料，港口不同，箱唛资料也不同； 2. 箱唛不可出现任何手写内容（箱数除外），重量与实际一致且不可手写; 3. 此单出澳大利亚，请按澳洲标准生产并满足当地法规要求; 4. 出无闪粉版本，需符合欧洲微塑料法规 | Y74: Christine Liao | Z74: 2.8789 | AA74: =I74*Z74 -> 506.6864 | AB74: 176 | AC74: =AB74-I74 -> 0 | AD74: OK | AE74: 9543GQ1-S001 | AF74: 已入 | AG74: 系统出单 | AH74: 94317-2.21 | AL74: =I74 -> 176 | AT74: =I74 -> 176 | AX74: =I74/11 -> 16 | BW74: 增加移印布标内容 | BX74: =I74/22*5 -> 40 | BY74: =I74/22*6 -> 48 | BZ74: =I74/22*6 -> 48 | CA74: =I74/22*5 -> 40 | CB74: =I74 -> 176 | CC74: =I74/11 -> 16 | CD74: =SUM(BX74:CA74) -> 176 | CE74: =I74-CD74 -> 0
A75: 45618 | B75: Dirk Rossmann GmbH | C75: 德国 | D75: 4500150125 | E75: 30241146B | F75: 4500150125-50 | G75: 9543-S001 | H75: 仓鼠 | I75: 1008 | J75: 0 | K75: 24 | L75: =I75/K75 -> 42 | M75: 45709 | N75: 45705 | P75: PASS | R75: 11/21收到 外箱需要是5层瓦楞纸，厚度在5-9mm。 | U75: EAN条码贴纸翻4500116318+德语callout贴纸翻4500122326+客版黑白WEEE声明说明书纸翻4500145491 | X75: 日期码格式：ZURU INC(BVI) 标准格式 日期：按实际生产日期 Tracking Code: Packaging Info: 9543: 最新MA 1L+多语收缩膜+EAN条码贴纸(翻单4500116318)+德语callout贴纸(翻单4500122326)+ 5L+9L说明书+客版黑白WEEE声明说明书纸(翻单#4500145491) Remark: 1. 出口欧洲，微塑料需符合法规，电池符合欧洲法规要求(如有) 2. 此客户要求：化学品无硼无香。 3. 外箱上下需加保护卡，以防开箱时产品被划破。（保护卡需要时整面） 4. 此单在出货前4周提供大货样品给Rossmann德国客人安排第三方验货。 请备额外物料。 5. 此单需要第三方验货，验货时间为完货后第二天，验货OK待客人放货后才能安排走货。 6. 所有包装材料都需要用PET材质。 7. 每箱需要放一包干燥剂（不能是silicon) 。品牌SUPER DRY，规格：10g/pc 。 8. 外箱需要是5层瓦楞纸，厚度在5-9mm。 9. 此单出德国，走整柜请知悉。 10.标准配比。 | Y75: Shirley Zhou | Z75: 2.5816 | AA75: =I75*Z75 -> 2602.2528 | AB75: 1008 | AC75: =AB75-I75 -> 0 | AD75: ok | AE75: 9543-S001 | AF75: 已入 | AG75: 系统出单 | AH75: 94348-2.25 | AL75: =I75 -> 1008 | AT75: =I75 -> 1008 | BW75: 增加移印布标内容 | BX75: =I75/4 -> 252 | BY75: =I75/4 -> 252 | BZ75: =I75/4 -> 252 | CA75: =I75/4 -> 252 | CB75: =I75 -> 1008 | CD75: =SUM(BX75:CA75) -> 1008 | CE75: =I75-CD75 -> 0
A76: 45656 | B76: Amazon CA (Vendor Center) | C76: 加拿大 | D76: 4500154964 | E76: 8Y3X63QD | F76: 4500154964-10 | G76: 9543A-S001 | H76: 仓鼠 | I76: 24 | J76: 0 | K76: 24 | L76: =I76/K76 -> 1 | M76: 45712 | N76: 45708 | P76: PASS | Q76: 2/27-3/5出 | R76: 12/30收到 | U76: UPC贴纸翻4500098824 | V76: 2/8-客供外箱贴纸 | X76: 日期码格式：ZURU INC(BVI) 标准格式 日期：按实际生产日期 Packaging Info: #9543：MA 3L 加UPC贴纸，UPC贴纸跟翻单4500098824。A:193052051776。 Remark: 1. Amazon FOB订单，出口CA。外箱最长边不能超过25" （超过了，case pack只能为1），不符合要求的大货，一律不接受。 2. 外箱正面印ZURU Logo + SSCC LABEL（客供贴纸)，侧面印item#（订单上显示的SKU#) + carton size(以工厂实际尺寸为准，单位: inch) + MADE IN CHINA， 日期使用ZURU 标准版本 SSCC Label 显示的是客人自己的item#，SSCC Label 贴在外箱正面的正中间，贴一面即可，跟单订购，贴纸离外箱距必须至少3cm，每一 张SSCC label 都是唯一且有不同流水及条码的，没有损耗，绝对不可贴错 ，否则贴错或损坏一张会导致全部都错，千万要注意: SSCC 贴纸务必要在正中间(可以覆 盖Logo <(>&<)> 箱唛)，否则会影响到仓库扫描识别。 3. 日期码使用ZURU标准版本。 4. 如果大货有要求入邮包盒，则对应的邮包盒上面要打上日期码。 5. 按照客户PO# 装柜/箱号顺序装柜，跟单会提前给到装柜计划。在大货生产/仓库存放时，请留意该装柜要求，以便装柜时不混乱（避免装错/装漏/找不到货号等 ）。 6. 出口加拿大，包装需要至少2/3L UPC版，无硼版本。 7.邮包盒上要印刷日期码 | Y76: Kelly/Mia | Z76: 2.6514 | AA76: =I76*Z76 -> 63.6336 | AB76: 24 | AC76: =AB76-I76 -> 0 | AD76: ok | AE76: 9543A-S001-3L | AF76: 已入 | AG76: 系统出单 | AH76: 94433-3.4 | AO76: =I76 -> 24 | AT76: =I76 -> 24 | BW76: 增加移印布标内容 | BX76: =I76 -> 24 | CB76: =I76 -> 24 | CD76: =SUM(BX76:CA76) -> 24 | CE76: =I76-CD76 -> 0
A77: 45656 | B77: Amazon CA (Vendor Center) | C77: 加拿大 | D77: 4500154964 | E77: 1DHPRYQN | F77: 4500154964-20 | G77: 9543A-S001 | H77: 仓鼠 | I77: 24 | J77: 0 | K77: 24 | L77: =I77/K77 -> 1 | M77: 45712 | N77: 45708 | P77: PASS | Q77: 2/27-3/5出 | R77: 12/30收到 | U77: UPC贴纸翻4500098824 | V77: 2/8-客供外箱贴纸 | X77: 日期码格式：ZURU INC(BVI) 标准格式 日期：按实际生产日期 Packaging Info: #9543：MA 3L 加UPC贴纸，UPC贴纸跟翻单4500098824。A:193052051776。 Remark: 1. Amazon FOB订单，出口CA。外箱最长边不能超过25" （超过了，case pack只能为1），不符合要求的大货，一律不接受。 2. 外箱正面印ZURU Logo + SSCC LABEL（客供贴纸)，侧面印item#（订单上显示的SKU#) + carton size(以工厂实际尺寸为准，单位: inch) + MADE IN CHINA， 日期使用ZURU 标准版本 SSCC Label 显示的是客人自己的item#，SSCC Label 贴在外箱正面的正中间，贴一面即可，跟单订购，贴纸离外箱距必须至少3cm，每一 张SSCC label 都是唯一且有不同流水及条码的，没有损耗，绝对不可贴错 ，否则贴错或损坏一张会导致全部都错，千万要注意: SSCC 贴纸务必要在正中间(可以覆 盖Logo <(>&<)> 箱唛)，否则会影响到仓库扫描识别。 3. 日期码使用ZURU标准版本。 4. 如果大货有要求入邮包盒，则对应的邮包盒上面要打上日期码。 5. 按照客户PO# 装柜/箱号顺序装柜，跟单会提前给到装柜计划。在大货生产/仓库存放时，请留意该装柜要求，以便装柜时不混乱（避免装错/装漏/找不到货号等 ）。 6. 出口加拿大，包装需要至少2/3L UPC版，无硼版本。 7.邮包盒上要印刷日期码 | Y77: Kelly/Mia | Z77: 2.5695 | AA77: =I77*Z77 -> 61.668 | AB77: 24 | AC77: =AB77-I77 -> 0 | AD77: ok | AE77: 9543A-S001-3L | AF77: 已入 | AG77: 系统出单 | AH77: 94433-3.4 | AO77: =I77 -> 24 | AT77: =I77 -> 24 | BW77: 增加移印布标内容 | BX77: =I77 -> 24 | CB77: =I77 -> 24 | CD77: =SUM(BX77:CA77) -> 24 | CE77: =I77-CD77 -> 0
A78: 45656 | B78: Amazon CA (Vendor Center) | C78: 加拿大 | D78: 4500154964 | E78: 8CD1IN7I | F78: 4500154964-30 | G78: 9543A-S001 | H78: 仓鼠 | I78: 24 | J78: 0 | K78: 24 | L78: =I78/K78 -> 1 | M78: 45712 | N78: 45708 | P78: PASS | Q78: 2/27-3/5出 | R78: 12/30收到 | U78: UPC贴纸翻4500098824 | V78: 2/8-客供外箱贴纸 | X78: 日期码格式：ZURU INC(BVI) 标准格式 日期：按实际生产日期 Packaging Info: #9543：MA 3L 加UPC贴纸，UPC贴纸跟翻单4500098824。A:193052051776。 Remark: 1. Amazon FOB订单，出口CA。外箱最长边不能超过25" （超过了，case pack只能为1），不符合要求的大货，一律不接受。 2. 外箱正面印ZURU Logo + SSCC LABEL（客供贴纸)，侧面印item#（订单上显示的SKU#) + carton size(以工厂实际尺寸为准，单位: inch) + MADE IN CHINA， 日期使用ZURU 标准版本 SSCC Label 显示的是客人自己的item#，SSCC Label 贴在外箱正面的正中间，贴一面即可，跟单订购，贴纸离外箱距必须至少3cm，每一 张SSCC label 都是唯一且有不同流水及条码的，没有损耗，绝对不可贴错 ，否则贴错或损坏一张会导致全部都错，千万要注意: SSCC 贴纸务必要在正中间(可以覆 盖Logo <(>&<)> 箱唛)，否则会影响到仓库扫描识别。 3. 日期码使用ZURU标准版本。 4. 如果大货有要求入邮包盒，则对应的邮包盒上面要打上日期码。 5. 按照客户PO# 装柜/箱号顺序装柜，跟单会提前给到装柜计划。在大货生产/仓库存放时，请留意该装柜要求，以便装柜时不混乱（避免装错/装漏/找不到货号等 ）。 6. 出口加拿大，包装需要至少2/3L UPC版，无硼版本。 7.邮包盒上要印刷日期码 | Y78: Kelly/Mia | Z78: 2.5695 | AA78: =I78*Z78 -> 61.668 | AB78: 24 | AC78: =AB78-I78 -> 0 | AD78: ok | AE78: 9543A-S001-3L | AF78: 已入 | AG78: 系统出单 | AH78: 94433-3.4 | AO78: =I78 -> 24 | AT78: =I78 -> 24 | BW78: 增加移印布标内容 | BX78: =I78 -> 24 | CB78: =I78 -> 24 | CD78: =SUM(BX78:CA78) -> 24 | CE78: =I78-CD78 -> 0
A79: 45656 | B79: Amazon CA (Vendor Center) | C79: 加拿大 | D79: 4500154964 | E79: 51VDTOVN | F79: 4500154964-40 | G79: 9543A-S001 | H79: 仓鼠 | I79: 24 | J79: 0 | K79: 24 | L79: =I79/K79 -> 1 | M79: 45712 | N79: 45708 | P79: PASS | Q79: 2/27-3/5出 | R79: 12/30收到 | U79: UPC贴纸翻4500098824 | V79: 2/8-客供外箱贴纸 | X79: 日期码格式：ZURU INC(BVI) 标准格式 日期：按实际生产日期 Packaging Info: #9543：MA 3L 加UPC贴纸，UPC贴纸跟翻单4500098824。A:193052051776。 Remark: 1. Amazon FOB订单，出口CA。外箱最长边不能超过25" （超过了，case pack只能为1），不符合要求的大货，一律不接受。 2. 外箱正面印ZURU Logo + SSCC LABEL（客供贴纸)，侧面印item#（订单上显示的SKU#) + carton size(以工厂实际尺寸为准，单位: inch) + MADE IN CHINA， 日期使用ZURU 标准版本 SSCC Label 显示的是客人自己的item#，SSCC Label 贴在外箱正面的正中间，贴一面即可，跟单订购，贴纸离外箱距必须至少3cm，每一 张SSCC label 都是唯一且有不同流水及条码的，没有损耗，绝对不可贴错 ，否则贴错或损坏一张会导致全部都错，千万要注意: SSCC 贴纸务必要在正中间(可以覆 盖Logo <(>&<)> 箱唛)，否则会影响到仓库扫描识别。 3. 日期码使用ZURU标准版本。 4. 如果大货有要求入邮包盒，则对应的邮包盒上面要打上日期码。 5. 按照客户PO# 装柜/箱号顺序装柜，跟单会提前给到装柜计划。在大货生产/仓库存放时，请留意该装柜要求，以便装柜时不混乱（避免装错/装漏/找不到货号等 ）。 6. 出口加拿大，包装需要至少2/3L UPC版，无硼版本。 7.邮包盒上要印刷日期码 | Y79: Kelly/Mia | Z79: 2.5695 | AA79: =I79*Z79 -> 61.668 | AB79: 24 | AC79: =AB79-I79 -> 0 | AD79: ok | AE79: 9543A-S001-3L | AF79: 已入 | AG79: 系统出单 | AH79: 94433-3.4 | AO79: =I79 -> 24 | AT79: =I79 -> 24 | BW79: 增加移印布标内容 | BX79: =I79 -> 24 | CB79: =I79 -> 24 | CD79: =SUM(BX79:CA79) -> 24 | CE79: =I79-CD79 -> 0
A80: 45651 | B80: AMIC TRADING (PTY) LTD | C80: 南非 | D80: 4500154694 | E80: PO#6006-00522 6PI#110002571 5-2 | F80: 4500154694-50 | G80: 9543GQ1-S001 | H80: 仓鼠 | I80: 1386 | J80: 0 | K80: 22 | L80: =I80/K80 -> 63 | M80: 45712 | N80: 45708 | P80: PASS | Q80: 2/25出 | R80: 12/25收到 | U80: 1/2-进口商贴纸 | X80: 日期码格式：ZURU INC(BVI) 标准格式 日期：按实际生产日期 Packaging Info: MA PKG, 优先1L +1张进口商贴纸（贴条码附近空白处，不得遮挡日期码） 该客户只有一款进口商贴纸，所有款通用，进口商贴纸AW可翻此客户旧订单 | Y80: Doris Shou | Z80: 2.8038 | AA80: =I80*Z80 -> 3886.0668 | AB80: 1386 | AC80: =AB80-I80 -> 0 | AD80: ok | AE80: 9543GQ1-S001 | AF80: 已入 | AG80: 系统出单 | AH80: 94351-2.25 | AL80: =I80 -> 1386 | AT80: =I80 -> 1386 | AX80: =I80/11 -> 126 | BW80: 增加移印布标内容 | BX80: =I80/22*5 -> 315 | BY80: =I80/22*6 -> 378 | BZ80: =I80/22*6 -> 378 | CA80: =I80/22*5 -> 315 | CB80: =I80 -> 1386 | CC80: =I80/11 -> 126 | CD80: =SUM(BX80:CA80) -> 1386 | CE80: =I80-CD80 -> 0
A81: 45608 | B81: TESCO CE | C81: 斯洛伐克 | D81: 4500150411 | E81: 999-29068 | F81: 4500150411-10 | G81: 9543GQ3-S002 | H81: 仓鼠 | I81: 2520 | J81: 7 | K81: 28 | L81: =I81/K81 -> 90 | M81: 45713 | N81: 45709 | P81: PASS | R81: 11/13收到 | U81: 四国语言警告语贴纸翻4500115674 | X81: 日期码格式：ZURU INC(BVI) 标准格式 日期：按实际生产日期 Packaging Info: 1.9543GQ3-S002：9543GQ3：MA最新1L 收缩膜+一张四国语言警告语贴纸( Czech-Hugarian-Polish-Slovak不能覆盖GB)，贴纸跟位置图翻4500115674，MA3L+9L说明 书 客版 PDQ 1L版（2Facing7pcs/Gravity PDQ)新稿 UPC#193052050328，请先检查包装条码是否正确再安排做货; 7product+demo;2pcs *AAA battery not include; Integral single ratio=bule/purple/pink/orange =1:1:1:1" Remark: 1. 此单出EU，需满足EU测试标准要求，不含微塑料。 产品及包装需要印UKCA图标，包装需要有ZURU UK LTD/ZURU France地址信息，QC同事请核查，如有问题与跟单确认。 2.裝櫃必須按TPND順序 (條形碼貼紙或正嘜必須要朝外向車門外) 3.外箱上有条码要求，排版时请留意并请确保条码清晰可扫描（封箱胶不要黏到条码上), 否则客人会有罚款； 4. 如含硼的话， 需用低硼版本(小于300ppm),硼含量需要符合欧洲标准,否则客人会退货有罚款产生 | Y81: Sharon | Z81: 2.8346 | AA81: =I81*Z81 -> 7143.192 | AB81: 2520 | AC81: =AB81-I81 -> 0 | AD81: ok | AE81: 9543GQ3-S002 | AF81: 已入 | AG81: 系统出单 | AH81: 94497-3.10 | AL81: =I81 -> 2520 | AT81: =I81 -> 2520 | BG81: =I81/7 -> 360 | BW81: 增加移印布标内容 | BX81: =I81/4 -> 630 | BY81: =I81/4 -> 630 | BZ81: =I81/4 -> 630 | CA81: =I81/4 -> 630 | CB81: =I81 -> 2520 | CC81: =I81/11 -> 229.09091 | CD81: =SUM(BX81:CA81) -> 2520 | CE81: =I81-CD81 -> 0
A82: 45577 | B82: WM MORRISON SUPERMARKET PLC | C82: 英国 | D82: 4500147426 | E82: 14067124 | F82: 4500147426-10 | G82: 9543GQ1-S004 | H82: 仓鼠 | I82: 4004 | J82: 11 | K82: 44 | L82: =I82/K82 -> 91 | M82: 45715 | N82: 45712 | P82: PASS | Q82: 2/26出 | R82: 12/26收到 | U82: 无 | X82: 日期码格式：ZURU INC(BVI) 标准格式 日期：按实际生产日期 Packaging Info: 1.9543GQ1：MA 1L UPC版收缩膜+MA 1L PDQ+MA其他包装 UPC#193052050328请先检查条码是否正确再安排做货如有问题请告知 2.配比跟MA Remark: 1）外箱有条码要求，排版时请留意并请确保条码清晰可扫描（封箱胶不要黏到条码上), 否则客人会有罚款。 2) 订单出英国，产品及包装需要印UKCA图标，包装需要有ZURU UK LTD/ZURU France地址信息，QC同事请查核，如有问题与跟单确认。 3) 箱唛日期码与包装保持一致 4) 若外箱重量超过16KGS，请提前告知ZURU跟单，需要客人批准才能出货，并且外箱需要印2 man lift标志 5）需要符合欧洲标准不能含有闪粉和微塑料，否则不和法规会有客诉产生 | Y82: Sheba Ye | Z82: 2.83 | AA82: =I82*Z82 -> 11331.32 | AB82: 4004 | AC82: =AB82-I82 -> 0 | AD82: 无 | AE82: 9543GQ1-S004 | AF82: 已入 | AG82: 系统出单 | AH82: 94387-2.27 | AL82: =I82 -> 4004 | AT82: =I82 -> 4004 | AX82: =I82/11 -> 364 | BW82: 增加移印布标内容 | BX82: =I82/22*5 -> 910 | BY82: =I82/22*6 -> 1092 | BZ82: =I82/22*6 -> 1092 | CA82: =I82/22*5 -> 910 | CB82: =I82 -> 4004 | CC82: =I82/11 -> 364 | CD82: =SUM(BX82:CA82) -> 4004 | CE82: =I82-CD82 -> 0
A83: 45652 | B83: AMAZON UK | C83: 德国 | D83: 4500154803 | E83: Amazon UK: 7IO721HP | F83: 4500154803-40 | G83: 9543E-S001-PKC | H83: 仓鼠 1只胶袋装 | I83: 504 | J83: 0 | K83: 24 | L83: =I83/K83 -> 21 | M83: 45716 | N83: 45712 | P83: PASS | Q83: 3/10-3/14出 | R83: 空白外箱（加印带Zuru字样的最新logo，除了邮包盒直接做外箱的产品） + SSCC LABEL一张, 无箱唛，MADE IN CHINA 外箱只印一正一侧。 | U83: UPC+IT环保标翻单4500120504ES环保标翻4500151280；ZURU邮箱+1/10-胶袋UPC贴纸 | V83: 12/30-客供外箱贴纸 | X83: 日期码格式：ZURU INC(BVI) 标准格式 日期：按实际生产日期 Packaging Info: Amazon UK(9543E)/DE(9543E/77515) 1. 9543E：9543E 24pcs/ctn, no inner, orange; MA 3L（9L warning）C版收缩膜+3张贴纸(1张#UPC，1张IT环保标，参考翻单PO#4500120504；1张ES环保标, 参 考翻单PO#4500151280；ZURU邮箱)+MA 5L(9L warning)A说明书+Polybag(含防窒息5L警示语+塑料循环标) +1张贴纸(UPC#，参考翻单PO#4500120504，贴在polybag)； 3. 最迟验货不得晚于2025/02/28; Remark: 1.空白外箱（加印带Zuru字样的最新logo，除了邮包盒直接做外箱的产品） + SSCC LABEL一张, 无箱唛，MADE IN CHINA 外箱只印一正一侧。箱唛资料按照给定的 标准去做即可，无需发回我方再行审批(新标准将另行通知)。 (SSCC LABEL竖贴在外箱正面的正中间，贴一面即可,贴纸离外箱边距必须至少3.2CM。如竖贴无法满足要求，则横贴。如横贴也无法满足要求，则竖贴，遮到ZURU lo go无影响), SSCC贴纸由工厂直接跟勤得采购或者工厂自行采购，每一张SSCC Label都是唯一且有不同流水及条码，且需要检查条码是否能正常扫描，另外，此贴纸 印刷不可出现模糊，溢出及粘胶不牢易脱落等现象，如工厂不按此要求导致贴纸有任何问题产生的罚款将由工厂承担一切责任 。 2.出往UK的产品+包装务必打上UKCA logo ，否则客人会退货且当地会有罚款。 3.订单必须经过ZURU QC验货并且通过后方可出货。 4.法国订单要求包装不使用矿物油，请按要求提供以下其中一份文件再出货 ，产品出到法国被相关部门抽检出现包装不符合此要求的，供应商需要为此承担责任， 故此请严格把关。 -油墨物质""由1 ~ 7个芳香环组成的MOAH""的包装检测报告，要求限值≤1.0%； -包装材料清单，包括包装油墨或物质的信息； -油墨制造商的证书； 5.每一批次出货只能有一个生产日期，不可多个生产日期混在同一批次出货；且邮包盒上必须统一加上日期码；外箱对于日期码没有硬性规定； 6.涉及到相关款式会有闪粉的或者微塑料的，请统一默认出无闪粉或者不含微塑料版本； 7.邮包盒及外箱封箱必须是工字型封箱方式； 8.5 Surprise or Mini Brands涉及包装是2个及2个以上的球入PVC桶包装时，单个球上若有UPC#或者EAN#，请用白色贴纸覆盖住； | Y83: Crystal Chen | Z83: 2.4196 | AA83: =I83*Z83 -> 1219.4784 | AB83: 504 | AC83: =AB83-I83 -> 0 | AD83: ok | AE83: 9543E-S001-3L | AF83: 已入 | AG83: 系统出单 | AH83: 94665-3.28 | AO83: =I83 -> 504 | AT83: =I83 -> 504 | BW83: 增加移印布标内容 | CA83: =I83 -> 504 | CB83: =I83 -> 504 | CD83: =SUM(BX83:CA83) -> 504 | CE83: =I83-CD83 -> 0
A84: 45652 | B84: AMAZON UK | C84: 德国 | D84: 4500154803 | E84: Amazon DE: 72LLHRBA | F84: 4500154803-50 | G84: 9543E-S001-PKC | H84: 仓鼠 1只胶袋装 | I84: 504 | J84: 0 | K84: 24 | L84: =I84/K84 -> 21 | M84: 45716 | N84: 45712 | P84: PASS | Q84: 3/10-3/14出 | R84: 空白外箱（加印带Zuru字样的最新logo，除了邮包盒直接做外箱的产品） + SSCC LABEL一张, 无箱唛，MADE IN CHINA 外箱只印一正一侧。 | U84: UPC+IT环保标翻单4500120504ES环保标翻4500151280；ZURU邮箱+1/10-胶袋UPC贴纸 | V84: 12/30-客供外箱贴纸 | X84: 日期码格式：ZURU INC(BVI) 标准格式 日期：按实际生产日期 Packaging Info: Amazon UK(9543E)/DE(9543E/77515) 1. 9543E：9543E 24pcs/ctn, no inner, orange; MA 3L（9L warning）C版收缩膜+3张贴纸(1张#UPC，1张IT环保标，参考翻单PO#4500120504；1张ES环保标, 参 考翻单PO#4500151280；ZURU邮箱)+MA 5L(9L warning)A说明书+Polybag(含防窒息5L警示语+塑料循环标) +1张贴纸(UPC#，参考翻单PO#4500120504，贴在polybag)； 3. 最迟验货不得晚于2025/02/28; Remark: 1.空白外箱（加印带Zuru字样的最新logo，除了邮包盒直接做外箱的产品） + SSCC LABEL一张, 无箱唛，MADE IN CHINA 外箱只印一正一侧。箱唛资料按照给定的 标准去做即可，无需发回我方再行审批(新标准将另行通知)。 (SSCC LABEL竖贴在外箱正面的正中间，贴一面即可,贴纸离外箱边距必须至少3.2CM。如竖贴无法满足要求，则横贴。如横贴也无法满足要求，则竖贴，遮到ZURU lo go无影响), SSCC贴纸由工厂直接跟勤得采购或者工厂自行采购，每一张SSCC Label都是唯一且有不同流水及条码，且需要检查条码是否能正常扫描，另外，此贴纸 印刷不可出现模糊，溢出及粘胶不牢易脱落等现象，如工厂不按此要求导致贴纸有任何问题产生的罚款将由工厂承担一切责任 。 2.出往UK的产品+包装务必打上UKCA logo ，否则客人会退货且当地会有罚款。 3.订单必须经过ZURU QC验货并且通过后方可出货。 4.法国订单要求包装不使用矿物油，请按要求提供以下其中一份文件再出货 ，产品出到法国被相关部门抽检出现包装不符合此要求的，供应商需要为此承担责任， 故此请严格把关。 -油墨物质""由1 ~ 7个芳香环组成的MOAH""的包装检测报告，要求限值≤1.0%； -包装材料清单，包括包装油墨或物质的信息； -油墨制造商的证书； 5.每一批次出货只能有一个生产日期，不可多个生产日期混在同一批次出货；且邮包盒上必须统一加上日期码；外箱对于日期码没有硬性规定； 6.涉及到相关款式会有闪粉的或者微塑料的，请统一默认出无闪粉或者不含微塑料版本； 7.邮包盒及外箱封箱必须是工字型封箱方式； 8.5 Surprise or Mini Brands涉及包装是2个及2个以上的球入PVC桶包装时，单个球上若有UPC#或者EAN#，请用白色贴纸覆盖住； | Y84: Crystal Chen | Z84: 2.4196 | AA84: =I84*Z84 -> 1219.4784 | AB84: 504 | AC84: =AB84-I84 -> 0 | AD84: ok | AE84: 9543E-S001-3L | AF84: 已入 | AG84: 系统出单 | AH84: 94665-3.28 | AO84: =I84 -> 504 | AT84: =I84 -> 504 | BW84: 增加移印布标内容 | CA84: =I84 -> 504 | CB84: =I84 -> 504 | CD84: =SUM(BX84:CA84) -> 504 | CE84: =I84-CD84 -> 0
A85: 45672 | B85: Coop Danmark A/S | C85: 丹麦 | D85: 4500155889 | E85: 4507867714 | F85: 4500155889-10 | G85: 9543GQ1-S002 | H85: 仓鼠 | I85: 363 | J85: 0 | K85: 11 | L85: =I85/K85 -> 33 | M85: 45719 | N85: 45715 | P85: PASS | Q85: 3/5出 | R85: 1/15收到 | U85: EAN贴纸翻4500133308 | X85: 日期码格式：ZURU INC(BVI) 标准格式 日期：按实际生产日期 Packaging Info: 9543GQ1-3L MA C版包装+MA5L-9L Warning A版说明书+EAN贴纸 （贴纸翻单4500133308） Remark: 1. 包装如含PVC,请改为PET 2. 产品/包装要求无硼无香； 3. 出欧洲，微塑料需合规。 4.带电池出货的产品所用到的电池需要符合欧洲电池新规(EU) 2023-1542 5.关于贴纸，如果贴纸位置图的包装版本与大货不一致，请工厂提前提出。跟单会重新调整确认是否更新贴纸或调整位置图 6.产品/包装不含PFAS成分 7. 产品信息： 9543GQ1-2pcs *AAA battery not Includedd; Integral single ratio=bule/purple/pink/orange =5:6:6:5 8. SKU-客户SKU-EAN-GTIN 9543GQ1-1000448977-4894680026995-10193052050325 9. 工厂需要在2025-3-1 提供客户模板的验货资料 10.此单出丹麦，订单上包装上需要显示ZURU Denmark ApS 地址，说明书/包装需要有丹麦语(DK)警告语 | Y85: Luna Lin | Z85: 2.8812 | AA85: =I85*Z85 -> 1045.8756 | AB85: 363 | AC85: =AB85-I85 -> 0 | AD85: ok | AE85: 9543GQ1-S002-3L | AF85: 已入 | AG85: 系统出单 | AH85: 94482-3.7 | AO85: =I85 -> 363 | AT85: =I85 -> 363 | BA85: =I85/11 -> 33 | BW85: 增加移印布标内容 | BX85: =I85/22*5 -> 82.5 | BY85: =I85/22*6 -> 99 | BZ85: =I85/22*6 -> 99 | CA85: =I85/22*5 -> 82.5 | CB85: =I85 -> 363 | CC85: =I85/11 -> 33 | CD85: =SUM(BX85:CA85) -> 363 | CE85: =I85-CD85 -> 0
A86: 45671 | B86: I-VISION TOYS.INC | C86: 韩国 | D86: 4500155860 | E86: IVI-0107SKH | F86: 4500155860-10 | G86: 9543GQ1-S002 | H86: 仓鼠 | I86: 5060 | J86: 0 | K86: 11 | L86: =I86/K86 -> 460 | M86: 45719 | N86: 45715 | P86: PASS | Q86: 3/7出 | R86: 箱唛（翻单4500133472） | U86: 1/15-韩语贴纸（新稿） | V86: 客版说明书翻单4500125430 | X86: 日期码格式：ZURU INC(BVI) 标准格式 日期：按实际生产日期 Packaging Info: MA 1L PKG+韩语贴纸（新稿）+ MA PDQ+客版说明书翻单4500133472+箱唛（翻单4500133472） 请确保大货包装的生产年月 信息跟到到贴纸上的一致。生产日信息不做特别要求，可安排统一日期，但必须确保生产年份"2025" 月份"02" 谢谢！ Remark: 由于韩国法律法规要求，吸塑需PET材质, 产品需符合韩国KC测试标准。 9543GQ1大货板需严格跟上单4500133472一致 | Y86: Doris Shou | Z86: 2.7699 | AA86: =I86*Z86 -> 14015.694 | AB86: =5049+11 -> 5060 | AC86: =AB86-I86 -> 0 | AD86: ok | AE86: 9543GQ1-S002-3 | AF86: 已入 | AG86: 系统出单 | AH86: 94443-3.5 | AL86: =I86 -> 5060 | AV86: =I86 -> 5060 | AX86: =I86/11 -> 460 | BW86: 增加移印布标内容 | BX86: =I86/22*5 -> 1150 | BY86: =I86/22*6 -> 1380 | BZ86: =I86/22*6 -> 1380 | CA86: =I86/22*5 -> 1150 | CB86: =I86 -> 5060 | CC86: =I86/11 -> 460 | CD86: =SUM(BX86:CA86) -> 5060 | CE86: =I86-CD86 -> 0
A87: 45672 | B87: SUCKOT SAC | C87: 秘鲁 | D87: 4500155723 | F87: 4500155723-110 | G87: 9543GQ1-S001 | H87: 仓鼠 | I87: 4180 | J87: 0 | K87: 22 | L87: =I87/K87 -> 190 | M87: 45720 | N87: 45717 | P87: PASS | Q87: 3/4出 | R87: 1/16收到 | U87: 2/7-进口商贴纸 | X87: 日期码格式：ZURU INC(BVI) 标准格式 日期：按实际生产日期 Packaging Info: 9543GQ1：MA 3L UPC包装+MA 3L PDQ包装+MA 多语说明书+进口商贴纸+箱唛 Remark: 9543GQ1：bule/purple/pink/orange =5:6:6:5; 2PCS AAA Batteries(Not Include) | Y87: Zoe Luo | Z87: 2.7927 | AA87: =I87*Z87 -> 11673.486 | AB87: 4180 | AC87: =AB87-I87 -> 0 | AD87: OK | AE87: 9543GQ1-S001-3L | AF87: 已入 | AG87: 系统出单 | AH87: 94426-3.4 | AO87: =I87 -> 4180 | AT87: =I87 -> 4180 | BA87: =I87/11 -> 380 | BW87: 增加移印布标内容 | BX87: =I87/22*5 -> 950 | BY87: =I87/22*6 -> 1140 | BZ87: =I87/22*6 -> 1140 | CA87: =I87/22*5 -> 950 | CB87: =I87 -> 4180 | CC87: =I87/11 -> 380 | CD87: =SUM(BX87:CA87) -> 4180 | CE87: =I87-CD87 -> 0
A88: 45694 | B88: Smyths Toys HQ UC IE | C88: 爱尔兰 | D88: 4500156774 | E88: 4400464037 | F88: 4500156774-10 | G88: 9543GQ1-S001 | H88: 仓鼠 | I88: 1320 | J88: 0 | K88: 22 | L88: =I88/K88 -> 60 | M88: 45720 | N88: 45717 | P88: PASS | Q88: 3/10出 | R88: 2/6收到 | U88: 德语callout翻译贴纸翻4500125086 | X88: 日期码格式：ZURU INC(BVI) 标准格式 日期：按实际生产日期 Packaging Info: 9543GQ1：MA 3L(9L warning) UPC版收缩膜+德语callout翻译贴纸+MA5L+9L Warning说明书+MA 3L PDQ BULE/PURPLE/PINK/ORANGE =5:6:6:5;贴纸和位置图翻#4500125086 Remark: 1）包装日期码按ZURU格式即可，请确保不迟于外箱日期码，可等于或者早于外箱日期码，必须为法定工作日，印刷前请先检查外箱日期码。 2）订单出英国，请注意检查产品及包装应带UKCA图标（14+产品除外），包装显示ZURU UK LTD/ZURU France地址信息，QC部门请查核，如有问题与跟单确认 3）订单必须经过ZURU QC验货并且通过后方可出货 4) 需要完全符合欧洲标准(符合微塑料法规)，否则不合法规会有客诉产生 Order Modifiable | Y88: May Wu | Z88: 2.8038 | AA88: =I88*Z88 -> 3701.016 | AB88: 1320 | AC88: =AB88-I88 -> 0 | AD88: ok | AE88: 9543GQ1-S001-3L | AF88: 已入 | AG88: 系统出单 | AH88: 94493-3.10 | AO88: =I88 -> 1320 | AT88: =I88 -> 1320 | BA88: =I88/11 -> 120 | BW88: 增加移印布标内容 | BX88: =I88/22*5 -> 300 | BY88: =I88/22*6 -> 360 | BZ88: =I88/22*6 -> 360 | CA88: =I88/22*5 -> 300 | CB88: =I88 -> 1320 | CC88: =I88/11 -> 120 | CD88: =SUM(BX88:CA88) -> 1320 | CE88: =I88-CD88 -> 0
A89: 45649 | B89: PPTOYS PTE LTD (SG) | C89: 新加坡 | D89: 4500154572 | E89: ZU24120901SG | F89: 4500154572-20 | G89: 9543-S001 | H89: 仓鼠 | I89: 504 | J89: 0 | K89: 24 | L89: =I89/K89 -> 21 | M89: 45723 | N89: 45719 | P89: PASS | Q89: 3/10出 | R89: 1/6收到 | U89: 进口商贴纸翻-4500139381 | X89: 日期码格式：ZURU INC(BVI) 标准格式 日期：按实际生产日期 Packaging Info: MA UPC包装（优先1L)+1张进口商贴纸 贴纸AW、位置图翻单如下： 9543-4500139381 所有item的贴纸图稿一模一样，请一起订购节省成本。 Remark: 9543-2pcs *AAA battery not include; bule/pink/purple/orange =1:1:1:1 9543GQ1-bule/purple/pink/orange =5:6:6:5;2PCS AAA Batteries(Not Include) | Y89: Emma Wu | Z89: 2.5695 | AA89: =I89*Z89 -> 1295.028 | AB89: 504 | AC89: =AB89-I89 -> 0 | AD89: ok | AE89: 9543-S001 | AF89: 已入 | AG89: 系统出单 | AH89: 94491-3.7 | AL89: =I89 -> 504 | AT89: =I89 -> 504 | BW89: 增加移印布标内容 | BX89: =I89/4 -> 126 | BY89: =I89/4 -> 126 | BZ89: =I89/4 -> 126 | CA89: =I89/4 -> 126 | CB89: =I89 -> 504 | CD89: =SUM(BX89:CA89) -> 504 | CE89: =I89-CD89 -> 0
A90: 45649 | B90: PPTOYS PTE LTD (SG) | C90: 新加坡 | D90: 4500154572 | E90: ZU24120901SG | F90: 4500154572-30 | G90: 9543GQ1-S001 | H90: 仓鼠 | I90: 660 | J90: 0 | K90: 22 | L90: =I90/K90 -> 30 | M90: 45723 | N90: 45719 | P90: PASS | Q90: 3/10出 | R90: 1/6收到 | U90: 进口商贴纸翻-4500139381 | X90: 日期码格式：ZURU INC(BVI) 标准格式 日期：按实际生产日期 Packaging Info: MA UPC包装（优先1L)+1张进口商贴纸 贴纸AW、位置图翻单如下： 9543-4500139381 所有item的贴纸图稿一模一样，请一起订购节省成本。 Remark: 9543-2pcs *AAA battery not include; bule/pink/purple/orange =1:1:1:1 9543GQ1-bule/purple/pink/orange =5:6:6:5;2PCS AAA Batteries(Not Include) | Y90: Emma Wu | Z90: 2.7825 | AA90: =I90*Z90 -> 1836.45 | AB90: 660 | AC90: =AB90-I90 -> 0 | AD90: ok | AE90: 9543GQ1-S001 | AF90: 已入 | AG90: 系统出单 | AH90: 94491-3.7 | AL90: =I90 -> 660 | AT90: =I90 -> 660 | AX90: =I90/11 -> 60 | BW90: 增加移印布标内容 | BX90: =I90/22*5 -> 150 | BY90: =I90/22*6 -> 180 | BZ90: =I90/22*6 -> 180 | CA90: =I90/22*5 -> 150 | CB90: =I90 -> 660 | CC90: =I90/11 -> 60 | CD90: =SUM(BX90:CA90) -> 660 | CE90: =I90-CD90 -> 0
A91: 45663 | B91: Ansaldo Chile | C91: 智利 | D91: 4500155330 | F91: 4500155330-50 | G91: 9543GQ1-S001 | H91: 仓鼠 | I91: 2222 | J91: 0 | K91: 22 | L91: =I91/K91 -> 101 | M91: 45723 | N91: 45719 | P91: PASS | Q91: 3/7出 | R91: 1/14收到 | U91: 2/17-进口商贴纸 | X91: 日期码格式：ZURU INC(BVI) 标准格式 日期：按实际生产日期 Packaging Info: 9543GQ1:MA 1L包装+MA 5L说明书+进口商贴纸+箱唛 | Y91: Ava Liang | Z91: 2.7943 | AA91: =I91*Z91 -> 6208.9346 | AB91: 2222 | AC91: =AB91-I91 -> 0 | AD91: OK | AE91: 9543GQ1-S001 | AF91: 已入 | AG91: 系统出单 | AH91: 94485-3.7 | AL91: =I91 -> 2222 | AT91: =I91 -> 2222 | AX91: =I91/11 -> 202 | BW91: 增加移印布标内容 | BX91: =I91/22*5 -> 505 | BY91: =I91/22*6 -> 606 | BZ91: =I91/22*6 -> 606 | CA91: =I91/22*5 -> 505 | CB91: =I91 -> 2222 | CC91: =I91/11 -> 202 | CD91: =SUM(BX91:CA91) -> 2222 | CE91: =I91-CD91 -> 0
A92: 45695 | B92: TOYS "R" US – JAPAN, LTD | C92: 日本 | D92: 4500156900 | E92: 47:0003119219 | F92: 4500156900-10 | G92: 9543GQ1-S001 | H92: 仓鼠 | I92: 594 | J92: 0 | K92: 22 | L92: =I92/K92 -> 27 | M92: 45719 | N92: =M92-4 -> 45715 | P92: PASS | Q92: 3/7出 | R92: 2/7收到 | U92: 日语贴纸翻4500122471 | X92: 日期码格式：ZURU INC(BVI) 标准格式 日期：按实际生产日期 Packaging Info: 9543GQ1： MA 1L PKG D版包装+MA 说明书+1张日语贴纸（贴纸内容及位置翻单4500122471） (9543GQ1)PDQ: MA 1L PDQ PKG B 版包装 Remark: 9543GQ1的大货的产品品质跟内容需跟4500129603这单一致，有任何更新（含包装）需提前告知。 | Y92: Doris Shou | Z92: 2.7825 | AA92: =I92*Z92 -> 1652.805 | AB92: 594 | AC92: =AB92-I92 -> 0 | AD92: ok | AE92: 9543GQ1-S001 | AF92: 已入 | AG92: 系统出单 | AH92: 94462-3.6 | AL92: =I92 -> 594 | AT92: =I92 -> 594 | AX92: =I92/11 -> 54 | BW92: 增加移印布标内容 | BX92: =I92/22*5 -> 135 | BY92: =I92/22*6 -> 162 | BZ92: =I92/22*6 -> 162 | CA92: =I92/22*5 -> 135 | CB92: =I92 -> 594 | CC92: =I92/11 -> 54 | CD92: =SUM(BX92:CA92) -> 594 | CE92: =I92-CD92 -> 0
A93: 45677 | B93: KMART AUSTRALIA LTD | C93: 澳大利亚 | D93: 4500156224 | E93: 20611030 | F93: 4500156224-10 | G93: 9543GQ2-S001 | H93: 仓鼠 | I93: 1500 | J93: 0 | K93: 6 | L93: =I93/K93 -> 250 | M93: 45726 | N93: 45722 | P93: PASS | Q93: 3/12-3/14出 | R93: 1/20收到 | U93: 2/10-防盗贴纸+2/17-外箱贴纸 | X93: 日期码格式：ZURU INC(BVI) 标准格式 日期：按实际生产日期 Packaging Info: 9543GQ1: MA英语UPC版本包装（首选1LUPC，如果无1L可用多语含英语UPC版本）+ 客版PDQ (翻单4500124321)+ 防盗贴纸（贴纸以及位置图翻单4500116403） + 箱 唛 + 外箱SSCC Label Remark: 1.请务必按时完货，验货。并且按期送货入货代指定仓库，如果晚了导致船期Delay将会有罚金产生或者客户要求空运，所产生的罚金和空运费由工厂承担。 2.SSCC 外箱贴纸请同纸箱瓦楞纸方向（竖纹向）垂直，即外箱贴纸横着贴(注意条码不要被胶带粘住），贴1pc，贴1面正唛，封箱胶纸不能挡住贴纸内容。外箱贴纸 离外箱边距离不少于2cm。 3.外箱材质为ZURU标准； 4.此单需使用KMART封箱胶上下工字型封箱;从2019年6月开始，要用KMART 新版封箱胶带，此单要用"ANKO"封箱胶带 5.此单出口澳大利亚，请按相应的澳新标准生产； 6.产品和包装上生产批号的显示格式ZURU标准日期码格式 7.外箱信息不可手写，重量和体积需要与实际的一致(不可手写） 8. 每款item装箱后的G.W.超过10KG或者CBM超过0.13,(9.5KG或者以上，四舍五入后也属于10KG) 需在外箱上加印超 重或者Bulky LOGO，若发现我们资料没有，请 帮忙提醒 1)重量超过10kg但不超过16kg且CBM不超过0.13,10-16kg 超重logo 2）CBM超过0.13且重量少于17kg，bulky logo 3）不属于以上两种情况，需要使用相应重量范围内的超重logo 4）超重logo需要在外箱四面都印刷(箱唛右上角，两面侧唛超重logo需要尽量靠近毛重)，尺寸为:110mm height* 95mm width 9. 实际外箱重量跟印在箱唛上的数据差异不能超3%，尺寸按实际数据印刷 | Y93: Lydia Wu | Z93: 2.771 | AA93: =I93*Z93 -> 4156.5 | AB93: 1500 | AC93: =AB93-I93 -> 0 | AD93: ok | AE93: 9543GQ2-S001 | AF93: 已入 | AG93: 系统出单 | AH93: 94538-3.13 | AL93: =I93 -> 1500 | AT93: =I93 -> 1500 | BE93: =I93/6 -> 250 | BW93: 增加移印布标内容 | BX93: =I93/4 -> 375 | BY93: =I93/4 -> 375 | BZ93: =I93/4 -> 375 | CA93: =I93/4 -> 375 | CB93: =I93 -> 1500 | CD93: =SUM(BX93:CA93) -> 1500 | CE93: =I93-CD93 -> 0
A94: 45677 | B94: Bol.com | C94: 新西兰 | D94: 4500156115 | E94: 7631985 | F94: 4500156115-100 | G94: 9543A-S001 | H94: 仓鼠 | I94: 216 | J94: 0 | K94: 24 | L94: =I94/K94 -> 9 | M94: 45730 | N94: 45726 | P94: PASS | Q94: 3/17出 | R94: 1/20收到 | U94: EAN#贴纸翻4500137487 | X94: 日期码格式：ZURU INC(BVI) 标准格式 日期：按实际生产日期 Packaging Info: BOL NL(9543ABDE) 11. 9543ABDE ---9543A: 24pcs/ctn, no inner, Blue, 2PCS AAA BATTERIES(NOT INCLUDED); MA 3L(9L warning UPC)C收缩膜+1张EAN#贴纸(参考翻单PO#4500137487)+MA 5L(9L warning)A 说明书; 13. 验货时间不迟于2025/3/17. Remark: 1. 出欧洲产品不可含闪粉或者微塑料，若所涉产品无闪粉或不含微塑料可忽略此点； 2. 5 Surprise or Mini Brands涉及包装是2个及2个以上的球入PVC桶包装时，单个球上若有UPC#或者EAN#，请用白色贴纸覆盖住； 3. 箱唛资料按照提供的要求去做即可，无需再发回我方确认； 4.柜货产品务必拉网且要拉紧，拉网要求： A: 网要结实同时网格要细，纸箱不能从网格处跌落下来 B: 打网固定8-10个点。请提供拉网的装柜照片给船务确认 后柜子再离厂。" | Y94: Crystal Chen | Z94: 2.5695 | AA94: =I94*Z94 -> 555.012 | AB94: 216 | AC94: =AB94-I94 -> 0 | AD94: OK | AE94: 9543A-S001-3L | AF94: 已入 | AG94: 系统出单 | AH94: 94548-3.14 | AO94: =I94 -> 216 | AT94: =I94 -> 216 | BW94: 增加移印布标内容 | BX94: =I94 -> 216 | CB94: =I94 -> 216 | CD94: =SUM(BX94:CA94) -> 216 | CE94: =I94-CD94 -> 0
A95: 45677 | B95: Bol.com | C95: 新西兰 | D95: 4500156115 | E95: 7631985 | F95: 4500156115-110 | G95: 9543E-S001 | H95: 仓鼠 | I95: 216 | J95: 0 | K95: 24 | L95: =I95/K95 -> 9 | M95: 45730 | N95: 45726 | P95: PASS | Q95: 3/17出 | R95: 1/20收到 | U95: EAN#贴纸翻4500137487 | X95: 日期码格式：ZURU INC(BVI) 标准格式 日期：按实际生产日期 Packaging Info: BOL NL(9543ABDE) 11. 9543ABDE ---9543E: 24pcs/ctn, no inner, Orange, 2PCS AAA BATTERIES(NOT INCLUDED); MA 3L(9L warning UPC)C收缩膜+1张EAN#贴纸(参考翻单PO#4500137487)+MA 5L(9 L warning)A 说明书; 13. 验货时间不迟于2025/3/17. Remark: 1. 出欧洲产品不可含闪粉或者微塑料，若所涉产品无闪粉或不含微塑料可忽略此点； 2. 5 Surprise or Mini Brands涉及包装是2个及2个以上的球入PVC桶包装时，单个球上若有UPC#或者EAN#，请用白色贴纸覆盖住； 3. 箱唛资料按照提供的要求去做即可，无需再发回我方确认； 4.柜货产品务必拉网且要拉紧，拉网要求： A: 网要结实同时网格要细，纸箱不能从网格处跌落下来 B: 打网固定8-10个点。请提供拉网的装柜照片给船务确认 后柜子再离厂。" | Y95: Crystal Chen | Z95: 2.5695 | AA95: =I95*Z95 -> 555.012 | AB95: 216 | AC95: =AB95-I95 -> 0 | AD95: OK | AE95: 9543E-S001-3L | AF95: 已入 | AG95: 系统出单 | AH95: 94548-3.14 | AO95: =I95 -> 216 | AT95: =I95 -> 216 | BW95: 增加移印布标内容 | CA95: =I95 -> 216 | CB95: =I95 -> 216 | CD95: =SUM(BX95:CA95) -> 216 | CE95: =I95-CD95 -> 0
A96: 45677 | B96: Bol.com | C96: 新西兰 | D96: 4500156115 | E96: 7631985 | F96: 4500156115-120 | G96: 9543D-S001 | H96: 仓鼠 | I96: 216 | J96: 0 | K96: 24 | L96: =I96/K96 -> 9 | M96: 45730 | N96: 45726 | P96: PASS | Q96: 3/17出 | R96: 1/20收到 | U96: EAN#贴纸翻4500137487 | X96: 日期码格式：ZURU INC(BVI) 标准格式 日期：按实际生产日期 Packaging Info: BOL NL(9543ABDE) 11. 9543ABDE ---9543D: 24pcs/ctn, no inner, Purple, 2PCS AAA BATTERIES(NOT INCLUDED); MA 3L(9L warning UPC)C收缩膜+1张EAN#贴纸(参考翻单PO#4500137487)+MA 5L(9 L warning)A 说明书; 13. 验货时间不迟于2025/3/17. Remark: 1. 出欧洲产品不可含闪粉或者微塑料，若所涉产品无闪粉或不含微塑料可忽略此点； 2. 5 Surprise or Mini Brands涉及包装是2个及2个以上的球入PVC桶包装时，单个球上若有UPC#或者EAN#，请用白色贴纸覆盖住； 3. 箱唛资料按照提供的要求去做即可，无需再发回我方确认； 4.柜货产品务必拉网且要拉紧，拉网要求： A: 网要结实同时网格要细，纸箱不能从网格处跌落下来 B: 打网固定8-10个点。请提供拉网的装柜照片给船务确认 后柜子再离厂。" | Y96: Crystal Chen | Z96: 2.5695 | AA96: =I96*Z96 -> 555.012 | AB96: 216 | AC96: =AB96-I96 -> 0 | AD96: OK | AE96: 9543D-S001-3L | AF96: 已入 | AG96: 系统出单 | AH96: 94548-3.14 | AO96: =I96 -> 216 | AT96: =I96 -> 216 | BW96: 增加移印布标内容 | BZ96: =I96 -> 216 | CB96: =I96 -> 216 | CD96: =SUM(BX96:CA96) -> 216 | CE96: =I96-CD96 -> 0
A97: 45677 | B97: Bol.com | C97: 新西兰 | D97: 4500156115 | E97: 7631985 | F97: 4500156115-130 | G97: 9543B-S001 | H97: 仓鼠 | I97: 216 | J97: 0 | K97: 24 | L97: =I97/K97 -> 9 | M97: 45730 | N97: 45726 | P97: PASS | Q97: 3/17出 | R97: 1/20收到 | U97: EAN#贴纸翻4500137487 | X97: 日期码格式：ZURU INC(BVI) 标准格式 日期：按实际生产日期 Packaging Info: BOL NL(9543ABDE) 11. 9543ABDE ---9543E: 24pcs/ctn, no inner, Orange, 2PCS AAA BATTERIES(NOT INCLUDED); MA 3L(9L warning UPC)C收缩膜+1张EAN#贴纸(参考翻单PO#4500137487)+MA 5L(9 L warning)A 说明书; 13. 验货时间不迟于2025/3/17. Remark: 1. 出欧洲产品不可含闪粉或者微塑料，若所涉产品无闪粉或不含微塑料可忽略此点； 2. 5 Surprise or Mini Brands涉及包装是2个及2个以上的球入PVC桶包装时，单个球上若有UPC#或者EAN#，请用白色贴纸覆盖住； 3. 箱唛资料按照提供的要求去做即可，无需再发回我方确认； 4.柜货产品务必拉网且要拉紧，拉网要求： A: 网要结实同时网格要细，纸箱不能从网格处跌落下来 B: 打网固定8-10个点。请提供拉网的装柜照片给船务确认 后柜子再离厂。" | Y97: Crystal Chen | Z97: 2.5695 | AA97: =I97*Z97 -> 555.012 | AB97: 216 | AC97: =AB97-I97 -> 0 | AD97: OK | AE97: 9543B-S001-3L | AF97: 已入 | AG97: 系统出单 | AH97: 94548-3.14 | AO97: =I97 -> 216 | AT97: =I97 -> 216 | BW97: 增加移印布标内容 | BY97: =I97 -> 216 | CB97: =I97 -> 216 | CD97: =SUM(BX97:CA97) -> 216 | CE97: =I97-CD97 -> 0
A98: 45695 | B98: BIG W | C98: 澳大利亚 | D98: 4500156306 | E98: CUS PO#47786981 SYD | F98: 4500156306-10 | G98: 9543GQ1-S001 | H98: 仓鼠 | I98: 528 | J98: 0 | K98: 22 | L98: =I98/K98 -> 24 | M98: 45730 | N98: =M98-4 -> 45726 | P98: PASS | Q98: 3/26出 | R98: 2/7收到 | U98: 进口商贴纸翻4500106537 | X98: 日期码格式：ZURU INC(BVI) 标准格式 日期：按实际生产日期 Packaging Info: 1. 9543GQ1：英文MA包装 (UPC版本，首选1L，无1L可用多L含英语)+1张进口商贴纸，贴纸翻单4500106537 2. 产品和包装上的日期码一致，请按要求在包装上打日期码（进口商贴纸不覆盖日期码） 3. 使用ZURU标准日期码 Remark: 1.共出4港口(SYD,BNE,MEL,FRE)， 不同港口数量信息请见订单行项目，并请参考箱唛资料，港口不同，箱唛资料也不同； 2. 箱唛不可出现任何手写内容（箱数除外），重量与实际一致且不可手写 3.此单出澳大利亚，请按澳洲标准生产并满足当地法规要求 4.出无闪粉版本，需符合欧洲微塑料法规 | Y98: Christine Liao | Z98: 2.8789 | AA98: =I98*Z98 -> 1520.0592 | AB98: 528 | AC98: =AB98-I98 -> 0 | AD98: ok | AE98: 9543GQ1-S001 | AF98: 已入 | AG98: 系统出单 | AH98: 94628-3.25 | AL98: =I98 -> 528 | AT98: =I98 -> 528 | AX98: =I98/11 -> 48 | BW98: 增加移印布标内容 | BX98: =I98/22*5 -> 120 | BY98: =I98/22*6 -> 144 | BZ98: =I98/22*6 -> 144 | CA98: =I98/22*5 -> 120 | CB98: =I98 -> 528 | CC98: =I98/11 -> 48 | CD98: =SUM(BX98:CA98) -> 528 | CE98: =I98-CD98 -> 0
A99: 45695 | B99: BIG W | C99: 澳大利亚 | D99: 4500156306 | E99: CUS PO#47786982 BNE | F99: 4500156306-20 | G99: 9543GQ1-S001 | H99: 仓鼠 | I99: 396 | J99: 0 | K99: 22 | L99: =I99/K99 -> 18 | M99: 45730 | N99: =M99-4 -> 45726 | P99: PASS | Q99: 3/24出 | R99: 2/7收到 | U99: 进口商贴纸翻4500106537 | X99: 日期码格式：ZURU INC(BVI) 标准格式 日期：按实际生产日期 Packaging Info: 1. 9543GQ1：英文MA包装 (UPC版本，首选1L，无1L可用多L含英语)+1张进口商贴纸，贴纸翻单4500106537 2. 产品和包装上的日期码一致，请按要求在包装上打日期码（进口商贴纸不覆盖日期码） 3. 使用ZURU标准日期码 Remark: 1.共出4港口(SYD,BNE,MEL,FRE)， 不同港口数量信息请见订单行项目，并请参考箱唛资料，港口不同，箱唛资料也不同； 2. 箱唛不可出现任何手写内容（箱数除外），重量与实际一致且不可手写 3.此单出澳大利亚，请按澳洲标准生产并满足当地法规要求 4.出无闪粉版本，需符合欧洲微塑料法规 | Y99: Christine Liao | Z99: 2.8789 | AA99: =I99*Z99 -> 1140.0444 | AB99: 396 | AC99: =AB99-I99 -> 0 | AD99: ok | AE99: 9543GQ1-S001 | AF99: 已入 | AG99: 系统出单 | AH99: 94596-3.21 | AL99: =I99 -> 396 | AT99: =I99 -> 396 | AX99: =I99/11 -> 36 | BW99: 增加移印布标内容 | BX99: =I99/22*5 -> 90 | BY99: =I99/22*6 -> 108 | BZ99: =I99/22*6 -> 108 | CA99: =I99/22*5 -> 90 | CB99: =I99 -> 396 | CC99: =I99/11 -> 36 | CD99: =SUM(BX99:CA99) -> 396 | CE99: =I99-CD99 -> 0
A100: 45695 | B100: BIG W | C100: 澳大利亚 | D100: 4500156306 | E100: CUS PO#47786983 MEL | F100: 4500156306-30 | G100: 9543GQ1-S001 | H100: 仓鼠 | I100: 418 | J100: 0 | K100: 22 | L100: =I100/K100 -> 19 | M100: 45730 | N100: =M100-4 -> 45726 | P100: PASS | Q100: 3/20出 | R100: 2/7收到 | U100: 进口商贴纸翻4500106537 | X100: 日期码格式：ZURU INC(BVI) 标准格式 日期：按实际生产日期 Packaging Info: 1. 9543GQ1：英文MA包装 (UPC版本，首选1L，无1L可用多L含英语)+1张进口商贴纸，贴纸翻单4500106537 2. 产品和包装上的日期码一致，请按要求在包装上打日期码（进口商贴纸不覆盖日期码） 3. 使用ZURU标准日期码 Remark: 1.共出4港口(SYD,BNE,MEL,FRE)， 不同港口数量信息请见订单行项目，并请参考箱唛资料，港口不同，箱唛资料也不同； 2. 箱唛不可出现任何手写内容（箱数除外），重量与实际一致且不可手写 3.此单出澳大利亚，请按澳洲标准生产并满足当地法规要求 4.出无闪粉版本，需符合欧洲微塑料法规 | Y100: Christine Liao | Z100: 2.8789 | AA100: =I100*Z100 -> 1203.3802 | AB100: 418 | AC100: =AB100-I100 -> 0 | AD100: ok | AE100: 9543GQ1-S001 | AF100: 已入 | AG100: 系统出单 | AH100: 94581-3.19 | AL100: =I100 -> 418 | AT100: =I100 -> 418 | AX100: =I100/11 -> 38 | BW100: 增加移印布标内容 | BX100: =I100/22*5 -> 95 | BY100: =I100/22*6 -> 114 | BZ100: =I100/22*6 -> 114 | CA100: =I100/22*5 -> 95 | CB100: =I100 -> 418 | CC100: =I100/11 -> 38 | CD100: =SUM(BX100:CA100) -> 418 | CE100: =I100-CD100 -> 0
...

Sheet 布料MA
A1: Description | C1: Ratio | F1: MA-RR-758 | G1: MA-RR-784 | H1: MA-RR-808 | I1: MA-RR-858 | M1: Total
A2: 下单日期 | C2: Bulk | D2: GQ1 | E2: SK | F2: 44853 | G2: 44897 | H2: 45005 | I2: 45039
A3: 要求完货日期 | F3: 44995 | G3: 45021 | H3: 45095 | I3: 45143
B4: 透明球 | F4: =SUM(F6:F9) -> 120000 | G4: =SUM(G6:G9) -> 80000 | H4: =SUM(H6:H9) -> 106000 | I4: 136000 | M4: =SUM(F4:I4) -> 442000
A5: SUM | F5: =SUM(F4:F4) -> 120000 | G5: =SUM(G4:G4) -> 80000 | H5: =SUM(H4:H4) -> 106000 | I5: 136000 | M5: =SUM(M4:M4) -> 442000
A6: 9543# Hamstermania | B6: 蓝色仓鼠(Blue) | C6: 6 | D6: 5 | E6: 6 | F6: 30000 | G6: 20000 | H6: 20000 | I6: 23000 | M6: =SUM(F6:I6) -> 93000
B7: 粉色仓鼠(Pink) | C7: 6 | D7: 6 | E7: 8 | F7: 30000 | G7: 20000 | H7: 41000 | I7: 62000 | M7: =SUM(F7:I7) -> 153000
B8: 紫色仓鼠(Purple) | C8: 6 | D8: 6 | E8: 8 | F8: 30000 | G8: 20000 | H8: 25000 | I8: 28000 | M8: =SUM(F8:I8) -> 103000
B9: 土黄色仓鼠(Orange) | C9: 6 | D9: 5 | E9: 7 | F9: 30000 | G9: 20000 | H9: 20000 | I9: 23000 | M9: =SUM(F9:I9) -> 93000
A10: SUM | C10: =SUM(C6:C9) -> 24 | D10: =SUM(D6:D9) -> 22 | E10: =SUM(E6:E9) -> 29 | F10: =SUM(F6:F9) -> 120000 | G10: =SUM(G6:G9) -> 80000 | H10: =SUM(H6:H9) -> 106000 | I10: 136000 | M10: =SUM(M6:M9) -> 442000
A11: 9543GQ1/GQ3/SK Demo（无功能） | B11: 粉色仓鼠(Pink)-Demo | H11: 20000 | M11: =SUM(F11:I11) -> 20000
A12: SUM | F12: =SUM(F11:F11) -> 0 | G12: =SUM(G11:G11) -> 0 | H12: =SUM(H11:H11) -> 20000 | I12: 0 | M12: =SUM(M11:M11) -> 20000

Sheet 9543包装MA
A1: 9543-仓鼠
A2: 日期 | C2: MA PO | D2: 負責 | E2: 扣MA | J2: 扣MA | M2: 扣MA | R2: 标准版 | U2: 标准版 | X2: 客办 | AP2: 标准版 | AQ2: 标准版
E3: MA 1語收縮膜 | F3: MA 1語收縮膜-B版本 | G3: MA 1語收縮膜-C版本 | H3: MA 1語收縮膜-D版本 | I3: MA 1語收縮膜-E版本 | J3: MA 3語收縮膜-A版本 | K3: MA 3語收縮膜-C版本 | L3: MA 3語收縮膜-D版本 | M3: MA 9語收藏指南-A版本 | N3: MA 9語收藏指南-B版本 | O3: MA 5語收藏指南-A版本 | P3: MA 5語收藏指南-B版本 | Q3: 客办说明书 | R3: GQ1-1L-A版本 | S3: GQ1-1L-B版本 | T3: GQ1-1L-C版本 | U3: GQ1-3L-A版本 | V3: GQ1-3L-B版本 | W3: GQ1-3L-C版本 | X3: GQ2-3L-KM单-WMCA-A版本 | Y3: GQ2-3L-KM单-WMCA-B版本 | Z3: GQ2-3L-KM单-WMCA-C版本 | AA3: GQ2-3L-KM单-WMCA-D版本 | AB3: GQ3-1L-客办 | AC3: GQ3-1L-客办-B版本 | AD3: GQ4-3L-TG单-A版本 | AE3: GQ4-3L-TG单-B版本 | AF3: GQ4-3L-TG单-C版本 | AG3: GQ4-3L-TG单-D版本 | AH3: TQ1 WM单 | AI3: TQ2 | AJ3: GQ5-A版本 | AK3: GQ5-B版本 | AL3: GQ6 | AM3: GQ6-B版本 | AN3: 客办收缩膜 | AO3: 客办PDQ | AP3: 9543 SK-S001展示架-无底盒-3L | AQ3: 9543 SK-S002展示架-有底盒-3L | AR3: 客办扣数PO
E4: A版本 | F4: B版本 | J4: A版本 | M4: A版本 | N4: B版本 | R4: A版本 | U4: A版本 | X4: A版本 | AB4: A版本 | AD4: A版本 | AH4: A版本 | AJ4: A版本
A5: 44923 | C5: 1000012936 | D5: Emily | E5: 80000
A6: 44923 | C6: 1000012937 | D6: Emily | M6: 80000
A7: 44923 | C7: 1000012938 | D7: Emily | R7: 2000
X8: 730 | AR8: @sara 4500095104 4500095105 4500096539 4500096550
A9: 44992 | B9: 44992 | C9: 1000013403 | D9: Emily | J9: 50000
A10: 44992 | B10: 44992 | C10: 1000013397 | D10: Emily | N10: 50000
A11: 44992 | B11: 44992 | C11: 1000013402 | D11: Emily | U11: 2000
B12: 45002 | D12: Daisy | X12: =2882+166 -> 3048 | AR12: @Willow 4500097125 & 4500097126 & 4500097127 & 4500097128 & 4500097511 & 4500103368 & 4500103370 & 4500105660 & 4500105661 & 4500106312 & 4500111177 & 4500111176
A13: 45006 | C13: 1000013551 | AH13: 1932 | AR13: Effy 用于订单 4500097065 4500097066
A14: 45020 | D14: Peggy Wu | AD14: 2548 | AR14: Holly/Jaycee 4500095175
A15: 45020 | C15: 1000013752 | D15: Emily | F15: 50000
A16: 45020 | C16: 1000013750 | D16: Emily | N16: 50000
A17: 45020 | C17: 1000013743 | D17: Emily | R17: 3000
A18: 45020 | C18: 1000013751 | D18: Emily | U18: 2000
C19: 1000013945 | D19: Charine Chen | AN19: 30000 | AR19: Linda#PO#4500094401-4500097498-4500101349-4500102943-4500102361-4500101675
C20: 1000013946 | D20: Charine Chen | AO20: 1603 | AR20: Linda#PO#4500094401-4500097498-4500102943-4500102361
A21: 45037 | B21: 45037 | C21: 1000014631 | D21: Emily | F21: 50000
A22: 45037 | B22: 45037 | C22: 1000014632 | D22: Emily | J22: 30000
A23: 45037 | B23: 45037 | C23: 1000014633 | D23: Emily | N23: 100000
A24: 45037 | B24: 45037 | C24: 1000014634 | D24: Emily | R24: 5000
A25: 45037 | B25: 45037 | C25: 1000014635 | D25: Emily | U25: 2000
A26: 45037 | B26: 45042 | C26: 10000114110 | D26: Emily | AQ26: 300
AB27: 448
C28: 1000014104 | D28: Daisy | AH28: 4256 | AR28: Effy用于订单 4500101892 4500101897 4500101900 4500101913 4500101901 4500101920 4500101923 4500101925 4500101928
C29: 1000014159 | D29: Charine Chen | AB29: 1140 | AR29: Sheba#TESCO UK NEW PO 4500096046 & 4500100986 & 4500106764
B30: 45044 | C30: 1000014162 | D30: Emily | F30: 100000
B31: 45044 | C31: 1000014163 | D31: Emily | N31: 100000
B32: 45042 | C32: 1000014164 | D32: Emily | AP32: 300
B33: 45055 | C33: 1000014298 | D33: Peggy Wu | AD33: 917 | AR33: @Holly/Jaycee 4500102786&4500103118
B34: 45061 | C34: 1000014386 | D34: Daisy | AL34: 1780 | AR34: Coral用于PO#4500100969 4500099925
B35: 45072 | C35: 1000014579 | D35: Charine Chen | AN35: 30000 | AR35: 4500102945-4500104422-4500105374-4500105999-4500104088-4500106823-4500107294-4500108108-4500108130
B36: 45072 | C36: 1000014580 | D36: Charine Chen | AO36: 951 | AR36: 4500102945-4500104422
B37: 45072 | C37: 1000014558 | D37: Daisy | AH37: 9408 | AR37: Effy用于订单 4500104809 4500104811 4500104812 4500104814 4500104815 4500104820 4500104822 4500104816 4500104817 4500104825 4500104828 4500104829 4500104830 4500104818 4500104832
B38: 45079 | D38: Peggy Wu | AE38: 583 | AR38: JayceePO#4500104446
B39: 45084 | C39: 1000014710 | D39: Daisy | AH39: 9354 | AR39: Effy用于订单 4500098420 4500098422 4500098423 4500098425 4500098426 4500098427 4500098434 4500098471 4500098473 4500098475 4500098476 4500099624 4500099625 4500099626 4500099627 4500099628 4500099629 4500099630 4500099631 4500099632
B40: 45093 | C40: 1000014944 | D40: Emily | F40: 60000
B41: 45093 | C41: 1000014945 | D41: Emily | N41: 40000
B42: 45106 | C42: 1000015122 | D42: Emily | F42: 100000
B43: 45106 | C43: 1000015123 | D43: Emily | N43: 100000
AJ44: 2565
AJ45: 764 | AR45: 4500103607
AJ46: 150 | AR46: 4500106355
B47: 45111 | D47: Peggy Wu | AE47: 500 | AR47: JayceePO#4500107612
B48: 45111 | C48: 1000015256 | D48: Daisy.Li | AH48: 7672 | AR48: Effy用于订单 4500108039 4500108041 4500108041 4500108042 4500108043 4500108044 4500108045 4500108047 4500108048 4500108048 4500108050
B49: 45111 | C49: 1000015258 | D49: Emily | U49: 1500
B50: 45118 | C50: 1000015377 | D50: Camilla Han | Y50: 732 | AR50: 4500106715 & 4500106717 & 4500107715 & 4500107717
B51: 45121 | C51: 1000015465 | D51: Emily | N51: 50000
B52: 45121 | C52: 1000015466 | D52: Emily | R52: 1000
B53: 45121 | C53: 1000015467 | D53: Emily | U53: 500
B54: 45121 | D54: Peggy Wu | AE54: 1667 | AR54: JayceePO#4500108451
B55: 45124 | D55: Peggy Wu | AJ55: 2014 | AR55: JasminePO#4500107170-107175/4500107178/4500107178/4500107181/4500107185/4500107186/4500107187
B56: 45125 | C56: 1000015478 | D56: Daisy.Li | AN56: 30000 | AR56: Sherry Smyths 4500108866-4500111219-4500110481-4500110417-4500108542
B57: 45128 | C57: 1000015564 | D57: Daisy.Li | AO57: 690 | AR57: Linda VEDES 4500108685: 80个PDQ Linda Smyths 4500108836: 182个PDQ
B58: 45131 | C58: 1000015641 | D58: Emily | U58: =500-121 -> 379
B59: 45135 | C59: 1000015714 | D59: Peggy Wu | AE59: 3842 | AR59: JayceePO#4500109494/4500109727
B60: 45145 | C60: 1000015856 | D60: Emily | F60: 100000
B61: 45145 | C61: 1000015857 | D61: Emily | N61: 100000
B62: 45145 | C62: 1000015858 | D62: Emily | R62: 3000
B63: 45140 | D63: Effy | AH63: 4336 | AR63: 4500109531 & 4500110379
B64: 45146 | D64: Camilla, | Y64: =1000+250 -> 1250 | AR64: 4500109266 & 4500109267 & 4500110045 & 4500110046 & 4500111958
B65: 45148 | C65: 1000015910 | D65: Winnie | AO65: 500 | AR65: 4500110481
B66: 45152 | D66: Peggy Wu | AE66: 1775 | AR66: JayceePO#4500110662 | AS66: `
B67: 45153 | C67: 1000016000 | D67: Emily | G67: 100000
B68: 45153 | C68: 1000016001 | D68: Emily | O68: 100000
B69: 45153 | C69: 1000016002 | D69: Emily | R69: =2000+48 -> 2048
B70: 45159 | AJ70: =500+132 -> 632 | AR70: 4500111182
B71: 45166 | AB71: 500 | AR71: 4500111360
B72: 45166 | AL72: 560 | AR72: 4500111831
B73: 45168 | AH73: 3240 | AR73: 4500112236
B74: 45169 | C74: 1000016226 | D74: Emily | V74: 500
B75: 45176 | C75: 1000016275 | AF75: 1750 | AR75: JayceePO#4500112629/4500112630
B76: 45180 | C76: 1000016330 | D76: Emily | J76: 30000
B77: 45180 | C77: 1000016318 | D77: Emily | V77: 1000
B78: 45187 | C78: 1000016439 | D78: Emily | S78: 1000
B79: 45187 | C79: 1000016443 | D79: Camilla | AB79: 1260 | AR79: Sheba#TESCO UK NEW PO#4500112525 #4500112527
B80: 45206 | C80: 1000016585 | Z80: 500 | AR80: 4500114715 & 4500117791 & 4500117793 4500124321-142pcs | AS80: =Z80-358-142 -> 0
B81: 45206 | C81: 1000016587 | AH81: =4212-8 -> 4204 | AR81: 4500114804 & 4500114815
B82: 45211 | C82: 1000016678 | AF82: 500 | AR82: JayceePO#4500113632-333pcs, 多出的167pcs 下次订单消耗
B83: 45215 | C83: 1000016741 | AC83: 500 | AR83: sheba#4500115674
B84: 45218 | C84: 1000016793 | AO84: 500 | AR84: Daisy-Smyths-4500111219-176PCS Winnie-ROFU Kinderland Spielwarenhandelsge-200pcs Rose-SUOMEN OSUUSKAUPPOJEN-186pcs 4500113295
B85: 45219 | AF85: 3167 | AR85: JayceePO#4500114883 & 4500116272
B86: 45222 | C86: 1000016845 | H86: 60000
B87: 45222 | C87: 1000016846 | O87: 60000
B88: 45222 | C88: 1000016847 | S88: 1000
B89: 45222 | C89: 1000016848 | V89: 1000
B90: 45225 | C90: 1000016925 | AH90: 3240
B91: 45239 | AF91: 2166 | AR91: Jaycee/KathyPO#4500116705/4500117622
B92: 45239 | C92: 1000017194 | H92: 60000
B93: 45239 | C93: 1000017202 | K93: 30000
B94: 45239 | C94: 1000017196 | O94: 100000
B95: 45239 | C95: 1000017197 | S95: 2000
B96: 45239 | C96: 1000017198 | V96: 500
B97: 45239 | C97: 1000017209 | Z97: 750 | AR97: 用于4500115741-192PCS; 4500115742-58PCS; 4500116403-470PCS; 4500116404-30PCS | AS97: =Z97-750 -> 0
B98: 45246 | C98: 1000017325 | AK98: 975 | AR98: 用于4500114433/4500114438/4500114441/4500114443/4500114445/4500114447/4500114449/4500114450/4500114451/4500114452/4500114454/4500114456
B99: 45246 | AH99: 7503 | AR99: 4500118791 & 4500118904 & 4500117911
B100: 45265 | C100: 1000017651 | H100: 50000
...

Sheet 9543MA半成品
A1: MA半成品扣數表 | L1: IC扣數表
A2: MA訂單號 | B2: 日期 | C2: #9543 | L2: MA訂單號 | M2: 日期 | N2: #9543
C3: 蓝色仓鼠 | D3: 粉色仓鼠 | E3: 紫色仓鼠 | F3: 土黄色仓鼠 | G3: 透明球 | H3: 四款合计 | I3: 无功能粉色仓鼠 | J3: 完成时间 | O3: 收货时间
C4: (Blue) | D4: (Pink) | E4: (Purple) | F4: (Orange)
A5: MA-RR-758 | B5: 44853 | C5: 30000 | D5: 30000 | E5: 30000 | F5: 30000 | G5: =SUM(C5:F5) -> 120000 | H5: =SUM(C5:F5) -> 120000 | J5: 44995 | L5: MA_RR_729 | M5: 44790 | N5: 68000
A6: MA-RR-784 | B6: 44897 | C6: 20000 | D6: 20000 | E6: 20000 | F6: 20000 | G6: =SUM(C6:F6) -> 80000 | H6: =SUM(C6:F6) -> 80000 | J6: 45021 | L6: MA_RR_737 | M6: 44805 | N6: 34000 | P6: 旧IC
A7: MA-RR-808 | B7: 45005 | C7: 20000 | D7: 41000 | E7: 25000 | F7: 20000 | G7: =SUM(C7:F7)+I7 -> 126000 | H7: =SUM(C7:F7) -> 106000 | I7: 20000 | J7: 45095 | L7: MA_RR_751 | M7: 44834 | N7: 102000 | P7: 旧IC
A8: MA-RR-858 | B8: 45039 | C8: 23000 | D8: 62000 | E8: 28000 | F8: 23000 | G8: =SUM(C8:F8) -> 136000 | H8: =SUM(C8:F8) -> 136000 | J8: 45143 | L8: MA_RR_815 | M8: 44984 | N8: 102000 | P8: 旧IC
A9: MA-RR-888 | B9: 45064 | C9: 21000 | D9: 38000 | E9: 21000 | F9: 22000 | G9: =SUM(C9:F9)+I9 -> 107000 | H9: =SUM(C9:F9) -> 102000 | I9: 5000 | J9: 45181 | L9: MA_RR_859 | M9: 45043 | N9: 136000 | P9: 旧IC
A10: MA-RR-894 | B10: 45082 | C10: 21000 | D10: 21500 | E10: 22500 | F10: 20000 | G10: =SUM(C10:F10) -> 85000 | H10: =SUM(C10:F10) -> 85000 | J10: 45188 | L10: MA_RR_889 | M10: 45064 | N10: 102000 | O10: 45096 | P10: 旧IC
A11: MA-RR-905 | B11: 45089 | D11: 34000 | G11: =SUM(C11:F11) -> 34000 | H11: =SUM(C11:F11) -> 34000 | J11: 45195 | L11: MA_RR_892 | M11: 45079 | N11: 85000 | O11: 45108 | P11: 旧IC
A12: MA-RR-913 | B12: 45111 | C12: 22500 | E12: 23000 | F12: 22500 | G12: =SUM(C12:F12) -> 68000 | H12: =SUM(C12:F12) -> 68000 | J12: 45208 | L12: MA_RR_906 | M12: 45091 | N12: 34000 | O12: 45117 | P12: 旧IC
A13: MA-RR-931 | B13: 45134 | C13: 20000 | D13: 22500 | E13: 22500 | F13: 20000 | G13: =SUM(C13:F13)+I13 -> 90000 | H13: =SUM(C13:F13) -> 85000 | I13: 5000 | J13: 45208 | L13: MA_RR_914 | M13: 45112 | N13: 68000 | O13: 45142 | P13: 旧IC
A14: MA-RR-948 | B14: 45152 | C14: 20000 | D14: 33000 | E14: 24000 | F14: 25000 | G14: =SUM(C14:F14)+I14 -> 107000 | H14: =SUM(C14:F14) -> 102000 | I14: 5000 | J14: 45252 | L14: MA_RR_932 | M14: 45132 | N14: 85000 | O14: 45161 | P14: 旧IC
A15: MA-RR-960 | B15: 45180 | C15: 20000 | D15: 25000 | E15: 20000 | F15: 20000 | G15: =SUM(C15:F15)+I15 -> 95000 | H15: =SUM(C15:F15) -> 85000 | I15: 10000 | J15: 45280 | L15: MA_RR_949 | M15: 45152 | N15: 102000 | O15: 45190 | P15: 旧IC
A16: MA-RR-1001 | B16: 45237 | C16: 20000 | D16: 28000 | E16: 20000 | F16: 20000 | G16: =SUM(C16:F16)+I16 -> 98000 | H16: =SUM(C16:F16) -> 88000 | I16: 10000 | J16: 45330.857 | L16: MA_RR_961 | M16: 45180 | N16: 85000 | P16: 旧IC
A17: MA-RR-1028 | B17: 45273 | C17: 20000 | D17: 30000 | E17: 20000 | F17: 20000 | G17: =SUM(C17:F17)+I17 -> 100000 | H17: =SUM(C17:F17) -> 90000 | I17: 10000 | J17: 45365 | M17: 45208 | N17: 34000 | P17: 旧IC
A18: MA-RR-1064 | B18: 45301 | C18: 20000 | D18: 30000 | E18: 20000 | F18: 20000 | G18: =SUM(C18:F18)+I18 -> 90000 | H18: =SUM(C18:F18) -> 90000 | J18: 45412 | L18: MA_RR_998 | M18: 45229 | N18: 54000 | P18: 新供应商：矽源特
A19: MA-RR-1106 | B19: 45356 | C19: 20000 | D19: 43000 | E19: 25000 | F19: 20000 | G19: =SUM(C19:F19)+I19 -> 118000 | H19: =SUM(C19:F19) -> 108000 | I19: 10000 | J19: 45435 | L19: MA_RR_1022 | M19: 45265 | N19: 90000 | P19: 新供应商：矽源特
A20: MA-RR-1128 | B20: 45370 | C20: 20000 | D20: 57000 | E20: 27000 | F20: 22000 | G20: =SUM(C20:F20)+I20 -> 126000 | H20: =SUM(C20:F20) -> 126000 | J20: 45474.571 | L20: MA_RR_1050 | M20: 45286 | N20: 90000 | P20: 新供应商：矽源特
A21: MA-RR-1157 | B21: 45390 | C21: 20000 | D21: 37000 | E21: 27000 | F21: 24000 | G21: =SUM(C21:F21)+I21 -> 118000 | H21: =SUM(C21:F21) -> 108000 | I21: 10000 | J21: 45509 | L21: MA_RR_1071 | M21: 45315 | N21: 108000 | P21: 新供应商：矽源特
A22: MA-RR-1196 | B22: 45411 | C22: 22000 | D22: 52000 | E22: 27000 | F22: 25000 | G22: =SUM(C22:F22)+I22 -> 126000 | H22: =SUM(C22:F22) -> 126000 | J22: 45522 | L22: MA_RR_1129 | M22: 45370 | N22: 126000 | P22: 新供应商：矽源特
A23: MA-RR-1218 | B23: 45422 | D23: 54000 | G23: =SUM(C23:F23)+I23 -> 54000 | H23: =SUM(C23:F23) -> 54000 | J23: 45547 | L23: MA_RR_1152 | M23: 45385 | N23: 108000 | P23: 新供应商：矽源特
A24: MA-RR-1228 | B24: 45427 | C24: 32500 | D24: 20000 | E24: 27500 | F24: 28000 | G24: =SUM(C24:F24)+I24 -> 118000 | H24: =SUM(C24:F24) -> 108000 | I24: 10000 | J24: 45552 | L24: MA_RR_1193 | M24: 45410 | N24: 72000 | P24: 新供应商：矽源特
A25: MA-RR-1290 | B25: 45467 | C25: 24500 | D25: 33500 | E25: 26500 | F25: 23500 | G25: =SUM(C25:F25)+I25 -> 118000 | H25: =SUM(C25:F25) -> 108000 | I25: 10000 | J25: 45595 | L25: MA_RR_1197 | M25: 45410 | N25: 54000 | P25: 新供应商：矽源特
A26: MA-RR-1385 | B26: 45559 | C26: 20000 | D26: 25000 | E26: 20000 | G26: =SUM(C26:F26)+I26 -> 65000 | H26: =SUM(C26:F26) -> 65000 | J26: 45614 | L26: MA_RR_1217 | M26: 45422 | N26: 54000 | P26: 新供应商：矽源特
A27: MA-RR-1413 | B27: 45582 | F27: 20000 | G27: =SUM(C27:F27)+I27 -> 20000 | H27: =SUM(C27:F27) -> 20000 | J27: 45639 | L27: MA_RR_1227 | M27: 45427 | N27: 108000 | P27: 新供应商：矽源特
A28: MA-RR-1450 | B28: 45618 | C28: 22000 | D28: 26000 | E28: 27000 | F28: 20000 | G28: =SUM(C28:F28)+I28 -> 115000 | H28: =SUM(C28:F28) -> 95000 | I28: 20000 | J28: 45342 | L28: MA_RR_1294 | M28: 45468 | N28: 108000 | P28: 新供应商：矽源特
A29: MA-RR-1468 | B29: 45630 | C29: 23000 | D29: 24000 | E29: 23000 | F29: 20000 | G29: =SUM(C29:F29)+I29 -> 90000 | H29: =SUM(C29:F29) -> 90000 | J29: 45666 | L29: MA_RR_1346 | M29: 45504 | N29: 54000 | P29: 新供应商：矽源特
A30: MA-RR-1595 | B30: 45733 | C30: 20000 | D30: 28500 | E30: 20000 | F30: 21500 | G30: =SUM(C30:F30)+I30 -> 90000 | H30: =SUM(C30:F30) -> 90000 | J30: 45795 | L30: MA_RR_1380 | M30: 45539 | N30: 18000 | P30: 新供应商：矽源特
A31: MA-RR-1637 | B31: 45784 | C31: 20000 | D31: 25000 | E31: 25000 | F31: 20000 | G31: =SUM(C31:F31)+I31 -> 90000 | H31: =SUM(C31:F31) -> 90000 | J31: 45859 | L31: MA_RR_1393 | M31: 45559 | N31: 36000 | P31: 新供应商：矽源特
A32: MA-RR-1709 | B32: 45806 | C32: 20000 | D32: 25000 | E32: 25000 | F32: 20000 | G32: =SUM(C32:F32)+I32 -> 100000 | H32: =SUM(C32:F32) -> 90000 | I32: 10000 | J32: 45881 | L32: MA_RR_1433 | M32: 45593 | N32: 72000 | P32: 新供应商：矽源特
A33: MA-RR-1790 | B33: 45849 | C33: 24000 | D33: 20000 | E33: 25000 | F33: 21000 | G33: =SUM(C33:F33)+I33 -> 100000 | H33: =SUM(C33:F33) -> 90000 | I33: 10000 | J33: 45940 | L33: MA_RR_1463 | M33: 45625 | N33: 90000 | P33: 新供应商：矽源特
A34: MA-RR-1943 | B34: 45954 | C34: 20500 | D34: 23500 | E34: 22000 | F34: 24000 | G34: =SUM(C34:F34)+I34 -> 90000 | H34: =SUM(C34:F34) -> 90000 | J34: 45985 | L34: MA_RR_1496 | M34: 45702 | N34: 72000 | P34: 新供应商：矽源特
A35: MA-RR-1999 | B35: 46000 | C35: 20000 | D35: 25000 | E35: 25000 | F35: 20000 | G35: =SUM(C35:F35)+I35 -> 100000 | H35: =SUM(C35:F35) -> 90000 | I35: 10000 | J35: 46027 | L35: MA_RR_1604 | M35: 45742 | N35: 72000 | P35: 新供应商：矽源特（降价）
A36: MA-RR-2133 | B36: 46091 | C36: 32000 | D36: 40500 | E36: 37500 | F36: 34000 | G36: =SUM(C36:F36)+I36 -> 144000 | H36: =SUM(C36:F36) -> 144000 | J36: 46213 | L36: MA_RR_1638 | N36: 36000 | P36: 新供应商：矽源特（降价）
A37: MA-RR-2317 | B37: 46167 | C37: 22500 | D37: 22250 | E37: 22750 | F37: 22500 | G37: =SUM(C37:F37)+I37 -> 90000 | H37: =SUM(C37:F37) -> 90000 | J37: 46275 | L37: MA_RR_1697 | M37: 45804 | N37: 72000 | P37: 新供应商：矽源特（降价）
A38: MA-RR-2467 | B38: 46240 | C38: 20000 | D38: 26000 | E38: 24000 | F38: 20000 | G38: =SUM(C38:F38)+I38 -> 100000 | H38: =SUM(C38:F38) -> 90000 | I38: 10000 | J38: 46320 | L38: MA_RR_1710 | M38: 45806 | N38: 18000 | P38: 新供应商：矽源特（降价）
L39: MA_RR_1756 | M39: 45838 | N39: 90000 | P39: 新供应商：矽源特（降价）
L40: MA_RR_1811 | M40: 45866 | N40: 54000 | P40: 新供应商：矽源特（降价）
B41: MA合計 | C41: =SUM(C5:C40) -> 680500 | D41: =SUM(D5:D40) -> 1022250 | E41: =SUM(E5:E40) -> 752250 | F41: =SUM(F5:F40) -> 688000 | G41: =SUM(G5:G40) -> 3308000 | H41: =SUM(H5:H40) -> 3143000 | I41: =SUM(I5:I40) -> 165000 | J41: =SUM(H41:I41) -> 3308000 | L41: MA_RR_1864 | M41: 45901 | N41: 36000 | P41: 新供应商：矽源特（降价）
B42: 23年删除数： | C42: 188624.32 | D42: 313646.68 | E42: 208240.68 | F42: 193857.32 | G42: 940610.73 | H42: =SUM(C42:F42) -> 904369 | I42: 37137.727 | L42: MA_RR_1900 | M42: 45925 | N42: 36000 | P42: 新供应商：矽源特（降价）
B43: 24年删除数： | C43: 218368 | D43: 393913.5 | E43: 240537.5 | F43: 214994 | G43: 1007742.5 | H43: =SUM(C43:F43) -> 1067813 | I43: 52973 | L43: MA_RR_1944 | M43: 45957 | N43: 36000 | P43: 新供应商：矽源特（降价）
B44: PO接單數量 | C44: ='9543'!BX903+C42+C43 -> 640056.73 | D44: ='9543'!BY903+D42+D43 -> 976131.77 | E44: ='9543'!BZ903+E42+E43 -> 705421.77 | F44: ='9543'!CA903+F42+F43 -> 649227.73 | G44: ='9543'!CB903+G42+G43 -> 2865777.2 | H44: =SUM(C44:F44) -> 2970838 | I44: ='9543'!CC903+I42+I43 -> 148711.73 | J44: =SUM(H44:I44) -> 3119549.7 | L44: MA_RR_1974 | M44: 45989 | N44: 36000 | P44: 新供应商：矽源特（降价）
B45: 樣板PO接單數 | L45: MA_RR_2020 | M45: 46015 | N45: 36000 | P45: 新供应商：矽源特（降价）
B46: MA半成品剩餘數 | C46: =C41-C44-C45 -> 40443.273 | D46: =D41-D44-D45 -> 46118.227 | E46: =E41-E44-E45 -> 46828.227 | F46: =F41-F44-F45 -> 38772.273 | G46: =G41-G44-G45 -> 442222.77 | H46: =H41-H44 -> 172162 | I46: =I41-I44 -> 16288.273 | J46: =J41-J44 -> 188450.27 | L46: MA_RR_2050 | M46: 46031 | N46: 90000 | P46: 新供应商：矽源特（降价）
B47: MA剩餘總數 | C47: =SUM(C46:F46) -> 172162 | L47: MA_RR_2318 | M47: 46167 | N47: 90000 | P47: 新供应商：矽源特（降价）
L48: MA_RR_2466 | M48: 46240 | N48: 90000 | P48: 新供应商：矽源特（降价）
K49: =I42+I43 -> 90110.727
C50: 425731.07 | D50: 730835.93 | E50: 467325.93 | F50: 425934.07 | G50: 2024486.2 | H50: 2049827 | I50: 95177.727 | J50: 2145004.7 | M50: MA合計 | N50: =SUM(N5:N49) -> 3143000
C51: =C50-C44 -> -214325.66 | D51: =D50-D44 -> -245295.84 | E51: =E50-E44 -> -238095.84 | F51: =F50-F44 -> -223293.66 | G51: =G50-G44 -> -841291 | H51: =H50-H44 -> -921011 | I51: =I50-I44 -> -53534 | M51: PO接單數量 | N51: =H41 -> 3143000
M52: MA IC 剩餘總數 | N52: =N50-N51 -> 0
C53: 567000 | D53: 1046000 | E53: 629000 | F53: 572000 | G53: =SUM(C53:F53) -> 2814000
P54: =N47-C47 -> -82162
C56: 蓝色仓鼠 | D56: 粉色仓鼠 | E56: 紫色仓鼠 | F56: 土黄色仓鼠 | G56: 无功能粉色仓鼠 | H56: 备注
B57: 截止2024/5月底每款毛绒实单数 | C57: 188624.32 | D57: 313646.68 | E57: 208240.68 | F57: 193857.32 | G57: 37137.727 | H57: 不包含提前订单数量毛绒
C58: 71767 | D58: =G57+137575+G58 -> 193265.73 | E58: 81535 | F58: 73162 | G58: 18553
B59: 合计： | C59: =SUM(C57:C58) -> 260391.32 | D59: =SUM(D57:D58) -> 506912.41 | E59: =SUM(E57:E58) -> 289775.68 | F59: =SUM(F57:F58) -> 267019.32 | G59: =SUM(G57:G58) -> 55690.727
B60: 已交毛绒实数： | C60: 288724 | D60: 528183 | E60: 315358 | F60: 294997
B61: 剩余数： | C61: =C60-C59 -> 28332.682 | D61: =D60-D59 -> 21270.591 | E61: =E60-E59 -> 25582.318 | F61: =F60-F59 -> 27977.682

Sheet 取消订单
A1: 接单期 | B1: 第三方客户名称 | C1: 国家 | D1: PO号 | E1: 小PO号 | F1: SKU号 | G1: 系统货号 | H1: 货号 | I1: 名称 | J1: 数量 | K1: 内箱装箱数量(pcs) | L1: 装箱数（PCS） | M1: 总箱数 | N1: 计划出货期 | O1: 计划验货期 | P1: 取消时间 | Q1: 物料情况 | R1: 纸箱滞留 | S1: 箱唛资料(收到日期) | T1: 外箱贴纸 | U1: 客供贴纸AI(收到日期) | V1: 客供物料 | W1: 日期码 | X1: 备注 | Y1: ZURU 跟单 | Z1: 单价USD | AA1: 金额USD | AB1: 發票號 | AC1: 是否入系统 | AD1: MA 1語收縮膜 A版本 | AE1: MA 3语收缩膜 | AF1: 客版收縮膜 | AG1: MA 9语 收藏指南 A版本 | AH1: 客版收藏指南 | AI1: GQ1-MA 1L | AJ1: GQ1-MA 3L | AK1: GQ2-MA 1L KM单+WM-CA | AL1: GQ3- 客版 1L | AM1: GQ4-MA 1L TG单 | AN1: TQ1 WM单 | AQ1: 客版PDQ | AR1: 客办收缩膜 | AT1: 布標 | AU1: 發票號 | AV1: 蓝色仓鼠(Blue) | AW1: 粉色仓鼠(Pink) | AX1: 紫色仓鼠(Purple) | AY1: 土黄色仓鼠(Orange) | AZ1: 透明球 | BA1: 无功能 粉色仓鼠 | BB1: 总数 | BC1: 相差 | BW1: 成品滞留
A2: 44986 | B2: SUOMEN OSUUSKAUPPOJEN | C2: 芬兰 | D2: 4500096312 | E2: =SUM(A2:C2) -> 44986 | F2: 4500096312-40 | G2: 9543GQ1-S001 | H2: 9543GQ1-S001 | I2: 仓鼠 | J2: 2002 | K2: 0 | L2: 22 | M2: =J2/L2 -> 91 | N2: 45056 | O2: 取消订单（3/16转PO) | S2: 欠 | U2: 欠EAN贴纸+警告语贴纸 | V2: 客办收藏指南 | X2: 日期码格式：ZURU 标准格式 日期：按实际生产日期 Packaging Info: 9543GQ1:1L A版收缩膜+1L A版PDQ+客版说明书+EAN贴纸+警告语贴纸 Remark: 1. 包装不可有PVC，包装上的吸塑需要用PET代替。 2. 产品要求无硼无香 3. 工厂款号 条码 9543GQ1 4894680026995 4. 产品信息： 9543GQ1:2pcs *AAA battery not include; bule/purple/pink/orange =5:6:6:5 5.此单有客人客验，请多备料。 6.出货前需寄3-4套大货样给客人签样。 7.客人需要大货样1pcs，请在4/21前寄到深圳办公室Luna签收 | Y2: Rose | Z2: 2.64 | AA2: =J2*Z2 -> 5285.28 | AD2: =J2 -> 2002 | AH2: =J2 -> 2002 | AI2: =J2/11 -> 182 | AT2: 无 | AV2: =J2/22*5 -> 455 | AW2: =J2/22*6 -> 546 | AX2: =J2/22*6 -> 546 | AY2: =J2/22*5 -> 455 | AZ2: =J2 -> 2002 | BA2: =J2/11 -> 182 | BB2: =SUM(AV2:AY2) -> 2002 | BC2: =BB2-J2 -> 0
A3: 45090 | B3: TARGET US | C3: 美国 | D3: 4500106533 | F3: 4500106533-10 | G3: 未接到实单 | H3: 9543GQ4-S001 | I3: 仓鼠 | J3: 15000 | K3: 0 | L3: 6 | M3: =J3/L3 -> 2500 | N3: 45159 | O3: 45211 | P3: 9/12取消订单 | S3: 欠 | U3: 无 | V3: 欠外箱贴纸 | X3: 日期码格式：ZURU INC(BVI) 标准格式 日期：按实际生产日期 Packaging Info: 9543GQ4: MA 1L，客版PDQ Remark: 1. 9543GQ4-S001-PETS ALIVE-HAMSTERMANIA- SERIES 1 CAPSULE,1Facing6pcs/Gravity PDQ,6pcs/CTN,No Inner,STD Color Assortment 2. 产品MA 1L包装，客版PDQ. 产品UPC显示193052050328, Integral single ratio=bule/purple/pink/orange =1:1:1:1 3. 外箱正唛左上角位置粘贴条码箱贴纸，每箱只贴一张，由ZURU订购。来料贴纸上显示的客户DPCI# 086-08-4053，UPC显示10193052050325; 4. 9543GQ4：Semi-Products (Customized PDQ), 做半成品-球，客版PDQ等我们通知再订购 6. 产品/包装:MA+1L, UPC显示 193052050014. MA PDQ 7. 外箱正唛左上角位置粘贴条码箱贴纸，每箱只贴一张，由ZURU订购。来料贴纸上显示的客户DPCI#086-08-3096， UPC显示10193052050011 10. MA 1L包装. 产品UPC显示193052050106,Kitten:Bunny:Puppy:Cow:Elephant:Flamingo=1:1:1:1:1:1; 11. 外箱正唛左上角位置粘贴条码箱贴纸，每箱只贴一张，由ZURU订购。来料贴纸上显示的客户DPCI# 086-08-6431，UPC显示10193052050103; 13. 产品和包装上印刷 tracking code信息，格式为ZURU常规格式; 14. 出货方式：货代自提。 | Y3: Holly Zheng | Z3: 2.5968 | AA3: =J3*Z3 -> 38952 | AC3: =AB3-J3 -> -15000 | AD3: ok | AI3: =J3 -> 15000 | AM3: =J3 -> 15000 | BH3: 3750 | BI3: 3750 | BJ3: 3750 | BK3: 3750 | BL3: 15000 | BN3: 15000 | BO3: 0
A4: 45089 | B4: ZURU | C4: 库有 | D4: MO20230612 | G4: 待定 | H4: 9543-S001 | I4: 仓鼠 | J4: 11000 | K4: 0 | L4: 24 | M4: =J4/L4 -> 458.33333 | N4: 45159 | O4: 45237 | P4: 未收到实单先取消9/28 | S4: 欠 | U4: 无 | V4: 欠客供RFID贴纸 | X4: 9543 1.包装信息：, MA A 版 1L收缩膜，MA A 版3L 收藏指南，客供RFID贴纸，客版PDQ 2.在外箱印刷带条码的箱唛以及四面印刷RFID的箱唛（新增ZURU黑色色带顶格四面印刷 ），不需要贴白色艾利贴纸(由我们提供艾利贴纸替代箱唛），箱唛内容见附件, 外箱侧面任一角落标注"MADE IN CHINA" 字样。每个slip sheet上面贴一张艾利贴纸和一张普通贴纸（可A4纸打印），slip sheet打印的普通贴纸的尺寸不能比艾利贴纸小。 3.产品如有扎带口要剪平，不能刮手。 4.此单需要验货以及抽板做测试，请自行多备包装物料。 5.此单打卡板出货 2Facing2pcs/PDQ, 2pcs *AAA battery not include | AC4: =AB4-J4 -> -11000 | AJ4: =J4 -> 11000 | AO4: =J4 -> 11000 | BB4: 确认后再订 | BM4: =J4 -> 11000 | BP4: 11000 | BR4: 11000 | BS4: 0
A5: 45215 | B5: FREDMEYER INC | C5: 美国 | D5: 4500116041 | E5: 30615474 | F5: 4500116041-10 | G5: 9543GQ1-S002 | H5: 9543GQ1-S002 | I5: 仓鼠 | J5: 3498 | K5: 0 | L5: 11 | M5: =J5/L5 -> 318 | N5: 45247 | O5: 45251 | P5: 11/9取消订单 | S5: 10/16收到 | U5: 无 | X5: 日期码格式：ZURU INC(BVI) 标准格式 日期：按实际生产日期 Packaging Info: 1、包装方式: MA UPC优先1L最新版包装，出口美国 Remark: 2、无测试无验货要求。 3、纸箱4面印ZURU LOGO + 箱唛。 4、日期码请按ZURU标准版执行即可。 5、ZURU QC验货。 6、REMARK: #9543GQ1: 2pcs *AAA battery not include; Integral single ratio=bule/purple/pink/orange =5:6:6:5; | Y5: Vicky Wu | Z5: 2.7038 | AA5: =J5*Z5 -> 9457.8924 | AC5: =AB5-J5 -> -3498 | AF5: 已入 | AG5: 系统出单 | AJ5: =J5 -> 3498 | AP5: =J5 -> 3498 | AS5: =J5/11 -> 318 | BL5: 增加移印布标内容 | BN5: =J5/22*5 -> 795 | BO5: =J5/22*6 -> 954 | BP5: =J5/22*6 -> 954 | BQ5: =J5/22*5 -> 795 | BR5: =J5 -> 3498 | BS5: =J5/11 -> 318 | BT5: =SUM(BN5:BQ5) -> 3498 | BU5: =BT5-J5 -> 0
A6: 45307 | B6: WALGREEN CO. | C6: 美国 | D6: 4500123425 | E6: 4540327798 | F6: 4500123425-70 | G6: 9543GQ5-S001 | H6: 9543GQ5-S001 | I6: 仓鼠 | J6: 900 | K6: 0 | L6: 12 | M6: =J6/L6 -> 75 | N6: 45377 | O6: 45373 | P6: 转4500126820消耗 | S6: 1/19收到 | U6: WIC 贴纸（翻单PO 4500099653） +PDQ折页 （翻单PO 4500099653 | W6: DG20240326 | X6: 日期码格式：ZURU INC(BVI) 标准格式 日期：03-26-2024 Packaging Info: Remark: MA 1L 包装 + WIC 贴纸（翻单PO 4500099653） + 客版PDQ （同PO4500114433）+ PDQ折页 （翻单PO 4500099653，PDQ折页放在PDQ的正上方，开箱即可看到） 产品和包装/外箱上面要有zuru标准格式的tracking code DG20240326 | Y6: Cara Li | Z6: 2.7269 | AA6: =J6*Z6 -> 2454.21 | AC6: =AB6-J6 -> -900 | AD6: ok | AF6: 已入 | AG6: 系统出单 | AK6: =J6 -> 900 | AQ6: =J6 -> 900 | BN6: 增加移印布标内容 | BO6: =J6/4 -> 225 | BP6: =J6/4 -> 225 | BQ6: =J6/4 -> 225 | BR6: =J6/4 -> 225 | BS6: =J6 -> 900 | BU6: =SUM(BO6:BR6) -> 900 | BV6: =BU6-J6 -> 0
A7: 45307 | B7: WALGREEN CO. | C7: 美国 | D7: 4500123425 | E7: 4540327784 | F7: 4500123425-30 | G7: 9543GQ5-S001 | H7: 9543GQ5-S001 | I7: 仓鼠 | J7: 948 | K7: 0 | L7: 12 | M7: =J7/L7 -> 79 | N7: 45377 | O7: 45373 | P7: 转4500126820消耗 | S7: 1/19收到 | U7: WIC 贴纸（翻单PO 4500099653） +PDQ折页 （翻单PO 4500099653 | W7: DG20240326 | X7: 日期码格式：ZURU INC(BVI) 标准格式 日期：03-26-2024 Packaging Info: Remark: MA 1L 包装 + WIC 贴纸（翻单PO 4500099653） + 客版PDQ （同PO4500114433）+ PDQ折页 （翻单PO 4500099653，PDQ折页放在PDQ的正上方，开箱即可看到） 产品和包装/外箱上面要有zuru标准格式的tracking code DG20240326 | Y7: Cara Li | Z7: 2.7269 | AA7: =J7*Z7 -> 2585.1012 | AC7: =AB7-J7 -> -948 | AD7: ok | AF7: 已入 | AG7: 系统出单 | AK7: =J7 -> 948 | AQ7: =J7 -> 948 | BN7: 增加移印布标内容 | BO7: =J7/4 -> 237 | BP7: =J7/4 -> 237 | BQ7: =J7/4 -> 237 | BR7: =J7/4 -> 237 | BS7: =J7 -> 948 | BU7: =SUM(BO7:BR7) -> 948 | BV7: =BU7-J7 -> 0
A8: 45477 | B8: Amazon CA (Vendor Center) | C8: 加拿大 | D8: 4500139232 | E8: 4KDM4B3Q | F8: 4500139232-500 | G8: 9543E-S001-3L | H8: 9543E-S001 | I8: 仓鼠 | J8: 24 | K8: 0 | L8: 24 | M8: =J8/L8 -> 1 | N8: 45516 | O8: 45512 | P8: 取消订单 | S8: 7/4收到 | U8: UPC贴纸跟翻4500098824 | V8: 欠客供外箱贴纸 | X8: 日期码格式： 标准格式 日期：按实际生产日期 Packaging Info: 出口加拿大，包装需要至少2/3L UPC版，无硼版本 #9543: MA 3L加UPC贴纸， UPC贴纸跟翻单4500098824。与Amazon US 合并订料； Remark: 1.Amazon FOB订单，出口CA。外箱最长边不能超过25" （超过了，case pack只能为1），不符合要求的大货，一律不接受。 2. 外箱正面印ZURU Logo+SSCC LABEL（客供贴纸), 侧面印item#（订单上显示的SKU#)+carton size(以工厂实际尺寸为准,单位: inch) +MADE IN CHINA,日期使用Z URU 标准版本 SSCC Label 显示的是客人自己的item#, SSCC Label 贴在外箱正面的正中间，贴一面即可，跟单订购，贴纸离外箱距必须至少3cm, 每一张SSCC labe l 都是唯一且有不同流水及条码的，没有损耗，绝对不可贴错 ，否则贴错或损坏一张会导致全部都错，千万要注意. SSCC 贴纸务必要在正中间(可以覆盖Logo <(>&<)> 箱唛), 否则会影响到仓库扫描识别 3.日期码使用ZURU标准版本 4.有要求入邮包盒的item，邮包盒上面要打上日期码。 5.按照客户PO# 装柜/箱号顺序装柜，跟单会提前给到装柜计划。在大货生产/仓库存放时，请留意该装柜要求，以便装柜时不混乱（避免装错/装漏/找不到货号等） | Y8: Agnes Zheng | Z8: 2.5958 | AA8: =J8*Z8 -> 62.2992 | AF8: 已入 | AM8: =J8 -> 24 | AQ8: =J8 -> 24 | BN8: 增加移印布标内容 | BR8: =J8 -> 24 | BS8: =J8 -> 24 | BU8: =SUM(BO8:BR8) -> 24 | BV8: =J8-BU8 -> 0
A9: 45436 | B9: Carlos Federspiel & Cia. - UNIVERSA | C9: 哥斯达黎加 | D9: 4500134694 | F9: 4500134694-90 | G9: 9543GQ1-S001-3L | H9: 9543GQ1-S001 | I9: 仓鼠 | J9: 726 | K9: 0 | L9: 22 | M9: =J9/L9 -> 33 | N9: 45485 | O9: 45510 | P9: 7/12取消 | S9: 欠 | U9: 欠进口商贴纸 | X9: 日期码格式：ZURU INC(BVI) 标准格式 日期：按实际生产日期 Packaging Info: 9543GQ1:MA 3L UPC包装+进口商贴纸+箱唛 Remark: | Y9: Ava Liang | Z9: 2.8179 | AA9: =J9*Z9 -> 2045.7954 | AC9: =AB9-J9 -> -726 | AF9: 已入 | AM9: =J9 -> 726 | AQ9: =J9 -> 726 | AV9: =J9/11 -> 66 | BN9: 增加移印布标内容 | BO9: =J9/22*5 -> 165 | BP9: =J9/22*6 -> 198 | BQ9: =J9/22*6 -> 198 | BR9: =J9/22*5 -> 165 | BS9: =J9 -> 726 | BT9: =J9/11 -> 66 | BU9: =SUM(BO9:BR9) -> 726 | BV9: =J9-BU9 -> 0
A10: 45499 | B10: Amazon CA (Vendor Center) | C10: 加拿大 | D10: 4500141223 | E10: 8VX6FHPO | F10: 4500141223-1640 | H10: 9543E-S001 | I10: 仓鼠 | J10: 24 | K10: 0 | L10: 24 | M10: =J10/L10 -> 1 | N10: 45544 | O10: 45540 | P10: 7/31取消订单 | X10: 日期码格式：ZURU INC(BVI) 标准格式 日期：按实际生产日期 Packaging Info: #9543: MA 3L 加UPC贴纸，UPC贴纸跟翻单4500098824。A:193052051776, E:193052051806, B:193052051783。 Remark: 1. Amazon FOB订单，出口CA。外箱最长边不能超过25" （超过了，case pack只能为1），不符合要求的大货，一律不接受。 2. 外箱正面印ZURU Logo + SSCC LABEL（客供贴纸)，侧面印item#（订单上显示的SKU#) + carton size(以工厂实际尺寸为准，单位: inch) + MADE IN CHINA， 日期使用ZURU 标准版本 SSCC Label 显示的是客人自己的item#，SSCC Label 贴在外箱正面的正中间，贴一面即可，跟单订购，贴纸离外箱距必须至少3cm，每一 张SSCC label 都是唯一且有不同流水及条码的，没有损耗，绝对不可贴错 ，否则贴错或损坏一张会导致全部都错，千万要注意: SSCC 贴纸务必要在正中间(可以覆 盖Logo <(>&<)> 箱唛)，否则会影响到仓库扫描识别。 3. 日期码使用ZURU标准版本。 4. 如果大货有要求入邮包盒，则对应的邮包盒上面要打上日期码。 5. 按照客户PO# 装柜/箱号顺序装柜，跟单会提前给到装柜计划。在大货生产/仓库存放时，请留意该装柜要求，以便装柜时不混乱（避免装错/装漏/找不到货号等 ）。 6. 出口加拿大，包装需要至少2/3L UPC版，无硼版本。 | Y10: Agnes Zheng | Z10: 2.5958 | AA10: =J10*Z10 -> 62.2992 | AC10: =AB10-J10 -> -24 | AM10: =J10 -> 24 | AQ10: =J10 -> 24 | BR10: =J10 -> 24 | BS10: =J10 -> 24 | BU10: =SUM(BO10:BR10) -> 24 | BV10: =J10-BU10 -> 0
A11: 45503 | B11: AMAZON.COM.DEDC,LLC | C11: 美国 | D11: 4500141501 | E11: 73Z36DSY | F11: 4500141501-230 | G11: 9543E-S001-MTS | H11: 9543E-S001 | I11: 仓鼠 | J11: 384 | K11: 0 | L11: 24 | M11: =J11/L11 -> 16 | N11: 45564 | O11: 45560 | P11: 8/8客户取消 | S11: 7/30收到 | U11: UPC贴纸跟翻4500098824 | V11: 欠客供外箱贴纸 | X11: 日期码格式：ZURU INC(BVI) 标准格式 日期：按实际生产日期 Packaging Info: ZURU MA 1L 8.#9543: MA 加UPC贴纸， UPC贴纸跟翻单4500098824。A:193052051776, B:193052051783,A:193052051776. Remark: 1.Amazon FOB订单，出口US。 2.日期码使用ZURU标准版本。邮包盒上要打日期码。 3.箱尺寸要求：外箱最长边不能超过25" （超过了，case pack只能为1），不符合要求的大货，一律不接受。 4.外箱箱唛要求： ①外箱正面印ZURU Logo+SSCC Label（客供贴纸，由跟单订购)。关于 SSCC Label 请注意： SSCC Label 显示的是客人自己的item#。 SSCC Label 必须贴在外箱正面的正中间位置（贴一面即可），并且贴纸离外箱边距必须至少3cm(可以覆盖Logo<(>&<)>箱唛)，否则会影响到客户那边仓库的扫描识 别。 每一张SSCC label 都是唯一且有不同流水及条码的，没有损耗，绝对不可贴错 。如果贴错或损坏任何一张，都会导致全部都错，千万要注意！ ②外箱侧面印item#（订单上显示的SKU#)+carton size(以工厂实际尺寸为准,单位: inch) +MADE IN CHINA,日期使用ZURU 标准版本。 5.装柜要求：按照客户PO# 装柜/箱号顺序装柜，跟单会提前给到装柜计划。 在大货生产/仓库存放时，请留意该装柜要求，以便装柜时不混乱（避免装错/装漏/找不到货号等）。 | Y11: Agnes Zheng | Z11: 2.5554 | AA11: =J11*Z11 -> 981.2736 | AF11: 已入 | AK11: =J11 -> 384 | AQ11: =J11 -> 384 | BN11: 增加移印布标内容 | BR11: =J11 -> 384 | BS11: =J11 -> 384 | BU11: =SUM(BO11:BR11) -> 384 | BV11: =J11-BU11 -> 0
A12: 45503 | B12: AMAZON.COM.DEDC,LLC | C12: 美国 | D12: 4500141501 | E12: 2ASLADBL | F12: 4500141501-240 | G12: 9543E-S001-MTS | H12: 9543E-S001 | I12: 仓鼠 | J12: 1368 | K12: 0 | L12: 24 | M12: =J12/L12 -> 57 | N12: 45564 | O12: 45560 | P12: 8/8客户取消 | S12: 7/30收到 | U12: UPC贴纸跟翻4500098824 | V12: 欠客供外箱贴纸 | X12: 日期码格式：ZURU INC(BVI) 标准格式 日期：按实际生产日期 Packaging Info: ZURU MA 1L 8.#9543: MA 加UPC贴纸， UPC贴纸跟翻单4500098824。A:193052051776, B:193052051783,A:193052051776. Remark: 1.Amazon FOB订单，出口US。 2.日期码使用ZURU标准版本。邮包盒上要打日期码。 3.箱尺寸要求：外箱最长边不能超过25" （超过了，case pack只能为1），不符合要求的大货，一律不接受。 4.外箱箱唛要求： ①外箱正面印ZURU Logo+SSCC Label（客供贴纸，由跟单订购)。关于 SSCC Label 请注意： SSCC Label 显示的是客人自己的item#。 SSCC Label 必须贴在外箱正面的正中间位置（贴一面即可），并且贴纸离外箱边距必须至少3cm(可以覆盖Logo<(>&<)>箱唛)，否则会影响到客户那边仓库的扫描识 别。 每一张SSCC label 都是唯一且有不同流水及条码的，没有损耗，绝对不可贴错 。如果贴错或损坏任何一张，都会导致全部都错，千万要注意！ ②外箱侧面印item#（订单上显示的SKU#)+carton size(以工厂实际尺寸为准,单位: inch) +MADE IN CHINA,日期使用ZURU 标准版本。 5.装柜要求：按照客户PO# 装柜/箱号顺序装柜，跟单会提前给到装柜计划。 在大货生产/仓库存放时，请留意该装柜要求，以便装柜时不混乱（避免装错/装漏/找不到货号等）。 | Y12: Agnes Zheng | Z12: 2.5554 | AA12: =J12*Z12 -> 3495.7872 | AF12: 已入 | AK12: =J12 -> 1368 | AQ12: =J12 -> 1368 | BN12: 增加移印布标内容 | BR12: =J12 -> 1368 | BS12: =J12 -> 1368 | BU12: =SUM(BO12:BR12) -> 1368 | BV12: =J12-BU12 -> 0
A13: 45482 | B13: AMAZON.COM.DEDC,LLC | C13: 美国 | D13: 4500139622 | E13: 84ABII4C | F13: 4500139622-110 | G13: 9543E-S001-MTS | H13: 9543E-S001 | I13: 仓鼠 | J13: 840 | K13: 0 | L13: 24 | M13: =J13/L13 -> 35 | N13: 45533 | O13: 45530 | P13: 8/8客户取消 | Q13: 纸箱滞留 | S13: 7/8收到 | U13: UPC贴纸翻4500098824 | V13: 欠客供外箱贴纸 | X13: 日期码格式： 标准格式 日期：按实际生产日期 Packaging Info: #9543: MA加UPC贴纸, UPC贴纸跟翻单4500098824. E:193052051806, B:193052051783, D:193052051790 Remark: 1. Amazon FOB订单，出口US。 2. 日期码使用ZURU标准版本。 3. 如果大货有要求入邮包盒，则对应的邮包盒上面要打上日期码。 4. 箱尺寸要求：外箱最长边不能超过25" （超过了，case pack只能为1），不符合要求的大货，一律不接受。 5. 外箱箱唛要求： ①外箱正面印ZURU Logo+SSCC Label（客供贴纸，由跟单订购)。关于 SSCC Label 请注意： SSCC Label 显示的是客人自己的item#。每一张SSCC label 都是唯一且有不同流水及条码的，没有损耗，绝对不可贴错 。如果贴错或损坏任何一张，都会导致全 部都错，千万要注意！ SSCC Label 必须贴在外箱正面的正中间位置（贴一面即可），并且贴纸离外箱边距必须至少3cm(可以覆盖Logo<(>&<)>箱唛)，否则会影响到客户那边仓库的扫描识 别。 ②外箱侧面印item#（订单上显示的SKU#)+carton size(以工厂实际尺寸为准,单位: inch) +MADE IN CHINA,日期使用ZURU 标准版本。 6. 装柜要求：按照客户PO# 装柜/箱号顺序装柜，跟单会提前给到装柜计划。 在大货生产/仓库存放时，请留意该装柜要求，以便装柜时不混乱（避免装错/装漏/找不到货号等）。 | Y13: Agnes Zheng | Z13: 2.5459 | AA13: =J13*Z13 -> 2138.556 | AC13: =AB13-J13 -> -840 | AF13: 已入 | AK13: =J13 -> 840 | AQ13: =J13 -> 840 | BN13: 增加移印布标内容 | BR13: =J13 -> 840 | BS13: =J13 -> 840 | BU13: =SUM(BO13:BR13) -> 840 | BV13: =J13-BU13 -> 0
A14: 45482 | B14: AMAZON.COM.DEDC,LLC | C14: 美国 | D14: 4500139622 | E14: 61GTMKLN | F14: 4500139622-120 | G14: 9543E-S001-MTS | H14: 9543E-S001 | I14: 仓鼠 | J14: 864 | K14: 0 | L14: 24 | M14: =J14/L14 -> 36 | N14: 45533 | O14: 45530 | P14: 8/8客户取消 | Q14: 纸箱滞留 | S14: 7/8收到 | U14: UPC贴纸翻4500098824 | V14: 欠客供外箱贴纸 | X14: 日期码格式： 标准格式 日期：按实际生产日期 Packaging Info: #9543: MA加UPC贴纸, UPC贴纸跟翻单4500098824. E:193052051806, B:193052051783, D:193052051790 Remark: 1. Amazon FOB订单，出口US。 2. 日期码使用ZURU标准版本。 3. 如果大货有要求入邮包盒，则对应的邮包盒上面要打上日期码。 4. 箱尺寸要求：外箱最长边不能超过25" （超过了，case pack只能为1），不符合要求的大货，一律不接受。 5. 外箱箱唛要求： ①外箱正面印ZURU Logo+SSCC Label（客供贴纸，由跟单订购)。关于 SSCC Label 请注意： SSCC Label 显示的是客人自己的item#。每一张SSCC label 都是唯一且有不同流水及条码的，没有损耗，绝对不可贴错 。如果贴错或损坏任何一张，都会导致全 部都错，千万要注意！ SSCC Label 必须贴在外箱正面的正中间位置（贴一面即可），并且贴纸离外箱边距必须至少3cm(可以覆盖Logo<(>&<)>箱唛)，否则会影响到客户那边仓库的扫描识 别。 ②外箱侧面印item#（订单上显示的SKU#)+carton size(以工厂实际尺寸为准,单位: inch) +MADE IN CHINA,日期使用ZURU 标准版本。 6. 装柜要求：按照客户PO# 装柜/箱号顺序装柜，跟单会提前给到装柜计划。 在大货生产/仓库存放时，请留意该装柜要求，以便装柜时不混乱（避免装错/装漏/找不到货号等）。 | Y14: Agnes Zheng | Z14: 2.5459 | AA14: =J14*Z14 -> 2199.6576 | AC14: =AB14-J14 -> -864 | AF14: 已入 | AK14: =J14 -> 864 | AQ14: =J14 -> 864 | BN14: 增加移印布标内容 | BR14: =J14 -> 864 | BS14: =J14 -> 864 | BU14: =SUM(BO14:BR14) -> 864 | BV14: =J14-BU14 -> 0
A15: 45418 | B15: BIG LOTS STORES, INC | C15: 美国 | D15: 4500131695 | E15: 95284017 | F15: 4500131695-50 | G15: 9543GQ1-S002 | H15: 9543GQ1-S002 | I15: 仓鼠 | J15: 1958 | K15: 0 | L15: 11 | M15: =J15/L15 -> 178 | N15: 45488 | O15: 45484 | P15: 客户取消8/14 成品消耗在4500142046 | S15: 5/9收到 | U15: 价格贴纸翻单4500128302 | X15: 日期码格式：ZURU INC(BVI) 标准格式 日期：按实际生产日期 Packaging Info: 1. MA UPC包装 （首选 1L/多语可以接受）+价格贴纸 Remark: 2. 价格贴纸由跟单提供文档及位置图，由工厂采购，价格贴需用可移贴纸，价格贴需先打样寄给跟单，客户确认贴纸样品后方可生产大货； 3. 工厂需保证所有item的BPA测试结果不超过100ppm，这点很重要，如果不能通过BPA测试将不能安排出货，工厂需保证生产的产品一次性通过BPA测试（可先安排自 测），如因为测试不通过需要重测的，工厂负责重测费用，因测试不通过导致出货延迟的，工厂需承担因延迟出货产生的罚款。 4. 按照规定日期准时交货，否则会有罚款； 5. 产品和包装上印刷ZURU 标准日期码； | Y15: Camellia Lyu | Z15: 2.7985 | AA15: =J15*Z15 -> 5479.463 | AB15: 1958 | AC15: =AB15-J15 -> 0 | AD15: OK | AF15: 已入 | AG15: 系统出单 | AK15: =J15 -> 1958 | AQ15: =J15 -> 1958 | AT15: =J15/11 -> 178 | BN15: 增加移印布标内容 | BO15: =J15/22*5 -> 445 | BP15: =J15/22*6 -> 534 | BQ15: =J15/22*6 -> 534 | BR15: =J15/22*5 -> 445 | BS15: =J15 -> 1958 | BT15: =J15/11 -> 178 | BU15: =SUM(BO15:BR15) -> 1958 | BV15: =J15-BU15 -> 0
A16: 45587 | B16: Amazon CA (Vendor Center) | C16: 加拿大 | D16: 4500148453 | E16: 6ICL64VA | F16: 4500148453-70 | H16: 9543A-S001 | I16: 仓鼠 | J16: 24 | K16: 0 | L16: 24 | M16: =J16/L16 -> 1 | N16: 45635 | O16: 45631 | P16: 10/24取消 | X16: 日期码格式：ZURU INC(BVI) 标准格式 日期：按实际生产日期 Packaging Info: 出口加拿大，包装需要至少2/3L UPC版，无硼版本 #9543: MA 3L UPC版本。A:193052051776, B:193052051783, E:193052051806,; Remark: 1. Amazon FOB订单，出口CA。外箱最长边不能超过25" （超过了，case pack只能为1），不符合要求的大货，一律不接受。 2. 外箱正面印ZURU Logo + SSCC LABEL（客供贴纸)，侧面印item#（订单上显示的SKU#) + carton size(以工厂实际尺寸为准，单位: inch) + MADE IN CHINA， 日期使用ZURU 标准版本 SSCC Label 显示的是客人自己的item#，SSCC Label 贴在外箱正面的正中间，贴一面即可，跟单订购，贴纸离外箱距必须至少3cm，每一 张SSCC label 都是唯一且有不同流水及条码的，没有损耗，绝对不可贴错 ，否则贴错或损坏一张会导致全部都错，千万要注意: SSCC 贴纸务必要在正中间(可以覆 盖Logo <(>&<)> 箱唛)，否则会影响到仓库扫描识别。 3. 日期码使用ZURU标准版本。 4. 如果大货有要求入邮包盒，则对应的邮包盒上面要打上日期码。 5. 按照客户PO# 装柜/箱号顺序装柜，跟单会提前给到装柜计划。在大货生产/仓库存放时，请留意该装柜要求，以便装柜时不混乱（避免装错/装漏/找不到货号等 ）。 6. 出口加拿大，包装需要至少2/3L UPC版，无硼版本。 7.邮包盒上要印刷日期码 | Y16: Kelly/Mia | Z16: 2.5695 | AA16: =J16*Z16 -> 61.668 | AM16: =J16 -> 24 | AQ16: =J16 -> 24 | BO16: =J16 -> 24 | BS16: =SUM(BO16:BR16) -> 24 | BU16: =SUM(BO16:BR16) -> 24 | BV16: =BU16-J16 -> 0
A17: 45587 | B17: Amazon CA (Vendor Center) | C17: 加拿大 | D17: 4500148453 | E17: 1SPX7AFA | F17: 4500148453-80 | H17: 9543A-S001 | I17: 仓鼠 | J17: 24 | K17: 0 | L17: 24 | M17: =J17/L17 -> 1 | N17: 45635 | O17: 45631 | P17: 10/24取消 | X17: 日期码格式：ZURU INC(BVI) 标准格式 日期：按实际生产日期 Packaging Info: 出口加拿大，包装需要至少2/3L UPC版，无硼版本 #9543: MA 3L UPC版本。A:193052051776, B:193052051783, E:193052051806,; Remark: 1. Amazon FOB订单，出口CA。外箱最长边不能超过25" （超过了，case pack只能为1），不符合要求的大货，一律不接受。 2. 外箱正面印ZURU Logo + SSCC LABEL（客供贴纸)，侧面印item#（订单上显示的SKU#) + carton size(以工厂实际尺寸为准，单位: inch) + MADE IN CHINA， 日期使用ZURU 标准版本 SSCC Label 显示的是客人自己的item#，SSCC Label 贴在外箱正面的正中间，贴一面即可，跟单订购，贴纸离外箱距必须至少3cm，每一 张SSCC label 都是唯一且有不同流水及条码的，没有损耗，绝对不可贴错 ，否则贴错或损坏一张会导致全部都错，千万要注意: SSCC 贴纸务必要在正中间(可以覆 盖Logo <(>&<)> 箱唛)，否则会影响到仓库扫描识别。 3. 日期码使用ZURU标准版本。 4. 如果大货有要求入邮包盒，则对应的邮包盒上面要打上日期码。 5. 按照客户PO# 装柜/箱号顺序装柜，跟单会提前给到装柜计划。在大货生产/仓库存放时，请留意该装柜要求，以便装柜时不混乱（避免装错/装漏/找不到货号等 ）。 6. 出口加拿大，包装需要至少2/3L UPC版，无硼版本。 7.邮包盒上要印刷日期码 | Y17: Kelly/Mia | Z17: 2.5695 | AA17: =J17*Z17 -> 61.668 | AM17: =J17 -> 24 | AQ17: =J17 -> 24 | BO17: =J17 -> 24 | BS17: =SUM(BO17:BR17) -> 24 | BU17: =SUM(BO17:BR17) -> 24 | BV17: =BU17-J17 -> 0
A18: 45726 | B18: DM LLC | C18: 俄罗斯联邦 | D18: 4500159461 | E18: 出Bekasovo 2 | F18: 4500159461-10 | G18: 9543-S001 | H18: 9543-S001 | I18: 仓鼠 | J18: 648 | K18: 0 | L18: 24 | M18: =J18/L18 -> 27 | N18: 45756 | O18: 45752 | P18: 转单合并-4500164028 | S18: 3/13收到 | U18: 3/25-进口商贴纸+EAN条码贴纸 | W18: 外包装/外箱不要打ZURU标准日期码 | X18: 日期码格式：外包装/外箱不要打ZURU标准日期码 日期： Packaging Info: 注意 ：外包装 (指: 收缩膜/彩卡/铝箔袋/挂卡/PDQ) /外箱不要打ZURU标准日期码！胶件可以打日期码。 9543 : 1L MA 收缩膜+ 进口商贴纸+EAN条码贴纸， MA指南/说明书（如有）； Remark: 标准配比 ； 请按期完货， 会有罚金。 出2个港口Bekasovo 2 和Ural . | Y18: Ann | Z18: 2.5135 | AA18: =J18*Z18 -> 1628.748 | AB18: 648 | AC18: =AB18-J18 -> 0 | AD18: OK | AF18: 已入 | AG18: 系统出单 | AK18: =J18 -> 648 | AQ18: =J18 -> 648 | BN18: 增加移印布标内容 | BO18: =J18/4 -> 162 | BP18: =J18/4 -> 162 | BQ18: =J18/4 -> 162 | BR18: =J18/4 -> 162 | BS18: =J18 -> 648 | BU18: =SUM(BO18:BR18) -> 648 | BV18: =J18-BU18 -> 0
A19: 45726 | B19: DM LLC | C19: 俄罗斯联邦 | D19: 4500159461 | E19: 出Ural | F19: 4500159461-60 | G19: 9543-S001 | H19: 9543-S001 | I19: 仓鼠 | J19: 264 | K19: 0 | L19: 24 | M19: =J19/L19 -> 11 | N19: 45756 | O19: 45752 | P19: 转单合并-4500164028 | S19: 3/13收到 | U19: 3/25-进口商贴纸+EAN条码贴纸 | W19: 外包装/外箱不要打ZURU标准日期码 | X19: 日期码格式：外包装/外箱不要打ZURU标准日期码 日期： Packaging Info: 注意 ：外包装 (指: 收缩膜/彩卡/铝箔袋/挂卡/PDQ) /外箱不要打ZURU标准日期码！胶件可以打日期码。 9543 : 1L MA 收缩膜+ 进口商贴纸+EAN条码贴纸， MA指南/说明书（如有）； Remark: 标准配比 ； 请按期完货， 会有罚金。 出2个港口Bekasovo 2 和Ural . | Y19: Ann | Z19: 2.5135 | AA19: =J19*Z19 -> 663.564 | AB19: 264 | AC19: =AB19-J19 -> 0 | AD19: OK | AF19: 已入 | AG19: 系统出单 | AK19: =J19 -> 264 | AQ19: =J19 -> 264 | BN19: 增加移印布标内容 | BO19: =J19/4 -> 66 | BP19: =J19/4 -> 66 | BQ19: =J19/4 -> 66 | BR19: =J19/4 -> 66 | BS19: =J19 -> 264 | BU19: =SUM(BO19:BR19) -> 264 | BV19: =J19-BU19 -> 0
A20: 45726 | B20: DM LLC | C20: 俄罗斯联邦 | D20: 4500159526 | E20: 去Bekasovo 2 | F20: 4500159526-10 | G20: 9543-S001 | H20: 9543-S001 | I20: 仓鼠 | J20: 1944 | K20: 0 | L20: 24 | M20: =J20/L20 -> 81 | N20: 45775 | O20: 45771 | P20: 转单合并-4500164028 | S20: 3/13收到 | U20: 进口商贴纸+EAN条码贴纸翻4500159461 | W20: 外包装/外箱不要打ZURU标准日期码 | X20: 日期码格式：外包装/外箱不要打ZURU标准日期码 日期： Packaging Info: 注意 ：外包装 (指: 收缩膜/彩卡/铝箔袋/挂卡/PDQ) /外箱不要打ZURU标准日期码！胶件可以打日期码。 9543 : 1L MA 收缩膜+ 进口商贴纸翻4500159461+EAN条码贴纸翻4500159461， MA指南/说明书（如有）； Remark: 标准配比 ； 请按期完货， 会有罚金。 出2个港口Bekasovo 2 和Ural . | Y20: Ann | Z20: 2.4904 | AA20: =J20*Z20 -> 4841.3376 | AC20: =AB20-J20 -> -1944 | AD20: OK | AF20: 已入 | AG20: 系统出单 | AK20: =J20 -> 1944 | AQ20: =J20 -> 1944 | BN20: 增加移印布标内容 | BO20: =J20/4 -> 486 | BP20: =J20/4 -> 486 | BQ20: =J20/4 -> 486 | BR20: =J20/4 -> 486 | BS20: =J20 -> 1944 | BU20: =SUM(BO20:BR20) -> 1944 | BV20: =J20-BU20 -> 0
A21: 45726 | B21: DM LLC | C21: 俄罗斯联邦 | D21: 4500159526 | E21: 去Ural | F21: 4500159526-80 | G21: 9543-S001 | H21: 9543-S001 | I21: 仓鼠 | J21: 744 | K21: 0 | L21: 24 | M21: =J21/L21 -> 31 | N21: 45775 | O21: 45771 | P21: 转单合并-4500164028 | S21: 3/13收到 | U21: 进口商贴纸+EAN条码贴纸翻4500159461 | W21: 外包装/外箱不要打ZURU标准日期码 | X21: 日期码格式：外包装/外箱不要打ZURU标准日期码 日期： Packaging Info: 注意 ：外包装 (指: 收缩膜/彩卡/铝箔袋/挂卡/PDQ) /外箱不要打ZURU标准日期码！胶件可以打日期码。 9543 : 1L MA 收缩膜+ 进口商贴纸翻4500159461+EAN条码贴纸翻4500159461， MA指南/说明书（如有）； Remark: 标准配比 ； 请按期完货， 会有罚金。 出2个港口Bekasovo 2 和Ural . | Y21: Ann | Z21: 2.4904 | AA21: =J21*Z21 -> 1852.8576 | AC21: =AB21-J21 -> -744 | AD21: OK | AF21: 已入 | AG21: 系统出单 | AK21: =J21 -> 744 | AQ21: =J21 -> 744 | BN21: 增加移印布标内容 | BO21: =J21/4 -> 186 | BP21: =J21/4 -> 186 | BQ21: =J21/4 -> 186 | BR21: =J21/4 -> 186 | BS21: =J21 -> 744 | BU21: =SUM(BO21:BR21) -> 744 | BV21: =J21-BU21 -> 0
A22: 45681 | B22: AMAZON.COM.DEDC,LLC | C22: 美国 | D22: 4500156588 | E22: 80M18VIC | F22: 4500156588-90 | G22: 9543B-S001-MTS | H22: 9543B-S001 | I22: 仓鼠 | J22: 336 | K22: 0 | L22: 24 | M22: =J22/L22 -> 14 | N22: 45750 | O22: =N22-3 -> 45747 | P22: 5/6取消 | Q22: 转4500167444 | R22: 0 | S22: 1/26收到 | U22: UPC贴纸翻4500098824 | V22: 3/12-客供外箱贴纸 | X22: 日期码格式：ZURU INC(BVI) 标准格式 日期：按实际生产日期 Packaging Info: #9543：MA 1L 加UPC贴纸，UPC贴纸跟翻单4500098824。A:193052051776，B:193052051783。 Remark: 1. Amazon FOB订单，出口US。 2. 日期码使用ZURU标准版本。 3. 如果大货有要求入邮包盒，则对应的邮包盒上面要打上日期码。 4. 箱尺寸要求：外箱最长边不能超过25"(超过了，case pack只能为1)，不符合要求的大货，一律不接受。 5. 外箱箱唛要求： ①外箱正面印ZURU Logo+SSCC Label(客供贴纸，由跟单订购)。关于 SSCC Label 请注意： SSCC Label显示的是客人自己的item#。每一张SSCC label都是唯一且有不同流水及条码的，没有损耗，绝对不可贴错。如果贴错或损坏任何一张，都会导致全部都 错，千万要注意！SSCC Label必须贴在外箱正面的正中间位置(贴一面即可)，并且贴纸离外箱边距必须至少3cm(可以覆盖Logo<(>&<)>箱唛)，否则会影响到客户那边 仓库的扫描识别。 ②外箱侧面印item#(订单上显示的SKU#)+carton size(以工厂实际尺寸为准，单位: inch)+MADE IN CHINA，日期使用ZURU 标准版本。 6. 装柜要求：按照客户PO#装柜/箱号顺序装柜，跟单会提前给到装柜计划。 在大货生产/仓库存放时，请留意该装柜要求，以便装柜时不混乱(避免装错/装漏/找不到货号等)。 | Y22: Kelly Shen | Z22: 2.5459 | AA22: =J22*Z22 -> 855.4224 | AB22: 336 | AC22: =AB22-J22 -> 0 | AD22: ok | AF22: 已入 | AG22: 系统出单 | AK22: =J22 -> 336 | AQ22: =J22 -> 336 | BN22: 增加移印布标内容 | BP22: =J22 -> 336 | BS22: =J22 -> 336 | BU22: =SUM(BO22:BR22) -> 336 | BV22: =J22-BU22 -> 0 | BW22: =J22 -> 336
A23: 45681 | B23: AMAZON.COM.DEDC,LLC | C23: 美国 | D23: 4500156588 | E23: 34SV4ONS | F23: 4500156588-100 | G23: 9543B-S001-MTS | H23: 9543B-S001 | I23: 仓鼠 | J23: 384 | K23: 0 | L23: 24 | M23: =J23/L23 -> 16 | N23: 45750 | O23: =N23-3 -> 45747 | P23: 5/6取消 | Q23: 转4500167444 | R23: 0 | S23: 1/26收到 | U23: UPC贴纸翻4500098824 | V23: 3/12-客供外箱贴纸 | X23: 日期码格式：ZURU INC(BVI) 标准格式 日期：按实际生产日期 Packaging Info: #9543：MA 1L 加UPC贴纸，UPC贴纸跟翻单4500098824。A:193052051776，B:193052051783。 Remark: 1. Amazon FOB订单，出口US。 2. 日期码使用ZURU标准版本。 3. 如果大货有要求入邮包盒，则对应的邮包盒上面要打上日期码。 4. 箱尺寸要求：外箱最长边不能超过25"(超过了，case pack只能为1)，不符合要求的大货，一律不接受。 5. 外箱箱唛要求： ①外箱正面印ZURU Logo+SSCC Label(客供贴纸，由跟单订购)。关于 SSCC Label 请注意： SSCC Label显示的是客人自己的item#。每一张SSCC label都是唯一且有不同流水及条码的，没有损耗，绝对不可贴错。如果贴错或损坏任何一张，都会导致全部都 错，千万要注意！SSCC Label必须贴在外箱正面的正中间位置(贴一面即可)，并且贴纸离外箱边距必须至少3cm(可以覆盖Logo<(>&<)>箱唛)，否则会影响到客户那边 仓库的扫描识别。 ②外箱侧面印item#(订单上显示的SKU#)+carton size(以工厂实际尺寸为准，单位: inch)+MADE IN CHINA，日期使用ZURU 标准版本。 6. 装柜要求：按照客户PO#装柜/箱号顺序装柜，跟单会提前给到装柜计划。 在大货生产/仓库存放时，请留意该装柜要求，以便装柜时不混乱(避免装错/装漏/找不到货号等)。 | Y23: Kelly Shen | Z23: 2.5459 | AA23: =J23*Z23 -> 977.6256 | AB23: 384 | AC23: =AB23-J23 -> 0 | AD23: ok | AF23: 已入 | AG23: 系统出单 | AK23: =J23 -> 384 | AQ23: =J23 -> 384 | BN23: 增加移印布标内容 | BP23: =J23 -> 384 | BS23: =J23 -> 384 | BU23: =SUM(BO23:BR23) -> 384 | BV23: =J23-BU23 -> 0 | BW23: =J23 -> 384
A24: 45681 | B24: AMAZON.COM.DEDC,LLC | C24: 美国 | D24: 4500156588 | E24: 3QUJVWNQ | F24: 4500156588-110 | G24: 9543B-S001-MTS | H24: 9543B-S001 | I24: 仓鼠 | J24: 264 | K24: 0 | L24: 24 | M24: =J24/L24 -> 11 | N24: 45750 | O24: =N24-3 -> 45747 | P24: 5/6取消 | Q24: 转4500167444 | R24: 0 | S24: 1/26收到 | U24: UPC贴纸翻4500098824 | V24: 3/12-客供外箱贴纸 | X24: 日期码格式：ZURU INC(BVI) 标准格式 日期：按实际生产日期 Packaging Info: #9543：MA 1L 加UPC贴纸，UPC贴纸跟翻单4500098824。A:193052051776，B:193052051783。 Remark: 1. Amazon FOB订单，出口US。 2. 日期码使用ZURU标准版本。 3. 如果大货有要求入邮包盒，则对应的邮包盒上面要打上日期码。 4. 箱尺寸要求：外箱最长边不能超过25"(超过了，case pack只能为1)，不符合要求的大货，一律不接受。 5. 外箱箱唛要求： ①外箱正面印ZURU Logo+SSCC Label(客供贴纸，由跟单订购)。关于 SSCC Label 请注意： SSCC Label显示的是客人自己的item#。每一张SSCC label都是唯一且有不同流水及条码的，没有损耗，绝对不可贴错。如果贴错或损坏任何一张，都会导致全部都 错，千万要注意！SSCC Label必须贴在外箱正面的正中间位置(贴一面即可)，并且贴纸离外箱边距必须至少3cm(可以覆盖Logo<(>&<)>箱唛)，否则会影响到客户那边 仓库的扫描识别。 ②外箱侧面印item#(订单上显示的SKU#)+carton size(以工厂实际尺寸为准，单位: inch)+MADE IN CHINA，日期使用ZURU 标准版本。 6. 装柜要求：按照客户PO#装柜/箱号顺序装柜，跟单会提前给到装柜计划。 在大货生产/仓库存放时，请留意该装柜要求，以便装柜时不混乱(避免装错/装漏/找不到货号等)。 | Y24: Kelly Shen | Z24: 2.5459 | AA24: =J24*Z24 -> 672.1176 | AB24: 264 | AC24: =AB24-J24 -> 0 | AD24: ok | AF24: 已入 | AG24: 系统出单 | AK24: =J24 -> 264 | AQ24: =J24 -> 264 | BN24: 增加移印布标内容 | BP24: =J24 -> 264 | BS24: =J24 -> 264 | BU24: =SUM(BO24:BR24) -> 264 | BV24: =J24-BU24 -> 0 | BW24: =J24 -> 264
A25: 45681 | B25: AMAZON.COM.DEDC,LLC | C25: 美国 | D25: 4500156588 | E25: 6EOFYM3P | F25: 4500156588-120 | G25: 9543B-S001-MTS | H25: 9543B-S001 | I25: 仓鼠 | J25: 864 | K25: 0 | L25: 24 | M25: =J25/L25 -> 36 | N25: 45750 | O25: =N25-3 -> 45747 | P25: 5/6取消 | Q25: 转4500167444 | R25: 0 | S25: 1/26收到 | U25: UPC贴纸翻4500098824 | V25: 3/12-客供外箱贴纸 | X25: 日期码格式：ZURU INC(BVI) 标准格式 日期：按实际生产日期 Packaging Info: #9543：MA 1L 加UPC贴纸，UPC贴纸跟翻单4500098824。A:193052051776，B:193052051783。 Remark: 1. Amazon FOB订单，出口US。 2. 日期码使用ZURU标准版本。 3. 如果大货有要求入邮包盒，则对应的邮包盒上面要打上日期码。 4. 箱尺寸要求：外箱最长边不能超过25"(超过了，case pack只能为1)，不符合要求的大货，一律不接受。 5. 外箱箱唛要求： ①外箱正面印ZURU Logo+SSCC Label(客供贴纸，由跟单订购)。关于 SSCC Label 请注意： SSCC Label显示的是客人自己的item#。每一张SSCC label都是唯一且有不同流水及条码的，没有损耗，绝对不可贴错。如果贴错或损坏任何一张，都会导致全部都 错，千万要注意！SSCC Label必须贴在外箱正面的正中间位置(贴一面即可)，并且贴纸离外箱边距必须至少3cm(可以覆盖Logo<(>&<)>箱唛)，否则会影响到客户那边 仓库的扫描识别。 ②外箱侧面印item#(订单上显示的SKU#)+carton size(以工厂实际尺寸为准，单位: inch)+MADE IN CHINA，日期使用ZURU 标准版本。 6. 装柜要求：按照客户PO#装柜/箱号顺序装柜，跟单会提前给到装柜计划。 在大货生产/仓库存放时，请留意该装柜要求，以便装柜时不混乱(避免装错/装漏/找不到货号等)。 | Y25: Kelly Shen | Z25: 2.5459 | AA25: =J25*Z25 -> 2199.6576 | AB25: 864 | AC25: =AB25-J25 -> 0 | AD25: ok | AF25: 已入 | AG25: 系统出单 | AK25: =J25 -> 864 | AQ25: =J25 -> 864 | BN25: 增加移印布标内容 | BP25: =J25 -> 864 | BS25: =J25 -> 864 | BU25: =SUM(BO25:BR25) -> 864 | BV25: =J25-BU25 -> 0 | BW25: =J25 -> 864
A26: 45681 | B26: AMAZON.COM.DEDC,LLC | C26: 美国 | D26: 4500156588 | E26: 85HNDESI | F26: 4500156588-130 | G26: 9543B-S001-MTS | H26: 9543B-S001 | I26: 仓鼠 | J26: 312 | K26: 0 | L26: 24 | M26: =J26/L26 -> 13 | N26: 45750 | O26: =N26-3 -> 45747 | P26: 5/6取消 | Q26: 转4500167444 | R26: 0 | S26: 1/26收到 | U26: UPC贴纸翻4500098824 | V26: 3/12-客供外箱贴纸 | X26: 日期码格式：ZURU INC(BVI) 标准格式 日期：按实际生产日期 Packaging Info: #9543：MA 1L 加UPC贴纸，UPC贴纸跟翻单4500098824。A:193052051776，B:193052051783。 Remark: 1. Amazon FOB订单，出口US。 2. 日期码使用ZURU标准版本。 3. 如果大货有要求入邮包盒，则对应的邮包盒上面要打上日期码。 4. 箱尺寸要求：外箱最长边不能超过25"(超过了，case pack只能为1)，不符合要求的大货，一律不接受。 5. 外箱箱唛要求： ①外箱正面印ZURU Logo+SSCC Label(客供贴纸，由跟单订购)。关于 SSCC Label 请注意： SSCC Label显示的是客人自己的item#。每一张SSCC label都是唯一且有不同流水及条码的，没有损耗，绝对不可贴错。如果贴错或损坏任何一张，都会导致全部都 错，千万要注意！SSCC Label必须贴在外箱正面的正中间位置(贴一面即可)，并且贴纸离外箱边距必须至少3cm(可以覆盖Logo<(>&<)>箱唛)，否则会影响到客户那边 仓库的扫描识别。 ②外箱侧面印item#(订单上显示的SKU#)+carton size(以工厂实际尺寸为准，单位: inch)+MADE IN CHINA，日期使用ZURU 标准版本。 6. 装柜要求：按照客户PO#装柜/箱号顺序装柜，跟单会提前给到装柜计划。 在大货生产/仓库存放时，请留意该装柜要求，以便装柜时不混乱(避免装错/装漏/找不到货号等)。 | Y26: Kelly Shen | Z26: 2.5721 | AA26: =J26*Z26 -> 802.4952 | AB26: 312 | AC26: =AB26-J26 -> 0 | AD26: OK | AF26: 已入 | AG26: 系统出单 | AK26: =J26 -> 312 | AQ26: =J26 -> 312 | BN26: 增加移印布标内容 | BP26: =J26 -> 312 | BS26: =J26 -> 312 | BU26: =SUM(BO26:BR26) -> 312 | BV26: =J26-BU26 -> 0 | BW26: =J26 -> 312
A27: 45789 | B27: MEIJER DISTRIBUTION, INC. | C27: 美国 | D27: 4500166083 | E27: 217111784 | F27: 4500166083-20 | G27: 9543GQ1-S002 | H27: 9543GQ1-S002 | I27: 仓鼠 | J27: 528 | K27: 0 | L27: 11 | M27: =J27/L27 -> 48 | N27: 45831 | O27: 45827 | P27: 6/11取消 | S27: 5/21收到 | U27: 无 | X27: 日期码格式：ZURU INC(BVI) 标准格式 日期： Packaging Info: 1. MA 1L 包装 2. 客人指定箱唛排版 Remark: 出货前 Zuru QC 验货 | Y27: Cherie Li | Z27: 1.6759 | AA27: =J27*Z27 -> 884.8752 | AC27: =AB27-J27 -> -528 | AD27: 无 | AF27: 已入 | AG27: 系统出单 | AK27: =J27 -> 528 | AQ27: =J27 -> 528 | AT27: =J27/11 -> 48 | BN27: 增加移印布标内容 | BO27: =J27/22*5 -> 120 | BP27: =J27/22*6 -> 144 | BQ27: =J27/22*6 -> 144 | BR27: =J27/22*5 -> 120 | BS27: =J27 -> 528 | BT27: =J27/11 -> 48 | BU27: =SUM(BO27:BR27) -> 528 | BV27: =J27-BU27 -> 0
A28: 45804 | B28: Amazon Mexico, S. DE R.L. DE CV | C28: 墨西哥 | D28: 4500168127 | E28: 4AKPACRA | F28: 4500168127-40 | G28: 9543B-S001-3L | H28: 9543B-S001 | I28: 仓鼠 | J28: 168 | K28: 0 | L28: 24 | M28: =J28/L28 -> 7 | N28: 45834 | O28: 45831 | P28: 6/16取消 | Q28: 纸箱滞留 | R28: =M28 -> 7 | U28: 欠UPC贴纸+进口商贴纸 | V28: 欠客供外箱贴纸 | X28: 日期码格式：ZURU INC(BVI) 标准格式 日期：按实际生产日期 Packaging Info: 4. 9543: MA 3L包装加UPC贴纸+进口商贴纸+SSCC label，B：193052051783 Remark: 1. Amazon FOB订单，出口Mexico，外箱最长边不能超过25" （超过了，case pack只能为1），不符合要求的大货，一律不接受。 2. 空白外箱加印ZURU Logo（四面加印）+MADE IN CHINA（只印一正一侧）+SSCC LABEL(客供贴纸），无shipping mark,日期使用ZURU 标准版本。SSCC Label显示 的是客人自己的item#，SSCC Label 贴在外箱正面的正中间，贴一面即可，跟单订购，贴纸离外箱距必须至少3cm,每一张SSCC Label都是唯一且有不同流水及条码的 ，没有损耗，绝对不可贴错，否则贴错或损坏一张会导致全部都错，千万要注意！ 3. 日期码使用ZURU标准版 | Y28: Ever Li | Z28: 2.5135 | AA28: =J28*Z28 -> 422.268 | AC28: =AB28-J28 -> -168 | AF28: 已入 | AG28: 系统出单 | AM28: =J28 -> 168 | AQ28: =J28 -> 168 | BN28: 增加移印布标内容 | BP28: =J28 -> 168 | BS28: =J28 -> 168 | BU28: =SUM(BO28:BR28) -> 168 | BV28: =J28-BU28 -> 0
A29: 45804 | B29: Amazon Mexico, S. DE R.L. DE CV | C29: 墨西哥 | D29: 4500168127 | E29: 4AKPACRA | F29: 4500168127-50 | G29: 9543A-S001-3L | H29: 9543A-S001 | I29: 仓鼠 | J29: 120 | K29: 0 | L29: 24 | M29: =J29/L29 -> 5 | N29: 45834 | O29: 45831 | P29: 6/16取消 | Q29: 纸箱滞留 | R29: =M29 -> 5 | U29: 欠UPC贴纸+进口商贴纸 | V29: 欠客供外箱贴纸 | X29: 日期码格式：ZURU INC(BVI) 标准格式 日期：按实际生产日期 Packaging Info: 4. 9543: MA 3L包装加UPC贴纸+进口商贴纸+SSCC label，A：193052051776 Remark: 1. Amazon FOB订单，出口Mexico，外箱最长边不能超过25" （超过了，case pack只能为1），不符合要求的大货，一律不接受。 2. 空白外箱加印ZURU Logo（四面加印）+MADE IN CHINA（只印一正一侧）+SSCC LABEL(客供贴纸），无shipping mark,日期使用ZURU 标准版本。SSCC Label显示 的是客人自己的item#，SSCC Label 贴在外箱正面的正中间，贴一面即可，跟单订购，贴纸离外箱距必须至少3cm,每一张SSCC Label都是唯一且有不同流水及条码的 ，没有损耗，绝对不可贴错，否则贴错或损坏一张会导致全部都错，千万要注意！ 3. 日期码使用ZURU标准版 | Y29: Ever Li | Z29: 2.5135 | AA29: =J29*Z29 -> 301.62 | AC29: =AB29-J29 -> -120 | AF29: 已入 | AG29: 系统出单 | AM29: =J29 -> 120 | AQ29: =J29 -> 120 | BN29: 增加移印布标内容 | BO29: =J29 -> 120 | BS29: =J29 -> 120 | BU29: =SUM(BO29:BR29) -> 120 | BV29: =J29-BU29 -> 0
A30: 45812 | B30: Amazon Mexico, S. DE R.L. DE CV | C30: 墨西哥 | D30: 4500168867 | E30: 7DT228PK | F30: 4500168867-40 | H30: 9543B-S001 | I30: 仓鼠 | J30: 72 | K30: 0 | L30: 24 | M30: =J30/L30 -> 3 | N30: 45847 | O30: 45843 | P30: 6/16取消 | Q30: 无物料产生 | U30: 欠UPC贴纸+进口商贴纸 | V30: 欠客供外箱贴纸 | X30: 日期码格式：ZURU INC(BVI) 标准格式 日期：按实际生产日期 Packaging Info: 2. 9543: MA 3L包装加UPC贴纸+进口商贴纸翻单PO4500168127+SSCC label，B：193052051783 Remark: 1. 9543：2PCS AAA BATTERIES(NOT INCLUDED) 2. Amazon FOB订单，出口Mexico，外箱最长边不能超过25" （超过了，case pack只能为1），不符合要求的大货，一律不接受。 3. 空白外箱加印ZURU Logo（四面加印）+MADE IN CHINA（只印一正一侧）+SSCC LABEL(客供贴纸），无shipping mark,日期使用ZURU 标准版本。SSCC Label显示 的是客人自己的item#，SSCC Label 贴在外箱正面的正中间，贴一面即可，跟单订购，贴纸离外箱距必须至少3cm,每一张SSCC Label都是唯一且有不同流水及条码的 ，没有损耗，绝对不可贴错，否则贴错或损坏一张会导致全部都错，千万要注意！ 4. 日期码使用ZURU标准版 | Y30: Ever Li | Z30: 2.5135 | AA30: =J30*Z30 -> 180.972 | AM30: =J30 -> 72 | AQ30: =J30 -> 72 | BP30: =J30 -> 72 | BS30: =J30 -> 72 | BU30: =SUM(BO30:BR30) -> 72 | BV30: =J30-BU30 -> 0
A31: 45819 | B31: Amazon CA (Vendor Center) | C31: 加拿大 | D31: 4500169697 | E31: 3UXYV2PC | F31: 4500169697-60 | H31: 9543E-S001 | I31: 仓鼠 | J31: 72 | K31: 0 | L31: 24 | M31: 3 | N31: 45855 | O31: =N31-3 -> 45852 | P31: 客户取消 | Q31: 无物料产生 | S31: 6/13收到 | U31: UPC贴纸翻4500098824 | V31: 欠外箱贴纸 | X31: 日期码格式：ZURU INC(BVI) 标准格式 日期：按实际生产日期 Packaging Info: #9543: MA 3L 加UPC贴纸， UPC贴纸跟翻单4500098824。B:193052051783,E:193052051806; Remark: 1. Amazon FOB订单，出口CA。外箱最长边不能超过25" （超过了，case pack只能为1），不符合要求的大货，一律不接受。 2. 外箱正面印ZURU Logo + SSCC LABEL（客供贴纸)，侧面印item#（订单上显示的SKU#) + carton size(以工厂实际尺寸为准，单位: inch) + MADE IN CHINA， 日期使用ZURU 标准版本 SSCC Label 显示的是客人自己的item#，SSCC Label 贴在外箱正面的正中间，贴一面即可，跟单订购，贴纸离外箱距必须至少3cm，每一 张SSCC label 都是唯一且有不同流水及条码的，没有损耗，绝对不可贴错 ，否则贴错或损坏一张会导致全部都错，千万要注意: SSCC 贴纸务必要在正中间(可以覆 盖Logo <(>&<)> 箱唛)，否则会影响到仓库扫描识别。 3. 日期码使用ZURU标准版本。 4. 如果大货有要求入邮包盒，则对应的邮包盒上面要打上日期码。 5. 按照客户PO# 装柜/箱号顺序装柜，跟单会提前给到装柜计划。在大货生产/仓库存放时，请留意该装柜要求，以便装柜时不混乱（避免装错/装漏/找不到货号等 ）。 6. 出口加拿大，包装需要至少2/3L UPC版，无硼版本。 7.邮包盒上要印刷日期码 | Y31: Kelly Shen | Z31: 2.4879 | AA31: =J31*Z31 -> 179.1288 | AC31: =AB31-J31 -> -72 | AM31: =J31 -> 72 | AQ31: =J31 -> 72 | BO31: 增加移印布标内容 | BS31: =J31 -> 72 | BT31: =J31 -> 72 | BV31: =SUM(BP31:BS31) -> 72 | BW31: =J31-BV31 -> 0
A32: 45819 | B32: Amazon CA (Vendor Center) | C32: 加拿大 | D32: 4500169697 | E32: 5CP1BTOR | F32: 4500169697-110 | H32: 9543E-S001 | I32: 仓鼠 | J32: 72 | K32: 0 | L32: 24 | M32: 3 | N32: 45855 | O32: =N32-3 -> 45852 | P32: 客户取消 | Q32: 无物料产生 | S32: 6/13收到 | U32: UPC贴纸翻4500098824 | V32: 欠外箱贴纸 | X32: 日期码格式：ZURU INC(BVI) 标准格式 日期：按实际生产日期 Packaging Info: #9543: MA 3L 加UPC贴纸， UPC贴纸跟翻单4500098824。B:193052051783,E:193052051806; Remark: 1. Amazon FOB订单，出口CA。外箱最长边不能超过25" （超过了，case pack只能为1），不符合要求的大货，一律不接受。 2. 外箱正面印ZURU Logo + SSCC LABEL（客供贴纸)，侧面印item#（订单上显示的SKU#) + carton size(以工厂实际尺寸为准，单位: inch) + MADE IN CHINA， 日期使用ZURU 标准版本 SSCC Label 显示的是客人自己的item#，SSCC Label 贴在外箱正面的正中间，贴一面即可，跟单订购，贴纸离外箱距必须至少3cm，每一 张SSCC label 都是唯一且有不同流水及条码的，没有损耗，绝对不可贴错 ，否则贴错或损坏一张会导致全部都错，千万要注意: SSCC 贴纸务必要在正中间(可以覆 盖Logo <(>&<)> 箱唛)，否则会影响到仓库扫描识别。 3. 日期码使用ZURU标准版本。 4. 如果大货有要求入邮包盒，则对应的邮包盒上面要打上日期码。 5. 按照客户PO# 装柜/箱号顺序装柜，跟单会提前给到装柜计划。在大货生产/仓库存放时，请留意该装柜要求，以便装柜时不混乱（避免装错/装漏/找不到货号等 ）。 6. 出口加拿大，包装需要至少2/3L UPC版，无硼版本。 7.邮包盒上要印刷日期码 | Y32: Kelly Shen | Z32: 2.4879 | AA32: =J32*Z32 -> 179.1288 | AC32: =AB32-J32 -> -72 | AM32: =J32 -> 72 | AQ32: =J32 -> 72 | BO32: 增加移印布标内容 | BS32: =J32 -> 72 | BT32: =J32 -> 72 | BV32: =SUM(BP32:BS32) -> 72 | BW32: =J32-BV32 -> 0
A33: 45824 | B33: AMAZON CA (VENDOR CENTER) | C33: 加拿大 | D33: 4500170130 | E33: 1RPFYRIE | F33: 4500170130-50 | H33: 9543E-S001 | I33: 仓鼠 | J33: 48 | K33: 0 | L33: 24 | M33: =J33/L33 -> 2 | N33: 45859 | O33: 45855 | P33: 客户预计取消 | Q33: 无物料产生 | S33: 6/13收到 | U33: UPC贴纸翻4500098824 | V33: 欠外箱贴纸 | X33: 日期码格式：ZURU INC(BVI) 标准格式 日期：按实际生产日期 Packaging Info: #9543: MA 3L 加UPC贴纸， UPC贴纸跟翻单4500098824。B:193052051783, D:193052051790; E:193052051806; Remark: 1. Amazon FOB订单，出口CA。外箱最长边不能超过25" （超过了，case pack只能为1），不符合要求的大货，一律不接受。 2. 外箱正面印ZURU Logo + SSCC LABEL（客供贴纸)，侧面印item#（订单上显示的SKU#) + carton size(以工厂实际尺寸为准，单位: inch) + MADE IN CHINA， 日期使用ZURU 标准版本 SSCC Label 显示的是客人自己的item#，SSCC Label 贴在外箱正面的正中间，贴一面即可，跟单订购，贴纸离外箱距必须至少3cm，每一 张SSCC label 都是唯一且有不同流水及条码的，没有损耗，绝对不可贴错 ，否则贴错或损坏一张会导致全部都错，千万要注意: SSCC 贴纸务必要在正中间(可以覆 盖Logo <(>&<)> 箱唛)，否则会影响到仓库扫描识别。 3. 日期码使用ZURU标准版本。 4. 如果大货有要求入邮包盒，则对应的邮包盒上面要打上日期码。 5. 按照客户PO# 装柜/箱号顺序装柜，跟单会提前给到装柜计划。在大货生产/仓库存放时，请留意该装柜要求，以便装柜时不混乱（避免装错/装漏/找不到货号等 ）。 6. 出口加拿大，包装需要至少2/3L UPC版，无硼版本。 7.邮包盒上要印刷日期码 | Y33: Kelly Shen | Z33: 2.5135 | AA33: =Z33*取消订单!J33 -> 120.648 | AC33: =AB33-J33 -> -48 | AM33: =J33 -> 48 | AQ33: =J33 -> 48 | BO33: 增加移印布标内容 | BS33: =J33 -> 48 | BT33: =J33 -> 48 | BV33: =SUM(BP33:BS33) -> 48 | BW33: =J33-BV33 -> 0
A34: 45824 | B34: AMAZON CA (VENDOR CENTER) | C34: 加拿大 | D34: 4500170130 | E34: 24U2MSNY | F34: 4500170130-70 | H34: 9543E-S001 | I34: 仓鼠 | J34: 48 | K34: 0 | L34: 24 | M34: =J34/L34 -> 2 | N34: 45859 | O34: 45855 | P34: 客户预计取消 | Q34: 无物料产生 | S34: 6/13收到 | U34: UPC贴纸翻4500098824 | V34: 欠外箱贴纸 | X34: 日期码格式：ZURU INC(BVI) 标准格式 日期：按实际生产日期 Packaging Info: #9543: MA 3L 加UPC贴纸， UPC贴纸跟翻单4500098824。B:193052051783, D:193052051790; E:193052051806; Remark: 1. Amazon FOB订单，出口CA。外箱最长边不能超过25" （超过了，case pack只能为1），不符合要求的大货，一律不接受。 2. 外箱正面印ZURU Logo + SSCC LABEL（客供贴纸)，侧面印item#（订单上显示的SKU#) + carton size(以工厂实际尺寸为准，单位: inch) + MADE IN CHINA， 日期使用ZURU 标准版本 SSCC Label 显示的是客人自己的item#，SSCC Label 贴在外箱正面的正中间，贴一面即可，跟单订购，贴纸离外箱距必须至少3cm，每一 张SSCC label 都是唯一且有不同流水及条码的，没有损耗，绝对不可贴错 ，否则贴错或损坏一张会导致全部都错，千万要注意: SSCC 贴纸务必要在正中间(可以覆 盖Logo <(>&<)> 箱唛)，否则会影响到仓库扫描识别。 3. 日期码使用ZURU标准版本。 4. 如果大货有要求入邮包盒，则对应的邮包盒上面要打上日期码。 5. 按照客户PO# 装柜/箱号顺序装柜，跟单会提前给到装柜计划。在大货生产/仓库存放时，请留意该装柜要求，以便装柜时不混乱（避免装错/装漏/找不到货号等 ）。 6. 出口加拿大，包装需要至少2/3L UPC版，无硼版本。 7.邮包盒上要印刷日期码 | Y34: Kelly Shen | Z34: 2.5135 | AA34: =Z34*取消订单!J34 -> 120.648 | AC34: =AB34-J34 -> -48 | AM34: =J34 -> 48 | AQ34: =J34 -> 48 | BO34: 增加移印布标内容 | BS34: =J34 -> 48 | BT34: =J34 -> 48 | BV34: =SUM(BP34:BS34) -> 48 | BW34: =J34-BV34 -> 0
A35: 45798 | B35: Amazon CA (Vendor Center) | C35: 加拿大 | D35: 4500167361 | E35: 1YI61R4Y | F35: 4500167361-40 | G35: 9543E-S001-3L | H35: 9543E-S001 | I35: 仓鼠 | J35: 72 | K35: 0 | L35: 24 | M35: =J35/L35 -> 3 | N35: 45834 | O35: 45831 | P35: 客户取消 | Q35: 无物料产生 | S35: 5/21收到 | U35: UPC贴纸翻4500098824 | V35: 6/11-客供外箱贴纸 | X35: 日期码格式：ZURU INC(BVI) 标准格式 日期：按实际生产日期 Packaging Info: 出口加拿大，包装需要至少2/3L UPC版，无硼版本。 #9543: MA 3L 加UPC贴纸， UPC贴纸跟翻单4500098824。A:193052051776, B:193052051783,E:193052051806; Remark: 1. Amazon FOB订单，出口CA。外箱最长边不能超过25" （超过了，case pack只能为1），不符合要求的大货，一律不接受。 2. 外箱正面印ZURU Logo + SSCC LABEL（客供贴纸)，侧面印item#（订单上显示的SKU#) + carton size(以工厂实际尺寸为准，单位: inch) + MADE IN CHINA， 日期使用ZURU 标准版本 SSCC Label 显示的是客人自己的item#，SSCC Label 贴在外箱正面的正中间，贴一面即可，跟单订购，贴纸离外箱距必须至少3cm，每一 张SSCC label 都是唯一且有不同流水及条码的，没有损耗，绝对不可贴错 ，否则贴错或损坏一张会导致全部都错，千万要注意: SSCC 贴纸务必要在正中间(可以覆 盖Logo <(>&<)> 箱唛)，否则会影响到仓库扫描识别。 3. 日期码使用ZURU标准版本。 4. 如果大货有要求入邮包盒，则对应的邮包盒上面要打上日期码。 5. 按照客户PO# 装柜/箱号顺序装柜，跟单会提前给到装柜计划。在大货生产/仓库存放时，请留意该装柜要求，以便装柜时不混乱（避免装错/装漏/找不到货号等 ）。 6. 出口加拿大，包装需要至少2/3L UPC版，无硼版本。 7.邮包盒上要印刷日期码 | Y35: Kelly Shen | Z35: 2.4879 | AA35: =J35*Z35 -> 179.1288 | AC35: =AB35-J35 -> -72 | AD35: ok | AE35: 已入 | AF35: 系统出单 | AM35: =J35 -> 72 | AQ35: =J35 -> 72 | BO35: 增加移印布标内容 | BS35: =J35 -> 72 | BT35: =J35 -> 72 | BV35: =SUM(BP35:BS35) -> 72 | BW35: =J35-BV35 -> 0
A36: 45611 | B36: DM LLC | C36: 俄罗斯联邦 | D36: 4500151414 | E36: 出Bekasovo 2 | F36: 4500151414-20 | G36: 9543-S001 | H36: 9543-S001 | I36: 仓鼠 | J36: 1824 | K36: 0 | L36: 24 | M36: =J36/L36 -> 76 | N36: 45847 | O36: 45843 | P36: 7/29取消订单 | Q36: 无物料产生 | S36: 11/19收到 | U36: 进口商贴纸+ EAN条码贴纸翻4500151398 | W36: 外包装/外箱不要打ZURU标准日期码 | X36: 日期码格式：外包装/外箱不要打ZURU标准日期码 日期： Packaging Info: 注意 ：外包装 (指: 收缩膜/彩卡/铝箔袋/挂卡/PDQ) /外箱不要打ZURU标准日期码！胶件可以打日期码。 9543: 1L MA 收缩膜 or 彩卡 + 进口商贴纸翻4500151398+ EAN条码贴纸翻4500151398，MA 指南 /说明书（如有）； | Y36: Ann Zhang | Z36: 2.5721 | AA36: =J36*Z36 -> 4691.5104 | AC36: =AB36-J36 -> -1824 | AD36: OK | AE36: 已入 | AF36: 系统出单 | AK36: =J36 -> 1824 | AQ36: =J36 -> 1824 | BO36: 增加移印布标内容 | BP36: =J36/4 -> 456 | BQ36: =J36/4 -> 456 | BR36: =J36/4 -> 456 | BS36: =J36/4 -> 456 | BT36: =J36 -> 1824 | BV36: =SUM(BP36:BS36) -> 1824 | BW36: =J36-BV36 -> 0
A37: 45611 | B37: DM LLC | C37: 俄罗斯联邦 | D37: 4500151414 | E37: 出Ural | F37: 4500151414-110 | G37: 9543-S001 | H37: 9543-S001 | I37: 仓鼠 | J37: 792 | K37: 0 | L37: 24 | M37: =J37/L37 -> 33 | N37: 45847 | O37: 45843 | P37: 7/29取消订单 | Q37: 无物料产生 | S37: 11/19收到 | U37: 进口商贴纸+ EAN条码贴纸翻4500151398 | W37: 外包装/外箱不要打ZURU标准日期码 | X37: 日期码格式：外包装/外箱不要打ZURU标准日期码 日期： Packaging Info: 注意 ：外包装 (指: 收缩膜/彩卡/铝箔袋/挂卡/PDQ) /外箱不要打ZURU标准日期码！胶件可以打日期码。 9543: 1L MA 收缩膜 or 彩卡 + 进口商贴纸翻4500151398+ EAN条码贴纸翻4500151398，MA 指南 /说明书（如有）； | Y37: Ann Zhang | Z37: 2.5721 | AA37: =J37*Z37 -> 2037.1032 | AC37: =AB37-J37 -> -792 | AD37: OK | AE37: 已入 | AF37: 系统出单 | AK37: =J37 -> 792 | AQ37: =J37 -> 792 | BO37: 增加移印布标内容 | BP37: =J37/4 -> 198 | BQ37: =J37/4 -> 198 | BR37: =J37/4 -> 198 | BS37: =J37/4 -> 198 | BT37: =J37 -> 792 | BV37: =SUM(BP37:BS37) -> 792 | BW37: =J37-BV37 -> 0
A38: 45726 | B38: DM LLC | C38: 俄罗斯联邦 | D38: 4500159511 | E38: 出Bekasovo 2 | F38: 4500159511-10 | G38: 9543-S001 | H38: 9543-S001 | I38: 仓鼠 | J38: 1656 | K38: 0 | L38: 24 | M38: =J38/L38 -> 69 | N38: 45806 | O38: 45803 | P38: 10/14取消 | Q38: 全部返工，费用已经收取-4500181762 | R38: 纸箱滞留 | S38: 3/13收到 | U38: 进口商贴纸+EAN条码贴纸翻4500159461 | W38: 外包装/外箱不要打ZURU标准日期码 | X38: 日期码格式：外包装/外箱不要打ZURU标准日期码 日期： Packaging Info: 注意 ：外包装 (指: 收缩膜/彩卡/铝箔袋/挂卡/PDQ) /外箱不要打ZURU标准日期码！胶件可以打日期码。 9543 : 1L MA 收缩膜+ 进口商贴纸翻4500159461+EAN条码贴纸翻4500159461， MA指南/说明书（如有）； Remark: 标准配比 ； 请按期完货， 会有罚金。 出2个港口Bekasovo 2 和Ural . | Y38: Ann | Z38: 2.4904 | AA38: =J38*Z38 -> 4124.1024 | AB38: 1656 | AC38: =AB38-J38 -> 0 | AD38: OK | AE38: 已入 | AF38: 系统出单 | AK38: =J38 -> 1656 | AQ38: =J38 -> 1656 | BO38: 增加移印布标内容 | BP38: =J38/4 -> 414 | BQ38: =J38/4 -> 414 | BR38: =J38/4 -> 414 | BS38: =J38/4 -> 414 | BT38: =J38 -> 1656 | BV38: =SUM(BP38:BS38) -> 1656 | BW38: =J38-BV38 -> 0
A39: 45726 | B39: DM LLC | C39: 俄罗斯联邦 | D39: 4500159511 | E39: 出Ural | F39: 4500159511-90 | G39: 9543-S001 | H39: 9543-S001 | I39: 仓鼠 | J39: 648 | K39: 0 | L39: 24 | M39: =J39/L39 -> 27 | N39: 45806 | O39: 45803 | P39: 10/14取消 | Q39: 全部返工，费用已经收取-4500181762 | R39: 纸箱滞留 | S39: 3/13收到 | U39: 进口商贴纸+EAN条码贴纸翻4500159461 | W39: 外包装/外箱不要打ZURU标准日期码 | X39: 日期码格式：外包装/外箱不要打ZURU标准日期码 日期： Packaging Info: 注意 ：外包装 (指: 收缩膜/彩卡/铝箔袋/挂卡/PDQ) /外箱不要打ZURU标准日期码！胶件可以打日期码。 9543 : 1L MA 收缩膜+ 进口商贴纸翻4500159461+EAN条码贴纸翻4500159461， MA指南/说明书（如有）； Remark: 标准配比 ； 请按期完货， 会有罚金。 出2个港口Bekasovo 2 和Ural . | Y39: Ann | Z39: 2.4904 | AA39: =J39*Z39 -> 1613.7792 | AB39: 648 | AC39: =AB39-J39 -> 0 | AD39: OK | AE39: 已入 | AF39: 系统出单 | AK39: =J39 -> 648 | AQ39: =J39 -> 648 | BO39: 增加移印布标内容 | BP39: =J39/4 -> 162 | BQ39: =J39/4 -> 162 | BR39: =J39/4 -> 162 | BS39: =J39/4 -> 162 | BT39: =J39 -> 648 | BV39: =SUM(BP39:BS39) -> 648 | BW39: =J39-BV39 -> 0
A40: 45611 | B40: DM LLC | C40: 俄罗斯联邦 | D40: 4500151404 | E40: 出Bekasovo 2 | F40: 4500151404-20 | G40: 9543-S001 | H40: 9543-S001 | I40: 仓鼠 | J40: 1680 | K40: 0 | L40: 24 | M40: =J40/L40 -> 70 | N40: 45817 | O40: 45813 | P40: 10/14取消 | Q40: 全部返工，费用已经收取-4500181762 | R40: 纸箱滞留 | S40: 11/19收到 | U40: 进口商贴纸+ EAN条码贴纸翻4500151398 | W40: 外包装/外箱不要打ZURU标准日期码 | X40: 日期码格式：外包装/外箱不要打ZURU标准日期码 日期： Packaging Info: 注意 ：外包装 (指: 收缩膜/彩卡/铝箔袋/挂卡/PDQ) /外箱不要打ZURU标准日期码！胶件可以打日期码。 9543 : 1L MA 收缩膜 or 彩卡 + 进口商贴纸翻4500151398+ EAN条码贴纸翻4500151398，MA 指南 /说明书（如有）； Remark: 标准配比 出BEKASOVO 2 和Ural 2 个港口； 货期不可延， 有罚金 。 | Y40: Ann Zhang | Z40: 2.5459 | AA40: =J40*Z40 -> 4277.112 | AB40: 1680 | AC40: =AB40-J40 -> 0 | AE40: 已入 | AF40: 系统出单 | AK40: =J40 -> 1680 | AQ40: =J40 -> 1680 | BO40: 增加移印布标内容 | BP40: =J40/4 -> 420 | BQ40: =J40/4 -> 420 | BR40: =J40/4 -> 420 | BS40: =J40/4 -> 420 | BT40: =J40 -> 1680 | BV40: =SUM(BP40:BS40) -> 1680 | BW40: =J40-BV40 -> 0
A41: 45611 | B41: DM LLC | C41: 俄罗斯联邦 | D41: 4500151404 | E41: 出Ural | F41: 4500151404-110 | G41: 9543-S001 | H41: 9543-S001 | I41: 仓鼠 | J41: 840 | K41: 0 | L41: 24 | M41: =J41/L41 -> 35 | N41: 45817 | O41: 45813 | P41: 10/14取消 | Q41: 全部返工，费用已经收取-4500181762 | R41: 纸箱滞留 | S41: 11/19收到 | U41: 进口商贴纸+ EAN条码贴纸翻4500151398 | W41: 外包装/外箱不要打ZURU标准日期码 | X41: 日期码格式：外包装/外箱不要打ZURU标准日期码 日期： Packaging Info: 注意 ：外包装 (指: 收缩膜/彩卡/铝箔袋/挂卡/PDQ) /外箱不要打ZURU标准日期码！胶件可以打日期码。 9543 : 1L MA 收缩膜 or 彩卡 + 进口商贴纸翻4500151398+ EAN条码贴纸翻4500151398，MA 指南 /说明书（如有）； Remark: 标准配比 出BEKASOVO 2 和Ural 2 个港口； 货期不可延， 有罚金 。 | Y41: Ann Zhang | Z41: 2.5459 | AA41: =J41*Z41 -> 2138.556 | AB41: 840 | AC41: =AB41-J41 -> 0 | AD41: OK | AE41: 已入 | AF41: 系统出单 | AK41: =J41 -> 840 | AQ41: =J41 -> 840 | BO41: 增加移印布标内容 | BP41: =J41/4 -> 210 | BQ41: =J41/4 -> 210 | BR41: =J41/4 -> 210 | BS41: =J41/4 -> 210 | BT41: =J41 -> 840 | BV41: =SUM(BP41:BS41) -> 840 | BW41: =J41-BV41 -> 0
A42: 45965 | B42: WALMART CENTRAL AMERICA-HN | C42: 洪都拉斯 | D42: 4500184399 | F42: 4500184399-60 | G42: 9543GQ1-S001-3L | H42: 9543GQ1-S001 | I42: 仓鼠 | J42: 132 | K42: 0 | L42: 22 | M42: =J42/L42 -> 6 | N42: 46009 | O42: 46006 | S42: 欠 | U42: 进口商贴纸翻4500158302 | X42: 日期码格式：ZURU INC(BVI) 标准格式 日期：按实际生产日期 Packaging Info: 5. 9543GQ1：MA 3L UPC包装+MA 3L PDQ包装+MA 多语说明书+进口商贴纸+箱唛，贴纸翻单PO4500158302 Remark: 1.请注意产品包装条形码必须是UPC 2.无第三方验货 8. 9543GQ1：bule/purple/pink/orange =5:6:6:5;2PCS AAA BATTERIES(NOT INCLUDED) | Y42: Ever Li | Z42: 2.7291 | AA42: =J42*Z42 -> 360.2412 | AE42: 已入 | AO42: =J42 -> 132 | AT42: =J42 -> 132 | BA42: =J42/11 -> 12 | BS42: 增加移印布标内容 | BT42: =J42/22*5 -> 30 | BU42: =J42/22*6 -> 36 | BV42: =J42/22*6 -> 36 | BW42: =J42/22*5 -> 30 | BX42: =J42 -> 132 | BY42: =J42/11 -> 12 | BZ42: =SUM(BT42:BW42) -> 132 | CA42: =J42-BZ42 -> 0
A43: 45895 | B43: ASDA STORES LTD | C43: 英国 | D43: 4500177833 | E43: PO#2950867080 | F43: 4500177833-10 | G43: 9543SLB-S002 | H43: 9543SLB-S002 | I43: 仓鼠卡板装 | J43: 1920 | K43: 8 | L43: 640 | M43: =J43/L43 -> 3 | N43: 45943 | O43: 45939 | P43: 11/4客户取消 | Q43: 4500185851消耗成品 | R43: 纸箱+PDQ 滞留 | U43: 8/28收到slip sheet贴纸+WEEE不带电池走货欧洲30语通用黑白说明书 | X43: 日期码格式：ZURU INC(BVI) 标准格式 日期：按实际生产日期 Packaging Info: 9543SLB-S002, MA最新UPC包装+WEEE不带电池走货欧洲30语通用黑白说明书 ，UPC :193052050328，请先检查条码是否正确再安排做货。 Slip sheet: 9543GQ6-S001 8pcs/CTN(Carton Size:24.5x24.5x25.5CM);16*5=80cartons=640pcs/Slip Sheet;一共需要3套slip sheet； Slip Sheet打包好后，需要在正唛、侧唛右下角各贴一张slip sheet贴纸，直接用A4纸打印出来即可，贴纸尺寸160mm width x 140mm high； Slip Sheet尺寸限制为100*115*130CM，一旦实际SLIP SHEET尺寸超过这个尺寸，请提前通知ZURU跟单，需同客人确认才能量产和出货.""" Remark: "1. 产品及包装需要印UKCA图标，包装需要有ZURU UK LTD/ZURU France地址信息，QC同事请核查，如有问题与跟单确认 2. 产品/包装/外箱都需要打ZURU格式日期码，日期必须为法定工作日。 3. 需要符合欧洲标准不能含有闪粉和微塑料，否则不合法规会有客诉产生" | Y43: Aaron Xia | Z43: 1564.6026 | AA43: =M43*Z43 -> 4693.8078 | AB43: 1920 | AC43: =AB43-J43 -> 0 | AD43: ok | AE43: 已入 | AF43: 系统出单 | AK43: =J43 -> 1920 | AS43: =J43 -> 1920 | BP43: =J43/8 -> 240 | BT43: 增加移印布标内容 | BU43: =J43/4 -> 480 | BV43: =J43/4 -> 480 | BW43: =J43/4 -> 480 | BX43: =J43/4 -> 480 | BY43: =J43 -> 1920 | CA43: =SUM(BU43:BX43) -> 1920 | CB43: =J43-CA43 -> 0
A44: 45986 | B44: ZURU GERMANY GMBH | C44: 德国 | D44: 4500186834 | E44: 5200008259 | F44: 4500186834-30 | G44: 9543GQ1-S002-MTS | H44: 仓鼠 | I44: 2607 | J44: 0 | K44: 11 | L44: 237 | M44: 46024 | N44: 46020 | O44: 5L(PL+HU+CZ+SK+RO)说明书（翻单4500176308） | R44: 12/5收到 | T44: baby EAN贴纸+多语折叠警告语贴纸+ B版 WEEE 30L不带电池走货说明书（翻单4500173920） | W44: 日期码格式：ZURU INC(BVI) 标准格式 日期：按实际生产日期 Packaging Info: 9543GQ1：MA 3L PDQ +MA 3L+9L警语 UPC 收缩膜 +1*baby EAN贴纸（翻单4500173920）+1*多语折叠警告语贴纸（翻单4500173920） + MA 5L+9LWarning 说明书+1* 5L(PL+HU+CZ+SK+RO)说明书（翻单4500176308）+ 1张B版 WEEE 30L不带电池走货说明书（翻单4500173920） Remark: 1.波兰内销单，需要通过ZURU 验货结果后才能出货 (工厂需要主动提前同ZURU QC预约验货避免延期出货造成不必要麻烦)； 2. 产品如含有化学品，需要无硼无香；无微塑料 3. 若有特定款有特殊外箱条码要求时,需要明确列出产品款对应的具体外箱条码号码/条码类型 (若无,可以忽略此需求)； 4.所有出口欧洲的产品, 法规规定禁止在包装和共公众用的印刷品中使用矿物油中含有的物质, 包装印刷油墨中含有的MOAH/MOSH的质量浓度不能超过1%, 否则出货 到法国被抽检出现问题, 供应商需要对此负责; 5. date code: 外箱日期码要晚于或等于产品日期码，不能早于产品的日期码； 6. 所有电子产品身上需要加字唛，为ZURU FRANCE 地址 (如无电子产品，或者产品布标有此地址，可忽略此信息) ZURU FRANCE 33 rue Paul Meurice 75020 Paris, France.； 7. 装柜时需要按照款式号码从小到大一款款依次装,避免终端仓库卸货混乱.若一个柜子涉及到几个不同国家内销单,装柜时需要一个国家装完后再装另一个国家的 产品,依次装柜,避免终端仓库因不同国家不同库位位置卸货混乱. (此点需要同工厂装柜人员强调)。 8. 所有出往波兰订单的电子产品需增加一张欧洲通用WEEE声明说明书，区分带电池和不带电池版本, 如已做客版说明书可忽略此要求。 | X44: Niki Chen | Y44: 2.7028 | Z44: 7046.1996 | AB44: -2607 | AC44: ok | AD44: 已入 | AE44: 系统出单 | AJ44: 2607 | AM44: 2607 | AR44: 237 | BF44: 增加移印布标内容 | BG44: 592.5 | BH44: 711 | BI44: 711 | BJ44: 592.5 | BK44: 2607 | BL44: 237 | BM44: 2607 | BN44: 0
A45: 46085 | B45: AMAZON CA (VENDOR CENTER) | C45: 加拿大 | D45: 4500195135 | E45: 4OAMZ5MH | F45: 4500195135-250 | G45: 9543D-S001-3L | H45: 9543D-S001 | I45: 仓鼠 | J45: 96 | K45: 0 | L45: 24 | M45: =J45/L45 -> 4 | N45: 46127 | O45: 46123 | P45: 客户取消 | S45: 3/4收到 | U45: UPC贴纸翻4500098824 | V45: 欠外箱贴纸 | X45: 日期码格式：ZURU INC(BVI) 标准格式 日期：按实际生产日期 Packaging Info: 出口加拿大，包装需要至少2/3L UPC版，无硼版本。 #9543: MA 3L 加UPC贴纸， UPC贴纸跟翻单4500098824。A:193052051776, B:193052051783, D:193052051790; E:193052051806; Remark: 1. Amazon FOB订单，出口CA。外箱最长边不能超过25" （超过了，case pack只能为1），不符合要求的大货，一律不接受。 2. 外箱正面印ZURU Logo + SSCC LABEL（客供贴纸)，侧面印item#（订单上显示的SKU#) + carton size(以工厂实际尺寸为准，单位: inch) + MADE IN CHINA， 日期使用ZURU 标准版本 SSCC Label 显示的是客人自己的item#，SSCC Label 贴在外箱正面的正中间，贴一面即可，跟单订购，贴纸离外箱距必须至少3cm，每一 张SSCC label 都是唯一且有不同流水及条码的，没有损耗，绝对不可贴错 ，否则贴错或损坏一张会导致全部都错，千万要注意: SSCC 贴纸务必要在正中间(可以覆 盖Logo <(>&<)> 箱唛)，否则会影响到仓库扫描识别。 3. 日期码使用ZURU标准版本。 4. 如果大货有要求入邮包盒，则对应的邮包盒上面要打上日期码。 5. 按照客户PO# 装柜/箱号顺序装柜，跟单会提前给到装柜计划。在大货生产/仓库存放时，请留意该装柜要求，以便装柜时不混乱（避免装错/装漏/找不到货号等 ）。 6. 出口加拿大，包装需要至少2/3L UPC版，无硼版本。 7.邮包盒上要印刷日期码 | Y45: Kelly Shen | Z45: 2.5718 | AA45: =J45*Z45 -> 246.8928 | AC45: =AB45-J45 -> -96 | AD45: ok | AE45: 已入 | AF45: 系统出单 | AO45: =J45 -> 96 | AT45: =J45 -> 96 | BV45: 增加移印布标内容 | BY45: =J45 -> 96 | CA45: =J45 -> 96 | CC45: =SUM(BW45:BZ45) -> 96 | CD45: =J45-CC45 -> 0
A46: 46085 | B46: AMAZON CA (VENDOR CENTER) | C46: 加拿大 | D46: 4500195135 | E46: 7XWIABXY | F46: 4500195135-260 | G46: 9543D-S001-3L | H46: 9543D-S001 | I46: 仓鼠 | J46: 48 | K46: 0 | L46: 24 | M46: =J46/L46 -> 2 | N46: 46127 | O46: 46123 | P46: 客户取消 | S46: 3/4收到 | U46: UPC贴纸翻4500098824 | V46: 欠外箱贴纸 | X46: 日期码格式：ZURU INC(BVI) 标准格式 日期：按实际生产日期 Packaging Info: 出口加拿大，包装需要至少2/3L UPC版，无硼版本。 #9543: MA 3L 加UPC贴纸， UPC贴纸跟翻单4500098824。A:193052051776, B:193052051783, D:193052051790; E:193052051806; Remark: 1. Amazon FOB订单，出口CA。外箱最长边不能超过25" （超过了，case pack只能为1），不符合要求的大货，一律不接受。 2. 外箱正面印ZURU Logo + SSCC LABEL（客供贴纸)，侧面印item#（订单上显示的SKU#) + carton size(以工厂实际尺寸为准，单位: inch) + MADE IN CHINA， 日期使用ZURU 标准版本 SSCC Label 显示的是客人自己的item#，SSCC Label 贴在外箱正面的正中间，贴一面即可，跟单订购，贴纸离外箱距必须至少3cm，每一 张SSCC label 都是唯一且有不同流水及条码的，没有损耗，绝对不可贴错 ，否则贴错或损坏一张会导致全部都错，千万要注意: SSCC 贴纸务必要在正中间(可以覆 盖Logo <(>&<)> 箱唛)，否则会影响到仓库扫描识别。 3. 日期码使用ZURU标准版本。 4. 如果大货有要求入邮包盒，则对应的邮包盒上面要打上日期码。 5. 按照客户PO# 装柜/箱号顺序装柜，跟单会提前给到装柜计划。在大货生产/仓库存放时，请留意该装柜要求，以便装柜时不混乱（避免装错/装漏/找不到货号等 ）。 6. 出口加拿大，包装需要至少2/3L UPC版，无硼版本。 7.邮包盒上要印刷日期码 | Y46: Kelly Shen | Z46: 2.5718 | AA46: =J46*Z46 -> 123.4464 | AC46: =AB46-J46 -> -48 | AD46: ok | AE46: 已入 | AF46: 系统出单 | AO46: =J46 -> 48 | AT46: =J46 -> 48 | BV46: 增加移印布标内容 | BY46: =J46 -> 48 | CA46: =J46 -> 48 | CC46: =SUM(BW46:BZ46) -> 48 | CD46: =J46-CC46 -> 0
A47: 46085 | B47: AMAZON CA (VENDOR CENTER) | C47: 加拿大 | D47: 4500195135 | E47: 5AA11OSJ | F47: 4500195135-270 | G47: 9543D-S001-3L | H47: 9543D-S001 | I47: 仓鼠 | J47: 120 | K47: 0 | L47: 24 | M47: =J47/L47 -> 5 | N47: 46127 | O47: 46123 | P47: 客户取消 | S47: 3/4收到 | U47: UPC贴纸翻4500098824 | V47: 欠外箱贴纸 | X47: 日期码格式：ZURU INC(BVI) 标准格式 日期：按实际生产日期 Packaging Info: 出口加拿大，包装需要至少2/3L UPC版，无硼版本。 #9543: MA 3L 加UPC贴纸， UPC贴纸跟翻单4500098824。A:193052051776, B:193052051783, D:193052051790; E:193052051806; Remark: 1. Amazon FOB订单，出口CA。外箱最长边不能超过25" （超过了，case pack只能为1），不符合要求的大货，一律不接受。 2. 外箱正面印ZURU Logo + SSCC LABEL（客供贴纸)，侧面印item#（订单上显示的SKU#) + carton size(以工厂实际尺寸为准，单位: inch) + MADE IN CHINA， 日期使用ZURU 标准版本 SSCC Label 显示的是客人自己的item#，SSCC Label 贴在外箱正面的正中间，贴一面即可，跟单订购，贴纸离外箱距必须至少3cm，每一 张SSCC label 都是唯一且有不同流水及条码的，没有损耗，绝对不可贴错 ，否则贴错或损坏一张会导致全部都错，千万要注意: SSCC 贴纸务必要在正中间(可以覆 盖Logo <(>&<)> 箱唛)，否则会影响到仓库扫描识别。 3. 日期码使用ZURU标准版本。 4. 如果大货有要求入邮包盒，则对应的邮包盒上面要打上日期码。 5. 按照客户PO# 装柜/箱号顺序装柜，跟单会提前给到装柜计划。在大货生产/仓库存放时，请留意该装柜要求，以便装柜时不混乱（避免装错/装漏/找不到货号等 ）。 6. 出口加拿大，包装需要至少2/3L UPC版，无硼版本。 7.邮包盒上要印刷日期码 | Y47: Kelly Shen | Z47: 2.5718 | AA47: =J47*Z47 -> 308.616 | AC47: =AB47-J47 -> -120 | AD47: ok | AE47: 已入 | AF47: 系统出单 | AO47: =J47 -> 120 | AT47: =J47 -> 120 | BV47: 增加移印布标内容 | BY47: =J47 -> 120 | CA47: =J47 -> 120 | CC47: =SUM(BW47:BZ47) -> 120 | CD47: =J47-CC47 -> 0
A48: 46083 | B48: AMAZON CA (VENDOR CENTER) | C48: 加拿大 | D48: 4500194885 | E48: 2954EQMV | F48: 4500194885-320 | G48: 9543D-S001-3L | H48: 9543D-S001 | I48: 仓鼠 | J48: 24 | K48: 0 | L48: 24 | M48: =J48/L48 -> 1 | N48: 46122 | O48: 46118 | P48: 客户取消 | S48: 3/2收到 | U48: UPC贴纸翻4500098824 | X48: 日期码格式：ZURU INC(BVI) 标准格式 日期：按实际生产日期 Packaging Info: 出口加拿大，包装需要至少2/3L UPC版，无硼版本. #9543: MA 3L 加UPC贴纸， UPC贴纸跟翻单4500098824。A:193052051776, B:193052051783, D:193052051790; E:193052051806; Remark: 1. Amazon FOB订单，出口CA。外箱最长边不能超过25" （超过了，case pack只能为1），不符合要求的大货，一律不接受。 2. 外箱正面印ZURU Logo + SSCC LABEL（客供贴纸)，侧面印item#（订单上显示的SKU#) + carton size(以工厂实际尺寸为准，单位: inch) + MADE IN CHINA， 日期使用ZURU 标准版本 SSCC Label 显示的是客人自己的item#，SSCC Label 贴在外箱正面的正中间，贴一面即可，跟单订购，贴纸离外箱距必须至少3cm，每一 张SSCC label 都是唯一且有不同流水及条码的，没有损耗，绝对不可贴错 ，否则贴错或损坏一张会导致全部都错，千万要注意: SSCC 贴纸务必要在正中间(可以覆 盖Logo <(>&<)> 箱唛)，否则会影响到仓库扫描识别。 3. 日期码使用ZURU标准版本。 4. 如果大货有要求入邮包盒，则对应的邮包盒上面要打上日期码。 5. 按照客户PO# 装柜/箱号顺序装柜，跟单会提前给到装柜计划。在大货生产/仓库存放时，请留意该装柜要求，以便装柜时不混乱（避免装错/装漏/找不到货号等 ）。 6. 出口加拿大，包装需要至少2/3L UPC版，无硼版本。 7.邮包盒上要印刷日期码 | Y48: Kelly Shen | Z48: 2.5115 | AA48: =J48*Z48 -> 60.276 | AC48: =AB48-J48 -> -24 | AD48: ok | AE48: 已入 | AF48: 系统出单 | AO48: =J48 -> 24 | AT48: =J48 -> 24 | BV48: 增加移印布标内容 | BY48: =J48 -> 24 | CA48: =J48 -> 24 | CC48: =SUM(BW48:BZ48) -> 24 | CD48: =J48-CC48 -> 0
A49: 46058 | B49: WALGREENS CO. | C49: 美国 | D49: 4500193110 | E49: 4561394696 | F49: 4500193110-50 | G49: 9543GQ4-S001 | H49: 9543GQ4-S001 | I49: 仓鼠 | J49: 606 | K49: 0 | L49: 6 | M49: =J49/L49 -> 101 | N49: 46119 | O49: 46115 | S49: 2/5收到 | U49: WIC 贴纸翻4500130295 PDQ折页翻4500099653 | X49: 日期码格式：ZURU INC(BVI) 标准格式 日期：04-07-2026 Packaging Info: 9543GQ4：MA 1L 包装 + WIC 贴纸（WIC # 280432 参考4500130295） + 客版PDQ(翻单4500130295) + PDQ折页 （翻单PO 4500099653，PDQ折页放在PDQ的正上方， 开箱即可看到） Remark: 产品和包装上面要有zuru标准格式的tracking code DG20260407 Order | Y49: Cara Li | Z49: 1.5775 | AA49: =J49*Z49 -> 955.965 | AC49: =AB49-J49 -> -606 | AD49: ok | AE49: 已入 | AF49: 系统出单 | AL49: =取消订单!J49 -> 606 | AT49: =取消订单!J49 -> 606 | BK49: =取消订单!J49/6 -> 101 | BV49: 增加移印布标内容 | BW49: =取消订单!J49/4 -> 151.5 | BX49: =取消订单!J49/4 -> 151.5 | BY49: =取消订单!J49/4 -> 151.5 | BZ49: =取消订单!J49/4 -> 151.5 | CA49: =取消订单!J49 -> 606 | CC49: =SUM(BW49:BZ49) -> 606 | CD49: =取消订单!J49-CC49 -> 0
A50: 46101 | B50: AMAZON CA (VENDOR CENTER) | C50: 加拿大 | D50: 4500197925 | E50: 2F3OU83S | F50: 4500197925-160 | G50: 9543D-S001 | H50: 仓鼠 | I50: 24 | J50: 0 | K50: 24 | L50: =I50/K50 -> 1 | M50: 46149 | N50: 46146 | O50: 4/3-取消 | T50: UPC贴纸翻4500098824 | U50: 欠外箱贴纸 | W50: 日期码格式：ZURU INC(BVI) 标准格式 日期：按实际生产日期 Packaging Info: 出口加拿大，包装需要至少2/3L UPC版，无硼版本。 #9298: MA 3L C版本加UPC贴纸，UPC贴纸图稿跟返单4500113996。需混入稀有款， 常规款：稀有款=58：2。 D:193052062642, E:193052062659,G:193052062666, H:193052062673; #9543: MA 3L 加UPC贴纸， UPC贴纸跟翻单4500098824。B:193052051783, D:193052051790; #9548: MA 5L D版本 加UPC贴纸，MA 5L-D版本收缩膜配套使用最新版本的包材，贴纸资料跟翻单#4500146603，UPC：193052064196。 #9572: MA 3L包装入邮包盒，邮包盒图稿翻单4500177315, A: 2PK 9565 (Pink + Brown), B: 2PK 9565 (Blue + Orange)。 Remark: 1. Amazon FOB订单，出口CA。外箱最长边不能超过25" （超过了，case pack只能为1），不符合要求的大货，一律不接受。 2. 外箱正面印ZURU Logo + SSCC LABEL（客供贴纸)，侧面印item#（订单上显示的SKU#) + carton size(以工厂实际尺寸为准，单位: inch) + MADE IN CHINA， 日期使用ZURU 标准版本 SSCC Label 显示的是客人自己的item#，SSCC Label 贴在外箱正面的正中间，贴一面即可，跟单订购，贴纸离外箱距必须至少3cm，每一 张SSCC label 都是唯一且有不同流水及条码的，没有损耗，绝对不可贴错 ，否则贴错或损坏一张会导致全部都错，千万要注意: SSCC 贴纸务必要在正中间(可以覆 盖Logo <(>&<)> 箱唛)，否则会影响到仓库扫描识别。 3. 日期码使用ZURU标准版本。 4. 如果大货有要求入邮包盒，则对应的邮包盒上面要打上日期码。 5. 按照客户PO# 装柜/箱号顺序装柜，跟单会提前给到装柜计划。在大货生产/仓库存放时，请留意该装柜要求，以便装柜时不混乱（避免装错/装漏/找不到货号等 )。 6. 出口加拿大，包装需要至少2/3L UPC版，无硼版本。 7.邮包盒上要印刷日期码 | X50: Kelly Shen | Y50: 2.5718 | Z50: =I50*Y50 -> 61.7232 | AB50: =AA50-I50 -> -24 | AD50: ok | AE50: 已入 | AO50: =I50 -> 24 | AT50: =I50 -> 24 | BV50: 增加移印布标内容 | BY50: =I50 -> 24 | CA50: =I50 -> 24 | CC50: =SUM(BW50:BZ50) -> 24 | CD50: 0
A51: 46101 | B51: AMAZON CA (VENDOR CENTER) | C51: 加拿大 | D51: 4500197925 | E51: 88BK83VQ | F51: 4500197925-170 | G51: 9543D-S001 | H51: 仓鼠 | I51: 24 | J51: 0 | K51: 24 | L51: =I51/K51 -> 1 | M51: 46149 | N51: 46146 | O51: 4/3-取消 | T51: UPC贴纸翻4500098824 | U51: 欠外箱贴纸 | W51: 日期码格式：ZURU INC(BVI) 标准格式 日期：按实际生产日期 Packaging Info: 出口加拿大，包装需要至少2/3L UPC版，无硼版本。 #9298: MA 3L C版本加UPC贴纸，UPC贴纸图稿跟返单4500113996。需混入稀有款， 常规款：稀有款=58：2。 D:193052062642, E:193052062659,G:193052062666, H:193052062673; #9543: MA 3L 加UPC贴纸， UPC贴纸跟翻单4500098824。B:193052051783, D:193052051790; #9548: MA 5L D版本 加UPC贴纸，MA 5L-D版本收缩膜配套使用最新版本的包材，贴纸资料跟翻单#4500146603，UPC：193052064196。 #9572: MA 3L包装入邮包盒，邮包盒图稿翻单4500177315, A: 2PK 9565 (Pink + Brown), B: 2PK 9565 (Blue + Orange)。 Remark: 1. Amazon FOB订单，出口CA。外箱最长边不能超过25" （超过了，case pack只能为1），不符合要求的大货，一律不接受。 2. 外箱正面印ZURU Logo + SSCC LABEL（客供贴纸)，侧面印item#（订单上显示的SKU#) + carton size(以工厂实际尺寸为准，单位: inch) + MADE IN CHINA， 日期使用ZURU 标准版本 SSCC Label 显示的是客人自己的item#，SSCC Label 贴在外箱正面的正中间，贴一面即可，跟单订购，贴纸离外箱距必须至少3cm，每一 张SSCC label 都是唯一且有不同流水及条码的，没有损耗，绝对不可贴错 ，否则贴错或损坏一张会导致全部都错，千万要注意: SSCC 贴纸务必要在正中间(可以覆 盖Logo <(>&<)> 箱唛)，否则会影响到仓库扫描识别。 3. 日期码使用ZURU标准版本。 4. 如果大货有要求入邮包盒，则对应的邮包盒上面要打上日期码。 5. 按照客户PO# 装柜/箱号顺序装柜，跟单会提前给到装柜计划。在大货生产/仓库存放时，请留意该装柜要求，以便装柜时不混乱（避免装错/装漏/找不到货号等 )。 6. 出口加拿大，包装需要至少2/3L UPC版，无硼版本。 7.邮包盒上要印刷日期码 | X51: Kelly Shen | Y51: 2.5718 | Z51: =I51*Y51 -> 61.7232 | AB51: =AA51-I51 -> -24 | AD51: ok | AE51: 已入 | AO51: =I51 -> 24 | AT51: =I51 -> 24 | BV51: 增加移印布标内容 | BY51: =I51 -> 24 | CA51: =I51 -> 24 | CC51: =SUM(BW51:BZ51) -> 24 | CD51: 0
A52: 46101 | B52: AMAZON CA (VENDOR CENTER) | C52: 加拿大 | D52: 4500197925 | E52: 3LXGA6EY | F52: 4500197925-180 | G52: 9543D-S001 | H52: 仓鼠 | I52: 24 | J52: 0 | K52: 24 | L52: =I52/K52 -> 1 | M52: 46149 | N52: 46146 | O52: 4/3-取消 | T52: UPC贴纸翻4500098824 | U52: 欠外箱贴纸 | W52: 日期码格式：ZURU INC(BVI) 标准格式 日期：按实际生产日期 Packaging Info: 出口加拿大，包装需要至少2/3L UPC版，无硼版本。 #9298: MA 3L C版本加UPC贴纸，UPC贴纸图稿跟返单4500113996。需混入稀有款， 常规款：稀有款=58：2。 D:193052062642, E:193052062659,G:193052062666, H:193052062673; #9543: MA 3L 加UPC贴纸， UPC贴纸跟翻单4500098824。B:193052051783, D:193052051790; #9548: MA 5L D版本 加UPC贴纸，MA 5L-D版本收缩膜配套使用最新版本的包材，贴纸资料跟翻单#4500146603，UPC：193052064196。 #9572: MA 3L包装入邮包盒，邮包盒图稿翻单4500177315, A: 2PK 9565 (Pink + Brown), B: 2PK 9565 (Blue + Orange)。 Remark: 1. Amazon FOB订单，出口CA。外箱最长边不能超过25" （超过了，case pack只能为1），不符合要求的大货，一律不接受。 2. 外箱正面印ZURU Logo + SSCC LABEL（客供贴纸)，侧面印item#（订单上显示的SKU#) + carton size(以工厂实际尺寸为准，单位: inch) + MADE IN CHINA， 日期使用ZURU 标准版本 SSCC Label 显示的是客人自己的item#，SSCC Label 贴在外箱正面的正中间，贴一面即可，跟单订购，贴纸离外箱距必须至少3cm，每一 张SSCC label 都是唯一且有不同流水及条码的，没有损耗，绝对不可贴错 ，否则贴错或损坏一张会导致全部都错，千万要注意: SSCC 贴纸务必要在正中间(可以覆 盖Logo <(>&<)> 箱唛)，否则会影响到仓库扫描识别。 3. 日期码使用ZURU标准版本。 4. 如果大货有要求入邮包盒，则对应的邮包盒上面要打上日期码。 5. 按照客户PO# 装柜/箱号顺序装柜，跟单会提前给到装柜计划。在大货生产/仓库存放时，请留意该装柜要求，以便装柜时不混乱（避免装错/装漏/找不到货号等 )。 6. 出口加拿大，包装需要至少2/3L UPC版，无硼版本。 7.邮包盒上要印刷日期码 | X52: Kelly Shen | Y52: 2.5718 | Z52: =I52*Y52 -> 61.7232 | AB52: =AA52-I52 -> -24 | AD52: ok | AE52: 已入 | AO52: =I52 -> 24 | AT52: =I52 -> 24 | BV52: 增加移印布标内容 | BY52: =I52 -> 24 | CA52: =I52 -> 24 | CC52: =SUM(BW52:BZ52) -> 24 | CD52: 0
A53: 46129 | B53: AMAZON EU SARL, NDL DEUTSCHLAND | C53: 德国 | D53: 4500202512 | E53: 2U1DLVJZ | F53: 4500202512-10 | G53: 9543D-S002-MB | H53: 紫色仓鼠邮包盒 | I53: 480 | J53: 0 | K53: 24 | L53: =I53/K53 -> 20 | M53: 46181 | N53: 46177 | P53: 客户取消6/15 | Q53: 成品待消耗 | T53: 贴纸（含IT环保标+西班牙洗涤,贴邮包盒,翻单4500198659)+WEEE_不带电池走货 _说明书欧洲EN+30L_B版；+5/12-外箱贴纸 | W53: 日期码格式：ZURU INC(BVI) 标准格式 日期：按实际生产日期 Packaging Info: Amazon DE :2U1DLVJZ DE(9543AD) 1. 9543AD: --9543D:9543D 24pcs/ctn, no inner, purple; 客版邮包盒(UPC#+英法德意西5L警示语+FR/ES/IT环保标+GPSR邮箱care@zuru.com+新FR/DK/UK地址+西班牙洗涤说 明)+1张贴纸（含IT环保标+西班牙洗涤,贴邮包盒,翻单4500198659)+MA 3L（5L warning EAN#）D收缩膜+MA 5L(9L warning) C 说明书+WEEE_不带电池走货 _ 说明 书欧洲EN+30L_B版； 2. 最迟验货不得晚于6/9 Remark: 1.空白外箱（加印带Zuru字样的最新logo，除了邮包盒直接做外箱的产品） + SSCC LABEL一张, 无箱唛，MADE IN CHINA 外箱只印一正一侧。箱唛资料按照给定的 标准去做即可，无需发回我方再行审批(新标准将另行通知)。 (SSCC LABEL竖贴在外箱正面的正中间，贴一面即可,贴纸离外箱边距必须至少3.2CM。如竖贴无法满足要求，则横贴。如横贴也无法满足要求，则竖贴，遮到ZURU lo go无影响), SSCC贴纸由工厂直接跟勤得采购或者工厂自行采购，每一张SSCC Label都是唯一且有不同流水及条码，且需要检查条码是否能正常扫描，另外，此贴纸 印刷不可出现模糊，溢出及粘胶不牢易脱落等现象，如工厂不按此要求导致贴纸有任何问题产生的罚款将由工厂承担一切责任 ,<(>,<)> 此要求只适用Amazon UK/DE /FR/ES/IT,不适用Amazon GPE，Amazon GPE无SSCC label, 但是有对应箱唛，需印刷到外箱 。 2.出往UK的产品+包装务必打上UKCA logo ，否则客人会退货且当地会有罚款。Amazon GPE（包含UK/FR/ES/DE/IT）的订单也需满足此要求。 3.订单必须经过ZURU QC验货或者工厂自检通过后方可出货，不涉及第三方验货。 4.法国订单要求包装不使用矿物油，请按要求提供以下其中一份文件再出货 ，产品出到法国被相关部门抽检出现包装不符合此要求的，供应商需要为此承担责任， 故此请严格把关。Amazon GPE（包含UK/FR/ES/DE/IT）的订单也需满足此要求。 -油墨物质""""由1 ~ 7个芳香环组成的MOAH""""的包装检测报告，要求限值≤1.0%； -包装材料清单，包括包装油墨或物质的信息； -油墨制造商的证书； 5.每一批次出货只能有一个生产日期，不可多个生产日期混在同一批次出货；且零售包装上必须统一加上日期码；外箱对于日期码没有硬性规定； 6.涉及到相关款式会有闪粉的或者微塑料的，请统一默认出无闪粉或者不含微塑料版本； 7.邮包盒及外箱封箱必须是工字型封箱方式； 8.5 Surprise or Mini Brands涉及包装是2个及2个以上的球入PVC桶包装时，单个球上若有UPC#或者EAN#，请用空白贴纸覆盖住，贴纸尺寸自行测量能覆盖原条码即 可； 9. 无论是工厂自检还是ZURU验货，验货报告中必须有产品6面图(正面/背面/左面/右面/顶部/底部，不带包装); 10. 按空海运鉴定报告的要求，只要带锂电池出货，都需要加贴UN贴纸； 11. 所有出往GAS市场(德国/奥地利/瑞士)的电子产品身上需要加字唛，为ZURU FRANCE 地址，需跟包装上的地址一致 (如无电子产品，产品布标有此地址，或产品 太小无法增加可忽略此信息。如产品无法加字唛，需让对应跟单提供产品贴纸资料);（Amazon GPE的订单也需满足此要求） 12. 所有出往GAS德国 (瑞士，奥地利)。水弹枪系列必须使用EN71版本（电子和非电子水弹枪系列都需要符合); 护目镜需打日期码, 格式跟ZURU标准格式一样; 枪 身上增加ZURU FRANCE公司名和地址。使用贴纸和辐射上去都可以。如果有位置，最好增加ZURU Represented by: (此最好翻译德语，如果位置不允许，那么就只增 加ZURU法国和地址)。使用最新的EN71版包装和说明书）。Amazon GPE（包含UK/FR/ES/DE/IT）的订单也需满足此要求。 | X53: Luna Lin | Y53: 2.6134 | Z53: =I53*Y53 -> 1254.432 | AA53: 480 | AB53: =AA53-I53 -> 0 | AC53: ok | AD53: 9543D-S002-MB | AE53: 已入 | AF53: 系统出单 | AO53: =I53 -> 480 | AT53: =I53 -> 480 | BV53: 增加移印布标内容 | BY53: =I53 -> 480 | CC53: =SUM(BW53:BZ53) -> 480 | CD53: =I53-CC53 -> 0
A54: 46185 | B54: AMAZON UK | C54: 英国 | D54: 4500211828 | E54: 8I2TI3BU | F54: 4500211828-10 | G54: 9543D-S002-MB | H54: 紫色仓鼠（邮包盒） | I54: 480 | J54: 0 | K54: 24 | L54: =I54/K54 -> 20 | M54: 46237 | N54: 46233 | O54: 6/15客户取消 | P54: 客版邮包盒翻4500202513 | Q54: 无物料产生 | T54: 贴邮包盒贴纸翻4500198659+WEEE_不带电池走货 _ 说明书欧洲EN+29L_C版+欠外箱贴纸 | V54: ZURU INC(BVI) 标准格式 日期：按实际生产日期 | W54: 日期码格式：ZURU INC(BVI) 标准格式 日期：按实际生产日期 Packaging Info: Amazon UK:8I2TI3BU/7PTKZ6NS Amazon DE:4FR81SGO UK(9543DE/77555)/DE(77876) 1. 9543DE: --9543D:9543D 24pcs/ctn, no inner, pink; 客版邮包盒(UPC#+英法德意西5L警示语+ES环保标+GPSR邮箱care@zuru.com+新UK地址，参考翻单PO#4500202512)+1张 贴纸（1张含FR/IT环保标+西班牙洗涤说明，贴邮包盒，翻单4500198659）+MA 3L（5L warning EAN#）D收缩膜+MA 5L(9L warning) C 说明书+WEEE_不带电池走货 ___ 说明书欧洲EN+29L_C版； 4. 最晚验货时间 Remark: 1.空白外箱（加印带Zuru字样的最新logo，除了邮包盒直接做外箱的产品） + SSCC LABEL一张, 无箱唛，MADE IN CHINA 外箱只印一正一侧。箱唛资料按照给定的 标准去做即可，无需发回我方再行审批(新标准将另行通知)。 (SSCC LABEL竖贴在外箱正面的正中间，贴一面即可,贴纸离外箱边距必须至少3.2CM。如竖贴无法满足要求，则横贴。如横贴也无法满足要求，则竖贴，遮到ZURU lo go无影响), SSCC贴纸由工厂直接跟勤得采购或者工厂自行采购，每一张SSCC Label都是唯一且有不同流水及条码，且需要检查条码是否能正常扫描，另外，此贴纸 印刷不可出现模糊，溢出及粘胶不牢易脱落等现象，如工厂不按此要求导致贴纸有任何问题产生的罚款将由工厂承担一切责任 ,<(>,<)> 此要求只适用Amazon UK/DE /FR/ES/IT,不适用Amazon GPE，Amazon GPE无SSCC label, 但是有对应箱唛，需印刷到外箱 。 2.出往UK的产品+包装务必打上UKCA logo ，否则客人会退货且当地会有罚款。Amazon GPE（包含UK/FR/ES/DE/IT）的订单也需满足此要求。 3.订单必须经过ZURU QC验货或者工厂自检通过后方可出货，不涉及第三方验货。 4.法国订单要求包装不使用矿物油，请按要求提供以下其中一份文件再出货 ，产品出到法国被相关部门抽检出现包装不符合此要求的，供应商需要为此承担责任， 故此请严格把关。Amazon~ GPE（包含UK/FR/ES/DE/IT）的订单也需满足此要求。 -油墨物质""""""""由1 7个芳香环组成的MOAH""""""""的包装检测报告，要求限值≤1.0%； -包装材料清单，包括包装油墨或物质的信息； -油墨制造商的证书； 5.每一批次出货只能有一个生产日期，不可多个生产日期混在同一批次出货；且零售包装上必须统一加上日期码；外箱对于日期码没有硬性规定； 6.涉及到相关款式会有闪粉的或者微塑料的，请统一默认出无闪粉或者不含微塑料版本； 7.邮包盒及外箱封箱必须是工字型封箱方式； 8.5 Surprise or Mini Brands涉及包装是2个及2个以上的球入PVC桶包装时，单个球上若有UPC#或者EAN#，请用空白贴纸覆盖住，贴纸尺寸自行测量能覆盖原条码即 可； 9. 无论是工厂自检还是ZURU验货，验货报告中必须有产品6面图(正面/背面/左面/右面/顶部/底部，不带包装); 10. 按空海运鉴定报告的要求，只要带锂电池出货，都需要加贴UN贴纸； 11. 所有出往GAS市场(德国/奥地利/瑞士)的电子产品身上需要加字唛，为ZURU FRANCE 地址，需跟包装上的地址一致 (如无电子产品，产品布标有此地址，或产品 太小无法增加可忽略此信息。如产品无法加字唛，需让对应跟单提供产品贴纸资料);（Amazon GPE的订单也需满足此要求） 12. 所有出往GAS德国 (瑞士，奥地利)。水弹枪系列必须使用EN71版本（电子和非电子水弹枪系列都需要符合); 护目镜需打日期码, 格式跟ZURU标准格式一样; 枪 身上增加ZURU FRANCE公司名和地址。使用贴纸和辐射上去都可以。如果有位置，最好增加ZURU Represented by: (此最好翻译德语，如果位置不允许，那么就只增 加ZURU法国和地址)。使用最新的EN71版包装和说明书）。Amazon GPE（包含UK/FR/ES/DE/IT）的订单也需满足此要求。 | X54: Aria Zhou | Y54: 2.6134 | Z54: =I54*Y54 -> 1254.432 | AD54: 9543D-S002-MB | AO54: =I54 -> 480 | AT54: =I54 -> 480 | BV54: 增加移印布标内容 | BY54: =I54 -> 480 | CC54: =SUM(BW54:BZ54) -> 480 | CD54: =I54-CC54 -> 0

Sheet 询单
A2: 9543
A3: 月份 | B3: 实单 | C3: 询单 | D3: 总数
A4: 3 | B4: 10200 | C4: 56000 | D4: =SUM(B4:C4) -> 66200
A5: 4 | B5: 14536 | C5: 102904 | D5: =SUM(B5:C5) -> 117440
A6: 5 | B6: 23364 | C6: 11352 | D6: =SUM(B6:C6) -> 34716
A7: 6 | B7: 12072 | C7: 21274 | D7: =SUM(B7:C7) -> 33346
A8: 7 | C8: 42098 | D8: =SUM(B8:C8) -> 42098
A9: 8 | C9: 20000 | D9: =SUM(B9:C9) -> 20000
A10: 9 | C10: 20000 | D10: =SUM(B10:C10) -> 20000
A11: 合计： | D11: =SUM(D4:D10) -> 333800
