Workbook

Sheet 樣板單
A1: ZURU Rainbocorn 樣板訂單 | V1: 1代珠片公仔#9201 | AE1: 2代珠片公仔#9202 | AN1: #9204 | AW1: #9214 | BE1: #9209 | BV1: #9202 | CI1: #9204 | CO1: #9214（第二代） | CU1: #9209 | CX1: #9215 | DE1: #9212 | DK1: #9213 | DN1: #9207 | DO1: #9208
V2: 收縮膜 | Y2: 說明書 | AE2: 收縮膜 | AH2: 說明書 | AN2: A版本 | AP2: B版本 | BJ2: 3 | BL2: 4 | BN2: 5 | BP2: 5 | BR2: 4 | BT2: 3
A3: 香港接单日期 | B3: ZURU 跟单 | C3: ZURU PO NO# | D3: 第三方客户 PO NO# | E3: 第三方客户名称 | F3: ITEM# | G3: 中文名 | H3: PO数量 (pcs) | I3: 内箱装箱数量(pcs) | J3: 外箱装箱数量(pcs) | K3: 总箱数 | L3: 单价USD | M3: 金额USD | N3: ZURU验货 日期 | O3: 驗貨結果 | P3: 第三方客户公证行验货 | Q3: ZURU订单走货日期 | R3: ZURU确认走货日期 | S3: 箱唛资料(收到日期) | T3: 箱唛资料(确认日期) | U3: 客供贴纸AI(收到日期) | V3: MA 1語收縮膜 | W3: MA 3語收縮膜 | X3: 客版收縮膜 | Y3: MA 1語说明书 A版本 | Z3: MA 1語说明书 B版本 | AA3: MA 3語說明書 A版本 | AB3: MA 3語說明書 B版本 | AC3: 客版說明書 | AD3: 布標 | AE3: MA 1語收縮膜 | AF3: MA 3語收縮膜 | AG3: 客版收縮膜 | AH3: MA 1語说明书 A版本 | AI3: MA 1語说明书 B版本 | AJ3: MA 3語說明書 A版本 | AK3: MA 3語說明書 B版本 | AL3: 客版說明書 | AM3: 布標 | AN3: MA 1語收縮膜 | AO3: MA 1語說明書 | AP3: MA 1語收縮膜 | AQ3: MA 1語說明書 | AR3: MA 2語收縮膜（加拿大版本） | AS3: MA 2語說明書（加拿大版本） | AT3: 落加拿大 棉花泥 | AU3: 9201SQ1 | AV3: 9204UQ1 | AW3: MA 1語收縮膜 A | AX3: MA 1語收縮膜 B | AY3: MA 1語說明書 A | AZ3: MA 1語收縮膜 B | BA3: MA 1語說明書 B | BB3: MA领养卡 | BC3: 9214SQ1 MA PDQ盒 | BD3: 9214UQ1 客办PDQ盒 | BE3: MA 1語收縮膜 | BF3: MA 1語說明書 | BG3: MA 3語收縮膜 | BH3: MA 3語說明書 | BI3: 發票號 | BJ3: 玫紅猴子 Monkey（A） | BK3: 黃色猴子 Monkey（B） | BL3: 粉紅貓 Kitty （A） | BM3: 玫紅貓 Kitty （B） | BN3: 白色兔子 Rabbit （A） | BO3: 玫紅兔子 Rabbit （B） | BP3: 白色獨角獸 Unicorn （A） | BQ3: 玫紅獨角獸 Unicorn （B） | BR3: 紫色小狗 Puppy （A） | BS3: 藍色小狗 Puppy （B） | BT3: 粉色倉鼠 Hamster （A） | BU3: 橙色倉鼠 Hamster （B） | BV3: 羊駝 Llama（白色） | BW3: 羊駝 Llama（紫色） | BX3: 火烈鳥 Flamingo （玫紅色） | BY3: 火烈鳥 Flamingo （彩虹色） | BZ3: 火烈鳥 Flamingo （金色） | CA3: 熊貓 Panda （黑白色） | CB3: 熊貓 Panda （粉紅色） | CC3: 貓頭鷹 OWL （紫色） | CD3: 貓頭鷹 OWL （白色） | CE3: 獨角獸 Unicorn （白色） | CF3: 獨角獸 Unicorn （紫色） | CG3: 獅子 Lion （粉紅色） | CH3: 獅子 Lion （黃色） | CI3: 白色獨角獸 Unicorn | CJ3: 枚红色火烈鸟 Flamingo | CK3: 白色羊驼 Llama | CL3: 粉红色猫 Kitty | CM3: 紫色兔子 Bunny | CN3: 蓝色小狗 Puppy | CO3: 白色猫头鹰 White Owl | CP3: 粉色狮子 Pink Lion | CQ3: 黄色猴子 Yellow Monkey | CR3: 紫色独角兽 Purple Unicorn | CS3: 白色熊猫 White Panda | CT3: 彩色火烈鸟 Colour Flamingo | CU3: 獨角獸 Unicorn | CV3: 白色羊驼 Llama | CW3: 枚红色火烈鸟 Flamingo | CX3: 孔雀 Peacock | CY3: 火烈鸟 Toucan | CZ3: 树懒 Sloth | DA3: 大象 Elephant | DB3: 老虎 Tiger | DC3: 梅花鹿 Giraffe | DD3: 斑马 Zebra | DE3: 兔子 Bunny 含海绵 | DF3: 小狗 Puppy | DG3: 羊驼 Llama | DH3: 小猫 Kitty 含海绵 | DI3: 独角兽 Unicorn | DJ3: 猴子 Monkey | DK3: 小猫 Kitten | DL3: 独角兽 Unicorn | DM3: 大嘴鸟 Toucan | DN3: 2PK超小蛋殼公仔 | DO3: 4PK超小蛋殼公仔
A4: 43243 | B4: Binnie | C4: ZMPO18068 | F4: 9201-S001 | G4: 珠片公仔 | H4: 360 | V4: =H4 -> 360 | Y4: =H4 -> 360 | AD4: MA布標 | BI4: 19573 | BJ4: =H4/12 -> 30 | BK4: =H4/12 -> 30 | BL4: =H4/12 -> 30 | BM4: =H4/12 -> 30 | BN4: =H4/12 -> 30 | BO4: =H4/12 -> 30 | BP4: =H4/12 -> 30 | BQ4: =H4/12 -> 30 | BR4: =H4/12 -> 30 | BS4: =H4/12 -> 30 | BT4: =H4/12 -> 30 | BU4: =H4/12 -> 30
A5: 43265 | B5: Amanda | C5: ZMPO18078 | F5: 9201-S001 | G5: 珠片公仔 | H5: 480 | V5: =H5 -> 480 | Y5: =H5 -> 480 | AD5: MA布標 | BI5: 19654 | BJ5: =H5/12 -> 40 | BK5: =H5/12 -> 40 | BL5: =H5/12 -> 40 | BM5: =H5/12 -> 40 | BN5: =H5/12 -> 40 | BO5: =H5/12 -> 40 | BP5: =H5/12 -> 40 | BQ5: =H5/12 -> 40 | BR5: =H5/12 -> 40 | BS5: =H5/12 -> 40 | BT5: =H5/12 -> 40 | BU5: =H5/12 -> 40
A6: 43265 | B6: Angela | C6: 4500010393 | E6: 簽板 | F6: 9201-S001 | G6: 珠片公仔 | H6: 36 | V6: =H6 -> 36 | Y6: =H6 -> 36 | AD6: MA布標 | BJ6: =H6/12 -> 3 | BK6: =H6/12 -> 3 | BL6: =H6/12 -> 3 | BM6: =H6/12 -> 3 | BN6: =H6/12 -> 3 | BO6: =H6/12 -> 3 | BP6: =H6/12 -> 3 | BQ6: =H6/12 -> 3 | BR6: =H6/12 -> 3 | BS6: =H6/12 -> 3 | BT6: =H6/12 -> 3 | BU6: =H6/12 -> 3
A7: 43265 | B7: Lingly | C7: 4500010570 | E7: GP測試版 | F7: 9201-S001 | G7: 珠片公仔 | H7: 12 | V7: =H7 -> 12 | Y7: =H7 -> 12 | AD7: MA布標 | BJ7: =H7/12 -> 1 | BK7: =H7/12 -> 1 | BL7: =H7/12 -> 1 | BM7: =H7/12 -> 1 | BN7: =H7/12 -> 1 | BO7: =H7/12 -> 1 | BP7: =H7/12 -> 1 | BQ7: =H7/12 -> 1 | BR7: =H7/12 -> 1 | BS7: =H7/12 -> 1 | BT7: =H7/12 -> 1 | BU7: =H7/12 -> 1
A8: 43265 | B8: Holly | C8: 4500009837 | E8: 寄客版 | F8: 9201-S001 | G8: 珠片公仔 | H8: 12 | V8: =H8 -> 12 | Y8: =H8 -> 12 | AD8: MA布標 | BJ8: =H8/12 -> 1 | BK8: =H8/12 -> 1 | BL8: =H8/12 -> 1 | BM8: =H8/12 -> 1 | BN8: =H8/12 -> 1 | BO8: =H8/12 -> 1 | BP8: =H8/12 -> 1 | BQ8: =H8/12 -> 1 | BR8: =H8/12 -> 1 | BS8: =H8/12 -> 1 | BT8: =H8/12 -> 1 | BU8: =H8/12 -> 1
A9: 43270 | B9: Sara | C9: 郵件 | E9: Candide客户样品 | F9: 9201-S001 | G9: 珠片公仔 | H9: 6 | V9: =H9 -> 6 | Y9: =H9 -> 6 | AD9: MA布標 | BJ9: 1 | BL9: 1 | BN9: 1 | BP9: 1 | BR9: 1 | BT9: 1
A10: 43270 | B10: Sara | C10: 4500010598 | E10: WABRO | F10: 9201-S001 | G10: 珠片公仔 | H10: 24 | V10: =H10 -> 24 | Y10: =H10 -> 24 | AD10: MA布標 | BJ10: =H10/12 -> 2 | BK10: =H10/12 -> 2 | BL10: =H10/12 -> 2 | BM10: =H10/12 -> 2 | BN10: =H10/12 -> 2 | BO10: =H10/12 -> 2 | BP10: =H10/12 -> 2 | BQ10: =H10/12 -> 2 | BR10: =H10/12 -> 2 | BS10: =H10/12 -> 2 | BT10: =H10/12 -> 2 | BU10: =H10/12 -> 2
A11: 43277 | B11: Tiffany | C11: 4500010957 | D11: 大貨簽板 | E11: EURO TOYS EUROPE BV | F11: 9201-S001 | G11: 珠片公仔 | H11: 36 | X11: 36 | AC11: 36 | AD11: MA布標 | BJ11: =H11/12 -> 3 | BK11: =H11/12 -> 3 | BL11: =H11/12 -> 3 | BM11: =H11/12 -> 3 | BN11: =H11/12 -> 3 | BO11: =H11/12 -> 3 | BP11: =H11/12 -> 3 | BQ11: =H11/12 -> 3 | BR11: =H11/12 -> 3 | BS11: =H11/12 -> 3 | BT11: =H11/12 -> 3 | BU11: =H11/12 -> 3
A12: 43277 | B12: Lucky | C12: 450012096 | D12: 產前測試 | E12: CENCOSUD CHILE | F12: 9201-S001 | G12: 珠片公仔 | H12: 12 | V12: 12 | Y12: 12 | AD12: MA布標 | BJ12: =H12/12 -> 1 | BK12: =H12/12 -> 1 | BL12: =H12/12 -> 1 | BM12: =H12/12 -> 1 | BN12: =H12/12 -> 1 | BO12: =H12/12 -> 1 | BP12: =H12/12 -> 1 | BQ12: =H12/12 -> 1 | BR12: =H12/12 -> 1 | BS12: =H12/12 -> 1 | BT12: =H12/12 -> 1 | BU12: =H12/12 -> 1
A13: 43265 | B13: Lingly | C13: 4500010570 | E13: 年齡評估樣品 | F13: 9201-S001 | G13: 珠片公仔 | H13: 2 | V13: 12 | Y13: 12 | AD13: MA布標 | BN13: 1 | BO13: 1
A14: 43284 | C14: ZMPO18086 | F14: 9201-S001 | G14: 珠片公仔 | H14: 480 | V14: 480 | Y14: 480 | AD14: MA布標 | BI14: 19655 | BJ14: =H14/12 -> 40 | BK14: =H14/12 -> 40 | BL14: =H14/12 -> 40 | BM14: =H14/12 -> 40 | BN14: =H14/12 -> 40 | BO14: =H14/12 -> 40 | BP14: =H14/12 -> 40 | BQ14: =H14/12 -> 40 | BR14: =H14/12 -> 40 | BS14: =H14/12 -> 40 | BT14: =H14/12 -> 40 | BU14: =H14/12 -> 40
A15: 43286 | C15: 4500010467 | F15: 9201-S001 | G15: 珠片公仔 | H15: 10 | V15: 10 | Y15: 10 | AD15: MA布標 | BL15: 1 | BM15: 1 | BN15: 1 | BO15: 1 | BP15: 1 | BQ15: 1 | BR15: 1 | BS15: 1 | BT15: 1 | BU15: 1
A16: 43287 | C16: 4500010333 | F16: 9201-S001 | G16: 珠片公仔 | H16: 10 | V16: 10 | Y16: 10 | AD16: MA布標 | BL16: 1 | BM16: 1 | BN16: 1 | BO16: 1 | BP16: 1 | BQ16: 1 | BR16: 1 | BS16: 1 | BT16: 1 | BU16: 1
A17: 43302 | C17: 4500012533 | F17: 9201-S001 | G17: 珠片公仔 | H17: 12 | V17: 12 | Y17: 12 | AD17: MA布標 | BJ17: 1 | BK17: 1 | BL17: 1 | BM17: 1 | BN17: 1 | BO17: 1 | BP17: 1 | BQ17: 1 | BR17: 1 | BS17: 1 | BT17: 1 | BU17: 1
A18: 43302 | C18: 4500010568 | F18: 9201-S001 | G18: 珠片公仔 | H18: 4 | V18: 4 | AC18: 4 | AD18: 丹麥布標 | BJ18: 1 | BL18: 1 | BN18: 1 | BP18: 1
A19: 43306 | C19: 4500010570 | E19: GP FRANCE | F19: 9201-S001 | G19: 珠片公仔 | H19: 28 | X19: 28 | Y19: 28 | AD19: 法國布標 | BJ19: 3 | BK19: 2 | BL19: 3 | BM19: 2 | BN19: 3 | BO19: 2 | BP19: 3 | BQ19: 2 | BR19: 2 | BS19: 2 | BT19: 2 | BU19: 2
A20: 43306 | C20: 4500010574 | E20: GP ITALY | F20: 9201-S001 | G20: 珠片公仔 | H20: 25 | X20: 25 | Y20: 25 | AD20: 意大利布標 | BJ20: 2 | BK20: 2 | BL20: 2 | BM20: 2 | BN20: 2 | BO20: 2 | BP20: 3 | BQ20: 2 | BR20: 2 | BS20: 2 | BT20: 2 | BU20: 2
A21: 43313 | C21: 4500009768 | E21: TOY TRIANGLE CO.W.L.L | F21: 9201-S001 | G21: 珠片公仔 | H21: 2 | V21: 2 | Y21: 2 | AD21: MA布標 | BN21: 1 | BP21: 1
A22: 43313 | C22: 4500012277 | E22: Express Gifts Ltd | F22: 9201-S006 | G22: 珠片公仔 | H22: 10 | V22: 10 | Y22: 10 | AD22: MA布標 | BL22: 1 | BM22: 1 | BN22: 1 | BO22: 1 | BP22: 1 | BQ22: 1 | BR22: 1 | BS22: 1 | BT22: 1 | BU22: 1
A23: 43316 | C23: 4500009878 | E23: P.M.I TRADING & ENTERPRISE LTS34 | F23: 9201-S001 | G23: 珠片公仔 | H23: 2 | V23: 2 | Y23: 2 | AD23: MA布標
A24: 43318 | C24: 4500012769 | E24: TOYS kingdom | F24: 9201-S001 | G24: 珠片公仔 | H24: 2 | AD24: MA布標 | BT24: 2
A25: 43321 | C25: 4500012192 | D25: 簽板 | E25: CANDIDE IND E COM LTDA | F25: 9201-S001 | G25: 珠片公仔 | H25: 25 | X25: 25 | AC25: 25 | AD25: 巴西布標 | BJ25: 2 | BK25: 2 | BL25: 2 | BM25: 2 | BN25: 2 | BO25: 2 | BP25: 3 | BQ25: 2 | BR25: 2 | BS25: 2 | BT25: 2 | BU25: 2
A26: 43323 | C26: 4500012835 | D26: 產前測試 | E26: WAL-MART.COM | F26: 9201-S001 | G26: 珠片公仔 | H26: 18 | V26: 18 | Y26: 18 | AD26: MA布標 | BJ26: 3 | BL26: 3 | BN26: 3 | BP26: 3 | BR26: 3 | BT26: 3
A27: 43332 | C27: 4500010580 | D27: 大貨版、簽板 | E27: GP SPAIN | F27: 9201-S001 | G27: 珠片公仔 | H27: 12 | X27: 12 | Y27: 12 | AD27: 西班牙布標 | BJ27: 2 | BK27: 2 | BL27: 2 | BM27: 2 | BN27: 2 | BO27: 2 | BP27: 3 | BQ27: 2 | BR27: 2 | BS27: 2 | BT27: 2 | BU27: 2
A28: 43332 | C28: 4500011417 | D28: 大貨版、簽板 | E28: GP TURKEY | F28: 9201-S001 | G28: 珠片公仔 | H28: 12 | X28: 12 | Y28: 12 | AD28: 土耳其布標 | BJ28: 2 | BK28: 2 | BL28: 2 | BM28: 2 | BN28: 2 | BO28: 2 | BP28: 3 | BQ28: 2 | BR28: 2 | BS28: 2 | BT28: 2 | BU28: 2
A29: 43335 | C29: 4500012306 | D29: MA 3語簽板 | E29: 360 SALES SOLUTIONS INC | F29: 9201-S001 | G29: 珠片公仔 | H29: 24 | W29: 24 | AA29: 24 | AD29: MA布標 | BJ29: 2 | BK29: 2 | BL29: 2 | BM29: 2 | BN29: 2 | BO29: 2 | BP29: 2 | BQ29: 2 | BR29: 2 | BS29: 2 | BT29: 2 | BU29: 2
A30: 43336 | C30: 4500009673 | D30: 大貨樣板 | E30: B&M RETAIL LIMITED | F30: 9201-S003 | G30: 珠片公仔 | H30: 10 | V30: 10 | Y30: 10 | AD30: MA布標 | BL30: 1 | BM30: 1 | BN30: 1 | BO30: 1 | BP30: 1 | BQ30: 1 | BR30: 1 | BS30: 1 | BT30: 1 | BU30: 1
A31: 43336 | C31: 郵件 | D31: Intek 客户样品 | E31: Lucky | F31: 9201-S001 | G31: 珠片公仔 | H31: 24 | V31: 24 | Y31: 24 | AD31: MA布標 | BJ31: 2 | BK31: 2 | BL31: 2 | BM31: 2 | BN31: 2 | BO31: 2 | BP31: 2 | BQ31: 2 | BR31: 2 | BS31: 2 | BT31: 2 | BU31: 2
A32: 43342 | C32: ZMPO18108 | F32: 9201-S001 | G32: 珠片公仔 | H32: 360 | V32: 24 | Y32: 24 | BI32: 19952 | BJ32: =H32/24*3/2 -> 22.5 | BK32: =H32/24*3/2 -> 22.5 | BL32: =H32/24*4/2 -> 30 | BM32: =H32/24*4/2 -> 30 | BN32: =H32/24*5/2 -> 37.5 | BO32: =H32/24*5/2 -> 37.5 | BP32: =H32/24*5/2 -> 37.5 | BQ32: =H32/24*5/2 -> 37.5 | BR32: =H32/24*4/2 -> 30 | BS32: =H32/24*4/2 -> 30 | BT32: =H32/24*3/2 -> 22.5 | BU32: =H32/24*3/2 -> 22.5
A33: 43364 | C33: 4500011712 | D33: 大貨樣板 | E33: TARGET US | F33: 9201-S001 | G33: 珠片公仔 | H33: 9 | V33: 9 | Y33: 9 | AD33: MA布標 | BJ33: 1 | BK33: 1 | BL33: 1 | BM33: 1 | BQ33: 1 | BR33: 1 | BS33: 1 | BT33: 1 | BU33: 1
A34: 43364 | C34: 4500013372 | D34: 大貨樣板 | E34: DISTRIBUIDORA JUGUETRON S.A DE C.V | F34: 9201-S001 | G34: 珠片公仔 | H34: 2 | W34: 2 | AA34: 2 | AD34: MA布標 | BN34: 1 | BP34: 1
A35: 43369 | C35: 4500013085 | D35: 抽版 | F35: 9201-S001 | G35: 粉紅色獨角獸 | H35: 8 | V35: 8 | Y35: 8 | AD35: MA布標 | BQ35: 8
A36: 43382 | C36: 4500013648 | D36: 簽板 | F36: 9201-S001 | G36: 珠片公仔 | H36: 24 | V36: 24 | Y36: 24 | AD36: MA布標 | BJ36: 2 | BK36: 2 | BL36: 2 | BM36: 2 | BN36: 2 | BO36: 2 | BP36: 2 | BQ36: 2 | BR36: 2 | BS36: 2 | BT36: 2 | BU36: 2
A37: 43384 | C37: 4500013155 | D37: 大貨版 | F37: 9201-S001 | G37: 珠片公仔 | H37: 12 | V37: 12 | Y37: 12 | AD37: MA布標 | BJ37: 1 | BK37: 1 | BL37: 1 | BM37: 1 | BN37: 1 | BO37: 1 | BP37: 1 | BQ37: 1 | BR37: 1 | BS37: 1 | BT37: 1 | BU37: 1
A38: 43392 | C38: 4500013641 | D38: 大貨版 | F38: 9201-S001 | G38: 珠片公仔 | H38: 12 | X38: 12 | AC38: 12 | AD38: GP法國 | BJ38: 1 | BK38: 1 | BL38: 1 | BM38: 1 | BN38: 1 | BO38: 1 | BP38: 1 | BQ38: 1 | BR38: 1 | BS38: 1 | BT38: 1 | BU38: 1
A39: 43392 | C39: ZMPO18123 | D39: 樣品訂單 | F39: 9201-S001 | G39: 珠片公仔 | H39: 204 | V39: 204 | Y39: 204 | AD39: MA布標 | BJ39: 17 | BK39: 17 | BL39: 17 | BM39: 17 | BN39: 17 | BO39: 17 | BP39: 17 | BQ39: 17 | BR39: 17 | BS39: 17 | BT39: 17 | BU39: 17
A40: 43392 | C40: ZMPO18131 | D40: 樣品訂單 | F40: 9201-S001 | G40: 珠片公仔 | H40: 480 | V40: 480 | Y40: 480 | AD40: MA布標 | BJ40: 40 | BK40: 40 | BL40: 40 | BM40: 40 | BN40: 40 | BO40: 40 | BP40: 40 | BQ40: 40 | BR40: 40 | BS40: 40 | BT40: 40 | BU40: 40
A41: 43395 | C41: 4500013346 | D41: 簽板 | F41: 9201-S001 | G41: 珠片公仔 | H41: 24 | W41: 24 | Z41: 24 | AD41: MA布標 | BJ41: 2 | BK41: 2 | BL41: 2 | BM41: 2 | BN41: 2 | BO41: 2 | BP41: 2 | BQ41: 2 | BR41: 2 | BS41: 2 | BT41: 2 | BU41: 2
A42: 43417 | C42: 4500014341 | D42: 大貨樣板 | F42: 9201-S001 | G42: 珠片公仔 | H42: 2 | V42: 2 | Z42: 2 | AD42: MA布標 | BL42: 2
A43: 43419 | B43: Emily | D43: 測試樣品 | E43: C/Sam's club | F43: 9201-S001 | G43: 珠片公仔 | H43: 48 | V43: 48 | Z43: 48 | AD43: MA布標 | BJ43: 4 | BK43: 4 | BL43: 4 | BM43: 4 | BN43: 4 | BO43: 4 | BP43: 4 | BQ43: 4 | BR43: 4 | BS43: 4 | BT43: 4 | BU43: 4
A44: 43419 | B44: Emily | D44: 簽板 | E44: C/Sam's club | F44: 9201-S001 | G44: 珠片公仔 | H44: 24 | V44: 24 | Z44: 24 | AD44: MA布標 | BJ44: 2 | BK44: 2 | BL44: 2 | BM44: 2 | BN44: 2 | BO44: 2 | BP44: 2 | BQ44: 2 | BR44: 2 | BS44: 2 | BT44: 2 | BU44: 2
A45: 43427 | B45: Emily | C45: MO 20181120 | D45: 測試樣品 | E45: WMCA | F45: 9201-S001 | G45: 珠片公仔 | H45: 48 | W45: 48 | AB45: 48 | AD45: MA布標 | BJ45: 4 | BK45: 4 | BL45: 4 | BM45: 4 | BN45: 4 | BO45: 4 | BP45: 4 | BQ45: 4 | BR45: 4 | BS45: 4 | BT45: 4 | BU45: 4
A46: 43444 | B46: Ever | C46: 4500014867 | D46: 大貨版 | E46: GP法國 | F46: 9201-S001 | G46: 珠片公仔 | H46: 12 | V46: 12 | AC46: 12 | AD46: GP法國 | BJ46: 1 | BK46: 1 | BL46: 1 | BM46: 1 | BN46: 1 | BO46: 1 | BP46: 1 | BQ46: 1 | BR46: 1 | BS46: 1 | BT46: 1 | BU46: 1
A47: 43444 | B47: Ever | C47: 4500015110 | D47: 大貨版 | E47: GP西班牙 | F47: 9201-S001 | G47: 珠片公仔 | H47: 12 | V47: 12 | AC47: 12 | AD47: GP西班牙 | BJ47: 1 | BK47: 1 | BL47: 1 | BM47: 1 | BN47: 1 | BO47: 1 | BP47: 1 | BQ47: 1 | BR47: 1 | BS47: 1 | BT47: 1 | BU47: 1
A48: 43446 | B48: Aimee | C48: ZY#5700005 | D48: 筑愉 | E48: 筑愉 | F48: 9201EC-S002 | G48: 空展示櫃 | H48: 40 | BI48: 25917
A49: 43448 | B49: Emily | C49: 4500015267 | E49: SAM’S CLUB US | F49: 9201PL-S002 | G49: 珠片公仔 | H49: 48 | V49: 48 | Z49: 48 | AD49: MA布標 | BJ49: 4 | BK49: 4 | BL49: 4 | BM49: 4 | BN49: 4 | BO49: 4 | BP49: 4 | BQ49: 4 | BR49: 4 | BS49: 4 | BT49: 4 | BU49: 4
A50: 43454 | B50: Ada | C50: ZMPO18162 | D50: 樣品訂單 | E50: 庫有 | F50: 9201-S001 | G50: 珠片公仔 | H50: 480 | V50: 480 | Z50: 480 | AD50: MA布標 | BI50: 25944 | BJ50: 40 | BK50: 40 | BL50: 40 | BM50: 40 | BN50: 40 | BO50: 40 | BP50: 40 | BQ50: 40 | BR50: 40 | BS50: 40 | BT50: 40 | BU50: 40
A51: 43479 | B51: Aimee | C51: 4800007665 | D51: 筑愉 | E51: 筑愉 | F51: 9201EC-S002 | G51: 空展示櫃 | H51: 20 | BI51: 26075
A52: 43488 | B52: Aimee | C52: 4500007847 | D52: 筑愉 | E52: 筑愉 | F52: 9201EC-S002 | G52: 空展示櫃 | H52: 30 | BI52: 26074
A53: 43510 | B53: Tiffany | C53: 郵件 | E53: 廣州ITS測試版 | F53: 9201-S001 | G53: 珠片公仔 | H53: 48 | V53: =H53 -> 48 | Z53: =H53 -> 48 | AD53: MA布標 | BJ53: 4 | BK53: 4 | BL53: 4 | BM53: 4 | BN53: 4 | BO53: 4 | BP53: 4 | BQ53: 4 | BR53: 4 | BS53: 4 | BT53: 4 | BU53: 4
A54: 43514 | B54: holly | C54: 4500016381 | E54: 大貨樣板 | F54: 9201-S001 | G54: 珠片公仔 | H54: 12 | V54: 12 | Z54: 12 | AD54: MA布標 | BJ54: 1 | BK54: 1 | BL54: 1 | BM54: 1 | BN54: 1 | BO54: 1 | BP54: 1 | BQ54: 1 | BR54: 1 | BS54: 1 | BT54: 1 | BU54: 1
A55: 43518 | B55: Elaine | C55: 4500016832 | D55: 測試版 | E55: RELIANCE LIFESTYLE HOLDINGS LIMITED | F55: 9201-S001 | G55: 珠片公仔 | H55: 15 | V55: 15 | Z55: 15 | AD55: MA布標 | BJ55: 1 | BK55: 1 | BL55: 1 | BM55: 1 | BN55: 1 | BO55: 1 | BP55: 1 | BQ55: 1 | BR55: 4 | BS55: 1 | BT55: 1 | BU55: 1
A56: 43522 | B56: Christal | C56: 4500017093 | D56: WM簽板 | E56: WAL-MART STORES INC.USA | F56: 9201PL-S003 | G56: 珠片公仔 | H56: 24 | V56: 24 | Z56: 24 | AD56: MA布標 | BJ56: 2 | BK56: 2 | BL56: 2 | BM56: 2 | BN56: 2 | BO56: 2 | BP56: 2 | BQ56: 2 | BR56: 2 | BS56: 2 | BT56: 2 | BU56: 2
A57: 43522 | B57: Ever | C57: 4500016464 | E57: GP Spain | F57: 9201-S001 | G57: 珠片公仔 | H57: 12 | X57: 12 | Z57: 12 | AD57: GP西班牙 | BJ57: 1 | BK57: 1 | BL57: 1 | BM57: 1 | BN57: 1 | BO57: 1 | BP57: 1 | BQ57: 1 | BR57: 1 | BS57: 1 | BT57: 1 | BU57: 1
A58: 43529 | B58: Tiffany | C58: 4500016256 | D58: 大貨樣品 | E58: EUROPRIS | F58: 9201-S001 | G58: 珠片公仔 | H58: 24 | V58: 24 | Z58: 24 | AD58: MA布標 | BJ58: 2 | BK58: 2 | BL58: 2 | BM58: 2 | BN58: 2 | BO58: 2 | BP58: 2 | BQ58: 2 | BR58: 2 | BS58: 2 | BT58: 2 | BU58: 2
A59: 43542 | B59: Tony | C59: 郵件 | D59: BV測試版 | F59: 9201-S001 | G59: 珠片公仔 | H59: 24 | V59: 24 | Z59: 24 | AD59: MA布標 | BJ59: 2 | BK59: 2 | BL59: 2 | BM59: 2 | BN59: 2 | BO59: 2 | BP59: 2 | BQ59: 2 | BR59: 2 | BS59: 2 | BT59: 2 | BU59: 2
A60: 43573 | B60: Ever | C60: 4500018212 | D60: GP | E60: GP測試版 | F60: 9202-S001 | G60: 2代珠片公仔 | H60: 13 | AE60: 13 | AH60: 13 | AM60: MA布標 | BV60: 1 | BW60: 1 | BX60: 1 | BY60: 1 | BZ60: 1 | CA60: 1 | CB60: 1 | CC60: 1 | CD60: 1 | CE60: 1 | CF60: 1 | CG60: 1 | CH60: 1
A61: 43574 | B61: Tony | C61: 4500017981 | D61: ASDA STORES LTD | E61: 測試版 | F61: 9202-WMUS-S001 | G61: 2代珠片公仔 | H61: 33 | AE61: 33 | AH61: 33 | AM61: MA布標 | BV61: 3 | BW61: 3 | BX61: 3 | BY61: 3 | BZ61: 3 | CA61: 3 | CB61: 3 | CE61: 3 | CF61: 3 | CG61: 3 | CH61: 3
A62: 43574 | B62: Maria | C62: 450018388 | D62: TARGET AUSTRALIA PTY LTD | E62: QA測試版 | F62: 9202-S001 | G62: 2代珠片公仔 | H62: 13 | AE62: 13 | AH62: 13 | AM62: MA布標 | BV62: 1 | BW62: 1 | BX62: 1 | BY62: 1 | BZ62: 1 | CA62: 1 | CB62: 1 | CC62: 1 | CD62: 1 | CE62: 1 | CF62: 1 | CG62: 1 | CH62: 1
A63: 43574 | B63: Bella | C63: 4500016572 | D63: Express Gifts Ltd | E63: 大貨版 | F63: 9202-S005 | G63: 2代珠片公仔 | H63: 11 | AE63: 11 | AH63: 11 | AM63: MA布標 | BV63: 1 | BW63: 1 | BX63: 1 | BY63: 1 | BZ63: 1 | CA63: 1 | CB63: 1 | CE63: 1 | CF63: 1 | CG63: 1 | CH63: 1
A64: 43580 | B64: Lucky | C64: 4500017858 | D64: GRUPO RUZ | E64: 測試樣品 | F64: 9201-S001 | G64: 1代珠片公仔 | H64: 2 | V64: 2 | Z64: 2 | AD64: MA布標 | BO64: 1 | BR64: 1
A65: 43580 | B65: Lucky | C65: 4500017858 | D65: GRUPO RUZ | E65: 測試樣品 | F65: 9201-S001 | G65: 小蛋殼毛絨公仔 | H65: 2 | V65: 2 | Z65: 2 | AD65: MA布標 | CL65: 1 | CN65: 1
A66: 43580 | B66: Tony | C66: 4500018097 | D66: ASDA STORES LTD | E66: 測試版 | F66: 9204UQ3-S001 | G66: 小蛋殼毛絨公仔 | H66: 18 | AN66: =H66 -> 18 | AO66: =H66 -> 18 | CI66: 3 | CJ66: 3 | CK66: 3 | CL66: 3 | CM66: 3 | CN66: 3
A67: 43580 | B67: Holly | C67: 4500017238 | D67: Target US | E67: 大貨版 | F67: 9202-S002 | G67: 2代珠片公仔 | H67: 11 | AE67: =H67 -> 11 | AH67: =H67 -> 11 | AM67: MA布標 | BV67: 1 | BW67: 1 | BX67: 1 | BY67: 1 | BZ67: 1 | CC67: 1 | CD67: 1 | CE67: 1 | CF67: 1 | CG67: 1 | CH67: 1
A68: 43580 | B68: Holly | C68: 4500017239 | D68: Target US | E68: 大貨版 | F68: 9204UQ1-S002 | G68: 小蛋殼毛絨公仔 | H68: 6 | AN68: =H68 -> 6 | AO68: =H68 -> 6 | AV68: 1 | CI68: 1 | CJ68: 1 | CK68: 1 | CL68: 1 | CM68: 1 | CN68: 1
A69: 43580 | B69: Hailey | C69: 4500017957 | D69: DOLLAR GENERAL CORPORATION | E69: 大貨簽板 | F69: 9204-S004 | G69: 小蛋殼毛絨公仔 PDQ裝 | H69: 36 | AN69: =H69 -> 36 | AO69: =H69 -> 36 | CI69: 6 | CJ69: =CI69 -> 6 | CK69: =CJ69 -> 6 | CL69: =CK69 -> 6 | CM69: =CL69 -> 6 | CN69: =CM69 -> 6
A70: 43589 | B70: Maria | C70: 4500018388 | D70: TARGET AUSTRALIA PTY LTD | E70: 大貨簽板 | F70: 9202-S001 | G70: 2代珠片公仔 | H70: 39 | AE70: 39 | AH70: 39 | AM70: MA布標 | BV70: 3 | BW70: 3 | BX70: 3 | BY70: 3 | BZ70: 3 | CA70: 3 | CB70: 3 | CC70: 3 | CD70: 3 | CE70: 3 | CF70: 3 | CG70: 3 | CH70: 3
A71: 43589 | B71: Victoria | C71: 4500017956 | D71: WM CA | E71: 測試樣品 | F71: 9202-S001 | G71: 2代珠片公仔 | H71: 52 | AE71: 52 | AH71: 52 | AM71: MA布標 | BV71: 4 | BW71: 4 | BX71: 4 | BY71: 4 | BZ71: 4 | CA71: 4 | CB71: 4 | CC71: 4 | CD71: 4 | CE71: 4 | CF71: 4 | CG71: 4 | CH71: 4
A72: 43593 | B72: Christal | C72: 4500018397 | D72: WM US | E72: 測試樣+大貨樣 | F72: 9204UQ1-S002 | G72: 小蛋殼毛絨公仔 PDQ裝 | H72: 54 | AN72: 54 | AO72: 54 | AV72: =H72/6 -> 9 | CI72: 9 | CJ72: 9 | CK72: 9 | CL72: 9 | CM72: 9 | CN72: 9
A73: 43593 | B73: bella | C73: 4500017078 | D73: B&M | E73: 大貨版 | F73: 9204SQ1-S001 | G73: 小蛋殼毛絨公仔 | H73: 6 | AN73: 6 | AO73: 6 | CI73: 1 | CJ73: 1 | CK73: 1 | CL73: 1 | CM73: 1 | CN73: 1
A74: 43595 | B74: Ann | C74: 4500019662 | D74: Toy triangle | E74: 樣板 | F74: 9202 | G74: 2代珠片公仔 | H74: 4 | AE74: 4 | AH74: 4 | AM74: MA布標 | CA74: 1 | CB74: 1 | CG74: 1 | CH74: 1
A75: 43659 | B75: harmony | C75: 邮件 | E75: 广告样品 | F75: 9202-S001 | G75: 2代珠片公仔 | H75: 13 | AF75: 13 | AK75: 13 | BV75: 1 | BW75: 1 | BX75: 1 | BY75: 1 | BZ75: 1 | CA75: 1 | CB75: 1 | CC75: 1 | CD75: 1 | CE75: 1 | CF75: 1 | CG75: 1 | CH75: 1
A76: 43659 | B76: harmony | C76: 邮件 | E76: 广告样品 | F76: 9204-S004 | G76: 小蛋殼毛絨公仔 | H76: 6 | AO76: 6 | AQ76: 6 | CI76: 1 | CJ76: 1 | CK76: 1 | CL76: 1 | CM76: 1 | CN76: 1
A77: 43670 | B77: estate | C77: 4500020704 | D77: WM US | E77: 产前测试版 | F77: 9209-S001 | G77: 超大蛋壳 | H77: 9 | BE77: 9 | BF77: 9 | CU77: 4 | CV77: 4 | CW77: 4
A78: 43667 | B78: Lori | C78: 4500022133 | D78: TOY TRIANGLE COMPANY(UAE) | E78: 大货样板 | F78: 9209-S001 | G78: 超大蛋壳 | H78: 4 | BE78: 4 | BF78: 4 | CU78: 1 | CV78: 2 | CW78: 1
A79: 43671 | B79: Vivian | C79: 邮件 | E79: KC测试样品需求 | F79: 9209-S001 | G79: 超大蛋壳 | H79: 3 | CU79: 1 | CV79: 1 | CW79: 1
A80: 43671 | B80: Monica | C80: 4500021345 | E80: 大货样板 | F80: 9209-S001 | G80: 超大蛋壳 | H80: 1 | BE80: 1 | BF80: 1 | CW80: 1
A81: 43675 | B81: Emily | C81: 邮件 | D81: Sam's | E81: 见客版 | F81: 9202-S002 | G81: 2代珠片公仔 | H81: 18 | AE81: 2 | AH81: 2 | BV81: 2 | BW81: 2 | BX81: 2 | BY81: 2 | BZ81: 2 | CE81: 2 | CF81: 2 | CG81: 2 | CH81: 2
A82: 43672 | B82: Andy | C82: 450019786 | D82: GP | E82: 大货样板 | F82: 9202-S001 | G82: 2代珠片公仔 | H82: 13 | AE82: 13 | AH82: 13 | BV82: 1 | BW82: 1 | BX82: 1 | BY82: 1 | BZ82: 1 | CA82: 1 | CB82: 1 | CC82: 1 | CD82: 1 | CE82: 1 | CF82: 1 | CG82: 1 | CH82: 1
A83: 43678 | B83: Monica | C83: 4500019768 | D83: Colony Brands | E83: 测试样板 | F83: 9209A-S001 | G83: 火烈鸟 | H83: 1 | BE83: 1 | BF83: 1 | CW83: 1
A84: 43678 | B84: Daisy | C84: 4500022323 | D84: TOYS R US JAPAN LTD | E84: 大货样板 | F84: 9209-S001 | G84: 火烈鸟 | H84: 1 | BE84: 1 | BF84: 1 | CW84: 1
A85: 43678 | B85: Estate | C85: 4500020704 | D85: WAL-MART.COM | E85: 签版 | F85: 9209-S001 | G85: 超大蛋壳 | H85: 9 | BE85: 9 | BF85: 9 | CU85: 3 | CV85: 3 | CW85: 3
A86: 43679 | B86: Elaine | C86: 4500022498 | D86: RELIANCE LIFESTYLE HOLDINGS LIMITED | E86: 测试办 | F86: 9209-S001 | G86: 超大蛋壳 | H86: 9 | BE86: 9 | BF86: 9 | CU86: 3 | CV86: 3 | CW86: 3
A87: 43680 | B87: Holly | C87: 邮件 | D87: GSS | E87: 产前办 | F87: 9204SQ1-S001 | G87: 小蛋壳毛絨公仔 | H87: 12 | AP87: 12 | AQ87: 12 | CI87: 2 | CJ87: 2 | CK87: 2 | CL87: 2 | CM87: 2 | CN87: 2
A88: 43682 | B88: estate | C88: 4500020707 | D88: WAL-MART.COM | E88: 产中抽板 | F88: 9209-S001 | G88: 超大蛋壳 | H88: 12 | BE88: 12 | BF88: 12 | CU88: 4 | CV88: 4 | CW88: 4
A89: 43683 | B89: Estate | C89: 4500021874 | D89: WAL-MART.COM | E89: 签办 | F89: 9202-WMUS-S001 | G89: 2代珠片公仔 | H89: 22 | AE89: 22 | AH89: 22 | BV89: 2 | BW89: 2 | BX89: 2 | BY89: 2 | BZ89: 2 | CA89: 2 | CB89: 2 | CE89: 2 | CF89: 2 | CG89: 2 | CH89: 2
A90: 43683 | B90: Kalyn | C90: 4500021576 | D90: G.T. WHOLESALE LIMITED | E90: 大货办 | F90: 9202-S009 | G90: 2代珠片公仔 | H90: 13 | BV90: 1 | BW90: 1 | BX90: 1 | BY90: 1 | BZ90: 1 | CA90: 1 | CB90: 1 | CC90: 1 | CD90: 1 | CE90: 1 | CF90: 1 | CG90: 1 | CH90: 1
A91: 43686 | B91: Abbey | C91: 4500022135 | D91: THE FARMERS'TRADING COMPANY LIMITE | E91: 大货办 | F91: 9209-S001 | G91: 超大蛋壳 | H91: 3 | BE91: 3 | BF91: 3 | CU91: 1 | CV91: 1 | CW91: 1
A92: 43686 | B92: Kate | C92: 4500017857 | D92: 筑愉（深圳）贸易有限公司 | E92: 签办 | F92: 9204SQ1-S001 | G92: 小蛋殼毛絨公仔 PDQ裝 | H92: 12 | AP92: 12 | CI92: 2 | CJ92: 2 | CK92: 2 | CL92: 2 | CM92: 2 | CN92: 2
A93: 43687 | B93: IDA LI | C93: 4500022562 | D93: GP SPAIN | E93: 大货办 | F93: 9201-S001 | G93: 珠片公仔 | H93: 12 | W93: 12 | AB93: 12 | BJ93: 1 | BK93: 1 | BL93: 1 | BM93: 1 | BN93: 1 | BO93: 1 | BP93: 1 | BQ93: 1 | BR93: 1 | BS93: 1 | BT93: 1 | BU93: 1
A94: 43689 | B94: Lois | C94: 4500019647 | D94: A.S. WATSON RETAIL (HK) LIMITED | E94: 大货办 | F94: 9204SQ1-S002 | G94: 小蛋殼毛絨公仔 PDQ裝 | H94: 6 | AR94: 6 | AS94: 6 | AT94: 6 | CI94: 1 | CJ94: 1 | CK94: 1 | CL94: 1 | CM94: 1 | CN94: 1
A95: 43689 | B95: Lori | C95: 4500022128 | D95: ORBICO SP.Z O O | E95: 大货办 | F95: 9204SQ1-S001 | G95: 小蛋殼毛絨公仔 PDQ裝 | H95: 12 | AP95: 12 | AQ95: 12 | CI95: 2 | CJ95: 2 | CK95: 2 | CL95: 2 | CM95: 2 | CN95: 2
A96: 43689 | B96: Lori | C96: 4500022128 | D96: ORBICO SP.Z O O | E96: 大货办 | F96: 9202-S001 | G96: 2代珠片公仔 | H96: 4 | AE96: 4 | AI96: 4 | CA96: 1 | CD96: 1 | CF96: 1 | CH96: 1
A97: 43689 | B97: Kate | C97: 4500017361 | D97: 筑愉(深圳）贸易有限公司 | E97: 签办 | F97: 9202-S007 (A款） | G97: 2代珠片公仔 | H97: 26 | AE97: 26 | AL97: 26 | BV97: 2 | BW97: 2 | BX97: 2 | BY97: 2 | BZ97: 2 | CA97: 2 | CB97: 2 | CC97: 2 | CD97: 2 | CE97: 2 | CF97: 2 | CG97: 2 | CH97: 2
A98: 43689 | B98: Sherry | C98: 4500018407 | D98: Smyths Toys HQ UC | E98: 大货办 | F98: 9209B-S001 | G98: 羊駝 | H98: 1 | BE98: 1 | BF98: 1 | CV98: 1
A99: 43690 | B99: Angel | C99: 4500017962 | D99: WAL-MART CANADA CORP | E99: 签办 | F99: 9202A | G99: 2代珠片公仔 | H99: 1 | BV99: 1
A100: 43690 | B100: Lori | C100: 4500022128 | D100: ORBICO SP.Z O O | E100: 大货办 | F100: 9204SQ1-S001 | G100: 小蛋殼毛絨公仔 PDQ裝 | H100: 6 | AP100: 6 | AQ100: 6 | CI100: 1 | CJ100: 1 | CK100: 1 | CL100: 1 | CM100: 1 | CN100: 1
...

Sheet 9561
A2: =#REF! -> #REF! | H2: （黃色表示更改或增加） | K2: （蓝色表示已完货） | O2: （綠色表示調整貨期） | AF2: 收缩膜 | AR2: 展示架
A3: 接单日期 | B3: 第三方客户名称 | C3: 国家 | D3: PO号 | E3: 客户PO号 | F3: SKU | G3: ITEM# | H3: 中文名 | I3: PO数量 (pcs) | J3: 内箱装箱数量(pcs) | K3: 外箱装箱数量(pcs) | L3: 总箱数 | M3: 客PO期 | N3: 验货期 | O3: 第三方验货期 | P3: 驗貨結果 | Q3: 船期SO | R3: 箱唛资料 | S3: 外箱贴纸 | T3: 客贴纸资料 | U3: 布料 | V3: 说明书（书纸） | W3: 客供物料 | X3: 日期码 | Y3: 备注 | Z3: ZURU 跟单 | AA3: 单价USD | AB3: 金额USD | AC3: 发票号 | AD3: 系统货号 | AE3: 是否入系统 | AF3: MA 1L收缩膜 | AG3: MA 5L收缩膜 | AH3: 客版收縮膜 | AI3: MA 1L收缩膜B版 | AJ3: MA 5L收缩膜 | AK3: MA 5L收缩膜B版 | AL3: MA 6L说明书 | AM3: MA6L说明书B版 | AN3: 客版说明书 | AO3: 客版收藏指南 | AP3: 纸卡A版 | AQ3: 纸卡B版 | AR3: EC展示架1L | AS3: EC展示架3L | AT3: 布標 | AU3: 合计数量 | AV3: 累计数量
A4: 45649 | D4: ZPO2411015 | G4: 9561-S001 | H4: 魔法小鸟 | I4: 650 | M4: 45673 | N4: 45670 | AA4: 5.4 | AB4: =AA4*I4 -> 3510 | AD4: # | AE4: # | AF4: =I4 -> 650 | AL4: =I4 -> 650 | AP4: =I4 -> 650 | AU4: 650 | AV4: =AU4 -> 650
A5: 45649 | D5: ZPO2411015 | G5: 9561EC-S001 | H5: 魔法小鸟 | M5: 45673 | N5: 45670 | AD5: # | AE5: # | AP5: =I5 -> 0 | AU5: =I5 -> 0 | AV5: =AV4+AU5 -> 650
A6: 45683 | B6: THE WAREHOUSE LIMITED | C6: 新西兰 | D6: 4500156569 | F6: 4500156569-20 | G6: 9561-S001 | H6: 魔法小鸟 | I6: 48 | J6: 0 | K6: 4 | L6: =I6/K6 -> 12 | M6: 45716 | N6: 45712 | P6: 走PP | X6: 日期码格式：ZURU INC(BVI) 标准格式 日期：按实际生产日期 | Y6: 日期码格式：ZURU INC(BVI) 标准格式 日期：按实际生产日期 Packaging Info: MA UPC 英语包装（优先1L英语版本，或者3L/5L含英语都可） 此客人不接受易掉落或者剥落或者可直接触碰的闪粉，可降解也不行，但可以接受符合欧洲微塑料标准的珠光粉或者闪片。 9561: 包装正面和说明书都需要加电池警告语贴纸（法规要求） 9561：外箱四个面要加一张大黄贴："ZURU Product for NZ test " Remark: 9561: 3PCS LR41 BATTERIES(INCLUDED) | Z6: Abby Liang | AA6: 5.4 | AB6: 259.2 | AC6: 94694-4.3 | AD6: 9561-S001 | AE6: 已入 | AF6: =I6 -> 48 | AL6: =I6 -> 48 | AP6: =I6 -> 48 | AU6: =I6 -> 48 | AV6: =AV5+AU6 -> 698
A7: 45666 | B7: PT.MAP Aktif Adiperkasa, Tbk | C7: 印度尼西亚 | D7: 4500155574 | E7: 241227-2MAAJKTQ225-ZURU | F7: 4500155574-40 | G7: 9561-S001 | H7: 魔法小鸟 | I7: 252 | J7: 0 | K7: 4 | L7: =I7/K7 -> 63 | M7: 45733 | N7: 45729 | P7: PASS | R7: 45667 | S7: 无 | T7: 2/6进口商贴纸 | U7: MA | X7: 日期码格式：ZURU INC(BVI) 标准格式 日期：按实际生产日期 | Y7: 日期码格式：ZURU INC(BVI) 标准格式 日期：按实际生产日期 Packaging Info: MA UPC包装（优先1L)+1张进口商贴纸, 所有item使用含电池信息的进口商贴纸，贴纸待提供 1.可能会被抽大货样做测试，请多备料，CRD前半个月会通知是否有抽到该订单中的item。 2.此订单送普通仓，送仓后会有第三方验货，所以需要按CRD准时完货。 Remark: 9561-3pcs LR41 Batteries（included） | Z7: Emma Wu | AA7: 5.4 | AB7: =I7*AA7 -> 1360.8 | AC7: 94672-3.29 | AD7: 9561-S001 | AE7: 已入 | AF7: =I7 -> 252 | AL7: =I7 -> 252 | AP7: =I7 -> 252 | AU7: =I7 -> 252 | AV7: =AV6+AU7 -> 950
A8: 45681 | B8: ALL BRANDS TOYS PTY LTD | C8: 澳大利亚 | D8: 4500156597 | E8: 83575 | F8: 4500156597-20 | G8: 9561-S001 | H8: 魔法小鸟 | I8: 1200 | J8: 0 | K8: 4 | L8: =I8/K8 -> 300 | M8: 45737 | N8: =M8-4 -> 45733 | P8: PASS | R8: 45694 | S8: 无 | T8: 口商贴纸+一张收缩膜纽扣电池警告语进口商贴纸 + 1张说明书纽扣电池+警告语贴纸 | U8: MA | X8: 日期码格式：ZURU INC(BVI) 标准格式 日期：按实际生产日期 | Y8: 日期码格式：ZURU INC(BVI) 标准格式 日期：按实际生产日期 Packaging Info: 9561：MA_UPC版本包装（收缩膜/彩卡和说明书, MA首选1L，如无1L可用多语且含英语的配套多语UPC包装）+ 1张收缩膜纽扣电池警告语进口商贴纸 + 1张说明书纽 扣电池警告语贴纸 Remark: 1.按实际生产日期; 2.出澳大利亚，请按照相应标准生产; | Z8: Lydia Wu | AA8: 5.4 | AB8: =I8*AA8 -> 6480 | AC8: 94724-4.8 | AD8: 9561-S001 | AE8: 已入 | AF8: =I8 -> 1200 | AL8: =I8 -> 1200 | AP8: =I8 -> 1200 | AU8: =I8 -> 1200 | AV8: =AV7+AU8 -> 2150
A9: 45683 | B9: ALL BRANDS TOYS PTY LTD | C9: 澳大利亚 | D9: 4500156675 | E9: 83576 | F9: 4500156675-10 | G9: 9561-S001 | H9: 魔法小鸟 | I9: 240 | J9: 0 | K9: 4 | L9: =I9/K9 -> 60 | M9: 45743 | N9: 45740 | O9: PASS | P9: PASS | R9: 45694 | S9: 无 | T9: 进口商贴纸+一张收缩膜纽扣电池警告语进口商贴纸 + 1张说明书纽 扣电池警告语贴纸 警告语贴纸翻单4500156597 | U9: MA | X9: 日期码格式：ZURU INC(BVI) 标准格式 日期：按实际生产日期 | Y9: 日期码格式：ZURU INC(BVI) 标准格式 日期：按实际生产日期 Packaging Info: 9560：MA_UPC版本包装（收缩膜/彩卡和说明书, MA首选1L，如无1L可用多语且含英语的配套多语UPC包装）+ 1张收缩膜纽扣电池警告语进口商贴纸 + 1张说明书纽 扣电池警告语贴纸 警告语贴纸翻单4500156597 Remark: | Z9: Lydia Wu | AA9: 5.4 | AB9: =I9*AA9 -> 1296 | AC9: 94664-3.28 | AD9: 9561-S001 | AE9: 已入 | AF9: =I9 -> 240 | AL9: =I9 -> 240 | AP9: =I9 -> 240 | AU9: =I9 -> 240 | AV9: =AV8+AU9 -> 2390
A10: 45716 | B10: PRO & PACIFIC CO.,LTD | C10: 台湾 | D10: 4500158781 | E10: ZU25021702 | F10: 4500158781-30 | G10: 9561-S001 | H10: 魔法小鸟 | I10: 600 | J10: 0 | K10: 4 | L10: =I10/K10 -> 150 | M10: 45744 | N10: 45740 | P10: PASS | R10: 45719 | S10: 无 | T10: 3/6进口商贴纸 | U10: MA | X10: 日期码格式：ZURU INC(BVI) 标准格式 日期：按实际生产日期 | Y10: 日期码格式：ZURU INC(BVI) 标准格式 日期：按实际生产日期 Packaging Info: MA 1L UPC包装+1张进口商贴纸,贴纸资料待提供 Remark: | Z10: Emma Wu | AA10: 5.4 | AB10: =I10*AA10 -> 3240 | AC10: 94827-4.22 | AD10: 9561-S001 | AE10: 已入 | AF10: =I10 -> 600 | AL10: =I10 -> 600 | AP10: =I10 -> 600 | AU10: =I10 -> 600 | AV10: =AV9+AU10 -> 2990
A11: 45703 | B11: TARGET AUSTRALIA PTY LTD | C11: 澳大利亚 | D11: 4500157612 | E11: 2447992 | F11: 4500157612-10 | G11: 9561-S001 | H11: 魔法小鸟 | I11: 2000 | J11: 0 | K11: 4 | L11: =I11/K11 -> 500 | M11: 45754 | N11: 45750 | P11: PASS | R11: 45706 | S11: 有 | T11: 3/3SSCC label外箱贴纸+2/24纽扣电池警告语贴纸 | U11: MA | X11: 日期码格式：ZURU INC(BVI) 标准格式 日期：按实际生产日期 | Y11: 日期码格式：ZURU INC(BVI) 标准格式 日期：按实际生产日期 Packaging Info: 9561：英文MA包装(UPC版本，首选1L，无1L可用多L含英语)+箱唛+SSCC label外箱贴纸，另外9561包含纽扣电池，包装跟说明书上需加纽扣电池警告语贴纸。 Remark: 1. 客人要求箱唛不可出现任何手写内容，重量与实际一致且不可手写; 2. 此单去澳大利亚，请按相应澳新标准生产; 3. 使用普通透明封箱胶封箱; 4. 外箱需要贴Target SSCC LABEL,客供PDF文档，工厂自行订购。请贴在正唛右下角（一箱一张，贴1面正唛右下角,封箱胶纸不能挡住贴纸内容。)；外箱贴纸距离 外箱边缘应在2cm以上。如果正唛无位置可以贴在侧唛; 5. 外箱材质为ZURU标准; 6. 产品和包装上要有tracking label信息：格式为Zuru标准格式（可以自行调整具体年月日生产日期,避开节假期日）; 7. SSCC Label 尺寸更新为：4x4 inch; 8. 请务必按时完货，验货PASS后请按时送货入货代指定仓库，如果晚了导致船期Delay将会有罚金产生或者客户要求空运，所产生的罚金和空运费由工厂承担。 | Z11: Christine Liao | AA11: 5.7921 | AB11: =I11*AA11 -> 11584.2 | AC11: 94741-4.10 | AD11: 9561-S001 | AE11: 已入 | AF11: =I11 -> 2000 | AL11: =I11 -> 2000 | AP11: =I11 -> 2000 | AU11: =I11 -> 2000 | AV11: =AV10+AU11 -> 4990
A12: 45707 | B12: KINGSKY CLEAN-TECH CO., LTD. | C12: 香港 | D12: 4500158006 | E12: ZU25020701HK | F12: 4500158006-10 | G12: 9561-S001 | H12: 魔法小鸟 | I12: 500 | J12: 0 | K12: 4 | L12: =I12/K12 -> 125 | M12: 45754 | N12: 45750 | P12: PASS | R12: 45721 | S12: 无 | T12: 3/5进口商贴纸 | U12: MA | X12: 日期码格式：ZURU INC(BVI) 标准格式 日期：按实际生产日期 | Y12: 日期码格式：ZURU INC(BVI) 标准格式 日期：按实际生产日期 Packaging Info: MA UPC包装（优先1L)+1张进口商贴纸 贴纸AW、位置图待提供 此单客人要求4月初出货，所以后面会尽量提前交期，请尽快处理此单 Remark: 3PCS LR44 BATTERIES(INCLUDED) | Z12: Emma Wu | AA12: 5.7921 | AB12: =I12*AA12 -> 2896.05 | AC12: 94742-4.10 | AD12: 9561-S001 | AE12: 已入 | AF12: =I12 -> 500 | AL12: =I12 -> 500 | AP12: =I12 -> 500 | AU12: =I12 -> 500 | AV12: =AV11+AU12 -> 5490
A13: 45657 | B13: DM LLC | C13: 俄罗斯联邦 | D13: 4500155065 | E13: 出Bekasovo 2 | F13: 4500155065-10 | G13: 9561-S001 | H13: 魔法小鸟 | I13: 2092 | J13: 0 | K13: 4 | L13: =I13/K13 -> 523 | M13: 45755 | N13: 45751 | P13: PASS | R13: 45700 | S13: 无 | T13: 2/12进口商贴纸+ EAN条码贴纸 | U13: MA | X13: 外箱不要打ZURU标准日期码!胶件可以打日期码。 | Y13: 日期码格式：外包装/外箱不要打ZURU标准日期码 日期： Packaging Info: 注意:外包装(指:收缩膜/彩卡/铝箔袋/挂卡/PDQ)/外箱不要打ZURU标准日期码!胶件可以打日期码。 1L MA 收缩膜 + 进口商贴纸+ EAN条码贴纸， MA 指南/说明书（如有）； Remark: 标准配比 请按期完货， 会有罚金。 出港口Bekasovo 2和 | Z13: Ann Zhang | AA13: 5.4 | AB13: =I13*AA13 -> 11296.8 | AC13: 94818-4.23 | AD13: 9561-S001 | AE13: 已入 | AF13: =I13 -> 2092 | AL13: =I13 -> 2092 | AP13: =I13 -> 2092 | AU13: =I13 -> 2092 | AV13: =AV12+AU13 -> 7582
A14: 45657 | B14: DM LLC | C14: 俄罗斯联邦 | D14: 4500155065 | E14: 出Ural | F14: 4500155065-20 | G14: 9561-S001 | H14: 魔法小鸟 | I14: 476 | J14: 0 | K14: 4 | L14: =I14/K14 -> 119 | M14: 45755 | N14: 45751 | P14: PASS | R14: 45700 | S14: 无 | T14: 2/12进口商贴纸+ EAN条码贴纸 | U14: MA | X14: 外箱不要打ZURU标准日期码!胶件可以打日期码。 | Y14: 日期码格式：外包装/外箱不要打ZURU标准日期码 日期： Packaging Info: 注意:外包装(指:收缩膜/彩卡/铝箔袋/挂卡/PDQ)/外箱不要打ZURU标准日期码!胶件可以打日期码。 1L MA 收缩膜 + 进口商贴纸+ EAN条码贴纸， MA 指南/说明书（如有）； Remark: 标准配比 请按期完货， 会有罚金。 出港口Bekasovo 2和 | Z14: Ann Zhang | AA14: 5.4 | AB14: =I14*AA14 -> 2570.4 | AC14: 94818-4.23 | AD14: 9561-S001 | AE14: 已入 | AF14: =I14 -> 476 | AL14: =I14 -> 476 | AP14: =I14 -> 476 | AU14: =I14 -> 476 | AV14: =AV13+AU14 -> 8058
A15: 45716 | B15: TARGET US | C15: 美国 | D15: 4500158830 | E15: 10001240713-3890 | F15: 4500158830-20 | G15: 9561-S001 | H15: 魔法小鸟 | I15: 12000 | J15: 0 | K15: 4 | L15: =I15/K15 -> 3000 | M15: 45761 | N15: 45757 | P15: PASS | Q15: 暂停出货 | R15: 45728 | S15: 有 | T15: 外箱正唛左上角位置粘贴条码箱贴纸，来料贴纸上显示的客户DPCI#086-08-0267, UPC显示10193052078909+Event label内容显示Toys Set Date：7/20/2025 | U15: MA | X15: 日期码格式：ZURU INC(BVI) 标准格式 日期：按实际生产日期 | Y15: 日期码格式：ZURU INC(BVI) 标准格式 日期：按实际生产日期 Packaging Info: 9561：产品包装MA 收缩膜(UPC版) Remark: 9561: 1.9561-S001-PETS ALIVE-MAGIC BIRD-SERIES 1-MAGIC BIRD SURPRISE PLAYSET-SHRINK WRAP-4PCS/CTN 2. 产品包装MA 收缩膜(UPC版)，收缩膜上的UPC显示193052078902； 3. 外箱正唛左上角位置粘贴条码箱贴纸，每箱只贴一张，由ZURU订购。来料贴纸上显示的客户DPCI#086-08-0267, UPC显示10193052078909; 此订单所有item： 1. 外箱正唛箱唛内容右侧需贴一张Event label，内容显示Toys Set Date：7/20/2025，工厂自行订购； 2. 产品和包装上印刷 tracking code信息，格式为ZURU常规格式; 3. 出货方式：货代自提 | Z15: Holly Zheng | AA15: 5.4 | AB15: =I15*AA15 -> 64800 | AC15: ZB00336-5.27 ZB00390-6.2 | AD15: 9561-S001 | AE15: 已入 | AF15: =I15 -> 12000 | AL15: =I15 -> 12000 | AP15: =I15 -> 12000 | AU15: =I15 -> 12000 | AV15: =AV14+AU15 -> 20058
A16: 45721 | B16: KMART AUSTRALIA LTD(NEW ZEALAND) | C16: 新西兰 | D16: 4500159288 | E16: 20676972 | F16: 4500159288-10 | G16: 9561-S001 | H16: 魔法小鸟 | I16: 180 | J16: 0 | K16: 4 | L16: =I16/K16 -> 45 | M16: 45761 | N16: 45757 | P16: PASS | R16: 45733 | S16: 有 | T16: 1张包装纽扣电池警告语贴纸 + 1张说明书纽扣电池警告语 贴纸 （贴纸及位置图翻单: PO#4500157612）+ 1张防盗贴纸 (贴纸以及位置图翻单PO#4500159287） | U16: MA | X16: 日期码格式：ZURU INC(BVI) 标准格式 日期：按实际生产日期 | Y16: 日期码格式：ZURU INC(BVI) 标准格式 日期：按实际生产日期 Packaging Info: 9561: MA英语UPC版本包装（收缩膜和说明书, MA首选1L，如无1L可用多语且含英语的配套多语包装) + 1张包装纽扣电池警告语贴纸 + 1张说明书纽扣电池警告语 贴纸 （贴纸及位置图翻单: PO#4500157612）+ 1张防盗贴纸 (贴纸以及位置图翻单PO#4500159287）+ 箱唛 + 外箱SSCC Label 配比信息：3pcs mini turtles: 4pcs mini tutles: 5pcs mini turtles= 87:10:3 Remark: 1.请务必按时完货，验货。并且按期送货入货代指定仓库，如果晚了导致船期Delay将会有罚金产生或者客户要求空运，所产生的罚金和空运费由工厂承担。 2.SSCC 外箱贴纸请同纸箱瓦楞纸方向（竖纹向）垂直，即外箱贴纸横着贴(注意条码不要被胶带粘住），贴1pc，贴1面正唛，封箱胶纸不能挡住贴纸内容。外箱贴纸 离外箱边距离不少于2cm。 3.外箱材质为ZURU标准； 4.此单需使用KMART封箱胶上下工字型封箱;从2019年6月开始，要用KMART 新版封箱胶带，此单要用"ANKO"封箱胶带 5.此单出口新西兰，请按相应的澳新标准生产； 6.产品和包装上生产批号的显示格式ZURU标准日期码格式 7.外箱信息不可手写，重量和体积需要与实际的一致(不可手写） 8. 每款item装箱后的G.W.超过10KG或者CBM超过0.13,(9.5KG或者以上，四舍五入后也属于10KG) 需在外箱上加印超 重或者Bulky LOGO，若发现我们资料没有，请 帮忙提醒 1)重量超过10kg但不超过16kg且CBM不超过0.13,10-16kg 超重logo 2）CBM超过0.13且重量少于17kg，bulky logo 3）不属于以上两种情况，需要使用相应重量范围内的超重logo 4）超重logo需要在外箱四面都印刷(箱唛右上角，两面侧唛超重logo需要尽量靠近毛重)，尺寸为:110mm height* 95mm width 9. 实际外箱重量跟印在箱唛上的数据差异不能超3%，尺寸按实际数据印刷 | Z16: Lydia Wu | AA16: 5.7921 | AB16: =I16*AA16 -> 1042.578 | AC16: 94784-4.17 | AD16: 9561-S001 | AE16: 已入 | AF16: =I16 -> 180 | AL16: =I16 -> 180 | AP16: =I16 -> 180 | AU16: =I16 -> 180 | AV16: =AV15+AU16 -> 20238
A17: 45721 | B17: KMART AUSTRALIA LTD | C17: 澳大利亚 | D17: 4500159287 | E17: 20676967 | F17: 4500159287-10 | G17: 9561-S001 | H17: 魔法小鸟 | I17: 1620 | J17: 0 | K17: 4 | L17: =I17/K17 -> 405 | M17: 45761 | N17: 45757 | P17: PASS | R17: 45733 | S17: 有 | T17: 1张包装纽扣电池警告语贴纸 + 1张说明书纽扣电池警告语 贴纸 （贴纸及位置图翻单: PO#4500157612）+ 1张防盗贴纸+ 箱唛 + 外箱SSCC Label | U17: MA | X17: 日期码格式：ZURU INC(BVI) 标准格式 日期：按实际生产日期 | Y17: 日期码格式：ZURU INC(BVI) 标准格式 日期：按实际生产日期 Packaging Info: 9561: MA英语UPC版本包装（收缩膜和说明书, MA首选1L，如无1L可用多语且含英语的配套多语包装) + 1张包装纽扣电池警告语贴纸 + 1张说明书纽扣电池警告语 贴纸 （贴纸及位置图翻单: PO#4500157612）+ 1张防盗贴纸+ 箱唛 + 外箱SSCC Label 配比信息：3pcs mini turtles: 4pcs mini tutles: 5pcs mini turtles= 87:10:3 Remark: 1.请务必按时完货，验货。并且按期送货入货代指定仓库，如果晚了导致船期Delay将会有罚金产生或者客户要求空运，所产生的罚金和空运费由工厂承担。 2.SSCC 外箱贴纸请同纸箱瓦楞纸方向（竖纹向）垂直，即外箱贴纸横着贴(注意条码不要被胶带粘住），贴1pc，贴1面正唛，封箱胶纸不能挡住贴纸内容。外箱贴纸 离外箱边距离不少于2cm。 3.外箱材质为ZURU标准； 4.此单需使用KMART封箱胶上下工字型封箱;从2019年6月开始，要用KMART 新版封箱胶带，此单要用"ANKO"封箱胶带 5.此单出口澳大利亚，请按相应的澳新标准生产； 6.产品和包装上生产批号的显示格式ZURU标准日期码格式 7.外箱信息不可手写，重量和体积需要与实际的一致(不可手写） 8. 每款item装箱后的G.W.超过10KG或者CBM超过0.13,(9.5KG或者以上，四舍五入后也属于10KG) 需在外箱上加印超 重或者Bulky LOGO，若发现我们资料没有，请 帮忙提醒 1)重量超过10kg但不超过16kg且CBM不超过0.13,10-16kg 超重logo 2）CBM超过0.13且重量少于17kg，bulky logo 3）不属于以上两种情况，需要使用相应重量范围内的超重logo 4）超重logo需要在外箱四面都印刷(箱唛右上角，两面侧唛超重logo需要尽量靠近毛重)，尺寸为:110mm height* 95mm width 9. 实际外箱重量跟印在箱唛上的数据差异不能超3%，尺寸按实际数据印刷 | Z17: Lydia Wu | AA17: 5.7921 | AB17: =I17*AA17 -> 9383.202 | AC17: 94783-4.17 | AD17: 9561-S001 | AE17: 已入 | AF17: =I17 -> 1620 | AL17: =I17 -> 1620 | AP17: =I17 -> 1620 | AU17: =I17 -> 1620 | AV17: =AV16+AU17 -> 21858
A18: 45726 | B18: PPTOYS PTE LTD (SG) | C18: 新加坡 | D18: 4500159608 | E18: ZU25022002SG | F18: 4500159608-20 | G18: 9561-S001 | H18: 魔法小鸟 | I18: 600 | J18: 0 | K18: 4 | L18: =I18/K18 -> 150 | M18: 45761 | N18: 45757 | P18: PASS | R18: 45726 | S18: 无 | T18: 3/14进口商贴纸 | U18: MA | X18: 日期码格式：ZURU INC(BVI) 标准格式 日期：按实际生产日期 | Y18: 日期码格式：ZURU INC(BVI) 标准格式 日期：按实际生产日期 Packaging Info: MA UPC包装（优先1L)+1张进口商贴纸 其他item贴纸AW、位置图待提供 此客人用的贴纸内容都是一样的，个别item可能存在尺寸差别，如果发现贴纸尺寸没差别，就请都统一订购节省成本 Remark: 9561-3PCS LR44 BATTERIES(INCLUDED) | Z18: Emma Wu | AA18: 5.3566 | AB18: =I18*AA18 -> 3213.96 | AC18: 94794-4.18 | AD18: 9561-S001 | AE18: 已入 | AF18: =I18 -> 600 | AL18: =I18 -> 600 | AP18: =I18 -> 600 | AU18: =I18 -> 600 | AV18: =AV17+AU18 -> 22458
A19: 45723 | B19: ZURU LLC | C19: 美国 | D19: 4500159483 | E19: 5200006344 | F19: 4500159483-10 | G19: 9561-S003-MB-MTS | H19: 魔法小鸟 （邮包盒装） | I19: 756 | J19: 0 | K19: 2 | L19: =I19/K19 -> 378 | M19: 45765 | N19: 45761 | P19: PASS | R19: 45726 | S19: 无 | T19: 无 | U19: MA | W19: 邮包盒图稿翻EU单4500159392. | X19: 日期码格式：ZURU INC(BVI) 标准格式 日期：按实际生产日期 | Y19: 日期码格式：ZURU INC(BVI) 标准格式 日期：按实际生产日期 Packaging Info: 9561 MA UPC版 包装入邮包盒，邮包盒图稿翻EU单4500159392. Remark: 1.Amazon domestic 订单。出口美国。外箱最长边不能超过25" （超过了，case pack只能为1），不符合要求的大货，一律不接受。 2.无第三方验货/测试要求。 3.日期码使用ZURU标准版本。 | Z19: Kelly Shen/Mia Pan/P | AA19: 6.2626 | AB19: =I19*AA19 -> 4734.5256 | AC19: ZB00163-4.23 | AD19: 9561-S003-MB-MTS | AE19: 已入 | AF19: =I19 -> 756 | AL19: =I19 -> 756 | AP19: =I19 -> 756 | AU19: =I19 -> 756 | AV19: =AV18+AU19 -> 23214
A20: 45721 | B20: THE FARMERS' TRADING COMPANY LIMITE | C20: 新西兰 | D20: 4500159217 | E20: SSF793 | F20: 4500159217-10 | G20: 9561-S001 | H20: 魔法小鸟 | I20: 720 | J20: 0 | K20: 4 | L20: =I20/K20 -> 180 | M20: 45766 | N20: 45762 | P20: PASS | R20: 45734 | S20: 无 | T20: 4/1包装正面和说明书都需要加电池警告语贴纸（法规要求）+可移动材质的价格贴纸（价格贴纸要切虚线） | U20: MA | X20: 日期码格式：ZURU INC(BVI) 标准格式 日期：按实际生产日期 | Y20: 日期码格式：ZURU INC(BVI) 标准格式 日期：按实际生产日期 Packaging Info: #9561:3PCS LR44 BATTERIES(INCLUDED);包装正面和说明书都需要加电池警告语贴纸（法规要求） Remark: MA UPC英语包装（优先1L英语版本,或者3L/L含英语即可); 可移动材质的价格贴纸（价格贴纸要切虚线） | Z20: Abby Liang | AA20: 5.4 | AB20: =I20*AA20 -> 3888 | AC20: 94884-4.30 | AD20: 9561-S001 | AE20: 已入 | AF20: =I20 -> 720 | AL20: =I20 -> 720 | AP20: =I20 -> 720 | AU20: =I20 -> 720 | AV20: =AV19+AU20 -> 23934
A21: 45707 | B21: ZURU Germany GMBH | C21: 德国 | D21: 4500157858 | E21: 5200006149 | F21: 4500157858-70 | G21: 9561-S001-MTS | H21: 魔法小鸟 | I21: 4000 | J21: 0 | K21: 4 | L21: =I21/K21 -> 1000 | M21: 45768 | N21: 45764 | P21: PASS | R21: 45707 | S21: 无 | T21: 3/7EAN条码贴纸+FR/DE/IT/ES警语贴纸+FR/DE/IT/ES说明书黑白书纸+WEEE通用黑白书纸（8L) | U21: MA | X21: 日期码格式：ZURU INC(BVI) 标准格式 日期：按实际生产日期 | Y21: 日期码格式：ZURU INC(BVI) 标准格式 日期：按实际生产日期 Packaging Info: 9561：MA最新版5L EAN收缩膜+多语折叠语警告贴纸+MA最新版5L收藏指南+MA最新版6L说明书+WEEE通用黑白书纸（8L) Remark: "1.德国内销单，需要通过ZURU 验货结果后才能出货 (工厂需要主动提前同ZURU QC预约验货避免延期出货造成不必要麻烦)； 2. 若有特定款有特殊外箱条码要求时,需要明确列出产品款对应的具体外箱条码号码/条码类型 (若无,可以忽略此需求) 3.所有出口欧洲的产品, 法规规定禁止在包装和共公众用的印刷品中使用矿物油中含有的物质, 包装印刷油墨中含有的MOAH/MOSH的质量浓度不能超过1%, 否则出货 到法国被抽检出现问题, 供应商需要对此负责; 4. date code: 外箱日期码要晚于或等于产品日期码，不能早于产品的日期码 5. 所有电子产品身上需要加字唛，为ZURU FRANCE 地址 (如无电子产品，或者产品布标有此地址，可忽略此信息) ZURU France 1/3, Rue d'Argenteuil 95210 SAINT-GRATIEN, FRANCE 6. 装柜时需要按照款式号码从小到大一款款依次装,避免终端仓库卸货混乱.若一个柜子涉及到几个不同国家内销单,装柜时需要一个国家装完后再装另一个国家的 产品,依次装柜,避免终端仓库因不同国家不同库位位置卸货混乱. (此点需要同工厂装柜人员强调)" | Z21: SD82 | AA21: 5.4 | AB21: =I21*AA21 -> 21600 | AC21: 94852-4.28 | AD21: 9561-S001-5L | AE21: 已入 | AJ21: =I21 -> 4000 | AL21: =I21 -> 4000 | AP21: =I21 -> 4000 | AU21: =I21 -> 4000 | AV21: =AV20+AU21 -> 27934
A22: 45729 | B22: Babyhouse | C22: 乌兹别克斯坦 | D22: 4500159866 | F22: 4500159866-30 | G22: 9561-S001 | H22: 魔法小鸟 | I22: 180 | J22: 0 | K22: 4 | L22: =I22/K22 -> 45 | M22: 45769 | N22: 45765 | P22: PASS | R22: 45729 | S22: 无 | T22: 3/14进口商贴纸 | U22: MA | X22: 日期码格式：ZURU INC(BVI) 标准格式 日期：按实际生产日期 | Y22: 日期码格式：ZURU INC(BVI) 标准格式 日期：按实际生产日期 Packaging Info: 9561 : 1L MA 收缩膜 + 进口商贴纸 ; MA 说明书/指南（如有）; Remark: 标准配比 | Z22: Ann Zhang | AA22: 5.4 | AB22: =I22*AA22 -> 972 | AC22: 94879-4.29 | AD22: 9561-S001 | AE22: 已入 | AF22: =I22 -> 180 | AL22: =I22 -> 180 | AP22: =I22 -> 180 | AU22: =I22 -> 180 | AV22: =AV21+AU22 -> 28114
A23: 45728 | B23: Smyths Toys HQ UC IE | C23: 爱尔兰 | D23: 4500159926 | E23: 4400471618 | F23: 4500159926-10 | G23: 9561-S001 | H23: 魔法小鸟 | I23: 1000 | J23: 0 | K23: 4 | L23: =I23/K23 -> 250 | M23: 45771 | N23: 45761 | P23: PASS | R23: 45734 | S23: 无 | T23: 无 | U23: MA | X23: 日期码格式：ZURU INC(BVI) 标准格式 日期：按实际生产日期 | Y23: 日期码格式：ZURU INC(BVI) 标准格式 日期：按实际生产日期 Packaging Info: 9561：MA 5L-6L EAN收缩膜+MA 5L-6L说明书<(>&<)>收藏指南 Remark: 1) 包装日期码按ZURU格式即可，请确保不迟于外箱日期码，可等于或者早于外箱日期码，必须为法定工作日，印刷前请先检查外箱日期码。 2) 订单出英国，请注意检查产品及包装应带UKCA图标（14+产品除外），包装显示ZURU UK LTD/ZURU France地址信息，QC部门请查核，如有问题与跟单确认 3) 需要完全符合欧洲标准(符合微塑料法规)，否则不合法规会有客诉产生 | Z23: May Wu | AA23: 5.4 | AB23: =I23*AA23 -> 5400 | AD23: 9561-S001-5L | AE23: 已入 | AJ23: =I23 -> 1000 | AL23: =I23 -> 1000 | AP23: =I23 -> 1000 | AU23: =I23 -> 1000 | AV23: =AV22+AU23 -> 29114
A24: 45733 | B24: SMYTHS TOYS HQ UC | C24: 法国 | D24: 4500160446 | E24: 4400472143 | F24: 4500160446-10 | G24: 9561-S001 | H24: 魔法小鸟 | I24: 800 | J24: 0 | K24: 4 | L24: =I24/K24 -> 200 | M24: 45771 | N24: 45764 | P24: PASS | R24: 45734 | S24: 无 | T24: 无 | U24: MA | X24: 日期码格式：ZURU INC(BVI) 标准格式 日期：按实际生产日期 | Y24: 日期码格式：ZURU INC(BVI) 标准格式 日期：按实际生产日期 Packaging Info: 1.9561:MA 5L-6L EAN收缩膜+MA 5L-6L说明书<(>&<)>收藏指南 Remark: 1. 此单出法国，所有包装都需要含有法语，需要满足Zuru Standard欧洲标准测试要求； 2. 请准时出货，推期会有罚款； 3. 所有出口法国的产品, 法规规定禁止在包装和共公众用的印刷品中使用矿物油中含有的物质, 包装印刷油墨中含有的MOAH/MOSH的质量浓度不能超过1%, 否则出 货到法国被抽检出现问题, 供应商需要对此负责; | Z24: Ula Zhao | AA24: 5.4 | AB24: =I24*AA24 -> 4320 | AC24: 94812-4.22 | AD24: 9561-S001-5L | AE24: 已入 | AJ24: =I24 -> 800 | AL24: =I24 -> 800 | AP24: =I24 -> 800 | AU24: =I24 -> 800 | AV24: =AV23+AU24 -> 29914
A25: 45728 | B25: Smyths Toys HQ UC IE | C25: 英国 | D25: 4500159895 | E25: 客户PO4400471 627 | F25: 4500159895-10 | G25: 9561-S001 | H25: 魔法小鸟 | I25: 2000 | J25: 0 | K25: 4 | L25: =I25/K25 -> 500 | M25: 45771 | N25: 45764 | P25: PASS | R25: 45734 | S25: 无 | T25: 无 | U25: MA | X25: 日期码格式：ZURU INC(BVI) 标准格式 日期：按实际生产日期 | Y25: 日期码格式：ZURU INC(BVI) 标准格式 日期：按实际生产日期 Packaging Info: 9561：MA 5L-6L EAN收缩膜+MA 5L-6L说明书<(>&<)>收藏指南 Remark: 1) 包装日期码按ZURU格式即可，请确保不迟于外箱日期码，可等于或者早于外箱日期码，必须为法定工作日，印刷前请先检查外箱日期码。 2) 订单出英国，请注意检查产品及包装应带UKCA图标（14+产品除外），包装显示ZURU UK LTD/ZURU France地址信息，QC部门请查核，如有问题与跟单确认 3) 需要完全符合欧洲标准(符合微塑料法规)，否则不合法规会有客诉产生 | Z25: May Wu | AA25: 5.4 | AB25: =I25*AA25 -> 10800 | AC25: 94853-4.28 | AD25: 9561-S001-5L | AE25: 已入 | AJ25: =I25 -> 2000 | AL25: =I25 -> 2000 | AP25: =I25 -> 2000 | AU25: =I25 -> 2000 | AV25: =AV24+AU25 -> 31914
A26: 45732 | B26: Smyths Toys HQ UC IE | C26: 英国 | D26: 4500159895 | E26: 客户PO4400471 628 | F26: 4500159895-20 | G26: 9561-S001 | H26: 魔法小鸟 | I26: 2000 | J26: 0 | K26: 4 | L26: =I26/K26 -> 500 | M26: 45771 | N26: 45764 | P26: PASS | R26: 45734 | S26: 无 | T26: 无 | U26: MA | X26: 日期码格式：ZURU INC(BVI) 标准格式 日期：按实际生产日期 | Y26: 日期码格式：ZURU INC(BVI) 标准格式 日期：按实际生产日期 Packaging Info: 9561：MA 5L-6L EAN收缩膜+MA 5L-6L说明书<(>&<)>收藏指南 Remark: 1) 包装日期码按ZURU格式即可，请确保不迟于外箱日期码，可等于或者早于外箱日期码，必须为法定工作日，印刷前请先检查外箱日期码。 2) 订单出英国，请注意检查产品及包装应带UKCA图标（14+产品除外），包装显示ZURU UK LTD/ZURU France地址信息，QC部门请查核，如有问题与跟单确认 3) 需要完全符合欧洲标准(符合微塑料法规)，否则不合法规会有客诉产生 | Z26: May Wu | AA26: 5.4 | AB26: =I26*AA26 -> 10800 | AC26: 94853-4.28 | AD26: 9561-S001-5L | AE26: 已入 | AJ26: =I26 -> 2000 | AL26: =I26 -> 2000 | AP26: =I26 -> 2000 | AU26: =I26 -> 2000 | AV26: =AV25+AU26 -> 33914
A27: 45719 | B27: PERTINI TOYS doo | C27: 塞尔维亚/蒙特内 | D27: 4500158989 | F27: 4500158989-10 | G27: 9561-S001 | H27: 魔法小鸟 | I27: 1400 | J27: 0 | K27: 4 | L27: =I27/K27 -> 350 | M27: 45772 | N27: 45768 | P27: PASS | R27: 45719 | S27: 无 | T27: 3/20EAN条码贴纸+进口商贴纸 | U27: MA | X27: 日期码格式：ZURU INC(BVI) 标准格式 日期：按实际生产日期 | Y27: 日期码格式：ZURU INC(BVI) 标准格式 日期：按实际生产日期 Packaging Info: 9561: MA 1L UPC 收缩膜+EAN条码贴纸+进口商贴纸;MA A版指南书，MA 5L+6L警告语/收藏指南 Remark: 此单出EU，需满足EU测试标准要求，不能含微塑料。 1. 9561-S001: 3PCS LR44 BATTERIES(INCLUDED) 2. 9543GQ1-S001: Ratio:bule/purple/pink/orange =5:6:6:5; 2PCS AAA BATTERIES(NOT INCLUDED) | Z27: Sharon Zhao | AA27: 5.4 | AB27: =I27*AA27 -> 7560 | AC27: 94930-5.6 | AD27: 9561-S001 | AE27: 已入 | AF27: =I27 -> 1400 | AL27: =I27 -> 1400 | AP27: =I27 -> 1400 | AU27: =I27 -> 1400 | AV27: =AV26+AU27 -> 35314
A28: 45736 | B28: THE ENTERTAINER | C28: 英国 | D28: 4500160901 | E28: 4500160901-1: FB12977 | F28: 4500160901-20 | G28: 9561-S001 | H28: 魔法小鸟 | I28: 368 | J28: 0 | K28: 4 | L28: =I28/K28 -> 92 | M28: 45772 | N28: 45768 | P28: PASS | R28: 45740 | S28: 无 | T28: 3/24一张2国语言电池说明书(英语+阿拉伯语) | U28: MA | X28: 日期码格式：ZURU INC(BVI) 标准格式 日期：按实际生产日期 | Y28: 日期码格式：ZURU INC(BVI) 标准格式 日期：按实际生产日期 Packaging Info: 9561-S001: MA 最新1L UPC包装+一张2国语言电池说明书(英语+阿拉伯语); BARCODE: 193052078902 Remark: *MA版本按工厂现有最新库存即可，订单出英国，请注意检查产品及包装应带UKCA图标，包装显示ZURU UK LTD信息，QC同事请查核，如有问题与跟单确认 *生产日期按实际（法定工作日），按ZURU标准格式即可 ，但是请知悉包装日期码需要早于或者等于外箱日期码 ，不能晚于外箱日期码 *请注意所有订单都需要经过ZURU QC验货并且通过后方可出货 *所有产品按符合欧洲标准走货，需要是不含微塑料版本 。 *涉及到硼的，如可选择情况下应使用低硼版本 （slime 类别低硼一般低于300ppm)，无选择的应与跟单复核再安排 。 *条码以订单显示为准 ，请安排生产前先核对 ，有问题请提出。 *订单对应客户3个PO号 ，备注有显示 ，注意分开做货/验货/装柜 ，混装有罚款。 * 大货样： 请在4/10 前寄出每款1整套大货样到罗湖办公室7B Sandy Shao 收。 | Z28: Sandy Shao | AA28: 5.3727 | AB28: =I28*AA28 -> 1977.1536 | AC28: 94866-4.29 | AD28: 9561-S001 | AE28: 已入 | AF28: =I28 -> 368 | AL28: =I28 -> 368 | AP28: =I28 -> 368 | AU28: =I28 -> 368 | AV28: =AV27+AU28 -> 35682
A29: 45736 | B29: THE ENTERTAINER | C29: 英国 | D29: 4500160901 | E29: 4500160901-2: FB12978 | F29: 4500160901-110 | G29: 9561-S001 | H29: 魔法小鸟 | I29: 368 | J29: 0 | K29: 4 | L29: =I29/K29 -> 92 | M29: 45772 | N29: 45768 | P29: PASS | R29: 45740 | S29: 无 | T29: 3/24一张2国语言电池说明书(英语+阿拉伯语) | U29: MA | X29: 日期码格式：ZURU INC(BVI) 标准格式 日期：按实际生产日期 | Y29: 日期码格式：ZURU INC(BVI) 标准格式 日期：按实际生产日期 Packaging Info: 9561-S001: MA 最新1L UPC包装+一张2国语言电池说明书(英语+阿拉伯语); BARCODE: 193052078902 Remark: *MA版本按工厂现有最新库存即可，订单出英国，请注意检查产品及包装应带UKCA图标，包装显示ZURU UK LTD信息，QC同事请查核，如有问题与跟单确认 *生产日期按实际（法定工作日），按ZURU标准格式即可 ，但是请知悉包装日期码需要早于或者等于外箱日期码 ，不能晚于外箱日期码 *请注意所有订单都需要经过ZURU QC验货并且通过后方可出货 *所有产品按符合欧洲标准走货，需要是不含微塑料版本 。 *涉及到硼的，如可选择情况下应使用低硼版本 （slime 类别低硼一般低于300ppm)，无选择的应与跟单复核再安排 。 *条码以订单显示为准 ，请安排生产前先核对 ，有问题请提出。 *订单对应客户3个PO号 ，备注有显示 ，注意分开做货/验货/装柜 ，混装有罚款。 * 大货样： 请在4/10 前寄出每款1整套大货样到罗湖办公室7B Sandy Shao 收。 | Z29: Sandy Shao | AA29: 5.3727 | AB29: =I29*AA29 -> 1977.1536 | AC29: 94866-4.29 | AD29: 9561-S001 | AE29: 已入 | AF29: =I29 -> 368 | AL29: =I29 -> 368 | AP29: =I29 -> 368 | AU29: =I29 -> 368 | AV29: =AV28+AU29 -> 36050
A30: 45736 | B30: THE ENTERTAINER | C30: 英国 | D30: 4500160901 | E30: 4500160901-3: FB12979 | F30: 4500160901-200 | G30: 9561-S001 | H30: 魔法小鸟 | I30: 368 | J30: 0 | K30: 4 | L30: =I30/K30 -> 92 | M30: 45772 | N30: 45768 | P30: PASS | R30: 45740 | S30: 无 | T30: 3/24一张2国语言电池说明书(英语+阿拉伯语) | U30: MA | X30: 日期码格式：ZURU INC(BVI) 标准格式 日期：按实际生产日期 | Y30: 日期码格式：ZURU INC(BVI) 标准格式 日期：按实际生产日期 Packaging Info: 9561-S001: MA 最新1L UPC包装+一张2国语言电池说明书(英语+阿拉伯语); BARCODE: 193052078902 Remark: *MA版本按工厂现有最新库存即可，订单出英国，请注意检查产品及包装应带UKCA图标，包装显示ZURU UK LTD信息，QC同事请查核，如有问题与跟单确认 *生产日期按实际（法定工作日），按ZURU标准格式即可 ，但是请知悉包装日期码需要早于或者等于外箱日期码 ，不能晚于外箱日期码 *请注意所有订单都需要经过ZURU QC验货并且通过后方可出货 *所有产品按符合欧洲标准走货，需要是不含微塑料版本 。 *涉及到硼的，如可选择情况下应使用低硼版本 （slime 类别低硼一般低于300ppm)，无选择的应与跟单复核再安排 。 *条码以订单显示为准 ，请安排生产前先核对 ，有问题请提出。 *订单对应客户3个PO号 ，备注有显示 ，注意分开做货/验货/装柜 ，混装有罚款。 * 大货样： 请在4/10 前寄出每款1整套大货样到罗湖办公室7B Sandy Shao 收。 | Z30: Sandy Shao | AA30: 5.3727 | AB30: =I30*AA30 -> 1977.1536 | AC30: 94866-4.29 | AD30: 9561-S001 | AE30: 已入 | AF30: =I30 -> 368 | AL30: =I30 -> 368 | AP30: =I30 -> 368 | AU30: =I30 -> 368 | AV30: =AV29+AU30 -> 36418
A31: 45761 | D31: ZMPO250315 | G31: 9561-S001 | H31: 魔法小鸟 | I31: 252 | J31: 0 | K31: 4 | L31: =I31/K31 -> 63 | M31: 45775 | N31: 45768 | P31: PASS | R31: 空白外箱 | S31: 无 | T31: 无 | U31: MA | Y31: Remark:大货最新版本/大货标准箱装箱/箱唛参照邮件附件;备注： 收到样品订单后尽快安排 ，此订单麻烦在外箱上备注是海运订单/注意样板品质质量要求要高于大货品质质量 ，送货时必须要附带送货单(没有送货单和QC检验合格报告的仓库一律拒绝收货)，请知悉，谢谢！ | Z31: Angus | AD31: 9561-S001 | AE31: 已入 | AF31: =I31 -> 252 | AL31: =I31 -> 252 | AP31: =I31 -> 252 | AU31: =I31 -> 252 | AV31: =AV30+AU31 -> 36670
A32: 45705 | B32: DIAMANT TOYS LTD | C32: 以色列 | D32: 4500157252 | E32: 56121 | F32: 4500157252-10 | G32: 9561-S001 | H32: 魔法小鸟 | I32: 1340 | J32: 0 | K32: 4 | L32: =I32/K32 -> 335 | M32: 45777 | N32: 45773 | P32: PASS | R32: 45707 | S32: 无 | T32: 3/10进口商贴纸+2张彩色贴纸 | U32: MA | X32: 日期码格式：ZURU INC(BVI) 标准格式 日期：按实际生产日期 | Y32: 日期码格式：ZURU INC(BVI) 标准格式 日期：按实际生产日期 Tracking Code: Packaging Info: 9561：1L MA包装+进口商贴纸+2张彩色贴纸; MA说明书 Remark: | Z32: Lena Huang | AA32: 5.4 | AB32: =I32*AA32 -> 7236 | AC32: 94885-4.30 | AD32: 9561-S001 | AE32: 已入 | AF32: =I32 -> 1340 | AL32: =I32 -> 1340 | AP32: =I32 -> 1340 | AU32: =I32 -> 1340 | AV32: =AV31+AU32 -> 38010
A33: 45734 | B33: ZURU LLC | C33: 美国 | D33: 4500160498 | E33: B0DR3T17RV | F33: 4500160498-20 | G33: 9561-S003-MB-MTS | H33: 魔法小鸟 （邮包盒装） | I33: 2744 | J33: 0 | K33: 2 | L33: =I33/K33 -> 1372 | M33: 45777 | N33: 45773 | P33: PASS | R33: 45735 | S33: 无 | T33: 邮包盒图稿翻EU单4500159392. | U33: MA | X33: 日期码格式：ZURU INC(BVI) 标准格式 日期：按实际生产日期 | Y33: 日期码格式：ZURU INC(BVI) 标准格式 日期：按实际生产日期 Packaging Info: #9561: MA 1L UPC版包装入邮包盒，邮包盒图稿翻EU单4500159392. Remark: 1.Amazon domestic 订单。出口美国。外箱最长边不能超过25" （超过了，case pack只能为1），不符合要求的大货，一律不接受。 2.无第三方验货/测试要求。 3.日期码使用ZURU标准版本。 4.邮包盒要印刷日期码。 | Z33: Kelly Shen/Mia Pan/P | AA33: 5.9569 | AB33: =I33*AA33 -> 16345.734 | AC33: ZB00241-5.13 | AD33: 9561-S003-MB-MTS | AE33: 已入 | AF33: =I33 -> 2744 | AL33: =I33 -> 2744 | AP33: =I33 -> 2744 | AU33: =I33 -> 2744 | AV33: =AV32+AU33 -> 40754
A34: 45737 | B34: Model & Hobby Toys | C34: 匈牙利 | D34: 4500161125 | F34: 4500161125-10 | G34: 9561-S001 | H34: 魔法小鸟 | I34: 300 | J34: 0 | K34: 4 | L34: =I34/K34 -> 75 | M34: 45782 | N34: 45778 | P34: PASS | R34: 45750 | S34: 无 | T34: 4/3进口商贴纸 | U34: MA | X34: 日期码格式：ZURU INC(BVI) 标准格式 日期：按实际生产日期 | Y34: 日期码格式：ZURU INC(BVI) 标准格式 日期：按实际生产日期 Packaging Info: 9561: A 版5L MA 收缩膜+进口商贴纸; A 版 5L MA guide book Remark: 1、若产品有比例使用ZURU STD 比例 2、所有item 均用MA UPC 条码，若包装不是UPC 条码的请告知 3、此单出欧洲需满足EU测试标准要求 | Z34: Snowy | AA34: 5.3727 | AB34: =I34*AA34 -> 1611.81 | AD34: 9561-S001-5L | AE34: 已入 | AJ34: =I34 -> 300 | AL34: =I34 -> 300 | AP34: =I34 -> 300 | AU34: =I34 -> 300 | AV34: =AV33+AU34 -> 41054
A35: 45737 | B35: FELYX TOYS | C35: 保加利亚 | D35: 4500161118 | F35: 4500161118-10 | G35: 9561-S001 | H35: 魔法小鸟 | I35: 1640 | J35: 0 | K35: 4 | L35: =I35/K35 -> 410 | M35: 45782 | N35: 45778 | P35: PASS | R35: 45741 | S35: 无 | T35: 4/7进口商贴纸 | U35: MA | X35: 日期码格式：ZURU INC(BVI) 标准格式 日期：按实际生产日期 | Y35: 日期码格式：ZURU INC(BVI) 标准格式 日期：按实际生产日期 Packaging Info: 9561:A 版 1L MA 收缩膜+进口商贴纸；客版guide book/客版说明书 Remark: 1、若产品有比例使用ZURU STD 比例 2、所有item 均用MA UPC 条码，若包装不是UPC 条码的请告知 3、此单出欧洲需满足EU测试标准要求 | Z35: Snowy Wu | AA35: 5.1379 | AB35: =I35*AA35 -> 8426.156 | AC35: 94953-5.9 | AD35: 9561-S001-1 | AE35: 已入 | AF35: =I35 -> 1640 | AN35: =I35 -> 1640 | AO35: =I35 -> 1640 | AP35: =I35 -> 1640 | AU35: =I35 -> 1640 | AV35: =AV34+AU35 -> 42694
A36: 45737 | B36: FELYX TOYS | C36: 保加利亚 | D36: 4500161118 | F36: 4500161118-20 | G36: 9561EC-S001 | H36: 魔法小鸟 | I36: 360 | J36: 0 | K36: 18 | L36: =I36/K36 -> 20 | M36: 45782 | N36: 45778 | P36: PASS | R36: 45741 | S36: 无 | T36: 4/7进口商贴纸 | U36: MA | X36: 日期码格式：ZURU INC(BVI) 标准格式 日期：按实际生产日期 | Y36: 日期码格式：ZURU INC(BVI) 标准格式 日期：按实际生产日期 Packaging Info: 9561EC:A 版 1L MA 收缩膜+进口商贴纸；客版guide book/客版说明书/A 版 1L MA 展示架 Remark: 1、若产品有比例使用ZURU STD 比例 2、所有item 均用MA UPC 条码，若包装不是UPC 条码的请告知 3、此单出欧洲需满足EU测试标准要求 | Z36: Snowy Wu | AA36: 118.7504 | AB36: =AA36*L36 -> 2375.008 | AC36: 94953-5.9 | AD36: 9561EC-S001-1 | AE36: 已入 | AF36: =I36 -> 360 | AN36: =I36 -> 360 | AO36: =I36 -> 360 | AP36: =I36 -> 360 | AR36: =L36 -> 20 | AU36: =I36 -> 360 | AV36: =AV35+AU36 -> 43054
A37: 45743 | B37: Smyths Toys EU HQ UC | C37: 德国 | D37: 4500161489 | E37: 4400474092 | F37: 4500161489-10 | G37: 9561-S001 | H37: 魔法小鸟 | I37: 2400 | J37: 0 | K37: 4 | L37: =I37/K37 -> 600 | M37: 45783 | N37: 45779 | P37: PASS | R37: 45744 | S37: 无 | T37: 产品贴纸(ZURU FRANCE 地址)翻单#4500136411+客版WEEE声明通用8L说明书(带电池，翻4500155594), EAN 条码：4894680042520 | U37: MA | X37: 日期码格式：ZURU INC(BVI) 标准格式 日期：按实际生产日期 | Y37: 日期码格式：ZURU INC(BVI) 标准格式 日期：按实际生产日期 Packaging Info: 9561:最新MA 5L(6L warning) EAN 收缩膜+MA 6L Guide book+产品贴纸(ZURU FRANCE 地址)+客版WEEE声明通用8L说明书(带电池，翻4500155594)+说明书法语贴纸 （翻4500160446）,EAN 条码：4894680042520 请核对条码后再做货 Remark: 1. 此单出德国，需要满足Zuru Standard欧洲标准测试要求； 2. 请准时出货，推期会有罚款； 3. 出口欧洲，微塑料需符合法规； 4. 所有电子产品身上需要加字唛，为ZURU FRANCE 地址 (如无电子产品，产品布标有此地址，或产品太小无法增加可忽略此信息) ZURU France 1/3, Rue d'Argenteuil 95210 SAINT-GRATIEN, FRANCE 5. 所有出往德国订单的电子产品需增加一张客版WEEE声明说明书，区分带电池和不带电池版本, 如已做客版说明书可忽略此要求。 6. 所有出往德国订单，化学品需无堋无香版本。 7. 标准配比 | Z37: Shirley Zhou | AA37: 5.1219 | AB37: =I37*AA37 -> 12292.56 | AD37: 9561-S001-5L | AE37: 已入 | AJ37: =I37 -> 2400 | AL37: =I37 -> 2400 | AP37: =I37 -> 2400 | AU37: =I37 -> 2400 | AV37: =AV36+AU37 -> 45454
A38: 45737 | B38: KMART AUSTRALIA LTD(NEW ZEALAND) | C38: 新西兰 | D38: 4500161020 | E38: 20722717 | F38: 4500161020-10 | G38: 9561-S001 | H38: 魔法小鸟 | I38: 48 | J38: 0 | K38: 4 | L38: =I38/K38 -> 12 | M38: 45783 | N38: 45779 | P38: PASS | R38: 45748 | S38: 有 | T38: 1张包装纽扣电池警告语贴纸 + 1张说明书纽扣电池警告语 贴纸 （贴纸及位置图翻单: PO#4500157612）+ 1张防盗贴纸 (贴纸以及位置图翻单PO#4500159287） | U38: MA | X38: 日期码格式：ZURU INC(BVI) 标准格式 日期：按实际生产日期 | Y38: 日期码格式：ZURU INC(BVI) 标准格式 日期：按实际生产日期 Packaging Info: 9561: MA英语UPC版本包装（收缩膜和说明书, MA首选1L，如无1L可用多语且含英语的配套多语包装) + 1张包装纽扣电池警告语贴纸 + 1张说明书纽扣电池警告语 贴纸 （贴纸及位置图翻单: PO#4500157612）+ 1张防盗贴纸 (贴纸以及位置图翻单PO#4500159287）+ 箱唛 + 外箱SSCC Label 配比信息：3pcs mini turtles: 4pcs mini tutles: 5pcs mini turtles= 87:10:3 Remark: 1.请务必按时完货，验货。并且按期送货入货代指定仓库，如果晚了导致船期Delay将会有罚金产生或者客户要求空运，所产生的罚金和空运费由工厂承担。 2.SSCC 外箱贴纸请同纸箱瓦楞纸方向（竖纹向）垂直，即外箱贴纸横着贴(注意条码不要被胶带粘住），贴1pc，贴1面正唛，封箱胶纸不能挡住贴纸内容。外箱贴纸 离外箱边距离不少于2cm。 3.外箱材质为ZURU标准； 4.此单需使用KMART封箱胶上下工字型封箱;从2019年6月开始，要用KMART 新版封箱胶带，此单要用"ANKO"封箱胶带 5.此单出口新西兰，请按相应的澳新标准生产； 6.产品和包装上生产批号的显示格式ZURU标准日期码格式 7.外箱信息不可手写，重量和体积需要与实际的一致(不可手写） 8. 每款item装箱后的G.W.超过10KG或者CBM超过0.13,(9.5KG或者以上，四舍五入后也属于10KG) 需在外箱上加印超 重或者Bulky LOGO，若发现我们资料没有，请 帮忙提醒 1)重量超过10kg但不超过16kg且CBM不超过0.13,10-16kg 超重logo 2）CBM超过0.13且重量少于17kg，bulky logo 3）不属于以上两种情况，需要使用相应重量范围内的超重logo 4）超重logo需要在外箱四面都印刷(箱唛右上角，两面侧唛超重logo需要尽量靠近毛重)，尺寸为:110mm height* 95mm width 9. 实际外箱重量跟印在箱唛上的数据差异不能超3%，尺寸按实际数据印刷 | Z38: Lydia Wu | AA38: 5.837 | AB38: =I38*AA38 -> 280.176 | AC38: 94954-5.9 | AD38: 9561-S001 | AE38: 已入 | AF38: =I38 -> 48 | AL38: =I38 -> 48 | AP38: =I38 -> 48 | AU38: =I38 -> 48 | AV38: =AV37+AU38 -> 45502
A39: 45737 | B39: KMART AUSTRALIA LTD | C39: 澳大利亚 | D39: 4500161007 | E39: 20722716 | F39: 4500161007-10 | G39: 9561-S001 | H39: 魔法小鸟 | I39: 1452 | J39: 0 | K39: 4 | L39: =I39/K39 -> 363 | M39: 45783 | N39: 45779 | P39: PASS | R39: 45748 | S39: 有 | T39: 1张包装纽扣电池警告语贴纸 + 1张说明书纽扣电池警告语 贴纸 （贴纸及位置图翻单: PO#4500157612）+ 1张防盗贴纸 (贴纸以及位置图翻单PO#4500159287）+ 箱唛 + 外箱SSCC Label | U39: MA | X39: 日期码格式：ZURU INC(BVI) 标准格式 日期：按实际生产日期 | Y39: 日期码格式：ZURU INC(BVI) 标准格式 日期：按实际生产日期 Packaging Info: 9561: MA英语UPC版本包装（收缩膜和说明书, MA首选1L，如无1L可用多语且含英语的配套多语包装) + 1张包装纽扣电池警告语贴纸 + 1张说明书纽扣电池警告语 贴纸 （贴纸及位置图翻单: PO#4500157612）+ 1张防盗贴纸 (贴纸以及位置图翻单PO#4500159287）+ 箱唛 + 外箱SSCC Label 配比信息：3pcs mini turtles: 4pcs mini tutles: 5pcs mini turtles= 87:10:3 Remark: 1.请务必按时完货，验货。并且按期送货入货代指定仓库，如果晚了导致船期Delay将会有罚金产生或者客户要求空运，所产生的罚金和空运费由工厂承担。 2.SSCC 外箱贴纸请同纸箱瓦楞纸方向（竖纹向）垂直，即外箱贴纸横着贴(注意条码不要被胶带粘住），贴1pc，贴1面正唛，封箱胶纸不能挡住贴纸内容。外箱贴纸 离外箱边距离不少于2cm。 3.外箱材质为ZURU标准； 4.此单需使用KMART封箱胶上下工字型封箱;从2019年6月开始，要用KMART 新版封箱胶带，此单要用"ANKO"封箱胶带 5.此单出口澳大利亚，请按相应的澳新标准生产； 6.产品和包装上生产批号的显示格式ZURU标准日期码格式 7.外箱信息不可手写，重量和体积需要与实际的一致(不可手写） 8. 每款item装箱后的G.W.超过10KG或者CBM超过0.13,(9.5KG或者以上，四舍五入后也属于10KG) 需在外箱上加印超 重或者Bulky LOGO，若发现我们资料没有，请 帮忙提醒 1)重量超过10kg但不超过16kg且CBM不超过0.13,10-16kg 超重logo 2）CBM超过0.13且重量少于17kg，bulky logo 3）不属于以上两种情况，需要使用相应重量范围内的超重logo 4）超重logo需要在外箱四面都印刷(箱唛右上角，两面侧唛超重logo需要尽量靠近毛重)，尺寸为:110mm height* 95mm width 9. 实际外箱重量跟印在箱唛上的数据差异不能超3%，尺寸按实际数据印刷 | Z39: Lydia Wu | AA39: 5.8209 | AB39: =I39*AA39 -> 8451.9468 | AC39: 94956-5.9 | AD39: 9561-S001 | AE39: 已入 | AF39: =I39 -> 1452 | AL39: =I39 -> 1452 | AP39: =I39 -> 1452 | AU39: =I39 -> 1452 | AV39: =AV38+AU39 -> 46954
A40: 45754 | B40: ZURU Denmark ApS | C40: 丹麦 | D40: 4500162346 | E40: 5200006527 | F40: 4500162346-40 | G40: 9561-S001-MTS | H40: 魔法小鸟 | I40: 1156 | J40: 0 | K40: 4 | L40: =I40/K40 -> 289 | M40: 45783 | N40: 45779 | P40: PASS | R40: 45763 | S40: 无 | T40: 1*多语折叠警告语贴纸（翻单4500157858）+ 北欧六语客版说明书(英语/丹麦/瑞典/芬兰/挪威/爱沙尼亚语言<(>,<)>翻单#450 0160993)+ 北欧六语客版guide book(英语/丹麦/瑞典/芬兰/挪威/爱沙尼亚语言, 翻单#4500160993) + 8L Slime袋子 + 北欧五语通用Slime黑白说明书 + 北欧五语通用带电池 出货黑白电池说明书+ZURU地址贴纸贴在鸟身上 | U40: MA | Y40: 日期码格式：ZURU INC(BVI) 标准格式 日期：按实际生产日期 Packaging Info: 9561: MA 5L+9L警语 EAN A版包装 +1*多语折叠警告语贴纸（翻单4500157858）+ 北欧六语客版说明书(英语/丹麦/瑞典/芬兰/挪威/爱沙尼亚语言<(>,<)>翻单#450 0160993)+ 北欧六语客版guide book(英语/丹麦/瑞典/芬兰/挪威/爱沙尼亚语言, 翻单#4500160993) + 8L Slime袋子 + 北欧五语通用Slime黑白说明书 + 北欧6语通用带电池 出货黑白电池说明书 Remark: 1.北欧内销单，需要通过ZURU 验货结果后才能出货 (工厂需要主动提前同ZURU QC预约验货避免延期出货造成不必要麻烦)； 2. 产品如含有化学品，需要无硼无香， 3.包装不能含有PVC，使用PET 4. date code: 外箱日期码要晚于产品日期码 5. 装柜时需要按照款式号码从小到大一款款依次装,避免终端仓库卸货混乱.若一个柜子涉及到几个不同国家内销单,装柜时需要一个国家装完后再装另一个国家的 产品,依次装柜,避免终端仓库因不同国家不同库位位置卸货混乱. (此点需要同工厂装柜人员强调)" 6.若有特定款有特殊外箱条码要求时,需要明确列出产品款对应的具体外箱条码号码/条码类型 (若无,可以忽略此需求) 7.所有出口欧洲的产品, 法规规定禁止在包装和共公众用的印刷品中使用矿物油中含有的物质, 包装印刷油墨中含有的MOAH/MOSH的质量浓度不能超过1%, 否则出货 到法国被抽检出现问题, 供应商需要对此负责; 8.带电池出货的产品所用到的电池需要符合欧洲电池新规(EU) 2023-1542。 9.ratio 同MA | Z40: SD04 | AA40: 5.4 | AB40: =I40*AA40 -> 6242.4 | AC40: 94941-5.7 | AD40: 9561-S001-芬兰 | AE40: 已入 | AJ40: =I40 -> 1156 | AN40: =I40 -> 1156 | AO40: =I40 -> 1156 | AP40: =I40 -> 1156 | AU40: =I40 -> 1156 | AV40: =AV39+AU40 -> 48110
A41: 45728 | B41: COOP Cooperative | C41: 瑞士 | D41: 4500159905 | E41: 7186490420 | F41: 4500159905-10 | G41: 9561-S001 | H41: 魔法小鸟 | I41: 264 | J41: 0 | K41: 4 | L41: =I41/K41 -> 66 | M41: 45783 | N41: 45779 | P41: PASS | R41: 45730 | S41: 无 | T41: 4/3WEEE说明书+客人价格贴纸 | U41: MA | X41: 日期码格式：ZURU INC(BVI) 标准格式 日期：按实际生产日期 | Y41: 日期码格式：ZURU INC(BVI) 标准格式 日期：按实际生产日期 Packaging Info: 9561: 最新MA 5L+6L EAN 收缩膜+ 最新MA 6L警语收藏指南+ WEEE说明书+客人价格贴纸 Remark: "1. 大货样品3套/item，用于第三方验货签办，请多备料。 2. 价格贴纸需使用可移动并无表面处理 3. EAN条码贴纸覆盖原先的条码；球的价格贴纸尽量贴平整避免起翘 4. 出口欧洲 微塑料需合规" | Z41: Joyce Chen | AA41: 5.4 | AB41: =I41*AA41 -> 1425.6 | AD41: 9561-S001-5L | AE41: 已入 | AJ41: =I41 -> 264 | AL41: =I41 -> 264 | AP41: =I41 -> 264 | AU41: =I41 -> 264 | AV41: =AV40+AU41 -> 48374
A42: 45723 | B42: B&M RETAIL LIMITED | C42: 英国 | D42: 4500159546 | E42: 客户PO:019236 28/1 | F42: 4500159546-20 | G42: 9561-S001 | H42: 魔法小鸟 | I42: 1252 | J42: 0 | K42: 4 | L42: =I42/K42 -> 313 | M42: 45783 | N42: 45779 | P42: PASS | R42: 45728 | S42: 无 | T42: 无 | U42: MA | X42: 日期码格式：ZURU INC(BVI) 标准格式 日期：按实际生产日期 | Y42: 日期码格式：ZURU INC(BVI) 标准格式 日期：按实际生产日期 Packaging Info: 标准配比 Remark: 订单对应2个PO，请分开做货，一个PO一个柜， 不要混装 *MA UPC版本按工厂现有最新库存即可，订单出英国，请注意检查产品及包装应带UKCA图标，包装显示ZURU UK LTD信息，QC同事请查核，如有问题与跟单确认。 *生产日期按实际（法定工作日），按ZURU标准格式即可 ，但是请知悉包装日期码需要早于或者等于外箱日期码 ，不能晚于外箱日期码 *请注意所有订单都需要经过ZURU QC验货并且通过后方可出货 *条码以订单显示为准 ，请安排生产前先核对 ，有问题请提出。 *所有产品按符合欧洲标准走货，需要是不含微塑料版本 。 *涉及到硼的，如可选择情况下应使用低硼版本 （slime 类别低硼一般低于300ppm)，无选择的应与跟单复核再安排 。 *大货完成后请及时提供shipment images 供客户批复 ，如未提供照片就直接走柜，有问题由工厂负责 。 *最终出货工厂需要按船务要求为集装箱挂网，如不按要求挂网导致罚款由工厂承担 。 | Z42: CORA ZHOU | AA42: 5.4 | AB42: =I42*AA42 -> 6760.8 | AD42: 9561-S001 | AE42: 已入 | AF42: =I42 -> 1252 | AL42: =I42 -> 1252 | AP42: =I42 -> 1252 | AU42: =I42 -> 1252 | AV42: =AV41+AU42 -> 49626
A43: 45723 | B43: B&M RETAIL LIMITED | C43: 英国 | D43: 4500159546 | E43: 客户PO:019236 30/1 | F43: 4500159546-40 | G43: 9561-S001 | H43: 魔法小鸟 | I43: 1252 | J43: 0 | K43: 4 | L43: =I43/K43 -> 313 | M43: 45783 | N43: 45779 | P43: PASS | R43: 45728 | S43: 无 | T43: 无 | U43: MA | X43: 日期码格式：ZURU INC(BVI) 标准格式 日期：按实际生产日期 | Y43: 日期码格式：ZURU INC(BVI) 标准格式 日期：按实际生产日期 Packaging Info: 标准配比 Remark: 订单对应2个PO，请分开做货，一个PO一个柜， 不要混装 *MA UPC版本按工厂现有最新库存即可，订单出英国，请注意检查产品及包装应带UKCA图标，包装显示ZURU UK LTD信息，QC同事请查核，如有问题与跟单确认。 *生产日期按实际（法定工作日），按ZURU标准格式即可 ，但是请知悉包装日期码需要早于或者等于外箱日期码 ，不能晚于外箱日期码 *请注意所有订单都需要经过ZURU QC验货并且通过后方可出货 *条码以订单显示为准 ，请安排生产前先核对 ，有问题请提出。 *所有产品按符合欧洲标准走货，需要是不含微塑料版本 。 *涉及到硼的，如可选择情况下应使用低硼版本 （slime 类别低硼一般低于300ppm)，无选择的应与跟单复核再安排 。 *大货完成后请及时提供shipment images 供客户批复 ，如未提供照片就直接走柜，有问题由工厂负责 。 *最终出货工厂需要按船务要求为集装箱挂网，如不按要求挂网导致罚款由工厂承担 。 | Z43: CORA ZHOU | AA43: 5.4 | AB43: =I43*AA43 -> 6760.8 | AD43: 9561-S001 | AE43: 已入 | AF43: =I43 -> 1252 | AL43: =I43 -> 1252 | AP43: =I43 -> 1252 | AU43: =I43 -> 1252 | AV43: =AV42+AU43 -> 50878
A44: 45705 | B44: Ambiental Paraguay | C44: 巴拉圭 | D44: 4500157158 | F44: 4500157158-60 | G44: 9561-S001 | H44: 魔法小鸟 | I44: 500 | J44: 0 | K44: 4 | L44: =I44/K44 -> 125 | M44: 45785 | N44: 45771 | P44: PASS | R44: 45736 | S44: 有 | T44: 进口商贴纸和UPC贴纸合并为一张 | U44: MA | Y44: 日期码格式：ZURU INC(BVI) 标准格式 日期：按实际生产日期 Packaging Info: 9561; MA 3L EAN包装+MA多语收藏指南+进口商贴纸+箱唛(进口商贴纸和UPC贴纸合并为一张） Remark: 9561：3PCS LR41 BATTERIES(INCLUDED) | Z44: Ava Liang | AA44: 5.4 | AB44: =I44*AA44 -> 2700 | AC44: 94962-5.10 | AD44: 9561-S001-5L | AE44: 已入 | AJ44: =I44 -> 500 | AL44: =I44 -> 500 | AP44: =I44 -> 500 | AU44: =I44 -> 500 | AV44: =AV43+AU44 -> 51378
A45: 45744 | B45: TARGET US | C45: 美国 | D45: 4500161830 | E45: 10001260966-3758 | F45: 4500161830-10 | G45: 9561-S001 | H45: 魔法小鸟 | I45: 940 | J45: 0 | K45: 4 | L45: =I45/K45 -> 235 | M45: 45786 | N45: 45782 | P45: PASS | R45: 45748 | S45: 有 | T45: 4/16收缩膜上的UPC显示193052078902+外箱正唛左上角位置粘贴条码箱贴纸，每箱只贴一张，由ZURU订购。来料贴纸上显示的客户DPCI#086-08-0267, UPC显示10193052078909; | U45: MA | Y45: 日期码格式：ZURU INC(BVI) 标准格式 日期：按实际生产日期 Packaging Info: 产品包装MA 收缩膜(UPC版) Remark: 1.9561-S001-PETS ALIVE-MAGIC BIRD-SERIES 1-MAGIC BIRD SURPRISE PLAYSET-SHRINK WRAP-4PCS/CTN 2. 产品包装MA 收缩膜(UPC版)，收缩膜上的UPC显示193052078902； 3. 外箱正唛左上角位置粘贴条码箱贴纸，每箱只贴一张，由ZURU订购。来料贴纸上显示的客户DPCI#086-08-0267, UPC显示10193052078909; 4.产品和包装上印刷 tracking code信息，格式为ZURU常规格式; 5. 出货方式：货代自提 | Z45: Holly Zheng | AA45: 5.1379 | AB45: =I45*AA45 -> 4829.626 | AC45: ZB00351-5.28 | AD45: 9561-S001 | AE45: 已入 | AF45: =I45 -> 940 | AL45: =I45 -> 940 | AP45: =I45 -> 940 | AU45: =I45 -> 940 | AV45: =AV44+AU45 -> 52318
A46: 45771 | D46: ZMPO250340 | G46: 9561-S001 | H46: 魔法小鸟 | I46: 100 | J46: 0 | K46: 4 | L46: =I46/K46 -> 25 | M46: 45787 | N46: 45783 | P46: PASS | R46: 空白外箱 | S46: 无 | T46: 无 | U46: MA | Y46: Remark:大货最新版本/大货标准箱装箱/箱唛参照邮件附件;备注： 收到样品订单后尽快安排 /注意样板品质质量要求要高于大货品质质量 ，送货时必须要附带送货单(没有送货单和QC检验合格报告的仓库一律拒绝收货)，请知悉，谢谢！ | Z46: Angus | AD46: 9561-S001 | AE46: 已入 | AF46: =I46 -> 100 | AP46: =I46 -> 100 | AU46: =I46 -> 100 | AV46: =AV45+AU46 -> 52418
A47: 45744 | B47: AB Gee of Ripley Ltd. | C47: 英国 | D47: 4500161792 | E47: 777 1MAY25 | F47: 4500161792-60 | G47: 9561-S001 | H47: 魔法小鸟 | I47: 500 | J47: 0 | K47: 4 | L47: =I47/K47 -> 125 | M47: 45789 | N47: 45785 | P47: PASS | R47: 45761 | S47: 无 | T47: 无 | U47: MA | Y47: 日期码格式：ZURU INC(BVI) 标准格式 日期：按实际生产日期 Packaging Info: MA 最新UPC包装，各款的条码如下，请先检查条码是否正确再安排做货，如有问题请告知 9561-S001:193052078902 配比跟MA Remark: 1.产品及包装需要印UKCA图标，包装需要有ZURU UK LTD/ZURU France地址信息，QC同事请核查，如有问题与跟单确认。 2. 需要符合欧洲标准不能含有闪粉和微塑料，否则不和法规会有客诉产生 | Z47: Yoga Huang | AA47: 5.3566 | AB47: =I47*AA47 -> 2678.3 | AD47: 9561-S001 | AE47: 已入 | AF47: =I47 -> 500 | AL47: =I47 -> 500 | AP47: =I47 -> 500 | AU47: =I47 -> 500 | AV47: =AV46+AU47 -> 52918
A48: 45748 | B48: T. PLANET SHOPS SL | C48: 西班牙 | D48: 4500162134 | F48: 4500162134-10 | G48: 9561-S001 | H48: 魔法小鸟 | I48: 1000 | J48: 0 | K48: 4 | L48: =I48/K48 -> 250 | M48: 45789 | N48: 45785 | P48: PASS | R48: 45764 | S48: 无 | T48: 4/22进口商贴纸+产品贴纸 | U48: MA | X48: 日期码格式：20250202 | Y48: 日期码格式：20250202 日期： Packaging Info: 9561:MA5L收缩膜+进口商贴纸+产品贴纸+MA B 5L收藏指南+MA 最新8L Slime bag Remark: 1, 此货出西班牙，需满足EU测试标准要求<(>&<)> 微塑料需符合法规。另外请确保所有包装都有西班牙环保标。 2，出货前两周需寄2-3套大货样品，请多备料 3, 此客人推期有罚款，请按时完货 4, 出货前要验货图片给客人确认OK后才出货 另外，15701 <(>&<)> 15727 <(>&<)> 15726 按MA配比 6. 其他款，若产品有比例使用ZURU STD 比例 8. 客户指定日期码码20250202，包装/产品/外箱需保持一致 | Z48: Mary Zhong | AA48: 5.3566 | AB48: =I48*AA48 -> 5356.6 | AD48: 9561-S001-5L | AE48: 已入 | AJ48: =I48 -> 1000 | AL48: =I48 -> 1000 | AP48: =I48 -> 1000 | AU48: =I48 -> 1000 | AV48: =AV47+AU48 -> 53918
A49: 45775 | D49: ZMPO250350 | G49: 9561-S001 | H49: 魔法小鸟 | I49: 150 | J49: 0 | K49: 4 | L49: =I49/K49 -> 37.5 | M49: 45789 | N49: =M49-4 -> 45785 | P49: PASS | R49: 空白外箱 | S49: 无 | T49: 无 | U49: MA | Y49: 大货最新版本/大货标准箱装箱/箱唛参照邮件附件 备注：收到样品订单后尽快安排 ，注意样板品质质量要求要高于大货品质要求 ，送货时必须要附带送货单(没有送货单和QC检验合格报告的仓库一律拒绝收货)，请知悉，谢谢！ | Z49: Angus | AD49: 9561-S001-5L | AE49: 已入 | AJ49: =I49 -> 150 | AL49: =I49 -> 150 | AP49: =I49 -> 150 | AU49: =I49 -> 150 | AV49: =AV48+AU49 -> 54068
A50: 45741 | B50: ZURU Germany GMBH | C50: 德国 | D50: 4500161394 | E50: 5200006461 | F50: 4500161394-10 | G50: 9561-S004-MTS | H50: 魔法小鸟 | I50: 1200 | J50: 0 | K50: 2 | L50: =I50/K50 -> 600 | M50: 45790 | N50: 45786 | P50: PASS | R50: 45742 | S50: 无 | T50: 多语折叠语警告贴纸+WEEE通用黑白书纸 | U50: MA | X50: 日期码格式：ZURU INC(BVI) 标准格式 日期：按实际生产日期 | Y50: 日期码格式：ZURU INC(BVI) 标准格式 日期：按实际生产日期 Packaging Info: MA最新版5L EAN收缩膜+多语折叠语警告贴纸+MA最新版5L收藏指南+MA最新版6L说明书+WEEE通用黑白书纸 Remark: 1.德国内销单，需要通过ZURU 验货结果后才能出货 (工厂需要主动提前同ZURU QC预约验货避免延期出货造成不必要麻烦)； 2. 若有特定款有特殊外箱条码要求时,需要明确列出产品款对应的具体外箱条码号码/条码类型 (若无,可以忽略此需求) 3.所有出口欧洲的产品, 法规规定禁止在包装和共公众用的印刷品中使用矿物油中含有的物质, 包装印刷油墨中含有的MOAH/MOSH的质量浓度不能超过1%, 否则出货 到法国被抽检出现问题, 供应商需要对此负责; 4. date code: 外箱日期码要晚于或等于产品日期码，不能早于产品的日期码 5. 所有电子产品身上需要加字唛，为ZURU FRANCE 地址 (如无电子产品，或者产品布标有此地址，可忽略此信息) ZURU France 1/3, Rue d'Argenteuil 95210 SAINT-GRATIEN, FRANCE 6. 装柜时需要按照款式号码从小到大一款款依次装,避免终端仓库卸货混乱.若一个柜子涉及到几个不同国家内销单,装柜时需要一个国家装完后再装另一个国家的 产品,依次装柜,避免终端仓库因不同国家不同库位位置卸货混乱. (此点需要同工厂装柜人员强调)" | Z50: SD04 | AA50: 5.3566 | AB50: =I50*AA50 -> 6427.92 | AD50: 9561-S004-1 | AE50: 已入 | AJ50: =I50 -> 1200 | AL50: =I50 -> 1200 | AP50: =I50 -> 1200 | AU50: =I50 -> 1200 | AV50: =AV49+AU50 -> 55268
A51: 45747 | B51: MEIJER DISTRIBUTION, INC. | C51: 美国 | D51: 4500161445 | E51: 216951853 | F51: 4500161445-10 | G51: 9561-S004 | H51: 魔法小鸟 | I51: 400 | J51: 0 | K51: 2 | L51: =I51/K51 -> 200 | M51: 45790 | N51: 45786 | P51: PASS | R51: 45757 | S51: 无 | T51: 无 | U51: MA | Y51: 日期码格式：ZURU INC(BVI) 标准格式 日期： Packaging Info: 1. MA 1L 包装 2. 客人指定箱唛排版 Remark: 出货前 Zuru QC 验货 | Z51: Cherie Li | AA51: 5.837 | AB51: =I51*AA51 -> 2334.8 | AC51: ZB00300-5.22 | AD51: 9561-S004 | AE51: 已入 | AF51: =I51 -> 400 | AL51: =I51 -> 400 | AP51: =I51 -> 400 | AU51: =I51 -> 400 | AV51: =AV50+AU51 -> 55668
A52: 45747 | B52: MEIJER DISTRIBUTION, INC. | C52: 美国 | D52: 4500161496 | E52: 216951858 | F52: 4500161496-10 | G52: 9561-S004 | H52: 魔法小鸟 | I52: 214 | J52: 0 | K52: 2 | L52: =I52/K52 -> 107 | M52: 45790 | N52: 45786 | P52: PASS | R52: 45757 | S52: 无 | T52: 无 | U52: MA | Y52: 日期码格式：ZURU INC(BVI) 标准格式 日期： Packaging Info: 1. MA 1L 包装 2. 客人指定箱唛排版 Remark: 出货前 Zuru QC 验货 | Z52: Cherie Li | AA52: 5.3727 | AB52: =I52*AA52 -> 1149.7578 | AD52: 9561-S004 | AE52: 已入 | AF52: =I52 -> 214 | AL52: =I52 -> 214 | AP52: =I52 -> 214 | AU52: =I52 -> 214 | AV52: =AV51+AU52 -> 55882
A53: 45750 | B53: ESAL ENTERPRISES FZC | C53: 卡塔尔 | D53: 4500162472 | E53: QATAR | F53: 4500162472-10 | G53: 9561-S001 | H53: 魔法小鸟 | I53: 480 | J53: 0 | K53: 4 | L53: =I53/K53 -> 120 | M53: 45792 | N53: 45789 | P53: PASS | R53: 45763 | S53: 无 | T53: 4/28贴纸 | U53: MA | Y53: 日期码格式：ZURU INC(BVI) 标准格式 日期：按实际生产日期 Packaging Info: 9561:MA+进口商贴纸+说明书（加贴纸） Remark: | Z53: Lena Huang | AA53: 5.1541 | AB53: =I53*AA53 -> 2473.968 | AD53: 9561-S001 | AE53: 已入 | AF53: =I53 -> 480 | AL53: =I53 -> 480 | AP53: =I53 -> 480 | AU53: =I53 -> 480 | AV53: =AV52+AU53 -> 56362
A54: 45750 | B54: ESAL TRADING L.L.C. | C54: 阿拉伯联合酋长国 | D54: 4500162345 | F54: 4500162345-20 | G54: 9561-S001 | H54: 魔法小鸟 | I54: 1600 | J54: 0 | K54: 4 | L54: =I54/K54 -> 400 | M54: 45792 | N54: 45789 | P54: PASS | R54: 45763 | S54: 无 | T54: 4/28贴纸 | U54: MA | Y54: 日期码格式：ZURU INC(BVI) 标准格式 日期：按实际生产日期 Packaging Info: 9561:MA+进口商贴纸+说明书（加贴纸） Remark: | Z54: Lena Huang | AA54: 5.3566 | AB54: =I54*AA54 -> 8570.56 | AD54: 9561-S001 | AE54: 已入 | AF54: =I54 -> 1600 | AL54: =I54 -> 1600 | AP54: =I54 -> 1600 | AU54: =I54 -> 1600 | AV54: =AV53+AU54 -> 57962
A55: 45750 | B55: ESAL ENTERPRISES FZC | C55: 沙特阿拉伯 | D55: 4500162474 | E55: KSA | F55: 4500162474-60 | G55: 9561PLB-S001 | H55: 魔法小鸟 | I55: 480 | J55: 0 | K55: 4 | L55: =I55/K55 -> 120 | M55: 45842 | N55: =M55-4 -> 45838 | P55: PASS | R55: 45763 | S55: 无 | T55: 4/28贴纸 | U55: MA | Y55: 日期码格式：ZURU INC(BVI) 标准格式 日期：按实际生产日期 Packaging Info: 9548：1L MA包装（含G Mark)+进口商贴纸翻4500128286(含QR code, 阿拉伯警语); 贴纸上的QR code需微信可扫，扫描结果为64431； MA说明书 9561:MA+进口商贴纸+说明书（加贴纸） 9543GQ1：MA+进口商贴纸；PDQ+进口商贴纸 71152：MA+进口商贴纸+说明书（加贴纸） 77673TQ1：MA PDQ+彩色贴纸+进口商贴纸；MA收藏指南+彩色贴纸；收缩膜+进口商贴纸；MA说明书+一张客制黑白说明书纸 1. 9561PLB：9561-S001 4pcs/CTN (Carton Size: 39.2x39.2x34.2CM); 6*5H=30CTN=30*4pcs=120pcs/pallet; 9561（共120箱）:每层6箱，装5层。装4个pallet。 2. 9548PLB：9548-S001 4pcs/CTN (Carton Size: 57.7x38.5x32.2CM); 5*6H=30CTN=30*4pcs=120pcs/pallet；9548（共36箱）:每层5箱，装6层。装1个pallet 装3 0箱，剩36-30=6箱。 3. MPLB11：9548-S001 4pcs/CTN (Carton Size: 57.7x38.5x32.2CM); 9543GQ1-S001 22PCS/2PDQ/CTN (Carton Size: 48.4x36.6x27.2CM); 6*4H=24-2=22CTN+6CTN (9548)，total 508pcs/pallet；9548-S001 4*6CTN=24pcs, 9543GQ1-S001 22*22CTN=484pcs; 9543GQ1（22箱）:每层6箱，装4层。装1个pallet，最上面1层少装2箱，其余空间装6箱9548-S001。 4. 71152PLB：71152-S001 6PCS/CTN (Carton Size: 31.7x29.2x43.3CM); 8*5H=40CTN=40*6pcs=240pcs/pallet； 71152（80箱）：每层8箱，装5层。装2个pallet。 5. 77673PLB：77673TQ1-S002 16PCS/4PDQ/CTN(SIZE:41.7*26.8*40.1CM)8*4H-2=30CTN=480PCS； 77673TQ1（30箱）：每层8箱，装4层。装1个pallet，最上面一层少放2箱。 6. 77803PLB：77803GQ2-S001-PRODCC-INT 50PCS/2PDQ/CTN(SIZE:42.6*33*41CM)8*4H-3=29CTN=1450PCS； 77803GQ2-S001（29箱）：每层8箱，装4层，装1个pallet ，最上面1层少装3箱。 7. 77803PLD：77803SK1-S002-PRODCC-INT 30PCS/SIDEKICK/CTN(SIZE:14.5*33.5*112.5CM)22*1H+6*2H+1=35CTN=1050PCS； 77803SK1-S002（35箱）：总高度（1290+670+145=2105mm）装1个pallet，竖放22箱+横放12箱，最上层再平放1箱 Remark: 9548:1 assorment,3pcs AAA batteries(not included) | Z55: Lena Huang | AA55: 5.3727 | AB55: =I55*AA55 -> 2578.896 | AC55: 96584-9.30 | AD55: 9561-S001 | AE55: 已入 | AF55: =I55 -> 480 | AL55: =I55 -> 480 | AP55: =I55 -> 480 | AU55: =I55 -> 480 | AV55: =AV54+AU55 -> 58442
A56: 45755 | B56: CANDIDE IND E COM LTDA | C56: 巴西 | D56: 4500162877 | E56: BR25882 | F56: 4500162877-20 | G56: 9561-S001 | H56: 魔法小鸟 | I56: 2500 | J56: 0 | K56: 4 | L56: =I56/K56 -> 625 | M56: 45792 | N56: 45789 | P56: PASS | R56: 45770 | S56: 无 | T56: 4/24进口商贴纸（进口商贴纸和客户条码贴纸合并为一张）+客版葡萄语说明书 | U56: MA | Y56: 日期码格式：ZURU INC(BVI) 标准格式 日期：按实际生产日期 Packaging Info: 9561:MA 5L EAN包装+进口商贴纸（进口商贴纸和客户条码贴纸合并为一张）+客版葡萄语说明书+箱唛 Remark: 外箱胶带要用CANDIDE格式 | Z56: Ava Liang | AA56: 5.1219 | AB56: =I56*AA56 -> 12804.75 | AD56: 9561-S001-5L-1 | AE56: 已入 | AJ56: =I56 -> 2500 | AN56: =I56 -> 2500 | AO56: =I56 -> 2500 | AP56: =I56 -> 2500 | AU56: =I56 -> 2500 | AV56: =AV55+AU56 -> 60942
A57: 45742 | B57: TAS IMPORT AS(Lekekassen) | C57: 挪威 | D57: 4500160993 | E57: 11098 | F57: 4500160993-20 | G57: 9561-S001 | H57: 魔法小鸟 | I57: 480 | J57: 0 | K57: 4 | L57: =I57/K57 -> 120 | M57: 45793 | N57: 45789 | P57: PASS | R57: 45759 | S57: 无 | T57: 4/16挪威/瑞典/丹麦语警告语/客人进口商地址贴纸做成一张贴纸 | U57: MA | X57: 日期码格式：ZURU INC(BVI) 标准格式 日期：按实际生产日期 | Y57: 日期码格式：ZURU INC(BVI) 标准格式 日期：按实际生产日期 Packaging Info: 2. 9561: MA 5L-6L EAN版收缩膜+挪威/瑞典/丹麦语警告语/客人进口商地址贴纸做成一张贴纸+北欧六语客版说明书(英语/丹麦/瑞典/芬兰/挪威/爱沙尼亚语言)+ 北欧六语客版guide book(英语/丹麦/瑞典/芬兰/挪威/爱沙尼亚语言) 4. 配比跟MA Remark: 1. 包装如含PVC,请改为PET并第一时间通知跟单 2. 产品/包装要求无硼无香，出欧洲，微塑料需合规。 3.带电池出货的产品所用到的电池需要符合欧洲电池新规(EU) 2023-1542 4.有胶袋的产品：要求产品的胶袋厚度要大于等于0.05mm 5.关于贴纸，如果贴纸位置图的包装版本与大货不一致，请工厂第一时间提前提出。跟单会重新调整确认是否更新贴纸或调整位置图 6.产品/包装不含PFAS成分 7.产品条码如下: 请先检查条码是否正确再安排做货，如有问题请告知 ZURU ITEM#<(>&<)>EAN 9561:4894680042520 | Z57: Sheba | AA57: 5.3727 | AB57: =I57*AA57 -> 2578.896 | AD57: 9561-S001-芬兰 | AE57: 已入 | AJ57: =I57 -> 480 | AK57: =I57 -> 480 | AN57: =I57 -> 480 | AO57: =I57 -> 480 | AP57: =I57 -> 480 | AQ57: =I57 -> 480 | AU57: =I57 -> 480 | AV57: =AV56+AU57 -> 61422
A58: 45763 | B58: ZURU Germany GMBH | C58: 德国 | D58: 4500163539 | E58: 5200006607 | F58: 4500163539-10 | G58: 9561-S004-MTS | H58: 魔法小鸟 | I58: 1540 | J58: 0 | K58: 2 | L58: =I58/K58 -> 770 | M58: 45793 | N58: 45789 | P58: PASS | R58: 45763 | S58: 无 | T58: 1张多语可折叠警告语贴纸+1*BG 名字贴纸+ZURU地址贴纸贴在鸟身上 | U58: MA | Y58: 日期码格式：ZURU INC(BVI) 标准格式 日期：按实际生产日期 Packaging Info: 1.9561:MA 5L+6L EAN收缩膜+1张多语可折叠警告语贴纸+1*BG 名字贴纸 +其它MA包装; Remark: 1.波兰内销单，需要通过ZURU 验货结果后才能出货 (工厂需要主动提前同ZURU QC预约验货避免延期出货造成不必要麻烦)； 2. 若有特定款有特殊外箱条码要求时,需要明确列出产品款对应的具体外箱条码号码/条码类型 (若无,可以忽略此需求) 3.所有出口欧洲的产品, 法规规定禁止在包装和共公众用的印刷品中使用矿物油中含有的物质, 包装印刷油墨中含有的MOAH/MOSH的质量浓度不能超过1%, 否则出货 到法国被抽检出现问题, 供应商需要对此负责; 4. date code: 外箱日期码要晚于或等于产品日期码，不能早于产品的日期码 5. 所有电子产品身上需要加字唛，为ZURU FRANCE 地址 (如无电子产品，或者产品布标有此地址，可忽略此信息) ZURU France 1/3, Rue d'Argenteuil 95210 SAINT-GRATIEN, FRANCE 6. 装柜时需要按照款式号码从小到大一款款依次装,避免终端仓库卸货混乱.若一个柜子涉及到几个不同国家内销单,装柜时需要一个国家装完后再装另一个国家的 产品,依次装柜,避免终端仓库因不同国家不同库位位置卸货混乱. (此点需要同工厂装柜人员强调) | Z58: SD04 | AA58: 5.3566 | AB58: =I58*AA58 -> 8249.164 | AD58: 9561-S004-1 | AE58: 已入 | AJ58: =I58 -> 1540 | AL58: =I58 -> 1540 | AP58: =I58 -> 1540 | AU58: =I58 -> 1540 | AV58: =AV57+AU58 -> 62962
A59: 45741 | B59: TOYS "R" US (CANADA) LTD. | C59: 加拿大 | D59: 4500161332 | E59: 3501527773 | F59: 4500161332-20 | G59: 9561-S001 | H59: 魔法小鸟 | I59: 1200 | J59: 0 | K59: 4 | L59: =I59/K59 -> 300 | M59: 45796 | N59: 45792 | P59: PASS | R59: 45761 | S59: 无 | T59: 4/24UPC 贴纸，UPC#193052078902 | U59: MA | X59: 日期码格式：ZURU INC(BVI) 标准格式 日期：按实际生产日期 | Y59: 日期码格式：ZURU INC(BVI) 标准格式 日期：按实际生产日期 Packaging Info: 1. 出口加拿大市场，MA UPC版本包装。 #9561：MA 5L+6L EAN版本加UPC 贴纸，UPC#193052078902; 3PCS LR44 BATTERIES(INCLUDED);说明书需要增加贴纸 2. 产品、包装、外箱上面tracking code的时间格式需要一致 Remark: 3. 需要第三方SGS验货，验货时间2025/05/19，每款每色请备1PC完整带包装样品供验货人员参考。用完后若无损坏可以放回大货里。 | Z59: Abby Mai,Lluvia Zeng | AA59: 5.3566 | AB59: =I59*AA59 -> 6427.92 | AD59: 9561-S001-5L | AE59: 已入 | AJ59: =I59 -> 1200 | AL59: =I59 -> 1200 | AP59: =I59 -> 1200 | AU59: =I59 -> 1200 | AV59: =AV58+AU59 -> 64162
A60: 45723 | B60: Amazon ES | C60: 西班牙 | D60: 4500159392 | E60: Amazon ES: 84MVCGXJ | F60: 4500159392-10 | G60: 9561-S003-MB | H60: 魔法小鸟 （邮包盒装） | I60: 538 | J60: 0 | K60: 2 | L60: =I60/K60 -> 269 | M60: 45799 | N60: 45796 | P60: PASS | R60: 空白外箱 | S60: 有 | T60: 客版邮包盒(UPC#+英法德意西5L警示语+FR/ES/IT环保标+ZURU邮箱care@zuru.co m) | U60: MA | W60: 客版邮包盒(UPC#+英法德意西5L警示语+FR/ES/IT环保标+ZURU邮箱care@zuru.co m) | X60: 日期码格式：ZURU INC(BVI) 标准格式 日期：按实际生产日期 | Y60: 日期码格式：ZURU INC(BVI) 标准格式 日期：按实际生产日期 Packaging Info: Amazon ES(9561) 1. 9561：MAIL BOX WITH PRODUCT PACKAGE, 1PCS/MAIL BOX,2PCS/2MAIL BOX/CTN; 客版邮包盒(UPC#+英法德意西5L警示语+FR/ES/IT环保标+ZURU邮箱care@zuru.co m)+MA 1L(1L warning)收缩膜+MA 6L warning 收藏指南+其他最新MA配套包装； 2. 最迟验货不得晚于2025/5/23; Remark: 1.空白外箱（加印带Zuru字样的最新logo，除了邮包盒直接做外箱的产品） + SSCC LABEL一张, 无箱唛，MADE IN CHINA 外箱只印一正一侧。箱唛资料按照给定的 标准去做即可，无需发回我方再行审批(新标准将另行通知)。 (SSCC LABEL竖贴在外箱正面的正中间，贴一面即可,贴纸离外箱边距必须至少3.2CM。如竖贴无法满足要求，则横贴。如横贴也无法满足要求，则竖贴，遮到ZURU lo go无影响), SSCC贴纸由工厂直接跟勤得采购或者工厂自行采购，每一张SSCC Label都是唯一且有不同流水及条码，且需要检查条码是否能正常扫描，另外，此贴纸 印刷不可出现模糊，溢出及粘胶不牢易脱落等现象，如工厂不按此要求导致贴纸有任何问题产生的罚款将由工厂承担一切责任 。 2.出往UK的产品+包装务必打上UKCA logo ，否则客人会退货且当地会有罚款。 3.订单必须经过ZURU QC验货并且通过后方可出货。 4.法国订单要求包装不使用矿物油，请按要求提供以下其中一份文件再出货 ，产品出到法国被相关部门抽检出现包装不符合此要求的，供应商需要为此承担责任， 故此请严格把关。 -油墨物质""由1 ~ 7个芳香环组成的MOAH""的包装检测报告，要求限值≤1.0%； -包装材料清单，包括包装油墨或物质的信息； -油墨制造商的证书； 5.每一批次出货只能有一个生产日期，不可多个生产日期混在同一批次出货；且邮包盒上必须统一加上日期码；外箱对于日期码没有硬性规定； 6.涉及到相关款式会有闪粉的或者微塑料的，请统一默认出无闪粉或者不含微塑料版本； 7.邮包盒及外箱封箱必须是工字型封箱方式； 8.5 Surprise or Mini Brands涉及包装是2个及2个以上的球入PVC桶包装时，单个球上若有UPC#或者EAN#，请用白色贴纸覆盖住； | Z60: Mandy Hu | AA60: 5.7569 | AB60: =I60*AA60 -> 3097.2122 | AD60: 9561-S003-MB-MTS | AE60: 已入 | AF60: =I60 -> 538 | AL60: =I60 -> 538 | AP60: =I60 -> 538 | AU60: =I60 -> 538 | AV60: =AV59+AU60 -> 64700
A61: 45726 | B61: AMAZON UK | C61: 英国 | D61: 4500159549 | E61: Amazon UK: 31XGVX7Q | F61: 4500159549-30 | G61: 9561-S003-MB | H61: 魔法小鸟 （邮包盒装） | I61: 4000 | J61: 0 | K61: 2 | L61: =I61/K61 -> 2000 | M61: 45799 | N61: 45796 | P61: PASS | R61: 空白外箱 | S61: 有 | T61: 客版邮包盒(UPC#+英法德意西5L警示语+FR/ES/IT环保标+ZURU邮箱care@zuru.com） | U61: MA | W61: 客版邮包盒(UPC#+英法德意西5L警示语+FR/ES/IT环保标+ZURU邮箱care@zuru.co m，参考翻单4500159392) | X61: 日期码格式：ZURU INC(BVI) 标准格式 日期：按实际生产日期 | Y61: 日期码格式：ZURU INC(BVI) 标准格式 日期：按实际生产日期 Packaging Info: Amazon UK(71152, 9561)/DE(71152, 9561) 2. 9561：MAIL BOX WITH PRODUCT PACKAGE, 1PCS/MAIL BOX,2PCS/2MAIL BOX/CTN; 客版邮包盒(UPC#+英法德意西5L警示语+FR/ES/IT环保标+ZURU邮箱care@zuru.co m，参考翻单4500159392)+MA 1L(1L warning)收缩膜+MA 6L warning 收藏指南+其他最新MA配套包装； 3. 最迟验货不得晚于2025/5/23; Remark: 1.空白外箱（加印带Zuru字样的最新logo，除了邮包盒直接做外箱的产品） + SSCC LABEL一张, 无箱唛，MADE IN CHINA 外箱只印一正一侧。箱唛资料按照给定的 标准去做即可，无需发回我方再行审批(新标准将另行通知)。 (SSCC LABEL竖贴在外箱正面的正中间，贴一面即可,贴纸离外箱边距必须至少3.2CM。如竖贴无法满足要求，则横贴。如横贴也无法满足要求，则竖贴，遮到ZURU lo go无影响), SSCC贴纸由工厂直接跟勤得采购或者工厂自行采购，每一张SSCC Label都是唯一且有不同流水及条码，且需要检查条码是否能正常扫描，另外，此贴纸 印刷不可出现模糊，溢出及粘胶不牢易脱落等现象，如工厂不按此要求导致贴纸有任何问题产生的罚款将由工厂承担一切责任 。 2.出往UK的产品+包装务必打上UKCA logo ，否则客人会退货且当地会有罚款。 3.订单必须经过ZURU QC验货并且通过后方可出货。 4.法国订单要求包装不使用矿物油，请按要求提供以下其中一份文件再出货 ，产品出到法国被相关部门抽检出现包装不符合此要求的，供应商需要为此承担责任， 故此请严格把关。 -油墨物质""由1 ~ 7个芳香环组成的MOAH""的包装检测报告，要求限值≤1.0%； -包装材料清单，包括包装油墨或物质的信息； -油墨制造商的证书； 5.每一批次出货只能有一个生产日期，不可多个生产日期混在同一批次出货；且邮包盒上必须统一加上日期码；外箱对于日期码没有硬性规定； 6.涉及到相关款式会有闪粉的或者微塑料的，请统一默认出无闪粉或者不含微塑料版本； 7.邮包盒及外箱封箱必须是工字型封箱方式； 8.5 Surprise or Mini Brands涉及包装是2个及2个以上的球入PVC桶包装时，单个球上若有UPC#或者EAN#，请用白色贴纸覆盖住； | Z61: Crystal Chen | AA61: 5.7167 | AB61: =I61*AA61 -> 22866.8 | AD61: 9561-S003-MB-MTS | AE61: 已入 | AF61: =I61 -> 4000 | AL61: =I61 -> 4000 | AP61: =I61 -> 4000 | AU61: =I61 -> 4000 | AV61: =AV60+AU61 -> 68700
A62: 45726 | B62: AMAZON UK | C62: 德国 | D62: 4500159549 | E62: Amazon DE: 475LP6EN | F62: 4500159549-40 | G62: 9561-S003-MB | H62: 魔法小鸟 （邮包盒装） | I62: 1622 | J62: 0 | K62: 2 | L62: =I62/K62 -> 811 | M62: 45799 | N62: 45796 | P62: PASS | R62: 空白外箱 | S62: 有 | T62: 客版邮包盒(UPC#+英法德意西5L警示语+FR/ES/IT环保标+ZURU邮箱care@zuru.co m) | U62: MA | W62: 客版邮包盒(UPC#+英法德意西5L警示语+FR/ES/IT环保标+ZURU邮箱care@zuru.co m，参考翻单4500159392) | X62: 日期码格式：ZURU INC(BVI) 标准格式 日期：按实际生产日期 | Y62: 日期码格式：ZURU INC(BVI) 标准格式 日期：按实际生产日期 Packaging Info: Amazon UK(71152, 9561)/DE(71152, 9561) 2. 9561：MAIL BOX WITH PRODUCT PACKAGE, 1PCS/MAIL BOX,2PCS/2MAIL BOX/CTN; 客版邮包盒(UPC#+英法德意西5L警示语+FR/ES/IT环保标+ZURU邮箱care@zuru.co m，参考翻单4500159392)+MA 1L(1L warning)收缩膜+MA 6L warning 收藏指南+其他最新MA配套包装； 3. 最迟验货不得晚于2025/5/23; Remark: 1.空白外箱（加印带Zuru字样的最新logo，除了邮包盒直接做外箱的产品） + SSCC LABEL一张, 无箱唛，MADE IN CHINA 外箱只印一正一侧。箱唛资料按照给定的 标准去做即可，无需发回我方再行审批(新标准将另行通知)。 (SSCC LABEL竖贴在外箱正面的正中间，贴一面即可,贴纸离外箱边距必须至少3.2CM。如竖贴无法满足要求，则横贴。如横贴也无法满足要求，则竖贴，遮到ZURU lo go无影响), SSCC贴纸由工厂直接跟勤得采购或者工厂自行采购，每一张SSCC Label都是唯一且有不同流水及条码，且需要检查条码是否能正常扫描，另外，此贴纸 印刷不可出现模糊，溢出及粘胶不牢易脱落等现象，如工厂不按此要求导致贴纸有任何问题产生的罚款将由工厂承担一切责任 。 2.出往UK的产品+包装务必打上UKCA logo ，否则客人会退货且当地会有罚款。 3.订单必须经过ZURU QC验货并且通过后方可出货。 4.法国订单要求包装不使用矿物油，请按要求提供以下其中一份文件再出货 ，产品出到法国被相关部门抽检出现包装不符合此要求的，供应商需要为此承担责任， 故此请严格把关。 -油墨物质""由1 ~ 7个芳香环组成的MOAH""的包装检测报告，要求限值≤1.0%； -包装材料清单，包括包装油墨或物质的信息； -油墨制造商的证书； 5.每一批次出货只能有一个生产日期，不可多个生产日期混在同一批次出货；且邮包盒上必须统一加上日期码；外箱对于日期码没有硬性规定； 6.涉及到相关款式会有闪粉的或者微塑料的，请统一默认出无闪粉或者不含微塑料版本； 7.邮包盒及外箱封箱必须是工字型封箱方式； 8.5 Surprise or Mini Brands涉及包装是2个及2个以上的球入PVC桶包装时，单个球上若有UPC#或者EAN#，请用白色贴纸覆盖住； | Z62: Crystal Chen | AA62: 5.7167 | AB62: =I62*AA62 -> 9272.4874 | AD62: 9561-S003-MB-MTS | AE62: 已入 | AF62: =I62 -> 1622 | AL62: =I62 -> 1622 | AP62: =I62 -> 1622 | AU62: =I62 -> 1622 | AV62: =AV61+AU62 -> 70322
A63: 45750 | B63: ZURU France | C63: 法国 | D63: 4500162314 | E63: 5200006540 | F63: 4500162314-60 | G63: 9561-S001-MTS | H63: 魔法小鸟 | I63: 2068 | J63: 0 | K63: 4 | L63: =I63/K63 -> 517 | M63: 45799 | N63: =M63-3 -> 45796 | P63: PASS | R63: 45754 | S63: 无 | T63: 多语警语折叠贴纸（含包装缺失的法/意/西环保标） | U63: MA | X63: 日期码格式：ZURU INC(BVI) 标准格式 日期：按实际生产日期 | Y63: 日期码格式：ZURU INC(BVI) 标准格式 日期：按实际生产日期 Packaging Info: 9561: A版 5L EAN收缩膜+MA A版5L+6L说明书（带法国说明书警语贴纸）+A版5L收藏指南+多语警语折叠贴纸（含包装缺失的法/意/西环保标）+ 多语版WEEE电池垃 圾桶的回收声明说明书（ included）,, Remark: 1. 法国国家内销单，需要通过ZURU 验货结果后才能出货 (工厂需要主动提前同ZURU QC预约验货避免延期出货造成不必要麻烦)； 2. 本订单所有 具有 baby items / assorted items 的款式，零售包装上都要用 母 EAN; 3. 若有特定款有特殊外箱条码要求时,需要明确列出产品款对应的具体外箱条码号码/条码类型 (若无,可以忽略此需求) 4. 所有出口欧洲的产品, 法规规定禁止在包装和共公众用的印刷品中使用矿物油中含有的物质, 包装印刷油墨中含有的MOAH/MOSH的质量浓度不能超过1%, 否则出 货到法国被抽检出现问题, 供应商需要对此负责; 5. Date code: 外箱/产品/包装 保持一致，完货后提供date code 信息以便我们保存记录做批次管理; 6. 装柜时需要按照款式号码从小到大一款款依次装,避免终端仓库卸货混乱.若一个柜子涉及到几个不同国家内销单,装柜时需要一个国家装完后再装另一个国家的 产品,依次装柜,避免终端仓库因不同国家不同库位位置卸货混乱. (此点需要同工厂装柜人员强调) | Z63: Jade Wang | AA63: 5.4 | AB63: =I63*AA63 -> 11167.2 | AD63: 9561-S001-5L | AE63: 已入 | AJ63: =I63 -> 2068 | AL63: =I63 -> 2068 | AP63: =I63 -> 2068 | AU63: =I63 -> 2068 | AV63: =AV62+AU63 -> 72390
A64: 45722 | B64: BINGO GLOBAL GROUP FOR TRADING SUPP | C64: 埃及 | D64: 4500159286 | F64: 4500159286-30 | G64: 9561-S001 | H64: 魔法小鸟 | I64: 1000 | J64: 0 | K64: 4 | L64: =I64/K64 -> 250 | M64: 45800 | N64: 45796 | P64: PASS | R64: 45757 | S64: 无 | T64: 4/27进口商贴纸 | U64: MA | X64: 日期码格式：ZURU INC(BVI) 标准格式 日期：按实际生产日期 | Y64: 日期码格式：ZURU INC(BVI) 标准格式 日期：按实际生产日期 Packaging Info: 9561: MA 5L EAN 收缩膜+ 进口商贴纸 +MA收藏指南/说明书 Remark: | Z64: Lena Huang | AA64: 5.4 | AB64: =I64*AA64 -> 5400 | AD64: 9561-S001-5L | AE64: 已入 | AJ64: =I64 -> 1000 | AL64: =I64 -> 1000 | AP64: =I64 -> 1000 | AU64: =I64 -> 1000 | AV64: =AV63+AU64 -> 73390
A65: 45775 | B65: Bol.com | C65: 荷兰 | D65: 4500164929 | E65: P2505494 | F65: 4500164929-10 | G65: 9561-S003-MB | H65: 魔法小鸟 （邮包盒装） | I65: 2500 | J65: 0 | K65: 2 | L65: =I65/K65 -> 1250 | M65: 45800 | N65: =M65-4 -> 45796 | P65: PASS | R65: 45777 | S65: 无 | T65: 客版邮包盒(UPC#+英法德意西5L警示语+FR/ES/IT环保标+ZURU邮箱care@zuru.co m，参考翻单4500159392)+2张贴纸(1张EAN#，1张NL警告语)+WEEE电子产品说明书(带电池 走货版，参考翻单PO#4500159555)； | U65: MA | Y65: 日期码格式：ZURU INC(BVI) 标准格式 日期：按实际生产日期 Packaging Info: BOL NL(9561) 1. 9561：MAIL BOX WITH PRODUCT PACKAGE, 1PCS/MAIL BOX,2PCS/2MAIL BOX/CTN; 客版邮包盒(UPC#+英法德意西5L警示语+FR/ES/IT环保标+ZURU邮箱care@zuru.co m，参考翻单4500159392)+2张贴纸(1张EAN#，1张NL警告语)+MA 1L(1L warning)收缩膜+MA 6L warning 收藏指南+其他最新MA配套包装+WEEE电子产品说明书(带电池 走货版，参考翻单PO#4500159555)； 2. 最迟验货不得晚于2025/5/26; Remark: 1. 出欧洲产品不可含闪粉或者微塑料，若所涉产品无闪粉或不含微塑料可忽略此点； 2. 5 Surprise or Mini Brands涉及包装是2个及2个以上的球入PVC桶包装时，单个球上若有UPC#或者EAN#，请用白色贴纸覆盖住； 3. 箱唛资料按照提供的要求去做即可，无需再发回我方确认； 4.柜货产品务必拉网且要拉紧，拉网要求： A: 网要结实同时网格要细，纸箱不能从网格处跌落下来 B: 打网固定8-10个点。请提供拉网的装柜照片给船务确认 后柜子再离厂。 | Z65: Crystal Chen | AA65: 5.7408 | AB65: =I65*AA65 -> 14352 | AC65: 95192-6.4 | AD65: 9561-S003-MB-MTS | AE65: 已入 | AF65: =I65 -> 2500 | AL65: =I65 -> 2500 | AP65: =I65 -> 2500 | AU65: =I65 -> 2500 | AV65: =AV64+AU65 -> 75890
A66: 45749 | B66: COOP NORGE HANDEL AS - DOM | C66: 挪威 | D66: 4500162197 | E66: 32577893 | F66: 4500162197-10 | G66: 9561-S001 | H66: 魔法小鸟 | I66: 200 | J66: 0 | K66: 4 | L66: =I66/K66 -> 50 | M66: 45803 | N66: 45799 | P66: PASS | R66: 45785 | S66: 无 | T66: 4/30挪威语警语贴纸 | U66: MA | X66: 日期码格式：ZURU INC(BVI) 标准格式 日期：按实际生产日期 | Y66: 日期码格式：ZURU INC(BVI) 标准格式 日期：按实际生产日期 Packaging Info: 1.9561：MA_A EAN 5L+6L收缩膜+挪威语警语贴纸+客版说明书（翻单4500160993）+客版guide book(翻单4500160993) Remark: 1/产品和包装要求无硼无香，包装不能含有PVC； 2/如有微塑料，必须合规欧洲标准，闪粉也是微塑料的一种，目前仅接受三张方式1.去除，2.用可降解材料，和3.永久封印在固体； 3/此订单有第三方验货，请准备三套大货样并不迟于5-14寄出给ZURU 深圳办公室； 4/带电池出货的产品所用到的电池需要符合欧洲电池新规(EU)2023-1542； 5/工厂货号-客户货号彩盒条码-外箱条码 9561-7254588-4894680042520-10193052078909 6/配比: | Z66: Zoe Zhou | AA66: 5.1541 | AB66: =I66*AA66 -> 1030.82 | AD66: 9561-S001-芬兰 | AE66: 已入 | AJ66: =I66 -> 200 | AN66: =I66 -> 200 | AO66: =I66 -> 200 | AP66: =I66 -> 200 | AU66: =I66 -> 200 | AV66: =AV65+AU66 -> 76090
A67: 45765 | B67: Lekia AB | C67: 瑞典 | D67: 4500164226 | E67: 156653-2 | F67: 4500164226-20 | G67: 9561-S001 | H67: 魔法小鸟 | I67: 480 | J67: 0 | K67: 4 | L67: =I67/K67 -> 120 | M67: 45811 | N67: =M67-4 -> 45807 | P67: PASS | R67: 45769 | S67: 无 | T67: 警告语/进口商贴纸 | U67: MA | Y67: 日期码格式：ZURU INC(BVI) 标准格式 日期：按实际生产日期 Packaging Info: 9561-S001:MA 5L-6L EAN版收缩膜+北欧客版说明书(英语/丹麦/瑞典/芬兰/挪威/爱沙尼亚/德语/荷兰语语言)+北欧客版guide book(英语/丹麦/瑞典/芬兰/挪威/爱 沙尼亚/德语/荷兰语语言)--客版说明书和guide book翻TAS PO#4500160993+警告语/进口商贴纸 北欧五语通用Slime黑白说明书 带纽扣电池走货北欧六语通用黑白电池说明书 不带电池走货北欧六语通用黑白电池说明书 上述说明书翻单4500162375,之前已通知按照MA采购，不要重复订购 Remark: "1. 包装如含PVC,请改为PET 2. 产品/包装要求无硼无香； 3. 出欧洲，微塑料需合规。 4.带电池出货的产品所用到的电池需要符合欧洲电池新规(EU) 2023-1542 5.关于贴纸，如果贴纸位置图的包装版本与大货不一致，请工厂提前提出。跟单会重新调整确认是否更新贴纸或调整位置图 6.产品/包装不含PFAS成分 7. 产品信息： 9561-S001//100-220511489//4894680042520 | Z67: Luna Lin | AA67: 5.1541 | AB67: =I67*AA67 -> 2473.968 | AD67: 9561-S001-芬兰 | AE67: 已入 | AJ67: =I67 -> 480 | AN67: =I67 -> 480 | AO67: =I67 -> 480 | AP67: =I67 -> 480 | AU67: =I67 -> 480 | AV67: =AV66+AU67 -> 76570
A68: 45758 | B68: JUGUETES PASTOR S.L. | C68: 西班牙 | D68: 4500163040 | F68: 4500163040-50 | G68: 9561-S001 | H68: 魔法小鸟 | I68: 600 | J68: 0 | K68: 4 | L68: =I68/K68 -> 150 | M68: 45807 | N68: 45803 | P68: PASS | R68: 45758 | S68: 无 | T68: 无 | U68: MA | Y68: 日期码格式：ZURU INC(BVI) 标准格式 日期：按实际生产日期 Packaging Info: 4.9561:最新MA 5L EAN版本包装+MA 5L说明书； Remark: | Z68: Miya Fang | AA68: 5.3566 | AB68: =I68*AA68 -> 3213.96 | AD68: 9561-S001-5L | AE68: 已入 | AJ68: =I68 -> 600 | AL68: =I68 -> 600 | AP68: =I68 -> 600 | AU68: =I68 -> 600 | AV68: =AV67+AU68 -> 77170
A69: 45758 | B69: ARGOS LIMITED | C69: 英国 | D69: 4500163218 | E69: PO#239937-Cus tomer SKU#7659423 | F69: 4500163218-10 | G69: 9561-S001 | H69: 魔法小鸟 | I69: 600 | J69: 0 | K69: 4 | L69: =I69/K69 -> 150 | M69: 45807 | N69: 45803 | P69: PASS | R69: 45759 | S69: 无 | T69: 4/29客人白色Cat.label 1张覆盖ZURU条码 | U69: MA | Y69: 日期码格式：ZURU INC(BVI) 标准格式 日期：按实际生产日期 Packaging Info: 9561-S001 MA -1L UPC包装+客人白色Cat.label 1张覆盖ZURU条码 -注意Cat.label (要求易撕类贴纸，但是粘性不能过低），同时此贴纸每个订单都是不相同的(会显示客户对应的订单号），切勿翻旧订单购买，该贴纸由工厂自行 购买。 Remark: *MA包装按最新版本安排即可 *包装日期码按ZURU格式即可，请确保不迟于外箱日期码，可等于或者早于外箱日期码，必须为法定工作日。 *外箱尺寸任何一条边长度超过75cm或者每箱重量超过10KG,需要在外箱上加三脚架符号，有问题请与ZURU跟单同事核实。 *订单必须经过ZURU QC验货并且通过后方可出货。 *订单出英国，请注意检查产品及包装应带UKCA图标，包装显示ZURU UK LTD信息，QC同事请查核，如有问题与跟单确认。 *条码扫描会显示客户7位数产品号 ，忽略订单显示的MA条码 *所有产品按符合欧洲标准走货，微塑料需合规。 *涉及到硼的，需要符合欧洲标准 | Z69: May Wu | AA69: 5.1379 | AB69: =I69*AA69 -> 3082.74 | AD69: 9561-S001 | AE69: 已入 | AF69: =I69 -> 600 | AL69: =I69 -> 600 | AP69: =I69 -> 600 | AU69: =I69 -> 600 | AV69: =AV68+AU69 -> 77770
A70: 45764 | B70: ZURU France | C70: 法国 | D70: 4500163334 | E70: 5200006584 | F70: 4500163334-80 | G70: 9561-S001-MTS | H70: 魔法小鸟 | I70: 4124 | J70: 0 | K70: 4 | L70: =I70/K70 -> 1031 | M70: 45808 | N70: 45804 | P70: PASS | R70: 45769 | S70: 无 | T70: MA A版5L+6L说明书（带法国说明书警语贴纸+多语警语折叠贴纸（含包装缺失的法/意/西环保标）+ 多语版WEEE电池垃 圾桶的回收声明说明书（ included）（贴纸和WEEE翻4500162314） | U70: MA | Y70: 日期码格式：ZURU INC(BVI) 标准格式 日期：按实际生产日期 Packaging Info: 9561: A版 5L EAN收缩膜+MA A版5L+6L说明书（带法国说明书警语贴纸）+A版5L收藏指南+多语警语折叠贴纸（含包装缺失的法/意/西环保标）+ 多语版WEEE电池垃 圾桶的回收声明说明书（ included）（贴纸和WEEE翻4500162314） Remark: 1. 法国国家内销单，需要通过ZURU 验货结果后才能出货 (工厂需要主动提前同ZURU QC预约验货避免延期出货造成不必要麻烦)； 2. 本订单所有 具有 baby items / assorted items 的款式，零售包装上都要用 母 EAN; 3. 若有特定款有特殊外箱条码要求时,需要明确列出产品款对应的具体外箱条码号码/条码类型 (若无,可以忽略此需求) 4. 所有出口欧洲的产品, 法规规定禁止在包装和共公众用的印刷品中使用矿物油中含有的物质, 包装印刷油墨中含有的MOAH/MOSH的质量浓度不能超过1%, 否则出 货到法国被抽检出现问题, 供应商需要对此负责; 5. Date code: 外箱/产品/包装 保持一致，完货后提供date code 信息以便我们保存记录做批次管理; 6. 装柜时需要按照款式号码从小到大一款款依次装,避免终端仓库卸货混乱.若一个柜子涉及到几个不同国家内销单,装柜时需要一个国家装完后再装另一个国家的 产品,依次装柜,避免终端仓库因不同国家不同库位位置卸货混乱. (此点需要同工厂装柜人员强调) | Z70: SD83 | AA70: 5.4 | AB70: =I70*AA70 -> 22269.6 | AD70: 9561-S001-5L | AE70: 已入 | AJ70: =I70 -> 4124 | AL70: =I70 -> 4124 | AP70: =I70 -> 4124 | AU70: =I70 -> 4124 | AV70: =AV69+AU70 -> 81894
A71: 45757 | B71: KESKO OYJ | C71: 芬兰 | D71: 4500163047 | E71: 4545554958 | F71: 4500163047-20 | G71: 9561-S001 | H71: 魔法小鸟 | I71: 560 | J71: 0 | K71: 4 | L71: =I71/K71 -> 140 | M71: 45810 | N71: 45806 | P71: PASS | R71: 45757 | S71: 无 | T71: 4/111张警示语贴纸+史莱姆说明书+客版说明书 | U71: MA | Y71: 日期码格式：ZURU INC(BVI) 标准格式 日期：按实际生产日期 Packaging Info: 9561-收缩膜MA EAN 5L+6L A+1张警示语贴纸+客版guide book（翻单4500160993）+客版说明书（翻单4500160993） Remark: 1/ SKU-客户货号-EAN-GTIN 9561-10193052078909-4894680042520-10193052078909 2/ 产品和包装要求无硼无香，包装不能含有PVC 3/ 如有微塑料，必须合规欧洲标准，闪粉也是微塑料的一种，目前仅接受三张方式1.去除，2.用可降解材料，和3. 永久封印在固体。 4/带电池出货的产品所用到的电池需要符合欧洲电池新规(EU) 2023-1542 5/需ZURU验货通过 6/每个产品需额外准备2套大货样，大货样需加上SAMPLE TAG,并于5/15前寄到罗湖办公室 | Z71: Zoe Zhou | AA71: 5.3566 | AB71: =I71*AA71 -> 2999.696 | AD71: 9561-S001-芬兰 | AE71: 已入 | AJ71: =I71 -> 560 | AN71: =I71 -> 560 | AO71: =I71 -> 560 | AP71: =I71 -> 560 | AU71: =I71 -> 560 | AV71: =AV70+AU71 -> 82454
A72: 45757 | B72: KESKO OYJ | C72: 芬兰 | D72: 4500163047 | E72: 4545554958 | F72: 4500163047-30 | G72: 9561EC-S001 | H72: 魔法小鸟 | I72: 234 | J72: 0 | K72: 18 | L72: =I72/K72 -> 13 | M72: 45810 | N72: 45806 | P72: PASS | R72: 45757 | S72: 无 | T72: 4/111张警示语贴纸+史莱姆说明书+客版说明书 | U72: MA | Y72: 日期码格式：ZURU INC(BVI) 标准格式 日期：按实际生产日期 Packaging Info: 9561EC-收缩膜MA EAN 5L+6L A+1张警示语贴纸+客版guide book（翻单4500160993）+客版说明书（翻单4500160993） Remark: 1/ SKU-客户货号-EAN-GTIN 9561EC-50193052078907-4894680052154-50193052078907 2/ 产品和包装要求无硼无香，包装不能含有PVC 3/ 如有微塑料，必须合规欧洲标准，闪粉也是微塑料的一种，目前仅接受三张方式1.去除，2.用可降解材料，和3. 永久封印在固体。 4/带电池出货的产品所用到的电池需要符合欧洲电池新规(EU) 2023-1542 5/需ZURU验货通过 6/每个产品需额外准备2套大货样，大货样需加上SAMPLE TAG,并于5/15前寄到罗湖办公室 | Z72: Zoe Zhou | AA72: 118.7504 | AB72: =AA72*L72 -> 1543.7552 | AD72: 9561EC-S001 | AE72: 已入 | AJ72: =I72 -> 234 | AN72: =I72 -> 234 | AO72: =I72 -> 234 | AP72: =I72 -> 234 | AR72: =K72 -> 18 | AU72: =I72 -> 234 | AV72: =AV71+AU72 -> 82688
A73: 45758 | B73: PT. TOYS GAMES INDONESIA | C73: 印度尼西亚 | D73: 4500163317 | F73: 4500163317-10 | G73: 9561-S001 | H73: 魔法小鸟 | I73: 200 | J73: 0 | K73: 4 | L73: =I73/K73 -> 50 | M73: 45804 | N73: 45800 | P73: PASS | R73: 45771 | S73: 无 | T73: 4/23进口商贴纸 | U73: MA | Y73: 日期码格式：ZURU INC(BVI) 标准格式 日期：按实际生产日期 Packaging Info: 1.MA UPC PKG（优先1L）+ 进口商贴纸(后续提供资料)； 2.装柜前有第三方验货，需要把货送到主拼工厂同其他货一起验，具体验货时间及安排届时邮件通知工厂； 3.第三方验货前所有产品须经过ZURU OQC检验通过，我司验货请在完货前 提前至少一周联系Minty@zuru.com预定验货日期； Remark: 9561:3PCS LR44 BATTERIES(INCLUDED); | Z73: Cathy.chen | AA73: 5.3727 | AB73: =I73*AA73 -> 1074.54 | AD73: 9561-S001 | AE73: 已入 | AF73: =I73 -> 200 | AL73: =I73 -> 200 | AP73: =I73 -> 200 | AU73: =I73 -> 200 | AV73: =AV72+AU73 -> 82888
A74: 45771 | B74: ZURU Germany GMBH | C74: 德国 | D74: 4500164783 | E74: 5200006663 | F74: 4500164783-110 | G74: 9561-S001-MTS | H74: 魔法小鸟 | I74: 1200 | J74: 0 | K74: 4 | L74: =I74/K74 -> 300 | M74: 45804 | N74: 45800 | P74: PASS | R74: 45772 | S74: 无 | T74: 1*多语折叠警语贴纸+5/6黑白5L（PL+HU+CZ+SK+RO)说明书+WEEE声明通用30L说明书(带电池) | U74: MA | Y74: 日期码格式：ZURU INC(BVI) 标准格式 日期：按实际生产日期 Packaging Info: 11.9561：最新MA 5L(6L warning) EAN 收缩膜+1*多语折叠警语贴纸+MA 6L Guide book+1*黑白5L（PL+HU+CZ+SK+RO)说明书+WEEE声明通用30L说明书(带电池)； Remark: 1.波兰内销单，需要通过ZURU 验货结果后才能出货 (工厂需要主动提前同ZURU QC预约验货避免延期出货造成不必要麻烦)； 2. 若有特定款有特殊外箱条码要求时,需要明确列出产品款对应的具体外箱条码号码/条码类型 (若无,可以忽略此需求) 3.所有出口欧洲的产品, 法规规定禁止在包装和共公众用的印刷品中使用矿物油中含有的物质, 包装印刷油墨中含有的MOAH/MOSH的质量浓度不能超过1%, 否则出货 到法国被抽检出现问题, 供应商需要对此负责; 4. date code: 外箱日期码要晚于或等于产品日期码，不能早于产品的日期码 5. 所有电子产品身上需要加字唛，为ZURU FRANCE 地址 (如无电子产品，或者产品布标有此地址，可忽略此信息) ZURU France 1/3, Rue d'Argenteuil 95210 SAINT-GRATIEN, FRANCE 6. 装柜时需要按照款式号码从小到大一款款依次装,避免终端仓库卸货混乱.若一个柜子涉及到几个不同国家内销单,装柜时需要一个国家装完后再装另一个国家的 产品,依次装柜,避免终端仓库因不同国家不同库位位置卸货混乱. (此点需要同工厂装柜人员强调) | Z74: Amy Xiao | AA74: 5.4 | AB74: =I74*AA74 -> 6480 | AD74: 9561-S001-5L | AE74: 已入 | AJ74: =I74 -> 1200 | AL74: =I74 -> 1200 | AP74: =I74 -> 1200 | AU74: =I74 -> 1200 | AV74: =AV73+AU74 -> 84088
A75: 45761 | B75: HARVEY WHOLESALE LTD | C75: 新西兰 | D75: 4500163518 | E75: 3006 | F75: 4500163518-30 | G75: 9561-S001 | H75: 魔法小鸟 | I75: 360 | J75: 0 | K75: 4 | L75: =I75/K75 -> 90 | M75: 45813 | N75: 45810 | P75: PASS | R75: 45762 | S75: 无 | T75: 无 | U75: MA | Y75: 日期码格式：ZURU INC(BVI) 标准格式 日期：按实际生产日期 Packaging Info: #9561:3PCS LR44 BATTERIES(INCLUDED) Remark: MA UPC 英语包装（优先1L英语版本,或者3L/L含英语即可 | Z75: Abby Liang | AA75: 5.3727 | AB75: =I75*AA75 -> 1934.172 | AC75: 95196-6.4 | AD75: 9561-S001 | AE75: 已入 | AF75: =I75 -> 360 | AL75: =I75 -> 360 | AP75: =I75 -> 360 | AU75: =I75 -> 360 | AV75: =AV74+AU75 -> 84448
A76: 45765 | B76: Indeks Retail A/S | C76: 丹麦 | D76: 4500164118 | E76: 253501 | F76: 4500164118-40 | G76: 9561-S001 | H76: 魔法小鸟 | I76: 400 | J76: 0 | K76: 4 | L76: =I76/K76 -> 100 | M76: 45814 | N76: 45810 | P76: PASS | R76: 45783 | S76: 无 | T76: 丹麦语警告语贴纸+北欧客版说明书(英语/丹麦/瑞典/芬兰/挪威/爱沙尼亚/德语/荷兰语语言)+北欧客版guide book(英语/丹 麦/瑞典/芬兰/挪威/爱沙尼亚/德语/荷兰语语言)--客版说明书和guide book翻TAS PO#4500160993 | U76: MA | Y76: 日期码格式：ZURU INC(BVI) 标准格式 日期：按实际生产日期 Packaging Info: 4. 9561-S001: MA 5L-6L EAN版收缩膜+丹麦语警告语贴纸+北欧客版说明书(英语/丹麦/瑞典/芬兰/挪威/爱沙尼亚/德语/荷兰语语言)+北欧客版guide book(英语/丹 麦/瑞典/芬兰/挪威/爱沙尼亚/德语/荷兰语语言)--客版说明书和guide book翻TAS PO#4500160993 Remark: 1. 包装如含PVC,请改为PET 2. 产品/包装要求无硼无香； 3. 出欧洲，微塑料需合规。 4.带电池出货的产品所用到的电池需要符合欧洲电池新规(EU) 2023-1542 5.关于贴纸，如果贴纸位置图的包装版本与大货不一致，请工厂提前提出。跟单会重新调整确认是否更新贴纸或调整位置图 6.产品/包装不含PFAS成分 7. 产品条码如下: 请先检查条码是否正确再安排做货，如有问题请告知: 9561-S001:4894680042520 | Z76: Sheba | AA76: 5.3727 | AB76: =I76*AA76 -> 2149.08 | AD76: 9561-S001-芬兰 | AE76: 已入 | AJ76: =I76 -> 400 | AN76: =I76 -> 400 | AO76: =I76 -> 400 | AP76: =I76 -> 400 | AU76: =I76 -> 400 | AV76: =AV75+AU76 -> 84848
A77: 45786 | B77: PPTOYS PTE LTD (SG) | C77: 新加坡 | D77: 4500165878 | E77: ZU25042302SG | F77: 4500165878-20 | G77: 9561-S001 | H77: 魔法小鸟 | I77: 500 | J77: 0 | K77: 4 | L77: =I77/K77 -> 125 | M77: 45818 | N77: 45814 | P77: PASS | R77: 45786 | S77: 无 | T77: 1张进口商贴纸 9561-贴纸AW、位置图翻单4500159608 | U77: MA | Y77: 日期码格式：ZURU INC(BVI) 标准格式 日期：按实际生产日期 Packaging Info: MA UPC包装（优先1L)+1张进口商贴纸 9561-贴纸AW、位置图翻单4500159608 此客人用的贴纸内容都是一样的，个别item可能存在尺寸差别，如果发现贴纸尺寸没差别，就请都统一订购节省成本 Remark: 9561-3PCS LR44 BATTERIES(INCLUDED) | Z77: Emma Wu | AA77: 5.1379 | AB77: =I77*AA77 -> 2568.95 | AD77: 9561-S001 | AE77: 已入 | AF77: =I77 -> 500 | AL77: =I77 -> 500 | AP77: =I77 -> 500 | AU77: =I77 -> 500 | AV77: =AV76+AU77 -> 85348
A78: 45765 | B78: TESCO CE | C78: 斯洛伐克 | D78: 4500164228 | E78: 999-44517 999-44528 | F78: 4500164228-60 | G78: 9561-S001 | H78: 魔法小鸟 | I78: 2000 | J78: 0 | K78: 4 | L78: =I78/K78 -> 500 | M78: 45810 | N78: 45806 | P78: PASS | R78: 45790 | S78: 无 | T78: 4/274国警告语贴纸(Czech-Hugarian-Polish-Slovak，不能覆盖GB语言） | U78: MA | Y78: 日期码格式：ZURU INC(BVI) 标准格式 日期：按实际生产日期 Packaging Info: - 9561: MA B版1L收缩膜+4国警告语贴纸(Czech-Hugarian-Polish-Slovak，不能覆盖GB语言） Remark: "1. 此单出EU，需满足EU测试标准要求，不含微塑料。 产品及包装需要印UKCA图标，包装需要有ZURU UK LTD/ZURU France地址信息，QC同事请核查，如有问题与跟单确认。 2.裝櫃必須按TPND順序 (條形碼貼紙或正嘜必須要朝外向車門外)，不可额外打缠绕带 3.外箱上有条码要求，排版时请留意并请确保条码清晰可扫描（封箱胶不要黏到条码上), 否则客人会有罚款； 4. 如含硼的话， 需用低硼版本(小于300ppm),硼含量需要符合欧洲标准,否则客人会退货有罚款产生" | Z78: Sharon Zhao | AA78: 5.3406 | AB78: =I78*AA78 -> 10681.2 | AD78: 9561-S001 | AE78: 已入 | AF78: =I78 -> 2000 | AL78: =I78 -> 2000 | AP78: =I78 -> 2000 | AU78: =I78 -> 2000 | AV78: =AV77+AU78 -> 87348
A79: 45741 | B79: KAUFHAUS MARTIN STOLZ GMBH | C79: 德国 | D79: 4500160865 | F79: 4500160865-10 | G79: 9561-S001 | H79: 魔法小鸟 | I79: 500 | J79: 0 | K79: 4 | L79: =I79/K79 -> 125 | M79: 45813 | N79: 45810 | P79: PASS | R79: 45783 | S79: 无 | T79: 4/21客供价格贴纸+WEEE 欧洲通用30L带电池出货版说明书 | U79: MA | X79: 日期码格式：ZURU INC(BVI) 标准格式 日期：按实际生产日期 | Y79: 日期码格式：ZURU INC(BVI) 标准格式 日期：按实际生产日期 Packaging Info: 9561:最新MA 5L+6L EAN收缩膜（4894680042520）+最新MA 5L+6L 说明书+客供价格贴纸+WEEE 欧洲通用30L带电池出货版说明书 Remark: "1. 此单出德国，需要满足Zuru Standard欧洲标准测试要求； 2. 请准时出货，推期会有罚款； 3. 出口欧洲，微塑料需符合法规。 4. 配比：标准配比 5. 大货样品一套 6. 需提供验货图片给客人确认才可以安排出货 7. 所有包装警语部分需含德语警语 | Z79: Joyce Chen | AA79: 5.4 | AB79: =I79*AA79 -> 2700 | AD79: 9561-S001-5L | AE79: 已入 | AJ79: =I79 -> 500 | AL79: =I79 -> 500 | AP79: =I79 -> 500 | AU79: =I79 -> 500 | AV79: =AV78+AU79 -> 87848
A80: 45768 | B80: TOYS "R" US (CANADA) LTD. | C80: 加拿大 | D80: 4500164212 | E80: 3501527848 | F80: 4500164212-20 | G80: 9561-S001 | H80: 魔法小鸟 | I80: 720 | J80: 0 | K80: 4 | L80: =I80/K80 -> 180 | M80: 45817 | N80: 45813 | P80: PASS | R80: 45784 | S80: 无 | T80: UPC贴纸；UPC#193052078902 | U80: MA | Y80: 日期码格式：ZURU INC(BVI) 标准格式 日期：按实际生产日期 Packaging Info: 1. 出口加拿大市场。 #9561: MA 5L EAN版本 + UPC贴纸；UPC#193052078902; 3PCS LR44 BATTERIES(INCLUDED) 2. 产品、包装、外箱上面tracking code的时间格式需要一致，tracking code的时间为：DG20250526 Remark: 3. 需要第三方SGS验货，验货时间2025/06/09，每款每色请备1PC完整带包装样品供验货人员参考。用完后若无损坏可以放回大货里。 | Z80: Lluvia Zeng | AA80: 5.3566 | AB80: =I80*AA80 -> 3856.752 | AD80: 9561-S001-5L | AE80: 已入 | AJ80: =I80 -> 720 | AL80: =I80 -> 720 | AP80: =I80 -> 720 | AU80: =I80 -> 720 | AV80: =AV79+AU80 -> 88568
A81: 45774 | B81: SUOMEN OSUUSKAUPPOJEN KESKUSKUNTA | C81: 芬兰 | D81: 4500160378 | E81: 164147 | F81: 4500160378-10 | G81: 9561-S001 | H81: 魔法小鸟 | I81: 272 | J81: 0 | K81: 4 | L81: =I81/K81 -> 68 | M81: 45818 | N81: 45814 | P81: PASS | R81: 45786 | S81: 无 | T81: 瑞典芬兰爱沙尼亚语警告语/MADE IN CHINA翻译成瑞典芬兰爱沙尼亚语言做成一张贴纸(贴纸和位置图翻K􀃤rkk􀃤inen PO#450016157 3 | U81: MA | Y81: 日期码格式：ZURU INC(BVI) 标准格式 日期：按实际生产日期 Packaging Info: 1. 9561: MA 5L-6L EAN版收缩膜+瑞典芬兰爱沙尼亚语警告语/MADE IN CHINA翻译成瑞典芬兰爱沙尼亚语言/电池信息产品包含信息翻译做成一张贴纸+北欧客版说明 书(英语/丹麦/瑞典/芬兰/挪威/爱沙尼亚/德语/荷兰语语言)+北欧客版guide book(英语/丹麦/瑞典/芬兰/挪威/爱沙尼亚/德语/荷兰语语言)--客版说明书和guide b ook翻TAS PO#4500160993 7. 配比跟MA Remark: 1. 9561: 需要在6/11安排ITS第三方验货，请多备料 请在6/2之前各提供一套大货签板给我们签回供第三方验货用，签板必须跟大货完全一致，否则验货会不合格 2. 9561新款: 请在6/2之前各提供两套大货样给我们寄给客人留底 3. 包装如含PVC,请改为PET并第一时间通知跟单 4. 产品/包装要求无硼无香，出欧洲，微塑料需合规。 5.带电池出货的产品所用到的电池需要符合欧洲电池新规(EU) 2023-1542 6.有胶袋的产品：要求产品的胶袋厚度要大于等于0.05mm 7.关于贴纸，如果贴纸位置图的包装版本与大货不一致，请工厂第一时间提前提出。跟单会重新调整确认是否更新贴纸或调整位置图 8.产品/包装不含PFAS成分 9.产品条码如下: 请先检查条码是否正确再安排做货，如有问题请告知 ZURU ITEM#<(>&<)>EAN: 9561-S001:4894680042520 | Z81: Sheba Ye | AA81: 5.4 | AB81: =I81*AA81 -> 1468.8 | AC81: 95522-7.1 | AD81: 9561-S001-芬兰 | AE81: 已入 | AJ81: =I81 -> 272 | AN81: =I81 -> 272 | AO81: =I81 -> 272 | AP81: =I81 -> 272 | AU81: =I81 -> 272 | AV81: =AV80+AU81 -> 88840
A82: 45775 | B82: CANADIAN TIRE | C82: 加拿大 | D82: 4500165230 | E82: 09848926 | F82: 4500165230-20 | G82: 9561-S001 | H82: 魔法小鸟 | I82: 3260 | J82: 0 | K82: 4 | L82: =I82/K82 -> 815 | M82: 45819 | N82: 45815 | P82: PASS | R82: 45793 | S82: 无 | T82: UPC 贴纸， UPC 193052078902 | U82: MA | Y82: 日期码格式：ZURU INC(BVI) 标准格式 日期：按实际生产日期 Packaging Info: 9561 ： MA多语收缩膜+UPC 贴纸， UPC 193052078902； MA 多语收藏指南 Remark: 出加拿大 Zuru验货.日期跟踪码：产品外包装及产品本身都必须有日期跟踪码，ZURU标准格式日期码 | Z82: Summer Mo | AA82: 5.3406 | AB82: =I82*AA82 -> 17410.356 | AD82: 9561-S001-5L | AE82: 已入 | AJ82: =I82 -> 3260 | AL82: =I82 -> 3260 | AP82: =I82 -> 3260 | AU82: =I82 -> 3260 | AV82: =AV81+AU82 -> 92100
A83: 45774 | B83: WALMART INC. | C83: 美国 | D83: 4500165199 | E83: 0923153988 | F83: 4500165199-10 | G83: 9561-S002 | H83: 魔法小鸟 | I83: 792 | J83: 0 | K83: 1 | L83: =I83/K83 -> 792 | M83: 45845 | N83: =M83-4 -> 45841 | P83: PASS | R83: 45754 | S83: 无 | T83: 5/12客供贴纸 | U83: MA | Y83: 日期码格式：ZURU DGYYYYMMDD CHINA(日期避开周末和法定节假日即可） 日期：按实际生产日期 Packaging Info: 9561-S002 1.包装要求： MA 1L收缩膜+MA 5L 收藏指南+MA Guide book +MA 8L Slime bag 每pcs产品上要贴1张RFID贴纸，贴纸由ZURU提供，贴纸位置请严格按照我们签回的签板； Remark: 9561-S002 1.包装要求： MA 1L收缩膜+MA 5L 收藏指南+MA Guide book +MA 8L Slime bag 每pcs产品上要贴1张RFID贴纸，贴纸由ZURU提供，贴纸位置请严格按照我们签回的签板； 2. 外箱印刷带条码的RFID箱唛：RFID紫色色带+WM Dept.图标+RFID图标+ITF-14条码+粉色艾利贴纸（不干胶打印），四面右下角印刷ZURU logo, ITFF条码只印刷在 正唛一面，在加印的时候确保条形码能扫描出来，1张粉红色贴纸贴在正唛对角线，外箱侧面任一角落加印："MADE IN CHINA" 字样； 3. 在产品上和包装上要有日期码、以及要有MADE IN CHINA和ZURU字样； 4. 产品如有扎带口要剪平，不能刮手。 5. 此单需要验货，请多备料 6. 此单以loose carton出货，1pc/CTN | Z83: Maggie Xie | AA83: 3.214 | AB83: =AA83*I83 -> 2545.488 | AC83: ZB00859-7.25 ZB00990-7.31 | AD83: 9561-S002 | AE83: 已入 | AF83: =I83 -> 792 | AL83: =I83 -> 792 | AP83: =I83 -> 792 | AU83: =I83 -> 792 | AV83: =AV82+AU83 -> 92892
A84: 45774 | B84: WALMART INC. | C84: 美国 | D84: 4500165199 | E84: 0923153970 | F84: 4500165199-20 | G84: 9561-S002 | H84: 魔法小鸟 | I84: 1106 | J84: 0 | K84: 1 | L84: =I84/K84 -> 1106 | M84: 45849 | N84: =M84-4 -> 45845 | P84: PASS | R84: 45754 | S84: 无 | T84: 5/12客供贴纸 | U84: MA | Y84: 日期码格式：ZURU DGYYYYMMDD CHINA(日期避开周末和法定节假日即可） 日期：按实际生产日期 Packaging Info: 9561-S002 1.包装要求： MA 1L收缩膜+MA 5L 收藏指南+MA Guide book +MA 8L Slime bag 每pcs产品上要贴1张RFID贴纸，贴纸由ZURU提供，贴纸位置请严格按照我们签回的签板； Remark: 9561-S002 1.包装要求： MA 1L收缩膜+MA 5L 收藏指南+MA Guide book +MA 8L Slime bag 每pcs产品上要贴1张RFID贴纸，贴纸由ZURU提供，贴纸位置请严格按照我们签回的签板； 2. 外箱印刷带条码的RFID箱唛：RFID紫色色带+WM Dept.图标+RFID图标+ITF-14条码+粉色艾利贴纸（不干胶打印），四面右下角印刷ZURU logo, ITFF条码只印刷在 正唛一面，在加印的时候确保条形码能扫描出来，1张粉红色贴纸贴在正唛对角线，外箱侧面任一角落加印："MADE IN CHINA" 字样； 3. 在产品上和包装上要有日期码、以及要有MADE IN CHINA和ZURU字样； 4. 产品如有扎带口要剪平，不能刮手。 5. 此单需要验货，请多备料 6. 此单以loose carton出货，1pc/CTN | Z84: Maggie Xie | AA84: 3.214 | AB84: =AA84*I84 -> 3554.684 | AC84: ZB00893-7.26 | AD84: 9561-S002 | AE84: 已入 | AF84: =I84 -> 1106 | AL84: =I84 -> 1106 | AP84: =I84 -> 1106 | AU84: =I84 -> 1106 | AV84: =AV83+AU84 -> 93998
A85: 45774 | B85: WALMART INC. | C85: 美国 | D85: 4500165199 | E85: 0923153974 | F85: 4500165199-30 | G85: 9561-S002 | H85: 魔法小鸟 | I85: 970 | J85: 0 | K85: 1 | L85: =I85/K85 -> 970 | M85: 45849 | N85: =M85-4 -> 45845 | P85: PASS | R85: 45754 | S85: 无 | T85: 5/12客供贴纸 | U85: MA | Y85: 日期码格式：ZURU DGYYYYMMDD CHINA(日期避开周末和法定节假日即可） 日期：按实际生产日期 Packaging Info: 9561-S002 1.包装要求： MA 1L收缩膜+MA 5L 收藏指南+MA Guide book +MA 8L Slime bag 每pcs产品上要贴1张RFID贴纸，贴纸由ZURU提供，贴纸位置请严格按照我们签回的签板； Remark: 9561-S002 1.包装要求： MA 1L收缩膜+MA 5L 收藏指南+MA Guide book +MA 8L Slime bag 每pcs产品上要贴1张RFID贴纸，贴纸由ZURU提供，贴纸位置请严格按照我们签回的签板； 2. 外箱印刷带条码的RFID箱唛：RFID紫色色带+WM Dept.图标+RFID图标+ITF-14条码+粉色艾利贴纸（不干胶打印），四面右下角印刷ZURU logo, ITFF条码只印刷在 正唛一面，在加印的时候确保条形码能扫描出来，1张粉红色贴纸贴在正唛对角线，外箱侧面任一角落加印："MADE IN CHINA" 字样； 3. 在产品上和包装上要有日期码、以及要有MADE IN CHINA和ZURU字样； 4. 产品如有扎带口要剪平，不能刮手。 5. 此单需要验货，请多备料 6. 此单以loose carton出货，1pc/CTN | Z85: Maggie Xie | AA85: 3.214 | AB85: =AA85*I85 -> 3117.58 | AC85: ZB00840-7.23 | AD85: 9561-S002 | AE85: 已入 | AF85: =I85 -> 970 | AL85: =I85 -> 970 | AP85: =I85 -> 970 | AU85: =I85 -> 970 | AV85: =AV84+AU85 -> 94968
A86: 45771 | B86: DISTRIBUIDORA JUGUETRON S.A. DE C.V | C86: 墨西哥 | D86: 4500164861 | E86: 50212500921 | F86: 4500164861-80 | G86: 9561-S001 | H86: 魔法小鸟 | I86: 720 | J86: 0 | K86: 4 | L86: =I86/K86 -> 180 | M86: 45813 | N86: 45810 | P86: PASS | R86: 45792 | S86: 有 | T86: 进口商贴纸产品/包装/说明书都需要贴一张进口商贴纸 | U86: MA | Y86: 日期码格式：ZURU INC(BVI) 标准格式 日期：按实际生产日期 Packaging Info: 9561:MA 3L EAN包装+UPC贴纸+MA 多语说明书+保证书+进口商贴纸+外箱贴纸，产品/包装/说明书都需要贴一张进口商贴纸 9561 保证书是通用的，翻单PO4500156374,请一起订购 Remark: 此单有第三方监柜，需要每款多备1套完整物料 | Z86: Ava Liang | AA86: 5.3566 | AB86: =I86*AA86 -> 3856.752 | AD86: 9561-S001-5L | AE86: 已入 | AJ86: =I86 -> 720 | AL86: =I86 -> 720 | AP86: =I86 -> 720 | AU86: =I86 -> 720 | AV86: =AV85+AU86 -> 95688
A87: 45789 | B87: TARGET US | C87: 美国 | D87: 4500166019 | E87: 10001260978-3758 | F87: 4500166019-10 | G87: 9561-S001 | H87: 魔法小鸟 | I87: 968 | J87: 0 | K87: 4 | L87: =I87/K87 -> 242 | M87: 45813 | N87: 45810 | P87: PASS | R87: 45790 | S87: 有 | T87: 无 | U87: MA | Y87: 日期码格式：ZURU INC(BVI) 标准格式 日期：按实际生产日期 Packaging Info: 产品包装MA 收缩膜(UPC版) Remark: 1.9561-S001-PETS ALIVE-MAGIC BIRD-SERIES 1-MAGIC BIRD SURPRISE PLAYSET-SHRINK WRAP-4PCS/CTN 2. 产品包装MA 收缩膜(UPC版)，收缩膜上的UPC显示193052078902； 3. 外箱正唛左上角位置粘贴条码箱贴纸，每箱只贴一张，由ZURU订购。来料贴纸上显示的客户DPCI#086-08-0267, UPC显示10193052078909; 4.产品和包装上印刷 tracking code信息，格式为ZURU常规格式; 5. 出货方式：货代自提 | Z87: Holly Zheng | AA87: 3.0827 | AB87: =I87*AA87 -> 2984.0536 | AC87: ZB00440-6.10 | AD87: 9561-S001 | AE87: 已入 | AF87: =I87 -> 968 | AL87: =I87 -> 968 | AP87: =I87 -> 968 | AU87: =I87 -> 968 | AV87: =AV86+AU87 -> 96656
A88: 45791 | B88: ZURU France | C88: 法国 | D88: 4500169682 | E88: 5200006789 | F88: 4500169682-20 | G88: 9561-S001-MTS | H88: 魔法小鸟 | I88: 3000 | J88: 0 | K88: 4 | L88: =I88/K88 -> 750 | M88: 45819 | N88: 45815 | O88: 4500164804转单、4500166428再转 | P88: PASS | R88: 45790 | S88: 无 | T88: 带法国说明书警语贴纸++多语警语折叠贴纸（含包装缺失的法/意/西环保标）+多语版WEEE电池垃圾桶的 回收声明说明书（included）（贴纸和WEEE翻4500162314） | U88: MA | Y88: 日期码格式：ZURU INC(BVI) 标准格式 日期：按实际生产日期 Packaging Info: 9561:A版5LEAN收缩膜+MAA版5L+6L说明书（带法国说明书警语贴纸）+A版5L收藏指南+多语警语折叠贴纸（含包装缺失的法/意/西环保标）+多语版WEEE电池垃圾桶的 回收声明说明书（included）（贴纸和WEEE翻4500162314） Remark: 1. 西班牙国家内销单，需要通过ZURU 验货结果后才能出货 (工厂需要主动提前同ZURU QC预约验货避免延期出货造成不必要麻烦)； 2. 本订单所有 具有 baby items / assorted items 的款式，零售包装上都要用 母 EAN; 所有订单出口西班牙都需要有西班牙环保标。 3. 若有特定款有特殊外箱条码要求时,需要明确列出产品款对应的具体外箱条码号码/条码类型 (若无,可以忽略此需求) 4. 所有出口欧洲的产品, 法规规定禁止在包装和共公众用的印刷品中使用矿物油中含有的物质, 包装印刷油墨中含有的MOAH/MOSH的质量浓度不能超过1%, 否则出 货到法国被抽检出现问题, 供应商需要对此负责; 5. Date code: 外箱/产品/包装 保持一致，完货后提供date code 信息以便我们保存记录做批次管理; 6. 装柜时需要按照款式号码从小到大一款款依次装,避免终端仓库卸货混乱.若一个柜子涉及到几个不同国家内销单,装柜时需要一个国家装完后再装另一个国家的 产品,依次装柜,避免终端仓库因不同国家不同库位位置卸货混乱. (此点需要同工厂装柜人员强调) 7， 带电池产品都需要包含多语WEEE黑白说明书。 8，MTS所有订单，SMASHERS 或含Slime产品，所有化合物使用无硼版本出；如有香味产品，出无香版本; BOB系列要符合欧洲要求不含亚硝酸版本; XShot Hyper系列 ，统一出EN71版本。 9， 请每款寄一套给Lisa Yang 用于上传西班牙网站, 以下是地址和联系方式，样品相关细节请与Lisa沟通@Lisa Yang - Merchandising <(>&<)> Operations <(> <<)>Lisa.ywx@zuru.com>. Lisa.Yang (+86) 755 6688 1988 – 3327| +86 15012613809 广东省深圳市罗湖区东门南路1006号口岸大楼A座7楼 | Z88: SD83 | AA88: 5.4 | AB88: =I88*AA88 -> 16200 | AD88: 9561-S001-5L | AE88: 已入 | AJ88: =I88*2 -> 6000 | AL88: =I88 -> 3000 | AP88: =I88 -> 3000 | AU88: =I88 -> 3000 | AV88: =AV87+AU88 -> 99656
A89: 45768 | B89: NORDIC TOY TEAM AS - DOM | C89: 挪威 | D89: 4500164402 | E89: 1310 | F89: 4500164402-40 | G89: 9561-S001 | H89: 魔法小鸟 | I89: 1200 | J89: 0 | K89: 4 | L89: =I89/K89 -> 300 | M89: 45814 | N89: 45810 | P89: PASS | R89: 45769 | S89: 无 | T89: 5/9进口商贴纸+30L WEEE带电池走货 | U89: MA | Y89: 日期码格式：ZURU INC(BVI) 标准格式 日期：按实际生产日期 Packaging Info: 9561: MA 5L-6L EAN版收缩膜+1进口商贴纸+MA说明书+WEEE带电池走货说明书30L Remark: 1/产品和包装要求无硼无香，包装不能含有PVC 2/如有微塑料，必须合规欧洲标准，闪粉也是微塑料的一种，目前仅接受三张方式1.去除，2.用可降解材料，和3.永久封印在固体。 3/带电池出货的产品，所用到的电池需要符合欧洲电池新规(EU)2023-1542 4/产品配比 | Z89: Zoe Zhou | AA89: 5.3566 | AB89: =I89*AA89 -> 6427.92 | AD89: 9561-S001-芬兰 | AE89: 已入 | AJ89: =I89 -> 1200 | AN89: =I89 -> 1200 | AO89: =I89 -> 1200 | AP89: =I89 -> 1200 | AU89: =I89 -> 1200 | AV89: =AV88+AU89 -> 100856
A90: 45765 | B90: COOLSHOP(ENTERTAINMENT TRADINGS APS | C90: 丹麦 | D90: 4500160030 | E90: 272908 | F90: 4500160030-20 | G90: 9561-S001 | H90: 魔法小鸟 | I90: 916 | J90: 0 | K90: 4 | L90: =I90/K90 -> 229 | M90: 45814 | N90: 45810 | P90: PASS | R90: 45783 | S90: 无 | T90: 丹麦瑞典挪威芬兰语警告语/客人进口商贴纸做成一张贴纸+北欧客版说明书(英语/丹麦/瑞典/芬兰/挪威/爱沙尼亚/德语/荷兰语语 | U90: MA | Y90: 日期码格式：ZURU INC(BVI) 标准格式 日期：按实际生产日期 Packaging Info: 2.9561：MA 5L-6L EAN版收缩膜+丹麦瑞典挪威芬兰语警告语/客人进口商贴纸做成一张贴纸+北欧客版说明书(英语/丹麦/瑞典/芬兰/挪威/爱沙尼亚/德语/荷兰语语 言)+北欧客版guide book(英语/丹麦/瑞典/芬兰/挪威/爱沙尼亚/德语/荷兰语语言)--客版说明书和guide book翻TAS PO#4500160993 Remark: 1. 包装如含PVC,请改为PET 2. 产品/包装要求无硼无香； 3. 出欧洲，微塑料需合规。 4.带电池出货的产品所用到的电池需要符合欧洲电池新规(EU) 2023-1542 5.关于贴纸，如果贴纸位置图的包装版本与大货不一致，请工厂提前提出。跟单会重新调整确认是否更新贴纸或调整位置图 6.产品/包装不含PFAS成分 7. 产品信息： 配比跟MA 8.SKU-客户款号-条码 9258-1195533-4894680021082 9561-1283417-4894680042520 | Z90: Sheba Ye | AA90: 5.3566 | AB90: =I90*AA90 -> 4906.6456 | AD90: 9561-S001-芬兰 | AE90: 已入 | AJ90: =I90 -> 916 | AN90: =I90 -> 916 | AO90: =I90 -> 916 | AP90: =I90 -> 916 | AU90: =I90 -> 916 | AV90: =AV89+AU90 -> 101772
A91: 45774 | B91: Meloman Home Video LLP | C91: 哈萨克斯坦 | D91: 4500164596 | F91: 4500164596-30 | G91: 9561-S001 | H91: 魔法小鸟 | I91: 152 | J91: 0 | K91: 4 | L91: =I91/K91 -> 38 | M91: 45817 | N91: =M91-4 -> 45813 | P91: PASS | R91: 45774 | S91: 无 | T91: 通用进口商贴纸 | U91: MA | Y91: 日期码格式：ZURU INC(BVI) 标准格式 日期：按实际生产日期 Packaging Info: 1L MA UPC 包装+ 通用进口商贴纸， MA 指南/说明书（如果有的话） Remark: 标准配比 | Z91: Ann | AA91: 5.1541 | AB91: =I91*AA91 -> 783.4232 | AD91: 9561-S001 | AE91: 已入 | AF91: =I91 -> 152 | AL91: =I91 -> 152 | AP91: =I91 -> 152 | AU91: =I91 -> 152 | AV91: =AV90+AU91 -> 101924
A92: 45786 | B92: PPTOYS PTE LTD (SG) | C92: 新加坡 | D92: 4500165924 | E92: ZU25042301SG | F92: 4500165924-10 | G92: 9561-S001 | H92: 魔法小鸟 | I92: 760 | J92: 0 | K92: 4 | L92: =I92/K92 -> 190 | M92: 45820 | N92: =M92-3 -> 45817 | P92: PASS | R92: 45792 | S92: 无 | T92: 进口商贴纸贴纸AW、位置图翻单4500159608 | U92: MA | Y92: 日期码格式：ZURU INC(BVI) 标准格式 日期：按实际生产日期 Packaging Info: MA UPC包装（优先1L)+1张进口商贴纸 9561-贴纸AW、位置图翻单4500159608 Remark: 3PCS LR44 BATTERIES(INCLUDED) | Z92: Emma Wu | AA92: 5.4381 | AB92: =I92*AA92 -> 4132.956 | AD92: 9561-S001 | AE92: 已入 | AF92: =I92 -> 760 | AL92: =I92 -> 760 | AP92: =I92 -> 760 | AU92: =I92 -> 760 | AV92: =AV91+AU92 -> 102684
A93: 45765 | B93: GP TURKEY | C93: 土耳其 | D93: 4500164154 | F93: 4500164154-10 | G93: 9561EC-S001 | H93: 魔法小鸟 | I93: 360 | J93: 0 | K93: 18 | L93: =I93/K93 -> 20 | M93: 45821 | N93: 45817 | P93: PASS | R93: 45797 | S93: 无 | T93: 5/9进口商贴纸（含客户条码）+MA 说明书（加贴纸）+slime bag 加贴纸 | U93: MA | X93: 日期码格式：ZUR5164 | Y93: 日期码格式：ZUR5164 日期： Packaging Info: 9561EC：MA 1L 展示架+ 产品MA 1L 包装+进口商贴纸（含客户条码）+客版说明书+客版收藏指南. 2.客户日期码：ZUR5164, 产品/包装/外箱请保持一致。产品外收缩膜需要印日期ZUR5164 3.9561EC需要两套完整大货样,还需要一套MA样，寄到客户香港办公室，请多备料，地址如下： Attn: Sylvia Li Company name: GP Services HK Limited Company address: Suite 1502, 15th Floor, Chinachem Golden Plaza, 77 Mody Road, TST East, Kowloon, Hong Kong Company address (Chinese): 香港九龍尖沙咀東部麼地道77號華懋廣場1502室 Contact Tel: +852 2739 5363 4.大货验货需要由ZURU QC抽如下数量样板寄到广州ITS做EN 71-3测试 Remark: 9561EC-S001 <(>&<)>9561: Pink, just one assortment 9561EC-S001 <(>&<)>9561: 3PCS LR44 BATTERIES(INCLUDED) | Z93: Lena Huang | AA93: 113.8227 | AB93: =AA93*L93 -> 2276.454 | AC93: 95751-7.24 | AD93: 9561EC-S001-2 | AE93: 已入 | AF93: =I93 -> 360 | AN93: =I93 -> 360 | AO93: =I93 -> 360 | AP93: =I93 -> 360 | AR93: =L93 -> 20 | AU93: =I93 -> 360 | AV93: =AV92+AU93 -> 103044
A94: 45765 | B94: GP TURKEY | C94: 土耳其 | D94: 4500164154 | F94: 4500164154-20 | G94: 9561-S001 | H94: 魔法小鸟 | I94: 3040 | J94: 0 | K94: 4 | L94: =I94/K94 -> 760 | M94: 45821 | N94: 45817 | P94: PASS | R94: 45797 | S94: 无 | T94: 5/9进口商贴纸（含客户条码）+MA 说明书（加贴纸）+slime bag 加贴纸 | U94: MA | X94: 日期码格式：ZUR5164 | Y94: 日期码格式：ZUR5164 日期： Packaging Info: 1.9561: MA 1L 包装+进口商贴纸（含客户条码）+客版说明书+客版收藏指南； 2.客户日期码：ZUR5164, 产品/包装/外箱请保持一致。产品外收缩膜需要印日期ZUR5164 3.9561需要两套完整大货样,还需要一套MA样，寄到客户香港办公室，请多备料，地址如下： Attn: Sylvia Li Company name: GP Services HK Limited Company address: Suite 1502, 15th Floor, Chinachem Golden Plaza, 77 Mody Road, TST East, Kowloon, Hong Kong Company address (Chinese): 香港九龍尖沙咀東部麼地道77號華懋廣場1502室 Contact Tel: +852 2739 5363 4.大货验货需要由ZURU QC抽如下数量样板寄到广州ITS做EN 71-3测试 #9561-3 pcs（包含三种不同颜色的沙子） Remark: | Z94: Lena Huang | AA94: 5.3406 | AB94: =I94*AA94 -> 16235.424 | AC94: 95751-7.24 | AD94: 9561-S001-土耳其 | AE94: 已入 | AF94: =I94 -> 3040 | AN94: =I94 -> 3040 | AO94: =I94 -> 3040 | AP94: =I94 -> 3040 | AU94: =I94 -> 3040 | AV94: =AV93+AU94 -> 106084
A95: 45779 | B95: Navy Exchange Service Command | C95: 美国 | D95: 4500165547 | E95: PO#37490767 | F95: 4500165547-30 | G95: 9561-S001 | H95: 魔法小鸟 | I95: 444 | J95: 0 | K95: 4 | L95: =I95/K95 -> 111 | M95: 45821 | N95: =M95-4 -> 45817 | P95: PASS | R95: 45799 | S95: 有 | T95: 外箱除了需要印刷箱唛外，还需额外加贴Packing Slip, UCC 贴纸和上架时间的贴纸 各一张 | U95: MA | X95: 日期码格式：ZURU INC(BVI) 标准格式 | Y95: 日期码格式：ZURU INC(BVI) 标准格式 日期：按实际生产日期 Packaging Info: ZURU MA UPC优先1L包装；出口美国 Remark: 1. 日期跟踪码：产品外包装及产品本身都必须有日期跟踪码，并且确保两者的日期跟踪码要一致；ZURU标准格式日期码 (请自行调整具体年月日生产期，但不能为 周末） 2. 外箱贴纸： 外箱除了需要印刷箱唛外，还需额外加贴Packing Slip一张 Packing Slip: 每款产品第一箱的外箱都需在1面正唛右上角处贴上Packing Slip（跟单提供资料；工厂用A4纸打印）<(>,<)>见箱唛资料详细内容。 3. 需要提供ZURU QC验货图片及验货报告给客户才能放SO出货，请QC验货时尽可能拍详细的图片。 | Z95: Annie Huang | AA95: 3.2236 | AB95: =I95*AA95 -> 1431.2784 | AC95: ZB00565-6.24 | AD95: 9561-S001 | AE95: 已入 | AF95: =I95 -> 444 | AL95: =I95 -> 444 | AP95: =I95 -> 444 | AU95: =I95 -> 444 | AV95: =AV94+AU95 -> 106528
A96: 45779 | B96: Navy Exchange Service Command | C96: 美国 | D96: 4500165547 | E96: PO#37490629 | F96: 4500165547-40 | G96: 9561-S001 | H96: 魔法小鸟 | I96: 120 | J96: 0 | K96: 4 | L96: =I96/K96 -> 30 | M96: 45821 | N96: =M96-4 -> 45817 | P96: PASS | R96: 45799 | S96: 有 | T96: 外箱除了需要印刷箱唛外，还需额外加贴Packing Slip, UCC 贴纸和上架时间的贴纸 各一张 | U96: MA | X96: 日期码格式：ZURU INC(BVI) 标准格式 | Y96: 日期码格式：ZURU INC(BVI) 标准格式 日期：按实际生产日期 Packaging Info: ZURU MA UPC优先1L包装；出口美国 Remark: 1. 日期跟踪码：产品外包装及产品本身都必须有日期跟踪码，并且确保两者的日期跟踪码要一致；ZURU标准格式日期码 (请自行调整具体年月日生产期，但不能为 周末） 2. 外箱贴纸： 外箱除了需要印刷箱唛外，还需额外加贴Packing Slip一张 Packing Slip: 每款产品第一箱的外箱都需在1面正唛右上角处贴上Packing Slip（跟单提供资料；工厂用A4纸打印）<(>,<)>见箱唛资料详细内容。 3. 需要提供ZURU QC验货图片及验货报告给客户才能放SO出货，请QC验货时尽可能拍详细的图片。 | Z96: Annie Huang | AA96: 3.2236 | AB96: =I96*AA96 -> 386.832 | AC96: ZB00565-6.24 | AD96: 9561-S001 | AE96: 已入 | AF96: =I96 -> 120 | AL96: =I96 -> 120 | AP96: =I96 -> 120 | AU96: =I96 -> 120 | AV96: =AV95+AU96 -> 106648
A97: 45735 | B97: MILLS FLEET FARM | C97: 美国 | D97: 4500160726 | E97: PO#4647606 | F97: 4500160726-40 | G97: 9561-S001 | H97: 魔法小鸟 | I97: 508 | J97: 0 | K97: 4 | L97: =I97/K97 -> 127 | M97: 45818 | N97: 45806 | P97: PASS | R97: 45750 | S97: 有 | T97: 无 | U97: MA | X97: 日期码格式：ZURU INC(BVI) 标准格式 日期：按实际生产日期 | Y97: 日期码格式：ZURU INC(BVI) 标准格式 日期：按实际生产日期 Packaging Info: 1. 包材：ZURU 最新 MA 1L UPC 版本，出口美国;| Remark: 2.日期跟踪码：产品包装及产品本身都必须有日期跟踪码，并且确保两者的日期跟踪码要一致；ZURU标准格式日期码(请自行调整具体年月日生产期，但不能为末). 3. 此单不同客户PO对应不同交期，PO详情看侧边remark ，交期请看PO上面的delivery date； 4. 外箱贴纸(请务必先发箱唛排版给跟单确认后再做印刷) 5. 出货配比：ZURU 标版配比 | Z97: Mila Yao | AA97: 5.4 | AB97: =I97*AA97 -> 2743.2 | AC97: ZB00534-6.21 | AD97: 9561-S001 | AE97: 已入 | AF97: =I97 -> 508 | AL97: =I97 -> 508 | AP97: =I97 -> 508 | AU97: =I97 -> 508 | AV97: =AV96+AU97 -> 107156
A98: 45772 | B98: UNIPAM SRL | C98: 意大利 | D98: 4500164781 | F98: 4500164781-50 | G98: 9561-S001 | H98: 魔法小鸟 | I98: 360 | J98: 0 | K98: 4 | L98: =I98/K98 -> 90 | M98: 45824 | N98: 45820 | P98: PASS | R98: 45793 | S98: 无 | T98: 一张意大利环保贴纸+ 多语版WEEE电池垃圾桶的回收声明说明书（ incl uded，翻4500162314） | U98: MA | Y98: 日期码格式：ZURU INC(BVI) 标准格式 日期：按实际生产日期 Packaging Info: 3.9561:A版 5L EAN收缩膜+MA A版5L+6L说明书（带法国说明书警语贴纸）+A版5L收藏指南+一张意大利环保贴纸+ 多语版WEEE电池垃圾桶的回收声明说明书（ incl uded，翻4500162314）+一张收缩膜callout 贴纸（翻4500166253） Remark: 1. SMASHERS 或含Slime产品，所有化合物使用无硼版本出意大利。 2. 本订单所有 具有 baby items / assorted items 的款式，零售包装上都要用 母 EAN; 3.所有出口欧洲的产品, 法规规定禁止在包装和共公众用的印刷品中使用矿物油中含有的物质, 包装印刷油墨中含有的MOAH/MOSH的质量浓度不能超过1%, 否则出货 到意大利被抽检出现问题, 供应商需要对此负责; 4. 意大利订单包装彩卡请确保含法规要求的环保回收logo。 | Z98: Christine He | AA98: 5.3727 | AB98: =I98*AA98 -> 1934.172 | AD98: 9561-S001-5L | AE98: 已入 | AJ98: =I98 -> 360 | AL98: =I98 -> 360 | AP98: =I98 -> 360 | AQ98: =I98 -> 360 | AU98: =I98 -> 360 | AV98: =AV97+AU98 -> 107516
A99: 45772 | B99: BASILE GIOCATTOLI SRL | C99: 意大利 | D99: 4500164791 | F99: 4500164791-10 | G99: 9561-S001 | H99: 魔法小鸟 | I99: 720 | J99: 0 | K99: 4 | L99: =I99/K99 -> 180 | M99: 45824 | N99: 45810 | P99: PASS | R99: 45786 | S99: 无 | T99: 5/12意大利sorting logo含进口商地址贴纸+WEEE带电池走货欧洲30语通用黑白说明书 | U99: MA | Y99: 日期码格式：ZURU INC(BVI) 标准格式 日期：按实际生产日期 Packaging Info: 9561:MA最新5L收缩膜+1*意大利sorting logo含进口商地址贴纸+MA 最新 5L收藏指南+MA 最新8L Slime bag+WEEE带电池走货欧洲30语通用黑白说明书 Remark: 1.此单出意大利，需满足EU测试标准要求<(>&<)> 微塑料需符合法规，如果有slime等化学品需要不含硼 2.需保证按期完货，延期罚款。 3.贴纸切勿盖住意大利警告语文字(QC 务必检查），特别是产品包装比较小的,如果会挡住产品上的警示语信息，在做大货前工厂需要提前告知跟单位置图是否OK， 需再次确认才能安排生产大货。 4. 标准配比 5. 需要ZURU OQC 验货， 需提供验货图片给到客户放货。 | Z99: Mary Zhong | AA99: 5.3566 | AB99: =I99*AA99 -> 3856.752 | AD99: 9561-S001-5L | AE99: 已入 | AJ99: =I99 -> 720 | AL99: =I99 -> 720 | AP99: =I99 -> 720 | AU99: =I99 -> 720 | AV99: =AV98+AU99 -> 108236
A100: 45772 | B100: BASILE GIOCATTOLI SRL | C100: 意大利 | D100: 4500164791 | F100: 4500164791-20 | G100: 9561EC-S001 | H100: 魔法小鸟 | I100: 648 | J100: 0 | K100: 18 | L100: =I100/K100 -> 36 | M100: 45824 | N100: 45810 | P100: PASS | R100: 45786 | S100: 无 | T100: 5/12意大利sorting logo含进口商地址贴纸+WEEE带电池走货欧洲30语通用黑白说明书 | U100: MA | Y100: 日期码格式：ZURU INC(BVI) 标准格式 日期：按实际生产日期 Packaging Info: 9561EC:MA 3L展示架+MA最新5L收缩膜+1*意大利sorting logo含进口商地址贴纸+MA 最新 5L收藏指南+MA 最新8L Slime bag+WEEE带电池走货欧洲30语通用黑白说明 书 Remark: 1.此单出意大利，需满足EU测试标准要求<(>&<)> 微塑料需符合法规，如果有slime等化学品需要不含硼 2.需保证按期完货，延期罚款。 3.贴纸切勿盖住意大利警告语文字(QC 务必检查），特别是产品包装比较小的,如果会挡住产品上的警示语信息，在做大货前工厂需要提前告知跟单位置图是否OK， 需再次确认才能安排生产大货。 4. 标准配比 5. 需要ZURU OQC 验货， 需提供验货图片给到客户放货。 | Z100: Mary Zhong | AA100: 118.4606 | AB100: =AA100*L100 -> 4264.5816 | AD100: 9561EC-S001-3L | AE100: 已入 | AJ100: =I100 -> 648 | AL100: =I100 -> 648 | AP100: =I100 -> 648 | AS100: =L100 -> 36 | AU100: =I100 -> 648 | AV100: =AV99+AU100 -> 108884
A101: 45749 | B101: SIPLEC | C101: 法国 | D101: 4500162245 | E101: 1042701 | F101: 4500162245-60 | G101: 9561-S001 | H101: 魔法小鸟 | I101: 240 | J101: 0 | K101: 4 | L101: =I101/K101 -> 60 | M101: 45824 | N101: 45820 | P101: PASS | R101: 45787 | S101: 有 | T101: 4/271张警语条码贴纸+1张PL/PT/SL贴纸++1张额外PL/PT/SL指引书+1张PL/SL警语贴纸+1张30LWEEE声明书(含电池版) | U101: MA | X101: 日期码格式：1042701-23 日期： | Y101: 日期码格式：1042701-23 日期： Packaging Info: 4.9561:MA 5语收缩膜+1张警语条码贴纸+MA 5L+6L收藏指南(英法德意西荷)+1张PL/PT/SL贴纸+MA 5L指引书+1张额外PL/PT/SL指引书+MA8L slime bag+1张PL/SL警语 贴纸+1张30LWEEE声明书(含电池版) Remark: 1.预计6/16第三方验货+抽板测试，此单需每款抽办8套左右测试，请多备料。5/20前准备好2套大货签板； 2.纸箱上加4张条形码贴纸, 外箱条码参考如下： 9561:53660441938052 3. 需在客户指定贴纸供货商Checkpoint订购， 联系方式如下, 并订购时请把范本发给Checkpoint Systems (ZJG) Co. Ltd. B Block, 28 Gang-ao Road, Zhangjiagang Free Trade Zone, Jiangsu, China, 215634 Office:+(86) 512 3500 3769 Mia.Wang Email: Mia.Wang@checkpt.com 4.每箱放3包透明颗粒状干燥剂(每包约5g)，包干燥剂的袋子要有"SILICA GEL - DO NOT EAT - DESSICANT - THROW AWAY " 字样 5. 包装禁止使用PVC塑料; 6. 此票出法国，需符合EU标准及微塑料法规，包装需含法国回收logo; | Z101: Ula Zhao | AA101: 5.1541 | AB101: =I101*AA101 -> 1236.984 | AC101: 95727-7.22 | AD101: 9561-S001 | AE101: 已入 | AJ101: =I101 -> 240 | AL101: =I101 -> 240 | AP101: =I101 -> 240 | AU101: =I101 -> 240 | AV101: =AV100+AU101 -> 109124
...

Sheet 布料MA
B2: 9561魔法小鸟IC MA
B3: 日期 | C3: MA订单号码 | D3: ITEM | E3: 名称 | F3: MA数量 | G3: 要求交货日期 | H3: IC 供应商 | I3: IC编号 | J3: 备注
B4: 45623 | C4: MA-RR-1459 | D4: 9561 | E4: IC | F4: 1000 | G4: 45638 | H4: 矽源特 | I4: CST2403170-13A MH 6118SOP-8 MHW 233B SOP23-6 MH261AA SOT-23 | J4: 开PP使用
B5: 45650 | C5: MA-RR-1491 | D5: 9561 | E5: IC | F5: 40000 | G5: 45665 | H5: 矽源特 | I5: CST2403170-13A MH 6118SOP-8 MHW 233B SOP23-6 MH261AA SOT-23
B6: 45673 | C6: MA-RR-1523 | D6: 9561 | E6: IC | F6: 40000 | G6: 45714 | H6: 矽源特 | I6: CST2403170-13A MH 6118SOP-8 MHW 233B SOP23-6 MH261AA SOT-23
B7: 45714 | C7: MA-RR-1563 | D7: 9561 | E7: IC | F7: 119000 | G7: 45729 | H7: 矽源特 | I7: CST2403170-13A MH 6118SOP-8 MHW 233B SOP23-6 MH261AA SOT-23
B8: 45735 | C8: MA-RR-1598 | D8: 9561 | E8: IC | F8: 120000 | G8: 45760 | H8: 矽源特 | I8: CST2403170-13A MH 6118SOP-8 MHW 233B SOP23-6 MH261AA SOT-23
B9: 45790 | C9: MA-RR-1654 | D9: 9561 | E9: IC | F9: 80000 | G9: 45805 | H9: 矽源特 | I9: CST2403170-13A MH 6118SOP-8 MHW 233B SOP23-6 MH261AA SOT-23
B10: 45803 | C10: MA-RR-1685 | D10: 9561 | E10: IC | F10: 100000 | G10: 45828 | H10: 矽源特 | I10: CST2403170-13A MH 6118SOP-8 MHW 233B SOP23-6 MH261AA SOT-23
B11: 45804 | C11: MA-RR-1689 | D11: 9561 | E11: IC | F11: 50000 | G11: 45829 | H11: 矽源特 | I11: CST2403170-13A MH 6118SOP-8 MHW 233B SOP23-6 MH261AA SOT-23
B12: 45824 | C12: MA-RR-1736 | D12: 9561 | E12: IC | F12: 100000 | G12: 45844 | H12: 矽源特 | I12: CST2403170-13A MH 6118SOP-8 MHW 233B SOP23-6 MH261AA SOT-23
B13: 45846 | C13: MA-RR-1780 | D13: 9561 | E13: IC | F13: 80000 | G13: 45866 | H13: 矽源特 | I13: CST2403170-13A MH 6118SOP-8 MHW 233B SOP23-6 MH261AA SOT-23
B14: 45999 | C14: MA-RR-1997 | D14: 9561 | E14: IC | F14: 30000 | G14: 46036 | H14: 矽源特 | I14: CST2403170-13A MH 6118SOP-8 MHW 233B SOP23-6 MH261AA SOT-23
B15: 46015 | C15: MA-RR-2017 | D15: 9561 | E15: IC | F15: 40000 | G15: 46035 | H15: 矽源特 | I15: CST2403170-13A MH 6118SOP-8 MHW 233B SOP23-6 MH261AA SOT-23
B16: 46031 | C16: MA-RR-2048 | D16: 9561 | E16: IC | F16: 60000 | G16: 46042 | H16: 矽源特 | I16: CST2403170-13A MH 6118SOP-8 MHW 233B SOP23-6 MH261AA SOT-23
... B21: 46169 | C21: MA-RR-2328 | D21: 9561 | E21: IC | F21: 80000 | G21: 46209 | H21: 矽源特 | I21: CST2403170-13A MH 6118SOP-8 MHW 233B SOP23-6 MH261AA SOT-23
E23: 合计 | F23: =SUM(F4:F22) -> 1150000
E24: 半成品MA数 | F24: =G52 -> 0
E25: 接单总数 | F25: ='9561'!I727 -> 974175
E26: 按实单扣数的IC MA剩余 | F26: =F23-F25 -> 175825
E27: 按半成品MA扣数的IC MA剩余 | F27: =F23-F24 -> 1150000
B31: 9561魔法小鸟 半成品生产MA
B32: 日期 | C32: MA订单号码 | D32: ITEM | E32: 名称 | H32: 合计 | I32: 要求完成日期 | J32: 备注
B33: 45706 | C33: MA_RR_1522 | D33: 9561 | E33: 魔法小鸟 | H33: 200000 | I33: 45767 | J33: 胶件
B34: 45735 | C34: MA-RR-1597 | D34: 9561 | E34: 魔法小鸟 | H34: 120000 | I34: 45794 | J34: 胶件
B35: 45789 | C35: MA-RR-1651 | D35: 9561 | E35: 魔法小鸟 | H35: 80000 | I35: 45849 | J35: 胶件
B36: 45803 | C36: MA-RR-1679 | D36: 9561 | E36: 魔法小鸟 | H36: 100000 | I36: 45859 | J36: 胶件
B37: 45824 | C37: MA-RR-1735 | D37: 9561 | E37: 魔法小鸟 | H37: 150000 | I37: 45884 | J37: 胶件
B38: 45846 | C38: MA-RR-1779 | D38: 9561 | E38: 魔法小鸟 | H38: 80000 | I38: 45906 | J38: 胶件
B39: 45999 | C39: MA-RR-1992 | D39: 9561 | E39: 魔法小鸟 | H39: 30000 | I39: 46047 | J39: 胶件
B40: 46015 | C40: MA-RR-2018 | D40: 9561 | E40: 魔法小鸟 | H40: 40000 | I40: 46079 | J40: 胶件
B41: 46057 | C41: MA-RR-2107 | D41: 9561 | E41: 魔法小鸟 | H41: 60000 | I41: 46143 | J41: 胶件
B42: 46090 | C42: MA-RR-2165 | D42: 9561 | E42: 魔法小鸟 | H42: 40000 | I42: 46150 | J42: 胶件
B43: 46094 | C43: MA-RR-2192 | D43: 9561 | E43: 魔法小鸟 | H43: 60000 | I43: 46186 | J43: 胶件
B44: 46140 | C44: MA-RR-2266 | D44: 9561 | E44: 魔法小鸟 | H44: 20000 | I44: 46234 | J44: 胶件
... B46: 46167 | C46: MA-RR-2321 | D46: 9561 | E46: 魔法小鸟 | H46: 30000 | I46: 46259 | J46: 胶件
E52: MA合计 | H52: =SUM(H33:H51) -> 1070000
G53: 接单总数 | H53: ='9561'!I727 -> 974175
G54: MA剩余 | H54: =H52-H53 -> 95825
G55: MA剩余占MA数比率 | H55: =H54/H52 -> 0.089556075
B62: 9561魔法小鸟 车缝MA
B63: 日期 | C63: MA订单号码 | D63: ITEM | E63: 名称 | F63: MA布标 （可按此数量订购MA布标并车缝） | G63: WM布标 | H63: 合计 | I63: 要求完成日期 | J63: 备注
B64: 45623 | C64: MA-RR-1443 | D64: 9561 | E64: 布料MA | F64: 80000 | H64: =F64 -> 80000 | I64: 45658
B65: 45706 | C65: MA-RR-1522 | D65: 9561 | E65: 布料MA | F65: 200000 | H65: 200000 | I65: 45767
B66: 45735 | C66: MA-RR-1597 | D66: 9561 | E66: 布料MA | F66: 40000 | H66: 40000 | I66: 45794
B67: 45792 | C67: MA-RR-1651 | D67: 9561 | E67: 布料MA | F67: 80000 | H67: 80000 | I67: 45849
B68: 45803 | C68: MA-RR-1679 | D68: 9561 | E68: 布料MA | F68: 100000 | H68: 100000 | I68: 45859
B69: 45824 | C69: MA-RR-1735 | D69: 9561 | E69: 布料MA | F69: 150000 | H69: 150000 | I69: 45884
B70: 45846 | C70: MA-RR-1779 | D70: 9561 | E70: 布料MA | F70: 80000 | H70: 80000 | I70: 45906 | K70: 多备15W
B71: 45999 | C71: MA-RR-1992 | D71: 9561 | E71: 布料MA | F71: 70000 | H71: 70000 | I71: 46047
B72: 46057 | C72: MA-RR-2107 | D72: 9561 | E72: 布料MA | F72: 60000 | H72: 60000 | I72: 46143
B73: 46094 | C73: MA-RR-2192 | D73: 9561 | E73: 布料MA | F73: 60000 | H73: 60000 | I73: 46186
B74: 46140 | C74: MA-RR-2266 | D74: 9561 | E74: 布料MA | F74: 60000 | H74: 60000 | I74: 46216
B75: 46162 | C75: MA-RR-2312 | D75: 9561 | E75: 布料MA | F75: 50000 | H75: 60000 | I75: 46247
B76: 46167 | C76: MA-RR-2321 | D76: 9561 | E76: 布料MA | F76: 30000 | H76: 30000 | I76: 46259
E80: MA合计 | F80: =SUM(F64:F79) -> 1060000 | G80: =SUM(G64:G70) -> 0 | H80: =SUM(H64:H77) -> 1070000
G81: 接单总数 | H81: =H53 -> 974175
G82: MA剩余 | H82: =H80-H81 -> 95825
G83: MA剩余占MA数比率 | H83: =H82/H80 -> 0.089556075

Sheet 包装MA
A2: 日期
C3: 名称 | D3: 包装名称 | E3: MA订单号码 | F3: 货号 | G3: 数量 | H3: 语言 | I3: 版本号 | J3: 镭射贴纸 | K3: 纸卡A版 | L3: 纸卡B版 | M3: 珍珠棉 | N3: 收藏指南A | O3: 收藏指南B | P3: 说明书A | Q3: 说明书B | R3: 收缩膜1L | S3: 收缩膜1LB版本 | T3: 收缩膜5L | U3: 收缩膜5LB版本 | V3: 客版收缩膜 | W3: 客版说明书 | X3: 客版收藏指南 | Y3: Endcap EC展架1L | Z3: Endcap EC展架3L | AA3: PLD展示架
A4: 45708 | C4: S001-PETS ALIVE-MAGIC BIRD-SERIES 1-MAGIC BIRD SURPRISE PLAYSET-SHRINK WRAP-4PCS/CTN | D4: Logo贴纸（无语言） | E4: 1000025855 | F4: 9561 | G4: 100000 | H4: 无语言 | I4: A | J4: 100000
A5: 45708 | C5: S001-PETS ALIVE-MAGIC BIRD-SERIES 1-MAGIC BIRD SURPRISE PLAYSET-SHRINK WRAP-4PCS/CTN | D5: 围卡 | E5: 1000025856 | F5: 9561 | G5: 100000 | H5: 无语言 | I5: A | K5: 100000
A6: 45708 | C6: S001-PETS ALIVE-MAGIC BIRD-SERIES 1-MAGIC BIRD SURPRISE PLAYSET-SHRINK WRAP-4PCS/CTN | D6: 珍珠膜 | E6: 1000025857 | F6: 9561 | G6: 100000 | H6: 无语言 | I6: A | M6: 100000
A7: 45708 | C7: S001-PETS ALIVE-MAGIC BIRD-SERIES 1-MAGIC BIRD SURPRISE PLAYSET-SHRINK WRAP-4PCS/CTN | D7: 说明书- (大张) | E7: 1000025858 | F7: 9561 | G7: 100000 | H7: 6L | I7: A | N7: 100000
A8: 45708 | C8: S001-PETS ALIVE-MAGIC BIRD-SERIES 1-MAGIC BIRD SURPRISE PLAYSET-SHRINK WRAP-4PCS/CTN | D8: 说明书-（小张) | E8: 1000025859 | F8: 9561 | G8: 100000 | H8: 5L+6L | I8: A | P8: 100000
A9: 45708 | C9: S001-PETS ALIVE-MAGIC BIRD-SERIES 1-MAGIC BIRD SURPRISE PLAYSET-SHRINK WRAP-4PCS/CTN | D9: 收缩套 | E9: 1000025860 | F9: 9561 | G9: 100000 | H9: 1L | I9: A | R9: 100000
A10: 45708 | C10: S001-PETS ALIVE-MAGIC BIRD-SERIES 1-MAGIC BIRD SURPRISE PLAYSET-SHRINK WRAP-4PCS/CTN | D10: 收缩套 | E10: 1000025861 | F10: 9561 | G10: 30000 | H10: 5L+6L | I10: A | T10: 30000
A11: 45708 | C11: S001-PETS ALIVE-MAGIC BIRD-SERIES 1-MAGIC BIRD SURPRISE PLAYSET-SHRINK WRAP-4PCS/CTN | D11: 展示架 | E11: 1000026887 | F11: 9561 | G11: 300 | H11: 1L | I11: A | Y11: 300
A12: 45768 | C12: S001-PETS ALIVE-MAGIC BIRD-SERIES 1-MAGIC BIRD SURPRISE PLAYSET-SHRINK WRAP-4PCS/CTN | D12: Logo贴纸（无语言） | F12: 9561 | G12: 30000 | H12: 无语言 | I12: A | J12: =G12 -> 30000
A13: 45768 | C13: S001-PETS ALIVE-MAGIC BIRD-SERIES 1-MAGIC BIRD SURPRISE PLAYSET-SHRINK WRAP-4PCS/CTN | D13: 围卡 | F13: 9561 | G13: 30000 | H13: 无语言 | I13: A | K13: =G13 -> 30000
A14: 45768 | C14: S001-PETS ALIVE-MAGIC BIRD-SERIES 1-MAGIC BIRD SURPRISE PLAYSET-SHRINK WRAP-4PCS/CTN | D14: 珍珠膜 | F14: 9561 | G14: 30000 | H14: 无语言 | I14: A | M14: =G14 -> 30000
A15: 45768 | C15: S001-PETS ALIVE-MAGIC BIRD-SERIES 1-MAGIC BIRD SURPRISE PLAYSET-SHRINK WRAP-4PCS/CTN | D15: 说明书- (大张) | E15: 1000027277 | F15: 9561 | G15: 30000 | H15: 6L | I15: A | N15: =G15 -> 30000
A16: 45768 | C16: S001-PETS ALIVE-MAGIC BIRD-SERIES 1-MAGIC BIRD SURPRISE PLAYSET-SHRINK WRAP-4PCS/CTN | D16: 说明书-（小张) | E16: 1000027278 | F16: 9561 | G16: 30000 | H16: 5L+6L | I16: A | P16: =G16 -> 30000
A17: 45768 | C17: S001-PETS ALIVE-MAGIC BIRD-SERIES 1-MAGIC BIRD SURPRISE PLAYSET-SHRINK WRAP-4PCS/CTN | D17: 收缩套 | E17: 1000027279 | F17: 9561 | G17: 15000 | H17: 5L+6L | I17: A | T17: =G17 -> 15000
A18: 45768 | C18: S001-PETS ALIVE-MAGIC BIRD-SERIES 1-MAGIC BIRD SURPRISE PLAYSET-SHRINK WRAP-4PCS/CTN | D18: 展示架 | E18: 1000027284 | F18: 9561 | G18: 500 | H18: 3L | I18: A | Z18: =G18 -> 500
A19: 45784 | C19: S001-PETS ALIVE-MAGIC BIRD-SERIES 1-MAGIC BIRD SURPRISE PLAYSET-SHRINK WRAP-4PCS/CTN | D19: Logo贴纸（无语言） | E19: 1000027683 | F19: 9561 | G19: 50000 | H19: 无语言 | J19: =G19 -> 50000
A20: 45789 | C20: S001-PETS ALIVE-MAGIC BIRD-SERIES 1-MAGIC BIRD SURPRISE PLAYSET-SHRINK WRAP-4PCS/CTN | D20: 围卡 | E20: 1000028378 | F20: 9561 | G20: 50000 | H20: 无语言 | I20: A | K20: =G20 -> 50000
A21: 45784 | C21: S001-PETS ALIVE-MAGIC BIRD-SERIES 1-MAGIC BIRD SURPRISE PLAYSET-SHRINK WRAP-4PCS/CTN | D21: 珍珠膜 | E21: 1000027685 | F21: 9561 | G21: 50000 | H21: 无语言 | M21: =G21 -> 50000
A22: 45784 | C22: S001-PETS ALIVE-MAGIC BIRD-SERIES 1-MAGIC BIRD SURPRISE PLAYSET-SHRINK WRAP-4PCS/CTN | D22: 说明书- (大张) | E22: 1000028375 | F22: 9561 | G22: 50000 | H22: 6L | I22: A | N22: =G22 -> 50000
A23: 45784 | C23: S001-PETS ALIVE-MAGIC BIRD-SERIES 1-MAGIC BIRD SURPRISE PLAYSET-SHRINK WRAP-4PCS/CTN | D23: 说明书-（小张) | E23: 1000028376 | F23: 9561 | G23: 50000 | H23: 5L+6L | I23: A | P23: =G23 -> 50000
A24: 45784 | C24: S001-PETS ALIVE-MAGIC BIRD-SERIES 1-MAGIC BIRD SURPRISE PLAYSET-SHRINK WRAP-4PCS/CTN | D24: 收缩套 | E24: 1000028377 | F24: 9561 | G24: 50000 | H24: 5L+6L | I24: A | T24: =G24 -> 50000
A25: 45784 | C25: S001-PETS ALIVE-MAGIC BIRD-SERIES 1-MAGIC BIRD SURPRISE PLAYSET-SHRINK WRAP-4PCS/CTN | D25: 展示架 | E25: 1000027689 | F25: 9561 | G25: 300 | H25: 3L | Z25: 300
A26: 45792 | C26: S001-PETS ALIVE-MAGIC BIRD-SERIES 1-MAGIC BIRD SURPRISE PLAYSET-SHRINK WRAP-4PCS/CTN | D26: 围卡 | E26: 1000027905 | F26: 9561 | G26: 50000 | H26: 无语言 | I26: A | K26: =G26 -> 50000
A27: 45792 | C27: S001-PETS ALIVE-MAGIC BIRD-SERIES 1-MAGIC BIRD SURPRISE PLAYSET-SHRINK WRAP-4PCS/CTN | D27: 说明书- (大张) | E27: 1000027906 | F27: 9561 | G27: 50000 | H27: 6L | I27: A | N27: =G27 -> 50000
A28: 45792 | C28: S001-PETS ALIVE-MAGIC BIRD-SERIES 1-MAGIC BIRD SURPRISE PLAYSET-SHRINK WRAP-4PCS/CTN | D28: 说明书-（小张) | E28: 1000027907 | F28: 9561 | G28: 50000 | H28: 5L+6L | I28: A | P28: =G28 -> 50000
A29: 45792 | C29: S001-PETS ALIVE-MAGIC BIRD-SERIES 1-MAGIC BIRD SURPRISE PLAYSET-SHRINK WRAP-4PCS/CTN | D29: 收缩套 | E29: 1000027908 | F29: 9561 | G29: 40000 | H29: 5L+6L | I29: A | T29: =G29 -> 40000
A30: 45803 | C30: S001-PETS ALIVE-MAGIC BIRD-SERIES 1-MAGIC BIRD SURPRISE PLAYSET-SHRINK WRAP-4PCS/CTN | D30: Logo贴纸（无语言） | E30: 1000028408 | F30: 9561 | G30: 150000 | H30: 无语言 | I30: A | J30: =G30 -> 150000
A31: 45803 | C31: S001-PETS ALIVE-MAGIC BIRD-SERIES 1-MAGIC BIRD SURPRISE PLAYSET-SHRINK WRAP-4PCS/CTN | D31: 围卡 | E31: 1000028397 | F31: 9561 | G31: 100000 | H31: 无语言 | I31: A | K31: =G31 -> 100000
A32: 45803 | C32: S001-PETS ALIVE-MAGIC BIRD-SERIES 1-MAGIC BIRD SURPRISE PLAYSET-SHRINK WRAP-4PCS/CTN | D32: 珍珠膜 | E32: 1000028398 | F32: 9561 | G32: 150000 | H32: 无语言 | I32: A | M32: =G32 -> 150000
A33: 45803 | C33: S001-PETS ALIVE-MAGIC BIRD-SERIES 1-MAGIC BIRD SURPRISE PLAYSET-SHRINK WRAP-4PCS/CTN | D33: 说明书- (大张) | E33: 1000028399 | F33: 9561 | G33: 60000 | H33: 6L | I33: A | N33: =G33 -> 60000
A34: 45803 | C34: S001-PETS ALIVE-MAGIC BIRD-SERIES 1-MAGIC BIRD SURPRISE PLAYSET-SHRINK WRAP-4PCS/CTN | D34: 说明书-（小张) | E34: 1000028400 | F34: 9561 | G34: 60000 | H34: 5L+6L | I34: A | P34: =G34 -> 60000
A35: 45803 | C35: S001-PETS ALIVE-MAGIC BIRD-SERIES 1-MAGIC BIRD SURPRISE PLAYSET-SHRINK WRAP-4PCS/CTN | D35: 收缩套 | E35: 1000028401 | F35: 9561 | G35: 150000 | H35: 1L | I35: A | R35: =G35 -> 150000
A36: 45828 | C36: S001-PETS ALIVE-MAGIC BIRD-SERIES 1-MAGIC BIRD SURPRISE PLAYSET-SHRINK WRAP-4PCS/CTN | D36: Logo贴纸（无语言） | E36: 1000029192 | F36: 9561 | G36: 150000 | H36: 无语言 | I36: A | J36: =G36 -> 150000
A37: 45828 | C37: S001-PETS ALIVE-MAGIC BIRD-SERIES 1-MAGIC BIRD SURPRISE PLAYSET-SHRINK WRAP-4PCS/CTN | D37: 围卡 | E37: 1000029194 | F37: 9561 | G37: 200000 | H37: 无语言 | I37: B | L37: =G37 -> 200000
A38: 45828 | C38: S001-PETS ALIVE-MAGIC BIRD-SERIES 1-MAGIC BIRD SURPRISE PLAYSET-SHRINK WRAP-4PCS/CTN | D38: 珍珠膜 | E38: 1000029193 | F38: 9561 | G38: 200000 | H38: 无语言 | I38: A | M38: =G38 -> 200000
A39: 45828 | C39: S001-PETS ALIVE-MAGIC BIRD-SERIES 1-MAGIC BIRD SURPRISE PLAYSET-SHRINK WRAP-4PCS/CTN | D39: 说明书- (大张) | E39: 1000029195 | F39: 9561 | G39: 200000 | H39: 6L | I39: B | O39: =G39 -> 200000
A40: 45828 | C40: S001-PETS ALIVE-MAGIC BIRD-SERIES 1-MAGIC BIRD SURPRISE PLAYSET-SHRINK WRAP-4PCS/CTN | D40: 说明书-（小张) | E40: 1000029196 | F40: 9561 | G40: 200000 | H40: 5L+6L | I40: B | Q40: =G40 -> 200000
A41: 45828 | C41: S001-PETS ALIVE-MAGIC BIRD-SERIES 1-MAGIC BIRD SURPRISE PLAYSET-SHRINK WRAP-4PCS/CTN | D41: 收缩套 | E41: 1000029197 | F41: 9561 | G41: 100000 | H41: 1L | I41: B | S41: =G41 -> 100000
A42: 45828 | C42: S001-PETS ALIVE-MAGIC BIRD-SERIES 1-MAGIC BIRD SURPRISE PLAYSET-SHRINK WRAP-4PCS/CTN | D42: 收缩套 | E42: 1000029198 | F42: 9561 | G42: 100000 | H42: 5L+6L | I42: B | U42: =G42 -> 100000
A43: 45846 | C43: S001-PETS ALIVE-MAGIC BIRD-SERIES 1-MAGIC BIRD SURPRISE PLAYSET-SHRINK WRAP-4PCS/CTN | D43: Logo贴纸（无语言） | E43: 1000029922 | F43: 9561 | G43: 100000 | H43: 无语言 | I43: A | J43: =G43 -> 100000
A44: 45846 | C44: S001-PETS ALIVE-MAGIC BIRD-SERIES 1-MAGIC BIRD SURPRISE PLAYSET-SHRINK WRAP-4PCS/CTN | D44: 围卡 | E44: 1000029923 | F44: 9561 | G44: 100000 | H44: 无语言 | I44: B | L44: =G44 -> 100000
A45: 45846 | C45: S001-PETS ALIVE-MAGIC BIRD-SERIES 1-MAGIC BIRD SURPRISE PLAYSET-SHRINK WRAP-4PCS/CTN | D45: 珍珠膜 | E45: 1000029924 | F45: 9561 | G45: 150000 | H45: 无语言 | I45: A | M45: =G45 -> 150000
A46: 45846 | C46: S001-PETS ALIVE-MAGIC BIRD-SERIES 1-MAGIC BIRD SURPRISE PLAYSET-SHRINK WRAP-4PCS/CTN | D46: 说明书- (大张) | E46: 1000029925 | F46: 9561 | G46: 100000 | H46: 6L | I46: B | O46: =G46 -> 100000
A47: 45846 | C47: S001-PETS ALIVE-MAGIC BIRD-SERIES 1-MAGIC BIRD SURPRISE PLAYSET-SHRINK WRAP-4PCS/CTN | D47: 说明书-（小张) | E47: 1000029926 | F47: 9561 | G47: 100000 | H47: 5L+6L | I47: B | Q47: =G47 -> 100000
A48: 45846 | C48: S001-PETS ALIVE-MAGIC BIRD-SERIES 1-MAGIC BIRD SURPRISE PLAYSET-SHRINK WRAP-4PCS/CTN | D48: 收缩套 | E48: 1000029927 | F48: 9561 | G48: 150000 | H48: 1L | I48: B | S48: =G48 -> 150000
A49: 45846 | C49: S001-PETS ALIVE-MAGIC BIRD-SERIES 1-MAGIC BIRD SURPRISE PLAYSET-SHRINK WRAP-4PCS/CTN | D49: 收缩套 | E49: 1000029928 | F49: 9561 | G49: 50000 | H49: 5L+6L | I49: B | U49: =G49 -> 50000
A50: 45930 | C50: S001-PETS ALIVE-MAGIC BIRD-MAGIC BIRD SURPRISE PLAYSET,S1,SHRINK WRAP,4PC | D50: 说明书- (大张) | E50: 1000032708 | F50: 9561 | G50: 3000 | H50: 5L+6L | I50: B | W50: 3000
A51: 45930 | C51: S001-PETS ALIVE-MAGIC BIRD-MAGIC BIRD SURPRISE PLAYSET,S1,SHRINK WRAP,5PC | D51: 说明书-（小张) | E51: 1000032740 | F51: 9561 | G51: 3000 | H51: 5L+6L | I51: B | X51: 3000
A52: 45999 | D52: Logo贴纸（无语言） | E52: 1000034839 | F52: 9561 | G52: 100000 | H52: 无语言 | I52: A | J52: 100000
A53: 45999 | D53: 围卡 | E53: 1000034840 | F53: 9561 | G53: 80000 | H53: 无语言 | I53: B | L53: 80000
A54: 45999 | D54: 说明书- (大张) | E54: 1000034841 | F54: 9561 | G54: 50000 | H54: 6L | I54: B | Q54: 50000
A55: 45999 | D55: 说明书-（小张) | E55: 1000034842 | F55: 9561 | G55: 50000 | H55: 5L+6L | I55: B | O55: 50000
A56: 45999 | D56: 收缩套 | E56: 1000034843 | F56: 9561 | G56: 70000 | H56: 1L | I56: B | S56: 70000
A57: 46015 | D57: Logo贴纸（无语言） | E57: 1000035130 | F57: 9561 | G57: 30000 | H57: 无语言 | I57: A | J57: 30000
A58: 46015 | D58: 珍珠膜 | E58: 1000035131 | F58: 9561 | G58: 30000 | H58: 无语言 | I58: A | M58: 30000
A59: 46049 | D59: 收缩套 | E59: 1000036228 | F59: 9561 | G59: 30000 | H59: 1L | I59: B | S59: 30000
A60: 46081 | D60: Logo贴纸（无语言） | E60: TBA | F60: 9561 | G60: 60000 | H60: 无语言 | I60: A | J60: 60000
A61: 46081 | D61: 围卡 | E61: TBA | F61: 9561 | G61: 60000 | H61: 无语言 | I61: B | M61: 60000
A62: 46081 | D62: 珍珠膜 | E62: TBA | F62: 9561 | G62: 60000 | H62: 无语言 | I62: A | L62: 60000
A63: 46081 | D63: 说明书- (大张) | E63: 1000036698 | F63: 9561 | G63: 50000 | H63: 6L | I63: B | O63: 50000
A64: 46081 | D64: 说明书-（小张) | E64: 1000036699 | F64: 9561 | G64: 50000 | H64: 5L+6L | I64: B | Q64: 50000
A65: 46081 | D65: 收缩套 | E65: 1000036700 | F65: 9561 | G65: 60000 | H65: 1L | I65: B | S65: 60000
A66: 46129 | D66: 说明书- (大张) | E66: 1000038809 | F66: 9561 | G66: 60000 | H66: 6L | I66: B | O66: 60000
A67: 46129 | D67: 说明书-（小张) | E67: 1000038810 | F67: 9561 | G67: 60000 | H67: 5L+6L | I67: B | Q67: 60000
A68: 46190 | D68: 收缩套 | E68: 1000041506 | F68: 9561 | G68: 20000 | H68: 1L | I68: B | S68: 20000
A69: 46198 | D69: 展示架 | E69: 1000041740 | F69: 9561 | G69: 1833 | H69: 1L | I69: A | AA69: =G69 -> 1833
A70: 46203 | D70: 说明书- (大张) | E70: 1000041957 | F70: 9561 | G70: 200000 | H70: 6L | I70: B | O70: 200000
A71: 46203 | D71: 说明书-（小张) | E71: 1000041958 | F71: 9561 | G71: 200000 | H71: 5L+6L | I71: B | Q71: 200000
A72: 46226 | D72: 收缩套 | E72: 1000043080 | F72: 9561 | G72: 60000 | H72: 1L | I72: B | S72: =G72 -> 60000
I73: 合计 | J73: =SUM(J4:J69) -> 770000 | K73: =SUM(K4:K69) -> 330000 | L73: =SUM(L13:L69) -> 440000 | M73: =SUM(M6:M69) -> 770000 | N73: =SUM(N6:N35) -> 290000 | O73: =SUM(O13:O71) -> 660000 | P73: =SUM(P6:P35) -> 290000 | Q73: =SUM(Q13:Q71) -> 660000 | R73: =SUM(R6:R35) -> 250000 | S73: =SUM(S4:S72) -> 490000 | T73: =SUM(T6:T29) -> 135000 | U73: =SUM(U4:U69) -> 150000 | V73: =SUM(V6:V25) -> 0 | W73: =SUM(W6:W25) -> 0 | Y73: =SUM(Y4:Y25) -> 300 | Z73: =SUM(Z6:Z25) -> 800
I74: 总接单数 | J74: ='9561'!I727 -> 974175 | K74: ='9561'!AP727 -> 332086 | L74: ='9561'!AQ727 -> 453015 | M74: ='9561'!I727 -> 974175 | N74: ='9561'!AL726 -> 284472 | O74: ='9561'!AM727 -> 596833 | P74: ='9561'!AL726 -> 284472 | Q74: ='9561'!AM727 -> 596833 | R74: ='9561'!AF726 -> 236566 | S74: ='9561'!AI726 -> 541614 | T74: ='9561'!AJ726 -> 122984 | U74: ='9561'!AK726 -> 92595 | V74: ='9561'!AH726 -> 0 | W74: ='9561'!AO727 -> 87028 | Y74: ='9561'!AR727 -> 83 | Z74: ='9561'!AS727 -> 754
I75: 剩余数 | J75: =J73-J74 -> -204175 | K75: =K73-K74 -> -2086 | L75: =L73-L74 -> -13015 | M75: =M73-M74 -> -204175 | N75: =N73-N74 -> 5528 | O75: =O73-O74 -> 63167 | P75: =P73-P74 -> 5528 | Q75: =Q73-Q74 -> 63167 | ... W75: =W73-W74 -> -87028 | Y75: =Y73-Y74 -> 217 | Z75: =Z73-Z74 -> 46
H77: 需求数 | U77: =U75-15000 -> 42405

Sheet 取消单
A1: 接单日期 | B1: 第三方客户名称 | C1: 国家 | D1: PO号 | E1: 客PO号 | F1: SKU | G1: 系统货号 | H1: ITEM# | I1: 中文名 | J1: PO数量 (pcs) | K1: 内箱装箱数量(pcs) | L1: 外箱装箱数量(pcs) | M1: 总箱数 | N1: 客PO期 | O1: 验货期 | P1: 第三方验货期 | Q1: 驗貨結果 | R1: 船期SO | S1: 箱唛资料 | T1: 外箱贴纸 | U1: 客贴纸资料 | V1: 布料 | W1: 客供物料 | X1: 日期码 | Y1: 备注 | Z1: ZURU 跟单 | AA1: 单价USD | AB1: 金额USD | AC1: 发票号 | AD1: 是否入系统 | AE1: MA 1L收缩膜 | AF1: MA 5L收缩膜 | AG1: MA 6L说明书 | AH1: MA 5L说明书 | AI1: 客版说明书 | AJ1: 客版收藏指南 | AK1: EC展示架1L | AL1: EC展示架3L | AM1: 布標 | AN1: 合计数量 | AO1: 累计数量
A2: 45747 | B2: Mid-States Distributing, LLC | C2: 美国 | D2: 4500161570 | E2: Murdoch's Southern DC PO 671605134 | F2: 4500161570-270 | G2: 9561-S001 | H2: 9561-S001 | I2: 魔法小鸟 | J2: 12 | K2: 0 | L2: 4 | M2: =J2/L2 -> 3 | N2: 45818 | O2: 45814 | P2: 取消 | S2: 欠 | T2: 无 | U2: 无 | V2: MA | Y2: 日期码格式：ZURU INC(BVI) 标准格式 日期：按实际生产日期 Packaging Info: 1.使用 MA UPC版本包装，优先1L，出口美国。 Remark: 1.产品和包装上印刷tracking code信息，格式为ZURU常规。 2.ZURU QC验货 | Z2: Cara Li | AA2: 5.837 | AB2: =J2*AA2 -> 70.044 | AD2: 已入 | AE2: =J2 -> 12 | AI2: =J2 -> 12 | AP2: =J2 -> 12 | AQ2: ='9561'!AV96+AP2 -> 106660
A3: 45747 | B3: Mid-States Distributing, LLC | C3: 美国 | D3: 4500161570 | E3: Murdoch's Norther DC PO 671605135 | F3: 4500161570-280 | G3: 9561-S001 | H3: 9561-S001 | I3: 魔法小鸟 | J3: 20 | K3: 0 | L3: 4 | M3: =J3/L3 -> 5 | N3: 45818 | O3: 45814 | P3: 取消 | S3: 欠 | T3: 无 | U3: 无 | V3: MA | Y3: 日期码格式：ZURU INC(BVI) 标准格式 日期：按实际生产日期 Packaging Info: 1.使用 MA UPC版本包装，优先1L，出口美国。 Remark: 1.产品和包装上印刷tracking code信息，格式为ZURU常规。 2.ZURU QC验货 | Z3: Cara Li | AA3: 5.837 | AB3: =J3*AA3 -> 116.74 | AD3: 已入 | AE3: =J3 -> 20 | AI3: =J3 -> 20 | AP3: =J3 -> 20 | AQ3: =AQ2+AP3 -> 106680
A4: 45747 | B4: Mid-States Distributing, LLC | C4: 美国 | D4: 4500161570 | E4: Murdoch's TX DC PO 671605136 | F4: 4500161570-290 | G4: 9561-S001 | H4: 9561-S001 | I4: 魔法小鸟 | J4: 8 | K4: 0 | L4: 4 | M4: =J4/L4 -> 2 | N4: 45818 | O4: 45814 | P4: 取消 | S4: 欠 | T4: 无 | U4: 无 | V4: MA | Y4: 日期码格式：ZURU INC(BVI) 标准格式 日期：按实际生产日期 Packaging Info: 1.使用 MA UPC版本包装，优先1L，出口美国。 Remark: 1.产品和包装上印刷tracking code信息，格式为ZURU常规。 2.ZURU QC验货 | Z4: Cara Li | AA4: 5.837 | AB4: =J4*AA4 -> 46.696 | AD4: 已入 | AE4: =J4 -> 8 | AI4: =J4 -> 8 | AP4: =J4 -> 8 | AQ4: =AQ3+AP4 -> 106688
A5: 45789 | B5: MEIJER DISTRIBUTION, INC. | C5: 美国 | D5: 4500166083 | E5: 217111784 | F5: 4500166083-40 | G5: 9561-S004 | H5: 9561-S004 | I5: 魔法小鸟 | J5: 390 | K5: 0 | L5: 2 | M5: =J5/L5 -> 195 | N5: 45820 | O5: 45817 | P5: 转单 | Q5: 6/11取消 | S5: 45796 | T5: 无 | U5: 无 | V5: MA | Y5: 日期码格式：ZURU INC(BVI) 标准格式 日期： Packaging Info: 1. MA 1L 包装 2. 客人指定箱唛排版 Remark: 出货前 Zuru QC 验货 | Z5: Cherie Li | AA5: 3.5022 | AB5: =J5*AA5 -> 1365.858 | AD5: 已入 | AE5: =J5 -> 390 | AK5: =J5 -> 390 | AO5: =J5 -> 390 | AT5: =J5 -> 390 | AU5: ='9561'!AV81+AT5 -> 89230
A6: 45796 | B6: WALMART INC. | C6: 美国 | D6: 4500166835 | E6: 0906596177 | F6: 4500166835-10 | G6: 9561-S002 | H6: 9561-S002 | I6: 魔法小鸟 | J6: 626 | K6: 0 | L6: 1 | M6: =J6/L6 -> 626 | N6: 45831 | O6: 45827 | P6: 客户取消 | Q6: 6/13取消 | S6: 45754 | T6: 无 | U6: 5/26客供贴纸 | V6: MA | Y6: 日期码格式：ZURU DGYYYYMMDD CHINA(日期避开周末和法定节假日即可） 日期：按实际生产日期 Packaging Info: 9561-S002 1.包装要求： MA 1L B版收缩膜+MA 5L B版收藏指南+MA Guide B版book+ MA 8L B版拉丝沙袋 每pcs产品上要贴1张RFID贴纸，贴纸由ZURU提供，贴纸位置请严格按照我们签回的签板； Remark: 9561-S002 1.包装要求： MA 1L B版收缩膜+MA 5L B版收藏指南+MA Guide B版book+ MA 8L B版拉丝沙袋 每pcs产品上要贴1张RFID贴纸，贴纸由ZURU提供，贴纸位置请严格按照我们签回的签板； 2. 外箱印刷带条码的RFID箱唛：RFID紫色色带+WM Dept.图标+RFID图标+ITF-14条码，四面右下角印刷ZURU logo, ITFF条码只印刷在正唛一面，在加印的时候确保 条形码能扫描出来，外箱侧面任一角落加印："MADE IN CHINA" 字样； 3. 在产品上和包装上要有日期码、以及要有MADE IN CHINA和ZURU字样； 4. 产品如有扎带口要剪平，不能刮手。 5. 此单需要验货，请多备料 6. 此单以loose carton出货，1pc/CTN | Z6: Maggie Xie | AA6: 3.214 | AB6: =AA6*J6 -> 2011.964 | AD6: 已入 | AE6: =J6 -> 626 | AK6: =J6 -> 626 | AO6: =J6 -> 626 | AT6: =J6 -> 626 | AU6: ='9561'!AV166+AT6 -> 224238
A7: 45796 | B7: WALMART INC. | C7: 美国 | D7: 4500166835 | E7: 0906596188 | F7: 4500166835-20 | G7: 9561-S002 | H7: 9561-S002 | I7: 魔法小鸟 | J7: 500 | K7: 0 | L7: 1 | M7: =J7/L7 -> 500 | N7: 45831 | O7: 45827 | P7: 客户取消 | Q7: 6/13取消 | S7: 45754 | T7: 无 | U7: 5/26客供贴纸 | V7: MA | Y7: 日期码格式：ZURU DGYYYYMMDD CHINA(日期避开周末和法定节假日即可） 日期：按实际生产日期 Packaging Info: 9561-S002 1.包装要求： MA 1L B版收缩膜+MA 5L B版收藏指南+MA Guide B版book+ MA 8L B版拉丝沙袋 每pcs产品上要贴1张RFID贴纸，贴纸由ZURU提供，贴纸位置请严格按照我们签回的签板； Remark: 9561-S002 1.包装要求： MA 1L B版收缩膜+MA 5L B版收藏指南+MA Guide B版book+ MA 8L B版拉丝沙袋 每pcs产品上要贴1张RFID贴纸，贴纸由ZURU提供，贴纸位置请严格按照我们签回的签板； 2. 外箱印刷带条码的RFID箱唛：RFID紫色色带+WM Dept.图标+RFID图标+ITF-14条码，四面右下角印刷ZURU logo, ITFF条码只印刷在正唛一面，在加印的时候确保 条形码能扫描出来，外箱侧面任一角落加印："MADE IN CHINA" 字样； 3. 在产品上和包装上要有日期码、以及要有MADE IN CHINA和ZURU字样； 4. 产品如有扎带口要剪平，不能刮手。 5. 此单需要验货，请多备料 6. 此单以loose carton出货，1pc/CTN | Z7: Maggie Xie | AA7: 3.214 | AB7: =AA7*J7 -> 1607 | AD7: 已入 | AE7: =J7 -> 500 | AK7: =J7 -> 500 | AO7: =J7 -> 500 | AT7: =J7 -> 500 | AU7: =AU6+AT7 -> 224738
A8: 45796 | B8: WALMART INC. | C8: 美国 | D8: 4500166835 | E8: 0906596193 | F8: 4500166835-30 | G8: 9561-S002 | H8: 9561-S002 | I8: 魔法小鸟 | J8: 594 | K8: 0 | L8: 1 | M8: =J8/L8 -> 594 | N8: 45831 | O8: 45827 | P8: 客户取消 | Q8: 6/13取消 | S8: 45754 | T8: 无 | U8: 5/26客供贴纸 | V8: MA | Y8: 日期码格式：ZURU DGYYYYMMDD CHINA(日期避开周末和法定节假日即可） 日期：按实际生产日期 Packaging Info: 9561-S002 1.包装要求： MA 1L B版收缩膜+MA 5L B版收藏指南+MA Guide B版book+ MA 8L B版拉丝沙袋 每pcs产品上要贴1张RFID贴纸，贴纸由ZURU提供，贴纸位置请严格按照我们签回的签板； Remark: 9561-S002 1.包装要求： MA 1L B版收缩膜+MA 5L B版收藏指南+MA Guide B版book+ MA 8L B版拉丝沙袋 每pcs产品上要贴1张RFID贴纸，贴纸由ZURU提供，贴纸位置请严格按照我们签回的签板； 2. 外箱印刷带条码的RFID箱唛：RFID紫色色带+WM Dept.图标+RFID图标+ITF-14条码，四面右下角印刷ZURU logo, ITFF条码只印刷在正唛一面，在加印的时候确保 条形码能扫描出来，外箱侧面任一角落加印："MADE IN CHINA" 字样； 3. 在产品上和包装上要有日期码、以及要有MADE IN CHINA和ZURU字样； 4. 产品如有扎带口要剪平，不能刮手。 5. 此单需要验货，请多备料 6. 此单以loose carton出货，1pc/CTN | Z8: Maggie Xie | AA8: 3.214 | AB8: =AA8*J8 -> 1909.116 | AD8: 已入 | AE8: =J8 -> 594 | AK8: =J8 -> 594 | AO8: =J8 -> 594 | AT8: =J8 -> 594 | AU8: =AU7+AT8 -> 225332
A9: 45796 | B9: WALMART INC. | C9: 美国 | D9: 4500166835 | E9: 0906596238 | F9: 4500166835-40 | G9: 9561-S002 | H9: 9561-S002 | I9: 魔法小鸟 | J9: 500 | K9: 0 | L9: 1 | M9: =J9/L9 -> 500 | N9: 45831 | O9: 45827 | P9: 客户取消 | Q9: 6/13取消 | S9: 45754 | T9: 无 | U9: 5/26客供贴纸 | V9: MA | Y9: 日期码格式：ZURU DGYYYYMMDD CHINA(日期避开周末和法定节假日即可） 日期：按实际生产日期 Packaging Info: 9561-S002 1.包装要求： MA 1L B版收缩膜+MA 5L B版收藏指南+MA Guide B版book+ MA 8L B版拉丝沙袋 每pcs产品上要贴1张RFID贴纸，贴纸由ZURU提供，贴纸位置请严格按照我们签回的签板； Remark: 9561-S002 1.包装要求： MA 1L B版收缩膜+MA 5L B版收藏指南+MA Guide B版book+ MA 8L B版拉丝沙袋 每pcs产品上要贴1张RFID贴纸，贴纸由ZURU提供，贴纸位置请严格按照我们签回的签板； 2. 外箱印刷带条码的RFID箱唛：RFID紫色色带+WM Dept.图标+RFID图标+ITF-14条码，四面右下角印刷ZURU logo, ITFF条码只印刷在正唛一面，在加印的时候确保 条形码能扫描出来，外箱侧面任一角落加印："MADE IN CHINA" 字样； 3. 在产品上和包装上要有日期码、以及要有MADE IN CHINA和ZURU字样； 4. 产品如有扎带口要剪平，不能刮手。 5. 此单需要验货，请多备料 6. 此单以loose carton出货，1pc/CTN | Z9: Maggie Xie | AA9: 3.214 | AB9: =AA9*J9 -> 1607 | AD9: 已入 | AE9: =J9 -> 500 | AK9: =J9 -> 500 | AO9: =J9 -> 500 | AT9: =J9 -> 500 | AU9: =AU8+AT9 -> 225832
A10: 45796 | B10: WALMART INC. | C10: 美国 | D10: 4500166835 | E10: 0906596255 | F10: 4500166835-50 | G10: 9561-S002 | H10: 9561-S002 | I10: 魔法小鸟 | J10: 500 | K10: 0 | L10: 1 | M10: =J10/L10 -> 500 | N10: 45831 | O10: 45827 | P10: 客户取消 | Q10: 6/13取消 | S10: 45754 | T10: 无 | U10: 5/26客供贴纸 | V10: MA | Y10: 日期码格式：ZURU DGYYYYMMDD CHINA(日期避开周末和法定节假日即可） 日期：按实际生产日期 Packaging Info: 9561-S002 1.包装要求： MA 1L B版收缩膜+MA 5L B版收藏指南+MA Guide B版book+ MA 8L B版拉丝沙袋 每pcs产品上要贴1张RFID贴纸，贴纸由ZURU提供，贴纸位置请严格按照我们签回的签板； Remark: 9561-S002 1.包装要求： MA 1L B版收缩膜+MA 5L B版收藏指南+MA Guide B版book+ MA 8L B版拉丝沙袋 每pcs产品上要贴1张RFID贴纸，贴纸由ZURU提供，贴纸位置请严格按照我们签回的签板； 2. 外箱印刷带条码的RFID箱唛：RFID紫色色带+WM Dept.图标+RFID图标+ITF-14条码，四面右下角印刷ZURU logo, ITFF条码只印刷在正唛一面，在加印的时候确保 条形码能扫描出来，外箱侧面任一角落加印："MADE IN CHINA" 字样； 3. 在产品上和包装上要有日期码、以及要有MADE IN CHINA和ZURU字样； 4. 产品如有扎带口要剪平，不能刮手。 5. 此单需要验货，请多备料 6. 此单以loose carton出货，1pc/CTN | Z10: Maggie Xie | AA10: 3.214 | AB10: =AA10*J10 -> 1607 | AD10: 已入 | AE10: =J10 -> 500 | AK10: =J10 -> 500 | AO10: =J10 -> 500 | AT10: =J10 -> 500 | AU10: =AU9+AT10 -> 226332
A11: 45793 | B11: WALMART INC. | C11: 美国 | D11: 4500166694 | E11: 0906596204 | F11: 4500166694-10 | G11: 9561-S002 | H11: 9561-S002 | I11: 魔法小鸟 | J11: 500 | K11: 0 | L11: 1 | M11: =J11/L11 -> 500 | N11: 45824 | O11: 45822 | P11: 客户取消 | Q11: 6/13取消 | S11: 45754 | T11: 无 | U11: 5/26客供贴纸 | V11: MA | Y11: 日期码格式：ZURU DGYYYYMMDD CHINA(日期避开周末和法定节假日即可） 日期：按实际生产日期 Packaging Info: 9561-S002 1.包装要求： MA 1L收缩膜+MA 5L 收藏指南+MA Guide book 每pcs产品上要贴1张RFID贴纸，贴纸由ZURU提供，贴纸位置请严格按照我们签回的签板； Remark: 9561-S002 1.包装要求： MA 1L收缩膜+MA 5L 收藏指南+MA Guide book 每pcs产品上要贴1张RFID贴纸，贴纸由ZURU提供，贴纸位置请严格按照我们签回的签板； 2. 外箱印刷带条码的RFID箱唛：RFID紫色色带+WM Dept.图标+RFID图标+ITF-14条码，四面右下角印刷ZURU logo, ITFF条码只印刷在正唛一面，在加印的时候确保 条形码能扫描出来，外箱侧面任一角落加印："MADE IN CHINA" 字样； 3. 在产品上和包装上要有日期码、以及要有MADE IN CHINA和ZURU字样； 4. 产品如有扎带口要剪平，不能刮手。 5. 此单需要验货，请多备料 6. 此单以loose carton出货，1pc/CTN | Z11: Maggie Xie | AA11: 3.214 | AB11: =AA11*J11 -> 1607 | AD11: 已入 | AE11: =J11 -> 500 | AK11: =J11 -> 500 | AO11: =J11 -> 500 | AT11: =J11 -> 500 | AU11: ='9561'!AV229+AT11 -> 327230
A12: 45793 | B12: WALMART INC. | C12: 美国 | D12: 4500166705 | E12: 0906596197 | F12: 4500166705-10 | G12: 9561-S002 | H12: 9561-S002 | I12: 魔法小鸟 | J12: 650 | K12: 0 | L12: 1 | M12: =J12/L12 -> 650 | N12: 45827 | O12: 45824 | P12: 客户取消 | Q12: 6/13取消 | S12: 45754 | T12: 无 | U12: 5/26客供贴纸 | V12: MA | Y12: 日期码格式：ZURU DGYYYYMMDD CHINA(日期避开周末和法定节假日即可） 日期：按实际生产日期 Packaging Info: 9561-S002 1.包装要求： MA 1L收缩膜+MA 5L 收藏指南+MA Guide book 每pcs产品上要贴1张RFID贴纸，贴纸由ZURU提供，贴纸位置请严格按照我们签回的签板； Remark: 9561-S002 1.包装要求： MA 1L收缩膜+MA 5L 收藏指南+MA Guide book 每pcs产品上要贴1张RFID贴纸，贴纸由ZURU提供，贴纸位置请严格按照我们签回的签板； 2. 外箱印刷带条码的RFID箱唛：RFID紫色色带+WM Dept.图标+RFID图标+ITF-14条码，四面右下角印刷ZURU logo, ITFF条码只印刷在正唛一面，在加印的时候确保 条形码能扫描出来，外箱侧面任一角落加印："MADE IN CHINA" 字样； 3. 在产品上和包装上要有日期码、以及要有MADE IN CHINA和ZURU字样； 4. 产品如有扎带口要剪平，不能刮手。 5. 此单需要验货，请多备料 6. 此单以loose carton出货，1pc/CTN | Z12: Maggie Xie | AA12: 3.214 | AB12: =AA12*J12 -> 2089.1 | AD12: 已入 | AE12: =J12 -> 650 | AK12: =J12 -> 650 | AO12: =J12 -> 650 | AT12: =J12 -> 650 | AU12: ='9561'!AV117+AT12 -> 156902
A13: 45774 | B13: WALMART INC. | C13: 美国 | D13: 4500165203 | E13: 0906596178 STATESBORO | F13: 4500165203-10 | G13: 9561-S002 | H13: 9561-S002 | I13: 魔法小鸟 | J13: 500 | K13: 0 | L13: 1 | M13: =J13/L13 -> 500 | N13: 45817 | O13: =N13-4 -> 45813 | P13: 客户取消 | Q13: 6/13取消 | S13: 45754 | T13: 无 | U13: 5/12客供贴纸 | V13: MA | Y13: 日期码格式：ZURU DGYYYYMMDD CHINA(日期避开周末和法定节假日即可） 日期：按实际生产日期 Packaging Info: 9561-S002 1.包装要求： MA 1L收缩膜+MA 5L 收藏指南+MA Guide book +MA 8L Slime bag 每pcs产品上要贴1张RFID贴纸，贴纸由ZURU提供，贴纸位置请严格按照我们签回的签板； Remark: 9561-S002 1.包装要求： MA 1L收缩膜+MA 5L 收藏指南+MA Guide book +MA 8L Slime bag 每pcs产品上要贴1张RFID贴纸，贴纸由ZURU提供，贴纸位置请严格按照我们签回的签板； 2. 外箱印刷带条码的RFID箱唛：RFID紫色色带+WM Dept.图标+RFID图标+ITF-14条码，四面右下角印刷ZURU logo, ITFF条码只印刷在正唛一面，在加印的时候确保 条形码能扫描出来，外箱侧面任一角落加印："MADE IN CHINA" 字样； 3. 在产品上和包装上要有日期码、以及要有MADE IN CHINA和ZURU字样； 4. 产品如有扎带口要剪平，不能刮手。 5. 此单需要验货，请多备料 6. 此单以loose carton出货，1pc/CTN | Z13: Maggie Xie | AA13: 3.214 | AB13: =AA13*J13 -> 1607 | AD13: 已入 | AE13: =J13 -> 500 | AK13: =J13 -> 500 | AO13: =J13 -> 500 | AT13: =J13 -> 500 | AU13: ='9561'!AV90+AT13 -> 102272
A14: 45774 | B14: WALMART INC. | C14: 美国 | D14: 4500165203 | E14: 0906596185 ELWOOD | F14: 4500165203-20 | G14: 9561-S002 | H14: 9561-S002 | I14: 魔法小鸟 | J14: 500 | K14: 0 | L14: 1 | M14: =J14/L14 -> 500 | N14: 45817 | O14: =N14-4 -> 45813 | P14: 客户取消 | Q14: 6/13取消 | S14: 45754 | T14: 无 | U14: 5/12客供贴纸 | V14: MA | Y14: 日期码格式：ZURU DGYYYYMMDD CHINA(日期避开周末和法定节假日即可） 日期：按实际生产日期 Packaging Info: 9561-S002 1.包装要求： MA 1L收缩膜+MA 5L 收藏指南+MA Guide book +MA 8L Slime bag 每pcs产品上要贴1张RFID贴纸，贴纸由ZURU提供，贴纸位置请严格按照我们签回的签板； Remark: 9561-S002 1.包装要求： MA 1L收缩膜+MA 5L 收藏指南+MA Guide book +MA 8L Slime bag 每pcs产品上要贴1张RFID贴纸，贴纸由ZURU提供，贴纸位置请严格按照我们签回的签板； 2. 外箱印刷带条码的RFID箱唛：RFID紫色色带+WM Dept.图标+RFID图标+ITF-14条码，四面右下角印刷ZURU logo, ITFF条码只印刷在正唛一面，在加印的时候确保 条形码能扫描出来，外箱侧面任一角落加印："MADE IN CHINA" 字样； 3. 在产品上和包装上要有日期码、以及要有MADE IN CHINA和ZURU字样； 4. 产品如有扎带口要剪平，不能刮手。 5. 此单需要验货，请多备料 6. 此单以loose carton出货，1pc/CTN | Z14: Maggie Xie | AA14: 3.214 | AB14: =AA14*J14 -> 1607 | AD14: 已入 | AE14: =J14 -> 500 | AK14: =J14 -> 500 | AO14: =J14 -> 500 | AT14: =J14 -> 500 | AU14: =AU13+AT14 -> 102772
A15: 45774 | B15: WALMART INC. | C15: 美国 | D15: 4500165203 | E15: 0906596187 SUFFOLK | F15: 4500165203-30 | G15: 9561-S002 | H15: 9561-S002 | I15: 魔法小鸟 | J15: 514 | K15: 0 | L15: 1 | M15: =J15/L15 -> 514 | N15: 45817 | O15: =N15-4 -> 45813 | P15: 客户取消 | Q15: 6/13取消 | S15: 45754 | T15: 无 | U15: 5/12客供贴纸 | V15: MA | Y15: 日期码格式：ZURU DGYYYYMMDD CHINA(日期避开周末和法定节假日即可） 日期：按实际生产日期 Packaging Info: 9561-S002 1.包装要求： MA 1L收缩膜+MA 5L 收藏指南+MA Guide book +MA 8L Slime bag 每pcs产品上要贴1张RFID贴纸，贴纸由ZURU提供，贴纸位置请严格按照我们签回的签板； Remark: 9561-S002 1.包装要求： MA 1L收缩膜+MA 5L 收藏指南+MA Guide book +MA 8L Slime bag 每pcs产品上要贴1张RFID贴纸，贴纸由ZURU提供，贴纸位置请严格按照我们签回的签板； 2. 外箱印刷带条码的RFID箱唛：RFID紫色色带+WM Dept.图标+RFID图标+ITF-14条码，四面右下角印刷ZURU logo, ITFF条码只印刷在正唛一面，在加印的时候确保 条形码能扫描出来，外箱侧面任一角落加印："MADE IN CHINA" 字样； 3. 在产品上和包装上要有日期码、以及要有MADE IN CHINA和ZURU字样； 4. 产品如有扎带口要剪平，不能刮手。 5. 此单需要验货，请多备料 6. 此单以loose carton出货，1pc/CTN | Z15: Maggie Xie | AA15: 3.2139 | AB15: =AA15*J15 -> 1651.9446 | AD15: 已入 | AE15: =J15 -> 514 | AK15: =J15 -> 514 | AO15: =J15 -> 514 | AT15: =J15 -> 514 | AU15: =AU14+AT15 -> 103286
A16: 45774 | B16: WALMART INC. | C16: 美国 | D16: 4500165203 | E16: 0906596201 RIDGEVILLE SC | F16: 4500165203-40 | G16: 9561-S002 | H16: 9561-S002 | I16: 魔法小鸟 | J16: 567 | K16: 0 | L16: 1 | M16: =J16/L16 -> 567 | N16: 45817 | O16: =N16-4 -> 45813 | P16: 客户取消 | Q16: 6/13取消 | S16: 45754 | T16: 无 | U16: 5/12客供贴纸 | V16: MA | Y16: 日期码格式：ZURU DGYYYYMMDD CHINA(日期避开周末和法定节假日即可） 日期：按实际生产日期 Packaging Info: 9561-S002 1.包装要求： MA 1L收缩膜+MA 5L 收藏指南+MA Guide book +MA 8L Slime bag 每pcs产品上要贴1张RFID贴纸，贴纸由ZURU提供，贴纸位置请严格按照我们签回的签板； Remark: 9561-S002 1.包装要求： MA 1L收缩膜+MA 5L 收藏指南+MA Guide book +MA 8L Slime bag 每pcs产品上要贴1张RFID贴纸，贴纸由ZURU提供，贴纸位置请严格按照我们签回的签板； 2. 外箱印刷带条码的RFID箱唛：RFID紫色色带+WM Dept.图标+RFID图标+ITF-14条码，四面右下角印刷ZURU logo, ITFF条码只印刷在正唛一面，在加印的时候确保 条形码能扫描出来，外箱侧面任一角落加印："MADE IN CHINA" 字样； 3. 在产品上和包装上要有日期码、以及要有MADE IN CHINA和ZURU字样； 4. 产品如有扎带口要剪平，不能刮手。 5. 此单需要验货，请多备料 6. 此单以loose carton出货，1pc/CTN | Z16: Maggie Xie | AA16: 3.214 | AB16: =AA16*J16 -> 1822.338 | AD16: 已入 | AE16: =J16 -> 567 | AK16: =J16 -> 567 | AO16: =J16 -> 567 | AT16: =J16 -> 567 | AU16: =AU15+AT16 -> 103853
A17: 45774 | B17: WALMART INC. | C17: 美国 | D17: 4500165203 | E17: 0906596285 EASTVALE | F17: 4500165203-50 | G17: 9561-S002 | H17: 9561-S002 | I17: 魔法小鸟 | J17: 500 | K17: 0 | L17: 1 | M17: =J17/L17 -> 500 | N17: 45817 | O17: =N17-4 -> 45813 | P17: 客户取消 | Q17: 6/13取消 | S17: 45754 | T17: 无 | U17: 5/12客供贴纸 | V17: MA | Y17: 日期码格式：ZURU DGYYYYMMDD CHINA(日期避开周末和法定节假日即可） 日期：按实际生产日期 Packaging Info: 9561-S002 1.包装要求： MA 1L收缩膜+MA 5L 收藏指南+MA Guide book +MA 8L Slime bag 每pcs产品上要贴1张RFID贴纸，贴纸由ZURU提供，贴纸位置请严格按照我们签回的签板； Remark: 9561-S002 1.包装要求： MA 1L收缩膜+MA 5L 收藏指南+MA Guide book +MA 8L Slime bag 每pcs产品上要贴1张RFID贴纸，贴纸由ZURU提供，贴纸位置请严格按照我们签回的签板； 2. 外箱印刷带条码的RFID箱唛：RFID紫色色带+WM Dept.图标+RFID图标+ITF-14条码，四面右下角印刷ZURU logo, ITFF条码只印刷在正唛一面，在加印的时候确保 条形码能扫描出来，外箱侧面任一角落加印："MADE IN CHINA" 字样； 3. 在产品上和包装上要有日期码、以及要有MADE IN CHINA和ZURU字样； 4. 产品如有扎带口要剪平，不能刮手。 5. 此单需要验货，请多备料 6. 此单以loose carton出货，1pc/CTN | Z17: Maggie Xie | AA17: 3.214 | AB17: =AA17*J17 -> 1607 | AD17: 已入 | AE17: =J17 -> 500 | AK17: =J17 -> 500 | AO17: =J17 -> 500 | AT17: =J17 -> 500 | AU17: =AU16+AT17 -> 104353
A18: 45750 | B18: WALMART INC. | C18: 美国 | D18: 4500162471 | E18: 0906596180 SUFFOLK | F18: 4500162471-10 | G18: 9561-S002 | H18: 9561-S002 | I18: 魔法小鸟 | J18: 500 | K18: 0 | L18: 1 | M18: =J18/L18 -> 500 | N18: 45806 | O18: =N18-3 -> 45803 | P18: 客户取消 | Q18: 6/13取消 | S18: 45754 | T18: 无 | U18: 4/16每pcs产品上要贴1张RFID贴纸，贴纸由ZURU提供翻单：4500162469 | V18: MA | X18: 日期码格式：ZURU DGYYYYMMDD CHINA(日期避开周末和法定节假日即可） 日期：按实际生产日期 | Y18: 日期码格式：ZURU DGYYYYMMDD CHINA(日期避开周末和法定节假日即可） 日期：按实际生产日期 Packaging Info: 9561-S002 1.包装要求： MA 1L收缩膜+MA 5L 收藏指南+MA Guide book+MA 8L Slime bag,翻单：4500162469 每pcs产品上要贴1张RFID贴纸，贴纸由ZURU提供，贴纸位置请严格按照我们签回的签板； Remark: 9561-S002 1.包装要求： MA 1L收缩膜+MA 5L 收藏指南+MA Guide book+MA 8L Slime bag,翻单：4500162469 每pcs产品上要贴1张RFID贴纸，贴纸由ZURU提供，贴纸位置请严格按照我们签回的签板； 2. 外箱印刷带条码的RFID箱唛：RFID紫色色带+WM Dept.图标+RFID图标+ITF-14条码，四面右下角印刷ZURU logo, ITFF条码只印刷在正唛一面，在加印的时候确保 条形码能扫描出来，外箱侧面任一角落加印："MADE IN CHINA" 字样； 3. 在产品上和包装上要有日期码、以及要有MADE IN CHINA和ZURU字样； 4. 产品如有扎带口要剪平，不能刮手。 5. 此单需要验货，请多备料 6. 此单以loose carton出货，1pc/CTN | Z18: Maggie Xie | AA18: 5.3566 | AB18: =AA18*J18 -> 2678.3 | AD18: 已入 | AE18: =J18 -> 500 | AK18: =J18 -> 500 | AO18: =J18 -> 500 | AT18: =J18 -> 500 | AU18: ='9561'!AV196+AT18 -> 273523
A19: 45750 | B19: WALMART INC. | C19: 美国 | D19: 4500162471 | E19: 0906596186 STATESBORO | F19: 4500162471-20 | G19: 9561-S002 | H19: 9561-S002 | I19: 魔法小鸟 | J19: 500 | K19: 0 | L19: 1 | M19: =J19/L19 -> 500 | N19: 45806 | O19: =N19-3 -> 45803 | P19: 客户取消 | Q19: 6/13取消 | S19: 45754 | T19: 无 | U19: 4/16每pcs产品上要贴1张RFID贴纸，贴纸由ZURU提供翻单：4500162469 | V19: MA | X19: 日期码格式：ZURU DGYYYYMMDD CHINA(日期避开周末和法定节假日即可） 日期：按实际生产日期 | Y19: 日期码格式：ZURU DGYYYYMMDD CHINA(日期避开周末和法定节假日即可） 日期：按实际生产日期 Packaging Info: 9561-S002 1.包装要求： MA 1L收缩膜+MA 5L 收藏指南+MA Guide book+MA 8L Slime bag,翻单：4500162469 每pcs产品上要贴1张RFID贴纸，贴纸由ZURU提供，贴纸位置请严格按照我们签回的签板； Remark: 9561-S002 1.包装要求： MA 1L收缩膜+MA 5L 收藏指南+MA Guide book+MA 8L Slime bag,翻单：4500162469 每pcs产品上要贴1张RFID贴纸，贴纸由ZURU提供，贴纸位置请严格按照我们签回的签板； 2. 外箱印刷带条码的RFID箱唛：RFID紫色色带+WM Dept.图标+RFID图标+ITF-14条码，四面右下角印刷ZURU logo, ITFF条码只印刷在正唛一面，在加印的时候确保 条形码能扫描出来，外箱侧面任一角落加印："MADE IN CHINA" 字样； 3. 在产品上和包装上要有日期码、以及要有MADE IN CHINA和ZURU字样； 4. 产品如有扎带口要剪平，不能刮手。 5. 此单需要验货，请多备料 6. 此单以loose carton出货，1pc/CTN | Z19: Maggie Xie | AA19: 5.3566 | AB19: =AA19*J19 -> 2678.3 | AD19: 已入 | AE19: =J19 -> 500 | AK19: =J19 -> 500 | AO19: =J19 -> 500 | AT19: =J19 -> 500 | AU19: =AU18+AT19 -> 274023
A20: 45750 | B20: WALMART INC. | C20: 美国 | D20: 4500162469 | E20: 0906596195 | F20: 4500162469-10 | G20: 9561-S002 | H20: 9561-S002 | I20: 魔法小鸟 | J20: 500 | K20: 0 | L20: 1 | M20: =J20/L20 -> 500 | N20: 45792 | O20: 45789 | P20: 客户取消 | Q20: 6/13取消 | S20: 45754 | T20: 无 | U20: 4/16每pcs产品上要贴1张RFID贴纸，贴纸由ZURU提供，贴纸位置请严格按照我们签回的签板 | V20: MA | Y20: 日期码格式：ZURU DGYYYYMMDD CHINA(日期避开周末和法定节假日即可） 日期：按实际生产日期 Packaging Info: 9561-S002 1.包装要求： MA 1L收缩膜+MA 5L 收藏指南+MA Guide book+MA 8L Slime bag 每pcs产品上要贴1张RFID贴纸，贴纸由ZURU提供，贴纸位置请严格按照我们签回的签板； Remark: 9561-S002 1.包装要求： MA 1L收缩膜+MA 5L 收藏指南+MA Guide book+MA 8L Slime bag 每pcs产品上要贴1张RFID贴纸，贴纸由ZURU提供，贴纸位置请严格按照我们签回的签板； 2. 外箱印刷带条码的RFID箱唛：RFID紫色色带+WM Dept.图标+RFID图标+ITF-14条码，四面右下角印刷ZURU logo, ITFF条码只印刷在正唛一面，在加印的时候确保 条形码能扫描出来，外箱侧面任一角落加印："MADE IN CHINA" 字样； 3. 在产品上和包装上要有日期码、以及要有MADE IN CHINA和ZURU字样； 4. 产品如有扎带口要剪平，不能刮手。 5. 此单需要验货和抽板测试，预计5/15抽板，请多备料 6. 此单以loose carton出货，1pc/CTN | Z20: Maggie Xie | AA20: 5.3566 | AB20: =AA20*J20 -> 2678.3 | AD20: 已入 | AE20: =J20 -> 500 | AK20: =J20 -> 500 | AO20: =J20 -> 500 | AT20: =J20 -> 500 | AU20: ='9561'!AV51+AT20 -> 56168
A21: 45774 | B21: WALMART INC. | C21: 美国 | D21: 4500165202 | E21: 0906596181 MOBILE | F21: 4500165202-10 | G21: 9561-S002 | H21: 9561-S002 | I21: 魔法小鸟 | J21: 500 | K21: 0 | L21: 1 | M21: =J21/L21 -> 500 | N21: 45811 | O21: =N21-4 -> 45807 | P21: 客户取消 | Q21: 6/13取消 | S21: 45754 | T21: 无 | U21: 5/12客供贴纸 | V21: MA | Y21: 日期码格式：ZURU DGYYYYMMDD CHINA(日期避开周末和法定节假日即可） 日期：按实际生产日期 Packaging Info: 9561-S002 1.包装要求： MA 1L收缩膜+MA 5L 收藏指南+MA Guide book +MA 8L Slime bag 每pcs产品上要贴1张RFID贴纸，贴纸由ZURU提供，贴纸位置请严格按照我们签回的签板； Remark: 9561-S002 1.包装要求： MA 1L收缩膜+MA 5L 收藏指南+MA Guide book +MA 8L Slime bag 每pcs产品上要贴1张RFID贴纸，贴纸由ZURU提供，贴纸位置请严格按照我们签回的签板； 2. 外箱印刷带条码的RFID箱唛：RFID紫色色带+WM Dept.图标+RFID图标+ITF-14条码，四面右下角印刷ZURU logo, ITFF条码只印刷在正唛一面，在加印的时候确保 条形码能扫描出来，外箱侧面任一角落加印："MADE IN CHINA" 字样； 3. 在产品上和包装上要有日期码、以及要有MADE IN CHINA和ZURU字样； 4. 产品如有扎带口要剪平，不能刮手。 5. 此单需要验货，请多备料 6. 此单以loose carton出货，1pc/CTN | Z21: Maggie Xie | AA21: 3.214 | AB21: =AA21*J21 -> 1607 | AD21: 已入 | AE21: =J21 -> 500 | AK21: =J21 -> 500 | AO21: =J21 -> 500 | AT21: =J21 -> 500 | AU21: ='9561'!AV84+AT21 -> 94498
A22: 45774 | B22: WALMART INC. | C22: 美国 | D22: 4500165202 | E22: 0906596215 HOUSTON | F22: 4500165202-20 | G22: 9561-S002 | H22: 9561-S002 | I22: 魔法小鸟 | J22: 538 | K22: 0 | L22: 1 | M22: =J22/L22 -> 538 | N22: 45811 | O22: =N22-4 -> 45807 | P22: 客户取消 | Q22: 6/13取消 | S22: 45754 | T22: 无 | U22: 5/12客供贴纸 | V22: MA | Y22: 日期码格式：ZURU DGYYYYMMDD CHINA(日期避开周末和法定节假日即可） 日期：按实际生产日期 Packaging Info: 9561-S002 1.包装要求： MA 1L收缩膜+MA 5L 收藏指南+MA Guide book +MA 8L Slime bag 每pcs产品上要贴1张RFID贴纸，贴纸由ZURU提供，贴纸位置请严格按照我们签回的签板； Remark: 9561-S002 1.包装要求： MA 1L收缩膜+MA 5L 收藏指南+MA Guide book +MA 8L Slime bag 每pcs产品上要贴1张RFID贴纸，贴纸由ZURU提供，贴纸位置请严格按照我们签回的签板； 2. 外箱印刷带条码的RFID箱唛：RFID紫色色带+WM Dept.图标+RFID图标+ITF-14条码，四面右下角印刷ZURU logo, ITFF条码只印刷在正唛一面，在加印的时候确保 条形码能扫描出来，外箱侧面任一角落加印："MADE IN CHINA" 字样； 3. 在产品上和包装上要有日期码、以及要有MADE IN CHINA和ZURU字样； 4. 产品如有扎带口要剪平，不能刮手。 5. 此单需要验货，请多备料 6. 此单以loose carton出货，1pc/CTN | Z22: Maggie Xie | AA22: 3.214 | AB22: =AA22*J22 -> 1729.132 | AD22: 已入 | AE22: =J22 -> 538 | AK22: =J22 -> 538 | AO22: =J22 -> 538 | AT22: =J22 -> 538 | AU22: =AU21+AT22 -> 95036
A23: 45775 | B23: Distribuidora Liverpool S.A de C.V. | C23: 墨西哥 | D23: 4500164920 | E23: 61963726 | F23: 4500164920-110 | G23: 9561-S001-5L | H23: 9561-S001 | I23: 魔法小鸟 | J23: 120 | K23: 0 | L23: 4 | M23: =J23/L23 -> 30 | N23: 45828 | O23: 45824 | P23: 取消 | S23: 45820 | T23: 无 | U23: 7/9进口商贴纸+价标贴纸+保证书，包装和说明书都需要贴一张进口商贴纸 | V23: MA | Y23: 日期码格式：ZURU INC(BVI) 标准格式 日期：按实际生产日期 Packaging Info: 9561：MA 5L EAN包装+UPC贴纸+MA 5L说明书+进口商贴纸+价标贴纸+箱唛+保证书，包装和说明书都需要贴一张进口商贴纸 Remark: 1. 此单价格贴纸（ZURU定购). 2.此单有第三方监柜，不用额外准备备品，会在大货中每款拆1pc，拆了包装的产品会由监装员用客供胶带封好或在外箱上写上"opened by telescope" | Z23: Ava Liang | AA23: 5.3727 | AB23: =J23*AA23 -> 644.724 | AD23: 已入 | AI23: =J23 -> 120 | AK23: =J23 -> 120 | AO23: =J23 -> 120 | AT23: =J23 -> 120 | AU23: ='9561'!AV339+AT23 -> 460506
A24: 45789 | B24: Distribuidora Liverpool S.A de C.V. | C24: 墨西哥 | D24: 4500165982 | E24: 61971743 | F24: 4500165982-190 | G24: 9561-S001-5L | H24: 9561-S001 | I24: 魔法小鸟 | J24: 800 | K24: 0 | L24: 4 | M24: =J24/L24 -> 200 | N24: 45828 | O24: 45824 | P24: 取消 | S24: 45841 | T24: 无 | U24: 7/9进口商贴纸+价标贴纸（包装和说明书都需要贴一张进口商贴纸） | V24: MA | Y24: 日期码格式：ZURU INC(BVI) 标准格式 日期：按实际生产日期 Packaging Info: 9561：MA 5L EAN包装+UPC贴纸+MA 5L说明书+进口商贴纸+价标贴纸+箱唛+保证书，包装和说明书都需要贴一张进口商贴纸 Remark: 1. 此单价格贴纸（ZURU定购). 2.此单有第三方监柜，不用额外准备备品，会在大货中每款拆1pc，拆了包装的产品会由监装员用客供胶带封好或在外箱上写上""opened by telescope” | Z24: Ava Liang | AA24: 5.3566 | AB24: =J24*AA24 -> 4285.28 | AD24: 已入 | AI24: =J24 -> 800 | AK24: =J24 -> 800 | AO24: =J24 -> 800 | AT24: =J24 -> 800 | AU24: =取消单!AU23+AT24 -> 461306
A25: 45827 | B25: AMAZON UK | C25: 德国 | D25: 4500170600 | E25: Amazon UK: 7UCFFCDK | F25: 4500170600-130 | G25: 9561-S003-MB-MTS | H25: 9561-S003-MB | I25: 魔法小鸟 （邮包盒装） | J25: 2026 | K25: 0 | L25: 2 | M25: =J25/L25 -> 1013 | N25: 45868 | O25: 45864 | S25: 空白外箱（加印带Zuru字样的最新logo，除了邮包盒直接做外箱的产品） + SSCC LABEL一张, 无箱唛，MADE IN CHINA 外箱只印一正一侧。箱唛资料按照给定的 | T25: 有 | U25: UPC#+英法德意西5L警示语+FR/ES/IT环保标+ZURU邮箱care@zuru.co m，参考翻单4500159392+WEEE电子产品说明书(带电池走货版)+1张获奖图标贴纸(贴在收 缩膜上指定位置;仅出DE需要增加)； | V25: MA | W25: 客版邮包盒(UPC#+英法德意西5L警示语+FR/ES/IT环保标+ZURU邮箱care@zuru.co m，参考翻单4500159392) | X25: 日期码格式：ZURU INC(BVI) 标准格式 日期：按实际生产日期 | Y25: 日期码格式：ZURU INC(BVI) 标准格式 日期：按实际生产日期 12 9561: MAIL BOX WITH PRODUCT PACKAGE, 1PCS/MAIL BOX,2PCS/2MAIL BOX/CTN; 客版邮包盒(UPC#+英法德意西5L警示语+FR/ES/IT环保标+ZURU邮箱care@zuru.co m，参考翻单4500159392)+MA 5L(6L warning EAN) B收缩膜+MA 5L(6L warning )B收藏指南+MA 5L(6L warning)B说明书+其他最新MA配套包装+WEEE电子产品说明书3 0L(带电池走货B版)+1张贴纸（TOP 10，仅出DE需要，参考翻单PO#4500167869）； 13. 验货时间不迟于2025/7/31. Remark: 1.空白外箱（加印带Zuru字样的最新logo，除了邮包盒直接做外箱的产品） + SSCC LABEL一张, 无箱唛，MADE IN CHINA 外箱只印一正一侧。箱唛资料按照给定的 标准去做即可，无需发回我方再行审批(新标准将另行通知)。 (SSCC LABEL竖贴在外箱正面的正中间，贴一面即可,贴纸离外箱边距必须至少3.2CM。如竖贴无法满足要求，则横贴。如横贴也无法满足要求，则竖贴，遮到ZURU lo go无影响), SSCC贴纸由工厂直接跟勤得采购或者工厂自行采购，每一张SSCC Label都是唯一且有不同流水及条码，且需要检查条码是否能正常扫描，另外，此贴纸 印刷不可出现模糊，溢出及粘胶不牢易脱落等现象，如工厂不按此要求导致贴纸有任何问题产生的罚款将由工厂承担一切责任 。 2.出往UK的产品+包装务必打上UKCA logo ，否则客人会退货且当地会有罚款。 3.订单必须经过ZURU QC验货或者工厂自检通过后方可出货，不涉及第三方验货。 4.法国订单要求包装不使用矿物油，请按要求提供以下其中一份文件再出货 ，产品出到法国被相关部门抽检出现包装不符合此要求的，供应商需要为此承担责任， 故此请严格把关。 -油墨物质""""由1 ~ 7个芳香环组成的MOAH""""的包装检测报告，要求限值≤1.0%； -包装材料清单，包括包装油墨或物质的信息； -油墨制造商的证书； 5.每一批次出货只能有一个生产日期，不可多个生产日期混在同一批次出货；且零售包装上必须统一加上日期码；外箱对于日期码没有硬性规定； 6.涉及到相关款式会有闪粉的或者微塑料的，请统一默认出无闪粉或者不含微塑料版本； 7.邮包盒及外箱封箱必须是工字型封箱方式； 8.5 Surprise or Mini Brands涉及包装是2个及2个以上的球入PVC桶包装时，单个球上若有UPC#或者EAN#，请用空白贴纸覆盖住，贴纸尺寸自行测量能覆盖原条码即 可； | Z25: Crystal Chen | AA25: 5.7408 | AB25: =J25*AA25 -> 11630.861 | AD25: 已入 | AH25: =J25 -> 2026 | AL25: =J25 -> 2026 | AP25: =J25 -> 2026 | AT25: =J25 -> 2026 | AU25: ='9561'!AV267+AT25 -> 367716
A26: 45820 | B26: AMAZON UK | C26: 英国 | D26: 4500169785 | E26: Amazon UK: 7APM9TGV | F26: 4500169785-20 | G26: 9561-S003-MB-MTS | H26: 9561-S003-MB | I26: 魔法小鸟 （邮包盒装） | J26: 962 | K26: 0 | L26: 2 | M26: =J26/L26 -> 481 | N26: 45876 | O26: 45873 | S26: 空白外箱（加印带Zuru字样的最新logo，除了邮包盒直接做外箱的产品） + SSCC LABEL一张, 无箱唛，MADE IN CHINA 外箱只印一正一侧。箱唛资料按照给定的 | T26: 有 | U26: UPC#+英法德意西5L警示语+FR/ES/IT环保标+ZURU邮箱care@zuru.co m，参考翻单4500159392+WEEE电子产品说明书(带电池走货版)+1张获奖图标贴纸(贴在收 缩膜上指定位置;仅出DE需要增加)；获奖贴纸(参考翻单PO#4500167869, 出DE需要加此贴纸) | V26: MA | W26: 客版邮包盒(UPC#+英法德意西5L警示语+FR/ES/IT环保标+ZURU邮箱care@zuru.co m，参考翻单4500159392) | X26: 日期码格式：ZURU INC(BVI) 标准格式 日期：按实际生产日期 | Y26: 日期码格式：ZURU INC(BVI) 标准格式 日期：按实际生产日期 Packaging Info: Amazon UK(77731/9561/15701A/71126) 2. 9561: MAIL BOX WITH PRODUCT PACKAGE, 1PCS/MAIL BOX,2PCS/2MAIL BOX/CTN; 客版邮包盒(UPC#+英法德意西5L警示语+FR/ES/IT环保标+ZURU邮箱care@zuru.co m，参考翻单4500159392)+MA 5L(6L warning EAN) B收缩膜+MA 5L(6L warning )B收藏指南+MA 5L(6L warning)B说明书+其他最新MA配套包装+WEEE电子产品说明书3 0L(带电池走货版)+获奖贴纸(参考翻单PO#4500167869, 出DE需要加此贴纸) 5. 验货时间不迟于2025/8/8. Remark: 1.空白外箱（加印带Zuru字样的最新logo，除了邮包盒直接做外箱的产品） + SSCC LABEL一张, 无箱唛，MADE IN CHINA 外箱只印一正一侧。箱唛资料按照给定的 标准去做即可，无需发回我方再行审批(新标准将另行通知)。 (SSCC LABEL竖贴在外箱正面的正中间，贴一面即可,贴纸离外箱边距必须至少3.2CM。如竖贴无法满足要求，则横贴。如横贴也无法满足要求，则竖贴，遮到ZURU lo go无影响), SSCC贴纸由工厂直接跟勤得采购或者工厂自行采购，每一张SSCC Label都是唯一且有不同流水及条码，且需要检查条码是否能正常扫描，另外，此贴纸 印刷不可出现模糊，溢出及粘胶不牢易脱落等现象，如工厂不按此要求导致贴纸有任何问题产生的罚款将由工厂承担一切责任 。 2.出往UK的产品+包装务必打上UKCA logo ，否则客人会退货且当地会有罚款。 3.订单必须经过ZURU QC验货或者工厂自检通过后方可出货，不涉及第三方验货。 4.法国订单要求包装不使用矿物油，请按要求提供以下其中一份文件再出货 ，产品出到法国被相关部门抽检出现包装不符合此要求的，供应商需要为此承担责任， 故此请严格把关。 -油墨物质""""由1 ~ 7个芳香环组成的MOAH""""的包装检测报告，要求限值≤1.0%； -包装材料清单，包括包装油墨或物质的信息； -油墨制造商的证书； 5.每一批次出货只能有一个生产日期，不可多个生产日期混在同一批次出货；且零售包装上必须统一加上日期码；外箱对于日期码没有硬性规定； 6.涉及到相关款式会有闪粉的或者微塑料的，请统一默认出无闪粉或者不含微塑料版本； 7.邮包盒及外箱封箱必须是工字型封箱方式； 8.5 Surprise or Mini Brands涉及包装是2个及2个以上的球入PVC桶包装时，单个球上若有UPC#或者EAN#，请用空白贴纸覆盖住，贴纸尺寸自行测量能覆盖原条码即 可； | Z26: Crystal Chen | AA26: 5.7569 | AB26: =J26*AA26 -> 5538.1378 | AD26: 已入 | AH26: =J26 -> 962 | AL26: =J26 -> 962 | AP26: =J26 -> 962 | AT26: =J26 -> 962 | AU26: ='9561'!AV281+AT26 -> 392944
A27: 45849 | D27: 手工单 | H27: 9561-S003-MB | I27: 魔法小鸟 （邮包盒装） | J27: 5000 | K27: 0 | L27: 2 | M27: =J27/L27 -> 2500 | N27: 45884 | O27: =N27-4 -> 45880 | AT27: =J27 -> 5000 | AU27: ='9561'!AV301+AT27 -> 433046
A28: 45849 | D28: 手工单 | H28: 9561-S003-MB | I28: 魔法小鸟 （邮包盒装） | J28: 15000 | K28: 0 | L28: 2 | M28: =J28/L28 -> 7500 | N28: 45891 | O28: =N28-4 -> 45887
A29: 45842 | D29: 4500172699 | F29: 4500172699-10 | G29: 9561-S001 | H29: 9561-S001 | I29: 魔法小鸟 | J29: 800 | K29: 0 | L29: 4 | M29: =J29/L29 -> 200 | N29: 45887 | O29: 45883 | P29: 订单取消 | S29: 欠 | T29: 有 | U29: 外箱需要贴4x6"UCC 贴纸，UCC贴纸为客供贴纸 | V29: MA | Y29: 日期码格式：ZURU INC(BVI) 标准格式 日期：按实际生产日期 Packaging Info: 1. MA+UPC版包裝,优先1L，出口美国. Remark: 2. 外箱需要贴4x6"UCC 贴纸，UCC贴纸为客供贴纸。具体贴法等收到正式PO后更新。 3. ZURU QC 验货。 4. 产品和包裝上需印刷tracking code信息，格式为ZURU常规。 | Z29: Cara Li | AA29: 5.8209 | AB29: =J29*AA29 -> 4656.72 | AD29: 已入 | AH29: =J29 -> 800 | AL29: =J29 -> 800 | AP29: =J29 -> 800 | AT29: =J29 -> 800 | AU29: ='9561'!AV314+AT29 -> 459692
A30: 45657 | B30: DM LLC | C30: 俄罗斯联邦 | D30: 4500155075 | E30: 出Bekasovo 2 | F30: 4500155075-10 | G30: 9561-S001 | H30: 9561-S001 | I30: 魔法小鸟 | J30: 768 | K30: 0 | L30: 4 | M30: =J30/L30 -> 192 | N30: 45786 | O30: 45782 | Q30: PASS | S30: 45700 | T30: 无 | U30: 贴纸 （贴纸及位置图翻单: PO#4500157612）+ 1张防盗贴纸 (贴纸以及位置图翻单PO#4500159287 | V30: MA | X30: 外箱不要打ZURU标准日期码!胶件可以打日期码。 | Y30: 日期码格式：外包装/外箱不要打ZURU标准日期码 日期： Packaging Info: 注意:外包装(指:收缩膜/彩卡/铝箔袋/挂卡/PDQ)/外箱不要打ZURU标准日期码!胶件可以打日期码。 1L MA 收缩膜 + 进口商贴纸翻4500155065+ EAN条码贴纸翻4500155065， MA 指南/说明书（如有）； Remark: 标准配比 请按期完货， 会有罚金。 出港口Bekasovo 2和 Ural . | Z30: Ann Zhang | AA30: 5.4 | AB30: =J30*AA30 -> 4147.2 | AD30: 已入 | AE30: =J30 -> 768 | AK30: =J30 -> 768 | AO30: =J30 -> 768 | AT30: =J30 -> 768 | AU30: ='9561'!AV44+AT30 -> 52146
A31: 45657 | B31: DM LLC | C31: 俄罗斯联邦 | D31: 4500155075 | E31: 出Ural | F31: 4500155075-20 | G31: 9561-S001 | H31: 9561-S001 | I31: 魔法小鸟 | J31: 264 | K31: 0 | L31: 4 | M31: =J31/L31 -> 66 | N31: 45786 | O31: 45782 | Q31: PASS | S31: 45700 | T31: 无 | U31: 进口商贴纸翻4500155065+ EAN条码贴纸翻450015506 | V31: MA | X31: 外箱不要打ZURU标准日期码!胶件可以打日期码。 | Y31: 日期码格式：外包装/外箱不要打ZURU标准日期码 日期： Packaging Info: 注意:外包装(指:收缩膜/彩卡/铝箔袋/挂卡/PDQ)/外箱不要打ZURU标准日期码!胶件可以打日期码。 1L MA 收缩膜 + 进口商贴纸翻4500155065+ EAN条码贴纸翻4500155065， MA 指南/说明书（如有）； Remark: 标准配比 请按期完货， 会有罚金。 出港口Bekasovo 2和 Ural . | Z31: Ann Zhang | AA31: 5.4 | AB31: =J31*AA31 -> 1425.6 | AD31: 已入 | AE31: =J31 -> 264 | AK31: =J31 -> 264 | AO31: =J31 -> 264 | AT31: =J31 -> 264 | AU31: =AU30+AT31 -> 52410
A32: 45889 | B32: TARGET AUSTRALIA PTY LTD | C32: 澳大利亚 | D32: 4500177451 | E32: 2465834 | F32: 4500177451-20 | G32: 9561-S001 | H32: 9561-S001 | I32: 魔法小鸟 | J32: 1500 | K32: 0 | L32: 4 | M32: =J32/L32 -> 375 | N32: 45930 | O32: 45926 | S32: 45898 | T32: 有 | U32: SSCC label外箱贴纸，另外9561包含纽扣电池，包装跟说明书上需加纽扣电池警告语贴纸。贴 | V32: MA | Y32: 日期码格式：ZURU INC(BVI) 标准格式 日期：按实际生产日期 Packaging Info: 2. 9561：英文MA包装(UPC版本，首选1L，无1L可用多L含英语)+箱唛+SSCC label外箱贴纸，另外9561包含纽扣电池，包装跟说明书上需加纽扣电池警告语贴纸。贴 纸及位置图翻单4500157612 Remark: 1. 客人要求箱唛不可出现任何手写内容，重量与实际一致且不可手写; 2. 此单去澳大利亚，请按相应澳新标准生产; 3. 使用普通透明封箱胶封箱; 4. 外箱需要贴Target SSCC LABEL,客供PDF文档，工厂自行订购。请贴在正唛右下角（一箱一张，贴1面正唛右下角,封箱胶纸不能挡住贴纸内容。)；外箱贴纸距离 外箱边缘应在2cm以上。如果正唛无位置可以贴在侧唛; 5. 外箱材质为ZURU标准; 6. 产品和包装上要有tracking label信息：格式为Zuru标准格式（可以自行调整具体年月日生产日期,避开节假期日）; 7. SSCC Label 尺寸更新为：4x4 inch; 8. 请务必按时完货，验货PASS后请按时送货入货代指定仓库，如果晚了导致船期Delay将会有罚金产生或者客户要求空运，所产生的罚金和空运费由工厂承担。 | Z32: Christine Liao | AA32: 5.8209 | AB32: =J32*AA32 -> 8731.35 | AD32: 已入 | AH32: =J32 -> 1500 | AL32: =J32 -> 1500 | AP32: =J32 -> 1500 | AT32: =J32 -> 1500 | AU32: ='9561'!AV378+AT32 -> 544845
A33: 45896 | B33: KMART AUSTRALIA LTD | C33: 澳大利亚 | D33: 4500177972 | E33: 21038341 | F33: 4500177972-10 | G33: 9561-S001 | H33: 9561-S001 | I33: 魔法小鸟 | J33: 2500 | K33: 0 | L33: 4 | M33: =J33/L33 -> 625 | N33: 45943 | O33: 45939 | S33: 45911 | T33: 有 | U33: 1张包装纽扣电池警告语贴纸 + 1张说明书纽扣电池警告语 贴纸 （贴纸及位置图翻单: PO#4500157612）+ 1张防盗贴纸 (贴纸以及位置图翻单PO#4500159287） | V33: MA | Y33: 日期码格式：ZURU INC(BVI) 标准格式 日期：按实际生产日期 Packaging Info: 9561: MA英语UPC版本包装（收缩膜和说明书, MA首选1L，如无1L可用多语且含英语的配套多语包装) + 1张包装纽扣电池警告语贴纸 + 1张说明书纽扣电池警告语 贴纸 （贴纸及位置图翻单: PO#4500157612）+ 1张防盗贴纸 (贴纸以及位置图翻单PO#4500159287）+ 箱唛 + 外箱SSCC Label Remark: 1.请务必按时完货，验货。并且按期送货入货代指定仓库，如果晚了导致船期Delay将会有罚金产生或者客户要求空运，所产生的罚金和空运费由工厂承担。 2.SSCC 外箱贴纸请同纸箱瓦楞纸方向（竖纹向）垂直，即外箱贴纸横着贴(注意条码不要被胶带粘住），贴1pc，贴1面正唛，封箱胶纸不能挡住贴纸内容。外箱贴纸 离外箱边距离不少于2cm。 3.外箱材质为ZURU标准； 4.此单需使用KMART封箱胶上下工字型封箱;从2019年6月开始，要用KMART 新版封箱胶带，此单要用"ANKO"封箱胶带 5.此单出口澳大利亚，请按相应的澳新标准生产； 6.产品和包装上生产批号的显示格式ZURU标准日期码格式 7.外箱信息不可手写，重量和体积需要与实际的一致(不可手写） 8. 每款item装箱后的G.W.超过10KG或者CBM超过0.13,(9.5KG或者以上，四舍五入后也属于10KG) 需在外箱上加印超 重或者Bulky LOGO，若发现我们资料没有，请 帮忙提醒 1)重量超过10kg但不超过16kg且CBM不超过0.13,10-16kg 超重logo 2）CBM超过0.13且重量少于17kg，bulky logo 3）不属于以上两种情况，需要使用相应重量范围内的超重logo 4）超重logo需要在外箱四面都印刷(箱唛右上角，两面侧唛超重logo需要尽量靠近毛重)，尺寸为:110mm height* 95mm width 9. 实际外箱重量跟印在箱唛上的数据差异不能超3%，尺寸按实际数据印刷 | Z33: Lydia Wu | AA33: 5.8049 | AB33: =J33*AA33 -> 14512.25 | AD33: 已入 | AH33: =J33 -> 2500 | AL33: =J33 -> 2500 | AP33: =J33 -> 2500 | AT33: =J33 -> 2500 | AU33: ='9561'!AV382+AT33 -> 548345
A34: 45896 | B34: KMART AUSTRALIA LTD | C34: 澳大利亚 | D34: 4500177972 | E34: 21105431 | F34: 4500177972-90 | G34: 9561-S001 | H34: 9561-S001 | I34: 魔法小鸟 | J34: 1104 | K34: 0 | L34: 4 | M34: =J34/L34 -> 276 | N34: 45943 | O34: 45939 | S34: 45911 | T34: 有 | U34: 1张包装纽扣电池警告语贴纸 + 1张说明书纽扣电池警告语 贴纸 （贴纸及位置图翻单: PO#4500157612）+ 1张防盗贴纸 (贴纸以及位置图翻单PO#4500159287） | V34: MA | Y34: 日期码格式：ZURU INC(BVI) 标准格式 日期：按实际生产日期 Packaging Info: 9561: MA英语UPC版本包装（收缩膜和说明书, MA首选1L，如无1L可用多语且含英语的配套多语包装) + 1张包装纽扣电池警告语贴纸 + 1张说明书纽扣电池警告语 贴纸 （贴纸及位置图翻单: PO#4500157612）+ 1张防盗贴纸 (贴纸以及位置图翻单PO#4500159287）+ 箱唛 + 外箱SSCC Label Remark: 1.请务必按时完货，验货。并且按期送货入货代指定仓库，如果晚了导致船期Delay将会有罚金产生或者客户要求空运，所产生的罚金和空运费由工厂承担。 2.SSCC 外箱贴纸请同纸箱瓦楞纸方向（竖纹向）垂直，即外箱贴纸横着贴(注意条码不要被胶带粘住），贴1pc，贴1面正唛，封箱胶纸不能挡住贴纸内容。外箱贴纸 离外箱边距离不少于2cm。 3.外箱材质为ZURU标准； 4.此单需使用KMART封箱胶上下工字型封箱;从2019年6月开始，要用KMART 新版封箱胶带，此单要用"ANKO"封箱胶带 5.此单出口澳大利亚，请按相应的澳新标准生产； 6.产品和包装上生产批号的显示格式ZURU标准日期码格式 7.外箱信息不可手写，重量和体积需要与实际的一致(不可手写） 8. 每款item装箱后的G.W.超过10KG或者CBM超过0.13,(9.5KG或者以上，四舍五入后也属于10KG) 需在外箱上加印超 重或者Bulky LOGO，若发现我们资料没有，请 帮忙提醒 1)重量超过10kg但不超过16kg且CBM不超过0.13,10-16kg 超重logo 2）CBM超过0.13且重量少于17kg，bulky logo 3）不属于以上两种情况，需要使用相应重量范围内的超重logo 4）超重logo需要在外箱四面都印刷(箱唛右上角，两面侧唛超重logo需要尽量靠近毛重)，尺寸为:110mm height* 95mm width 9. 实际外箱重量跟印在箱唛上的数据差异不能超3%，尺寸按实际数据印刷 | Z34: Lydia Wu | AA34: 5.8209 | AB34: =J34*AA34 -> 6426.2736 | AD34: 已入 | AH34: =J34 -> 1104 | AL34: =J34 -> 1104 | AP34: =J34 -> 1104 | AT34: =J34 -> 1104 | AU34: =AU33+AT34 -> 549449
A35: 45896 | B35: KMART AUSTRALIA LTD(NEW ZEALAND) | C35: 新西兰 | D35: 4500177974 | E35: 21105433 | F35: 4500177974-60 | G35: 9561-S001 | H35: 9561-S001 | I35: 魔法小鸟 | J35: 396 | K35: 0 | L35: 4 | M35: =J35/L35 -> 99 | N35: 45943 | O35: 45939 | S35: 45911 | T35: 有 | U35: 1张包装纽扣电池警告语贴纸 + 1张说明书纽扣电池警告语 贴纸 （贴纸及位置图翻单: PO#4500157612）+ 1张防盗贴纸 (贴纸以及位置图翻单PO#4500159287） | V35: MA | Y35: 日期码格式：ZURU INC(BVI) 标准格式 日期：按实际生产日期 Packaging Info: 9561: MA英语UPC版本包装（收缩膜和说明书, MA首选1L，如无1L可用多语且含英语的配套多语包装) + 1张包装纽扣电池警告语贴纸 + 1张说明书纽扣电池警告语 贴纸 （贴纸及位置图翻单: PO#4500157612）+ 1张防盗贴纸 (贴纸以及位置图翻单PO#4500159287）+ 箱唛 + 外箱SSCC Label Remark: 1.请务必按时完货，验货。并且按期送货入货代指定仓库，如果晚了导致船期Delay将会有罚金产生或者客户要求空运，所产生的罚金和空运费由工厂承担。 2.SSCC 外箱贴纸请同纸箱瓦楞纸方向（竖纹向）垂直，即外箱贴纸横着贴(注意条码不要被胶带粘住），贴1pc，贴1面正唛，封箱胶纸不能挡住贴纸内容。外箱贴纸 离外箱边距离不少于2cm。 3.外箱材质为ZURU标准； 4.此单需使用KMART封箱胶上下工字型封箱;从2019年6月开始，要用KMART 新版封箱胶带，此单要用"ANKO"封箱胶带 5.此单出口新西兰，请按相应的澳新标准生产； 6.产品和包装上生产批号的显示格式ZURU标准日期码格式 7.外箱信息不可手写，重量和体积需要与实际的一致(不可手写） 8. 每款item装箱后的G.W.超过10KG或者CBM超过0.13,(9.5KG或者以上，四舍五入后也属于10KG) 需在外箱上加印超 重或者Bulky LOGO，若发现我们资料没有，请 帮忙提醒 1)重量超过10kg但不超过16kg且CBM不超过0.13,10-16kg 超重logo 2）CBM超过0.13且重量少于17kg，bulky logo 3）不属于以上两种情况，需要使用相应重量范围内的超重logo 4）超重logo需要在外箱四面都印刷(箱唛右上角，两面侧唛超重logo需要尽量靠近毛重)，尺寸为:110mm height* 95mm width 9. 实际外箱重量跟印在箱唛上的数据差异不能超3%，尺寸按实际数据印刷 | Z35: Lydia Wu | AA35: 5.837 | AB35: =J35*AA35 -> 2311.452 | AD35: 已入 | AH35: =J35 -> 396 | AL35: =J35 -> 396 | AP35: =J35 -> 396 | AT35: =J35 -> 396 | AU35: =取消单!AU34+AT35 -> 549845
A36: 45968 | B36: KMART AUSTRALIA LTD(NEW ZEALAND) | C36: 新西兰 | D36: 4500184779 | E36: 21297199 | F36: 4500184779-50 | G36: 9561-S001 | H36: 9561-S001 | I36: 魔法小鸟 | J36: 128 | K36: 0 | L36: 4 | M36: =J36/L36 -> 32 | N36: 46013 | O36: 46009 | P36: 待确认取消 | S36: 欠 | T36: 有 | U36: 1张包装纽扣电池警告语贴纸 + 1张说明书纽扣电池警告语 贴纸 （贴纸及位置图翻单: PO#4500157612）+ 1张防盗贴纸 (贴纸以及位置图翻单PO#4500159287） | V36: MA | Y36: 日期码格式：ZURU INC(BVI) 标准格式 日期：按实际生产日期 Packaging Info: 9561: MA英语UPC版本包装（收缩膜和说明书, MA首选1L，如无1L可用多语且含英语的配套多语包装) + 1张包装纽扣电池警告语贴纸 + 1张说明书纽扣电池警告语 贴纸 （贴纸及位置图翻单: PO#4500157612）+ 1张防盗贴纸 (贴纸以及位置图翻单PO#4500159287）+ 箱唛 + 外箱SSCC Label Remark: 1.请务必按时完货，验货。并且按期送货入货代指定仓库，如果晚了导致船期Delay将会有罚金产生或者客户要求空运，所产生的罚金和空运费由工厂承担。 2.SSCC 外箱贴纸请同纸箱瓦楞纸方向（竖纹向）垂直，即外箱贴纸横着贴(注意条码不要被胶带粘住），贴1pc，贴1面正唛，封箱胶纸不能挡住贴纸内容。外箱贴纸 离外箱边距离不少于2cm。 3.外箱材质为ZURU标准； 4.此单需使用KMART封箱胶上下工字型封箱;从2019年6月开始，要用KMART 新版封箱胶带，此单要用"ANKO"封箱胶带 5.此单出口新西兰，请按相应的澳新标准生产； 6.产品和包装上生产批号的显示格式ZURU标准日期码格式 7.外箱信息不可手写，重量和体积需要与实际的一致(不可手写） 8. 每款item装箱后的G.W.超过10KG或者CBM超过0.13,(9.5KG或者以上，四舍五入后也属于10KG) 需在外箱上加印超 重或者Bulky LOGO，若发现我们资料没有，请 帮忙提醒 1)重量超过10kg但不超过16kg且CBM不超过0.13,10-16kg 超重logo 2）CBM超过0.13且重量少于17kg，bulky logo 3）不属于以上两种情况，需要使用相应重量范围内的超重logo 4）超重logo需要在外箱四面都印刷(箱唛右上角，两面侧唛超重logo需要尽量靠近毛重)，尺寸为:110mm height* 95mm width 9. 实际外箱重量跟印在箱唛上的数据差异不能超3%，尺寸按实际数据印刷 | Z36: Lydia Wu | AA36: 6.0907 | AB36: =J36*AA36 -> 779.6096 | AD36: 已入 | AH36: =J36 -> 128 | AL36: =J36 -> 128 | AP36: =J36 -> 128 | AT36: =J36 -> 128 | AU36: ='9561'!AV392+AT36 -> 547973
A37: 45968 | B37: KMART AUSTRALIA LTD | C37: 澳大利亚 | D37: 4500184776 | E37: 21297198 | F37: 4500184776-50 | G37: 9561-S001 | H37: 9561-S001 | I37: 魔法小鸟 | J37: 1372 | K37: 0 | L37: 4 | M37: =J37/L37 -> 343 | N37: 46013 | O37: 46009 | P37: 待确认取消 | S37: 欠 | T37: 有 | U37: 1张包装纽扣电池警告语贴纸 + 1张说明书纽扣电池警告语 贴纸 （贴纸及位置图翻单: PO#4500157612）+ 1张防盗贴纸 (贴纸以及位置图翻单PO#4500159287） | V37: MA | Y37: 日期码格式：ZURU INC(BVI) 标准格式 日期：按实际生产日期 Packaging Info: 9561: MA英语UPC版本包装（收缩膜和说明书, MA首选1L，如无1L可用多语且含英语的配套多语包装) + 1张包装纽扣电池警告语贴纸 + 1张说明书纽扣电池警告语 贴纸 （贴纸及位置图翻单: PO#4500157612）+ 1张防盗贴纸 (贴纸以及位置图翻单PO#4500159287）+ 箱唛 + 外箱SSCC Label Remark: 1.请务必按时完货，验货。并且按期送货入货代指定仓库，如果晚了导致船期Delay将会有罚金产生或者客户要求空运，所产生的罚金和空运费由工厂承担。 2.SSCC 外箱贴纸请同纸箱瓦楞纸方向（竖纹向）垂直，即外箱贴纸横着贴(注意条码不要被胶带粘住），贴1pc，贴1面正唛，封箱胶纸不能挡住贴纸内容。外箱贴纸 离外箱边距离不少于2cm。 3.外箱材质为ZURU标准； 4.此单需使用KMART封箱胶上下工字型封箱;从2019年6月开始，要用KMART 新版封箱胶带，此单要用"ANKO"封箱胶带 5.此单出口澳大利亚，请按相应的澳新标准生产； 6.产品和包装上生产批号的显示格式ZURU标准日期码格式 7.外箱信息不可手写，重量和体积需要与实际的一致(不可手写） 8. 每款item装箱后的G.W.超过10KG或者CBM超过0.13,(9.5KG或者以上，四舍五入后也属于10KG) 需在外箱上加印超 重或者Bulky LOGO，若发现我们资料没有，请 帮忙提醒 1)重量超过10kg但不超过16kg且CBM不超过0.13,10-16kg 超重logo 2）CBM超过0.13且重量少于17kg，bulky logo 3）不属于以上两种情况，需要使用相应重量范围内的超重logo 4）超重logo需要在外箱四面都印刷(箱唛右上角，两面侧唛超重logo需要尽量靠近毛重)，尺寸为:110mm height* 95mm width 9. 实际外箱重量跟印在箱唛上的数据差异不能超3%，尺寸按实际数据印刷 | Z37: Lydia Wu | AA37: 6.0743 | AB37: =J37*AA37 -> 8333.9396 | AD37: 已入 | AH37: =J37 -> 1372 | AL37: =J37 -> 1372 | AP37: =J37 -> 1372 | AT37: =J37 -> 1372 | AU37: ='9561'!AV393+AT37 -> 548917
A38: 2026/05/27 星期三 | B38: WALMART INC. | C38: 美国 | D38: 4500208669 | E38: 0999647663 | F38: 4500208669-40 | G38: 9561-S002 | H38: 魔法小鸟 | I38: 540 | J38: 0 | K38: 1 | L38: 540 | M38: 2026/8/3周一 | N38: 2026/7/30周四 | R38: 翻单 | S38: 无 | T38: 无 | X38: 日期码格式：ZURU INC(BVI) 标准格式 日期：按实际生产日期 Packaging Info: 9561-S002 1.包装要求： MA 1L B版收缩膜+MA 5L B版收藏指南+MA Guide B版book+ MA 8L B版拉丝沙袋 每pcs产品上要贴1张RFID贴纸，贴纸由ZURU提供，贴纸位置请严格按照我们签回的签板； Remark: 2. 外箱印刷带条码的RFID箱唛：RFID紫色色带+WM Dept.图标+RFID图标+ITF-14条码，四面右下角印刷ZURU logo, ITFF条码只印刷在正唛一面，在加印的时候确保 条形码能扫描出来，外箱侧面任一角落加印："MADE IN CHINA" 字样； 3. 在产品上和包装上要有日期码、以及要有MADE IN CHINA和ZURU字样； 4. 产品如有扎带口要剪平，不能刮手。 5. 此单需要验货，请多备料 6. 此单以loose carton出货，1pc/CTN | Y38: Maggie xie | Z38: 3.48 | AA38: 1881.846 | AC38: 9561-S002 | AD38: 已入 | AF38: 540 | AH38: 540 | AP38: 540 | AQ38: 549205
A39: 46169 | B39: WALMART INC. | C39: 美国 | D39: 4500208669 | E39: 0999644134 | F39: 4500208669-10 | G39: 9561-S002 | H39: 魔法小鸟 | I39: 1620 | J39: 0 | K39: 1 | L39: =I39/K39 -> 1620 | M39: 46244 | N39: 46240 | R39: 翻单 | S39: 无 | T39: 无 | Y39: 日期码格式：ZURU INC(BVI) 标准格式 日期：按实际生产日期 Packaging Info: 9561-S002 1.包装要求： MA 1L B版收缩膜+MA 5L B版收藏指南+MA Guide B版book+ MA 8L B版拉丝沙袋 每pcs产品上要贴1张RFID贴纸，贴纸由ZURU提供，贴纸位置请严格按照我们签回的签板； Remark: 2. 外箱印刷带条码的RFID箱唛：RFID紫色色带+WM Dept.图标+RFID图标+ITF-14条码，四面右下角印刷ZURU logo, ITFF条码只印刷在正唛一面，在加印的时候确保 条形码能扫描出来，外箱侧面任一角落加印："MADE IN CHINA" 字样； 3. 在产品上和包装上要有日期码、以及要有MADE IN CHINA和ZURU字样； 4. 产品如有扎带口要剪平，不能刮手。 5. 此单需要验货，请多备料 6. 此单以loose carton出货，1pc/CTN | Z39: Maggie xie | AA39: 3.5756 | AB39: =AA39*I39 -> 5792.472 | AD39: 9561-S002 | AE39: 已入 | AI39: =I39 -> 1620 | AM39: =I39 -> 1620 | AU39: =I39 -> 1620 | AV39: ='9561'!AV652+AU39 -> 552151
A40: 46169 | B40: WALMART INC. | C40: 美国 | D40: 4500208669 | E40: 0999644265 | F40: 4500208669-30 | G40: 9561-S002 | H40: 魔法小鸟 | I40: 1404 | J40: 0 | K40: 1 | L40: =I40/K40 -> 1404 | M40: 46244 | N40: 46240 | R40: 翻单 | S40: 无 | T40: 无 | Y40: 日期码格式：ZURU INC(BVI) 标准格式 日期：按实际生产日期 Packaging Info: 9561-S002 1.包装要求： MA 1L B版收缩膜+MA 5L B版收藏指南+MA Guide B版book+ MA 8L B版拉丝沙袋 每pcs产品上要贴1张RFID贴纸，贴纸由ZURU提供，贴纸位置请严格按照我们签回的签板； Remark: 2. 外箱印刷带条码的RFID箱唛：RFID紫色色带+WM Dept.图标+RFID图标+ITF-14条码，四面右下角印刷ZURU logo, ITFF条码只印刷在正唛一面，在加印的时候确保 条形码能扫描出来，外箱侧面任一角落加印："MADE IN CHINA" 字样； 3. 在产品上和包装上要有日期码、以及要有MADE IN CHINA和ZURU字样； 4. 产品如有扎带口要剪平，不能刮手。 5. 此单需要验货，请多备料 6. 此单以loose carton出货，1pc/CTN | Z40: Maggie xie | AA40: 3.3472 | AB40: =AA40*I40 -> 4699.4688 | AD40: 9561-S002 | AE40: 已入 | AI40: =I40 -> 1404 | AM40: =I40 -> 1404 | AU40: =I40 -> 1404 | AV40: ='9561'!AV562+AU40 -> 548349
A41: 46169 | B41: WALMART INC. | C41: 美国 | D41: 4500208669 | E41: 0999644172 | F41: 4500208669-20 | G41: 9561-S002 | H41: 魔法小鸟 | I41: 756 | J41: 0 | K41: 1 | L41: =I41/K41 -> 756 | M41: 46253 | N41: 46249 | R41: 翻单 | S41: 无 | T41: 无 | Y41: 日期码格式：ZURU INC(BVI) 标准格式 日期：按实际生产日期 Packaging Info: 9561-S002 1.包装要求： MA 1L B版收缩膜+MA 5L B版收藏指南+MA Guide B版book+ MA 8L B版拉丝沙袋 每pcs产品上要贴1张RFID贴纸，贴纸由ZURU提供，贴纸位置请严格按照我们签回的签板； Remark: 2. 外箱印刷带条码的RFID箱唛：RFID紫色色带+WM Dept.图标+RFID图标+ITF-14条码，四面右下角印刷ZURU logo, ITFF条码只印刷在正唛一面，在加印的时候确保 条形码能扫描出来，外箱侧面任一角落加印："MADE IN CHINA" 字样； 3. 在产品上和包装上要有日期码、以及要有MADE IN CHINA和ZURU字样； 4. 产品如有扎带口要剪平，不能刮手。 5. 此单需要验货，请多备料 6. 此单以loose carton出货，1pc/CTN | Z41: Maggie xie | AA41: 3.3472 | AB41: =AA41*I41 -> 2530.4832 | AD41: 9561-S002 | AE41: 已入 | AI41: =I41 -> 756 | AM41: =I41 -> 756 | AU41: =I41 -> 756 | AV41: ='9561'!AV653+AU41 -> 550169
A42: 46175 | B42: WALMART INC. | C42: 美国 | D42: 4500210347 | E42: 0999647679 | F42: 4500210347-10 | G42: 9561-S002 | H42: 魔法小鸟 | I42: 540 | J42: 0 | K42: 1 | L42: =I42/K42 -> 540 | M42: 46237 | N42: 46233 | R42: 翻单 | S42: 无 | T42: 客供贴纸 | Y42: 日期码格式：ZURU INC(BVI) 标准格式 日期：按实际生产日期 Packaging Info: 9561-S002 1.包装要求： MA 1L B版收缩膜+MA 5L B版收藏指南+MA Guide B版book+ MA 8L B版拉丝沙袋 每pcs产品上要贴1张RFID贴纸，贴纸由ZURU提供，贴纸位置请严格按照我们签回的签板； Remark: 9561-S002 1.包装要求： MA 1L B版收缩膜+MA 5L B版收藏指南+MA Guide B版book+ MA 8L B版拉丝沙袋 每pcs产品上要贴1张RFID贴纸，贴纸由ZURU提供，贴纸位置请严格按照我们签回的签板； 2. 外箱印刷带条码的RFID箱唛：RFID紫色色带+WM Dept.图标+RFID图标+ITF-14条码，四面右下角印刷ZURU logo, ITFF条码只印刷在正唛一面，在加印的时候确保 条形码能扫描出来，外箱侧面任一角落加印："MADE IN CHINA" 字样； 3. 在产品上和包装上要有日期码、以及要有MADE IN CHINA和ZURU字样； 4. 产品如有扎带口要剪平，不能刮手。 5. 此单需要验货，请多备料 6. 此单以loose carton出货，1pc/CTN | Z42: Maggie xie | AA42: 3.5756 | AB42: =AA42*I42 -> 1930.824 | AD42: 9561-S002 | AE42: 已入 | AI42: =I42 -> 540 | AM42: =I42 -> 540 | AU42: =I42 -> 540 | AV42: ='9561'!AV604+AU42 -> 549689
A43: 46150 | B43: WALMART INC. | C43: 美国 | D43: 4500205770 | E43: 0999647889 | F43: 4500205770-10 | G43: 9561-S002 | H43: 魔法小鸟 | I43: 540 | J43: 0 | K43: 1 | L43: =I43/K43 -> 540 | M43: 46244 | N43: 46240 | O43: 6/22 BV | R43: 翻单 | S43: 无 | T43: 客供贴纸 | Y43: 日期码格式：ZURU DGYYYYMMDD CHINA(日期避开周末和法定节假日即可） 日期：按实际生产日期 Packaging Info: 9561-S002 1.包装要求： MA 1L B版收缩膜+MA 5L B版收藏指南+MA Guide B版book+ MA 8L B版拉丝沙袋 每pcs产品上要贴1张RFID贴纸，贴纸由ZURU提供，贴纸位置请严格按照我们签回的签板； Remark: 9561-S002 1.包装要求： MA 1L B版收缩膜+MA 5L B版收藏指南+MA Guide B版book+ MA 8L B版拉丝沙袋 每pcs产品上要贴1张RFID贴纸，贴纸由ZURU提供，贴纸位置请严格按照我们签回的签板； 2. 外箱印刷带条码的RFID箱唛：RFID紫色色带+WM Dept.图标+RFID图标+ITF-14条码，四面右下角印刷ZURU logo, ITFF条码只印刷在正唛一面，在加印的时候确保 条形码能扫描出来，外箱侧面任一角落加印："MADE IN CHINA" 字样； 3. 在产品上和包装上要有日期码、以及要有MADE IN CHINA和ZURU字样； 4. 产品如有扎带口要剪平，不能刮手。 5. 此单需要验货，请多备料 6. 此单以loose carton出货，1pc/CTN | Z43: Maggie Xie | AA43: 3.4748 | AB43: =AA43*I43 -> 1876.392 | AD43: 9561-S002 | AE43: 已入 | AI43: =I43 -> 540 | AM43: =I43 -> 540 | AQ43: =I43 -> 540 | AU43: =I43 -> 540 | AV43: ='9561'!AV605+AU43 -> 540
A44: 46150 | B44: WALMART INC. | C44: 美国 | D44: 4500205770 | E44: 0999647946 | F44: 4500205770-20 | G44: 9561-S002 | H44: 魔法小鸟 | I44: 2484 | J44: 0 | K44: 1 | L44: =I44/K44 -> 2484 | M44: 46244 | N44: 46240 | O44: 6/22 BV | R44: 翻单 | S44: 无 | T44: 客供贴纸 | Y44: 日期码格式：ZURU DGYYYYMMDD CHINA(日期避开周末和法定节假日即可） 日期：按实际生产日期 Packaging Info: 9561-S002 1.包装要求： MA 1L B版收缩膜+MA 5L B版收藏指南+MA Guide B版book+ MA 8L B版拉丝沙袋 每pcs产品上要贴1张RFID贴纸，贴纸由ZURU提供，贴纸位置请严格按照我们签回的签板； Remark: 9561-S002 1.包装要求： MA 1L B版收缩膜+MA 5L B版收藏指南+MA Guide B版book+ MA 8L B版拉丝沙袋 每pcs产品上要贴1张RFID贴纸，贴纸由ZURU提供，贴纸位置请严格按照我们签回的签板； 2. 外箱印刷带条码的RFID箱唛：RFID紫色色带+WM Dept.图标+RFID图标+ITF-14条码，四面右下角印刷ZURU logo, ITFF条码只印刷在正唛一面，在加印的时候确保 条形码能扫描出来，外箱侧面任一角落加印："MADE IN CHINA" 字样； 3. 在产品上和包装上要有日期码、以及要有MADE IN CHINA和ZURU字样； 4. 产品如有扎带口要剪平，不能刮手。 5. 此单需要验货，请多备料 6. 此单以loose carton出货，1pc/CTN | Z44: Maggie Xie | AA44: 3.4748 | AB44: =AA44*I44 -> 8631.4032 | AD44: 9561-S002 | AE44: 已入 | AI44: =I44 -> 2484 | AM44: =I44 -> 2484 | AQ44: =I44 -> 2484 | AU44: =I44 -> 2484 | AV44: ='9561'!AV550+AU44 -> 550837
A45: 46161 | B45: WALMART INC. | C45: 美国 | D45: 4500207848 | E45: 0999648045 | F45: 4500207848-10 | G45: 9561-S002 | H45: 魔法小鸟 | I45: 1620 | J45: 0 | K45: 1 | L45: =I45/K45 -> 1620 | M45: 46244 | N45: 46240 | R45: 翻单 | S45: 无 | T45: 客供贴纸 | Y45: 日期码格式：ZURU DGYYYYMMDD CHINA(日期避开周末和法定节假日即可） 日期：按实际生产日期 Remark: 9561-S002 1.包装要求： MA 1L B版收缩膜+MA 5L B版收藏指南+MA Guide B版book+ MA 8L B版拉丝沙袋 每pcs产品上要贴1张RFID贴纸，贴纸由ZURU提供，贴纸位置请严格按照我们签回的签板； 2. 外箱印刷带条码的RFID箱唛：RFID紫色色带+WM Dept.图标+RFID图标+ITF-14条码，四面右下角印刷ZURU logo, ITFF条码只印刷在正唛一面，在加印的时候确保 条形码能扫描出来，外箱侧面任一角落加印："MADE IN CHINA" 字样； 3. 在产品上和包装上要有日期码、以及要有MADE IN CHINA和ZURU字样； 4. 产品如有扎带口要剪平，不能刮手。 5. 此单需要验货，请多备料 6. 此单以loose carton出货，1pc/CTN | Z45: Maggie xie | AA45: 3.3472 | AB45: =AA45*I45 -> 5422.464 | AD45: 9561-S002 | AE45: 已入 | AI45: =I45 -> 1620 | AM45: =I45 -> 1620 | AU45: =I45 -> 1620 | AV45: ='9561'!AV645+AU45 -> 550913
A46: 46161 | B46: WALMART INC. | C46: 美国 | D46: 4500207848 | E46: 0999648363 | F46: 4500207848-20 | G46: 9561-S002 | H46: 魔法小鸟 | I46: 1080 | J46: 0 | K46: 1 | L46: =I46/K46 -> 1080 | M46: 46244 | N46: 46240 | R46: 翻单 | S46: 无 | T46: 客供贴纸 | Y46: 日期码格式：ZURU DGYYYYMMDD CHINA(日期避开周末和法定节假日即可） 日期：按实际生产日期 Remark: 9561-S002 1.包装要求： MA 1L B版收缩膜+MA 5L B版收藏指南+MA Guide B版book+ MA 8L B版拉丝沙袋 每pcs产品上要贴1张RFID贴纸，贴纸由ZURU提供，贴纸位置请严格按照我们签回的签板； 2. 外箱印刷带条码的RFID箱唛：RFID紫色色带+WM Dept.图标+RFID图标+ITF-14条码，四面右下角印刷ZURU logo, ITFF条码只印刷在正唛一面，在加印的时候确保 条形码能扫描出来，外箱侧面任一角落加印："MADE IN CHINA" 字样； 3. 在产品上和包装上要有日期码、以及要有MADE IN CHINA和ZURU字样； 4. 产品如有扎带口要剪平，不能刮手。 5. 此单需要验货，请多备料 6. 此单以loose carton出货，1pc/CTN | Z46: Maggie xie | AA46: 3.3472 | AB46: =AA46*I46 -> 3614.976 | AD46: 9561-S002 | AE46: 已入 | AI46: =I46 -> 1080 | AM46: =I46 -> 1080 | AU46: =I46 -> 1080 | AV46: ='9561'!AV646+AU46 -> 550391
A47: 46175 | B47: WALMART INC. | C47: 美国 | D47: 4500210354 | E47: 0999648463 | F47: 4500210354-10 | G47: 9561-S002 | H47: 魔法小鸟 | I47: 1188 | J47: 0 | K47: 1 | L47: =I47/K47 -> 1188 | M47: 46262 | N47: 46258 | R47: 翻单 | S47: 无 | T47: 无 | Y47: 日期码格式：ZURU INC(BVI) 标准格式 日期：按实际生产日期 Packaging Info: 9561-S002 1.包装要求： MA 1L B版收缩膜+MA 5L B版收藏指南+MA Guide B版book+ MA 8L B版拉丝沙袋 每pcs产品上要贴1张RFID贴纸，贴纸由ZURU提供，贴纸位置请严格按照我们签回的签板； Remark: 9561-S002 1.包装要求： MA 1L B版收缩膜+MA 5L B版收藏指南+MA Guide B版book+ MA 8L B版拉丝沙袋 每pcs产品上要贴1张RFID贴纸，贴纸由ZURU提供，贴纸位置请严格按照我们签回的签板； 2. 外箱印刷带条码的RFID箱唛：RFID紫色色带+WM Dept.图标+RFID图标+ITF-14条码，四面右下角印刷ZURU logo, ITFF条码只印刷在正唛一面，在加印的时候确保 条形码能扫描出来，外箱侧面任一角落加印："MADE IN CHINA" 字样； 3. 在产品上和包装上要有日期码、以及要有MADE IN CHINA和ZURU字样； 4. 产品如有扎带口要剪平，不能刮手。 5. 此单需要验货，请多备料 6. 此单以loose carton出货，1pc/CTN | Z47: Maggie xie | AA47: 3.5756 | AB47: =AA47*I47 -> 4247.8128 | AD47: 9561-S002 | AE47: 已入 | AI47: =I47 -> 1188 | AM47: =I47 -> 1188 | AU47: =I47 -> 1188 | AV47: =取消单!#REF!+AU47 -> #REF!
A48: 46175 | B48: WALMART INC. | C48: 美国 | D48: 4500210353 | E48: 0999647981 | F48: 4500210353-10 | G48: 9561-S002 | H48: 魔法小鸟 | I48: 864 | J48: 0 | K48: 1 | L48: =I48/K48 -> 864 | M48: 46253 | N48: 46249 | R48: 翻单 | S48: 无 | T48: 无 | Y48: 日期码格式：ZURU INC(BVI) 标准格式 日期：按实际生产日期 Packaging Info: 9561-S002 1.包装要求： MA 1L B版收缩膜+MA 5L B版收藏指南+MA Guide B版book+ MA 8L B版拉丝沙袋 每pcs产品上要贴1张RFID贴纸，贴纸由ZURU提供，贴纸位置请严格按照我们签回的签板； Remark: 9561-S002 1.包装要求： MA 1L B版收缩膜+MA 5L B版收藏指南+MA Guide B版book+ MA 8L B版拉丝沙袋 每pcs产品上要贴1张RFID贴纸，贴纸由ZURU提供，贴纸位置请严格按照我们签回的签板； 2. 外箱印刷带条码的RFID箱唛：RFID紫色色带+WM Dept.图标+RFID图标+ITF-14条码，四面右下角印刷ZURU logo, ITFF条码只印刷在正唛一面，在加印的时候确保 条形码能扫描出来，外箱侧面任一角落加印："MADE IN CHINA" 字样； 3. 在产品上和包装上要有日期码、以及要有MADE IN CHINA和ZURU字样； 4. 产品如有扎带口要剪平，不能刮手。 5. 此单需要验货，请多备料 6. 此单以loose carton出货，1pc/CTN | Z48: Maggie xie | AA48: 3.5756 | AB48: =AA48*I48 -> 3089.3184 | AD48: 9561-S002 | AE48: 已入 | AI48: =I48 -> 864 | AM48: =I48 -> 864 | AU48: =I48 -> 864 | AV48: =取消单!AV41+AU48 -> 551033
A49: 46175 | B49: WALMART INC. | C49: 美国 | D49: 4500210351 | E49: 0999648003 | F49: 4500210351-10 | G49: 9561-S002 | H49: 魔法小鸟 | I49: 648 | J49: 0 | K49: 1 | L49: =I49/K49 -> 648 | M49: 46248 | N49: 46244 | R49: 翻单 | S49: 无 | T49: 无 | Y49: 日期码格式：ZURU INC(BVI) 标准格式 日期：按实际生产日期 Packaging Info: 9561-S002 1.包装要求： MA 1L B版收缩膜+MA 5L B版收藏指南+MA Guide B版book+ MA 8L B版拉丝沙袋 每pcs产品上要贴1张RFID贴纸，贴纸由ZURU提供，贴纸位置请严格按照我们签回的签板； Remark: 9561-S002 1.包装要求： MA 1L B版收缩膜+MA 5L B版收藏指南+MA Guide B版book+ MA 8L B版拉丝沙袋 每pcs产品上要贴1张RFID贴纸，贴纸由ZURU提供，贴纸位置请严格按照我们签回的签板； 2. 外箱印刷带条码的RFID箱唛：RFID紫色色带+WM Dept.图标+RFID图标+ITF-14条码，四面右下角印刷ZURU logo, ITFF条码只印刷在正唛一面，在加印的时候确保 条形码能扫描出来，外箱侧面任一角落加印："MADE IN CHINA" 字样； 3. 在产品上和包装上要有日期码、以及要有MADE IN CHINA和ZURU字样； 4. 产品如有扎带口要剪平，不能刮手。 5. 此单需要验货，请多备料 6. 此单以loose carton出货，1pc/CTN | Z49: Maggie xie | AA49: 3.5756 | AB49: =AA49*I49 -> 2316.9888 | AD49: 9561-S002 | AE49: 已入 | AI49: =I49 -> 648 | AM49: =I49 -> 648 | AU49: =I49 -> 648 | AV49: =取消单!AV39+AU49 -> 552799
A50: 46175 | B50: WALMART INC. | C50: 美国 | D50: 4500210350 | E50: 0999648327 | F50: 4500210350-10 | G50: 9561-S002 | H50: 魔法小鸟 | I50: 540 | J50: 0 | K50: 1 | L50: =I50/K50 -> 540 | M50: 46244 | N50: 46240 | R50: 翻单 | S50: 无 | T50: 无 | Y50: 日期码格式：ZURU INC(BVI) 标准格式 日期：按实际生产日期 Packaging Info: 9561-S002 1.包装要求： MA 1L B版收缩膜+MA 5L B版收藏指南+MA Guide B版book+ MA 8L B版拉丝沙袋 每pcs产品上要贴1张RFID贴纸，贴纸由ZURU提供，贴纸位置请严格按照我们签回的签板； Remark: 9561-S002 1.包装要求： MA 1L B版收缩膜+MA 5L B版收藏指南+MA Guide B版book+ MA 8L B版拉丝沙袋 每pcs产品上要贴1张RFID贴纸，贴纸由ZURU提供，贴纸位置请严格按照我们签回的签板； 2. 外箱印刷带条码的RFID箱唛：RFID紫色色带+WM Dept.图标+RFID图标+ITF-14条码，四面右下角印刷ZURU logo, ITFF条码只印刷在正唛一面，在加印的时候确保 条形码能扫描出来，外箱侧面任一角落加印："MADE IN CHINA" 字样； 3. 在产品上和包装上要有日期码、以及要有MADE IN CHINA和ZURU字样； 4. 产品如有扎带口要剪平，不能刮手。 5. 此单需要验货，请多备料 6. 此单以loose carton出货，1pc/CTN | Z50: Maggie xie | AA50: 3.5756 | AB50: =AA50*I50 -> 1930.824 | AD50: 9561-S002 | AE50: 已入 | AI50: =I50 -> 540 | AM50: =I50 -> 540 | AU50: =I50 -> 540 | AV50: ='9561'!AV599+AU50 -> 549477
A51: 46175 | B51: WALMART INC. | C51: 美国 | D51: 4500210350 | E51: 0999648561 | F51: 4500210350-20 | G51: 9561-S002 | H51: 魔法小鸟 | I51: 540 | J51: 0 | K51: 1 | L51: =I51/K51 -> 540 | M51: 46244 | N51: 46240 | R51: 翻单 | S51: 无 | T51: 无 | Y51: 日期码格式：ZURU INC(BVI) 标准格式 日期：按实际生产日期 Packaging Info: 9561-S002 1.包装要求： MA 1L B版收缩膜+MA 5L B版收藏指南+MA Guide B版book+ MA 8L B版拉丝沙袋 每pcs产品上要贴1张RFID贴纸，贴纸由ZURU提供，贴纸位置请严格按照我们签回的签板； Remark: 9561-S002 1.包装要求： MA 1L B版收缩膜+MA 5L B版收藏指南+MA Guide B版book+ MA 8L B版拉丝沙袋 每pcs产品上要贴1张RFID贴纸，贴纸由ZURU提供，贴纸位置请严格按照我们签回的签板； 2. 外箱印刷带条码的RFID箱唛：RFID紫色色带+WM Dept.图标+RFID图标+ITF-14条码，四面右下角印刷ZURU logo, ITFF条码只印刷在正唛一面，在加印的时候确保 条形码能扫描出来，外箱侧面任一角落加印："MADE IN CHINA" 字样； 3. 在产品上和包装上要有日期码、以及要有MADE IN CHINA和ZURU字样； 4. 产品如有扎带口要剪平，不能刮手。 5. 此单需要验货，请多备料 6. 此单以loose carton出货，1pc/CTN | Z51: Maggie xie | AA51: 3.5756 | AB51: =AA51*I51 -> 1930.824 | AD51: 9561-S002 | AE51: 已入 | AI51: =I51 -> 540 | AM51: =I51 -> 540 | AU51: =I51 -> 540 | AV51: ='9561'!AV596+AU51 -> 549285
