Workbook

Sheet 9283
A1: ZURU Rainbocorn 美人鱼毛絨公仔生产排期表 #9283
A2: 44982 | G2: （黃色表示更改或增加） | J2: （蓝色表示已完货） | M2: （綠色表示調整貨期） | AE2: 收縮膜 | AL2: 收藏指南 | AP2: 贴纸 | BH2: 无闪粉毛绒比例 | BN2: 有闪粉毛绒
A3: 接单期 | B3: 第三方客户名称 | C3: 走货国家 | D3: PO号 | E3: 客户 PO 号 | F3: SKU | G3: ITEM# | H3: 中文名 | I3: PO数量 (pcs) | J3: 内箱装箱数量(pcs) | K3: 外箱装箱数量(pcs) | L3: 总箱数 | M3: 计划出货期 | N3: 计划验货期 | O3: 第三方验货日期 | P3: 驗貨結果 | Q3: 船期SO | R3: 箱唛资料 | S3: 是否有外箱贴 | T3: PMC订购 说明书纸 | U3: 贴纸资料 | V3: 客供物料 | W3: 日期码 | X3: 备注 | Y3: ZURU 跟单 | Z3: 单价USD | AA3: 金额USD | AB3: 發票號 | AC3: 系统货号 | AD3: 是否入系统 | AE3: MA 1語收縮膜 A版本 | AF3: MA 1語收縮膜 B版本 | AG3: MA 1語收縮膜 C版本无闪粉 | AH3: MA 3語收縮膜 A版本 | AI3: MA 3語收縮膜 B版本 | AJ3: MA 3語收縮膜 C版本无闪粉 | AK3: 客版收縮膜 | AL3: 5语 收藏指南 A版本 | AM3: 5语 收藏指南 B版本 | AN3: 5语 收藏指南 C版本无闪粉 | AO3: 客版收藏指南 | AP3: Try Me-1L贴纸 | AQ3: Try Me-1L贴纸-B版本 | AR3: Try Me-1L贴纸-C版本无闪粉 | AS3: Try Me-3L贴纸 | AT3: Try Me-3L贴纸-B版本 | AU3: Try Me-3L贴纸-C版本无闪粉 | AV3: Try Me-客办 | AW3: 藏宝图-C版本无闪粉 | AX3: 藏宝图-客版 | AY3: 9283 MA1L展示架 | AZ3: 9283 MA3L展示架 | BA3: 9283SLT-托盘 | BB3: MEC222展示架 | BC3: 客办展示架 | BD3: 客办PDQ | BE3: 旧布标+布标贴纸+新布标 | BF3: 布標 | BG3: 无闪粉毛绒 | BH3: A 小猫 Kitten | BI3: B 兔子 Bunny | BJ3: D 小狗 Puppy | BK3: E 奶牛 Cow | BL3: G 大象 Elephant | BM3: H 火烈鸟 Flamingo | BN3: A 小猫 Kitten | BO3: B 兔子 Bunny | BP3: D 小狗 Puppy | BQ3: E 奶牛 Cow | BR3: G 大象 Elephant | BS3: H 火烈鸟 Flamingo | BT3: 总数 | BU3: 相差 | BV3: 客户回复
A4: 45455 | B4: B&M RETAIL LIMITED | C4: 英国 | D4: 4500135559 | E4: 4500135559-5 01424822/1 | F4: 4500135559-60 | G4: 9283-S001 | H4: 美人鱼6只装（无闪粉） | I4: 2898 | J4: 0 | K4: 6 | L4: =I4/K4 -> 483 | M4: 45492 | N4: 45488 | P4: PASS | Q4: 7/29出 | R4: 6/13收到. | U4: 无 | X4: 日期码格式：ZURU INC(BVI) 标准格式 日期：按实际生产日期 Packaging Info: 9283:MA-1L 配套包装 Kitten:Bunny:Puppy:Cow:Elephant:Flamingo=1:1:1:1:1:1; 订单对应客户9个PO号 ，备注有显示 ，注意分开做货/验货/装柜 ，混装有罚款。 Remark: *MA版本按工厂现有最新库存即可，订单出英国，请注意检查产品及包装应带UKCA图标，包装显示ZURU UK LTD信息，QC同事请查核，如有问题与跟单确认。 *生产日期按实际的（法定工作日），按ZURU标准格式即可 ，但是请知悉包装日期码需要早于或者等于外箱日期码 ，不能晚于外箱日期码 *请注意所有订单都需要经过ZURU QC验货并且通过后方可出货 *条码以订单显示为准 ，请安排生产前先核对 ，有问题请提出。 *所有产品按符合欧洲标准走货，不能出带闪粉版本 ，需要是不含微塑料版本 。 | Y4: Sherry Lu | Z4: 5.8973 | AA4: =Z4*I4 -> 17090.375 | AC4: 9283-S001 | AD4: 已入 | AG4: =I4 -> 2898 | AN4: =I4 -> 2898 | AR4: =I4 -> 2898 | AW4: =I4 -> 2898 | BF4: MA布标 | BG4: =I4 -> 2898 | BH4: =I4/6 -> 483 | BI4: =I4/6 -> 483 | BJ4: =I4/6 -> 483 | BK4: =I4/6 -> 483 | BL4: =I4/6 -> 483 | BM4: =I4/6 -> 483 | BT4: =SUM(BH4:BS4) -> 2898 | BU4: =I4-BT4 -> 0
A5: 45600 | B5: TARGET US | C5: 美国 | D5: 4500150025 | E5: 10001106171-3890 | F5: 4500150025-10 | G5: 9283-S001 | H5: 美人鱼6只装 | I5: 3486 | J5: 0 | K5: 6 | L5: =I5/K5 -> 581 | M5: 45645 | N5: 45642 | P5: PASS | Q5: 收到SO | R5: 11/18收到 | U5: 无 | V5: 11/29-客供外箱贴纸 | X5: 日期码格式：ZURU INC(BVI) 标准格式 日期：按实际生产日期 Packaging Info: MA 包装, MA 1L 收缩膜(UPC版); Remark: 1. 9283-S001-RAINBOCORNS-MERMAIDCORN SURPRISE-SERIES 7 Plush Medium,Bulk,6pcs,No Inner,STD Color Assortment 2. MA 包装, MA 1L 收缩膜(UPC版); 收缩膜上的UPC显示193052050106； Kitten:Bunny:Puppy:Cow:Elephant:Flamingo=1:1:1:1:1:1; 3.外箱正唛左上角位置粘贴条码箱贴纸，每箱只贴一张，由ZURU订购。来料贴纸上显示的客户DPCI# 086-08-6431，UPC显示10193052050103; 4.产品和包装上印刷 tracking code信息，格式为ZURU常规格式; 5.出货方式：货代自提。 | Y5: Holly Zheng | Z5: 5.701 | AA5: =Z5*I5 -> 19873.686 | AB5: 88830-1.2 | AC5: 9283-S001 | AD5: 已入 | AG5: =I5 -> 3486 | AN5: =I5 -> 3486 | AR5: =I5 -> 3486 | AW5: =I5 -> 3486 | BF5: MA布标 | BH5: =I5/6 -> 581 | BI5: =I5/6 -> 581 | BJ5: =I5/6 -> 581 | BK5: =I5/6 -> 581 | BL5: =I5/6 -> 581 | BM5: =I5/6 -> 581 | BT5: =SUM(BH5:BS5) -> 3486 | BU5: =I5-BT5 -> 0
A6: 45586 | B6: TJX COMPANIES, INC | C6: 美国 | D6: 4500147789 | E6: Marshalls DC#881-372PCS , DC#884-288PCS , DC#886-420PCS , DC#887-354PCS , DC#888-366PCS | F6: 4500147789-10 | G6: 9283-S001 | H6: 美人鱼6只装 | I6: 1800 | J6: 0 | K6: 6 | L6: =I6/K6 -> 300 | M6: 45649 | N6: 45645 | P6: PASS | Q6: 1/2出 | R6: 11/4收到 | U6: 无 | V6: 11/19-价格贴纸 | X6: 日期码格式：ZURU INC(BVI) 标准格式 日期：按实际生产日期 Packaging Info: MA UPC包装+价格贴纸，价格贴纸客供。 Remark: 1. 产品和包装上印刷tracking code信息，格式为ZURU常规格式。 2. 分5个DC出货，每款产品每个DC的箱唛资料不同。具体分DC数量，请参考后面行项目备注。 3. ZURU QC验货。 | Y6: Emily Wu | Z6: 5.712 | AA6: =Z6*I6 -> 10281.6 | AB6: 94169-1.23 | AC6: 9283-S001 | AD6: 已入 | AG6: =I6 -> 1800 | AN6: =I6 -> 1800 | AR6: =I6 -> 1800 | AW6: =I6 -> 1800 | BF6: MA布标 | BH6: =I6/6 -> 300 | BI6: =I6/6 -> 300 | BJ6: =I6/6 -> 300 | BK6: =I6/6 -> 300 | BL6: =I6/6 -> 300 | BM6: =I6/6 -> 300 | BT6: =SUM(BH6:BS6) -> 1800 | BU6: =I6-BT6 -> 0
A7: 45587 | B7: PT. EMWAY GLOBALINDO | C7: 印度尼西亚 | D7: 4500148621 | E7: 24000405 | F7: 4500148621-30 | G7: 9283-S001 | H7: 美人鱼6只装 | I7: 252 | J7: 0 | K7: 6 | L7: =I7/K7 -> 42 | M7: 45651 | N7: 45647 | P7: PASS | Q7: 1/2出 | R7: 10/31收到 | U7: 无 | X7: 日期码格式：ZURU INC(BVI) 标准格式 日期：按实际生产日期 Packaging Info: 1.MA UPC包装(优先1L) 3.有第三方验货，将于CRD前一周提供验货员信息，请按订单CRD准时完货。 Remark:9283-Kitten:Bunny:Puppy:Cow:Elephant:Flamingo=1:1:1:1:1:1; | Y7: Emma Wu | Z7: 5.7196 | AA7: =Z7*I7 -> 1441.3392 | AB7: 88865-1.4 | AC7: 9283-S001 | AD7: 已入 | AG7: =I7 -> 252 | AN7: =I7 -> 252 | AR7: =I7 -> 252 | AW7: =I7 -> 252 | BF7: MA布标 | BH7: =I7/6 -> 42 | BI7: =I7/6 -> 42 | BJ7: =I7/6 -> 42 | BK7: =I7/6 -> 42 | BL7: =I7/6 -> 42 | BM7: =I7/6 -> 42 | BT7: =SUM(BH7:BS7) -> 252 | BU7: =I7-BT7 -> 0
A8: 45590 | B8: Amazon EU SARL, Ndl Deutschland | C8: 德国 | D8: 4500148999 | E8: 5WJDQBAA | F8: 4500148999-40 | G8: 9283B-S003 | H8: 兔子 | I8: 500 | J8: 0 | K8: 4 | L8: =I8/K8 -> 125 | M8: 45651 | N8: 45647 | P8: PASS | Q8: 1/4-1/8出 | R8: 空白外箱（加印带Zuru字样的最新logo，除了邮包盒直接做外箱的产品） + SSCC LABEL一张, 无箱唛’MADE IN CHINA 外箱只印一正一侧。 | U8: UPC+IT sorting labe翻4500139313+ZURU邮箱贴纸翻单4500149035 | V8: 11/21收到客供外箱贴纸 | X8: 日期码格式：ZURU INC(BVI) 标准格式 日期：按实际生产日期 Packaging Info: Amazon DE 9283B 4.9283B: 9283B Plush Medium Bunny, 4pcs/ctn,no inner; MA 3L(9L warning, EAN#)C收缩膜+3张贴纸（1张UPC#+IT环保标，参考翻单PO#4500139313；1张ES回 收标，参考翻单PO#4500149035；1张ZURU邮箱，参考翻单PO#4500149035）+MA 5L(9L warning)C收藏指南+其他最新MA配套包装; 5. ZURU 验货最迟不得晚于2024/12/26 Remark: 1.空白外箱（加印带Zuru字样的最新logo，除了邮包盒直接做外箱的产品） + SSCC LABEL一张, 无箱唛. (SSCC LABEL贴在外箱正面的正中间，贴一面即可,贴纸离外箱边距必须至少3.2CM),SSCC贴纸由工厂直接跟勤得采购或者工厂自行采购，每一张SSCC Label都是唯一 且有不同流水及条码，且需要检查条码是否能正常扫描，另外，此贴纸印刷不可出现模糊，溢出及粘胶不牢易脱落等现象，如工厂不按此要求导致贴纸有任何问题产 生的罚款将由工厂承担一切责任 。’MADE IN CHINA 外箱只印一正一侧。 2. 出往UK的产品+包装务必打上UKCA logo ，否则客人会退货且当地会有罚款。 3.订单必须经过ZURU QC验货并且通过后方可出货。 4.法国订单要求包装不使用矿物油，请按要求提供以下其中一份文件再出货 ，产品出到法国被相关部门抽检出现包装不符合此要求的，供应商需要为此承担责任， 故此请严格把关 。 -油墨物质""由1 ~ 7个芳香环组成的MOAH""的包装检测报告，要求限值≤1.0%; -包装材料清单，包括包装油墨或物质的信息 -油墨制造商的证书。 5 . 每一批次出货只能有一个生产日期，不可多个生产日期混在同一批次出货；且邮包盒上必须统一加上日期码； 6. 涉及到相关款式会有闪粉的或 者微塑料的，请统一默认出无闪粉或者不含微塑料 版本; 7 .邮包盒及外箱封箱必须是工字型封箱方式； 8 . 5 Surprise or Mini Brands涉及包装是2个及2个以上的球入PVC桶包装时，单个球上若有UPC#或者EAN#，请用白色贴纸覆盖住； | Y8: Zoe Chen | Z8: 5.8612 | AA8: =Z8*I8 -> 2930.6 | AB8: 88946-1.8 | AC8: 9283B-S003 | AD8: 已入 | AJ8: =I8 -> 500 | AN8: =I8 -> 500 | AU8: =I8 -> 500 | AW8: =I8 -> 500 | BF8: MA布标 | BI8: =I8 -> 500 | BT8: =SUM(BH8:BS8) -> 500 | BU8: =I8-BT8 -> 0
A9: 45595 | B9: AMAZON UK | C9: 英国 | D9: 4500149496 | E9: Amazon UK: 5J18RF7X | F9: 4500149496-20 | G9: 9283B-S003 | H9: 兔子 | I9: 500 | J9: 0 | K9: 4 | L9: =I9/K9 -> 125 | M9: 45651 | N9: 45647 | P9: PASS | R9: 空白外箱（加印带Zuru字样的最新logo，除了邮包盒直接做外箱的产品） + SSCC LABEL一张, 无箱唛。MADE IN CHINA 外箱只印一正一侧。 | U9: UPC+IT环保标翻4500139313+ES回收标翻4500149035 | V9: 11/29-客供外箱贴纸 | X9: 日期码格式：ZURU INC(BVI) 标准格式 日期：按实际生产日期 Packaging Info: Amazon UK(9279H, 9283B, 9281A, 9298B, 71109B) 2. 9283B：9283B Plush Medium Bunny, 4pcs/ctn,no inner; MA 3L(9L warning, EAN#)C收缩膜+2张贴纸（1张UPC#+IT环保标，参考翻单PO#4500139313；1张ES回 收标，参考翻单PO#4500149035）+MA 5L(9L warning)C收藏指南+其他最新MA配套包装; 6. 最迟验货不得晚于2024/12/26; Remark: 1.空白外箱（加印带Zuru字样的最新logo，除了邮包盒直接做外箱的产品） + SSCC LABEL一张, 无箱唛。 (SSCC LABEL贴在外箱正面的正中间，贴一面即可,贴纸离外箱边距必须至少3.2CM), SSCC贴纸由工厂直接跟勤得采购或者工厂自行采购，每一张SSCC Label都是唯一 且有不同流水及条码，且需要检查条码是否能正常扫描，另外，此贴纸印刷不可出现模糊，溢出及粘胶不牢易脱落等现象，如工厂不按此要求导致贴纸有任何问题产 生的罚款将由工厂承担一切责任 。’MADE IN CHINA 外箱只印一正一侧。 2.出往UK的产品+包装务必打上UKCA logo ，否则客人会退货且当地会有罚款。 3.订单必须经过ZURU QC验货并且通过后方可出货。 4.法国订单要求包装不使用矿物油，请按要求提供以下其中一份文件再出货 ，产品出到法国被相关部门抽检出现包装不符合此要求的，供应商需要为此承担责任， 故此请严格把关。 -油墨物质""由1 ~ 7个芳香环组成的MOAH""的包装检测报告，要求限值≤1.0%； -包装材料清单，包括包装油墨或物质的信息； -油墨制造商的证书； 5.每一批次出货只能有一个生产日期，不可多个生产日期混在同一批次出货；且邮包盒上必须统一加上日期码； 6.涉及到相关款式会有闪粉的或者微塑料的，请统一默认出无闪粉或者不含微塑料版本； 7.邮包盒及外箱封箱必须是工字型封箱方式； 8.5 Surprise or Mini Brands涉及包装是2个及2个以上的球入PVC桶包装时，单个球上若有UPC#或者EAN#，请用白色贴纸覆盖住； 9.箱唛资料按照给定的标准去做即可，无需发回我方再行审批(新标准将另行通知); | Y9: Crystal Chen | Z9: 5.8612 | AA9: =Z9*I9 -> 2930.6 | AB9: 88934-1.8 | AC9: 9283B-S003 | AD9: 已入 | AJ9: =I9 -> 500 | AN9: =I9 -> 500 | AU9: =I9 -> 500 | AW9: =I9 -> 500 | BF9: MA布标 | BI9: =I9 -> 500 | BT9: =SUM(BH9:BS9) -> 500 | BU9: =I9-BT9 -> 0
A10: 45621 | B10: Zhuyu(Shenzhen)Trading Co.,Ltd. | C10: 中国 | D10: 4500152175 | E10: 5000001714 | F10: 4500152175-50 | G10: 9283-S001 | H10: 美人鱼6只装 | I10: 8004 | J10: 0 | K10: 6 | L10: =I10/K10 -> 1334 | M10: 45651 | N10: 45647 | P10: PASS | Q10: 12/24出 | R10: 翻单4500150993 | U10: 中文3C贴纸+中文布标(可用布标贴纸)+年龄贴纸翻单4500150993 | V10: 12/2-芯片码（客供） | X10: 日期码格式：ZURU INC(BVI) 标准格式 日期：按实际生产日期 Tracking Code: Packaging Info: 物料要求 SKU 所有款号务必使用带有CCC 标识的AW 翻单： 5 9283 MA+中文3C贴纸 +中文收藏指南+中文布标(可用布标贴纸)+中文领养卡 +年龄贴纸+芯片码（客供） 翻单： 4500150993 Remark: 2.外箱材质如下： 1）毛重小于5kg 外箱纸质 K=B 爆破:1000Kpa 边压:4400N/M; 2）毛重大于5kg 外箱纸质 K636K 爆破:1400Kpa 边压:6300N/M; 3. 产品/销售包装/外箱日期码要一致， 4.芯片码横向平贴在上半部分蛋壳/彩盒内侧立面处，注意事项请见跟单提供文档资料。 5.此产品务必满足国内6P 测试标准，因为可能会被市场监督局抽查，如有问题产生，工厂要负全责 6. 这张订单做出厂价，我司自行安排车辆去贵司提货，贵司需要配合提供出口报关 | Y10: Tina Chen | Z10: 5.6846 | AA10: =Z10*I10 -> 45499.538 | AB10: 94157-1.23 | AC10: 9283-S001-6 | AD10: 已入 | AG10: =I10 -> 8004 | AO10: =I10 -> 8004 | AR10: =I10 -> 8004 | AW10: =I10 -> 8004 | BF10: MA布标 | BH10: =I10/6 -> 1334 | BI10: =I10/6 -> 1334 | BJ10: =I10/6 -> 1334 | BK10: =I10/6 -> 1334 | BL10: =I10/6 -> 1334 | BM10: =I10/6 -> 1334 | BT10: =SUM(BH10:BS10) -> 8004 | BU10: =I10-BT10 -> 0
A11: 45623 | B11: Zhuyu(Shenzhen)Trading Co.,Ltd. | C11: 中国 | D11: 4500152175 | E11: 5000001714 | F11: 4500152175-60 | G11: 9283-S001 | H11: 美人鱼6只装 | I11: 2400 | J11: 0 | K11: 6 | L11: =I11/K11 -> 400 | M11: 45653 | N11: 45649 | P11: PASS | Q11: 12/24出 | R11: 翻单4500150993 | U11: 中文3C贴纸+中文布标(可用布标贴纸)+年龄贴纸翻单4500150993 | V11: 12/6-芯片码（客供） | X11: 日期码格式：ZURU INC(BVI) 标准格式 日期：按实际生产日期 Packaging Info: 物料要求 SKU 所有款号务必使用带有CCC 标识的AW 翻单： 5 9283 MA+中文3C贴纸 +中文收藏指南+中文布标(可用布标贴纸)+中文领养卡 +年龄贴纸+芯片码（客供） 翻单： 4500150993 Remark: 2.外箱材质如下： 1）毛重小于5kg 外箱纸质 K=B 爆破:1000Kpa 边压:4400N/M; 2）毛重大于5kg 外箱纸质 K636K 爆破:1400Kpa 边压:6300N/M; 3. 产品/销售包装/外箱日期码要一致， 4.芯片码横向平贴在上半部分蛋壳/彩盒内侧立面处，注意事项请见跟单提供文档资料。 5.此产品务必满足国内6P 测试标准，因为可能会被市场监督局抽查，如有问题产生，工厂要负全责 6. 这张订单做出厂价，我司自行安排车辆去贵司提货，贵司需要配合提供出口报关 | Y11: Tina Chen | Z11: 5.6684 | AA11: =Z11*I11 -> 13604.16 | AB11: 94157-1.23 | AC11: 9283-S001-6 | AD11: 已入 | AG11: =I11 -> 2400 | AO11: =I11 -> 2400 | AR11: =I11 -> 2400 | AW11: =I11 -> 2400 | BF11: MA布标 | BH11: =I11/6 -> 400 | BI11: =I11/6 -> 400 | BJ11: =I11/6 -> 400 | BK11: =I11/6 -> 400 | BL11: =I11/6 -> 400 | BM11: =I11/6 -> 400 | BT11: =SUM(BH11:BS11) -> 2400 | BU11: =I11-BT11 -> 0
A12: 45618 | B12: WAL-MART STORES INC. USA | C12: 美国 | D12: 4500152092 | E12: 877286412 | F12: 4500152092-20 | G12: 9283SLB-S002 | H12: 美人鱼卡板装 | I12: 540 | J12: 0 | K12: 108 | L12: =I12/K12 -> 5 | M12: 45650 | N12: 45646 | O12: 12/25 BV | P12: PASS | Q12: 12/30出 | R12: 外箱四面印刷RFID箱唛，正唛左前下角印刷ITF-14格式条码的艾利替代标箱唛，只印刷正唛一面，Z URU logo跟MADE IN CHINA四面右下角印刷 | U12: 消耗4500132388客版布标贴纸 | V12: 消耗4500132388客供RFID贴纸 | X12: 日期码格式：ZURU DGYYYYMMDD CHINA(日期避开周末和法定节假日即可） 日期：按实际生产日期 Tracking Code: Packaging Info: 1.包装信息：MA C版 UPC版 1L收缩膜，MA C版 5L收藏指南，MA B版 1L Try Me贴纸，MA A版 3L贴纸，MA B版 5L配件袋，MA B版 5L泡泡水袋，MA B版 5L魔力沙袋 ，MA B版 5L领养卡，MA C版 5L藏宝图（原刮刮卡），MA B版车缝布标，客版布标贴纸，客供RFID贴纸（标贴位置严格按照我们签板的位置图，不可擅自调整位置， 贴纸不能有任何破损或折坏，不可淋湿）。 2.外箱四面印刷RFID箱唛，正唛左前下角印刷ITF-14格式条码的艾利替代标箱唛，只印刷正唛一面，整个内容尺寸最小10*10cm，加印时需确保条形码能扫描出来，Z URU logo跟MADE IN CHINA四面右下角印刷，外箱印刷日期码，每个slip sheet上面贴一张10*10cm艾利替代标（工厂自行用不干胶打印）和一张普通贴纸（可A4纸 打印），slip sheet打印的普通贴纸的尺寸不能比艾利替代标小。 3.在产品上和包装上要有日期码（避开周末和节假日），以及要有MADE IN CHINA和ZURU字样。 4.产品如有扎带口要剪平，不能刮手。 5.此单需要第三方验货，请自行多备物料。 6.此单打卡板出货（18x6H=108carton=108pcs/Slip Sheet）。 7.其它信息：Kitten : Bunny : Puppy : Cow : Elephant : Flamingo=1:1:1:1:1:1。 | Y12: Effy Li | Z12: 658.0781 | AA12: =L12*Z12 -> 3290.3905 | AB12: 88866-1.4 | AC12: 9283SLB-S002 | AD12: 已入 | AG12: =I12 -> 540 | AN12: =I12 -> 540 | AR12: =I12 -> 540 | AW12: =I12 -> 540 | BF12: MA布标新日期格式 | BG12: =I12 -> 540 | BH12: =I12/6 -> 90 | BI12: =I12/6 -> 90 | BJ12: =I12/6 -> 90 | BK12: =I12/6 -> 90 | BL12: =I12/6 -> 90 | BM12: =I12/6 -> 90 | BT12: =SUM(BH12:BS12) -> 540 | BU12: =I12-BT12 -> 0
A13: 45587 | B13: ROSS PROCUREMENT.INC | C13: 美国 | D13: 4500147716 | E13: 60190663 | F13: 4500147716-20 | G13: 9283-S001 | H13: 美人鱼6只装 | I13: 2004 | J13: 0 | K13: 6 | L13: =I13/K13 -> 334 | M13: 45653 | N13: 45649 | P13: PASS | Q13: 1/3出 | R13: 指定箱唛格式 | U13: 无 | V13: 11/20-客供价格贴纸 | X13: 日期码格式： 标准格式 日期：按实际生产日期 Packaging Info: 1.ZURU MA UPC 现有版本包装 + 客供价格贴纸，出口美国 , 优先使用MA 1L 最新版本 。 Remark: 1.ZURU MA UPC 现有版本包装 + 客供价格贴纸，出口美国 , 优先使用MA 1L 最新版本 。 2.价格贴纸位于包装正面右下角，不挡住重要信息即可，可适当调整 ，价格贴纸由跟单提供。 3.标准日期码格式，产品和包装必须有日期码 。 4.同个产品同个货期不可出现不同的包装。 5. 跟单提供ROSS通用的箱唛模版，工厂按实际45 PO上客户PO/Item号/装箱数 提供箱唛排版来确认 | Y13: Sophia Zhou | Z13: 5.712 | AA13: =Z13*I13 -> 11446.848 | AB13: 88881-1.6 | AC13: 9283-S001 | AD13: 已入 | AG13: =I13 -> 2004 | AN13: =I13 -> 2004 | AR13: =I13 -> 2004 | AW13: =I13 -> 2004 | BF13: MA布标 | BH13: =I13/6 -> 334 | BI13: =I13/6 -> 334 | BJ13: =I13/6 -> 334 | BK13: =I13/6 -> 334 | BL13: =I13/6 -> 334 | BM13: =I13/6 -> 334 | BT13: =SUM(BH13:BS13) -> 2004 | BU13: =I13-BT13 -> 0
A14: 45611 | B14: GP TURKEY | C14: 土耳其 | D14: 4500151435 | E14: 83721 | F14: 4500151435-30 | G14: 9283-S001 | H14: 美人鱼6只装 | I14: 1302 | J14: 0 | K14: 6 | L14: =I14/K14 -> 217 | M14: 45656 | N14: 45652 | P14: PASS | Q14: 1/2出 | R14: 11/28收到 | U14: 11/28-进口商贴纸（含客户条码 | W14: ZUR4365 | X14: 日期码格式：ZUR4365 日期： Packaging Info: 9283：MA 1L 收缩膜+进口商贴纸（含客户条码）; MA收藏指南 2.客户日期码：ZUR4365, 产品/包装/外箱请保持一致。产品蛋壳需要印日期和item号码 3.大货样版3套寄到客户香港办公室，请多备料 4.大货验货需要由ZURU QC抽1pc样板寄到广州ITS做EN 71-3测试 Remark: 9283:Kitten:Bunny:Puppy:Cow:Elephant:Flamingo=1:1:1:1:1:1; Bubble water;NO Boron; One plastic horn filled in water mixture; A pack of sand(60g) | Y14: Lena Huang | Z14: 5.8973 | AA14: =Z14*I14 -> 7678.2846 | AB14: 94160-1.23 | AC14: 9283-S001 | AD14: 已入 | AG14: =I14 -> 1302 | AN14: =I14 -> 1302 | AR14: =I14 -> 1302 | AW14: =I14 -> 1302 | BF14: MA布标 | BH14: =I14/6 -> 217 | BI14: =I14/6 -> 217 | BJ14: =I14/6 -> 217 | BK14: =I14/6 -> 217 | BL14: =I14/6 -> 217 | BM14: =I14/6 -> 217 | BT14: =SUM(BH14:BS14) -> 1302 | BU14: =I14-BT14 -> 0
A15: 45586 | B15: TJX COMPANIES, INC | C15: 美国 | D15: 4500147796 | E15: TJ MAXX DC#891-396PCS , DC#894-342PCS , DC#896-318PCS , DC#897-624PCS , DC#898-318PCS | F15: 4500147796-20 | G15: 9283-S001 | H15: 美人鱼6只装 | I15: 1998 | J15: 0 | K15: 6 | L15: =I15/K15 -> 333 | M15: 45656 | N15: 45652 | P15: PASS | Q15: 1/8出 | R15: 11/4收到 | U15: 无 | V15: 12/6-价格贴纸 | X15: 日期码格式：ZURU INC(BVI) 标准格式 日期：按实际生产日期 Packaging Info: MA UPC包装+价格贴纸，价格贴纸客供。 Remark: 1. 产品和包装上印刷tracking code信息，格式为ZURU常规格式。 2. 分5个DC出货，每款产品每个DC的箱唛资料不同。具体分DC数量，请参考后面行项目备注。 3. ZURU QC验货。 | Y15: Emily Wu | Z15: 5.8973 | AA15: =Z15*I15 -> 11782.805 | AB15: 94170-1.23 | AC15: 9283-S001 | AD15: 已入 | AG15: =I15 -> 1998 | AN15: =I15 -> 1998 | AR15: =I15 -> 1998 | AW15: =I15 -> 1998 | BF15: MA布标 | BH15: =I15/6 -> 333 | BI15: =I15/6 -> 333 | BJ15: =I15/6 -> 333 | BK15: =I15/6 -> 333 | BL15: =I15/6 -> 333 | BM15: =I15/6 -> 333 | BT15: =SUM(BH15:BS15) -> 1998 | BU15: =I15-BT15 -> 0
A16: 45586 | B16: TJX COMPANIES, INC | C16: 美国 | D16: 4500147793 | E16: Marshalls DC#881-372PCS , DC#884-288PCS , DC#886-414PCS , DC#887-348PCS , DC#888-378PCS | F16: 4500147793-20 | G16: 9283-S001 | H16: 美人鱼6只装 | I16: 1800 | J16: 0 | K16: 6 | L16: =I16/K16 -> 300 | M16: 45656 | N16: 45652 | P16: PASS | Q16: 1/4出 | R16: 11/4收到 | U16: 无 | V16: 12/6-价格贴纸 | X16: 日期码格式：ZURU INC(BVI) 标准格式 日期：按实际生产日期 Packaging Info: MA UPC包装+价格贴纸，价格贴纸客供。 Remark: 1. 产品和包装上印刷tracking code信息，格式为ZURU常规格式。 2. 分5个DC出货，每款产品每个DC的箱唛资料不同。具体分DC数量，请参考后面行项目备注。 3. ZURU QC验货。 | Y16: Emily Wu | Z16: 5.8973 | AA16: =Z16*I16 -> 10615.14 | AB16: 94171-1.23 | AC16: 9283-S001 | AD16: 已入 | AG16: =I16 -> 1800 | AN16: =I16 -> 1800 | AR16: =I16 -> 1800 | AW16: =I16 -> 1800 | BF16: MA布标 | BH16: =I16/6 -> 300 | BI16: =I16/6 -> 300 | BJ16: =I16/6 -> 300 | BK16: =I16/6 -> 300 | BL16: =I16/6 -> 300 | BM16: =I16/6 -> 300 | BT16: =SUM(BH16:BS16) -> 1800 | BU16: =I16-BT16 -> 0
A17: 45586 | B17: TJX COMPANIES, INC | C17: 美国 | D17: 4500147795 | E17: TJ MAXX DC#891-396PCS , DC#894-342PCS , DC#896-312PCS , DC#897-624PCS , DC#898-324PCS | F17: 4500147795-20 | G17: 9283-S001 | H17: 美人鱼6只装 | I17: 1998 | J17: 0 | K17: 6 | L17: =I17/K17 -> 333 | M17: 45656 | N17: 45652 | P17: PASS | Q17: 1/8出 | R17: 11/4收到 | U17: 无 | V17: 12/6-价格贴纸 | X17: 日期码格式：ZURU INC(BVI) 标准格式 日期：按实际生产日期 Packaging Info: MA UPC包装+价格贴纸，价格贴纸客供。 Remark: 1. 产品和包装上印刷tracking code信息，格式为ZURU常规格式。 2. 分5个DC出货，每款产品每个DC的箱唛资料不同。具体分DC数量，请参考后面行项目备注。 3. ZURU QC验货。 | Y17: Emily Wu | Z17: 5.8973 | AA17: =Z17*I17 -> 11782.805 | AB17: 94175-1.23 | AC17: 9283-S001 | AD17: 已入 | AG17: =I17 -> 1998 | AN17: =I17 -> 1998 | AR17: =I17 -> 1998 | AW17: =I17 -> 1998 | BF17: MA布标 | BH17: =I17/6 -> 333 | BI17: =I17/6 -> 333 | BJ17: =I17/6 -> 333 | BK17: =I17/6 -> 333 | BL17: =I17/6 -> 333 | BM17: =I17/6 -> 333 | BT17: =SUM(BH17:BS17) -> 1998 | BU17: =I17-BT17 -> 0
A18: 45586 | B18: TJX COMPANIES, INC | C18: 美国 | D18: 4500147792 | E18: Marshalls DC#881-372PCS , DC#884-288PCS , DC#886-420PCS , DC#887-354PCS , DC#888-366PCS | F18: 4500147792-20 | G18: 9283-S001 | H18: 美人鱼6只装 | I18: 1800 | J18: 0 | K18: 6 | L18: =I18/K18 -> 300 | M18: 45656 | N18: 45652 | P18: PASS | Q18: 1/14出 | R18: 11/4收到 | U18: 无 | V18: 12/6-价格贴纸 | X18: 日期码格式：ZURU INC(BVI) 标准格式 日期：按实际生产日期 Packaging Info: MA UPC包装+价格贴纸，价格贴纸客供。 Remark: 1. 产品和包装上印刷tracking code信息，格式为ZURU常规格式。 2. 分5个DC出货，每款产品每个DC的箱唛资料不同。具体分DC数量，请参考后面行项目备注。 3. ZURU QC验货。 | Y18: Emily Wu | Z18: 5.8973 | AA18: =Z18*I18 -> 10615.14 | AB18: 94166-1.23 | AC18: 9283-S001 | AD18: 已入 | AG18: =I18 -> 1800 | AN18: =I18 -> 1800 | AR18: =I18 -> 1800 | AW18: =I18 -> 1800 | BF18: MA布标 | BH18: =I18/6 -> 300 | BI18: =I18/6 -> 300 | BJ18: =I18/6 -> 300 | BK18: =I18/6 -> 300 | BL18: =I18/6 -> 300 | BM18: =I18/6 -> 300 | BT18: =SUM(BH18:BS18) -> 1800 | BU18: =I18-BT18 -> 0
A19: 45586 | B19: TJX COMPANIES, INC | C19: 美国 | D19: 4500147798 | E19: TJ MAXX DC#891-396PCS , DC#894-342PCS , DC#896-312PCS , DC#897-624PCS , DC#898-324PCS | F19: 4500147798-20 | G19: 9283-S001 | H19: 美人鱼6只装 | I19: 1998 | J19: 0 | K19: 6 | L19: =I19/K19 -> 333 | M19: 45657 | N19: 45653 | P19: PASS | Q19: 1/8出 | R19: 11/4收到 | U19: 无 | V19: 12/6-价格贴纸 | X19: 日期码格式：ZURU INC(BVI) 标准格式 日期：按实际生产日期 Packaging Info: MA UPC包装+价格贴纸，价格贴纸客供。 Remark: 1. 产品和包装上印刷tracking code信息，格式为ZURU常规格式。 2. 分5个DC出货，每款产品每个DC的箱唛资料不同。具体分DC数量，请参考后面行项目备注。 3. ZURU QC验货。 | Y19: Emily Wu | Z19: 5.8973 | AA19: =Z19*I19 -> 11782.805 | AB19: 94174-1.23 | AC19: 9283-S001 | AD19: 已入 | AG19: =I19 -> 1998 | AN19: =I19 -> 1998 | AR19: =I19 -> 1998 | AW19: =I19 -> 1998 | BF19: MA布标 | BH19: =I19/6 -> 333 | BI19: =I19/6 -> 333 | BJ19: =I19/6 -> 333 | BK19: =I19/6 -> 333 | BL19: =I19/6 -> 333 | BM19: =I19/6 -> 333 | BT19: =SUM(BH19:BS19) -> 1998 | BU19: =I19-BT19 -> 0
A20: 45586 | B20: TJX COMPANIES, INC | C20: 美国 | D20: 4500147794 | E20: Marshalls DC#881-372PCS , DC#884-288PCS , DC#886-420PCS , DC#887-354PCS , DC#888-366PCS | F20: 4500147794-20 | G20: 9283-S001 | H20: 美人鱼6只装 | I20: 1800 | J20: 0 | K20: 6 | L20: =I20/K20 -> 300 | M20: 45657 | N20: 45653 | P20: PASS | Q20: 1/10出 | R20: 11/4收到 | U20: 无 | V20: 12/6-价格贴纸 | X20: 日期码格式：ZURU INC(BVI) 标准格式 日期：按实际生产日期 Packaging Info: MA UPC包装+价格贴纸，价格贴纸客供。 Remark: 1. 产品和包装上印刷tracking code信息，格式为ZURU常规格式。 2. 分5个DC出货，每款产品每个DC的箱唛资料不同。具体分DC数量，请参考后面行项目备注。 3. ZURU QC验货。 | Y20: Emily Wu | Z20: 5.8973 | AA20: =Z20*I20 -> 10615.14 | AB20: 94176-1.23 | AC20: 9283-S001 | AD20: 已入 | AG20: =I20 -> 1800 | AN20: =I20 -> 1800 | AR20: =I20 -> 1800 | AW20: =I20 -> 1800 | BF20: MA布标 | BH20: =I20/6 -> 300 | BI20: =I20/6 -> 300 | BJ20: =I20/6 -> 300 | BK20: =I20/6 -> 300 | BL20: =I20/6 -> 300 | BM20: =I20/6 -> 300 | BT20: =SUM(BH20:BS20) -> 1800 | BU20: =I20-BT20 -> 0
A21: 45604 | B21: ASDA STORES LTD | C21: 英国 | D21: 4500150696 | E21: 2950866090 | F21: 4500150696-20 | G21: 9283SLB-S001 | H21: 美人鱼卡板装（无闪粉） | I21: 1040 | J21: 1 | K21: 80 | L21: =I21/K21 -> 13 | M21: 45656 | N21: 45652 | P21: PASS | Q21: 1/8出 | R21: 11/29收到 | U21: 11/29-卡板贴纸 | X21: 日期码格式：ZURU INC(BVI) 标准格式 日期：按实际生产日期 Packaging Info: 6.9283SLB 9283-S002:MA 1L最新UPC包装； UPC#193052050106，请先检查条码是否正确再安排做货； Kitten:Bunny:Puppy:Cow:Elephant:Flamingo=1:1:1:1:1:1; Slip Sheet: 1 PCS/CTN, 22*4=88ctn=88pcs/slip sheet, 一共需要13套slip sheet; Slip Sheet打包好后，需要在正唛、侧唛右下角各贴一张slip sheet贴纸，直接用A4纸打印出来即可，贴纸尺寸160mm width x 140mm high； Slip Sheet尺寸限制为100*115*130CM，一旦实际SLIP SHEET尺寸超过这个尺寸，请提前通知ZURU跟单，需同客人确 认才能量产和出货; Remark: 1. 产品及包装需要印UKCA图标，包装需要有ZURU UK LTD/ZURU France地址信息，QC同事请核查，如有问题与跟单确认 2. 产品/包装/外箱都需要打ZURU格式日期码，日期必须为法定工作日。 3. 需要符合欧洲标准不能含有闪粉和微塑料，否则不合法规会有客诉产生 | Y21: Amy Ding | Z21: 482.4908 | AA21: =Z21*L21 -> 6272.3804 | AB21: 88944-1.8 | AC21: 9283SLB-S001 | AD21: 已入 | AG21: =I21 -> 1040 | AN21: =I21 -> 1040 | AR21: =I21 -> 1040 | AW21: =I21 -> 1040 | BF21: MA布标 | BG21: =I21 -> 1040 | BH21: =I21/6 -> 173.33333 | BI21: =I21/6 -> 173.33333 | BJ21: =I21/6 -> 173.33333 | BK21: =I21/6 -> 173.33333 | BL21: =I21/6 -> 173.33333 | BM21: =I21/6 -> 173.33333 | BT21: =SUM(BH21:BS21) -> 1040 | BU21: =I21-BT21 -> 0
A22: 45617 | B22: TARGET US | C22: 美国 | D22: 4500151914 | E22: 10001106177-3890 | F22: 4500151914-10 | G22: 9283-S001 | H22: 美人鱼6只装 | I22: 3030 | J22: 0 | K22: 6 | L22: =I22/K22 -> 505 | M22: 45657 | N22: 45654 | P22: PASS | Q22: 1/6出 | R22: 11/28收到 | U22: 无 | V22: 12/6-外箱贴纸 | X22: 日期码格式：ZURU INC(BVI) 标准格式 日期：按实际生产日期 Tracking Code: Packaging Info: MA 包装, MA 1L 收缩膜(UPC版); Remark: 1. 9283-S001-RAINBOCORNS-MERMAIDCORN SURPRISE-SERIES 7 Plush Medium,Bulk,6pcs,No Inner,STD Color Assortment 2. MA 包装, MA 1L 收缩膜(UPC版); 收缩膜上的UPC显示193052050106； Kitten:Bunny:Puppy:Cow:Elephant:Flamingo=1:1:1:1:1:1; 3.外箱正唛左上角位置粘贴条码箱贴纸，每箱只贴一张，由ZURU订购。来料贴纸上显示的客户DPCI# 086-08-6431，UPC显示10193052050103; 4.产品和包装上印刷 tracking code信息，格式为ZURU常规格式; 5.出货方式：货代自提。 | Y22: Holly Zheng | Z22: 5.701 | AA22: =Z22*I22 -> 17274.03 | AB22: 88882-1.6 | AC22: 9283-S001 | AD22: 已入 | AG22: =I22 -> 3030 | AN22: =I22 -> 3030 | AR22: =I22 -> 3030 | AW22: =I22 -> 3030 | BF22: MA布标 | BH22: =I22/6 -> 505 | BI22: =I22/6 -> 505 | BJ22: =I22/6 -> 505 | BK22: =I22/6 -> 505 | BL22: =I22/6 -> 505 | BM22: =I22/6 -> 505 | BT22: =SUM(BH22:BS22) -> 3030 | BU22: =I22-BT22 -> 0
A23: 45614 | B23: BURLINGTON COAT FACTORY | C23: 美国 | D23: 4500151472 | E23: 客户PO#383017 503 | F23: 4500151472-20 | G23: 9283-S001 | H23: 美人鱼6只装 | I23: 2400 | J23: 0 | K23: 6 | L23: =I23/K23 -> 400 | M23: 45663 | N23: 45659 | P23: PASS | Q23: 1/10出 | R23: 11/18收到 | U23: 12/13-客供价格贴纸+12/12-外箱贴纸 | X23: 日期码格式：ZURU INC(BVI) 标准格式 日期：按实际生产日期 Packaging Info: 1，ZURU MA （首选1L）UPC版本+客供价格贴纸+外箱贴纸，出口美国 有PVC桶的价格贴纸贴在PVC桶上面 Remark: 2，产品和包装上印刷ZURU 标准日期码； 3，纸箱中间靠上沿印刷ZURU LOGO，见箱唛资料 4、外箱UCC 条码贴纸，尺寸: 4*6inch，贴在其中一面正唛右下角，贴纸距离外箱底部3.5cm, 侧边距离3.5cm。外箱贴纸由跟单提供电子版, 工厂自行安排，不可用 封箱胶覆盖贴纸条码，贴纸需要可以扫描且无损坏. 5，每个产品有一个价格贴纸， 价格贴纸覆盖UPC条码上 （若UPC 条码太大，可以露出ITEM#, 覆盖条码即可），若价格贴纸覆盖UPC 会挡住文字/图案，在产品背面 找空白处粘贴价格贴纸即可。贴的时候要是会覆盖包装上重要的信息和图案，需要告知跟单。 | Y23: Jessi Xu | Z23: 5.8973 | AA23: =Z23*I23 -> 14153.52 | AB23: 88981-1.10 | AC23: 9283-S001 | AD23: 已入 | AG23: =I23 -> 2400 | AN23: =I23 -> 2400 | AR23: =I23 -> 2400 | AW23: =I23 -> 2400 | BF23: MA布标 | BH23: =I23/6 -> 400 | BI23: =I23/6 -> 400 | BJ23: =I23/6 -> 400 | BK23: =I23/6 -> 400 | BL23: =I23/6 -> 400 | BM23: =I23/6 -> 400 | BT23: =SUM(BH23:BS23) -> 2400 | BU23: =I23-BT23 -> 0
A24: 45614 | B24: BURLINGTON COAT FACTORY | C24: 美国 | D24: 4500151472 | E24: 客户PO#383019 403 | F24: 4500151472-70 | G24: 9283-S001 | H24: 美人鱼6只装 | I24: 2400 | J24: 0 | K24: 6 | L24: =I24/K24 -> 400 | M24: 45663 | N24: 45659 | P24: PASS | Q24: 1/10出 | R24: 11/18收到 | U24: 12/13-客供价格贴纸+12/12-外箱贴纸 | X24: 日期码格式：ZURU INC(BVI) 标准格式 日期：按实际生产日期 Packaging Info: 1，ZURU MA （首选1L）UPC版本+客供价格贴纸+外箱贴纸，出口美国 有PVC桶的价格贴纸贴在PVC桶上面 Remark: 2，产品和包装上印刷ZURU 标准日期码； 3，纸箱中间靠上沿印刷ZURU LOGO，见箱唛资料 4、外箱UCC 条码贴纸，尺寸: 4*6inch，贴在其中一面正唛右下角，贴纸距离外箱底部3.5cm, 侧边距离3.5cm。外箱贴纸由跟单提供电子版, 工厂自行安排，不可用 封箱胶覆盖贴纸条码，贴纸需要可以扫描且无损坏. 5，每个产品有一个价格贴纸， 价格贴纸覆盖UPC条码上 （若UPC 条码太大，可以露出ITEM#, 覆盖条码即可），若价格贴纸覆盖UPC 会挡住文字/图案，在产品背面 找空白处粘贴价格贴纸即可。贴的时候要是会覆盖包装上重要的信息和图案，需要告知跟单。 | Y24: Jessi Xu | Z24: 5.8973 | AA24: =Z24*I24 -> 14153.52 | AB24: 88988-1.11 | AC24: 9283-S001 | AD24: 已入 | AG24: =I24 -> 2400 | AN24: =I24 -> 2400 | AR24: =I24 -> 2400 | AW24: =I24 -> 2400 | BF24: MA布标 | BH24: =I24/6 -> 400 | BI24: =I24/6 -> 400 | BJ24: =I24/6 -> 400 | BK24: =I24/6 -> 400 | BL24: =I24/6 -> 400 | BM24: =I24/6 -> 400 | BT24: =SUM(BH24:BS24) -> 2400 | BU24: =I24-BT24 -> 0
A25: 45617 | B25: N.V. DREAMLAND | C25: 比利时 | D25: 4500151910 | E25: 450054548 | F25: 4500151910-20 | G25: 9283-S001 | H25: 美人鱼6只装 | I25: 1596 | J25: 0 | K25: 6 | L25: =I25/K25 -> 266 | M25: 45663 | N25: 45659 | P25: PASS | R25: 11/21收到 | U25: 无 | X25: 日期码格式：ZURU INC(BVI) 标准格式 日期：按实际生产日期 Tracking Code: Packaging Info: 9283: MA C版 3L EAN收缩膜（含NL警语），MA B版 3L Try Me 贴纸，MA C版 5L收藏指南（含NL警语），MA C版 5L地图（含NL警语），MA B版 5L配件袋，MA B版 5L证书，MA B版布标，MA B版贴纸 Remark: 1.外箱需要印条码，请确保条码可以清晰扫描，且条码内容正确 2.出欧洲，微塑料需合规（如item本身不含微塑料,则忽略此要求） 3.STD配比 4. 所有产品符合REACH申明 | Y25: Amber Zhang | Z25: 5.712 | AA25: =Z25*I25 -> 9116.352 | AB25: 94005-1.13 | AC25: 9283-S001-1 | AD25: 已入 | AJ25: =I25 -> 1596 | AN25: =I25 -> 1596 | AU25: =I25 -> 1596 | AW25: =I25 -> 1596 | BF25: MA布标 | BH25: =I25/6 -> 266 | BI25: =I25/6 -> 266 | BJ25: =I25/6 -> 266 | BK25: =I25/6 -> 266 | BL25: =I25/6 -> 266 | BM25: =I25/6 -> 266 | BT25: =SUM(BH25:BS25) -> 1596 | BU25: =I25-BT25 -> 0
A26: 45622 | B26: MCD BRANDS SAS | C26: 乌拉圭 | D26: 4500152326 | F26: 4500152326-60 | G26: 9283-S001 | H26: 美人鱼6只装 | I26: 120 | J26: 0 | K26: 6 | L26: =I26/K26 -> 20 | M26: 45663 | N26: 45659 | P26: PASS | Q26: 1/9出 | R26: 翻单4500108308 | U26: 进口商贴纸/EAN贴纸翻单4500108308 | X26: 日期码格式：ZURU INC(BVI) 标准格式 日期：按实际生产日期 Packaging Info: 9283：MA 3L包装+进口商贴纸+箱唛 +EAN贴纸，进口商贴纸/箱唛/EAN贴纸翻单PO4500108308 Remark: 进口商贴纸请多备料5pcs,出货后需要寄给客户 | Y26: Ava Liang | Z26: 5.905 | AA26: =Z26*I26 -> 708.6 | AB26: 88941-1.8 | AC26: 9283-S001-1 | AD26: 已入 | AJ26: =I26 -> 120 | AN26: =I26 -> 120 | AU26: =I26 -> 120 | AW26: =I26 -> 120 | BF26: MA布标 | BH26: =I26/6 -> 20 | BI26: =I26/6 -> 20 | BJ26: =I26/6 -> 20 | BK26: =I26/6 -> 20 | BL26: =I26/6 -> 20 | BM26: =I26/6 -> 20 | BT26: =SUM(BH26:BS26) -> 120 | BU26: =I26-BT26 -> 0
A27: 45618 | B27: KMART AUSTRALIA LTD(NEW ZEALAND) | C27: 新西兰 | D27: 4500152016 | E27: 20478298 | F27: 4500152016-20 | G27: 9283-S001 | H27: 美人鱼6只装 | I27: 42 | J27: 0 | K27: 6 | L27: =I27/K27 -> 7 | M27: 45663 | N27: 45659 | P27: PASS | Q27: 1/8-1/10出 | R27: 11/22收到 | U27: 12/13-防盗贴纸+12/16-外箱贴纸 | X27: 日期码格式：ZURU INC(BVI) 标准格式 日期：按实际生产日期 Tracking Code: Packaging Info: 9283: MA英语UPC版本包装（收缩膜和说明书, MA首选1L，如无1L可用多语且含英语的配套多语包装) + 1张防盗贴纸 (贴纸以及位置图翻单PO#4500095104）+ 箱唛 + 外箱SSCC Label Remark: 1.请务必按时完货，验货。并且按期送货入货代指定仓库，如果晚了导致船期Delay将会有罚金产生或者客户要求空运，所产生的罚金和空运费由工厂承担。 2.SSCC 外箱贴纸请同纸箱瓦楞纸方向（竖纹向）垂直，即外箱贴纸横着贴(注意条码不要被胶带粘住），贴1pc，贴1面正唛，封箱胶纸不能挡住贴纸内容。外箱贴纸 离外箱边距离不少于2cm。 3.外箱材质为ZURU标准； 4.此单需使用KMART封箱胶上下工字型封箱;从2019年6月开始，要用KMART 新版封箱胶带，此单要用"ANKO"封箱胶带 5.此单出口新西兰，请按相应的澳新标准生产； 6.产品和包装上生产批号的显示格式ZURU标准日期码格式 7.外箱信息不可手写，重量和体积需要与实际的一致(不可手写） 8. 每款item装箱后的G.W.超过10KG或者CBM超过0.13,(9.5KG或者以上，四舍五入后也属于10KG) 需在外箱上加印超 重或者Bulky LOGO，若发现我们资料没有，请 帮忙提醒 1)重量超过10kg但不超过16kg且CBM不超过0.13,10-16kg 超重logo 2）CBM超过0.13且重量少于17kg，bulky logo 3）不属于以上两种情况，需要使用相应重量范围内的超重logo 4）超重logo需要在外箱四面都印刷(箱唛右上角，两面侧唛超重logo需要尽量靠近毛重)，尺寸为:110mm height* 95mm width 9. 实际外箱重量跟印在箱唛上的数据差异不能超3%，尺寸按实际数据印刷 | Y27: Lydia Wu | Z27: 6.2984 | AA27: =Z27*I27 -> 264.5328 | AB27: 88967-1.10 | AC27: 9283-S001 | AD27: 已入 | AG27: =I27 -> 42 | AN27: =I27 -> 42 | AR27: =I27 -> 42 | AW27: =I27 -> 42 | BF27: MA布标 | BH27: =I27/6 -> 7 | BI27: =I27/6 -> 7 | BJ27: =I27/6 -> 7 | BK27: =I27/6 -> 7 | BL27: =I27/6 -> 7 | BM27: =I27/6 -> 7 | BT27: =SUM(BH27:BS27) -> 42 | BU27: =I27-BT27 -> 0
A28: 45618 | B28: KMART AUSTRALIA LTD | C28: 澳大利亚 | D28: 4500152006 | E28: 20357441 | F28: 4500152006-30 | G28: 9283-S001 | H28: 美人鱼6只装 | I28: 1458 | J28: 0 | K28: 6 | L28: =I28/K28 -> 243 | M28: 45663 | N28: 45659 | P28: PASS | Q28: 1/8-1/10出 | R28: 11/22收到 | U28: 12/13-防盗贴纸+12/16-外箱贴纸 | X28: 日期码格式：ZURU INC(BVI) 标准格式 日期：按实际生产日期 Tracking Code: Packaging Info: 9283: MA英语UPC版本包装（收缩膜和说明书, MA首选1L，如无1L可用多语且含英语的配套多语包装) + 1张防盗贴纸 (贴纸以及位置图翻单PO#4500095104）+ 箱唛 + 外箱SSCC Label Remark: 1.请务必按时完货，验货。并且按期送货入货代指定仓库，如果晚了导致船期Delay将会有罚金产生或者客户要求空运，所产生的罚金和空运费由工厂承担。 2.SSCC 外箱贴纸请同纸箱瓦楞纸方向（竖纹向）垂直，即外箱贴纸横着贴(注意条码不要被胶带粘住），贴1pc，贴1面正唛，封箱胶纸不能挡住贴纸内容。外箱贴纸 离外箱边距离不少于2cm。 3.外箱材质为ZURU标准； 4.此单需使用KMART封箱胶上下工字型封箱;从2019年6月开始，要用KMART 新版封箱胶带，此单要用"ANKO"封箱胶带 5.此单出口澳大利亚，请按相应的澳新标准生产； 6.产品和包装上生产批号的显示格式ZURU标准日期码格式 7.外箱信息不可手写，重量和体积需要与实际的一致(不可手写） 8. 每款item装箱后的G.W.超过10KG或者CBM超过0.13,(9.5KG或者以上，四舍五入后也属于10KG) 需在外箱上加印超 重或者Bulky LOGO，若发现我们资料没有，请 帮忙提醒 1)重量超过10kg但不超过16kg且CBM不超过0.13,10-16kg 超重logo 2）CBM超过0.13且重量少于17kg，bulky logo 3）不属于以上两种情况，需要使用相应重量范围内的超重logo 4）超重logo需要在外箱四面都印刷(箱唛右上角，两面侧唛超重logo需要尽量靠近毛重)，尺寸为:110mm height* 95mm width 9. 实际外箱重量跟印在箱唛上的数据差异不能超3%，尺寸按实际数据印刷 | Y28: Lydia Wu | Z28: 6.2908 | AA28: =Z28*I28 -> 9171.9864 | AB28: 88966-1.10 | AC28: 9283-S001 | AD28: 已入 | AG28: =I28 -> 1458 | AN28: =I28 -> 1458 | AR28: =I28 -> 1458 | AW28: =I28 -> 1458 | BF28: MA布标 | BH28: =I28/6 -> 243 | BI28: =I28/6 -> 243 | BJ28: =I28/6 -> 243 | BK28: =I28/6 -> 243 | BL28: =I28/6 -> 243 | BM28: =I28/6 -> 243 | BT28: =SUM(BH28:BS28) -> 1458 | BU28: =I28-BT28 -> 0
A29: 45621 | B29: KMART AUSTRALIA LTD | C29: 澳大利亚 | D29: 4500152292 | E29: 20357441 | F29: 4500152292-40 | G29: 9283-S001 | H29: 美人鱼6只装 | I29: 1362 | J29: 0 | K29: 6 | L29: =I29/K29 -> 227 | M29: 45663 | N29: 45659 | P29: PASS | Q29: 1/8-1/10出 | R29: 12/3收到 | U29: 12/13-防盗贴纸+12/16-外箱贴纸 | X29: 日期码格式：ZURU INC(BVI) 标准格式 日期：按实际生产日期 Tracking Code: Packaging Info: 9283: MA英语UPC版本包装（收缩膜和说明书, MA首选1L，如无1L可用多语且含英语的配套多语包装) + 1张防盗贴纸 (贴纸以及位置图翻单PO#4500095104）+ 箱唛 + 外箱SSCC Label Remark: 1.请务必按时完货，验货。并且按期送货入货代指定仓库，如果晚了导致船期Delay将会有罚金产生或者客户要求空运，所产生的罚金和空运费由工厂承担。 2.SSCC 外箱贴纸请同纸箱瓦楞纸方向（竖纹向）垂直，即外箱贴纸横着贴(注意条码不要被胶带粘住），贴1pc，贴1面正唛，封箱胶纸不能挡住贴纸内容。外箱贴纸 离外箱边距离不少于2cm。 3.外箱材质为ZURU标准； 4.此单需使用KMART封箱胶上下工字型封箱;从2019年6月开始，要用KMART 新版封箱胶带，此单要用"ANKO"封箱胶带 5.此单出口澳大利亚，请按相应的澳新标准生产； 6.产品和包装上生产批号的显示格式ZURU标准日期码格式 7.外箱信息不可手写，重量和体积需要与实际的一致(不可手写） 8. 每款item装箱后的G.W.超过10KG或者CBM超过0.13,(9.5KG或者以上，四舍五入后也属于10KG) 需在外箱上加印超 重或者Bulky LOGO，若发现我们资料没有，请 帮忙提醒 1)重量超过10kg但不超过16kg且CBM不超过0.13,10-16kg 超重logo 2）CBM超过0.13且重量少于17kg，bulky logo 3）不属于以上两种情况，需要使用相应重量范围内的超重logo 4）超重logo需要在外箱四面都印刷(箱唛右上角，两面侧唛超重logo需要尽量靠近毛重)，尺寸为:110mm height* 95mm width 9. 实际外箱重量跟印在箱唛上的数据差异不能超3%，尺寸按实际数据印刷 | Y29: Lydia Wu | Z29: 6.2908 | AA29: =Z29*I29 -> 8568.0696 | AB29: 88993-1.11 | AC29: 9283-S001 | AD29: 已入 | AG29: =I29 -> 1362 | AN29: =I29 -> 1362 | AR29: =I29 -> 1362 | AW29: =I29 -> 1362 | BF29: MA布标 | BH29: =I29/6 -> 227 | BI29: =I29/6 -> 227 | BJ29: =I29/6 -> 227 | BK29: =I29/6 -> 227 | BL29: =I29/6 -> 227 | BM29: =I29/6 -> 227 | BT29: =SUM(BH29:BS29) -> 1362 | BU29: =I29-BT29 -> 0
A30: 45621 | B30: SUCKOT SAC | C30: 秘鲁 | D30: 4500152261 | F30: 45000152261-70 | G30: 9283-S001 | H30: 美人鱼6只装 | I30: 600 | J30: 0 | K30: 6 | L30: =I30/K30 -> 100 | M30: 45663 | N30: 45659 | P30: PASS | Q30: 1/6出 | R30: 11/26出 | U30: 12/19-UPC贴纸+进口商贴纸 | X30: 日期码格式：ZURU INC(BVI) 标准格式 日期：按实际生产日期 Tracking Code: Packaging Info: 9283：MA 3L EAN包装+UPC贴纸+MA 多语收藏指南+进口商贴纸+箱唛 Remark: 9283: Kitten:Bunny:Puppy:Cow:Elephant:Flamingo=1:1:1:1:1:1; 出货前要提供大货照片给客户确认后才能出货，请按期完货 | Y30: Zoe Luo | Z30: 5.905 | AA30: =Z30*I30 -> 3543 | AB30: 88921-1.7 | AC30: 9283-S001-1 | AD30: 已入 | AJ30: =I30 -> 600 | AN30: =I30 -> 600 | AU30: =I30 -> 600 | AW30: =I30 -> 600 | BF30: MA布标 | BH30: =I30/6 -> 100 | BI30: =I30/6 -> 100 | BJ30: =I30/6 -> 100 | BK30: =I30/6 -> 100 | BL30: =I30/6 -> 100 | BM30: =I30/6 -> 100 | BT30: =SUM(BH30:BS30) -> 600 | BU30: =I30-BT30 -> 0
A31: 45624 | B31: WABRO | C31: 阿根廷 | D31: 4500152720 | F31: 4500152720-160 | G31: 9283-S001 | H31: 美人鱼6只装 | I31: 900 | J31: 0 | K31: 6 | L31: =I31/K31 -> 150 | M31: 45663 | N31: 45659 | P31: PASS | Q31: 1/8出 | R31: 12/3收到 | U31: 12/6-进口商贴纸 | X31: 日期码格式：ZURU INC(BVI) 标准格式 日期：按实际生产日期 Packaging Info: 9283:MA 3L包装+进口商贴纸+箱唛 Remark: LR44 电池品牌为ONLY | Y31: Ava Liang | Z31: 5.905 | AA31: =Z31*I31 -> 5314.5 | AB31: 88958-1.9 | AC31: 9283-S001-1 | AD31: 已入 | AJ31: =I31 -> 900 | AN31: =I31 -> 900 | AU31: =I31 -> 900 | AW31: =I31 -> 900 | BF31: MA布标 | BH31: =I31/6 -> 150 | BI31: =I31/6 -> 150 | BJ31: =I31/6 -> 150 | BK31: =I31/6 -> 150 | BL31: =I31/6 -> 150 | BM31: =I31/6 -> 150 | BT31: =SUM(BH31:BS31) -> 900 | BU31: =I31-BT31 -> 0
A32: 45623 | B32: AMAZON.COM.DEDC,LLC | C32: 美国 | D32: 4500152379 | E32: 24XZNY6S | F32: 4500152379-340 | G32: 9283D-S002 | H32: 小狗（邮包盒） | I32: 36 | J32: 1 | K32: 4 | L32: =I32/K32 -> 9 | M32: 45664 | N32: 45660 | P32: PASS | Q32: 2/7出 | R32: 11/27收到 | U32: 无 | V32: 12/20-客供外箱贴纸 | W32: 9283D邮包盒图稿跟返单4500139401 | X32: 日期码格式： 标准格式 日期：按实际生产日期 Packaging Info: #9283: MA 1L入邮包盒，9283A邮包盒图稿跟翻单#4500135161，9283D邮包盒图稿跟返单4500139401。 Remark: 1. Amazon FOB订单，出口US。 2. 日期码使用ZURU标准版本。 3. 如果大货有要求入邮包盒，则对应的邮包盒上面要打上日期码。 4. 箱尺寸要求：外箱最长边不能超过25" （超过了，case pack只能为1），不符合要求的大货，一律不接受。 5. 外箱箱唛要求： ①外箱正面印ZURU Logo+SSCC Label（客供贴纸，由跟单订购)。关于 SSCC Label 请注意： SSCC Label 显示的是客人自己的item#。每一张SSCC label 都是唯一且有不同流水及条码的，没有损耗，绝对不可贴错 。如果贴错或损坏任何一张，都会导致全 部都错，千万要注意！ SSCC Label 必须贴在外箱正面的正中间位置（贴一面即可），并且贴纸离外箱边距必须至少3cm(可以覆盖Logo<(>&<)>箱唛)，否则会影响到客户那边仓库的扫描识 别。 ②外箱侧面印item#（订单上显示的SKU#)+carton size(以工厂实际尺寸为准,单位: inch) +MADE IN CHINA,日期使用ZURU 标准版本。 6. 装柜要求：按照客户PO# 装柜/箱号顺序装柜，跟单会提前给到装柜计划。 在大货生产/仓库存放时，请留意该装柜要求，以便装柜时不混乱（避免装错/装漏/找不到货号等）。 | Y32: Kelly Shen | Z32: 6.1693 | AA32: =Z32*I32 -> 222.0948 | AB32: 94201-2.10 | AC32: 9283D-S002 | AD32: 已入 | AG32: =I32 -> 36 | AN32: =I32 -> 36 | AR32: =I32 -> 36 | AW32: =I32 -> 36 | BF32: MA布标 | BJ32: =I32 -> 36 | BT32: =SUM(BH32:BS32) -> 36 | BU32: =I32-BT32 -> 0
A33: 45623 | B33: AMAZON.COM.DEDC,LLC | C33: 美国 | D33: 4500152379 | E33: 1776T8ZG | F33: 4500152379-350 | G33: 9283D-S002 | H33: 小狗（邮包盒） | I33: 116 | J33: 1 | K33: 4 | L33: =I33/K33 -> 29 | M33: 45664 | N33: 45660 | P33: PASS | Q33: 2/7出 | R33: 11/27收到 | U33: 无 | V33: 12/20-客供外箱贴纸 | W33: 9283D邮包盒图稿跟返单4500139401 | X33: 日期码格式： 标准格式 日期：按实际生产日期 Packaging Info: #9283: MA 1L入邮包盒，9283A邮包盒图稿跟翻单#4500135161，9283D邮包盒图稿跟返单4500139401。 Remark: 1. Amazon FOB订单，出口US。 2. 日期码使用ZURU标准版本。 3. 如果大货有要求入邮包盒，则对应的邮包盒上面要打上日期码。 4. 箱尺寸要求：外箱最长边不能超过25" （超过了，case pack只能为1），不符合要求的大货，一律不接受。 5. 外箱箱唛要求： ①外箱正面印ZURU Logo+SSCC Label（客供贴纸，由跟单订购)。关于 SSCC Label 请注意： SSCC Label 显示的是客人自己的item#。每一张SSCC label 都是唯一且有不同流水及条码的，没有损耗，绝对不可贴错 。如果贴错或损坏任何一张，都会导致全 部都错，千万要注意！ SSCC Label 必须贴在外箱正面的正中间位置（贴一面即可），并且贴纸离外箱边距必须至少3cm(可以覆盖Logo<(>&<)>箱唛)，否则会影响到客户那边仓库的扫描识 别。 ②外箱侧面印item#（订单上显示的SKU#)+carton size(以工厂实际尺寸为准,单位: inch) +MADE IN CHINA,日期使用ZURU 标准版本。 6. 装柜要求：按照客户PO# 装柜/箱号顺序装柜，跟单会提前给到装柜计划。 在大货生产/仓库存放时，请留意该装柜要求，以便装柜时不混乱（避免装错/装漏/找不到货号等）。 | Y33: Kelly Shen | Z33: 6.1693 | AA33: =Z33*I33 -> 715.6388 | AB33: 94201-2.10 | AC33: 9283D-S002 | AD33: 已入 | AG33: =I33 -> 116 | AN33: =I33 -> 116 | AR33: =I33 -> 116 | AW33: =I33 -> 116 | BF33: MA布标 | BJ33: =I33 -> 116 | BT33: =SUM(BH33:BS33) -> 116 | BU33: =I33-BT33 -> 0
A34: 45623 | B34: AMAZON.COM.DEDC,LLC | C34: 美国 | D34: 4500152657 | E34: 5JF5W6AV | F34: 4500152657-100 | G34: 9283D-S002 | H34: 小狗（邮包盒） | I34: 172 | J34: 1 | K34: 4 | L34: =I34/K34 -> 43 | M34: 45664 | N34: 45660 | P34: PASS | Q34: 1/14出 | R34: 11/27收到 | U34: 无 | V34: 12/20-客供外箱贴纸 | W34: 9283D邮包盒图稿跟返单4500139401 | X34: 日期码格式： 标准格式 日期：按实际生产日期 Packaging Info: #9283: MA 1L入邮包盒，9283A邮包盒图稿跟翻单#4500135161，9283D邮包盒图稿跟返单4500139401。 Remark: 1. Amazon FOB订单，出口US。 2. 日期码使用ZURU标准版本。 3. 如果大货有要求入邮包盒，则对应的邮包盒上面要打上日期码。 4. 箱尺寸要求：外箱最长边不能超过25" （超过了，case pack只能为1），不符合要求的大货，一律不接受。 5. 外箱箱唛要求： ①外箱正面印ZURU Logo+SSCC Label（客供贴纸，由跟单订购)。关于 SSCC Label 请注意： SSCC Label 显示的是客人自己的item#。每一张SSCC label 都是唯一且有不同流水及条码的，没有损耗，绝对不可贴错 。如果贴错或损坏任何一张，都会导致全 部都错，千万要注意！ SSCC Label 必须贴在外箱正面的正中间位置（贴一面即可），并且贴纸离外箱边距必须至少3cm(可以覆盖Logo<(>&<)>箱唛)，否则会影响到客户那边仓库的扫描识 别。 ②外箱侧面印item#（订单上显示的SKU#)+carton size(以工厂实际尺寸为准,单位: inch) +MADE IN CHINA,日期使用ZURU 标准版本。 6. 装柜要求：按照客户PO# 装柜/箱号顺序装柜，跟单会提前给到装柜计划。 在大货生产/仓库存放时，请留意该装柜要求，以便装柜时不混乱（避免装错/装漏/找不到货号等）。 | Y34: Kelly Shen | Z34: 6.1693 | AA34: =Z34*I34 -> 1061.1196 | AB34: 94001-1.13 | AC34: 9283D-S002 | AD34: 已入 | AG34: =I34 -> 172 | AN34: =I34 -> 172 | AR34: =I34 -> 172 | AW34: =I34 -> 172 | BF34: MA布标 | BJ34: =I34 -> 172 | BT34: =SUM(BH34:BS34) -> 172 | BU34: =I34-BT34 -> 0
A35: 45623 | B35: AMAZON.COM.DEDC,LLC | C35: 美国 | D35: 4500152472 | E35: 8M75H1DC | F35: 4500152472-50 | G35: 9283A-S002 | H35: 小猫（邮包盒） | I35: 548 | J35: 1 | K35: 4 | L35: =I35/K35 -> 137 | M35: 45666 | N35: 45663 | P35: PASS | Q35: 1/20出 | R35: 11/27收到 | U35: 无 | V35: 12/20-客供外箱贴纸 | W35: 9283A邮包盒图稿跟翻单#4500135161 | X35: 日期码格式：ZURU INC(BVI) 标准格式 日期：按实际生产日期 Packaging Info: #9283：MA 1L入邮包盒，9283A邮包盒图稿跟翻单#4500135161，9283D邮包盒图稿跟返单4500139401。 Remark: 1. Amazon FOB订单，出口US。 2. 日期码使用ZURU标准版本。 3. 如果大货有要求入邮包盒，则对应的邮包盒上面要打上日期码。 4. 箱尺寸要求：外箱最长边不能超过25"(超过了，case pack只能为1)，不符合要求的大货，一律不接受。 5. 外箱箱唛要求： ①外箱正面印ZURU Logo+SSCC Label(客供贴纸，由跟单订购)。关于 SSCC Label 请注意： SSCC Label显示的是客人自己的item#。每一张SSCC label都是唯一且有不同流水及条码的，没有损耗，绝对不可贴错。如果贴错或损坏任何一张，都会导致全部都 错，千万要注意！SSCC Label必须贴在外箱正面的正中间位置(贴一面即可)，并且贴纸离外箱边距必须至少3cm(可以覆盖Logo<(>&<)>箱唛)，否则会影响到客户那边 仓库的扫描识别。 ②外箱侧面印item#(订单上显示的SKU#)+carton size(以工厂实际尺寸为准，单位: inch)+MADE IN CHINA，日期使用ZURU 标准版本。 6. 装柜要求：按照客户PO#装柜/箱号顺序装柜，跟单会提前给到装柜计划。 在大货生产/仓库存放时，请留意该装柜要求，以便装柜时不混乱(避免装错/装漏/找不到货号等)。 | Y35: Kelly Shen | Z35: 6.1693 | AA35: =Z35*I35 -> 3380.7764 | AB35: 94109-1.18 | AC35: 9283A-S002 | AD35: 已入 | AG35: =I35 -> 548 | AN35: =I35 -> 548 | AR35: =I35 -> 548 | AW35: =I35 -> 548 | BF35: MA布标 | BH35: =I35 -> 548 | BT35: =SUM(BH35:BS35) -> 548 | BU35: =I35-BT35 -> 0
A36: 45618 | B36: CRG | C36: 哥斯达黎加 | D36: 4500152087 | E36: ZU01-25 | F36: 4500152087-70 | G36: 9283-S001 | H36: 美人鱼6只装 | I36: 504 | J36: 0 | K36: 6 | L36: =I36/K36 -> 84 | M36: 45660 | N36: 45656 | P36: PASS | Q36: 1/8出 | R36: 11/27收到 | U36: 进口商贴纸翻4500098650 | X36: 日期码格式：ZURU INC(BVI) 标准格式 日期：按实际生产日期 Packaging Info: 9283:MA 1L包装+进口商贴纸+箱唛，进口商贴纸翻单PO4500098650 Remark: | Y36: Ava Liang | Z36: 5.905 | AA36: =Z36*I36 -> 2976.12 | AB36: 88961-1.9 | AC36: 9283-S001 | AD36: 已入 | AG36: =I36 -> 504 | AN36: =I36 -> 504 | AR36: =I36 -> 504 | AW36: =I36 -> 504 | BF36: MA布标 | BH36: =I36/6 -> 84 | BI36: =I36/6 -> 84 | BJ36: =I36/6 -> 84 | BK36: =I36/6 -> 84 | BL36: =I36/6 -> 84 | BM36: =I36/6 -> 84 | BT36: =SUM(BH36:BS36) -> 504 | BU36: =I36-BT36 -> 0
A37: 45625 | B37: TJX UK | C37: 英国 | D37: 4500152937 | E37: TJX UK: PO#50343294 | F37: 4500152937-10 | G37: 9283-S001 | H37: 美人鱼6只装 | I37: 900 | J37: 0 | K37: 6 | L37: =I37/K37 -> 150 | M37: 45660 | N37: 45656 | P37: PASS | Q37: 1/9出 | R37: 12/5收到 | U37: 12/6-客供价格贴纸 | X37: 日期码格式：ZURU INC(BVI) 标准格式 日期：按实际生产日期 Tracking Code: Packaging Info: TJX UK: PO#50343294(9283) <(>&<)> PO#50343296(9258) <(>&<)> PO#50343296(9281) <(>&<)> PO#50343305(9298) <(>&<)> PO#50343349(7132) <(>&<)> PO#503 43349(92107) <(>&<)> PO#50343392(9279) <(>&<)> PO#50343399(9279) 1) 9283: MA 3L(9Lwarning) C版收缩膜+ 其他最新MA配套包装+1张客供价格贴纸 8) 最迟验货时间不得晚于1/4 Remark: 1. 出往UK的产品+包装务必打上UKCA logo ，否则客人会退货且当地会有罚款； 2. 订单必须经过ZURU QC验货并且通过后方可出货； 3. 订单每行对应客人不同的PO， 箱唛也有不同，做货的时候请分开堆放； 4. 订单每行对应客人不同的PO，即同款item的价格贴纸都不相同，请注意收到贴纸后不要弄混!（客人PO号请参考PO最后一栏remark）； 5. 价格贴纸位置为产品正面右上角，不能遮住产品信息，大货生产前，请把贴纸位置先发给跟单确认 6. 涉及到相关款式会有闪粉的或 者微塑料的，请统一默认出无闪粉或者不含微塑料 版本; 7. 外箱封箱必须是工字型封箱方式； | Y37: Zoe Chen | Z37: 5.905 | AA37: =Z37*I37 -> 5314.5 | AB37: 88953-1.9 | AC37: 9283-S001-1 | AD37: 已入 | AJ37: =I37 -> 900 | AN37: =I37 -> 900 | AU37: =I37 -> 900 | AW37: =I37 -> 900 | BF37: MA布标 | BH37: =I37/6 -> 150 | BI37: =I37/6 -> 150 | BJ37: =I37/6 -> 150 | BK37: =I37/6 -> 150 | BL37: =I37/6 -> 150 | BM37: =I37/6 -> 150 | BT37: =SUM(BH37:BS37) -> 900 | BU37: =I37-BT37 -> 0
A38: 45625 | B38: TJX UK c/o TJX Distribution Ltd & C | C38: 英国 | D38: 4500152906 | E38: TJX Europe(DE): PO#55343895 | F38: 4500152906-10 | G38: 9283-S001 | H38: 美人鱼6只装 | I38: 900 | J38: 0 | K38: 6 | L38: =I38/K38 -> 150 | M38: 45660 | N38: 45656 | P38: PASS | Q38: 1/10出 | R38: 12/5收到 | U38: 12/6-客供价格贴纸+含波兰警示语翻4500150830 | X38: 日期码格式：ZURU INC(BVI) 标准格式 日期：按实际生产日期 Packaging Info: TJX Europe(DE): PO#55343895(9283) <(>&<)> PO#55343898(9258) <(>&<)> PO#55343898(9281) <(>&<)> PO#55343901(9281) <(>&<)> PO#55343906(9298) <(>& <)> PO#55343909(9298) <(>&<)> PO#55343918(7132) <(>&<)> PO#55343920(7132) <(>&<)> PO#55343920(92107) <(>&<)> PO#55343844(9279) <(>&<)> PO#553438 77(9279) 1) 9283: MA 3L(9Lwarning) C版收缩膜+ 其他最新MA配套包装+1张客供价格贴纸+1张贴纸（含波兰警示语） 8) 最迟验货时间不得晚于1/4 Remark: 1. 出往UK的产品+包装务必打上UKCA logo ，否则客人会退货且当地会有罚款； 2.订单必须经过ZURU QC验货并且通过后方可出货； 3. 订单每行对应客人不同的PO， 箱唛也有不同，做货的时候请分开堆放； 4. 订单每行对应客人不同的PO，即同款item的价格贴纸都不相同，请注意收到贴纸后不要弄混!（客人PO号请参考PO最后一栏remark）； 5. 价格贴纸位置为产品正面右上角，不能遮住产品信息，大货生产前，请把贴纸位置先发给跟单确认 6. 涉及到相关款式会有闪粉的或者微塑料的，请统一默认出无闪粉或者不含微塑料版本; 7. 外箱封箱必须是工字型封箱方式； | Y38: Zoe Chen | Z38: 5.905 | AA38: =Z38*I38 -> 5314.5 | AB38: 88968-1.10 | AC38: 9283-S001-1 | AD38: 已入 | AJ38: =I38 -> 900 | AN38: =I38 -> 900 | AU38: =I38 -> 900 | AW38: =I38 -> 900 | BF38: MA布标 | BH38: =I38/6 -> 150 | BI38: =I38/6 -> 150 | BJ38: =I38/6 -> 150 | BK38: =I38/6 -> 150 | BL38: =I38/6 -> 150 | BM38: =I38/6 -> 150 | BT38: =SUM(BH38:BS38) -> 900 | BU38: =I38-BT38 -> 0
A39: 45623 | B39: HEB GROCERY COMPANY, LP | C39: 美国 | D39: 4500152429 | E39: PO#60X356210 | F39: 4500152429-20 | G39: 9283-S003 | H39: 美人鱼2只装(无闪粉） | I39: 1344 | J39: 0 | K39: 2 | L39: =I39/K39 -> 672 | M39: 45665 | N39: 45661 | O39: 1/9第三方 | P39: PASS | Q39: 1/19出 | R39: 11/27收到 | U39: 无 | X39: 日期码格式：ZURU INC(BVI) 标准格式 日期：按实际生产日期 Packaging Info: 1. ZURU MA UPC版本，出口美国. Remark: 2. 日期跟踪码：ZURU标准格式日期码，产品包装及产品本身都必须有ZURU标准格式日期码，并且确保两者格式和时间保持一致(请自行调整具体年月日生产期，但不能为周末）。 针对你们目前没办法保持日期码一致的做法是： * 大货：可以按照实际生产的日期码打，毛绒布标和蛋壳上的日期码格式和时间这次特例可以不保持一致出货；但到时需手动贴一套公仔的布标贴纸，使布标跟蛋壳 日期码格式和时间一样，拍照给我们发给实验室review 日期码，让实验室知道订单大货出的日期码格式和时间是跟抽板指定款的保持一样。 * 指定款抽板：需手动贴布标贴纸，保证布标跟蛋壳上的日期码格式和时间都一样，且这个时间要跟大货的时间一样。 3. 大货样 #9283签样同旧单4500105770, 但如订单最终出货有物料变更，须提前告知跟单决定是否重新寄签样。 4. 验货+ 抽板 （同一天进行） 预约1月9日第三方（利丰）到工厂做100%大货现场验货和抽板，验货需打印EPM出来跟客户回签样板供第三方验货参考。 PS:EPM是跟单提供。 抽板： 因#9283的ZURU测试报告上被客户指定实验室发现产品和产品包装上的日期码不一致，所以这款寄样给实验室的是按照 利丰验货员现场针对指定款随机抽板6PCS（须带包装）;其他利丰验货员现场针对指定款随机抽板6PCS。 工厂需把抽板寄到以下MTS 地址做测试，测试通过后才能出货；如产品有油漆的工厂需额外准备5G/色的油漆涂在同材质胶件上(面积类似A4纸大小)一并寄出； 实验室收件地址： 东莞现代产品整理服务有限公司（MTS） 广东省东莞市寮步镇新旧围村良平路76号 收件人：Cherry Wang （汪单） Tel: +86 769- 8112 0818 ext.893 抽板有随样文件TRF（跟单提供），工厂在寄样时打印出来放纸箱内随样寄走。 5. 出货配比：ZURU 标版配比 6. ZURU QA 验货时需拍齐每款角色的产品和产品包装上的日期码照片（供实验室review） | Y39: Elsa Zheng | Z39: 5.8775 | AA39: =Z39*I39 -> 7899.36 | AB39: 94212-2.11 | AC39: 9283-S003 | AD39: 已入 | AG39: =I39 -> 1344 | AN39: =I39 -> 1344 | AR39: =I39 -> 1344 | AW39: =I39 -> 1344 | BF39: MA布标 | BH39: =I39/6 -> 224 | BI39: =I39/6 -> 224 | BJ39: =I39/6 -> 224 | BK39: =I39/6 -> 224 | BL39: =I39/6 -> 224 | BM39: =I39/6 -> 224 | BT39: =SUM(BH39:BS39) -> 1344 | BU39: =I39-BT39 -> 0
A40: 45625 | B40: TIENDAS CHEDRAUI, S.A. DE C.V. | C40: 墨西哥 | D40: 4500153048 | F40: 4500153048-30 | G40: 9283-S001 | H40: 美人鱼6只装 | I40: 906 | J40: 0 | K40: 6 | L40: =I40/K40 -> 151 | M40: 45667 | N40: 45663 | P40: PASS | Q40: 1/15出 | R40: 12/13收到 | U40: 12/12-UPC条码贴纸+进口商贴纸 | X40: 日期码格式：ZURU INC(BVI) 标准格式 日期：按实际生产日期 Packaging Info: 2. 9283: MA 3L EAN包装+MA 5L收藏指南+MA 3L try me sticker+进口商贴纸(已包含UPC条码）+箱唛 Remark: 3. 9283：Kitten:Bunny:Puppy:Cow:Elephant:Flamingo=1:1:1:1:1:1; | Y40: Ever Li | Z40: 5.7196 | AA40: =Z40*I40 -> 5181.9576 | AB40: 94048-1.15 | AC40: 9283-S001-1 | AD40: 已入 | AJ40: =I40 -> 906 | AN40: =I40 -> 906 | AU40: =I40 -> 906 | AW40: =I40 -> 906 | BF40: MA布标 | BH40: =I40/6 -> 151 | BI40: =I40/6 -> 151 | BJ40: =I40/6 -> 151 | BK40: =I40/6 -> 151 | BL40: =I40/6 -> 151 | BM40: =I40/6 -> 151 | BT40: =SUM(BH40:BS40) -> 906 | BU40: =I40-BT40 -> 0
A41: 45637 | B41: DIAMANT TOYS LTD | C41: 以色列 | D41: 4500153669 | E41: 56072 | F41: 4500153669-30 | G41: 9283-S001 | H41: 美人鱼6只装 | I41: 1002 | J41: 0 | K41: 6 | L41: =I41/K41 -> 167 | M41: 45672 | N41: 45668 | P41: PASS | Q41: 1/21出 | R41: 12/10收到 | U41: 进口商贴纸翻4500136786+彩色贴纸翻4500136786 | X41: 日期码格式：ZURU INC(BVI) 标准格式 日期：按实际生产日期 Packaging Info: 9283:1L MA收缩膜+进口商贴纸翻4500136786+彩色贴纸翻4500136786;MA指南 Remark: 标准产品标准配比 | Y41: Lena Huang | Z41: 5.8973 | AA41: =Z41*I41 -> 5909.0946 | AB41: 94126-1.20 | AC41: 9283-S001 | AD41: 已入 | AG41: =I41 -> 1002 | AN41: =I41 -> 1002 | AR41: =I41 -> 1002 | AW41: =I41 -> 1002 | BF41: MA布标 | BH41: =I41/6 -> 167 | BI41: =I41/6 -> 167 | BJ41: =I41/6 -> 167 | BK41: =I41/6 -> 167 | BL41: =I41/6 -> 167 | BM41: =I41/6 -> 167 | BT41: =SUM(BH41:BS41) -> 1002 | BU41: =I41-BT41 -> 0
A42: 45604 | B42: AEON TOPVALU (HONG KONG) CO.,LTD | C42: 柬埔寨 | D42: 4500150770 | E42: SDN24-0024 | F42: 4500150770-70 | G42: 9283-S001 | H42: 美人鱼6只装 | I42: 252 | J42: 0 | K42: 6 | L42: =I42/K42 -> 42 | M42: 45663 | N42: 45659 | P42: PASS | Q42: 1/15出 | R42: 11/11收到 | U42: 无 | X42: 日期码格式：ZURU INC(BVI) 标准格式 日期：按实际生产日期 Packaging Info: MA PKG, 优先1L Remark: 出柬埔寨 | Y42: Doris Shou | Z42: 5.974 | AA42: 1505.448 | AB42: 94063-1.16 | AC42: 9283-S001 | AD42: 已入 | AG42: 252 | AN42: 252 | AR42: 252 | AW42: 252 | BF42: MA布标 | BH42: 42 | BI42: 42 | BJ42: 42 | BK42: 42 | BL42: 42 | BM42: 42 | BT42: 252 | BU42: 0
A43: 45623 | B43: Amazon CA (Vendor Center) | C43: 加拿大 | D43: 4500152544 | E43: 7PRRUB6G | F43: 4500152544-80 | G43: 9283A-S002 | H43: 小猫（邮包盒） | I43: 24 | J43: 1 | K43: 4 | L43: =I43/K43 -> 6 | M43: 45670 | N43: 45666 | P43: PASS | Q43: 1/16-1/21出 | R43: 11/27收到 | U43: 无 | V43: 12/20-客供外箱贴纸 | W43: 9283A邮包盒图稿跟翻单#4500135161 | X43: 日期码格式：ZURU INC(BVI) 标准格式 日期：按实际生产日期 Packaging Info: 出口加拿大，包装需要至少2/3L UPC版，无硼版本。 #9283: MA 3L入邮包盒，9283A邮包盒图稿跟翻单#4500135161,跟Amazon US合并订购物料 Remark: 1. Amazon FOB订单，出口CA。外箱最长边不能超过25" （超过了，case pack只能为1），不符合要求的大货，一律不接受。 2. 外箱正面印ZURU Logo + SSCC LABEL（客供贴纸)，侧面印item#（订单上显示的SKU#) + carton size(以工厂实际尺寸为准，单位: inch) + MADE IN CHINA， 日期使用ZURU 标准版本 SSCC Label 显示的是客人自己的item#，SSCC Label 贴在外箱正面的正中间，贴一面即可，跟单订购，贴纸离外箱距必须至少3cm，每一 张SSCC label 都是唯一且有不同流水及条码的，没有损耗，绝对不可贴错 ，否则贴错或损坏一张会导致全部都错，千万要注意: SSCC 贴纸务必要在正中间(可以覆 盖Logo <(>&<)> 箱唛)，否则会影响到仓库扫描识别。 3. 日期码使用ZURU标准版本。 4. 如果大货有要求入邮包盒，则对应的邮包盒上面要打上日期码。 5. 按照客户PO# 装柜/箱号顺序装柜，跟单会提前给到装柜计划。在大货生产/仓库存放时，请留意该装柜要求，以便装柜时不混乱（避免装错/装漏/找不到货号等 ）。 6. 出口加拿大，包装需要至少2/3L UPC版，无硼版本。 7.邮包盒上要印刷日期码 | Y43: Kelly/Mia | Z43: 5.9383 | AA43: =Z43*I43 -> 142.5192 | AB43: 94134-1.21 | AC43: 9283A-S002-3L-1 | AD43: 已入 | AJ43: =I43 -> 24 | AN43: =I43 -> 24 | AU43: =I43 -> 24 | AW43: =I43 -> 24 | BF43: MA布标 | BH43: =I43 -> 24 | BT43: =SUM(BH43:BS43) -> 24 | BU43: =I43-BT43 -> 0
A44: 45623 | B44: Amazon CA (Vendor Center) | C44: 加拿大 | D44: 4500152544 | E44: 1RJYL2VD | F44: 4500152544-150 | G44: 9283A-S002 | H44: 小猫（邮包盒） | I44: 36 | J44: 1 | K44: 4 | L44: =I44/K44 -> 9 | M44: 45670 | N44: 45666 | P44: PASS | Q44: 1/16-1/21出 | R44: 11/27收到 | U44: 无 | V44: 12/20-客供外箱贴纸 | W44: 9283A邮包盒图稿跟翻单#4500135161 | X44: 日期码格式：ZURU INC(BVI) 标准格式 日期：按实际生产日期 Packaging Info: 出口加拿大，包装需要至少2/3L UPC版，无硼版本。 #9283: MA 3L入邮包盒，9283A邮包盒图稿跟翻单#4500135161,跟Amazon US合并订购物料 Remark: 1. Amazon FOB订单，出口CA。外箱最长边不能超过25" （超过了，case pack只能为1），不符合要求的大货，一律不接受。 2. 外箱正面印ZURU Logo + SSCC LABEL（客供贴纸)，侧面印item#（订单上显示的SKU#) + carton size(以工厂实际尺寸为准，单位: inch) + MADE IN CHINA， 日期使用ZURU 标准版本 SSCC Label 显示的是客人自己的item#，SSCC Label 贴在外箱正面的正中间，贴一面即可，跟单订购，贴纸离外箱距必须至少3cm，每一 张SSCC label 都是唯一且有不同流水及条码的，没有损耗，绝对不可贴错 ，否则贴错或损坏一张会导致全部都错，千万要注意: SSCC 贴纸务必要在正中间(可以覆 盖Logo <(>&<)> 箱唛)，否则会影响到仓库扫描识别。 3. 日期码使用ZURU标准版本。 4. 如果大货有要求入邮包盒，则对应的邮包盒上面要打上日期码。 5. 按照客户PO# 装柜/箱号顺序装柜，跟单会提前给到装柜计划。在大货生产/仓库存放时，请留意该装柜要求，以便装柜时不混乱（避免装错/装漏/找不到货号等 ）。 6. 出口加拿大，包装需要至少2/3L UPC版，无硼版本。 7.邮包盒上要印刷日期码 | Y44: Kelly/Mia | Z44: 5.9383 | AA44: =Z44*I44 -> 213.7788 | AB44: 94134-1.21 | AC44: 9283A-S002-3L-1 | AD44: 已入 | AJ44: =I44 -> 36 | AN44: =I44 -> 36 | AU44: =I44 -> 36 | AW44: =I44 -> 36 | BF44: MA布标 | BH44: =I44 -> 36 | BT44: =SUM(BH44:BS44) -> 36 | BU44: =I44-BT44 -> 0
A45: 45623 | B45: Amazon CA (Vendor Center) | C45: 加拿大 | D45: 4500152544 | E45: 1H8EP2XX | F45: 4500152544-210 | G45: 9283A-S002 | H45: 小猫（邮包盒） | I45: 12 | J45: 1 | K45: 4 | L45: =I45/K45 -> 3 | M45: 45670 | N45: 45666 | P45: PASS | Q45: 1/16-1/21出 | R45: 11/27收到 | U45: 无 | V45: 12/20-客供外箱贴纸 | W45: 9283A邮包盒图稿跟翻单#4500135161 | X45: 日期码格式：ZURU INC(BVI) 标准格式 日期：按实际生产日期 Packaging Info: 出口加拿大，包装需要至少2/3L UPC版，无硼版本。 #9283: MA 3L入邮包盒，9283A邮包盒图稿跟翻单#4500135161,跟Amazon US合并订购物料 Remark: 1. Amazon FOB订单，出口CA。外箱最长边不能超过25" （超过了，case pack只能为1），不符合要求的大货，一律不接受。 2. 外箱正面印ZURU Logo + SSCC LABEL（客供贴纸)，侧面印item#（订单上显示的SKU#) + carton size(以工厂实际尺寸为准，单位: inch) + MADE IN CHINA， 日期使用ZURU 标准版本 SSCC Label 显示的是客人自己的item#，SSCC Label 贴在外箱正面的正中间，贴一面即可，跟单订购，贴纸离外箱距必须至少3cm，每一 张SSCC label 都是唯一且有不同流水及条码的，没有损耗，绝对不可贴错 ，否则贴错或损坏一张会导致全部都错，千万要注意: SSCC 贴纸务必要在正中间(可以覆 盖Logo <(>&<)> 箱唛)，否则会影响到仓库扫描识别。 3. 日期码使用ZURU标准版本。 4. 如果大货有要求入邮包盒，则对应的邮包盒上面要打上日期码。 5. 按照客户PO# 装柜/箱号顺序装柜，跟单会提前给到装柜计划。在大货生产/仓库存放时，请留意该装柜要求，以便装柜时不混乱（避免装错/装漏/找不到货号等 ）。 6. 出口加拿大，包装需要至少2/3L UPC版，无硼版本。 7.邮包盒上要印刷日期码 | Y45: Kelly/Mia | Z45: 5.9383 | AA45: =Z45*I45 -> 71.2596 | AB45: 94134-1.21 | AC45: 9283A-S002-3L-1 | AD45: 已入 | AJ45: =I45 -> 12 | AN45: =I45 -> 12 | AU45: =I45 -> 12 | AW45: =I45 -> 12 | BF45: MA布标 | BH45: =I45 -> 12 | BT45: =SUM(BH45:BS45) -> 12 | BU45: =I45-BT45 -> 0
A46: 45630 | B46: WAL-MART STORES INC. USA | C46: 美国 | D46: 4500153263 | E46: 881410092 | F46: 4500153263-10 | G46: 9283SLB-S002 | H46: 美人鱼卡板装 | I46: 540 | J46: 0 | K46: 108 | L46: =I46/K46 -> 5 | M46: 45664 | N46: 45660 | O46: 1/9 BV（自检） | P46: PASS | Q46: 1/9出 | R46: 外箱四面印刷RFID箱唛，正唛左前下角印刷ITF-14格式条码的艾利替代标箱唛，只印刷正唛一面，Z URU logo跟MADE IN CHINA四面右下角印刷 | U46: 消耗4500132388客版布标贴纸 | V46: 消耗4500132388客供RFID贴纸 | X46: 日期码格式：ZURU DGYYYYMMDD CHINA(日期避开周末和法定节假日即可） 日期：按实际生产日期 Packaging Info: Remark: 9283 1.包装信息：MA C版 UPC版 1L收缩膜，MA C版 5L收藏指南，MA B版 1L Try Me贴纸，MA A版 3L贴纸，MA B版 5L配件袋，MA B版 5L泡泡水袋，MA B版 5L魔力沙袋 ，MA B版 5L领养卡，MA C版 5L藏宝图（原刮刮卡），MA B版车缝布标，客版布标贴纸，客供RFID贴纸（标贴位置严格按照我们签板的位置图，不可擅自调整位置， 贴纸不能有任何破损或折坏，不可淋湿）。 2.外箱四面印刷RFID箱唛，正唛左前下角印刷ITF-14格式条码的艾利替代标箱唛，只印刷正唛一面，整个内容尺寸最小10*10cm，加印时需确保条形码能扫描出来，Z URU logo跟MADE IN CHINA四面右下角印刷，外箱印刷日期码，每个slip sheet上面贴一张10*10cm艾利替代标（工厂自行用不干胶打印）和一张普通贴纸（可A4纸 打印），slip sheet打印的普通贴纸的尺寸不能比艾利替代标小。 3.在产品上和包装上要有日期码（避开周末和节假日），以及要有MADE IN CHINA和ZURU字样。 4.产品如有扎带口要剪平，不能刮手。 5.此单需要第三方验货，请自行多备物料。 6.此单打卡板出货（18x6H=108carton=108pcs/Slip Sheet）。 7.其它信息：Kitten : Bunny : Puppy : Cow : Elephant : Flamingo=1:1:1:1:1:1。 | Y46: Effy Li | Z46: 54.1605 | AA46: =L46*Z46 -> 270.8025 | AB46: 94082-1.17 | AC46: 9283SLB-S002 | AD46: 已入 | AG46: =I46 -> 540 | AN46: =I46 -> 540 | AR46: =I46 -> 540 | AW46: =I46 -> 540 | BF46: MA布标新日期格式 | BH46: =I46/6 -> 90 | BI46: =I46/6 -> 90 | BJ46: =I46/6 -> 90 | BK46: =I46/6 -> 90 | BL46: =I46/6 -> 90 | BM46: =I46/6 -> 90 | BT46: =SUM(BH46:BS46) -> 540 | BU46: =I46-BT46 -> 0
A47: 45630 | B47: WAL-MART STORES INC. USA | C47: 美国 | D47: 4500153263 | E47: 881410096 | F47: 450015326320-20 | G47: 9283SLB-S002 | H47: 美人鱼卡板装 | I47: 540 | J47: 0 | K47: 108 | L47: =I47/K47 -> 5 | M47: 45664 | N47: 45660 | O47: 1/9 BV（自检） | P47: PASS | Q47: 1/24出 | R47: 外箱四面印刷RFID箱唛，正唛左前下角印刷ITF-14格式条码的艾利替代标箱唛，只印刷正唛一面，Z URU logo跟MADE IN CHINA四面右下角印刷 | U47: 消耗4500132388客版布标贴纸 | V47: 消耗4500132388客供RFID贴纸 | X47: 日期码格式：ZURU DGYYYYMMDD CHINA(日期避开周末和法定节假日即可） 日期：按实际生产日期 Packaging Info: Remark: 9283 1.包装信息：MA C版 UPC版 1L收缩膜，MA C版 5L收藏指南，MA B版 1L Try Me贴纸，MA A版 3L贴纸，MA B版 5L配件袋，MA B版 5L泡泡水袋，MA B版 5L魔力沙袋 ，MA B版 5L领养卡，MA C版 5L藏宝图（原刮刮卡），MA B版车缝布标，客版布标贴纸，客供RFID贴纸（标贴位置严格按照我们签板的位置图，不可擅自调整位置， 贴纸不能有任何破损或折坏，不可淋湿）。 2.外箱四面印刷RFID箱唛，正唛左前下角印刷ITF-14格式条码的艾利替代标箱唛，只印刷正唛一面，整个内容尺寸最小10*10cm，加印时需确保条形码能扫描出来，Z URU logo跟MADE IN CHINA四面右下角印刷，外箱印刷日期码，每个slip sheet上面贴一张10*10cm艾利替代标（工厂自行用不干胶打印）和一张普通贴纸（可A4纸 打印），slip sheet打印的普通贴纸的尺寸不能比艾利替代标小。 3.在产品上和包装上要有日期码（避开周末和节假日），以及要有MADE IN CHINA和ZURU字样。 4.产品如有扎带口要剪平，不能刮手。 5.此单需要第三方验货，请自行多备物料。 6.此单打卡板出货（18x6H=108carton=108pcs/Slip Sheet）。 7.其它信息：Kitten : Bunny : Puppy : Cow : Elephant : Flamingo=1:1:1:1:1:1。 | Y47: Effy Li | Z47: 54.1605 | AA47: =L47*Z47 -> 270.8025 | AB47: 94002-1.13 | AC47: 9283SLB-S002 | AD47: 已入 | AG47: =I47 -> 540 | AN47: =I47 -> 540 | AR47: =I47 -> 540 | AW47: =I47 -> 540 | BF47: MA布标新日期格式 | BH47: =I47/6 -> 90 | BI47: =I47/6 -> 90 | BJ47: =I47/6 -> 90 | BK47: =I47/6 -> 90 | BL47: =I47/6 -> 90 | BM47: =I47/6 -> 90 | BT47: =SUM(BH47:BS47) -> 540 | BU47: =I47-BT47 -> 0
A48: 45630 | B48: WAL-MART STORES INC. USA | C48: 美国 | D48: 4500153263 | E48: 881410102 | F48: 4500153263-30 | G48: 9283SLB-S002 | H48: 美人鱼卡板装 | I48: 648 | J48: 0 | K48: 108 | L48: =I48/K48 -> 6 | M48: 45664 | N48: 45660 | O48: 1/9 BV（自检） | P48: PASS | Q48: 1/14出 | R48: 外箱四面印刷RFID箱唛，正唛左前下角印刷ITF-14格式条码的艾利替代标箱唛，只印刷正唛一面，Z URU logo跟MADE IN CHINA四面右下角印刷 | U48: 消耗4500132388客版布标贴纸 | V48: 消耗4500132388客供RFID贴纸 | X48: 日期码格式：ZURU DGYYYYMMDD CHINA(日期避开周末和法定节假日即可） 日期：按实际生产日期 Packaging Info: Remark: 9283 1.包装信息：MA C版 UPC版 1L收缩膜，MA C版 5L收藏指南，MA B版 1L Try Me贴纸，MA A版 3L贴纸，MA B版 5L配件袋，MA B版 5L泡泡水袋，MA B版 5L魔力沙袋 ，MA B版 5L领养卡，MA C版 5L藏宝图（原刮刮卡），MA B版车缝布标，客版布标贴纸，客供RFID贴纸（标贴位置严格按照我们签板的位置图，不可擅自调整位置， 贴纸不能有任何破损或折坏，不可淋湿）。 2.外箱四面印刷RFID箱唛，正唛左前下角印刷ITF-14格式条码的艾利替代标箱唛，只印刷正唛一面，整个内容尺寸最小10*10cm，加印时需确保条形码能扫描出来，Z URU logo跟MADE IN CHINA四面右下角印刷，外箱印刷日期码，每个slip sheet上面贴一张10*10cm艾利替代标（工厂自行用不干胶打印）和一张普通贴纸（可A4纸 打印），slip sheet打印的普通贴纸的尺寸不能比艾利替代标小。 3.在产品上和包装上要有日期码（避开周末和节假日），以及要有MADE IN CHINA和ZURU字样。 4.产品如有扎带口要剪平，不能刮手。 5.此单需要第三方验货，请自行多备物料。 6.此单打卡板出货（18x6H=108carton=108pcs/Slip Sheet）。 7.其它信息：Kitten : Bunny : Puppy : Cow : Elephant : Flamingo=1:1:1:1:1:1。 | Y48: Effy Li | Z48: 54.1605 | AA48: =L48*Z48 -> 324.963 | AB48: 94002-1.13 | AC48: 9283SLB-S002 | AD48: 已入 | AG48: =I48 -> 648 | AN48: =I48 -> 648 | AR48: =I48 -> 648 | AW48: =I48 -> 648 | BF48: MA布标新日期格式 | BH48: =I48/6 -> 108 | BI48: =I48/6 -> 108 | BJ48: =I48/6 -> 108 | BK48: =I48/6 -> 108 | BL48: =I48/6 -> 108 | BM48: =I48/6 -> 108 | BT48: =SUM(BH48:BS48) -> 648 | BU48: =I48-BT48 -> 0
A49: 45630 | B49: WAL-MART STORES INC. USA | C49: 美国 | D49: 4500153263 | E49: 881410118 | F49: 4500153263-40 | G49: 9283SLB-S002 | H49: 美人鱼卡板装 | I49: 540 | J49: 0 | K49: 108 | L49: =I49/K49 -> 5 | M49: 45664 | N49: 45660 | O49: 1/9 BV（自检） | P49: PASS | Q49: 1/23出 | R49: 外箱四面印刷RFID箱唛，正唛左前下角印刷ITF-14格式条码的艾利替代标箱唛，只印刷正唛一面，Z URU logo跟MADE IN CHINA四面右下角印刷 | U49: 消耗4500132388客版布标贴纸 | V49: 消耗4500132388客供RFID贴纸 | X49: 日期码格式：ZURU DGYYYYMMDD CHINA(日期避开周末和法定节假日即可） 日期：按实际生产日期 Packaging Info: Remark: 9283 1.包装信息：MA C版 UPC版 1L收缩膜，MA C版 5L收藏指南，MA B版 1L Try Me贴纸，MA A版 3L贴纸，MA B版 5L配件袋，MA B版 5L泡泡水袋，MA B版 5L魔力沙袋 ，MA B版 5L领养卡，MA C版 5L藏宝图（原刮刮卡），MA B版车缝布标，客版布标贴纸，客供RFID贴纸（标贴位置严格按照我们签板的位置图，不可擅自调整位置， 贴纸不能有任何破损或折坏，不可淋湿）。 2.外箱四面印刷RFID箱唛，正唛左前下角印刷ITF-14格式条码的艾利替代标箱唛，只印刷正唛一面，整个内容尺寸最小10*10cm，加印时需确保条形码能扫描出来，Z URU logo跟MADE IN CHINA四面右下角印刷，外箱印刷日期码，每个slip sheet上面贴一张10*10cm艾利替代标（工厂自行用不干胶打印）和一张普通贴纸（可A4纸 打印），slip sheet打印的普通贴纸的尺寸不能比艾利替代标小。 3.在产品上和包装上要有日期码（避开周末和节假日），以及要有MADE IN CHINA和ZURU字样。 4.产品如有扎带口要剪平，不能刮手。 5.此单需要第三方验货，请自行多备物料。 6.此单打卡板出货（18x6H=108carton=108pcs/Slip Sheet）。 7.其它信息：Kitten : Bunny : Puppy : Cow : Elephant : Flamingo=1:1:1:1:1:1。 | Y49: Effy Li | Z49: 54.1605 | AA49: =L49*Z49 -> 270.8025 | AB49: 94094-1.18 | AC49: 9283SLB-S002 | AD49: 已入 | AG49: =I49 -> 540 | AN49: =I49 -> 540 | AR49: =I49 -> 540 | AW49: =I49 -> 540 | BF49: MA布标新日期格式 | BH49: =I49/6 -> 90 | BI49: =I49/6 -> 90 | BJ49: =I49/6 -> 90 | BK49: =I49/6 -> 90 | BL49: =I49/6 -> 90 | BM49: =I49/6 -> 90 | BT49: =SUM(BH49:BS49) -> 540 | BU49: =I49-BT49 -> 0
A50: 45630 | B50: WAL-MART STORES INC. USA | C50: 美国 | D50: 4500153263 | E50: 881410133 | F50: 4500153263-50 | G50: 9283SLB-S002 | H50: 美人鱼卡板装 | I50: 540 | J50: 0 | K50: 108 | L50: =I50/K50 -> 5 | M50: 45664 | N50: 45660 | O50: 1/9 BV（自检） | P50: PASS | Q50: 1/13出 | R50: 外箱四面印刷RFID箱唛，正唛左前下角印刷ITF-14格式条码的艾利替代标箱唛，只印刷正唛一面，Z URU logo跟MADE IN CHINA四面右下角印刷 | U50: 消耗4500132388客版布标贴纸 | V50: 消耗4500132388客供RFID贴纸 | X50: 日期码格式：ZURU DGYYYYMMDD CHINA(日期避开周末和法定节假日即可） 日期：按实际生产日期 Packaging Info: Remark: 9283 1.包装信息：MA C版 UPC版 1L收缩膜，MA C版 5L收藏指南，MA B版 1L Try Me贴纸，MA A版 3L贴纸，MA B版 5L配件袋，MA B版 5L泡泡水袋，MA B版 5L魔力沙袋 ，MA B版 5L领养卡，MA C版 5L藏宝图（原刮刮卡），MA B版车缝布标，客版布标贴纸，客供RFID贴纸（标贴位置严格按照我们签板的位置图，不可擅自调整位置， 贴纸不能有任何破损或折坏，不可淋湿）。 2.外箱四面印刷RFID箱唛，正唛左前下角印刷ITF-14格式条码的艾利替代标箱唛，只印刷正唛一面，整个内容尺寸最小10*10cm，加印时需确保条形码能扫描出来，Z URU logo跟MADE IN CHINA四面右下角印刷，外箱印刷日期码，每个slip sheet上面贴一张10*10cm艾利替代标（工厂自行用不干胶打印）和一张普通贴纸（可A4纸 打印），slip sheet打印的普通贴纸的尺寸不能比艾利替代标小。 3.在产品上和包装上要有日期码（避开周末和节假日），以及要有MADE IN CHINA和ZURU字样。 4.产品如有扎带口要剪平，不能刮手。 5.此单需要第三方验货，请自行多备物料。 6.此单打卡板出货（18x6H=108carton=108pcs/Slip Sheet）。 7.其它信息：Kitten : Bunny : Puppy : Cow : Elephant : Flamingo=1:1:1:1:1:1。 | Y50: Effy Li | Z50: 54.1605 | AA50: =L50*Z50 -> 270.8025 | AB50: 94139-1.21 | AC50: 9283SLB-S002 | AD50: 已入 | AG50: =I50 -> 540 | AN50: =I50 -> 540 | AR50: =I50 -> 540 | AW50: =I50 -> 540 | BF50: MA布标新日期格式 | BH50: =I50/6 -> 90 | BI50: =I50/6 -> 90 | BJ50: =I50/6 -> 90 | BK50: =I50/6 -> 90 | BL50: =I50/6 -> 90 | BM50: =I50/6 -> 90 | BT50: =SUM(BH50:BS50) -> 540 | BU50: =I50-BT50 -> 0
A51: 45609 | B51: TOY TRIANGLE COMPANY (UAE) | C51: 阿拉伯联合酋长国 | D51: 4500151230 | E51: 2025TTC006 | F51: 4500151230-20 | G51: 9283-S001 | H51: 美人鱼6只装 | I51: 10002 | J51: 0 | K51: 6 | L51: =I51/K51 -> 1667 | M51: 45666 | N51: 45663 | P51: PASS | Q51: 1/16出 | R51: 11/13收到 | U51: 无 | W51: 客版收缩膜翻4500137300 11/25收到客版收藏指南 | X51: 日期码格式：ZURU INC(BVI) 标准格式 日期：按实际生产日期 Packaging Info: 9283:客版收缩膜翻4500137300（改彩虹颜色，不含希伯来警告语，需要印G MARK，含进口商贴纸，含QR code), QR code要求印刷清晰且手机可扫描，扫描结果387 11。客版指南 92115：客版收缩膜翻4500134696（改彩虹颜色，不含slime和希伯来警告语)，需要印G MARK，含进口商贴纸，含QR code), QR code要求印刷清晰且手机可扫描， 扫描结果38711 。客版指南翻4500134696（改彩虹颜色，不含slime和希伯来警告语));客版挂卡翻4500134696 92117/92118：客版收缩膜翻4500134696（改彩虹颜色，不含slime和希伯来警告语，需含阿拉伯警告语，印G mark+TTC panel 信息，客版指南翻4500134696（改彩 虹颜色，不含slime和希伯来警告语）;；客版收缩膜上的二维码微信可扫, 扫描结果38711. 客版沙子PE POLYBAG 含阿拉伯警语翻4500134696 Remark: 92115:#92106 Remove Slime RHINO:KOALA:ELEPHANT=1:1:1 92117:#92107 Smart Sandy replaces slime 4 Assortment Ratio (Ladybug: Giraffe: Butterfly: Elephant)=1:1:1:1 92118:#92108 Smart Sandy replaces slime 4 Assortments (bunny: puppy: unicorn: kitten)=1:1:1:1 3pcs AAA batteries (not included) | Y51: Lena Huang | Z51: 5.8538 | AA51: =Z51*I51 -> 58549.708 | AB51: 94062-1.16 | AC51: 9283-S001-7 | AD51: 已入 | AK51: =I51 -> 10002 | AO51: =I51 -> 10002 | AR51: =I51 -> 10002 | AW51: =I51 -> 10002 | BF51: MA布标 | BH51: =I51/6 -> 1667 | BI51: =I51/6 -> 1667 | BJ51: =I51/6 -> 1667 | BK51: =I51/6 -> 1667 | BL51: =I51/6 -> 1667 | BM51: =I51/6 -> 1667 | BT51: =SUM(BH51:BS51) -> 10002 | BU51: =I51-BT51 -> 0
A52: 45603 | B52: DD’S DISCOUNTS | C52: 美国 | D52: 4500150317 | E52: 70054070 | F52: 4500150317-30 | G52: 9283-S001 | H52: 美人鱼6只装 | I52: 402 | J52: 0 | K52: 6 | L52: =I52/K52 -> 67 | M52: 45670 | N52: 45666 | P52: PASS | Q52: 1/20出 | R52: 指定箱唛格式 | U52: 无 | V52: 12/2客供价格贴纸 | X52: 日期码格式： 标准格式 日期：按实际生产日期 Packaging Info: 1.ZURU MA UPC 现有版本包装 + 客供价格贴纸，出口美国 , 优先使用MA 1L 最新版本 。 Remark: 1.ZURU MA UPC 现有版本包装 + 客供价格贴纸，出口美国 , 优先使用MA 1L 最新版本 。 2.价格贴纸位于包装正面右下角，不挡住重要信息即可，可适当调整 ，价格贴纸由跟单提供。 3.标准日期码格式，产品和包装必须有日期码 。 4.同个产品同个货期不可出现不同的包装。 5. 跟单提供ROSS通用的箱唛模版，工厂按实际45 PO上客户PO/Item号/装箱数 提供箱唛排版来确认 | Y52: Taylor Liao | Z52: 5.7196 | AA52: =Z52*I52 -> 2299.2792 | AB52: 94129-1.21 | AC52: 9283-S001 | AD52: 已入 | AG52: =I52 -> 402 | AN52: =I52 -> 402 | AR52: =I52 -> 402 | AW52: =I52 -> 402 | BF52: MA布标 | BH52: =I52/6 -> 67 | BI52: =I52/6 -> 67 | BJ52: =I52/6 -> 67 | BK52: =I52/6 -> 67 | BL52: =I52/6 -> 67 | BM52: =I52/6 -> 67 | BT52: =SUM(BH52:BS52) -> 402 | BU52: =I52-BT52 -> 0
A53: 45635 | B53: Zhuyu(Shenzhen)Trading Co.,Ltd. | C53: 中国 | D53: 4500153795 | E53: 5000001719 | F53: 4500153795-10 | G53: 9283-S001 | H53: 美人鱼6只装 | I53: 1968 | J53: 0 | K53: 6 | L53: =I53/K53 -> 328 | M53: 45670 | N53: 45666 | P53: PASS | Q53: 2/6出 | R53: 翻单： 4500152175 | U53: 中文3C贴纸+中文布标(可用布标贴纸)+年龄贴纸 翻4500152175 | V53: 12/19-芯片码（客供） | X53: 日期码格式：ZURU INC(BVI) 标准格式 日期：按实际生产日期 Packaging Info: 2.外箱材质如下： 1）毛重小于5kg 外箱纸质 K=B 爆破:1000Kpa 边压:4400N/M; 2）毛重大于5kg 外箱纸质 K636K 爆破:1400Kpa 边压:6300N/M; 3. 产品/销售包装/外箱日期码要一致， 4.芯片码横向平贴在上半部分蛋壳/彩盒内侧立面处，注意事项请见跟单提供文档资料。 5.此产品务必满足国内6P 测试标准，因为可能会被市场监督局抽查，如有问题产生，工厂要负全责 6. 这张订单做出厂价，我司自行安排车辆去贵司提货，贵司需要配合提供出口报关 Remark: 物料要求 SKU 所有款号务必使用带有CCC 标识的AW A. 9283 MA+中文3C贴纸 +中文收藏指南+中文布标(可用布标贴纸)+中文领养卡 +年龄贴纸+芯片码（客供） 翻单： 4500152175 | Y53: Tina Chen | Z53: 5.712 | AA53: =Z53*I53 -> 11241.216 | AB53: 94181-2.6 | AC53: 9283-S001-6 | AD53: 已入 | AG53: =I53 -> 1968 | AO53: =I53 -> 1968 | AR53: =I53 -> 1968 | AW53: =I53 -> 1968 | BF53: MA布标+布标贴纸 | BH53: =I53/6 -> 328 | BI53: =I53/6 -> 328 | BJ53: =I53/6 -> 328 | BK53: =I53/6 -> 328 | BL53: =I53/6 -> 328 | BM53: =I53/6 -> 328 | BT53: =SUM(BH53:BS53) -> 1968 | BU53: =I53-BT53 -> 0
A54: 45635 | B54: Zhuyu(Shenzhen)Trading Co.,Ltd. | C54: 中国 | D54: 4500153795 | E54: 5000001719 | F54: 4500153795-30 | G54: 9283-S001 | H54: 美人鱼6只装 | I54: 1632 | J54: 0 | K54: 6 | L54: =I54/K54 -> 272 | M54: 45670 | N54: 45666 | P54: PASS | Q54: 2/6出 | R54: 翻单： 4500152175 | U54: 中文3C贴纸+中文布标(可用布标贴纸)+年龄贴纸 翻4500152175 | V54: 12/19-芯片码（客供） | X54: 日期码格式：ZURU INC(BVI) 标准格式 日期：按实际生产日期 Packaging Info: 2.外箱材质如下： 1）毛重小于5kg 外箱纸质 K=B 爆破:1000Kpa 边压:4400N/M; 2）毛重大于5kg 外箱纸质 K636K 爆破:1400Kpa 边压:6300N/M; 3. 产品/销售包装/外箱日期码要一致， 4.芯片码横向平贴在上半部分蛋壳/彩盒内侧立面处，注意事项请见跟单提供文档资料。 5.此产品务必满足国内6P 测试标准，因为可能会被市场监督局抽查，如有问题产生，工厂要负全责 6. 这张订单做出厂价，我司自行安排车辆去贵司提货，贵司需要配合提供出口报关 Remark: 物料要求 SKU 所有款号务必使用带有CCC 标识的AW A. 9283 MA+中文3C贴纸 +中文收藏指南+中文布标(可用布标贴纸)+中文领养卡 +年龄贴纸+芯片码（客供） 翻单： 4500152175 | Y54: Tina Chen | Z54: 5.712 | AA54: =Z54*I54 -> 9321.984 | AB54: 94181-2.6 | AC54: 9283-S001-6 | AD54: 已入 | AG54: =I54 -> 1632 | AO54: =I54 -> 1632 | AR54: =I54 -> 1632 | AW54: =I54 -> 1632 | BF54: MA布标+布标贴纸 | BH54: =I54/6 -> 272 | BI54: =I54/6 -> 272 | BJ54: =I54/6 -> 272 | BK54: =I54/6 -> 272 | BL54: =I54/6 -> 272 | BM54: =I54/6 -> 272 | BT54: =SUM(BH54:BS54) -> 1632 | BU54: =I54-BT54 -> 0
A55: 45586 | B55: TJX COMPANIES, INC | C55: 美国 | D55: 4500147800 | E55: Marshalls DC#881-372PCS , DC#884-288PCS , DC#886-414PCS , DC#887-348PCS , DC#888-378PCS | F55: 4500147800-20 | G55: 9283-S001 | H55: 美人鱼6只装 | I55: 1800 | J55: 0 | K55: 6 | L55: =I55/K55 -> 300 | M55: 45677 | N55: 45673 | P55: PASS | Q55: 2/14出 | R55: 11/4收到 | U55: 无 | V55: 12/20-价格贴纸 | X55: 日期码格式：ZURU INC(BVI) 标准格式 日期：按实际生产日期 Packaging Info: MA UPC包装+价格贴纸，价格贴纸客供。 Remark: 1. 产品和包装上印刷tracking code信息，格式为ZURU常规格式。 2. 分5个DC出货，每款产品每个DC的箱唛资料不同。具体分DC数量，请参考后面行项目备注。 3. ZURU QC验货。 | Y55: Emily Wu | Z55: 5.8973 | AA55: =Z55*I55 -> 10615.14 | AC55: 9283-S001 | AD55: 已入 | AG55: =I55 -> 1800 | AN55: =I55 -> 1800 | AR55: =I55 -> 1800 | AW55: =I55 -> 1800 | BF55: MA布标 | BH55: =I55/6 -> 300 | BI55: =I55/6 -> 300 | BJ55: =I55/6 -> 300 | BK55: =I55/6 -> 300 | BL55: =I55/6 -> 300 | BM55: =I55/6 -> 300 | BT55: =SUM(BH55:BS55) -> 1800 | BU55: =I55-BT55 -> 0
A56: 45586 | B56: TJX COMPANIES, INC | C56: 美国 | D56: 4500147803 | E56: TJ MAXX DC#891-396PCS , DC#894-342PCS , DC#896-318PCS , DC#897-624PCS , DC#898-318PCS | F56: 4500147803-20 | G56: 9283-S001 | H56: 美人鱼6只装 | I56: 1998 | J56: 0 | K56: 6 | L56: =I56/K56 -> 333 | M56: 45677 | N56: 45673 | P56: PASS | Q56: 2/13出 | R56: 11/4收到 | U56: 无 | V56: 12/20-价格贴纸 | X56: 日期码格式：ZURU INC(BVI) 标准格式 日期：按实际生产日期 Packaging Info: MA UPC包装+价格贴纸，价格贴纸客供。 Remark: 1. 产品和包装上印刷tracking code信息，格式为ZURU常规格式。 2. 分5个DC出货，每款产品每个DC的箱唛资料不同。具体分DC数量，请参考后面行项目备注。 3. ZURU QC验货。 | Y56: Emily Wu | Z56: 5.8973 | AA56: =Z56*I56 -> 11782.805 | AC56: 9283-S001 | AD56: 已入 | AG56: =I56 -> 1998 | AN56: =I56 -> 1998 | AR56: =I56 -> 1998 | AW56: =I56 -> 1998 | BF56: MA布标 | BH56: =I56/6 -> 333 | BI56: =I56/6 -> 333 | BJ56: =I56/6 -> 333 | BK56: =I56/6 -> 333 | BL56: =I56/6 -> 333 | BM56: =I56/6 -> 333 | BT56: =SUM(BH56:BS56) -> 1998 | BU56: =I56-BT56 -> 0
A57: 45586 | B57: TJX COMPANIES, INC | C57: 美国 | D57: 4500147799 | E57: Marshalls DC#881-372PCS , DC#884-288PCS , DC#886-414PCS , DC#887-348PCS , DC#888-378PCS | F57: 4500147799-10 | G57: 9283-S001 | H57: 美人鱼6只装 | I57: 1800 | J57: 0 | K57: 6 | L57: =I57/K57 -> 300 | M57: 45677 | N57: 45673 | P57: PASS | Q57: 2/14出 | R57: 11/4收到 | U57: 无 | V57: 12/20-价格贴纸 | X57: 日期码格式：ZURU INC(BVI) 标准格式 日期：按实际生产日期 Packaging Info: MA UPC包装+价格贴纸，价格贴纸客供。 Remark: 1. 产品和包装上印刷tracking code信息，格式为ZURU常规格式。 2. 分5个DC出货，每款产品每个DC的箱唛资料不同。具体分DC数量，请参考后面行项目备注。 3. ZURU QC验货。 | Y57: Emily Wu | Z57: 5.712 | AA57: =Z57*I57 -> 10281.6 | AC57: 9283-S001 | AD57: 已入 | AG57: =I57 -> 1800 | AN57: =I57 -> 1800 | AR57: =I57 -> 1800 | AW57: =I57 -> 1800 | BF57: MA布标 | BH57: =I57/6 -> 300 | BI57: =I57/6 -> 300 | BJ57: =I57/6 -> 300 | BK57: =I57/6 -> 300 | BL57: =I57/6 -> 300 | BM57: =I57/6 -> 300 | BT57: =SUM(BH57:BS57) -> 1800 | BU57: =I57-BT57 -> 0
A58: 45586 | B58: TJX COMPANIES, INC | C58: 美国 | D58: 4500147801 | E58: TJ MAXX DC#891-396PCS , DC#894-342PCS , DC#896-318PCS , DC#897-624PCS , DC#898-318PCS | F58: 4500147801-10 | G58: 9283-S001 | H58: 美人鱼6只装 | I58: 1998 | J58: 0 | K58: 6 | L58: =I58/K58 -> 333 | M58: 45677 | N58: 45673 | P58: PASS | Q58: 2/11出 | R58: 11/4收到 | U58: 无 | V58: 12/19-价格贴纸 | X58: 日期码格式：ZURU INC(BVI) 标准格式 日期：按实际生产日期 Packaging Info: MA UPC包装+价格贴纸，价格贴纸客供。 Remark: 1. 产品和包装上印刷tracking code信息，格式为ZURU常规格式。 2. 分5个DC出货，每款产品每个DC的箱唛资料不同。具体分DC数量，请参考后面行项目备注。 3. ZURU QC验货。 | Y58: Emily Wu | Z58: 5.8973 | AA58: =Z58*I58 -> 11782.805 | AC58: 9283-S001 | AD58: 已入 | AG58: =I58 -> 1998 | AN58: =I58 -> 1998 | AR58: =I58 -> 1998 | AW58: =I58 -> 1998 | BF58: MA布标 | BH58: =I58/6 -> 333 | BI58: =I58/6 -> 333 | BJ58: =I58/6 -> 333 | BK58: =I58/6 -> 333 | BL58: =I58/6 -> 333 | BM58: =I58/6 -> 333 | BT58: =SUM(BH58:BS58) -> 1998 | BU58: =I58-BT58 -> 0
A59: 45608 | B59: ROSS PROCUREMENT.INC | C59: 美国 | D59: 4500150488 | E59: 60190680 | F59: 4500150488-30 | G59: 9283-S001 | H59: 美人鱼6只装 | I59: 1500 | J59: 0 | K59: 6 | L59: =I59/K59 -> 250 | M59: 45677 | N59: 45673 | P59: PASS | Q59: 2/11出 | R59: 指定箱唛格式 | U59: 无 | V59: 12/20-价格贴纸 | X59: 日期码格式： 标准格式 日期：按实际生产日期 Packaging Info: 1.ZURU MA UPC 现有版本包装 + 客供价格贴纸，出口美国 , 优先使用MA 1L 最新版本 。 Remark: 1.ZURU MA UPC 现有版本包装 + 客供价格贴纸，出口美国 , 优先使用MA 1L 最新版本 。 2.价格贴纸位于包装正面右下角，不挡住重要信息即可，可适当调整 ，价格贴纸由跟单提供。 3.标准日期码格式，产品和包装必须有日期码 。 4.同个产品同个货期不可出现不同的包装。 5. 跟单提供ROSS通用的箱唛模版，工厂按实际45 PO上客户PO/Item号/装箱数 提供箱唛排版来确认 | Y59: Sophia Zhou | Z59: 5.8973 | AA59: =Z59*I59 -> 8845.95 | AB59: 94441-3.5 | AC59: 9283-S001 | AD59: 已入 | AG59: =I59 -> 1500 | AN59: =I59 -> 1500 | AR59: =I59 -> 1500 | AW59: =I59 -> 1500 | BF59: MA布标 | BH59: =I59/6 -> 250 | BI59: =I59/6 -> 250 | BJ59: =I59/6 -> 250 | BK59: =I59/6 -> 250 | BL59: =I59/6 -> 250 | BM59: =I59/6 -> 250 | BT59: =SUM(BH59:BS59) -> 1500 | BU59: =I59-BT59 -> 0
A60: 45621 | B60: TARGET US | C60: 美国 | D60: 4500152157 | E60: 10001106180-3890 | F60: 4500152157-10 | G60: 9283-S001 | H60: 美人鱼6只装 | I60: 3030 | J60: 0 | K60: 6 | L60: =I60/K60 -> 505 | M60: 45681 | N60: 45677 | P60: PASS | Q60: 2/12出 | R60: 12/23收到 | U60: 无 | V60: 1/3-外箱贴纸 | X60: 日期码格式：ZURU INC(BVI) 标准格式 日期：按实际生产日期 Packaging Info: MA 包装, MA 1L 收缩膜(UPC版); Remark: 1. 9283-S001-RAINBOCORNS-MERMAIDCORN SURPRISE-SERIES 7 Plush Medium,Bulk,6pcs,No Inner,STD Color Assortment 2. MA 包装, MA 1L 收缩膜(UPC版); 收缩膜上的UPC显示193052050106； Kitten:Bunny:Puppy:Cow:Elephant:Flamingo=1:1:1:1:1:1; 3.外箱正唛左上角位置粘贴条码箱贴纸，每箱只贴一张，由ZURU订购。来料贴纸上显示的客户DPCI# 086-08-6431，UPC显示10193052050103; 4.产品和包装上印刷 tracking code信息，格式为ZURU常规格式; 5.出货方式：货代自提。 | Y60: Holly Zheng | Z60: 5.701 | AA60: =Z60*I60 -> 17274.03 | AB60: 94224-2.12 | AC60: 9283-S001 | AD60: 已入 | AG60: =I60 -> 3030 | AN60: =I60 -> 3030 | AR60: =I60 -> 3030 | AW60: =I60 -> 3030 | BF60: MA布标 | BH60: =I60/6 -> 505 | BI60: =I60/6 -> 505 | BJ60: =I60/6 -> 505 | BK60: =I60/6 -> 505 | BL60: =I60/6 -> 505 | BM60: =I60/6 -> 505 | BT60: =SUM(BH60:BS60) -> 3030 | BU60: =I60-BT60 -> 0
A61: 45586 | B61: TJX COMPANIES, INC | C61: 美国 | D61: 4500147804 | E61: Marshalls DC#881-372PCS , DC#884-288PCS , DC#886-414PCS , DC#887-348PCS , DC#888-378PCS | F61: 4500147804-10 | G61: 9283-S001 | H61: 美人鱼6只装 | I61: 1800 | J61: 0 | K61: 6 | L61: =I61/K61 -> 300 | M61: 45698 | N61: 45694 | P61: PASS | Q61: 2/18出 | R61: 11/4收到 | U61: 无 | V61: 12/20-价格贴纸 | X61: 日期码格式：ZURU INC(BVI) 标准格式 日期：按实际生产日期 Packaging Info: MA UPC包装+价格贴纸，价格贴纸客供。 Remark: 1. 产品和包装上印刷tracking code信息，格式为ZURU常规格式。 2. 分5个DC出货，每款产品每个DC的箱唛资料不同。具体分DC数量，请参考后面行项目备注。 3. ZURU QC验货。 | Y61: Emily Wu | Z61: 5.8973 | AA61: =Z61*I61 -> 10615.14 | AB61: 94381-2.27 | AC61: 9283-S001 | AD61: 已入 | AG61: =I61 -> 1800 | AN61: =I61 -> 1800 | AR61: =I61 -> 1800 | AW61: =I61 -> 1800 | BF61: MA布标 | BH61: =I61/6 -> 300 | BI61: =I61/6 -> 300 | BJ61: =I61/6 -> 300 | BK61: =I61/6 -> 300 | BL61: =I61/6 -> 300 | BM61: =I61/6 -> 300 | BT61: =SUM(BH61:BS61) -> 1800 | BU61: =I61-BT61 -> 0
A62: 45586 | B62: TJX COMPANIES, INC | C62: 美国 | D62: 4500147806 | E62: TJ MAXX DC#891-354PCS , DC#894-312PCS , DC#896-288PCS , DC#897-558PCS , DC#898-288PCS | F62: 4500147806-10 | G62: 9283-S001 | H62: 美人鱼6只装 | I62: 1800 | J62: 0 | K62: 6 | L62: =I62/K62 -> 300 | M62: 45698 | N62: 45694 | P62: PASS | Q62: 2/21出 | R62: 11/4收到 | U62: 无 | V62: 12/20-价格贴纸 | X62: 日期码格式：ZURU INC(BVI) 标准格式 日期：按实际生产日期 Packaging Info: MA UPC包装+价格贴纸，价格贴纸客供。 Remark: 1. 产品和包装上印刷tracking code信息，格式为ZURU常规格式。 2. 分5个DC出货，每款产品每个DC的箱唛资料不同。具体分DC数量，请参考后面行项目备注。 3. ZURU QC验货。 | Y62: Emily Wu | Z62: 5.8973 | AA62: =Z62*I62 -> 10615.14 | AB62: 94380-2.27 | AC62: 9283-S001 | AD62: 已入 | AG62: =I61 -> 1800 | AN62: =I62 -> 1800 | AR62: =I62 -> 1800 | AW62: =I62 -> 1800 | BF62: MA布标 | BH62: =I62/6 -> 300 | BI62: =I62/6 -> 300 | BJ62: =I62/6 -> 300 | BK62: =I62/6 -> 300 | BL62: =I62/6 -> 300 | BM62: =I62/6 -> 300 | BT62: =SUM(BH62:BS62) -> 1800 | BU62: =I62-BT62 -> 0
A63: 45642 | B63: CANADIAN TIRE | C63: 加拿大 | D63: 4500154089 | E63: 9646513 | F63: 4500154089-10 | G63: 9283-S001 | H63: 美人鱼6只装 | I63: 786 | J63: 0 | K63: 6 | L63: =I63/K63 -> 131 | M63: 45702 | N63: 45698 | P63: PASS | Q63: 2/18出 | R63: 12/16收到 | U63: 12/16收到UPC贴纸 | X63: 日期码格式：ZURU INC(BVI) 标准格式 日期：按实际生产日期 Packaging Info: MA 3L EAN+UPC贴纸，UPC号码193052050106 Remark: 出加拿大 Zuru验货.日期跟踪码：产品外包装及产品本身都必须有日期跟踪码，ZURU标准格式日期码 | Y63: Summer Mo | Z63: 5.905 | AA63: =Z63*I63 -> 4641.33 | AC63: 9283-S001-1 | AD63: 已入 | AJ63: =I63 -> 786 | AN63: =I63 -> 786 | AU63: =I63 -> 786 | AW63: =I63 -> 786 | BF63: MA布标 | BH63: =I63/6 -> 131 | BI63: =I63/6 -> 131 | BJ63: =I63/6 -> 131 | BK63: =I63/6 -> 131 | BL63: =I63/6 -> 131 | BM63: =I63/6 -> 131 | BT63: =SUM(BH63:BS63) -> 786 | BU63: =I63-BT63 -> 0
A64: 45635 | B64: 4 Kidz Polska Sp. z o.o. | C64: 波兰 | D64: 4500153562 | F64: 4500153562-10 | G64: MB158-9283-S001 | H64: 混装（9283+9261+71102） | I64: 10000 | J64: 0 | K64: 2 | L64: =I64/K64 -> 5000 | M64: 45670 | N64: 45666 | P64: PASS | Q64: 2/18出 | R64: 12/10收到 | U64: 12/11-进口商贴纸 | X64: 日期码格式：ZURU INC(BVI) 标准格式 日期：按实际生产日期 Packaging Info: MB158 MA 标准PDQ 9261：MA C版3L收缩膜+进口商贴纸；MA C版布标；MA B版5L塑料袋；MA C版5L收藏指南； 9283：MA C版1L收缩膜+进口商贴纸；MA B版5L淋膜纸袋；MA C版5L改藏宝图+MA C版5L收藏指南；MA B版5L证书+塑料袋；MA B版布标 71102: MA C版收缩膜+进口商贴纸；MA B版袋；MA B版3L使用指南+信息卡 Remark: 1、若产品有比例使用ZURU STD 比例 2、所有item 均用MA UPC 条码，若包装不是UPC 条码的请告知 3、此单出欧洲需满足EU测试标准要求 | Y64: Sharon Zhao | Z64: 1.1739 | AA64: =L64*Z64 -> 5869.5 | AB64: 94223-2.12 | AC64: MB158-S001 | AD64: 已入 | AG64: =I64 -> 10000 | AN64: =I64 -> 10000 | AR64: =I64 -> 10000 | AW64: =I64 -> 10000 | BF64: MA布标 | BH64: =I64/6 -> 1666.6667 | BI64: =I64/6 -> 1666.6667 | BJ64: =I64/6 -> 1666.6667 | BK64: =I64/6 -> 1666.6667 | BL64: =I64/6 -> 1666.6667 | BM64: =I64/6 -> 1666.6667 | BT64: =SUM(BH64:BS64) -> 10000 | BU64: =I64-BT64 -> 0
A65: 45623 | B65: THE ENTERTAINER | C65: 英国 | D65: 4500152538 | E65: 4500152538-2: FB12127 | F65: 4500152538-90 | G65: 9283-S001 | H65: 美人鱼6只装 | I65: 1200 | J65: 0 | K65: 6 | L65: =I65/K65 -> 200 | M65: 45696 | N65: 45692 | P65: PASS | Q65: 2/19出 | R65: 11/28收到 | U65: 客户EAN条码贴翻4500148687 | X65: 日期码格式：ZURU INC(BVI) 标准格式 日期：按实际生产日期 Packaging Info: 9283：MA最新1L配套包装+客户EAN条码贴一张覆盖ZURU 原条码，条码贴翻订单4500148687 Kitten:Bunny:Puppy:Cow:Elephant:Flamingo=1:1:1:1:1:1; Remark: *MA版本按工厂现有最新库存即可，订单出英国，请注意检查产品及包装应带UKCA图标，包装显示ZURU UK LTD信息，QC同事请查核，如有问题与跟单确认。 *生产日期按实际（法定工作日），按ZURU标准格式即可 ，但是请知悉包装日期码需要早于或者等于外箱日期码 ，不能晚于外箱日期码 *请注意所有订单都需要经过ZURU QC验货并且通过后方可出货 *条码以订单显示为准 ，请安排生产前先核对 ，有问题请提出。 *所有产品按符合欧洲标准走货，需要是不含微塑料版本 。 *涉及到硼的，如可选择情况下应使用低硼版本 （slime 类别低硼一般低于300ppm)，无选择的应与跟单复核再安排 。 | Y65: Amy Ding | Z65: 5.8973 | AA65: =Z65*I65 -> 7076.76 | AC65: 9283-S001 | AD65: 已入 | AG65: =I65 -> 1200 | AN65: =I65 -> 1200 | AR65: =I65 -> 1200 | AW65: =I65 -> 1200 | BF65: MA布标 | BH65: =I65/6 -> 200 | BI65: =I65/6 -> 200 | BJ65: =I65/6 -> 200 | BK65: =I65/6 -> 200 | BL65: =I65/6 -> 200 | BM65: =I65/6 -> 200 | BT65: =SUM(BH65:BS65) -> 1200 | BU65: =I65-BT65 -> 0
A66: 45623 | B66: THE ENTERTAINER | C66: 英国 | D66: 4500152538 | E66: 4500152538-3: FB12155 | F66: 4500152538-180 | G66: 9283-S001 | H66: 美人鱼6只装 | I66: 996 | J66: 0 | K66: 6 | L66: =I66/K66 -> 166 | M66: 45696 | N66: 45692 | P66: PASS | Q66: 2/19出 | R66: 11/28收到 | U66: 客户EAN条码贴翻4500148687 | X66: 日期码格式：ZURU INC(BVI) 标准格式 日期：按实际生产日期 Packaging Info: 9283：MA最新1L配套包装+客户EAN条码贴一张覆盖ZURU 原条码，条码贴翻订单4500148687 Kitten:Bunny:Puppy:Cow:Elephant:Flamingo=1:1:1:1:1:1; Remark: *MA版本按工厂现有最新库存即可，订单出英国，请注意检查产品及包装应带UKCA图标，包装显示ZURU UK LTD信息，QC同事请查核，如有问题与跟单确认。 *生产日期按实际（法定工作日），按ZURU标准格式即可 ，但是请知悉包装日期码需要早于或者等于外箱日期码 ，不能晚于外箱日期码 *请注意所有订单都需要经过ZURU QC验货并且通过后方可出货 *条码以订单显示为准 ，请安排生产前先核对 ，有问题请提出。 *所有产品按符合欧洲标准走货，需要是不含微塑料版本 。 *涉及到硼的，如可选择情况下应使用低硼版本 （slime 类别低硼一般低于300ppm)，无选择的应与跟单复核再安排 。 | Y66: Amy Ding | Z66: 5.905 | AA66: =Z66*I66 -> 5881.38 | AC66: 9283-S001 | AD66: 已入 | AG66: =I66 -> 996 | AN66: =I66 -> 996 | AR66: =I66 -> 996 | AW66: =I66 -> 996 | BF66: MA布标 | BH66: =I66/6 -> 166 | BI66: =I66/6 -> 166 | BJ66: =I66/6 -> 166 | BK66: =I66/6 -> 166 | BL66: =I66/6 -> 166 | BM66: =I66/6 -> 166 | BT66: =SUM(BH66:BS66) -> 996 | BU66: =I66-BT66 -> 0
A67: 45642 | B67: BIG W | C67: 澳大利亚 | D67: 4500154142 | E67: CUS PO#47758607 - SYD | F67: 4500154142-10 | G67: 9283-S001 | H67: 美人鱼6只装 | I67: 588 | J67: 0 | K67: 6 | L67: =I67/K67 -> 98 | M67: 45702 | N67: 45698 | P67: PASS | Q67: 2/20出 | R67: 12/16收到 | U67: 进口商贴纸翻4500106537 | X67: 日期码格式：ZURU INC(BVI) 标准格式 日期：按实际生产日期 Packaging Info: 1.包装 9283：MA UPC PKG+1张进口商贴纸，贴纸翻单4500106537 2. 进口商贴纸上已经去掉日期码，产品和包装上的日期码一致，请按要求在包装上打日期码（进口商贴纸不覆盖日期码） 3. 原指定日期码DDMMYY可改用ZURU标准日期码 Remark: 1.共出4港口(SYD,BNE,MEL,FRE)， 不同港口数量信息请见订单行项目，并请参考箱唛资料，港口不同，箱唛资料也不同； 2. 箱唛不可出现任何手写内容（箱数除外），重量与实际一致且不可手写 3.此单出澳大利亚，请按澳洲标准生产并满足当地法规要求 4.出无闪粉版本，需符合欧洲微塑料法规 | Y67: Christine Liao | Z67: 5.712 | AA67: =Z67*I67 -> 3358.656 | AB67: 94321-2.22 | AC67: 9283-S001 | AD67: 已入 | AG67: =I63 -> 786 | AN67: =I67 -> 588 | AR67: =I67 -> 588 | AW67: =I67 -> 588 | BF67: MA布标 | BH67: =I67/6 -> 98 | BI67: =I67/6 -> 98 | BJ67: =I67/6 -> 98 | BK67: =I67/6 -> 98 | BL67: =I67/6 -> 98 | BM67: =I67/6 -> 98 | BT67: =SUM(BH67:BS67) -> 588 | BU67: =I67-BT67 -> 0
A68: 45642 | B68: BIG W | C68: 澳大利亚 | D68: 4500154142 | E68: CUS PO#47758608 - BNE | F68: 4500154142-50 | G68: 9283-S001 | H68: 美人鱼6只装 | I68: 396 | J68: 0 | K68: 6 | L68: =I68/K68 -> 66 | M68: 45702 | N68: 45698 | P68: PASS | Q68: 2/27出 | R68: 12/16收到 | U68: 进口商贴纸翻4500106537 | X68: 日期码格式：ZURU INC(BVI) 标准格式 日期：按实际生产日期 Packaging Info: 1.包装 9283：MA UPC PKG+1张进口商贴纸，贴纸翻单4500106537 2. 进口商贴纸上已经去掉日期码，产品和包装上的日期码一致，请按要求在包装上打日期码（进口商贴纸不覆盖日期码） 3. 原指定日期码DDMMYY可改用ZURU标准日期码 Remark: 1.共出4港口(SYD,BNE,MEL,FRE)， 不同港口数量信息请见订单行项目，并请参考箱唛资料，港口不同，箱唛资料也不同； 2. 箱唛不可出现任何手写内容（箱数除外），重量与实际一致且不可手写 3.此单出澳大利亚，请按澳洲标准生产并满足当地法规要求 4.出无闪粉版本，需符合欧洲微塑料法规 | Y68: Christine Liao | Z68: 5.712 | AA68: =Z68*I68 -> 2261.952 | AB68: 94359-2.26 | AC68: 9283-S001 | AD68: 已入 | AG68: =I67 -> 588 | AN68: =I68 -> 396 | AR68: =I68 -> 396 | AW68: =I68 -> 396 | BF68: MA布标 | BH68: =I68/6 -> 66 | BI68: =I68/6 -> 66 | BJ68: =I68/6 -> 66 | BK68: =I68/6 -> 66 | BL68: =I68/6 -> 66 | BM68: =I68/6 -> 66 | BT68: =SUM(BH68:BS68) -> 396 | BU68: =I68-BT68 -> 0
A69: 45642 | B69: BIG W | C69: 澳大利亚 | D69: 4500154142 | E69: CUS PO#47758609 - MEL | F69: 4500154142-90 | G69: 9283-S001 | H69: 美人鱼6只装 | I69: 516 | J69: 0 | K69: 6 | L69: =I69/K69 -> 86 | M69: 45702 | N69: 45698 | P69: PASS | Q69: 2/27出 | R69: 12/16收到 | U69: 进口商贴纸翻4500106537 | X69: 日期码格式：ZURU INC(BVI) 标准格式 日期：按实际生产日期 Packaging Info: 1.包装 9283：MA UPC PKG+1张进口商贴纸，贴纸翻单4500106537 2. 进口商贴纸上已经去掉日期码，产品和包装上的日期码一致，请按要求在包装上打日期码（进口商贴纸不覆盖日期码） 3. 原指定日期码DDMMYY可改用ZURU标准日期码 Remark: 1.共出4港口(SYD,BNE,MEL,FRE)， 不同港口数量信息请见订单行项目，并请参考箱唛资料，港口不同，箱唛资料也不同； 2. 箱唛不可出现任何手写内容（箱数除外），重量与实际一致且不可手写 3.此单出澳大利亚，请按澳洲标准生产并满足当地法规要求 4.出无闪粉版本，需符合欧洲微塑料法规 | Y69: Christine Liao | Z69: 5.712 | AA69: =Z69*I69 -> 2947.392 | AB69: 94370-2.27 | AC69: 9283-S001 | AD69: 已入 | AG69: =I68 -> 396 | AN69: =I69 -> 516 | AR69: =I69 -> 516 | AW69: =I69 -> 516 | BF69: MA布标 | BH69: =I69/6 -> 86 | BI69: =I69/6 -> 86 | BJ69: =I69/6 -> 86 | BK69: =I69/6 -> 86 | BL69: =I69/6 -> 86 | BM69: =I69/6 -> 86 | BT69: =SUM(BH69:BS69) -> 516 | BU69: =I69-BT69 -> 0
A70: 45643 | B70: MCD BRANDS SAS | C70: 乌拉圭 | D70: 4500153776 | F70: 4500153776-80 | G70: 9283-S001 | H70: 美人鱼6只装 | I70: 120 | J70: 0 | K70: 6 | L70: =I70/K70 -> 20 | M70: 45715 | N70: =M70-3 -> 45712 | P70: PASS | Q70: 收到SO | R70: 箱唛翻4500108308 | U70: 进口商贴纸+EAN贴纸翻4500108308 | X70: 日期码格式：ZURU INC(BVI) 标准格式 日期：按实际生产日期 Packaging Info: 9283:MA 3L包装+进口商贴纸+EAN贴纸+箱唛，进口商贴纸/EAN贴纸/箱唛翻单PO4500108308 翻单箱唛请注意ZURU LOGO需要使用最新的 Remark: 进口商贴纸请多备料5pcs,出货后需要寄给客户 | Y70: Ava Liang | Z70: 5.905 | AA70: =Z70*I70 -> 708.6 | AB70: 94577-3.18 | AC70: 9283-S001-1 | AD70: 已入 | AJ70: =I70 -> 120 | AN70: =I70 -> 120 | AU70: =I70 -> 120 | AW70: =I70 -> 120 | BF70: MA布标 | BH70: =I70/6 -> 20 | BI70: =I70/6 -> 20 | BJ70: =I70/6 -> 20 | BK70: =I70/6 -> 20 | BL70: =I70/6 -> 20 | BM70: =I70/6 -> 20 | BT70: =SUM(BH70:BS70) -> 120 | BU70: =I70-BT70 -> 0
A71: 45632 | B71: BIG W | C71: 澳大利亚 | D71: 4500153408 | E71: CUS PO#47763523 - FRE | F71: 4500153408-20 | G71: 9283-S001 | H71: 美人鱼6只装 | I71: 240 | J71: 0 | K71: 6 | L71: =I71/K71 -> 40 | M71: 45702 | N71: 45698 | P71: PASS | Q71: 2/20出 | R71: 12/16收到 | U71: 进口商贴纸翻4500106537 | X71: 日期码格式：ZURU INC(BVI) 标准格式 日期：按实际生产日期 Packaging Info: 1. 包装 9283：MA UPC PKG+1张进口商贴纸，贴纸翻单4500106537 2. 进口商贴纸上已经去掉日期码，产品和包装上的日期码一致，请按要求在包装上打日期码（进口商贴纸不覆盖日期码） 3. 原指定日期码DDMMYY可改用ZURU标准日期码 Remark: 1.共出4港口(SYD,BNE,MEL,FRE)， 不同港口数量信息请见订单行项目，并请参考箱唛资料，港口不同，箱唛资料也不同； 2. 箱唛不可出现任何手写内容（箱数除外），重量与实际一致且不可手写 3.此单出澳大利亚，请按澳洲标准生产并满足当地法规要求 4.出无闪粉版本，需符合欧洲微塑料法规 | Y71: Christine Liao | Z71: 6.2908 | AA71: =Z71*I71 -> 1509.792 | AB71: 94320-2.21 | AC71: 9283-S001 | AD71: 已入 | AG71: =I71 -> 240 | AN71: =I71 -> 240 | AR71: =I71 -> 240 | AW71: =I71 -> 240 | BF71: MA布标 | BH71: =I71/6 -> 40 | BI71: =I71/6 -> 40 | BJ71: =I71/6 -> 40 | BK71: =I71/6 -> 40 | BL71: =I71/6 -> 40 | BM71: =I71/6 -> 40 | BT71: =SUM(BH71:BS71) -> 240 | BU71: =I71-BT71 -> 0
A72: 45632 | B72: BIG W | C72: 澳大利亚 | D72: 4500153408 | E72: CUS PO#47763725 - SYD | F72: 4500153408-60 | G72: 9283-S001 | H72: 美人鱼6只装 | I72: 534 | J72: 0 | K72: 6 | L72: =I72/K72 -> 89 | M72: 45702 | N72: 45698 | P72: PASS | Q72: 2/20出 | R72: 12/16收到 | U72: 进口商贴纸翻4500106537 | X72: 日期码格式：ZURU INC(BVI) 标准格式 日期：按实际生产日期 Packaging Info: 1. 包装 9283：MA UPC PKG+1张进口商贴纸，贴纸翻单4500106537 2. 进口商贴纸上已经去掉日期码，产品和包装上的日期码一致，请按要求在包装上打日期码（进口商贴纸不覆盖日期码） 3. 原指定日期码DDMMYY可改用ZURU标准日期码 Remark: 1.共出4港口(SYD,BNE,MEL,FRE)， 不同港口数量信息请见订单行项目，并请参考箱唛资料，港口不同，箱唛资料也不同； 2. 箱唛不可出现任何手写内容（箱数除外），重量与实际一致且不可手写 3.此单出澳大利亚，请按澳洲标准生产并满足当地法规要求 4.出无闪粉版本，需符合欧洲微塑料法规 | Y72: Christine Liao | Z72: 5.712 | AA72: =Z72*I72 -> 3050.208 | AB72: 94322-2.22 | AC72: 9283-S001 | AD72: 已入 | AG72: =I72 -> 534 | AN72: =I72 -> 534 | AR72: =I72 -> 534 | AW72: =I72 -> 534 | BF72: MA布标 | BH72: =I72/6 -> 89 | BI72: =I72/6 -> 89 | BJ72: =I72/6 -> 89 | BK72: =I72/6 -> 89 | BL72: =I72/6 -> 89 | BM72: =I72/6 -> 89 | BT72: =SUM(BH72:BS72) -> 534 | BU72: =I72-BT72 -> 0
A73: 45632 | B73: BIG W | C73: 澳大利亚 | D73: 4500153408 | E73: CUS PO#47763726 - BNE | F73: 4500153408-90 | G73: 9283-S001 | H73: 美人鱼6只装 | I73: 60 | J73: 0 | K73: 6 | L73: =I73/K73 -> 10 | M73: 45702 | N73: 45698 | P73: PASS | Q73: 2/27出 | R73: 12/16收到 | U73: 进口商贴纸翻4500106537 | X73: 日期码格式：ZURU INC(BVI) 标准格式 日期：按实际生产日期 Packaging Info: 1. 包装 9283：MA UPC PKG+1张进口商贴纸，贴纸翻单4500106537 2. 进口商贴纸上已经去掉日期码，产品和包装上的日期码一致，请按要求在包装上打日期码（进口商贴纸不覆盖日期码） 3. 原指定日期码DDMMYY可改用ZURU标准日期码 Remark: 1.共出4港口(SYD,BNE,MEL,FRE)， 不同港口数量信息请见订单行项目，并请参考箱唛资料，港口不同，箱唛资料也不同； 2. 箱唛不可出现任何手写内容（箱数除外），重量与实际一致且不可手写 3.此单出澳大利亚，请按澳洲标准生产并满足当地法规要求 4.出无闪粉版本，需符合欧洲微塑料法规 | Y73: Christine Liao | Z73: 6.2908 | AA73: =Z73*I73 -> 377.448 | AB73: 94358-2.26 | AC73: 9283-S001 | AD73: 已入 | AG73: =I73 -> 60 | AN73: =I73 -> 60 | AR73: =I73 -> 60 | AW73: =I73 -> 60 | BF73: MA布标 | BH73: =I73/6 -> 10 | BI73: =I73/6 -> 10 | BJ73: =I73/6 -> 10 | BK73: =I73/6 -> 10 | BL73: =I73/6 -> 10 | BM73: =I73/6 -> 10 | BT73: =SUM(BH73:BS73) -> 60 | BU73: =I73-BT73 -> 0
A74: 45632 | B74: BIG W | C74: 澳大利亚 | D74: 4500153408 | E74: CUS PO#47763727 - MEL | F74: 4500153408-130 | G74: 9283-S001 | H74: 美人鱼6只装 | I74: 672 | J74: 0 | K74: 6 | L74: =I74/K74 -> 112 | M74: 45702 | N74: 45698 | P74: PASS | Q74: 2/27出 | R74: 12/16收到 | U74: 进口商贴纸翻4500106537 | X74: 日期码格式：ZURU INC(BVI) 标准格式 日期：按实际生产日期 Packaging Info: 1. 包装 9283：MA UPC PKG+1张进口商贴纸，贴纸翻单4500106537 2. 进口商贴纸上已经去掉日期码，产品和包装上的日期码一致，请按要求在包装上打日期码（进口商贴纸不覆盖日期码） 3. 原指定日期码DDMMYY可改用ZURU标准日期码 Remark: 1.共出4港口(SYD,BNE,MEL,FRE)， 不同港口数量信息请见订单行项目，并请参考箱唛资料，港口不同，箱唛资料也不同； 2. 箱唛不可出现任何手写内容（箱数除外），重量与实际一致且不可手写 3.此单出澳大利亚，请按澳洲标准生产并满足当地法规要求 4.出无闪粉版本，需符合欧洲微塑料法规 | Y74: Christine Liao | Z74: 6.2908 | AA74: =Z74*I74 -> 4227.4176 | AB74: 94371-2.27 | AC74: 9283-S001 | AD74: 已入 | AG74: =I74 -> 672 | AN74: =I74 -> 672 | AR74: =I74 -> 672 | AW74: =I74 -> 672 | BF74: MA布标 | BH74: =I74/6 -> 112 | BI74: =I74/6 -> 112 | BJ74: =I74/6 -> 112 | BK74: =I74/6 -> 112 | BL74: =I74/6 -> 112 | BM74: =I74/6 -> 112 | BT74: =SUM(BH74:BS74) -> 672 | BU74: =I74-BT74 -> 0
A75: 45639 | B75: ASDA STORES LTD | C75: 英国 | D75: 4500151765 | E75: 2950866117 | F75: 4500151765-70 | G75: 9283SLB-S001 | H75: 美人鱼卡板装（无闪粉） | I75: 1040 | J75: 1 | K75: 80 | L75: =I75/K75 -> 13 | M75: 45705 | N75: 45701 | P75: PASS | Q75: 2/25出 | R75: 12/25收到 | U75: 卡板贴纸 | X75: 日期码格式：ZURU INC(BVI) 标准格式 日期：按实际生产日期 Packaging Info: 7.9283SLB 9283-S002:MA 1L最新UPC包装； UPC#193052050106，请先检查条码是否正确再安排做货； Kitten:Bunny:Puppy:Cow:Elephant:Flamingo=1:1:1:1:1:1; Slip Sheet: 1 PCS/CTN, 22*4=88ctn=88pcs/slip sheet, 一共需要13套slip sheet; Slip Sheet打包好后，需要在正唛、侧唛右下角各贴一张slip sheet贴纸，直接用A4纸打印出来即可，贴纸尺寸160mm width x 140mm high； Slip Sheet尺寸限制为100*115*130CM，一旦实际SLIP SHEET尺寸超过这个尺寸，请提前通知ZURU跟单，需同客人确 认才能量产和出货 Remark: 1. 产品及包装需要印UKCA图标，包装需要有ZURU UK LTD/ZURU France地址信息，QC同事请核查，如有问题与跟单确认。 2. 产品/包装/外箱都需要打ZURU格式日期码，日期必须为法定工作日。 3. 需要符合欧洲标准不能含有闪粉和微塑料，否则不合法规会有客诉产生 | Y75: Amy Ding | Z75: 465.1502 | AA75: =Z75*L75 -> 6046.9526 | AB75: 94349-2.25 | AC75: 9283SLB-S001 | AD75: 已入 | AG75: =I75 -> 1040 | AN75: =I75 -> 1040 | AR75: =I75 -> 1040 | AW75: =I75 -> 1040 | BF75: MA布标 | BH75: =I75/6 -> 173.33333 | BI75: =I75/6 -> 173.33333 | BJ75: =I75/6 -> 173.33333 | BK75: =I75/6 -> 173.33333 | BL75: =I75/6 -> 173.33333 | BM75: =I75/6 -> 173.33333 | BT75: =SUM(BH75:BS75) -> 1040 | BU75: =I75-BT75 -> 0
A76: 45651 | B76: Zhuyu(Shenzhen)Trading Co.,Ltd. | C76: 中国 | D76: 4500154728 | E76: 5000001743 | F76: 4500154728-10 | G76: 9283-S001 | H76: 美人鱼6只装 | I76: 4800 | J76: 0 | K76: 6 | L76: =I76/K76 -> 800 | M76: 45705 | N76: 45701 | P76: PASS | Q76: 2/18出 | R76: 翻单： 4500153795 | U76: 中文3C贴纸 +中文布标(可用布标贴纸)+年龄贴纸+ 翻单： 4500153795 | V76: 1/7-芯片码（客供） | X76: 日期码格式：ZURU INC(BVI) 标准格式 日期：按实际生产日期 Packaging Info: 物料要求 SKU 所有款号务必使用带有CCC 标识的AW 1 9283 MA+中文3C贴纸 +中文收藏指南+中文布标(可用布标贴纸)+中文领养卡 +年龄贴纸+芯片码（客供） 翻单： 4500153795 Remark: 2.外箱材质如下： 1）毛重小于5kg 外箱纸质 K=B 爆破:1000Kpa 边压:4400N/M; 2）毛重大于5kg 外箱纸质 K636K 爆破:1400Kpa 边压:6300N/M; 3. 产品/销售包装/外箱日期码要一致， 4.芯片码横向平贴在上半部分蛋壳/彩盒内侧立面处，注意事项请见跟单提供文档资料。 5.此产品务必满足国内6P 测试标准，因为可能会被市场监督局抽查，如有问题产生，工厂要负全责 6. 这张订单做出厂价，我司自行安排车辆去贵司提货，贵司需要配合提供出口报关 | Y76: Tina Chen | Z76: 5.701 | AA76: =Z76*I76 -> 27364.8 | AC76: 9283-S001-6 | AD76: 已入 | AG76: =I76 -> 4800 | AO76: =I76 -> 4800 | AR76: =I76 -> 4800 | AW76: =I76 -> 4800 | BF76: MA布标 | BH76: =I76/6 -> 800 | BI76: =I76/6 -> 800 | BJ76: =I76/6 -> 800 | BK76: =I76/6 -> 800 | BL76: =I76/6 -> 800 | BM76: =I76/6 -> 800 | BT76: =SUM(BH76:BS76) -> 4800 | BU76: =I76-BT76 -> 0
A77: 45594 | B77: Distribuidora Liverpool S.A de C.V. | C77: 墨西哥 | D77: 4500149460 | E77: 61900883 | F77: 4500149460-110 | G77: 9283-S001 | H77: 美人鱼6只装 | I77: 936 | J77: 0 | K77: 6 | L77: =I77/K77 -> 156 | M77: 45708 | N77: 45703 | P77: PASS | Q77: 2/26出 | R77: 1/3收到 | U77: 2/8-UPC贴纸+进口商贴纸+价标贴纸 | V77: 2/11-价标贴纸 | X77: 日期码格式：ZURU INC(BVI) 标准格式 日期：按实际生产日期 Packaging Info: 9283:MA 3LEAN包装+UPC贴纸+进口商贴纸+价标贴纸+箱唛 Remark: 1. 此单价格贴纸（ZURU定购). 2.此单有第三方监柜，不用额外准备备品，会在大货中每款拆1pc，拆了包装的产品会由监装员用客供胶带封好或在外箱上写上""opened by telescope” | Y77: Ava Liang | Z77: 5.905 | AA77: =Z77*I77 -> 5527.08 | AB77: 94382-2.27 | AC77: 9283-S001-1 | AD77: 已入 | AJ77: =I77 -> 936 | AN77: =I77 -> 936 | AU77: =I77 -> 936 | AW77: =I77 -> 936 | BF77: MA布标 | BH77: =I77/6 -> 156 | BI77: =I77/6 -> 156 | BJ77: =I77/6 -> 156 | BK77: =I77/6 -> 156 | BL77: =I77/6 -> 156 | BM77: =I77/6 -> 156 | BT77: =SUM(BH77:BS77) -> 936 | BU77: =I77-BT77 -> 0
A78: 45611 | B78: Distribuidora Liverpool S.A de C.V. | C78: 墨西哥 | D78: 4500151307 | F78: 4500151307-60 | G78: 9283-S001 | H78: 美人鱼6只装 | I78: 42 | J78: 0 | K78: 6 | L78: =I78/K78 -> 7 | M78: 45712 | N78: 45708 | P78: PASS | Q78: 2/26出 | R78: 1/9收到 | U78: UPC贴纸+进口商贴纸翻4500149460 | V78: 2/11-价标贴纸 | X78: 日期码格式：ZURU INC(BVI) 标准格式 日期：按实际生产日期 Packaging Info: 9283:MA 3LEAN包装+UPC贴纸+进口商贴纸+价标贴纸+箱唛,UPC贴纸/进口商贴纸翻单PO4500149460 Remark: 1. 此单价格贴纸（ZURU定购). 2.此单有第三方监柜，不用额外准备备品，会在大货中每款拆1pc，拆了包装的产品会由监装员用客供胶带封好或在外箱上写上""opened by telescope” Order Modifiable | Y78: Ava Liang | Z78: 5.905 | AA78: =Z78*I78 -> 248.01 | AB78: 94352-2.25 | AC78: 9283-S001-1 | AD78: 已入 | AJ78: =I78 -> 42 | AN78: =I78 -> 42 | AU78: =I78 -> 42 | AW78: =I78 -> 42 | BF78: MA布标 | BH78: =I78/6 -> 7 | BI78: =I78/6 -> 7 | BJ78: =I78/6 -> 7 | BK78: =I78/6 -> 7 | BL78: =I78/6 -> 7 | BM78: =I78/6 -> 7 | BT78: =SUM(BH78:BS78) -> 42 | BU78: =I78-BT78 -> 0
A79: 45657 | B79: Kelly Shen/Mia Pan | C79: 美国 | D79: 4500155048 | E79: 6SGZZ69Z | F79: 4500155048-50 | G79: 9283A-S002 | H79: 小猫（邮包盒） | I79: 272 | J79: 1 | K79: 4 | L79: =I79/K79 -> 68 | M79: 45715 | N79: 45712 | P79: PASS | Q79: 收到SO | R79: 12/31收到 | U79: 无 | V79: 2/8-外箱贴纸 | W79: 邮包盒图稿跟翻单#4500135161 | X79: 日期码格式：ZURU INC(BVI) 标准格式 日期：按实际生产日期 Packaging Info: #9283: MA 1L入邮包盒，9283A邮包盒图稿跟翻单#4500135161，9283D邮包盒图稿跟返单4500139401。 Remark: 1. Amazon FOB订单，出口US。 2. 日期码使用ZURU标准版本。 3. 如果大货有要求入邮包盒，则对应的邮包盒上面要打上日期码。 4. 箱尺寸要求：外箱最长边不能超过25" （超过了，case pack只能为1），不符合要求的大货，一律不接受。 5. 外箱箱唛要求： ①外箱正面印ZURU Logo+SSCC Label（客供贴纸，由跟单订购)。关于 SSCC Label 请注意： SSCC Label 显示的是客人自己的item#。每一张SSCC label 都是唯一且有不同流水及条码的，没有损耗，绝对不可贴错 。如果贴错或损坏任何一张，都会导致全 部都错，千万要注意！ SSCC Label 必须贴在外箱正面的正中间位置（贴一面即可），并且贴纸离外箱边距必须至少3cm(可以覆盖Logo<(>&<)>箱唛)，否则会影响到客户那边仓库的扫描识 别。 ②外箱侧面印item#（订单上显示的SKU#)+carton size(以工厂实际尺寸为准,单位: inch) +MADE IN CHINA,日期使用ZURU 标准版本。 6. 装柜要求：按照客户PO# 装柜/箱号顺序装柜，跟单会提前给到装柜计划。 在大货生产/仓库存放时，请留意该装柜要求，以便装柜时不混乱（避免装错/装漏/找不到货号等）。 | Y79: Kelly Shen/Mia Pan | Z79: 6.1693 | AA79: =Z79*I79 -> 1678.0496 | AB79: 94483-3.7 | AC79: 9283A-S002 | AD79: 已入 | AG79: =I79 -> 272 | AN79: =I79 -> 272 | AR79: =I79 -> 272 | AW79: =I79 -> 272 | BF79: MA布标 | BH79: =I79 -> 272 | BT79: =SUM(BH79:BS79) -> 272 | BU79: =I79-BT79 -> 0
A80: 45678 | B80: SUPER LTD | C80: 格鲁吉亚 | D80: 4500156297 | F80: 4500156297-50 | G80: 9283-S001 | H80: 美人鱼6只装 | I80: 504 | J80: 0 | K80: 6 | L80: =I80/K80 -> 84 | M80: 45717 | N80: 45713 | P80: PASS | Q80: 3/19出 | R80: 1/22收到 | U80: 1/22-进口商贴纸 | X80: 日期码格式：ZURU INC(BVI) 标准格式 日期：按实际生产日期 Packaging Info: 9283: MA C版1L 收缩膜(含UPC条码)+进口商贴纸；MA C版5L收藏指南;MA 塑胶袋+复合袋+纸袋(MA C版5L地图+MA B版5L证书)+布标； Remark: 9283:Kitten:Bunny:Puppy:Cow:Elephant:Flamingo=1:1:1:1:1:1 | Y80: Amy Xiao | Z80: 5.7196 | AA80: =Z80*I80 -> 2882.6784 | AB80: 94566-3.17 | AC80: 9283-S001 | AD80: 已入 | AG80: =I80 -> 504 | AN80: =I80 -> 504 | AR80: =I80 -> 504 | AW80: =I80 -> 504 | BF80: MA布标 | BH80: =I80/6 -> 84 | BI80: =I80/6 -> 84 | BJ80: =I80/6 -> 84 | BK80: =I80/6 -> 84 | BL80: =I80/6 -> 84 | BM80: =I80/6 -> 84 | BT80: =SUM(BH80:BS80) -> 504 | BU80: =I80-BT80 -> 0
A81: 45665 | B81: TJX UK c/o TJX Distribution Ltd & C | C81: 德国 | D81: 4500155456 | E81: TJX EU (DE): PO#55565149 | F81: 4500155456-10 | G81: 9283-S001 | H81: 美人鱼6只装 | I81: 552 | J81: 0 | K81: 6 | L81: =I81/K81 -> 92 | M81: 45719 | N81: 45715 | P81: PASS | R81: 1/8收到 | U81: 1/13-1张贴纸（含波兰警示语） | V81: 1/10-客供价格贴纸 | X81: 日期码格式：ZURU INC(BVI) 标准格式 日期：按实际生产日期 Packaging Info: TJX EU (DE): PO#55565149(9283) 9283: MA 3L(9Lwarning) 最新EAN包装+1张客供价格贴纸+1张贴纸（含波兰警示语） Remark: 1. 出往UK的产品+包装务必打上UKCA logo ，否则客人会退货且当地会有罚款； 2. 订单必须经过ZURU QC验货并且通过后方可出货； 3. 订单每行对应客人不同的PO， 箱唛也有不同，做货的时候请分开堆放； 4. 包装条码请按包装备注上的对应的警示语语种包装，出德国的订单(订单备注为TJX Europe-DE)需要确保有英语+德语+荷兰语+波兰语警示语； 5. 订单每行对应客人不同的PO，即同款item的价格贴纸都不相同，请注意收到贴纸后不要弄混!（客人PO号请参考PO最后一栏remark）； 6. 客供价格贴纸位置为产品正面右上角，不能遮住产品信息，大货生产前，请把贴纸位置先发给跟单确认 7. 涉及到相关款式会有闪粉的或者微塑料的，请统一默认出无闪粉或者不含微塑料版本; 8. 外箱封箱必须是工字型封箱方式； | Y81: Sandy Shao | Z81: 5.7196 | AA81: =Z81*I81 -> 3157.2192 | AB81: 94473-3.6 | AC81: 9283-S001-1 | AD81: 已入 | AJ81: =I81 -> 552 | AN81: =I81 -> 552 | AU81: =I81 -> 552 | AW81: =I81 -> 552 | BF81: MA布标 | BH81: =I81/6 -> 92 | BI81: =I81/6 -> 92 | BJ81: =I81/6 -> 92 | BK81: =I81/6 -> 92 | BL81: =I81/6 -> 92 | BM81: =I81/6 -> 92 | BT81: =SUM(BH81:BS81) -> 552 | BU81: =I81-BT81 -> 0
A82: 45665 | B82: TJX UK | C82: 英国 | D82: 4500155467 | E82: TJX UK: PO#50565012 | F82: 4500155467-10 | G82: 9283-S001 | H82: 美人鱼6只装 | I82: 528 | J82: 0 | K82: 6 | L82: =I82/K82 -> 88 | M82: 45719 | N82: 45715 | P82: PASS | Q82: 3/13出 | R82: 1/8收到 | U82: 无 | V82: 1/10-客供价格贴纸 | X82: 日期码格式：ZURU INC(BVI) 标准格式 日期：按实际生产日期 Packaging Info: TJX UK: PO#50565012(9283) 9283: MA 3L(9Lwarning) 最新EAN包装+1张客供价格贴纸 Remark: 1. 出往UK的产品+包装务必打上UKCA logo ，否则客人会退货且当地会有罚款； 2. 订单必须经过ZURU QC验货并且通过后方可出货； 3. 订单每行对应客人不同的PO， 箱唛也有不同，做货的时候请分开堆放； 4. 订单每行对应客人不同的PO，即同款item的价格贴纸都不相同，请注意收到贴纸后不要弄混!（客人PO号请参考PO最后一栏remark）； 5. 价格贴纸位置为产品正面右上角，不能遮住产品信息，大货生产前，请把贴纸位置先发给跟单确认 6. 涉及到相关款式会有闪粉的或者微塑料的，请统一默认出无闪粉或者不含微塑料版本; 7. 外箱封箱必须是工字型封箱方式； | Y82: Sandy Shao | Z82: 5.905 | AA82: =Z82*I82 -> 3117.84 | AB82: 94522-3.12 | AC82: 9283-S001-1 | AD82: 已入 | AJ82: =I82 -> 528 | AN82: =I82 -> 528 | AU82: =I82 -> 528 | AW82: =I82 -> 528 | BF82: MA布标 | BH82: =I82/6 -> 88 | BI82: =I82/6 -> 88 | BJ82: =I82/6 -> 88 | BK82: =I82/6 -> 88 | BL82: =I82/6 -> 88 | BM82: =I82/6 -> 88 | BT82: =SUM(BH82:BS82) -> 528 | BU82: =I82-BT82 -> 0
A83: 45672 | B83: SUCKOT SAC | C83: 秘鲁 | D83: 4500155723 | F83: 4500155723-70 | G83: 9283-S001 | H83: 美人鱼6只装 | I83: 1800 | J83: 0 | K83: 6 | L83: =I83/K83 -> 300 | M83: 45720 | N83: 45716 | P83: PASS | Q83: 3/4出 | R83: 1/16收到 | U83: 1/16-UPC贴纸+进口商贴纸 | X83: 日期码格式：ZURU INC(BVI) 标准格式 日期：按实际生产日期 Packaging Info: 9283：MA 3L EAN包装+UPC贴纸+MA 多语收藏指南+进口商贴纸+箱唛 Remark: 9283: Kitten:Bunny:Puppy:Cow:Elephant:Flamingo=1:1:1:1:1:1; | Y83: Zoe Luo | Z83: 5.8973 | AA83: =Z83*I83 -> 10615.14 | AB83: 94426-3.4 | AC83: 9283-S001-1 | AD83: 已入 | AJ83: =I83 -> 1800 | AN83: =I83 -> 1800 | AU83: =I83 -> 1800 | AW83: =I83 -> 1800 | BF83: MA布标 | BH83: =I83/6 -> 300 | BI83: =I83/6 -> 300 | BJ83: =I83/6 -> 300 | BK83: =I83/6 -> 300 | BL83: =I83/6 -> 300 | BM83: =I83/6 -> 300 | BT83: =SUM(BH83:BS83) -> 1800 | BU83: =I83-BT83 -> 0
A84: 45651 | B84: Distribuidora Liverpool S.A de C.V. | C84: 墨西哥 | D84: 4500154604 | E84: 61900884 | F84: 4500154604-110 | G84: 9283-S001 | H84: 美人鱼6只装 | I84: 936 | J84: 0 | K84: 6 | L84: =I84/K84 -> 156 | M84: 45721 | N84: 45717 | P84: PASS | Q84: 3/14出 | R84: 2/7收到 | U84: UPC贴纸/进口商贴纸翻4500149460 | V84: 2/18-价标贴纸 | X84: 日期码格式：ZURU INC(BVI) 标准格式 日期：按实际生产日期 Packaging Info: 9283:MA 3LEAN包装+UPC贴纸+进口商贴纸+价标贴纸+箱唛，UPC贴纸/进口商贴纸翻单PO4500149460 Remark: 1. 此单价格贴纸（ZURU定购). 2.此单有第三方监柜，不用额外准备备品，会在大货中每款拆1pc，拆了包装的产品会由监装员用客供胶带封好或在外箱上写上""opened by telescope” | Y84: Ava Liang | Z84: 5.905 | AA84: =Z84*I84 -> 5527.08 | AB84: 94525-3.12 | AC84: 9283-S001-1 | AD84: 已入 | AJ84: =I84 -> 936 | AN84: =I84 -> 936 | AU84: =I84 -> 936 | AW84: =I84 -> 936 | BF84: MA布标 | BH84: =I84/6 -> 156 | BI84: =I84/6 -> 156 | BJ84: =I84/6 -> 156 | BK84: =I84/6 -> 156 | BL84: =I84/6 -> 156 | BM84: =I84/6 -> 156 | BT84: =SUM(BH84:BS84) -> 936 | BU84: =I84-BT84 -> 0
A85: 45635 | D85: ZMPO24927 | G85: 9283-S001 | H85: 美人鱼6只装 | I85: 180 | J85: 0 | K85: 6 | L85: =I85/K85 -> 30 | M85: 45649 | N85: 45645 | P85: 完成 | R85: 周转箱 | U85: 无 | X85: Remark：大货最新版本/款号平均/麻烦按款号装箱/请用大货标准箱装箱6PCS/箱共30箱/箱唛请参照邮件附件；备注： 收到样品订单后尽快安排 ，注意样板品质质量要求要高于大货品质要求 ，送货时必须要附带送货单(没有送货单和QC检验合格报告的仓库一律拒绝收货)，请知悉，谢谢！ | AB85: 94680-3.31 | AC85: 9283-S001 | AD85: 已入 | AG85: =I85 -> 180 | AN85: =I85 -> 180 | AR85: =I85 -> 180 | AW85: =I85 -> 180 | BF85: MA布标 | BH85: =I85/6 -> 30 | BI85: =I85/6 -> 30 | BJ85: =I85/6 -> 30 | BK85: =I85/6 -> 30 | BL85: =I85/6 -> 30 | BM85: =I85/6 -> 30 | BT85: =SUM(BH85:BS85) -> 180 | BU85: =I85-BT85 -> 0
A86: 45650 | B86: TARGET AUSTRALIA PTY LTD | C86: 澳大利亚 | D86: 4500154618 | E86: 2385734 | F86: 4500154618-90 | G86: 9283-S001 | H86: 美人鱼6只装 | I86: 1500 | J86: 0 | K86: 6 | L86: =I86/K86 -> 250 | M86: 45712 | N86: 45708 | P86: PASS | Q86: 2/26-2/28出 | R86: 12/24收到 | U86: 2/12-外箱贴纸 | X86: 日期码格式：ZURU INC(BVI) 标准格式 日期：按实际生产日期 Packaging Info: 8. 9283:英文MA包装(UPC版本，首选1L，无1L可用多L含英语)+箱唛+外箱贴纸；Kitten:Bunny:Puppy:Cow:Elephant:Flamingo=1:1:1:1:1:1; Remark: 1. 客人要求箱唛不可出现任何手写内容，重量与实际一致且不可手写; 2. 此单去澳大利亚，请按相应澳新标准生产; 3. 使用普通透明封箱胶封箱（若有客版封箱胶带库存可先消耗完库存） 4. 外箱需要贴Target SSCC LABEL,客供PDF文档，工厂自行订购。请贴在正唛右下角（一箱一张，贴1面正唛右下角,封箱胶纸不能挡住贴纸内容。)；外箱贴纸距离 外箱边缘应在2cm以上。如果正唛无位置可以贴在侧唛。 5. 外箱材质为ZURU标准； 6. 产品和包装上要有tracking label信息：格式为Zuru标准格式（可以自行调整具体年月日生产日期,避开节假期日）； 7. SSCC Label 尺寸更新为：4x4 inch。 8. 请务必按时完货，验货PASS后请按时送货入货代指定仓库，如果晚了导致船期Delay将会有罚金产生或者客户要求空运，所产生的罚金和空运费由工厂承担。 | Y86: Christine Liao | Z86: 6.2908 | AA86: =Z86*I86 -> 9436.2 | AB86: 94374-2.27 | AC86: 9283-S001 | AD86: 已入 | AG86: =I86 -> 1500 | AN86: =I86 -> 1500 | AR86: =I86 -> 1500 | AW86: =I86 -> 1500 | BF86: MA布标 | BH86: =I86/6 -> 250 | BI86: =I86/6 -> 250 | BJ86: =I86/6 -> 250 | BK86: =I86/6 -> 250 | BL86: =I86/6 -> 250 | BM86: =I86/6 -> 250 | BT86: =SUM(BH86:BS86) -> 1500 | BU86: =I86-BT86 -> 0
A87: 45672 | B87: Zhuyu(Shenzhen)Trading Co.,Ltd. | C87: 中国 | D87: 4500155924 | E87: 5000001770 | F87: 4500155924-20 | G87: 9283-S001 | H87: 美人鱼6只装 | I87: 1500 | J87: 0 | K87: 6 | L87: =I87/K87 -> 250 | M87: 45722 | N87: 45717 | P87: PASS | Q87: 3/7出 | R87: 翻单： 4500154728 | U87: 中文3C贴纸+中文布标(可用布标贴纸)+年龄贴纸翻4500154728 | V87: 2/8-芯片码 | X87: 日期码格式：ZURU INC(BVI) 标准格式 日期：按实际生产日期 Packaging Info: 物料要求 SKU 所有款号务必使用带有CCC 标识的AW 2 9283 MA+中文3C贴纸 +中文收藏指南+中文布标(可用布标贴纸)+中文领养卡 +年龄贴纸+芯片码 翻单： 4500154728 Remark: 2.外箱材质如下： 1）毛重小于5kg 外箱纸质 K=B 爆破:1000Kpa 边压:4400N/M; 2）毛重大于5kg 外箱纸质 K636K 爆破:1400Kpa 边压:6300N/M; 3. 产品/销售包装/外箱日期码要一致， 4.此产品务必满足国内6P 测试标准，因为可能会被市场监督局抽查，如有问题产生，工厂要负全责 5. 这张订单做出厂价，我司自行安排车辆去贵司提货，贵司需要配合提供出口报关 6.芯片码横向平贴在上半部分蛋壳/彩盒内侧立面处，注意事项请见跟单提供文档资料。 | Y87: Dona tang | Z87: 5.712 | AA87: =Z87*I87 -> 8568 | AB87: 94472-3.6 | AC87: 9283-S001-6 | AD87: 已入 | AG87: =I87 -> 1500 | AO87: =I87 -> 1500 | AR87: =I87 -> 1500 | AW87: =I87 -> 1500 | BF87: MA布标+布标贴纸 | BH87: =I87/6 -> 250 | BI87: =I87/6 -> 250 | BJ87: =I87/6 -> 250 | BK87: =I87/6 -> 250 | BL87: =I87/6 -> 250 | BM87: =I87/6 -> 250 | BT87: =SUM(BH87:BS87) -> 1500 | BU87: =I87-BT87 -> 0
A88: 45672 | B88: Zhuyu(Shenzhen)Trading Co.,Ltd. | C88: 中国 | D88: 4500155924 | E88: 5000001770 | F88: 4500155924-30 | G88: 9283-S001 | H88: 美人鱼6只装 | I88: 1200 | J88: 0 | K88: 6 | L88: =I88/K88 -> 200 | M88: 45722 | N88: 45717 | P88: PASS | Q88: 3/7出 | R88: 翻单： 4500154728 | U88: 中文3C贴纸+中文布标(可用布标贴纸)+年龄贴纸翻4500154728 | V88: 2/8-芯片码 | X88: 日期码格式：ZURU INC(BVI) 标准格式 日期：按实际生产日期 Packaging Info: 物料要求 SKU 所有款号务必使用带有CCC 标识的AW 2 9283 MA+中文3C贴纸 +中文收藏指南+中文布标(可用布标贴纸)+中文领养卡 +年龄贴纸+芯片码 翻单： 4500154728 Remark: 2.外箱材质如下： 1）毛重小于5kg 外箱纸质 K=B 爆破:1000Kpa 边压:4400N/M; 2）毛重大于5kg 外箱纸质 K636K 爆破:1400Kpa 边压:6300N/M; 3. 产品/销售包装/外箱日期码要一致， 4.此产品务必满足国内6P 测试标准，因为可能会被市场监督局抽查，如有问题产生，工厂要负全责 5. 这张订单做出厂价，我司自行安排车辆去贵司提货，贵司需要配合提供出口报关 6.芯片码横向平贴在上半部分蛋壳/彩盒内侧立面处，注意事项请见跟单提供文档资料。 | Y88: Dona tang | Z88: 5.712 | AA88: =Z88*I88 -> 6854.4 | AB88: 94472-3.6 | AC88: 9283-S001-6 | AD88: 已入 | AG88: =I88 -> 1200 | AO88: =I88 -> 1200 | AR88: =I88 -> 1200 | AW88: =I88 -> 1200 | BF88: MA布标+布标贴纸 | BH88: =I88/6 -> 200 | BI88: =I88/6 -> 200 | BJ88: =I88/6 -> 200 | BK88: =I88/6 -> 200 | BL88: =I88/6 -> 200 | BM88: =I88/6 -> 200 | BT88: =SUM(BH88:BS88) -> 1200 | BU88: =I88-BT88 -> 0
A89: 45680 | B89: Zhuyu(Shenzhen)Trading Co.,Ltd. | C89: 中国 | D89: 4500155924 | E89: 5000001770 | F89: 4500155924-50 | G89: 9283-S001 | H89: 美人鱼6只装 | I89: 1200 | J89: 0 | K89: 6 | L89: =I89/K89 -> 200 | M89: 45722 | N89: 45717 | P89: PASS | Q89: 3/7出 | R89: 翻单： 4500154728 | U89: 中文3C贴纸+中文布标(可用布标贴纸)+年龄贴纸翻4500154728 | V89: 2/8-芯片码 | X89: 日期码格式：ZURU INC(BVI) 标准格式 日期：按实际生产日期 Packaging Info: 物料要求 SKU 所有款号务必使用带有CCC 标识的AW 2 9283 MA+中文3C贴纸 +中文收藏指南+中文布标(可用布标贴纸)+中文领养卡 +年龄贴纸+芯片码 翻单： 4500154728 Remark: 2.外箱材质如下： 1）毛重小于5kg 外箱纸质 K=B 爆破:1000Kpa 边压:4400N/M; 2）毛重大于5kg 外箱纸质 K636K 爆破:1400Kpa 边压:6300N/M; 3. 产品/销售包装/外箱日期码要一致， 4.此产品务必满足国内6P 测试标准，因为可能会被市场监督局抽查，如有问题产生，工厂要负全责 5. 这张订单做出厂价，我司自行安排车辆去贵司提货，贵司需要配合提供出口报关 6.芯片码横向平贴在上半部分蛋壳/彩盒内侧立面处，注意事项请见跟单提供文档资料。 | Y89: Dona tang | Z89: 5.701 | AA89: =Z89*I89 -> 6841.2 | AB89: 94472-3.6 | AC89: 9283-S001-6 | AD89: 已入 | AG89: =I89 -> 1200 | AO89: =I89 -> 1200 | AR89: =I89 -> 1200 | AW89: =I89 -> 1200 | BF89: MA布标+布标贴纸 | BH89: =I89/6 -> 200 | BI89: =I89/6 -> 200 | BJ89: =I89/6 -> 200 | BK89: =I89/6 -> 200 | BL89: =I89/6 -> 200 | BM89: =I89/6 -> 200 | BT89: =SUM(BH89:BS89) -> 1200 | BU89: =I89-BT89 -> 0
A90: 45636 | B90: THE WAREHOUSE LIMITED | C90: 新西兰 | D90: 4500153598 | E90: 287909 | F90: 4500153598-10 | G90: 9283-S001 | H90: 美人鱼6只装 | I90: 372 | J90: 0 | K90: 6 | L90: =I90/K90 -> 62 | M90: 45726 | N90: 45722 | P90: PASS | Q90: 3/20出 | R90: 12/10收到 | U90: 无 | X90: 日期码格式：ZURU INC(BVI) 标准格式 日期：按实际生产日期 Packaging Info: MA UPC 英语包装（优先1L英语版本，或者3L/5L含英语都可） 此客人不接受易掉落或者剥落或者可直接触碰的闪粉，可降解也不行，但可以接受符合欧洲微塑料标准的珠光粉或者闪片。 Remark: 9283: Kitten:Bunny:Puppy:Cow:Elephant:Flamingo=1:1:1:1:1:1; | Y90: Abby Liang | Z90: 5.7196 | AA90: =Z90*I90 -> 2127.6912 | AB90: 94793-4.18 | AC90: 9283-S001 | AD90: 已入 | AG90: =I62 -> 1800 | AN90: =I90 -> 372 | AR90: =I90 -> 372 | AW90: =I90 -> 372 | BF90: MA布标 | BH90: =I90/6 -> 62 | BI90: =I90/6 -> 62 | BJ90: =I90/6 -> 62 | BK90: =I90/6 -> 62 | BL90: =I90/6 -> 62 | BM90: =I90/6 -> 62 | BT90: =SUM(BH90:BS90) -> 372 | BU90: =I90-BT90 -> 0
A91: 45636 | B91: THE WAREHOUSE LIMITED | C91: 新西兰 | D91: 4500153593 | E91: 28797907 | F91: 4500153593-10 | G91: 9283-S001 | H91: 美人鱼6只装 | I91: 1128 | J91: 0 | K91: 6 | L91: =I91/K91 -> 188 | M91: 45726 | N91: 45722 | P91: PASS | Q91: 3/20出 | R91: 12/10收到 | U91: 无 | X91: 日期码格式：ZURU INC(BVI) 标准格式 日期：按实际生产日期 Packaging Info: MA UPC 英语包装（优先1L英语版本，或者3L/5L含英语都可） 此客人不接受易掉落或者剥落或者可直接触碰的闪粉，可降解也不行，但可以接受符合欧洲微塑料标准的珠光粉或者闪片。 Remark: 9283: Kitten:Bunny:Puppy:Cow:Elephant:Flamingo=1:1:1:1:1:1; | Y91: Abby Liang | Z91: 5.712 | AA91: =Z91*I91 -> 6443.136 | AB91: 94792-4.18 | AC91: 9283-S001 | AD91: 已入 | AG91: =I90 -> 372 | AN91: =I91 -> 1128 | AR91: =I91 -> 1128 | AW91: =I91 -> 1128 | BF91: MA布标 | BH91: =I91/6 -> 188 | BI91: =I91/6 -> 188 | BJ91: =I91/6 -> 188 | BK91: =I91/6 -> 188 | BL91: =I91/6 -> 188 | BM91: =I91/6 -> 188 | BT91: =SUM(BH91:BS91) -> 1128 | BU91: =I91-BT91 -> 0
A92: 45678 | B92: DISTRIBUIDORA JUGUETRON S.A. DE C.V | C92: 墨西哥 | D92: 4500156374 | F92: 4500156374-50 | G92: 9283-S001 | H92: 美人鱼6只装 | I92: 720 | J92: 0 | K92: 6 | L92: =I92/K92 -> 120 | M92: 45726 | N92: 45722 | P92: PASS | Q92: 3/11出 | R92: 1/21收到 | U92: 2/24-UPC贴纸+外箱贴纸+进口商贴纸 | X92: 日期码格式：ZURU INC(BVI) 标准格式 日期：按实际生产日期 Packaging Info: 9283:MA 3L EAN包装+UPC贴纸+外箱贴纸+进口商贴纸+箱唛 Remark: 此单有第三方监柜，需要每款多备1套完整物料 | Y92: Ava Liang | Z92: 5.905 | AA92: =Z92*I92 -> 4251.6 | AB92: 94515-3.11 | AC92: 9283-S001-1 | AD92: 已入 | AJ92: =I92 -> 720 | AN92: =I92 -> 720 | AU92: =I92 -> 720 | AW92: =I92 -> 720 | BF92: MA布标 | BH92: =I92/6 -> 120 | BI92: =I92/6 -> 120 | BJ92: =I92/6 -> 120 | BK92: =I92/6 -> 120 | BL92: =I92/6 -> 120 | BM92: =I92/6 -> 120 | BT92: =SUM(BH92:BS92) -> 720 | BU92: =I92-BT92 -> 0
A93: 45700 | B93: Zhuyu(Shenzhen)Trading Co.,Ltd. | C93: 中国 | D93: 4500157394 | E93: 5000001791 | F93: 4500157394-10 | G93: 9283-S001 | H93: 美人鱼6只装 | I93: 2400 | J93: 0 | K93: 6 | L93: =I93/K93 -> 400 | M93: 45728 | N93: 45724 | P93: PASS | Q93: 3/13出 | R93: 翻单： 4500154728 | U93: 中文3C贴纸+中文布标(可用布标贴纸)+年龄贴纸 翻4500154728 | V93: 2/26芯片贴纸 | X93: 日期码格式：ZURU INC(BVI) 标准格式 日期：按实际生产日期 Packaging Info: 物料要求 SKU 所有款号务必使用带有CCC 标识的AW 1.9283 MA+中文3C贴纸 +中文收藏指南+中文布标(可用布标贴纸)+中文领养卡 +年龄贴纸+芯片码（客供） 翻单： 4500154728 此单为 首单 需要提供3箱大货样 留样 Remark: 2.外箱材质如下： 1）毛重小于5kg 外箱纸质 K=B 爆破:1000Kpa 边压:4400N/M; 2）毛重大于5kg 外箱纸质 K636K 爆破:1400Kpa 边压:6300N/M; 3. 产品/销售包装/外箱日期码要一致， 4.此产品务必满足国内6P 测试标准，因为可能会被市场监督局抽查，如有问题产生，工厂要负全责 5. 这张订单做出厂价，我司自行安排车辆去贵司提货，贵司需要配合提供出口报关 6.芯片码横向平贴在上半部分蛋壳/彩盒内侧立面处，注意事项请见跟单提供文档资料。 | Y93: Dona tang | Z93: 5.6846 | AA93: =Z93*I93 -> 13643.04 | AB93: 94537-3.13 | AC93: 9283-S001-6 | AD93: 已入 | AG93: =I93 -> 2400 | AO93: =I93 -> 2400 | AR93: =I93 -> 2400 | AW93: =I93 -> 2400 | BF93: MA布标+布标贴纸 | BH93: =I93/6 -> 400 | BI93: =I93/6 -> 400 | BJ93: =I93/6 -> 400 | BK93: =I93/6 -> 400 | BL93: =I93/6 -> 400 | BM93: =I93/6 -> 400 | BT93: =SUM(BH93:BS93) -> 2400 | BU93: =I93-BT93 -> 0
A94: 45700 | B94: Zhuyu(Shenzhen)Trading Co.,Ltd. | C94: 中国 | D94: 4500157394 | E94: 5000001791 | F94: 4500157394-20 | G94: 9283-S001 | H94: 美人鱼6只装 | I94: 3600 | J94: 0 | K94: 6 | L94: =I94/K94 -> 600 | M94: 45728 | N94: 45724 | P94: PASS | Q94: 3/13出 | R94: 翻单： 4500154728 | U94: 中文3C贴纸+中文布标(可用布标贴纸)+年龄贴纸 翻4500154728 | V94: 2/26芯片贴纸 | X94: 日期码格式：ZURU INC(BVI) 标准格式 日期：按实际生产日期 Packaging Info: 物料要求 SKU 所有款号务必使用带有CCC 标识的AW 1.9283 MA+中文3C贴纸 +中文收藏指南+中文布标(可用布标贴纸)+中文领养卡 +年龄贴纸+芯片码（客供） 翻单： 4500154728 此单为 首单 需要提供3箱大货样 留样 Remark: 2.外箱材质如下： 1）毛重小于5kg 外箱纸质 K=B 爆破:1000Kpa 边压:4400N/M; 2）毛重大于5kg 外箱纸质 K636K 爆破:1400Kpa 边压:6300N/M; 3. 产品/销售包装/外箱日期码要一致， 4.此产品务必满足国内6P 测试标准，因为可能会被市场监督局抽查，如有问题产生，工厂要负全责 5. 这张订单做出厂价，我司自行安排车辆去贵司提货，贵司需要配合提供出口报关 6.芯片码横向平贴在上半部分蛋壳/彩盒内侧立面处，注意事项请见跟单提供文档资料。 | Y94: Dona tang | Z94: 5.6846 | AA94: =Z94*I94 -> 20464.56 | AB94: 94537-3.13 | AC94: 9283-S001-6 | AD94: 已入 | AG94: =I94 -> 3600 | AO94: =I94 -> 3600 | AR94: =I94 -> 3600 | AW94: =I94 -> 3600 | BF94: MA布标+布标贴纸 | BH94: =I94/6 -> 600 | BI94: =I94/6 -> 600 | BJ94: =I94/6 -> 600 | BK94: =I94/6 -> 600 | BL94: =I94/6 -> 600 | BM94: =I94/6 -> 600 | BT94: =SUM(BH94:BS94) -> 3600 | BU94: =I94-BT94 -> 0
A95: 45677 | B95: KMART AUSTRALIA LTD | C95: 澳大利亚 | D95: 4500156224 | E95: 20611030 | F95: 4500156224-30 | G95: 9283-S001 | H95: 美人鱼6只装 | I95: 1500 | J95: 0 | K95: 6 | L95: =I95/K95 -> 250 | M95: 45730 | N95: 45726 | P95: PASS | Q95: 3/12-3/14出 | R95: 1/20收到 | U95: 2/10-防盗贴纸+2/17-外箱贴纸 | X95: 日期码格式：ZURU INC(BVI) 标准格式 日期：按实际生产日期 Packaging Info: 9283: MA英语UPC版本包装（收缩膜和说明书, MA首选1L，如无1L可用多语且含英语的配套多语包装) + 1张防盗贴纸 (贴纸以及位置图翻单PO#4500095104）+ 箱唛 + 外箱SSCC Label Remark: 1.请务必按时完货，验货。并且按期送货入货代指定仓库，如果晚了导致船期Delay将会有罚金产生或者客户要求空运，所产生的罚金和空运费由工厂承担。 2.SSCC 外箱贴纸请同纸箱瓦楞纸方向（竖纹向）垂直，即外箱贴纸横着贴(注意条码不要被胶带粘住），贴1pc，贴1面正唛，封箱胶纸不能挡住贴纸内容。外箱贴纸 离外箱边距离不少于2cm。 3.外箱材质为ZURU标准； 4.此单需使用KMART封箱胶上下工字型封箱;从2019年6月开始，要用KMART 新版封箱胶带，此单要用"ANKO"封箱胶带 5.此单出口澳大利亚，请按相应的澳新标准生产； 6.产品和包装上生产批号的显示格式ZURU标准日期码格式 7.外箱信息不可手写，重量和体积需要与实际的一致(不可手写） 8. 每款item装箱后的G.W.超过10KG或者CBM超过0.13,(9.5KG或者以上，四舍五入后也属于10KG) 需在外箱上加印超 重或者Bulky LOGO，若发现我们资料没有，请 帮忙提醒 1)重量超过10kg但不超过16kg且CBM不超过0.13,10-16kg 超重logo 2）CBM超过0.13且重量少于17kg，bulky logo 3）不属于以上两种情况，需要使用相应重量范围内的超重logo 4）超重logo需要在外箱四面都印刷(箱唛右上角，两面侧唛超重logo需要尽量靠近毛重)，尺寸为:110mm height* 95mm width 9. 实际外箱重量跟印在箱唛上的数据差异不能超3%，尺寸按实际数据印刷 | Y95: Lydia Wu | Z95: 6.2908 | AA95: =Z95*I95 -> 9436.2 | AB95: 94538-3.13 | AC95: 9283-S001 | AD95: 已入 | AG95: =I95 -> 1500 | AN95: =I95 -> 1500 | AR95: =I95 -> 1500 | AW95: =I95 -> 1500 | BF95: MA布标 | BH95: =I95/6 -> 250 | BI95: =I95/6 -> 250 | BJ95: =I95/6 -> 250 | BK95: =I95/6 -> 250 | BL95: =I95/6 -> 250 | BM95: =I95/6 -> 250 | BT95: =SUM(BH95:BS95) -> 1500 | BU95: =I95-BT95 -> 0
A96: 45677 | B96: Bol.com | C96: 新西兰 | D96: 4500156115 | E96: 7631985 | F96: 4500156115-30 | G96: 9283B-S003 | H96: 兔子 | I96: 252 | J96: 0 | K96: 4 | L96: =I96/K96 -> 63 | M96: 45730 | N96: 45726 | P96: PASS | Q96: 3/17出 | R96: 1/20收到 | U96: EAN贴纸翻4500109185 | X96: 日期码格式：ZURU INC(BVI) 标准格式 日期：按实际生产日期 Tracking Code: Packaging Info: BOL NL(9283ABDE) 8. 9283ABDE ---9283B: 4 pcs/ctn,No Inner,Medium Bunny,Bubble water;NO Boron; One plastic horn filled in water mixture; A pack of sand(60g); MA 3L(9L warning EAN)C 收缩膜+1张EAN#贴纸(参考翻单PO#4500109185<(>,<)>贴在收缩膜原EAN位置)+MA 3L B try me sticker+MA B Laser sticker+MA B布标+MA 5L(9L warning) C 收藏指南+MA 5L B证书+MA 5L(23L warning)B 配件袋(sand bag)+MA 5L B 配件袋+MA 5L B 泡泡水胶袋； 13. 验货时间不迟于2025/3/17. Remark: 1. 出欧洲产品不可含闪粉或者微塑料，若所涉产品无闪粉或不含微塑料可忽略此点； 2. 5 Surprise or Mini Brands涉及包装是2个及2个以上的球入PVC桶包装时，单个球上若有UPC#或者EAN#，请用白色贴纸覆盖住； 3. 箱唛资料按照提供的要求去做即可，无需再发回我方确认； 4.柜货产品务必拉网且要拉紧，拉网要求： A: 网要结实同时网格要细，纸箱不能从网格处跌落下来 B: 打网固定8-10个点。请提供拉网的装柜照片给船务确认 后柜子再离厂。" | Y96: Crystal Chen | Z96: 5.6717 | AA96: =Z96*I96 -> 1429.2684 | AB96: 94548-3.14 | AC96: 9283B-S003 | AD96: 已入 | AJ96: =I96 -> 252 | AN96: =I96 -> 252 | AU96: =I96 -> 252 | AW96: =I96 -> 252 | BF96: MA布标 | BI96: =I96 -> 252 | BT96: =SUM(BH96:BS96) -> 252 | BU96: =I96-BT96 -> 0
A97: 45677 | B97: Bol.com | C97: 新西兰 | D97: 4500156115 | E97: 7631985 | F97: 4500156115-190 | G97: 9283A-S003 | H97: 小猫 | I97: 252 | J97: 0 | K97: 4 | L97: =I97/K97 -> 63 | M97: 45730 | N97: 45726 | P97: PASS | Q97: 3/17出 | R97: 1/20收到 | U97: EAN贴纸翻4500109185 | X97: 日期码格式：ZURU INC(BVI) 标准格式 日期：按实际生产日期 Tracking Code: Packaging Info: BOL NL(9283ABDE) 8. 9283ABDE ---9283A: 4 pcs/ctn,No Inner,Medium Kitten,Bubble water;NO Boron; One plastic horn filled in water mixture; A pack of sand(60g); MA 3L(9L warnin g EAN)C 收缩膜+1张EAN#贴纸(参考翻单PO#4500109185<(>,<)>贴在收缩膜原EAN位置)+MA 3L B try me sticker+MA B Laser sticker+MA B布标+MA 5L(9L warning) C 收藏指南+MA 5L B证书+MA 5L(23L warning)B 配件袋(sand bag)+MA 5L B 配件袋+MA 5L B 泡泡水胶袋； 13. 验货时间不迟于2025/3/17. Remark: 1. 出欧洲产品不可含闪粉或者微塑料，若所涉产品无闪粉或不含微塑料可忽略此点； 2. 5 Surprise or Mini Brands涉及包装是2个及2个以上的球入PVC桶包装时，单个球上若有UPC#或者EAN#，请用白色贴纸覆盖住； 3. 箱唛资料按照提供的要求去做即可，无需再发回我方确认； 4.柜货产品务必拉网且要拉紧，拉网要求： A: 网要结实同时网格要细，纸箱不能从网格处跌落下来 B: 打网固定8-10个点。请提供拉网的装柜照片给船务确认 后柜子再离厂。" | Y97: Crystal Chen | Z97: 5.6717 | AA97: =Z97*I97 -> 1429.2684 | AB97: 94548-3.14 | AC97: 9283A-S003 | AD97: 已入 | AJ97: =I97 -> 252 | AN97: =I97 -> 252 | AU97: =I97 -> 252 | AW97: =I97 -> 252 | BF97: MA布标 | BH97: =I97 -> 252 | BT97: =SUM(BH97:BS97) -> 252 | BU97: =I97-BT97 -> 0
A98: 45677 | B98: Bol.com | C98: 新西兰 | D98: 4500156115 | E98: 7631985 | F98: 4500156115-260 | G98: 9283E-S003 | H98: 奶牛 | I98: 252 | J98: 0 | K98: 4 | L98: =I98/K98 -> 63 | M98: 45730 | N98: 45726 | P98: PASS | Q98: 3/17出 | R98: 1/20收到 | U98: EAN贴纸翻4500109185 | X98: 日期码格式：ZURU INC(BVI) 标准格式 日期：按实际生产日期 Tracking Code: Packaging Info: BOL NL(9283ABDE) 8. 9283ABDE ---9283E: 4 pcs/ctn,No Inner,Medium Cow,Bubble water;NO Boron; One plastic horn filled in water mixture; A pack of sand(60g); MA 3L(9L warning E AN)C 收缩膜+1张EAN#贴纸(参考翻单PO#4500109185<(>,<)>贴在收缩膜原EAN位置)+MA 3L B try me sticker+MA B Laser sticker+MA B布标+MA 5L(9L warning)C 收藏指南+MA 5L B证书+MA 5L(23L warning)B 配件袋(sand bag)+MA 5L B 配件袋+MA 5L B 泡泡水胶袋； 13. 验货时间不迟于2025/3/17. Remark: 1. 出欧洲产品不可含闪粉或者微塑料，若所涉产品无闪粉或不含微塑料可忽略此点； 2. 5 Surprise or Mini Brands涉及包装是2个及2个以上的球入PVC桶包装时，单个球上若有UPC#或者EAN#，请用白色贴纸覆盖住； 3. 箱唛资料按照提供的要求去做即可，无需再发回我方确认； 4.柜货产品务必拉网且要拉紧，拉网要求： A: 网要结实同时网格要细，纸箱不能从网格处跌落下来 B: 打网固定8-10个点。请提供拉网的装柜照片给船务确认 后柜子再离厂。" | Y98: Crystal Chen | Z98: 5.6717 | AA98: =Z98*I98 -> 1429.2684 | AB98: 94548-3.14 | AC98: 9283E-S003 | AD98: 已入 | AJ98: =I98 -> 252 | AN98: =I98 -> 252 | AU98: =I98 -> 252 | AW98: =I98 -> 252 | BF98: MA布标 | BK98: =I98 -> 252 | BT98: =SUM(BH98:BS98) -> 252 | BU98: =I98-BT98 -> 0
A99: 45677 | B99: Bol.com | C99: 新西兰 | D99: 4500156115 | E99: 7631985 | F99: 4500156115-280 | G99: 9283D-S003 | H99: 小狗 | I99: 252 | J99: 0 | K99: 4 | L99: =I99/K99 -> 63 | M99: 45730 | N99: 45726 | P99: PASS | Q99: 3/17出 | R99: 1/20收到 | U99: EAN贴纸翻4500109185 | X99: 日期码格式：ZURU INC(BVI) 标准格式 日期：按实际生产日期 Tracking Code: Packaging Info: BOL NL(9283ABDE) 8. 9283ABDE ---9283D: 4 pcs/ctn,No Inner,Medium Puppy,Bubble water;NO Boron; One plastic horn filled in water mixture; A pack of sand(60g); MA 3L(9L warning EAN)C 收缩膜+1张EAN#贴纸(参考翻单PO#4500109185<(>,<)>贴在收缩膜原EAN位置)+MA 3L B try me sticker+MA B Laser sticker+MA B布标+MA 5L(9L warning) C 收藏指南+MA 5L B证书+MA 5L(23L warning)B 配件袋(sand bag)+MA 5L B 配件袋+MA 5L B 泡泡水胶袋； 13. 验货时间不迟于2025/3/17. Remark: 1. 出欧洲产品不可含闪粉或者微塑料，若所涉产品无闪粉或不含微塑料可忽略此点； 2. 5 Surprise or Mini Brands涉及包装是2个及2个以上的球入PVC桶包装时，单个球上若有UPC#或者EAN#，请用白色贴纸覆盖住； 3. 箱唛资料按照提供的要求去做即可，无需再发回我方确认； 4.柜货产品务必拉网且要拉紧，拉网要求： A: 网要结实同时网格要细，纸箱不能从网格处跌落下来 B: 打网固定8-10个点。请提供拉网的装柜照片给船务确认 后柜子再离厂。" | Y99: Crystal Chen | Z99: 5.6717 | AA99: =Z99*I99 -> 1429.2684 | AB99: 94548-3.14 | AC99: 9283D-S003 | AD99: 已入 | AJ99: =I99 -> 252 | AN99: =I99 -> 252 | AU99: =I99 -> 252 | AW99: =I99 -> 252 | BF99: MA布标 | BJ99: =I99 -> 252 | BT99: =SUM(BH99:BS99) -> 252 | BU99: =I99-BT99 -> 0
A100: 45696 | B100: PPTOYS PTE LTD (SG) | C100: 新加坡 | D100: 4500157001 | E100: ZU25012001SG | F100: 4500157001-20 | G100: 9283-S001 | H100: 美人鱼6只装 | I100: 600 | J100: 0 | K100: 6 | L100: =I100/K100 -> 100 | M100: 45730 | N100: 45726 | P100: PASS | Q100: 3/15出 | R100: 2/8收到 | U100: 进口商贴纸翻4500122433 | X100: 日期码格式：ZURU INC(BVI) 标准格式 日期：按实际生产日期 Packaging Info: MA UPC包装（优先1L)+1张进口商贴纸,贴纸图稿及位置图翻单如下 71126-4500135387 9283-4500122433 所有item贴纸都是一样的（尺寸有很小差别并不影响），请一起订购节省成本 Remark: 9283-Kitten:Bunny:Puppy:Cow:Elephant:Flamingo=1:1:1:1:1:1; | Y100: Emma Wu | Z100: 5.7196 | AA100: =Z100*I100 -> 3431.76 | AB100: 94575-3.18 | AC100: 9283-S001 | AD100: 已入 | AG100: =I100 -> 600 | AN100: =I100 -> 600 | AR100: =I100 -> 600 | AW100: =I100 -> 600 | BF100: MA布标 | BH100: =I100/6 -> 100 | BI100: =I100/6 -> 100 | BJ100: =I100/6 -> 100 | BK100: =I100/6 -> 100 | BL100: =I100/6 -> 100 | BM100: =I100/6 -> 100 | BT100: =SUM(BH100:BS100) -> 600 | BU100: =I100-BT100 -> 0
...

Sheet MA包裝
A1: #9283美人鱼系列MA 包装扣数表
A2: 日期 | B2: MA PO | C2: 負責 | D2: MA收缩膜
D3: MA 1语收缩膜 | E3: MA 1语收缩膜 | F3: MA 1语收缩膜 | G3: MA 3语收缩膜 | H3: MA 3语收缩膜 | I3: MA 3语收缩膜 | J3: 5语收藏指南 | K3: 5语收藏指南 | L3: 5语收藏指南 | M3: 客版收缩膜 | N3: 客版收藏指南 | O3: 藏宝图 | P3: 藏宝图 | Q3: 领养卡 | R3: MEC展示架-1L | S3: EC展示架-1L | T3: 9283SLT-托盘
D4: A版本 | E4: B版本 | F4: C版本-无闪粉 | G4: A版本 | H4: B版本 | I4: C版本-无闪粉 | J4: A版本 | K4: B版本 | L4: C版本-无闪粉 | O4: B版本 | P4: C版本-无闪粉
A5: 44931 | B5: 1000012986 | C5: Amy | D5: 150000
A6: 44931 | B6: 1000012987 | C6: Amy | G6: 30000
A7: 44931 | B7: 1000012988 | C7: Amy | J7: 150000 | O7: 50000 | Q7: 50000
A8: 45001 | B8: 1000013497 | C8: Mona | M8: 30000 | U8: @Emma Chen 4500092956-9804pcs 4500116561-2100pcs 4500122428-3000pcs 4500123591-3600pcs 4500128665-3000PCS 4500129356-1002pcs 4500136786-2100pcs | V8: =M8-9804-2100-3000-3600-3000-1002-2100 -> 5394
A9: 45020 | B9: 1000013757 | C9: Mona | M9: 30000 | U9: 4500097084-15000pcs 4500101379-10002pcs 4500137318-2580pcs | V9: =M9-15000-10002-2580 -> 2418
A10: 2023/4/11 | B10: 1000013809 | C10: Charine Chen | M10: 39984 | U10: Smyths客使用 Linda 4500094401 | V10: 翻单 4500094401扣数
A11: 45037 | B11: 1000014019 | R11: 4000 | U11: Effy用于4500100631 4500100632 4500100633 4500100635（543座 剩3457座）1L
A12: 45039 | B12: 1000014039 | C12: Amy | D12: 100000
A13: 45039 | B13: 1000014040 | C13: Amy | G13: 30000
A14: 45039 | B14: 1000014041 | C14: Amy | J14: 150000
A15: 45043 | B15: 1000014119 | C15: Amy | O15: 250000
A16: 45043 | B16: 1000014120 | C16: Amy | Q16: 250000
A17: 45043 | B17: 1000014121 | C17: Amy | S17: 300
A18: 45056 | B18: 1000014350 | C18: Amy | D18: 100000
A19: 45056 | B19: 1000014351 | C19: Amy | J19: 150000
A20: 45056 | B20: 1000014352 | C20: Amy | O20: 150000
A21: 45056 | B21: 1000014353 | C21: Amy | Q21: 150000
A22: 45068 | B22: 1000014511 | C22: Daisy.Li | T22: =197 -> 197 | U22: Willow用于订单 4500104331
A23: 45090 | B23: 1000014795 | C23: Charine Chen | M23: 20000 | U23: 4500105312 4500100289 4500100344 | V23: 翻单 4500094401扣数
A24: 45091 | B24: 1000014896 | C24: Amy | D24: 70000
A25: 45091 | B25: 1000014897 | C25: Amy | G25: 60000
A26: 45091 | B26: 1000014898 | C26: Amy | J26: 140000
A27: 45091 | B27: 1000014899 | C27: Amy | O27: 140000
A28: 45091 | B28: 100014900 | C28: Amy | Q28: 140000
A29: 45107 | B29: 1000015170 | C29: Amy | D29: 120000
A30: 45107 | B30: 1000015171 | C30: Amy | J30: 130000
A31: 45107 | B31: 1000015174 | C31: Amy | O31: 140000
A32: 45107 | B32: 1000015176 | C32: Amy | Q32: 140000
A33: 45125 | B33: 1000015477 | C33: Daisy.Li | M33: 30000 | U33: Linda Smyths EU:4500108836 334PCS Sherry Smyths 4500108866 2406pcs | V33: 翻单 4500094401扣数
A34: 45127 | B34: 1000015544 | C34: Amy | D34: 100000
A35: 45127 | B35: 1000015545 | C35: Amy | K35: 100000
A36: 45127 | B36: 1000015546 | C36: Amy | O36: 100000
A37: 45127 | B37: 1000015547 | C37: Amy | Q37: 100000
A38: 45166 | B38: 1000016178 | C38: Amy | E38: 150000
A39: 45166 | B39: 1000016179 | C39: Amy | G39: 30000
A40: 45166 | B40: 1000016180 | C40: Amy | K40: 200000
A41: 45166 | B41: 1000016181 | C41: Amy | O41: 200000
A42: 45166 | B42: 1000016182 | C42: Amy | Q42: 200000
A43: 45215 | B43: 1000016767 | C43: Amy | E43: 150000
A44: 45215 | B44: 1000016768 | C44: Amy | K44: 150000
A45: 45215 | B45: 1000016769 | C45: Amy | O45: 180000
A46: 45215 | B46: 1000016770 | C46: Amy | Q46: 180000
A47: 45240 | B47: 1000017244 | C47: Amy | E47: 100000
A48: 45240 | B48: 1000017245 | C48: Amy | H48: 30000
A49: 45240 | B49: 1000017246 | C49: Amy | O49: 100000
A50: 45240 | B50: 1000017247 | C50: Amy | Q50: 100000
A51: 45240 | B51: 1000017248 | C51: Amy | K51: 100000
A52: 45253 | B52: 1000017425 | C52: Amy | F52: 30000
A53: 45253 | B53: 1000017426 | C53: Amy | I53: 20000
A54: 45253 | B54: 1000017427 | C54: Amy | L54: 50000
A55: 45253 | B55: 1000017428 | C55: Amy | P55: 50000
A56: 45258 | B56: 1000017514 | C56: Amy | I56: 10000
A57: 45258 | B57: 1000017515 | C57: Amy | Q57: 100000
A58: 45295 | B58: 1000018105 | C58: Amy | F58: 150000
A59: 45295 | B59: 1000018106 | C59: Amy | L59: 100000
A60: 45295 | B60: 1000018107 | C60: Amy | P60: 150000
A61: 45295 | B61: 1000018108 | C61: Amy | Q61: 100000
A62: 45390 | B62: 1000019402 | C62: Amy | F62: 130000
A63: 45390 | B63: 1000019403 | C63: Amy | I63: 30000
A64: 45390 | B64: 1000019404 | C64: Amy | L64: 150000
A65: 45390 | B65: 1000019405 | C65: Amy | Q65: 180000
A66: 45404 | E66: 30395
A67: 45420 | B67: 1000020122 | C67: Amy | F67: 120000
A68: 45420 | B68: 1000020123 | C68: Amy | I68: 30000
A69: 45420 | B69: 1000020124 | C69: Amy | L69: 150000
A70: 45420 | B70: 1000020125 | C70: Amy | P70: 200000 | Q70: 200000
A71: 45470 | B71: 1000021353 | C71: Amy | F71: 100000
A72: 45470 | B72: 1000021354 | C72: Amy | I72: 40000
A73: 45470 | B73: 1000021355 | C73: Amy | L73: 200000
A74: 45470 | B74: 1000021356 | C74: Amy | P74: 150000 | Q74: 150000
A75: 45512 | B75: 1000022433 | F75: 100000
A76: 45512 | B76: 1000022435 | I76: 40000
A77: 45512 | B77: 1000022436 | L77: 130000
A78: 45512 | B78: 1000022437 | P78: 200000 | Q78: 200000
M81: 10002 | U81: 4500137300-7422pcs 4500137318-2580pcs | V81: =M81-7422-2580 -> 0
A82: 45560 | B82: 1000023382 | F82: 150000
A83: 45560 | B83: 1000023383 | I83: 30000
A84: 45560 | B84: 1000023384 | L84: 80000
A85: 45560 | B85: 1000023385 | Q85: 150000
A86: 45610 | B86: 1000024470 | F86: 150000
A87: 45610 | B87: 1000024471 | L87: 150000
A88: 45610 | B88: 1000024472 | Q88: 150000
A89: 45639 | B89: 1000025126 | F89: 30000
A90: 45639 | B90: 1000025127 | I90: 30000
A91: 45639 | B91: 1000025128 | Q91: 50000
M92: 10002 | U92: 4500151230
A93: 45743 | B93: 1000026675 | C93: AMY | F93: 30000
A94: 45743 | B94: 1000026676 | C94: AMY | I94: 30000
A95: 45743 | B95: 1000026677 | C95: AMY | L95: 30000
A96: 45743 | B96: 1000026678 | C96: AMY | Q96: 50000
A97: 45777 | B97: 1000027597 | C97: AMY | F97: 40000
A98: 45777 | B98: 1000027598 | C98: AMY | L98: 50000
A99: 45777 | B99: 1000027599 | C99: AMY | Q99: 50000
A100: 45807 | B100: 1000028595 | C100: AMY | F100: 80000
A101: 45807 | B101: 1000028596 | C101: AMY | L101: 80000
A102: 45807 | B102: 1000028597 | C102: AMY | Q102: 80000
...

Sheet 布料MA
A1: Item | B1: Character | C1: Ratio | D1: Materials Description | F1: MOQ | G1: 产品用量 | H1: MOQ生产数量 | I1: MA-RR-747 | J1: MA-RR-783 | K1: MA-RR-804 | L1: MA-RR-849 | M1: MA-RR-880 | N1: MA-RR-930 | O1: MA-RR-947 | P1: MA-RR-968 （共用布料挪给无闪粉用） | Q1: MA-RR-986 (无闪粉) | R1: MA-RR-1044 (补放有闪粉的共用布料) | S1: MA-RR-1067 (无闪粉) | T1: MA-RR-1162 (无闪粉) | U1: MA-RR-1206 (无闪粉) | V1: MA-RR-1292 (无闪粉) | W1: MA-RR-1389 (无闪粉) | X1: MA-RR-1472 (无闪粉) | Y1: MA-RR-1873 (无闪粉) | Z1: MA-RR-1996 (无闪粉) | AA1: MA-RR-2103 (无闪粉) | AB1: Grand Total | AC1: MA可生产数量
A2: Order Date | I2: 44825 | J2: 44897 | K2: 44966 | L2: 45029 | M2: 45056 | N2: 45128 | O2: 45149 | P2: 45190 | Q2: 45217 | R2: 45217 | S2: 45310 | T2: 45392 | U2: 45422 | V2: 45468 | W2: 45558 | X2: 45629 | Y2: 45902 | Z2: 46000 | AA2: 46055
A3: Delivery Date | I3: =I2+35 -> 44860 | J3: =J2+35 -> 44932 | K3: 45001 | L3: =L2+35 -> 45064 | M3: =M2+35 -> 45091 | N3: =N2+35 -> 45163 | O3: =O2+35 -> 45184 | P3: =P2+35 -> 45225 | Q3: =Q2+35 -> 45252 | R3: =R2+35 -> 45252 | S3: 45388 | T3: =T2+35 -> 45427 | U3: 45457 | V3: 45503 | W3: 45593 | X3: 45664 | Y3: 45942 | Z3: =Z2+35+5 -> 46040 | AA3: =AA2+35+30 -> 46120
A4: Rainbocorn Mermaidcorn Surprise 9283# | B4: 小猫/Kitten | C4: 1 | D4: 10mm白色兔毛 | E4: 共用物料1 | F4: 0 | G4: 0.106605 | H4: =F4/G4 -> 0 | I4: 3198.15 | J4: 3199 | K4: 3198 | L4: 4264 | M4: 3198 | N4: 3198 | O4: 3198 | P4: 4265 | R4: 4264 | S4: 3198 | T4: 3198 | U4: 3198 | V4: 3198 | W4: 4478 | X4: 4264 | Y4: 2132 | Z4: 2132 | AA4: 2132 | AB4: =SUM(I4:AA4) -> 59912.15 | AC4: =ROUND(AB4/G4,-1) -> 562000
D5: 10mm粉色小兔毛/烫银色镭射鱼尾纹 | F5: 800 | G5: 0.087653 | H5: =F5/G5 -> 9126.8981 | I5: 2629.59 | J5: 2630 | K5: 2630 | L5: 3506 | M5: 2629 | N5: 2630 | O5: 2630 | P5: 3506 | R5: 3506 | S5: 2629 | T5: 2630 | U5: 2630 | V5: 2629 | W5: 3682 | X5: 3506 | Y5: 1753 | Z5: 1753 | AA5: 1753 | AB5: =SUM(I5:AA5) -> 49261.59 | AC5: =ROUND(AB5/G5,-1) -> 562010
D6: 紫色闪粉边伦布 | F6: 500 | G6: 0.074675 | H6: =F6/G6 -> 6695.6813 | I6: 2240.25 | J6: 2241 | K6: 2240 | L6: 2987 | M6: 2240 | N6: 2240 | O6: 2241 | P6: 2987 | AB6: =SUM(I6:AA6) -> 19416.25 | AC6: =ROUND(AB6/G6,-1) -> 260010
D7: 粉紫色幻彩PU | F7: 500 | G7: 0.0665 | H7: 7518.797 | Q7: 2660 | R7: 0 | S7: 1995 | T7: 1995 | U7: 1995 | V7: 1995 | W7: 2793 | X7: 2660 | Y7: 1330 | Z7: 1330 | AA7: 1330 | AB7: =SUM(I7:AA7) -> 20083 | AC7: =ROUND(AB7/G7,-1) -> 302000
D8: 1MM紫色戟绒 | F8: 0 | G8: 0.015141 | H8: =F8/G8 -> 0 | I8: 454.23 | J8: 455 | K8: 455 | L8: 605 | M8: 454 | N8: 454 | O8: 454 | P8: 606 | R8: 606 | S8: 454 | T8: 454 | U8: 454 | V8: 454 | W8: 636 | X8: 606 | Y8: 303 | Z8: 303 | AA8: 303 | AB8: =SUM(I8:AA8) -> 8510.23 | AC8: =ROUND(AB8/G8,-1) -> 562070
D9: 110mm粉色长毛绒 | F9: 300 | G9: 0.006489 | H9: =F9/G9 -> 46232.085 | I9: 300 | J9: 300 | L9: 300 | M9: 300 | N9: 300 | P9: 300 | R9: 147 | S9: 195 | T9: 195 | U9: 194 | V9: 195 | W9: 272 | X9: 260 | Y9: 130 | Z9: 130 | AA9: 129 | AB9: =SUM(I9:AA9) -> 3647 | AC9: =ROUND(AB9/G9,-1) -> 562030
D10: 1.5MM漂白水晶超柔 | E10: 共用物料3 | F10: 0 | G10: 0.005253 | H10: =F10/G10 -> 0 | I10: 157.59 | J10: 158 | K10: 158 | L10: 210 | M10: 157 | N10: 158 | O10: 158 | P10: 210 | R10: 210 | S10: 157 | T10: 158 | U10: 158 | V10: 157 | W10: 221 | X10: 210 | Y10: 105 | Z10: 105 | AA10: 105 | AB10: =SUM(I10:AA10) -> 2952.59 | AC10: =ROUND(AB10/G10,-1) -> 562080
D11: 白色边伦布 | E11: 共用物料4 | F11: 0 | G11: 0.004429 | H11: =F11/G11 -> 0 | I11: 132.87 | J11: 133 | K11: 133 | L11: 178 | M11: 132 | N11: 133 | O11: 133 | P11: 177 | R11: 177 | S11: 133 | T11: 133 | U11: 133 | V11: 133 | W11: 186 | X11: 177 | Y11: 89 | Z11: 88 | AA11: 89 | AB11: =SUM(I11:AA11) -> 2489.87 | AC11: =ROUND(AB11/G11,-1) -> 562170
D12: 紫色巴黎之星 | F12: 500 | G12: 0.061079 | H12: =F12/G12 -> 8186.1196 | I12: 1832.37 | J12: 1833 | K12: 1832 | L12: 2443 | M12: 1833 | N12: 1832 | O12: 1833 | P12: 2443 | R12: 2443 | S12: 1832 | T12: 1833 | U12: 1832 | V12: 1832 | W12: 2566 | X12: 2443 | Y12: 1221 | Z12: 1222 | AA12: 1222 | AB12: =SUM(I12:AA12) -> 34327.37 | AC12: =ROUND(AB12/G12,-1) -> 562020
D13: 白色喷棉 | E13: 共用物料5 | F13: 0 | G13: 0.023896 | H13: =F13/G13 -> 0 | I13: 716.88 | J13: 717 | K13: 717 | L13: 956 | M13: 717 | N13: 717 | O13: 717 | P13: 956 | R13: 955 | S13: 717 | T13: 717 | U13: 717 | V13: 717 | W13: 1004 | X13: 955 | Y13: 478 | Z13: 478 | AA13: 478 | AB13: =SUM(I13:AA13) -> 13429.88 | AC13: =ROUND(AB13/G13,-1) -> 562010
D14: 紫色闪粉PU | F14: 300 | G14: 0.001957 | H14: =F14/G14 -> 153295.86 | I14: 300 | M14: 300 | S14: 46 | T14: 59 | U14: 59 | V14: 58 | W14: 83 | X14: 78 | Y14: 39 | Z14: 39 | AA14: 39 | AB14: =SUM(I14:AA14) -> 1100 | AC14: =ROUND(AB14/G14,-1) -> 562080
D15: 6mm宽棉带 | E15: 共用物料6 | F15: 0 | G15: 4.635 | H15: =F15/G15 -> 0 | I15: 139050 | J15: 139050 | K15: 139050 | L15: 185400 | M15: 139050 | N15: 139050 | O15: 139050 | P15: 185400 | R15: 185400 | S15: 139050 | T15: 139050 | U15: 139050 | V15: 139050 | W15: 194670 | X15: 185400 | Y15: 92700 | Z15: 92700 | AA15: 92700 | AB15: =SUM(I15:AA15) -> 2604870 | AC15: =ROUND(AB15/G15,-1) -> 562000
D16: 车缝线 | E16: 共用物料7 | F16: 0 | G16: 28.634 | H16: =F16/G16 -> 0 | I16: 859020 | J16: 859020 | K16: 859020 | L16: 1145360 | M16: 859020 | N16: 859020 | O16: 859020 | P16: 1145360 | R16: 1145360 | S16: 859020 | T16: 859020 | U16: 859020 | V16: 859020 | W16: 1202628 | X16: 1145360 | Y16: 572680 | Z16: 572680 | AA16: 572680 | AB16: =SUM(I16:AA16) -> 16092308 | AC16: =ROUND(AB16/G16,-1) -> 562000
D17: 32MM直径全包扣水晶眼/介子 | E17: 共用物料8 | F17: 0 | G17: 2 | H17: =F17/G17 -> 0 | I17: 60000 | J17: 60000 | K17: 60000 | L17: 80000 | M17: 60000 | N17: 60000 | O17: 60000 | P17: 80000 | R17: 80000 | S17: 60000 | T17: 60000 | U17: 60000 | V17: 60000 | W17: 84000 | X17: 80000 | Y17: 40000 | Z17: 40000 | AA17: 40000 | AB17: =SUM(I17:AA17) -> 1124000 | AC17: =ROUND(AB17/G17,-1) -> 562000
D18: 棉花 | E18: 共用物料9 | F18: 0 | G18: 120 | H18: =F18/G18 -> 0 | I18: 3600000 | J18: 3600000 | K18: 3600000 | L18: 4800000 | M18: 3600000 | N18: 3600000 | O18: 3600000 | P18: 4800000 | R18: 4800000 | S18: 3600000 | T18: 3600000 | U18: 3600000 | V18: 3600000 | W18: 5040000 | X18: 4800000 | Y18: 2400000 | Z18: 2400000 | AA18: 2400000 | AB18: =SUM(I18:AA18) -> 67440000 | AC18: =ROUND(AB18/G18,-1) -> 562000
D19: 布标 | E19: 共用物料10 | F19: 0 | G19: 1 | H19: =F19/G19 -> 0 | I19: 30000 | J19: 30000 | K19: 30000 | L19: 40000 | M19: 30000 | N19: 30000 | O19: 30000 | P19: 40000 | R19: 40000 | S19: 30000 | T19: 30000 | U19: 30000 | V19: 30000 | W19: 42000 | X19: 40000 | Y19: 20000 | Z19: 20000 | AA19: 20000 | AB19: =SUM(I19:AA19) -> 562000 | AC19: =ROUND(AB19/G19,-1) -> 562000
D20: 丝印/电绣 | F20: 0 | G20: 1 | H20: =F20/G20 -> 0 | I20: 30000 | J20: 30000 | K20: 30000 | L20: 40000 | M20: 30000 | N20: 30000 | O20: 30000 | P20: 40000 | R20: 40000 | S20: 30000 | T20: 30000 | U20: 30000 | V20: 30000 | W20: 42000 | X20: 40000 | Y20: 20000 | Z20: 20000 | AA20: 20000 | AB20: =SUM(I20:AA20) -> 562000 | AC20: =ROUND(AB20/G20,-1) -> 562000
B21: 兔子/Bunny | C21: 1 | D21: 10mm粉色兔毛 | F21: 800 | G21: 0.139668 | H21: =F21/G21 -> 5727.8689 | I21: 4190.04 | J21: 4191 | K21: 4190 | L21: 4190 | M21: 5586 | N21: 4190 | O21: 4190 | P21: 4470 | R21: 4469 | S21: 4889 | T21: 5586 | U21: 4889 | V21: 4190 | W21: 5307 | X21: 4190 | Y21: 2793 | Z21: 2794 | AA21: 2793 | AB21: =SUM(I21:AA21) -> 77097.04 | AC21: =ROUND(AB21/G21,-1) -> 552000
D22: 10mm紫色小兔毛/烫银色镭射鱼尾纹 | F22: 800 | G22: 0.087653 | H22: =F22/G22 -> 9126.8981 | I22: 2629.59 | J22: 2630 | K22: 2630 | L22: 2630 | M22: 3505 | N22: 2630 | O22: 2630 | P22: 2804 | R22: 2805 | S22: 3068 | T22: 3506 | U22: 3068 | V22: 2630 | W22: 3331 | X22: 2629 | Y22: 1753 | Z22: 1753 | AA22: 1753 | AB22: =SUM(I22:AA22) -> 48384.59 | AC22: =ROUND(AB22/G22,-1) -> 552000
D23: 蓝色闪粉边伦布 | F23: 500 | G23: 0.069216 | H23: =F23/G23 -> 7223.7633 | I23: 2076.48 | J23: 2077 | K23: 2076 | L23: 2076 | M23: 2770 | N23: 2076 | O23: 2077 | P23: 2214 | W23: -1 | AB23: =SUM(I23:AA23) -> 17441.48 | AC23: =ROUND(AB23/G23,-1) -> 251990
D24: 蓝色幻彩PU | F24: 500 | G24: 0.0603 | H24: 8291.874 | Q24: 1930 | S24: 2111 | T24: 2412 | U24: 2110 | V24: 1809 | W24: 2291 | X24: 1809 | Y24: 1206 | Z24: 1206 | AA24: 1206 | AB24: =SUM(I24:AA24) -> 18090 | AC24: =ROUND(AB24/G24,-1) -> 300000
D25: 1MM蓝色戟绒 | F25: 0 | G25: 0.015141 | H25: =F25/G25 -> 0 | I25: 454.23 | J25: 455 | K25: 455 | L25: 454 | M25: 605 | N25: 454 | O25: 454 | P25: 485 | R25: 484 | S25: 530 | T25: 606 | U25: 530 | V25: 454 | W25: 575 | X25: 455 | Y25: 302 | Z25: 303 | AA25: 303 | AB25: =SUM(I25:AA25) -> 8358.23 | AC25: =ROUND(AB25/G25,-1) -> 552030
D26: 110mm紫色长毛绒 | F26: 300 | G26: 0.006489 | H26: =F26/G26 -> 46232.085 | I26: 300 | J26: 300 | L26: 300 | M26: 300 | N26: 300 | P26: 300 | R26: 43 | S26: 227 | T26: 300 | U26: 187 | V26: 195 | W26: 246 | X26: 195 | Y26: 130 | Z26: 130 | AA26: 129 | AB26: =SUM(I26:AA26) -> 3582 | AC26: =ROUND(AB26/G26,-1) -> 552010
D27: 1.5MM漂白水晶超柔 | E27: 共用物料3 | F27: 0 | G27: 0.004223 | H27: =F27/G27 -> 0 | I27: 126.69 | J27: 127 | K27: 127 | L27: 127 | M27: 168 | N27: 127 | O27: 127 | P27: 135 | R27: 135 | S27: 148 | T27: 169 | U27: 148 | V27: 126 | W27: 161 | X27: 127 | Y27: 84 | Z27: 84 | AA27: 85 | AB27: =SUM(I27:AA27) -> 2331.69 | AC27: =ROUND(AB27/G27,-1) -> 552140
D28: 白色边伦布 | E28: 共用物料4 | F28: 0 | G28: 0.004429 | H28: =F28/G28 -> 0 | I28: 132.87 | J28: 133 | K28: 133 | L28: 133 | M28: 177 | N28: 133 | O28: 133 | P28: 142 | R28: 141 | S28: 155 | T28: 178 | U28: 155 | V28: 133 | W28: 168 | X28: 133 | Y28: 88 | Z28: 89 | AA28: 88 | AB28: =SUM(I28:AA28) -> 2444.87 | AC28: =ROUND(AB28/G28,-1) -> 552010
D29: 蓝色巴黎之星 | F29: 500 | G29: 0.061079 | H29: =F29/G29 -> 8186.1196 | I29: 1832.37 | J29: 1833 | K29: 1832 | L29: 1832 | M29: 2444 | N29: 1832 | O29: 1833 | P29: 1954 | R29: 1955 | S29: 2137 | T29: 2443 | U29: 2138 | V29: 1833 | W29: 2321 | X29: 1832 | Y29: 1222 | Z29: 1221 | AA29: 1222 | AB29: =SUM(I29:AA29) -> 33716.37 | AC29: =ROUND(AB29/G29,-1) -> 552010
D30: 白色喷棉 | E30: 共用物料5 | F30: 0 | G30: 0.023896 | H30: =F30/G30 -> 0 | I30: 716.88 | J30: 717 | K30: 717 | L30: 717 | M30: 956 | N30: 717 | O30: 717 | P30: 764 | R30: 765 | S30: 836 | T30: 956 | U30: 837 | V30: 717 | W30: 908 | X30: 716 | Y30: 478 | Z30: 478 | AA30: 478 | AB30: =SUM(I30:AA30) -> 13190.88 | AC30: =ROUND(AB30/G30,-1) -> 552010
D31: 3MM白色戟绒 | F31: 0 | G31: 0.01957 | H31: =F31/G31 -> 0 | I31: 587.1 | J31: 588 | K31: 587 | L31: 587 | M31: 783 | N31: 587 | O31: 587 | P31: 626 | R31: 626 | S31: 685 | T31: 783 | U31: 685 | V31: 587 | W31: 744 | X31: 587 | Y31: 391 | Z31: 392 | AA31: 391 | AB31: =SUM(I31:AA31) -> 10803.1 | AC31: =ROUND(AB31/G31,-1) -> 552020
D32: 蓝色闪粉PU | F32: 300 | G32: 0.001957 | H32: =F32/G32 -> 153295.86 | I32: 300 | M32: 300 | S32: 25 | T32: 78 | U32: 69 | V32: 58 | W32: 75 | X32: 58 | Y32: 39 | Z32: 40 | AA32: 39 | AB32: =SUM(I32:AA32) -> 1081 | AC32: =ROUND(AB32/G32,-1) -> 552380
D33: 6mm宽棉带 | E33: 共用物料6 | F33: 0 | G33: 4.635 | H33: =F33/G33 -> 0 | I33: 139050 | J33: 139050 | K33: 139050 | L33: 139050 | M33: 185400 | N33: 139050 | O33: 139050 | P33: 148320 | R33: 148320 | S33: 162225 | T33: 185400 | U33: 162225 | V33: 139050 | W33: 176130 | X33: 139050 | Y33: 92700 | Z33: 92700 | AA33: 92700 | AB33: =SUM(I33:AA33) -> 2558520 | AC33: =ROUND(AB33/G33,-1) -> 552000
D34: 车缝线 | E34: 共用物料7 | F34: 0 | G34: 28.634 | H34: =F34/G34 -> 0 | I34: 859020 | J34: 859020 | K34: 859020 | L34: 859020 | M34: 1145360 | N34: 859020 | O34: 859020 | P34: 916288 | R34: 916288 | S34: 1002190 | T34: 1145360 | U34: 1002190 | V34: 859020 | W34: 1088092 | X34: 859020 | Y34: 572680 | Z34: 572680 | AA34: 572680 | AB34: =SUM(I34:AA34) -> 15805968 | AC34: =ROUND(AB34/G34,-1) -> 552000
D35: 32MM直径全包扣水晶眼/介子 | E35: 共用物料8 | F35: 0 | G35: 2 | H35: =F35/G35 -> 0 | I35: 60000 | J35: 60000 | K35: 60000 | L35: 60000 | M35: 80000 | N35: 60000 | O35: 60000 | P35: 64000 | R35: 64000 | S35: 70000 | T35: 80000 | U35: 70000 | V35: 60000 | W35: 76000 | X35: 60000 | Y35: 40000 | Z35: 40000 | AA35: 40000 | AB35: =SUM(I35:AA35) -> 1104000 | AC35: =ROUND(AB35/G35,-1) -> 552000
D36: 棉花 | E36: 共用物料9 | F36: 0 | G36: 120 | H36: =F36/G36 -> 0 | I36: 3600000 | J36: 3600000 | K36: 3600000 | L36: 3600000 | M36: 4800000 | N36: 3600000 | O36: 3600000 | P36: 3840000 | R36: 3840000 | S36: 4200000 | T36: 4800000 | U36: 4200000 | V36: 3600000 | W36: 4560000 | X36: 3600000 | Y36: 2400000 | Z36: 2400000 | AA36: 2400000 | AB36: =SUM(I36:AA36) -> 66240000 | AC36: =ROUND(AB36/G36,-1) -> 552000
D37: 布标 | E37: 共用物料10 | F37: 0 | G37: 1 | H37: =F37/G37 -> 0 | I37: 30000 | J37: 30000 | K37: 30000 | L37: 30000 | M37: 40000 | N37: 30000 | O37: 30000 | P37: 32000 | R37: 32000 | S37: 35000 | T37: 40000 | U37: 35000 | V37: 30000 | W37: 38000 | X37: 30000 | Y37: 20000 | Z37: 20000 | AA37: 20000 | AB37: =SUM(I37:AA37) -> 552000 | AC37: =ROUND(AB37/G37,-1) -> 552000
D38: 丝印/电绣 | F38: 0 | G38: 1 | H38: =F38/G38 -> 0 | I38: 30000 | J38: 30000 | K38: 30000 | L38: 30000 | M38: 40000 | N38: 30000 | O38: 30000 | P38: 32000 | R38: 32000 | S38: 35000 | T38: 40000 | U38: 35000 | V38: 30000 | W38: 38000 | X38: 30000 | Y38: 20000 | Z38: 20000 | AA38: 20000 | AB38: =SUM(I38:AA38) -> 552000 | AC38: =ROUND(AB38/G38,-1) -> 552000
B39: 小狗/Puppy | C39: 1 | D39: 10mm深蓝色兔毛 | F39: 800 | G39: 0.095172 | H39: =F39/G39 -> 8405.8336 | I39: 2855.16 | J39: 2856 | K39: 2855 | L39: 4758 | M39: 2856 | N39: 2855 | O39: 2855 | P39: 2855 | R39: 2855 | S39: 2855 | T39: 2856 | U39: 2855 | V39: 2855 | W39: 3045 | X39: 2856 | Y39: 1903 | Z39: 1903 | AA39: 1904 | AB39: =SUM(I39:AA39) -> 50632.16 | AC39: =ROUND(AB39/G39,-1) -> 532010
D40: 蓝色气蒸绒 | F40: 800 | G40: 0.023484 | H40: =F40/G40 -> 34065.747 | I40: 800 | J40: 800 | K40: 800 | L40: 984 | M40: 800 | N40: 800 | O40: 800 | P40: 800 | R40: 227 | S40: 704 | T40: 800 | U40: 609 | V40: 705 | W40: 751 | X40: 705 | Y40: 470 | Z40: 469 | AA40: 470 | AB40: =SUM(I40:AA40) -> 12494 | AC40: =ROUND(AB40/G40,-1) -> 532020
D41: #16银色烫点布贴合T/C布 | F41: 800 | G41: 0.023484 | H41: =F41/G41 -> 34065.747 | I41: 800 | J41: 800 | K41: 800 | L41: 984 | M41: 800 | N41: 800 | O41: 800 | P41: 800 | R41: 227 | S41: 704 | T41: 800 | U41: 609 | V41: 705 | W41: 751 | X41: 705 | Y41: 470 | Z41: 469 | AA41: 470 | AB41: =SUM(I41:AA41) -> 12494 | AC41: =ROUND(AB41/G41,-1) -> 532020
D42: 10mm深粉色小兔毛/烫银色镭射鱼尾纹 | F42: 800 | G42: 0.087653 | H42: =F42/G42 -> 9126.8981 | I42: 2629.59 | J42: 2630 | K42: 2630 | L42: 4383 | M42: 2629 | N42: 2630 | O42: 2629 | P42: 2630 | AB42: =SUM(I42:AA42) -> 22790.59 | AC42: =ROUND(AB42/G42,-1) -> 260010
D43: 粉色闪粉边伦布 | F43: 500 | G43: 0.060358 | H43: =F43/G43 -> 8283.906 | I43: 1810.74 | J43: 1811 | K43: 1811 | L43: 3018 | M43: 1811 | N43: 1810 | O43: 1811 | P43: 1811 | AB43: =SUM(I43:AA43) -> 15693.74 | AC43: =ROUND(AB43/G43,-1) -> 260010
D44: 浅粉色幻彩PU | F44: 500 | G44: 0.0526 | H44: 9505.7034 | Q44: 1578 | R44: 0 | S44: 1578 | T44: 1578 | U44: 1578 | V44: 1578 | W44: 1684 | X44: 1578 | Y44: 1052 | Z44: 1052 | AA44: 1052 | AB44: =SUM(I44:AA44) -> 14308 | AC44: =ROUND(AB44/G44,-1) -> 272020
D45: 1MM白色戟绒 | E45: 共用物料2 | F45: 0 | G45: 0.0132 | H45: 0 | Q45: 396 | R45: 0 | S45: 396 | T45: 396 | U45: 396 | V45: 396 | W45: 423 | X45: 396 | Y45: 264 | Z45: 264 | AA45: 264 | AB45: =SUM(I45:AA45) -> 3591 | AC45: =ROUND(AB45/G45,-1) -> 272050
D46: 110mm红色长毛绒 | F46: 300 | G46: 0.006489 | H46: =F46/G46 -> 46232.085 | I46: 300 | J46: 300 | L46: 310 | M46: 300 | N46: 300 | P46: 300 | R46: 72 | S46: 195 | T46: 195 | U46: 194 | V46: 195 | W46: 208 | X46: 194 | Y46: 130 | Z46: 130 | AA46: 130 | AB46: =SUM(I46:AA46) -> 3453 | AC46: =ROUND(AB46/G46,-1) -> 532130
D47: 1.5MM漂白水晶超柔 | E47: 共用物料3 | F47: 0 | G47: 0.004223 | H47: =F47/G47 -> 0 | I47: 126.69 | J47: 127 | K47: 127 | L47: 211 | M47: 127 | N47: 126 | O47: 127 | P47: 127 | R47: 126 | S47: 127 | T47: 127 | U47: 127 | V47: 126 | W47: 135 | X47: 127 | Y47: 85 | Z47: 84 | AA47: 84 | AB47: =SUM(I47:AA47) -> 2246.69 | AC47: =ROUND(AB47/G47,-1) -> 532010
D48: 白色边伦布 | E48: 共用物料4 | F48: 0 | G48: 0.004429 | H48: =F48/G48 -> 0 | I48: 132.87 | J48: 133 | K48: 133 | L48: 222 | M48: 133 | N48: 132 | O48: 133 | P48: 133 | R48: 133 | S48: 133 | T48: 133 | U48: 133 | V48: 133 | W48: 141 | X48: 133 | Y48: 89 | Z48: 88 | AA48: 89 | AB48: =SUM(I48:AA48) -> 2356.87 | AC48: =ROUND(AB48/G48,-1) -> 532140
D49: 粉色巴黎之星 | F49: 500 | G49: 0.061079 | H49: =F49/G49 -> 8186.1196 | I49: 1832.37 | J49: 1833 | K49: 1832 | L49: 3054 | M49: 1833 | N49: 1832 | O49: 1832 | P49: 1833 | R49: 1832 | S49: 1832 | T49: 1833 | U49: 1832 | V49: 1833 | W49: 1954 | X49: 1832 | Y49: 1222 | Z49: 1222 | AA49: 1221 | AB49: =SUM(I49:AA49) -> 32494.37 | AC49: =ROUND(AB49/G49,-1) -> 532010
D50: 白色喷棉 | E50: 共用物料5 | F50: 0 | G50: 0.023896 | H50: =F50/G50 -> 0 | I50: 716.88 | J50: 717 | K50: 717 | L50: 1195 | M50: 717 | N50: 717 | O50: 717 | P50: 717 | R50: 716 | S50: 717 | T50: 717 | U50: 717 | V50: 717 | W50: 765 | X50: 717 | Y50: 477 | Z50: 478 | AA50: 478 | AB50: =SUM(I50:AA50) -> 12712.88 | AC50: =ROUND(AB50/G50,-1) -> 532010
D51: 红色闪粉PU | F51: 300 | G51: 0.001957 | H51: =F51/G51 -> 153295.86 | I51: 300 | M51: 300 | S51: 27 | T51: 58 | U51: 59 | V51: 59 | W51: 62 | X51: 59 | Y51: 39 | Z51: 39 | AA51: 40 | AB51: =SUM(I51:AA51) -> 1042 | AC51: =ROUND(AB51/G51,-1) -> 532450
D52: 6mm宽棉带 | E52: 共用物料6 | F52: 0 | G52: 4.635 | H52: =F52/G52 -> 0 | I52: 139050 | J52: 139050 | K52: 139050 | L52: 231750 | M52: 139050 | N52: 139050 | O52: 139050 | P52: 139050 | R52: 139050 | S52: 139050 | T52: 139050 | U52: 139050 | V52: 139050 | W52: 148320 | X52: 139050 | Y52: 92700 | Z52: 92700 | AA52: 92700 | AB52: =SUM(I52:AA52) -> 2465820 | AC52: =ROUND(AB52/G52,-1) -> 532000
D53: 车缝线 | E53: 共用物料7 | F53: 0 | G53: 28.634 | H53: =F53/G53 -> 0 | I53: 859020 | J53: 859020 | K53: 859020 | L53: 1431700 | M53: 859020 | N53: 859020 | O53: 859020 | P53: 859020 | R53: 859020 | S53: 859020 | T53: 859020 | U53: 859020 | V53: 859020 | W53: 916288 | X53: 859020 | Y53: 572680 | Z53: 572680 | AA53: 572680 | AB53: =SUM(I53:AA53) -> 15233288 | AC53: =ROUND(AB53/G53,-1) -> 532000
D54: 32MM直径全包扣水晶眼/介子 | E54: 共用物料8 | F54: 0 | G54: 2 | H54: =F54/G54 -> 0 | I54: 60000 | J54: 60000 | K54: 60000 | L54: 100000 | M54: 60000 | N54: 60000 | O54: 60000 | P54: 60000 | R54: 60000 | S54: 60000 | T54: 60000 | U54: 60000 | V54: 60000 | W54: 64000 | X54: 60000 | Y54: 40000 | Z54: 40000 | AA54: 40000 | AB54: =SUM(I54:AA54) -> 1064000 | AC54: =ROUND(AB54/G54,-1) -> 532000
D55: 棉花 | E55: 共用物料9 | F55: 0 | G55: 120 | H55: =F55/G55 -> 0 | I55: 3600000 | J55: 3600000 | K55: 3600000 | L55: 6000000 | M55: 3600000 | N55: 3600000 | O55: 3600000 | P55: 3600000 | R55: 3600000 | S55: 3600000 | T55: 3600000 | U55: 3600000 | V55: 3600000 | W55: 3840000 | X55: 3600000 | Y55: 2400000 | Z55: 2400000 | AA55: 2400000 | AB55: =SUM(I55:AA55) -> 63840000 | AC55: =ROUND(AB55/G55,-1) -> 532000
D56: 布标 | E56: 共用物料10 | F56: 0 | G56: 1 | H56: =F56/G56 -> 0 | I56: 30000 | J56: 30000 | K56: 30000 | L56: 50000 | M56: 30000 | N56: 30000 | O56: 30000 | P56: 30000 | R56: 30000 | S56: 30000 | T56: 30000 | U56: 30000 | V56: 30000 | W56: 32000 | X56: 30000 | Y56: 20000 | Z56: 20000 | AA56: 20000 | AB56: =SUM(I56:AA56) -> 532000 | AC56: =ROUND(AB56/G56,-1) -> 532000
D57: 丝印/电绣 | F57: 0 | G57: 1 | H57: =F57/G57 -> 0 | I57: 30000 | J57: 30000 | K57: 30000 | L57: 50000 | M57: 30000 | N57: 30000 | O57: 30000 | P57: 30000 | R57: 30000 | S57: 30000 | T57: 30000 | U57: 30000 | V57: 30000 | W57: 32000 | X57: 30000 | Y57: 20000 | Z57: 20000 | AA57: 20000 | AB57: =SUM(I57:AA57) -> 532000 | AC57: =ROUND(AB57/G57,-1) -> 532000
B58: 奶牛/Cow | C58: 1 | D58: 10mm白色兔毛 | E58: 共用物料1 | F58: 0 | G58: 0.111137 | H58: =F58/G58 -> 0 | I58: 3334.11 | J58: 3335 | K58: 3334 | L58: 3334 | M58: 3334 | N58: 3334 | O58: 3334 | P58: 3334 | R58: 3334 | S58: 3334 | T58: 3335 | U58: 3334 | V58: 3334 | W58: 2778 | X58: 2779 | Y58: 2222 | Z58: 2223 | AA58: 2223 | AB58: =SUM(I58:AA58) -> 55569.11 | AC58: =ROUND(AB58/G58,-1) -> 500010
D59: 10mm黑色兔毛 | F59: 800 | G59: 0.019055 | H59: =F59/G59 -> 41983.731 | I59: 800 | J59: 800 | K59: 800 | L59: 115 | M59: 800 | N59: 800 | P59: 800 | R59: 230 | S59: 572 | T59: 572 | U59: 571 | V59: 572 | W59: 476 | X59: 477 | Y59: 381 | Z59: 381 | AA59: 381 | AB59: =SUM(I59:AA59) -> 9528 | AC59: =ROUND(AB59/G59,-1) -> 500030
D60: 10mm深粉色小兔毛/烫银色镭射鱼尾纹 | F60: 800 | G60: 0.087653 | H60: =F60/G60 -> 9126.8981 | I60: 2629.59 | J60: 2630 | K60: 2630 | L60: 2630 | M60: 2629 | N60: 2629 | O60: 2630 | P60: 2630 | R60: 2629 | S60: 2630 | T60: 2629 | U60: 2630 | V60: 2630 | W60: 2191 | X60: 2191 | Y60: 1753 | Z60: 1753 | AA60: 1753 | AB60: =SUM(I60:AA60) -> 43826.59 | AC60: =ROUND(AB60/G60,-1) -> 500000
D61: 浅金色闪粉边伦布 | F61: 500 | G61: 0.081267 | H61: =F61/G61 -> 6152.5588 | I61: 2438.01 | J61: 2439 | K61: 2438 | L61: 2438 | M61: 2438 | N61: 2438 | O61: 2438 | P61: 2438 | AB61: =SUM(I61:AA61) -> 19505.01 | AC61: =ROUND(AB61/G61,-1) -> 240010
D62: 金色烫金布/边纶底 | F62: 500 | G62: 0.0756 | H62: 6613.7566 | Q62: 2268 | R62: 0 | S62: 2268 | T62: 2268 | U62: 2268 | V62: 2268 | W62: 1890 | X62: 1890 | Y62: 1512 | Z62: 1512 | AA62: 1512 | AB62: =SUM(I62:AA62) -> 19656 | AC62: =ROUND(AB62/G62,-1) -> 260000
D63: 1MM白色戟绒 | E63: 共用物料2 | F63: 0 | G63: 0.015141 | H63: =F63/G63 -> 0 | I63: 454.23 | J63: 455 | K63: 454 | L63: 454 | M63: 454 | N63: 455 | O63: 454 | P63: 454 | R63: 454 | S63: 455 | T63: 454 | U63: 454 | V63: 454 | W63: 379 | X63: 378 | Y63: 303 | Z63: 303 | AA63: 303 | AB63: =SUM(I63:AA63) -> 7571.23 | AC63: =ROUND(AB63/G63,-1) -> 500050
D64: 110mm橙色长毛绒 | F64: 300 | G64: 0.006489 | H64: =F64/G64 -> 46232.085 | I64: 300 | J64: 300 | L64: 300 | M64: 300 | O64: 300 | P64: 300 | S64: 147 | T64: 300 | U64: 90 | V64: 194 | W64: 162 | X64: 163 | Y64: 129 | Z64: 130 | AA64: 130 | AB64: =SUM(I64:AA64) -> 3245 | AC64: =ROUND(AB64/G64,-1) -> 500080
D65: 1.5MM橙红色水晶超柔 | F65: 800 | G65: 0.004223 | H65: =F65/G65 -> 189438.79 | I65: 800 | O65: 800 | V65: 47 | W65: 106 | X65: 106 | Y65: 84 | Z65: 85 | AA65: 84 | AB65: =SUM(I65:AA65) -> 2112 | AC65: =ROUND(AB65/G65,-1) -> 500120
D66: 白色边伦布 | E66: 共用物料4 | F66: 0 | G66: 0.004429 | H66: =F66/G66 -> 0 | I66: 132.87 | J66: 133 | K66: 133 | L66: 133 | M66: 133 | N66: 133 | O66: 133 | P66: 133 | R66: 132 | S66: 133 | T66: 133 | U66: 133 | V66: 133 | W66: 111 | X66: 110 | Y66: 89 | Z66: 89 | AA66: 88 | AB66: =SUM(I66:AA66) -> 2214.87 | AC66: =ROUND(AB66/G66,-1) -> 500080
D67: 红色巴黎之星 | F67: 500 | G67: 0.061079 | H67: =F67/G67 -> 8186.1196 | I67: 1832.37 | J67: 1833 | K67: 1833 | L67: 1832 | M67: 1832 | N67: 1832 | O67: 1833 | P67: 1832 | R67: 1832 | S67: 1833 | T67: 1832 | U67: 1833 | V67: 1832 | W67: 1527 | X67: 1527 | Y67: 1221 | Z67: 1222 | AA67: 1222 | AB67: =SUM(I67:AA67) -> 30540.37 | AC67: =ROUND(AB67/G67,-1) -> 500010
D68: 白色喷棉 | E68: 共用物料5 | F68: 0 | G68: 0.023896 | H68: =F68/G68 -> 0 | I68: 716.88 | J68: 717 | K68: 717 | L68: 717 | M68: 717 | N68: 717 | O68: 717 | P68: 717 | R68: 717 | S68: 716 | T68: 717 | U68: 717 | V68: 717 | W68: 597 | X68: 598 | Y68: 478 | Z68: 478 | AA68: 478 | AB68: =SUM(I68:AA68) -> 11948.88 | AC68: =ROUND(AB68/G68,-1) -> 500040
D69: 金色闪粉PU | F69: 300 | G69: 0.001957 | H69: =F69/G69 -> 153295.86 | I69: 300 | N69: 300 | T69: 46 | U69: 59 | V69: 59 | W69: 49 | X69: 49 | Y69: 39 | Z69: 39 | AA69: 39 | AB69: =SUM(I69:AA69) -> 979 | AC69: =ROUND(AB69/G69,-1) -> 500260
D70: 6mm宽棉带 | E70: 共用物料6 | F70: 0 | G70: 4.635 | H70: =F70/G70 -> 0 | I70: 139050 | J70: 139050 | K70: 139050 | L70: 139050 | M70: 139050 | N70: 139050 | O70: 139050 | P70: 139050 | R70: 139050 | S70: 139050 | T70: 139050 | U70: 139050 | V70: 139050 | W70: 115875 | X70: 115875 | Y70: 92700 | Z70: 92700 | AA70: 92700 | AB70: =SUM(I70:AA70) -> 2317500 | AC70: =ROUND(AB70/G70,-1) -> 500000
D71: 车缝线 | E71: 共用物料7 | F71: 0 | G71: 28.634 | H71: =F71/G71 -> 0 | I71: 859020 | J71: 859020 | K71: 859020 | L71: 859020 | M71: 859020 | N71: 859020 | O71: 859020 | P71: 859020 | R71: 859020 | S71: 859020 | T71: 859020 | U71: 859020 | V71: 859020 | W71: 715850 | X71: 715850 | Y71: 572680 | Z71: 572680 | AA71: 572680 | AB71: =SUM(I71:AA71) -> 14317000 | AC71: =ROUND(AB71/G71,-1) -> 500000
D72: 32MM直径全包扣水晶眼/介子 | E72: 共用物料8 | F72: 0 | G72: 2 | H72: =F72/G72 -> 0 | I72: 60000 | J72: 60000 | K72: 60000 | L72: 60000 | M72: 60000 | N72: 60000 | O72: 60000 | P72: 60000 | R72: 60000 | S72: 60000 | T72: 60000 | U72: 60000 | V72: 60000 | W72: 50000 | X72: 50000 | Y72: 40000 | Z72: 40000 | AA72: 40000 | AB72: =SUM(I72:AA72) -> 1000000 | AC72: =ROUND(AB72/G72,-1) -> 500000
D73: 棉花 | E73: 共用物料9 | F73: 0 | G73: 120 | H73: =F73/G73 -> 0 | I73: 3600000 | J73: 3600000 | K73: 3600000 | L73: 3600000 | M73: 3600000 | N73: 3600000 | O73: 3600000 | P73: 3600000 | R73: 3600000 | S73: 3600000 | T73: 3600000 | U73: 3600000 | V73: 3600000 | W73: 3000000 | X73: 3000000 | Y73: 2400000 | Z73: 2400000 | AA73: 2400000 | AB73: =SUM(I73:AA73) -> 60000000 | AC73: =ROUND(AB73/G73,-1) -> 500000
D74: 布标 | E74: 共用物料10 | F74: 0 | G74: 1 | H74: =F74/G74 -> 0 | I74: 30000 | J74: 30000 | K74: 30000 | L74: 30000 | M74: 30000 | N74: 30000 | O74: 30000 | P74: 30000 | R74: 30000 | S74: 30000 | T74: 30000 | U74: 30000 | V74: 30000 | W74: 25000 | X74: 25000 | Y74: 20000 | Z74: 20000 | AA74: 20000 | AB74: =SUM(I74:AA74) -> 500000 | AC74: =ROUND(AB74/G74,-1) -> 500000
D75: 丝印/电绣 | F75: 0 | G75: 1 | H75: =F75/G75 -> 0 | I75: 30000 | J75: 30000 | K75: 30000 | L75: 30000 | M75: 30000 | N75: 30000 | O75: 30000 | P75: 30000 | R75: 30000 | S75: 30000 | T75: 30000 | U75: 30000 | V75: 30000 | W75: 25000 | X75: 25000 | Y75: 20000 | Z75: 20000 | AA75: 20000 | AB75: =SUM(I75:AA75) -> 500000 | AC75: =ROUND(AB75/G75,-1) -> 500000
B76: 大象/Elephent | C76: 1 | D76: 10mm蓝色兔毛 | F76: 800 | G76: 0.16274 | H76: =F76/G76 -> 4915.8166 | I76: 4882.2 | J76: 4883 | K76: 4882 | L76: 5696 | M76: 6184 | N76: 7323 | O76: 4882 | P76: 4883 | R76: 4882 | S76: 4882 | T76: 4882 | U76: 4882 | V76: 4883 | W76: 4068 | X76: 4882 | Y76: 3255 | Z76: 3255 | AA76: 3255 | AB76: =SUM(I76:AA76) -> 86741.2 | AC76: =ROUND(AB76/G76,-1) -> 533000
D77: 10mm白色小兔毛/烫银色镭射鱼尾纹 | F77: 0 | G77: 0.087653 | H77: =F77/G77 -> 0 | I77: 2629.59 | J77: 2630 | K77: 2630 | L77: 3068 | M77: 3330 | N77: 3945 | O77: 2629 | P77: 2630 | R77: 2630 | S77: 2629 | T77: 2630 | U77: 2629 | V77: 2630 | W77: 2191 | Y77: 1753 | Z77: 1753 | AA77: 1753 | AB77: =SUM(I77:AA77) -> 44089.59 | AC77: =ROUND(AB77/G77,-1) -> 503000
D78: 浅蓝色闪粉边伦布 | F78: 500 | G78: 0.060358 | H78: =F78/G78 -> 8283.906 | I78: 1810.74 | J78: 1811 | K78: 1811 | L78: 2113 | M78: 2293 | N78: 2716 | O78: 1811 | P78: 1811 | W78: -1 | AB78: =SUM(I78:AA78) -> 16175.74 | AC78: =ROUND(AB78/G78,-1) -> 268000
D79: 绿色幻彩PU | F79: 500 | G79: 0.0849 | H79: 5889.2815 | Q79: 2547 | R79: 0 | S79: 2547 | T79: 2547 | U79: 2547 | V79: 2547 | W79: 2123 | X79: 2547 | Y79: 1698 | Z79: 1698 | AA79: 1698 | AB79: =SUM(I79:AA79) -> 22499 | AC79: =ROUND(AB79/G79,-1) -> 265010
D80: 1MM绿色戟绒 | F80: 0 | G80: 0.015141 | H80: =F80/G80 -> 0 | I80: 454.23 | J80: 455 | K80: 454 | L80: 530 | M80: 575 | N80: 682 | O80: 454 | P80: 454 | R80: 454 | S80: 455 | T80: 454 | U80: 454 | V80: 454 | W80: 379 | X80: 454 | Y80: 303 | Z80: 303 | AA80: 302 | AB80: =SUM(I80:AA80) -> 8070.23 | AC80: =ROUND(AB80/G80,-1) -> 533010
D81: 110mm绿色长毛绒 | F81: 300 | G81: 0.015141 | H81: =F81/G81 -> 19813.751 | I81: 454.23 | J81: 455 | K81: 454 | L81: 530 | M81: 575 | N81: 682 | O81: 454 | P81: 454 | R81: 454 | S81: 455 | T81: 454 | U81: 454 | V81: 454 | W81: 379 | X81: 454 | Y81: 303 | Z81: 303 | AA81: 302 | AB81: =SUM(I81:AA81) -> 8070.23 | AC81: =ROUND(AB81/G81,-1) -> 533010
D82: 2mm白色戟绒 | E82: 共用物料2 | F82: 0 | G82: 0.00103 | H82: =F82/G82 -> 0 | I82: 30.9 | J82: 31 | K82: 31 | L82: 36 | M82: 39 | N82: 47 | O82: 31 | P82: 31 | R82: 31 | S82: 30 | T82: 31 | U82: 31 | V82: 31 | W82: 26 | X82: 31 | Y82: 20 | Z82: 21 | AA82: 21 | AB82: =SUM(I82:AA82) -> 549.9 | AC82: =ROUND(AB82/G82,-1) -> 533880
D83: 白色边伦布 | E83: 共用物料4 | F83: 0 | G83: 0.004429 | H83: =F83/G83 -> 0 | I83: 132.87 | J83: 133 | K83: 133 | L83: 155 | M83: 169 | N83: 199 | O83: 133 | P83: 133 | R83: 132 | S83: 133 | T83: 133 | U83: 133 | V83: 133 | W83: 111 | X83: 133 | Y83: 88 | Z83: 89 | AA83: 88 | AB83: =SUM(I83:AA83) -> 2360.87 | AC83: =ROUND(AB83/G83,-1) -> 533050
D84: 1MM白色戟绒 | E84: 共用物料2 | F84: 0 | G84: 0.017819 | H84: =F84/G84 -> 0 | I84: 534.57 | J84: 535 | K84: 535 | L84: 624 | M84: 676 | N84: 802 | O84: 535 | P84: 534 | R84: 535 | S84: 535 | T84: 534 | U84: 535 | V84: 534 | W84: 446 | X84: 534 | Y84: 357 | Z84: 356 | AA84: 356 | AB84: =SUM(I84:AA84) -> 9497.57 | AC84: =ROUND(AB84/G84,-1) -> 533000
D85: 绿色巴黎之星 | F85: 500 | G85: 0.061079 | H85: =F85/G85 -> 8186.1196 | I85: 1832.37 | J85: 1833 | K85: 1832 | L85: 2138 | M85: 2321 | N85: 2749 | O85: 1832 | P85: 1832 | R85: 1833 | S85: 1832 | T85: 1832 | U85: 1833 | V85: 1832 | W85: 1527 | X85: 1832 | Y85: 1222 | Z85: 1222 | AA85: 1221 | AB85: =SUM(I85:AA85) -> 32555.37 | AC85: =ROUND(AB85/G85,-1) -> 533000
D86: 白色喷棉 | E86: 共用物料5 | F86: 0 | G86: 0.023896 | H86: =F86/G86 -> 0 | I86: 716.88 | J86: 717 | K86: 717 | L86: 837 | M86: 908 | N86: 1075 | O86: 717 | P86: 717 | R86: 717 | S86: 717 | T86: 716 | U86: 717 | V86: 717 | W86: 598 | X86: 716 | Y86: 478 | Z86: 478 | AA86: 478 | AB86: =SUM(I86:AA86) -> 12736.88 | AC86: =ROUND(AB86/G86,-1) -> 533010
D87: 绿色闪粉PU | F87: 300 | G87: 0.001957 | H87: =F87/G87 -> 153295.86 | I87: 300 | M87: 300 | S87: 42 | T87: 59 | U87: 59 | V87: 59 | W87: 48 | X87: 59 | Y87: 39 | Z87: 39 | AA87: 40 | AB87: =SUM(I87:AA87) -> 1044 | AC87: =ROUND(AB87/G87,-1) -> 533470
D88: 6mm宽棉带 | E88: 共用物料6 | F88: 0 | G88: 4.635 | H88: =F88/G88 -> 0 | I88: 139050 | J88: 139050 | K88: 139050 | L88: 162225 | M88: 176130 | N88: 208575 | O88: 139050 | P88: 139050 | R88: 139050 | S88: 139050 | T88: 139050 | U88: 139050 | V88: 139050 | W88: 115875 | X88: 139050 | Y88: 92700 | Z88: 92700 | AA88: 92700 | AB88: =SUM(I88:AA88) -> 2470455 | AC88: =ROUND(AB88/G88,-1) -> 533000
D89: 车缝线 | E89: 共用物料7 | F89: 0 | G89: 28.634 | H89: =F89/G89 -> 0 | I89: 859020 | J89: 859020 | K89: 859020 | L89: 1002190 | M89: 1088092 | N89: 1288530 | O89: 859020 | P89: 859020 | R89: 859020 | S89: 859020 | T89: 859020 | U89: 859020 | V89: 859020 | W89: 715850 | X89: 859020 | Y89: 572680 | Z89: 572680 | AA89: 572680 | AB89: =SUM(I89:AA89) -> 15261922 | AC89: =ROUND(AB89/G89,-1) -> 533000
D90: 32MM直径全包扣水晶眼/介子 | E90: 共用物料8 | F90: 0 | G90: 2 | H90: =F90/G90 -> 0 | I90: 60000 | J90: 60000 | K90: 60000 | L90: 70000 | M90: 76000 | N90: 90000 | O90: 60000 | P90: 60000 | R90: 60000 | S90: 60000 | T90: 60000 | U90: 60000 | V90: 60000 | W90: 50000 | X90: 60000 | Y90: 40000 | Z90: 40000 | AA90: 40000 | AB90: =SUM(I90:AA90) -> 1066000 | AC90: =ROUND(AB90/G90,-1) -> 533000
D91: 棉花 | E91: 共用物料9 | F91: 0 | G91: 120 | H91: =F91/G91 -> 0 | I91: 3600000 | J91: 3600000 | K91: 3600000 | L91: 4200000 | M91: 4560000 | N91: 5400000 | O91: 3600000 | P91: 3600000 | R91: 3600000 | S91: 3600000 | T91: 3600000 | U91: 3600000 | V91: 3600000 | W91: 3000000 | X91: 3600000 | Y91: 2400000 | Z91: 2400000 | AA91: 2400000 | AB91: =SUM(I91:AA91) -> 63960000 | AC91: =ROUND(AB91/G91,-1) -> 533000
D92: 布标 | E92: 共用物料10 | F92: 0 | G92: 1 | H92: =F92/G92 -> 0 | I92: 30000 | J92: 30000 | K92: 30000 | L92: 35000 | M92: 38000 | N92: 45000 | O92: 30000 | P92: 30000 | R92: 30000 | S92: 30000 | T92: 30000 | U92: 30000 | V92: 30000 | W92: 25000 | X92: 30000 | Y92: 20000 | Z92: 20000 | AA92: 20000 | AB92: =SUM(I92:AA92) -> 533000 | AC92: =ROUND(AB92/G92,-1) -> 533000
D93: 丝印/电绣 | F93: 0 | G93: 1 | H93: =F93/G93 -> 0 | I93: 30000 | J93: 30000 | K93: 30000 | L93: 35000 | M93: 38000 | N93: 45000 | O93: 30000 | P93: 30000 | R93: 30000 | S93: 30000 | T93: 30000 | U93: 30000 | V93: 30000 | W93: 25000 | X93: 30000 | Y93: 20000 | Z93: 20000 | AA93: 20000 | AB93: =SUM(I93:AA93) -> 533000 | AC93: =ROUND(AB93/G93,-1) -> 533000
B94: 火烈鸟/Flamingo | C94: 1 | D94: 10mm粉色扎染兔毛 | F94: 800 | G94: 0.095172 | H94: =F94/G94 -> 8405.8336 | I94: 2855.16 | J94: 2856 | K94: 2855 | L94: 3521 | M94: 2855 | N94: 2856 | O94: 2855 | P94: 2855 | R94: 2855 | S94: 2855 | T94: 2855 | U94: 2855 | V94: 2856 | W94: 2379 | X94: 2379 | Y94: 1904 | Z94: 1903 | AA94: 1904 | AB94: =SUM(I94:AA94) -> 48253.16 | AC94: =ROUND(AB94/G94,-1) -> 507010
D95: 10mm深粉色小兔毛/烫银色镭射鱼尾纹 | F95: 800 | G95: 0.087653 | H95: =F95/G95 -> 9126.8981 | I95: 2629.59 | J95: 2630 | K95: 2630 | L95: 3243 | M95: 2629 | N95: 2630 | O95: 2630 | P95: 2629 | R95: 2630 | S95: 2629 | T95: 2630 | U95: 2630 | V95: 2629 | W95: 2191 | X95: 2192 | Y95: 1753 | Z95: 1753 | AA95: 1753 | AB95: =SUM(I95:AA95) -> 44440.59 | AC95: =ROUND(AB95/G95,-1) -> 507010
D96: 银色闪粉边伦布 | F96: 500 | G96: 0.038316 | H96: =F96/G96 -> 13049.379 | I96: 1149.48 | J96: 1150 | K96: 1150 | L96: 1418 | M96: 1149 | N96: 1149 | O96: 1150 | P96: 1149 | AB96: =SUM(I96:AA96) -> 9464.48 | AC96: =ROUND(AB96/G96,-1) -> 247010
D97: 银色烫金布/边纶底 | F97: 500 | G97: 0.0334 | H97: 14970.06 | Q97: 1002 | R97: 0 | S97: 1002 | T97: 1002 | U97: 1002 | V97: 1002 | W97: 835 | X97: 835 | Y97: 668 | Z97: 668 | AA97: 668 | AB97: =SUM(I97:AA97) -> 8684 | AC97: =ROUND(AB97/G97,-1) -> 260000
D98: 1MM白色戟绒 | E98: 共用物料2 | F98: 0 | G98: 0.015141 | H98: =F98/G98 -> 0 | I98: 454.23 | J98: 455 | K98: 454 | L98: 560 | M98: 454 | N98: 455 | O98: 454 | P98: 454 | R98: 454 | S98: 455 | T98: 454 | U98: 454 | V98: 454 | W98: 379 | X98: 378 | Y98: 303 | Z98: 303 | AA98: 303 | AB98: =SUM(I98:AA98) -> 7677.23 | AC98: =ROUND(AB98/G98,-1) -> 507050
D99: 110mm红色长毛绒 | F99: 300 | G99: 0.025441 | H99: =F99/G99 -> 11791.989 | I99: 763.23 | J99: 764 | K99: 763 | L99: 941 | M99: 764 | N99: 763 | O99: 763 | P99: 763 | R99: 763 | S99: 764 | T99: 763 | U99: 763 | V99: 763 | W99: 636 | X99: 636 | Y99: 509 | Z99: 509 | AA99: 509 | AB99: =SUM(I99:AA99) -> 12899.23 | AC99: =ROUND(AB99/G99,-1) -> 507030
D100: 玫红色边伦布 | F100: 300 | G100: 0.018952 | H100: =F100/G100 -> 15829.464 | I100: 568.56 | J100: 569 | K100: 569 | L100: 701 | M100: 568 | N100: 569 | O100: 569 | P100: 568 | R100: 569 | S100: 568 | T100: 569 | U100: 568 | V100: 569 | W100: 474 | X100: 473 | Y100: 380 | Z100: 379 | AA100: 379 | AB100: =SUM(I100:AA100) -> 9609.56 | AC100: =ROUND(AB100/G100,-1) -> 507050
...

Sheet 半成品MA
A2: #9283 MA半成品扣數表（有闪粉毛绒） | M2: 布料 | N2: 布料剩余
A3: MA訂單號 | B3: 日期 | C3: 小猫 | D3: 兔子 | E3: 小狗 | F3: 奶牛 | G3: 大象 | H3: 火烈鸟 | I3: 6款合計 | J3: MA布标 | K3: 预留客版布标 | L3: 要求完成時間 | M3: =布料MA!AC114 -> 3186000 | N3: =M3-I13-I40 -> 0 | XFD3: =SUM(A3:XFC3) -> 3186000
A4: MA-RR-781 | B4: 44929 | C4: 30000 | D4: 30000 | E4: 30000 | F4: 30000 | G4: 30000 | H4: 30000 | I4: =SUM(C4:H4) -> 180000 | J4: 138000 | K4: =I4-J4 -> 42000 | L4: 45010
A5: MA-RR-805 | B5: 44966 | C5: 30000 | D5: 30000 | E5: 30000 | F5: 30000 | G5: 30000 | H5: 30000 | I5: =SUM(C5:H5) -> 180000 | J5: 138000 | K5: =I6-J5 -> 42000 | L5: 45056
A6: MA_RR_829 | B6: 45006 | C6: 30000 | D6: 30000 | E6: 30000 | F6: 30000 | G6: 30000 | H6: 30000 | I6: =SUM(C6:H6) -> 180000 | J6: 138000 | L6: 45102
A7: MA_RR_881 | B7: 45056 | C7: 40000 | D7: 30000 | E7: 50000 | F7: 30000 | G7: 35000 | H7: 37000 | I7: =SUM(C7:H7) -> 222000 | L7: 45123
A8: MA_RR_924 | B8: 45111 | C8: 30000 | D8: 40000 | E8: 30000 | F8: 30000 | G8: 38000 | H8: 30000 | I8: =SUM(C8:H8) -> 198000 | L8: 45205
A9: MA_RR_945 | B9: 45149 | C9: 30000 | D9: 30000 | E9: 30000 | F9: 30000 | G9: 45000 | H9: 30000 | I9: =SUM(C9:H9) -> 195000 | L9: 45231 | M9: 兔子B版本布标
A10: MA_RR_967 | B10: 45194 | C10: 30000 | D10: 30000 | E10: 30000 | F10: 30000 | G10: 30000 | H10: 30000 | I10: =SUM(C10:H10) -> 180000 | L10: 45250 | M10: 兔子B版本布标
A11: MA_RR_1053 | B11: 45285 | C11: 40000 | D11: 32000 | E11: 30000 | F11: 30000 | G11: 30000 | H11: 30000 | I11: =SUM(C11:H11) -> 192000 | L11: 45371
B12: 有闪粉欠数 | C12: -9309 | D12: -2939 | E12: -6864 | F12: -2625 | G12: -2976 | H12: -6902 | I12: =SUM(C12:H12) -> -31615
B13: MA合計 | C13: =SUM(C4:C12) -> 250691 | D13: =SUM(D4:D12) -> 249061 | E13: =SUM(E4:E12) -> 253136 | F13: =SUM(F4:F12) -> 237375 | G13: =SUM(G4:G12) -> 265024 | H13: =SUM(H4:H12) -> 240098 | I13: =SUM(I4:I12) -> 1495385
A14: 2023年删除数： | C14: 207404.5 | D14: 207016.5 | E14: 198317.5 | F14: 180929.5 | G14: 215246.5 | H14: 190041.5 | I14: =SUM(C14:H14) -> 1198956
A15: 2024年删除数： | C15: 43286.667 | D15: 42044.333 | E15: 54818.333 | F15: 56445.667 | G15: 49777.333 | H15: 50056.333 | I15: =SUM(C15:H15) -> 296428.67
B16: PO接單數量 | C16: ='9283'!BN564+C14+C15 -> 250691.17 | D16: ='9283'!BO564+D14+D15 -> 249060.83 | E16: ='9283'!BP564+E14+E15 -> 253135.83 | F16: ='9283'!BQ564+F14+F15 -> 237375.17 | G16: ='9283'!BR564+G14+G15 -> 265023.83 | H16: ='9283'!BS564+H14+H15 -> 240097.83 | I16: =SUM(C16:H16) -> 1495384.7
B17: 樣板PO接單數
B18: MA半成品剩餘數 | C18: =C13-C16-C17 -> -0.16666667 | D18: =D13-D16-D17 -> 0.16666667 | E18: =E13-E16-E17 -> 0.16666667 | F18: =F13-F16-F17 -> -0.16666667 | G18: =G13-G16-G17 -> 0.16666667 | H18: =H13-H16-H17 -> 0.16666667 | I18: =SUM(C18:H18) -> 0.33333333
B19: MA剩餘總數 | C19: =SUM(C18:H18) -> 0.33333333
C20: 250691.17 | D20: 249060.83 | E20: 253135.83 | F20: 237375.17 | G20: 265023.83 | H20: 240097.83 | I20: 1495384.7
C21: =C20-C16 -> 0 | D21: =D20-D16 -> 0 | E21: =E20-E16 -> 0 | F21: =F20-F16 -> 0 | G21: =G20-G16 -> 0 | H21: =H20-H16 -> 0 | I21: =I20-I16 -> 3.9581209e-09
L22: 1276196
L23: =L22-I16 -> -219188.67
A25: #9283 MA半成品扣數表（无闪粉毛绒）
A26: MA訂單號 | B26: 日期 | C26: 小猫 | D26: 兔子 | E26: 小狗 | F26: 奶牛 | G26: 大象 | H26: 火烈鸟 | I26: 6款合計 | J26: MA布标 | K26: 预留客版布标 | L26: 要求完成時間
A27: MA_RR_1013 | B27: 45244 | C27: 40000 | D27: 32000 | E27: 30000 | F27: 30000 | G27: 30000 | H27: 30000 | I27: =SUM(C27:H27) -> 192000 | L27: 45301
A28: MA_RR_1098 | B28: 45352 | C28: 30000 | D28: 35000 | E28: 30000 | F28: 30000 | G28: 30000 | H28: 30000 | I28: =SUM(C28:H28) -> 185000 | L28: 45434 | M28: 布标新日期格式
A29: MA_RR_1205 | B29: 45422 | C29: =30000 -> 30000 | D29: =40000 -> 40000 | E29: =30000 -> 30000 | F29: 30000 | G29: 30000 | H29: 30000 | I29: =SUM(C29:H29) -> 190000 | L29: 45503 | M29: 布标新日期格式
A30: MA_RR_1266 | B30: 45456 | C30: 30000 | D30: 35000 | E30: 30000 | F30: 30000 | G30: 30000 | H30: 30000 | I30: =SUM(C30:H30) -> 185000 | L30: 45538 | M30: 布标新日期格式
A31: MA_RR_1329 | B31: 45496 | C31: 30000 | D31: 30000 | E31: 30000 | F31: 30000 | G31: 30000 | H31: 30000 | I31: =SUM(C31:H31) -> 180000 | L31: 45573 | M31: 布标新日期格式
B32: 补有闪粉欠数 | C32: 9309 | D32: 2939 | E32: 6864 | F32: 2625 | G32: 2976 | H32: 6902 | I32: =SUM(C32:H32) -> 31615 | M32: 布标新日期格式
A33: MA_RR_1412 | B33: 45580 | C33: 42000 | D33: 38000 | E33: 32000 | F33: 25000 | G33: 25000 | H33: 25000 | I33: =SUM(C33:H33) -> 187000 | L33: 45646 | M33: 布标新日期格式
A34: MA_RR_1473 | B34: 45629 | C34: 40000 | D34: 30000 | E34: 30000 | F34: 25000 | G34: 30000 | H34: 25000 | I34: =SUM(C34:H34) -> 180000 | L34: 45721 | M34: 布标新日期格式
A35: MA_RR_1917 | B35: 45939 | C35: =20000-C36 -> 11666 | D35: =20000-D36 -> 11666 | E35: =20000-E36 -> 11666 | F35: =20000-F36 -> 11666 | G35: =20000-G36 -> 11666 | H35: =20000-H36 -> 11666 | I35: =SUM(C35:H35) -> 69996 | K35: 9286 | L35: 45974
A36: MA_RR_1917 | B36: 45939 | C36: 8334 | D36: 8334 | E36: 8334 | F36: 8334 | G36: 8334 | H36: 8334 | I36: =SUM(C36:H36) -> 50004 | K36: 9283 | L36: 45974 | M36: 新布标地址
A37: MA_RR_2064 | B37: 46036 | C37: 20000 | D37: 20000 | E37: 20000 | F37: 20000 | G37: 20000 | H37: 20000 | I37: =SUM(C37:H37) -> 120000 | L37: 46106 | M37: 新布标地址
A38: MA-RR-2436 | B38: 46227 | C38: 20000 | D38: 20000 | E38: 20000 | F38: 20000 | G38: 20000 | H38: 20000 | I38: =SUM(C38:H38) -> 120000 | L38: 46295 | M38: 新布标地址
B40: MA合計 | C40: =SUM(C27:C39) -> 311309 | D40: =SUM(D27:D39) -> 302939 | E40: =SUM(E27:E39) -> 278864 | F40: =SUM(F27:F39) -> 262625 | G40: =SUM(G27:G39) -> 267976 | H40: =SUM(H27:H39) -> 266902 | I40: =SUM(I27:I39) -> 1690615
A41: 2024年删除数： | C41: 183134.5 | D41: 174470.83 | E41: 148006.83 | F41: 132023.5 | G41: 139031.83 | H41: 139404.83 | I41: =SUM(C41:H41) -> 916072.33
B42: PO接單數量 | C42: ='9283'!BH564+C41 -> 288487.21 | D42: ='9283'!BI564+D41 -> 278992.96 | E42: ='9283'!BJ564+E41 -> 255159.37 | F42: ='9283'!BK564+F41 -> 239109.52 | G42: ='9283'!BL564+G41 -> 242754.05 | H42: ='9283'!BM564+H41 -> 244417.27 | I42: =SUM(C42:H42) -> 1548920.4
B43: 樣板PO接單數
B44: MA半成品剩餘數 | C44: =C40-C42-C43 -> 22821.789 | D44: =D40-D42-D43 -> 23946.042 | E44: =E40-E42-E43 -> 23704.63 | F44: =F40-F42-F43 -> 23515.477 | G44: =G40-G42-G43 -> 25221.95 | H44: =H40-H42-H43 -> 22484.73 | I44: =SUM(C44:H44) -> 141694.62 | M44: 合计半品MA | N44: 总接单
B45: MA剩餘總數 | C45: =SUM(C44:H44) -> 141694.62 | M45: =I40+I13 -> 3186000 | N45: =I16+I42 -> 3044305 | O45: =M45-N45 -> 141694.95
C46: 204911.83 | D46: 196356.17 | E46: 169216.17 | F46: 152908.83 | G46: 159917.17 | H46: 160290.17 | I46: 1043600.3
C47: =C46-C42 -> -83575.378 | D47: =D46-D42 -> -82636.791 | E47: =E46-E42 -> -85943.204 | F47: =F46-F42 -> -86200.69 | G47: =G46-G42 -> -82836.884 | H47: =H46-H42 -> -84127.103 | I47: =I46-I42 -> -505320.05
B49: 合计接单数： | C49: =C42+C16 -> 539178.38 | D49: =D42+D16 -> 528053.79 | E49: =E42+E16 -> 508295.2 | F49: =F42+F16 -> 476484.69 | G49: =G42+G16 -> 507777.88 | H49: =H42+H16 -> 484515.1

Sheet 取消订单
A1: 接单日期 | B1: 第三方客户名称 | C1: 走货国家 | D1: PO号 | E1: 客户 PO 号 | F1: SKU | G1: 系统货号 | H1: ITEM# | I1: 中文名 | J1: PO数量 (pcs) | K1: 内箱装箱数量(pcs) | L1: 外箱装箱数量(pcs) | M1: 总箱数 | N1: 计划出货期 | O1: 计划验货期 | P1: 第三方验货日期 | Q1: 取消时间 | R1: 是否有物料产生 | S1: 消耗明细 | T1: 箱唛资料 | U1: 是否有外箱贴 | V1: 贴纸资料 | W1: 客供物料 | X1: 日期码 | Y1: 备注 | Z1: ZURU 跟单 | AA1: 单价USD | AB1: 金额USD | AC1: 發票號 | AD1: 是否入系统 | AE1: MA 1語收縮膜 A版本 | AF1: MA 3语收缩膜 | AG1: 客版收縮膜 | AH1: 5语 收藏指南 A版本 | AI1: 客版收藏指南 | AJ1: Try Me-1L贴纸 | AK1: Try Me-3L贴纸 | AL1: Try Me-客办 | AM1: 9283 MA1L展示架 | AN1: 9283 MA3L展示架 | AO1: 布標 | AP1: A 小猫 Kitten | AQ1: B 兔子 Bunny | AR1: D 小狗 Puppy | AS1: 奶牛 Cow | AT1: 大象 Elephant | AU1: H火烈鸟 Flamingo | AV1: 生產狀態 | AW1: 总数 | AX1: 相差
A2: 44986 | B2: SUOMEN OSUUSKAUPPOJEN | C2: 芬兰 | D2: 4500096312 | F2: 4500096312-30 | G2: 9283-S001 | H2: 9283-S001 | I2: 美人鱼6只装 | J2: 1500 | K2: 0 | L2: 6 | M2: =J2/6 -> 250 | N2: 45056 | O2: 45052 | T2: 欠 | V2: 欠布标贴 纸+EAN贴纸+警告语贴纸 | Y2: 日期码格式：ZURU 标准格式 日期：按实际生产日期 Packaging Info: 9283:MA 3L A版领养卡+MA 5L A版收藏指南+A_1L收缩膜+try me 1L A版贴纸+MA 3L A版地图+MA A版布标+MA 3L polybag/Accessories Bag/Magic sand bag+布标贴 纸+EAN贴纸+警告语贴纸 Remark: 1. 包装不可有PVC，包装上的吸塑需要用PET代替。 2. 产品要求无硼无香 3. 工厂款号 条码 9283 4894680026841 4. 产品信息： 9283:Kitten:Bunny:Puppy:Cow:Elephant:Flamingo=1:1:1:1:1:1; 5.此单有客人客验，请多备料。 6.出货前需寄3-4套大货样给客人签样。 7.客人需要大货样1pcs，请在4/21前寄到深圳办公室Luna签收 | Z2: Rose | AA2: 5.8012 | AB2: =AA2*J2 -> 8701.8 | AD2: 已入 | AE2: =J2 -> 1500 | AH2: =J2 -> 1500 | AJ2: =J2 -> 1500 | AO2: MA布标 | AP2: =J2/6 -> 250 | AQ2: =J2/6 -> 250 | AR2: =J2/6 -> 250 | AS2: =J2/6 -> 250 | AT2: =J2/6 -> 250 | AU2: =J2/6 -> 250 | AW2: =SUM(AP2:AV2) -> 1500 | AX2: =J2-AW2 -> 0
A3: 45090 | B3: TARGET US | C3: 美国 | D3: 4500106533 | F3: 4500106533-30 | G3: 未接单实单 | H3: 9283-S001 | I3: 美人鱼6只装 | J3: 6000 | K3: 0 | L3: 6 | M3: =J3/6 -> 1000 | N3: 45159 | O3: 45211 | P3: 9/12取消 | T3: 欠 | V3: 无 | W3: 8/16收到外箱贴纸 | Y3: 日期码格式：ZURU INC(BVI) 标准格式 日期：按实际生产日期 Packaging Info: 9283: MA +1L Remark: 2. 产品MA 1L包装，客版PDQ. 产品UPC显示193052050328, Integral single ratio=bule/purple/pink/orange =1:1:1:1 3. 外箱正唛左上角位置粘贴条码箱贴纸，每箱只贴一张，由ZURU订购。来料贴纸上显示的客户DPCI# 086-08-4053，UPC显示10193052050325; 6. 产品/包装:MA+1L, UPC显示 193052050014. MA PDQ 7. 外箱正唛左上角位置粘贴条码箱贴纸，每箱只贴一张，由ZURU订购。来料贴纸上显示的客户DPCI#086-08-3096， UPC显示10193052050011 9. 9283-S001-RAINBOCORNS-MERMAIDCORN SURPRISE-SERIES 7 Plush Medium,Bulk,6pcs,No Inner,STD Color Assortment 10. MA 1L包装. 产品UPC显示193052050106,Kitten:Bunny:Puppy:Cow:Elephant:Flamingo=1:1:1:1:1:1; 11. 外箱正唛左上角位置粘贴条码箱贴纸，每箱只贴一张，由ZURU订购。来料贴纸上显示的客户DPCI# 086-08-6431，UPC显示10193052050103; 12. 9283：Semi-products (Large size)，做半成品，只做好毛绒公仔，不入壳 13. 产品和包装上印刷 tracking code信息，格式为ZURU常规格式; 14. 出货方式：货代自提。 | Z3: Holly Zheng | AA3: 5.9464 | AB3: =AA3*J3 -> 35678.4 | AD3: 已入 | AE3: =J3 -> 6000 | AH3: =J3 -> 6000 | AJ3: =J3 -> 6000 | AT3: MA布标 | AU3: =J3/6 -> 1000 | AV3: =J3/6 -> 1000 | AW3: =J3/6 -> 1000 | AX3: =J3/6 -> 1000 | AY3: =J3/6 -> 1000 | AZ3: =J3/6 -> 1000 | BA3: =SUM(AU3:AZ3) -> 6000 | BB3: =J3-BA3 -> 0
A4: 45166 | B4: ZURU | C4: 库有 | D4: MO20230828 | G4: 待定 | H4: 9283-S001 | I4: 美人鱼6只装 | J4: =46116-'9283'!#REF!-'9283'!#REF!-'9283'!#REF!-'9283'!#REF!-'9283'!#REF! -> #REF! | K4: 0 | L4: 6 | M4: =J4/6 -> #REF! | N4: 45196 | O4: 45211 | P4: 9/18取消 | T4: 欠 | V4: 无 | Y4: 请先按数量备料，正式订单会于周三前下 | AF4: =J4 -> #REF! | AK4: =J4 -> #REF! | AN4: =J4 -> #REF! | AY4: MA布标 | AZ4: =J4/6 -> #REF! | BA4: =J4/6 -> #REF! | BB4: =J4/6 -> #REF! | BC4: =J4/6 -> #REF! | BD4: =J4/6 -> #REF! | BE4: =J4/6 -> #REF! | BF4: =SUM(AZ4:BE4) -> #REF! | BG4: =J4-BF4 -> #REF!
A5: 45089 | B5: ZURU | C5: 库有 | D5: MO20230612 | G5: 待定 | H5: 9283-S001 | I5: 美人鱼6只装 | J5: 10000 | K5: 0 | L5: 6 | M5: =J5/L5 -> 1666.6667 | N5: 45230 | O5: 45226 | P5: 手工单暂未实单9/28 | T5: 待确认后订购 | V5: 客版布标贴纸, 客供RFID贴纸 | Y5: 9283 1.包装信息：, MA A 版 1L收缩膜，MA A 版 收藏指南，MA A版 3L贴纸，MA A版 1L贴纸袋，MA A 版 3L泡泡水袋，MA A 版 3L小配件袋，MA A 版 3L魔力沙袋，MA A 版 3L领养卡，MA A 版 3L刮刮卡，MA车缝布标, 客版布标贴纸, 客供RFID贴纸， 2.在外箱印刷带条码的箱唛以及四面印刷RFID的箱唛（新增ZURU黑色色带顶格四面印刷)，不需要贴白色艾利贴纸(由我们提供艾利贴纸替代箱唛），箱唛内容见附件, 外箱侧面任一角落标注"MADE IN CHINA" 字样。 3.产品如有扎带口要剪平，不能刮手。 4.此单需要验货，请自行多备包装物料。 5.此单BULIK PACK出货 配比：Kitten:Bunny:Puppy:Cow:Elephant:Flamingo=1:1:1:1:1:1; | AF5: =J5 -> 10000 | AK5: =J5 -> 10000 | AN5: =J5 -> 10000 | AY5: MA布标 | AZ5: =J5/6 -> 1666.6667 | BA5: =J5/6 -> 1666.6667 | BB5: =J5/6 -> 1666.6667 | BC5: =J5/6 -> 1666.6667 | BD5: =J5/6 -> 1666.6667 | BE5: =J5/6 -> 1666.6667 | BF5: =SUM(AZ5:BE5) -> 10000 | BG5: =J5-BF5 -> 0
A6: 45341 | B6: BIG W | C6: 澳大利亚 | D6: 4500124253 | E6: 47672839 FRE | F6: 4500124253-30 | G6: 9283-S001 | H6: 美人鱼6只装 | I6: 480 | J6: 0 | K6: 6 | L6: 80 | M6: 45376 | N6: 改到4500125363 | O6: 转PO | R6: 2/2收到 | U6: 进口商贴纸翻单4500106537 | W6: 日期码一致，为250324 | X6: 日期码格式：250324 日期： Packaging Info: 1.包装(MA UPC 包装,1L 3L都可接受） 9283:MA UPC PKG+1张进口商贴纸，贴纸翻单4500106537 2.产品和产品包装上的日期码一致，为250324 (dd/mm/yy；进口商贴纸上已经去掉日期码，请按要求在包装上打日期码， 进口商贴纸不覆盖日期码） Remark: 1.共出4港口， 不同港口数量信息请见订单行项目，并请参考箱唛资料，港口不同，箱唛资料也不同； 2.箱唛不可出现任何手写内容，重量与实际一致且不可手写 3. 此单出澳大利亚，请按澳洲标准生产并满足当地法规要求 4.比例： 9283：Kitten:Bunny:Puppy:Cow:Elephant:Flamingo=1:1:1:1:1:1; | Y6: Lillian Li | Z6: 5.9155 | AA6: 2839.44 | AD6: 480 | AI6: 480 | AL6: 480 | AR6: MA布标 | AZ6: 80 | BA6: 80 | BB6: 80 | BC6: 80 | BD6: 80 | BE6: 80 | BF6: 480 | BG6: 0
A7: 45412 | B7: WAL-MART STORES INC. USA | C7: 美国 | D7: 4500132388 | E7: 0831529356 | F7: 4500132388-30 | G7: 9283SLB-S002 | H7: 9283SLB-S002 | I7: 美人鱼卡板装（无闪粉） | J7: 2052 | K7: 0 | L7: 108 | M7: =J7/L7 -> 19 | N7: 45448 | O7: 45474 | P7: 6/3取消订单 | R7: 滞留客供RFID贴纸 | T7: 在外箱印刷带条码的箱唛以及四面印刷RFID的箱唛（ZURU新logo右下角四面印刷)，外箱侧面任一角落标注"MADE IN CHINA" 字样。 | V7: 客版布标贴纸 | W7: 5/16 收到客供RFID贴纸 | Y7: 日期码格式：ZURU DGYYYYMMDD CHINA(日期避开周末和法定节假日即可） 日期：按实际生产日期 Packaging Info: Remark: 9283SLB 1.包装信息：, MA A 版 1L收缩膜，MA A 版 收藏指南，MA A版 3L贴纸，MA A版 1L贴纸袋，MA A 版 3L泡泡水袋，MA A 版 3L小配件袋，MA A 版 3L魔力沙袋，M A A 版 3L领养卡，MA A 版 3L刮刮卡，MA车缝布标, 客版布标贴纸, 客供RFID贴纸， 2.2.在外箱印刷带条码的箱唛以及四面印刷RFID的箱唛（ZURU新logo右下角四面印刷)，不需要贴白色艾利贴纸(由我们提供艾利贴纸替代箱唛），箱唛内容见附件, 外箱侧面任一角落标注"MADE IN CHINA" 字样。每个slip sheet上面贴一张艾利贴纸和一张普通贴纸（可A4纸打印），slip sheet打印的普通贴纸的尺寸不能比艾 利贴纸小 3.产品如有扎带口要剪平，不能刮手。 4.此单需要验货，请自行多备包装物料。 5.此单打卡板出货 配比：Kitten:Bunny:Puppy:Cow:Elephant:Flamingo=1:1:1:1:1:1; | Z7: Estate Chen | AA7: 647.4909 | AB7: =M7*AA7 -> 12302.327 | AD7: 已入 | AG7: =J7 -> 2052 | AN7: =J7 -> 2052 | AR7: =J7 -> 2052 | AW7: =J7 -> 2052 | BF7: MA布标新日期格式 | BG7: =J7 -> 2052 | BH7: =J7/6 -> 342 | BI7: =J7/6 -> 342 | BJ7: =J7/6 -> 342 | BK7: =J7/6 -> 342 | BL7: =J7/6 -> 342 | BM7: =J7/6 -> 342 | BT7: =SUM(BH7:BS7) -> 2052 | BU7: =J7-BT7 -> 0
A8: 45412 | B8: WAL-MART STORES INC. USA | C8: 美国 | D8: 4500132388 | E8: 0831529368 | F8: 4500132388-50 | G8: 9283SLB-S002 | H8: 9283SLB-S002 | I8: 美人鱼卡板装（无闪粉） | J8: 3780 | K8: 0 | L8: 108 | M8: =J8/L8 -> 35 | N8: 45448 | O8: 45474 | P8: 6/3取消订单 | R8: 滞留客供RFID贴纸 | T8: 在外箱印刷带条码的箱唛以及四面印刷RFID的箱唛（ZURU新logo右下角四面印刷)，外箱侧面任一角落标注"MADE IN CHINA" 字样。 | V8: 客版布标贴纸 | W8: 5/16 收到客供RFID贴纸 | Y8: 日期码格式：ZURU DGYYYYMMDD CHINA(日期避开周末和法定节假日即可） 日期：按实际生产日期 Packaging Info: Remark: 9283SLB 1.包装信息：, MA A 版 1L收缩膜，MA A 版 收藏指南，MA A版 3L贴纸，MA A版 1L贴纸袋，MA A 版 3L泡泡水袋，MA A 版 3L小配件袋，MA A 版 3L魔力沙袋，M A A 版 3L领养卡，MA A 版 3L刮刮卡，MA车缝布标, 客版布标贴纸, 客供RFID贴纸， 2.2.在外箱印刷带条码的箱唛以及四面印刷RFID的箱唛（ZURU新logo右下角四面印刷)，不需要贴白色艾利贴纸(由我们提供艾利贴纸替代箱唛），箱唛内容见附件, 外箱侧面任一角落标注"MADE IN CHINA" 字样。每个slip sheet上面贴一张艾利贴纸和一张普通贴纸（可A4纸打印），slip sheet打印的普通贴纸的尺寸不能比艾 利贴纸小 3.产品如有扎带口要剪平，不能刮手。 4.此单需要验货，请自行多备包装物料。 5.此单打卡板出货 配比：Kitten:Bunny:Puppy:Cow:Elephant:Flamingo=1:1:1:1:1:1; | Z8: Estate Chen | AA8: 647.4909 | AB8: =M8*AA8 -> 22662.181 | AD8: 已入 | AG8: =J8 -> 3780 | AN8: =J8 -> 3780 | AR8: =J8 -> 3780 | AW8: =J8 -> 3780 | BF8: MA布标新日期格式 | BG8: =J8 -> 3780 | BH8: =J8/6 -> 630 | BI8: =J8/6 -> 630 | BJ8: =J8/6 -> 630 | BK8: =J8/6 -> 630 | BL8: =J8/6 -> 630 | BM8: =J8/6 -> 630 | BT8: =SUM(BH8:BS8) -> 3780 | BU8: =J8-BT8 -> 0
A9: 45418 | B9: WAL-MART STORES INC. USA | C9: 美国 | D9: 4500132486 | E9: 0833375370 | F9: 4500132486-70 | G9: 9283SLB-S002 | H9: 9283SLB-S002 | I9: 美人鱼卡板装（无闪粉） | J9: 972 | K9: 0 | L9: 108 | M9: =J9/L9 -> 9 | N9: 45455 | O9: 45474 | P9: 6/3取消订单 | R9: 滞留客供RFID贴纸 | T9: 在外箱印刷带条码的箱唛以及四面印刷RFID的箱唛（ZURU新logo右下角四面印刷)，外箱侧面任一角落标注"MADE IN CHINA" 字样。 | V9: 客版布标贴纸 | W9: 5/16 收到客供RFID贴纸 | Y9: 日期码格式：ZURU DGYYYYMMDD CHINA(日期避开周末和法定节假日即可） 日期：按实际生产日期 Packaging Info: Remark: 9283SLB 1.包装信息：, MA A 版 1L收缩膜，MA A 版 收藏指南，MA A版 3L贴纸，MA A版 1L贴纸袋，MA A 版 3L泡泡水袋，MA A 版 3L小配件袋，MA A 版 3L魔力沙袋，M A A 版 3L领养卡，MA A 版 3L刮刮卡，MA车缝布标, 客版布标贴纸, 客供RFID贴纸， 2.在外箱印刷带条码的箱唛以及四面印刷RFID的箱唛（新增ZURU黑色色带顶格四面印刷)，不需要贴白色艾利贴纸(由我们提供艾利贴纸替代箱唛），箱唛内容见附件 , 外箱侧面任一角落标注"MADE IN CHINA" 字样。每个slip sheet上面贴一张艾利贴纸和一张普通贴纸（可A4纸打印），slip sheet打印的普通贴纸的尺寸不能比艾 利贴纸小。 3.产品如有扎带口要剪平，不能刮手。 4.此单需要验货，请自行多备包装物料。 5.此单打卡板出货 配比：Kitten:Bunny:Puppy:Cow:Elephant:Flamingo=1:1:1:1:1:1; Order | Z9: Effy Li | AA9: 653.0097 | AB9: =M9*AA9 -> 5877.0873 | AD9: 已入 | AG9: =J9 -> 972 | AN9: =J9 -> 972 | AR9: =J9 -> 972 | AW9: =J9 -> 972 | BF9: MA布标新日期格式 | BG9: =J9 -> 972 | BH9: =J9/6 -> 162 | BI9: =J9/6 -> 162 | BJ9: =J9/6 -> 162 | BK9: =J9/6 -> 162 | BL9: =J9/6 -> 162 | BM9: =J9/6 -> 162 | BT9: =SUM(BH9:BS9) -> 972 | BU9: =J9-BT9 -> 0
A10: 45412 | B10: WAL-MART STORES INC. USA | C10: 美国 | D10: 4500132388 | E10: 0831529353 | F10: 4500132388-10 | G10: 9283SLB-S002 | H10: 9283SLB-S002 | I10: 美人鱼卡板装（无闪粉） | J10: 10152 | K10: 0 | L10: 108 | M10: =J10/L10 -> 94 | N10: 45456 | O10: 45474 | P10: 6/3取消订单 | R10: 滞留客供RFID贴纸 | T10: 在外箱印刷带条码的箱唛以及四面印刷RFID的箱唛（ZURU新logo右下角四面印刷)，外箱侧面任一角落标注"MADE IN CHINA" 字样。 | V10: 客版布标贴纸 | W10: 5/16 收到客供RFID贴纸 | Y10: 日期码格式：ZURU DGYYYYMMDD CHINA(日期避开周末和法定节假日即可） 日期：按实际生产日期 Packaging Info: Remark: 9283SLB 1.包装信息：, MA A 版 1L收缩膜，MA A 版 收藏指南，MA A版 3L贴纸，MA A版 1L贴纸袋，MA A 版 3L泡泡水袋，MA A 版 3L小配件袋，MA A 版 3L魔力沙袋，M A A 版 3L领养卡，MA A 版 3L刮刮卡，MA车缝布标, 客版布标贴纸, 客供RFID贴纸， 2.2.在外箱印刷带条码的箱唛以及四面印刷RFID的箱唛（ZURU新logo右下角四面印刷)，不需要贴白色艾利贴纸(由我们提供艾利贴纸替代箱唛），箱唛内容见附件, 外箱侧面任一角落标注"MADE IN CHINA" 字样。每个slip sheet上面贴一张艾利贴纸和一张普通贴纸（可A4纸打印），slip sheet打印的普通贴纸的尺寸不能比艾 利贴纸小 3.产品如有扎带口要剪平，不能刮手。 4.此单需要验货，请自行多备包装物料。 5.此单打卡板出货 配比：Kitten:Bunny:Puppy:Cow:Elephant:Flamingo=1:1:1:1:1:1; | Z10: Estate Chen | AA10: 647.4909 | AB10: =M10*AA10 -> 60864.145 | AD10: 已入 | AG10: =J10 -> 10152 | AN10: =J10 -> 10152 | AR10: =J10 -> 10152 | AW10: =J10 -> 10152 | BF10: MA布标新日期格式 | BG10: =J10 -> 10152 | BH10: =J10/6 -> 1692 | BI10: =J10/6 -> 1692 | BJ10: =J10/6 -> 1692 | BK10: =J10/6 -> 1692 | BL10: =J10/6 -> 1692 | BM10: =J10/6 -> 1692 | BT10: =SUM(BH10:BS10) -> 10152 | BU10: =J10-BT10 -> 0
A11: 45412 | B11: WAL-MART STORES INC. USA | C11: 美国 | D11: 4500132388 | E11: 0831529355 | F11: 4500132388-20 | G11: 9283SLB-S002 | H11: 9283SLB-S002 | I11: 美人鱼卡板装（无闪粉） | J11: 5940 | K11: 0 | L11: 108 | M11: =J11/L11 -> 55 | N11: 45456 | O11: 45474 | P11: 6/3取消订单 | R11: 滞留客供RFID贴纸 | T11: 在外箱印刷带条码的箱唛以及四面印刷RFID的箱唛（ZURU新logo右下角四面印刷)，外箱侧面任一角落标注"MADE IN CHINA" 字样。 | V11: 客版布标贴纸 | W11: 5/16 收到客供RFID贴纸 | Y11: 日期码格式：ZURU DGYYYYMMDD CHINA(日期避开周末和法定节假日即可） 日期：按实际生产日期 Packaging Info: Remark: 9283SLB 1.包装信息：, MA A 版 1L收缩膜，MA A 版 收藏指南，MA A版 3L贴纸，MA A版 1L贴纸袋，MA A 版 3L泡泡水袋，MA A 版 3L小配件袋，MA A 版 3L魔力沙袋，M A A 版 3L领养卡，MA A 版 3L刮刮卡，MA车缝布标, 客版布标贴纸, 客供RFID贴纸， 2.2.在外箱印刷带条码的箱唛以及四面印刷RFID的箱唛（ZURU新logo右下角四面印刷)，不需要贴白色艾利贴纸(由我们提供艾利贴纸替代箱唛），箱唛内容见附件, 外箱侧面任一角落标注"MADE IN CHINA" 字样。每个slip sheet上面贴一张艾利贴纸和一张普通贴纸（可A4纸打印），slip sheet打印的普通贴纸的尺寸不能比艾 利贴纸小 3.产品如有扎带口要剪平，不能刮手。 4.此单需要验货，请自行多备包装物料。 5.此单打卡板出货 配比：Kitten:Bunny:Puppy:Cow:Elephant:Flamingo=1:1:1:1:1:1; | Z11: Estate Chen | AA11: 647.4909 | AB11: =M11*AA11 -> 35611.999 | AD11: 已入 | AG11: =J11 -> 5940 | AN11: =J11 -> 5940 | AR11: =J11 -> 5940 | AW11: =J11 -> 5940 | BF11: MA布标新日期格式 | BG11: =J11 -> 5940 | BH11: =J11/6 -> 990 | BI11: =J11/6 -> 990 | BJ11: =J11/6 -> 990 | BK11: =J11/6 -> 990 | BL11: =J11/6 -> 990 | BM11: =J11/6 -> 990 | BT11: =SUM(BH11:BS11) -> 5940 | BU11: =J11-BT11 -> 0
A12: 45412 | B12: WAL-MART STORES INC. USA | C12: 美国 | D12: 4500132388 | E12: 0831529357 | F12: 4500132388-40 | G12: 9283SLB-S002 | H12: 9283SLB-S002 | I12: 美人鱼卡板装（无闪粉） | J12: 4428 | K12: 0 | L12: 108 | M12: =J12/L12 -> 41 | N12: 45456 | O12: 45474 | P12: 6/3取消订单 | R12: 滞留客供RFID贴纸 | T12: 在外箱印刷带条码的箱唛以及四面印刷RFID的箱唛（ZURU新logo右下角四面印刷)，外箱侧面任一角落标注"MADE IN CHINA" 字样。 | V12: 客版布标贴纸 | W12: 5/16 收到客供RFID贴纸 | Y12: 日期码格式：ZURU DGYYYYMMDD CHINA(日期避开周末和法定节假日即可） 日期：按实际生产日期 Packaging Info: Remark: 9283SLB 1.包装信息：, MA A 版 1L收缩膜，MA A 版 收藏指南，MA A版 3L贴纸，MA A版 1L贴纸袋，MA A 版 3L泡泡水袋，MA A 版 3L小配件袋，MA A 版 3L魔力沙袋，M A A 版 3L领养卡，MA A 版 3L刮刮卡，MA车缝布标, 客版布标贴纸, 客供RFID贴纸， 2.2.在外箱印刷带条码的箱唛以及四面印刷RFID的箱唛（ZURU新logo右下角四面印刷)，不需要贴白色艾利贴纸(由我们提供艾利贴纸替代箱唛），箱唛内容见附件, 外箱侧面任一角落标注"MADE IN CHINA" 字样。每个slip sheet上面贴一张艾利贴纸和一张普通贴纸（可A4纸打印），slip sheet打印的普通贴纸的尺寸不能比艾 利贴纸小 3.产品如有扎带口要剪平，不能刮手。 4.此单需要验货，请自行多备包装物料。 5.此单打卡板出货 配比：Kitten:Bunny:Puppy:Cow:Elephant:Flamingo=1:1:1:1:1:1; | Z12: Estate Chen | AA12: 647.4909 | AB12: =M12*AA12 -> 26547.127 | AD12: 已入 | AG12: =J12 -> 4428 | AN12: =J12 -> 4428 | AR12: =J12 -> 4428 | AW12: =J12 -> 4428 | BF12: MA布标新日期格式 | BG12: =J12 -> 4428 | BH12: =J12/6 -> 738 | BI12: =J12/6 -> 738 | BJ12: =J12/6 -> 738 | BK12: =J12/6 -> 738 | BL12: =J12/6 -> 738 | BM12: =J12/6 -> 738 | BT12: =SUM(BH12:BS12) -> 4428 | BU12: =J12-BT12 -> 0
A13: 45412 | B13: WAL-MART STORES INC. USA | C13: 美国 | D13: 4500132388 | E13: 0831529371 | F13: 4500132388-60 | G13: 9283SLB-S002 | H13: 9283SLB-S002 | I13: 美人鱼卡板装（无闪粉） | J13: 4752 | K13: 0 | L13: 108 | M13: =J13/L13 -> 44 | N13: 45456 | O13: 45474 | P13: 6/3取消订单 | R13: 滞留客供RFID贴纸 | T13: 在外箱印刷带条码的箱唛以及四面印刷RFID的箱唛（ZURU新logo右下角四面印刷)，外箱侧面任一角落标注"MADE IN CHINA" 字样。 | V13: 客版布标贴纸 | W13: 5/16 收到客供RFID贴纸 | Y13: 日期码格式：ZURU DGYYYYMMDD CHINA(日期避开周末和法定节假日即可） 日期：按实际生产日期 Packaging Info: Remark: 9283SLB 1.包装信息：, MA A 版 1L收缩膜，MA A 版 收藏指南，MA A版 3L贴纸，MA A版 1L贴纸袋，MA A 版 3L泡泡水袋，MA A 版 3L小配件袋，MA A 版 3L魔力沙袋，M A A 版 3L领养卡，MA A 版 3L刮刮卡，MA车缝布标, 客版布标贴纸, 客供RFID贴纸， 2.2.在外箱印刷带条码的箱唛以及四面印刷RFID的箱唛（ZURU新logo右下角四面印刷)，不需要贴白色艾利贴纸(由我们提供艾利贴纸替代箱唛），箱唛内容见附件, 外箱侧面任一角落标注"MADE IN CHINA" 字样。每个slip sheet上面贴一张艾利贴纸和一张普通贴纸（可A4纸打印），slip sheet打印的普通贴纸的尺寸不能比艾 利贴纸小 3.产品如有扎带口要剪平，不能刮手。 4.此单需要验货，请自行多备包装物料。 5.此单打卡板出货 配比：Kitten:Bunny:Puppy:Cow:Elephant:Flamingo=1:1:1:1:1:1; | Z13: Estate Chen | AA13: 647.4909 | AB13: =M13*AA13 -> 28489.6 | AD13: 已入 | AG13: =J13 -> 4752 | AN13: =J13 -> 4752 | AR13: =J13 -> 4752 | AW13: =J13 -> 4752 | BF13: MA布标新日期格式 | BG13: =J13 -> 4752 | BH13: =J13/6 -> 792 | BI13: =J13/6 -> 792 | BJ13: =J13/6 -> 792 | BK13: =J13/6 -> 792 | BL13: =J13/6 -> 792 | BM13: =J13/6 -> 792 | BT13: =SUM(BH13:BS13) -> 4752 | BU13: =J13-BT13 -> 0
A14: 45418 | B14: WAL-MART STORES INC. USA | C14: 美国 | D14: 4500132486 | E14: 0833375350 | F14: 4500132486-40 | G14: 9283SLB-S002 | H14: 9283SLB-S002 | I14: 美人鱼卡板装（无闪粉） | J14: 864 | K14: 0 | L14: 108 | M14: =J14/L14 -> 8 | N14: 45457 | O14: 45474 | P14: 6/3取消订单 | R14: 无 | T14: 在外箱印刷带条码的箱唛以及四面印刷RFID的箱唛（ZURU新logo右下角四面印刷)，外箱侧面任一角落标注"MADE IN CHINA" 字样。 | V14: 客版布标贴纸 | W14: 5/16收到客供RFID贴纸 | Y14: 日期码格式：ZURU DGYYYYMMDD CHINA(日期避开周末和法定节假日即可） 日期：按实际生产日期 Packaging Info: Remark: 9283SLB 1.包装信息：, MA A 版 1L收缩膜，MA A 版 收藏指南，MA A版 3L贴纸，MA A版 1L贴纸袋，MA A 版 3L泡泡水袋，MA A 版 3L小配件袋，MA A 版 3L魔力沙袋，M A A 版 3L领养卡，MA A 版 3L刮刮卡，MA车缝布标, 客版布标贴纸, 客供RFID贴纸， 2.在外箱印刷带条码的箱唛以及四面印刷RFID的箱唛（新增ZURU黑色色带顶格四面印刷)，不需要贴白色艾利贴纸(由我们提供艾利贴纸替代箱唛），箱唛内容见附件 , 外箱侧面任一角落标注"MADE IN CHINA" 字样。每个slip sheet上面贴一张艾利贴纸和一张普通贴纸（可A4纸打印），slip sheet打印的普通贴纸的尺寸不能比艾 利贴纸小。 3.产品如有扎带口要剪平，不能刮手。 4.此单需要验货，请自行多备包装物料。 5.此单打卡板出货 配比：Kitten:Bunny:Puppy:Cow:Elephant:Flamingo=1:1:1:1:1:1; Order | Z14: Effy Li | AA14: 653.0097 | AB14: =M14*AA14 -> 5224.0776 | AD14: 已入 | AG14: =J14 -> 864 | AN14: =J14 -> 864 | AR14: =J14 -> 864 | AW14: =J14 -> 864 | BF14: MA布标新日期格式 | BG14: =J14 -> 864 | BH14: =J14/6 -> 144 | BI14: =J14/6 -> 144 | BJ14: =J14/6 -> 144 | BK14: =J14/6 -> 144 | BL14: =J14/6 -> 144 | BM14: =J14/6 -> 144 | BT14: =SUM(BH14:BS14) -> 864 | BU14: =J14-BT14 -> 0
A15: 45418 | B15: WAL-MART STORES INC. USA | C15: 美国 | D15: 4500132486 | E15: 0833375351 | F15: 4500132486-50 | G15: 9283SLB-S002 | H15: 9283SLB-S002 | I15: 美人鱼卡板装（无闪粉） | J15: 1404 | K15: 0 | L15: 108 | M15: =J15/L15 -> 13 | N15: 45462 | O15: 45474 | P15: 6/3取消订单 | R15: 无 | T15: 在外箱印刷带条码的箱唛以及四面印刷RFID的箱唛（ZURU新logo右下角四面印刷)，外箱侧面任一角落标注"MADE IN CHINA" 字样。 | V15: 客版布标贴纸 | W15: 欠客供RFID贴纸 | Y15: 日期码格式：ZURU DGYYYYMMDD CHINA(日期避开周末和法定节假日即可） 日期：按实际生产日期 Packaging Info: Remark: 9283SLB 1.包装信息：, MA A 版 1L收缩膜，MA A 版 收藏指南，MA A版 3L贴纸，MA A版 1L贴纸袋，MA A 版 3L泡泡水袋，MA A 版 3L小配件袋，MA A 版 3L魔力沙袋，M A A 版 3L领养卡，MA A 版 3L刮刮卡，MA车缝布标, 客版布标贴纸, 客供RFID贴纸， 2.在外箱印刷带条码的箱唛以及四面印刷RFID的箱唛（新增ZURU黑色色带顶格四面印刷)，不需要贴白色艾利贴纸(由我们提供艾利贴纸替代箱唛），箱唛内容见附件 , 外箱侧面任一角落标注"MADE IN CHINA" 字样。每个slip sheet上面贴一张艾利贴纸和一张普通贴纸（可A4纸打印），slip sheet打印的普通贴纸的尺寸不能比艾 利贴纸小。 3.产品如有扎带口要剪平，不能刮手。 4.此单需要验货，请自行多备包装物料。 5.此单打卡板出货 配比：Kitten:Bunny:Puppy:Cow:Elephant:Flamingo=1:1:1:1:1:1; Order | Z15: Effy Li | AA15: 652.1889 | AB15: =M15*AA15 -> 8478.4557 | AD15: 已入 | AG15: =J15 -> 1404 | AN15: =J15 -> 1404 | AR15: =J15 -> 1404 | AW15: =J15 -> 1404 | BF15: MA布标新日期格式 | BG15: =J15 -> 1404 | BH15: =J15/6 -> 234 | BI15: =J15/6 -> 234 | BJ15: =J15/6 -> 234 | BK15: =J15/6 -> 234 | BL15: =J15/6 -> 234 | BM15: =J15/6 -> 234 | BT15: =SUM(BH15:BS15) -> 1404 | BU15: =J15-BT15 -> 0
A16: 45418 | B16: WAL-MART STORES INC. USA | C16: 美国 | D16: 4500132486 | E16: 0833375457 | F16: 4500132486-120 | G16: 9283SLB-S002 | H16: 9283SLB-S002 | I16: 美人鱼卡板装（无闪粉） | J16: 1080 | K16: 0 | L16: 108 | M16: =J16/L16 -> 10 | N16: 45462 | O16: 45474 | P16: 6/3取消订单 | R16: 无 | T16: 在外箱印刷带条码的箱唛以及四面印刷RFID的箱唛（ZURU新logo右下角四面印刷)，外箱侧面任一角落标注"MADE IN CHINA" 字样。 | V16: 客版布标贴纸 | W16: 欠客供RFID贴纸 | Y16: 日期码格式：ZURU DGYYYYMMDD CHINA(日期避开周末和法定节假日即可） 日期：按实际生产日期 Packaging Info: Remark: 9283SLB 1.包装信息：, MA A 版 1L收缩膜，MA A 版 收藏指南，MA A版 3L贴纸，MA A版 1L贴纸袋，MA A 版 3L泡泡水袋，MA A 版 3L小配件袋，MA A 版 3L魔力沙袋，M A A 版 3L领养卡，MA A 版 3L刮刮卡，MA车缝布标, 客版布标贴纸, 客供RFID贴纸， 2.在外箱印刷带条码的箱唛以及四面印刷RFID的箱唛（新增ZURU黑色色带顶格四面印刷)，不需要贴白色艾利贴纸(由我们提供艾利贴纸替代箱唛），箱唛内容见附件 , 外箱侧面任一角落标注"MADE IN CHINA" 字样。每个slip sheet上面贴一张艾利贴纸和一张普通贴纸（可A4纸打印），slip sheet打印的普通贴纸的尺寸不能比艾 利贴纸小。 3.产品如有扎带口要剪平，不能刮手。 4.此单需要验货，请自行多备包装物料。 5.此单打卡板出货 配比：Kitten:Bunny:Puppy:Cow:Elephant:Flamingo=1:1:1:1:1:1; Order | Z16: Effy Li | AA16: 652.1889 | AB16: =M16*AA16 -> 6521.889 | AD16: 已入 | AG16: =J16 -> 1080 | AN16: =J16 -> 1080 | AR16: =J16 -> 1080 | AW16: =J16 -> 1080 | BF16: MA布标新日期格式 | BG16: =J16 -> 1080 | BH16: =J16/6 -> 180 | BI16: =J16/6 -> 180 | BJ16: =J16/6 -> 180 | BK16: =J16/6 -> 180 | BL16: =J16/6 -> 180 | BM16: =J16/6 -> 180 | BT16: =SUM(BH16:BS16) -> 1080 | BU16: =J16-BT16 -> 0
A17: 45418 | B17: WAL-MART STORES INC. USA | C17: 美国 | D17: 4500132486 | E17: 0833375373 | F17: 4500132486-80 | G17: 9283SLB-S002 | H17: 9283SLB-S002 | I17: 美人鱼卡板装（无闪粉） | J17: 1728 | K17: 0 | L17: 108 | M17: =J17/L17 -> 16 | N17: 45464 | O17: 45474 | P17: 6/3取消订单 | R17: 无 | T17: 在外箱印刷带条码的箱唛以及四面印刷RFID的箱唛（ZURU新logo右下角四面印刷)，外箱侧面任一角落标注"MADE IN CHINA" 字样。 | V17: 客版布标贴纸 | W17: 欠客供RFID贴纸 | Y17: 日期码格式：ZURU DGYYYYMMDD CHINA(日期避开周末和法定节假日即可） 日期：按实际生产日期 Packaging Info: Remark: 9283SLB 1.包装信息：, MA A 版 1L收缩膜，MA A 版 收藏指南，MA A版 3L贴纸，MA A版 1L贴纸袋，MA A 版 3L泡泡水袋，MA A 版 3L小配件袋，MA A 版 3L魔力沙袋，M A A 版 3L领养卡，MA A 版 3L刮刮卡，MA车缝布标, 客版布标贴纸, 客供RFID贴纸， 2.在外箱印刷带条码的箱唛以及四面印刷RFID的箱唛（新增ZURU黑色色带顶格四面印刷)，不需要贴白色艾利贴纸(由我们提供艾利贴纸替代箱唛），箱唛内容见附件 , 外箱侧面任一角落标注"MADE IN CHINA" 字样。每个slip sheet上面贴一张艾利贴纸和一张普通贴纸（可A4纸打印），slip sheet打印的普通贴纸的尺寸不能比艾 利贴纸小。 3.产品如有扎带口要剪平，不能刮手。 4.此单需要验货，请自行多备包装物料。 5.此单打卡板出货 配比：Kitten:Bunny:Puppy:Cow:Elephant:Flamingo=1:1:1:1:1:1; Order | Z17: Effy Li | AA17: 652.1889 | AB17: =M17*AA17 -> 10435.022 | AD17: 已入 | AG17: =J17 -> 1728 | AN17: =J17 -> 1728 | AR17: =J17 -> 1728 | AW17: =J17 -> 1728 | BF17: MA布标新日期格式 | BG17: =J17 -> 1728 | BH17: =J17/6 -> 288 | BI17: =J17/6 -> 288 | BJ17: =J17/6 -> 288 | BK17: =J17/6 -> 288 | BL17: =J17/6 -> 288 | BM17: =J17/6 -> 288 | BT17: =SUM(BH17:BS17) -> 1728 | BU17: =J17-BT17 -> 0
A18: 45418 | B18: WAL-MART STORES INC. USA | C18: 美国 | D18: 4500132486 | E18: 0833375439 | F18: 4500132486-110 | G18: 9283SLB-S002 | H18: 9283SLB-S002 | I18: 美人鱼卡板装（无闪粉） | J18: 864 | K18: 0 | L18: 108 | M18: =J18/L18 -> 8 | N18: 45464 | O18: 45474 | P18: 6/3取消订单 | R18: 无 | T18: 在外箱印刷带条码的箱唛以及四面印刷RFID的箱唛（ZURU新logo右下角四面印刷)，外箱侧面任一角落标注"MADE IN CHINA" 字样。 | V18: 客版布标贴纸 | W18: 欠客供RFID贴纸 | Y18: 日期码格式：ZURU DGYYYYMMDD CHINA(日期避开周末和法定节假日即可） 日期：按实际生产日期 Packaging Info: Remark: 9283SLB 1.包装信息：, MA A 版 1L收缩膜，MA A 版 收藏指南，MA A版 3L贴纸，MA A版 1L贴纸袋，MA A 版 3L泡泡水袋，MA A 版 3L小配件袋，MA A 版 3L魔力沙袋，M A A 版 3L领养卡，MA A 版 3L刮刮卡，MA车缝布标, 客版布标贴纸, 客供RFID贴纸， 2.在外箱印刷带条码的箱唛以及四面印刷RFID的箱唛（新增ZURU黑色色带顶格四面印刷)，不需要贴白色艾利贴纸(由我们提供艾利贴纸替代箱唛），箱唛内容见附件 , 外箱侧面任一角落标注"MADE IN CHINA" 字样。每个slip sheet上面贴一张艾利贴纸和一张普通贴纸（可A4纸打印），slip sheet打印的普通贴纸的尺寸不能比艾 利贴纸小。 3.产品如有扎带口要剪平，不能刮手。 4.此单需要验货，请自行多备包装物料。 5.此单打卡板出货 配比：Kitten:Bunny:Puppy:Cow:Elephant:Flamingo=1:1:1:1:1:1; Order | Z18: Effy Li | AA18: 653.0097 | AB18: =M18*AA18 -> 5224.0776 | AD18: 已入 | AG18: =J18 -> 864 | AN18: =J18 -> 864 | AR18: =J18 -> 864 | AW18: =J18 -> 864 | BF18: MA布标新日期格式 | BG18: =J18 -> 864 | BH18: =J18/6 -> 144 | BI18: =J18/6 -> 144 | BJ18: =J18/6 -> 144 | BK18: =J18/6 -> 144 | BL18: =J18/6 -> 144 | BM18: =J18/6 -> 144 | BT18: =SUM(BH18:BS18) -> 864 | BU18: =J18-BT18 -> 0
... A25: 45418 | B25: WAL-MART STORES INC. USA | C25: 美国 | D25: 4500132486 | E25: 0833375408 | F25: 4500132486-100 | G25: 9283SLB-S002 | H25: 9283SLB-S002 | I25: 美人鱼卡板装（无闪粉） | J25: 1512 | K25: 0 | L25: 108 | M25: =J25/L25 -> 14 | N25: 45471 | O25: 45474 | P25: 6/3取消订单 | R25: 无 | T25: 在外箱印刷带条码的箱唛以及四面印刷RFID的箱唛（ZURU新logo右下角四面印刷)，外箱侧面任一角落标注"MADE IN CHINA" 字样。 | V25: 客版布标贴纸 | W25: 欠客供RFID贴纸 | Y25: 日期码格式：ZURU DGYYYYMMDD CHINA(日期避开周末和法定节假日即可） 日期：按实际生产日期 Packaging Info: Remark: 9283SLB 1.包装信息：, MA A 版 1L收缩膜，MA A 版 收藏指南，MA A版 3L贴纸，MA A版 1L贴纸袋，MA A 版 3L泡泡水袋，MA A 版 3L小配件袋，MA A 版 3L魔力沙袋，M A A 版 3L领养卡，MA A 版 3L刮刮卡，MA车缝布标, 客版布标贴纸, 客供RFID贴纸， 2.在外箱印刷带条码的箱唛以及四面印刷RFID的箱唛（新增ZURU黑色色带顶格四面印刷)，不需要贴白色艾利贴纸(由我们提供艾利贴纸替代箱唛），箱唛内容见附件 , 外箱侧面任一角落标注"MADE IN CHINA" 字样。每个slip sheet上面贴一张艾利贴纸和一张普通贴纸（可A4纸打印），slip sheet打印的普通贴纸的尺寸不能比艾 利贴纸小。 3.产品如有扎带口要剪平，不能刮手。 4.此单需要验货，请自行多备包装物料。 5.此单打卡板出货 配比：Kitten:Bunny:Puppy:Cow:Elephant:Flamingo=1:1:1:1:1:1; Order | Z25: Effy Li | AA25: 652.1889 | AB25: =M25*AA25 -> 9130.6446 | AD25: 已入 | AG25: =J25 -> 1512 | AN25: =J25 -> 1512 | AR25: =J25 -> 1512 | AW25: =J25 -> 1512 | BF25: MA布标新日期格式 | BG25: =J25 -> 1512 | BH25: =J25/6 -> 252 | BI25: =J25/6 -> 252 | BJ25: =J25/6 -> 252 | BK25: =J25/6 -> 252 | BL25: =J25/6 -> 252 | BM25: =J25/6 -> 252 | BT25: =SUM(BH25:BS25) -> 1512 | BU25: =J25-BT25 -> 0
A26: 45427 | B26: KMART AUSTRALIA LTD(NEW ZEALAND) | C26: 新西兰 | D26: 4500133663 | E26: 20091071 | F26: 4500133663-70 | G26: 9283-S001 | H26: 9283-S001 | I26: 美人鱼6只装 | J26: 126 | K26: 0 | L26: 6 | M26: =J26/L26 -> 21 | N26: 45471 | O26: 45467 | P26: 6/24取消订单 | T26: 5/15收到 | V26: 6/7收到防盗贴纸+5/14收到外箱贴纸 | Y26: 日期码格式：ZURU INC(BVI) 标准格式 日期：按实际生产日期 Packaging Info: 7.9283: MA英语UPC版本包装（收缩膜和说明书, MA首选1L，如无1L可用多语且含英语的配套多语包装) + 1张防盗贴纸 (贴纸以及位置图翻单PO#4500095104）+ 箱 唛 + 外箱SSCC Label Remark: 1.请务必按时完货，验货。并且按期送货入货代指定仓库，如果晚了导致船期Delay将会有罚金产生或者客户要求空运，所产生的罚金和空运费由工厂承担。 2.SSCC 外箱贴纸请同纸箱瓦楞纸方向（竖纹向）垂直，即外箱贴纸横着贴(注意条码不要被胶带粘住），贴1pc，贴1面正唛，封箱胶纸不能挡住贴纸内容。外箱贴纸 离外箱边距离不少于2cm。 3.外箱材质为ZURU标准； 4.此单需使用KMART封箱胶上下工字型封箱;从2019年6月开始，要用KMART 新版封箱胶带，此单要用"ANKO"封箱胶带 5.此单出口新西兰，请按相应的澳新标准生产； 6.产品和包装上生产批号的显示格式ZURU标准日期码格式 7.外箱信息不可手写，重量和体积需要与实际的一致(不可手写） 8. 每款item装箱后的G.W.超过10KG或者CBM超过0.13,(9.5KG或者以上，四舍五入后也属于10KG) 需在外箱上加印超 重或者Bulky LOGO，若发现我们资料没有，请 帮忙提醒 1)重量超过10kg但不超过16kg且CBM不超过0.13,10-16kg 超重logo 2）CBM超过0.13且重量少于17kg，bulky logo 3）不属于以上两种情况，需要使用相应重量范围内的超重logo 4）超重logo需要在外箱四面都印刷(箱唛右上角，两面侧唛超重logo需要尽量靠近毛重)，尺寸为:110mm height* 95mm width 9. 实际外箱重量跟印在箱唛上的数据差异不能超3%，尺寸按实际数据印刷 | Z26: Lydia Wu | AA26: 6.2984 | AB26: =AA26*J26 -> 793.5984 | AD26: 已入 | AG26: =J26 -> 126 | AN26: =J26 -> 126 | AR26: =J26 -> 126 | AW26: =J26 -> 126 | BF26: MA布标 | BG26: 有无混用 | BH26: =J26/6 -> 21 | BI26: =J26/6 -> 21 | BJ26: =J26/6 -> 21 | BL26: =J26/6 -> 21 | BM26: =J26/6 -> 21 | BQ26: =J26/6 -> 21 | BT26: =SUM(BH26:BS26) -> 126 | BU26: =J26-BT26 -> 0
A27: 45477 | B27: Amazon CA (Vendor Center) | C27: 加拿大 | D27: 4500139220 | E27: 51XO6Y7U | F27: 4500139220-440 | H27: 9283H-S002 | I27: 火烈鸟（邮包盒） | J27: 44 | K27: 1 | L27: 4 | M27: =J27/L27 -> 11 | N27: 45516 | O27: 45512 | P27: 7/8取消 | T27: 7/4收到 | V27: 无 | W27: 欠客供外箱贴纸 | Y27: 日期码格式：ZURU INC(BVI) 标准格式 日期：按实际生产日期 Packaging Info: 出口加拿大，包装需要至少2/3L UPC版，无硼版本； #9283: MA 3L入邮包盒， 9283A，8283B 邮包盒图稿跟翻单#4500135161， 9283D邮包盒图稿跟返单4500097545。 Remark: 1.Amazon FOB订单，出口CA。外箱最长边不能超过25" （超过了，case pack只能为1），不符合要求的大货，一律不接受。 2. 外箱正面印ZURU Logo+SSCC LABEL（客供贴纸), 侧面印item#（订单上显示的SKU#)+carton size(以工厂实际尺寸为准,单位: inch) +MADE IN CHINA,日期使用Z URU 标准版本 SSCC Label 显示的是客人自己的item#, SSCC Label 贴在外箱正面的正中间，贴一面即可，跟单订购，贴纸离外箱距必须至少3cm, 每一张SSCC labe l 都是唯一且有不同流水及条码的，没有损耗，绝对不可贴错 ，否则贴错或损坏一张会导致全部都错，千万要注意. SSCC 贴纸务必要在正中间(可以覆盖Logo <(>&<)> 箱唛), 否则会影响到仓库扫描识别 3.日期码使用ZURU标准版本 4.有要求入邮包盒的item，邮包盒上面要打上日期码。 5.按照客户PO# 装柜/箱号顺序装柜，跟单会提前给到装柜计划。在大货生产/仓库存放时，请留意该装柜要求，以便装柜时不混乱（避免装错/装漏/找不到货号等） | Z27: Agnes Zheng | AA27: 6.1693 | AB27: =AA27*M27 -> 67.8623 | AJ27: =J27 -> 44 | AN27: =J27 -> 44 | AU27: =J27 -> 44 | AW27: =J27 -> 44 | BF27: MA布标 | BG27: =J27 -> 44 | BM27: =J27 -> 44
A28: 45428 | B28: BIG W | C28: 澳大利亚 | D28: 4500133767 | E28: 47707079 | F28: 4500133767-40 | G28: 9283-S001 | H28: 9283-S001 | I28: 美人鱼6只装(无闪粉） | J28: 240 | K28: 0 | L28: 6 | M28: =J28/L28 -> 40 | N28: 45471 | O28: 45467 | P28: 8/2取消 | Q28: PASS | R28: 4500138615-此单消耗 | T28: 5/20收到 | V28: 进口商贴纸翻单4500106537 | Y28: 日期码格式：280624 日期： Packaging Info: 1.包装 (MA UPC 包装,1L 3L都可接受） 9283：MA UPC PKG+1张进口商贴纸，贴纸翻单4500106537 2.产品和产品包装上的日期码一致，为280624(dd/mm/yy；进口商贴纸上已经去掉日期码，请按要求在包装上打日期码， 进口商贴纸不覆盖日期码） Remark: 1.共出4港口， 不同港口数量信息请见订单行项目，并请参考箱唛资料，港口不同，箱唛资料也不同； 2.箱唛不可出现任何手写内容，重量与实际一致且不可手写 3. 此单出澳大利亚，请按澳洲标准生产并满足当地法规要求 4.比例： 9283：Kitten:Bunny:Puppy:Cow:Elephant:Flamingo=1:1:1:1:1:1; | Z28: Lillian Li | AA28: 5.712 | AB28: =AA28*J28 -> 1370.88 | AD28: 已入 | AG28: =J28 -> 240 | AN28: =J28 -> 240 | AR28: =J28 -> 240 | AW28: =J28 -> 240 | BF28: MA布标 | BG28: 有无混用 | BH28: =J28/6 -> 40 | BI28: =J28/6 -> 40 | BJ28: =J28/6 -> 40 | BK28: =J28/6 -> 40 | BL28: =J28/6 -> 40 | BM28: =J28/6 -> 40 | BT28: =SUM(BH28:BS28) -> 240 | BU28: =J28-BT28 -> 0
A29: 45428 | B29: BIG W | C29: 澳大利亚 | D29: 4500133767 | E29: 47706373 | F29: 4500133767-30 | G29: 9283-S001 | H29: 9283-S001 | I29: 美人鱼6只装(无闪粉） | J29: 240 | K29: 0 | L29: 6 | M29: =J29/L29 -> 40 | N29: 45471 | O29: 45467 | P29: 转4500138615此单消耗 | Q29: PASS | R29: 7/10出 | T29: 5/20收到 | V29: 进口商贴纸翻单4500106537 | Y29: 日期码格式：280624 日期： Packaging Info: 1.包装 (MA UPC 包装,1L 3L都可接受） 9283：MA UPC PKG+1张进口商贴纸，贴纸翻单4500106537 2.产品和产品包装上的日期码一致，为280624(dd/mm/yy；进口商贴纸上已经去掉日期码，请按要求在包装上打日期码， 进口商贴纸不覆盖日期码） Remark: 1.共出4港口， 不同港口数量信息请见订单行项目，并请参考箱唛资料，港口不同，箱唛资料也不同； 2.箱唛不可出现任何手写内容，重量与实际一致且不可手写 3. 此单出澳大利亚，请按澳洲标准生产并满足当地法规要求 4.比例： 9283：Kitten:Bunny:Puppy:Cow:Elephant:Flamingo=1:1:1:1:1:1; | Z29: Lillian Li | AA29: 5.712 | AB29: =AA29*J29 -> 1370.88 | AD29: 已入 | AG29: =J29 -> 240 | AN29: =J29 -> 240 | AR29: =J29 -> 240 | AW29: =J29 -> 240 | BF29: MA布标 | BG29: 有无混用 | BH29: =J29/6 -> 40 | BI29: =J29/6 -> 40 | BJ29: =J29/6 -> 40 | BK29: =J29/6 -> 40 | BL29: =J29/6 -> 40 | BM29: =J29/6 -> 40 | BT29: =SUM(BH29:BS29) -> 240 | BU29: =J29-BT29 -> 0
A30: 45526 | B30: AMAZON.COM.DEDC,LLC | C30: 美国 | D30: 4500143709 | E30: 49JQLGZY | F30: 4500143709-340 | G30: 9283A-S002 | H30: 9283A-S002 | I30: 小猫（邮包盒） | J30: 116 | K30: 1 | L30: 4 | M30: =J30/L30 -> 29 | N30: 45576 | O30: 45572 | P30: 8/27取消-无物料产生 | T30: 外箱正面印ZURU Logo+SSCC LABEL（客供贴纸), 侧面印item#（订单上显示的SKU#)+carton size(以工厂实际尺寸为准,单位: inch) +MADE IN CHINA | V30: 无 | W30: 欠客供外箱贴纸 | X30: 邮包盒图稿跟翻单#4500135161 | Y30: 日期码格式：ZURU INC(BVI) 标准格式 日期：按实际生产日期 Packaging Info: #9283: MA 1L入邮包盒，9283A邮包盒图稿跟翻单#4500135161，9283D邮包盒图稿跟返单4500139401。 Remark: 1.Amazon FOB订单，出口US。外箱最长边不能超过25" （超过了，case pack只能为1），不符合要求的大货，一律不接受。 2. 外箱正面印ZURU Logo+SSCC LABEL（客供贴纸), 侧面印item#（订单上显示的SKU#)+carton size(以工厂实际尺寸为准,单位: inch) +MADE IN CHINA,日期使用Z URU 标准版本 SSCC Label 显示的是客人自己的item#, SSCC Label 贴在外箱正面的正中间，贴一面即可，跟单订购，贴纸离外箱距必须至少3cm, 每一张SSCC labe l 都是唯一且有不同流水及条码的，没有损耗，绝对不可贴错 ，否则贴错或损坏一张会导致全部都错，千万要注意. SSCC 贴纸务必要在正中间(可以覆盖Logo <(>&<)> 箱唛), 否则会影响到仓库扫描识别 3.日期码使用ZURU标准版本 邮包盒上要打日期码 4.按照客户PO# 装柜/箱号顺序装柜，跟单会提前给到装柜计划。请大货生产/仓库存放时留意，以便装柜时不混乱（装错/装漏/找不到货号） | Z30: Agnes Zheng | AA30: 6.1693 | AB30: =AA30*J30 -> 715.6388 | AD30: 已入 | AG30: =J30 -> 116 | AN30: =J30 -> 116 | AR30: =J30 -> 116 | AW30: =J30 -> 116 | BF30: MA布标 | BG30: =J30 -> 116 | BH30: =J30 -> 116 | BT30: =SUM(BH30:BS30) -> 116 | BU30: =J30-BT30 -> 0
A31: 45526 | B31: AMAZON.COM.DEDC,LLC | C31: 美国 | D31: 4500143730 | E31: 4LFAXSCQ | F31: 4500143730-290 | G31: 9283A-S002 | H31: 9283A-S002 | I31: 小猫（邮包盒） | J31: 1276 | K31: 1 | L31: 4 | M31: =J31/L31 -> 319 | N31: 45576 | O31: 45572 | P31: 8/27取消-无物料产生 | T31: 外箱正面印ZURU Logo+SSCC LABEL（客供贴纸), 侧面印item#（订单上显示的SKU#)+carton size(以工厂实际尺寸为准,单位: inch) +MADE IN CHINA | V31: 无 | W31: 欠客供外箱贴纸 | X31: 邮包盒图稿跟翻单#4500135161 | Y31: 日期码格式：ZURU INC(BVI) 标准格式 日期：按实际生产日期 Packaging Info: #9283: MA 1L入邮包盒，9283A邮包盒图稿跟翻单#4500135161，9283D邮包盒图稿跟返单4500139401。 Remark: 1.Amazon FOB订单，出口US。 2.日期码使用ZURU标准版本。 3.如果大货有要求入邮包盒，则对应的邮包盒上面要打上日期码。 4.箱尺寸要求：外箱最长边不能超过25" （超过了，case pack只能为1），不符合要求的大货，一律不接受。 5.外箱箱唛要求： ①外箱正面印ZURU Logo+SSCC Label（客供贴纸，由跟单订购)。关于 SSCC Label 请注意： SSCC Label 显示的是客人自己的item#。每一张SSCC label 都是唯一且有不同流水及条码的，没有损耗，绝对不可贴错 。如果贴错或损坏任何一张，都会导致全 部都错，千万要注意！ SSCC Label 必须贴在外箱正面的正中间位置（贴一面即可），并且贴纸离外箱边距必须至少3cm(可以覆盖Logo<(>&<)>箱唛)，否则会影响到客户那边仓库的扫描识 别。 ②外箱侧面印item#（订单上显示的SKU#)+carton size(以工厂实际尺寸为准,单位: inch) +MADE IN CHINA,日期使用ZURU 标准版本。 6.装柜要求：按照客户PO# 装柜/箱号顺序装柜，跟单会提前给到装柜计划。 在大货生产/仓库存放时，请留意该装柜要求，以便装柜时不混乱（避免装错/装漏/找不到货号等）。 | Z31: Agnes Zheng | AA31: 6.1617 | AB31: =AA31*J31 -> 7862.3292 | AD31: 已入 | AG31: =J31 -> 1276 | AN31: =J31 -> 1276 | AR31: =J31 -> 1276 | AW31: =J31 -> 1276 | BF31: MA布标 | BG31: =J31 -> 1276 | BH31: =J31 -> 1276 | BT31: =SUM(BH31:BS31) -> 1276 | BU31: =J31-BT31 -> 0
A32: 45534 | B32: Smyths Toys HQ UC UK | C32: 英国 | D32: 4500144369 | E32: 4400430922 | F32: 4500144369-40 | G32: 9283D-S001-3L-1 | H32: 9283D-S001 | I32: 小狗(无闪粉） | J32: 2004 | K32: 0 | L32: 6 | M32: =J32/L32 -> 334 | N32: 45586 | O32: 45582 | Q32: 10/9取消 | R32: 纸箱滞留 | S32: 纸箱消耗在4500145942此单中 | U32: UPC贴纸翻4500120617+德语callout翻译贴纸翻4500117992 | W32: 客版 Try me贴纸翻4500094401 | X32: 日期码格式：ZURU INC(BVI) 标准格式 日期：按实际生产日期 Packaging In 4.9283D: MA最新版3L (warning 9L)收缩膜+新的9283D 条码贴纸（9283D UPC#193052052896-UPC贴纸和位置图翻PO#4500120617)+德语callout翻译贴纸(德语callou t翻译贴纸以及位置图翻4500117992这张单)+客版 Try me贴纸（翻4500094401这张单） MA 5L(Warning 9L)收藏指南+MA 5L polybag+MA 5L太空沙胶袋+MA 5L纸袋+MA 5L证书+MA 5L地图+MA布标 7.所有配比跟MA配比 Remark: 1）包装日期码按ZURU格式即可，请确保不迟于外箱日期码，可等于或者早于外箱日期码，必须为法定工作日，印刷前请先检查外箱日期码。 2）订单出英国，请注意检查产品及包装应带UKCA图标（14+产品除外），包装显示ZURU UK LTD/ZURU France地址信息，QC部门请查核，如有问题与跟单确认 3）订单必须经过ZURU QC验货并且通过后方可出货 4) 需要符合欧洲标准不能含有闪粉和微塑料，否则不和法规会有客诉产生 | Y32: Sheba Ye | Z32: 5.8973 | AA32: =Z32*J32 -> 11818.189 | AC32: 已入 | AI32: =J32 -> 2004 | AM32: =J32 -> 2004 | AU32: =J32 -> 2004 | AV32: =J32 -> 2004 | BE32: MA布标 | BF32: =J32 -> 2004 | BI32: =J32 -> 2004 | BS32: =SUM(BG32:BR32) -> 2004 | BT32: =J32-BS32 -> 0
A33: 45595 | B33: BIG W | C33: 澳大利亚 | D33: 4500149671 | E33: CUS PO#47751858 BNE | F33: 4500149671-140 | H33: 9283-S001 | I33: 美人鱼6只装 | J33: 396 | K33: 0 | L33: 6 | M33: =J33/L33 -> 66 | N33: 45639 | O33: 45635 | Q33: 11/1取消 | R33: 无 | U33: 进口商贴纸翻4500144447 | X33: 日期码格式：ZURU INC(BVI) 标准格式 日期：按实际生产日期 Packaging Info: 1. 包装 9283：英文MA包装 (UPC版本，首选1L，无1L可用多L含英语) + 1张进口商贴纸，贴纸翻单4500144447； Ratio：Kitten:Bunny:Puppy:Cow:Elephant:Flamingo=1:1:1:1:1:1; 2. 进口商贴纸上已经去掉日期码，产品和包装上的日期码一致，请按要求在包装上打日期码（进口商贴纸不覆盖日期码） 3. 原指定日期码DDMMYY可改用ZURU标准日期码 Remark: 1. 共出4港口(SYD, BNE, MEL, FRE), 不同港口数量信息请见订单行项目，并请参考箱唛资料，港口不同，箱唛资料也不同； 2. 箱唛不可出现任何手写内容（箱数除外），重量与实际一致且不可手写; 3. 此单出澳大利亚，请按澳洲标准生产并满足当地法规要求; 4. 出无闪粉版本，需符合欧洲微塑料法规 | Y33: Christine Liao | Z33: 6.2908 | AA33: =Z33*J33 -> 2491.1568 | AF33: =J33 -> 396 | AM33: =J33 -> 396 | AQ33: =J33 -> 396 | AV33: =J33 -> 396 | BE33: MA布标 | BG33: =J33/6 -> 66 | BH33: =J33/6 -> 66 | BI33: =J33/6 -> 66 | BJ33: =J33/6 -> 66 | BK33: =J33/6 -> 66 | BL33: =J33/6 -> 66 | BS33: =SUM(BG33:BR33) -> 396 | BT33: =J33-BS33 -> 0
A34: 45603 | B34: HOBBY LOBBY INC. | C34: 美国 | D34: 4500150311 | E34: W0692846 | F34: 4500150311-30 | G34: 9283-S001 | H34: 9283-S001 | I34: 美人鱼6只装 | J34: 3174 | K34: 0 | L34: 6 | M34: =J34/L34 -> 529 | N34: 45645 | O34: 45642 | Q34: 11/12取消 | R34: 无 | U34: 欠价格贴纸+外箱贴纸 | X34: 日期码格式：ZURU INC(BVI) 标准格式 日期：按实际生产日期 Packaging Info:2. 外箱正唛右下角贴条码贴纸2张，贴纸大小：2.75 x 1.5 inch。(跟单提供文档，工厂采购) Remark: 3. 产品外包装及产品本身都必须有日期跟踪码，格式为：ZURU 标准日期码。 4. ZURU QC验货，无测试。 5. 产品配比：#9283: Kitten:Bunny:Puppy:Cow:Elephant:Flamingo=1:1:1:1:1:1; | Y34: Eleven Zhang | Z34: 5.701 | AA34: =Z34*J34 -> 18094.974 | AC34: 已入 | AF34: =J34 -> 3174 | AM34: =J34 -> 3174 | AQ34: =J34 -> 3174 | AV34: =J34 -> 3174 | BE34: MA布标 | BG34: =J34/6 -> 529 | BH34: =J34/6 -> 529 | BI34: =J34/6 -> 529 | BJ34: =J34/6 -> 529 | BK34: =J34/6 -> 529 | BL34: =J34/6 -> 529 | BS34: =SUM(BG34:BR34) -> 3174 | BT34: =J34-BS34 -> 0
A35: 45618 | B35: KMART AUSTRALIA LTD | C35: 澳大利亚 | D35: 4500151624 | E35: 20478291 | F35: 4500151624-40 | G35: 9283-S001 | H35: 9283-S001 | I35: 美人鱼6只装 | J35: 1422 | K35: 0 | L35: 6 | M35: =J35/L35 -> 237 | N35: 45656 | O35: 45652 | Q35: 12/13取消 | R35: 无 | U35: 欠防盗贴纸+欠外箱贴纸 | X35: 日期码格式：ZURU INC(BVI) 标准格式 日期：按实际生产日期 Tracking Code: Packaging Info: 9283: MA英语UPC版本包装（收缩膜和说明书, MA首选1L，如无1L可用多语且含英语的配套多语包装) + 1张防盗贴纸 (贴纸以及位置图翻单PO#4500095104）+ 箱唛 + 外箱SSCC Label Remark: 1.请务必按时完货，验货。并且按期送货入货代指定仓库，如果晚了导致船期Delay将会有罚金产生或者客户要求空运，所产生的罚金和空运费由工厂承担。 2.SSCC 外箱贴纸请同纸箱瓦楞纸方向（竖纹向）垂直，即外箱贴纸横着贴(注意条码不要被胶带粘住），贴1pc，贴1面正唛，封箱胶纸不能挡住贴纸内容。外箱贴纸 离外箱边距离不少于2cm。 3.外箱材质为ZURU标准； 4.此单需使用KMART封箱胶上下工字型封箱;从2019年6月开始，要用KMART 新版封箱胶带，此单要用"ANKO"封箱胶带 5.此单出口澳大利亚，请按相应的澳新标准生产； 6.产品和包装上生产批号的显示格式ZURU标准日期码格式 7.外箱信息不可手写，重量和体积需要与实际的一致(不可手写） 8. 每款item装箱后的G.W.超过10KG或者CBM超过0.13,(9.5KG或者以上，四舍五入后也属于10KG) 需在外箱上加印超 重或者Bulky LOGO，若发现我们资料没有，请 帮忙提醒 1)重量超过10kg但不超过16kg且CBM不超过0.13,10-16kg 超重logo 2）CBM超过0.13且重量少于17kg，bulky logo 3）不属于以上两种情况，需要使用相应重量范围内的超重logo 4）超重logo需要在外箱四面都印刷(箱唛右上角，两面侧唛超重logo需要尽量靠近毛重)，尺寸为:110mm height* 95mm width 9. 实际外箱重量跟印在箱唛上的数据差异不能超3%，尺寸按实际数据印刷 | Y35: Lydia Wu | Z35: 6.2908 | AA35: =Z35*J35 -> 8945.5176 | AC35: 已入 | AF35: =J35 -> 1422 | AM35: =J35 -> 1422 | AQ35: =J35 -> 1422 | AV35: =J35 -> 1422 | BE35: MA布标 | BG35: =J35/6 -> 237 | BH35: =J35/6 -> 237 | BI35: =J35/6 -> 237 | BJ35: =J35/6 -> 237 | BK35: =J35/6 -> 237 | BL35: =J35/6 -> 237 | BS35: =SUM(BG35:BR35) -> 1422 | BT35: =J35-BS35 -> 0
A36: 45618 | B36: KMART AUSTRALIA LTD(NEW ZEALAND) | C36: 新西兰 | D36: 4500151625 | E36: 20478293 | F36: 4500151625-30 | G36: 9283-S001 | H36: 9283-S001 | I36: 美人鱼6只装 | J36: 78 | K36: 0 | L36: 6 | M36: =J36/L36 -> 13 | N36: 45656 | O36: 45652 | Q36: 12/13取消 | R36: 无 | U36: 欠防盗贴纸+欠外箱贴纸 | X36: 日期码格式：ZURU INC(BVI) 标准格式 日期：按实际生产日期 Tracking Code: Packaging Info: 9283: MA英语UPC版本包装（收缩膜和说明书, MA首选1L，如无1L可用多语且含英语的配套多语包装) + 1张防盗贴纸 (贴纸以及位置图翻单PO#4500095104）+ 箱唛 + 外箱SSCC Label Remark: 1.请务必按时完货，验货。并且按期送货入货代指定仓库，如果晚了导致船期Delay将会有罚金产生或者客户要求空运，所产生的罚金和空运费由工厂承担。 2.SSCC 外箱贴纸请同纸箱瓦楞纸方向（竖纹向）垂直，即外箱贴纸横着贴(注意条码不要被胶带粘住），贴1pc，贴1面正唛，封箱胶纸不能挡住贴纸内容。外箱贴纸 离外箱边距离不少于2cm。 3.外箱材质为ZURU标准； 4.此单需使用KMART封箱胶上下工字型封箱;从2019年6月开始，要用KMART 新版封箱胶带，此单要用"ANKO"封箱胶带 5.此单出口新西兰，请按相应的澳新标准生产； 6.产品和包装上生产批号的显示格式ZURU标准日期码格式 7.外箱信息不可手写，重量和体积需要与实际的一致(不可手写） 8. 每款item装箱后的G.W.超过10KG或者CBM超过0.13,(9.5KG或者以上，四舍五入后也属于10KG) 需在外箱上加印超 重或者Bulky LOGO，若发现我们资料没有，请 帮忙提醒 1)重量超过10kg但不超过16kg且CBM不超过0.13,10-16kg 超重logo 2）CBM超过0.13且重量少于17kg，bulky logo 3）不属于以上两种情况，需要使用相应重量范围内的超重logo 4）超重logo需要在外箱四面都印刷(箱唛右上角，两面侧唛超重logo需要尽量靠近毛重)，尺寸为:110mm height* 95mm width 9. 实际外箱重量跟印在箱唛上的数据差异不能超3%，尺寸按实际数据印刷 | Y36: Lydia Wu | Z36: 6.2984 | AA36: =Z36*J36 -> 491.2752 | AC36: 已入 | AF36: =J36 -> 78 | AM36: =J36 -> 78 | AQ36: =J36 -> 78 | AV36: =J36 -> 78 | BE36: MA布标 | BG36: =J36/6 -> 13 | BH36: =J36/6 -> 13 | BI36: =J36/6 -> 13 | BJ36: =J36/6 -> 13 | BK36: =J36/6 -> 13 | BL36: =J36/6 -> 13 | BS36: =SUM(BG36:BR36) -> 78 | BT36: =J36-BS36 -> 0
A37: 45701 | B37: BIG W | C37: 澳大利亚 | D37: 4500157563 | E37: CUS PO#47792480 SYD | F37: 4500157563-20 | G37: 9283-S001 | H37: 9283-S001 | I37: 美人鱼6只装 | J37: 444 | K37: 0 | L37: 6 | M37: =J37/L37 -> 74 | N37: 45750 | O37: 45747 | Q37: 3/11取消 | R37: 无 | U37: 进口商贴纸翻450010653 | X37: 日期码格式：ZURU INC(BVI) 标准格式 日期：按实际生产日期 Packaging Info: 1.包装 9283：MA UPC PKG+1张进口商贴纸，贴纸翻单4500106537 2. 进口商贴纸上已经去掉日期码，产品和包装上的日期码一致，请按要求在包装上打日期码（进口商贴纸不覆盖日期码） 3. 原指定日期码DDMMYY可改用ZURU标准日期码 Remark: 1.共出4港口(SYD,BNE,MEL,FRE)， 不同港口数量信息请见订单行项目，并请参考箱唛资料，港口不同，箱唛资料也不同； 2. 箱唛不可出现任何手写内容（箱数除外），重量与实际一致且不可手写 3.此单出澳大利亚，请按澳洲标准生产并满足当地法规要求 4.出无闪粉版本，需符合欧洲微塑料法规 | Y37: Christine Liao | Z37: 5.712 | AA37: =Z37*J37 -> 2536.128 | AC37: 已入 | AF37: =J37 -> 444 | AM37: =J37 -> 444 | AQ37: =J37 -> 444 | AV37: =J37 -> 444 | BE37: MA布标 | BG37: =J37/6 -> 74 | BH37: =J37/6 -> 74 | BI37: =J37/6 -> 74 | BJ37: =J37/6 -> 74 | BK37: =J37/6 -> 74 | BL37: =J37/6 -> 74 | BS37: =SUM(BG37:BR37) -> 444 | BT37: =J37-BS37 -> 0
A38: 45701 | B38: BIG W | C38: 澳大利亚 | D38: 4500157563 | E38: CUS PO#47792597 MEL | F38: 4500157563-40 | G38: 9283-S001 | H38: 9283-S001 | I38: 美人鱼6只装 | J38: 384 | K38: 0 | L38: 6 | M38: =J38/L38 -> 64 | N38: 45750 | O38: 45747 | Q38: 3/11取消 | R38: 无 | U38: 进口商贴纸翻450010653 | X38: 日期码格式：ZURU INC(BVI) 标准格式 日期：按实际生产日期 Packaging Info: 1.包装 9283：MA UPC PKG+1张进口商贴纸，贴纸翻单4500106537 2. 进口商贴纸上已经去掉日期码，产品和包装上的日期码一致，请按要求在包装上打日期码（进口商贴纸不覆盖日期码） 3. 原指定日期码DDMMYY可改用ZURU标准日期码 Remark: 1.共出4港口(SYD,BNE,MEL,FRE)， 不同港口数量信息请见订单行项目，并请参考箱唛资料，港口不同，箱唛资料也不同； 2. 箱唛不可出现任何手写内容（箱数除外），重量与实际一致且不可手写 3.此单出澳大利亚，请按澳洲标准生产并满足当地法规要求 4.出无闪粉版本，需符合欧洲微塑料法规 | Y38: Christine Liao | Z38: 5.712 | AA38: =Z38*J38 -> 2193.408 | AC38: 已入 | AF38: =J38 -> 384 | AM38: =J38 -> 384 | AQ38: =J38 -> 384 | AV38: =J38 -> 384 | BE38: MA布标 | BG38: =J38/6 -> 64 | BH38: =J38/6 -> 64 | BI38: =J38/6 -> 64 | BJ38: =J38/6 -> 64 | BK38: =J38/6 -> 64 | BL38: =J38/6 -> 64 | BS38: =SUM(BG38:BR38) -> 384 | BT38: =J38-BS38 -> 0
A39: 45701 | B39: BIG W | C39: 澳大利亚 | D39: 4500157563 | E39: CUS PO#47793022 BNE | F39: 4500157563-70 | G39: 9283-S001 | H39: 9283-S001 | I39: 美人鱼6只装 | J39: 678 | K39: 0 | L39: 6 | M39: =J39/L39 -> 113 | N39: 45750 | O39: 45747 | Q39: 3/11取消 | R39: 无 | U39: 进口商贴纸翻450010653 | X39: 日期码格式：ZURU INC(BVI) 标准格式 日期：按实际生产日期 Packaging Info: 1.包装 9283：MA UPC PKG+1张进口商贴纸，贴纸翻单4500106537 2. 进口商贴纸上已经去掉日期码，产品和包装上的日期码一致，请按要求在包装上打日期码（进口商贴纸不覆盖日期码） 3. 原指定日期码DDMMYY可改用ZURU标准日期码 Remark: 1.共出4港口(SYD,BNE,MEL,FRE)， 不同港口数量信息请见订单行项目，并请参考箱唛资料，港口不同，箱唛资料也不同； 2. 箱唛不可出现任何手写内容（箱数除外），重量与实际一致且不可手写 3.此单出澳大利亚，请按澳洲标准生产并满足当地法规要求 4.出无闪粉版本，需符合欧洲微塑料法规 | Y39: Christine Liao | Z39: 5.712 | AA39: =Z39*J39 -> 3872.736 | AC39: 已入 | AF39: =J39 -> 678 | AM39: =J39 -> 678 | AQ39: =J39 -> 678 | AV39: =J39 -> 678 | BE39: MA布标 | BG39: =J39/6 -> 113 | BH39: =J39/6 -> 113 | BI39: =J39/6 -> 113 | BJ39: =J39/6 -> 113 | BK39: =J39/6 -> 113 | BL39: =J39/6 -> 113 | BS39: =SUM(BG39:BR39) -> 678 | BT39: =J39-BS39 -> 0
A40: 45750 | B40: ZURU France | C40: 法国 | D40: 4500162314 | E40: 5200006540 | F40: 4500162314-10 | G40: 9283-S006 | H40: 9283-S006-MTS | I40: 美人鱼6只装 | J40: 435 | K40: 0 | L40: 3 | M40: =J40/L40 -> 145 | N40: 45799 | O40: 45796 | Q40: 4/16取消 | R40: 无 | U40: 欠多语警语折叠贴纸（含包装缺失的法/意/西环保标） | X40: 日期码格式：ZURU INC(BVI) 标准格式 日期：按实际生产日期 Packaging Info: 1.9283:最新MA 3L EAN收缩膜+最新MA 3L贴纸+最新MA 5L收藏指南+最新MA 布标+最新MA 5L包装+多语警语折叠贴纸（含包装缺失的法/意/西环保标） Remark: 1. 法国国家内销单，需要通过ZURU 验货结果后才能出货 (工厂需要主动提前同ZURU QC预约验货避免延期出货造成不必要麻烦)； 2. 本订单所有 具有 baby items / assorted items 的款式，零售包装上都要用 母 EAN; 3. 若有特定款有特殊外箱条码要求时,需要明确列出产品款对应的具体外箱条码号码/条码类型 (若无,可以忽略此需求) 4. 所有出口欧洲的产品, 法规规定禁止在包装和共公众用的印刷品中使用矿物油中含有的物质, 包装印刷油墨中含有的MOAH/MOSH的质量浓度不能超过1%, 否则出 货到法国被抽检出现问题, 供应商需要对此负责; 5. Date code: 外箱/产品/包装 保持一致，完货后提供date code 信息以便我们保存记录做批次管理; 6. 装柜时需要按照款式号码从小到大一款款依次装,避免终端仓库卸货混乱.若一个柜子涉及到几个不同国家内销单,装柜时需要一个国家装完后再装另一个国家的 产品,依次装柜,避免终端仓库因不同国家不同库位位置卸货混乱. (此点需要同工厂装柜人员强调) | Y40: Jade Wang | Z40: 5.8523 | AA40: =Z40*J40 -> 2545.7505 | AC40: 已入 | AI40: =J40 -> 435 | AM40: =J40 -> 435 | AT40: =J40 -> 435 | AV40: =J40 -> 435 | BE40: MA布标 | BG40: =J40/6 -> 72.5 | BH40: =J40/6 -> 72.5 | BI40: =J40/6 -> 72.5 | BJ40: =J40/6 -> 72.5 | BK40: =J40/6 -> 72.5 | BL40: =J40/6 -> 72.5 | BS40: =SUM(BG40:BR40) -> 435 | BT40: =J40-BS40 -> 0
A41: 45804 | B41: Amazon Mexico, S. DE R.L. DE CV | C41: 墨西哥 | D41: 4500168127 | E41: 5UL3UKAR | F41: 4500168127-180 | H41: 9283E-S002 | I41: 奶牛（邮包盒）新稿 | J41: 36 | K41: 1 | L41: 4 | M41: =J41/L41 -> 9 | N41: 45834 | O41: 45831 | Q41: 6/16取消 | R41: 无 | U41: 欠进口商贴纸 | V41: 欠外箱贴纸 | X41: 日期码格式：ZURU INC(BVI) 标准格式 日期：按实际生产日期 Packaging Info: 8. 9283: MA 3L包装入邮包盒， 9283A的邮包盒图稿跟翻单 4500135161，9283E和9283G的邮包盒图稿由跟单重新提供+进口商贴纸+SSCC label，A：193052052872， E:193052052902, G:193052052919 Remark: 1. Amazon FOB订单，出口Mexico，外箱最长边不能超过25" （超过了，case pack只能为1），不符合要求的大货，一律不接受。 2. 空白外箱加印ZURU Logo（四面加印）+MADE IN CHINA（只印一正一侧）+SSCC LABEL(客供贴纸），无shipping mark,日期使用ZURU 标准版本。SSCC Label显示 的是客人自己的item#，SSCC Label 贴在外箱正面的正中间，贴一面即可，跟单订购，贴纸离外箱距必须至少3cm,每一张SSCC Label都是唯一且有不同流水及条码的 ，没有损耗，绝对不可贴错，否则贴错或损坏一张会导致全部都错，千万要注意！ 3. 日期码使用ZURU标准版 | Y41: Ever Li | Z41: 6.0417 | AA41: =Z41*J41 -> 217.5012 | AI41: =J41 -> 36 | AM41: =J41 -> 36 | AT41: =J41 -> 36 | AV41: =J41 -> 36 | BE41: MA布标新日期格式 | BJ41: =J41 -> 36 | BS41: =SUM(BG41:BR41) -> 36 | BT41: =J41-BS41 -> 0
A42: 45804 | B42: Amazon Mexico, S. DE R.L. DE CV | C42: 墨西哥 | D42: 4500168127 | E42: 4LIGUCJC | F42: 4500168127-390 | H42: 9283G-S002 | I42: 大象（邮包盒）新稿 | J42: 24 | K42: 1 | L42: 4 | M42: =J42/L42 -> 6 | N42: 45834 | O42: 45831 | Q42: 6/16取消 | R42: 无 | U42: 欠进口商贴纸 | V42: 欠外箱贴纸 | X42: 日期码格式：ZURU INC(BVI) 标准格式 日期：按实际生产日期 Packaging Info: 8. 9283: MA 3L包装入邮包盒， 9283A的邮包盒图稿跟翻单 4500135161，9283E和9283G的邮包盒图稿由跟单重新提供+进口商贴纸+SSCC label，A：193052052872， E:193052052902, G:193052052919 Remark: 1. Amazon FOB订单，出口Mexico，外箱最长边不能超过25" （超过了，case pack只能为1），不符合要求的大货，一律不接受。 2. 空白外箱加印ZURU Logo（四面加印）+MADE IN CHINA（只印一正一侧）+SSCC LABEL(客供贴纸），无shipping mark,日期使用ZURU 标准版本。SSCC Label显示 的是客人自己的item#，SSCC Label 贴在外箱正面的正中间，贴一面即可，跟单订购，贴纸离外箱距必须至少3cm,每一张SSCC Label都是唯一且有不同流水及条码的 ，没有损耗，绝对不可贴错，否则贴错或损坏一张会导致全部都错，千万要注意！ 3. 日期码使用ZURU标准版 | Y42: Ever Li | Z42: 6.0417 | AA42: =Z42*J42 -> 145.0008 | AI42: =J42 -> 24 | AM42: =J42 -> 24 | AT42: =J42 -> 24 | AV42: =J42 -> 24 | BE42: MA布标新日期格式 | BK42: =J42 -> 24 | BS42: =SUM(BG42:BR42) -> 24 | BT42: =J42-BS42 -> 0
A43: 45821 | B43: AMAZON CA (VENDOR CENTER) | C43: 加拿大 | D43: 4500169926 | E43: 2M3CKZJZ | F43: 4500169926-250 | G43: 9283H-S002-3L-1 | H43: 9283H-S002 | I43: 火烈鸟（邮包盒） | J43: 36 | K43: 0 | L43: 4 | M43: 9 | N43: 45856 | O43: 45852 | U43: 无 | V43: 欠外箱贴纸 | X43: 日期码格式：ZURU INC(BVI) 标准格式 日期：按实际生产日期 Packaging Info: #9283: MA 3L入邮包盒，邮包盒图稿跟单提供； Remark: 1. Amazon FOB订单，出口CA。外箱最长边不能超过25" （超过了，case pack只能为1），不符合要求的大货，一律不接受。 2. 外箱正面印ZURU Logo + SSCC LABEL（客供贴纸)，侧面印item#（订单上显示的SKU#) + carton size(以工厂实际尺寸为准，单位: inch) + MADE IN CHINA， 日期使用ZURU 标准版本 SSCC Label 显示的是客人自己的item#，SSCC Label 贴在外箱正面的正中间，贴一面即可，跟单订购，贴纸离外箱距必须至少3cm，每一 张SSCC label 都是唯一且有不同流水及条码的，没有损耗，绝对不可贴错 ，否则贴错或损坏一张会导致全部都错，千万要注意: SSCC 贴纸务必要在正中间(可以覆 盖Logo <(>&<)> 箱唛)，否则会影响到仓库扫描识别。 3. 日期码使用ZURU标准版本。 4. 如果大货有要求入邮包盒，则对应的邮包盒上面要打上日期码。 5. 按照客户PO# 装柜/箱号顺序装柜，跟单会提前给到装柜计划。在大货生产/仓库存放时，请留意该装柜要求，以便装柜时不混乱（避免装错/装漏/找不到货号等 ）。 6. 出口加拿大，包装需要至少2/3L UPC版，无硼版本。 7.邮包盒上要印刷日期码 | Y43: Kelly Shen | Z43: 6.0417 | AA43: =Z43*J43 -> 217.5012 | AC43: 已入 | AI43: =J43 -> 36 | AM43: =J43 -> 36 | AT43: =J43 -> 36 | AV43: =J43 -> 36 | BE43: MA布标 | BL43: =J43 -> 36 | BS43: =SUM(BG43:BR43) -> 36 | BT43: =J43-BS43 -> 0
A44: 45821 | B44: AMAZON CA (VENDOR CENTER) | C44: 加拿大 | D44: 4500169926 | E44: 8VF42DHN | F44: 4500169926-260 | G44: 9283H-S002-3L-1 | H44: 9283H-S002 | I44: 火烈鸟（邮包盒） | J44: 16 | K44: 0 | L44: 4 | M44: 4 | N44: 45856 | O44: 45852 | U44: 无 | V44: 欠外箱贴纸 | X44: 日期码格式：ZURU INC(BVI) 标准格式 日期：按实际生产日期 Packaging Info: #9283: MA 3L入邮包盒，邮包盒图稿跟单提供； Remark: 1. Amazon FOB订单，出口CA。外箱最长边不能超过25" （超过了，case pack只能为1），不符合要求的大货，一律不接受。 2. 外箱正面印ZURU Logo + SSCC LABEL（客供贴纸)，侧面印item#（订单上显示的SKU#) + carton size(以工厂实际尺寸为准，单位: inch) + MADE IN CHINA， 日期使用ZURU 标准版本 SSCC Label 显示的是客人自己的item#，SSCC Label 贴在外箱正面的正中间，贴一面即可，跟单订购，贴纸离外箱距必须至少3cm，每一 张SSCC label 都是唯一且有不同流水及条码的，没有损耗，绝对不可贴错 ，否则贴错或损坏一张会导致全部都错，千万要注意: SSCC 贴纸务必要在正中间(可以覆 盖Logo <(>&<)> 箱唛)，否则会影响到仓库扫描识别。 3. 日期码使用ZURU标准版本。 4. 如果大货有要求入邮包盒，则对应的邮包盒上面要打上日期码。 5. 按照客户PO# 装柜/箱号顺序装柜，跟单会提前给到装柜计划。在大货生产/仓库存放时，请留意该装柜要求，以便装柜时不混乱（避免装错/装漏/找不到货号等 ）。 6. 出口加拿大，包装需要至少2/3L UPC版，无硼版本。 7.邮包盒上要印刷日期码 | Y44: Kelly Shen | Z44: 6.0417 | AA44: =Z44*J44 -> 96.6672 | AC44: 已入 | AI44: =J44 -> 16 | AM44: =J44 -> 16 | AT44: =J44 -> 16 | AV44: =J44 -> 16 | BE44: MA布标 | BL44: =J44 -> 16 | BS44: =SUM(BG44:BR44) -> 16 | BT44: =J44-BS44 -> 0
