Workbook

Sheet 77673
A1: 香港接单日期 | B1: 第三方客户名称 | C1: 走货国家 | D1: ZURU PO NO# | E1: 第三方客户 PO NO# | F1: SKU | G1: ITEM# | H1: 货品名称 | I1: PO数量(只) | J1: 内箱装箱数量(只) | K1: 外箱装箱数量(只) | L1: 总箱数 | M1: 计划出货期 | N1: 计划验货期 | O1: 第三方客户公证行验货 | P1: 验货结果 | Q1: S/O(截仓期) | R1: 箱唛 (收到日期) | S1: 外箱贴纸 | T1: 贴纸资料 (收到日期及订购日期) | U1: 额外说明书/保证书 | V1: 客供物料 | W1: 样办 | X1: 备注 | Y1: ZURU跟单组员 | Z1: 单价USD | AA1: 金额USD | AB1: 是否收到客版包装资料 | AC1: 发票号 | AD1: 系统货号 | AE1: 是否入系统 | AF1: 下单情况 | AG1: 生产情况 | AH1: 采购单 | AI1: 已回数量 | AJ1: 欠数 | AK1: HN回复完成时间 | AL1: 贴纸 | AM1: 纸箱 | AN1: 77673标准版本 订单数量 | AO1: 77673COSTCO-NA 客版订单数量 | AP1: 77673 TARGET US 客版 订单数量 | AQ1: 77673COSTCO-INT 客版订单数量 | AR1: 收缩膜 1L A版本 | AS1: 收缩膜 3L A版本 | AT1: 客版3L 无条码版本收缩膜 | AU1: 收藏指南 5L A版本 | AV1: 中文收藏指南 | AW1: 黑白说明书 | AX1: 中文黑白说明书 | AY1: 客版说明书 | AZ1: BJ'S WHOLESALE CLUB, INC.客版收缩膜.收藏指南 | BA1: COSTCO客版收缩膜 | BB1: COSTCO客版收藏指南 | BC1: COSTCO客版说明书 | BD1: Smyths客版收缩膜 | BE1: Smyths客版收藏指南 | BF1: TARGET客版收缩膜 | BG1: TARGET客版收藏指南 | BH1: 77637TQ1 1L | BI1: 77637TQ1 3L | BJ1: 77637TQ2 3L | BK1: 77721彩盒 | BL1: 77721托盘 | BM1: 77785彩盒 1L | BN1: 77785彩盒 3L | BO1: MEC305-S001-INT
A2: 45650 | D2: ZPO2412009 | G2: 77673-S001 | H2: 迷你冰箱12pcs/箱 | I2: 424 | J2: 0 | K2: 12 | L2: =I2/K2 -> 35.333333 | R2: 45650 | S2: 无 | T2: 无 | Y2: Alison Chen | AC2: 97420-8.17 | AD2: 77673-S001 | AE2: N/A | AG2: 已完成 | AI2: =I2 -> 424 | AJ2: =AI2-I2 -> 0 | AN2: =I2 -> 424 | AR2: =I2 -> 424 | AU2: =I2 -> 424 | AW2: =I2 -> 424
A3: 45701 | B3: THE WAREHOUSE LIMITED | C3: 新西兰 | D3: 4500157534 | F3: 4500157534-50 | G3: 77673-S001 | H3: 迷你冰箱12pcs/箱 | I3: 144 | J3: 0 | K3: 12 | L3: =I3/K3 -> 12 | M3: 45731 | N3: 45727 | Q3: 消耗PP订单出货 | R3: 45804 | S3: 无 | T3: 45804 | X3: 日期码格式：ZURU INC(BVI) 标准格式 日期：按实际生产日期 Packaging Info: MA UPC 英语包装（优先1L英语版本，或者3L/5L含英语都可） 此客人不接受易掉落或者剥落或者可直接触碰的闪粉，可降解也不行，但可以接受符合欧洲微塑料标准的珠光粉或者闪片。 77673：包装正面和说明书都需要加电池警告语贴纸（法规要求） 所有外箱上都要贴一张大黄贴："ZURU Product for NZ test " Remark: 77673：3PCS AG13 BATTERIES(INCLUDED) | Y3: Abby Liang | Z3: 4.1 | AA3: =Z3*I3 -> 590.4 | AC3: 95262-8.17 | AD3: 77673-S001 | AE3: 已入 | AG3: 已完成 | AI3: =I3 -> 144 | AJ3: =AI3-I3 -> 0 | AN3: =I3 -> 144 | AR3: =I3 -> 144 | AU3: =I3 -> 144 | AW3: =I3 -> 144
A4: 45722 | D4: ZMPO250187 | G4: 77673-S001 | H4: 迷你冰箱12pcs/箱 | I4: 168 | J4: 0 | K4: 12 | L4: =I4/K4 -> 14 | M4: 45736 | N4: 45733 | R4: 45722 | S4: 无 | T4: 无 | X4: Remark:大货最新版本包装/大货标准箱装箱/箱唛请参照邮件附件;备注：收到样品订单后尽快安排 ，注意样板品质质量要求要高于大货品质要求 ，送货时必须要附带送货单(没有送货单和QC检验合格报告的仓库一律拒绝收货)，请知悉，谢谢！ | Y4: Angus | AC4: 94898-8.17 | AD4: 77673-S001 | AE4: 已入 | AG4: 已完成 | AI4: 东莞安排 | AJ4: =AI4-I4 -> #VALUE! | AN4: =I4 -> 168 | AR4: =I4 -> 168 | AU4: =I4 -> 168 | AW4: =I4 -> 168
A5: 45737 | D5: ZMPO250244 | G5: 77673-S001 | H5: 迷你冰箱P39饮料瓶散件 | I5: 1100套 | J5: 0 | K5: 1100 | L5: 1 | M5: 45740 | N5: 45736 | R5: 45737 | S5: 无 | T5: 无 | X5: Remark：大货版本/只需要左图款散件；备注： 收到订单后请尽快安排，谢谢 | Y5: Angus | AC5: 94899-8.17 | AD5: 77673-S001 | AE5: N/A | AG5: 已完成 | AI5: 东莞安排 | AJ5: =AI5-I5 -> #VALUE!
A6: 45749 | D6: ZMPO250283 | G6: 77673-S001 | H6: 迷你冰箱12pcs/箱 | I6: 80套散件 | M6: 45757 | N6: 45754 | R6: 45749 | S6: 无 | T6: 无 | X6: Remark:大货最新版本/只需要齐套散件/麻烦用胶袋分装好一套为一袋/箱唛参照邮件附件;备注： 收到订单后请尽快安排，谢谢 | Y6: Angus | AD6: N/A | AE6: N/A | AI6: =I6 -> 80套散件
A7: 45726 | B7: WAL-MART STORES INC. USA | C7: 美国 | D7: 4500159641 | E7: 0902763014 | F7: 4500159641-10 | G7: 77673TQ1-S001 | H7: 迷你冰箱4pcs/箱 | I7: 616 | J7: 0 | K7: 4 | L7: =I7/K7 -> 154 | M7: 45770 | N7: 45766 | O7: 4/25 第三方抽办 | R7: 45727 | S7: 有 | T7: 45727 | X7: 日期码格式：ZURU DGYYYYMMDD CHINA(日期避开周末和法定节假日即可） 日期：按实际生产日期 Packaging Info: 77673TQ1-S001 1.包装要求： MA 1L A版收缩膜+MA 5L 收藏指南+MA 说明书+MA playset 每pcs产品上要贴1张RFID贴纸，贴纸由ZURU提供，贴纸位置请严格按照我们签回的签板； Remark: 77673TQ1-S001 1.包装要求： MA 1L A版收缩膜+MA 5L 收藏指南+MA 说明书+MA playset 每pcs产品上要贴1张RFID贴纸，贴纸由ZURU提供，贴纸位置请严格按照我们签回的签板； 2. 外箱印刷带条码的RFID箱唛：RFID紫色色带+WM Dept.图标+RFID图标+ITF-14条码，四面右下角印刷ZURU logo, ITFF条码只印刷在正唛一面，在加印的时候确保 条形码能扫描出来，外箱侧面任一角落加印："MADE IN CHINA" 字样； 3. 在产品上和包装上要有日期码、以及要有MADE IN CHINA和ZURU字样； 4. 产品如有扎带口要剪平，不能刮手。 5. 此单需要抽板和验货，抽板时间预计4/23，请多备料 6. 此单以loose carton出货，4pcs/PDQ/CTN | Y7: Maggie Xie | Z7: 5 | AA7: =Z7*I7 -> 3080 | AD7: 77673TQ1-S001 | AE7: 已入 | AG7: 已完成 | AI7: 东莞安排 | AJ7: =AI7-I7 -> #VALUE! | AN7: =I7 -> 616 | AR7: =I7 -> 616 | AU7: =I7 -> 616 | AW7: =I7 -> 616 | BH7: =I7/4 -> 154
A8: 45761 | D8: ZMPO250315 | G8: 77673-S001 | H8: 迷你冰箱12pcs/箱 | I8: 720 | J8: 0 | K8: 12 | L8: =I8/K8 -> 60 | M8: 45771 | N8: 45768 | R8: 45761 | S8: 无 | T8: 无 | X8: Remark:大货最新版本/大货标准箱装箱/箱唛参照邮件附件;备注： 收到样品订单后尽快安排 ，此订单麻烦在外箱上备注是海运订单/注意样板品质质量要求要高于大货品质质量 ，送货时必须要附带送货单(没有送货单和QC检验合格报告的仓库一律拒绝收货)，请知悉，谢谢！ | Y8: Angus | AC8: 95176-8.17 | AD8: 77673-S001 | AE8: 已入 | AG8: 已完成 | AI8: 720 | AJ8: 0 | AN8: =I8 -> 720 | AR8: =I8 -> 720 | AU8: =I8 -> 720 | AW8: =I8 -> 720
A9: 45728 | B9: THE WAREHOUSE LIMITED | C9: 新西兰 | D9: 4500159882 | F9: 4500159882-20 | G9: 77673TQ1-S002 | H9: 迷你冰箱 | I9: 608 | J9: 0 | K9: 16 | L9: =I9/K9 -> 38 | M9: 45772 | N9: 45768 | P9: PASS | Q9: 4/25 出货 | R9: 45735 | S9: 无 | T9: 45735 | X9: 日期码格式：ZURU INC(BVI) 标准格式 日期：按实际生产日期 Packaging Info: #77673TQ1: 1.3PCS AG13 BATTERIES(INCLUDED)，有纽扣电池，包装正面和说明书都需要加电池警告语贴纸（法规要求） 2.Filxed Collection #77673需要加UPC贴纸 Remark: 1.MA UPC 英语包装（优先1L英语版本，或者3L/5L含英语都可） 2.此客人不接受易掉落或者剥落或者可直接触碰的闪粉，可降解也不行，但可以接受符合欧洲微塑料标准的珠光粉或者闪片。 | Y9: Abby Liang | Z9: 4.39 | AA9: =Z9*I9 -> 2669.12 | AC9: 95093-8.17 | AD9: 77673TQ1-S002 | AE9: 已入 | AG9: 已完成 | AI9: 东莞安排 | AJ9: =AI9-I9 -> #VALUE! | AN9: =I9 -> 608 | AR9: =I9 -> 608 | AU9: =I9 -> 608 | AW9: =I9 -> 608 | BH9: =I9/4 -> 152
A10: 45728 | B10: THE WAREHOUSE LIMITED | C10: 新西兰 | D10: 4500159886 | F10: 4500159886-20 | G10: 77673TQ1-S002 | H10: 迷你冰箱 | I10: 192 | J10: 0 | K10: 16 | L10: =I10/K10 -> 12 | M10: 45772 | N10: 45768 | P10: PASS | R10: 45735 | S10: 无 | T10: 45735 | X10: 日期码格式：ZURU INC(BVI) 标准格式 日期：按实际生产日期 Packaging Info: #77673TQ1: 1.3PCS AG13 BATTERIES(INCLUDED)，有纽扣电池，包装正面和说明书都需要加电池警告语贴纸（法规要求） 2.Filxed Collection #77673需要加UPC贴纸 Remark: 1.MA UPC 英语包装（优先1L英语版本，或者3L/5L含英语都可） 2.此客人不接受易掉落或者剥落或者可直接触碰的闪粉，可降解也不行，但可以接受符合欧洲微塑料标准的珠光粉或者闪片。 | Y10: Abby Liang | Z10: 4.39 | AA10: =Z10*I10 -> 842.88 | AC10: 95094-8.17 | AD10: 77673TQ1-S002 | AE10: 已入 | AG10: 已完成 | AI10: 东莞安排 | AJ10: =AI10-I10 -> #VALUE! | AN10: =I10 -> 192 | AR10: =I10 -> 192 | AU10: =I10 -> 192 | AW10: =I10 -> 192 | BH10: =I10/4 -> 48
A11: 45734 | B11: ZURU LLC | C11: 美国 | D11: 4500160498 | E11: B0DR3VG3YH | F11: 4500160498-30 | G11: 77673-S001-MTS | H11: 迷你冰箱12pcs/箱 | I11: 4548 | J11: 0 | K11: 12 | L11: =I11/K11 -> 379 | M11: 45777 | N11: 45773 | P11: PASS | R11: 45734 | S11: 无 | T11: 无 | X11: 日期码格式：ZURU INC(BVI) 标准格式 日期：按实际生产日期 Packaging Info: #77673: MA 1L UPC版包装，出口美国。 Remark: 1.Amazon domestic 订单。出口美国。外箱最长边不能超过25" （超过了，case pack只能为1），不符合要求的大货，一律不接受。 2.无第三方验货/测试要求。 3.日期码使用ZURU标准版本。 4.邮包盒要印刷日期码。 | Y11: Kelly Shen/Mia Pan/P | Z11: 4.1 | AA11: =Z11*I11 -> 18646.8 | AD11: 77673-S001 | AE11: 已入 | AG11: OK | AI11: 4548 | AJ11: =AI11-I11 -> 0 | AN11: =I11 -> 4548 | AR11: =I11 -> 4548 | AU11: =I11 -> 4548 | AW11: =I11 -> 4548
A12: 45728 | B12: ALL BRANDS TOYS PTY LTD | C12: 澳大利亚 | D12: 4500159576 | E12: 83718 | F12: 4500159576-20 | G12: 77673-S003 | H12: 迷你冰箱6pcs/箱 | I12: 1800 | J12: 0 | K12: 6 | L12: =I12/K12 -> 300 | M12: 45777 | N12: 45773 | P12: PASS | R12: 45728 | S12: 无 | T12: 45728 | X12: 日期码格式：ZURU INC(BVI) 标准格式 日期：按实际生产日期 Packaging Info: 2. 77673: MA_UPC版本包装（MA首选1L，如无1L可用多语且含英语的配套多语UPC包装）+ 1张小纽扣电池警告语贴纸贴于包装正面 + 2张大纽扣电池警告语贴纸附 带进口商信息分别贴于包装背面以及说明书上 Remark: 1.按实际生产日期; 2.出澳大利亚，请按照相应标准生产; | Y12: Lydia Wu | Z12: 4.1 | AA12: =Z12*I12 -> 7380 | AC12: 95160-8.17 | AD12: 77673-S003 | AE12: 已入 | AG12: OK | AI12: 1800 | AJ12: =AI12-I12 -> 0 | AN12: =I12 -> 1800 | AR12: =I12 -> 1800 | AU12: =I12 -> 1800 | AW12: =I12 -> 1800
A13: 45729 | B13: KMART AUSTRALIA LTD | C13: 澳大利亚 | D13: 4500160026 | E13: 20627370 | F13: 4500160026-20 | G13: 77673-S001 | H13: 迷你冰箱12pcs/箱 | I13: 3300 | J13: 0 | K13: 12 | L13: =I13/K13 -> 275 | M13: 45786 | N13: 45782 | P13: PASS | R13: 45748 | S13: 有 | T13: 外箱贴纸 | X13: 日期码格式：ZURU INC(BVI) 标准格式 日期：按实际生产日期 Packaging Info: 77673-S001: MA英语UPC版本包装（收缩膜和说明书, MA首选1L，如无1L可用多语且含英语的配套多语包装) + 1张说明书纽扣电池警告语贴纸+ 1张收缩膜纽扣电池 警告语贴纸+ 1张防盗贴纸+箱唛 + 外箱SSCC Label Remark: 1.请务必按时完货，验货。并且按期送货入货代指定仓库，如果晚了导致船期Delay将会有罚金产生或者客户要求空运，所产生的罚金和空运费由工厂承担。 2.SSCC 外箱贴纸请同纸箱瓦楞纸方向（竖纹向）垂直，即外箱贴纸横着贴(注意条码不要被胶带粘住），贴1pc，贴1面正唛，封箱胶纸不能挡住贴纸内容。外箱贴纸 离外箱边距离不少于2cm。 3.外箱材质为ZURU标准； 4.此单需使用KMART封箱胶上下工字型封箱;从2019年6月开始，要用KMART 新版封箱胶带，此单要用"ANKO"封箱胶带 5.此单出口澳大利亚，请按相应的澳新标准生产； 6.产品和包装上生产批号的显示格式ZURU标准日期码格式 7.外箱信息不可手写，重量和体积需要与实际的一致(不可手写） 8. 每款item装箱后的G.W.超过10KG或者CBM超过0.13,(9.5KG或者以上，四舍五入后也属于10KG) 需在外箱上加印超 重或者Bulky LOGO，若发现我们资料没有，请 帮忙提醒 1)重量超过10kg但不超过16kg且CBM不超过0.13,10-16kg 超重logo 2）CBM超过0.13且重量少于17kg，bulky logo 3）不属于以上两种情况，需要使用相应重量范围内的超重logo 4）超重logo需要在外箱四面都印刷(箱唛右上角，两面侧唛超重logo需要尽量靠近毛重)，尺寸为:110mm height* 95mm width 9. 实际外箱重量跟印在箱唛上的数据差异不能超3%，尺寸按实际数据印刷 | Y13: Lydia Wu | Z13: 4.19 | AA13: =Z13*I13 -> 13827 | AC13: 95095-8.17 | AD13: 77673-S001 | AE13: 已入 | AG13: 已完成 | AI13: 3300 | AJ13: =AI13-I13 -> 0 | AN13: =I13 -> 3300 | AR13: =I13 -> 3300 | AU13: =I13 -> 3300 | AW13: =I13 -> 3300
A14: 45729 | B14: KMART AUSTRALIA LTD(NEW ZEALAND) | C14: 新西兰 | D14: 4500160027 | E14: 20627371 | F14: 4500160027-20 | G14: 77673-S001 | H14: 迷你冰箱12pcs/箱 | I14: 432 | J14: 0 | K14: 12 | L14: =I14/K14 -> 36 | M14: 45786 | N14: 45782 | P14: PASS | R14: 45748 | S14: 有 | T14: 外箱贴纸 | X14: 日期码格式：ZURU INC(BVI) 标准格式 日期：按实际生产日期 Packaging Info: 77673-S001: MA英语UPC版本包装（收缩膜和说明书, MA首选1L，如无1L可用多语且含英语的配套多语包装) + 1张说明书纽扣电池警告语贴纸+ 1张收缩膜纽扣电池 警告语贴纸+ 1张防盗贴纸+箱唛 + 外箱SSCC Label (贴纸以及位置图翻单PO#4500160026） Remark: 1.请务必按时完货，验货。并且按期送货入货代指定仓库，如果晚了导致船期Delay将会有罚金产生或者客户要求空运，所产生的罚金和空运费由工厂承担。 2.SSCC 外箱贴纸请同纸箱瓦楞纸方向（竖纹向）垂直，即外箱贴纸横着贴(注意条码不要被胶带粘住），贴1pc，贴1面正唛，封箱胶纸不能挡住贴纸内容。外箱贴纸 离外箱边距离不少于2cm。 3.外箱材质为ZURU标准； 4.此单需使用KMART封箱胶上下工字型封箱;从2019年6月开始，要用KMART 新版封箱胶带，此单要用"ANKO"封箱胶带 5.此单出口新西兰，请按相应的澳新标准生产； 6.产品和包装上生产批号的显示格式ZURU标准日期码格式 7.外箱信息不可手写，重量和体积需要与实际的一致(不可手写） 8. 每款item装箱后的G.W.超过10KG或者CBM超过0.13,(9.5KG或者以上，四舍五入后也属于10KG) 需在外箱上加印超 重或者Bulky LOGO，若发现我们资料没有，请 帮忙提醒 1)重量超过10kg但不超过16kg且CBM不超过0.13,10-16kg 超重logo 2）CBM超过0.13且重量少于17kg，bulky logo 3）不属于以上两种情况，需要使用相应重量范围内的超重logo 4）超重logo需要在外箱四面都印刷(箱唛右上角，两面侧唛超重logo需要尽量靠近毛重)，尺寸为:110mm height* 95mm width 9. 实际外箱重量跟印在箱唛上的数据差异不能超3%，尺寸按实际数据印刷 | Y14: Lydia Wu | Z14: 4.19 | AA14: =Z14*I14 -> 1810.08 | AC14: 95097-8.17 | AD14: 77673-S001 | AE14: 已入 | AG14: 已完成 | AI14: 432 | AJ14: =AI14-I14 -> 0 | AN14: =I14 -> 432 | AR14: =I14 -> 432 | AU14: =I14 -> 432 | AW14: =I14 -> 432
A15: 45744 | B15: WALMART INC. | C15: 美国 | D15: 4500161759 | E15: 0904512308 STATESBORO | F15: 4500161759-10 | G15: 77673TQ1-S001 | H15: 迷你冰箱4pcs/箱 | I15: 512 | J15: 0 | K15: 4 | L15: =I15/K15 -> 128 | M15: 45785 | N15: 45782 | O15: 5/9 第三方验货 | P15: PASS | R15: 外箱印刷带条码的RFID箱唛：RFID紫色色带+WM Dept.图标+RFID图标+ITF-14条码，四面右下角印刷ZURU logo, ITFF条码只印刷在正唛一面，在加印的时候确保 条形码能扫描出来，外箱侧面任一角落加印："MADE IN CHINA" 字样； | S15: 无 | T15: RFID贴纸 | V15: RFID贴纸 | X15: 日期码格式：ZURU DGYYYYMMDD CHINA(日期避开周末和法定节假日即可） 日期：按实际生产日期 Packaging Info: 77673TQ1-S001 1.包装要求： MA 1L A版收缩膜+MA 5L 收藏指南+MA 说明书+MA playset，翻单：4500159641 每pcs产品上要贴1张RFID贴纸，贴纸由ZURU提供，贴纸位置请严格按照我们签回的签板； Remark: 77673TQ1-S001 1.包装要求： MA 1L A版收缩膜+MA 5L 收藏指南+MA 说明书+MA playset，翻单：4500159641 每pcs产品上要贴1张RFID贴纸，贴纸由ZURU提供，贴纸位置请严格按照我们签回的签板； 2. 外箱印刷带条码的RFID箱唛：RFID紫色色带+WM Dept.图标+RFID图标+ITF-14条码，四面右下角印刷ZURU logo, ITFF条码只印刷在正唛一面，在加印的时候确保 条形码能扫描出来，外箱侧面任一角落加印："MADE IN CHINA" 字样； 3. 在产品上和包装上要有日期码、以及要有MADE IN CHINA和ZURU字样； 4. 产品如有扎带口要剪平，不能刮手。 5. 此单需要验货，请多备料 6. 此单以loose carton出货，4pcs/PDQ/CTN | Y15: Maggie Xie | Z15: 5 | AA15: =Z15*I15 -> 2560 | AD15: 77673TQ1-S001 | AE15: 已入 | AG15: 已完成 | AI15: 512 | AJ15: =AI15-I15 -> 0 | AN15: =I15 -> 512 | AR15: =I15 -> 512 | AU15: =I15 -> 512 | AW15: =I15 -> 512 | BH15: =I15/4 -> 128
A16: 45744 | B16: WALMART INC. | C16: 美国 | D16: 4500161759 | E16: 0904512292 SUFFOLK | F16: 4500161759-20 | G16: 77673TQ1-S001 | H16: 迷你冰箱4pcs/箱 | I16: 656 | J16: 0 | K16: 4 | L16: =I16/K16 -> 164 | M16: 45785 | N16: 45782 | O16: 5/9 第三方验货 | P16: PASS | R16: 外箱印刷带条码的RFID箱唛：RFID紫色色带+WM Dept.图标+RFID图标+ITF-14条码，四面右下角印刷ZURU logo, ITFF条码只印刷在正唛一面，在加印的时候确保 条形码能扫描出来，外箱侧面任一角落加印："MADE IN CHINA" 字样； | S16: 无 | T16: RFID贴纸 | V16: RFID贴纸 | X16: 日期码格式：ZURU DGYYYYMMDD CHINA(日期避开周末和法定节假日即可） 日期：按实际生产日期 Packaging Info: 77673TQ1-S001 1.包装要求： MA 1L A版收缩膜+MA 5L 收藏指南+MA 说明书+MA playset，翻单：4500159641 每pcs产品上要贴1张RFID贴纸，贴纸由ZURU提供，贴纸位置请严格按照我们签回的签板； Remark: 77673TQ1-S001 1.包装要求： MA 1L A版收缩膜+MA 5L 收藏指南+MA 说明书+MA playset，翻单：4500159641 每pcs产品上要贴1张RFID贴纸，贴纸由ZURU提供，贴纸位置请严格按照我们签回的签板； 2. 外箱印刷带条码的RFID箱唛：RFID紫色色带+WM Dept.图标+RFID图标+ITF-14条码，四面右下角印刷ZURU logo, ITFF条码只印刷在正唛一面，在加印的时候确保 条形码能扫描出来，外箱侧面任一角落加印："MADE IN CHINA" 字样； 3. 在产品上和包装上要有日期码、以及要有MADE IN CHINA和ZURU字样； 4. 产品如有扎带口要剪平，不能刮手。 5. 此单需要验货，请多备料 6. 此单以loose carton出货，4pcs/PDQ/CTN | Y16: Maggie Xie | Z16: 5 | AA16: =Z16*I16 -> 3280 | AC16: ZB00239-5.13 | AD16: 77673TQ1-S001 | AE16: 已入 | AG16: 已完成 | AI16: 656 | AJ16: =AI16-I16 -> 0 | AN16: =I16 -> 656 | AR16: =I16 -> 656 | AU16: =I16 -> 656 | AW16: =I16 -> 656 | BH16: =I16/4 -> 164
A17: 45734 | B17: ZURU Germany GMBH | C17: 德国 | D17: 4500160634 | E17: 5200006405 | F17: 4500160634-20 | G17: 77673TQ1-S001-MTS | H17: 迷你冰箱4pcs/箱 | I17: 800 | J17: 0 | K17: 4 | L17: =I17/K17 -> 200 | M17: 45786 | N17: 45782 | P17: PASS | R17: 45735 | S17: 无 | T17: 多语折叠警告语贴纸（翻单4500157858）+WEEE通用黑色书纸带电池走货 | V17: 所有电子产品身上需要加字唛，为ZURU FRANCE 地址 (如无电子产品，或者产品布标有此地址，可忽略此信息) ZURU France 1/3, Rue d'Argenteuil 95210 SAINT-GRATIEN, FRANCE | X17: 日期码格式：ZURU INC(BVI) 标准格式 日期：按实际生产日期 Tracking Code: Packaging Info: 77673TQ1: MA_3L PDQ + MA 3L EAN 收缩膜 + 多语折叠警告语贴纸（翻单4500157858） +MA5L收藏指南+ MA 23L说明书+MA纸袋 + WEEE通用黑色书纸带电池走货 EAN # 4894680042773 Remark: 1.德国内销单，需要通过ZURU 验货结果后才能出货 (工厂需要主动提前同ZURU QC预约验货避免延期出货造成不必要麻烦)； 2. 若有特定款有特殊外箱条码要求时,需要明确列出产品款对应的具体外箱条码号码/条码类型 (若无,可以忽略此需求) 3.所有出口欧洲的产品, 法规规定禁止在包装和共公众用的印刷品中使用矿物油中含有的物质, 包装印刷油墨中含有的MOAH/MOSH的质量浓度不能超过1%, 否则出货 到法国被抽检出现问题, 供应商需要对此负责; 4. date code: 外箱日期码要晚于或等于产品日期码，不能早于产品的日期码 5. 所有电子产品身上需要加字唛，为ZURU FRANCE 地址 (如无电子产品，或者产品布标有此地址，可忽略此信息) ZURU France 1/3, Rue d'Argenteuil 95210 SAINT-GRATIEN, FRANCE 6. 装柜时需要按照款式号码从小到大一款款依次装,避免终端仓库卸货混乱.若一个柜子涉及到几个不同国家内销单,装柜时需要一个国家装完后再装另一个国家的 产品,依次装柜,避免终端仓库因不同国家不同库位位置卸货混乱. (此点需要同工厂装柜人员强调)" | Y17: SD04 | Z17: 5.03 | AA17: =Z17*I17 -> 4024 | AC17: 95096-8.17 | AD17: 77673TQ1-S001-MTS | AE17: 已入 | AG17: 已完成 | AI17: 800 | AJ17: =AI17-I17 -> 0 | AN17: =I17 -> 800 | AS17: =I17 -> 800 | AU17: =I17 -> 800 | AW17: =I17 -> 800 | BI17: =I17/4 -> 200
A18: 45671 | B18: Smyths Toys EU HQ UC | C18: 德国 | D18: 4500155594 | E18: 4400459913 | F18: 4500155594-10 | G18: 77673TQ1-S003 | H18: 迷你冰箱 | I18: 3008 | J18: 0 | K18: 8 | L18: =I18/K18 -> 376 | M18: 45787 | N18: 45783 | O18: 所有电子产品身上需要加字唛，为ZURU FRANCE 地址 (如无电子产品，或者产品布标有此地址，可忽略此信息) ZURU France 1/3, Rue d'Argenteuil 95210 SAINT-GRATIEN, FRANCE | P18: PASS | R18: 45671 | S18: 无 | T18: WEEE声明(带电池)走货欧洲通用30L-B版说明书 | X18: 日期码格式：ZURU INC(BVI) 标准格式 日期：按实际生产日期 Packaging Info: 最新MA PDQ(优先3L )+ 客版收缩膜(英法德callout/英法德意荷警语/法国环保logo) +23L 说明书+客版收藏指南(英法德意荷) +客版WEEE声明通用说明书(带电池) EAN: 4894680042773 Remark: 1. 此单出德国，需要满足Zuru Standard欧洲标准测试要求； 2. 请准时出货，推期会有罚款； 3. 出口欧洲，微塑料需符合法规； 4. 所有电子产品身上需要加字唛，为ZURU FRANCE 地址 (如无电子产品，或者产品布标有此地址，可忽略此信息) ZURU France 1/3, Rue d'Argenteuil 95210 SAINT-GRATIEN, FRANCE 5. 标准配比 | Y18: Shirley Zhou | Z18: 5.1379 | AA18: =Z18*I18 -> 15454.803 | AC18: 94982-8.17 | AD18: 77673TQ1-S003 | AE18: 已入 | AG18: 已完成 | AI18: 3008 | AJ18: =AI18-I18 -> 0 | AN18: =I18 -> 3008 | AW18: =I18 -> 3008 | BD18: =I18 -> 3008 | BE18: =I18 -> 3008 | BI18: =I18/4 -> 752
A19: 45733 | B19: WAL-MART CANADA CORP. | C19: 加拿大 | D19: 4500160504 | E19: 9900923471 | F19: 4500160504-40 | G19: 77673-S002 | H19: 迷你冰箱 | I19: 884 | J19: 0 | K19: 2 | L19: =I19/K19 -> 442 | M19: 45776 | N19: 45772 | O19: 5/19 第三方验货，#77673需于2025/4/18安排签版, 签样数量：空PDQ2PCS, 大货样各4PCS+散件3套; #77673 需于2025/4/28安排抽办测试, 抽办数量：大货各4 SETS | P19: PASS | R19: 45748 | S19: 无 | T19: 45734 | X19: 日期码格式：ZURU INC(BVI) 标准格式 日期：按实际生产日期 Packaging Info: #77673： MA3L收缩膜+UPC贴纸(UPC:193052079404)+MA23L说明书+MA5L收藏指南+MA5L,UV胶瓶身贴 产品配比： 7 Assortment, Polar bear: Penguin: Walrus: Mammoth: Owl: Seal: Snow man=10:10:10:10:10:8:2. Snow man is the rare item. Remark: 1. 此单有箱唛； 3. 此单有第三方验货，烦请多备包装物料； 5. #77673需于2025/4/18安排签版, 签样数量：空PDQ2PCS, 大货样各4PCS+齐套散件3套; 9. #77673 需于2025/4/28安排抽办测试, 抽办数量：大货4 pcs+齐套散件4SETS; 11. UPC贴纸：必须在原来错误的条码上用黑色粗头笔涂黑直至不能扫描，再贴上正确的UPC; ********************* a. 请确保产品符合1999年版本的加拿大环境保护法(CEPA)和2012年禁止某些有毒物质法规的要求。该产品不含任何在加拿大禁用的化学物质，包括但不限于有毒物 质清单中列出的化学物质，并且在为加拿大沃尔玛生产产品期间没有使用任何禁用化学物质。 Supplier certify that the products comply with the requirements of Canadian Environmental Protection Act, 1999 (CEPA), Prohibition of Certain To xic Substances Regulations, 2012. The products do not contain any chemicals that are banned in Canada, including but not limited to those listed in the Toxic Substances List and no banned chemicals were used during the manufacturing of product for Walmart Canada. 附件列表： (1) Letter of Guarantee for Canada banned chemicals - (1-5CA) b. 请确保产品在均质材料中的汞浓度不超过0.1%（按重量计）。 Supplier certify that the WAL-MART vendor products does not have a mercury concentration of more than 0.1% by weight in homogeneous material. 附件列表： (1) Letter of Guarantee for Mercury COC c. 请确保产品的塑料材料不含以下物质（SOR 2011-17 27B): Supplier certify that the plastic materials do not contain the following substances(SOR 2011-17 27B): (a) carbon tetrachloride or any substance that contains it; (b) methyl alcohol or any substance thay contains >1.0%; (c) petroleum distillates or any substance that contains >10% weight to volume of petroleum distillates; (d) benzene; (e) turpentine or any substance that contains >10% weight to volume of turpentine; (f) boric acid or salts of boric acid; or (g) ethyl ether. 附件列表： (1) Letter of Guarantee for WM CA-Other prohibited substances in plastic(less than 3 years) | Y19: Monica Zhou | Z19: 4.1 | AA19: =Z19*I19 -> 3624.4 | AC19: 95077-8.17 | AD19: 77673-S002 | AE19: 已入 | AG19: 已完成 | AI19: 东莞安排 | AJ19: =AI19-I19 -> #VALUE! | AN19: =I19 -> 884 | AS19: =I19 -> 884 | AU19: =I19 -> 884 | AW19: =I19 -> 884
A20: 45726 | B20: 360 SALES SOLUTIONS INC | C20: 加拿大 | D20: 4500159666 | E20: 2025ZURU11 | F20: 4500159666-20 | G20: 77673-S001 | H20: 迷你冰箱12pcs/箱 | I20: 15396 | J20: 0 | K20: 12 | L20: =I20/K20 -> 1283 | M20: 45786 | N20: 45782 | P20: PASS | Q20: 5/17 SI | R20: 45727 | S20: 无 | T20: 无 | X20: 日期码格式： 标准格式 日期：按实际生产日期 Packaging Info: 77673 MA 多语（含英法）EAN包装+UPC贴纸， UPC号码193052079404 Remark: 出加拿大 Zuru验货.日期跟踪码：产品外包装及产品本身都必须有日期跟踪码，ZURU标准格式日期码。（箱唛日期码按跟单提供格式） | Y20: Summer Mo | Z20: 4.1 | AA20: =Z20*I20 -> 63123.6 | AC20: 95002-8.17 | AD20: 77673-S001-3L | AE20: 已入 | AG20: 预计5/14验货 | AI20: 东莞安排 | AJ20: =AI20-I20 -> #VALUE! | AN20: =I20 -> 15396 | AS20: =I20 -> 15396 | AU20: =I20 -> 15396 | AW20: =I20 -> 15396
A21: 45744 | B21: WALMART INC. | C21: 美国 | D21: 4500161760 | E21: 0904512282 | F21: 4500161760-10 | G21: 77673TQ1-S001 | H21: 迷你冰箱4pcs/箱 | I21: 760 | J21: 0 | K21: 4 | L21: =I21/K21 -> 190 | M21: 45789 | N21: 45785 | O21: 5/14 第三方验货 | P21: PASS | R21: 外箱印刷带条码的RFID箱唛：RFID紫色色带+WM Dept.图标+RFID图标+ITF-14条码，四面右下角印刷ZURU logo, ITFF条码只印刷在正唛一面，在加印的时候确保 条形码能扫描出来，外箱侧面任一角落加印："MADE IN CHINA" 字样； | S21: 无 | T21: RFID贴纸 | V21: RFID贴纸 | X21: 日期码格式：ZURU DGYYYYMMDD CHINA(日期避开周末和法定节假日即可） 日期：按实际生产日期 Packaging Info: 77673TQ1-S001 1.包装要求： MA 1L A版收缩膜+MA 5L 收藏指南+MA 说明书+MA playset，翻单：4500159641 每pcs产品上要贴1张RFID贴纸，贴纸由ZURU提供，贴纸位置请严格按照我们签回的签板； Remark: 77673TQ1-S001 1.包装要求： MA 1L A版收缩膜+MA 5L 收藏指南+MA 说明书+MA playset，翻单：4500159641 每pcs产品上要贴1张RFID贴纸，贴纸由ZURU提供，贴纸位置请严格按照我们签回的签板； 2. 外箱印刷带条码的RFID箱唛：RFID紫色色带+WM Dept.图标+RFID图标+ITF-14条码，四面右下角印刷ZURU logo, ITFF条码只印刷在正唛一面，在加印的时候确保 条形码能扫描出来，外箱侧面任一角落加印："MADE IN CHINA" 字样； 3. 在产品上和包装上要有日期码、以及要有MADE IN CHINA和ZURU字样； 4. 产品如有扎带口要剪平，不能刮手。 5. 此单需要验货，请多备料 6. 此单以loose carton出货，4pcs/PDQ/CTN | Y21: Maggie Xie | Z21: 5 | AA21: =Z21*I21 -> 3800 | AD21: 77673TQ1-S001 | AE21: 已入 | AG21: 已完成 | AI21: 760 | AJ21: =AI21-I21 -> 0 | AN21: =I21 -> 760 | AR21: =I21 -> 760 | AU21: =I21 -> 760 | AW21: =I21 -> 760 | BH21: =I21/4 -> 190
A22: 45726 | B22: WAL-MART STORES INC. USA | C22: 美国 | D22: 4500159654 | E22: 0902421331 SAVANNAH | F22: 4500159654-10 | G22: 77673TQ1-S001 | H22: 迷你冰箱4pcs/箱 | I22: 2768 | J22: 0 | K22: 4 | L22: =I22/K22 -> 692 | M22: 45789 | N22: 45785 | O22: 5/14 第三方验货 | P22: PASS | R22: 45727 | S22: 有 | T22: 45727 | V22: 每pcs产品上要贴1张RFID贴纸，贴纸由ZURU提供，贴纸位置请严格按照我们签回的签板，粉色艾利贴纸（不干胶打印） | X22: 日期码格式：ZURU DGYYYYMMDD CHINA(日期避开周末和法定节假日即可） 日期：按实际生产日期 Packaging Info: 77673TQ1-S001 1.包装要求： MA 1L A版收缩膜+MA 5L 收藏指南+MA 说明书+MA playset 每pcs产品上要贴1张RFID贴纸，贴纸由ZURU提供，贴纸位置请严格按照我们签回的签板； Remark: 77673TQ1-S001 1.包装要求： MA 1L A版收缩膜+MA 5L 收藏指南+MA 说明书+MA playset 每pcs产品上要贴1张RFID贴纸，贴纸由ZURU提供，贴纸位置请严格按照我们签回的签板； 2. 外箱印刷带条码的RFID箱唛：RFID紫色色带+WM Dept.图标+RFID图标+ITF-14条码+粉色艾利贴纸（不干胶打印），四面右下角印刷ZURU logo, ITFF条码只印刷在 正唛一面，在加印的时候确保条形码能扫描出来，1张粉红色贴纸贴在正唛对角线，外箱侧面任一角落加印："MADE IN CHINA" 字样； 3. 在产品上和包装上要有日期码、以及要有MADE IN CHINA和ZURU字样； 4. 产品如有扎带口要剪平，不能刮手。 5. 此单需要验货，请多备料 6. 此单以loose carton出货，4pcs/PDQ/CTN | Y22: Maggie Xie | Z22: 5 | AA22: =Z22*I22 -> 13840 | AD22: 77673TQ1-S001 | AE22: 已入 | AG22: 已完成 | AI22: 2768 | AJ22: =AI22-I22 -> 0 | AN22: =I22 -> 2768 | AR22: =I22 -> 2768 | AU22: =I22 -> 2768 | AW22: =I22 -> 2768 | BH22: =I22/4 -> 692
A23: 45726 | B23: WAL-MART STORES INC. USA | C23: 美国 | D23: 4500159654 | E23: 0902421341 SUFFOLK | F23: 4500159654-20 | G23: 77673TQ1-S001 | H23: 迷你冰箱4pcs/箱 | I23: 3560 | J23: 0 | K23: 4 | L23: =I23/K23 -> 890 | M23: 45789 | N23: 45785 | O23: 5/14 第三方验货 | P23: PASS | R23: 45727 | S23: 有 | T23: 45727 | V23: 每pcs产品上要贴1张RFID贴纸，贴纸由ZURU提供，贴纸位置请严格按照我们签回的签板，粉色艾利贴纸（不干胶打印） | X23: 日期码格式：ZURU DGYYYYMMDD CHINA(日期避开周末和法定节假日即可） 日期：按实际生产日期 Packaging Info: 77673TQ1-S001 1.包装要求： MA 1L A版收缩膜+MA 5L 收藏指南+MA 说明书+MA playset 每pcs产品上要贴1张RFID贴纸，贴纸由ZURU提供，贴纸位置请严格按照我们签回的签板； Remark: 77673TQ1-S001 1.包装要求： MA 1L A版收缩膜+MA 5L 收藏指南+MA 说明书+MA playset 每pcs产品上要贴1张RFID贴纸，贴纸由ZURU提供，贴纸位置请严格按照我们签回的签板； 2. 外箱印刷带条码的RFID箱唛：RFID紫色色带+WM Dept.图标+RFID图标+ITF-14条码+粉色艾利贴纸（不干胶打印），四面右下角印刷ZURU logo, ITFF条码只印刷在 正唛一面，在加印的时候确保条形码能扫描出来，1张粉红色贴纸贴在正唛对角线，外箱侧面任一角落加印："MADE IN CHINA" 字样； 3. 在产品上和包装上要有日期码、以及要有MADE IN CHINA和ZURU字样； 4. 产品如有扎带口要剪平，不能刮手。 5. 此单需要验货，请多备料 6. 此单以loose carton出货，4pcs/PDQ/CTN | Y23: Maggie Xie | Z23: 5 | AA23: =Z23*I23 -> 17800 | AD23: 77673TQ1-S001 | AE23: 已入 | AG23: 已完成 | AI23: 3560 | AJ23: =AI23-I23 -> 0 | AN23: =I23 -> 3560 | AR23: =I23 -> 3560 | AU23: =I23 -> 3560 | AW23: =I23 -> 3560 | BH23: =I23/4 -> 890
A24: 45726 | B24: WAL-MART STORES INC. USA | C24: 美国 | D24: 4500159654 | E24: 0902421349 RIDGEVILLE SC | F24: 4500159654-30 | G24: 77673TQ1-S001 | H24: 迷你冰箱4pcs/箱 | I24: 3344 | J24: 0 | K24: 4 | L24: =I24/K24 -> 836 | M24: 45789 | N24: 45785 | O24: 5/14 第三方验货 | P24: PASS | R24: 45727 | S24: 有 | T24: 45727 | V24: 每pcs产品上要贴1张RFID贴纸，贴纸由ZURU提供，贴纸位置请严格按照我们签回的签板，粉色艾利贴纸（不干胶打印） | X24: 日期码格式：ZURU DGYYYYMMDD CHINA(日期避开周末和法定节假日即可） 日期：按实际生产日期 Packaging Info: 77673TQ1-S001 1.包装要求： MA 1L A版收缩膜+MA 5L 收藏指南+MA 说明书+MA playset 每pcs产品上要贴1张RFID贴纸，贴纸由ZURU提供，贴纸位置请严格按照我们签回的签板； Remark: 77673TQ1-S001 1.包装要求： MA 1L A版收缩膜+MA 5L 收藏指南+MA 说明书+MA playset 每pcs产品上要贴1张RFID贴纸，贴纸由ZURU提供，贴纸位置请严格按照我们签回的签板； 2. 外箱印刷带条码的RFID箱唛：RFID紫色色带+WM Dept.图标+RFID图标+ITF-14条码+粉色艾利贴纸（不干胶打印），四面右下角印刷ZURU logo, ITFF条码只印刷在 正唛一面，在加印的时候确保条形码能扫描出来，1张粉红色贴纸贴在正唛对角线，外箱侧面任一角落加印："MADE IN CHINA" 字样； 3. 在产品上和包装上要有日期码、以及要有MADE IN CHINA和ZURU字样； 4. 产品如有扎带口要剪平，不能刮手。 5. 此单需要验货，请多备料 6. 此单以loose carton出货，4pcs/PDQ/CTN | Y24: Maggie Xie | Z24: 5 | AA24: =Z24*I24 -> 16720 | AD24: 77673TQ1-S001 | AE24: 已入 | AG24: 已完成 | AI24: 3344 | AJ24: =AI24-I24 -> 0 | AN24: =I24 -> 3344 | AR24: =I24 -> 3344 | AU24: =I24 -> 3344 | AW24: =I24 -> 3344 | BH24: =I24/4 -> 836
A25: 45755 | B25: ZURU Denmark ApS | C25: 丹麦 | D25: 4500162820 | E25: 5200006528 | F25: 4500162820-20 | G25: 77673TQ1-S001-MTS | H25: 迷你冰箱4pcs/箱 | I25: 2444 | J25: 0 | K25: 4 | L25: =I25/K25 -> 611 | M25: 45789 | N25: 45785 | P25: PASS | R25: 45757 | S25: 无 | T25: 45764 | X25: 日期码格式：ZURU INC(BVI) 标准格式 日期：按实际生产日期 Packaging Info: 77673 MA3L EAN 版本收缩膜+1*多语警告语贴纸+MA 5L 收藏指南+ MA 23L 电池UV 警告语+MA PDQ （语言不限） Remark: 1.北欧内销单，需要通过ZURU 验货结果后才能出货 (工厂需要主动提前同ZURU QC预约验货避免延期出货造成不必要麻烦)； 2. 产品如含有化学品，需要无硼无香， 3.包装不能含有PVC，使用PET 4. date code: 外箱日期码要晚于产品日期码 5. 装柜时需要按照款式号码从小到大一款款依次装,避免终端仓库卸货混乱.若一个柜子涉及到几个不同国家内销单,装柜时需要一个国家装完后再装另一个国家的 产品,依次装柜,避免终端仓库因不同国家不同库位位置卸货混乱. (此点需要同工厂装柜人员强调)" 6.若有特定款有特殊外箱条码要求时,需要明确列出产品款对应的具体外箱条码号码/条码类型 (若无,可以忽略此需求) 7.所有出口欧洲的产品, 法规规定禁止在包装和共公众用的印刷品中使用矿物油中含有的物质, 包装印刷油墨中含有的MOAH/MOSH的质量浓度不能超过1%, 否则出货 到法国被抽检出现问题, 供应商需要对此负责; 8.带电池出货的产品所用到的电池需要符合欧洲电池新规(EU) 2023-1542。 9.ratio 同MA | Y25: SD04 | Z25: 5.03 | AA25: =Z25*I25 -> 12293.32 | AC25: 94995-8.17 | AD25: 77673TQ1-S001-MTS | AE25: 已入 | AG25: 已完成 | AI25: 2444 | AJ25: =AI25-I25 -> 0 | AN25: =I25 -> 2444 | AS25: =I25 -> 2444 | AU25: =I25 -> 2444 | AW25: =I25 -> 2444 | BI25: =I25/4 -> 611
A26: 45773 | D26: ZMPO250350 | G26: 77673-S001 | H26: 迷你冰箱12pcs/箱 | I26: 108 | J26: 0 | K26: 12 | L26: =I26/K26 -> 9 | M26: 45789 | N26: 45785 | P26: PASS | R26: 45773 | S26: 无 | T26: 无 | X26: Remark:大货最新版本/大货标准箱装箱/箱唛请参照邮件附件;备注：收到样品订单后尽快安排 ，注意样板品质质量要求要高于大货品质要求 ，送货时必须要附带送货单(没有送货单和QC检验合格报告的仓库一律拒绝收货)，请知悉，谢谢！ | Y26: Angus | AC26: 95497-8.17 | AD26: 77673-S001 | AE26: 已入 | AG26: 已完成 | AI26: 108 | AJ26: =AI26-I26 -> 0 | AN26: =I26 -> 108 | AR26: =I26 -> 108 | AU26: =I26 -> 108 | AW26: =I26 -> 108
A27: 45741 | B27: MEIJER DISTRIBUTION, INC. | C27: 美国 | D27: 4500161407 | E27: 216951853 | F27: 4500161407-20 | G27: 77673-S004 | H27: 迷你冰箱4pcs/箱 | I27: 800 | J27: 0 | K27: 4 | L27: =I27/K27 -> 200 | M27: 45790 | N27: 45786 | P27: PASS | R27: 45771 | S27: 无 | T27: 无 | X27: 日期码格式：ZURU INC(BVI) 标准格式 日期： Packaging Info: 1. MA 1L 包装 2. 客人指定箱唛排版 Remark: 出货前 Zuru QC 验货 | Y27: Cherie Li | Z27: 4.1 | AA27: =Z27*I27 -> 3280 | AD27: 77673-S004 | AE27: 已入 | AG27: 已完成 | AI27: 800 | AJ27: =AI27-I27 -> 0 | AN27: =I27 -> 800 | AR27: =I27 -> 800 | AU27: =I27 -> 800 | AW27: =I27 -> 800
A28: 45741 | B28: MEIJER DISTRIBUTION, INC. | C28: 美国 | D28: 4500161408 | E28: 216951858 | F28: 4500161408-20 | G28: 77673-S004 | H28: 迷你冰箱4pcs/箱 | I28: 600 | J28: 0 | K28: 4 | L28: =I28/K28 -> 150 | M28: 45790 | N28: 45786 | P28: PASS | R28: 45771 | S28: 无 | T28: 无 | X28: 日期码格式：ZURU INC(BVI) 标准格式 日期： Packaging Info: 1. MA 1L 包装 2. 客人指定箱唛排版 Remark: 出货前 Zuru QC 验货 | Y28: Cherie Li | Z28: 4.19 | AA28: =Z28*I28 -> 2514 | AD28: 77673-S004 | AE28: 已入 | AG28: 已完成 | AI28: 600 | AJ28: =AI28-I28 -> 0 | AN28: =I28 -> 600 | AR28: =I28 -> 600 | AU28: =I28 -> 600 | AW28: =I28 -> 600
A29: 45737 | B29: ASIA GOAL LIMITED | C29: 香港 | D29: 4500160943 | E29: AG240427-HK | F29: 4500160943-20 | G29: 77673TQ1-S001 | H29: 迷你冰箱4pcs/箱 | I29: 608 | J29: 0 | K29: 4 | L29: =I29/K29 -> 152 | M29: 45792 | N29: 45789 | P29: PASS | R29: 45737 | S29: 无 | T29: 45755 | V29: 客供警告语贴纸 | X29: 日期码格式：ZURU INC(BVI) 标准格式 日期：按实际生产日期 Packaging Info: 77711GQ1 （INT): MA 3L 收缩膜+1张UPC 条码贴纸+ MA 3L PDQ+MA 5L 收藏指南+客供警语贴纸 （1张贴球底部，1张贴说明书，1张贴收藏指南） 77673TQ1:MA 1L 收缩膜+MA 1L PDQ+MA 5L 收藏指南+MA 说明书+1张客供警语贴纸+1张客供电池警语贴纸+1张客供中文警告说明书） Remark: 此单出香港 | Y29: Doris Shou | Z29: 5 | AA29: =Z29*I29 -> 3040 | AC29: 95022-8.17 | AD29: 77673TQ1-S001 | AE29: 已入 | AG29: 已完成 | AI29: 608 | AJ29: =AI29-I29 -> 0 | AN29: =I29 -> 608 | AS29: =I29 -> 608 | AU29: =I29 -> 608 | AW29: =I29 -> 608 | BI29: =I29/4 -> 152
A30: 45742 | B30: ASIA GOAL LIMITED TAIWAN BRANCH (H. | C30: 台湾 | D30: 4500161426 | E30: AG240431-TW | F30: 4500161426-20 | G30: 77673TQ1-S001 | H30: 迷你冰箱4pcs/箱 | I30: 240 | J30: 0 | K30: 4 | L30: =I30/K30 -> 60 | M30: 45792 | N30: 45789 | P30: PASS | R30: 45742 | S30: 无 | T30: 45755 | X30: 日期码格式：ZURU INC(BVI) 标准格式 日期：按实际生产日期 Packaging Info: 77673TQ1：MA 1L 收缩膜+MA 1L PDQ+MA 5L 收藏指南+MA 说明书+1张警语贴纸 Remark: 此单出TW | Y30: Doris Shou | Z30: 5 | AA30: =Z30*I30 -> 1200 | AC30: 95068-8.17 | AD30: 77673TQ1-S001 | AE30: 已入 | AG30: 已完成 | AI30: 240 | AJ30: =AI30-I30 -> 0 | AN30: =I30 -> 240 | AR30: =I30 -> 240 | AU30: =I30 -> 240 | AW30: =I30 -> 240 | BI30: =I30/4 -> 60
A31: 45757 | B31: PPTOYS PTE LTD (SG) | C31: 新加坡 | D31: 4500163177 | E31: ZU25032701SG | F31: 4500163177-20 | G31: 77673-S001 | H31: 迷你冰箱12pcs/箱 | I31: 720 | J31: 0 | K31: 12 | L31: =I31/K31 -> 60 | M31: 45792 | N31: 45789 | P31: PASS | R31: 45758 | S31: 无 | T31: 45762 | X31: 日期码格式：ZURU INC(BVI) 标准格式 日期：按实际生产日期 Packaging Info: 1. 77673因系统问题，暂时开40GP，待系统维护后会改成20GP发过来。 2. 77673-MA UPC包装（优先1L)+1张进口商贴纸 77673进口商贴纸资料待提供。 Remark: 77673-Filxed Collection， 3PCS AG13 BATTERIES(INCLUDED) | Y31: Emma Wu | Z31: 4.18 | AA31: =Z31*I31 -> 3009.6 | AC31: 95067-8.17 | AD31: 77673-S001 | AE31: 已入 | AG31: 已完成 | AI31: 东莞安排 | AJ31: =AI31-I31 -> #VALUE! | AN31: =I31 -> 720 | AR31: =I31 -> 720 | AU31: =I31 -> 720 | AW31: =I31 -> 720
A32: 45733 | B32: WAL-MART CANADA CORP. | C32: 加拿大 | D32: 4500160504 | E32: 9900923472 | F32: 4500160504-50 | G32: 77673-S002 | H32: 迷你冰箱 | I32: 10 | J32: 0 | K32: 2 | L32: =I32/K32 -> 5 | M32: 45793 | N32: 45789 | O32: 5/19 第三方验货，77673需于2025/4/18安排签版, 签样数量：空PDQ2PCS, 大货样各4PCS+齐套散件3套; 9. #77673 需于2025/4/28安排抽办测试, 抽办数量：大货4 pcs+齐套散件4SETS; | P32: PASS | R32: 45748 | S32: 无 | T32: 45734 | X32: 日期码格式：ZURU INC(BVI) 标准格式 日期：按实际生产日期 Packaging Info: #77673： MA3L收缩膜+UPC贴纸(UPC:193052079404)+MA23L说明书+MA5L收藏指南+MA5L,UV胶瓶身贴 产品配比： 7 Assortment, Polar bear: Penguin: Walrus: Mammoth: Owl: Seal: Snow man=10:10:10:10:10:8:2. Snow man is the rare item. Remark: 1. 此单有箱唛； 2. 9900923472单为ECOM订单，外箱四面须加一张黄色贴纸； 3. 此单有第三方验货，烦请多备包装物料； 5. #77673需于2025/4/18安排签版, 签样数量：空PDQ2PCS, 大货样各4PCS+齐套散件3套; 9. #77673 需于2025/4/28安排抽办测试, 抽办数量：大货4 pcs+齐套散件4SETS; 11. UPC贴纸：必须在原来错误的条码上用黑色粗头笔涂黑直至不能扫描，再贴上正确的UPC; ********************* a. 请确保产品符合1999年版本的加拿大环境保护法(CEPA)和2012年禁止某些有毒物质法规的要求。该产品不含任何在加拿大禁用的化学物质，包括但不限于有毒物 质清单中列出的化学物质，并且在为加拿大沃尔玛生产产品期间没有使用任何禁用化学物质。 Supplier certify that the products comply with the requirements of Canadian Environmental Protection Act, 1999 (CEPA), Prohibition of Certain To xic Substances Regulations, 2012. The products do not contain any chemicals that are banned in Canada, including but not limited to those listed in the Toxic Substances List and no banned chemicals were used during the manufacturing of product for Walmart Canada. 附件列表： (1) Letter of Guarantee for Canada banned chemicals - (1-5CA) b. 请确保产品在均质材料中的汞浓度不超过0.1%（按重量计）。 Supplier certify that the WAL-MART vendor products does not have a mercury concentration of more than 0.1% by weight in homogeneous material. 附件列表： (1) Letter of Guarantee for Mercury COC c. 请确保产品的塑料材料不含以下物质（SOR 2011-17 27B): Supplier certify that the plastic materials do not contain the following substances(SOR 2011-17 27B): (a) carbon tetrachloride or any substance that contains it; (b) methyl alcohol or any substance thay contains >1.0%; (c) petroleum distillates or any substance that contains >10% weight to volume of petroleum distillates; (d) benzene; (e) turpentine or any substance that contains >10% weight to volume of turpentine; (f) boric acid or salts of boric acid; or (g) ethyl ether. 附件列表： (1) Letter of Guarantee for WM CA-Other prohibited substances in plastic(less than 3 years) | Y32: Monica Zhou | Z32: 4.1 | AA32: =Z32*I32 -> 41 | AC32: 95066-8.17 | AD32: 77673-S002 | AE32: 已入 | AG32: 已完成 | AI32: 10 | AJ32: =AI32-I32 -> 0 | AN32: =I32 -> 10 | AS32: =I32 -> 10 | AU32: =I32 -> 10 | AW32: =I32 -> 10
A33: 45733 | B33: WAL-MART CANADA CORP. | C33: 加拿大 | D33: 4500160504 | E33: 9900924260 | F33: 4500160504-60 | G33: 77673-S002 | H33: 迷你冰箱 | I33: 1996 | J33: 0 | K33: 2 | L33: =I33/K33 -> 998 | M33: 45793 | N33: 45789 | O33: 5/19 第三方验货，77673需于2025/4/18安排签版, 签样数量：空PDQ2PCS, 大货样各4PCS+齐套散件3套; 9. #77673 需于2025/4/28安排抽办测试, 抽办数量：大货4 pcs+齐套散件4SETS; | P33: PASS | R33: 45748 | S33: 无 | T33: 45734 | X33: 日期码格式：ZURU INC(BVI) 标准格式 日期：按实际生产日期 Packaging Info: #77673： MA3L收缩膜+UPC贴纸(UPC:193052079404)+MA23L说明书+MA5L收藏指南+MA5L,UV胶瓶身贴 产品配比： 7 Assortment, Polar bear: Penguin: Walrus: Mammoth: Owl: Seal: Snow man=10:10:10:10:10:8:2. Snow man is the rare item. Remark: 1. 此单有箱唛； 3. 此单有第三方验货，烦请多备包装物料； 5. #77673需于2025/4/18安排签版, 签样数量：空PDQ2PCS, 大货样各4PCS+齐套散件3套; 9. #77673 需于2025/4/28安排抽办测试, 抽办数量：大货4 pcs+齐套散件4SETS; 11. UPC贴纸：必须在原来错误的条码上用黑色粗头笔涂黑直至不能扫描，再贴上正确的UPC; ********************* a. 请确保产品符合1999年版本的加拿大环境保护法(CEPA)和2012年禁止某些有毒物质法规的要求。该产品不含任何在加拿大禁用的化学物质，包括但不限于有毒物 质清单中列出的化学物质，并且在为加拿大沃尔玛生产产品期间没有使用任何禁用化学物质。 Supplier certify that the products comply with the requirements of Canadian Environmental Protection Act, 1999 (CEPA), Prohibition of Certain To xic Substances Regulations, 2012. The products do not contain any chemicals that are banned in Canada, including but not limited to those listed in the Toxic Substances List and no banned chemicals were used during the manufacturing of product for Walmart Canada. 附件列表： (1) Letter of Guarantee for Canada banned chemicals - (1-5CA) b. 请确保产品在均质材料中的汞浓度不超过0.1%（按重量计）。 Supplier certify that the WAL-MART vendor products does not have a mercury concentration of more than 0.1% by weight in homogeneous material. 附件列表： (1) Letter of Guarantee for Mercury COC c. 请确保产品的塑料材料不含以下物质（SOR 2011-17 27B): Supplier certify that the plastic materials do not contain the following substances(SOR 2011-17 27B): (a) carbon tetrachloride or any substance that contains it; (b) methyl alcohol or any substance thay contains >1.0%; (c) petroleum distillates or any substance that contains >10% weight to volume of petroleum distillates; (d) benzene; (e) turpentine or any substance that contains >10% weight to volume of turpentine; (f) boric acid or salts of boric acid; or (g) ethyl ether. 附件列表： (1) Letter of Guarantee for WM CA-Other prohibited substances in plastic(less than 3 years) | Y33: Monica Zhou | Z33: 4.1 | AA33: =Z33*I33 -> 8183.6 | AC33: 95077-8.17 | AD33: 77673-S002 | AE33: 已入 | AG33: 已完成 | AI33: =1968+28 -> 1996 | AJ33: =AI33-I33 -> 0 | AN33: =I33 -> 1996 | AS33: =I33 -> 1996 | AU33: =I33 -> 1996 | AW33: =I33 -> 1996
A34: 45744 | B34: WALMART INC. | C34: 美国 | D34: 4500161761 | E34: 0904512278 | F34: 4500161761-10 | G34: 77673TQ1-S001 | H34: 迷你冰箱4pcs/箱 | I34: 912 | J34: 0 | K34: 4 | L34: =I34/K34 -> 228 | M34: 45793 | N34: 45789 | O34: 5/19 第三方验货 | P34: PASS | R34: 外箱印刷带条码的RFID箱唛：RFID紫色色带+WM Dept.图标+RFID图标+ITF-14条码，四面右下角印刷ZURU logo, ITFF条码只印刷在正唛一面，在加印的时候确保 条形码能扫描出来，外箱侧面任一角落加印："MADE IN CHINA" 字样； | S34: 无 | T34: RFID贴纸 | V34: RFID贴纸 | X34: 日期码格式：ZURU DGYYYYMMDD CHINA(日期避开周末和法定节假日即可） 日期：按实际生产日期 Packaging Info: 77673TQ1-S001 1.包装要求： MA 1L A版收缩膜+MA 5L 收藏指南+MA 说明书+MA playset，翻单：4500159641 每pcs产品上要贴1张RFID贴纸，贴纸由ZURU提供，贴纸位置请严格按照我们签回的签板； Remark: 77673TQ1-S001 1.包装要求： MA 1L A版收缩膜+MA 5L 收藏指南+MA 说明书+MA playset，翻单：4500159641 每pcs产品上要贴1张RFID贴纸，贴纸由ZURU提供，贴纸位置请严格按照我们签回的签板； 2. 外箱印刷带条码的RFID箱唛：RFID紫色色带+WM Dept.图标+RFID图标+ITF-14条码，四面右下角印刷ZURU logo, ITFF条码只印刷在正唛一面，在加印的时候确保 条形码能扫描出来，外箱侧面任一角落加印："MADE IN CHINA" 字样； 3. 在产品上和包装上要有日期码、以及要有MADE IN CHINA和ZURU字样； 4. 产品如有扎带口要剪平，不能刮手。 5. 此单需要验货，请多备料 6. 此单以loose carton出货，4pcs/PDQ/CTN | Y34: Maggie Xie | Z34: 5 | AA34: =Z34*I34 -> 4560 | AD34: 77673TQ1-S001 | AE34: 已入 | AG34: 已完成 | AI34: 912 | AJ34: =AI34-I34 -> 0 | AN34: =I34 -> 912 | AR34: =I34 -> 912 | AU34: =I34 -> 912 | AW34: =I34 -> 912 | BH34: =I34/4 -> 228
A35: 45742 | B35: TAS IMPORT AS(Lekekassen) | C35: 挪威 | D35: 4500160993 | E35: 11098 | F35: 4500160993-30 | G35: 77673-S001 | H35: 迷你冰箱12pcs/箱 | I35: 240 | J35: 0 | K35: 12 | L35: =I35/K35 -> 20 | M35: 45793 | N35: 45789 | P35: PASS | R35: 45758 | S35: 无 | T35: 45762 | X35: 日期码格式：ZURU INC(BVI) 标准格式 日期：按实际生产日期 Packaging Info: 3. 77673: MA 3L EAN版收缩膜+挪威/瑞典/丹麦语警告语/客人进口商地址贴纸做成一张贴纸+MA 5L收藏指南+MA 电池+UV胶警告语-23L + WEEE__带电池走货北欧六 语通用黑白说明书 4. 配比跟MA Remark: 1. 包装如含PVC,请改为PET并第一时间通知跟单 2. 产品/包装要求无硼无香，出欧洲，微塑料需合规。 3.带电池出货的产品所用到的电池需要符合欧洲电池新规(EU) 2023-1542 4.有胶袋的产品：要求产品的胶袋厚度要大于等于0.05mm 5.关于贴纸，如果贴纸位置图的包装版本与大货不一致，请工厂第一时间提前提出。跟单会重新调整确认是否更新贴纸或调整位置图 6.产品/包装不含PFAS成分 7.产品条码如下: 请先检查条码是否正确再安排做货，如有问题请告知 ZURU ITEM#<(>&<)>EAN 77673:4894680042773 | Y35: Sheba | Z35: 4.1 | AA35: =Z35*I35 -> 984 | AC35: 95092-8.17 | AD35: 77673-S001-3L | AE35: 已入 | AG35: 已完成 | AI35: 240 | AJ35: =AI35-I35 -> 0 | AN35: =I35 -> 240 | AS35: =I35 -> 240 | AU35: =I35 -> 240 | AW35: =I35 -> 240
A36: 45727 | B36: TARGET US | C36: 美国 | D36: 4500159604 | E36: 10001232749-3890 | F36: 4500159604-10 | G36: 77673TQ1-S001-CC | H36: 迷你冰箱 4pcs/箱（客版配件） | I36: 4704 | J36: 0 | K36: 4 | L36: =I36/K36 -> 1176 | M36: 45777 | N36: 45789 | P36: PASS | R36: 45743 | S36: 有 | T36: 45749 | X36: 日期码格式：ZURU INC(BVI) 标准格式 日期：按实际生产日期 Packaging Info: 77673TQ1：产品包装 客版收缩膜+客版收藏指南+MA说明书+ MA 1L PDQ；客版收缩膜+客版收藏指南翻单4500158149 Remark: 77673TQ1: 1. 77673TQ1-S001-CC-MINI BRANDS-FILL THE FRIDGE PLAYSET-SERIES 1-SHRINK WRAP,4PCS/PDQ,4PCS/PDQ/CTN 2. 产品包装 客版收缩膜+客版收藏指南+MA说明书+ MA 1L PDQ；客版收缩膜上的UPC显示193052079404；客版收缩膜+客版收藏指南翻单4500158149 3. 外箱正唛左上角位置粘贴条码箱贴纸，每箱只贴一张，由ZURU订购。来料贴纸上显示的客户DPCI# 086-02-3468， UPC显示10193052079401; 此订单所有item： 1. 产品和包装上印刷 tracking code信息，格式为ZURU常规格式; 2. 出货方式：货代自提 | Y36: Holly Zheng | Z36: 5.53 | AA36: =Z36*I36 -> 26013.12 | AD36: 77673TQ1-S001-CC | AE36: 已入 | AG36: 已完成 | AI36: 东莞安排 | AJ36: =AI36-I36 -> #VALUE! | AP36: =I36 -> 4704 | AW36: =I36 -> 4704 | BF36: =I36 -> 4704 | BG36: =I36 -> 4704 | BH36: =I36/4 -> 1176
A37: 45709 | B37: TARGET US | C37: 美国 | D37: 4500158149 | E37: 10001245308-3890 | F37: 4500158149-10 | G37: 77673TQ1-S001-CC | H37: 迷你冰箱 4pcs/箱（客版配件） | I37: 3416 | J37: 0 | K37: 4 | L37: =I37/K37 -> 854 | M37: 45775 | N37: 45789 | O37: 5/9 第三方验货 | P37: PASS | R37: 45748 | S37: 有 | T37: 45749 | X37: 日期码格式：ZURU INC(BVI) 标准格式 日期：按实际生产日期 Packaging Info: 77673TQ1：产品包装 客版收缩膜+客版收藏指南+MA说明书+ MA 1L PDQ； Remark: 77673TQ1: 1. 77673TQ1-S001-CC-MINI BRANDS-FILL THE FRIDGE PLAYSET-SERIES 1-SHRINK WRAP,4PCS/PDQ,4PCS/PDQ/CTN 2. 产品包装 客版收缩膜+客版收藏指南+MA说明书+ MA 1L PDQ；客版收缩膜上的UPC显示193052079404； 3. 外箱正唛左上角位置粘贴条码箱贴纸，每箱只贴一张，由ZURU订购。来料贴纸上显示的客户DPCI# 086-02-3468， UPC显示10193052079401; 4. 外箱正唛箱唛内容右侧需贴一张Event label，内容显示Toys Set Date：7/20/2025，工厂自行订购； 此订单所有item： 1. 产品和包装上印刷 tracking code信息，格式为ZURU常规格式; 2. 出货方式：货代自提 | Y37: Holly Zheng | Z37: 5.53 | AA37: =Z37*I37 -> 18890.48 | AD37: 77673TQ1-S001-CC | AE37: 已入 | AG37: 已完成 | AI37: 东莞安排 | AJ37: =AI37-I37 -> #VALUE! | AP37: =I37 -> 3416 | AW37: =I37 -> 3416 | BF37: =I37 -> 3416 | BG37: =I37 -> 3416 | BH37: =I37/4 -> 854
A38: 45670 | B38: Smyths Toys HQ UC UK | C38: 爱尔兰 | D38: 4500155602 | E38: PO4400460300 | F38: 4500155602-10 | G38: 77673TQ1-S003 | H38: 迷你冰箱 | I38: 3008 | J38: 0 | K38: 8 | L38: =I38/K38 -> 376 | M38: 45796 | N38: 45792 | P38: PASS | R38: 45670 | S38: 无 | T38: WEEE声明(带电池)走货欧洲通用30L-B版说明书 | X38: 日期码格式：ZURU INC(BVI) 标准格式 日期：按实际生产日期 Packaging Info: 77673TQ1：最新MA PDQ(优先3L )+客版收缩膜+23L说明书+客版收藏指南+客版WEEE声明通用说明书(带电池) （所有资料翻#4500155594） 客户PO号码请参考remark Remark: 1）包装日期码按ZURU格式即可，请确保不迟于外箱日期码，可等于或者早于外箱日期码，必须为法定工作日，印刷前请先检查外箱日期码。 2）订单出英国，请注意检查产品及包装应带UKCA图标（14+产品除外），包装显示ZURU UK LTD/ZURU France地址信息，QC部门请查核，如有问题与跟单确认 3) 需要完全符合欧洲标准(符合微塑料法规)，否则不合法规会有客诉产生 | Y38: Ula Zhao | Z38: 5 | AA38: =Z38*I38 -> 15040 | AC38: 95064-8.17 | AD38: 77673TQ1-S003 | AE38: 已入 | AG38: 已完成 | AI38: =3000+8 -> 3008 | AJ38: =AI38-I38 -> 0 | AN38: =I38 -> 3008 | AW38: =I38 -> 3008 | BD38: =I38 -> 3008 | BE38: =I38 -> 3008 | BI38: =I38/4 -> 752
A39: 45670 | B39: Smyths Toys HQ UC UK | C39: 爱尔兰 | D39: 4500155602 | E39: PO4400460306 | F39: 4500155602-20 | G39: 77673TQ1-S003 | H39: 迷你冰箱 | I39: 1504 | J39: 0 | K39: 8 | L39: =I39/K39 -> 188 | M39: 45796 | N39: 45792 | P39: PASS | R39: 45670 | S39: 无 | T39: WEEE声明(带电池)走货欧洲通用30L-B版说明书 | X39: 日期码格式：ZURU INC(BVI) 标准格式 日期：按实际生产日期 Packaging Info: 77673TQ1：最新MA PDQ(优先3L )+客版收缩膜+23L说明书+客版收藏指南+客版WEEE声明通用说明书(带电池) （所有资料翻#4500155594） 客户PO号码请参考remark Remark: 1）包装日期码按ZURU格式即可，请确保不迟于外箱日期码，可等于或者早于外箱日期码，必须为法定工作日，印刷前请先检查外箱日期码。 2）订单出英国，请注意检查产品及包装应带UKCA图标（14+产品除外），包装显示ZURU UK LTD/ZURU France地址信息，QC部门请查核，如有问题与跟单确认 3) 需要完全符合欧洲标准(符合微塑料法规)，否则不合法规会有客诉产生 | Y39: Ula Zhao | Z39: 5 | AA39: =Z39*I39 -> 7520 | AC39: 95041-8.17 | AD39: 77673TQ1-S003 | AE39: 已入 | AG39: 已完成 | AI39: 1504 | AJ39: =AI39-I39 -> 0 | AN39: =I39 -> 1504 | AW39: =I39 -> 1504 | BD39: =I39 -> 1504 | BE39: =I39 -> 1504 | BI39: =I39/4 -> 376
A40: 45758 | B40: TOYS "R" US (CANADA) LTD. | C40: 加拿大 | D40: 4500163438 | E40: 3501527805 | F40: 4500163438-10 | G40: 77673-S001 | H40: 迷你冰箱12pcs/箱 | I40: 1104 | J40: 0 | K40: 12 | L40: =I40/K40 -> 92 | M40: 45796 | N40: 45792 | O40: 需要第三方SGS验货，验货时间2025/05/19，每款每色请备1PC完整带包装样品供验货人员参考。用完后若无损坏可以放回大货里。 | P40: PASS | R40: 45764 | S40: 无 | T40: 45764 | X40: 日期码格式：ZURU INC(BVI) 标准格式 日期：按实际生产日期 Packaging Info: 1. 出口加拿大市场，MA UPC版本包装。 #77673: MA 3L EAN版本 +UPC贴纸；UPC#193052079404; 3PCS AG13 BATTERIES(INCLUDED) 2. 产品、包装、外箱上面tracking code的时间格式需要一致 Remark: 3. 需要第三方SGS验货，验货时间2025/05/19，每款每色请备1PC完整带包装样品供验货人员参考。用完后若无损坏可以放回大货里。 | Y40: Abby Mai,Lluvia Zeng | Z40: 4.1 | AA40: =Z40*I40 -> 4526.4 | AC40: 95233-8.17 | AD40: 77673-S001-3L | AE40: 已入 | AG40: 已完成 | AI40: 1104 | AJ40: =AI40-I40 -> 0 | AN40: =I40 -> 1104 | AS40: =I40 -> 1104 | AU40: =I40 -> 1104 | AW40: =I40 -> 1104
A41: 45726 | B41: WAL-MART STORES INC. USA | C41: 美国 | D41: 4500159658 | E41: 0902421329 HOUSTON | F41: 4500159658-10 | G41: 77673TQ1-S001 | H41: 迷你冰箱4pcs/箱 | I41: 4960 | J41: 0 | K41: 4 | L41: =I41/K41 -> 1240 | M41: 45797 | N41: 45793 | O41: 5/22 第三方验货 | P41: PASS | R41: 45727 | S41: 有 | T41: 45727 | V41: 每pcs产品上要贴1张RFID贴纸，贴纸由ZURU提供，贴纸位置请严格按照我们签回的签板，粉色艾利贴纸（不干胶打印） | X41: 日期码格式：ZURU DGYYYYMMDD CHINA(日期避开周末和法定节假日即可） 日期：按实际生产日期 Packaging Info: 77673TQ1-S001 1.包装要求： MA 1L A版收缩膜+MA 5L 收藏指南+MA 说明书+MA playset 每pcs产品上要贴1张RFID贴纸，贴纸由ZURU提供，贴纸位置请严格按照我们签回的签板； Remark: 77673TQ1-S001 1.包装要求： MA 1L A版收缩膜+MA 5L 收藏指南+MA 说明书+MA playset 每pcs产品上要贴1张RFID贴纸，贴纸由ZURU提供，贴纸位置请严格按照我们签回的签板； 2. 外箱印刷带条码的RFID箱唛：RFID紫色色带+WM Dept.图标+RFID图标+ITF-14条码+粉色艾利贴纸（不干胶打印），四面右下角印刷ZURU logo, ITFF条码只印刷在 正唛一面，在加印的时候确保条形码能扫描出来，1张粉红色贴纸贴在正唛对角线，外箱侧面任一角落加印："MADE IN CHINA" 字样； 3. 在产品上和包装上要有日期码、以及要有MADE IN CHINA和ZURU字样； 4. 产品如有扎带口要剪平，不能刮手。 5. 此单需要验货，请多备料 6. 此单以loose carton出货，4pcs/PDQ/CTN | Y41: Maggie Xie | Z41: 5 | AA41: =Z41*I41 -> 24800 | AD41: 77673TQ1-S001 | AE41: 已入 | AG41: 已完成 | AI41: 东莞安排 | AJ41: =AI41-I41 -> #VALUE! | AN41: =I41 -> 4960 | AR41: =I41 -> 4960 | AU41: =I41 -> 4960 | AW41: =I41 -> 4960 | BH41: =I41/4 -> 1240
A42: 45726 | B42: WAL-MART STORES INC. USA | C42: 美国 | D42: 4500159658 | E42: 0902421316 MOBILE | F42: 4500159658-20 | G42: 77673TQ1-S001 | H42: 迷你冰箱4pcs/箱 | I42: 4112 | J42: 0 | K42: 4 | L42: =I42/K42 -> 1028 | M42: 45797 | N42: 45793 | O42: 5/22 第三方验货 | P42: PASS | R42: 45727 | S42: 有 | T42: 45727 | V42: 每pcs产品上要贴1张RFID贴纸，贴纸由ZURU提供，贴纸位置请严格按照我们签回的签板，粉色艾利贴纸（不干胶打印） | X42: 日期码格式：ZURU DGYYYYMMDD CHINA(日期避开周末和法定节假日即可） 日期：按实际生产日期 Packaging Info: 77673TQ1-S001 1.包装要求： MA 1L A版收缩膜+MA 5L 收藏指南+MA 说明书+MA playset 每pcs产品上要贴1张RFID贴纸，贴纸由ZURU提供，贴纸位置请严格按照我们签回的签板； Remark: 77673TQ1-S001 1.包装要求： MA 1L A版收缩膜+MA 5L 收藏指南+MA 说明书+MA playset 每pcs产品上要贴1张RFID贴纸，贴纸由ZURU提供，贴纸位置请严格按照我们签回的签板； 2. 外箱印刷带条码的RFID箱唛：RFID紫色色带+WM Dept.图标+RFID图标+ITF-14条码+粉色艾利贴纸（不干胶打印），四面右下角印刷ZURU logo, ITFF条码只印刷在 正唛一面，在加印的时候确保条形码能扫描出来，1张粉红色贴纸贴在正唛对角线，外箱侧面任一角落加印："MADE IN CHINA" 字样； 3. 在产品上和包装上要有日期码、以及要有MADE IN CHINA和ZURU字样； 4. 产品如有扎带口要剪平，不能刮手。 5. 此单需要验货，请多备料 6. 此单以loose carton出货，4pcs/PDQ/CTN | Y42: Maggie Xie | Z42: 5 | AA42: =Z42*I42 -> 20560 | AD42: 77673TQ1-S001 | AE42: 已入 | AG42: 已完成 | AI42: 4112 | AJ42: =AI42-I42 -> 0 | AN42: =I42 -> 4112 | AR42: =I42 -> 4112 | AU42: =I42 -> 4112 | AW42: =I42 -> 4112 | BH42: =I42/4 -> 1028
A43: 45729 | B43: WM MORRISON SUPERMARKET PLC | C43: 英国 | D43: 4500160042 | E43: 14402521 | F43: 4500160042-10 | G43: 77673TQ1-S004 | H43: 迷你冰箱16pcs/箱 | I43: 2656 | J43: 4 | K43: 16 | L43: =I43/K43 -> 166 | M43: 45797 | N43: 45793 | P43: PASS | R43: 45740 | S43: 无 | T43: 无 | X43: 日期码格式：ZURU INC(BVI) 标准格式 日期：按实际生产日期 Packaging Info: 77673TQ1-S004： MA 1L UPC 包装+其他MA 最新包装+1张防盗贴纸（贴纸类型10111896：40R ECON YBL DE 8.2 1kr）请工厂自行跟checkpoint供应商订购贴纸 UPC#193052079404，请先检查包装条码是否正确再安排做货 Remark: 1）外箱有条码要求，排版时请留意并请确保条码清晰可扫描（封箱胶不要黏到条码上), 否则客人会有罚款。 2) 订单出英国，产品及包装需要印UKCA图标，包装需要有ZURU UK LTD/ZURU France地址信息，QC同事请查核，如有问题与跟单确认。 3) 箱唛日期码与包装保持一致 4) 若外箱重量超过16KGS，请提前告知ZURU跟单，需要客人批准才能出货，并且外箱需要印2 man lift标志 | Y43: Yoga Huang | Z43: 5 | AA43: =Z43*I43 -> 13280 | AC43: 95102-8.17 | AD43: 77673TQ1-S004 | AE43: 已入 | AG43: 已完成 | AI43: 东莞安排 | AJ43: =AI43-I43 -> #VALUE! | AN43: =I43 -> 2656 | AR43: =I43 -> 2656 | AU43: =I43 -> 2656 | AW43: =I43 -> 2656 | BH43: =I43/4 -> 664
A44: 45744 | B44: WALMART INC. | C44: 美国 | D44: 4500161762 | E44: 0904512284 EASTVALE | F44: 4500161762-10 | G44: 77673TQ1-S001 | H44: 迷你冰箱4pcs/箱 | I44: 608 | J44: 0 | K44: 4 | L44: =I44/K44 -> 152 | M44: 45797 | N44: 45793 | O44: 5/22 第三方验货 | P44: PASS | R44: 外箱印刷带条码的RFID箱唛：RFID紫色色带+WM Dept.图标+RFID图标+ITF-14条码，四面右下角印刷ZURU logo, ITFF条码只印刷在正唛一面，在加印的时候确保 条形码能扫描出来，外箱侧面任一角落加印："MADE IN CHINA" 字样； | S44: 无 | T44: RFID贴纸 | V44: RFID贴纸 | X44: 日期码格式：ZURU DGYYYYMMDD CHINA(日期避开周末和法定节假日即可） 日期：按实际生产日期 Packaging Info: 77673TQ1-S001 1.包装要求： MA 1L A版收缩膜+MA 5L 收藏指南+MA 说明书+MA playset，翻单：4500159641 每pcs产品上要贴1张RFID贴纸，贴纸由ZURU提供，贴纸位置请严格按照我们签回的签板； Remark: 77673TQ1-S001 1.包装要求： MA 1L A版收缩膜+MA 5L 收藏指南+MA 说明书+MA playset，翻单：4500159641 每pcs产品上要贴1张RFID贴纸，贴纸由ZURU提供，贴纸位置请严格按照我们签回的签板； 2. 外箱印刷带条码的RFID箱唛：RFID紫色色带+WM Dept.图标+RFID图标+ITF-14条码，四面右下角印刷ZURU logo, ITFF条码只印刷在正唛一面，在加印的时候确保 条形码能扫描出来，外箱侧面任一角落加印："MADE IN CHINA" 字样； 3. 在产品上和包装上要有日期码、以及要有MADE IN CHINA和ZURU字样； 4. 产品如有扎带口要剪平，不能刮手。 5. 此单需要验货，请多备料 6. 此单以loose carton出货，4pcs/PDQ/CTN | Y44: Maggie Xie | Z44: 5 | AA44: =Z44*I44 -> 3040 | AD44: 77673TQ1-S001 | AE44: 已入 | AG44: 已完成 | AI44: =592+16 -> 608 | AJ44: =AI44-I44 -> 0 | AN44: =I44 -> 608 | AR44: =I44 -> 608 | AU44: =I44 -> 608 | AW44: =I44 -> 608 | BH44: =I44/4 -> 152
A45: 45744 | B45: WALMART INC. | C45: 美国 | D45: 4500161762 | E45: 0904512309 ELWOOD | F45: 4500161762-20 | G45: 77673TQ1-S001 | H45: 迷你冰箱4pcs/箱 | I45: 608 | J45: 0 | K45: 4 | L45: =I45/K45 -> 152 | M45: 45797 | N45: 45793 | O45: 5/22 第三方验货 | P45: PASS | R45: 外箱印刷带条码的RFID箱唛：RFID紫色色带+WM Dept.图标+RFID图标+ITF-14条码，四面右下角印刷ZURU logo, ITFF条码只印刷在正唛一面，在加印的时候确保 条形码能扫描出来，外箱侧面任一角落加印："MADE IN CHINA" 字样； | S45: 无 | T45: RFID贴纸 | V45: RFID贴纸 | X45: 日期码格式：ZURU DGYYYYMMDD CHINA(日期避开周末和法定节假日即可） 日期：按实际生产日期 Packaging Info: 77673TQ1-S001 1.包装要求： MA 1L A版收缩膜+MA 5L 收藏指南+MA 说明书+MA playset，翻单：4500159641 每pcs产品上要贴1张RFID贴纸，贴纸由ZURU提供，贴纸位置请严格按照我们签回的签板； Remark: 77673TQ1-S001 1.包装要求： MA 1L A版收缩膜+MA 5L 收藏指南+MA 说明书+MA playset，翻单：4500159641 每pcs产品上要贴1张RFID贴纸，贴纸由ZURU提供，贴纸位置请严格按照我们签回的签板； 2. 外箱印刷带条码的RFID箱唛：RFID紫色色带+WM Dept.图标+RFID图标+ITF-14条码，四面右下角印刷ZURU logo, ITFF条码只印刷在正唛一面，在加印的时候确保 条形码能扫描出来，外箱侧面任一角落加印："MADE IN CHINA" 字样； 3. 在产品上和包装上要有日期码、以及要有MADE IN CHINA和ZURU字样； 4. 产品如有扎带口要剪平，不能刮手。 5. 此单需要验货，请多备料 6. 此单以loose carton出货，4pcs/PDQ/CTN | Y45: Maggie Xie | Z45: 5 | AA45: =Z45*I45 -> 3040 | AD45: 77673TQ1-S001 | AE45: 已入 | AG45: 已完成 | AI45: =600+8 -> 608 | AJ45: =AI45-I45 -> 0 | AN45: =I45 -> 608 | AR45: =I45 -> 608 | AU45: =I45 -> 608 | AW45: =I45 -> 608 | BH45: =I45/4 -> 152
A46: 45744 | B46: WALMART INC. | C46: 美国 | D46: 4500161762 | E46: 0904512289 STATESBORO | F46: 4500161762-30 | G46: 77673TQ1-S001 | H46: 迷你冰箱4pcs/箱 | I46: 616 | J46: 0 | K46: 4 | L46: =I46/K46 -> 154 | M46: 45797 | N46: 45793 | O46: 5/22 第三方验货 | P46: PASS | R46: 外箱印刷带条码的RFID箱唛：RFID紫色色带+WM Dept.图标+RFID图标+ITF-14条码，四面右下角印刷ZURU logo, ITFF条码只印刷在正唛一面，在加印的时候确保 条形码能扫描出来，外箱侧面任一角落加印："MADE IN CHINA" 字样； | S46: 无 | T46: RFID贴纸 | V46: RFID贴纸 | X46: 日期码格式：ZURU DGYYYYMMDD CHINA(日期避开周末和法定节假日即可） 日期：按实际生产日期 Packaging Info: 77673TQ1-S001 1.包装要求： MA 1L A版收缩膜+MA 5L 收藏指南+MA 说明书+MA playset，翻单：4500159641 每pcs产品上要贴1张RFID贴纸，贴纸由ZURU提供，贴纸位置请严格按照我们签回的签板； Remark: 77673TQ1-S001 1.包装要求： MA 1L A版收缩膜+MA 5L 收藏指南+MA 说明书+MA playset，翻单：4500159641 每pcs产品上要贴1张RFID贴纸，贴纸由ZURU提供，贴纸位置请严格按照我们签回的签板； 2. 外箱印刷带条码的RFID箱唛：RFID紫色色带+WM Dept.图标+RFID图标+ITF-14条码，四面右下角印刷ZURU logo, ITFF条码只印刷在正唛一面，在加印的时候确保 条形码能扫描出来，外箱侧面任一角落加印："MADE IN CHINA" 字样； 3. 在产品上和包装上要有日期码、以及要有MADE IN CHINA和ZURU字样； 4. 产品如有扎带口要剪平，不能刮手。 5. 此单需要验货，请多备料 6. 此单以loose carton出货，4pcs/PDQ/CTN | Y46: Maggie Xie | Z46: 5 | AA46: =Z46*I46 -> 3080 | AD46: 77673TQ1-S001 | AE46: 已入 | AG46: 已完成 | AI46: =608+8 -> 616 | AJ46: =AI46-I46 -> 0 | AN46: =I46 -> 616 | AR46: =I46 -> 616 | AU46: =I46 -> 616 | AW46: =I46 -> 616 | BH46: =I46/4 -> 154
A47: 45744 | B47: WALMART INC. | C47: 美国 | D47: 4500161762 | E47: 0904512339 SUFFOLK | F47: 4500161762-40 | G47: 77673TQ1-S001 | H47: 迷你冰箱4pcs/箱 | I47: 792 | J47: 0 | K47: 4 | L47: =I47/K47 -> 198 | M47: 45797 | N47: 45793 | O47: 5/22 第三方验货 | P47: PASS | R47: 外箱印刷带条码的RFID箱唛：RFID紫色色带+WM Dept.图标+RFID图标+ITF-14条码，四面右下角印刷ZURU logo, ITFF条码只印刷在正唛一面，在加印的时候确保 条形码能扫描出来，外箱侧面任一角落加印："MADE IN CHINA" 字样； | S47: 无 | T47: RFID贴纸 | V47: RFID贴纸 | X47: 日期码格式：ZURU DGYYYYMMDD CHINA(日期避开周末和法定节假日即可） 日期：按实际生产日期 Packaging Info: 77673TQ1-S001 1.包装要求： MA 1L A版收缩膜+MA 5L 收藏指南+MA 说明书+MA playset，翻单：4500159641 每pcs产品上要贴1张RFID贴纸，贴纸由ZURU提供，贴纸位置请严格按照我们签回的签板； Remark: 77673TQ1-S001 1.包装要求： MA 1L A版收缩膜+MA 5L 收藏指南+MA 说明书+MA playset，翻单：4500159641 每pcs产品上要贴1张RFID贴纸，贴纸由ZURU提供，贴纸位置请严格按照我们签回的签板； 2. 外箱印刷带条码的RFID箱唛：RFID紫色色带+WM Dept.图标+RFID图标+ITF-14条码，四面右下角印刷ZURU logo, ITFF条码只印刷在正唛一面，在加印的时候确保 条形码能扫描出来，外箱侧面任一角落加印："MADE IN CHINA" 字样； 3. 在产品上和包装上要有日期码、以及要有MADE IN CHINA和ZURU字样； 4. 产品如有扎带口要剪平，不能刮手。 5. 此单需要验货，请多备料 6. 此单以loose carton出货，4pcs/PDQ/CTN | Y47: Maggie Xie | Z47: 5 | AA47: =Z47*I47 -> 3960 | AC47: ZB00389-6.2 | AD47: 77673TQ1-S001 | AE47: 已入 | AG47: 已完成 | AI47: 792 | AJ47: =AI47-I47 -> 0 | AN47: =I47 -> 792 | AR47: =I47 -> 792 | AU47: =I47 -> 792 | AW47: =I47 -> 792 | BH47: =I47/4 -> 198
A48: 45744 | B48: WALMART INC. | C48: 美国 | D48: 4500161762 | E48: 0904512352 RIDGEVILLE SC | F48: 4500161762-50 | G48: 77673TQ1-S001 | H48: 迷你冰箱4pcs/箱 | I48: 744 | J48: 0 | K48: 4 | L48: =I48/K48 -> 186 | M48: 45797 | N48: 45793 | O48: 5/22 第三方验货 | P48: PASS | R48: 外箱印刷带条码的RFID箱唛：RFID紫色色带+WM Dept.图标+RFID图标+ITF-14条码，四面右下角印刷ZURU logo, ITFF条码只印刷在正唛一面，在加印的时候确保 条形码能扫描出来，外箱侧面任一角落加印："MADE IN CHINA" 字样； | S48: 无 | T48: RFID贴纸 | V48: RFID贴纸 | X48: 日期码格式：ZURU DGYYYYMMDD CHINA(日期避开周末和法定节假日即可） 日期：按实际生产日期 Packaging Info: 77673TQ1-S001 1.包装要求： MA 1L A版收缩膜+MA 5L 收藏指南+MA 说明书+MA playset，翻单：4500159641 每pcs产品上要贴1张RFID贴纸，贴纸由ZURU提供，贴纸位置请严格按照我们签回的签板； Remark: 77673TQ1-S001 1.包装要求： MA 1L A版收缩膜+MA 5L 收藏指南+MA 说明书+MA playset，翻单：4500159641 每pcs产品上要贴1张RFID贴纸，贴纸由ZURU提供，贴纸位置请严格按照我们签回的签板； 2. 外箱印刷带条码的RFID箱唛：RFID紫色色带+WM Dept.图标+RFID图标+ITF-14条码，四面右下角印刷ZURU logo, ITFF条码只印刷在正唛一面，在加印的时候确保 条形码能扫描出来，外箱侧面任一角落加印："MADE IN CHINA" 字样； 3. 在产品上和包装上要有日期码、以及要有MADE IN CHINA和ZURU字样； 4. 产品如有扎带口要剪平，不能刮手。 5. 此单需要验货，请多备料 6. 此单以loose carton出货，4pcs/PDQ/CTN | Y48: Maggie Xie | Z48: 5 | AA48: =Z48*I48 -> 3720 | AD48: 77673TQ1-S001 | AE48: 已入 | AG48: 已完成 | AI48: =740+4 -> 744 | AJ48: =AI48-I48 -> 0 | AN48: =I48 -> 744 | AR48: =I48 -> 744 | AU48: =I48 -> 744 | AW48: =I48 -> 744 | BH48: =I48/4 -> 186
A49: 45749 | B49: Outlet Drift AS | C49: 挪威 | D49: 4500162375 | E49: 20106 | F49: 4500162375-40 | G49: 77673-S001 | H49: 迷你冰箱12pcs/箱 | I49: 252 | J49: 0 | K49: 12 | L49: =I49/K49 -> 21 | M49: 45797 | N49: 45793 | P49: PASS | R49: 45750 | S49: 无 | T49: 45768 | X49: 日期码格式：ZURU INC(BVI) 标准格式 日期：按实际生产日期 Packaging Info: 77673:收缩膜MA EAN 3L A+收藏指南5L A+MA 说明书 23L+1张警示语贴纸+带纽扣电池走货北欧六语通用黑白电池说明书 Remark: 1/配比: 2/产品和包装要求无硼无香，包装不能含有PVC 3/如有微塑料，必须合规欧洲标准，闪粉也是微塑料的一种，目前仅接受三张方式1.去除，2.用可降解材料，和3.永久封印在固体。 4/带电池出货的产品，所用到的电池需要符合欧洲电池新规(EU)2023-1542 | Y49: Zoe Zhou | Z49: 4.1 | AA49: =Z49*I49 -> 1033.2 | AC49: 95040-8.17 | AD49: 77673-S001-3L | AE49: 已入 | AG49: 已完成 | AI49: 252 | AJ49: =AI49-I49 -> 0 | AN49: =I49 -> 252 | AS49: =I49 -> 252 | AU49: =I49 -> 252 | AW49: =I49 -> 252
A50: 45750 | B50: ZURU France | C50: 法国 | D50: 4500162314 | E50: 5200006540 | F50: 4500162314-80 | G50: 77673TQ1-S001-MTS | H50: 迷你冰箱4pcs/箱 | I50: 3352 | J50: 0 | K50: 4 | L50: =I50/K50 -> 838 | M50: 45799 | N50: 45796 | P50: PASS | R50: 45750 | S50: 无 | T50: 45768 | X50: 日期码格式：ZURU INC(BVI) 标准格式 日期：按实际生产日期 Packaging Info: 77673TQ1:最新MA 3L EAN收缩膜+最新MA 5L收藏指南+最新MA 23L说明书+最新MA纸袋+最新MA 3L PDQ+多语警语折叠贴纸（含包装缺失的法/意/西环保标）+ 多语版W EEE电池垃圾桶的回收声明说明书（ included）,, Remark: 1. 法国国家内销单，需要通过ZURU 验货结果后才能出货 (工厂需要主动提前同ZURU QC预约验货避免延期出货造成不必要麻烦)； 2. 本订单所有 具有 baby items / assorted items 的款式，零售包装上都要用 母 EAN; 3. 若有特定款有特殊外箱条码要求时,需要明确列出产品款对应的具体外箱条码号码/条码类型 (若无,可以忽略此需求) 4. 所有出口欧洲的产品, 法规规定禁止在包装和共公众用的印刷品中使用矿物油中含有的物质, 包装印刷油墨中含有的MOAH/MOSH的质量浓度不能超过1%, 否则出 货到法国被抽检出现问题, 供应商需要对此负责; 5. Date code: 外箱/产品/包装 保持一致，完货后提供date code 信息以便我们保存记录做批次管理; 6. 装柜时需要按照款式号码从小到大一款款依次装,避免终端仓库卸货混乱.若一个柜子涉及到几个不同国家内销单,装柜时需要一个国家装完后再装另一个国家的 产品,依次装柜,避免终端仓库因不同国家不同库位位置卸货混乱. (此点需要同工厂装柜人员强调) | Y50: Jade Wang | Z50: 5.03 | AA50: =Z50*I50 -> 16860.56 | AC50: 95050-8.17 | AD50: 77673TQ1-S001-MTS | AE50: 已入 | AG50: 已完成 | AI50: 3352 | AJ50: =AI50-I50 -> 0 | AN50: =I50 -> 3352 | AS50: =I50 -> 3352 | AU50: =I50 -> 3352 | AW50: =I50 -> 3352 | BI50: =I50/4 -> 838
A51: 45722 | B51: SCHEEL'S ALL SPORTS, INC. | C51: 美国 | D51: 4500159089 | E51: PO#019848172 | F51: 4500159089-20 | G51: 77673-S001 | H51: 迷你冰箱12pcs/箱 | I51: 2064 | J51: 0 | K51: 12 | L51: =I51/K51 -> 172 | M51: 45800 | N51: =M51-4 -> 45796 | P51: PASS | R51: 45722 | S51: 无 | T51: 无 | X51: 日期码格式：ZURU INC(BVI) 标准格式 日期：按实际生产日期 Packaging Info: 1. 包装：ZURU MA 1L 最新UPC版本；出口美国<(>&<)>CA； Remark: 2. 日期跟踪码：产品包装及产品本身都必须有日期跟踪码，并且确保两者的日期跟踪码要一致；ZURU标准格式日期码(请自行调整具体年月日生产期，但不能为周 末）。 3. 此单有4个客户PO， 请见侧边备注； 4. 出货配比: Zuru 标版配比。 | Y51: Mila Yao | Z51: 4.1 | AA51: =Z51*I51 -> 8462.4 | AD51: 77673-S001 | AE51: 已入 | AG51: 已完成 | AI51: =2040+24 -> 2064 | AJ51: =AI51-I51 -> 0 | AN51: =I51 -> 2064 | AR51: =I51 -> 2064 | AU51: =I51 -> 2064 | AW51: =I51 -> 2064
A52: 45727 | B52: THE ENTERTAINER | C52: 英国 | D52: 4500159575 | E52: FB12980 | F52: 4500159575-40 | G52: 77673TQ1-S002 | H52: 迷你冰箱 | I52: 3008 | J52: 0 | K52: 16 | L52: =I52/K52 -> 188 | M52: 45800 | N52: =M52-4 -> 45796 | O52: 大货样： 请在5/10 前寄出每款1整套大货样到罗湖办公室7B Sandy Shao 收。 | P52: PASS | R52: 45727 | S52: 无 | T52: 45776 | X52: 日期码格式：ZURU INC(BVI) 标准格式 日期：按实际生产日期 Packaging Info: *MA版本按工厂现有最新库存即可，订单出英国，请注意检查产品及包装应带UKCA图标，包装显示ZURU UK LTD信息，QC同事请查核，如有问题与跟单确认 *生产日期按实际（法定工作日），按ZURU标准格式即可 ，但是请知悉包装日期码需要早于或者等于外箱日期码 ，不能晚于外箱日期码 *请注意所有订单都需要经过ZURU QC验货并且通过后方可出货 *所有产品按符合欧洲标准走货，需要是不含微塑料版本 。 *涉及到硼的，如可选择情况下应使用低硼版本 （slime 类别低硼一般低于300ppm)，无选择的应与跟单复核再安排 。 *条码如下，请核查 77673TQ1-S002 193052079404 * 大货样： 请在5/10 前寄出每款1整套大货样到罗湖办公室7B Sandy Shao 收。 Remark: 77673TQ1-S002 MA-1L 配套包装+UPC 条码覆盖原包装条码位置，另外产品内包装再加多一张2国语言电池说明书(英文+阿拉伯文） | Y52: Sandy Shao | Z52: 4.39 | AA52: =Z52*I52 -> 13205.12 | AC52: 95078-8.17 | AD52: 77673TQ1-S002 | AE52: 已入 | AG52: 已完成 | AI52: =2976+32 -> 3008 | AJ52: =AI52-I52 -> 0 | AN52: =I52 -> 3008 | AR52: =I52 -> 3008 | AU52: =I52 -> 3008 | AW52: =I52 -> 3008 | BH52: =I52/4 -> 752
A53: 45761 | B53: SAINSBURY'S SUPERMARKET LTD | C53: 英国 | D53: 4500163316 | E53: PO#2735217-Cu stomer SKU#146638251 | F53: 4500163316-20 | G53: 77673TQ1-S001 | H53: 迷你冰箱4pcs/箱 | I53: 1608 | J53: 0 | K53: 4 | L53: =I53/K53 -> 402 | M53: 45800 | N53: 45796 | P53: PASS | R53: 45758 | S53: 无 | T53: 45764 | X53: 日期码格式：ZURU INC(BVI) 标准格式 日期：按实际生产日期 Packaging Info: 77673TQ1：MA 3L+UPC贴纸（UPC#193052079404） Remark: *胶带最少宽度要保证6.0CM,厚度最少0.05毫米,外箱不可以打钉/扎带；以工字型封箱； *如果重量超过5KGS，箱唛需加黄色警示图标志 ，有疑问请与ZURU跟单同事联系,十分重要！ *订单出英国，请注意检查产品及包装应带UKCA图标，包装需要显示ZURU UK LTD/ZURU France地址信息，QC同事请查核，如有问题与跟单确认。 *生产日期按实际的（法定工作日），按ZURU标准格式即可 ，但是请知悉包装日期码需要早于或者等于外箱日期码 ，不能晚于外箱日期码 *请注意所有订单都需要经过ZURU QC验货并且通过后方可出货 *产品条码以订单显示为准 ，请安排生产前先核对再生产。 *外箱上的条码请确保清晰可扫描 ，左上角的条码格式是UPC-A格式，下面14位数的条码格式是ITF-14格式，否则到目的仓无法扫描入仓由工厂承担责任 。 *所有产品按符合欧洲标准走货，微塑料需合规 。 *涉及到硼的，需要符合欧洲标准 *客户不接受PVC材质 *外箱不得使用带金属夹子或带扣 | Y53: May Wu | Z53: 5.1 | AA53: =Z53*I53 -> 8200.8 | AC53: 95110-8.17 | AD53: 77673TQ1-S001-MTS | AE53: 已入 | AG53: 已完成 | AI53: 1608 | AJ53: =AI53-I53 -> 0 | AN53: =I53 -> 1608 | AS53: =I53 -> 1608 | AU53: =I53 -> 1608 | AW53: =I53 -> 1608 | BI53: =I53/4 -> 402
A54: 45723 | B54: TARGET US | C54: 美国 | D54: 4500159315 | E54: 10001263725-3890 | F54: 4500159315-30 | G54: 77673TQ1-S001-CC | H54: 迷你冰箱 4pcs/箱（客版配件） | I54: 6000 | J54: 0 | K54: 4 | L54: =I54/K54 -> 1500 | M54: 45775 | N54: 45789 | P54: PASS | R54: 45741 | S54: 有 | T54: 45749 | X54: 日期码格式：ZURU INC(BVI) 标准格式 日期：按实际生产日期 Packaging Info: 77673TQ1：产品包装 客版收缩膜+客版收藏指南+MA说明书+ MA 1L PDQ；客版收缩膜+客版收藏指南翻单4500158149 Remark: 77673TQ1： 1. 77673TQ1-S001-CC-MINI BRANDS-FILL THE FRIDGE PLAYSET-SERIES 1-SHRINK WRAP,4PCS/PDQ,4PCS/PDQ/CTN 2. 产品包装 客版收缩膜+客版收藏指南+MA说明书+ MA 1L PDQ；客版收缩膜上的UPC显示193052079404；客版收缩膜+客版收藏指南翻单4500158149 3. 外箱正唛左上角位置粘贴条码箱贴纸，每箱只贴一张，由ZURU订购。来料贴纸上显示的客户DPCI# 086-02-3468， UPC显示10193052079401; 此订单所有item： 1. 产品和包装上印刷 tracking code信息，格式为ZURU常规格式; 2. 出货方式：货代自提 | Y54: Holly Zheng | Z54: 5.53 | AA54: =Z54*I54 -> 33180 | AD54: 77673TQ1-S001-CC | AE54: 已入 | AG54: 已完成 | AI54: 6000 | AJ54: =AI54-I54 -> 0 | AP54: =I54 -> 6000 | AW54: =I54 -> 6000 | BF54: =I54 -> 6000 | BG54: =I54 -> 6000 | BH54: =I54/4 -> 1500
A55: 45695 | B55: Smyths Toys HQ UC | C55: 法国 | D55: 4500156861 | E55: 4400464930 | F55: 4500156861-10 | G55: 77673TQ1-S003 | H55: 迷你冰箱 | I55: 1000 | J55: 0 | K55: 8 | L55: =I55/K55 -> 125 | M55: 45799 | N55: 45796 | P55: PASS | R55: 45696 | S55: 无 | T55: 荷兰警语贴纸(含法国环保logo)翻4500155602 | X55: 日期码格式：ZURU INC(BVI) 标准格式 日期：按实际生产日期 Packaging Info: 77673TQ1：最新MA PDQ(优先3L )+ 客版收缩膜(英法德callout/英法德意荷警语/法国环保logo) +23L 说明书+客版收藏指南(英法德意荷) +客版WEEE声明通用说明 书(带电池) （所有资料翻单#4500155594） Remark: 1. 此单出法国，所有包装都需要含有法语，需要满足Zuru Standard欧洲标准测试要求； 2. 请准时出货，推期会有罚款； 3. 所有出口法国的产品, 法规规定禁止在包装和共公众用的印刷品中使用矿物油中含有的物质, 包装印刷油墨中含有的MOAH/MOSH的质量浓度不能超过1%, 否则出 货到法国被抽检出现问题, 供应商需要对此负责; | Y55: Ula Zhao | Z55: 5 | AA55: =Z55*I55 -> 5000 | AC55: 95065-8.17 | AD55: 77673TQ1-S003 | AE55: 已入 | AG55: 已完成 | AI55: 1000 | AJ55: =AI55-I55 -> 0 | AN55: =I55 -> 1000 | AW55: =I55 -> 1000 | BD55: =I55 -> 1000 | BE55: =I55 -> 1000 | BI55: =I55/4 -> 250
A56: 45741 | B56: Walmart Central America | C56: 萨尔瓦多 | D56: 4500161312 | E56: 5907181238 | F56: 4500161312-20 | G56: 77673-S001 | H56: 迷你冰箱12pcs/箱 | I56: 360 | J56: 0 | K56: 12 | L56: =I56/K56 -> 30 | M56: 45799 | N56: 45796 | P56: PASS | R56: 4/21，用双坑外箱 | S56: 无 | T56: 贴纸翻单PO4500161302 | X56: 日期码格式：ZURU INC(BVI) 标准格式 日期：按实际生产日期 Packaging Info: 2. 77673：MA 3L EAN包装+UPC条码贴纸+MA多语说明书+进口商贴纸+箱唛，贴纸翻单PO4500161302 Remark: 1.使用双坑外箱 2.请注意产品包装条形码必须是UPC 3.无第三方验货 | Y56: Ever Li | Z56: 4.1 | AA56: =Z56*I56 -> 1476 | AC56: 95361-8.17 | AD56: 77673-S001-3L | AE56: 已入 | AG56: 已完成 | AI56: 360 | AJ56: =AI56-I56 -> 0 | AN56: =I56 -> 360 | AS56: =I56 -> 360 | AU56: =I56 -> 360 | AW56: =I56 -> 360
A57: 45741 | B57: Walmart Central America-GT | C57: 危地马拉 | D57: 4500161302 | E57: 4407181237 | F57: 4500161302-20 | G57: 77673-S001 | H57: 迷你冰箱12pcs/箱 | I57: 396 | J57: 0 | K57: 12 | L57: =I57/K57 -> 33 | M57: 45799 | N57: 45796 | P57: PASS | R57: 4/21，用双坑外箱 | S57: 无 | T57: 45768 | X57: 日期码格式：ZURU INC(BVI) 标准格式 日期：按实际生产日期 Packaging Info: 2. 77673：MA 3L EAN包装+UPC条码贴纸+MA多语说明书+进口商贴纸+箱唛 Remark: 1.使用双坑外箱 2.请注意产品包装条形码必须是UPC 3.无第三方验货 | Y57: Ever Li | Z57: 4.1 | AA57: =Z57*I57 -> 1623.6 | AC57: 95360-8.17 | AD57: 77673-S001-3L | AE57: 已入 | AG57: 已完成 | AI57: 396 | AJ57: =AI57-I57 -> 0 | AN57: =I57 -> 396 | AS57: =I57 -> 396 | AU57: =I57 -> 396 | AW57: =I57 -> 396
A58: 45741 | B58: Walmart Central America-CR | C58: 哥斯达黎加 | D58: 4500161306 | E58: 8807181239 | F58: 4500161306-20 | G58: 77673-S001 | H58: 迷你冰箱12pcs/箱 | I58: 540 | J58: 0 | K58: 12 | L58: =I58/K58 -> 45 | M58: 45799 | N58: 45796 | P58: PASS | R58: 4/21，用双坑外箱 | S58: 无 | T58: 贴纸翻单PO4500161302 | X58: 日期码格式：ZURU INC(BVI) 标准格式 日期：按实际生产日期 Packaging Info: 2. 77673：MA 3L EAN包装+UPC条码贴纸+MA多语说明书+进口商贴纸+箱唛，贴纸翻单PO4500161302 Remark: 1.使用双坑外箱 2.请注意产品包装条形码必须是UPC 3.无第三方验货 | Y58: Ever Li | Z58: 4.1 | AA58: =Z58*I58 -> 2214 | AC58: 95359-8.17 | AD58: 77673-S001-3L | AE58: 已入 | AG58: 已完成 | AI58: 540 | AJ58: =AI58-I58 -> 0 | AN58: =I58 -> 540 | AS58: =I58 -> 540 | AU58: =I58 -> 540 | AW58: =I58 -> 540
A59: 45758 | B59: THE KROGER CO. | C59: 美国 | D59: 4500163428 | E59: PO#500-23710 | F59: 4500163428-40 | G59: 77673TQ1-S001 | H59: 迷你冰箱4pcs/箱 | I59: 640 | J59: 0 | K59: 4 | L59: =I59/K59 -> 160 | M59: 45824 | N59: 45820 | P59: PASS | R59: 45758 | S59: 无 | T59: 无 | X59: 日期码格式：ZURU INC(BVI) 标准格式 日期：按实际生产日期 Packaging Info: 1、包装方式: MA UPC 优先1L最新版，出口美国 Remark: 2、无测试无验货要求 3、纸箱4面印ZURU LOGO + 箱唛 4、日期码请按ZURU标准版执行即可 5、ZURU OQC验货 | Y59: Vicky Wu | Z59: 5.1 | AA59: =Z59*I59 -> 3264 | AC59: ZB00622-7.1 | AD59: 77673TQ1-S001 | AE59: 已入 | AG59: 已完成 | AI59: 640 | AJ59: =AI59-I59 -> 0 | AN59: =I59 -> 640 | AR59: =I59 -> 640 | AU59: =I59 -> 640 | AW59: =I59 -> 640 | BH59: =I59/4 -> 160
A60: 45758 | B60: THE KROGER CO. | C60: 美国 | D60: 4500163428 | E60: PO#600-59500 | F60: 4500163428-70 | G60: 77673TQ1-S001 | H60: 迷你冰箱4pcs/箱 | I60: 1440 | J60: 0 | K60: 4 | L60: =I60/K60 -> 360 | M60: 45824 | N60: 45820 | P60: PASS | R60: 45758 | S60: 无 | T60: 无 | X60: 日期码格式：ZURU INC(BVI) 标准格式 日期：按实际生产日期 Packaging Info: 1、包装方式: MA UPC 优先1L最新版，出口美国 Remark: 2、无测试无验货要求 3、纸箱4面印ZURU LOGO + 箱唛 4、日期码请按ZURU标准版执行即可 5、ZURU OQC验货 | Y60: Vicky Wu | Z60: 5.1 | AA60: =Z60*I60 -> 7344 | AC60: ZB00627-7.2 | AD60: 77673TQ1-S001 | AE60: 已入 | AG60: 已完成 | AI60: 1440 | AJ60: =AI60-I60 -> 0 | AN60: =I60 -> 1440 | AR60: =I60 -> 1440 | AU60: =I60 -> 1440 | AW60: =I60 -> 1440 | BH60: =I60/4 -> 360
A61: 45726 | B61: WAL-MART STORES INC. USA | C61: 美国 | D61: 4500159664 | E61: 0902421327 EASTVALE | F61: 4500159664-10 | G61: 77673TQ1-S001 | H61: 迷你冰箱4pcs/箱 | I61: 3304 | J61: 0 | K61: 4 | L61: =I61/K61 -> 826 | M61: 45803 | N61: 45799 | O61: 5/27 第三方验货 | P61: PASS | R61: 45727 | S61: 有 | T61: 45727 | V61: 每pcs产品上要贴1张RFID贴纸，贴纸由ZURU提供，贴纸位置请严格按照我们签回的签板，粉色艾利贴纸（不干胶打印） | X61: 日期码格式：ZURU DGYYYYMMDD CHINA(日期避开周末和法定节假日即可） 日期：按实际生产日期 Packaging Info: 77673TQ1-S001 1.包装要求： MA 1L A版收缩膜+MA 5L 收藏指南+MA 说明书+MA playset 每pcs产品上要贴1张RFID贴纸，贴纸由ZURU提供，贴纸位置请严格按照我们签回的签板； Remark: 77673TQ1-S001 1.包装要求： MA 1L A版收缩膜+MA 5L 收藏指南+MA 说明书+MA playset 每pcs产品上要贴1张RFID贴纸，贴纸由ZURU提供，贴纸位置请严格按照我们签回的签板； 2. 外箱印刷带条码的RFID箱唛：RFID紫色色带+WM Dept.图标+RFID图标+ITF-14条码+粉色艾利贴纸（不干胶打印），四面右下角印刷ZURU logo, ITFF条码只印刷在 正唛一面，在加印的时候确保条形码能扫描出来，1张粉红色贴纸贴在正唛对角线，外箱侧面任一角落加印："MADE IN CHINA" 字样； 3. 在产品上和包装上要有日期码、以及要有MADE IN CHINA和ZURU字样； 4. 产品如有扎带口要剪平，不能刮手。 5. 此单需要验货，请多备料 6. 此单以loose carton出货，4pcs/PDQ/CTN | Y61: Maggie Xie | Z61: 5 | AA61: =Z61*I61 -> 16520 | AD61: 77673TQ1-S001 | AE61: 已入 | AG61: 已完成 | AI61: 3304 | AJ61: =AI61-I61 -> 0 | AN61: =I61 -> 3304 | AR61: =I61 -> 3304 | AU61: =I61 -> 3304 | AW61: =I61 -> 3304 | BH61: =I61/4 -> 826
A62: 45726 | B62: WAL-MART STORES INC. USA | C62: 美国 | D62: 4500159664 | E62: 0902421372 ELWOOD | F62: 4500159664-20 | G62: 77673TQ1-S001 | H62: 迷你冰箱4pcs/箱 | I62: 3320 | J62: 0 | K62: 4 | L62: =I62/K62 -> 830 | M62: 45803 | N62: 45799 | O62: 5/27 第三方验货 | P62: PASS | R62: 45727 | S62: 有 | T62: 45727 | V62: 每pcs产品上要贴1张RFID贴纸，贴纸由ZURU提供，贴纸位置请严格按照我们签回的签板，粉色艾利贴纸（不干胶打印） | X62: 日期码格式：ZURU DGYYYYMMDD CHINA(日期避开周末和法定节假日即可） 日期：按实际生产日期 Packaging Info: 77673TQ1-S001 1.包装要求： MA 1L A版收缩膜+MA 5L 收藏指南+MA 说明书+MA playset 每pcs产品上要贴1张RFID贴纸，贴纸由ZURU提供，贴纸位置请严格按照我们签回的签板； Remark: 77673TQ1-S001 1.包装要求： MA 1L A版收缩膜+MA 5L 收藏指南+MA 说明书+MA playset 每pcs产品上要贴1张RFID贴纸，贴纸由ZURU提供，贴纸位置请严格按照我们签回的签板； 2. 外箱印刷带条码的RFID箱唛：RFID紫色色带+WM Dept.图标+RFID图标+ITF-14条码+粉色艾利贴纸（不干胶打印），四面右下角印刷ZURU logo, ITFF条码只印刷在 正唛一面，在加印的时候确保条形码能扫描出来，1张粉红色贴纸贴在正唛对角线，外箱侧面任一角落加印："MADE IN CHINA" 字样； 3. 在产品上和包装上要有日期码、以及要有MADE IN CHINA和ZURU字样； 4. 产品如有扎带口要剪平，不能刮手。 5. 此单需要验货，请多备料 6. 此单以loose carton出货，4pcs/PDQ/CTN | Y62: Maggie Xie | Z62: 5 | AA62: =Z62*I62 -> 16600 | AD62: 77673TQ1-S001 | AE62: 已入 | AG62: 已完成 | AI62: 3320 | AJ62: =AI62-I62 -> 0 | AN62: =I62 -> 3320 | AR62: =I62 -> 3320 | AU62: =I62 -> 3320 | AW62: =I62 -> 3320 | BH62: =I62/4 -> 830
A63: 45744 | B63: WALMART INC. | C63: 美国 | D63: 4500161763 | E63: 0904512337 | F63: 4500161763-10 | G63: 77673TQ1-S001 | H63: 迷你冰箱4pcs/箱 | I63: 912 | J63: 0 | K63: 4 | L63: =I63/K63 -> 228 | M63: 45803 | N63: 45799 | O63: 5/30 第三方验货 | P63: PASS | R63: 外箱印刷带条码的RFID箱唛：RFID紫色色带+WM Dept.图标+RFID图标+ITF-14条码，四面右下角印刷ZURU logo, ITFF条码只印刷在正唛一面，在加印的时候确保 条形码能扫描出来，外箱侧面任一角落加印："MADE IN CHINA" 字样； | S63: 无 | T63: 4/11 RFID贴纸 | V63: RFID贴纸 | X63: 日期码格式：ZURU DGYYYYMMDD CHINA(日期避开周末和法定节假日即可） 日期：按实际生产日期 Packaging Info: 77673TQ1-S001 1.包装要求： MA 1L A版收缩膜+MA 5L 收藏指南+MA 说明书+MA playset，翻单：4500159641 每pcs产品上要贴1张RFID贴纸，贴纸由ZURU提供，贴纸位置请严格按照我们签回的签板 Remark: 77673TQ1-S001 1.包装要求： MA 1L A版收缩膜+MA 5L 收藏指南+MA 说明书+MA playset，翻单：4500159641 每pcs产品上要贴1张RFID贴纸，贴纸由ZURU提供，贴纸位置请严格按照我们签回的签板； 2. 外箱印刷带条码的RFID箱唛：RFID紫色色带+WM Dept.图标+RFID图标+ITF-14条码，四面右下角印刷ZURU logo, ITFF条码只印刷在正唛一面，在加印的时候确保 条形码能扫描出来，外箱侧面任一角落加印："MADE IN CHINA" 字样； 3. 在产品上和包装上要有日期码、以及要有MADE IN CHINA和ZURU字样； 4. 产品如有扎带口要剪平，不能刮手。 5. 此单需要验货，请多备料 6. 此单以loose carton出货，4pcs/PDQ/CTN | Y63: Maggie Xie | Z63: 5 | AA63: =Z63*I63 -> 4560 | AD63: 77673TQ1-S001 | AE63: 已入 | AG63: 已完成 | AI63: 912 | AJ63: =AI63-I63 -> 0 | AN63: =I63 -> 912 | AR63: =I63 -> 912 | AU63: =I63 -> 912 | AW63: =I63 -> 912 | BH63: =I63/4 -> 228
A64: 45749 | B64: COOP NORGE HANDEL AS - DOM | C64: 挪威 | D64: 4500162197 | E64: 32577893 | F64: 4500162197-20 | G64: 77673TQ1-S001 | H64: 迷你冰箱4pcs/箱 | I64: 200 | J64: 0 | K64: 4 | L64: =I64/K64 -> 50 | M64: 45803 | N64: 45799 | O64: 5/27 第三方验货 | P64: PASS | R64: 45749 | S64: 无 | T64: 无 | X64: 日期码格式：ZURU INC(BVI) 标准格式 日期：按实际生产日期 Packaging Info: 2.77673TQ1：MA EAN 3L收缩膜+挪威语警语贴纸+MA 23L 电池警告语说明书+MA-A 3L 展示盒+带纽扣电池走货北欧六语通用黑白电池说明书 Remark: 1/产品和包装要求无硼无香，包装不能含有PVC； 2/如有微塑料，必须合规欧洲标准，闪粉也是微塑料的一种，目前仅接受三张方式1.去除，2.用可降解材料，和3.永久封印在固体； 3/此订单有第三方验货，请准备三套大货样并不迟于5-14寄出给ZURU 深圳办公室； 4/带电池出货的产品所用到的电池需要符合欧洲电池新规(EU)2023-1542； 5/工厂货号-客户货号彩盒条码-外箱条码 77673TQ1-7254554-4894680042773-10193052079401 6/配比: 77673TQ1：Filxed Collection | Y64: Zoe Zhou | Z64: 4.3 | AA64: =Z64*I64 -> 860 | AC64: 95228-8.17 | AD64: 77673TQ1-S001-MTS | AE64: 已入 | AG64: 已完成 | AI64: =196+4 -> 200 | AJ64: =AI64-I64 -> 0 | AN64: =I64 -> 200 | AS64: =I64 -> 200 | AU64: =I64 -> 200 | AW64: =I64 -> 200 | BI64: =I64/4 -> 50
A65: 45749 | B65: K􀃤rkk􀃤inen Oy /Centrawla rehouse | C65: 芬兰 | D65: 4500161573 | E65: 4100411993 | F65: 4500161573-230 | G65: 77673TQ1-S001 | H65: 迷你冰箱 | I65: 240 | J65: 0 | K65: 4 | L65: =I65/K65 -> 60 | M65: 45803 | N65: 45799 | P65: PASS | R65: 45769 | S65: 无 | T65: 45765 | X65: 日期码格式：ZURU INC(BVI) 标准格式 日期：按实际生产日期 Packaging Info: 16. 77673TQ1: MA 3L EAN版收缩膜+瑞典芬兰爱沙尼亚语警告语/MADE IN CHINA翻译成瑞典芬兰爱沙尼亚语言做成一张贴纸+MA 5L收藏指南+MA 电池+UV胶警告语-23 L+MA 3L PDQ+带纽扣电池走货北欧六语通用黑白电池说明书 2. 配比跟MA Remark: 1. 包装如含PVC,请改为PET并第一时间通知跟单 2. 产品/包装要求无硼无香，出欧洲，微塑料需合规。 3.带电池出货的产品所用到的电池需要符合欧洲电池新规(EU) 2023-1542 4.有胶袋的产品：要求产品的胶袋厚度要大于等于0.05mm 5.关于贴纸，如果贴纸位置图的包装版本与大货不一致，请工厂第一时间提前提出。跟单会重新调整确认是否更新贴纸或调整位置图 6.产品/包装不含PFAS成分 7.产品条码如下: 请先检查条码是否正确再安排做货，如有问题请告知 ZURU ITEM#<(>&<)>EAN: 77673TQ1:4894680042773 | Y65: Sheba | Z65: 5.1 | AA65: =Z65*I65 -> 1224 | AC65: 95198-8.17 | AD65: 77673TQ1-S001-MTS | AE65: 已入 | AG65: 已完成 | AI65: 240 | AJ65: =AI65-I65 -> 0 | AN65: =I65 -> 240 | AS65: =I65 -> 240 | AU65: =I65 -> 240 | AW65: =I65 -> 240 | BI65: =I65/4 -> 60
A66: 45768 | B66: UPD, INC. | C66: 美国 | D66: 4500164375 | E66: PO# 34501 | F66: 4500164375-30 | G66: 77673TQ1-S002 | H66: 迷你冰箱 | I66: 800 | J66: 0 | K66: 16 | L66: =I66/K66 -> 50 | M66: 45804 | N66: 45800 | P66: PASS | R66: 45771 | S66: 无 | T66: 无 | X66: 日期码格式：ZURU INC(BVI) 标准格式 日期：按实际生产日期 Packaging Info: 1. 包装方式：MA UPC 优先1L 最新包装，出口美国 Remark: 2. 外箱箱唛红色和黑色双色印刷 3. 产品和包装上印刷tracking code信息，格式为ZURU常规 4. 需要ZURU QC 验货合格后方可出货 5. 整柜出货。 | Y66: Sia Liu | Z66: 2.634 | AA66: =Z66*I66 -> 2107.2 | AD66: 77673TQ1-S002 | AE66: 已入 | AG66: 已完成 | AI66: 800 | AJ66: =AI66-I66 -> 0 | AN66: =I66 -> 800 | AR66: =I66 -> 800 | AU66: =I66 -> 800 | AW66: =I66 -> 800 | BH66: =I66/4 -> 200
A67: 45771 | B67: ZURU Germany GMBH | C67: 德国 | D67: 4500164783 | E67: 5200006663 | F67: 4500164783-80 | G67: 77673-S004-MTS | H67: 迷你冰箱 4pcs/箱 | I67: 1200 | J67: 0 | K67: 4 | L67: =I67/K67 -> 300 | M67: 45804 | N67: 45800 | P67: PASS | R67: 45772 | S67: 无 | T67: 45783 | X67: 日期码格式：ZURU INC(BVI) 标准格式 日期：按实际生产日期 Packaging Info: 8.77673：MA 3L 最新版EAN收缩膜+1张多语可折叠贴纸+MA 5L收藏指南+1张5L（PL+HU+CZ+SK+RO )贴纸+MA 23L 电池+UV胶警告语+1张30L WEEE带电池走货说明书+ 其它MA包装； Remark: 1.波兰内销单，需要通过ZURU 验货结果后才能出货 (工厂需要主动提前同ZURU QC预约验货避免延期出货造成不必要麻烦)； 2. 若有特定款有特殊外箱条码要求时,需要明确列出产品款对应的具体外箱条码号码/条码类型 (若无,可以忽略此需求) 3.所有出口欧洲的产品, 法规规定禁止在包装和共公众用的印刷品中使用矿物油中含有的物质, 包装印刷油墨中含有的MOAH/MOSH的质量浓度不能超过1%, 否则出货 到法国被抽检出现问题, 供应商需要对此负责; 4. date code: 外箱日期码要晚于或等于产品日期码，不能早于产品的日期码 5. 所有电子产品身上需要加字唛，为ZURU FRANCE 地址 (如无电子产品，或者产品布标有此地址，可忽略此信息) ZURU France 1/3, Rue d'Argenteuil 95210 SAINT-GRATIEN, FRANCE 6. 装柜时需要按照款式号码从小到大一款款依次装,避免终端仓库卸货混乱.若一个柜子涉及到几个不同国家内销单,装柜时需要一个国家装完后再装另一个国家的 产品,依次装柜,避免终端仓库因不同国家不同库位位置卸货混乱. (此点需要同工厂装柜人员强调) | Y67: Amy Xiao | Z67: 4.1 | AA67: =Z67*I67 -> 4920 | AC67: 95098-8.17 | AD67: 77673-S004-3L | AE67: 已入 | AG67: 已完成 | AI67: 1200 | AJ67: =AI67-I67 -> 0 | AN67: =I67 -> 1200 | AS67: =I67 -> 1200 | AU67: =I67 -> 1200 | AW67: =I67 -> 1200 | BI67: =I67/4 -> 300
A68: 45740 | B68: GLOBUS Logistik GmbH and Co KG | C68: 德国 | D68: 4500161168 | E68: 10355376 | F68: 4500161168-70 | G68: 77673TQ1-S001 | H68: 迷你冰箱4pcs/箱 | I68: 540 | J68: 0 | K68: 4 | L68: =I68/K68 -> 135 | M68: 45807 | N68: 45803 | P68: PASS | R68: 45772 | S68: 有 | T68: 45774 | X68: 日期码格式：ZURU INC(BVI) 标准格式 日期：按实际生产日期 Packaging Info: "77673TQ1: MA EAN收缩膜3L-A版本（+德语警告语贴纸）+MA电池+UV胶警告语23L说明书+MA纸袋+MA收藏指南5L-A版本+ MA PDQ3L-A版本+WEEE 带电池走货 通用30 L 说明书 EAN:4894680042773 Remark: "1. 此单出德国，需准时出货。无须客户第三方验货但是需要在6-2 提供验货图片(含不良图）。待客人放货后才能安排走货。 2. 外箱正唛需要贴产品图片贴纸，（外箱印4面-2*正唛+2*侧唛） 3. 外箱正唛需要印GTIN, 请保证GTIN条码能扫描。 4. 需要在货期前一个月安排2套样品给客户评估（非测试，包装无要求）" | Y68: Claire Wang | Z68: 5 | AA68: =Z68*I68 -> 2700 | AC68: 95229-8.17 | AD68: 77673TQ1-S001-MTS | AE68: 已入 | AG68: 已完成 | AI68: 540 | AJ68: =AI68-I68 -> 0 | AN68: =I68 -> 540 | AS68: =I68 -> 540 | AU68: =I68 -> 540 | AW68: =I68 -> 540 | BI68: =I68/4 -> 135
A69: 45744 | B69: WALMART INC. | C69: 美国 | D69: 4500161764 | E69: 0904512321 | F69: 4500161764-10 | G69: 77673TQ1-S001 | H69: 迷你冰箱4pcs/箱 | I69: 1104 | J69: 0 | K69: 4 | L69: =I69/K69 -> 276 | M69: 45807 | N69: 45803 | O69: 5/30 第三方验货 | P69: PASS | R69: 外箱印刷带条码的RFID箱唛：RFID紫色色带+WM Dept.图标+RFID图标+ITF-14条码，四面右下角印刷ZURU logo, ITFF条码只印刷在正唛一面，在加印的时候确保 条形码能扫描出来，外箱侧面任一角落加印："MADE IN CHINA" 字样； | S69: 无 | T69: 4/11 RFID贴纸 | V69: RFID贴纸 | X69: 日期码格式：ZURU DGYYYYMMDD CHINA(日期避开周末和法定节假日即可） 日期：按实际生产日期 Packaging Info: 77673TQ1-S001 1.包装要求： MA 1L A版收缩膜+MA 5L 收藏指南+MA 说明书+MA playset，翻单：4500159641 每pcs产品上要贴1张RFID贴纸，贴纸由ZURU提供，贴纸位置请严格按照我们签回的签板； Remark: 77673TQ1-S001 1.包装要求： MA 1L A版收缩膜+MA 5L 收藏指南+MA 说明书+MA playset，翻单：4500159641 每pcs产品上要贴1张RFID贴纸，贴纸由ZURU提供，贴纸位置请严格按照我们签回的签板； 2. 外箱印刷带条码的RFID箱唛：RFID紫色色带+WM Dept.图标+RFID图标+ITF-14条码，四面右下角印刷ZURU logo, ITFF条码只印刷在正唛一面，在加印的时候确保 条形码能扫描出来，外箱侧面任一角落加印："MADE IN CHINA" 字样； 3. 在产品上和包装上要有日期码、以及要有MADE IN CHINA和ZURU字样； 4. 产品如有扎带口要剪平，不能刮手。 5. 此单需要验货，请多备料 6. 此单以loose carton出货，4pcs/PDQ/CTN | Y69: Maggie Xie | Z69: 5 | AA69: =Z69*I69 -> 5520 | AD69: 77673TQ1-S001 | AE69: 已入 | AG69: 已完成 | AI69: 1104 | AJ69: =AI69-I69 -> 0 | AN69: =I69 -> 1104 | AR69: =I69 -> 1104 | AU69: =I69 -> 1104 | AW69: =I69 -> 1104 | BH69: =I69/4 -> 276
A70: 45758 | B70: JUGUETES PASTOR S.L. | C70: 西班牙 | D70: 4500163040 | F70: 4500163040-30 | G70: 77673-S001 | H70: 迷你冰箱12pcs/箱 | I70: 240 | J70: 0 | K70: 12 | L70: =I70/K70 -> 20 | M70: 45807 | N70: 45803 | P70: PASS | R70: 45758 | S70: 无 | T70: 45761 | X70: 日期码格式：ZURU INC(BVI) 标准格式 日期：按实际生产日期 Packaging Info: 2.77673:最新MA 3L EAN 版本包装+一张西班牙环保标<(>&<)>邮箱贴纸+MA 23L 说明书+MA 5L Creative 说明书+MA 3L PDQ； Remark: | Y70: Miya Fang | Z70: 4.1 | AA70: =Z70*I70 -> 984 | AC70: 95263-8.17 | AD70: 77673-S001-3L | AE70: 已入 | AG70: 已完成 | AI70: 240 | AJ70: =AI70-I70 -> 0 | AN70: =I70 -> 240 | AS70: =I70 -> 240 | AU70: =I70 -> 240 | AW70: =I70 -> 240
A71: 45758 | B71: ARGOS LIMITED | C71: 英国 | D71: 4500163218 | E71: PO#239936-Cus tomer SKU#7624348 | F71: 4500163218-30 | G71: 77673-S001 | H71: 迷你冰箱12pcs/箱 | I71: 156 | J71: 0 | K71: 12 | L71: =I71/K71 -> 13 | M71: 45807 | N71: 45803 | P71: PASS | R71: 45758 | S71: 无 | T71: 45775 | X71: 日期码格式：ZURU INC(BVI) 标准格式 日期：按实际生产日期 Packaging Info: 77673-S001 MA -1L UPC包装+客人白色Cat.label 1张覆盖ZURU条码 -注意Cat.label (要求易撕类贴纸，但是粘性不能过低），同时此贴纸每个订单都是不相同的(会显示客户对应的订单号），切勿翻旧订单购买，该贴纸由工厂自行 购买。 -订单对应客户PO号备注有显示 Remark: *MA包装按最新版本安排即可 *包装日期码按ZURU格式即可，请确保不迟于外箱日期码，可等于或者早于外箱日期码，必须为法定工作日。 *外箱尺寸任何一条边长度超过75cm或者每箱重量超过10KG,需要在外箱上加三脚架符号，有问题请与ZURU跟单同事核实。 *订单必须经过ZURU QC验货并且通过后方可出货。 *订单出英国，请注意检查产品及包装应带UKCA图标，包装显示ZURU UK LTD信息，QC同事请查核，如有问题与跟单确认。 *条码扫描会显示客户7位数产品号 ，忽略订单显示的MA条码 *所有产品按符合欧洲标准走货，微塑料需合规。 *涉及到硼的，需要符合欧洲标准 | Y71: May Wu | Z71: 4.1 | AA71: =Z71*I71 -> 639.6 | AC71: 95151-8.17 | AD71: 77673-S001 | AE71: 已入 | AG71: 已完成 | AI71: 156 | AJ71: =AI71-I71 -> 0 | AN71: =I71 -> 156 | AR71: =I71 -> 156 | AU71: =I71 -> 156 | AW71: =I71 -> 156
A72: 45772 | B72: UNIPAM SRL | C72: 意大利 | D72: 4500164781 | F72: 4500164781-20 | G72: 77673TQ1-S001 | H72: 迷你冰箱4pcs/箱 | I72: 320 | J72: 0 | K72: 4 | L72: =I72/K72 -> 80 | M72: 45810 | N72: 45806 | P72: PASS | R72: 45785 | S72: 无 | T72: 贴纸和WEEE翻4500162314 | X72: 日期码格式：ZURU INC(BVI) 标准格式 日期：按实际生产日期 Packaging Info: 2.77673TQ1:最新MA 3L EAN收缩膜+最新MA 5L收藏指南+最新MA 23L说明书+最新MA纸袋+最新MA 3L PDQ+一张警语贴纸（含意大利警语和意大利环保标）+ 多语版WEE E电池垃圾桶的回收声明说明书（ included，翻4500162314） Remark: 1. SMASHERS 或含Slime产品，所有化合物使用无硼版本出意大利。 2. 本订单所有 具有 baby items / assorted items 的款式，零售包装上都要用 母 EAN; 3.所有出口欧洲的产品, 法规规定禁止在包装和共公众用的印刷品中使用矿物油中含有的物质, 包装印刷油墨中含有的MOAH/MOSH的质量浓度不能超过1%, 否则出货 到意大利被抽检出现问题, 供应商需要对此负责; 4. 意大利订单包装彩卡请确保含法规要求的环保回收logo。 | Y72: Christine He | Z72: 5.1 | AA72: =Z72*I72 -> 1632 | AC72: 95380-8.17 | AD72: 77673TQ1-S001-MTS | AE72: 已入 | AG72: 已完成 | AI72: 320 | AJ72: =AI72-I72 -> 0 | AN72: =I72 -> 320 | AS72: =I72 -> 320 | AU72: =I72 -> 320 | AW72: =I72 -> 320 | BI72: =I72/4 -> 80
A73: 45763 | B73: NORWEGIAN TOY IMPORT AS - DOM | C73: 挪威 | D73: 4500163205 | E73: 14675 | F73: 4500163205-150 | G73: 77673TQ1-S001 | H73: 迷你冰箱4pcs/箱 | I73: 12 | J73: 0 | K73: 4 | L73: =I73/K73 -> 3 | M73: 45811 | N73: 45807 | P73: PASS | R73: 45763 | S73: 无 | T73: 45789 | X73: 日期码格式：ZURU INC(BVI) 标准格式 日期：按实际生产日期 Packaging Info: 77673TQ1：MA EAN 3L收缩膜 +MA 23L 电池警告语说明书 +MA-A 3L 展示盒+进口商贴纸+带纽扣电池走货北欧六语通用黑白电池说明书_OL_画板 1 Remark: 1/配比： 2/产品和包装要求无硼无香，包装不能含有PVC; 如有微塑料，必须合规欧洲标准，闪粉也是微塑料的一种，目前仅接受三张方式1.去除，2.用可降解材料，和3. 永久封印在固体。 3/带电池出货的产品,电池需要符合欧洲电池新规(EU) 2023-1542. | Y73: Zoe Zhou | Z73: 5.1 | AA73: =Z73*I73 -> 61.2 | AC73: 95231-8.17 | AD73: 77673TQ1-S001-MTS | AE73: 已入 | AG73: 已完成 | AI73: 12 | AJ73: =AI73-I73 -> 0 | AN73: =I73 -> 12 | AS73: =I73 -> 12 | AU73: =I73 -> 12 | AW73: =I73 -> 12 | BI73: =I73/4 -> 3
A74: 45763 | B74: NORWEGIAN TOY IMPORT AS - DOM | C74: 挪威 | D74: 4500163205 | E74: 14675 | F74: 4500163205-120 | G74: 77673-S001 | H74: 迷你冰箱12pcs/箱 | I74: 300 | J74: 0 | K74: 12 | L74: =I74/K74 -> 25 | M74: 45811 | N74: 45807 | P74: PASS | R74: 45763 | S74: 无 | T74: 45789 | X74: 日期码格式：ZURU INC(BVI) 标准格式 日期：按实际生产日期 Packaging Info: 77673：MA_A EAN 3L 收缩膜 +进口商贴纸+带纽扣电池走货北欧六语通用黑白电池说明书_OL_画板 1 Remark: 1/配比： 2/产品和包装要求无硼无香，包装不能含有PVC; 如有微塑料，必须合规欧洲标准，闪粉也是微塑料的一种，目前仅接受三张方式1.去除，2.用可降解材料，和3. 永久封印在固体。 3/带电池出货的产品,电池需要符合欧洲电池新规(EU) 2023-1542. | Y74: Zoe Zhou | Z74: 4.1 | AA74: =Z74*I74 -> 1230 | AC74: 95231-8.17 | AD74: 77673-S001-3L | AE74: 已入 | AG74: 已完成 | AI74: 300 | AJ74: =AI74-I74 -> 0 | AN74: =I74 -> 300 | AS74: =I74 -> 300 | AU74: =I74 -> 300 | AW74: =I74 -> 300
A75: 45765 | B75: Lekia AB | C75: 瑞典 | D75: 4500164226 | E75: 156653-2 | F75: 4500164226-30 | G75: 77673TQ1-S001 | H75: 迷你冰箱4pcs/箱 | I75: 960 | J75: 0 | K75: 4 | L75: =I75/K75 -> 240 | M75: 45811 | N75: 45807 | P75: PASS | R75: 45772 | S75: 无 | T75: 45786 | X75: 日期码格式：ZURU INC(BVI) 标准格式 日期：按实际生产日期 Packaging Info: 77673TQ1-S001:MA 3L EAN版收缩膜+警告语/进口商贴纸+MA 5L收藏指南+MA （电池+UV胶警告语-23L）说明书+MA 3L PDQ+带纽扣电池走货北欧六语通用黑白电池说 明书 北欧五语通用Slime黑白说明书 带纽扣电池走货北欧六语通用黑白电池说明书 不带电池走货北欧六语通用黑白电池说明书 上述说明书翻单4500162375,之前已通知按照MA采购，不要重复订购 Remark: "1. 包装如含PVC,请改为PET 2. 产品/包装要求无硼无香； 3. 出欧洲，微塑料需合规。 4.带电池出货的产品所用到的电池需要符合欧洲电池新规(EU) 2023-1542 5.关于贴纸，如果贴纸位置图的包装版本与大货不一致，请工厂提前提出。跟单会重新调整确认是否更新贴纸或调整位置图 6.产品/包装不含PFAS成分 7. 产品信息： 77673TQ1-S001//100-223011473//4894680042773 | Y75: Luna Lin | Z75: 5 | AA75: =Z75*I75 -> 4800 | AC75: 95199-8.17 | AD75: 77673TQ1-S001-MTS | AE75: 已入 | AG75: 已完成 | AI75: 960 | AJ75: =AI75-I75 -> 0 | AN75: =I75 -> 960 | AS75: =I75 -> 960 | AU75: =I75 -> 960 | AW75: =I75 -> 960 | BI75: =I75/4 -> 240
A76: 45761 | B76: HARVEY WHOLESALE LTD | C76: 新西兰 | D76: 4500163518 | E76: 3006 | F76: 4500163518-20 | G76: 77673-S003 | H76: 迷你冰箱6pcs/箱 | I76: 504 | J76: 0 | K76: 6 | L76: =I76/K76 -> 84 | M76: 45813 | N76: 45810 | P76: PASS | R76: 45761 | S76: 无 | T76: 45768 | X76: 日期码格式：ZURU INC(BVI) 标准格式 日期：按实际生产日期 Packaging Info: #77673:Filxed Collection; 3PCS AG13 BATTERIES(INCLUDED) Remark: MA UPC 英语包装（优先1L英语版本,或者3L/L含英语即可 #77673包装正面和说明书都需要加电池警告语贴纸（法规要求） | Y76: Abby Liang | Z76: 4.2099 | AA76: =Z76*I76 -> 2121.7896 | AC76: 95196-8.17 | AD76: 77673-S003 | AE76: 已入 | AG76: 已完成 | AI76: 504 | AJ76: =AI76-I76 -> 0 | AN76: =I76 -> 504 | AR76: =I76 -> 504 | AU76: =I76 -> 504 | AW76: =I76 -> 504
A77: 45756 | B77: KMART AUSTRALIA LTD | C77: 澳大利亚 | D77: 4500162968 | E77: 20768339 | F77: 4500162968-70 | G77: 77673-S001 | H77: 迷你冰箱12pcs/箱 | I77: 1500 | J77: 0 | K77: 12 | L77: =I77/K77 -> 125 | M77: 45803 | N77: 45799 | P77: PASS | R77: 45769 | S77: 有 | T77: 45783 | X77: 日期码格式：ZURU INC(BVI) 标准格式 日期：按实际生产日期 Packaging Info: 77673-S001: MA英语UPC版本包装（收缩膜和说明书, MA首选1L，如无1L可用多语且含英语的配套多语包装) + 1张说明书纽扣电池警告语贴纸+ 1张收缩膜纽扣电池 警告语贴纸+ 1张防盗贴纸+箱唛 + 外箱SSCC Label (贴纸以及位置图翻单PO#4500160026） Remark: 1.请务必按时完货，验货。并且按期送货入货代指定仓库，如果晚了导致船期Delay将会有罚金产生或者客户要求空运，所产生的罚金和空运费由工厂承担。 2.SSCC 外箱贴纸请同纸箱瓦楞纸方向（竖纹向）垂直，即外箱贴纸横着贴(注意条码不要被胶带粘住），贴1pc，贴1面正唛，封箱胶纸不能挡住贴纸内容。外箱贴纸 离外箱边距离不少于2cm。 3.外箱材质为ZURU标准； 4.此单需使用KMART封箱胶上下工字型封箱;从2019年6月开始，要用KMART 新版封箱胶带，此单要用"ANKO"封箱胶带 5.此单出口澳大利亚，请按相应的澳新标准生产； 6.产品和包装上生产批号的显示格式ZURU标准日期码格式 7.外箱信息不可手写，重量和体积需要与实际的一致(不可手写） 8. 每款item装箱后的G.W.超过10KG或者CBM超过0.13,(9.5KG或者以上，四舍五入后也属于10KG) 需在外箱上加印超 重或者Bulky LOGO，若发现我们资料没有，请 帮忙提醒 1)重量超过10kg但不超过16kg且CBM不超过0.13,10-16kg 超重logo 2）CBM超过0.13且重量少于17kg，bulky logo 3）不属于以上两种情况，需要使用相应重量范围内的超重logo 4）超重logo需要在外箱四面都印刷(箱唛右上角，两面侧唛超重logo需要尽量靠近毛重)，尺寸为:110mm height* 95mm width 9. 实际外箱重量跟印在箱唛上的数据差异不能超3%，尺寸按实际数据印刷 | Y77: Lydia Wu | Z77: 4.19 | AA77: =Z77*I77 -> 6285 | AC77: 95157-8.17 | AD77: 77673-S001 | AE77: 已入 | AG77: 已完成 | AI77: 1500 | AJ77: =AI77-I77 -> 0 | AN77: =I77 -> 1500 | AR77: =I77 -> 1500 | AU77: =I77 -> 1500 | AW77: =I77 -> 1500
A78: 45791 | D78: ZMPO250381 | G78: 77673-S001 | H78: 迷你冰箱12pcs/箱 | I78: 168 | J78: 0 | K78: 12 | L78: =I78/K78 -> 14 | M78: 45806 | N78: 45803 | P78: PASS | R78: 45791 | S78: 无 | T78: 无 | X78: Remark:大货最新版本包装/大货标准箱装箱/箱唛请参照邮件附件;备注：收到样品订单后尽快安排 ，注意样板品质质量要求要高于大货品质要求 ，送货时必须要附带送货单(没有送货单和QC检验合格报告的仓库一律拒绝收货)，请知悉，谢谢！ | Y78: Angus | AC78: 95867-7.31 | AD78: 77673-S001 | AE78: 已入 | AG78: 已完成 | AI78: 168 | AJ78: =AI78-I78 -> 0 | AN78: =I78 -> 168 | AR78: =I78 -> 168 | AU78: =I78 -> 168 | AW78: =I78 -> 168
A79: 45764 | B79: ZURU France | C79: 法国 | D79: 4500163334 | E79: 5200006584 | F79: 4500163334-70 | G79: 77673TQ1-S001-MTS | H79: 迷你冰箱4pcs/箱 | I79: 6700 | J79: 0 | K79: 4 | L79: =I79/K79 -> 1675 | M79: 45808 | N79: 45804 | P79: PASS | R79: 45768 | S79: 无 | T79: 贴纸和WEEE翻4500162314 | X79: 日期码格式：ZURU INC(BVI) 标准格式 日期：按实际生产日期 Packaging Info: 77673TQ1:最新MA 3L EAN收缩膜+最新MA 5L收藏指南+最新MA 23L说明书+最新MA纸袋+最新MA 3L PDQ+多语警语折叠贴纸（含包装缺失的法/意/西环保标）+ 多语版W EEE电池垃圾桶的回收声明说明书（ included）（贴纸和WEEE翻4500162314） Remark: 1. 法国国家内销单，需要通过ZURU 验货结果后才能出货 (工厂需要主动提前同ZURU QC预约验货避免延期出货造成不必要麻烦)； 2. 本订单所有 具有 baby items / assorted items 的款式，零售包装上都要用 母 EAN; 3. 若有特定款有特殊外箱条码要求时,需要明确列出产品款对应的具体外箱条码号码/条码类型 (若无,可以忽略此需求) 4. 所有出口欧洲的产品, 法规规定禁止在包装和共公众用的印刷品中使用矿物油中含有的物质, 包装印刷油墨中含有的MOAH/MOSH的质量浓度不能超过1%, 否则出 货到法国被抽检出现问题, 供应商需要对此负责; 5. Date code: 外箱/产品/包装 保持一致，完货后提供date code 信息以便我们保存记录做批次管理; 6. 装柜时需要按照款式号码从小到大一款款依次装,避免终端仓库卸货混乱.若一个柜子涉及到几个不同国家内销单,装柜时需要一个国家装完后再装另一个国家的 产品,依次装柜,避免终端仓库因不同国家不同库位位置卸货混乱. (此点需要同工厂装柜人员强调) | Y79: Jade Wang | Z79: 5.03 | AA79: =Z79*I79 -> 33701 | AC79: 95292-8.17 | AD79: 77673TQ1-S001-MTS | AE79: 已入 | AG79: 已完成 | AI79: =20+6680 -> 6700 | AJ79: =AI79-I79 -> 0 | AN79: =I79 -> 6700 | AS79: =I79 -> 6700 | AU79: =I79 -> 6700 | AW79: =I79 -> 6700 | BI79: =I79/4 -> 1675
A80: 45765 | B80: MAGGIO 3 SRL | C80: 意大利 | D80: 4500163950 | F80: 4500163950-10 | G80: 77673TQ1-S002 | H80: 迷你冰箱 | I80: 1600 | J80: 0 | K80: 16 | L80: =I80/K80 -> 100 | M80: 45810 | N80: 45806 | P80: PASS | R80: 45777 | S80: 无 | T80: 45784 | X80: 日期码格式：ZURU INC(BVI) 标准格式 日期：按实际生产日期 Packaging Info: 77673TQ1: （MA 3L PDQ+1张展示架ITF14条码贴纸）+MA A 3L 收缩膜含EAN条码+进口商含意大利环保标贴纸+MA A5L收藏指南，MA A23L说明书 Remark: 1.此单出意大利，需满足EU测试标准要求<(>&<)> 微塑料需符合法规，如果有slime等化学品需要不含硼 2.需保证按期完货，延期罚款。 3.贴纸切勿盖住意大利警告语文字(QC 务必检查），特别是产品包装比较小的,如果会挡住产品上的警示语信息，在做大货前工厂需要提前告知跟单位置图是否OK， 需再次确认才能安排生产大货。 4. 标准配比 5. 需要ZURU OQC 验货， 需提供验货图片给到客户放货。 | Y80: Mary Zhong | Z80: 4.39 | AA80: =Z80*I80 -> 7024 | AC80: 95665-7.17 | AD80: 77673TQ1-S002-3L | AE80: 已入 | AG80: 已完成 | AI80: 1600 | AJ80: =AI80-I80 -> 0 | AN80: =I80 -> 1600 | AS80: =I80 -> 1600 | AU80: =I80 -> 1600 | AW80: =I80 -> 1600 | BI80: =I80/4 -> 400
A81: 45769 | B81: JUGATOYS S.L. | C81: 西班牙 | D81: 4500163874 | F81: 4500163874-30 | G81: 77673-S003 | H81: 迷你冰箱6pcs/箱 | I81: 480 | J81: 0 | K81: 6 | L81: =I81/K81 -> 80 | M81: 45812 | N81: =M81-4 -> 45808 | P81: PASS | R81: 45774 | S81: 无 | T81: 45790 | V81: 日期码格式：LOTE：39-工厂城市名缩写 20250602,只显示在包装上面即可 | X81: 日期码格式：LOTE：39-工厂城市名缩写 20250603,只显示在包装上面即可 日期： Packaging Info 77673:MA A 3L 收缩膜含EAN条码+进口商贴纸+MA A5L收藏指南，MA A23L说明书（产品包装和PDQ都需要贴纸）+WEEE带电池走货欧洲30语通用黑白说明书 Remark: 1. 此单出西班牙，需满足EU测试标准要求，另外微塑料需符合EU法规； 2. 标准配比 3. 客户日期码格式 LOTE：39-工厂城市名缩写 20250603 ，客户日期码格式需显示在包装上，否则会有客诉。不用重复显示在产品上面，产品<(>&<)> 外箱格式可 以用回ZURU格式。 4.根据新电池法规（EU） 2023/1542， 所有走欧洲市场的电子产品，都需要增加WEEE通用30L说明书（分带电池走货 跟 不带电池走货两种），如工厂没有此文件， 可以找我们跟单提供 5. 准时完货，需安排ZURU OQC验货。 另外， 包装贴纸上面的警告语不可以覆盖西班牙警告语。 | Y81: Mary Zhong | Z81: 4.2099 | AA81: =Z81*I81 -> 2020.752 | AC81: 95237-8.17 | AD81: 77673-S003-3L | AE81: 已入 | AG81: 已完成 | AI81: 480 | AJ81: =AI81-I81 -> 0 | AL81: 欠 | AN81: =I81 -> 480 | AS81: =I81 -> 480 | AU81: =I81 -> 480 | AW81: =I81 -> 480
A82: 45768 | B82: NORDIC TOY TEAM AS - DOM | C82: 挪威 | D82: 4500164402 | E82: 1310 | F82: 4500164402-20 | G82: 77673-S001 | H82: 迷你冰箱12pcs/箱 | I82: 1800 | J82: 0 | K82: 12 | L82: =I82/K82 -> 150 | M82: 45814 | N82: 45810 | P82: PASS | R82: 45768 | S82: 无 | T82: 45786 | V82: 进口商贴纸 | X82: 日期码格式：ZURU INC(BVI) 标准格式 日期：按实际生产日期 Packaging Info: 77673: MA_A EAN 3L 收缩膜+MA 5L 收藏指南+进口商贴纸 Remark: 1/产品和包装要求无硼无香，包装不能含有PVC 2/如有微塑料，必须合规欧洲标准，闪粉也是微塑料的一种，目前仅接受三张方式1.去除，2.用可降解材料，和3.永久封印在固体。 3/带电池出货的产品，所用到的电池需要符合欧洲电池新规(EU)2023-1542 4/产品配比 77673: Filxed Collection | Y82: Zoe Zhou | Z82: 4.1 | AA82: =Z82*I82 -> 7380 | AC82: 95230-8.17 | AD82: 77673-S001-3L | AE82: 已入 | AG82: 已完成 | AI82: 1800 | AJ82: =AI82-I82 -> 0 | AN82: =I82 -> 1800 | AS82: =I82 -> 1800 | AU82: =I82 -> 1800 | AW82: =I82 -> 1800
A83: 45765 | B83: Amazon EU SARL, Ndl Deutschland | C83: 英国 | D83: 4500164250 | E83: Amazon UK:3P5HOGHS | F83: 4500164250-100 | G83: 77673-S001 | H83: 迷你冰箱12pcs/箱 | I83: 504 | J83: 0 | K83: 12 | L83: =I83/K83 -> 42 | M83: 45814 | N83: 45810 | P83: PASS | R83: 空白外箱（加印带Zuru字样的最新logo，除了邮包盒直接做外箱的产品） + SSCC LABEL一张, 无箱唛，MADE IN CHINA 外箱只印一正一侧。箱唛资料按照给定的 标准去做即可，无需发回我方再行审批(新标准将另行通知)。 | S83: 有 | T83: 2张贴纸(1张UPC#，参考翻单PO#4500158582；1张可折叠警语贴 含德意警告语+IT环保标，参考翻单PO#4500157858); | X83: 日期码格式：ZURU INC(BVI) 标准格式 日期：按实际生产日期 Packaging Info: Amazon UK(15714K/7150B/77673/77723/92119AH/9279B/9561)/FR(9543D)/DE(71126/77555/77731/92104G/9543E) 3. 77673：12pcs/ctn; MA 3L(3L warning EAN#)A收缩膜+MA 23L warning说明书+MA 5L A收藏指南+2张贴纸(1张UPC#，参考翻单PO#4500158582；1张可折叠警语贴 含德意警告语+IT环保标，参考翻单PO#4500157858); 14. 最迟验货不得晚于2025/6/6 & 2025/6/9; Remark: 1.空白外箱（加印带Zuru字样的最新logo，除了邮包盒直接做外箱的产品） + SSCC LABEL一张, 无箱唛，MADE IN CHINA 外箱只印一正一侧。箱唛资料按照给定的 标准去做即可，无需发回我方再行审批(新标准将另行通知)。 (SSCC LABEL竖贴在外箱正面的正中间，贴一面即可,贴纸离外箱边距必须至少3.2CM。如竖贴无法满足要求，则横贴。如横贴也无法满足要求，则竖贴，遮到ZURU lo go无影响), SSCC贴纸由工厂直接跟勤得采购或者工厂自行采购，每一张SSCC Label都是唯一且有不同流水及条码，且需要检查条码是否能正常扫描，另外，此贴纸 印刷不可出现模糊，溢出及粘胶不牢易脱落等现象，如工厂不按此要求导致贴纸有任何问题产生的罚款将由工厂承担一切责任 。 2.出往UK的产品+包装务必打上UKCA logo ，否则客人会退货且当地会有罚款。 3.订单必须经过ZURU QC验货并且通过后方可出货。 4.法国订单要求包装不使用矿物油，请按要求提供以下其中一份文件再出货 ，产品出到法国被相关部门抽检出现包装不符合此要求的，供应商需要为此承担责任， 故此请严格把关。 -油墨物质""由1 ~ 7个芳香环组成的MOAH""的包装检测报告，要求限值≤1.0%； -包装材料清单，包括包装油墨或物质的信息； -油墨制造商的证书； 5.每一批次出货只能有一个生产日期，不可多个生产日期混在同一批次出货；且邮包盒上必须统一加上日期码；外箱对于日期码没有硬性规定； 6.涉及到相关款式会有闪粉的或者微塑料的，请统一默认出无闪粉或者不含微塑料版本； 7.邮包盒及外箱封箱必须是工字型封箱方式； 8.5 Surprise or Mini Brands涉及包装是2个及2个以上的球入PVC桶包装时，单个球上若有UPC#或者EAN#，请用白色贴纸覆盖住； | Y83: Crystal Chen | Z83: 4.1 | AA83: =Z83*I83 -> 2066.4 | AC83: 95330-8.17 | AD83: 77673-S001-3L | AE83: 已入 | AG83: 已完成 | AI83: 504 | AJ83: =AI83-I83 -> 0 | AN83: =I83 -> 504 | AS83: =I83 -> 504 | AU83: =I83 -> 504 | AW83: =I83 -> 504
A84: 45775 | B84: Lobbes Speelgoed BV | C84: 荷兰 | D84: 4500164557 | E84: 47996 | F84: 4500164557-20 | G84: 77673-S001 | H84: 迷你冰箱12pcs/箱 | I84: 504 | J84: 0 | K84: 12 | L84: =I84/K84 -> 42 | M84: 45814 | N84: 45810 | P84: PASS | R84: 45775 | S84: 无 | T84: 45783 | X84: 日期码格式：ZURU INC(BVI) 标准格式 日期：按实际生产日期 Packaging Info: 77673: 客版EN FR DE IT NL 5L收缩膜（翻单4500155594），客版EN FR DE IT NL 5L收藏指南（翻单4500155594），MA 5L配件袋，MA 23L黑白说明书，WEEE带电池 走货欧洲30L通用黑白说明书 Remark: 1. STD配比 2.EAN条码 77673: 4894680042773 3.须符合欧洲微塑料法规 | Y84: Nicole Ye | Z84: 4.18 | AA84: =Z84*I84 -> 2106.72 | AC84: 95264-8.17 | AD84: 77673-S001-1 | AE84: 已入 | AG84: 已完成 | AI84: 504 | AJ84: =AI84-I84 -> 0 | AN84: =I84 -> 504 | AW84: =I84 -> 504 | BD84: =I84 -> 504 | BE84: =I84 -> 504
A85: 45784 | D85: ZMPO250363 | G85: 77785-S001-77673-INT-MTS | H85: 1pcs迷你冰箱+2pcs迷你球混装 | I85: 48 | J85: 0 | K85: 6 | L85: =I85/K85 -> 8 | M85: 45797 | N85: 45793 | R85: 45784 | S85: 无 | T85: 无 | X85: Remark:大货版本/大货标准箱装箱/箱唛请参照邮件附件;备注：收到样品订单后尽快安排 ，注意样板品质质量要求要高于大货品质要求 ，送货时必须要附带送货单(没有送货单和QC检验合格报告的仓库一律拒绝收货)，请知悉，谢谢！ | Y85: Angus | AC85: 95863-7.31 | AD85: 77785-S001-INT | AE85: 已入 | AG85: 已完成 | AI85: 48 | AJ85: =AI85-I85 -> 0 | AN85: =I85 -> 48 | AS85: =I85 -> 48 | AU85: =I85 -> 48 | AW85: =I85 -> 48 | BN85: =I85 -> 48
A86: 45775 | B86: WALMART INC. | C86: 美国 | D86: 4500162787 | E86: 0904512288EAS TVALE | F86: 4500162787-10 | G86: 77673TQ1-S001 | H86: 迷你冰箱4pcs/箱 | I86: 732 | J86: 0 | K86: 4 | L86: =I86/K86 -> 183 | M86: 45811 | N86: 45807 | P86: PASS | R86: 外箱印刷带条码的RFID箱唛：RFID紫色色带+WM Dept.图标+RFID图标+ITF-14条码，四面右下角印刷ZURU logo, ITFF条码只印刷在正唛一面，在加印的时候确 保 | S86: 无 | T86: RFID贴纸 | V86: RFID贴纸 | X86: 日期码格式：ZURU DGYYYYMMDD CHINA(日期避开周末和法定节假日即可） 日期：按实际生产日期 Packaging Info: 77673TQ1-S001 1.包装要求： MA 1L A版收缩膜+MA 5L 收藏指南+MA 说明书+MA playset 每pcs产品上要贴1张RFID贴纸，贴纸由ZURU提供，贴纸位置请严格按照我们签回的签板； Remark: 77673TQ1-S001 1.包装要求： MA 1L A版收缩膜+MA 5L 收藏指南+MA 说明书+MA playset 每pcs产品上要贴1张RFID贴纸，贴纸由ZURU提供，贴纸位置请严格按照我们签回的签板； 2. 外箱印刷带条码的RFID箱唛：RFID紫色色带+WM Dept.图标+RFID图标+ITF-14条码，四面右下角印刷ZURU logo, ITFF条码只印刷在正唛一面，在加印的时候确 保 条形码能扫描出来，外箱侧面任一角落加印："MADE IN CHINA" 字样； 3. 在产品上和包装上要有日期码、以及要有MADE IN CHINA和ZURU字样； 4. 产品如有扎带口要剪平，不能刮手。 5.此单以loose carton出货，4pcs/PDQ/CT | Y86: Maggie Xie | Z86: 3.06 | AA86: =Z86*I86 -> 2239.92 | AD86: 77673TQ1-S001 | AE86: 已入 | AG86: 已完成 | AI86: =728+4 -> 732 | AJ86: =AI86-I86 -> 0 | AN86: =I86 -> 732 | AR86: =I86 -> 732 | AU86: =I86 -> 732 | AW86: =I86 -> 732 | BH86: =I86/4 -> 183
A87: 45775 | B87: WALMART INC. | C87: 美国 | D87: 4500162787 | E87: 0904512338ELW OOD | F87: 4500162787-20 | G87: 77673TQ1-S001 | H87: 迷你冰箱4pcs/箱 | I87: 740 | J87: 0 | K87: 4 | L87: =I87/K87 -> 185 | M87: 45811 | N87: 45807 | P87: PASS | R87: 外箱印刷带条码的RFID箱唛：RFID紫色色带+WM Dept.图标+RFID图标+ITF-14条码，四面右下角印刷ZURU logo, ITFF条码只印刷在正唛一面，在加印的时候确 保 | S87: 无 | T87: RFID贴纸 | V87: RFID贴纸 | X87: 日期码格式：ZURU DGYYYYMMDD CHINA(日期避开周末和法定节假日即可） 日期：按实际生产日期 Packaging Info: 77673TQ1-S001 1.包装要求： MA 1L A版收缩膜+MA 5L 收藏指南+MA 说明书+MA playset 每pcs产品上要贴1张RFID贴纸，贴纸由ZURU提供，贴纸位置请严格按照我们签回的签板； Remark: 77673TQ1-S001 1.包装要求： MA 1L A版收缩膜+MA 5L 收藏指南+MA 说明书+MA playset 每pcs产品上要贴1张RFID贴纸，贴纸由ZURU提供，贴纸位置请严格按照我们签回的签板； 2. 外箱印刷带条码的RFID箱唛：RFID紫色色带+WM Dept.图标+RFID图标+ITF-14条码，四面右下角印刷ZURU logo, ITFF条码只印刷在正唛一面，在加印的时候确 保 条形码能扫描出来，外箱侧面任一角落加印："MADE IN CHINA" 字样； 3. 在产品上和包装上要有日期码、以及要有MADE IN CHINA和ZURU字样； 4. 产品如有扎带口要剪平，不能刮手。 5.此单以loose carton出货，4pcs/PDQ/CT | Y87: Maggie Xie | Z87: 3.06 | AA87: =Z87*I87 -> 2264.4 | AD87: 77673TQ1-S001 | AE87: 已入 | AG87: 已完成 | AI87: 740 | AJ87: =AI87-I87 -> 0 | AN87: =I87 -> 740 | AR87: =I87 -> 740 | AU87: =I87 -> 740 | AW87: =I87 -> 740 | BH87: =I87/4 -> 185
A88: 45775 | B88: WALMART INC. | C88: 美国 | D88: 4500162787 | E88: 0904512314STA TESBORO | F88: 4500162787-30 | G88: 77673TQ1-S001 | H88: 迷你冰箱4pcs/箱 | I88: 656 | J88: 0 | K88: 4 | L88: =I88/K88 -> 164 | M88: 45811 | N88: 45807 | P88: PASS | R88: 外箱印刷带条码的RFID箱唛：RFID紫色色带+WM Dept.图标+RFID图标+ITF-14条码，四面右下角印刷ZURU logo, ITFF条码只印刷在正唛一面，在加印的时候确 保 | S88: 无 | T88: RFID贴纸 | V88: RFID贴纸 | X88: 日期码格式：ZURU DGYYYYMMDD CHINA(日期避开周末和法定节假日即可） 日期：按实际生产日期 Packaging Info: 77673TQ1-S001 1.包装要求： MA 1L A版收缩膜+MA 5L 收藏指南+MA 说明书+MA playset 每pcs产品上要贴1张RFID贴纸，贴纸由ZURU提供，贴纸位置请严格按照我们签回的签板； Remark: 77673TQ1-S001 1.包装要求： MA 1L A版收缩膜+MA 5L 收藏指南+MA 说明书+MA playset 每pcs产品上要贴1张RFID贴纸，贴纸由ZURU提供，贴纸位置请严格按照我们签回的签板； 2. 外箱印刷带条码的RFID箱唛：RFID紫色色带+WM Dept.图标+RFID图标+ITF-14条码，四面右下角印刷ZURU logo, ITFF条码只印刷在正唛一面，在加印的时候确 保 条形码能扫描出来，外箱侧面任一角落加印："MADE IN CHINA" 字样； 3. 在产品上和包装上要有日期码、以及要有MADE IN CHINA和ZURU字样； 4. 产品如有扎带口要剪平，不能刮手。 5.此单以loose carton出货，4pcs/PDQ/CT | Y88: Maggie Xie | Z88: 3.06 | AA88: =Z88*I88 -> 2007.36 | AD88: 77673TQ1-S001 | AE88: 已入 | AG88: 已完成 | AI88: =652+4 -> 656 | AJ88: =AI88-I88 -> 0 | AN88: =I88 -> 656 | AR88: =I88 -> 656 | AU88: =I88 -> 656 | AW88: =I88 -> 656 | BH88: =I88/4 -> 164
A89: 45775 | B89: WALMART INC. | C89: 美国 | D89: 4500162787 | E89: 0904512301SUF FOLK | F89: 4500162787-40 | G89: 77673TQ1-S001 | H89: 迷你冰箱4pcs/箱 | I89: 848 | J89: 0 | K89: 4 | L89: =I89/K89 -> 212 | M89: 45811 | N89: 45807 | P89: PASS | R89: 外箱印刷带条码的RFID箱唛：RFID紫色色带+WM Dept.图标+RFID图标+ITF-14条码，四面右下角印刷ZURU logo, ITFF条码只印刷在正唛一面，在加印的时候确 保 | S89: 无 | T89: RFID贴纸 | V89: RFID贴纸 | X89: 日期码格式：ZURU DGYYYYMMDD CHINA(日期避开周末和法定节假日即可） 日期：按实际生产日期 Packaging Info: 77673TQ1-S001 1.包装要求： MA 1L A版收缩膜+MA 5L 收藏指南+MA 说明书+MA playset 每pcs产品上要贴1张RFID贴纸，贴纸由ZURU提供，贴纸位置请严格按照我们签回的签板； Remark: 77673TQ1-S001 1.包装要求： MA 1L A版收缩膜+MA 5L 收藏指南+MA 说明书+MA playset 每pcs产品上要贴1张RFID贴纸，贴纸由ZURU提供，贴纸位置请严格按照我们签回的签板； 2. 外箱印刷带条码的RFID箱唛：RFID紫色色带+WM Dept.图标+RFID图标+ITF-14条码，四面右下角印刷ZURU logo, ITFF条码只印刷在正唛一面，在加印的时候确 保 条形码能扫描出来，外箱侧面任一角落加印："MADE IN CHINA" 字样； 3. 在产品上和包装上要有日期码、以及要有MADE IN CHINA和ZURU字样； 4. 产品如有扎带口要剪平，不能刮手。 5.此单以loose carton出货，4pcs/PDQ/CT | Y89: Maggie Xie | Z89: 3.06 | AA89: =Z89*I89 -> 2594.88 | AD89: 77673TQ1-S001 | AE89: 已入 | AG89: 已完成 | AI89: =836+12 -> 848 | AJ89: =AI89-I89 -> 0 | AN89: =I89 -> 848 | AR89: =I89 -> 848 | AU89: =I89 -> 848 | AW89: =I89 -> 848 | BH89: =I89/4 -> 212
A90: 45775 | B90: WALMART INC. | C90: 美国 | D90: 4500162787 | E90: 0904512358RID GEVILLE SC | F90: 4500162787-50 | G90: 77673TQ1-S001 | H90: 迷你冰箱4pcs/箱 | I90: 796 | J90: 0 | K90: 4 | L90: =I90/K90 -> 199 | M90: 45811 | N90: 45807 | P90: PASS | R90: 外箱印刷带条码的RFID箱唛：RFID紫色色带+WM Dept.图标+RFID图标+ITF-14条码，四面右下角印刷ZURU logo, ITFF条码只印刷在正唛一面，在加印的时候确 保 | S90: 无 | T90: RFID贴纸 | V90: RFID贴纸 | X90: 日期码格式：ZURU DGYYYYMMDD CHINA(日期避开周末和法定节假日即可） 日期：按实际生产日期 Packaging Info: 77673TQ1-S001 1.包装要求： MA 1L A版收缩膜+MA 5L 收藏指南+MA 说明书+MA playset 每pcs产品上要贴1张RFID贴纸，贴纸由ZURU提供，贴纸位置请严格按照我们签回的签板； Remark: 77673TQ1-S001 1.包装要求： MA 1L A版收缩膜+MA 5L 收藏指南+MA 说明书+MA playset 每pcs产品上要贴1张RFID贴纸，贴纸由ZURU提供，贴纸位置请严格按照我们签回的签板； 2. 外箱印刷带条码的RFID箱唛：RFID紫色色带+WM Dept.图标+RFID图标+ITF-14条码，四面右下角印刷ZURU logo, ITFF条码只印刷在正唛一面，在加印的时候确 保 条形码能扫描出来，外箱侧面任一角落加印："MADE IN CHINA" 字样； 3. 在产品上和包装上要有日期码、以及要有MADE IN CHINA和ZURU字样； 4. 产品如有扎带口要剪平，不能刮手。 5.此单以loose carton出货，4pcs/PDQ/CT | Y90: Maggie Xie | Z90: 3.06 | AA90: =Z90*I90 -> 2435.76 | AD90: 77673TQ1-S001 | AE90: 已入 | AG90: 已完成 | AI90: =792+4 -> 796 | AJ90: =AI90-I90 -> 0 | AN90: =I90 -> 796 | AR90: =I90 -> 796 | AU90: =I90 -> 796 | AW90: =I90 -> 796 | BH90: =I90/4 -> 199
A91: 45771 | B91: AB Gee of Ripley Ltd. | C91: 英国 | D91: 4500164759 | E91: 777 4APR25 | F91: 4500164759-120 | G91: 77673TQ1-S004 | H91: 迷你冰箱16pcs/箱 | I91: 512 | J91: 4 | K91: 16 | L91: =I91/K91 -> 32 | M91: 45812 | N91: =M91-4 -> 45808 | P91: PASS | R91: 45784 | S91: 无 | T91: 翻单 | X91: 日期码格式：ZURU INC(BVI) 标准格式 日期：按实际生产日期 Packaging Info: 12. 77673TQ1-S004：MA 最新UPC包装+WEEE带电池走货欧洲30语通用黑白说明书, UPC# 193052079404，请先检查条码是否正确再安排做货，如有问题请告知 Remark: 1.产品及包装需要印UKCA图标，包装需要有ZURU UK LTD/ZURU France地址信息，QC同事请核查，如有问题与跟单确认。 2. 需要符合欧洲标准不能含有闪粉和微塑料，否则不合法规会有客诉产生 | Y91: Yoga Huang | Z91: 5 | AA91: =Z91*I91 -> 2560 | AC91: 95251-8.17 | AD91: 77673TQ1-S004 | AE91: 已入 | AG91: 已完成 | AI91: 512 | AJ91: =AI91-I91 -> 0 | AL91: OK | AN91: =I91 -> 512 | AR91: =I91 -> 512 | AU91: =I91 -> 512 | AW91: =I91 -> 512 | BH91: =I91/4 -> 128
A92: 45750 | B92: ESAL ENTERPRISES FZC | C92: 沙特阿拉伯 | D92: 4500162474 | E92: KSA | F92: 4500162474-100 | G92: 77673PLB-S001 | H92: 迷你冰箱 | I92: 480 | J92: 0 | K92: 16 | L92: =I92/K92 -> 30 | M92: 45792 | N92: 45810 | P92: PASS | R92: 45762 | S92: 无 | T92: 45776 | X92: 日期码格式：ZURU INC(BVI) 标准格式 日期：按实际生产日期 Packaging Info: 9548：1L MA包装（含G Mark)+进口商贴纸翻4500128286(含QR code, 阿拉伯警语); 贴纸上的QR code需微信可扫，扫描结果为64431； MA说明书 9561:MA+进口商贴纸+说明书（加贴纸） 9543GQ1：MA+进口商贴纸；PDQ+进口商贴纸 71152：MA+进口商贴纸+说明书（加贴纸） 77673TQ1：MA PDQ+彩色贴纸+进口商贴纸；MA收藏指南+彩色贴纸；收缩膜+进口商贴纸；MA说明书+一张客制黑白说明书纸 1. 9561PLB：9561-S001 4pcs/CTN (Carton Size: 39.2x39.2x34.2CM); 6*5H=30CTN=30*4pcs=120pcs/pallet; 9561（共120箱）:每层6箱，装5层。装4个pallet。 2. 9548PLB：9548-S001 4pcs/CTN (Carton Size: 57.7x38.5x32.2CM); 5*6H=30CTN=30*4pcs=120pcs/pallet；9548（共36箱）:每层5箱，装6层。装1个pallet 装3 0箱，剩36-30=6箱。 3. MPLB11：9548-S001 4pcs/CTN (Carton Size: 57.7x38.5x32.2CM); 9543GQ1-S001 22PCS/2PDQ/CTN (Carton Size: 48.4x36.6x27.2CM); 6*4H=24-2=22CTN+6CTN (9548)，total 508pcs/pallet；9548-S001 4*6CTN=24pcs, 9543GQ1-S001 22*22CTN=484pcs; 9543GQ1（22箱）:每层6箱，装4层。装1个pallet，最上面1层少装2箱，其余空间装6箱9548-S001。 4. 71152PLB：71152-S001 6PCS/CTN (Carton Size: 31.7x29.2x43.3CM); 8*5H=40CTN=40*6pcs=240pcs/pallet； 71152（80箱）：每层8箱，装5层。装2个pallet。 5. 77673PLB：77673TQ1-S002 16PCS/4PDQ/CTN(SIZE:41.7*26.8*40.1CM)8*4H-2=30CTN=480PCS； 77673TQ1（30箱）：每层8箱，装4层。装1个pallet，最上面一层少放2箱。 6. 77803PLB：77803GQ2-S001-PRODCC-INT 50PCS/2PDQ/CTN(SIZE:42.6*33*41CM)8*4H-3=29CTN=1450PCS； 77803GQ2-S001（29箱）：每层8箱，装4层，装1个pallet ，最上面1层少装3箱。 7. 77803PLD：77803SK1-S002-PRODCC-INT 30PCS/SIDEKICK/CTN(SIZE:14.5*33.5*112.5CM)22*1H+6*2H+1=35CTN=1050PCS； 77803SK1-S002（35箱）：总高度（1290+670+145=2105mm）装1个pallet，竖放22箱+横放12箱，最上层再平放1箱 Remark: 9548:1 assorment,3pcs AAA batteries(not included) | Y92: Lena Huang | Z92: 4.39 | AA92: =Z92*I92 -> 2107.2 | AC92: 96584-2-9.30 | AD92: 77673TQ1-S002 | AE92: 已入 | AG92: 已完成 | AI92: 480 | AJ92: =AI92-I92 -> 0 | AL92: 欠 | AN92: =I92 -> 480 | AR92: =I92 -> 480 | AU92: =I92 -> 480 | AW92: =I92 -> 480 | BH92: =I92/4 -> 120
A93: 45763 | B93: CCD SELL OUT SERVICE SRL | C93: 意大利 | D93: 4500163782 | F93: 4500163782-30 | G93: MEC305-S001-INT | H93: 18pc冰箱+90pc球混装展示架 | I93: 30 | J93: 0 | K93: 1 | L93: =I93/K93 -> 30 | M93: 45814 | N93: 45810 | P93: PASS | Q93: 6/9 截SI | R93: 45786 | S93: 无 | T93: 45777 | X93: 日期码格式：ZURU INC(BVI) 标准格式 日期：按实际生产日期 Packaging Info: MEC305：MA展示架 子件77673:最新MA3LEAN收缩膜+最新MA5L收藏指南+最新MA23L说明书+最新MA纸袋+意大利环保标通用地址贴(含意大利警语) Remark: 1. 此单出意大利，需要满足EU标准，通过ZURU验货即可； 2. 产品均符合EU微塑料法规要求：不能含有微塑料/闪粉 3, SMASHERS 或含Slime产品，所有化合物使用无硼版本出意大利。 | Y93: Lena Li | Z93: 0 | AA93: =Z93*L93 -> 0 | AC93: 95252-8.17 | AD93: MEC305-S001-INT-77673 | AE93: 已入 | AG93: 已完成 | AI93: 540 | AJ93: 0 | AW93: =I93 -> 30
A94: 45763 | B94: CCD SELL OUT SERVICE SRL | C94: 意大利 | D94: 4500163782 | F94: 4500163782-30 | G94: 77673 | H94: 迷你冰箱 | I94: 540 | J94: 0 | K94: 18 | L94: =I94/K94 -> 30 | M94: 45814 | N94: 45810 | P94: PASS | Q94: 6/9 截SI | R94: 45786 | S94: 无 | T94: 45777 | X94: 日期码格式：ZURU INC(BVI) 标准格式 日期：按实际生产日期 Packaging Info: MEC305：MA展示架 子件77673:最新MA3LEAN收缩膜+最新MA5L收藏指南+最新MA23L说明书+最新MA纸袋+意大利环保标通用地址贴(含意大利警语) Remark: 1. 此单出意大利，需要满足EU标准，通过ZURU验货即可； 2. 产品均符合EU微塑料法规要求：不能含有微塑料/闪粉 3, SMASHERS 或含Slime产品，所有化合物使用无硼版本出意大利。 | Y94: Lena Li | Z94: 171.3 | AA94: =Z94*L94 -> 5139 | AC94: 95252-8.17 | AD94: MEC305-S001-INT-77673 | AE94: 已入 | AG94: 已完成 | AI94: 0 | AJ94: 0 | AN94: =I94 -> 540 | AS94: =I94 -> 540 | AU94: =I94 -> 540 | AW94: =I94 -> 540 | BO94: =I94/18 -> 30
A95: 45755 | B95: ASIA GOAL LIMITED | C95: 香港 | D95: 4500161438 | E95: AG240428-HK | F95: 4500161438-10 | G95: 77785-S001-77673-INT | H95: 1pcs迷你冰箱+2pcs迷你球混装 | I95: 600 | J95: 0 | K95: 6 | L95: =I95/K95 -> 100 | M95: 45805 | N95: 45814 | P95: PASS | Q95: 6/8 出货 | R95: 45755 | S95: 无 | T95: 45772 | V95: 1张客供警语贴+1张客供电池警语贴纸+1张客供中文警告说明书 | X95: 日期码格式：ZURU INC(BVI) 标准格式 日期：按实际生产日期 Packaging Info: 77785：客版MA 3L UPC 彩盒+客供警语贴纸（具体贴纸位置参考HK客供贴纸位置图） 77785 =2pcs 77711+1pcs 77673 77785：1张客供警语贴+1张客供电池警语贴纸 （77785里的77673：MA 1L 收缩膜，MA 警语说明书+MA 收藏指南+1张客供警语贴+1张客供电池警语贴纸+1张客供中文警告说明书） （具体贴纸位置参考HK客供贴纸位置图） Remark: 此单出HK | Y95: Doris Shou | Z95: 8.9 | AA95: =Z95*I95 -> 5340 | AC95: 95358-8.17 | AD95: 77785-S001-INT | AE95: 已入 | AG95: 已完成 | AI95: =I95 -> 600 | AJ95: =AI95-I95 -> 0 | AN95: =I95 -> 600 | AR95: =I95 -> 600 | AU95: =I95 -> 600 | AW95: =I95 -> 600 | BN95: =I95 -> 600
A96: 45771 | B96: DISTRIBUIDORA JUGUETRON S.A. DE C.V | C96: 墨西哥 | D96: 4500164861 | E96: 50212500921 | F96: 4500164861-110 | G96: 77673-S001 | H96: 迷你冰箱12pcs/箱 | I96: 1800 | J96: 0 | K96: 12 | L96: =I96/K96 -> 150 | M96: 45819 | N96: 45815 | P96: PASS | Q96: 返工，6/10 出货 | R96: 45777 | S96: 无 | T96: 45800 | V96: 产品/包装/说明书都需要贴一张进口商贴纸 | X96: 日期码格式：ZURU INC(BVI) 标准格式 日期：按实际生产日期 Packaging Info: 77673:MA 3L EAN包装+UPC贴纸+MA 多语说明书+保证书+进口商贴纸+外箱贴纸，产品/包装/说明书都需要贴一张进口商贴纸 Remark: 此单有第三方监柜，需要每款多备1套完整物料 | Y96: Ava Liang | Z96: 4.1456 | AA96: =Z96*I96 -> 7462.08 | AC96: 95261-8.17 | AD96: 77673-S001-3L | AE96: 已入 | AG96: 已完成 | AI96: 1800 | AJ96: =AI96-I96 -> 0 | AL96: 欠 | AN96: =I96 -> 1800 | AS96: =I96 -> 1800 | AU96: =I96 -> 1800 | AW96: =I96 -> 1800
A97: 45765 | B97: MAGGIO 3 SRL | C97: 意大利 | D97: 4500163950 | F97: 4500163950-30 | G97: MEC305-S001-INT | H97: 18pc冰箱+90pc球混装展示架 | I97: 80 | J97: 0 | K97: 1 | L97: =I97/K97 -> 80 | M97: 45810 | N97: 45806 | P97: PASS | R97: 45777 | S97: 无 | T97: 45789 | X97: 日期码格式：ZURU INC(BVI) 标准格式 日期：按实际生产日期 Packaging Info: MEC305:MA 展示架（如有MA3L则不用MA1L）+1张展示架ITF14条码贴纸 Remark: 1.此单出意大利，需满足EU测试标准要求<(>&<)> 微塑料需符合法规，如果有slime等化学品需要不含硼 2.需保证按期完货，延期罚款。 3.贴纸切勿盖住意大利警告语文字(QC 务必检查），特别是产品包装比较小的,如果会挡住产品上的警示语信息，在做大货前工厂需要提前告知跟单位置图是否OK， 需再次确认才能安排生产大货。 4. 标准配比 5. 需要ZURU OQC 验货， 需提供验货图片给到客户放货。 | Y97: Mary Zhong | Z97: 0 | AA97: =Z97*L97 -> 0 | AC97: 95665 | AD97: MEC305-S001-INT-77673 | AE97: 已入 | AG97: 已完成 | AI97: 0 | AJ97: =AI97-I97 -> -80 | AW97: =I97 -> 80
A98: 45765 | B98: MAGGIO 3 SRL | C98: 意大利 | D98: 4500163950 | F98: 4500163950-30 | G98: 77673 | H98: 迷你冰箱 | I98: 1440 | J98: 0 | K98: 18 | L98: =I98/K98 -> 80 | M98: 45810 | N98: 45806 | P98: PASS | R98: 45777 | S98: 无 | T98: 45789 | X98: 日期码格式：ZURU INC(BVI) 标准格式 日期：按实际生产日期 Packaging Info: MEC305:MA 展示架（如有MA3L则不用MA1L）+1张展示架ITF14条码贴纸 Remark: 1.此单出意大利，需满足EU测试标准要求<(>&<)> 微塑料需符合法规，如果有slime等化学品需要不含硼 2.需保证按期完货，延期罚款。 3.贴纸切勿盖住意大利警告语文字(QC 务必检查），特别是产品包装比较小的,如果会挡住产品上的警示语信息，在做大货前工厂需要提前告知跟单位置图是否OK， 需再次确认才能安排生产大货。 4. 标准配比 5. 需要ZURU OQC 验货， 需提供验货图片给到客户放货。 | Y98: Mary Zhong | Z98: 172.3098 | AA98: =Z98*L98 -> 13784.784 | AC98: 95665-7.17 | AD98: MEC305-S001-INT-77673 | AE98: 已入 | AG98: 已完成 | AI98: 1440 | AJ98: =AI98-I98 -> 0 | AN98: =I98 -> 1440 | AS98: =I98 -> 1440 | AU98: =I98 -> 1440 | AW98: =I98 -> 1440
A99: 45769 | B99: Smyths Toys HQ UC IE | C99: 爱尔兰 | D99: 4500164476 | E99: 4400474094 | F99: 4500164476-10 | G99: 77673TQ1-S003 | H99: 迷你冰箱 | I99: 1000 | J99: 0 | K99: 8 | L99: =I99/K99 -> 125 | M99: 45811 | N99: 45807 | P99: PASS | R99: 45769 | S99: 无 | T99: （所有资料翻#4500155594） | X99: 日期码格式：ZURU INC(BVI) 标准格式 日期：按实际生产日期 Packaging Info: 77673TQ1：最新MA PDQ(优先3L )+客版收缩膜(英法德callout/英法德意荷警语/法国环保logo)+23L说明书+客版收藏指南(英法德意荷)（所有资料翻#4500155594）+ WEEE电池通用30L说明书（带电池） Remark: 1) 包装日期码按ZURU格式即可，请确保不迟于外箱日期码，可等于或者早于外箱日期码，必须为法定工作日，印刷前请先检查外箱日期码。 2) 订单出英国，请注意检查产品及包装应带UKCA图标（14+产品除外），包装显示ZURU UK LTD/ZURU France地址信息，QC部门请查核，如有问题与跟单确认 3) 需要完全符合欧洲标准(符合微塑料法规)，否则不合法规会有客诉产生 | Y99: Yoga Huang | Z99: 5 | AA99: =Z99*I99 -> 5000 | AC99: 95301-8.17 | AD99: 77673TQ1-S003 | AE99: 已入 | AG99: 已完成 | AI99: =976+24 -> 1000 | AJ99: =AI99-I99 -> 0 | AL99: OK | AN99: =I99 -> 1000 | AW99: =I99 -> 1000 | BD99: =I99 -> 1000 | BE99: =I99 -> 1000 | BI99: =I99/4 -> 250
A100: 45714 | B100: Amazon ES | C100: 西班牙 | D100: 4500158623 | E100: Amazon ES: 24T2QNEG | F100: 4500158623-10 | G100: 77673-S001 | H100: 迷你冰箱12pcs/箱 | I100: 492 | J100: 0 | K100: 12 | L100: =I100/K100 -> 41 | M100: 45813 | N100: 45810 | P100: PASS | R100: 空白外箱（加印带Zuru字样的最新logo，除了邮包盒直接做外箱的产品） + SSCC LABEL一张, 无箱唛，MADE IN CHINA 外箱只印一正一侧。箱唛资料按照给定的 标准去做即可，无需发回我方再行审批(新标准将另行通知)。 | S100: 有 | T100: 2张贴纸(1张UPC#，参考翻单PO#4500158582；1张可折叠警语贴 含德意警告语+IT环保标，参考翻单PO#4500157858) | X100: 日期码格式：ZURU INC(BVI) 标准格式 日期：按实际生产日期 Packaging Info: Amazon ES(77673, 77731)/IT(77673, 77731) 1. 77673：12pcs/ctn; MA 3L(3L warning EAN#)A收缩膜+MA 23L warning说明书+MA 5L A收藏指南+2张贴纸(1张UPC#，参考翻单PO#4500158582；1张可折叠警语贴 含德意警告语+IT环保标，参考翻单PO#4500157858); 3. 最迟验货不得晚于2025/6/6; Remark: 1.空白外箱（加印带Zuru字样的最新logo，除了邮包盒直接做外箱的产品） + SSCC LABEL一张, 无箱唛，MADE IN CHINA 外箱只印一正一侧。箱唛资料按照给定的 标准去做即可，无需发回我方再行审批(新标准将另行通知)。 (SSCC LABEL竖贴在外箱正面的正中间，贴一面即可,贴纸离外箱边距必须至少3.2CM。如竖贴无法满足要求，则横贴。如横贴也无法满足要求，则竖贴，遮到ZURU lo go无影响), SSCC贴纸由工厂直接跟勤得采购或者工厂自行采购，每一张SSCC Label都是唯一且有不同流水及条码，且需要检查条码是否能正常扫描，另外，此贴纸 印刷不可出现模糊，溢出及粘胶不牢易脱落等现象，如工厂不按此要求导致贴纸有任何问题产生的罚款将由工厂承担一切责任 。 2.出往UK的产品+包装务必打上UKCA logo ，否则客人会退货且当地会有罚款。 3.订单必须经过ZURU QC验货并且通过后方可出货。 4.法国订单要求包装不使用矿物油，请按要求提供以下其中一份文件再出货 ，产品出到法国被相关部门抽检出现包装不符合此要求的，供应商需要为此承担责任， 故此请严格把关。 -油墨物质""由1 ~ 7个芳香环组成的MOAH""的包装检测报告，要求限值≤1.0%； -包装材料清单，包括包装油墨或物质的信息； -油墨制造商的证书； 5.每一批次出货只能有一个生产日期，不可多个生产日期混在同一批次出货；且邮包盒上必须统一加上日期码；外箱对于日期码没有硬性规定； 6.涉及到相关款式会有闪粉的或者微塑料的，请统一默认出无闪粉或者不含微塑料版本； 7.邮包盒及外箱封箱必须是工字型封箱方式； 8.5 Surprise or Mini Brands涉及包装是2个及2个以上的球入PVC桶包装时，单个球上若有UPC#或者EAN#，请用白色贴纸覆盖住； | Y100: Mandy Hu | Z100: 4.1 | AA100: =Z100*I100 -> 2017.2 | AC100: 95341-8.17 | AD100: 77673-S001-3L | AE100: 已入 | AG100: 已完成 | AI100: =480+12 -> 492 | AJ100: =AI100-I100 -> 0 | AN100: =I100 -> 492 | AS100: =I100 -> 492 | AU100: =I100 -> 492 | AW100: =I100 -> 492
...

Sheet 77711
A1: 香港接单日期 | B1: 第三方客户名称 | C1: 走货国家 | D1: ZURU PO NO# | E1: 第三方客户 PO NO# | F1: SKU | G1: ITEM# | H1: 货品名称 | I1: PO数量(只) | J1: 内箱装箱数量(只) | K1: 外箱装箱数量(只) | L1: 总箱数 | M1: 计划出货期 | N1: 计划验货期 | O1: 第三方客户公证行验货 | P1: 验货结果 | Q1: S/O(截仓期) | R1: 箱唛 (收到日期) | S1: 外箱贴纸 | T1: 贴纸资料 (收到日期及订购日期) | U1: 额外说明书/保证书 | V1: 其他物料 | W1: 样板 | X1: 备注 | Y1: ZURU跟单组员 | Z1: 单价USD | AA1: 金额USD | AB1: 是否收到客版包装资料 | AC1: 发票号 | AD1: 系统货号 | AE1: 是否入系统 | AF1: 下单情况 | AG1: 生产情况 | AH1: 采购单 | AI1: 已回数量 | AJ1: 欠数 | AK1: HN回复完成时间 | AL1: 贴纸 | AM1: 纸箱 | AN1: 77711 NA 球数 | AO1: 77711 INT 球数 | AP1: MA 1L A收缩膜 | AQ1: MA 2L 收缩膜 无条码 | AR1: MA 3L 收缩膜 无条码 | AS1: MA 2L 收缩膜 | AT1: MA 3L 收缩膜 | AU1: MA 2L 收藏指南（NA） | AV1: MA 5L 收藏指南（INT） | AW1: 中文单专用客版收缩膜 | AX1: 中文吊牌/收藏指南 | AY1: 77803收缩膜 | AZ1: 77803客版收藏指南 | BA1: 中文黑白说明书 | BB1: UV胶黑白说明书 | BC1: 客版收缩膜 | BD1: BJ'S WHOLESALE CLUB, INC.客版收缩膜及收藏指南 | BE1: Smyths 客版收缩膜 | BF1: COSTCO 客版收缩膜 | BG1: WM US客版1L 无条码收缩膜 | BH1: COSTCO 客版收藏指南 | BI1: COSTCO 客版彩盒 | BJ1: COSTCO 客版PDQ | BK1: GQ1 1L 13pcs | BL1: GQ1 2L 13PCS | BM1: GQ1 3L 13PCS | BN1: GQ2 1L 25pcs | BO1: GQ2 2L 25pcs | BP1: GQ2 3L 25pcs | BQ1: 1L 16PCS GQ4 | BR1: 3L 16PCS GQ4 | BS1: 客版 8PCS GQ5 | BT1: 客版 6PCS GQ6 | BU1: 1L 24pcs GQ8 | BV1: 77782客版收缩膜 | BW1: 77782客版收藏指南 | BX1: 77782 客版PDQ | BY1: 77785 1L 彩盒 | BZ1: 77785 3L INT彩盒 | CA1: 77785 3L NA彩盒 | CB1: 77785 彩盒4500212396-新客版NA | CC1: 77785 彩盒4500191865-C版本 | CD1: 77785 彩盒4500194447-D版本 | CE1: 77785 彩盒4500194198-E版本客版SAM 's | CF1: 77758彩盒 | CG1: 77758托盘 | CH1: 77785展示架 | CI1: MEC356 | CJ1: MEC305 | CK1: 1L SK-S002 含底座 60pcs | CL1: 2L SK-S002 含底座 60pcs | CM1: 3L SK-S002 含底座 60pcs | CN1: 2L SK-S002 无底座 60pcs | CO1: 2L SK1-S001 30pcs | CP1: 3L SK1-S002 30pcs | CQ1: 客版 77803SK1-S002 30pcs | CR1: 77731圆筒 | CS1: 77731彩纸 | CT1: 77731贴纸 | CU1: GQ2/4展示小产品 | CV1: SK展示小产品 | CW1: MEC305展示小产品
A2: 45651 | C2: 库有 | D2: ZMPO24991 | G2: 77711-S001-NA | H2: 冰箱迷你球24pcs/箱 | I2: 500 | J2: 0 | K2: 24 | L2: =I2/K2 -> 20.833333 | R2: 周转箱 | S2: 无 | T2: 无 | X2: Remark：跟PP单一起安排 备注： 此板单为TVC 拍摄样板单，PM 有提供让工厂备料，请与PP一起交货，谢谢 | Y2: Angus | AD2: N/A | AE2: N/A | AG2: 已完成 | AJ2: =AI2-I2 -> -500 | AN2: =I2 -> 500 | CU2: =BQ2+BP2+BO2+BN2+BX2+BR2 -> 0 | CV2: =CK2+CL2+CM2+CN2+CO2+CQ2+CP2 -> 0 | CW2: =CI2+CJ2 -> 0
A3: 45651 | C3: 库有 | D3: ZMPO24991 | G3: 77711-S001-NA | H3: 冰箱迷你球24pcs/箱 | I3: 25套散件 | R3: 周转箱 | S3: 无 | T3: 无 | X3: Remark：跟PP单一起安排/只需要齐套散件/麻烦用胶袋分装好一套为一袋 备注： 此板单为TVC 拍摄样板单，PM 有提供让工厂备料，请与PP一起交货，谢谢 | Y3: Angus | AD3: N/A | AE3: N/A | AG3: 已完成 | CU3: =BQ3+BP3+BO3+BN3+BX3+BR3 -> 0 | CV3: =CK3+CL3+CM3+CN3+CO3+CQ3+CP3 -> 0 | CW3: =CI3+CJ3 -> 0
A4: 45651 | C4: 库有 | D4: ZMPO24991 | G4: 77711-S001-INT | H4: 冰箱迷你球pcs24/箱 | I4: 200 | J4: 0 | K4: 24 | L4: =I4/K4 -> 8.3333333 | R4: 周转箱 | S4: 无 | T4: 无 | X4: Remark：跟PP单一起安排 备注： 此板单为TVC 拍摄样板单，PM 有提供让工厂备料，请与PP一起交货，谢谢 | Y4: Angus | AD4: N/A | AE4: N/A | AG4: 已完成 | AJ4: =AI4-I4 -> -200 | AO4: =I4 -> 200 | CU4: =BQ4+BP4+BO4+BN4+BX4+BR4 -> 0 | CV4: =CK4+CL4+CM4+CN4+CO4+CQ4+CP4 -> 0 | CW4: =CI4+CJ4 -> 0
A5: 45651 | C5: 库有 | D5: ZMPO24991 | G5: 77711-S001-INT | H5: 冰箱迷你球pcs24/箱 | I5: 25套散件 | J5: 0 | K5: 24 | R5: 周转箱 | S5: 无 | T5: 无 | X5: Remark：跟PP单一起安排/只需要齐套散件/麻烦用胶袋分装好一套为一袋 备注： 此板单为TVC 拍摄样板单，PM 有提供让工厂备料，请与PP一起交货，谢谢 | Y5: Angus | AD5: N/A | AE5: N/A | AG5: 已完成 | CU5: =BQ5+BP5+BO5+BN5+BX5+BR5 -> 0 | CV5: =CK5+CL5+CM5+CN5+CO5+CQ5+CP5 -> 0 | CW5: =CI5+CJ5 -> 0
A6: 45652 | C6: 库有 | G6: 77711-S001-NA | H6: 冰箱迷你球24pcs/箱 | I6: 504 | J6: 0 | K6: 24 | L6: =I6/K6 -> 21 | R6: 周转箱 | S6: 无 | T6: 无 | X6: Remark：跟PP单一起安排/大货标准箱装箱/箱唛参照邮件附件 备注： 请跟PP订单一起安排，谢谢 | Y6: Angus | AD6: N/A | AE6: N/A | AG6: 已完成 | AN6: =I6 -> 504 | CU6: =BQ6+BP6+BO6+BN6+BX6+BR6 -> 0 | CV6: =CK6+CL6+CM6+CN6+CO6+CQ6+CP6 -> 0 | CW6: =CI6+CJ6 -> 0
A7: 45652 | C7: 库有 | D7: ZMPO24995 | G7: 77711-S001-NA | H7: 冰箱迷你球24pcs/箱 | I7: 5套散件 | R7: 周转箱 | S7: 无 | T7: 无 | X7: Remark：跟PP单一起安排/只需要齐套散件/麻烦用胶袋分装好一套为一袋 备注： 请跟PP订单一起安排，谢谢 | Y7: Angus | AD7: N/A | AE7: N/A | AG7: 已完成 | CU7: =BQ7+BP7+BO7+BN7+BX7+BR7 -> 0 | CV7: =CK7+CL7+CM7+CN7+CO7+CQ7+CP7 -> 0 | CW7: =CI7+CJ7 -> 0
A8: 45652 | C8: 库有 | D8: ZMPO24995 | G8: 77711GQ1-S001-NA | H8: 冰箱迷你球 | I8: 20个空PDQ | R8: 周转箱 | S8: 无 | T8: 无 | X8: Remark：跟PP单一起安排/只需要空PDQ/请配齐PDQ上应有的物料如展示公仔/吸塑等 备注： 请跟PP订单一起安排，谢谢 | Y8: Angus | AD8: N/A | AE8: N/A | AG8: 已完成 | BL8: 20 | CU8: =BQ8+BP8+BO8+BN8+BX8+BR8 -> 0 | CV8: =CK8+CL8+CM8+CN8+CO8+CQ8+CP8 -> 0 | CW8: =CI8+CJ8 -> 0
A9: 45652 | C9: 库有 | D9: ZMPO24995 | G9: 77711GQ2-S001-NA | I9: 20个空PDQ | R9: 周转箱 | S9: 无 | T9: 无 | X9: Remark：跟PP单一起安排/只需要空PDQ/请配齐PDQ上应有的物料如展示公仔/吸塑等 备注： 请跟PP订单一起安排，谢谢 | Y9: Angus | AD9: N/A | AE9: N/A | AG9: 已完成 | BN9: 20 | CU9: =BQ9+BP9+BO9+BN9+BX9+BR9 -> 20 | CV9: =CK9+CL9+CM9+CN9+CO9+CQ9+CP9 -> 0 | CW9: =CI9+CJ9 -> 0
A10: 45652 | C10: 库有 | D10: ZMPO24995 | G10: 77711-S001-INT | H10: 冰箱迷你球pcs24/箱 | I10: 504 | J10: 0 | K10: 24 | L10: =I10/K10 -> 21 | R10: 周转箱 | S10: 无 | T10: 无 | X10: Remark：跟PP单一起安排/大货标准箱装箱/箱唛参照邮件附件 备注：请跟PP订单一起安排，谢谢 | Y10: Angus | AD10: N/A | AE10: N/A | AG10: 已完成 | AJ10: =AI10-I10 -> -504 | AO10: =I10 -> 504 | CU10: =BQ10+BP10+BO10+BN10+BX10+BR10 -> 0 | CV10: =CK10+CL10+CM10+CN10+CO10+CQ10+CP10 -> 0 | CW10: =CI10+CJ10 -> 0
A11: 45652 | C11: 库有 | D11: ZMPO24995 | G11: 77711-S001-INT | H11: 冰箱迷你球pcs24/箱 | I11: 5套散件 | J11: 0 | K11: 24 | R11: 周转箱 | S11: 无 | T11: 无 | X11: Remark：跟PP单一起安排/只需要齐套散件/麻烦用胶袋分装好一套为一袋 备注： 请跟PP订单一起安排，谢谢 | Y11: Angus | AD11: N/A | AE11: N/A | AG11: 已完成 | CU11: =BQ11+BP11+BO11+BN11+BX11+BR11 -> 0 | CV11: =CK11+CL11+CM11+CN11+CO11+CQ11+CP11 -> 0 | CW11: =CI11+CJ11 -> 0
A12: 45652 | C12: 库有 | D12: ZMPO24995 | G12: 77711GQ1-S001-INT | H12: 冰箱迷你球pcs52/箱 | I12: 20个空PDQ | R12: 周转箱 | S12: 无 | T12: 无 | X12: Remark：跟PP单一起安排/只需要空PDQ/请配齐PDQ上应有的物料如展示公仔/吸塑等 备注： 请跟PP订单一起安排，谢谢 | Y12: Angus | AD12: N/A | AE12: N/A | AG12: 已完成 | BM12: 20 | CU12: =BQ12+BP12+BO12+BN12+BX12+BR12 -> 0 | CV12: =CK12+CL12+CM12+CN12+CO12+CQ12+CP12 -> 0 | CW12: =CI12+CJ12 -> 0
A13: 45652 | C13: 库有 | D13: ZMPO24995 | G13: 77711GQ2-S001-INT | I13: 20个空PDQ | R13: 周转箱 | S13: 无 | T13: 无 | X13: Remark：跟PP单一起安排/只需要空PDQ/请配齐PDQ上应有的物料如展示公仔/吸塑等 备注： 请跟PP订单一起安排，谢谢 | Y13: Angus | AD13: N/A | AE13: N/A | AG13: 已完成 | BP13: 20 | CU13: =BQ13+BP13+BO13+BN13+BX13+BR13 -> 20 | CV13: =CK13+CL13+CM13+CN13+CO13+CQ13+CP13 -> 0 | CW13: =CI13+CJ13 -> 0
A14: 45650 | C14: PP | D14: ZPO2412010 | G14: 77711-S001-NA | H14: 冰箱迷你球24pcs/箱 | I14: 570 | J14: 0 | K14: 24 | L14: =I14/K14 -> 23.75 | R14: 周转箱 | S14: 无 | T14: 无 | Y14: Alison Chen | AD14: N/A | AE14: N/A | AG14: 已完成 | CU14: =BQ14+BP14+BO14+BN14+BX14+BR14 -> 0 | CV14: =CK14+CL14+CM14+CN14+CO14+CQ14+CP14 -> 0 | CW14: =CI14+CJ14 -> 0
A15: 45650 | C15: PP | D15: ZPO2412010 | G15: 77711-S001-INT | H15: 冰箱迷你球pcs24/箱 | I15: 670 | J15: 0 | K15: 24 | L15: =I15/K15 -> 27.916667 | R15: 周转箱 | S15: 无 | T15: 无 | Y15: Alison Chen | AD15: N/A | AE15: N/A | AG15: 已完成 | CU15: =BQ15+BP15+BO15+BN15+BX15+BR15 -> 0 | CV15: =CK15+CL15+CM15+CN15+CO15+CQ15+CP15 -> 0 | CW15: =CI15+CJ15 -> 0
A16: 45701 | B16: THE WAREHOUSE LIMITED | C16: 新西兰 | D16: 4500157534 | F16: 4500157534-40 | G16: 77711GQ2-S002-INT | H16: 冰箱迷你球pcs25/箱 | I16: 200 | J16: 0 | K16: 25 | L16: =I16/K16 -> 8 | M16: 45731 | N16: 45727 | R16: 45804 | S16: 无 | T16: 45804 | X16: 日期码格式：ZURU INC(BVI) 标准格式 日期：按实际生产日期 Packaging Info: MA UPC 英语包装（优先1L英语版本，或者3L/5L含英语都可） 此客人不接受易掉落或者剥落或者可直接触碰的闪粉，可降解也不行，但可以接受符合欧洲微塑料标准的珠光粉或者闪片。 所有外箱上都要贴一张大黄贴："ZURU Product for NZ test " Remark: | Y16: Abby Liang | Z16: 0.95 | AA16: =Z16*I16 -> 190 | AC16: 95262-8.17 | AD16: 77711GQ2-S002-INT | AE16: 已入 | AG16: 已完成 | AJ16: =AI16-I16+200 -> 0 | AO16: =I16 -> 200 | AT16: =I16 -> 200 | AV16: =I16 -> 200 | BB16: =I16/24 -> 8.3333333 | BP16: =I16/25 -> 8 | CU16: =BQ16+BP16+BO16+BN16+BX16+BR16 -> 8 | CV16: =CK16+CL16+CM16+CN16+CO16+CQ16+CP16 -> 0 | CW16: =CI16+CJ16 -> 0
A17: 45722 | D17: ZMPO250187 | G17: 77711-S001-NA | H17: 冰箱迷你球24pcs/箱 | I17: 1584 | J17: 0 | K17: 24 | L17: =I17/K17 -> 66 | M17: 45736 | N17: 45733 | P17: PASS | R17: 45722 | S17: 无 | T17: 无 | X17: Remark：大货最新版本包装/大货标准箱装箱/箱唛请参照邮件附件；备注：收到样品订单后尽快安排 ，注意样板品质质量要求要高于大货品质要求 ，送货时必须要附带送货单(没有送货单和QC检验合格报告的仓库一律拒绝收货)，请知悉，谢谢！ | Y17: Angus | AC17: 95496-8.17 | AD17: 77711-S001（北美） | AE17: 已入 | AG17: 已完成 | AI17: 1584 | AJ17: =AI17-I17 -> 0 | AN17: =I17 -> 1584 | AP17: =I17 -> 1584 | AU17: =I17 -> 1584 | BB17: =I17/48 -> 33 | CU17: =BQ17+BP17+BO17+BN17+BX17+BR17 -> 0 | CV17: =CK17+CL17+CM17+CN17+CO17+CQ17+CP17 -> 0 | CW17: =CI17+CJ17 -> 0
A18: 45737 | D18: ZMPO250244 | G18: 77711-S001-NA | H18: 冰箱迷你球24pcs/箱 | I18: 20套散件 | M18: 45740 | N18: 45736 | R18: 45737 | S18: 无 | T18: 无 | X18: Remark：大货版本/只需要左图中3款散件每款各20PCS,共60PCS；备注： 收到订单后请尽快安排，谢谢 | Y18: Angus | AD18: N/A | AE18: N/A | AG18: 已完成 | AI18: 20 | AJ18: =AI18-K18 -> 20 | CU18: =BQ18+BP18+BO18+BN18+BX18+BR18 -> 0 | CV18: =CK18+CL18+CM18+CN18+CO18+CQ18+CP18 -> 0 | CW18: =CI18+CJ18 -> 0
A19: 45737 | D19: ZMPO250244 | G19: 77711-S001-INT | H19: 冰箱迷你球pcs24/箱 | I19: 1100套散件 | J19: 0 | K19: 550 | L19: 2 | M19: 45740 | N19: 45736 | R19: 45737 | S19: 无 | T19: 无 | X19: Remark：大货版本/只需要左图中2款散件每款各1100PCS,共2200PCS；备注： 收到订单后请尽快安排，谢谢 | Y19: Angus | AD19: N/A | AE19: N/A | AG19: 已完成 | AI19: 1100 | AJ19: =AI19-1100 -> 0 | CU19: =BQ19+BP19+BO19+BN19+BX19+BR19 -> 0 | CV19: =CK19+CL19+CM19+CN19+CO19+CQ19+CP19 -> 0 | CW19: =CI19+CJ19 -> 0
A20: 45749 | D20: ZMPO250283 | G20: 77711-S001-NA | H20: 冰箱迷你球24pcs/箱 | I20: 80套散件 | M20: 45757 | N20: 45754 | R20: 45749 | S20: 无 | T20: 无 | X20: Remark:大货最新版本/只需要齐套散件/麻烦用胶袋分装好一套为一袋/箱唛参照邮件附件;备注： 收到订单后请尽快安排，谢谢 | Y20: Angus | AD20: N/A | AE20: N/A | AG20: 已完成 | CU20: =BQ20+BP20+BO20+BN20+BX20+BR20 -> 0 | CV20: =CK20+CL20+CM20+CN20+CO20+CQ20+CP20 -> 0 | CW20: =CI20+CJ20 -> 0
A21: 45749 | D21: ZMPO250283 | G21: 77711-S001-INT | H21: 冰箱迷你球pcs24/箱 | I21: 30套散件 | J21: 0 | K21: 550 | L21: 2 | M21: 45757 | N21: 45754 | R21: 45749 | S21: 无 | T21: 无 | X21: Remark:大货最新版本/只需要齐套散件/麻烦用胶袋分装好一套为一袋/箱唛参照邮件附件;备注： 收到订单后请尽快安排，谢谢 | Y21: Angus | AD21: N/A | AE21: N/A | AG21: 已完成 | CU21: =BQ21+BP21+BO21+BN21+BX21+BR21 -> 0 | CV21: =CK21+CL21+CM21+CN21+CO21+CQ21+CP21 -> 0 | CW21: =CI21+CJ21 -> 0
A22: 45740 | D22: ZMPO250247 | G22: 77711-S001-NA | H22: 冰箱迷你球24pcs/箱 | I22: 600 | J22: 0 | K22: 24 | L22: =I22/K22 -> 25 | M22: 45759 | N22: 45755 | P22: PASS | R22: 45740 | S22: 无 | T22: 无 | X22: Remark：大货最新版本/大货标准箱装箱/箱唛参照邮件附件；备注： 收到订单后请尽快安排，谢谢 | Y22: Angus | AC22: 95177-8.17 | AD22: 77711-S001（北美） | AE22: 已入 | AG22: 已完成 | AI22: 600 | AJ22: =AI22-I22 -> 0 | AN22: =I22 -> 600 | AP22: =I22 -> 600 | AU22: =I22 -> 600 | BB22: =I22/48 -> 12.5 | CU22: =BQ22+BP22+BO22+BN22+BX22+BR22 -> 0 | CV22: =CK22+CL22+CM22+CN22+CO22+CQ22+CP22 -> 0 | CW22: =CI22+CJ22 -> 0
A23: 45740 | D23: ZMPO250247 | G23: 77711-S001-NA | H23: 冰箱迷你球24pcs/箱 | I23: 30套散件 | M23: 45759 | N23: 45755 | R23: 45740 | S23: 无 | T23: 无 | X23: Remark：大货最新版本/只需要齐套散件/麻烦用胶袋分装好一套为一袋；备注： 收到订单后请尽快安排，谢谢 | Y23: Angus | AD23: N/A | AE23: N/A | AG23: 已完成 | AI23: 30 | AJ23: 0 | CU23: =BQ23+BP23+BO23+BN23+BX23+BR23 -> 0 | CV23: =CK23+CL23+CM23+CN23+CO23+CQ23+CP23 -> 0 | CW23: =CI23+CJ23 -> 0
A24: 45740 | D24: ZMPO250247 | G24: 77711-S001-INT | H24: 冰箱迷你球pcs24/箱 | I24: 400 | J24: 0 | K24: 24 | L24: =I24/K24 -> 16.666667 | M24: 45759 | N24: 45755 | R24: 45740 | S24: 无 | T24: 无 | X24: Remark：大货最新版本/大货标准箱装箱/箱唛参照邮件附件；备注： 收到订单后请尽快安排，谢谢 | Y24: Angus | AC24: 95177-8.17 | AD24: 77711-S001-INT | AE24: 已入 | AG24: 已完成 | AI24: 400 | AJ24: =AI24-I24 -> 0 | AO24: =I24 -> 400 | AT24: =I24 -> 400 | AV24: =I24 -> 400 | BB24: =I24/24 -> 16.666667 | CU24: =BQ24+BP24+BO24+BN24+BX24+BR24 -> 0 | CV24: =CK24+CL24+CM24+CN24+CO24+CQ24+CP24 -> 0 | CW24: =CI24+CJ24 -> 0
A25: 45740 | D25: ZMPO250247 | G25: 77711-S001-INT | H25: 冰箱迷你球pcs24/箱 | I25: 30套散件 | J25: 0 | K25: 24 | L25: 2 | M25: 45759 | N25: 45755 | R25: 45740 | S25: 无 | T25: 无 | X25: Remark：大货最新版本/只需要齐套散件/麻烦用胶袋分装好一套为一袋；备注： 收到订单后请尽快安排，谢谢 | Y25: Angus | AD25: N/A | AE25: N/A | AG25: 已完成 | AI25: 30 | AJ25: 0 | CU25: =BQ25+BP25+BO25+BN25+BX25+BR25 -> 0 | CV25: =CK25+CL25+CM25+CN25+CO25+CQ25+CP25 -> 0 | CW25: =CI25+CJ25 -> 0
A26: 45726 | B26: WAL-MART STORES INC. USA | C26: 美国 | D26: 4500159672 | E26: 902763064 | F26: 4500159672-10 | G26: 77711GQ4-S001-NA | H26: 冰箱迷你球16pcs/箱 | I26: 3136 | J26: 0 | K26: 16 | L26: =I26/K26 -> 196 | M26: 45770 | N26: 45766 | O26: 4/25 第三方抽办 | R26: 45727 | S26: 无 | T26: RFID贴纸 | X26: 日期码格式：ZURU DGYYYYMMDD CHINA(日期避开周末和法定节假日即可） 日期：按实际生产日期 Packaging Info: 77711GQ4-S001-NA 1.包装要求： MA 1L A版收缩膜+MA 5L A版收藏指南+MA 说明书+客版1L PDQ 每pcs产品上要贴1张RFID贴纸，贴纸由ZURU提供，贴纸位置请严格按照我们签回的签板； Remark: 77711GQ4-S001-NA 1.包装要求： MA 1L A版收缩膜+MA 5L A版收藏指南+MA 说明书+客版1L PDQ 每pcs产品上要贴1张RFID贴纸，贴纸由ZURU提供，贴纸位置请严格按照我们签回的签板； 2. 外箱印刷带条码的RFID箱唛：RFID紫色色带+WM Dept.图标+RFID图标+ITF-14条码，四面右下角印刷ZURU logo, ITFF条码只印刷在正唛一面，在加印的时候确保 条形码能扫描出来，外箱侧面任一角落加印："MADE IN CHINA" 字样； 3. 在产品上和包装上要有日期码、以及要有MADE IN CHINA和ZURU字样； 4. 产品如有扎带口要剪平，不能刮手。 5. 此单需要抽板和验货，抽板时间预计4/23，请多备料 6. 此单以loose carton出货，16pcs/PDQ/CTN | Y26: Maggie Xie | Z26: 1.68 | AA26: =Z26*I26 -> 5268.48 | AD26: 77711GQ4-S001-NA | AE26: 已入 | AG26: 已完成 | AI26: =504+2632 -> 3136 | AJ26: =AI26-I26 -> 0 | AN26: =I26 -> 3136 | AP26: =I26 -> 3136 | AU26: =I26 -> 3136 | BB26: =I26/48 -> 65.333333 | BQ26: =I26/16 -> 196 | CU26: =BQ26+BP26+BO26+BN26+BX26+BR26 -> 196 | CV26: =CK26+CL26+CM26+CN26+CO26+CQ26+CP26 -> 0 | CW26: =CI26+CJ26 -> 0
A27: 45761 | D27: ZMPO250315 | G27: 77711-S001-NA | H27: 冰箱迷你球24pcs/箱 | I27: 816 | J27: 0 | K27: 24 | L27: =I27/K27 -> 34 | M27: 45771 | N27: 45768 | P27: PASS | R27: 45761 | S27: 无 | T27: 无 | X27: Remark:大货最新版本包装/大货标准箱装箱/箱唛请参照邮件附件;备注： 收到样品订单后尽快安排 ，此订单麻烦在外箱上备注是海运订单/注意样板品质质量要求要高于大货品质质量 ，送货时必须要附带送货单(没有送货单和QC检验合格报告的仓库一律拒绝收货)，请知悉，谢谢！ | Y27: Angus | AC27: 95176-8.17 | AD27: 77711-S001（北美） | AE27: 已入 | AG27: 已完成 | AI27: 816 | AJ27: =AI27-I27 -> 0 | AN27: =I27 -> 816 | AP27: =I27 -> 816 | AU27: =I27 -> 816 | BB27: =I27/48 -> 17 | CU27: =BQ27+BP27+BO27+BN27+BX27+BR27 -> 0 | CV27: =CK27+CL27+CM27+CN27+CO27+CQ27+CP27 -> 0 | CW27: =CI27+CJ27 -> 0
A28: 45761 | D28: ZMPO250315 | G28: 77711-S001-INT | H28: 冰箱迷你球pcs24/箱 | I28: 504 | J28: 0 | K28: 24 | L28: 2 | M28: 45771 | N28: 45768 | P28: PASS | R28: 45761 | S28: 无 | T28: 无 | X28: Remark:大货最新版本包装/大货标准箱装箱/箱唛请参照邮件附件;备注： 收到样品订单后尽快安排 ，此订单麻烦在外箱上备注是海运订单/注意样板品质质量要求要高于大货品质质量 ，送货时必须要附带送货单(没有送货单和QC检验合格报告的仓库一律拒绝收货)，请知悉，谢谢！ | Y28: Angus | AD28: N/A | AE28: N/A | AG28: 已完成 | AI28: 504 | AJ28: =AI28-I28 -> 0 | AO28: =I28 -> 504 | AP28: =I28 -> 504 | AV28: =I28 -> 504 | BB28: =I28/24 -> 21 | CU28: =BQ28+BP28+BO28+BN28+BX28+BR28 -> 0 | CV28: =CK28+CL28+CM28+CN28+CO28+CQ28+CP28 -> 0 | CW28: =CI28+CJ28 -> 0
A29: 45670 | B29: Smyths Toys HQ UC UK | C29: 爱尔兰 | D29: 4500155601 | E29: PO4400460299 | F29: 4500155601-10 | G29: 77711GQ2-S002-INT | H29: 冰箱迷你球25pcs/箱 | I29: 9000 | J29: 0 | K29: 25 | L29: =I29/K29 -> 360 | M29: 45772 | N29: 45768 | P29: PASS | R29: 45670 | S29: 无 | T29: 所有资料翻#4500155592 | X29: 日期码格式：ZURU INC(BVI) 标准格式 日期：按实际生产日期 Packaging Info: 77711GQ2：最新MA PDQ(优先3L)+客版收缩膜+23L说明书+5-23L警语收藏指南+MA 5L creative说明书+creative说明书荷兰语贴纸（所有资料翻#4500155592） 客户PO号码请参考remark Remark: 1）包装日期码按ZURU格式即可，请确保不迟于外箱日期码，可等于或者早于外箱日期码，必须为法定工作日，印刷前请先检查外箱日期码。 2）订单出英国，请注意检查产品及包装应带UKCA图标（14+产品除外），包装显示ZURU UK LTD/ZURU France地址信息，QC部门请查核，如有问题与跟单确认 3) 需要完全符合欧洲标准(符合微塑料法规)，否则不合法规会有客诉产生 | Y29: Ula Zhao | Z29: 1.24 | AA29: =Z29*I29 -> 11160 | AC29: 95083-8.17 | AD29: 77711GQ2-S002-INT-客版Smyths | AE29: 已入 | AG29: 已完成 | AI29: 9000 | AJ29: =AI29-I29 -> 0 | AO29: =I29 -> 9000 | AV29: =I29 -> 9000 | BB29: =I29/48 -> 187.5 | BE29: =I29 -> 9000 | BP29: =I29/25 -> 360 | CU29: =BQ29+BP29+BO29+BN29+BX29+BR29 -> 360 | CV29: =CK29+CL29+CM29+CN29+CO29+CQ29+CP29 -> 0 | CW29: =CI29+CJ29 -> 0
A30: 45670 | B30: Smyths Toys HQ UC UK | C30: 爱尔兰 | D30: 4500155601 | E30: PO4400460305 | F30: 4500155601-20 | G30: 77711GQ2-S002-INT | H30: 冰箱迷你球25pcs/箱 | I30: 3000 | J30: 0 | K30: 25 | L30: =I30/K30 -> 120 | M30: 45772 | N30: 45768 | P30: PASS | Q30: 4/28 出货 | R30: 45670 | S30: 无 | T30: 所有资料翻#4500155592 | X30: 日期码格式：ZURU INC(BVI) 标准格式 日期：按实际生产日期 Packaging Info: 77711GQ2：最新MA PDQ(优先3L)+客版收缩膜+23L说明书+5-23L警语收藏指南+MA 5L creative说明书+creative说明书荷兰语贴纸（所有资料翻#4500155592） 客户PO号码请参考remark Remark: 1）包装日期码按ZURU格式即可，请确保不迟于外箱日期码，可等于或者早于外箱日期码，必须为法定工作日，印刷前请先检查外箱日期码。 2）订单出英国，请注意检查产品及包装应带UKCA图标（14+产品除外），包装显示ZURU UK LTD/ZURU France地址信息，QC部门请查核，如有问题与跟单确认 3) 需要完全符合欧洲标准(符合微塑料法规)，否则不合法规会有客诉产生 | Y30: Ula Zhao | Z30: 1.24 | AA30: =Z30*I30 -> 3720 | AC30: 95081-8.17 | AD30: 77711GQ2-S002-INT-客版Smyths | AE30: 已入 | AG30: 已完成 | AI30: 3000 | AJ30: =AI30-I30 -> 0 | AO30: =I30 -> 3000 | AV30: =I30 -> 3000 | BB30: =I30/48 -> 62.5 | BE30: =I30 -> 3000 | BP30: =I30/25 -> 120 | CU30: =BQ30+BP30+BO30+BN30+BX30+BR30 -> 120 | CV30: =CK30+CL30+CM30+CN30+CO30+CQ30+CP30 -> 0 | CW30: =CI30+CJ30 -> 0
A31: 45728 | B31: THE WAREHOUSE LIMITED | C31: 新西兰 | D31: 4500159882 | F31: 4500159882-10 | G31: 77711SK-S002-INT | H31: 冰箱迷你球展示架（带底座） | I31: 2280 | J31: 0 | K31: 60 | L31: =I31/K31 -> 38 | M31: 45772 | N31: 45768 | P31: PASS | Q31: 4/25 出货 | R31: 45735 | S31: 无 | T31: 45735 | X31: 日期码格式：ZURU INC(BVI) 标准格式 日期：按实际生产日期 Packaging Info: #77673TQ1: 1.3PCS AG13 BATTERIES(INCLUDED)，有纽扣电池，包装正面和说明书都需要加电池警告语贴纸（法规要求） 2.Filxed Collection #77711需要加UPC贴纸 Remark: 1.MA UPC 英语包装（优先1L英语版本，或者3L/5L含英语都可） 2.此客人不接受易掉落或者剥落或者可直接触碰的闪粉，可降解也不行，但可以接受符合欧洲微塑料标准的珠光粉或者闪片。 | Y31: Abby Liang | Z31: 63.7 | AA31: =Z31*L31 -> 2420.6 | AC31: 95093-8.17 | AD31: 77711SK-S002-INT | AE31: 已入 | AG31: 已完成 | AI31: 2280 | AJ31: =AI31-I31 -> 0 | AO31: =I31 -> 2280 | AT31: =I31 -> 2280 | AV31: =I31 -> 2280 | BB31: =I31/24 -> 95 | CM31: =I31/60 -> 38 | CU31: =BQ31+BP31+BO31+BN31+BX31+BR31 -> 0 | CV31: =CK31+CL31+CM31+CN31+CO31+CQ31+CP31 -> 38 | CW31: =CI31+CJ31 -> 0
A32: 45728 | B32: THE WAREHOUSE LIMITED | C32: 新西兰 | D32: 4500159886 | F32: 4500159886-10 | G32: 77711SK-S002-INT | H32: 冰箱迷你球展示架（带底座） | I32: 720 | J32: 0 | K32: 60 | L32: =I32/K32 -> 12 | M32: 45772 | N32: 45768 | P32: PASS | R32: 45735 | S32: 无 | T32: 45735 | X32: 日期码格式：ZURU INC(BVI) 标准格式 日期：按实际生产日期 Packaging Info: #77673TQ1: 1.3PCS AG13 BATTERIES(INCLUDED)，有纽扣电池，包装正面和说明书都需要加电池警告语贴纸（法规要求） 2.Filxed Collection #77711需要加UPC贴纸 Remark: 1.MA UPC 英语包装（优先1L英语版本，或者3L/5L含英语都可） 2.此客人不接受易掉落或者剥落或者可直接触碰的闪粉，可降解也不行，但可以接受符合欧洲微塑料标准的珠光粉或者闪片。 | Y32: Abby Liang | Z32: 63.7 | AA32: =Z32*L32 -> 764.4 | AC32: 95094-8.17 | AD32: 77711SK-S002-INT | AE32: 已入 | AG32: 已完成 | AI32: 720 | AJ32: =AI32-I32 -> 0 | AO32: =I32 -> 720 | AT32: =I32 -> 720 | AV32: =I32 -> 720 | BB32: =I32/24 -> 30 | CM32: =I32/60 -> 12 | CU32: =BQ32+BP32+BO32+BN32+BX32+BR32 -> 0 | CV32: =CK32+CL32+CM32+CN32+CO32+CQ32+CP32 -> 12 | CW32: =CI32+CJ32 -> 0
A33: 45733 | B33: WAL-MART CANADA CORP. | C33: 加拿大 | D33: 4500160504 | E33: 9900923469 | F33: 4500160504-70 | G33: 77711GQ2-S002-NA | H33: 冰箱迷你球 25pcs/箱 | I33: 10075 | J33: 0 | K33: 25 | L33: =I33/K33 -> 403 | M33: 45775 | N33: 45771 | O33: 5/19 第三方验货，3. 此单有第三方验货，烦请多备包装物料； 6. #77711需于2025/4/18安排签版, 签样数量：大货样各4PCS+散件3套; 7. #77711 需于2025/4/28安排抽办测试, 抽办数量：大货各4 SETS; | P33: PASS | R33: 45748 | S33: 无 | T33: 45734 | X33: 日期码格式：ZURU INC(BVI) 标准格式 日期：按实际生产日期 Packaging Info: #77711： MA2L,PDQ(NA版,25装)+MA2L收缩膜(NA版,UPC:193052080127)+MA5L收藏指南((NA版)+MA配件袋+MA5L说明书+MA23L警告语说明书 产品配比： 7 Assortment, Polar bear: Penguin: Walrus: Mammoth: Owl: Seal: Snow man=10:10:10:10:10:8:2. Snow man is the rare item. Remark: 1. 此单有箱唛； 3. 此单有第三方验货，烦请多备包装物料； 6. #77711需于2025/4/18安排签版, 签样数量：大货样各4PCS+齐套散件3套; 9. #77711 需于2025/4/28安排抽办测试, 抽办数量：大货4 pcs+齐套散件4SETS; 11. UPC贴纸：必须在原来错误的条码上用黑色粗头笔涂黑直至不能扫描，再贴上正确的UPC; ********************* a. 请确保产品符合1999年版本的加拿大环境保护法(CEPA)和2012年禁止某些有毒物质法规的要求。该产品不含任何在加拿大禁用的化学物质，包括但不限于有毒物 质清单中列出的化学物质，并且在为加拿大沃尔玛生产产品期间没有使用任何禁用化学物质。 Supplier certify that the products comply with the requirements of Canadian Environmental Protection Act, 1999 (CEPA), Prohibition of Certain To xic Substances Regulations, 2012. The products do not contain any chemicals that are banned in Canada, including but not limited to those listed in the Toxic Substances List and no banned chemicals were used during the manufacturing of product for Walmart Canada. 附件列表： (1) Letter of Guarantee for Canada banned chemicals - (1-5CA) b. 请确保产品在均质材料中的汞浓度不超过0.1%（按重量计）。 Supplier certify that the WAL-MART vendor products does not have a mercury concentration of more than 0.1% by weight in homogeneous material. 附件列表： (1) Letter of Guarantee for Mercury COC c. 请确保产品的塑料材料不含以下物质（SOR 2011-17 27B): Supplier certify that the plastic materials do not contain the following substances(SOR 2011-17 27B): (a) carbon tetrachloride or any substance that contains it; (b) methyl alcohol or any substance thay contains >1.0%; (c) petroleum distillates or any substance that contains >10% weight to volume of petroleum distillates; (d) benzene; (e) turpentine or any substance that contains >10% weight to volume of turpentine; (f) boric acid or salts of boric acid; or (g) ethyl ether. 附件列表： (1) Letter of Guarantee for WM CA-Other prohibited substances in plastic(less than 3 years) | Y33: Monica Zhou | Z33: 0.95 | AA33: =Z33*I33 -> 9571.25 | AC33: 95066/95077 | AD33: 77711GQ2-S002-NA-2L | AE33: 已入 | AG33: 已完成 | AI33: 10075 | AJ33: =AI33-I33 -> 0 | AN33: =I33 -> 10075 | AS33: =I33 -> 10075 | AU33: =I33 -> 10075 | BB33: =I33/24 -> 419.79167 | BO33: =I33/25 -> 403 | CU33: =BQ33+BP33+BO33+BN33+BX33+BR33 -> 403 | CV33: =CK33+CL33+CM33+CN33+CO33+CQ33+CP33 -> 0 | CW33: =CI33+CJ33 -> 0
A34: 45733 | B34: THE FARMERS' TRADING COMPANY LIMITE | C34: 新西兰 | D34: 4500160427 | E34: SSF792 | F34: 4500160427-10 | G34: 77711GQ1-S002-INT | H34: 冰箱迷你球13pcs/箱 | I34: 1300 | J34: 0 | K34: 13 | L34: =I34/K34 -> 100 | M34: 45775 | N34: 45771 | P34: PASS | R34: 45740 | S34: 无 | T34: 45755 | X34: 日期码格式：ZURU INC(BVI) 标准格式 日期：按实际生产日期 Packaging Info: Remark: MA UPC英语包装（优先1L英语版本,或者3L/L含英语即可); 可移动材质的价格贴纸（价格贴纸要切易撕线） 新增upc贴纸覆盖原EAN条码 | Y34: Kido he | Z34: 0.92 | AA34: =Z34*I34 -> 1196 | AC34: 95085-8.17 | AD34: 77711GQ1-S002-INT | AE34: 已入 | AG34: 已完成 | AI34: 1300 | AJ34: =AI34-I34 -> 0 | AO34: =I34 -> 1300 | AT34: =I34 -> 1300 | AV34: =I34 -> 1300 | BB34: =I34/24 -> 54.166667 | BM34: =I34/13 -> 100 | CU34: =BQ34+BP34+BO34+BN34+BX34+BR34 -> 0 | CV34: =CK34+CL34+CM34+CN34+CO34+CQ34+CP34 -> 0 | CW34: =CI34+CJ34 -> 0
A35: 45733 | B35: COLES SUPERMARKETS | C35: 澳大利亚 | D35: 4500160492 | E35: 港口：SYD PO#46423734 | F35: 4500160492-10 | G35: 77711GQ6-S001-INT | H35: 冰箱迷你球6pcs/箱 | I35: 1146 | J35: 0 | K35: 6 | L35: =I35/K35 -> 191 | M35: 45775 | N35: 45771 | P35: PASS | R35: 45733 | S35: 无 | T35: 无 | X35: 日期码格式：ZURU INC(BVI) 标准格式 日期：按实际生产日期 Packaging Info: MA UPC 包装+客版PDQ+箱唛 Remark: 1.此单出口澳大利亚，请按相应的澳新标准生产； 2.产品和包装上生产批号请按我司标准 3.当同一PO或item有多个批次代码时，每个批次代码的纸箱必须分组在一起，且明显分开 | Y35: Lydia Wu | Z35: 0.97 | AA35: =Z35*I35 -> 1111.62 | AC35: 95099-8.17 | AD35: 77711GQ6-S001-INT | AE35: 已入 | AG35: 已完成 | AI35: 1146 | AJ35: =AI35-I35 -> 0 | AO35: =I35 -> 1146 | AT35: =I35 -> 1146 | AV35: =I35 -> 1146 | BB35: =I35/24 -> 47.75 | BT35: =I35/6 -> 191 | CF35: =I35/6 -> 191 | CU35: =BQ35+BP35+BO35+BN35+BX35+BR35 -> 0 | CV35: =CK35+CL35+CM35+CN35+CO35+CQ35+CP35 -> 0 | CW35: =CI35+CJ35 -> 0
A36: 45733 | B36: COLES SUPERMARKETS | C36: 澳大利亚 | D36: 4500160492 | E36: 港口：MEL PO#46423735 | F36: 4500160492-20 | G36: 77711GQ6-S001-INT | H36: 冰箱迷你球6pcs/箱 | I36: 2292 | J36: 0 | K36: 6 | L36: =I36/K36 -> 382 | M36: 45775 | N36: 45771 | P36: PASS | R36: 45733 | S36: 无 | T36: 无 | X36: 日期码格式：ZURU INC(BVI) 标准格式 日期：按实际生产日期 Packaging Info: MA UPC 包装+客版PDQ+箱唛 Remark: 1.此单出口澳大利亚，请按相应的澳新标准生产； 2.产品和包装上生产批号请按我司标准 3.当同一PO或item有多个批次代码时，每个批次代码的纸箱必须分组在一起，且明显分开 | Y36: Lydia Wu | Z36: 0.97 | AA36: =Z36*I36 -> 2223.24 | AC36: 95099-8.17 | AD36: 77711GQ6-S001-INT | AE36: 已入 | AG36: 已完成 | AI36: 2292 | AJ36: =AI36-I36 -> 0 | AO36: =I36 -> 2292 | AT36: =I36 -> 2292 | AV36: =I36 -> 2292 | BB36: =I36/24 -> 95.5 | BT36: =I36/6 -> 382 | CF36: =I36/6 -> 382 | CU36: =BQ36+BP36+BO36+BN36+BX36+BR36 -> 0 | CV36: =CK36+CL36+CM36+CN36+CO36+CQ36+CP36 -> 0 | CW36: =CI36+CJ36 -> 0
A37: 45733 | B37: COLES SUPERMARKETS | C37: 澳大利亚 | D37: 4500160492 | E37: 港口：BNE PO#46423736 | F37: 4500160492-30 | G37: 77711GQ6-S001-INT | H37: 冰箱迷你球6pcs/箱 | I37: 1146 | J37: 0 | K37: 6 | L37: =I37/K37 -> 191 | M37: 45775 | N37: 45771 | P37: PASS | R37: 45733 | S37: 无 | T37: 无 | X37: 日期码格式：ZURU INC(BVI) 标准格式 日期：按实际生产日期 Packaging Info: MA UPC 包装+客版PDQ+箱唛 Remark: 1.此单出口澳大利亚，请按相应的澳新标准生产； 2.产品和包装上生产批号请按我司标准 3.当同一PO或item有多个批次代码时，每个批次代码的纸箱必须分组在一起，且明显分开 | Y37: Lydia Wu | Z37: 0.97 | AA37: =Z37*I37 -> 1111.62 | AC37: 95099-8.17 | AD37: 77711GQ6-S001-INT | AE37: 已入 | AG37: 已完成 | AI37: 1146 | AJ37: =AI37-I37 -> 0 | AO37: =I37 -> 1146 | AT37: =I37 -> 1146 | AV37: =I37 -> 1146 | BB37: =I37/24 -> 47.75 | BT37: =I37/6 -> 191 | CF37: =I37/6 -> 191 | CU37: =BQ37+BP37+BO37+BN37+BX37+BR37 -> 0 | CV37: =CK37+CL37+CM37+CN37+CO37+CQ37+CP37 -> 0 | CW37: =CI37+CJ37 -> 0
A38: 45728 | B38: ALL BRANDS TOYS PTY LTD | C38: 澳大利亚 | D38: 4500159576 | E38: 83718 | F38: 4500159576-10 | G38: 77711GQ2-S001-INT | H38: 冰箱迷你球50pcs/箱 | I38: 5000 | J38: 0 | K38: 50 | L38: =I38/K38 -> 100 | M38: 45777 | N38: 45773 | P38: PASS | R38: 45728 | S38: 无 | T38: 45776 | X38: 日期码格式：ZURU INC(BVI) 标准格式 日期：按实际生产日期 Packaging Info: 1. 77711GQ2: MA INT 3L包装（MA收缩膜和说明书） + 一张UPC条码贴纸 （UPC#193052080134）+ 1张客人通用进口商贴纸; Remark: 1.按实际生产日期; 2.出澳大利亚，请按照相应标准生产; | Y38: Lydia Wu | Z38: 0.95 | AA38: =Z38*I38 -> 4750 | AC38: 95160-8.17 | AD38: 77711GQ2-S001-INT | AE38: 已入 | AG38: 已完成 | AI38: 5000 | AJ38: =AI38-I38 -> 0 | AO38: =I38 -> 5000 | AT38: =I38 -> 5000 | AV38: =I38 -> 5000 | BB38: =I38/24 -> 208.33333 | BP38: =I38/25 -> 200 | CU38: =BQ38+BP38+BO38+BN38+BX38+BR38 -> 200 | CV38: =CK38+CL38+CM38+CN38+CO38+CQ38+CP38 -> 0 | CW38: =CI38+CJ38 -> 0
A39: 45728 | B39: ALL BRANDS TOYS PTY LTD | C39: 澳大利亚 | D39: 4500159576 | E39: 83718 | F39: 4500159576-50 | G39: 77711SK-S002-INT | H39: 冰箱迷你球展示架（带底座） | I39: 3600 | J39: 0 | K39: 60 | L39: =I39/K39 -> 60 | M39: 45777 | N39: 45773 | P39: PASS | R39: 45728 | S39: 无 | T39: 45776 | X39: 日期码格式：ZURU INC(BVI) 标准格式 日期：按实际生产日期 Packaging Info: 5. 77711SK: MA INT 3L包装（MA收缩膜和说明书） + 一张UPC条码贴纸 （UPC#193052080134）+ 1张客人通用进口商贴纸 Remark: 1.按实际生产日期; 2.出澳大利亚，请按照相应标准生产; | Y39: Lydia Wu | Z39: 63.7 | AA39: =Z39*L39 -> 3822 | AC39: 95160-8.17 | AD39: 77711SK-S002-INT | AE39: 已入 | AG39: 已完成 | AI39: 3600 | AJ39: =AI39-I39 -> 0 | AO39: =I39 -> 3600 | AT39: =I39 -> 3600 | AV39: =I39 -> 3600 | BB39: =I39/24 -> 150 | CM39: =I39/60 -> 60 | CU39: =BQ39+BP39+BO39+BN39+BX39+BR39 -> 0 | CV39: =CK39+CL39+CM39+CN39+CO39+CQ39+CP39 -> 60 | CW39: =CI39+CJ39 -> 0
A40: 45729 | B40: KMART AUSTRALIA LTD | C40: 澳大利亚 | D40: 4500160026 | E40: 20627370 | F40: 4500160026-10 | G40: 77711GQ1-S002-INT | H40: 冰箱迷你球13pcs/箱 | I40: 10413 | J40: 0 | K40: 13 | L40: =I40/K40 -> 801 | M40: 45786 | N40: 45782 | P40: PASS | R40: 45748 | S40: 有 | T40: 防盗贴纸+ 外箱贴纸SSCC Label | X40: 日期码格式：ZURU INC(BVI) 标准格式 日期：按实际生产日期 Packaging Info: 77711GQ1-S002-INT: MA 3L包装 + 一张UPC条码贴（收缩膜和说明书）+ 防盗贴纸+ 箱唛 + 外箱贴纸SSCC Label Remark: 1.请务必按时完货，验货。并且按期送货入货代指定仓库，如果晚了导致船期Delay将会有罚金产生或者客户要求空运，所产生的罚金和空运费由工厂承担。 2.SSCC 外箱贴纸请同纸箱瓦楞纸方向（竖纹向）垂直，即外箱贴纸横着贴(注意条码不要被胶带粘住），贴1pc，贴1面正唛，封箱胶纸不能挡住贴纸内容。外箱贴纸 离外箱边距离不少于2cm。 3.外箱材质为ZURU标准； 4.此单需使用KMART封箱胶上下工字型封箱;从2019年6月开始，要用KMART 新版封箱胶带，此单要用"ANKO"封箱胶带 5.此单出口澳大利亚，请按相应的澳新标准生产； 6.产品和包装上生产批号的显示格式ZURU标准日期码格式 7.外箱信息不可手写，重量和体积需要与实际的一致(不可手写） 8. 每款item装箱后的G.W.超过10KG或者CBM超过0.13,(9.5KG或者以上，四舍五入后也属于10KG) 需在外箱上加印超 重或者Bulky LOGO，若发现我们资料没有，请 帮忙提醒 1)重量超过10kg但不超过16kg且CBM不超过0.13,10-16kg 超重logo 2）CBM超过0.13且重量少于17kg，bulky logo 3）不属于以上两种情况，需要使用相应重量范围内的超重logo 4）超重logo需要在外箱四面都印刷(箱唛右上角，两面侧唛超重logo需要尽量靠近毛重)，尺寸为:110mm height* 95mm width 9. 实际外箱重量跟印在箱唛上的数据差异不能超3%，尺寸按实际数据印刷 | Y40: Lydia Wu | Z40: 0.95 | AA40: =Z40*I40 -> 9892.35 | AC40: 95095-8.17 | AD40: 77711GQ1-S002-INT | AE40: 已入 | AG40: 已完成 | AI40: 10413 | AJ40: =AI40-I40 -> 0 | AO40: =I40 -> 10413 | AT40: =I40 -> 10413 | AV40: =I40 -> 10413 | BB40: =I40/24 -> 433.875 | BM40: =I40/13 -> 801 | CU40: =BQ40+BP40+BO40+BN40+BX40+BR40 -> 0 | CV40: =CK40+CL40+CM40+CN40+CO40+CQ40+CP40 -> 0 | CW40: =CI40+CJ40 -> 0
A41: 45729 | B41: KMART AUSTRALIA LTD(NEW ZEALAND) | C41: 新西兰 | D41: 4500160027 | E41: 20627371 | F41: 4500160027-10 | G41: 77711GQ1-S002-INT | H41: 冰箱迷你球13pcs/箱 | I41: 1352 | J41: 0 | K41: 13 | L41: =I41/K41 -> 104 | M41: 45786 | N41: 45782 | P41: PASS | R41: 45748 | S41: 有 | T41: 防盗贴纸+ 外箱贴纸SSCC Label | X41: 日期码格式：ZURU INC(BVI) 标准格式 日期：按实际生产日期 Packaging Info: 77711GQ1-S002-INT: MA 3L包装（MA收缩膜和说明书） + 一张UPC条码贴+ 防盗贴纸（贴纸以及位置图翻单PO#4500160026）+ 箱唛 + 外箱贴纸SSCC Label Remark: 1.请务必按时完货，验货。并且按期送货入货代指定仓库，如果晚了导致船期Delay将会有罚金产生或者客户要求空运，所产生的罚金和空运费由工厂承担。 2.SSCC 外箱贴纸请同纸箱瓦楞纸方向（竖纹向）垂直，即外箱贴纸横着贴(注意条码不要被胶带粘住），贴1pc，贴1面正唛，封箱胶纸不能挡住贴纸内容。外箱贴纸 离外箱边距离不少于2cm。 3.外箱材质为ZURU标准； 4.此单需使用KMART封箱胶上下工字型封箱;从2019年6月开始，要用KMART 新版封箱胶带，此单要用"ANKO"封箱胶带 5.此单出口新西兰，请按相应的澳新标准生产； 6.产品和包装上生产批号的显示格式ZURU标准日期码格式 7.外箱信息不可手写，重量和体积需要与实际的一致(不可手写） 8. 每款item装箱后的G.W.超过10KG或者CBM超过0.13,(9.5KG或者以上，四舍五入后也属于10KG) 需在外箱上加印超 重或者Bulky LOGO，若发现我们资料没有，请 帮忙提醒 1)重量超过10kg但不超过16kg且CBM不超过0.13,10-16kg 超重logo 2）CBM超过0.13且重量少于17kg，bulky logo 3）不属于以上两种情况，需要使用相应重量范围内的超重logo 4）超重logo需要在外箱四面都印刷(箱唛右上角，两面侧唛超重logo需要尽量靠近毛重)，尺寸为:110mm height* 95mm width 9. 实际外箱重量跟印在箱唛上的数据差异不能超3%，尺寸按实际数据印刷 | Y41: Lydia Wu | Z41: 0.95 | AA41: =Z41*I41 -> 1284.4 | AC41: 95097-8.17 | AD41: 77711GQ1-S002-INT | AE41: 已入 | AG41: 已完成 | AI41: 1352 | AJ41: =AI41-I41 -> 0 | AO41: =I41 -> 1352 | AT41: =I41 -> 1352 | AV41: =I41 -> 1352 | BB41: =I41/24 -> 56.333333 | BM41: =I41/13 -> 104 | CU41: =BQ41+BP41+BO41+BN41+BX41+BR41 -> 0 | CV41: =CK41+CL41+CM41+CN41+CO41+CQ41+CP41 -> 0 | CW41: =CI41+CJ41 -> 0
A42: 45734 | B42: ZURU Germany GMBH | C42: 德国 | D42: 4500160634 | E42: 5200006405 | F42: 4500160634-10 | G42: 77711GQ1-S002-INT-MTS | H42: 冰箱迷你球13pcs/箱 | I42: 2600 | J42: 0 | K42: 13 | L42: =I42/K42 -> 200 | M42: 45786 | N42: 45782 | P42: PASS | R42: 45735 | S42: 无 | T42: 多语折叠警告语贴纸（翻单4500157858） | X42: 日期码格式：ZURU INC(BVI) 标准格式 日期：按实际生产日期 Packaging Info: 77711GQ1: MA_3L_13PCS_A PDQ + MA 3L EAN 收缩膜 +多语折叠警告语贴纸（翻单4500157858） + MA5L收藏指南+ MA 23L说明书+ UV胶黑白警告语 + MA纸袋 EAN # 4894680043350 Remark: 1.德国内销单，需要通过ZURU 验货结果后才能出货 (工厂需要主动提前同ZURU QC预约验货避免延期出货造成不必要麻烦)； 2. 若有特定款有特殊外箱条码要求时,需要明确列出产品款对应的具体外箱条码号码/条码类型 (若无,可以忽略此需求) 3.所有出口欧洲的产品, 法规规定禁止在包装和共公众用的印刷品中使用矿物油中含有的物质, 包装印刷油墨中含有的MOAH/MOSH的质量浓度不能超过1%, 否则出货 到法国被抽检出现问题, 供应商需要对此负责; 4. date code: 外箱日期码要晚于或等于产品日期码，不能早于产品的日期码 5. 所有电子产品身上需要加字唛，为ZURU FRANCE 地址 (如无电子产品，或者产品布标有此地址，可忽略此信息) ZURU France 1/3, Rue d'Argenteuil 95210 SAINT-GRATIEN, FRANCE 6. 装柜时需要按照款式号码从小到大一款款依次装,避免终端仓库卸货混乱.若一个柜子涉及到几个不同国家内销单,装柜时需要一个国家装完后再装另一个国家的 产品,依次装柜,避免终端仓库因不同国家不同库位位置卸货混乱. (此点需要同工厂装柜人员强调)" | Y42: SD04 | Z42: 1.16 | AA42: =Z42*I42 -> 3016 | AC42: 95096-8.17 | AD42: 77711GQ1-S002-INT | AE42: 已入 | AG42: 已完成 | AI42: 2600 | AJ42: =AI42-I42 -> 0 | AO42: =I42 -> 2600 | AT42: =I42 -> 2600 | AV42: =I42 -> 2600 | BB42: =I42/24 -> 108.33333 | BM42: =I42/13 -> 200 | CU42: =BQ42+BP42+BO42+BN42+BX42+BR42 -> 0 | CV42: =CK42+CL42+CM42+CN42+CO42+CQ42+CP42 -> 0 | CW42: =CI42+CJ42 -> 0
A43: 45734 | B43: ZURU LLC | C43: 美国 | D43: 4500160498 | E43: B0DR3SZ2QP | F43: 4500160498-10 | G43: 77731-S001-NA-MTS | H43: 冰箱迷你球 PVC圆筒两个装 | I43: 9348 | J43: 0 | K43: 12 | L43: =I43/K43 -> 779 | M43: 45777 | N43: 45773 | P43: PASS | R43: 45734 | S43: 无 | T43: 无 | X43: 日期码格式：ZURU INC(BVI) 标准格式 日期：按实际生产日期 Packaging Info: #77731：2PK STD #77711入PVC桶，3L 2PK铜版纸，客版无UPC版本收缩膜跟单提供。收藏指南，说明书均为MA 1L标版。（两个球的配比不能重复）。 Remark: 1.Amazon domestic 订单。出口美国。外箱最长边不能超过25" （超过了，case pack只能为1），不符合要求的大货，一律不接受。 2.无第三方验货/测试要求。 3.日期码使用ZURU标准版本。 4.邮包盒要印刷日期码。 | Y43: Kelly Shen/Mia Pan/P | Z43: 2.72 | AA43: =Z43*I43 -> 25426.56 | AD43: 77731-NA-S001-MTS | AE43: 已入 | AG43: 已完成 | AI43: =6924+2400+24 -> 9348 | AJ43: =AI43-I43 -> 0 | AN43: =I43*2 -> 18696 | AQ43: =I43*2 -> 18696 | AU43: =I43*2 -> 18696 | BB43: =I43/24*2 -> 779 | CR43: =I43 -> 9348 | CS43: =I43 -> 9348 | CT43: =I43 -> 9348 | CU43: =BQ43+BP43+BO43+BN43+BX43+BR43 -> 0 | CV43: =CK43+CL43+CM43+CN43+CO43+CQ43+CP43 -> 0 | CW43: =CI43+CJ43 -> 0
A44: 45723 | B44: B&M RETAIL LIMITED | C44: 英国 | D44: 4500159525 | E44: 客户PO;019235 84/1 | F44: 4500159525-10 | G44: 77711GQ2-S002-INT | H44: 冰箱迷你球pcs25/箱 | I44: 5850 | J44: 0 | K44: 25 | L44: =I44/K44 -> 234 | M44: 45782 | N44: 45778 | P44: PASS | R44: 45727 | S44: 无 | T44: 无 | X44: 日期码格式：ZURU INC(BVI) 标准格式 日期：按实际生产日期 Packaging Info: 标准配比 Remark: 订单对应4个客户PO，请不要混装， 不同PO分开装柜 收缩膜需要加贴UPC条码 *MA UPC版本按工厂现有最新库存即可，订单出英国，请注意检查产品及包装应带UKCA图标，包装显示ZURU UK LTD信息，QC同事请查核，如有问题与跟单确认。 *生产日期按实际（法定工作日），按ZURU标准格式即可 ，但是请知悉包装日期码需要早于或者等于外箱日期码 ，不能晚于外箱日期码 *请注意所有订单都需要经过ZURU QC验货并且通过后方可出货 *条码以订单显示为准 ，请安排生产前先核对 ，有问题请提出。 *所有产品按符合欧洲标准走货，需要是不含微塑料版本 。 *涉及到硼的，如可选择情况下应使用低硼版本 （slime 类别低硼一般低于300ppm)，无选择的应与跟单复核再安排 。 *大货完成后请及时提供shipment images 供客户批复 ，如未提供照片就直接走柜，有问题由工厂负责 。 *最终出货工厂需要按船务要求为集装箱挂网，如不按要求挂网导致罚款由工厂承担 。 | Y44: CORA ZHOU | Z44: 0.95 | AA44: =Z44*I44 -> 5557.5 | AC44: 95034/95086 | AD44: 77711GQ2-S002-INT | AE44: 已入 | AG44: 已完成 | AI44: 5850 | AJ44: =AI44-I44 -> 0 | AO44: =I44 -> 5850 | AT44: =I44 -> 5850 | AV44: =I44 -> 5850 | BB44: =I44/24 -> 243.75 | BP44: =I44/25 -> 234 | CU44: =BQ44+BP44+BO44+BN44+BX44+BR44 -> 234 | CV44: =CK44+CL44+CM44+CN44+CO44+CQ44+CP44 -> 0 | CW44: =CI44+CJ44 -> 0
A45: 45723 | B45: B&M RETAIL LIMITED | C45: 英国 | D45: 4500159525 | E45: 客户PO:019235 87/1 | F45: 4500159525-20 | G45: 77711GQ2-S002-INT | H45: 冰箱迷你球pcs25/箱 | I45: 5850 | J45: 0 | K45: 25 | L45: =I45/K45 -> 234 | M45: 45782 | N45: 45778 | P45: PASS | R45: 45727 | S45: 无 | T45: 无 | X45: 日期码格式：ZURU INC(BVI) 标准格式 日期：按实际生产日期 Packaging Info: 标准配比 Remark: 订单对应4个客户PO，请不要混装， 不同PO分开装柜 收缩膜需要加贴UPC条码 *MA UPC版本按工厂现有最新库存即可，订单出英国，请注意检查产品及包装应带UKCA图标，包装显示ZURU UK LTD信息，QC同事请查核，如有问题与跟单确认。 *生产日期按实际（法定工作日），按ZURU标准格式即可 ，但是请知悉包装日期码需要早于或者等于外箱日期码 ，不能晚于外箱日期码 *请注意所有订单都需要经过ZURU QC验货并且通过后方可出货 *条码以订单显示为准 ，请安排生产前先核对 ，有问题请提出。 *所有产品按符合欧洲标准走货，需要是不含微塑料版本 。 *涉及到硼的，如可选择情况下应使用低硼版本 （slime 类别低硼一般低于300ppm)，无选择的应与跟单复核再安排 。 *大货完成后请及时提供shipment images 供客户批复 ，如未提供照片就直接走柜，有问题由工厂负责 。 *最终出货工厂需要按船务要求为集装箱挂网，如不按要求挂网导致罚款由工厂承担 。 | Y45: CORA ZHOU | Z45: 0.95 | AA45: =Z45*I45 -> 5557.5 | AC45: 95034/95086 | AD45: 77711GQ2-S002-INT | AE45: 已入 | AG45: 已完成 | AI45: 5850 | AJ45: =AI45-I45 -> 0 | AO45: =I45 -> 5850 | AT45: =I45 -> 5850 | AV45: =I45 -> 5850 | BB45: =I45/24 -> 243.75 | BP45: =I45/25 -> 234 | CU45: =BQ45+BP45+BO45+BN45+BX45+BR45 -> 234 | CV45: =CK45+CL45+CM45+CN45+CO45+CQ45+CP45 -> 0 | CW45: =CI45+CJ45 -> 0
A46: 45729 | B46: WM MORRISON SUPERMARKET PLC | C46: 英国 | D46: 4500159818 | E46: 14202268 | F46: 4500159818-10 | G46: 77711GQ1-S003-INT | H46: 冰箱迷你球104pcs/箱（有内箱） | I46: 5200 | J46: 13 | K46: =J46*8 -> 104 | L46: =I46/K46 -> 50 | M46: 45784 | N46: 45780 | P46: PASS | R46: 45740 | S46: 无 | T46: 45730 | X46: 日期码格式：ZURU INC(BVI) 标准格式 日期：按实际生产日期 Packaging Info: 77711GQ1-S003-INT：MA 3L收缩膜+一张UPC条码贴纸（UPC#193052080134）+MA 3L PDQ+其他最新MA包装 Remark: 1）外箱有条码要求，排版时请留意并请确保条码清晰可扫描（封箱胶不要黏到条码上), 否则客人会有罚款。 2) 订单出英国，产品及包装需要印UKCA图标，包装需要有ZURU UK LTD/ZURU France地址信息，QC同事请查核，如有问题与跟单确认。 3) 箱唛日期码与包装保持一致 4) 若外箱重量超过16KGS，请提前告知ZURU跟单，需要客人批准才能出货，并且外箱需要印2 man lift标志 | Y46: Yoga Huang | Z46: 1.16 | AA46: =Z46*I46 -> 6032 | AC46: 95100-8.17 | AD46: 77711GQ1-S003-INT | AE46: 已入 | AG46: 已完成 | AI46: 5200 | AJ46: =AI46-I46 -> 0 | AO46: =I46 -> 5200 | AT46: =I46 -> 5200 | AV46: =I46 -> 5200 | BB46: =I46/24 -> 216.66667 | BM46: =I46/13 -> 400 | CU46: =BQ46+BP46+BO46+BN46+BX46+BR46 -> 0 | CV46: =CK46+CL46+CM46+CN46+CO46+CQ46+CP46 -> 0 | CW46: =CI46+CJ46 -> 0
A47: 45748 | B47: WALMART INC. | C47: 美国 | D47: 4500162160 | E47: 0904512435 STATESBORO | F47: 4500162160-10 | G47: 77711GQ4-S001-NA | H47: 冰箱迷你球16pcs/箱 | I47: 2624 | J47: 0 | K47: 16 | L47: =I47/K47 -> 164 | M47: 45785 | N47: 45781 | O47: 5/9 第三方验货 | P47: PASS | R47: 外箱印刷带条码的RFID箱唛：RFID紫色色带+WM Dept.图标+RFID图标+ITF-14条码，四面右下角印刷ZURU logo, ITFF条码只印刷在正唛一面，在加印的时候确保 条形码能扫描出来，外箱侧面任一角落加印："MADE IN CHINA" 字样； | S47: 无 | T47: 4/11 寄出 | V47: RFID贴纸 | X47: 日期码格式：ZURU DGYYYYMMDD CHINA(日期避开周末和法定节假日即可） 日期：按实际生产日期 Packaging Info: 77711GQ4-S001-NA 1.包装要求： MA 1L A版收缩膜+MA 5L A版收藏指南+MA 说明书+客版1L PDQ，翻单：4500159672 每pcs产品上要贴1张RFID贴纸，贴纸由ZURU提供，贴纸位置请严格按照我们签回的签板； Remark: 77711GQ4-S001-NA 1.包装要求： MA 1L A版收缩膜+MA 5L A版收藏指南+MA 说明书+客版1L PDQ，翻单：4500159672 每pcs产品上要贴1张RFID贴纸，贴纸由ZURU提供，贴纸位置请严格按照我们签回的签板； 2. 外箱印刷带条码的RFID箱唛：RFID紫色色带+WM Dept.图标+RFID图标+ITF-14条码，四面右下角印刷ZURU logo, ITFF条码只印刷在正唛一面，在加印的时候确保 条形码能扫描出来，外箱侧面任一角落加印："MADE IN CHINA" 字样； 3. 在产品上和包装上要有日期码、以及要有MADE IN CHINA和ZURU字样； 4. 产品如有扎带口要剪平，不能刮手。 5. 此单验货，请多备料 6. 此单以loose carton出货，16pcs/PDQ/CTN | Y47: Maggie Xie | Z47: 1.68 | AA47: =Z47*I47 -> 4408.32 | AD47: 77711GQ4-S001-NA | AE47: 已入 | AG47: 已完成 | AI47: 2624 | AJ47: =AI47-I47 -> 0 | AN47: =I47 -> 2624 | AP47: =I47 -> 2624 | AU47: =I47 -> 2624 | BB47: =I47/48 -> 54.666667 | BQ47: =I47/16 -> 164 | CU47: =BQ47+BP47+BO47+BN47+BX47+BR47 -> 164 | CV47: =CK47+CL47+CM47+CN47+CO47+CQ47+CP47 -> 0 | CW47: =CI47+CJ47 -> 0
A48: 45748 | B48: WALMART INC. | C48: 美国 | D48: 4500162160 | E48: 0904512480 SUFFOLK | F48: 4500162160-20 | G48: 77711GQ4-S001-NA | H48: 冰箱迷你球16pcs/箱 | I48: 3520 | J48: 0 | K48: 16 | L48: =I48/K48 -> 220 | M48: 45785 | N48: 45781 | O48: 5/9 第三方验货 | P48: PASS | R48: 外箱印刷带条码的RFID箱唛：RFID紫色色带+WM Dept.图标+RFID图标+ITF-14条码，四面右下角印刷ZURU logo, ITFF条码只印刷在正唛一面，在加印的时候确保 条形码能扫描出来，外箱侧面任一角落加印："MADE IN CHINA" 字样； | S48: 无 | T48: 4/11 寄出 | V48: RFID贴纸 | X48: 日期码格式：ZURU DGYYYYMMDD CHINA(日期避开周末和法定节假日即可） 日期：按实际生产日期 Packaging Info: 77711GQ4-S001-NA 1.包装要求： MA 1L A版收缩膜+MA 5L A版收藏指南+MA 说明书+客版1L PDQ，翻单：4500159672 每pcs产品上要贴1张RFID贴纸，贴纸由ZURU提供，贴纸位置请严格按照我们签回的签板； Remark: 77711GQ4-S001-NA 1.包装要求： MA 1L A版收缩膜+MA 5L A版收藏指南+MA 说明书+客版1L PDQ，翻单：4500159672 每pcs产品上要贴1张RFID贴纸，贴纸由ZURU提供，贴纸位置请严格按照我们签回的签板； 2. 外箱印刷带条码的RFID箱唛：RFID紫色色带+WM Dept.图标+RFID图标+ITF-14条码，四面右下角印刷ZURU logo, ITFF条码只印刷在正唛一面，在加印的时候确保 条形码能扫描出来，外箱侧面任一角落加印："MADE IN CHINA" 字样； 3. 在产品上和包装上要有日期码、以及要有MADE IN CHINA和ZURU字样； 4. 产品如有扎带口要剪平，不能刮手。 5. 此单验货，请多备料 6. 此单以loose carton出货，16pcs/PDQ/CTN | Y48: Maggie Xie | Z48: 1.68 | AA48: =Z48*I48 -> 5913.6 | AD48: 77711GQ4-S001-NA | AE48: 已入 | AG48: 已完成 | AI48: 3520 | AJ48: =AI48-I48 -> 0 | AN48: =I48 -> 3520 | AP48: =I48 -> 3520 | AU48: =I48 -> 3520 | BB48: =I48/48 -> 73.333333 | BQ48: =I48/16 -> 220 | CU48: =BQ48+BP48+BO48+BN48+BX48+BR48 -> 220 | CV48: =CK48+CL48+CM48+CN48+CO48+CQ48+CP48 -> 0 | CW48: =CI48+CJ48 -> 0
A49: 45695 | B49: Smyths Toys HQ UC | C49: 法国 | D49: 4500156860 | E49: 4400464929 | F49: 4500156860-10 | G49: 77711GQ2-S002-INT | H49: 冰箱迷你球pcs25/箱 | I49: 3500 | J49: 0 | K49: 25 | L49: =I49/K49 -> 140 | M49: 45786 | N49: 45782 | P49: PASS | R49: 45696 | S49: 无 | T49: 无 | X49: 日期码格式：ZURU INC(BVI) 标准格式 日期：按实际生产日期 Packaging Info: 77711GQ2：最新MA PDQ(优先3L)+客版收缩膜(英法德callout/英法德意荷警语/法国环保logo) +23L 说明书+ 5+23L警语收藏指南+ MA 5L creative说明书 + crea tive说明书荷兰语贴纸（所有资料翻单#4500155592） Remark: 1. 此单出法国，所有包装都需要含有法语，需要满足Zuru Standard欧洲标准测试要求； 2. 请准时出货，推期会有罚款； 3. 所有出口法国的产品, 法规规定禁止在包装和共公众用的印刷品中使用矿物油中含有的物质, 包装印刷油墨中含有的MOAH/MOSH的质量浓度不能超过1%, 否则出 货到法国被抽检出现问题, 供应商需要对此负责;国被抽检出现问题 ，供应商需要对此负责; | Y49: Ula Zhao | Z49: 1.24 | AA49: =Z49*I49 -> 4340 | AC49: 94994-8.17 | AD49: 77711GQ2-S002-INT-客版Smyths | AE49: 已入 | AG49: 已完成 | AI49: 3500 | AJ49: =AI49-I49 -> 0 | AO49: =I49 -> 3500 | AV49: =I49 -> 3500 | BB49: =I49/48 -> 72.916667 | BE49: =I49 -> 3500 | BP49: =I49/25 -> 140 | CU49: =BQ49+BP49+BO49+BN49+BX49+BR49 -> 140 | CV49: =CK49+CL49+CM49+CN49+CO49+CQ49+CP49 -> 0 | CW49: =CI49+CJ49 -> 0
A50: 45671 | B50: Smyths Toys EU HQ UC | C50: 德国 | D50: 4500155592 | E50: 4400459912 | F50: 4500155592-10 | G50: 77711GQ2-S002-INT | H50: 冰箱迷你球pcs25/箱 | I50: 8000 | J50: 0 | K50: 25 | L50: =I50/K50 -> 320 | M50: 45786 | N50: 45782 | P50: PASS | R50: 45671 | S50: 无 | T50: 无 | X50: 日期码格式：ZURU INC(BVI) 标准格式 日期：按实际生产日期 Packaging Info: 最新MA PDQ(优先3L)+客版收缩膜(英法德callout/英法德意荷警语/法国环保logo) +23L 说明书+ 5+23L警语收藏指南+ MA 5L creative说明书 + creative说明书 荷兰语贴纸 EAN: 4894680043350 Remark: 1. 此单出德国，需要满足Zuru Standard欧洲标准测试要求； 2. 请准时出货，推期会有罚款； 3. 出口欧洲，微塑料需符合法规; 4. 所有电子产品身上需要加字唛，为ZURU FRANCE 地址 (如无电子产品，或者产品布标有此地址，可忽略此信息) ZURU France 1/3, Rue d'Argenteuil 95210 SAINT-GRATIEN, FRANCE 5. 标准配比 | Y50: Shirley Zhou | Z50: 1.24 | AA50: =Z50*I50 -> 9920 | AC50: 95084-8.17 | AD50: 77711GQ2-S002-INT-客版Smyths | AE50: 已入 | AG50: 已完成 | AI50: =7950+50 -> 8000 | AJ50: =AI50-I50 -> 0 | AO50: =I50 -> 8000 | AV50: =I50 -> 8000 | BB50: =I50/48 -> 166.66667 | BE50: =I50 -> 8000 | BP50: =I50/25 -> 320 | CU50: =BQ50+BP50+BO50+BN50+BX50+BR50 -> 320 | CV50: =CK50+CL50+CM50+CN50+CO50+CQ50+CP50 -> 0 | CW50: =CI50+CJ50 -> 0
A51: 45707 | B51: ZURU Germany GMBH | C51: 德国 | D51: 4500157858 | E51: 5200006149 | F51: 4500157858-80 | G51: 77711GQ1-S002-INT-MTS | H51: 冰箱迷你球13pcs/箱 | I51: 5200 | J51: 0 | K51: 13 | L51: =I51/K51 -> 400 | M51: 45786 | N51: 45782 | P51: PASS | R51: 45707 | S51: 无 | T51: 45737 | X51: 日期码格式：ZURU INC(BVI) 标准格式 日期：按实际生产日期 Packaging Info: 77711GQ1：MA_3L_13PCS_A PDQ + MA 3L EAN 收缩膜 +多语折叠警告语贴纸（含环保标） + MA5L收藏指南+ MA 23L说明书+ UV胶黑白警告语 + MA纸袋 EAN #489468 0043350 Remark: "1.德国内销单，需要通过ZURU 验货结果后才能出货 (工厂需要主动提前同ZURU QC预约验货避免延期出货造成不必要麻烦)； 2. 若有特定款有特殊外箱条码要求时,需要明确列出产品款对应的具体外箱条码号码/条码类型 (若无,可以忽略此需求) 3.所有出口欧洲的产品, 法规规定禁止在包装和共公众用的印刷品中使用矿物油中含有的物质, 包装印刷油墨中含有的MOAH/MOSH的质量浓度不能超过1%, 否则出货 到法国被抽检出现问题, 供应商需要对此负责; 4. date code: 外箱日期码要晚于或等于产品日期码，不能早于产品的日期码 5. 所有电子产品身上需要加字唛，为ZURU FRANCE 地址 (如无电子产品，或者产品布标有此地址，可忽略此信息) ZURU France 1/3, Rue d'Argenteuil 95210 SAINT-GRATIEN, FRANCE 6. 装柜时需要按照款式号码从小到大一款款依次装,避免终端仓库卸货混乱.若一个柜子涉及到几个不同国家内销单,装柜时需要一个国家装完后再装另一个国家的 产品,依次装柜,避免终端仓库因不同国家不同库位位置卸货混乱. (此点需要同工厂装柜人员强调)" | Y51: SD82 | Z51: 1.16 | AA51: =Z51*I51 -> 6032 | AC51: 95082-8.17 | AD51: 77711GQ1-S002-INT | AE51: 已入 | AG51: 已完成 | AI51: 5200 | AJ51: =AI51-I51 -> 0 | AO51: =I51 -> 5200 | AT51: =I51 -> 5200 | AV51: =I51 -> 5200 | BB51: =I51/24 -> 216.66667 | BM51: =I51/13 -> 400 | CU51: =BQ51+BP51+BO51+BN51+BX51+BR51 -> 0 | CV51: =CK51+CL51+CM51+CN51+CO51+CQ51+CP51 -> 0 | CW51: =CI51+CJ51 -> 0
A52: 45742 | B52: ASIA GOAL LIMITED TAIWAN BRANCH (H. | C52: 台湾 | D52: 4500161426 | E52: AG240431-TW | F52: 4500161426-10 | G52: 77711GQ1-S001-INT | H52: 冰箱迷你球pcs52/箱 | I52: 1300 | J52: 0 | K52: 52 | L52: =I52/K52 -> 25 | M52: 45792 | N52: 45789 | P52: PASS | R52: 45742 | S52: 无 | T52: 45750 | X52: 日期码格式：ZURU INC(BVI) 标准格式 日期：按实际生产日期 Packaging Info: 77711GQ1 （INT): MA 3L 收缩膜+1张UPC 条码贴纸+ MA 3L PDQ+MA 5L 收藏指南+1张警语贴纸 （贴球底部） Remark: 此单出TW | Y52: Doris Shou | Z52: 0.92 | AA52: =Z52*I52 -> 1196 | AC52: 95068-8.17 | AD52: 77711GQ1-S001-INT | AE52: 已入 | AG52: 已完成 | AI52: 1300 | AJ52: =AI52-I52 -> 0 | AO52: =I52 -> 1300 | AT52: =I52 -> 1300 | AV52: =I52 -> 1300 | BB52: =I52/24 -> 54.166667 | BM52: =I52/13 -> 100 | CU52: =BQ52+BP52+BO52+BN52+BX52+BR52 -> 0 | CV52: =CK52+CL52+CM52+CN52+CO52+CQ52+CP52 -> 0 | CW52: =CI52+CJ52 -> 0
A53: 45709 | B53: TARGET US | C53: 美国 | D53: 4500158149 | E53: 10001245308-3890 | F53: 4500158149-20 | G53: 77711GQ2-S002-NA | H53: 冰箱迷你球 25pcs/箱 | I53: 21900 | J53: 0 | K53: 25 | L53: =I53/K53 -> 876 | M53: 45775 | N53: 45789 | P53: PASS | R53: 45743 | S53: 有 | T53: 45749 | X53: 日期码格式：ZURU INC(BVI) 标准格式 日期：按实际生产日期 Packaging Info: 77711GQ2： 产品包装(UPC版) MA 1L 收缩膜 + MA1L PDQ； Remark: 77711GQ2: 1. 77711GQ2-S002-NA-MINI BRANDS-FILL THE FRIDGE-SERIES 1-CAPSULE,25PCS/Gravity PDQ, 25PCS/PDQ/CTN 2. 产品包装(UPC版) MA 1L 收缩膜 + MA1L PDQ；收缩膜上的UPC显示193052080127； 3. 外箱正唛左上角位置粘贴条码箱贴纸，每箱只贴一张，由ZURU订购。来料贴纸上显示的客户DPCI# 086-02-9357, UPC显示10193052080124; 4. 外箱正唛箱唛内容右侧需贴一张Event label，内容显示Toys Set Date：7/20/2025，工厂自行订购； 此订单所有item： 1. 产品和包装上印刷 tracking code信息，格式为ZURU常规格式; 2. 出货方式：货代自提 | Y53: Holly Zheng | Z53: 1.65 | AA53: =Z53*I53 -> 36135 | AD53: 77711GQ2-S002-NA | AE53: 已入 | AG53: 已完成 | AI53: 21900 | AJ53: =AI53-I53 -> 0 | AN53: =I53 -> 21900 | AP53: =I53 -> 21900 | AU53: =I53 -> 21900 | BB53: =I53/48 -> 456.25 | BN53: =I53/25 -> 876 | CU53: =BQ53+BP53+BO53+BN53+BX53+BR53 -> 876 | CV53: =CK53+CL53+CM53+CN53+CO53+CQ53+CP53 -> 0 | CW53: =CI53+CJ53 -> 0
A54: 45723 | B54: TARGET US | C54: 美国 | D54: 4500159315 | E54: 10001263725-3890 | F54: 4500159315-40 | G54: 77711GQ2-S002-NA | H54: 冰箱迷你球 25pcs/箱 | I54: 20000 | J54: 0 | K54: 25 | L54: =I54/K54 -> 800 | M54: 45775 | N54: 45789 | P54: PASS | R54: 45741 | S54: 有 | T54: 45749 | X54: 日期码格式：ZURU INC(BVI) 标准格式 日期：按实际生产日期 Packaging Info: 77711GQ2：产品包装(UPC版) MA 1L 收缩膜 + MA1L PDQ； Remark: 5. 外箱正唛箱唛左上方位置粘贴条码箱贴纸，每箱贴一张由ZURU 订购，来料显示DPCI:086-02-7025,UPC# 10193052075106 77711GQ2： 1. 77711GQ2-S002-NA-MINI BRANDS-FILL THE FRIDGE-SERIES 1-CAPSULE,25PCS/Gravity PDQ, 25PCS/PDQ/CTN 2. 产品包装(UPC版) MA 1L 收缩膜 + MA1L PDQ；收缩膜上的UPC显示193052080127； 3. 外箱正唛左上角位置粘贴条码箱贴纸，每箱只贴一张，由ZURU订购。来料贴纸上显示的客户DPCI# 086-02-9357, UPC显示10193052080124; 此订单所有item： 1. 产品和包装上印刷 tracking code信息，格式为ZURU常规格式; 2. 出货方式：货代自提 | Y54: Holly Zheng | Z54: 1.65 | AA54: =Z54*I54 -> 33000 | AD54: 77711GQ2-S002-NA | AE54: 已入 | AG54: 已完成 | AI54: 20000 | AJ54: =AI54-I54 -> 0 | AN54: =I54 -> 20000 | AP54: =I54 -> 20000 | AU54: =I54 -> 20000 | BB54: =I54/48 -> 416.66667 | BN54: =I54/25 -> 800 | CU54: =BQ54+BP54+BO54+BN54+BX54+BR54 -> 800 | CV54: =CK54+CL54+CM54+CN54+CO54+CQ54+CP54 -> 0 | CW54: =CI54+CJ54 -> 0
A55: 45727 | B55: TARGET US | C55: 美国 | D55: 4500159604 | E55: 10001232749-3890 | F55: 4500159604-20 | G55: 77711GQ2-S002-NA | H55: 冰箱迷你球 25pcs/箱 | I55: 30150 | J55: 0 | K55: 25 | L55: =I55/K55 -> 1206 | M55: 45777 | N55: 45789 | P55: PASS | R55: 45743 | S55: 有 | T55: 45749 | X55: 日期码格式：ZURU INC(BVI) 标准格式 日期：按实际生产日期 Packaging Info: 77711GQ2： 产品包装(UPC版) MA 1L 收缩膜 + MA1L PDQ； Remark: 77711GQ2: 1. 77711GQ2-S002-NA-MINI BRANDS-FILL THE FRIDGE-SERIES 1-CAPSULE,25PCS/Gravity PDQ, 25PCS/PDQ/CTN 2. 产品包装(UPC版) MA 1L 收缩膜 + MA1L PDQ；收缩膜上的UPC显示193052080127； 3. 外箱正唛左上角位置粘贴条码箱贴纸，每箱只贴一张，由ZURU订购。来料贴纸上显示的客户DPCI# 086-02-9357, UPC显示10193052080124; 此订单所有item： 1. 产品和包装上印刷 tracking code信息，格式为ZURU常规格式; 2. 出货方式：货代自提 | Y55: Holly Zheng | Z55: 1.65 | AA55: =Z55*I55 -> 49747.5 | AD55: 77711GQ2-S002-NA | AE55: 已入 | AG55: 已完成 | AI55: =10650+19500 -> 30150 | AJ55: =AI55-I55 -> 0 | AN55: =I55 -> 30150 | AP55: =I55 -> 30150 | AU55: =I55 -> 30150 | BB55: =I55/48 -> 628.125 | BN55: =I55/25 -> 1206 | CU55: =BQ55+BP55+BO55+BN55+BX55+BR55 -> 1206 | CV55: =CK55+CL55+CM55+CN55+CO55+CQ55+CP55 -> 0 | CW55: =CI55+CJ55 -> 0
A56: 45726 | B56: 360 SALES SOLUTIONS INC | C56: 加拿大 | D56: 4500159666 | E56: 2025ZURU11 | F56: 4500159666-10 | G56: 77711GQ1-S002-NA | H56: 冰箱迷你球13pcs/箱 | I56: 16133 | J56: 0 | K56: 13 | L56: =I56/K56 -> 1241 | M56: 45786 | N56: 45782 | P56: PASS | R56: 45727 | S56: 无 | T56: 无 | X56: 日期码格式： 标准格式 日期：按实际生产日期 Packaging Info: 77711GQ1 MA 多语（含英法）EAN包装+UPC贴纸， UPC号码193052080127 Remark: 出加拿大 Zuru验货.日期跟踪码：产品外包装及产品本身都必须有日期跟踪码，ZURU标准格式日期码。（箱唛日期码按跟单提供格式） | Y56: Summer Mo | Z56: 0.92 | AA56: =Z56*I56 -> 14842.36 | AC56: 95002-8.17 | AD56: 77711GQ1-S002-NA | AE56: 已入 | AG56: 已完成 | AI56: =16120+13 -> 16133 | AJ56: =AI56-I56 -> 0 | AN56: =I56 -> 16133 | AS56: =I56 -> 16133 | AU56: =I56 -> 16133 | BB56: =I56/24 -> 672.20833 | BL56: =I56/13 -> 1241 | CU56: =BQ56+BP56+BO56+BN56+BX56+BR56 -> 0 | CV56: =CK56+CL56+CM56+CN56+CO56+CQ56+CP56 -> 0 | CW56: =CI56+CJ56 -> 0
A57: 45726 | B57: WAL-MART STORES INC. USA | C57: 美国 | D57: 4500159673 | E57: 0902421332 SAVANNAH | F57: 4500159673-10 | G57: 77711GQ4-S001-NA | H57: 冰箱迷你球16pcs/箱 | I57: 12736 | J57: 0 | K57: 16 | L57: =I57/K57 -> 796 | M57: 45789 | N57: 45785 | O57: 5/14 第三方验货 | P57: PASS | R57: 45727 | S57: 有 | T57: RFID+粉色艾利贴纸 | X57: 日期码格式：ZURU DGYYYYMMDD CHINA(日期避开周末和法定节假日即可） 日期：按实际生产日期 Packaging Info: 77711GQ4-S001-NA 1.包装要求： MA 1L A版收缩膜+MA 5L A版收藏指南+MA 说明书+客版1L PDQ 每pcs产品上要贴1张RFID贴纸，贴纸由ZURU提供，贴纸位置请严格按照我们签回的签板； Remark: 77711GQ4-S001-NA 1.包装要求： MA 1L A版收缩膜+MA 5L A版收藏指南+MA 说明书+客版1L PDQ 每pcs产品上要贴1张RFID贴纸，贴纸由ZURU提供，贴纸位置请严格按照我们签回的签板； 2. 外箱印刷带条码的RFID箱唛：RFID紫色色带+WM Dept.图标+RFID图标+ITF-14条码+粉色艾利贴纸（不干胶打印），四面右下角印刷ZURU logo, ITFF条码只印刷在 正唛一面，在加印的时候确保条形码能扫描出来，1张粉红色贴纸贴在正唛对角线，外箱侧面任一角落加印："MADE IN CHINA" 字样； 3. 在产品上和包装上要有日期码、以及要有MADE IN CHINA和ZURU字样； 4. 产品如有扎带口要剪平，不能刮手。 5. 此单需要验货，请多备料 6. 此单以loose carton出货，16pcs/PDQ/CTN | Y57: Maggie Xie | Z57: 1.68 | AA57: =Z57*I57 -> 21396.48 | AD57: 77711GQ4-S001-NA | AE57: 已入 | AG57: 已完成 | AI57: 12736 | AJ57: =AI57-I57 -> 0 | AN57: =I57 -> 12736 | AP57: =I57 -> 12736 | AU57: =I57 -> 12736 | BB57: =I57/48 -> 265.33333 | BQ57: =I57/16 -> 796 | CU57: =BQ57+BP57+BO57+BN57+BX57+BR57 -> 796 | CV57: =CK57+CL57+CM57+CN57+CO57+CQ57+CP57 -> 0 | CW57: =CI57+CJ57 -> 0
A58: 45726 | B58: WAL-MART STORES INC. USA | C58: 美国 | D58: 4500159673 | E58: 0902421357 SUFFOLK | F58: 4500159673-20 | G58: 77711GQ4-S001-NA | H58: 冰箱迷你球16pcs/箱 | I58: 16960 | J58: 0 | K58: 16 | L58: =I58/K58 -> 1060 | M58: 45789 | N58: 45785 | O58: 5/14 第三方验货 | P58: PASS | R58: 45727 | S58: 有 | T58: RFID+粉色艾利贴纸 | X58: 日期码格式：ZURU DGYYYYMMDD CHINA(日期避开周末和法定节假日即可） 日期：按实际生产日期 Packaging Info: 77711GQ4-S001-NA 1.包装要求： MA 1L A版收缩膜+MA 5L A版收藏指南+MA 说明书+客版1L PDQ 每pcs产品上要贴1张RFID贴纸，贴纸由ZURU提供，贴纸位置请严格按照我们签回的签板； Remark: 77711GQ4-S001-NA 1.包装要求： MA 1L A版收缩膜+MA 5L A版收藏指南+MA 说明书+客版1L PDQ 每pcs产品上要贴1张RFID贴纸，贴纸由ZURU提供，贴纸位置请严格按照我们签回的签板； 2. 外箱印刷带条码的RFID箱唛：RFID紫色色带+WM Dept.图标+RFID图标+ITF-14条码+粉色艾利贴纸（不干胶打印），四面右下角印刷ZURU logo, ITFF条码只印刷在 正唛一面，在加印的时候确保条形码能扫描出来，1张粉红色贴纸贴在正唛对角线，外箱侧面任一角落加印："MADE IN CHINA" 字样； 3. 在产品上和包装上要有日期码、以及要有MADE IN CHINA和ZURU字样； 4. 产品如有扎带口要剪平，不能刮手。 5. 此单需要验货，请多备料 6. 此单以loose carton出货，16pcs/PDQ/CTN | Y58: Maggie Xie | Z58: 1.68 | AA58: =Z58*I58 -> 28492.8 | AD58: 77711GQ4-S001-NA | AE58: 已入 | AG58: 预计4/13完成 | AI58: 16960 | AJ58: =AI58-I58 -> 0 | AN58: =I58 -> 16960 | AP58: =I58 -> 16960 | AU58: =I58 -> 16960 | BB58: =I58/48 -> 353.33333 | BQ58: =I58/16 -> 1060 | CU58: =BQ58+BP58+BO58+BN58+BX58+BR58 -> 1060 | CV58: =CK58+CL58+CM58+CN58+CO58+CQ58+CP58 -> 0 | CW58: =CI58+CJ58 -> 0
A59: 45726 | B59: WAL-MART STORES INC. USA | C59: 美国 | D59: 4500159673 | E59: 0902421335 RIDGEVILLE SC | F59: 4500159673-30 | G59: 77711GQ4-S001-NA | H59: 冰箱迷你球16pcs/箱 | I59: 15104 | J59: 0 | K59: 16 | L59: =I59/K59 -> 944 | M59: 45789 | N59: 45785 | O59: 5/14 第三方验货 | P59: PASS | R59: 45727 | S59: 有 | T59: RFID+粉色艾利贴纸 | X59: 日期码格式：ZURU DGYYYYMMDD CHINA(日期避开周末和法定节假日即可） 日期：按实际生产日期 Packaging Info: 77711GQ4-S001-NA 1.包装要求： MA 1L A版收缩膜+MA 5L A版收藏指南+MA 说明书+客版1L PDQ 每pcs产品上要贴1张RFID贴纸，贴纸由ZURU提供，贴纸位置请严格按照我们签回的签板； Remark: 77711GQ4-S001-NA 1.包装要求： MA 1L A版收缩膜+MA 5L A版收藏指南+MA 说明书+客版1L PDQ 每pcs产品上要贴1张RFID贴纸，贴纸由ZURU提供，贴纸位置请严格按照我们签回的签板； 2. 外箱印刷带条码的RFID箱唛：RFID紫色色带+WM Dept.图标+RFID图标+ITF-14条码+粉色艾利贴纸（不干胶打印），四面右下角印刷ZURU logo, ITFF条码只印刷在 正唛一面，在加印的时候确保条形码能扫描出来，1张粉红色贴纸贴在正唛对角线，外箱侧面任一角落加印："MADE IN CHINA" 字样； 3. 在产品上和包装上要有日期码、以及要有MADE IN CHINA和ZURU字样； 4. 产品如有扎带口要剪平，不能刮手。 5. 此单需要验货，请多备料 6. 此单以loose carton出货，16pcs/PDQ/CTN | Y59: Maggie Xie | Z59: 1.68 | AA59: =Z59*I59 -> 25374.72 | AD59: 77711GQ4-S001-NA | AE59: 已入 | AG59: 预计4/13完成 | AI59: 15104 | AJ59: =AI59-I59 -> 0 | AN59: =I59 -> 15104 | AP59: =I59 -> 15104 | AU59: =I59 -> 15104 | BB59: =I59/48 -> 314.66667 | BQ59: =I59/16 -> 944 | CU59: =BQ59+BP59+BO59+BN59+BX59+BR59 -> 944 | CV59: =CK59+CL59+CM59+CN59+CO59+CQ59+CP59 -> 0 | CW59: =CI59+CJ59 -> 0
A60: 45748 | B60: WALMART INC. | C60: 美国 | D60: 4500162161 | E60: 904512396 | F60: 4500162161-10 | G60: 77711GQ4-S001-NA | H60: 冰箱迷你球16pcs/箱 | I60: 4032 | J60: 0 | K60: 16 | L60: =I60/K60 -> 252 | M60: 45789 | N60: 45785 | O60: 5/14 第三方验货 | P60: PASS | R60: 外箱印刷带条码的RFID箱唛：RFID紫色色带+WM Dept.图标+RFID图标+ITF-14条码，四面右下角印刷ZURU logo, ITFF条码只印刷在正唛一面，在加印的时候确保 条形码能扫描出来，外箱侧面任一角落加印："MADE IN CHINA" 字样； | S60: 无 | T60: 4/11 寄出 | V60: RFID贴纸 | X60: 日期码格式：ZURU DGYYYYMMDD CHINA(日期避开周末和法定节假日即可） 日期：按实际生产日期 Packaging Info: 77711GQ4-S001-NA 1.包装要求： MA 1L A版收缩膜+MA 5L A版收藏指南+MA 说明书+客版1L PDQ，翻单：4500159672 每pcs产品上要贴1张RFID贴纸，贴纸由ZURU提供，贴纸位置请严格按照我们签回的签板； Remark: 77711GQ4-S001-NA 1.包装要求： MA 1L A版收缩膜+MA 5L A版收藏指南+MA 说明书+客版1L PDQ，翻单：4500159672 每pcs产品上要贴1张RFID贴纸，贴纸由ZURU提供，贴纸位置请严格按照我们签回的签板； 2. 外箱印刷带条码的RFID箱唛：RFID紫色色带+WM Dept.图标+RFID图标+ITF-14条码，四面右下角印刷ZURU logo, ITFF条码只印刷在正唛一面，在加印的时候确保 条形码能扫描出来，外箱侧面任一角落加印："MADE IN CHINA" 字样； 3. 在产品上和包装上要有日期码、以及要有MADE IN CHINA和ZURU字样； 4. 产品如有扎带口要剪平，不能刮手。 5. 此单验货，请多备料 6. 此单以loose carton出货，16pcs/PDQ/CTN | Y60: Maggie Xie | Z60: 1.68 | AA60: =Z60*I60 -> 6773.76 | AD60: 77711GQ4-S001-NA | AE60: 已入 | AG60: 已完成 | AI60: 4032 | AJ60: =AI60-I60 -> 0 | AN60: =I60 -> 4032 | AP60: =I60 -> 4032 | AU60: =I60 -> 4032 | BB60: =I60/48 -> 84 | BQ60: =I60/16 -> 252 | CU60: =BQ60+BP60+BO60+BN60+BX60+BR60 -> 252 | CV60: =CK60+CL60+CM60+CN60+CO60+CQ60+CP60 -> 0 | CW60: =CI60+CJ60 -> 0
A61: 45748 | B61: T. PLANET SHOPS SL | C61: 西班牙 | D61: 4500162134 | F61: 4500162134-50 | G61: 77711GQ2-S001-INT | H61: 冰箱迷你球50pcs/箱 | I61: 2000 | J61: 0 | K61: 50 | L61: =I61/K61 -> 40 | M61: 45789 | N61: 45785 | O61: 出货前两周需寄2-3套大货样品 | P61: PASS | Q61: 5/16 出货 | R61: 45761 | S61: 无 | T61: 45768 | V61: 客户指定日期码码20250202，包装/产品/外箱需保持一致 | X61: 日期码格式：20250202 日期： Packaging Info: 77711GQ2:MA 3L PDQ+MA A 3L 收缩膜+MA5L收藏指南+进口商贴纸 Remark: 1, 此货出西班牙，需满足EU测试标准要求<(>&<)> 微塑料需符合法规。另外请确保所有包装都有西班牙环保标。 2，出货前两周需寄2-3套大货样品，请多备料 3, 此客人推期有罚款，请按时完货 4, 出货前要验货图片给客人确认OK后才出货 6. 其他款，若产品有比例使用ZURU STD 比例 7，77711GQ2 外箱跟77711SK1 不能用同一个条码， 77711GQ2此款改为4894680053465， 77711SK1外箱条码为4894680053571 8. 客户指定日期码码20250202，包装/产品/外箱需保持一致 | Y61: Mary Zhong | Z61: 0.95 | AA61: =Z61*I61 -> 1900 | AC61: 95140-8.17 | AD61: 77711GQ2-S001-INT | AE61: 已入 | AG61: 已完成 | AI61: 2000 | AJ61: =AI61-I61 -> 0 | AO61: =I61 -> 2000 | AT61: =I61 -> 2000 | AV61: =I61 -> 2000 | BB61: =I61/24 -> 83.333333 | BP61: =I61/25 -> 80 | CU61: =BQ61+BP61+BO61+BN61+BX61+BR61 -> 80 | CV61: =CK61+CL61+CM61+CN61+CO61+CQ61+CP61 -> 0 | CW61: =CI61+CJ61 -> 0
A62: 45755 | B62: ZURU Denmark ApS | C62: 丹麦 | D62: 4500162820 | E62: 5200006528 | F62: 4500162820-10 | G62: 77711GQ1-S002-INT-MTS | H62: 冰箱迷你球13pcs/箱 | I62: 6604 | J62: 0 | K62: 13 | L62: =I62/K62 -> 508 | M62: 45789 | N62: 45785 | P62: PASS | R62: 45757 | S62: 无 | T62: 无 | X62: 日期码格式：ZURU INC(BVI) 标准格式 日期：按实际生产日期 Packaging Info: 77711 MA 3L EAN 版本收缩膜+1*多语警告语贴纸+MA 5L 收藏指南+MA 23L 警告语说明书+MA 5L 装配说明书+MA PDQ （语言不限） Remark: 1.北欧内销单，需要通过ZURU 验货结果后才能出货 (工厂需要主动提前同ZURU QC预约验货避免延期出货造成不必要麻烦)； 2. 产品如含有化学品，需要无硼无香， 3.包装不能含有PVC，使用PET 4. date code: 外箱日期码要晚于产品日期码 5. 装柜时需要按照款式号码从小到大一款款依次装,避免终端仓库卸货混乱.若一个柜子涉及到几个不同国家内销单,装柜时需要一个国家装完后再装另一个国家的 产品,依次装柜,避免终端仓库因不同国家不同库位位置卸货混乱. (此点需要同工厂装柜人员强调)" 6.若有特定款有特殊外箱条码要求时,需要明确列出产品款对应的具体外箱条码号码/条码类型 (若无,可以忽略此需求) 7.所有出口欧洲的产品, 法规规定禁止在包装和共公众用的印刷品中使用矿物油中含有的物质, 包装印刷油墨中含有的MOAH/MOSH的质量浓度不能超过1%, 否则出货 到法国被抽检出现问题, 供应商需要对此负责; 8.带电池出货的产品所用到的电池需要符合欧洲电池新规(EU) 2023-1542。 9.ratio 同MA | Y62: SD04 | Z62: 1.16 | AA62: =Z62*I62 -> 7660.64 | AC62: 94995-8.17 | AD62: 77711GQ1-S002-INT | AE62: 已入 | AG62: 已完成 | AI62: 6604 | AJ62: =AI62-I62 -> 0 | AO62: =I62 -> 6604 | AT62: =I62 -> 6604 | AV62: =I62 -> 6604 | BB62: =I62/24 -> 275.16667 | BM62: =I62/13 -> 508 | CU62: =BQ62+BP62+BO62+BN62+BX62+BR62 -> 0 | CV62: =CK62+CL62+CM62+CN62+CO62+CQ62+CP62 -> 0 | CW62: =CI62+CJ62 -> 0
A63: 45737 | B63: ASIA GOAL LIMITED | C63: 香港 | D63: 4500160943 | E63: AG240427-HK | F63: 4500160943-10 | G63: 77711GQ1-S002-INT | H63: 冰箱迷你球13pcs/箱 | I63: 3016 | J63: 0 | K63: 13 | L63: =I63/K63 -> 232 | M63: 45792 | N63: 45789 | P63: PASS | R63: 45737 | S63: 无 | T63: 4/8寄出 | X63: 日期码格式：ZURU INC(BVI) 标准格式 日期：按实际生产日期 Packaging Info: 77711GQ1 （INT): MA 3L 收缩膜+1张UPC 条码贴纸+ MA 3L PDQ+MA 5L 收藏指南+客供警语贴纸 （1张贴球底部，1张贴说明书，1张贴收藏指南） Remark: 此单出香港 | Y63: Doris Shou | Z63: 0.92 | AA63: =Z63*I63 -> 2774.72 | AC63: 95022-8.17 | AD63: 77711GQ1-S002-INT | AE63: 已入 | AG63: 已完成 | AI63: 3016 | AJ63: =AI63-I63 -> 0 | AO63: =I63 -> 3016 | AT63: =I63 -> 3016 | AV63: =I63 -> 3016 | BB63: =I63/24 -> 125.66667 | BM63: =I63/13 -> 232 | CU63: =BQ63+BP63+BO63+BN63+BX63+BR63 -> 0 | CV63: =CK63+CL63+CM63+CN63+CO63+CQ63+CP63 -> 0 | CW63: =CI63+CJ63 -> 0
A64: 45757 | B64: PPTOYS PTE LTD (SG) | C64: 新加坡 | D64: 4500163177 | E64: ZU25032701SG | F64: 4500163177-10 | G64: 77711GQ1-S001-INT | H64: 冰箱迷你球pcs52/箱 | I64: 2080 | J64: 0 | K64: 52 | L64: =I64/K64 -> 40 | M64: 45792 | N64: 45789 | P64: PASS | R64: 45758 | S64: 无 | T64: 45757 | X64: 日期码格式：ZURU INC(BVI) 标准格式 日期：按实际生产日期 Packaging Info: 1. 77711GQ1因系统问题，暂时开40GP，待系统维护后会改成20GP发过来。 77711GQ1-MA EAN包装（3L)+1张进口商贴纸+1张UPC条码贴纸覆盖原EAN条码，UPC条码贴纸见邮件附件。 77711GQ1进口商贴纸资料待提供。 Remark: | Y64: Emma Wu | Z64: 0.92 | AA64: =Z64*I64 -> 1913.6 | AC64: 95067-8.17 | AD64: 77711GQ1-S001-INT | AE64: 已入 | AG64: 已完成 | AI64: 2080 | AJ64: =AI64-I64 -> 0 | AO64: =I64 -> 2080 | AT64: =I64 -> 2080 | AV64: =I64 -> 2080 | BB64: =I64/24 -> 86.666667 | BM64: =I64/13 -> 160 | CU64: =BQ64+BP64+BO64+BN64+BX64+BR64 -> 0 | CV64: =CK64+CL64+CM64+CN64+CO64+CQ64+CP64 -> 0 | CW64: =CI64+CJ64 -> 0
A65: 45733 | B65: WAL-MART CANADA CORP. | C65: 加拿大 | D65: 4500160504 | E65: 9900923470 | F65: 4500160504-80 | G65: 77711GQ2-S002-NA | H65: 冰箱迷你球 25pcs/箱 | I65: 50 | J65: 0 | K65: 25 | L65: =I65/K65 -> 2 | M65: 45793 | N65: 45789 | O65: 5/19 第三方验货 3. 此单有第三方验货，烦请多备包装物料； 6. #77711需于2025/4/18安排签版, 签样数量：大货样各4PCS+散件3套; 7. #77711 需于2025/4/28安排抽办测试, 抽办数量：大货各4 SETS; | P65: PASS | R65: 45748 | S65: 无 | T65: 45734 | X65: 日期码格式：ZURU INC(BVI) 标准格式 日期：按实际生产日期 Packaging Info: #77711： MA2L,PDQ(NA版,25装)+MA2L收缩膜(NA版,UPC:193052080127)+MA5L收藏指南((NA版)+MA配件袋+MA5L说明书+MA23L警告语说明书 产品配比： 7 Assortment, Polar bear: Penguin: Walrus: Mammoth: Owl: Seal: Snow man=10:10:10:10:10:8:2. Snow man is the rare item. Remark: 1. 此单有箱唛； 2. 9900923470单为ECOM订单，外箱四面须加一张黄色贴纸； 3. 此单有第三方验货，烦请多备包装物料； 6. #77711需于2025/4/18安排签版, 签样数量：大货样各4PCS+齐套散件3套; 9. #77711 需于2025/4/28安排抽办测试, 抽办数量：大货4 pcs+齐套散件4SETS; 11. UPC贴纸：必须在原来错误的条码上用黑色粗头笔涂黑直至不能扫描，再贴上正确的UPC; ********************* a. 请确保产品符合1999年版本的加拿大环境保护法(CEPA)和2012年禁止某些有毒物质法规的要求。该产品不含任何在加拿大禁用的化学物质，包括但不限于有毒物 质清单中列出的化学物质，并且在为加拿大沃尔玛生产产品期间没有使用任何禁用化学物质。 Supplier certify that the products comply with the requirements of Canadian Environmental Protection Act, 1999 (CEPA), Prohibition of Certain To xic Substances Regulations, 2012. The products do not contain any chemicals that are banned in Canada, including but not limited to those listed in the Toxic Substances List and no banned chemicals were used during the manufacturing of product for Walmart Canada. 附件列表： (1) Letter of Guarantee for Canada banned chemicals - (1-5CA) b. 请确保产品在均质材料中的汞浓度不超过0.1%（按重量计）。 Supplier certify that the WAL-MART vendor products does not have a mercury concentration of more than 0.1% by weight in homogeneous material. 附件列表： (1) Letter of Guarantee for Mercury COC c. 请确保产品的塑料材料不含以下物质（SOR 2011-17 27B): Supplier certify that the plastic materials do not contain the following substances(SOR 2011-17 27B): (a) carbon tetrachloride or any substance that contains it; (b) methyl alcohol or any substance thay contains >1.0%; (c) petroleum distillates or any substance that contains >10% weight to volume of petroleum distillates; (d) benzene; (e) turpentine or any substance that contains >10% weight to volume of turpentine; (f) boric acid or salts of boric acid; or (g) ethyl ether. 附件列表： (1) Letter of Guarantee for WM CA-Other prohibited substances in plastic(less than 3 years) | Y65: Monica Zhou | Z65: 0.95 | AA65: =Z65*I65 -> 47.5 | AC65: 95066-8.17 | AD65: 77711GQ2-S002-NA-2L | AE65: 已入 | AG65: 已完成 | AI65: 50 | AJ65: =AI65-I65 -> 0 | AN65: =I65 -> 50 | AS65: =I65 -> 50 | AU65: =I65 -> 50 | BB65: =I65/24 -> 2.0833333 | BO65: =I65/25 -> 2 | CU65: =BQ65+BP65+BO65+BN65+BX65+BR65 -> 2 | CV65: =CK65+CL65+CM65+CN65+CO65+CQ65+CP65 -> 0 | CW65: =CI65+CJ65 -> 0
A66: 45733 | B66: WAL-MART CANADA CORP. | C66: 加拿大 | D66: 4500160504 | E66: 9900924254 | F66: 4500160504-90 | G66: 77711GQ2-S002-NA | H66: 冰箱迷你球 25pcs/箱 | I66: 10075 | J66: 0 | K66: 25 | L66: =I66/K66 -> 403 | M66: 45793 | N66: 45789 | O66: 5/19 第三方验货 3. 此单有第三方验货，烦请多备包装物料； 6. #77711需于2025/4/18安排签版, 签样数量：大货样各4PCS+散件3套; 7. #77711 需于2025/4/28安排抽办测试, 抽办数量：大货各4 SETS; | P66: PASS | R66: 45748 | S66: 无 | T66: 45734 | X66: 日期码格式：ZURU INC(BVI) 标准格式 日期：按实际生产日期 Packaging Info: #77711： MA2L,PDQ(NA版,25装)+MA2L收缩膜(NA版,UPC:193052080127)+MA5L收藏指南((NA版)+MA配件袋+MA5L说明书+MA23L警告语说明书 产品配比： 7 Assortment, Polar bear: Penguin: Walrus: Mammoth: Owl: Seal: Snow man=10:10:10:10:10:8:2. Snow man is the rare item. Remark: 1. 此单有箱唛； 3. 此单有第三方验货，烦请多备包装物料； 6. #77711需于2025/4/18安排签版, 签样数量：大货样各4PCS+齐套散件3套; 9. #77711 需于2025/4/28安排抽办测试, 抽办数量：大货4 pcs+齐套散件4SETS; 11. UPC贴纸：必须在原来错误的条码上用黑色粗头笔涂黑直至不能扫描，再贴上正确的UPC; ********************* a. 请确保产品符合1999年版本的加拿大环境保护法(CEPA)和2012年禁止某些有毒物质法规的要求。该产品不含任何在加拿大禁用的化学物质，包括但不限于有毒物 质清单中列出的化学物质，并且在为加拿大沃尔玛生产产品期间没有使用任何禁用化学物质。 Supplier certify that the products comply with the requirements of Canadian Environmental Protection Act, 1999 (CEPA), Prohibition of Certain To xic Substances Regulations, 2012. The products do not contain any chemicals that are banned in Canada, including but not limited to those listed in the Toxic Substances List and no banned chemicals were used during the manufacturing of product for Walmart Canada. 附件列表： (1) Letter of Guarantee for Canada banned chemicals - (1-5CA) b. 请确保产品在均质材料中的汞浓度不超过0.1%（按重量计）。 Supplier certify that the WAL-MART vendor products does not have a mercury concentration of more than 0.1% by weight in homogeneous material. 附件列表： (1) Letter of Guarantee for Mercury COC c. 请确保产品的塑料材料不含以下物质（SOR 2011-17 27B): Supplier certify that the plastic materials do not contain the following substances(SOR 2011-17 27B): (a) carbon tetrachloride or any substance that contains it; (b) methyl alcohol or any substance thay contains >1.0%; (c) petroleum distillates or any substance that contains >10% weight to volume of petroleum distillates; (d) benzene; (e) turpentine or any substance that contains >10% weight to volume of turpentine; (f) boric acid or salts of boric acid; or (g) ethyl ether. 附件列表： (1) Letter of Guarantee for WM CA-Other prohibited substances in plastic(less than 3 years) | Y66: Monica Zhou | Z66: 0.95 | AA66: =Z66*I66 -> 9571.25 | AC66: 95066/95077 | AD66: 77711GQ2-S002-NA-2L | AE66: 已入 | AG66: 已完成 | AI66: 10075 | AJ66: =AI66-I66 -> 0 | AN66: =I66 -> 10075 | AS66: =I66 -> 10075 | AU66: =I66 -> 10075 | BB66: =I66/24 -> 419.79167 | BO66: =I66/25 -> 403 | CU66: =BQ66+BP66+BO66+BN66+BX66+BR66 -> 403 | CV66: =CK66+CL66+CM66+CN66+CO66+CQ66+CP66 -> 0 | CW66: =CI66+CJ66 -> 0
A67: 45709 | B67: OSIRIS INC | C67: 加拿大 | D67: 4500158159 | E67: 40824 | F67: 4500158159-20 | G67: 77711GQ2-S002-NA | H67: 冰箱迷你球25pcs/箱 | I67: 5000 | J67: 0 | K67: 25 | L67: =I67/K67 -> 200 | M67: 45793 | N67: 45789 | P67: PASS | R67: 45709 | S67: 无 | T67: 无 | X67: 日期码格式： 标准格式 日期：按实际生产日期 Packaging Info: 77711GQ2 MA 多语 UPC版本，193052080127 Remark: 出加拿大 Zuru验货.日期跟踪码：产品外包装及产品本身都必须有日期跟踪码，ZURU标准格式日期码 | Y67: Summer Mo | Z67: 1.65 | AA67: =Z67*I67 -> 8250 | AC67: 95006-8.17 | AD67: 77711GQ2-S002-NA-2L | AE67: 已入 | AG67: 已完成 | AI67: 5000 | AJ67: =AI67-I67 -> 0 | AN67: =I67 -> 5000 | AS67: =I67 -> 5000 | AU67: =I67 -> 5000 | BB67: =I67/24 -> 208.33333 | BO67: =I67/25 -> 200 | CU67: =BQ67+BP67+BO67+BN67+BX67+BR67 -> 200 | CV67: =CK67+CL67+CM67+CN67+CO67+CQ67+CP67 -> 0 | CW67: =CI67+CJ67 -> 0
A68: 45748 | B68: WALMART INC. | C68: 美国 | D68: 4500162162 | E68: 904512416 | F68: 4500162162-10 | G68: 77711GQ4-S001-NA | H68: 冰箱迷你球16pcs/箱 | I68: 4672 | J68: 0 | K68: 16 | L68: =I68/K68 -> 292 | M68: 45793 | N68: 45789 | O68: 5/19 第三方验货 | P68: PASS | R68: 外箱印刷带条码的RFID箱唛：RFID紫色色带+WM Dept.图标+RFID图标+ITF-14条码，四面右下角印刷ZURU logo, ITFF条码只印刷在正唛一面，在加印的时候确保 条形码能扫描出来，外箱侧面任一角落加印："MADE IN CHINA" 字样； | S68: 无 | T68: 4/11 寄出 | V68: RFID贴纸 | X68: 日期码格式：ZURU DGYYYYMMDD CHINA(日期避开周末和法定节假日即可） 日期：按实际生产日期 Packaging Info: 77711GQ4-S001-NA 1.包装要求： MA 1L A版收缩膜+MA 5L A版收藏指南+MA 说明书+客版1L PDQ，翻单：4500159672 每pcs产品上要贴1张RFID贴纸，贴纸由ZURU提供，贴纸位置请严格按照我们签回的签板； Remark: 77711GQ4-S001-NA 1.包装要求： MA 1L A版收缩膜+MA 5L A版收藏指南+MA 说明书+客版1L PDQ，翻单：4500159672 每pcs产品上要贴1张RFID贴纸，贴纸由ZURU提供，贴纸位置请严格按照我们签回的签板； 2. 外箱印刷带条码的RFID箱唛：RFID紫色色带+WM Dept.图标+RFID图标+ITF-14条码，四面右下角印刷ZURU logo, ITFF条码只印刷在正唛一面，在加印的时候确保 条形码能扫描出来，外箱侧面任一角落加印："MADE IN CHINA" 字样； 3. 在产品上和包装上要有日期码、以及要有MADE IN CHINA和ZURU字样； 4. 产品如有扎带口要剪平，不能刮手。 5. 此单验货，请多备料 6. 此单以loose carton出货，16pcs/PDQ/CTN | Y68: Maggie Xie | Z68: 1.68 | AA68: =Z68*I68 -> 7848.96 | AD68: 77711GQ4-S001-NA | AE68: 已入 | AG68: 已完成 | AI68: 4672 | AJ68: =AI68-I68 -> 0 | AN68: =I68 -> 4672 | AP68: =I68 -> 4672 | AU68: =I68 -> 4672 | BB68: =I68/48 -> 97.333333 | BQ68: =I68/16 -> 292 | CU68: =BQ68+BP68+BO68+BN68+BX68+BR68 -> 292 | CV68: =CK68+CL68+CM68+CN68+CO68+CQ68+CP68 -> 0 | CW68: =CI68+CJ68 -> 0
A69: 45723 | B69: B&M RETAIL LIMITED | C69: 英国 | D69: 4500159525 | E69: 客户PO:019235 88/1 | F69: 4500159525-30 | G69: 77711GQ2-S002-INT | H69: 冰箱迷你球pcs25/箱 | I69: 5850 | J69: 0 | K69: 25 | L69: =I69/K69 -> 234 | M69: 45796 | N69: 45792 | P69: PASS | R69: 45727 | S69: 无 | T69: 无 | X69: 日期码格式：ZURU INC(BVI) 标准格式 日期：按实际生产日期 Packaging Info: 标准配比 Remark: 订单对应4个客户PO，请不要混装， 不同PO分开装柜 收缩膜需要加贴UPC条码 *MA UPC版本按工厂现有最新库存即可，订单出英国，请注意检查产品及包装应带UKCA图标，包装显示ZURU UK LTD信息，QC同事请查核，如有问题与跟单确认。 *生产日期按实际（法定工作日），按ZURU标准格式即可 ，但是请知悉包装日期码需要早于或者等于外箱日期码 ，不能晚于外箱日期码 *请注意所有订单都需要经过ZURU QC验货并且通过后方可出货 *条码以订单显示为准 ，请安排生产前先核对 ，有问题请提出。 *所有产品按符合欧洲标准走货，需要是不含微塑料版本 。 *涉及到硼的，如可选择情况下应使用低硼版本 （slime 类别低硼一般低于300ppm)，无选择的应与跟单复核再安排 。 *大货完成后请及时提供shipment images 供客户批复 ，如未提供照片就直接走柜，有问题由工厂负责 。 *最终出货工厂需要按船务要求为集装箱挂网，如不按要求挂网导致罚款由工厂承担 。 | Y69: CORA ZHOU | Z69: 0.95 | AA69: =Z69*I69 -> 5557.5 | AC69: 95034/95086 | AD69: 77711GQ2-S002-INT | AE69: 已入 | AG69: 已完成 | AI69: 5850 | AJ69: =AI69-I69 -> 0 | AO69: =I69 -> 5850 | AT69: =I69 -> 5850 | AV69: =I69 -> 5850 | BB69: =I69/24 -> 243.75 | BP69: =I69/25 -> 234 | CU69: =BQ69+BP69+BO69+BN69+BX69+BR69 -> 234 | CV69: =CK69+CL69+CM69+CN69+CO69+CQ69+CP69 -> 0 | CW69: =CI69+CJ69 -> 0
A70: 45723 | B70: B&M RETAIL LIMITED | C70: 英国 | D70: 4500159525 | E70: 客户PO:019235 89/1 | F70: 4500159525-40 | G70: 77711GQ2-S002-INT | H70: 冰箱迷你球pcs25/箱 | I70: 5850 | J70: 0 | K70: 25 | L70: =I70/K70 -> 234 | M70: 45796 | N70: 45792 | P70: PASS | R70: 45727 | S70: 无 | T70: 无 | X70: 日期码格式：ZURU INC(BVI) 标准格式 日期：按实际生产日期 Packaging Info: 标准配比 Remark: 订单对应4个客户PO，请不要混装， 不同PO分开装柜 收缩膜需要加贴UPC条码 *MA UPC版本按工厂现有最新库存即可，订单出英国，请注意检查产品及包装应带UKCA图标，包装显示ZURU UK LTD信息，QC同事请查核，如有问题与跟单确认。 *生产日期按实际（法定工作日），按ZURU标准格式即可 ，但是请知悉包装日期码需要早于或者等于外箱日期码 ，不能晚于外箱日期码 *请注意所有订单都需要经过ZURU QC验货并且通过后方可出货 *条码以订单显示为准 ，请安排生产前先核对 ，有问题请提出。 *所有产品按符合欧洲标准走货，需要是不含微塑料版本 。 *涉及到硼的，如可选择情况下应使用低硼版本 （slime 类别低硼一般低于300ppm)，无选择的应与跟单复核再安排 。 *大货完成后请及时提供shipment images 供客户批复 ，如未提供照片就直接走柜，有问题由工厂负责 。 *最终出货工厂需要按船务要求为集装箱挂网，如不按要求挂网导致罚款由工厂承担 。 | Y70: CORA ZHOU | Z70: 0.95 | AA70: =Z70*I70 -> 5557.5 | AC70: 95034/95086 | AD70: 77711GQ2-S002-INT | AE70: 已入 | AG70: 已完成 | AI70: 5850 | AJ70: =AI70-I70 -> 0 | AO70: =I70 -> 5850 | AT70: =I70 -> 5850 | AV70: =I70 -> 5850 | BB70: =I70/24 -> 243.75 | BP70: =I70/25 -> 234 | CU70: =BQ70+BP70+BO70+BN70+BX70+BR70 -> 234 | CV70: =CK70+CL70+CM70+CN70+CO70+CQ70+CP70 -> 0 | CW70: =CI70+CJ70 -> 0
A71: 45754 | B71: KMART AUSTRALIA LTD | C71: 澳大利亚 | D71: 4500162690 | E71: 20756003 | F71: 4500162690-10 | G71: 77711GQ1-S002-INT | H71: 冰箱迷你球13pcs/箱 | I71: 2106 | J71: 0 | K71: 13 | L71: =I71/K71 -> 162 | M71: 45796 | N71: 45792 | P71: PASS | R71: 45764 | S71: 有 | T71: 两款贴纸以及防盗贴纸位置图翻单PO#4500160026 | X71: 日期码格式：ZURU INC(BVI) 标准格式 日期：按实际生产日期 Packaging Info: 77711GQ1-S002-INT: MA 3L包装（MA收缩膜和说明书） + 一张UPC条码贴+ 防盗贴纸（两款贴纸以及防盗贴纸位置图翻单PO#4500160026）+ 箱唛 + 外箱贴纸SSCC L abel Remark: 1.请务必按时完货，验货。并且按期送货入货代指定仓库，如果晚了导致船期Delay将会有罚金产生或者客户要求空运，所产生的罚金和空运费由工厂承担。 2.SSCC 外箱贴纸请同纸箱瓦楞纸方向（竖纹向）垂直，即外箱贴纸横着贴(注意条码不要被胶带粘住），贴1pc，贴1面正唛，封箱胶纸不能挡住贴纸内容。外箱贴纸 离外箱边距离不少于2cm。 3.外箱材质为ZURU标准； 4.此单需使用KMART封箱胶上下工字型封箱;从2019年6月开始，要用KMART 新版封箱胶带，此单要用"ANKO"封箱胶带 5.此单出口澳大利亚，请按相应的澳新标准生产； 6.产品和包装上生产批号的显示格式ZURU标准日期码格式 7.外箱信息不可手写，重量和体积需要与实际的一致(不可手写） 8. 每款item装箱后的G.W.超过10KG或者CBM超过0.13,(9.5KG或者以上，四舍五入后也属于10KG) 需在外箱上加印超 重或者Bulky LOGO，若发现我们资料没有，请 帮忙提醒 1)重量超过10kg但不超过16kg且CBM不超过0.13,10-16kg 超重logo 2）CBM超过0.13且重量少于17kg，bulky logo 3）不属于以上两种情况，需要使用相应重量范围内的超重logo 4）超重logo需要在外箱四面都印刷(箱唛右上角，两面侧唛超重logo需要尽量靠近毛重)，尺寸为:110mm height* 95mm width 9. 实际外箱重量跟印在箱唛上的数据差异不能超3%，尺寸按实际数据印刷 | Y71: Lydia Wu | Z71: 0.95 | AA71: =Z71*I71 -> 2000.7 | AC71: 95039-8.17 | AD71: 77711GQ1-S002-INT | AE71: 已入 | AG71: 已完成 | AI71: 2106 | AJ71: =AI71-I71 -> 0 | AO71: =I71 -> 2106 | AT71: =I71 -> 2106 | AV71: =I71 -> 2106 | BB71: =I71/24 -> 87.75 | BM71: =I71/13 -> 162 | CU71: =BQ71+BP71+BO71+BN71+BX71+BR71 -> 0 | CV71: =CK71+CL71+CM71+CN71+CO71+CQ71+CP71 -> 0 | CW71: =CI71+CJ71 -> 0
A72: 45763 | B72: ZURU Denmark ApS | C72: 丹麦 | D72: 4500163403 | E72: 5200006595 | F72: 4500163403-20 | G72: 77711GQ1-S002-INT-MTS | H72: 冰箱迷你球13pcs/箱 | I72: 260 | J72: 0 | K72: 13 | L72: =I72/K72 -> 20 | M72: 45796 | N72: 45792 | P72: PASS | R72: 45757 | S72: 无 | T72: 多语折叠警语贴纸（翻单4500162820） | X72: 日期码格式：ZURU INC(BVI) 标准格式 日期：按实际生产日期 Packaging Info: 2. 77711GQ1：MA 3L A版PDQ + 3L EAN B版收缩膜 +1*多语折叠警语贴纸（翻单4500162820） + MA 5L A版收藏指南 +MA 23L 说明书 +MA 5L creative说明书 EAN#4894680043350； Remark: 1.北欧内销单，需要通过ZURU 验货结果后才能出货 (工厂需要主动提前同ZURU QC预约验货避免延期出货造成不必要麻烦)； 2. 产品如含有化学品，需要无硼无香， 3.包装不能含有PVC，使用PET 4. date code: 外箱日期码要晚于产品日期码 5. 装柜时需要按照款式号码从小到大一款款依次装,避免终端仓库卸货混乱.若一个柜子涉及到几个不同国家内销单,装柜时需要一个国家装完后再装另一个国家的 产品,依次装柜,避免终端仓库因不同国家不同库位位置卸货混乱. (此点需要同工厂装柜人员强调)" 6.若有特定款有特殊外箱条码要求时,需要明确列出产品款对应的具体外箱条码号码/条码类型 (若无,可以忽略此需求) 7.所有出口欧洲的产品, 法规规定禁止在包装和共公众用的印刷品中使用矿物油中含有的物质, 包装印刷油墨中含有的MOAH/MOSH的质量浓度不能超过1%, 否则出货 到法国被抽检出现问题, 供应商需要对此负责; 8.带电池出货的产品所用到的电池需要符合欧洲电池新规(EU) 2023-1542。 9.ratio 同MA | Y72: AMY XIAO | Z72: 1.16 | AA72: =Z72*I72 -> 301.6 | AC72: 95028-8.17 | AD72: 77711GQ1-S002-INT | AE72: 已入 | AG72: 已完成 | AI72: 260 | AJ72: =AI72-I72 -> 0 | AO72: =I72 -> 260 | AT72: =I72 -> 260 | AV72: =I72 -> 260 | BB72: =I72/24 -> 10.833333 | BM72: =I72/13 -> 20 | CU72: =BQ72+BP72+BO72+BN72+BX72+BR72 -> 0 | CV72: =CK72+CL72+CM72+CN72+CO72+CQ72+CP72 -> 0 | CW72: =CI72+CJ72 -> 0
A73: 45748 | B73: WALMART INC. | C73: 美国 | D73: 4500162168 | E73: 0904512442 EASTVALE | F73: 4500162168-10 | G73: 77711GQ4-S001-NA | H73: 冰箱迷你球16pcs/箱 | I73: 3296 | J73: 0 | K73: 16 | L73: =I73/K73 -> 206 | M73: 45797 | N73: 45793 | O73: 5/22 第三方验货 | P73: PASS | R73: 外箱印刷带条码的RFID箱唛：RFID紫色色带+WM Dept.图标+RFID图标+ITF-14条码，四面右下角印刷ZURU logo, ITFF条码只印刷在正唛一面，在加印的时候确保 条形码能扫描出来，外箱侧面任一角落加印："MADE IN CHINA" 字样； | S73: 无 | T73: 4/11 寄出 | V73: RFID贴纸 | X73: 日期码格式：ZURU DGYYYYMMDD CHINA(日期避开周末和法定节假日即可） 日期：按实际生产日期 Packaging Info: 77711GQ4-S001-NA 1.包装要求： MA 1L A版收缩膜+MA 5L A版收藏指南+MA 说明书+客版1L PDQ，翻单：4500159672 每pcs产品上要贴1张RFID贴纸，贴纸由ZURU提供，贴纸位置请严格按照我们签回的签板； Remark: 77711GQ4-S001-NA 1.包装要求： MA 1L A版收缩膜+MA 5L A版收藏指南+MA 说明书+客版1L PDQ，翻单：4500159672 每pcs产品上要贴1张RFID贴纸，贴纸由ZURU提供，贴纸位置请严格按照我们签回的签板； 2. 外箱印刷带条码的RFID箱唛：RFID紫色色带+WM Dept.图标+RFID图标+ITF-14条码，四面右下角印刷ZURU logo, ITFF条码只印刷在正唛一面，在加印的时候确保 条形码能扫描出来，外箱侧面任一角落加印："MADE IN CHINA" 字样； 3. 在产品上和包装上要有日期码、以及要有MADE IN CHINA和ZURU字样； 4. 产品如有扎带口要剪平，不能刮手。 5. 此单验货，请多备料 6. 此单以loose carton出货，16pcs/PDQ/CTN | Y73: Maggie Xie | Z73: 1.68 | AA73: =Z73*I73 -> 5537.28 | AD73: 77711GQ4-S001-NA | AE73: 已入 | AG73: 已完成 | AI73: 3296 | AJ73: =AI73-I73 -> 0 | AN73: =I73 -> 3296 | AP73: =I73 -> 3296 | AU73: =I73 -> 3296 | BB73: =I73/48 -> 68.666667 | BQ73: =I73/16 -> 206 | CU73: =BQ73+BP73+BO73+BN73+BX73+BR73 -> 206 | CV73: =CK73+CL73+CM73+CN73+CO73+CQ73+CP73 -> 0 | CW73: =CI73+CJ73 -> 0
A74: 45748 | B74: WALMART INC. | C74: 美国 | D74: 4500162168 | E74: 0904512293 STATESBORO | F74: 4500162168-30 | G74: 77711GQ4-S001-NA | H74: 冰箱迷你球16pcs/箱 | I74: 3184 | J74: 0 | K74: 16 | L74: =I74/K74 -> 199 | M74: 45797 | N74: 45793 | O74: 5/22 第三方验货 | P74: PASS | R74: 外箱印刷带条码的RFID箱唛：RFID紫色色带+WM Dept.图标+RFID图标+ITF-14条码，四面右下角印刷ZURU logo, ITFF条码只印刷在正唛一面，在加印的时候确保 条形码能扫描出来，外箱侧面任一角落加印："MADE IN CHINA" 字样； | S74: 无 | T74: 4/11 寄出 | V74: RFID贴纸 | X74: 日期码格式：ZURU DGYYYYMMDD CHINA(日期避开周末和法定节假日即可） 日期：按实际生产日期 Packaging Info: 77711GQ4-S001-NA 1.包装要求： MA 1L A版收缩膜+MA 5L A版收藏指南+MA 说明书+客版1L PDQ，翻单：4500159672 每pcs产品上要贴1张RFID贴纸，贴纸由ZURU提供，贴纸位置请严格按照我们签回的签板； Remark: 77711GQ4-S001-NA 1.包装要求： MA 1L A版收缩膜+MA 5L A版收藏指南+MA 说明书+客版1L PDQ，翻单：4500159672 每pcs产品上要贴1张RFID贴纸，贴纸由ZURU提供，贴纸位置请严格按照我们签回的签板； 2. 外箱印刷带条码的RFID箱唛：RFID紫色色带+WM Dept.图标+RFID图标+ITF-14条码，四面右下角印刷ZURU logo, ITFF条码只印刷在正唛一面，在加印的时候确保 条形码能扫描出来，外箱侧面任一角落加印："MADE IN CHINA" 字样； 3. 在产品上和包装上要有日期码、以及要有MADE IN CHINA和ZURU字样； 4. 产品如有扎带口要剪平，不能刮手。 5. 此单验货，请多备料 6. 此单以loose carton出货，16pcs/PDQ/CTN | Y74: Maggie Xie | Z74: 1.68 | AA74: =Z74*I74 -> 5349.12 | AD74: 77711GQ4-S001-NA | AE74: 已入 | AG74: 已完成 | AI74: 3184 | AJ74: =AI74-I74 -> 0 | AN74: =I74 -> 3184 | AP74: =I74 -> 3184 | AU74: =I74 -> 3184 | BB74: =I74/48 -> 66.333333 | BQ74: =I74/16 -> 199 | CU74: =BQ74+BP74+BO74+BN74+BX74+BR74 -> 199 | CV74: =CK74+CL74+CM74+CN74+CO74+CQ74+CP74 -> 0 | CW74: =CI74+CJ74 -> 0
A75: 45748 | B75: WALMART INC. | C75: 美国 | D75: 4500162168 | E75: 0904512275 SUFFOLK | F75: 4500162168-40 | G75: 77711GQ4-S001-NA | H75: 冰箱迷你球16pcs/箱 | I75: 4240 | J75: 0 | K75: 16 | L75: =I75/K75 -> 265 | M75: 45797 | N75: 45793 | O75: 5/22 第三方验货 | P75: PASS | R75: 外箱印刷带条码的RFID箱唛：RFID紫色色带+WM Dept.图标+RFID图标+ITF-14条码，四面右下角印刷ZURU logo, ITFF条码只印刷在正唛一面，在加印的时候确保 条形码能扫描出来，外箱侧面任一角落加印："MADE IN CHINA" 字样； | S75: 无 | T75: 4/11 寄出 | V75: RFID贴纸 | X75: 日期码格式：ZURU DGYYYYMMDD CHINA(日期避开周末和法定节假日即可） 日期：按实际生产日期 Packaging Info: 77711GQ4-S001-NA 1.包装要求： MA 1L A版收缩膜+MA 5L A版收藏指南+MA 说明书+客版1L PDQ，翻单：4500159672 每pcs产品上要贴1张RFID贴纸，贴纸由ZURU提供，贴纸位置请严格按照我们签回的签板； Remark: 77711GQ4-S001-NA 1.包装要求： MA 1L A版收缩膜+MA 5L A版收藏指南+MA 说明书+客版1L PDQ，翻单：4500159672 每pcs产品上要贴1张RFID贴纸，贴纸由ZURU提供，贴纸位置请严格按照我们签回的签板； 2. 外箱印刷带条码的RFID箱唛：RFID紫色色带+WM Dept.图标+RFID图标+ITF-14条码，四面右下角印刷ZURU logo, ITFF条码只印刷在正唛一面，在加印的时候确保 条形码能扫描出来，外箱侧面任一角落加印："MADE IN CHINA" 字样； 3. 在产品上和包装上要有日期码、以及要有MADE IN CHINA和ZURU字样； 4. 产品如有扎带口要剪平，不能刮手。 5. 此单验货，请多备料 6. 此单以loose carton出货，16pcs/PDQ/CTN | Y75: Maggie Xie | Z75: 1.68 | AA75: =Z75*I75 -> 7123.2 | AC75: ZB00387-6.2 | AD75: 77711GQ4-S001-NA | AE75: 已入 | AG75: 已完成 | AI75: 4240 | AJ75: =AI75-I75 -> 0 | AN75: =I75 -> 4240 | AP75: =I75 -> 4240 | AU75: =I75 -> 4240 | BB75: =I75/48 -> 88.333333 | BQ75: =I75/16 -> 265 | CU75: =BQ75+BP75+BO75+BN75+BX75+BR75 -> 265 | CV75: =CK75+CL75+CM75+CN75+CO75+CQ75+CP75 -> 0 | CW75: =CI75+CJ75 -> 0
A76: 45749 | B76: Outlet Drift AS | C76: 挪威 | D76: 4500162375 | E76: 20106 | F76: 4500162375-30 | G76: 77711GQ2-S002-INT | H76: 冰箱迷你球pcs25/箱 | I76: 475 | J76: 0 | K76: 25 | L76: =I76/K76 -> 19 | M76: 45797 | N76: 45793 | P76: PASS | R76: 45750 | S76: 无 | T76: 45765 | X76: 日期码格式：ZURU INC(BVI) 标准格式 日期：按实际生产日期 Packaging Info: 77711GQ2: 收缩膜MA EAN 3L A+收藏指南5L A+使用说明23L+1张警示语贴纸 2/产品和包装要求无硼无香，包装不能含有PVC 3/如有微塑料，必须合规欧洲标准，闪粉也是微塑料的一种，目前仅接受三张方式1.去除，2.用可降解材料，和3.永久封印在固体。 4/带电池出货的产品，所用到的电池需要符合欧洲电池新规(EU)2023-1542 | Y76: Zoe Zhou | Z76: 0.95 | AA76: =Z76*I76 -> 451.25 | AC76: 95040-8.17 | AD76: 77711GQ2-S002-INT | AE76: 已入 | AG76: 已完成 | AI76: 475 | AJ76: =AI76-I76 -> 0 | AO76: =I76 -> 475 | AT76: =I76 -> 475 | AV76: =I76 -> 475 | BB76: =I76/24 -> 19.791667 | BP76: =I76/25 -> 19 | CU76: =BQ76+BP76+BO76+BN76+BX76+BR76 -> 19 | CV76: =CK76+CL76+CM76+CN76+CO76+CQ76+CP76 -> 0 | CW76: =CI76+CJ76 -> 0
A77: 45748 | B77: T. PLANET SHOPS SL | C77: 西班牙 | D77: 4500162134 | F77: 4500162134-60 | G77: 77711SK1-S002-INT | H77: 冰箱迷你球展示架（带底座） | I77: 3000 | J77: 0 | K77: 30 | L77: =I77/K77 -> 100 | M77: 45789 | N77: 45785 | O77: 出货前两周需寄2-3套大货样品 | P77: PASS | Q77: 5/16 出货 | R77: 45761 | S77: 无 | T77: 45768 | V77: 客户指定日期码码20250202，包装/产品/外箱需保持一致 | X77: 日期码格式：20250202 日期： Packaging Info: 77711SK1:MA 3L 展示架+MA A 3L 收缩膜+MA5L收藏指南+进口商贴纸 Remark: 1, 此货出西班牙，需满足EU测试标准要求<(>&<)> 微塑料需符合法规。另外请确保所有包装都有西班牙环保标。 2，出货前两周需寄2-3套大货样品，请多备料 3, 此客人推期有罚款，请按时完货 4, 出货前要验货图片给客人确认OK后才出货 另外，15701 <(>&<)> 15727 <(>&<)> 15726 按MA配比 6. 其他款，若产品有比例使用ZURU STD 比例 7，77711GQ2 外箱跟77711SK1 不能用同一个条码， 77711GQ2此款改为4894680053465， 77711SK1外箱条码为4894680053571 8. 客户指定日期码码20250202，包装/产品/外箱需保持一致 | Y77: Mary Zhong | Z77: 35.1 | AA77: =Z77*L77 -> 3510 | AC77: 95140-8.17 | AD77: 77711SK1-S002-INT | AE77: 已入 | AG77: 已完成 | AI77: 3000 | AJ77: =AI77-I77 -> 0 | AO77: =I77 -> 3000 | AT77: =I77 -> 3000 | AV77: =I77 -> 3000 | BB77: =I77/24 -> 125 | CP77: =I77/30 -> 100 | CU77: =BQ77+BP77+BO77+BN77+BX77+BR77 -> 0 | CV77: =CK77+CL77+CM77+CN77+CO77+CQ77+CP77 -> 100 | CW77: =CI77+CJ77 -> 0
A78: 45747 | B78: THE WAREHOUSE LIMITED | C78: 新西兰 | D78: 4500162027 | E78: 29036564 | F78: 4500162027-10 | G78: 77711SK-S002-INT | H78: 冰箱迷你球展示架（带底座） | I78: 1140 | J78: 0 | K78: 60 | L78: =I78/K78 -> 19 | M78: 45796 | N78: 45792 | P78: PASS | R78: 45749 | S78: 无 | T78: 无 | X78: 日期码格式：ZURU INC(BVI) 标准格式 日期：按实际生产日期 Packaging Info: 77711：Refer Packing Ratio Remark: MA UPC 英语包装（优先1L英语版本，或者3L/5L含英语都可） 要加UPC贴纸 此客人不接受易掉落或者剥落或者可直接触碰的闪粉，可降解也不行，但可以接受符合欧洲微塑料标准的珠光粉或者闪片。 | Y78: Abby Liang | Z78: 63.7 | AA78: =Z78*L78 -> 1210.3 | AC78: 95080-8.17 | AD78: 77711SK-S002-INT | AE78: 已入 | AG78: 已完成 | AI78: 1140 | AJ78: =AI78-I78 -> 0 | AO78: =I78 -> 1140 | AT78: =I78 -> 1140 | AV78: =I78 -> 1140 | BB78: =I78/24 -> 47.5 | CM78: =I78/60 -> 19 | CU78: =BQ78+BP78+BO78+BN78+BX78+BR78 -> 0 | CV78: =CK78+CL78+CM78+CN78+CO78+CQ78+CP78 -> 19 | CW78: =CI78+CJ78 -> 0
A79: 45747 | B79: THE WAREHOUSE LIMITED | C79: 新西兰 | D79: 4500162028 | E79: 29036565 | F79: 4500162028-10 | G79: 77711SK-S002-INT | H79: 冰箱迷你球展示架（带底座） | I79: 360 | J79: 0 | K79: 60 | L79: =I79/K79 -> 6 | M79: 45796 | N79: 45792 | P79: PASS | R79: 45749 | S79: 无 | T79: 无 | X79: 日期码格式：ZURU INC(BVI) 标准格式 日期：按实际生产日期 Packaging Info: 77711：Refer Packing Ratio Remark: MA UPC 英语包装（优先1L英语版本，或者3L/5L含英语都可） 要加UPC贴纸 此客人不接受易掉落或者剥落或者可直接触碰的闪粉，可降解也不行，但可以接受符合欧洲微塑料标准的珠光粉或者闪片。 | Y79: Abby Liang | Z79: 63.7 | AA79: =Z79*L79 -> 382.2 | AC79: 95079-8.17 | AD79: 77711SK-S002-INT | AE79: 已入 | AG79: 已完成 | AI79: 360 | AJ79: =AI79-I79 -> 0 | AO79: =I79 -> 360 | AT79: =I79 -> 360 | AV79: =I79 -> 360 | BB79: =I79/24 -> 15 | CM79: =I79/60 -> 6 | CU79: =BQ79+BP79+BO79+BN79+BX79+BR79 -> 0 | CV79: =CK79+CL79+CM79+CN79+CO79+CQ79+CP79 -> 6 | CW79: =CI79+CJ79 -> 0
A80: 45758 | B80: American Eagle | C80: 美国 | D80: 4500163327 | E80: Customer PO# 1247640 | F80: 4500163327-10 | G80: 77711-S001-NA | H80: 冰箱迷你球24pcs/箱 | I80: 1512 | J80: 0 | K80: 24 | L80: =I80/K80 -> 63 | M80: 45796 | N80: 45792 | P80: PASS | R80: 45769 | S80: 有 | T80: 45769 | X80: 日期码格式：ZURU INC(BVI) 标准格式 日期：按实际生产日期 Packaging Info: MA 1L UPC 包装+客供价格贴+外箱贴（跟单提供资料，工厂自行安排） Remark: 1. MA 1L UPC 包装+客供价格贴+外箱贴（跟单提供资料，工厂自行安排） 2. 产品和包装上印刷tracking code信息，格式为ZURU常规 3. 箱子最小的尺寸要求： 30.48 x 22.86 x 10.16cm, 最大的尺寸为 66. 04 X 45.72 X 43.18cm, 外箱的高不能大于宽，否则会有罚款，如外箱达不到要求请告知 跟单，需要调整。 4. 外箱贴纸尺寸4x6英寸，贴纸居中贴在侧面，且距离外箱底部1.5英寸，外箱胶纸不可以覆盖住贴纸上的条形码，不可以有褶皱/刮花导致扫描不出信息，否则会 有罚款. 5. 需ZURU QC 验货合格后方可出货 6. 价格贴的位置为球的顶部或者底部的空白处，不可以覆盖住重要文字以及图案. | Y80: Iris Yuan | Z80: 1 | AA80: =Z80*I80 -> 1512 | AD80: 77711-S001（北美） | AE80: 已入 | AG80: 已完成 | AI80: 1512 | AJ80: =AI80-I80 -> 0 | AN80: =I80 -> 1512 | AP80: =I80 -> 1512 | AU80: =I80 -> 1512 | BB80: =I80/48 -> 31.5 | CU80: =BQ80+BP80+BO80+BN80+BX80+BR80 -> 0 | CV80: =CK80+CL80+CM80+CN80+CO80+CQ80+CP80 -> 0 | CW80: =CI80+CJ80 -> 0
A81: 45758 | B81: TOYS "R" US (CANADA) LTD. | C81: 加拿大 | D81: 4500163438 | E81: 3501527805 | F81: 4500163438-30 | G81: 77711GQ2-S002-NA | H81: 冰箱迷你球25pcs/箱 | I81: 2200 | J81: 0 | K81: 25 | L81: =I81/K81 -> 88 | M81: 45796 | N81: 45792 | O81: 需要第三方SGS验货，验货时间2025/05/19，每款每色请备1PC完整带包装样品供验货人员参考。用完后若无损坏可以放回大货里。 | P81: PASS | R81: 45764 | S81: 无 | T81: 45764 | X81: 日期码格式：ZURU INC(BVI) 标准格式 日期：按实际生产日期 Packaging Info: 1. 出口加拿大市场，MA UPC版本包装。 #77711GQ2: MA 2L UPC版本； 2. 产品、包装、外箱上面tracking code的时间格式需要一致 Remark: 3. 需要第三方SGS验货，验货时间2025/05/19，每款每色请备1PC完整带包装样品供验货人员参考。用完后若无损坏可以放回大货里。 | Y81: Abby Mai,Lluvia Zeng | Z81: 0.95 | AA81: =Z81*I81 -> 2090 | AC81: 95233-8.17 | AD81: 77711GQ2-S002-NA-2L | AE81: 已入 | AG81: 已完成 | AI81: 2200 | AJ81: =AI81-I81 -> 0 | AN81: =I81 -> 2200 | AS81: =I81 -> 2200 | AU81: =I81 -> 2200 | BB81: =I81/24 -> 91.666667 | BO81: =I81/25 -> 88 | CU81: =BQ81+BP81+BO81+BN81+BX81+BR81 -> 88 | CV81: =CK81+CL81+CM81+CN81+CO81+CQ81+CP81 -> 0 | CW81: =CI81+CJ81 -> 0
A82: 45726 | B82: WAL-MART STORES INC. USA | C82: 美国 | D82: 4500159675 | E82: 0902421336 HOUSTON | F82: 4500159675-10 | G82: 77711GQ4-S001-NA | H82: 冰箱迷你球16pcs/箱 | I82: 22656 | J82: 0 | K82: 16 | L82: =I82/K82 -> 1416 | M82: 45797 | N82: 45793 | O82: 5/22 第三方验货 | P82: PASS | R82: 45727 | S82: 有 | T82: RFID+粉色艾利贴纸 | X82: 日期码格式：ZURU DGYYYYMMDD CHINA(日期避开周末和法定节假日即可） 日期：按实际生产日期 Packaging Info: 77711GQ4-S001-NA 1.包装要求： MA 1L A版收缩膜+MA 5L A版收藏指南+MA 说明书+客版1L PDQ 每pcs产品上要贴1张RFID贴纸，贴纸由ZURU提供，贴纸位置请严格按照我们签回的签板； Remark: 77711GQ4-S001-NA 1.包装要求： MA 1L A版收缩膜+MA 5L A版收藏指南+MA 说明书+客版1L PDQ 每pcs产品上要贴1张RFID贴纸，贴纸由ZURU提供，贴纸位置请严格按照我们签回的签板； 2. 外箱印刷带条码的RFID箱唛：RFID紫色色带+WM Dept.图标+RFID图标+ITF-14条码+粉色艾利贴纸（不干胶打印），四面右下角印刷ZURU logo, ITFF条码只印刷在 正唛一面，在加印的时候确保条形码能扫描出来，1张粉红色贴纸贴在正唛对角线，外箱侧面任一角落加印："MADE IN CHINA" 字样； 3. 在产品上和包装上要有日期码、以及要有MADE IN CHINA和ZURU字样； 4. 产品如有扎带口要剪平，不能刮手。 5. 此单需要验货，请多备料 6. 此单以loose carton出货，16pcs/PDQ/CTN | Y82: Maggie Xie | Z82: 1.68 | AA82: =Z82*I82 -> 38062.08 | AD82: 77711GQ4-S001-NA | AE82: 已入 | AG82: 已完成 | AI82: 22656 | AJ82: =AI82-I82 -> 0 | AN82: =I82 -> 22656 | AP82: =I82 -> 22656 | AU82: =I82 -> 22656 | BB82: =I82/48 -> 472 | BQ82: =I82/16 -> 1416 | CU82: =BQ82+BP82+BO82+BN82+BX82+BR82 -> 1416 | CV82: =CK82+CL82+CM82+CN82+CO82+CQ82+CP82 -> 0 | CW82: =CI82+CJ82 -> 0
A83: 45726 | B83: WAL-MART STORES INC. USA | C83: 美国 | D83: 4500159675 | E83: 0902421337 MOBILE | F83: 4500159675-20 | G83: 77711GQ4-S001-NA | H83: 冰箱迷你球16pcs/箱 | I83: 19552 | J83: 0 | K83: 16 | L83: =I83/K83 -> 1222 | M83: 45797 | N83: 45793 | O83: 5/22 第三方验货 | P83: PASS | R83: 45727 | S83: 有 | T83: RFID+粉色艾利贴纸 | X83: 日期码格式：ZURU DGYYYYMMDD CHINA(日期避开周末和法定节假日即可） 日期：按实际生产日期 Packaging Info: 77711GQ4-S001-NA 1.包装要求： MA 1L A版收缩膜+MA 5L A版收藏指南+MA 说明书+客版1L PDQ 每pcs产品上要贴1张RFID贴纸，贴纸由ZURU提供，贴纸位置请严格按照我们签回的签板； Remark: 77711GQ4-S001-NA 1.包装要求： MA 1L A版收缩膜+MA 5L A版收藏指南+MA 说明书+客版1L PDQ 每pcs产品上要贴1张RFID贴纸，贴纸由ZURU提供，贴纸位置请严格按照我们签回的签板； 2. 外箱印刷带条码的RFID箱唛：RFID紫色色带+WM Dept.图标+RFID图标+ITF-14条码+粉色艾利贴纸（不干胶打印），四面右下角印刷ZURU logo, ITFF条码只印刷在 正唛一面，在加印的时候确保条形码能扫描出来，1张粉红色贴纸贴在正唛对角线，外箱侧面任一角落加印："MADE IN CHINA" 字样； 3. 在产品上和包装上要有日期码、以及要有MADE IN CHINA和ZURU字样； 4. 产品如有扎带口要剪平，不能刮手。 5. 此单需要验货，请多备料 6. 此单以loose carton出货，16pcs/PDQ/CTN | Y83: Maggie Xie | Z83: 1.68 | AA83: =Z83*I83 -> 32847.36 | AD83: 77711GQ4-S001-NA | AE83: 已入 | AG83: 已完成 | AI83: 19552 | AJ83: =AI83-I83 -> 0 | AN83: =I83 -> 19552 | AP83: =I83 -> 19552 | AU83: =I83 -> 19552 | BB83: =I83/48 -> 407.33333 | BQ83: =I83/16 -> 1222 | CU83: =BQ83+BP83+BO83+BN83+BX83+BR83 -> 1222 | CV83: =CK83+CL83+CM83+CN83+CO83+CQ83+CP83 -> 0 | CW83: =CI83+CJ83 -> 0
A84: 45748 | B84: WALMART INC. | C84: 美国 | D84: 4500162168 | E84: 0904512455 ELWOOD | F84: 4500162168-20 | G84: 77711GQ4-S001-NA | H84: 冰箱迷你球16pcs/箱 | I84: 3168 | J84: 0 | K84: 16 | L84: =I84/K84 -> 198 | M84: 45797 | N84: 45793 | O84: 5/22 第三方验货 | P84: PASS | R84: 外箱印刷带条码的RFID箱唛：RFID紫色色带+WM Dept.图标+RFID图标+ITF-14条码，四面右下角印刷ZURU logo, ITFF条码只印刷在正唛一面，在加印的时候确保 条形码能扫描出来，外箱侧面任一角落加印："MADE IN CHINA" 字样； | S84: 无 | T84: 4/11 寄出 | V84: RFID贴纸 | X84: 日期码格式：ZURU DGYYYYMMDD CHINA(日期避开周末和法定节假日即可） 日期：按实际生产日期 Packaging Info: 77711GQ4-S001-NA 1.包装要求： MA 1L A版收缩膜+MA 5L A版收藏指南+MA 说明书+客版1L PDQ，翻单：4500159672 每pcs产品上要贴1张RFID贴纸，贴纸由ZURU提供，贴纸位置请严格按照我们签回的签板； Remark: 77711GQ4-S001-NA 1.包装要求： MA 1L A版收缩膜+MA 5L A版收藏指南+MA 说明书+客版1L PDQ，翻单：4500159672 每pcs产品上要贴1张RFID贴纸，贴纸由ZURU提供，贴纸位置请严格按照我们签回的签板； 2. 外箱印刷带条码的RFID箱唛：RFID紫色色带+WM Dept.图标+RFID图标+ITF-14条码，四面右下角印刷ZURU logo, ITFF条码只印刷在正唛一面，在加印的时候确保 条形码能扫描出来，外箱侧面任一角落加印："MADE IN CHINA" 字样； 3. 在产品上和包装上要有日期码、以及要有MADE IN CHINA和ZURU字样； 4. 产品如有扎带口要剪平，不能刮手。 5. 此单验货，请多备料 6. 此单以loose carton出货，16pcs/PDQ/CTN | Y84: Maggie Xie | Z84: 1.68 | AA84: =Z84*I84 -> 5322.24 | AD84: 77711GQ4-S001-NA | AE84: 已入 | AG84: 已完成 | AI84: 3168 | AJ84: =AI84-I84 -> 0 | AN84: =I84 -> 3168 | AP84: =I84 -> 3168 | AU84: =I84 -> 3168 | BB84: =I84/48 -> 66 | BQ84: =I84/16 -> 198 | CU84: =BQ84+BP84+BO84+BN84+BX84+BR84 -> 198 | CV84: =CK84+CL84+CM84+CN84+CO84+CQ84+CP84 -> 0 | CW84: =CI84+CJ84 -> 0
A85: 45748 | B85: WALMART INC. | C85: 美国 | D85: 4500162168 | E85: 0904512277 RIDGEVILLE SC | F85: 4500162168-50 | G85: 77711GQ4-S001-NA | H85: 冰箱迷你球16pcs/箱 | I85: 3760 | J85: 0 | K85: 16 | L85: =I85/K85 -> 235 | M85: 45797 | N85: 45793 | O85: 5/22 第三方验货 | P85: PASS | R85: 外箱印刷带条码的RFID箱唛：RFID紫色色带+WM Dept.图标+RFID图标+ITF-14条码，四面右下角印刷ZURU logo, ITFF条码只印刷在正唛一面，在加印的时候确保 条形码能扫描出来，外箱侧面任一角落加印："MADE IN CHINA" 字样； | S85: 无 | T85: 4/11 寄出 | V85: RFID贴纸 | X85: 日期码格式：ZURU DGYYYYMMDD CHINA(日期避开周末和法定节假日即可） 日期：按实际生产日期 Packaging Info: 77711GQ4-S001-NA 1.包装要求： MA 1L A版收缩膜+MA 5L A版收藏指南+MA 说明书+客版1L PDQ，翻单：4500159672 每pcs产品上要贴1张RFID贴纸，贴纸由ZURU提供，贴纸位置请严格按照我们签回的签板； Remark: 77711GQ4-S001-NA 1.包装要求： MA 1L A版收缩膜+MA 5L A版收藏指南+MA 说明书+客版1L PDQ，翻单：4500159672 每pcs产品上要贴1张RFID贴纸，贴纸由ZURU提供，贴纸位置请严格按照我们签回的签板； 2. 外箱印刷带条码的RFID箱唛：RFID紫色色带+WM Dept.图标+RFID图标+ITF-14条码，四面右下角印刷ZURU logo, ITFF条码只印刷在正唛一面，在加印的时候确保 条形码能扫描出来，外箱侧面任一角落加印："MADE IN CHINA" 字样； 3. 在产品上和包装上要有日期码、以及要有MADE IN CHINA和ZURU字样； 4. 产品如有扎带口要剪平，不能刮手。 5. 此单验货，请多备料 6. 此单以loose carton出货，16pcs/PDQ/CTN | Y85: Maggie Xie | Z85: 1.68 | AA85: =Z85*I85 -> 6316.8 | AD85: 77711GQ4-S001-NA | AE85: 已入 | AG85: 已完成 | AI85: 3760 | AJ85: =AI85-I85 -> 0 | AN85: =I85 -> 3760 | AP85: =I85 -> 3760 | AU85: =I85 -> 3760 | BB85: =I85/48 -> 78.333333 | BQ85: =I85/16 -> 235 | CU85: =BQ85+BP85+BO85+BN85+BX85+BR85 -> 235 | CV85: =CK85+CL85+CM85+CN85+CO85+CQ85+CP85 -> 0 | CW85: =CI85+CJ85 -> 0
A86: 45734 | B86: COMERCIALIZADORA MEXICO AMERICANA S | C86: 墨西哥 | D86: 4500160573 | E86: 5251215522 | F86: 4500160573-20 | G86: 77711GQ2-S001-INT | H86: 冰箱迷你球50pcs/箱 | I86: 17000 | J86: 0 | K86: 50 | L86: =I86/K86 -> 340 | M86: 45798 | N86: 45794 | O86: 客版日期码要求：LOT+ZURU标准日期码格式。东莞生产的格式：LOTDGYYYYMMDD, DG是东莞拼音首字母， YYYYMMDD是实际的年月日，例如(LOTDG20240920) | P86: PASS | R86: 45768 | S86: 无 | T86: 无 | V86: W5.WM墨西哥防霉的新要求:货物必须在出货主箱和集装箱中按要求放置干燥剂，干燥剂指定品牌干霸 77711GQ2：需要在每箱放入6小包干燥剂，每包干燥剂重量2g 如走柜货等loading plan 确认后再通知集装箱干燥剂数量 此单兴信将安排8*40HC柜子，每个HC需要放置10包干燥剂，每包干燥剂1KG | X86: 日期码格式：LOTDGYYYYMMDD 日期：按实际生产日期 Packaging Info: 2. 77711GQ2：3L MA EAN 收缩膜+UPC条码贴纸+进口商贴纸+MA 5L 收藏指南+MA 3L PDQ+箱唛； Remark: 1. 客版日期码要求：LOT+ZURU标准日期码格式。东莞生产的格式：LOTDGYYYYMMDD, DG是东莞拼音首字母， YYYYMMDD是实际的年月日，例如(LOTDG20240920) 4. 此单有第三方监柜，至少多备一套完整的物料用于监柜，请多备料。 5.WM墨西哥防霉的新要求:货物必须在出货主箱和集装箱中按要求放置干燥剂，干燥剂指定品牌干霸 77711GQ2：需要在每箱放入6小包干燥剂，每包干燥剂重量2g 如走柜货等loading plan 确认后再通知集装箱干燥剂数量 此单兴信将安排8*40HC柜子，每个HC需要放置10包干燥剂，每包干燥剂1KG | Y86: Ever Li | Z86: 0.95 | AA86: =Z86*I86 -> 16150 | AC86: 95123-8.17 | AD86: 77711GQ2-S001-INT | AE86: 已入 | AG86: 已完成 | AI86: =11100 -> 11100 | AJ86: =AI86-I86 -> -5900 | AO86: =I86 -> 17000 | AT86: =I86 -> 17000 | AV86: =I86 -> 17000 | BB86: =I86/24 -> 708.33333 | BP86: =I86/25 -> 680 | CU86: =BQ86+BP86+BO86+BN86+BX86+BR86 -> 680 | CV86: =CK86+CL86+CM86+CN86+CO86+CQ86+CP86 -> 0 | CW86: =CI86+CJ86 -> 0
A87: 45750 | B87: ZURU France | C87: 法国 | D87: 4500162314 | E87: 5200006540 | F87: 4500162314-70 | G87: 77711GQ1-S002-INT-MTS | H87: 冰箱迷你球13pcs/箱 | I87: 4888 | J87: 0 | K87: 13 | L87: =I87/K87 -> 376 | M87: 45799 | N87: 45796 | P87: PASS | Q87: 客人告知下周会出货 | R87: 45750 | S87: 无 | T87: 翻单 | X87: 日期码格式：ZURU INC(BVI) 标准格式 日期：按实际生产日期 Packaging Info: 77711GQ1:最新MA 3L EAN收缩膜+最新MA 5L收藏指南+最新MA 23L说明书+最新MA 5L creative+最新MA纸袋+最新MA 3L PDQ+多语警语折叠贴纸（含包装缺失的法/意/ 西环保标）,, Remark: 1. 法国国家内销单，需要通过ZURU 验货结果后才能出货 (工厂需要主动提前同ZURU QC预约验货避免延期出货造成不必要麻烦)； 2. 本订单所有 具有 baby items / assorted items 的款式，零售包装上都要用 母 EAN; 3. 若有特定款有特殊外箱条码要求时,需要明确列出产品款对应的具体外箱条码号码/条码类型 (若无,可以忽略此需求) 4. 所有出口欧洲的产品, 法规规定禁止在包装和共公众用的印刷品中使用矿物油中含有的物质, 包装印刷油墨中含有的MOAH/MOSH的质量浓度不能超过1%, 否则出 货到法国被抽检出现问题, 供应商需要对此负责; 5. Date code: 外箱/产品/包装 保持一致，完货后提供date code 信息以便我们保存记录做批次管理; 6. 装柜时需要按照款式号码从小到大一款款依次装,避免终端仓库卸货混乱.若一个柜子涉及到几个不同国家内销单,装柜时需要一个国家装完后再装另一个国家的 产品,依次装柜,避免终端仓库因不同国家不同库位位置卸货混乱. (此点需要同工厂装柜人员强调) | Y87: Jade Wang | Z87: 1.16 | AA87: =Z87*I87 -> 5670.08 | AC87: 95050-8.17 | AD87: 77711GQ1-S002-INT | AE87: 已入 | AG87: 已完成 | AI87: 4888 | AJ87: =AI87-I87 -> 0 | AO87: =I87 -> 4888 | AT87: =I87 -> 4888 | AV87: =I87 -> 4888 | BB87: =I87/24 -> 203.66667 | BM87: =I87/13 -> 376 | CU87: =BQ87+BP87+BO87+BN87+BX87+BR87 -> 0 | CV87: =CK87+CL87+CM87+CN87+CO87+CQ87+CP87 -> 0 | CW87: =CI87+CJ87 -> 0
A88: 45727 | B88: THE ENTERTAINER | C88: 英国 | D88: 4500159575 | E88: FB12980 | F88: 4500159575-30 | G88: 77711GQ1-S001-INT | H88: 冰箱迷你球pcs52/箱 | I88: 5512 | J88: 0 | K88: 52 | L88: =I88/K88 -> 106 | M88: 45800 | N88: =M88-4 -> 45796 | O88: 大货样： 请在5/10 前寄出每款1整套大货样到罗湖办公室7B Sandy Shao 收 | P88: PASS | R88: 45727 | S88: 无 | T88: 45776 | X88: 日期码格式：ZURU INC(BVI) 标准格式 日期：按实际生产日期 Packaging Info: *MA版本按工厂现有最新库存即可，订单出英国，请注意检查产品及包装应带UKCA图标，包装显示ZURU UK LTD信息，QC同事请查核，如有问题与跟单确认 *生产日期按实际（法定工作日），按ZURU标准格式即可 ，但是请知悉包装日期码需要早于或者等于外箱日期码 ，不能晚于外箱日期码 *请注意所有订单都需要经过ZURU QC验货并且通过后方可出货 *所有产品按符合欧洲标准走货，需要是不含微塑料版本 。 *涉及到硼的，如可选择情况下应使用低硼版本 （slime 类别低硼一般低于300ppm)，无选择的应与跟单复核再安排 。 *条码如下，请核查 77711GQ1-S001-INT 193052080134 * 大货样： 请在5/10 前寄出每款1整套大货样到罗湖办公室7B Sandy Shao 收。 Remark: 77711GQ1-S001-INT MA-1L 配套包装+ INT UPC 条码覆盖原条码位置 | Y88: Sandy Shao | Z88: 0.92 | AA88: =Z88*I88 -> 5071.04 | AC88: 95078-8.17 | AD88: 77711GQ1-S001-INT-1 | AE88: 已入 | AG88: 已完成 | AI88: =5460+52 -> 5512 | AJ88: =AI88-I88 -> 0 | AO88: =I88 -> 5512 | AP88: =I88 -> 5512 | AV88: =I88 -> 5512 | BB88: =I88/24 -> 229.66667 | BM88: =I88/13 -> 424 | CU88: =BQ88+BP88+BO88+BN88+BX88+BR88 -> 0 | CV88: =CK88+CL88+CM88+CN88+CO88+CQ88+CP88 -> 0 | CW88: =CI88+CJ88 -> 0
A89: 45741 | B89: MEIJER DISTRIBUTION, INC. | C89: 美国 | D89: 4500161407 | E89: 216951853 | F89: 4500161407-10 | G89: 77711GQ1-S002-NA | H89: 冰箱迷你球13pcs/箱 | I89: 5200 | J89: 0 | K89: 13 | L89: =I89/K89 -> 400 | M89: 45790 | N89: 45797 | P89: PASS | R89: 45771 | S89: 无 | T89: 无 | X89: 日期码格式：ZURU INC(BVI) 标准格式 日期： Packaging Info: 1. MA 1L 包装 2. 客人指定箱唛排版 Remark: 出货前 Zuru QC 验货 | Y89: Cherie Li | Z89: 0.92 | AA89: =Z89*I89 -> 4784 | AD89: 77711GQ1-S002-NA-1L | AE89: 已入 | AG89: 已完成 | AI89: 5200 | AJ89: =AI89-I89 -> 0 | AN89: =I89 -> 5200 | AP89: =I89 -> 5200 | AU89: =I89 -> 5200 | BB89: =I89/48 -> 108.33333 | BK89: =I89/13 -> 400 | CU89: =BQ89+BP89+BO89+BN89+BX89+BR89 -> 0 | CV89: =CK89+CL89+CM89+CN89+CO89+CQ89+CP89 -> 0 | CW89: =CI89+CJ89 -> 0
A90: 45741 | B90: MEIJER DISTRIBUTION, INC. | C90: 美国 | D90: 4500161408 | E90: 216951858 | F90: 4500161408-10 | G90: 77711GQ1-S002-NA | H90: 冰箱迷你球13pcs/箱 | I90: 2600 | J90: 0 | K90: 13 | L90: =I90/K90 -> 200 | M90: 45790 | N90: 45797 | P90: PASS | R90: 45771 | S90: 无 | T90: 无 | X90: 日期码格式：ZURU INC(BVI) 标准格式 日期： Packaging Info: 1. MA 1L 包装 2. 客人指定箱唛排版 Remark: 出货前 Zuru QC 验货 | Y90: Cherie Li | Z90: 0.92 | AA90: =Z90*I90 -> 2392 | AD90: 77711GQ1-S002-NA-1L | AE90: 已入 | AG90: 已完成 | AI90: 2600 | AJ90: =AI90-I90 -> 0 | AN90: =I90 -> 2600 | AP90: =I90 -> 2600 | AU90: =I90 -> 2600 | BB90: =I90/48 -> 54.166667 | BK90: =I90/13 -> 200 | CU90: =BQ90+BP90+BO90+BN90+BX90+BR90 -> 0 | CV90: =CK90+CL90+CM90+CN90+CO90+CQ90+CP90 -> 0 | CW90: =CI90+CJ90 -> 0
A91: 45722 | B91: SCHEEL'S ALL SPORTS, INC. | C91: 美国 | D91: 4500159089 | E91: PO#019848185 | F91: 4500159089-40 | G91: 77711GQ2-S001-NA | H91: 冰箱迷你球 | I91: 4150 | J91: 0 | K91: 50 | L91: =I91/K91 -> 83 | M91: 45800 | N91: =M91-4 -> 45796 | P91: PASS | R91: 45722 | S91: 无 | T91: 无 | X91: 日期码格式：ZURU INC(BVI) 标准格式 日期：按实际生产日期 Packaging Info: 1. 包装：ZURU MA 1L 最新UPC版本；出口美国<(>&<)>CA； Remark: 2. 日期跟踪码：产品包装及产品本身都必须有日期跟踪码，并且确保两者的日期跟踪码要一致；ZURU标准格式日期码(请自行调整具体年月日生产期，但不能为周 末）。 3. 此单有4个客户PO， 请见侧边备注； 4. 出货配比: Zuru 标版配比。 | Y91: Mila Yao | Z91: 0.95 | AA91: =Z91*I91 -> 3942.5 | AD91: 77711GQ2-S001-NA | AE91: 已入 | AG91: 已完成 | AI91: 4150 | AJ91: =AI91-I91 -> 0 | AN91: =I91 -> 4150 | AP91: =I91 -> 4150 | AU91: =I91 -> 4150 | BB91: =I91/48 -> 86.458333 | BN91: =I91/25 -> 166 | CU91: =BQ91+BP91+BO91+BN91+BX91+BR91 -> 166 | CV91: =CK91+CL91+CM91+CN91+CO91+CQ91+CP91 -> 0 | CW91: =CI91+CJ91 -> 0
A92: 45761 | B92: SAINSBURY'S SUPERMARKET LTD | C92: 英国 | D92: 4500163316 | E92: PO#2735217-Cu stomer SKU#146638234 | F92: 4500163316-10 | G92: 77711GQ1-S002-INT | H92: 冰箱迷你球13pcs/箱 | I92: 6019 | J92: 0 | K92: 13 | L92: =I92/K92 -> 463 | M92: 45800 | N92: =M92-4 -> 45796 | P92: PASS | Q92: 6/3出货 | R92: 45758 | S92: 无 | T92: 45770 | X92: 日期码格式：ZURU INC(BVI) 标准格式 日期：按实际生产日期 Packaging Info: 77711GQ1：MA 3L+UPC贴纸（UPC#193052080134） Remark: *胶带最少宽度要保证6.0CM,厚度最少0.05毫米,外箱不可以打钉/扎带；以工字型封箱； *如果重量超过5KGS，箱唛需加黄色警示图标志 ，有疑问请与ZURU跟单同事联系,十分重要！ *订单出英国，请注意检查产品及包装应带UKCA图标，包装需要显示ZURU UK LTD/ZURU France地址信息，QC同事请查核，如有问题与跟单确认。 *生产日期按实际的（法定工作日），按ZURU标准格式即可 ，但是请知悉包装日期码需要早于或者等于外箱日期码 ，不能晚于外箱日期码 *请注意所有订单都需要经过ZURU QC验货并且通过后方可出货 *产品条码以订单显示为准 ，请安排生产前先核对再生产。 *外箱上的条码请确保清晰可扫描 ，左上角的条码格式是UPC-A格式，下面14位数的条码格式是ITF-14格式，否则到目的仓无法扫描入仓由工厂承担责任 。 *所有产品按符合欧洲标准走货，微塑料需合规 。 *涉及到硼的，需要符合欧洲标准 *客户不接受PVC材质 *外箱不得使用带金属夹子或带扣 | Y92: May Wu | Z92: 0.92 | AA92: =Z92*I92 -> 5537.48 | AC92: 95110-8.17 | AD92: 77711GQ1-S002-INT | AE92: 已入 | AG92: 已完成 | AI92: =26+5993+13 -> 6032 | AJ92: =AI92-I92 -> 13 | AO92: =I92 -> 6019 | AT92: =I92 -> 6019 | AV92: =I92 -> 6019 | BB92: =I92/24 -> 250.79167 | BM92: =I92/13 -> 463 | CU92: =BQ92+BP92+BO92+BN92+BX92+BR92 -> 0 | CV92: =CK92+CL92+CM92+CN92+CO92+CQ92+CP92 -> 0 | CW92: =CI92+CJ92 -> 0
A93: 45726 | B93: WAL-MART STORES INC. USA | C93: 美国 | D93: 4500159676 | E93: 0902421339 EASTVALE | F93: 4500159676-10 | G93: 77711GQ4-S001-NA | H93: 冰箱迷你球16pcs/箱 | I93: 15904 | J93: 0 | K93: 16 | L93: =I93/K93 -> 994 | M93: 45803 | N93: 45799 | O93: 5/27 第三方验货 | P93: PASS | R93: 45727 | S93: 有 | T93: RFID+粉色艾利贴纸 | X93: 日期码格式：ZURU DGYYYYMMDD CHINA(日期避开周末和法定节假日即可） 日期：按实际生产日期 Packaging Info: 77711GQ4-S001-NA 1.包装要求： MA 1L A版收缩膜+MA 5L A版收藏指南+MA 说明书+客版1L PDQ 每pcs产品上要贴1张RFID贴纸，贴纸由ZURU提供，贴纸位置请严格按照我们签回的签板； Remark: 77711GQ4-S001-NA 1.包装要求： MA 1L A版收缩膜+MA 5L A版收藏指南+MA 说明书+客版1L PDQ 每pcs产品上要贴1张RFID贴纸，贴纸由ZURU提供，贴纸位置请严格按照我们签回的签板； 2. 外箱印刷带条码的RFID箱唛：RFID紫色色带+WM Dept.图标+RFID图标+ITF-14条码+粉色艾利贴纸（不干胶打印），四面右下角印刷ZURU logo, ITFF条码只印刷在 正唛一面，在加印的时候确保条形码能扫描出来，1张粉红色贴纸贴在正唛对角线，外箱侧面任一角落加印："MADE IN CHINA" 字样； 3. 在产品上和包装上要有日期码、以及要有MADE IN CHINA和ZURU字样； 4. 产品如有扎带口要剪平，不能刮手。 5. 此单需要验货，请多备料 6. 此单以loose carton出货，16pcs/PDQ/CTN | Y93: Maggie Xie | Z93: 1.68 | AA93: =Z93*I93 -> 26718.72 | AD93: 77711GQ4-S001-NA | AE93: 已入 | AG93: 已完成 | AI93: 15904 | AJ93: =AI93-I93 -> 0 | AN93: =I93 -> 15904 | AP93: =I93 -> 15904 | AU93: =I93 -> 15904 | BB93: =I93/48 -> 331.33333 | BQ93: =I93/16 -> 994 | CU93: =BQ93+BP93+BO93+BN93+BX93+BR93 -> 994 | CV93: =CK93+CL93+CM93+CN93+CO93+CQ93+CP93 -> 0 | CW93: =CI93+CJ93 -> 0
A94: 45726 | B94: WAL-MART STORES INC. USA | C94: 美国 | D94: 4500159676 | E94: 0902421366 ELWOOD | F94: 4500159676-20 | G94: 77711GQ4-S001-NA | H94: 冰箱迷你球16pcs/箱 | I94: 15296 | J94: 0 | K94: 16 | L94: =I94/K94 -> 956 | M94: 45803 | N94: 45799 | O94: 5/27 第三方验货 | P94: PASS | R94: 45727 | S94: 有 | T94: RFID+粉色艾利贴纸 | X94: 日期码格式：ZURU DGYYYYMMDD CHINA(日期避开周末和法定节假日即可） 日期：按实际生产日期 Packaging Info: 77711GQ4-S001-NA 1.包装要求： MA 1L A版收缩膜+MA 5L A版收藏指南+MA 说明书+客版1L PDQ 每pcs产品上要贴1张RFID贴纸，贴纸由ZURU提供，贴纸位置请严格按照我们签回的签板； Remark: 77711GQ4-S001-NA 1.包装要求： MA 1L A版收缩膜+MA 5L A版收藏指南+MA 说明书+客版1L PDQ 每pcs产品上要贴1张RFID贴纸，贴纸由ZURU提供，贴纸位置请严格按照我们签回的签板； 2. 外箱印刷带条码的RFID箱唛：RFID紫色色带+WM Dept.图标+RFID图标+ITF-14条码+粉色艾利贴纸（不干胶打印），四面右下角印刷ZURU logo, ITFF条码只印刷在 正唛一面，在加印的时候确保条形码能扫描出来，1张粉红色贴纸贴在正唛对角线，外箱侧面任一角落加印："MADE IN CHINA" 字样； 3. 在产品上和包装上要有日期码、以及要有MADE IN CHINA和ZURU字样； 4. 产品如有扎带口要剪平，不能刮手。 5. 此单需要验货，请多备料 6. 此单以loose carton出货，16pcs/PDQ/CTN | Y94: Maggie Xie | Z94: 1.68 | AA94: =Z94*I94 -> 25697.28 | AD94: 77711GQ4-S001-NA | AE94: 已入 | AG94: 已完成 | AI94: 15296 | AJ94: =AI94-I94 -> 0 | AN94: =I94 -> 15296 | AP94: =I94 -> 15296 | AU94: =I94 -> 15296 | BB94: =I94/48 -> 318.66667 | BQ94: =I94/16 -> 956 | CU94: =BQ94+BP94+BO94+BN94+BX94+BR94 -> 956 | CV94: =CK94+CL94+CM94+CN94+CO94+CQ94+CP94 -> 0 | CW94: =CI94+CJ94 -> 0
A95: 45748 | B95: WALMART INC. | C95: 美国 | D95: 4500162169 | E95: 904512276 | F95: 4500162169-10 | G95: 77711GQ4-S001-NA | H95: 冰箱迷你球16pcs/箱 | I95: 4880 | J95: 0 | K95: 16 | L95: =I95/K95 -> 305 | M95: 45803 | N95: 45799 | O95: 5/30 第三方验货 | P95: PASS | R95: 外箱印刷带条码的RFID箱唛：RFID紫色色带+WM Dept.图标+RFID图标+ITF-14条码，四面右下角印刷ZURU logo, ITFF条码只印刷在正唛一面，在加印的时候确保 条形码能扫描出来，外箱侧面任一角落加印："MADE IN CHINA" 字样； | S95: 无 | T95: 4/11 寄出 | V95: RFID贴纸 | X95: 日期码格式：ZURU DGYYYYMMDD CHINA(日期避开周末和法定节假日即可） 日期：按实际生产日期 Packaging Info: 77711GQ4-S001-NA 1.包装要求： MA 1L A版收缩膜+MA 5L A版收藏指南+MA 说明书+客版1L PDQ，翻单：4500159672 每pcs产品上要贴1张RFID贴纸，贴纸由ZURU提供，贴纸位置请严格按照我们签回的签板； Remark: 77711GQ4-S001-NA 1.包装要求： MA 1L A版收缩膜+MA 5L A版收藏指南+MA 说明书+客版1L PDQ，翻单：4500159672 每pcs产品上要贴1张RFID贴纸，贴纸由ZURU提供，贴纸位置请严格按照我们签回的签板； 2. 外箱印刷带条码的RFID箱唛：RFID紫色色带+WM Dept.图标+RFID图标+ITF-14条码，四面右下角印刷ZURU logo, ITFF条码只印刷在正唛一面，在加印的时候确保 条形码能扫描出来，外箱侧面任一角落加印："MADE IN CHINA" 字样； 3. 在产品上和包装上要有日期码、以及要有MADE IN CHINA和ZURU字样； 4. 产品如有扎带口要剪平，不能刮手。 5. 此单验货，请多备料 6. 此单以loose carton出货，16pcs/PDQ/CTN | Y95: Maggie Xie | Z95: 1.68 | AA95: =Z95*I95 -> 8198.4 | AD95: 77711GQ4-S001-NA | AE95: 已入 | AG95: 已完成 | AI95: 4880 | AJ95: =AI95-I95 -> 0 | AN95: =I95 -> 4880 | AP95: =I95 -> 4880 | AU95: =I95 -> 4880 | BB95: =I95/48 -> 101.66667 | BQ95: =I95/16 -> 305 | CU95: =BQ95+BP95+BO95+BN95+BX95+BR95 -> 305 | CV95: =CK95+CL95+CM95+CN95+CO95+CQ95+CP95 -> 0 | CW95: =CI95+CJ95 -> 0
A96: 45749 | B96: COOP NORGE HANDEL AS - DOM | C96: 挪威 | D96: 4500162231 | E96: 32578104 | F96: 4500162231-10 | G96: 77711GQ2-S002-INT | H96: 冰箱迷你球pcs25/箱 | I96: 6250 | J96: 0 | K96: 25 | L96: =I96/K96 -> 250 | M96: 45803 | N96: 45799 | P96: PASS | R96: 45749 | S96: 无 | T96: 45777 | X96: 日期码格式：ZURU INC(BVI) 标准格式 日期：按实际生产日期 Packaging Info: 77711GQ2:MA-A EAN 3L收缩膜+MA 5L+23 L guide book+MA 3L A 展示盒+挪威语警语贴纸; Remark: 1/产品和包装要求无硼无香，包装不能含有PVC； 2/如有微塑料，必须合规欧洲标准，闪粉也是微塑料的一种，目前仅接受三张方式1.去除，2.用可降解材料，和3.永久封印在固体； 3/此订单有第三方验货，请准备三套大货样并不迟于5-14寄出给ZURU 深圳办公室； 4/带电池出货的产品所用到的电池需要符合欧洲电池新规(EU)2023-1542； 5/工厂货号-客户货号彩盒条码-外箱条码 77711GQ2-7254555-4894680043350-10193052080131 6/配比: 77711GQ2:TBC | Y96: Zoe Zhou | Z96: 0.95 | AA96: =Z96*I96 -> 5937.5 | AC96: 95232-8.17 | AD96: 77711GQ2-S002-INT | AE96: 已入 | AG96: 已完成 | AI96: 6250 | AJ96: =AI96-I96 -> 0 | AO96: =I96 -> 6250 | AT96: =I96 -> 6250 | AV96: =I96 -> 6250 | BB96: =I96/24 -> 260.41667 | BP96: =I96/25 -> 250 | CU96: =BQ96+BP96+BO96+BN96+BX96+BR96 -> 250 | CV96: =CK96+CL96+CM96+CN96+CO96+CQ96+CP96 -> 0 | CW96: =CI96+CJ96 -> 0
A97: 45758 | B97: THE KROGER CO. | C97: 美国 | D97: 4500163428 | E97: PO#500-23710 | F97: 4500163428-50 | G97: 77711GQ2-S002-NA | H97: 冰箱迷你球25pcs/箱 | I97: 4500 | J97: 0 | K97: 25 | L97: =I97/K97 -> 180 | M97: 45824 | N97: 45820 | P97: PASS | R97: 45758 | S97: 无 | T97: 无 | X97: 日期码格式：ZURU INC(BVI) 标准格式 日期：按实际生产日期 Packaging Info: 1、包装方式: MA UPC 优先1L最新版，出口美国 Remark: 2、无测试无验货要求 3、纸箱4面印ZURU LOGO + 箱唛 4、日期码请按ZURU标准版执行即可 5、ZURU OQC验货 | Y97: Vicky Wu | Z97: 0.95 | AA97: =Z97*I97 -> 4275 | AC97: ZB00622-7.1 | AD97: 77711GQ2-S002-NA | AE97: 已入 | AG97: 已完成 | AI97: 4500 | AJ97: =AI97-I97 -> 0 | AN97: =I97 -> 4500 | AP97: =I97 -> 4500 | AU97: =I97 -> 4500 | BB97: =I97/48 -> 93.75 | BN97: =I97/25 -> 180 | CU97: =BQ97+BP97+BO97+BN97+BX97+BR97 -> 180 | CV97: =CK97+CL97+CM97+CN97+CO97+CQ97+CP97 -> 0 | CW97: =CI97+CJ97 -> 0
A98: 45758 | B98: THE KROGER CO. | C98: 美国 | D98: 4500163428 | E98: PO#600-59500 | F98: 4500163428-80 | G98: 77711GQ2-S002-NA | H98: 冰箱迷你球25pcs/箱 | I98: 9000 | J98: 0 | K98: 25 | L98: =I98/K98 -> 360 | M98: 45824 | N98: 45820 | P98: PASS | R98: 45758 | S98: 无 | T98: 无 | X98: 日期码格式：ZURU INC(BVI) 标准格式 日期：按实际生产日期 Packaging Info: 1、包装方式: MA UPC 优先1L最新版，出口美国 Remark: 2、无测试无验货要求 3、纸箱4面印ZURU LOGO + 箱唛 4、日期码请按ZURU标准版执行即可 5、ZURU OQC验货 | Y98: Vicky Wu | Z98: 0.95 | AA98: =Z98*I98 -> 8550 | AC98: ZB00627-7.2 | AD98: 77711GQ2-S002-NA | AE98: 已入 | AG98: 已完成 | AI98: 9000 | AJ98: =AI98-I98 -> 0 | AN98: =I98 -> 9000 | AP98: =I98 -> 9000 | AU98: =I98 -> 9000 | BB98: =I98/48 -> 187.5 | BN98: =I98/25 -> 360 | CU98: =BQ98+BP98+BO98+BN98+BX98+BR98 -> 360 | CV98: =CK98+CL98+CM98+CN98+CO98+CQ98+CP98 -> 0 | CW98: =CI98+CJ98 -> 0
A99: 45741 | B99: Walmart Central America | C99: 萨尔瓦多 | D99: 4500161312 | E99: 5907181238 | F99: 4500161312-10 | G99: 77782GQ1-S001-INT | H99: 冰箱迷你球(客版） | I99: 3950 | J99: 0 | K99: 50 | L99: =I99/K99 -> 79 | M99: 45799 | N99: 45796 | P99: PASS | R99: 4/21 提供箱唛资料，使用双坑外箱 | S99: 无 | T99: 进口商贴纸翻单PO4500161302 | X99: 日期码格式：ZURU INC(BVI) 标准格式 日期：按实际生产日期 Packaging Info: 1. 77782GQ1：客版3L UPC包装+ 客版3L PDQ包装+客版收藏指南+进口商贴纸+箱唛，客版收缩膜包装/客版PDQ包装/客版收藏指南/进口商贴纸翻单PO4500161302 Remark: 1.使用双坑外箱 2.请注意产品包装条形码必须是UPC 3.无第三方验货 15. 77782GQ1:WITH 4 DEMO; Base on #77711GQ2-S001-INT ver.:Remove Kikkoman-Soy Sauce Hershey's-Chocolate Syrup 24 oz Hershey's-Mini Chocolate Syrup 24 oz Hershey's-Strawberry Syrup 22 oz | Y99: Ever Li | Z99: 1.32 | AA99: =Z99*I99 -> 5214 | AC99: 95361-8.17 | AD99: 77782GQ1-S001-INT | AE99: 已入 | AG99: 已完成 | AI99: 3950 | AJ99: =AI99-I99 -> 0 | AO99: =I99 -> 3950 | BB99: =I99 -> 3950 | BV99: =I99 -> 3950 | BW99: =I99 -> 3950 | BX99: =I99/25 -> 158 | CU99: =BQ99+BP99+BO99+BN99+BX99+BR99 -> 158 | CV99: =CK99+CL99+CM99+CN99+CO99+CQ99+CP99 -> 0 | CW99: =CI99+CJ99 -> 0
