Workbook

Sheet 71172大脑
A1: 接单期 | B1: 第三方客户名称 | C1: 国家 | D1: PO号 | E1: 第三方客户 PO NO# | F1: SKU | G1: 货号 | H1: 名称 | I1: PO数量(只) | J1: 内箱装箱数量(只) | K1: 外箱装箱数量(只) | L1: 总箱数 | M1: 客PO期 | N1: 计划验货期 | O1: 第三方验货期 | P1: 验货结果 | Q1: 船期SO | R1: 蓝色表示寄出 黄色表示出单 | S1: 是否有外箱贴纸 | T1: 箱唛资料 | U1: 客贴纸 | V1: 其他物料 | W1: 日期码 | X1: 额外黑白书纸 | Y1: 备注 | Z1: 客跟单 | AA1: 单价USD | AB1: 金额USD | AC1: 发票号 | AD1: 系统货号 | AE1: 是否已入系统 | AF1: 已完成数量 | AG1: 欠数 | AH1: 贴纸情况 | AI1: 是否已入系统 | AJ1: 包装 | AK1: 标准=0,客版=1 | AL1: 说明书 | AM1: 标准=0,客版=1 | AN1: 走货情况(离厂日期) | AO1: 71172 产品数 | AP1: 71172 MA 1L彩盒 | AQ1: 71172 MA 3L彩盒 | AR1: 71172 MA 15L说明书A版 | AS1: 71172 MA15L说明书B版 | AT1: 客版MA 2L(ES+PT) | AU1: 客版
A2: 46016 | B2: ZURU NEW ZEALAND LIMITED | C2: 新西兰 | D2: 4500189979 | E2: 5200008513 | F2: 4500189979-10 | G2: 71172-S001-FS | H2: 大脑 | I2: 32 | J2: 0 | K2: 4 | L2: =I2/K2 -> 8 | M2: 46041 | N2: 46037 | O2: N/A | P2: PASS | Q2: 46111 | R2: 需要增加隔电片和加工电池盖做货 | Y2: 日期码格式：ZURU INC(BVI) 标准格式 日期：按实际生产日期 Packaging Info: Remark: NZ Fast Start Order, MA 1L UPC包装，用fast start专用UPC贴纸，外箱除常规箱唛印刷四面外，还需要贴一张黄色A4纸，印"fast start"内容。 旧桶身小硅胶管柱未加高：打防水胶+产线现有硅胶套 | Z2: SD92 | AA2: 9.86 | AB2: =I2*AA2 -> 315.52 | AD2: 71172-S001-1L | AE2: 已入 | AO2: =I2 -> 32
A3: 46078 | B3: KMART AUSTRALIA LTD(NEW ZEALAND) | C3: 新西兰 | D3: 4500193541 | E3: 21431981 | F3: 4500193541-40 | G3: 71172-S001 | H3: 大脑 | I3: 108 | J3: 0 | K3: 4 | L3: =I3/K3 -> 27 | M3: 46121 | N3: 46123 | O3: N/A | P3: PASS | Q3: 4/13上午入仓 | S3: 有 | T3: 46088 | U3: 46099 | Y3: 日期码格式：ZURU INC(BVI) 标准格式 日期：按实际生产日期 Packaging Info: 77772GQ1:MA英语UPC版本包装（收缩膜和说明书, MA首选1L，如无1L可用多语且含英语的配套多语包装) +防盜贴纸(贴纸以及防盜贴纸位置图翻单PO#4500193539)+ 两张张覆盖PDQ上唱片的贴纸+两张张覆盖收藏指南上唱片的贴纸+一张覆盖PDQ上数字"45"的贴纸+一张覆盖收藏指南上数字"45"的贴纸+箱唛+外箱贴纸SSCC Label 配比信息：4 mini vinyls,1 accessory Removed了 ""Messy <(>&<)> Delicious""两张唱片 77794UQ1:MA英语UPC版本包装（收缩膜和说明书, MA首选1L，如无1L可用多语且含英语的配套多语包装) +1张锂电池黑白警语书纸 + 1张防盗贴纸 (贴纸以及位置图 翻单PO#4500193539）+ 箱唛 + 外箱SSCC Label 77843GQ1：MA英语UPC版本包装（MA首选1L，如无1L可用多语且含英语的配套多语包装) +箱唛 + 外箱SSCC Label 77843-sushi <(>&<)> rainbow cake: MA sushi <(>&<)> rainbow cake专用黑白说明书+ 1张防盗贴纸 77843-其他款:MA UV灯说明书+1张防盗贴纸+1张说明书上面加警告语贴纸+1张收缩膜纽扣电池警告语贴纸 （贴纸资料以及位置图翻单PO#4500193539） 配比信息：Ratio: PIZZA: HAMBURGER: PANCAKES: BUBBLE TEA: Matcha TEA: TACO: SUSHI: DONUT: Charcuterie Board: RAINBOW CAKE(Rare)=10.88%: 10.88%: 10.88%: 10.88%: 10.88%: 10.88%: 10.88%: 10.88%: 10.88%: 2.08%=68:68:68:68:68:68:68:68:68:13 71172：MA英语UPC版本包装（收缩膜和说明书, MA首选1L，如无1L可用多语且含英语的配套多语包装) + 一张防盗贴纸（贴纸资料及位置图翻单PO#4500193539）+箱 唛 + 外箱SSCC Label 3PCS AA BATTERIES(INCLUDED) Remark: 1.请务必按时完货，验货。并且按期送货入货代指定仓库，如果晚了导致船期Delay将会有罚金产生或者客户要求空运，所产生的罚金和空运费由工厂承担。 2.SSCC 外箱贴纸请同纸箱瓦楞纸方向（竖纹向）垂直，即外箱贴纸横着贴(注意条码不要被胶带粘住），贴1pc，贴1面正唛，封箱胶纸不能挡住贴纸内容。外箱贴纸 离外箱边距离不少于2cm。 3.外箱材质为ZURU标准； 4.此单需使用KMART封箱胶上下工字型封箱;从2019年6月开始，要用KMART 新版封箱胶带，此单要用"ANKO"封箱胶带 5.此单出口新西兰，请按相应的澳新标准生产； 6.产品和包装上生产批号的显示格式ZURU标准日期码格式 7.外箱信息不可手写，重量和体积需要与实际的一致(不可手写） 8. 每款item装箱后的G.W.超过10KG或者CBM超过0.13,(9.5KG或者以上，四舍五入后也属于10KG) 需在外箱上加印超 重或者Bulky LOGO，若发现我们资料没有，请 帮忙提醒 1)重量超过10kg但不超过16kg且CBM不超过0.13,10-16kg 超重logo 2）CBM超过0.13且重量少于17kg，bulky logo 3）不属于以上两种情况，需要使用相应重量范围内的超重logo 4）超重logo需要在外箱四面都印刷(箱唛右上角，两面侧唛超重logo需要尽量靠近毛重)，尺寸为:110mm height* 95mm width 9. 实际外箱重量跟印在箱唛上的数据差异不能超3%，尺寸按实际数据印刷 71172实际上为LCL散货出柜，请注意此订单与AU po#4500193539一起合并计算 77772务必赶最晚5/11上午交仓 旧桶身小硅胶管柱未加高：打防水胶+产线现有硅胶套 | Z3: Louise Lu | AA3: 9.86 | AB3: =I3*AA3 -> 1064.88 | AD3: 71172-S001-1L | AE3: 已入 | AO3: =I3 -> 108 | AP3: =I3 -> 108 | AR3: =I3 -> 108
A4: 46078 | B4: KMART AUSTRALIA LTD | C4: 澳大利亚 | D4: 4500193539 | E4: 21431979 | F4: 4500193539-40 | G4: 71172-S001 | H4: 大脑 | I4: 1392 | J4: 0 | K4: 4 | L4: =I4/K4 -> 348 | M4: 46121 | N4: 46123 | O4: N/A | P4: PASS | Q4: 4/13上午入仓 | S4: 有 | T4: 46088 | U4: 46099 | Y4: 日期码格式：ZURU INC(BVI) 标准格式 日期：按实际生产日期 Packaging Info: 77772GQ1:MA英语UPC版本包装（收缩膜和说明书, MA首选1L，如无1L可用多语且含英语的配套多语包装) +防盜贴纸(贴纸以及防盜贴纸位置图翻单PO#4500193539)+ 两张张覆盖PDQ上唱片的贴纸+两张张覆盖收藏指南上唱片的贴纸+一张覆盖PDQ上数字"45"的贴纸+一张覆盖收藏指南上数字"45"的贴纸+箱唛+外箱贴纸SSCC Label 配比信息：4 mini vinyls,1 accessory Removed了 ""Messy <(>&<)> Delicious""两张唱片 77794UQ1:MA英语UPC版本包装（收缩膜和说明书, MA首选1L，如无1L可用多语且含英语的配套多语包装) +1张锂电池黑白书纸 + 1张防盗贴纸+ 箱唛 + 外箱SSCC La bel 77843GQ1：MA英语UPC版本包装（MA首选1L，如无1L可用多语且含英语的配套多语包装) +箱唛 + 外箱SSCC Label 77843-sushi <(>&<)> rainbow cake: MA sushi <(>&<)> rainbow cake专用黑白说明书+ 1张防盗贴纸 77843-其他款:MA UV灯说明书+1张防盗贴纸+1张说明书上面加警告语贴纸+1张收缩膜纽扣电池警告语贴纸 配比信息：Ratio: PIZZA: HAMBURGER: PANCAKES: BUBBLE TEA: Matcha TEA: TACO: SUSHI: DONUT: Charcuterie Board: RAINBOW CAKE(Rare)=10.88%: 10.88%: 10.88%: 10.88%: 10.88%: 10.88%: 10.88%: 10.88%: 10.88%: 2.08%=68:68:68:68:68:68:68:68:68:13 71172：MA英语UPC版本包装（收缩膜和说明书, MA首选1L，如无1L可用多语且含英语的配套多语包装) + 一张防盗贴纸+箱唛 + 外箱SSCC Label 3PCS AA BATTERIES(INCLUDED) Remark: 1.请务必按时完货，验货。并且按期送货入货代指定仓库，如果晚了导致船期Delay将会有罚金产生或者客户要求空运，所产生的罚金和空运费由工厂承担。 2.SSCC 外箱贴纸请同纸箱瓦楞纸方向（竖纹向）垂直，即外箱贴纸横着贴(注意条码不要被胶带粘住），贴1pc，贴1面正唛，封箱胶纸不能挡住贴纸内容。外箱贴纸 离外箱边距离不少于2cm。 3.外箱材质为ZURU标准； 4.此单需使用KMART封箱胶上下工字型封箱;从2019年6月开始，要用KMART 新版封箱胶带，此单要用"ANKO"封箱胶带 5.此单出口澳大利亚，请按相应的澳新标准生产； 6.产品和包装上生产批号的显示格式ZURU标准日期码格式 7.外箱信息不可手写，重量和体积需要与实际的一致(不可手写） 8. 每款item装箱后的G.W.超过10KG或者CBM超过0.13,(9.5KG或者以上，四舍五入后也属于10KG) 需在外箱上加印超 重或者Bulky LOGO，若发现我们资料没有，请 帮忙提醒 1)重量超过10kg但不超过16kg且CBM不超过0.13,10-16kg 超重logo 2）CBM超过0.13且重量少于17kg，bulky logo 3）不属于以上两种情况，需要使用相应重量范围内的超重logo 4）超重logo需要在外箱四面都印刷(箱唛右上角，两面侧唛超重logo需要尽量靠近毛重)，尺寸为:110mm height* 95mm width 9. 实际外箱重量跟印在箱唛上的数据差异不能超3%，尺寸按实际数据印刷 71172实际上走LCL散货出柜，请注意此订单与NZ po#4500193541一起合并计算 77772务必赶最晚5/11上午交仓 旧桶身小硅胶管柱未加高：打防水胶+产线现有硅胶套 | Z4: Louise Lu | AA4: 9.86 | AB4: =I4*AA4 -> 13725.12 | AD4: 71172-S001-1L | AE4: 已入 | AO4: =I4 -> 1392 | AP4: =I4 -> 1392 | AR4: =I4 -> 1392
A5: 46065 | B5: KANDYTOYS LIMITED | C5: 英国 | D5: 4500193688 | E5: AS191225ZUR15 274 | F5: 4500193688-100 | G5: 71172-S001 | H5: 大脑 | I5: 500 | J5: 0 | K5: 4 | L5: =I5/K5 -> 125 | M5: 46125 | N5: 46125 | O5: N/A | P5: PASS | Q5: 计划4/18装柜 | S5: 无 | T5: 46091 | U5: 46125 | Y5: 日期码格式：ZURU INC(BVI) 标准格式 日期：按实际生产日期 Packaging Info: 71172-S001:MA UPC包装+WEEE 30L 带电池说明书 B Remark: 1.订单出英国，请注意检查产品及包装应带UKCA图标，包装需要显示ZURU UK LTD/ZURU France地址信息，QC同事请查核，如有问题与跟单确认。 2.生产日期按实际的（法定工作日），按ZURU标准格式即可 ，并需要在出货前提供每个产品外包上对应的生产日期明细 3.请注意所有订单都需要经过ZURU QC验货并且通过后方可出货 4.一个产品一个条码，单款有多个子件条码的请让跟单提供贴纸覆盖。 5.外箱上的条码请确保清晰可扫描，有PDQ， 需要在PDQ底部贴一张带条码并可扫描的贴纸(ZURU 跟单提供模板）。 6.所有产品按符合欧洲标准走货，微塑料需合规并增加IFUD声明，含电池的需要增加WEEE说明书。 旧桶身小硅胶管柱未加高：打防水胶+产线现有硅胶套 | Z5: Zoe Zhou | AA5: 9.86 | AB5: =I5*AA5 -> 4930 | AD5: 71172-S001-1L | AE5: 已入 | AO5: =I5 -> 500 | AP5: =I5 -> 500 | AR5: =I5 -> 500
A6: 46059 | B6: ZURU LLC | C6: 美国 | D6: 4500193356 | E6: 5200008960 | F6: 4500193356-10 | G6: 71172-S001-FS | H6: 大脑 | I6: 20 | J6: 0 | K6: 4 | L6: =I6/K6 -> 5 | M6: 46118 | N6: 46126 | O6: N/A | P6: PASS | S6: 无 | T6: 3/17更新 | U6: 46060 | Y6: 日期码格式：DGYYYYMMDD(日期避开周末和法定节假日) 日期：按实际生产日期 Packaging Info: WMUS FAST START 项目要求: 1. 包装要求：MA 1L包装+MA说明书 (不需要客供RFID贴纸) Remark: 2. 此单New UPC与STD不同，需加贴New UPC贴纸。贴前须用黑色笔将原UPC条码完全涂黑，使其无法扫描，再粘贴新UPC贴纸。 3.#71172——71172-S001-FS UPC：193052109309 GTIN：10193052109306 4. 外箱印四面唛头信息，默认正唛和侧唛各两面。参考提供模版，排版供确认后，才能生产。 外箱需印刷外箱GTIN barcode（格式：ITF-14） ，确保清晰可见，可正常扫描。 MFG：DGYYYYMMDD（两面正唛打日期码） Gross weight/lbs: 可手写上去 5. 此MTS订单不需要第三方抽板验货，但是要通过ZURU QC验货PASS后才能出货。 空运到3PL仓库。 旧桶身小硅胶管柱未加高：打防水胶+产线现有硅胶套 | Z6: Nikki Mo | AA6: 5.916 | AB6: =I6*AA6 -> 118.32 | AC6: ZB05678-8.17 | AD6: 71172-S001-1L | AE6: 已入 | AO6: =I6 -> 20 | AP6: =I6 -> 20 | AR6: =I6 -> 20
A7: 46094 | B7: ZURU NEW ZEALAND LIMITED | C7: 新西兰 | D7: 4500196745 | E7: 5200009279 | F7: 4500196745-50 | G7: 71172-S001-FS | H7: 大脑 | I7: 20 | J7: 0 | K7: 4 | L7: =I7/K7 -> 5 | M7: 46121 | N7: 46126 | O7: N/A | P7: PASS | Q7: 46128 | R7: 需要增加隔电片和加工电池盖做货 | S7: 无 | T7: 46094 | U7: 46104 | Y7: 日期码格式：ZURU INC(BVI) 标准格式 日期：按实际生产日期 Packaging Info: 71172：MA英语UPC版本包装（收缩膜和说明书, MA首选1L，如无1L可用多语且含英语的配套多语包装) + 1张fast start专用UPC贴纸+贴一张黄色A4纸，印"fast sta rt"内容。（两张贴纸及位置图翻单4500189979)+箱唛 3PCS AA BATTERIES(INCLUDED) Remark: 1.请务必按时完货，验货。并且按期送货入货代指定仓库，如果晚了导致船期Delay将会有罚金产生或者客户要求空运，所产生的罚金和空运费由工厂承担。 2.外箱材质为ZURU标准； 3.此单需使用KMART封箱胶上下工字型封箱;从2019年6月开始，要用KMART 新版封箱胶带，此单要用"ANKO"封箱胶带 4.此单出口新西兰，请按相应的澳新标准生产； 5.产品和包装上生产批号的显示格式ZURU标准日期码格式 6.外箱信息不可手写，重量和体积需要与实际的一致(不可手写） 7. 实际外箱重量跟印在箱唛上的数据差异不能超3%，尺寸按实际数据印刷 旧桶身小硅胶管柱未加高：打防水胶+产线现有硅胶套 | Z7: Louise Lu | AA7: 9.86 | AB7: =I7*AA7 -> 197.2 | AD7: 71172-S001-1L | AE7: 已入 | AO7: =I7 -> 20 | AP7: =I7 -> 20 | AR7: =I7 -> 20
A8: 46065 | B8: TARGET US | C8: 美国 | D8: 4500193071 | E8: 10001662903-3890 | F8: 4500193071-10 | G8: 71172-S001 | H8: 大脑 | I8: 188 | J8: 0 | K8: 4 | L8: =I8/K8 -> 47 | M8: 46119 | N8: 46127 | O8: N/A | P8: PASS | Q8: 4/16客上柜 | S8: 有 | T8: 46085 | U8: 2/7收到Event Label,3/12收外箱贴纸 | Y8: 日期码格式：ZURU INC(BVI) 标准格式 日期：按实际生产日期 Packaging Info: 产品包装MA 1L彩盒 Remark: 1. 71172-S001-ROBO ALIVE-BRAIN-SERIES 1-BRIAN THE BRAIN-OPEN BOX-4PCS/CTN 2. 产品包装MA 1L彩盒；彩盒上的UPC显示193052098443； 3. 每个外箱正唛箱唛信息左上方位置粘贴条码箱贴纸，每箱只贴一张; 由ZURU向艾利订购， 对应的外箱贴DPCI：087-02-9468, UPC显示10193052098440 ； 4. 每个外箱正唛信息的右侧需要贴一张Event Label，贴纸内容显示 7/19 TRANSITION TOYS Set Date 7/19/2026，工厂自行订购； 5. 产品和包装上要印刷tracking code信息，格式为ZURU常规； 6. 出货方式：货代自提 旧桶身小硅胶管柱未加高：打防水胶+产线现有硅胶套 | Z8: Holly Zheng | AA8: 5.82 | AB8: =I8*AA8 -> 1094.16 | AC8: ZB05677-8.17 | AD8: 71172-S001-1L | AE8: 已入 | AO8: =I8 -> 188 | AP8: =I8 -> 188 | AR8: =I8 -> 188
A9: 46079 | B9: TARGET US | C9: 美国 | D9: 4500194286 | E9: 10001662883-3 890 | F9: 4500194286-10 | G9: 71172-S001 | H9: 大脑 | I9: 3828 | J9: 0 | K9: 4 | L9: =I9/K9 -> 957 | M9: 46119 | N9: 46127 | O9: N/A | P9: PASS | Q9: 4/16客上柜-168PCS,4/18客上柜-3660PCS | S9: 有 | T9: 46085 | U9: 2/7收到Event Label,3/12收外箱贴纸 | Y9: 日期码格式：ZURU INC(BVI) 标准格式 日期：按实际生产日期 Packaging Info: 产品包装MA 1L彩盒 Remark: 1. 71172-S001-ROBO ALIVE-BRAIN-SERIES 1-BRIAN THE BRAIN-OPEN BOX-4PCS/CTN 2. 产品包装MA 1L彩盒；彩盒上的UPC显示193052098443； 3. 每个外箱正唛箱唛信息左上方位置粘贴条码箱贴纸，每箱只贴一张; 由ZURU向艾利订购， 对应的外箱贴DPCI：087-02-9468, UPC显示10193052098440 ； 4. 每个外箱正唛信息的右侧需要贴一张Event Label，贴纸内容显示 7/19 TRANSITION TOYS Set Date 7/19/2026，工厂自行订购；贴纸资料翻单4500193070； 5. 产品和包装上要印刷tracking code信息，格式为ZURU常规； 6. 出货方式：货代自提 此PO有新旧桶，新桶有打A | Z9: Holly Zheng | AA9: 5.82 | AB9: =I9*AA9 -> 22278.96 | AC9: ZB05675/ZB05676 | AD9: 71172-S001-1L | AE9: 已入 | AO9: =I9 -> 3828 | AP9: =I9 -> 3828 | AR9: =I9 -> 3828
A10: 46086 | B10: KMART AUSTRALIA LTD | C10: 澳大利亚 | D10: 4500193164 | E10: 21570516 | F10: 4500193164-30 | G10: 71172-S001 | H10: 大脑 | I10: 1320 | J10: 0 | K10: 4 | L10: =I10/K10 -> 330 | M10: 46125 | N10: 46129 | O10: N/A | P10: PASS | Q10: 4/15-4/17入仓，在申请4/18上午入仓 | S10: 有 | T10: 46093 | U10: 46105 | Y10: 日期码格式：ZURU INC(BVI) 标准格式 日期：按实际生产日期 Packaging Info: 71172：MA英语UPC版本包装（收缩膜和说明书, MA首选1L，如无1L可用多语且含英语的配套多语包装) + 一张防盗贴纸（贴纸资料及位置图翻单PO#4500193539）+箱 唛 + 外箱SSCC Label 3PCS AA BATTERIES(INCLUDED) Remark: 1.请务必按时完货，验货。并且按期送货入货代指定仓库，如果晚了导致船期Delay将会有罚金产生或者客户要求空运，所产生的罚金和空运费由工厂承担。 2.SSCC 外箱贴纸请同纸箱瓦楞纸方向（竖纹向）垂直，即外箱贴纸横着贴(注意条码不要被胶带粘住），贴1pc，贴1面正唛，封箱胶纸不能挡住贴纸内容。外箱贴纸 离外箱边距离不少于2cm。 3.外箱材质为ZURU标准； 4.此单需使用KMART封箱胶上下工字型封箱;从2019年6月开始，要用KMART 新版封箱胶带，此单要用"ANKO"封箱胶带 5.此单出口澳大利亚，请按相应的澳新标准生产； 6.产品和包装上生产批号的显示格式ZURU标准日期码格式 7.外箱信息不可手写，重量和体积需要与实际的一致(不可手写） 8. 每款item装箱后的G.W.超过10KG或者CBM超过0.13,(9.5KG或者以上，四舍五入后也属于10KG) 需在外箱上加印超 重或者Bulky LOGO，若发现我们资料没有，请 帮忙提醒 1)重量超过10kg但不超过16kg且CBM不超过0.13,10-16kg 超重logo 2）CBM超过0.13且重量少于17kg，bulky logo 3）不属于以上两种情况，需要使用相应重量范围内的超重logo 4）超重logo需要在外箱四面都印刷(箱唛右上角，两面侧唛超重logo需要尽量靠近毛重)，尺寸为:110mm height* 95mm width 9. 实际外箱重量跟印在箱唛上的数据差异不能超3%，尺寸按实际数据印刷 请注意此订单与NZ PO#4500193165一起合并计算，71172实际上是LCL散货出柜 旧桶身小硅胶管柱未加高：打防水胶+产线现有硅胶套 | Z10: Louise Lu | AA10: 9.86 | AB10: =I10*AA10 -> 13015.2 | AD10: 71172-S001-1L | AE10: 已入 | AO10: =I10 -> 1320 | AP10: =I10 -> 1320 | AR10: =I10 -> 1320
A11: 46086 | B11: KMART AUSTRALIA LTD(NEW ZEALAND) | C11: 新西兰 | D11: 4500193165 | E11: 21570517 | F11: 4500193165-40 | G11: 71172-S001 | H11: 大脑 | I11: 180 | J11: 0 | K11: 4 | L11: =I11/K11 -> 45 | M11: 46125 | N11: 46129 | O11: N/A | P11: PASS | Q11: 4/15-4/17入仓，在申请4/18上午入仓 | S11: 有 | T11: 46093 | U11: 46105 | Y11: 日期码格式：ZURU INC(BVI) 标准格式 日期：按实际生产日期 Packaging Info: 71172：MA英语UPC版本包装（收缩膜和说明书, MA首选1L，如无1L可用多语且含英语的配套多语包装) + 一张防盗贴纸（贴纸资料及位置图翻单PO#4500193539）+箱 唛 + 外箱SSCC Label 3PCS AA BATTERIES(INCLUDED) Remark: 1.请务必按时完货，验货。并且按期送货入货代指定仓库，如果晚了导致船期Delay将会有罚金产生或者客户要求空运，所产生的罚金和空运费由工厂承担。 2.SSCC 外箱贴纸请同纸箱瓦楞纸方向（竖纹向）垂直，即外箱贴纸横着贴(注意条码不要被胶带粘住），贴1pc，贴1面正唛，封箱胶纸不能挡住贴纸内容。外箱贴纸 离外箱边距离不少于2cm。 3.外箱材质为ZURU标准； 4.此单需使用KMART封箱胶上下工字型封箱;从2019年6月开始，要用KMART 新版封箱胶带，此单要用"ANKO"封箱胶带 5.此单出口新西兰，请按相应的澳新标准生产； 6.产品和包装上生产批号的显示格式ZURU标准日期码格式 7.外箱信息不可手写，重量和体积需要与实际的一致(不可手写） 8. 每款item装箱后的G.W.超过10KG或者CBM超过0.13,(9.5KG或者以上，四舍五入后也属于10KG) 需在外箱上加印超 重或者Bulky LOGO，若发现我们资料没有，请 帮忙提醒 1)重量超过10kg但不超过16kg且CBM不超过0.13,10-16kg 超重logo 2）CBM超过0.13且重量少于17kg，bulky logo 3）不属于以上两种情况，需要使用相应重量范围内的超重logo 4）超重logo需要在外箱四面都印刷(箱唛右上角，两面侧唛超重logo需要尽量靠近毛重)，尺寸为:110mm height* 95mm width 9. 实际外箱重量跟印在箱唛上的数据差异不能超3%，尺寸按实际数据印刷 请注意此订单与AU PO#4500193164一起合并计算，71172实际上为LCL散货出柜 新桶身小硅胶管柱加高：未打防水胶+新开小一点有硅胶套 | Z11: Louise Lu | AA11: 9.86 | AB11: =I11*AA11 -> 1774.8 | AD11: 71172-S001-1L | AE11: 已入 | AO11: =I11 -> 180 | AP11: =I11 -> 180 | AR11: =I11 -> 180
A12: 46022 | D12: ZPO2512023 | G12: 71172-S001 | H12: 大脑 | I12: 500 | J12: 0 | K12: 4 | L12: =I12/K12 -> 125 | M12: 46042 | N12: 46133 | O12: N/A | P12: PASS | R12: 用第二次PP阶段订购的彩盒包装 | S12: N/A | T12: 空白箱 | U12: 无 | Y12: 新桶身小硅胶管柱加高：未打防水胶+新开小一点有硅胶套 | AD12: 71172-S001-1L | AE12: 已入
A13: 46091 | B13: SMYTHS TOYS EU HQ UC | C13: 德国 | D13: 4500195772 | E13: 4400545646 | F13: 4500195772-70 | G13: 71172-S001 | H13: 大脑 | I13: 1800 | J13: 0 | K13: 4 | L13: =I13/K13 -> 450 | M13: 46127 | N13: 46133 | O13: N/A | P13: PASS | Q13: 4/21截SI | S13: 无 | T13: 46095 | U13: 46100 | Y13: 日期码格式：ZURU INC(BVI) 标准格式 日期：按实际生产日期 Packaging Info: 71172: MA3L-23Lwarning彩盒+1张德语callout贴纸(本单放稿)+C版WEEE声明(带电池)走货欧洲通用29L说明书 EAN#4894680057272 3PCS AA BATTERIES(INCLUDED) Remark: Smyths 德国 1. 请准时出货，推期会有罚款； 2. 所有产品按符合欧洲标准走货，需要是不含微塑料版本。 3. 所有电子产品身上需要加字唛，为ZURU FRANCE 地址 (如无电子产品，产品布标有此地址，或产品太小无法增加可忽略此信息)，新地址ZURU FRANCE.33 rue Pa ul Meurice 75020 Paris, France. 4. 电子产品需增加一张C版WEEE声明29L通用黑白说明书(不接受A版本，翻译有误)，区分带电池和不带电池出货版本, 如已做客版说明书可忽略此要求；如包装备注 上缺少此部分信息，请提醒跟单更新备注。 5.所有出往德国市场有关slime和带香味的都需要出无硼无香版本； 6.订单备注显示有分批的(不同仓库/订单号), 一定要区分客户订单号做货出货，否则会导致罚款 。 7.包装日期码按ZURU格式即可，请确保不迟于外箱日期码，可等于或者早于外箱日期码，必须为法定工作日。 8.做货前请先复核包装条码与订单是否一致再安排，对不上的需与ZURU跟单确认再安排。 9.包装必须含法国回收标(Sorting Label)，如没有，请提醒跟单提供贴纸资料。 新桶身小硅胶管柱加高：未打防水胶+新开小一点有硅胶套 | Z13: Sherry Lu | AA13: 9.86 | AB13: =I13*AA13 -> 17748 | AD13: 71172-S001-3L | AE13: 已入 | AO13: =I13 -> 1800 | AQ13: =I13 -> 1800 | AR13: =I13 -> 1800
A14: 46093 | B14: SMYTHS TOYS HQ UC UK | C14: 英国 | D14: 4500196579 | E14: 4400544507 | F14: 4500196579-10 | G14: 71172-S001 | H14: 大脑 | I14: 2500 | J14: 0 | K14: 4 | L14: =I14/K14 -> 625 | M14: 46125 | N14: 46134 | O14: N/A | P14: PASS | Q14: 4/24截SI | S14: 无 | T14: 46094 | U14: 46093 | Y14: 日期码格式：ZURU INC(BVI) 标准格式 日期：按实际生产日期 Packaging Info: "71172: MA3L-23Lwarning彩盒(含法国sorting label)+C版WEEE声明(带电池)走货欧洲通用29L说明书 EAN#4894680057272 3PCS AA BATTERIES(INCLUDED)" Remark: Smyths 英国/爱尔兰 1. 请准时出货，推期会有罚款； 2. 所有产品按符合欧洲标准走货，需要是不含微塑料版本。 3.包装日期码按ZURU格式即可，请确保不迟于外箱日期码，可等于或者早于外箱日期码，必须为法定工作日，印刷前请先检查外箱日期码。 4.请注意检查产品及包装应带UKCA图标（14+产品除外），包装显示ZURU UK LTD/ZURU France地址信息，QC部门请查核，如有问题与跟单确认 5.电子产品需增加一张C版WEEE声明29L通用黑白说明书(不接受A版本，翻译有误)，区分带电池和不带电池出货版本, 如已做客版说明书可忽略此要求；如包装备注 上缺少此部分信息，请提醒跟单更新备注。 6.订单备注显示有分批的(不同仓库/订单号), 一定要区分客户订单号做货出货，否则会导致罚款 。 7.做货前请先复核包装条码与订单是否一致再安排，对不上的需与ZURU跟单确认再安排。 8.包装必须含法国回收标(Sorting Label)，如没有，请提醒跟单提供贴纸资料。 新桶身小硅胶管柱加高：未打防水胶+新开小一点有硅胶套 | Z14: Sherry Lu | AA14: 9.86 | AB14: =I14*AA14 -> 24650 | AD14: 71172-S001-3L | AE14: 已入 | AO14: =I14 -> 2500 | AQ14: =I14 -> 2500 | AR14: =I14 -> 2500
A15: 46091 | B15: SMYTHS TOYS HQ UC IE | C15: 爱尔兰 | D15: 4500195833 | E15: 4400544510 | F15: 4500195833-40 | G15: 71172-S001 | H15: 大脑 | I15: 500 | J15: 0 | K15: 4 | L15: =I15/K15 -> 125 | M15: 46129 | N15: 46136 | O15: N/A | P15: PASS | Q15: 4/27截SI | S15: 无 | T15: 46095 | U15: 46093 | Y15: 日期码格式：ZURU INC(BVI) 标准格式 日期：按实际生产日期 Packaging Info: 71172: MA3L-23Lwarning彩盒(含法国sorting label)+C版WEEE声明(带电池)走货欧洲通用29L说明书 EAN#4894680057272 3PCS AA BATTERIES(INCLUDED) Remark: Smyths 英国/爱尔兰 1. 请准时出货，推期会有罚款； 2. 所有产品按符合欧洲标准走货，需要是不含微塑料版本。 3.包装日期码按ZURU格式即可，请确保不迟于外箱日期码，可等于或者早于外箱日期码，必须为法定工作日，印刷前请先检查外箱日期码。 4.请注意检查产品及包装应带UKCA图标（14+产品除外），包装显示ZURU UK LTD/ZURU France地址信息，QC部门请查核，如有问题与跟单确认 5.电子产品需增加一张C版WEEE声明29L通用黑白说明书(不接受A版本，翻译有误)，区分带电池和不带电池出货版本, 如已做客版说明书可忽略此要求；如包装备注 上缺少此部分信息，请提醒跟单更新备注。 6.订单备注显示有分批的(不同仓库/订单号), 一定要区分客户订单号做货出货，否则会导致罚款 。 7.做货前请先复核包装条码与订单是否一致再安排，对不上的需与ZURU跟单确认再安排。 8.包装必须含法国回收标(Sorting Label)，如没有，请提醒跟单提供贴纸资料。 新桶身小硅胶管柱加高：未打防水胶+新开小一点有硅胶套 | Z15: Sherry Lu | AA15: 9.86 | AB15: =I15*AA15 -> 4930 | AD15: 71172-S001-3L | AE15: 已入 | AO15: =I15 -> 500 | AQ15: =I15 -> 500 | AR15: =I15 -> 500
A16: 46061 | B16: ASIA GOAL LIMITED TAIWAN BRANCH (H. | C16: 台湾 | D16: 4500193394 | E16: AG250407-TW | F16: 4500193394-20 | G16: 71172-S001 | H16: 大脑 | I16: 120 | J16: 0 | K16: 4 | L16: =I16/K16 -> 30 | M16: 46134 | N16: 46136 | O16: N/A | P16: PASS | S16: 无 | T16: 46067 | U16: 无 | Y16: 日期码格式：ZURU INC(BVI) 标准格式 日期：按实际生产日期 Packaging Info: 此单出TW 71172：MA 1L PKG , MA 说明书 （该款无需贴纸，出ZURU 标准包装即可） Remark: 新桶身小硅胶管柱加高：未打防水胶+新开小一点有硅胶套 | Z16: Chelsea Luo | AA16: 9.86 | AB16: =I16*AA16 -> 1183.2 | AD16: 71172-S001-1L | AE16: 已入 | AO16: =I16 -> 120 | AP16: =I16 -> 120 | AR16: =I16 -> 120
A17: 46094 | B17: ARGOS LIMITED | C17: 英国 | D17: 4500196827 | F17: 4500196827-20 | G17: 71172-S001 | H17: 大脑 | I17: 500 | J17: 0 | K17: 4 | L17: =I17/K17 -> 125 | M17: 46133 | N17: 46139 | O17: N/A | P17: PASS | Q17: 4/27截SI | S17: 无 | T17: 46106 | U17: 46106 | Y17: 日期码格式：ZURU INC(BVI) 标准格式 日期：按实际生产日期 Packaging Info: 71172： MA 包装+客人白色Cat.label 1张; MA说明书+WEEE带电池说明书 2.注意Cat.label （要求易撕类贴纸，但是粘性不能过低），同时此贴纸每个订单都是不相同的（会显示客户对应的订单号），切勿翻旧订单购买。此贴纸由ZURU提 供贴纸图稿和贴纸位置图给工厂后，工厂自行购买。 3.请先检查条码是否正确再安排做，标签上的目录编号数字高度必须至少为5mm （14.17pt） Remark: 新桶身小硅胶管柱加高：未打防水胶+新开小一点有硅胶套 | Z17: Lena Huang | AA17: 9.86 | AB17: =I17*AA17 -> 4930 | AD17: 71172-S001-1L | AE17: 已入 | AO17: =I17 -> 500 | AP17: =I17 -> 500 | AR17: =I17 -> 500
A18: 46083 | B18: AMAZON.COM SERVICES LLC | C18: 美国 | D18: 4500194918 | E18: 8V4WFTAX | F18: 4500194918-10 | G18: 71172-S003-MB | H18: 大脑（邮包盒装） | I18: 84 | J18: 0 | K18: 4 | L18: =I18/K18 -> 21 | M18: 46140 | N18: 46140 | O18: N/A | P18: PASS | Q18: 4/29截SI | S18: 有 | T18: 46084 | U18: 46123 | Y18: 日期码格式：ZURU INC(BVI) 标准格式 日期：按实际生产日期 Packaging Info: #71172:MA 1L UPC版本 #71172带MA包装入邮包盒，邮包盒图稿翻单4500192525。 Remark: 1. Amazon MDDP订单，出口US。 2. 日期码使用ZURU标准版本。 3. 如果大货有要求入邮包盒，则对应的邮包盒上面要打上日期码。 4. 箱尺寸要求：外箱最长边不能超过25"(超过了，case pack只能为1)，不符合要求的大货，一律不接受。 5. 外箱箱唛要求： ①外箱正面印ZURU Logo+SSCC Label(客供贴纸，由跟单订购)。关于 SSCC Label 请注意： SSCC Label显示的是客人自己的item#。每一张SSCC label都是唯一且有不同流水及条码的，没有损耗，绝对不可贴错。如果贴错或损坏任何一张，都会导致全部都 错，千万要注意！SSCC Label必须贴在外箱正面的正中间位置(贴一面即可)，并且贴纸离外箱边距必须至少3cm(可以覆盖Logo<(>&<)>箱唛)，否则会影响到客户那边 仓库的扫描识别。 ②外箱侧面印item#(订单上显示的SKU#)+carton size(以工厂实际尺寸为准，单位: inch)+MADE IN CHINA，日期使用ZURU 标准版本。 6. 装柜要求：按照客户PO#装柜/箱号顺序装柜，跟单会提前给到装柜计划。 在大货生产/仓库存放时，请留意该装柜要求，以便装柜时不混乱(避免装错/装漏/找不到货号等)。 新桶身小硅胶管柱加高：未打防水胶+新开小一点有硅胶套 | Z18: Kelly Shen/Mia Pan/P | AA18: 5.916 | AB18: =I18*AA18 -> 496.944 | AC18: ZB05653-8.17 | AD18: 71172-S003-MB-1L | AE18: 已入 | AO18: =I18 -> 84 | AP18: =I18 -> 84 | AR18: =I18 -> 84
A19: 46091 | B19: SMYTHS TOYS EU HQ UNLIMITED COMPANY | C19: 法国 | D19: 4500195839 | E19: 4400544509 | F19: 4500195839-40 | G19: 71172-S001 | H19: 大脑 | I19: 216 | J19: 0 | K19: 4 | L19: =I19/K19 -> 54 | M19: 46129 | N19: 46141 | O19: N/A | P19: PASS | Q19: 4/30送库有拼柜 | S19: 无 | T19: 46095 | U19: 46093 | Y19: 日期码格式：ZURU INC(BVI) 标准格式 日期：按实际生产日期 Packaging Info: 71172: MA3L-23Lwarning彩盒(含法国sorting label)+C版WEEE声明(带电池)走货欧洲通用29L说明书 EAN#4894680057272 3PCS AA BATTERIES(INCLUDED) Remark: Smyths 法国 1. 请准时出货，推期会有罚款； 2. 所有产品按符合欧洲标准走货，需要是不含微塑料版本。 3. 电子产品需增加一张C版WEEE声明29L通用黑白说明书(不接受A版本，翻译有误)，区分带电池和不带电池出货版本, 如已做客版说明书可忽略此要求；如包装备注 上缺少此部分信息，请提醒跟单更新备注。 4. 出口法国的产品, 法规规定禁止在包装和共公众用的印刷品中使用矿物油中含有的物质, 包装印刷油墨中含有的MOAH/MOSH的质量浓度不能超过0.1%, 否则出货 到法国被抽检出现问题, 供应商需要对此负责; 5.订单备注显示有分批的(不同仓库/订单号), 一定要区分客户订单号做货出货，否则会导致罚款 。 6.包装日期码按ZURU格式即可，请确保不迟于外箱日期码，可等于或者早于外箱日期码，必须为法定工作日。 7.做货前请先复核包装条码与订单是否一致再安排，对不上的需与ZURU跟单确认再安排。 8.包装必须含法国回收标(Sorting Label)，如没有，请提醒跟单提供贴纸资料。 新桶身小硅胶管柱加高：未打防水胶+新开小一点有硅胶套 | Z19: Sherry Lu | AA19: 9.86 | AB19: =I19*AA19 -> 2129.76 | AD19: 71172-S001-3L | AE19: 已入 | AO19: =I19 -> 216 | AQ19: =I19 -> 216 | AR19: =I19 -> 216
A20: 46061 | B20: ASIA GOAL LIMITED TAIWAN BRANCH (H. | C20: 香港 | D20: 4500193390 | E20: AG250406-HK | F20: 4500193390-20 | G20: 71172-S001 | H20: 大脑 | I20: 120 | J20: 0 | K20: 4 | L20: =I20/K20 -> 30 | M20: 46134 | N20: 46141 | O20: N/A | P20: PASS | Q20: 4/30客上柜 | S20: 无 | T20: 46067 | U20: 46105 | Y20: 日期码格式：ZURU INC(BVI) 标准格式 日期：按实际生产日期 Packaging Info: 此单出HK 71172：MA 1L PKG, MA 说明书+ HK客供警语贴纸 ， 1张贴彩盒底部，1张客供电池警语贴纸贴彩盒底部，1张贴说明书 新桶身小硅胶管柱加高：未打防水胶+新开小一点有硅胶套 新桶身小硅胶管柱加高：未打防水胶+新开小一点有硅胶套 | Z20: Chelsea Luo | AA20: 9.86 | AB20: =I20*AA20 -> 1183.2 | AD20: 71172-S001-1L | AE20: 已入 | AO20: =I20 -> 120 | AP20: =I20 -> 120 | AR20: =I20 -> 120
A21: 46091 | B21: SMYTHS TOYS EU HQ UNLIMITED COMPANY | C21: 法国 | D21: 4500195839 | E21: 4400544508 | F21: 4500195839-30 | G21: 71172-S001 | H21: 大脑 | I21: 444 | J21: 0 | K21: 4 | L21: =I21/K21 -> 111 | M21: 46129 | N21: 46142 | O21: N/A | P21: PASS | Q21: 5/4截SI | S21: 无 | T21: 46095 | U21: 46093 | Y21: 日期码格式：ZURU INC(BVI) 标准格式 日期：按实际生产日期 Packaging Info: 71172: MA3L-23Lwarning彩盒(含法国sorting label)+C版WEEE声明(带电池)走货欧洲通用29L说明书 EAN#4894680057272 3PCS AA BATTERIES(INCLUDED) Remark: Smyths 法国 1. 请准时出货，推期会有罚款； 2. 所有产品按符合欧洲标准走货，需要是不含微塑料版本。 3. 电子产品需增加一张C版WEEE声明29L通用黑白说明书(不接受A版本，翻译有误)，区分带电池和不带电池出货版本, 如已做客版说明书可忽略此要求；如包装备注 上缺少此部分信息，请提醒跟单更新备注。 4. 出口法国的产品, 法规规定禁止在包装和共公众用的印刷品中使用矿物油中含有的物质, 包装印刷油墨中含有的MOAH/MOSH的质量浓度不能超过0.1%, 否则出货 到法国被抽检出现问题, 供应商需要对此负责; 5.订单备注显示有分批的(不同仓库/订单号), 一定要区分客户订单号做货出货，否则会导致罚款 。 6.包装日期码按ZURU格式即可，请确保不迟于外箱日期码，可等于或者早于外箱日期码，必须为法定工作日。 7.做货前请先复核包装条码与订单是否一致再安排，对不上的需与ZURU跟单确认再安排。 8.包装必须含法国回收标(Sorting Label)，如没有，请提醒跟单提供贴纸资料。 新桶身小硅胶管柱加高：未打防水胶+新开小一点有硅胶套 | Z21: Sherry Lu | AA21: 9.86 | AB21: =I21*AA21 -> 4377.84 | AD21: 71172-S001-3L | AE21: 已入 | AO21: =I21 -> 444 | AQ21: =I21 -> 444 | AR21: =I21 -> 444
A22: 46083 | B22: AMAZON.COM SERVICES LLC | C22: 美国 | D22: 4500194919 | E22: 2ZFDDQ7I | F22: 4500194919-10 | G22: 71172-S003-MB | H22: 大脑（邮包盒装） | I22: 268 | J22: 0 | K22: 4 | L22: =I22/K22 -> 67 | M22: 46140 | N22: 46142 | O22: N/A | P22: PASS | Q22: 5/5截SI | S22: 有 | T22: 46084 | U22: 46123 | Y22: 日期码格式：ZURU INC(BVI) 标准格式 日期：按实际生产日期 Packaging Info: #71172:MA 1L UPC版本 #71172带MA包装入邮包盒，邮包盒图稿翻单4500192525。 Remark: 1. Amazon MDDP订单，出口US。 2. 日期码使用ZURU标准版本。 3. 如果大货有要求入邮包盒，则对应的邮包盒上面要打上日期码。 4. 箱尺寸要求：外箱最长边不能超过25"(超过了，case pack只能为1)，不符合要求的大货，一律不接受。 5. 外箱箱唛要求： ①外箱正面印ZURU Logo+SSCC Label(客供贴纸，由跟单订购)。关于 SSCC Label 请注意： SSCC Label显示的是客人自己的item#。每一张SSCC label都是唯一且有不同流水及条码的，没有损耗，绝对不可贴错。如果贴错或损坏任何一张，都会导致全部都 错，千万要注意！SSCC Label必须贴在外箱正面的正中间位置(贴一面即可)，并且贴纸离外箱边距必须至少3cm(可以覆盖Logo<(>&<)>箱唛)，否则会影响到客户那边 仓库的扫描识别。 ②外箱侧面印item#(订单上显示的SKU#)+carton size(以工厂实际尺寸为准，单位: inch)+MADE IN CHINA，日期使用ZURU 标准版本。 6. 装柜要求：按照客户PO#装柜/箱号顺序装柜，跟单会提前给到装柜计划。 在大货生产/仓库存放时，请留意该装柜要求，以便装柜时不混乱(避免装错/装漏/找不到货号等)。 新桶身小硅胶管柱加高：未打防水胶+新开小一点有硅胶套 | Z22: Kelly Shen/Mia Pan/P | AA22: 5.916 | AB22: =I22*AA22 -> 1585.488 | AC22: ZB05654-8.17 | AD22: 71172-S003-MB-1L | AE22: 已入 | AO22: =I22 -> 268 | AP22: =I22 -> 268 | AR22: =I22 -> 268
A23: 46065 | B23: TARGET US | C23: 美国 | D23: 4500193070 | E23: 10001662884-3891 | F23: 4500193070-10 | G23: 71172-S001 | H23: 大脑 | I23: 2500 | J23: 0 | K23: 4 | L23: =I23/K23 -> 625 | M23: 46135 | N23: 46148 | O23: N/A | P23: PASS | Q23: 5/6客上柜 | S23: 有 | T23: 46085 | U23: 2/7收到Event Label,3/12收外箱贴纸 | Y23: 日期码格式：ZURU INC(BVI) 标准格式 日期：按实际生产日期 Packaging Info: 产品包装MA 1L彩盒 Remark: 1. 71172-S001-ROBO ALIVE-BRAIN-SERIES 1-BRIAN THE BRAIN-OPEN BOX-4PCS/CTN 2. 产品包装MA 1L彩盒；彩盒上的UPC显示193052098443； 3. 每个外箱正唛箱唛信息左上方位置粘贴条码箱贴纸，每箱只贴一张; 由ZURU向艾利订购， 对应的外箱贴DPCI：087-02-9468, UPC显示10193052098440 ； 4. 每个外箱正唛信息的右侧需要贴一张Event Label，贴纸内容显示 7/19 TRANSITION TOYS Set Date 7/19/2026，工厂自行订购； 5. 产品和包装上要印刷tracking code信息，格式为ZURU常规； 6. 出货方式：货代自提 | Z23: Holly Zheng | AA23: 5.82 | AB23: =I23*AA23 -> 14550 | AC23: ZB05674-8.17 | AD23: 71172-S001 | AE23: 已入 | AO23: =I23 -> 2500 | AP23: =I23 -> 2500 | AR23: =I23 -> 2500
A24: 46104 | B24: MEIJER DISTRIBUTION, INC. | C24: 美国 | D24: 4500198132 | E24: 219222806 | F24: 4500198132-10 | G24: 71172-S004 | H24: 大脑 | I24: 976 | J24: 0 | K24: 2 | L24: =I24/K24 -> 488 | M24: 46148 | N24: 46148 | O24: N/A | P24: PASS | Q24: 5/7截仓 | S24: 无 | T24: 46104 | U24: 无 | Y24: 日期码格式：ZURU INC(BVI) 标准格式 日期： Packaging Info: 1. MA UPC包装（优先1L） 2. 客人指定箱唛排版 Remark: 出货前 Zuru QC 验货 | Z24: Agnes Zheng | AA24: 5.82 | AB24: =I24*AA24 -> 5680.32 | AC24: ZB05652-8.17 | AD24: 71172-S004-1L | AE24: 已入 | AO24: =I24 -> 976 | AP24: =I24 -> 976 | AR24: =I24 -> 976
A25: 46104 | B25: MEIJER DISTRIBUTION, INC. | C25: 美国 | D25: 4500198132 | E25: 219222804 | F25: 4500198132-20 | G25: 71172-S004 | H25: 大脑 | I25: 526 | J25: 0 | K25: 2 | L25: =I25/K25 -> 263 | M25: 46148 | N25: 46148 | O25: N/A | P25: PASS | Q25: 5/8截仓 | S25: 无 | T25: 46104 | U25: 无 | Y25: 日期码格式：ZURU INC(BVI) 标准格式 日期： Packaging Info: 1. MA UPC包装（优先1L） 2. 客人指定箱唛排版 Remark: 出货前 Zuru QC 验货 | Z25: Agnes Zheng | AA25: 5.916 | AB25: =I25*AA25 -> 3111.816 | AC25: ZB05652-8.17 | AD25: 71172-S004-1L | AE25: 已入 | AO25: =I25 -> 526 | AP25: =I25 -> 526 | AR25: =I25 -> 526
A26: 46122 | B26: BIG W | C26: 澳大利亚 | D26: 4500201310 | E26: 47948601 | F26: 4500201310-10 | G26: 71172-S001 | H26: 大脑 | I26: 600 | J26: 0 | K26: 4 | L26: =I26/K26 -> 150 | M26: 46151 | N26: 46149 | O26: N/A | P26: PASS | Q26: 5/7装柜 | S26: 无 | T26: 46122 | U26: 46122 | Y26: 日期码格式：ZURU INC(BVI) 标准格式 日期：按实际生产日期 Packaging Info: 1. 包装 71172: 英文MA包装 (UPC版本，首选1L，无1L可用多L含英语)+1张进口商贴纸 2. 产品和包装上的日期码一致，请按要求在包装上打日期码（进口商贴纸不覆盖日期码） 3. 使用ZURU标准日期码 Remark: 1. 共出4港口 (SYD, BNE, MEL, FRE)，不同港口数量信息请见订单行项目，并请参考箱唛资料，港口不同，箱唛资料也不同； 2. 箱唛不可出现任何手写内容（箱数除外），重量与实际一致且不可手写； 3. 此单出澳大利亚，请按澳洲标准生产并满足当地法规要求； 4. 出无闪粉版本，需符合欧洲微塑料法规； 5. 确保所出货的产品及包装不含PFAS（全氟/多氟烷基化合物）及其盐类和其相关物质，特别留意 PFOA、PFOS、PFHxS 不得检出。 | Z26: Christine Liao | AA26: 9.7 | AB26: =I26*AA26 -> 5820 | AD26: 71172-S001-1L | AE26: 已入 | AO26: =I26 -> 600 | AP26: =I26 -> 600 | AR26: =I26 -> 600
A27: 46022 | D27: ZMPO251178 | G27: 71172-S001 | H27: 大脑 | I27: 200 | J27: 0 | K27: 4 | L27: =I27/K27 -> 50 | M27: 46042 | N27: 46150 | O27: N/A | P27: PASS | R27: 用第二次PP阶段订购的彩盒包装 | S27: N/A | T27: 空白箱 | U27: 无 | Y27: Remark:跟PP订单一起安排/大货标准箱装箱/箱唛请参照邮件附件 备注：收到样品订单后尽快安排 ，注意样板品质质量要求要高于大货品质要求 ，送货时必须要附带送货单(没有送货单和QC检验合格报告的仓库一律拒绝收货)，请知悉，谢谢！ | AD27: 71172-S001-1L | AE27: 已入 | AO27: =I27 -> 200 | AP27: =I27 -> 200 | AR27: =I27 -> 200
A28: 46051 | B28: ZURU LLC | C28: 美国 | D28: 4500192525 | E28: 5200008815 | F28: 4500192525-10 | G28: 71172-S003-MB-MTS | H28: 大脑（邮包盒装） | I28: 1000 | J28: 0 | K28: 4 | L28: =I28/K28 -> 250 | M28: 46148 | N28: 46150 | O28: N/A | P28: PASS | Q28: 5/22 SI | S28: 无 | T28: 46059 | U28: 无 | Y28: 日期码格式：ZURU INC(BVI) 标准格式 日期：按实际生产日期 Packaging Info: #71172:MA 1L UPC版本 #71172带MA包装入邮包盒，邮包盒图稿跟单提供。 Remark: 1.Amazon domestic 订单。出口美国。外箱最长边不能超过25" （超过了，case pack只能为1），不符合要求的大货，一律不接受。 2.无第三方验货/测试要求。 3.日期码使用ZURU标准版本。 4.如果大货有要求入邮包盒，则对应的邮包盒上面要打上日期码。 | Z28: SD24 | AA28: 5.916 | AB28: =I28*AA28 -> 5916 | AC28: ZB05746-8.17 | AD28: 71172-S003-MB-MTS | AE28: 已入 | AO28: =I28 -> 1000 | AP28: =I28 -> 1000 | AR28: =I28 -> 1000
A29: 46108 | B29: AMAZON EU SARL, NDL DEUTSCHLAND | C29: 英国 | D29: 4500198640 | E29: 1VCZUJZI | F29: 4500198640-280 | G29: 71172-S003-MB | H29: 大脑（邮包盒装） | I29: 712 | J29: 0 | K29: 4 | L29: =I29/K29 -> 178 | M29: 46150 | N29: 46150 | O29: N/A | P29: PASS | Q29: 46161 | S29: 有 | T29: 46108 | U29: 46139 | Y29: 日期码格式：ZURU INC(BVI) 标准格式 日期：按实际生产日期 Packaging Info: Amazon UK: 5TKIJIXX/3O77XWME/2EIMZ29W/1VCZUJZI/7N1D8FUG/5Z2UXPOL/5PNQ9H8L Amazon DE: 4EO3QWQS/3LFCI9MA/115AX8DW Amazon FR: 6VRKJU2V Amazon ES: 53YR16IV Amazon IT: 5D2ZS8EV Amazon UK(157114DG/157140/157143/15780ABD/15788G/71172/77878/92146BDG/92147E)/DE(157114G/15788BG/92146GH/92147E)/FR(92146G)/ES(157143/77858)/IT( 157140/157143/92146G) 1. 157114DG ---157114D: 1pc 15787D 9"(Rabid Rabbit) into mailbox, 12mailboxes/ctn; 客版邮包盒(参考Amazon US翻单PO#4500192979); ---157114G: 1pc 15787G 9"(Mr Screech) into mailbox, 12mailboxes/ctn; 客版邮包盒(参考Amazon US翻单PO#4500192979); 2. 157140: 2PK 15774 into window box respectively, then into polybag, 6polybags/ctn, MA 5L(5L warning UPC)B 开窗彩盒+1张贴纸(含IT环保标+西班牙洗 涤说明,参考翻单PO#4500198613)+客版透明胶袋(双面打孔+含英法德意西警告语+塑料循环标, 参考翻单PO#4500166364)+1张UPC#贴纸(贴在胶袋上,参考翻单PO#450 0198613)+1张空白贴纸(贴在彩盒条码位置, 参考翻单PO#4500198613); 3. 157143: 8PK 157117 IN MAIL BOX,12mailboxes/ctn; 8 Assortment=1:1:1:1:1:1:1:1; 客版邮包盒(参考Amazon US翻单PO#4500195274); 4. 15780ABD: ---15780A: 1pc 15780A(Rabid Rabbit/Sir Nobbynuts/Nobbybits) in window box, then into polybag,12polybags/ctn; MA 5L(5L warning UPC)B开窗彩盒+MA其 它最新配套包装+客版透明胶袋(含英法德意西荷兰警告语+双面打孔+塑料循环标)+1张贴纸(含UPC#+IT环保标+ES洗涤说明); ---15780B: 1pc 15780B(Sasquoosh/Stinkface/Squooshface) in window box, then into polybag,12polybags/ctn; MA 5L(5L warning UPC)B开窗彩盒+MA其它最 新配套包装+客版透明胶袋(含英法德意西荷兰警告语+双面打孔+塑料循环标)+1张贴纸(含UPC#+IT环保标+ES洗涤说明); ---15780D: 1pc 15780D(Munch Munch/Reek-o/Munch-o) in window box, then into polybag,12polybags/ctn; MA 5L(5L warning UPC)B开窗彩盒+MA其它最新配套 包装+客版透明胶袋(含英法德意西荷兰警告语+双面打孔+塑料循环标)+1张贴纸(含UPC#+IT环保标+ES洗涤说明); 5. 15788BG: ---15788B: 1pc 15788B 9"(Sir Nobbynuts) in window box,then into polybag, 12polybags/ctn; Global onshelf date after 2026/7/9; MA 5L(5L warning UP C)A开窗彩盒+MA其它最新配套包装+客版胶袋(含英法德意西荷兰警告语+双面打孔+塑料循环标,参考翻单PO#4500164364)+2张贴纸(1张含UPC#<(>&<)>IT环保标<(>& <)>ES洗涤说明贴纸+1张上架日期贴纸) ---15788G: 1pc 15788G 9"(Sir Belch) in window box,then into polybag, 12polybags/ctn; Global onshelf date after 2026/7/9; MA 5L(5L warning UPC)A 开窗彩盒+MA其它最新配套包装+客版胶袋(含英法德意西荷兰警告语+双面打孔+塑料循环标,参考翻单PO#4500164364)+2张贴纸(1张含UPC#<(>&<)>IT环保标<(>&<)>E S洗涤说明贴纸+1张上架日期贴纸) 6.71172: 1pc 71172 BRIAN THE BRAIN into open box, then into mailbox, 4mailboxes/ctn; 3PCS AA BATTERIES(INCLUDED); MA 1L(23L warning UPC)A开口彩 盒+MA 15L A说明书+客版邮包盒(参考Amazon US翻单PO#4500192525)+WEEE_带电池走货 _ 说明书欧洲EN+30L_B版; 7. 77878: 2pk 77843 in PVC tube,12tubes/ctn;Contain Sand, UV Glue and Cream Glue; SUSHI and RAINBOW CAKE(Rare) without batteries, other assortme nts: 6PCS AG13 BATTERIES(INCLUDED); Ratio: PIZZA: HAMBURGER: PANCAKES: BUBBLE TEA: Matcha TEA: TACO: SUSHI: DONUT: Charcuterie Board: RAINBOW C AKE(Rare)=10.88%: 10.88%: 10.88%: 10.88%: 10.88%: 10.88%: 10.88%: 10.88%: 10.88%: 2.08%=68:68:68:68:68:68:68:68:68:13; MA 1L(1L Warning UPC)A收 缩膜+1张空白贴纸(覆盖收缩上条码, 参考Amazon US翻单PO#4500192514)+MA 5L A收藏指南+MA 23L warning A SUSHI <(>&<)> RAINBOW CAKE说明书+MA 23L warni ng A UV Glue说明书+客版3L(3L warning UPC)A彩卡(参考Amazon US翻单PO#4500192514，新UK地址)+1张贴纸(含DE/IT警告语+IT环保标)+WEEE_带电池走货 _ 说明 书欧洲EN+30L_B版; 8. 92146BDGH: ---92146B: 1pc 92146B SMALL(Raccoon) into shrink wraps,24pcs/ctn;Bubble powder;NO Boron; MA 3L(8L warning EAN)A收缩膜+MA其它最新配套包装+MA 5L( 19L warning)A收藏指南+1张贴纸(含UPC+IT环保标+ES洗涤说明贴纸); ---92146D: 1pc 92146D SMALL(Deer) into shrink wraps,24pcs/ctn;Bubble powder;NO Boron; MA 3L(8L warning EAN)A收缩膜+MA其它最新配套包装+MA 5L(19L warning)A收藏指南+1张贴纸(含UPC+IT环保标+ES洗涤说明贴纸); ---92146G: 1pc 92146G SMALL(Pigeon) into shrink wraps,24pcs/ctn;Bubble powder;NO Boron; MA 3L(8L warning EAN)A收缩膜+MA其它最新配套包装+MA 5L(19 L warning)A收藏指南+1张贴纸(含UPC+IT环保标+ES洗涤说明贴纸); ---92146H: 1pc 92146H SMALL(Owl) into shrink wraps,24pcs/ctn;Bubble powder;NO Boron; MA 3L(8L warning EAN)A收缩膜+MA其它最新配套包装+MA 5L(19L w arning)A收藏指南+1张贴纸(含UPC+IT环保标+ES洗涤说明贴纸); 9. 92147E: 1pc 92147E LARGE(Unicorn) into shrink wrap, then into mailbox, 4mailboxes/ctn; MA 3L(8L warning EAN)A收缩膜+MA 5L(19L warning)A收藏指 南+MA 5L(19L warning)A Magic guide book说明书+MA其它最新配套包装+客版邮包盒; 10. 77858: 1pc 77858 playset into mailbox, 3mailboxes/ctn; Including magnets; 3PCS AA BATTERIES(NOT INCLUDED); MA 3L(23L warning EAN)A 透明PVC窗 彩盒+MA 23L warning A 电池黑白说明书+MA 5L A收藏指南+MA其它最新配套包装+客版邮包盒(参考Amazon US翻单PO#4500192979)+WEEE_不带电池走货 _ 说明书欧 洲EN+30L_B版 11.验货时间不迟于2026/5/11. 注意：77858需将邮包盒尺寸图<(>&<)>重量图放进验货报告； Remark: 1.空白外箱（加印带Zuru字样的最新logo，除了邮包盒直接做外箱的产品） + SSCC LABEL一张, 无箱唛，MADE IN CHINA 外箱只印一正一侧。箱唛资料按照给定的 标准去做即可，无需发回我方再行审批(新标准将另行通知)。 (SSCC LABEL竖贴在外箱正面的正中间，贴一面即可,贴纸离外箱边距必须至少3.2CM。如竖贴无法满足要求，则横贴。如横贴也无法满足要求，则竖贴，遮到ZURU lo go无影响), SSCC贴纸由工厂直接跟勤得采购或者工厂自行采购，每一张SSCC Label都是唯一且有不同流水及条码，且需要检查条码是否能正常扫描，另外，此贴纸 印刷不可出现模糊，溢出及粘胶不牢易脱落等现象，如工厂不按此要求导致贴纸有任何问题产生的罚款将由工厂承担一切责任 ,<(>,<)> 此要求只适用Amazon UK/DE /FR/ES/IT,不适用Amazon GPE，Amazon GPE无SSCC label, 但是有对应箱唛，需印刷到外箱 。 2.出往UK的产品+包装务必打上UKCA logo ，否则客人会退货且当地会有罚款。 3.订单必须经过ZURU QC验货或者工厂自检通过后方可出货，不涉及第三方验货。 4.法国订单要求包装不使用矿物油，请按要求提供以下其中一份文件再出货 ，产品出到法国被相关部门抽检出现包装不符合此要求的，供应商需要为此承担责任， 故此请严格把关。 -油墨物质""""由1 ~ 7个芳香环组成的MOAH""""的包装检测报告，要求限值≤1.0%； -包装材料清单，包括包装油墨或物质的信息； -油墨制造商的证书； 5.每一批次出货只能有一个生产日期，不可多个生产日期混在同一批次出货；且零售包装上必须统一加上日期码；外箱对于日期码没有硬性规定； 6.涉及到相关款式会有闪粉的或者微塑料的，请统一默认出无闪粉或者不含微塑料版本； 7.邮包盒及外箱封箱必须是工字型封箱方式； 8.5 Surprise or Mini Brands涉及包装是2个及2个以上的球入PVC桶包装时，单个球上若有UPC#或者EAN#，请用空白贴纸覆盖住，贴纸尺寸自行测量能覆盖原条码即 可； 9. 无论是工厂自检还是ZURU验货，验货报告中必须有产品6面图(正面/背面/左面/右面/顶部/底部，不带包装); 10. 按空海运鉴定报告的要求，只要带锂电池出货，都需要加贴UN贴纸； 11. 所有出往GAS市场(德国/奥地利/瑞士)的电子产品身上需要加字唛，为ZURU FRANCE 地址，需跟包装上的地址一致 (如无电子产品，产品布标有此地址，或产品 太小无法增加可忽略此信息。如产品无法加字唛，需让对应跟单提供产品贴纸资料); 12. 所有出往GAS德国 (瑞士，奥地利)。水弹枪系列必须使用EN71版本（电子和非电子水弹枪系列都需要符合); 护目镜需打日期码, 格式跟ZURU标准格式一样; 枪 身上增加ZURU FRANCE公司名和地址。使用贴纸和辐射上去都可以。如果有位置，最好增加ZURU Represented by: (此最好翻译德语，如果位置不允许，那么就只增 加ZURU法国和地址)。使用最新的EN71版包装和说明书）. | Z29: Luna Lin | AA29: 9.86 | AB29: =I29*AA29 -> 7020.32 | AD29: 71172-S003-MB-1L | AE29: 已入 | AO29: =I29 -> 712 | AP29: =I29 -> 712 | AR29: =I29 -> 712
A30: 46122 | B30: BIG W | C30: 澳大利亚 | D30: 4500201310 | E30: 47948602 | F30: 4500201310-20 | G30: 71172-S001 | H30: 大脑 | I30: 520 | J30: 0 | K30: 4 | L30: =I30/K30 -> 130 | M30: 46151 | N30: 46150 | O30: N/A | P30: PASS | Q30: 5/9入仓 | S30: 无 | T30: 46122 | U30: 46122 | Y30: 日期码格式：ZURU INC(BVI) 标准格式 日期：按实际生产日期 Packaging Info: 1. 包装 71172: 英文MA包装 (UPC版本，首选1L，无1L可用多L含英语)+1张进口商贴纸 2. 产品和包装上的日期码一致，请按要求在包装上打日期码（进口商贴纸不覆盖日期码） 3. 使用ZURU标准日期码 Remark: 1. 共出4港口 (SYD, BNE, MEL, FRE)，不同港口数量信息请见订单行项目，并请参考箱唛资料，港口不同，箱唛资料也不同； 2. 箱唛不可出现任何手写内容（箱数除外），重量与实际一致且不可手写； 3. 此单出澳大利亚，请按澳洲标准生产并满足当地法规要求； 4. 出无闪粉版本，需符合欧洲微塑料法规； 5. 确保所出货的产品及包装不含PFAS（全氟/多氟烷基化合物）及其盐类和其相关物质，特别留意 PFOA、PFOS、PFHxS 不得检出。 | Z30: Christine Liao | AA30: 9.7 | AB30: =I30*AA30 -> 5044 | AD30: 71172-S001-1L | AE30: 已入 | AO30: =I30 -> 520 | AP30: =I30 -> 520 | AR30: =I30 -> 520
A31: 46122 | B31: BIG W | C31: 澳大利亚 | D31: 4500201310 | E31: 47948603 | F31: 4500201310-30 | G31: 71172-S001 | H31: 大脑 | I31: 488 | J31: 0 | K31: 4 | L31: =I31/K31 -> 122 | M31: 46151 | N31: 46150 | O31: N/A | P31: PASS | Q31: 5/9入仓 | S31: 无 | T31: 46122 | U31: 46122 | Y31: 日期码格式：ZURU INC(BVI) 标准格式 日期：按实际生产日期 Packaging Info: 1. 包装 71172: 英文MA包装 (UPC版本，首选1L，无1L可用多L含英语)+1张进口商贴纸 2. 产品和包装上的日期码一致，请按要求在包装上打日期码（进口商贴纸不覆盖日期码） 3. 使用ZURU标准日期码 Remark: 1. 共出4港口 (SYD, BNE, MEL, FRE)，不同港口数量信息请见订单行项目，并请参考箱唛资料，港口不同，箱唛资料也不同； 2. 箱唛不可出现任何手写内容（箱数除外），重量与实际一致且不可手写； 3. 此单出澳大利亚，请按澳洲标准生产并满足当地法规要求； 4. 出无闪粉版本，需符合欧洲微塑料法规； 5. 确保所出货的产品及包装不含PFAS（全氟/多氟烷基化合物）及其盐类和其相关物质，特别留意 PFOA、PFOS、PFHxS 不得检出。 | Z31: Christine Liao | AA31: 10.75 | AB31: =I31*AA31 -> 5246 | AD31: 71172-S001-1L | AE31: 已入 | AO31: =I31 -> 488 | AP31: =I31 -> 488 | AR31: =I31 -> 488
A32: 46122 | B32: BIG W | C32: 澳大利亚 | D32: 4500201310 | E32: 47948604 | F32: 4500201310-40 | G32: 71172-S001 | H32: 大脑 | I32: 192 | J32: 0 | K32: 4 | L32: =I32/K32 -> 48 | M32: 46151 | N32: 46150 | O32: N/A | P32: PASS | Q32: 5/9入仓 | S32: 无 | T32: 46122 | U32: 46122 | Y32: 日期码格式：ZURU INC(BVI) 标准格式 日期：按实际生产日期 Packaging Info: 1. 包装 71172: 英文MA包装 (UPC版本，首选1L，无1L可用多L含英语)+1张进口商贴纸 2. 产品和包装上的日期码一致，请按要求在包装上打日期码（进口商贴纸不覆盖日期码） 3. 使用ZURU标准日期码 Remark: 1. 共出4港口 (SYD, BNE, MEL, FRE)，不同港口数量信息请见订单行项目，并请参考箱唛资料，港口不同，箱唛资料也不同； 2. 箱唛不可出现任何手写内容（箱数除外），重量与实际一致且不可手写； 3. 此单出澳大利亚，请按澳洲标准生产并满足当地法规要求； 4. 出无闪粉版本，需符合欧洲微塑料法规； 5. 确保所出货的产品及包装不含PFAS（全氟/多氟烷基化合物）及其盐类和其相关物质，特别留意 PFOA、PFOS、PFHxS 不得检出。 | Z32: Christine Liao | AA32: 10.75 | AB32: =I32*AA32 -> 2064 | AD32: 71172-S001-1L | AE32: 已入 | AO32: =I32 -> 192 | AP32: =I32 -> 192 | AR32: =I32 -> 192
A33: 46112 | B33: 360 SALES SOLUTIONS INC | C33: 加拿大 | D33: 4500199523 | E33: 2026ZURU09 | F33: 4500199523-20 | G33: 71172-S001 | H33: 大脑 | I33: 320 | J33: 0 | K33: 4 | L33: =I33/K33 -> 80 | M33: 46154 | N33: 46154 | O33: N/A | P33: PASS | Q33: 5/14 12:00前交仓 | S33: 无 | T33: 46119 | U33: 46122 | Y33: 日期码格式： 标准格式 日期：按实际生产日期 Packaging Info: 71172 MA 多语EAN+UPC贴纸193052098443 Remark: 出加拿大 Zuru验货. 日期跟踪码：产品外包装及产品本身都必须有日期跟踪码，ZURU标准格式日期码。（箱唛日期码按跟单提供格式） | Z33: Katrina | AA33: 9.86 | AB33: =I33*AA33 -> 3155.2 | AD33: 71172-S001-3L | AE33: 已入 | AO33: =I33 -> 320 | AQ33: =I33 -> 320 | AR33: =I33 -> 320
A34: 46090 | B34: LLC SALUS | C34: 俄罗斯联邦 | D34: 4500195784 | F34: 4500195784-80 | G34: 71172-S001 | H34: 大脑 | I34: 100 | J34: 0 | K34: 4 | L34: =I34/K34 -> 25 | M34: 46154 | N34: 46156 | O34: N/A | P34: PASS | S34: 有 | T34: 46098 | U34: 46113 | Y34: 日期码格式：ZURU INC(BVI) 标准格式 日期：按实际生产日期 Packaging Info: 71172: 1L MA UPC 彩卡+ 进口商贴纸+QR code (一物一码) ，MA 说明书。 Remark: 出厂价 ； 注意： 1. QR 贴纸要求： 需包含产品型号（item）+ 序列号，二维码（QR code）正方形边长 1.5cm 。 材质与粘性：采用与进口商贴纸一致的材质，强粘性、不易脱落/掉色。 印刷与尺寸：印刷质量不低于 1.5c，整体贴纸尺寸为 3×3cm（正方形）。 2. 二维码贴纸位置要远离包装上的条码及其他二维码， 贴在背面。 3. QR code贴纸（要求一物一码，每PCS的二维码不一样）; 4. QR code 格式 ：DATA MATRIX GS1 ； | Z34: Ann | AA34: 9.7 | AB34: =I34*AA34 -> 970 | AD34: 71172-S001-1L | AE34: 已入 | AO34: =I34 -> 100 | AP34: =I34 -> 100 | AR34: =I34 -> 100
A35: 46113 | B35: PT.MAP AKTIF ADIPERKASA, TBK | C35: 印度尼西亚 | D35: 4500199667 | F35: 4500199667-10 | G35: 71172-S001 | H35: 大脑 | I35: 208 | J35: 0 | K35: 4 | L35: =I35/K35 -> 52 | M35: 46154 | N35: 46156 | O35: 有 | P35: 第三方抽样，需提前准备多7套样办 | Q35: 6/4交仓 | S35: 无 | T35: 46120 | U35: 46128 | Y35: 日期码格式：ZURU INC(BVI) 标准格式 日期：按实际生产日期 Packaging Info: MA UPC包装（优先1L)+1张进口商贴纸,待提供9574/71172的贴纸资料 Remark: 9574-2pcs baby capybara: 3pcs baby capybara= 5:1 | Z35: Emma Wu | AA35: 9.7 | AB35: =I35*AA35 -> 2017.6 | AD35: 71172-S001-1L | AE35: 已入 | AO35: =I35 -> 208 | AP35: =I35 -> 208 | AR35: =I35 -> 208
A36: 46115 | B36: T. PLANET SHOPS SL | C36: 西班牙 | D36: 4500200070 | E36: 22362602 | F36: 4500200070-10 | G36: 71172-S001 | H36: 大脑 | I36: 1200 | J36: 0 | K36: 4 | L36: =I36/K36 -> 300 | M36: 46160 | N36: 46157 | O36: N/A | P36: PASS | Q36: 46184 | S36: 无 | T36: 46126 | U36: 46136 | W36: 202602 | Y36: 日期码格式：202602 日期： Packaging Info: 1.71172:【最新MA 3L EAN版本包装+一张客户进口商内容贴纸】+最新MA 15L说明书+一张产品贴纸+WEEE带电池走货欧洲29L通用黑白说明书； 2.9574:【最新MA 3L EAN版本包装+一张客户进口商内容贴纸】+最新MA 5L说明书+WEEE不带电池走货欧洲29L通用黑白说明书； 3.77711SK1:【MA 3L EAN版本包装+一张客户进口商贴纸（含西班牙环保标)】+MA 收藏指南+MA 23L说明书+MA 3L 展示架； 4.77843GQ2:【MA 3L EAN版本包装+一张客户进口商贴纸（含西班牙环保标)】+MA 收藏指南+MA 23L说明书+MA 3L PDQ+WEEE带电池走货欧洲29L通用黑白说明书； 5.77843SK1:【MA 3L EAN版本包装+一张客户进口商贴纸（含西班牙环保标)】+MA 收藏指南+MA 23L说明书+MA 3L 展示架+WEEE带电池走货欧洲29L通用黑白说明书 ； 6.157117UQ1:【MA 3L包装+一张客户进口商贴纸+一张Mother EAN条码贴纸】+MA PDQ； 7.15788:【MA 5L包装+一张客户进口商贴纸+一张Mother EAN条码贴纸】； 8.15783UQ1:【最新MA 5L包装+一张客户进口商贴纸+一张EAN条码贴纸】+MA PDQ； 9.92146TQ1:【MA 3L EAN版本包装+一张客户进口商内容贴纸】+MA 5L收藏指南+一张产品贴纸； 10.92147:【MA 3L EAN版本包装+一张客户进口商内容贴纸】+MA 5L说明书+一张产品贴纸； Remark: 1. 此单出西班牙，需满足EU测试标准要求，另外微塑料需符合EU法规； 2. 标准配比； 3.根据新电池法规（EU） 2023/1542，所有走欧洲市场的电子产品，都需要增加WEEE通用29L说明书（分带电池走货和不带电池走货两种），如工厂没有此文件，可 以找我们跟单提供； 4. 准时完货，需安排ZURU OQC验货并要求提供客户格式的自检报告给到客户审批放货。 另外，包装贴纸上面的警告语不可以覆盖西班牙警告语。 5. 此单需要每款准备3套大货样，请注意备料； 6.注意： 同款产品含PDQ /展示架的外箱条码需要跟item包装条码不一样; 7.此单客户指定日期码：202602 | Z36: Mary Zhong | AA36: 9.86 | AB36: =I36*AA36 -> 11832 | AD36: 71172-S001-3L | AE36: 已入 | AO36: =I36 -> 1200 | AQ36: =I36 -> 1200 | AR36: =I36 -> 1200
A37: 46114 | B37: NUEVOS ALMACENES, S.A. | C37: 危地马拉 | D37: 4500199843 | E37: 4504719305 | F37: 4500199843-10 | G37: 71172-S001 | H37: 大脑 | I37: 240 | J37: 0 | K37: 4 | L37: =I37/K37 -> 60 | M37: 46162 | N37: 46157 | O37: N/A | P37: PASS | S37: 无 | T37: 46127 | U37: 46137 | Y37: 日期码格式：ZURU INC(BVI) 标准格式 日期： Packaging Info: MA 多语包装+UPC贴纸+箱唛，无客户贴纸 Remark: 订单需提交自检报告，客户审核通过才可以出货。 外箱上的箱唛资料显示客户指定日期30-MAY-2026,产品/包装/外箱可以按ZURU 标准日期码打，也可以跟回外箱日期码，工厂自行选择,两者均可接受 | Z37: Ava Liang | AA37: 9.86 | AB37: =I37*AA37 -> 2366.4 | AD37: 71172-S001-3L | AE37: 已入 | AO37: =I37 -> 240 | AQ37: =I37 -> 240 | AR37: =I37 -> 240
A38: 46129 | D38: ZMPO260410 | F38: ZMPO260410-10 | G38: 71172-S001 | H38: 大脑 | I38: 200 | J38: 0 | K38: 4 | L38: =I38/K38 -> 50 | M38: 46162 | N38: 46157 | O38: N/A | P38: PASS | S38: 无 | T38: 46129 | U38: 无 | Y38: Remark大货版本/大货标准箱装箱/箱唛请参照邮件附件 备注：收到样品订单后尽快安排 ，注意样板品质质量要求要高于大货品质要求 ，送货时必须要附带送货单(没有送货单和QC检验合格报告的仓库一律拒绝收货)，请知悉，谢谢！ | Z38: Angus | AD38: 71172-S001-1L | AE38: 已入 | AO38: =I38 -> 200 | AP38: =I38 -> 200
A39: 46121 | B39: WALMART INC. | C39: 美国 | D39: 4500200590 | E39: 0988641197 | F39: 4500200590-40 | G39: 71172-S002 | H39: 大脑 | I39: 976 | J39: 0 | K39: 1 | L39: =I39/K39 -> 976 | M39: 46163 | N39: 46162 | O39: 6/3 BV公证行验货+抽办,6/8 | P39: PASS | S39: 有 | T39: 46121 | U39: 4/9-粉色MOD艾利贴纸,4/22收RFID贴纸 | Y39: 日期码格式：DGYYYYMMDD(日期避开周末和法定节假日) 日期：按实际生产日期 Packaging Info: 此单为WMUS首单，需安排产中抽板，抽板时间：2026/5/21，抽板WMPO: 0988641197，抽板需完成订单数量506PCS，抽走6PCS给到测试行，请自行多备包装物料。请 于抽板前寄出5PCS样板给到我签板。 1.包装方式： 71172: MA 1L彩盒包装+MA 15L警告语 A版说明书+ RFID贴纸 Remark: 2. 外箱四面印刷紫色RFID箱唛 主唛左前下角印刷艾利贴纸替代标箱唛(ITF-14格式)，条码只印刷一面 主唛右下角加印 MADE IN CHINA以及ZURU LOGO，对角线位置加贴一张粉色MOD艾利贴纸（工厂自行打印或订购贴纸） 3. 71172 UPC：193052098443 4.此批单散箱出货，1PCS/CTN 5.此单需要验货，请自行多备包装物料。 6.产品和包装上要有日期码、MADE IN CHINA和ZURU字样。 7.每PCS要加RFID 贴纸(ZURU提供)，严格按照我们提供的位置图，不可擅自调整位置，贴纸也不可有任何破损或折坏，不可淋湿（如缺数请及时告知） | Z39: Nikki Mo | AA39: 5.916 | AB39: =I39*AA39 -> 5774.016 | AC39: ZB06229-8.17 | AD39: 71172-S002-1L | AE39: 已入 | AO39: =I39 -> 976 | AP39: =I39 -> 976 | AR39: =I39 -> 976
A40: 46121 | B40: WALMART INC. | C40: 美国 | D40: 4500200590 | E40: 0988641171 | F40: 4500200590-30 | G40: 71172-S002 | H40: 大脑 | I40: 1102 | J40: 0 | K40: 1 | L40: =I40/K40 -> 1102 | M40: 46163 | N40: 46162 | O40: 46181 | P40: PASS | S40: 有 | T40: 46121 | U40: 4/9-粉色MOD艾利贴纸,4/22收RFID贴纸 | Y40: 日期码格式：DGYYYYMMDD(日期避开周末和法定节假日) 日期：按实际生产日期 Packaging Info: 此单为WMUS首单，需安排产中抽板，抽板时间：2026/5/21，抽板WMPO: 0988641197，抽板需完成订单数量506PCS，抽走6PCS给到测试行，请自行多备包装物料。请 于抽板前寄出5PCS样板给到我签板。 1.包装方式： 71172: MA 1L彩盒包装+MA 15L警告语 A版说明书+ RFID贴纸 Remark: 2. 外箱四面印刷紫色RFID箱唛 主唛左前下角印刷艾利贴纸替代标箱唛(ITF-14格式)，条码只印刷一面 主唛右下角加印 MADE IN CHINA以及ZURU LOGO，对角线位置加贴一张粉色MOD艾利贴纸（工厂自行打印或订购贴纸） 3. 71172 UPC：193052098443 4.此批单散箱出货，1PCS/CTN 5.此单需要验货，请自行多备包装物料。 6.产品和包装上要有日期码、MADE IN CHINA和ZURU字样。 7.每PCS要加RFID 贴纸(ZURU提供)，严格按照我们提供的位置图，不可擅自调整位置，贴纸也不可有任何破损或折坏，不可淋湿（如缺数请及时告知） | Z40: Nikki Mo | AA40: 5.82 | AB40: =I40*AA40 -> 6413.64 | AC40: ZB06425-8.17 | AD40: 71172-S002-1L | AE40: 已入 | AO40: =I40 -> 1102 | AP40: =I40 -> 1102 | AR40: =I40 -> 1102
A41: 46104 | B41: UPD, INC. | C41: 美国 | D41: 4500198024 | E41: 36245 | F41: 4500198024-30 | G41: 71172-S001 | H41: 大脑 | I41: 180 | J41: 0 | K41: 4 | L41: =I41/K41 -> 45 | M41: 46164 | N41: 46162 | O41: N/A | P41: PASS | Q41: 46167 | S41: 无 | T41: 46133 | U41: 无 | Y41: 日期码格式：ZURU INC(BVI) 标准格式 日期：按实际生产日期 Packaging Info: 1. 包装方式：MA UPC 优先1L 最新包装，出口美国 Remark: 2. 外箱箱唛红色和黑色双色印刷 3. 产品和包装上印刷tracking code信息，格式为ZURU常规 | Z41: Angel Lin | AA41: 5.916 | AB41: =I41*AA41 -> 1064.88 | AC41: ZB05771-8.17 | AD41: 71172-S001-1L | AE41: 已入 | AO41: =I41 -> 180 | AP41: =I41 -> 180 | AR41: =I41 -> 180
A42: 46097 | B42: H-E-B, LP | C42: 美国 | D42: 4500197095 | E42: 60X740350 | F42: 4500197095-40 | G42: 71172-S001 | H42: 大脑 | I42: 276 | J42: 0 | K42: 4 | L42: =I42/K42 -> 69 | M42: 46164 | N42: 46164 | O42: 5/25 100%验货和抽板（多备6PCS) | P42: PASS | Q42: 46185 | S42: 无 | T42: 46125 | U42: 无 | W42: DG20260505 | Y42: 日期码格式：ZURU INC(BVI) 标准格式 日期：按实际生产日期 Packaging Info: 1. 包材：ZURU MA UPC 版本，出口美国； Remark: 2. 日期跟踪码：ZURU标准格式日期码，产品包装及产品本身都必须有ZURU标准格式日期码，并且确保两者信息保持一致(请自行调整具体年月日生产期，但不能为 周末）。 PS: 毛绒款产品包装和布标上日期码可以不一致，但需提前提供照片给到我们找客户特批出货. 3. 大货样 ；#71172； 需在5月6日前每款寄出3套大货样板（含PDQ），样板须跟大货一模一样（含日期码）。 样板一套我们将给到美国HEB，两套寄到以下深圳利丰地址，到时利丰会回签一套用于第三方100%大货验货。 回签的样板工厂需要长期保存好，只要产品没更新每次的第三方验货都是用这套样板做参考不再走客户签样流程。 4. 验货+ 抽板 （同一天进行） ；#71172 验货时间是5月25日 验货时第三方（利丰）到工厂做100%大货现场验货和抽板，验货需打印EPM出来跟客户回签样板供第三方验货参考。 PS:EPM是跟单提供。注意毛绒款在华登厂验货，请留意验货邮件每款的工厂备注。 抽板： 因这款产品的ZURU测试报告上被客户指定实验室发现产品和产品包装上的日期码不一致，所以这款寄样给实验室的是按照利丰验货员现场针对指定款随机抽板6PCS（ 须带包装）。 工厂需把抽板寄到以下MTS 地址做测试，测试通过后才能出货；如产品有油漆的工厂需额外准备5G/色的油漆涂在同材质胶件上(面积类似A4纸大小)一并寄出； 实验室收件地址： 东莞现代产品整理服务有限公司（MTS） 广东省东莞市寮步镇新旧围村良平路76号 收件人：Cherry Wang （汪单） Tel: +86 769- 8112 0818 ext.893 抽板有随样文件TRF（跟单提供），工厂在寄样时打印出来放纸箱内随样寄走。 5. 出货配比：ZURU 标版配比 6. ZURU QA 验货时需拍齐每款角色的产品和产品包装上的日期码照片（供实验室review） | Z42: Elsa Zheng | AA42: 5.916 | AB42: =I42*AA42 -> 1632.816 | AC42: ZB06300-8.17 | AD42: 71172-S001-1L | AE42: 已入 | AO42: =I42 -> 276 | AP42: =I42 -> 276 | AR42: =I42 -> 276
A43: 46114 | B43: MILLS FLEET FARM | C43: 美国 | D43: 4500199572 | E43: 4891217 | F43: 4500199572-180 | G43: 71172-S001 | H43: 大脑 | I43: 520 | J43: 0 | K43: 4 | L43: =I43/K43 -> 130 | M43: 46164 | N43: 46168 | O43: N/A | P43: PASS | Q43: 5/26 SI | S43: 无 | T43: 46132 | U43: 无 | Y43: 日期码格式：ZURU INC(BVI) 标准格式 日期：按实际生产日期 Packaging Info: 1. 包装：ZURU MA 1L UPC版本最新包装；出口美国; Remark: 2. 日期跟踪码：产品包装及产品本身都必须有日期跟踪码，并且确保两者的日期跟踪码要一致；ZURU标准格式日期码(请自行调整具体年月日生产期，但不能为周 末）。 3. 出货配比: Zuru 标准 配比 | Z43: Mila Yao | AA43: 5.916 | AB43: =I43*AA43 -> 3076.32 | AC43: ZB05796-8.17 | AD43: 71172-S001-1L | AE43: 已入 | AO43: =I43 -> 520 | AP43: =I43 -> 520 | AR43: =I43 -> 520
A44: 46120 | B44: ALL BRANDS TOYS PTY LTD | C44: 澳大利亚 | D44: 4500200399 | E44: 86445 | F44: 4500200399-30 | G44: 71172-S001 | H44: 大脑 | I44: 1120 | J44: 0 | K44: 4 | L44: =I44/K44 -> 280 | M44: 46167 | N44: 46168 | O44: N/A | P44: PASS | S44: 无 | T44: 46141 | U44: 46141 | Y44: 日期码格式：ZURU INC(BVI) 标准格式 日期：按实际生产日期 Packaging Info: 71126：MA_UPC版本包装（ MA首选1L，如无1L可用多语且含英语的配套多语UPC包装）+ 1张客人通用进口商贴纸（翻单4500125432）+ 箱唛. 9565GQ1： MA_UPC版本包装（ MA首选1L，如无1L可用多语且含英语的配套多语UPC包装）+ 1张客人通用进口商贴纸(贴纸及其位置图跟回翻单4500172669） 71172：MA_UPC版本包装（ MA首选1L，如无1L可用多语且含英语的配套多语UPC包装）+ 1张客人通用进口商贴纸 + 箱唛. Remark: 1.按实际生产日期; 2.出澳大利亚，请按照相应标准生产; | Z44: Louise Lu | AA44: 9.86 | AB44: =I44*AA44 -> 11043.2 | AD44: 71172-S001-1L | AE44: 已入 | AO44: =I44 -> 1120 | AP44: =I44 -> 1120 | AR44: =I44 -> 1120
A45: 46122 | B45: TARGET US | C45: 美国 | D45: 4500201099 | E45: 10001823930-0581 | F45: 4500201099-10 | G45: 71172-S001 | H45: 大脑 | I45: 1100 | J45: 0 | K45: 4 | L45: =I45/K45 -> 275 | M45: 46169 | N45: 46169 | O45: N/A | P45: PASS | Q45: 46178 | S45: 有 | T45: 46136 | U45: 46148 | Y45: 日期码格式：ZURU INC(BVI) 标准格式 日期：按实际生产日期 Packaging Info: 产品包装MA 1L彩盒； Remark: 1. 71172-S001-ROBO ALIVE-BRAIN-SERIES 1-BRIAN THE BRAIN-OPEN BOX-4PCS/CTN 2. 产品包装MA 1L彩盒；彩盒上的UPC显示193052098443； 3. 每个外箱正唛箱唛信息左上方位置粘贴条码箱贴纸，每箱只贴一张; 由ZURU向艾利订购， 对应的外箱贴DPCI：087-02-9468, UPC显示10193052098440 ； 4. 产品和包装上要印刷tracking code信息，格式为ZURU常规； 5. 出货方式：货代自提 | Z45: Holly Zheng | AA45: 5.82 | AB45: =I45*AA45 -> 6402 | AC45: ZB06069-8.17 | AD45: 71172-S001-1L | AE45: 已入 | AO45: =I45 -> 1100 | AP45: =I45 -> 1100 | AR45: =I45 -> 1100
A46: 46125 | B46: AMAZON EU SARL, NDL DEUTSCHLAND | C46: 英国 | D46: 4500201277 | E46: 5L2NQ1EM | F46: 4500201277-110 | G46: 71172-S003-MB | H46: 大脑（邮包盒装） | I46: 1008 | J46: 0 | K46: 4 | L46: =I46/K46 -> 252 | M46: 46169 | N46: 46169 | O46: N/A | P46: PASS | Q46: 46188 | S46: 有 | T46: 46125 | U46: 46139 | Y46: 日期码格式：ZURU INC(BVI) 标准格式 日期：按实际生产日期 Packaging Info: Amazon DE:48F4XT2K Amazon ES:8SRTRZLX Amazon UK:76R8OF5K/5L2NQ1EM/5AKNDX6G/56V56PGC/1W8YE3KG DE(9574/157114A)/ES(15757/77806/77731/77673)/UK(157143/17588A/71172/77876/92146BDG/9574) 5. 71172:1pc 71172 BRIAN THE BRAIN into open box, then into mailbox, 4mailboxes/ctn; 3PCS AA BATTERIES(INCLUDED); MA 1L(23L warning UPC)A开口彩 盒+MA 15L A说明书+客版邮包盒(参考Amazon US翻单PO#4500192525)+WEEE_带电池走货 _ 说明书欧洲EN+30L_D版本; 12. 最迟验货不得晚于5/26 Remark: 1.空白外箱（加印带Zuru字样的最新logo，除了邮包盒直接做外箱的产品） + SSCC LABEL一张, 无箱唛，MADE IN CHINA 外箱只印一正一侧。箱唛资料按照给定的 标准去做即可，无需发回我方再行审批(新标准将另行通知)。 (SSCC LABEL竖贴在外箱正面的正中间，贴一面即可,贴纸离外箱边距必须至少3.2CM。如竖贴无法满足要求，则横贴。如横贴也无法满足要求，则竖贴，遮到ZURU lo go无影响), SSCC贴纸由工厂直接跟勤得采购或者工厂自行采购，每一张SSCC Label都是唯一且有不同流水及条码，且需要检查条码是否能正常扫描，另外，此贴纸 印刷不可出现模糊，溢出及粘胶不牢易脱落等现象，如工厂不按此要求导致贴纸有任何问题产生的罚款将由工厂承担一切责任 ,<(>,<)> 此要求只适用Amazon UK/DE /FR/ES/IT,不适用Amazon GPE，Amazon GPE无SSCC label, 但是有对应箱唛，需印刷到外箱 。 2.出往UK的产品+包装务必打上UKCA logo ，否则客人会退货且当地会有罚款。Amazon GPE（包含UK/FR/ES/DE/IT）的订单也需满足此要求。 3.订单必须经过ZURU QC验货或者工厂自检通过后方可出货，不涉及第三方验货。 4.法国订单要求包装不使用矿物油，请按要求提供以下其中一份文件再出货 ，产品出到法国被相关部门抽检出现包装不符合此要求的，供应商需要为此承担责任， 故此请严格把关。Amazon GPE（包含UK/FR/ES/DE/IT）的订单也需满足此要求。 -油墨物质""""由1 ~ 7个芳香环组成的MOAH""""的包装检测报告，要求限值≤1.0%； -包装材料清单，包括包装油墨或物质的信息； -油墨制造商的证书； 5.每一批次出货只能有一个生产日期，不可多个生产日期混在同一批次出货；且零售包装上必须统一加上日期码；外箱对于日期码没有硬性规定； 6.涉及到相关款式会有闪粉的或者微塑料的，请统一默认出无闪粉或者不含微塑料版本； 7.邮包盒及外箱封箱必须是工字型封箱方式； 8.5 Surprise or Mini Brands涉及包装是2个及2个以上的球入PVC桶包装时，单个球上若有UPC#或者EAN#，请用空白贴纸覆盖住，贴纸尺寸自行测量能覆盖原条码即 可； 9. 无论是工厂自检还是ZURU验货，验货报告中必须有产品6面图(正面/背面/左面/右面/顶部/底部，不带包装); 10. 按空海运鉴定报告的要求，只要带锂电池出货，都需要加贴UN贴纸； 11. 所有出往GAS市场(德国/奥地利/瑞士)的电子产品身上需要加字唛，为ZURU FRANCE 地址，需跟包装上的地址一致 (如无电子产品，产品布标有此地址，或产品 太小无法增加可忽略此信息。如产品无法加字唛，需让对应跟单提供产品贴纸资料);（Amazon GPE的订单也需满足此要求） 12. 所有出往GAS德国 (瑞士，奥地利)。水弹枪系列必须使用EN71版本（电子和非电子水弹枪系列都需要符合); 护目镜需打日期码, 格式跟ZURU标准格式一样; 枪 身上增加ZURU FRANCE公司名和地址。使用贴纸和辐射上去都可以。如果有位置，最好增加ZURU Represented by: (此最好翻译德语，如果位置不允许，那么就只增 加ZURU法国和地址)。使用最新的EN71版包装和说明书）。Amazon GPE（包含UK/FR/ES/DE/IT）的订单也需满足此要求。 | Z46: Luna Lin | AA46: 9.86 | AB46: =I46*AA46 -> 9938.88 | AD46: 71172-S003-MB-1L | AE46: 已入 | AO46: =I46 -> 1008 | AP46: =I46 -> 1008 | AR46: =I46 -> 1008
A47: 46129 | B47: WALMART INC. | C47: 美国 | D47: 4500202318 | E47: 0989813245 | F47: 4500202318-20 | G47: 71172-S002 | H47: 大脑 | I47: 936 | J47: 0 | K47: 1 | L47: =I47/K47 -> 936 | M47: 46170 | N47: 46169 | O47: 46181 | P47: PASS | Q47: 46185 | S47: 有 | T47: 46129 | U47: 46134 | Y47: 日期码格式：DGYYYYMMDD(日期避开周末和法定节假日) 日期：按实际生产日期 Packaging Info: 1.包装方式： 71172: MA 1L彩盒包装+MA 15L A版说明书+ RFID贴纸 Remark: 2. 外箱四面印刷紫色RFID箱唛 主唛左前下角印刷艾利贴纸替代标箱唛(ITF-14格式)，条码只印刷一面 主唛右下角加印 MADE IN CHINA以及ZURU LOGO 3. 71172 UPC：193052098443 4.此批单#71172散箱出货； 1PCS/CTN：3PCS AA BATTERIES(INCLUDED) 5.此单需要验货，请自行多备包装物料。 6.产品和包装上要有日期码、MADE IN CHINA和ZURU字样。 7.每PCS要加RFID 贴纸(ZURU提供)，严格按照我们提供的位置图，不可擅自调整位置，贴纸也不可有任何破损或折坏，不可淋湿（如缺数请及时告知） | Z47: Nikki Mo | AA47: 5.916 | AB47: =I47*AA47 -> 5537.376 | AC47: ZB06112-8.17 | AD47: 71172-S002-1L | AE47: 已入 | AO47: =I47 -> 936 | AP47: =I47 -> 936 | AR47: =I47 -> 936
A48: 46128 | B48: NORWEGIAN TOY IMPORT AS - DOM | C48: 挪威 | D48: 4500202500 | E48: 14992 | F48: 4500202500-20 | G48: 71172-S001 | H48: 大脑 | I48: 800 | J48: 0 | K48: 4 | L48: =I48/K48 -> 200 | M48: 46174 | N48: 46169 | O48: N/A | P48: PASS | Q48: 6/9 SI | S48: 无 | T48: 46141 | U48: 贴纸5月20日已回 | Y48: 日期码格式：ZURU INC(BVI) 标准格式 日期：按实际生产日期 Packaging Info: 92106：MA 3L EAN收缩膜+进口商贴纸； 71172：MA 3L EAN彩盒+进口商贴纸； Remark: 1. 产品和包装要求无硼无香，包装不能含有PVC; 此客户NTI不能出14+的产品 2. 如有微塑料，必须合规欧洲标准，闪粉也是微塑料的一种，目前仅接受三张方式1.去除，2.用可降解材料，和3. 永久封印在固体。 3. 带电池出货的产品,电池需要符合欧洲电池新规(EU) 2023-1542. 4. 同一个SKU, 如果客户同时下Bulk/PDQ/SK/EC, 进口商贴纸可以只显示Bulk 的客户客户款号。产品包装上必须有客户进口商信息。 | Z48: Zoe Zhou | AA48: 9.86 | AB48: =I48*AA48 -> 7888 | AD48: 71172-S001-3L | AE48: 已入 | AO48: =I48 -> 800 | AQ48: =I48 -> 800 | AR48: =I48 -> 800
A49: 46129 | B49: TARGET US | C49: 美国 | D49: 4500202446 | E49: 10001748602-0581 | F49: 4500202446-10 | G49: 71172-S001 | H49: 大脑 | I49: 1000 | J49: 0 | K49: 4 | L49: =I49/K49 -> 250 | M49: 46176 | N49: 46171 | O49: N/A | P49: PASS | S49: 有 | T49: 46141 | U49: 46154 | Y49: 日期码格式：ZURU INC(BVI) 标准格式 日期：按实际生产日期 Packaging Info: 产品包装MA 1L彩盒； Remark: 1. 71172-S001-ROBO ALIVE-BRAIN-SERIES 1-BRIAN THE BRAIN-OPEN BOX-4PCS/CTN 2. 产品包装MA 1L彩盒；彩盒上的UPC显示193052098443； 3. 每个外箱正唛箱唛信息左上方位置粘贴条码箱贴纸，每箱只贴一张; 由ZURU向艾利订购， 对应的外箱贴DPCI：087-02-9468, UPC显示10193052098440 ； 4. 产品和包装上要印刷tracking code信息，格式为ZURU常规； 5. 出货方式：货代自提 | Z49: Holly Zheng | AA49: 5.82 | AB49: =I49*AA49 -> 5820 | AC49: ZB06347-8.17 | AD49: 71172-S001-1L | AE49: 已入 | AO49: =I49 -> 1000 | AP49: =I49 -> 1000 | AR49: =I49 -> 1000
A50: 46120 | B50: LEKIA AB | C50: 瑞典 | D50: 4500200447 | E50: 160826 | F50: 4500200447-10 | G50: 71172-S001 | H50: 大脑 | I50: 2000 | J50: 0 | K50: 4 | L50: =I50/K50 -> 500 | M50: 46177 | N50: 46174 | O50: N/A | P50: PASS | Q50: 6/10 SI | S50: 无 | T50: 46133 | U50: 无 | V50: WEEE 书仔5/16 | Y50: 日期码格式：ZURU INC(BVI) 标准格式 日期：按实际生产日期 Packaging Info: 1. 71172: MA A3L(23L warning) EAN版彩盒+MA A15L说明书+一张额外说明书书纸(说明书上的玩法/battery safety information以及WEEE翻译成丹麦瑞典芬兰挪威 爱沙尼亚语) Remark: 1. 包装如含PVC,请改为PET 2. 产品/包装要求无硼无香； 3. 出欧洲，微塑料需合规。 4.带电池出货的产品所用到的电池需要符合欧洲电池新规(EU) 2023-1542 5.产品/包装不含PFAS and/or Bisfenol成分，, 以及不含石棉成分 6. 产品条码如下: 请先检查条码是否正确再安排做货，如有问题请告知: 71172-S001:4894680057272 | Z50: Sheba Ye | AA50: 9.86 | AB50: =I50*AA50 -> 19720 | AD50: 71172-S001-3L | AE50: 已入 | AO50: =I50 -> 2000 | AQ50: =I50 -> 2000 | AR50: =I50 -> 2000
A51: 46140 | B51: ASIA GOAL LIMITED | C51: 香港 | D51: 4500204383 | E51: AG260022-HK | F51: 4500204383-30 | G51: 71172-S001 | H51: 大脑 | I51: 120 | J51: 0 | K51: 4 | L51: =I51/K51 -> 30 | M51: 46178 | N51: 46174 | O51: N/A | P51: PASS | S51: 无 | T51: 46140 | U51: 46155 | Y51: 日期码格式：ZURU INC(BVI) 标准格式 日期：按实际生产日期 Packaging Info: 7151/71126：MA PKG ，优先 1L（含MA说明书）+1张客供警语贴纸+1张客供电池警告贴纸+1张客供中文警告说明书 71172：MA 1L PKG, MA 说明书+ HK客供警语贴纸 ， 1张贴彩盒底部，1张客供电池警语贴纸贴彩盒底部，1张贴说明书 77711GQ1 （INT): MA 3L 收缩膜+1张UPC 条码贴纸(UPC#193052080134) + MA 3L PDQ+MA 5L 收藏指南+HK客供警语贴纸（1张贴球底部，1张贴说明书，1张贴收藏 指南）具体参考HK客供警语贴纸位置图 77785：客版MA 3L UPC 彩盒+客供警语贴纸（具体贴纸位置参考HK客供贴纸位置图） 77785 =2pcs 77711+1pcs 77673 77785：1张客供警语贴+1张客供电池警语贴纸 （77785里的77673：MA 1L 收缩膜，MA 警语说明书+MA 收藏指南+1张客供警语贴+1张客供电池警语贴纸+1张客供中文警告说明书） （77785里的77711 （INT): MA 3L 收缩膜+1张空白贴纸覆盖条码+MA 收藏指南+ MA 说明书+球底部贴1张客供警语贴纸，收藏指南贴一张客供警语贴纸，说明书贴一 张客供警语贴纸） 77843GQ1: MA 1L PKG, PDQ, MA 收藏指南，说明书+ HK客供警语贴纸，具体如下： 1张HK客供电池警语贴纸贴球顶部，1张HK客供警语贴纸贴球底部， 球内5包小配件包装袋需贴1张警语贴纸，寿司和彩虹蛋糕的黑白安全说明书 贴1张警语贴纸，UV 灯的黑白安全说明书需贴1张警语贴纸 每款HK客供贴内容都不一样，详情参考HK客供贴纸位置图。 77858: MA PKG , 优先1L+ HK客供警语贴纸（2 张HK客供警语贴纸，1张贴彩盒背面，1张贴说明书，贴纸内容不一样） 所有贴纸不得遮挡日期码 Remark: 此单出HK | Z51: Chelsea Luo | AA51: 9.7 | AB51: =I51*AA51 -> 1164 | AD51: 71172-S001-1L | AE51: 已入 | AO51: =I51 -> 120 | AP51: =I51 -> 120 | AR51: =I51 -> 120
A52: 46129 | B52: WALMART INC. | C52: 美国 | D52: 4500202318 | E52: 0989813225 | F52: 4500202318-10 | G52: 71172-S002 | H52: 大脑 | I52: 504 | J52: 0 | K52: 1 | L52: =I52/K52 -> 504 | M52: 46170 | N52: 46175 | O52: 46181 | P52: PASS | S52: 有 | T52: 46129 | U52: 46134 | Y52: 日期码格式：DGYYYYMMDD(日期避开周末和法定节假日) 日期：按实际生产日期 Packaging Info: 1.包装方式： 71172: MA 1L彩盒包装+MA 15L A版说明书+ RFID贴纸 Remark: 2. 外箱四面印刷紫色RFID箱唛 主唛左前下角印刷艾利贴纸替代标箱唛(ITF-14格式)，条码只印刷一面 主唛右下角加印 MADE IN CHINA以及ZURU LOGO 3. 71172 UPC：193052098443 4.此批单#71172散箱出货； 1PCS/CTN：3PCS AA BATTERIES(INCLUDED) 5.此单需要验货，请自行多备包装物料。 6.产品和包装上要有日期码、MADE IN CHINA和ZURU字样。 7.每PCS要加RFID 贴纸(ZURU提供)，严格按照我们提供的位置图，不可擅自调整位置，贴纸也不可有任何破损或折坏，不可淋湿（如缺数请及时告知） | Z52: Nikki Mo | AA52: 5.82 | AB52: =I52*AA52 -> 2933.28 | AC52: ZB06228-8.17 | AD52: 71172-S002-1L | AE52: 已入 | AO52: =I52 -> 504 | AP52: =I52 -> 504 | AR52: =I52 -> 504
A53: 46129 | B53: WALMART INC. | C53: 美国 | D53: 4500202322 | E53: 0989813201 | F53: 4500202322-10 | G53: 71172-S002 | H53: 大脑 | I53: 936 | J53: 0 | K53: 1 | L53: =I53/K53 -> 936 | M53: 46174 | N53: 46175 | O53: 46181 | P53: PASS | Q53: 46191 | S53: 有 | T53: 46129 | U53: 46134 | Y53: 日期码格式：DGYYYYMMDD(日期避开周末和法定节假日) 日期：按实际生产日期 Packaging Info: 40REP 包装/箱唛翻单：4500202318 1.包装方式： 71172: MA 1L彩盒包装+MA 15L A版说明书+ RFID贴纸 Remark: 2. 外箱四面印刷紫色RFID箱唛 主唛左前下角印刷艾利贴纸替代标箱唛(ITF-14格式)，条码只印刷一面 主唛右下角加印 MADE IN CHINA以及ZURU LOGO 3. 71172 UPC：193052098443 4.此批单#71172散箱出货； 1PCS/CTN：3PCS AA BATTERIES(INCLUDED) 5.此单需要验货，请自行多备包装物料。 6.产品和包装上要有日期码、MADE IN CHINA和ZURU字样。 7.每PCS要加RFID 贴纸(ZURU提供)，严格按照我们提供的位置图，不可擅自调整位置，贴纸也不可有任何破损或折坏，不可淋湿（如缺数请及时告知） | Z53: Nikki Mo | AA53: 5.82 | AB53: =I53*AA53 -> 5447.52 | AC53: ZB06260-8.17 | AD53: 71172-S002-1L | AE53: 已入 | AO53: =I53 -> 936 | AP53: =I53 -> 936 | AR53: =I53 -> 936
A54: 46129 | B54: WALMART INC. | C54: 美国 | D54: 4500202322 | E54: 0989813271 | F54: 4500202322-20 | G54: 71172-S002 | H54: 大脑 | I54: 504 | J54: 0 | K54: 1 | L54: =I54/K54 -> 504 | M54: 46174 | N54: 46175 | O54: 46181 | P54: PASS | Q54: 46195 | S54: 有 | T54: 46129 | U54: 46134 | Y54: 日期码格式：DGYYYYMMDD(日期避开周末和法定节假日) 日期：按实际生产日期 Packaging Info: 40REP 包装/箱唛翻单：4500202318 1.包装方式： 71172: MA 1L彩盒包装+MA 15L A版说明书+ RFID贴纸 Remark: 2. 外箱四面印刷紫色RFID箱唛 主唛左前下角印刷艾利贴纸替代标箱唛(ITF-14格式)，条码只印刷一面 主唛右下角加印 MADE IN CHINA以及ZURU LOGO 3. 71172 UPC：193052098443 4.此批单#71172散箱出货； 1PCS/CTN：3PCS AA BATTERIES(INCLUDED) 5.此单需要验货，请自行多备包装物料。 6.产品和包装上要有日期码、MADE IN CHINA和ZURU字样。 7.每PCS要加RFID 贴纸(ZURU提供)，严格按照我们提供的位置图，不可擅自调整位置，贴纸也不可有任何破损或折坏，不可淋湿（如缺数请及时告知） | Z54: Nikki Mo | AA54: 5.916 | AB54: =I54*AA54 -> 2981.664 | AC54: ZB06371-8.17 | AD54: 71172-S002-1L | AE54: 已入 | AO54: =I54 -> 504 | AP54: =I54 -> 504 | AR54: =I54 -> 504
A55: 46129 | B55: WALMART INC. | C55: 美国 | D55: 4500202322 | E55: 0989813145 | F55: 4500202322-30 | G55: 71172-S002 | H55: 大脑 | I55: 1008 | J55: 0 | K55: 1 | L55: =I55/K55 -> 1008 | M55: 46174 | N55: 46175 | O55: 46181 | P55: PASS | Q55: 46195 | S55: 有 | T55: 46129 | U55: 46134 | Y55: 日期码格式：DGYYYYMMDD(日期避开周末和法定节假日) 日期：按实际生产日期 Packaging Info: 40REP 包装/箱唛翻单：4500202318 1.包装方式： 71172: MA 1L彩盒包装+MA 15L A版说明书+ RFID贴纸 Remark: 2. 外箱四面印刷紫色RFID箱唛 主唛左前下角印刷艾利贴纸替代标箱唛(ITF-14格式)，条码只印刷一面 主唛右下角加印 MADE IN CHINA以及ZURU LOGO 3. 71172 UPC：193052098443 4.此批单#71172散箱出货； 1PCS/CTN：3PCS AA BATTERIES(INCLUDED) 5.此单需要验货，请自行多备包装物料。 6.产品和包装上要有日期码、MADE IN CHINA和ZURU字样。 7.每PCS要加RFID 贴纸(ZURU提供)，严格按照我们提供的位置图，不可擅自调整位置，贴纸也不可有任何破损或折坏，不可淋湿（如缺数请及时告知） | Z55: Nikki Mo | AA55: 5.916 | AB55: =I55*AA55 -> 5963.328 | AC55: ZB06290-8.17 | AD55: 71172-S002-1L | AE55: 已入 | AO55: =I55 -> 1008 | AP55: =I55 -> 1008 | AR55: =I55 -> 1008
A56: 46120 | B56: ARGOS LIMITED | C56: 英国 | D56: 4500200458 | E56: 414770 | F56: 4500200458-10 | G56: 71172-S001 | H56: 大脑 | I56: 660 | J56: 0 | K56: 4 | L56: =I56/K56 -> 165 | M56: 46181 | N56: 46177 | O56: N/A | P56: PASS | Q56: 6/13送库有 | S56: 无 | T56: 46120 | U56: 46149 | Y56: 日期码格式：ZURU INC(BVI) 标准格式 日期：按实际生产日期 Packaging Info: 1.71172:1L MA包装+cat label 1张+MA说明书+WEEE带电池说明书 71152:1L MA包装+cat label 1张+MA说明书+WEEE不带电池说明书 2.注意Cat.label （要求易撕类贴纸，但是粘性不能过低），同时此贴纸每个订单都是不相同的（会显示客户对应的订单号），切勿翻旧订单购买。此贴纸由ZURU提 供贴纸图稿和贴纸位置图给工厂后，工厂自行购买。 3.请先检查条码是否正确再安排做，标签上的目录编号数字高度必须至少为5mm （14.17pt） Remark: *MA包装最新版本 *包装日期码按ZURU格式即可，请确保不迟于外箱日期码，可等于或者早于外箱日期码，必须为法定工作日。 *外箱尺寸任何一条边长度超过75cm或者每箱重量超过10KG，需要在外箱上加三脚架符号，有问题请与ZURU跟单同事核实。 *主拼工厂需要准备密网安排装柜 *出欧洲电子产品需要加WEEE说明书，区分带电池和不带电池两种版本，不是电子产品可忽略。 *订单必须经过ZURU QC验货并且通过后方可出货。 *订单出英国，请注意检查产品及包装应带UKCA图标，包装显示ZURU UK LTD信息，QC同事请查核，如有问题与跟单确认。 *条码扫描会显示客户7位数产品号而不是客户的订单号码。 *标签上的目录编号数字高度必须至少为5mm （14.17pt）。 *所有产品按符合欧洲标准走货，需要是不含微塑料版本 。 *若任何产品涉及到硼的，请使用低硼版本(没有则忽略此要求) *客户不接受PVC材质包装。 *外箱不得使用带金属夹子或带扣。 *出欧洲的电子产品需要额外增加WEEE电池说明书，区分带电池走货和不带电池走货两种版本，如果不是电子产品可忽略 *主拼工厂需要提前准备密网用于装柜，装柜拉网请务必按照客人要求固定好，避免货物在运输过程中坍塌，不规范的拉网或者漏掉都会导致客人罚款 | Z56: Lena Huang | AA56: 9.86 | AB56: =I56*AA56 -> 6507.6 | AD56: 71172-S001-1L | AE56: 已入 | AO56: =I56 -> 660 | AP56: =I56 -> 660 | AR56: =I56 -> 660
A57: 46121 | B57: WALMART INC. | C57: 美国 | D57: 4500200592 | E57: 0988641156 | F57: 4500200592-30 | G57: 71172-S002 | H57: 大脑 | I57: 1258 | J57: 0 | K57: 1 | L57: =I57/K57 -> 1258 | M57: 46177 | N57: 46178 | O57: 46181 | P57: PASS | Q57: 6/16 SI | S57: 有 | T57: 46121 | U57: 4/9-粉色MOD艾利贴纸,4/22收RFID贴纸 | Y57: 日期码格式：DGYYYYMMDD(日期避开周末和法定节假日) 日期：按实际生产日期 Packaging Info: 包装/箱唛翻单：4500200590 1.包装方式： 71172: MA 1L彩盒包装+MA 15L警告语 A版说明书+ RFID贴纸 Remark: 2. 外箱四面印刷紫色RFID箱唛 主唛左前下角印刷艾利贴纸替代标箱唛(ITF-14格式)，条码只印刷一面 主唛右下角加印 MADE IN CHINA以及ZURU LOGO，对角线位置加贴一张粉色MOD艾利贴纸（工厂自行打印或订购贴纸） 3. 71172 UPC：193052098443 4.此批单散箱出货，1PCS/CTN 5.此单需要验货，请自行多备包装物料。 6.产品和包装上要有日期码、MADE IN CHINA和ZURU字样。 7.每PCS要加RFID 贴纸(ZURU提供)，严格按照我们提供的位置图，不可擅自调整位置，贴纸也不可有任何破损或折坏，不可淋湿（如缺数请及时告知） | Z57: Nikki Mo | AA57: 5.916 | AB57: =I57*AA57 -> 7442.328 | AC57: ZB06291-8.17 | AD57: 71172-S002-1L | AE57: 已入 | AO57: =I57 -> 1258 | AP57: =I57 -> 1258 | AS57: =AP57 -> 1258
A58: 46121 | B58: WALMART INC. | C58: 美国 | D58: 4500200592 | E58: 0988641246 | F58: 4500200592-40 | G58: 71172-S002 | H58: 大脑 | I58: 814 | J58: 0 | K58: 1 | L58: =I58/K58 -> 814 | M58: 46177 | N58: 46178 | O58: 46181 | P58: PASS | Q58: 6/16 SI | S58: 有 | T58: 46121 | U58: 4/9-粉色MOD艾利贴纸,4/22收RFID贴纸 | Y58: 日期码格式：DGYYYYMMDD(日期避开周末和法定节假日) 日期：按实际生产日期 Packaging Info: 包装/箱唛翻单：4500200590 1.包装方式： 71172: MA 1L彩盒包装+MA 15L警告语 A版说明书+ RFID贴纸 Remark: 2. 外箱四面印刷紫色RFID箱唛 主唛左前下角印刷艾利贴纸替代标箱唛(ITF-14格式)，条码只印刷一面 主唛右下角加印 MADE IN CHINA以及ZURU LOGO，对角线位置加贴一张粉色MOD艾利贴纸（工厂自行打印或订购贴纸） 3. 71172 UPC：193052098443 4.此批单散箱出货，1PCS/CTN 5.此单需要验货，请自行多备包装物料。 6.产品和包装上要有日期码、MADE IN CHINA和ZURU字样。 7.每PCS要加RFID 贴纸(ZURU提供)，严格按照我们提供的位置图，不可擅自调整位置，贴纸也不可有任何破损或折坏，不可淋湿（如缺数请及时告知） | Z58: Nikki Mo | AA58: 5.916 | AB58: =I58*AA58 -> 4815.624 | AC58: ZB06261-8.17 | AD58: 71172-S002-1L | AE58: 已入 | AO58: =I58 -> 814 | AP58: =I58 -> 814 | AS58: =AP58 -> 814
A59: 46121 | B59: WALMART INC. | C59: 美国 | D59: 4500200594 | E59: 0988641229 | F59: 4500200594-20 | G59: 71172-S002 | H59: 大脑 | I59: 1472 | J59: 0 | K59: 1 | L59: =I59/K59 -> 1472 | M59: 46181 | N59: 46178 | O59: 46181 | P59: PASS | Q59: 6/22 SI | S59: 有 | T59: 46121 | U59: 4/9-粉色MOD艾利贴纸,4/22收RFID贴纸 | Y59: 日期码格式：DGYYYYMMDD(日期避开周末和法定节假日) 日期：按实际生产日期 Packaging Info: 包装/箱唛翻单：4500200590 1.包装方式： 71172: MA 1L彩盒包装+MA 15L警告语 A版说明书+ RFID贴纸 Remark: 2. 外箱四面印刷紫色RFID箱唛 主唛左前下角印刷艾利贴纸替代标箱唛(ITF-14格式)，条码只印刷一面 主唛右下角加印 MADE IN CHINA以及ZURU LOGO，对角线位置加贴一张粉色MOD艾利贴纸（工厂自行打印或订购贴纸） 3. 71172 UPC：193052098443 4.此批单散箱出货，1PCS/CTN 5.此单需要验货，请自行多备包装物料。 6.产品和包装上要有日期码、MADE IN CHINA和ZURU字样。 7.每PCS要加RFID 贴纸(ZURU提供)，严格按照我们提供的位置图，不可擅自调整位置，贴纸也不可有任何破损或折坏，不可淋湿（如缺数请及时告知） | Z59: Nikki Mo | AA59: 5.916 | AB59: =I59*AA59 -> 8708.352 | AC59: ZB06424-8.17 | AD59: 71172-S002-1L | AE59: 已入 | AO59: =I59 -> 1472 | AP59: =I59 -> 1472 | AS59: =AP59 -> 1472
A60: 46126 | B60: MID-STATES DISTRIBUTING, LLC | C60: 美国 | D60: 4500201308 | E60: 1736153-99 | F60: 4500201308-430 | G60: 71172-S001 | H60: 大脑 | I60: 160 | J60: 0 | K60: 4 | L60: =I60/K60 -> 40 | M60: 46183 | N60: 46179 | O60: N/A | P60: PASS | Q60: 46213 | S60: 无 | T60: 46126 | U60: 无 | Y60: 日期码格式：ZURU INC(BVI) 标准格式 日期：按实际生产日期 Packaging Info: 1.使用 MA UPC版本包装，优先1L，出口美国。 157117UQ1：8 Assortment=1:1:1:1:1:1:1:1. 15758SLD：4 Assortments; even ratio. 15783UQ1：7 Assortments; Rare assortment 1/24, others even ratio. 15787：4 Assortments; Even ratio. 15789UQ1：7 Assortments; Rare assortment 1/24, others even ratio. 25257：Duck:Crocodile:Fish=4:4:4. 7153：Mix #7149（2asst)+#7150（2asst). 7154：Mix #7149（8asst)+#7150（4asst). 92119：7 Assortment, Polar bear: Penguin: Walrus: Mammoth: Owl: Seal: Snow man=10:10:10:10:10:8:2. Snow man is the rare item. 92146TQ2：6 Assortment, Cat:Raccoon:Deer:Tiger:Pigeon:Owl=1:1:1:1:1:1. 92147：6 Assortment,Black Cat:Owl:Axolotl:Unicorn:Bat:Bunny=1:1:1:1:1:1. Remark: 1.产品和包装上印刷tracking code信息，格式为ZURU常规。 2.ZURU QC验货 | Z60: Cara Li | AA60: 7.1735 | AB60: =I60*AA60 -> 1147.76 | AC60: ZB06466-8.17 | AD60: 71172-S001-1L | AE60: 已入 | AO60: =I60 -> 160 | AP60: =I60 -> 160 | AR60: =I60 -> 160
A61: 46126 | B61: MID-STATES DISTRIBUTING, LLC | C61: 美国 | D61: 4500201308 | E61: A000214035 | F61: 4500201308-440 | G61: 71172-S001 | H61: 大脑 | I61: 92 | J61: 0 | K61: 4 | L61: =I61/K61 -> 23 | M61: 46183 | N61: 46179 | O61: N/A | P61: PASS | Q61: 46213 | S61: 无 | T61: 46126 | U61: 无 | Y61: 日期码格式：ZURU INC(BVI) 标准格式 日期：按实际生产日期 Packaging Info: 1.使用 MA UPC版本包装，优先1L，出口美国。 157117UQ1：8 Assortment=1:1:1:1:1:1:1:1. 15758SLD：4 Assortments; even ratio. 15783UQ1：7 Assortments; Rare assortment 1/24, others even ratio. 15787：4 Assortments; Even ratio. 15789UQ1：7 Assortments; Rare assortment 1/24, others even ratio. 25257：Duck:Crocodile:Fish=4:4:4. 7153：Mix #7149（2asst)+#7150（2asst). 7154：Mix #7149（8asst)+#7150（4asst). 92119：7 Assortment, Polar bear: Penguin: Walrus: Mammoth: Owl: Seal: Snow man=10:10:10:10:10:8:2. Snow man is the rare item. 92146TQ2：6 Assortment, Cat:Raccoon:Deer:Tiger:Pigeon:Owl=1:1:1:1:1:1. 92147：6 Assortment,Black Cat:Owl:Axolotl:Unicorn:Bat:Bunny=1:1:1:1:1:1. Remark: 1.产品和包装上印刷tracking code信息，格式为ZURU常规。 2.ZURU QC验货 | Z61: Cara Li | AA61: 7.1735 | AB61: =I61*AA61 -> 659.962 | AC61: ZB06828-8.17 | AD61: 71172-S001-1L | AE61: 已入 | AO61: =I61 -> 92 | AP61: =I61 -> 92 | AR61: =I61 -> 92
A62: 46126 | B62: MID-STATES DISTRIBUTING, LLC | C62: 美国 | D62: 4500201308 | E62: 671996908 | F62: 4500201308-450 | G62: 71172-S001 | H62: 大脑 | I62: 24 | J62: 0 | K62: 4 | L62: =I62/K62 -> 6 | M62: 46183 | N62: 46179 | O62: N/A | P62: PASS | Q62: 46213 | S62: 无 | T62: 46126 | U62: 无 | Y62: 日期码格式：ZURU INC(BVI) 标准格式 日期：按实际生产日期 Packaging Info: 1.使用 MA UPC版本包装，优先1L，出口美国。 157117UQ1：8 Assortment=1:1:1:1:1:1:1:1. 15758SLD：4 Assortments; even ratio. 15783UQ1：7 Assortments; Rare assortment 1/24, others even ratio. 15787：4 Assortments; Even ratio. 15789UQ1：7 Assortments; Rare assortment 1/24, others even ratio. 25257：Duck:Crocodile:Fish=4:4:4. 7153：Mix #7149（2asst)+#7150（2asst). 7154：Mix #7149（8asst)+#7150（4asst). 92119：7 Assortment, Polar bear: Penguin: Walrus: Mammoth: Owl: Seal: Snow man=10:10:10:10:10:8:2. Snow man is the rare item. 92146TQ2：6 Assortment, Cat:Raccoon:Deer:Tiger:Pigeon:Owl=1:1:1:1:1:1. 92147：6 Assortment,Black Cat:Owl:Axolotl:Unicorn:Bat:Bunny=1:1:1:1:1:1. Remark: 1.产品和包装上印刷tracking code信息，格式为ZURU常规。 2.ZURU QC验货 | Z62: Cara Li | AA62: 7.556 | AB62: =I62*AA62 -> 181.344 | AC62: ZB06208-8.17 | AD62: 71172-S001-1L | AE62: 已入 | AO62: =I62 -> 24 | AP62: =I62 -> 24 | AR62: =I62 -> 24
A63: 46126 | B63: MID-STATES DISTRIBUTING, LLC | C63: 美国 | D63: 4500201308 | E63: 671996909 | F63: 4500201308-460 | G63: 71172-S001 | H63: 大脑 | I63: 20 | J63: 0 | K63: 4 | L63: =I63/K63 -> 5 | M63: 46183 | N63: 46179 | O63: N/A | P63: PASS | Q63: 46213 | S63: 无 | T63: 46126 | U63: 无 | Y63: 日期码格式：ZURU INC(BVI) 标准格式 日期：按实际生产日期 Packaging Info: 1.使用 MA UPC版本包装，优先1L，出口美国。 157117UQ1：8 Assortment=1:1:1:1:1:1:1:1. 15758SLD：4 Assortments; even ratio. 15783UQ1：7 Assortments; Rare assortment 1/24, others even ratio. 15787：4 Assortments; Even ratio. 15789UQ1：7 Assortments; Rare assortment 1/24, others even ratio. 25257：Duck:Crocodile:Fish=4:4:4. 7153：Mix #7149（2asst)+#7150（2asst). 7154：Mix #7149（8asst)+#7150（4asst). 92119：7 Assortment, Polar bear: Penguin: Walrus: Mammoth: Owl: Seal: Snow man=10:10:10:10:10:8:2. Snow man is the rare item. 92146TQ2：6 Assortment, Cat:Raccoon:Deer:Tiger:Pigeon:Owl=1:1:1:1:1:1. 92147：6 Assortment,Black Cat:Owl:Axolotl:Unicorn:Bat:Bunny=1:1:1:1:1:1. Remark: 1.产品和包装上印刷tracking code信息，格式为ZURU常规。 2.ZURU QC验货 | Z63: Cara Li | AA63: 7.556 | AB63: =I63*AA63 -> 151.12 | AC63: ZB06208-8.17 | AD63: 71172-S001-1L | AE63: 已入 | AO63: =I63 -> 20 | AP63: =I63 -> 20 | AR63: =I63 -> 20
A64: 46126 | B64: MID-STATES DISTRIBUTING, LLC | C64: 美国 | D64: 4500201308 | E64: 671996910 | F64: 4500201308-470 | G64: 71172-S001 | H64: 大脑 | I64: 4 | J64: 0 | K64: 4 | L64: =I64/K64 -> 1 | M64: 46183 | N64: 46179 | O64: N/A | P64: PASS | Q64: 46213 | S64: 无 | T64: 46126 | U64: 无 | Y64: 日期码格式：ZURU INC(BVI) 标准格式 日期：按实际生产日期 Packaging Info: 1.使用 MA UPC版本包装，优先1L，出口美国。 157117UQ1：8 Assortment=1:1:1:1:1:1:1:1. 15758SLD：4 Assortments; even ratio. 15783UQ1：7 Assortments; Rare assortment 1/24, others even ratio. 15787：4 Assortments; Even ratio. 15789UQ1：7 Assortments; Rare assortment 1/24, others even ratio. 25257：Duck:Crocodile:Fish=4:4:4. 7153：Mix #7149（2asst)+#7150（2asst). 7154：Mix #7149（8asst)+#7150（4asst). 92119：7 Assortment, Polar bear: Penguin: Walrus: Mammoth: Owl: Seal: Snow man=10:10:10:10:10:8:2. Snow man is the rare item. 92146TQ2：6 Assortment, Cat:Raccoon:Deer:Tiger:Pigeon:Owl=1:1:1:1:1:1. 92147：6 Assortment,Black Cat:Owl:Axolotl:Unicorn:Bat:Bunny=1:1:1:1:1:1. Remark: 1.产品和包装上印刷tracking code信息，格式为ZURU常规。 2.ZURU QC验货 | Z64: Cara Li | AA64: 7.556 | AB64: =I64*AA64 -> 30.224 | AC64: ZB06208-8.17 | AD64: 71172-S001-1L | AE64: 已入 | AO64: =I64 -> 4 | AP64: =I64 -> 4 | AR64: =I64 -> 4
A65: 46129 | B65: ESAL ENTERPRISES FZC | C65: 卡塔尔 | D65: 4500202591 | F65: 4500202591-140 | G65: 71172-S001 | H65: 大脑 | I65: 240 | J65: 0 | K65: 4 | L65: =I65/K65 -> 60 | M65: 46185 | N65: =M65-4 -> 46181 | O65: N/A | P65: PASS | Q65: 46214 | S65: 无 | T65: 46132 | U65: 46149 | Y65: 日期码格式：ZURU INC(BVI) 标准格式 日期：按实际生产日期 Packaging Info: 出QATAR, 包装不能有希伯来语，带Slime（口水胶)的产品需寄2套MA样板到SZ办公室， 急需寄出给客户测试。 所有RBC的产品（内外）包装不能有彩虹。 所有包装含说明书，说明书上都需要有阿拉伯语（AR)， 或者带单独的阿拉伯语（AR)说明书出货。 71172：MA PKG+进口商贴纸 (含G Mark, QR code, 阿拉伯警语); 贴纸上的QR code需微信可扫; 扫描结果另外通知； UPC条码显示193052098443；含MA说明书，需 加一张黑白印刷的说明纸一起出货， 所有AW翻单4500202382。 客人箱唛排版，印4面，条码内容193052098443. Remark: | Z65: Doris Shou | AA65: 9.86 | AB65: =I65*AA65 -> 2366.4 | AD65: 71172-S001-1L | AE65: 已入 | AO65: =I65 -> 240 | AP65: =I65 -> 240 | AR65: =I65 -> 240
A66: 46129 | B66: ESAL ENTERPRISES FZC | C66: 沙特 | D66: 4500202631 | F66: 4500202631-180 | G66: 71172-S001 | H66: 大脑 | I66: 360 | J66: 0 | K66: 4 | L66: =I66/K66 -> 90 | M66: 46185 | N66: =M66-4 -> 46181 | O66: N/A | P66: PASS | Q66: 46199 | S66: 无 | T66: 46132 | U66: 46149 | Y66: 日期码格式：ZURU INC(BVI) 标准格式 日期：按实际生产日期 Packaging Info: 出KSA, 所有包装不能有希伯来语（HE), 所有RBC的产品（内外）包装上都不能有彩虹 所有包装含说明书，说明书上都需要有阿拉伯语（AR)， 或者带单独的阿拉伯语（AR)说明书出货。 71172：MA PKG+进口商贴纸 (含G Mark, QR code, 阿拉伯警语); 贴纸上的QR code需微信可扫; 扫描结果另外通知； UPC条码显示193052098443；含MA说明书，需 加一张黑白印刷的阿拉伯语说明纸一起出货， AW翻单4500202382。 客人箱唛排版，印4面，条码内容193052098443. 2. 客人箱唛排版，印4面，条码内容193052028174； Remark: | Z66: Doris Shou | AA66: 9.86 | AB66: =I66*AA66 -> 3549.6 | AD66: 71172-S001-1L | AE66: 已入 | AO66: =I66 -> 360 | AP66: =I66 -> 360 | AR66: =I66 -> 360
A67: 46136 | B67: KIDDISVIT LTD | C67: 乌克兰 | D67: 4500203583 | F67: 4500203583-50 | G67: 71172-S001 | H67: 大脑 | I67: 2000 | J67: 0 | K67: 4 | L67: =I67/K67 -> 500 | M67: 46185 | N67: 46181 | O67: 46188 | P67: PASS | Q67: 大货办1套 | S67: 无 | T67: 46149 | U67: 46154 | Y67: 日期码格式：ZURU INC(BVI) 标准格式 日期：按实际生产日期 Packaging Info: 71172：3L EAN 彩卡+ 进口商贴纸（需要覆盖MA 包装上RU俄文警告语）， 客版说明书（不含RU俄罗斯警告语 ， 需要有UA乌克兰警告语）， 增加EN+28L_C版(无俄 语版）WEEE_带电池走货说明书 ； Remark: 1.此单出欧洲需满足EU测试标准要求，另外不能出闪粉（若产品本身不含闪粉则忽略这句话）；包装上需要有CE logo . 2.若产品有比例请使用标准比例 3.此单会有第三方验货。 4.此单客户的包装/说明书/收藏指南上均不可出现俄罗斯语言，若有我遗漏的地方请务必告知 5.若产品中的口水胶/棉花泥等配件已提前印刷好了日期码，需明确告知ZURU跟单日期码是多少，客户不接受距离货物到店时间只有半年的有效期 . | Z67: Ann | AA67: 9.86 | AB67: =I67*AA67 -> 19720 | AD67: 71172-S001-3L-客说明书 | AE67: 已入 | AO67: =I67 -> 2000 | AQ67: =I67 -> 2000 | AU67: =I67 -> 2000
A68: 46129 | B68: WALMART INC. | C68: 美国 | D68: 4500202325 | E68: 0989813124 | F68: 4500202325-10 | G68: 71172-S002 | H68: 大脑 | I68: 504 | J68: 0 | K68: 1 | L68: =I68/K68 -> 504 | M68: 46183 | N68: 46182 | O68: 6/12 自检 | P68: PASS | Q68: 6/24 SI | S68: 有 | T68: 46129 | U68: 46134 | Y68: 日期码格式：DGYYYYMMDD(日期避开周末和法定节假日) 日期：按实际生产日期 Packaging Info: 40REP 包装/箱唛翻单：4500202318 1.包装方式： 71172: MA 1L彩盒包装+MA 15L A版说明书+ RFID贴纸 Remark: 2. 外箱四面印刷紫色RFID箱唛 主唛左前下角印刷艾利贴纸替代标箱唛(ITF-14格式)，条码只印刷一面 主唛右下角加印 MADE IN CHINA以及ZURU LOGO 3. 71172 UPC：193052098443 4.此批单#71172散箱出货； 1PCS/CTN：3PCS AA BATTERIES(INCLUDED) 5.此单需要验货，请自行多备包装物料。 6.产品和包装上要有日期码、MADE IN CHINA和ZURU字样。 7.每PCS要加RFID 贴纸(ZURU提供)，严格按照我们提供的位置图，不可擅自调整位置，贴纸也不可有任何破损或折坏，不可淋湿（如缺数请及时告知） | Z68: Nikki Mo | AA68: 5.82 | AB68: =I68*AA68 -> 2933.28 | AC68: ZB06461-8.17 | AD68: 71172-S002-1L | AE68: 已入 | AO68: =I68 -> 504 | AP68: =I68 -> 504 | AS68: =AP68 -> 504
A69: 46129 | B69: WALMART INC. | C69: 美国 | D69: 4500202325 | E69: 0989813177 | F69: 4500202325-20 | G69: 71172-S002 | H69: 大脑 | I69: 720 | J69: 0 | K69: 1 | L69: =I69/K69 -> 720 | M69: 46183 | N69: 46182 | O69: 6/16自检 | P69: PASS | Q69: 6/24 SI | S69: 有 | T69: 46129 | U69: 46134 | Y69: 日期码格式：DGYYYYMMDD(日期避开周末和法定节假日) 日期：按实际生产日期 Packaging Info: 40REP 包装/箱唛翻单：4500202318 1.包装方式： 71172: MA 1L彩盒包装+MA 15L A版说明书+ RFID贴纸 Remark: 2. 外箱四面印刷紫色RFID箱唛 主唛左前下角印刷艾利贴纸替代标箱唛(ITF-14格式)，条码只印刷一面 主唛右下角加印 MADE IN CHINA以及ZURU LOGO 3. 71172 UPC：193052098443 4.此批单#71172散箱出货； 1PCS/CTN：3PCS AA BATTERIES(INCLUDED) 5.此单需要验货，请自行多备包装物料。 6.产品和包装上要有日期码、MADE IN CHINA和ZURU字样。 7.每PCS要加RFID 贴纸(ZURU提供)，严格按照我们提供的位置图，不可擅自调整位置，贴纸也不可有任何破损或折坏，不可淋湿（如缺数请及时告知） | Z69: Nikki Mo | AA69: 5.82 | AB69: =I69*AA69 -> 4190.4 | AC69: ZB06508-8.17 | AD69: 71172-S002-1L | AE69: 已入 | AO69: =I69 -> 720 | AP69: =I69 -> 720 | AS69: =AP69 -> 720
A70: 46129 | B70: WALMART INC. | C70: 美国 | D70: 4500202325 | E70: 0989813333 | F70: 4500202325-30 | G70: 71172-S002 | H70: 大脑 | I70: 576 | J70: 0 | K70: 1 | L70: =I70/K70 -> 576 | M70: 46183 | N70: 46182 | O70: 6/12 自检 | P70: PASS | Q70: 6/24 SI | S70: 有 | T70: 46129 | U70: 46134 | Y70: 日期码格式：DGYYYYMMDD(日期避开周末和法定节假日) 日期：按实际生产日期 Packaging Info: 40REP 包装/箱唛翻单：4500202318 1.包装方式： 71172: MA 1L彩盒包装+MA 15L A版说明书+ RFID贴纸 Remark: 2. 外箱四面印刷紫色RFID箱唛 主唛左前下角印刷艾利贴纸替代标箱唛(ITF-14格式)，条码只印刷一面 主唛右下角加印 MADE IN CHINA以及ZURU LOGO 3. 71172 UPC：193052098443 4.此批单#71172散箱出货； 1PCS/CTN：3PCS AA BATTERIES(INCLUDED) 5.此单需要验货，请自行多备包装物料。 6.产品和包装上要有日期码、MADE IN CHINA和ZURU字样。 7.每PCS要加RFID 贴纸(ZURU提供)，严格按照我们提供的位置图，不可擅自调整位置，贴纸也不可有任何破损或折坏，不可淋湿（如缺数请及时告知） | Z70: Nikki Mo | AA70: 5.916 | AB70: =I70*AA70 -> 3407.616 | AC70: ZB06773-8.17 | AD70: 71172-S002-1L | AE70: 已入 | AO70: =I70 -> 576 | AP70: =I70 -> 576 | AS70: =AP70 -> 576
A71: 46121 | B71: WALMART INC. | C71: 美国 | D71: 4500200598 | E71: 0988641100 | F71: 4500200598-30 | G71: 71172-S002 | H71: 大脑 | I71: 980 | J71: 0 | K71: 1 | L71: =I71/K71 -> 980 | M71: 46188 | N71: 46184 | O71: 6/16自检 | P71: PASS | Q71: 7/2 SI | S71: 有 | T71: 46121 | U71: 4/9-粉色MOD艾利贴纸,4/22收RFID贴纸 | Y71: 日期码格式：DGYYYYMMDD(日期避开周末和法定节假日) 日期：按实际生产日期 Packaging Info: 包装/箱唛翻单：4500200590 1.包装方式： 71172: MA 1L彩盒包装+MA 15L警告语 A版说明书+ RFID贴纸 Remark: 2. 外箱四面印刷紫色RFID箱唛 主唛左前下角印刷艾利贴纸替代标箱唛(ITF-14格式)，条码只印刷一面 主唛右下角加印 MADE IN CHINA以及ZURU LOGO，对角线位置加贴一张粉色MOD艾利贴纸（工厂自行打印或订购贴纸） 3. 71172 UPC：193052098443 4.此批单散箱出货，1PCS/CTN 5.此单需要验货，请自行多备包装物料。 6.产品和包装上要有日期码、MADE IN CHINA和ZURU字样。 7.每PCS要加RFID 贴纸(ZURU提供)，严格按照我们提供的位置图，不可擅自调整位置，贴纸也不可有任何破损或折坏，不可淋湿（如缺数请及时告知） | Z71: Nikki Mo | AA71: 5.82 | AB71: =I71*AA71 -> 5703.6 | AC71: ZB06692-8.17 | AD71: 71172-S002-1L | AE71: 已入 | AO71: =I71 -> 980 | AP71: =I71 -> 980 | AS71: =AP71 -> 980
A72: 46121 | B72: WALMART INC. | C72: 美国 | D72: 4500200598 | E72: 0988641135 | F72: 4500200598-40 | G72: 71172-S002 | H72: 大脑 | I72: 1038 | J72: 0 | K72: 1 | L72: =I72/K72 -> 1038 | M72: 46188 | N72: 46184 | O72: 6/16自检 | P72: PASS | Q72: 7/2 SI | S72: 有 | T72: 46121 | U72: 4/9-粉色MOD艾利贴纸,4/22收RFID贴纸 | Y72: 日期码格式：DGYYYYMMDD(日期避开周末和法定节假日) 日期：按实际生产日期 Packaging Info: 包装/箱唛翻单：4500200590 1.包装方式： 71172: MA 1L彩盒包装+MA 15L警告语 A版说明书+ RFID贴纸 Remark: 2. 外箱四面印刷紫色RFID箱唛 主唛左前下角印刷艾利贴纸替代标箱唛(ITF-14格式)，条码只印刷一面 主唛右下角加印 MADE IN CHINA以及ZURU LOGO，对角线位置加贴一张粉色MOD艾利贴纸（工厂自行打印或订购贴纸） 3. 71172 UPC：193052098443 4.此批单散箱出货，1PCS/CTN 5.此单需要验货，请自行多备包装物料。 6.产品和包装上要有日期码、MADE IN CHINA和ZURU字样。 7.每PCS要加RFID 贴纸(ZURU提供)，严格按照我们提供的位置图，不可擅自调整位置，贴纸也不可有任何破损或折坏，不可淋湿（如缺数请及时告知） | Z72: Nikki Mo | AA72: 5.916 | AB72: =I72*AA72 -> 6140.808 | AC72: ZB06693-8.17 | AD72: 71172-S002-1L | AE72: 已入 | AO72: =I72 -> 1038 | AP72: =I72 -> 1038 | AS72: =AP72 -> 1038
A73: 46122 | B73: YOYO LLC | C73: 吉尔吉斯斯坦 | D73: 4500201054 | F73: 4500201054-60 | G73: 71172-S001 | H73: 大脑 | I73: 120 | J73: 0 | K73: 4 | L73: =I73/K73 -> 30 | M73: 46188 | N73: 46184 | P73: PASS | Q73: 6/16入仓 | S73: 无 | T73: 46122 | U73: 46122 | Y73: 日期码格式：ZURU INC(BVI) 标准格式 日期：按实际生产日期 Packaging Info: MA UPC包装+通用贴纸，MA PDQ, MA 说明书（如有） Remark: 1，标准配比； 2，需要通过ZURU 验货结果后才能出货 (工厂需要主动提前同ZURU QC预约验货避免延期出货造成不必要麻烦)； | Z73: Ann Zhang | AA73: 9.86 | AB73: =I73*AA73 -> 1183.2 | AD73: 71172-S001-1L | AE73: 已入 | AO73: =I73 -> 120 | AP73: =I73 -> 120 | AR73: =I73 -> 120
A74: 46134 | B74: ZETA PLAY LLC | C74: 阿塞拜疆 | D74: 4500203207 | F74: 4500203207-80 | G74: 71172-S001 | H74: 大脑 | I74: 120 | J74: 0 | K74: 4 | L74: =I74/K74 -> 30 | M74: 46188 | N74: 46184 | P74: PASS | Q74: 6/16 SI | S74: 无 | T74: 46135 | U74: 46135 | Y74: 日期码格式：ZURU INC(BVI) 标准格式 日期：按实际生产日期 Packaging Info: MA UPC 包装+通用贴纸，MA PDQ/说明书/收藏指南（如有） Remark: | Z74: Ann | AA74: 9.7 | AB74: =I74*AA74 -> 1164 | AD74: 71172-S001-1L | AE74: 已入 | AO74: =I74 -> 120 | AP74: =I74 -> 120 | AR74: =I74 -> 120
A75: 46129 | B75: WALMART INC. | C75: 美国 | D75: 4500202327 | E75: 0989812986 | F75: 4500202327-10 | G75: 71172-S002 | H75: 大脑 | I75: 504 | J75: 0 | K75: 1 | L75: =I75/K75 -> 504 | M75: 46188 | N75: 46184 | O75: 6/16自检 | P75: PASS | Q75: 6/22 SI | S75: 有 | T75: 46129 | U75: 46134 | Y75: 日期码格式：DGYYYYMMDD(日期避开周末和法定节假日) 日期：按实际生产日期 Packaging Info: 40REP 包装/箱唛翻单：4500202318 1.包装方式： 71172: MA 1L彩盒包装+MA 15L A版说明书+ RFID贴纸 Remark: 2. 外箱四面印刷紫色RFID箱唛 主唛左前下角印刷艾利贴纸替代标箱唛(ITF-14格式)，条码只印刷一面 主唛右下角加印 MADE IN CHINA以及ZURU LOGO 3. 71172 UPC：193052098443 4.此批单#71172散箱出货； 1PCS/CTN：3PCS AA BATTERIES(INCLUDED) 5.此单需要验货，请自行多备包装物料。 6.产品和包装上要有日期码、MADE IN CHINA和ZURU字样。 7.每PCS要加RFID 贴纸(ZURU提供)，严格按照我们提供的位置图，不可擅自调整位置，贴纸也不可有任何破损或折坏，不可淋湿（如缺数请及时告知） | Z75: Nikki Mo | AA75: 5.82 | AB75: =I75*AA75 -> 2933.28 | AC75: ZB06557-8.17 | AD75: 71172-S002-1L | AE75: 已入 | AO75: =I75 -> 504 | AP75: =I75 -> 504 | AS75: =AP75 -> 504
A76: 46129 | B76: WALMART INC. | C76: 美国 | D76: 4500202327 | E76: 0989813325 | F76: 4500202327-20 | G76: 71172-S002 | H76: 大脑 | I76: 1008 | J76: 0 | K76: 1 | L76: =I76/K76 -> 1008 | M76: 46188 | N76: 46184 | O76: 6/16自检 | P76: PASS | Q76: 6/22 SI | S76: 有 | T76: 46129 | U76: 46134 | Y76: 日期码格式：DGYYYYMMDD(日期避开周末和法定节假日) 日期：按实际生产日期 Packaging Info: 40REP 包装/箱唛翻单：4500202318 1.包装方式： 71172: MA 1L彩盒包装+MA 15L A版说明书+ RFID贴纸 Remark: 2. 外箱四面印刷紫色RFID箱唛 主唛左前下角印刷艾利贴纸替代标箱唛(ITF-14格式)，条码只印刷一面 主唛右下角加印 MADE IN CHINA以及ZURU LOGO 3. 71172 UPC：193052098443 4.此批单#71172散箱出货； 1PCS/CTN：3PCS AA BATTERIES(INCLUDED) 5.此单需要验货，请自行多备包装物料。 6.产品和包装上要有日期码、MADE IN CHINA和ZURU字样。 7.每PCS要加RFID 贴纸(ZURU提供)，严格按照我们提供的位置图，不可擅自调整位置，贴纸也不可有任何破损或折坏，不可淋湿（如缺数请及时告知） | Z76: Nikki Mo | AA76: 5.82 | AB76: =I76*AA76 -> 5866.56 | AC76: ZB06805-8.17 | AD76: 71172-S002-1L | AE76: 已入 | AO76: =I76 -> 1008 | AP76: =I76 -> 1008 | AS76: =AP76 -> 1008
A77: 46129 | B77: WALMART INC. | C77: 美国 | D77: 4500202327 | E77: 0989813334 | F77: 4500202327-30 | G77: 71172-S002 | H77: 大脑 | I77: 576 | J77: 0 | K77: 1 | L77: =I77/K77 -> 576 | M77: 46188 | N77: 46184 | O77: 6/16自检 | P77: PASS | Q77: 6/22 SI | S77: 有 | T77: 46129 | U77: 46134 | Y77: 日期码格式：DGYYYYMMDD(日期避开周末和法定节假日) 日期：按实际生产日期 Packaging Info: 40REP 包装/箱唛翻单：4500202318 1.包装方式： 71172: MA 1L彩盒包装+MA 15L A版说明书+ RFID贴纸 Remark: 2. 外箱四面印刷紫色RFID箱唛 主唛左前下角印刷艾利贴纸替代标箱唛(ITF-14格式)，条码只印刷一面 主唛右下角加印 MADE IN CHINA以及ZURU LOGO 3. 71172 UPC：193052098443 4.此批单#71172散箱出货； 1PCS/CTN：3PCS AA BATTERIES(INCLUDED) 5.此单需要验货，请自行多备包装物料。 6.产品和包装上要有日期码、MADE IN CHINA和ZURU字样。 7.每PCS要加RFID 贴纸(ZURU提供)，严格按照我们提供的位置图，不可擅自调整位置，贴纸也不可有任何破损或折坏，不可淋湿（如缺数请及时告知） | Z77: Nikki Mo | AA77: 5.916 | AB77: =I77*AA77 -> 3407.616 | AC77: ZB06611-8.17 | AD77: 71172-S002-1L | AE77: 已入 | AO77: =I77 -> 576 | AP77: =I77 -> 576 | AS77: =AP77 -> 576
A78: 46129 | B78: WALMART INC. | C78: 美国 | D78: 4500202327 | E78: 0989813074 | F78: 4500202327-40 | G78: 71172-S002 | H78: 大脑 | I78: 648 | J78: 0 | K78: 1 | L78: =I78/K78 -> 648 | M78: 46188 | N78: 46184 | O78: 6/16自检 | P78: PASS | Q78: 6/22 SI | S78: 有 | T78: 46129 | U78: 46134 | Y78: 日期码格式：DGYYYYMMDD(日期避开周末和法定节假日) 日期：按实际生产日期 Packaging Info: 40REP 包装/箱唛翻单：4500202318 1.包装方式： 71172: MA 1L彩盒包装+MA 15L A版说明书+ RFID贴纸 Remark: 2. 外箱四面印刷紫色RFID箱唛 主唛左前下角印刷艾利贴纸替代标箱唛(ITF-14格式)，条码只印刷一面 主唛右下角加印 MADE IN CHINA以及ZURU LOGO 3. 71172 UPC：193052098443 4.此批单#71172散箱出货； 1PCS/CTN：3PCS AA BATTERIES(INCLUDED) 5.此单需要验货，请自行多备包装物料。 6.产品和包装上要有日期码、MADE IN CHINA和ZURU字样。 7.每PCS要加RFID 贴纸(ZURU提供)，严格按照我们提供的位置图，不可擅自调整位置，贴纸也不可有任何破损或折坏，不可淋湿（如缺数请及时告知） | Z78: Nikki Mo | AA78: 5.916 | AB78: =I78*AA78 -> 3833.568 | AC78: ZB06750-8.17 | AD78: 71172-S002-1L | AE78: 已入 | AO78: =I78 -> 648 | AP78: =I78 -> 648 | AS78: =AP78 -> 648
A79: 46148 | B79: CRG | C79: 哥斯达黎加 | D79: 4500205015 | F79: 4500205015-60 | G79: 71172-S001 | H79: 大脑 | I79: 360 | J79: 0 | K79: 4 | L79: =I79/K79 -> 90 | M79: 46188 | N79: 46184 | P79: PASS | Q79: 6/24截仓 | S79: 无 | T79: 46154 | U79: 46167 | Y79: 日期码格式：ZURU INC(BVI) 标准格式 日期：按实际生产日期 Packaging Info: 71137/71101/71172/77843GQ2/77858:MA 多语包装+进口商贴纸+UPC贴纸+箱唛 Remark: 后续提供的进口商贴纸和UPC贴纸合并为一张的话，请忽略订单的UPC贴纸需求，产品的条码必须是UPC的 | Z79: Ava Liang | AA79: 9.86 | AB79: =I79*AA79 -> 3549.6 | AD79: 71172-S001-3L | AE79: 已入 | AO79: =I79 -> 360 | AQ79: =AO79 -> 360 | AR79: =AO79 -> 360
A80: 46140 | B80: LEKIA AB | C80: 瑞典 | D80: 4500204487 | F80: 4500204487-10 | G80: 71172-S001 | H80: 大脑 | I80: 1000 | J80: 0 | K80: 4 | L80: =I80/K80 -> 250 | M80: 46191 | N80: 46188 | P80: PASS | Q80: 6/23 SI | S80: 无 | T80: 46149 | U80: 无 | V80: WEEE书仔5/20 | Y80: 日期码格式：ZURU INC(BVI) 标准格式 日期：按实际生产日期 Packaging Info: 1. 71172: MA A3L(23L warning) EAN版彩盒+MA A15L说明书+一张额外说明书书纸(说明书上的玩法/battery safety information以及WEEE翻译成丹麦瑞典芬兰挪威 爱沙尼亚语--书纸翻单PO#4500200447)) Remark: 1. 包装如含PVC,请改为PET 2. 产品/包装要求无硼无香； 3. 出欧洲，微塑料需合规。 4.带电池出货的产品所用到的电池需要符合欧洲电池新规(EU) 2023-1542 5.产品/包装不含PFAS and/or Bisfenol成分, 以及不含石棉成分 6. 产品条码如下: 请先检查条码是否正确再安排做货，如有问题请告知: 71172-S001:4894680057272 | Z80: Sheba | AA80: 9.86 | AB80: =I80*AA80 -> 9860 | AD80: 71172-S001-3L | AE80: 已入 | AO80: =I80 -> 1000 | AQ80: =I80 -> 1000 | AR80: =I80 -> 1000
A81: 46151 | B81: JOINCO IMPORTACAO E EXPORTACAO LDA | C81: 葡萄牙 | D81: 4500205940 | F81: 4500205940-30 | G81: 71172-S001 | H81: 大脑 | I81: 400 | J81: 0 | K81: 4 | L81: =I81/K81 -> 100 | M81: 46191 | N81: =M81-3 -> 46188 | O81: 有 | P81: PASS | Q81: 46208 | S81: 无 | T81: 46163 | U81: 46169 | Y81: 日期码格式：ZURU INC(BVI) 标准格式 日期：按实际生产日期 Packaging Info:3.71172：最新MA 3L EAN 版本包装+ 一张进口商贴纸+最新MA 15L 说明书； Remark: 1.此单有第三方验货，请多备料。走LC信用证。需准时完货 延期有罚款。 2.大货样品2套/item，CRD前两周寄出。 3. 此单出葡萄牙，需满足EU测试标准，微塑料需符合法规 | Z81: Miya Fang | AA81: 9.86 | AB81: =I81*AA81 -> 3944 | AD81: 71172-S001-3L | AE81: 已入 | AO81: =I81 -> 400 | AQ81: =AO81 -> 400 | AS81: =AO81 -> 400
A82: 46136 | B82: SMYTHS TOYS EU HQ UNLIMITED COMPANY | C82: 法国 | D82: 4500204054 | E82: 4400564507 | F82: 4500204054-130 | G82: 71172-S001 | H82: 大脑 | I82: 88 | J82: 0 | K82: 4 | L82: =I82/K82 -> 22 | M82: 46192 | N82: 46188 | P82: PASS | Q82: 6/18送库有6/22 SI | S82: 无 | T82: 46141 | U82: 无 | Y82: 日期码格式：ZURU INC(BVI) 标准格式 日期：按实际生产日期 Packaging Info: "71172: MA3L-23Lwarning彩盒(含法国sorting label)+D版WEEE声明(带电池)走货欧洲通用29L说明书 EAN#4894680057272 3PCS AA BATTERIES(INCLUDED)" Remark: Smyths 法国 1. 请准时出货，推期会有罚款； 2. 所有产品按符合欧洲标准走货，需要是不含微塑料版本。 3. 电子产品需增加一张C版WEEE声明29L通用黑白说明书(不接受A版本，翻译有误)，区分带电池和不带电池出货版本, 如已做客版说明书可忽略此要求；如包装备注 上缺少此部分信息，请提醒跟单更新备注。 4. 出口法国的产品, 法规规定禁止在包装和共公众用的印刷品中使用矿物油中含有的物质, 包装印刷油墨中含有的MOAH/MOSH的质量浓度不能超过0.1%, 否则出货 到法国被抽检出现问题, 供应商需要对此负责; 5.订单备注显示有分批的(不同仓库/订单号), 一定要区分客户订单号做货出货，否则会导致罚款 。 6.包装日期码按ZURU格式即可，请确保不迟于外箱日期码，可等于或者早于外箱日期码，必须为法定工作日。 7.做货前请先复核包装条码与订单是否一致再安排，对不上的需与ZURU跟单确认再安排。 8.包装必须含法国回收标(Sorting Label)，如没有，请提醒跟单提供贴纸资料。 | Z82: Sherry Lu | AA82: 9.86 | AB82: =I82*AA82 -> 867.68 | AD82: 71172-S001-3L | AE82: 已入 | AO82: =I82 -> 88 | AQ82: =I82 -> 88 | AR82: =I82 -> 88
A83: 46136 | B83: SMYTHS TOYS EU HQ UNLIMITED COMPANY | C83: 法国 | D83: 4500204054 | E83: 4400564839 | F83: 4500204054-140 | G83: 71172-S001 | H83: 大脑 | I83: 212 | J83: 0 | K83: 4 | L83: =I83/K83 -> 53 | M83: 46192 | N83: 46188 | P83: PASS | Q83: 6/18送库有6/22 SI | S83: 无 | T83: 46141 | U83: 无 | Y83: 日期码格式：ZURU INC(BVI) 标准格式 日期：按实际生产日期 Packaging Info: "71172: MA3L-23Lwarning彩盒(含法国sorting label)+D版WEEE声明(带电池)走货欧洲通用29L说明书 EAN#4894680057272 3PCS AA BATTERIES(INCLUDED)" Remark: Smyths 法国 1. 请准时出货，推期会有罚款； 2. 所有产品按符合欧洲标准走货，需要是不含微塑料版本。 3. 电子产品需增加一张C版WEEE声明29L通用黑白说明书(不接受A版本，翻译有误)，区分带电池和不带电池出货版本, 如已做客版说明书可忽略此要求；如包装备注 上缺少此部分信息，请提醒跟单更新备注。 4. 出口法国的产品, 法规规定禁止在包装和共公众用的印刷品中使用矿物油中含有的物质, 包装印刷油墨中含有的MOAH/MOSH的质量浓度不能超过0.1%, 否则出货 到法国被抽检出现问题, 供应商需要对此负责; 5.订单备注显示有分批的(不同仓库/订单号), 一定要区分客户订单号做货出货，否则会导致罚款 。 6.包装日期码按ZURU格式即可，请确保不迟于外箱日期码，可等于或者早于外箱日期码，必须为法定工作日。 7.做货前请先复核包装条码与订单是否一致再安排，对不上的需与ZURU跟单确认再安排。 8.包装必须含法国回收标(Sorting Label)，如没有，请提醒跟单提供贴纸资料。 | Z83: Sherry Lu | AA83: 9.86 | AB83: =I83*AA83 -> 2090.32 | AD83: 71172-S001-3L | AE83: 已入 | AO83: =I83 -> 212 | AQ83: =I83 -> 212 | AR83: =I83 -> 212
A84: 46142 | B84: TARGET US | C84: 美国 | D84: 4500204928 | E84: 10001737601-3890 | F84: 4500204928-10 | G84: 71172-S001 | H84: 大脑 | I84: 700 | J84: 0 | K84: 4 | L84: =I84/K84 -> 175 | M84: 46192 | N84: 46188 | P84: PASS | Q84: 7/9客上柜 | S84: 有 | T84: 46157 | U84: 46169 | Y84: 日期码格式：ZURU INC(BVI) 标准格式 日期：按实际生产日期 Packaging Info: 产品包装MA 1L彩盒 Remark: 1. 71172-S001-ROBO ALIVE-BRAIN-SERIES 1-BRIAN THE BRAIN-OPEN BOX-4PCS/CTN 2. 产品包装MA 1L彩盒；彩盒上的UPC显示193052098443； 3. 每个外箱正唛箱唛信息左上方位置粘贴条码箱贴纸，每箱只贴一张; 由ZURU向艾利订购， 对应的外箱贴DPCI：087-02-9468, UPC显示10193052098440 ； 4. 产品和包装上要印刷tracking code信息，格式为ZURU常规； 5. 出货方式：货代自提 | Z84: Holly Zheng | AA84: 5.82 | AB84: =I84*AA84 -> 4074 | AC84: ZB06829-8.17 | AD84: 71172-S001-1L | AE84: 已入 | AO84: =I84 -> 700 | AP84: =I84 -> 700 | AR84: =I84 -> 700
A85: 46129 | B85: ESAL TRADING L.L.C. | C85: 阿拉伯联合酋长国 | D85: 4500202382 | F85: 4500202382-180 | G85: 71172-S001 | H85: 大脑 | I85: 720 | J85: 0 | K85: 4 | L85: 180 | M85: 46171 | N85: 46191 | O85: N/A | P85: PASS | Q85: 7/6 SI | T85: 46132 | U85: 5/21增加AR黑白双面说明纸 | Y85: 日期码格式：ZURU INC(BVI) 标准格式 日期：按实际生产日期 Packaging Info: 出UAE, 包装不能有希伯来语，需备两套大货版寄到SZ办公室。 所有RBC的产品（内外）包装上不能有彩虹。 77673TQ1:MA 1L PKG, PDQ+彩色贴纸+进口商贴纸（贴纸翻单4500162345）；收缩膜+进口商贴纸(含G Mark, QR code, 阿拉伯警语) （贴纸翻单4500162345）；贴 纸上的QR code需微信可扫; MA收藏指南+彩色贴纸（贴纸翻单4500162345）； MA说明书+一张客制黑白说明书纸（书纸翻单4500162345）； 客人箱唛排版，印4面，条码内容：193052079404 77803GQ2:MA 1L PKG, 收缩膜(加UPC贴纸+进口商贴纸) +贴纸+客版PDQ跟回77782GQ1-S001-INT（翻单号4500161302）+客版收藏指南（客版包装翻单4500162410）; PDQ+进口商贴纸， 贴纸AW翻单4500189510。 客人箱唛排版，印4面，条码内容193052092403 77843GQ2:MA 1L PKG+进口商贴纸 (含G Mark, QR code, 阿拉伯警语); 贴纸上的QR code需微信可扫; 扫描结果另外通知； UPC条码显示193052099105； 客人箱唛排版，印4面，条码内容193052099105 77858:MA 1L PKG+进口商贴纸 (含G Mark, QR code, 阿拉伯警语); 贴纸上的QR code需微信可扫; 扫描结果另外通知； UPC条码显示193052100238； 客人箱唛排版，印4面，条码内容193052100238 9565GQ1:MA 1L 收缩膜+进口商贴纸(含G Mark, QR code, 阿拉伯警语) ；贴纸上的QR code需微信可扫; MA说明书(不含希伯来语/Hebrew/He)+一张客制黑白说明书 纸(翻单4500167242)；MA PDQ+进口商贴纸; 产品年龄2+;AW翻单4500193317 4 assortment, Orange:blue:pink:brown=5:5:6:6 客人箱唛排版，印4面，条码内容：193052084545； 返工消耗4500189510/4500189525的库存，需将WEEE(含希伯来语）的说明书去除。 9574:MA 1L PKG+进口商贴纸 (含G Mark, QR code, 阿拉伯警语); 贴纸上的QR code需微信可扫; 扫描结果另外通知； UPC条码显示193052098436； 客人箱唛排版，印4面，条码内容193052098436 92104TQ1: 客版收缩膜(含G Mark, QR code, 阿拉伯警语); 贴纸上的QR code需微信可扫; UPC条码显示193052064417; 客版PDQ+进口商贴纸; 客版收藏指南; 客版 镭射贴纸；MA 口水胶袋+贴纸；产品年龄3+；AW翻单4500189525 客人箱唛排版，印4面，条码内容193052064417； 92105: 客版包装(含G Mark, QR code, 阿拉伯警语); 贴纸上的QR code需微信可扫，扫描结果另外通知; UPC条码显示193052064165；客版收藏指南/客版贴纸/客 版证明卡， MA 胶袋。 客人箱唛排版，印4面，条码内容193052064165 92119:客版收缩膜 (含G Mark, QR code, 阿拉伯警语); 贴纸上的QR code需微信可扫; UPC条码显示193052078391; 客版收藏指南; MA 口水胶袋+贴纸；产品年龄3 +；AW全部翻单4500189525 客人箱唛排版，印4面，条码内容193052078391； 92119-S001: 7 Assortment, Polar bear: Penguin: Walrus: Mammoth: Owl: Seal: Snow man=10:10:10:10:10:8:2. Snow man is the rare item. 92125：1. 客版收缩膜 (含G Mark, QR code, 阿拉伯警语); 贴纸上的QR code需微信可扫，扫描结果另外通知; UPC条码显示193052083951; 客版收藏指南；客版 镭射贴纸；客版出生证明卡片；MA 口水胶袋/罐子+logo贴纸；产品年龄3+；AW全部翻单4500189525 2. 6 Assortments,siamese cat:pink-white cat:purple cat:black cat:brown-white cat:orange cat=1:1:1:1:1:1, no rare; 3.客人箱唛排版，印4面，条码内容193052083951； 92129TQ1：客版收缩膜(含G Mark, QR code, 阿拉伯警语); 贴纸上的QR code需微信可扫，扫描结果另外通知; UPC条码显示193052088925;客版PDQ+进口商贴纸; 客 版收藏指南; 客版镭射贴纸；MA 口水胶袋+贴纸；产品年龄3+；AW全部翻单4500189525 客人箱唛排版，印4面，条码内容193052088925； 7 assortments, Ratio: Elephant: Toucan: Zebra: Sloth: Giraffe: Tiger: Peacock=10: 10: 10: 10: 10: 8: 2; 92146TQ1：客版收缩膜 (含G Mark, QR code, 阿拉伯警语); 贴纸上的QR code需微信可扫; 扫描结果另外通知； UPC条码显示193052100375；客版PDQ, 客版收藏 指南，其他配件包装为MA。 客人箱唛排版，印4面，条码内容1193052100375. 92147：客版收缩膜 (含G Mark, QR code, 阿拉伯警语); 贴纸上的QR code需微信可扫; 扫描结果另外通知； UPC条码显示193052100382；客版收藏指南，其他配件 等包装用MA. 客人箱唛排版，印4面，条码内容193052100382. 9283：客版收缩膜(含G Mark, QR code, 阿拉伯警语); 贴纸上的QR code需微信可扫; UPC条码显示193052050106; 客版收藏指南;客版卡片；客版地图指南；客版镭 射贴纸；MA 口水胶袋+贴纸；产品年龄3+；AW全部翻单4500189525 客人箱唛排版，印4面，条码内容193052050106； 9283-S001: Kitten:Bunny:Puppy:Cow:Elephant:Flamingo=1:1:1:1:1:1; 9296：客版收缩膜(含G Mark, QR code, 阿拉伯警语); 贴纸上的QR code需微信可扫; 扫描结果另外通知； UPC条码显示193052057129；客版收藏指南，其他配件为 MA。 客人箱唛排版，印4面，条码内容193052057129. 9298TQ1：客版收缩膜 (含G Mark, QR code, 阿拉伯警语); 贴纸上的QR code需微信可扫; UPC条码显示193052057426; 客版PDQ+进口商贴纸; 客版收藏指南; MA 口 水胶袋+贴纸；产品年龄3+；AW全部翻单4500189510 客人箱唛排版，印4面，条码内容193052057426； 7 assortment (6 common + 1 rare)=CORGI(Rare):SHEPHERD:POODLE:DALMATIAN: SCHNAUZER:BROWN DALNATIAN:HOUND DOG=2:8:10:10:10:10:10; 71152：MA 1L 收缩膜+进口商贴纸 (含G Mark, QR code, 阿拉伯警语)( 贴纸翻单4500162474); 贴纸上的QR code需微信可扫，扫描结果另外通知; 收缩膜上UPC条 码为193052079190；说明书+贴纸(说明书贴纸翻单4500162345); 产品年龄3+； 客人箱唛排版，印4面，条码内容193052079190； 所有包装需要不含希伯来语/Hebrew/(He) 语言 71172：MA PKG+进口商贴纸 (含G Mark, QR code, 阿拉伯警语); 贴纸上的QR code需微信可扫; 扫描结果另外通知； UPC条码显示193052098443；含MA说明书，需 另外加一张阿拉伯语的黑白印刷sheet一起出货。 客人箱唛排版，印4面，条码内容193052098443. 7132：1. MA 彩盒+进口商贴纸 (含G Mark, QR code, 阿拉伯警语)(贴纸翻单4500128286); 贴纸上的QR code需微信可扫，扫描结果为40935; UPC条码显示19305202 8174; MA说明书(不含希伯来语/Hebrew/He); 产品年龄3+; 2. 客人箱唛排版，印4面，条码内容193052028174； 所有包装需要不含希伯来语/Hebrew/(He) 语言 7133：MA 彩盒+进口商贴纸 (含G Mark, QR code, 阿拉伯警语)（贴纸翻单4500148906）; 贴纸上的QR code需微信可扫，扫描结果另外通知; 收缩膜上UPC条码为19 3052028181；客版说明书（说明书翻单4500148906）；产品年龄3+； 客人箱唛排版，印4面，条码内容193052028181； 所有包装需要不含希伯来语/Hebrew/(He) 语言 Remark: | Z85: Doris Shou | AA85: 9.86 | AB85: 7099.2 | AD85: 71172-S001-1L | AE85: 已入 | AO85: 720 | AP85: 720 | AR85: 720
A86: 46136 | B86: SMYTHS TOYS HQ UC IE | C86: 爱尔兰 | D86: 4500204025 | E86: 4400563555 | F86: 4500204025-90 | G86: 71172-S001 | H86: 大脑 | I86: 352 | J86: 0 | K86: 4 | L86: =I86/K86 -> 88 | M86: 46195 | N86: 46191 | P86: PASS | Q86: 46206 | T86: 46141 | U86: 无 | Y86: 日期码格式：ZURU INC(BVI) 标准格式 日期：按实际生产日期 Packaging Info: "71172: MA3L-23Lwarning彩盒(含法国sorting label)+D版WEEE声明(带电池)走货欧洲通用29L说明书 EAN#4894680057272 3PCS AA BATTERIES(INCLUDED)" 7 Assortments; Rare assortment 1/24, others even ratio *外箱四面需要贴一张限制上架日期贴纸(GLOBAL ONSHELF DATE:2026/6/14), 翻PO#4500203953*" Remark: Smyths 英国/爱尔兰 1. 请准时出货，推期会有罚款； 2. 所有产品按符合欧洲标准走货，需要是不含微塑料版本。 3.包装日期码按ZURU格式即可，请确保不迟于外箱日期码，可等于或者早于外箱日期码，必须为法定工作日，印刷前请先检查外箱日期码。 4.请注意检查产品及包装应带UKCA图标（14+产品除外），包装显示ZURU UK LTD/ZURU France地址信息，QC部门请查核，如有问题与跟单确认 5.电子产品需增加一张C版WEEE声明29L通用黑白说明书(不接受A版本，翻译有误)，区分带电池和不带电池出货版本, 如已做客版说明书可忽略此要求；如包装备注 上缺少此部分信息，请提醒跟单更新备注。 6.订单备注显示有分批的(不同仓库/订单号), 一定要区分客户订单号做货出货，否则会导致罚款 。 7.做货前请先复核包装条码与订单是否一致再安排，对不上的需与ZURU跟单确认再安排。 8.包装必须含法国回收标(Sorting Label)，如没有，请提醒跟单提供贴纸资料。 | Z86: Sherry Lu | AA86: 9.86 | AB86: =I86*AA86 -> 3470.72 | AD86: 71172-S001-3L | AE86: 已入 | AO86: =I86 -> 352 | AQ86: =I86 -> 352 | AR86: =I86 -> 352
A87: 46153 | B87: ARMY & AIR FORCE EXCHANGE SERVICE | C87: 美国 | D87: 4500206179 | E87: 0092593222 | F87: 4500206179-360 | G87: 71172-S001 | H87: 大脑 | I87: 60 | J87: 0 | K87: 4 | L87: =I87/K87 -> 15 | M87: 46195 | N87: 46191 | P87: HOLD | Q87: 46199 | T87: 46161 | U87: 46169 | Y87: 日期码格式：ZURU INC(BVI) 标准格式 日期：按实际生产日期 Packaging Info: 1. MA+UPC版包裝,优先1L，出口美国 Remark: 2. PO# 0092593216, 0092593219, 0092593222, 这3个订单外箱需要贴4x6"UCC 贴纸，只需贴一面（UCC贴纸为客供贴纸）。PO# 0092593217, 0092593221，这2个订 单外箱不需要UCC贴纸。 3. ZURU QC 验货。 4. 产品和包裝上需印刷tracking code信息，格式为ZURU常规。 | Z87: Cara Li | AA87: 7.1735 | AB87: =I87*AA87 -> 430.41 | AC87: ZB06751-8.17 | AD87: 71172-S001-1L | AE87: 已入 | AO87: =I87 -> 60 | AP87: =AO87 -> 60 | AR87: =AO87 -> 60
A88: 46153 | B88: ARMY & AIR FORCE EXCHANGE SERVICE | C88: 美国 | D88: 4500206179 | E88: 0092593221 | F88: 4500206179-370 | G88: 71172-S001 | H88: 大脑 | I88: 36 | J88: 0 | K88: 4 | L88: =I88/K88 -> 9 | M88: 46195 | N88: 46191 | P88: HOLD | Q88: 46199 | T88: 46161 | U88: 无 | Y88: 日期码格式：ZURU INC(BVI) 标准格式 日期：按实际生产日期 Packaging Info: 1. MA+UPC版包裝,优先1L，出口美国 Remark: 2. PO# 0092593216, 0092593219, 0092593222, 这3个订单外箱需要贴4x6"UCC 贴纸，只需贴一面（UCC贴纸为客供贴纸）。PO# 0092593217, 0092593221，这2个订 单外箱不需要UCC贴纸。 3. ZURU QC 验货。 4. 产品和包裝上需印刷tracking code信息，格式为ZURU常规。 | Z88: Cara Li | AA88: 7.1736 | AB88: =I88*AA88 -> 258.2496 | AC88: ZB06627-8.17 | AD88: 71172-S001-1L | AE88: 已入 | AO88: =I88 -> 36 | AP88: =AO88 -> 36 | AR88: =AO88 -> 36
A89: 46153 | B89: ARMY & AIR FORCE EXCHANGE SERVICE | C89: 美国 | D89: 4500206179 | E89: 0092593219 | F89: 4500206179-380 | G89: 71172-S001 | H89: 大脑 | I89: 84 | J89: 0 | K89: 4 | L89: =I89/K89 -> 21 | M89: 46195 | N89: 46191 | P89: HOLD | Q89: 46199 | T89: 46161 | U89: 46169 | Y89: 日期码格式：ZURU INC(BVI) 标准格式 日期：按实际生产日期 Packaging Info: 1. MA+UPC版包裝,优先1L，出口美国 Remark: 2. PO# 0092593216, 0092593219, 0092593222, 这3个订单外箱需要贴4x6"UCC 贴纸，只需贴一面（UCC贴纸为客供贴纸）。PO# 0092593217, 0092593221，这2个订 单外箱不需要UCC贴纸。 3. ZURU QC 验货。 4. 产品和包裝上需印刷tracking code信息，格式为ZURU常规。 | Z89: Cara Li | AA89: 7.1735 | AB89: =I89*AA89 -> 602.574 | AC89: ZB06635-8.17 | AD89: 71172-S001-1L | AE89: 已入 | AO89: =I89 -> 84 | AP89: =AO89 -> 84 | AR89: =AO89 -> 84
A90: 46153 | B90: ARMY & AIR FORCE EXCHANGE SERVICE | C90: 美国 | D90: 4500206179 | E90: 0092593216 | F90: 4500206179-390 | G90: 71172-S001 | H90: 大脑 | I90: 56 | J90: 0 | K90: 4 | L90: =I90/K90 -> 14 | M90: 46195 | N90: 46191 | P90: HOLD | Q90: 46199 | T90: 46161 | U90: 46169 | Y90: 日期码格式：ZURU INC(BVI) 标准格式 日期：按实际生产日期 Packaging Info: 1. MA+UPC版包裝,优先1L，出口美国 Remark: 2. PO# 0092593216, 0092593219, 0092593222, 这3个订单外箱需要贴4x6"UCC 贴纸，只需贴一面（UCC贴纸为客供贴纸）。PO# 0092593217, 0092593221，这2个订 单外箱不需要UCC贴纸。 3. ZURU QC 验货。 4. 产品和包裝上需印刷tracking code信息，格式为ZURU常规。 | Z90: Cara Li | AA90: 7.1734 | AB90: =I90*AA90 -> 401.7104 | AC90: ZB06751-8.17 | AD90: 71172-S001-1L | AE90: 已入 | AO90: =I90 -> 56 | AP90: =AO90 -> 56 | AR90: =AO90 -> 56
A91: 46153 | B91: ARMY & AIR FORCE EXCHANGE SERVICE | C91: 美国 | D91: 4500206179 | E91: 0092593217 | F91: 4500206179-400 | G91: 71172-S001 | H91: 大脑 | I91: 64 | J91: 0 | K91: 4 | L91: =I91/K91 -> 16 | M91: 46195 | N91: 46191 | P91: HOLD | Q91: 46199 | T91: 46161 | U91: 无 | Y91: 日期码格式：ZURU INC(BVI) 标准格式 日期：按实际生产日期 Packaging Info: 1. MA+UPC版包裝,优先1L，出口美国 Remark: 2. PO# 0092593216, 0092593219, 0092593222, 这3个订单外箱需要贴4x6"UCC 贴纸，只需贴一面（UCC贴纸为客供贴纸）。PO# 0092593217, 0092593221，这2个订 单外箱不需要UCC贴纸。 3. ZURU QC 验货。 4. 产品和包裝上需印刷tracking code信息，格式为ZURU常规。 | Z91: Cara Li | AA91: 7.1734 | AB91: =I91*AA91 -> 459.0976 | AC91: ZB06751-8.17 | AD91: 71172-S001-1L | AE91: 已入 | AO91: =I91 -> 64 | AP91: =AO91 -> 64 | AR91: =AO91 -> 64
A92: 46142 | B92: SALLING GROUP A/S | C92: 丹麦 | D92: 4500203672 | E92: 4045802239 | F92: 4500203672-10 | G92: 71172-S001 | H92: 大脑 | I92: 1160 | J92: 0 | K92: 4 | L92: =I92/K92 -> 290 | M92: 46196 | N92: 46192 | P92: PASS | Q92: 6/30 SI | T92: 46163 | U92: 无 | Y92: 日期码格式：ZURU INC(BVI) 标准格式 日期：按实际生产日期 Packaging Info: 1. MA A3L(23L warning) EAN版彩盒+MA A15L说明书+一张额外说明书书纸(说明书上的玩法/battery safety information以及WEEE翻译成丹麦瑞典芬兰挪威爱沙尼 亚语--书纸翻单Lekia PO#4500200447) Remark: * 71172是新品，请在6/10寄两套大货样给客人留底 1. 包装如含PVC,请改为PET 2. 产品/包装要求无硼无香； 3. 出欧洲，微塑料需合规。 4.带电池出货的产品所用到的电池需要符合欧洲电池新规(EU) 2023-1542 5.关于贴纸，如果贴纸位置图的包装版本与大货不一致，请工厂提前提出, 跟单会重新调整确认是否更新贴纸或调整位置图 6.产品/包装不含PFAS and/or Bisfenol成分,以及不含石棉成分 7. 产品条码如下: 请先检查条码是否正确再安排做货，如有问题请告知: 71172-S001:4894680057272 | Z92: Sheba | AA92: 9.86 | AB92: =I92*AA92 -> 11437.6 | AD92: 71172-S001-3L | AE92: 已入 | AO92: =I92 -> 1160 | AQ92: =I92 -> 1160 | AR92: =I92 -> 1160
A93: 46142 | B93: SALLING GROUP A/S | C93: 丹麦 | D93: 4500203674 | E93: 4045802242 | F93: 4500203674-10 | G93: 71172-S001 | H93: 大脑 | I93: 340 | J93: 0 | K93: 4 | L93: =I93/K93 -> 85 | M93: 46196 | N93: 46192 | P93: PASS | Q93: 6/30 SI | T93: 46163 | U93: 无 | Y93: 日期码格式：ZURU INC(BVI) 标准格式 日期：按实际生产日期 Packaging Info: 1. 71172: MA A3L(23L warning) EAN版彩盒+MA A15L说明书+一张额外说明书书纸(说明书上的玩法/battery safety information以及WEEE翻译成丹麦瑞典芬兰挪威 爱沙尼亚语--书纸翻单Lekia PO#4500200447) Remark: * 请准备1个40尺平柜的安全网，客人要求所有柜货需要加安全网出货，漏拉网会有罚款产生 * 77711+92146是新品，请在6/10各寄两套大货样给客人留底 1. 包装如含PVC,请改为PET 2. 产品/包装要求无硼无香； 3. 出欧洲，微塑料需合规。 4.带电池出货的产品所用到的电池需要符合欧洲电池新规(EU) 2023-1542 5.关于贴纸，如果贴纸位置图的包装版本与大货不一致，请工厂提前提出, 跟单会重新调整确认是否更新贴纸或调整位置图 6.产品/包装不含PFAS and/or Bisfenol成分,以及不含石棉成分 7. 产品条码如下: 请先检查条码是否正确再安排做货，如有问题请告知: 71172-S001:4894680057272 77711GQ1-S002-INT:4894680043350 92146TQ1-S002:4894680058934 | Z93: Sheba | AA93: 9.86 | AB93: =I93*AA93 -> 3352.4 | AD93: 71172-S001-3L | AE93: 已入 | AO93: =I93 -> 340 | AQ93: =I93 -> 340 | AR93: =I93 -> 340
A94: 46129 | B94: WALMART INC. | C94: 美国 | D94: 4500202341 | E94: 0989813181 | F94: 4500202341-10 | G94: 71172-S002 | H94: 大脑 | I94: 504 | J94: 0 | K94: 1 | L94: =I94/K94 -> 504 | M94: 46197 | N94: 46193 | O94: 46203 | P94: PASS | Q94: 7/9 SI | S94: 有 | T94: 46129 | U94: 46134 | Y94: 日期码格式：DGYYYYMMDD(日期避开周末和法定节假日) 日期：按实际生产日期 Packaging Info: 40REP 包装/箱唛翻单：4500202318 1.包装方式： 71172: MA 1L彩盒包装+MA 15L A版说明书+ RFID贴纸 Remark: 2. 外箱四面印刷紫色RFID箱唛 主唛左前下角印刷艾利贴纸替代标箱唛(ITF-14格式)，条码只印刷一面 主唛右下角加印 MADE IN CHINA以及ZURU LOGO 3. 71172 UPC：193052098443 4.此批单#71172散箱出货； 1PCS/CTN：3PCS AA BATTERIES(INCLUDED) 5.此单需要验货，请自行多备包装物料。 6.产品和包装上要有日期码、MADE IN CHINA和ZURU字样。 7.每PCS要加RFID 贴纸(ZURU提供)，严格按照我们提供的位置图，不可擅自调整位置，贴纸也不可有任何破损或折坏，不可淋湿（如缺数请及时告知） | Z94: Nikki Mo | AA94: 5.82 | AB94: =I94*AA94 -> 2933.28 | AC94: ZB06881-8.17 | AD94: 71172-S002-1L | AE94: 已入 | AO94: =I94 -> 504 | AP94: =I94 -> 504 | AS94: =AP94 -> 504
A95: 46129 | B95: WALMART INC. | C95: 美国 | D95: 4500202341 | E95: 0989813277 | F95: 4500202341-20 | G95: 71172-S002 | H95: 大脑 | I95: 504 | J95: 0 | K95: 1 | L95: =I95/K95 -> 504 | M95: 46197 | N95: 46193 | O95: 46198 | P95: PASS | Q95: 7/9 SI | S95: 有 | T95: 46129 | U95: 46134 | Y95: 日期码格式：DGYYYYMMDD(日期避开周末和法定节假日) 日期：按实际生产日期 Packaging Info: 40REP 包装/箱唛翻单：4500202318 1.包装方式： 71172: MA 1L彩盒包装+MA 15L A版说明书+ RFID贴纸 Remark: 2. 外箱四面印刷紫色RFID箱唛 主唛左前下角印刷艾利贴纸替代标箱唛(ITF-14格式)，条码只印刷一面 主唛右下角加印 MADE IN CHINA以及ZURU LOGO 3. 71172 UPC：193052098443 4.此批单#71172散箱出货； 1PCS/CTN：3PCS AA BATTERIES(INCLUDED) 5.此单需要验货，请自行多备包装物料。 6.产品和包装上要有日期码、MADE IN CHINA和ZURU字样。 7.每PCS要加RFID 贴纸(ZURU提供)，严格按照我们提供的位置图，不可擅自调整位置，贴纸也不可有任何破损或折坏，不可淋湿（如缺数请及时告知） | Z95: Nikki Mo | AA95: 5.916 | AB95: =I95*AA95 -> 2981.664 | AC95: ZB06860-8.17 | AD95: 71172-S002-1L | AE95: 已入 | AO95: =I95 -> 504 | AP95: =I95 -> 504 | AS95: =AP95 -> 504
A96: 46129 | B96: WALMART INC. | C96: 美国 | D96: 4500202341 | E96: 0989813289 | F96: 4500202341-30 | G96: 71172-S002 | H96: 大脑 | I96: 576 | J96: 0 | K96: 1 | L96: =I96/K96 -> 576 | M96: 46197 | N96: 46193 | O96: 46198 | P96: PASS | Q96: 7/9 SI | S96: 有 | T96: 46129 | U96: 46134 | Y96: 日期码格式：DGYYYYMMDD(日期避开周末和法定节假日) 日期：按实际生产日期 Packaging Info: 40REP 包装/箱唛翻单：4500202318 1.包装方式： 71172: MA 1L彩盒包装+MA 15L A版说明书+ RFID贴纸 Remark: 2. 外箱四面印刷紫色RFID箱唛 主唛左前下角印刷艾利贴纸替代标箱唛(ITF-14格式)，条码只印刷一面 主唛右下角加印 MADE IN CHINA以及ZURU LOGO 3. 71172 UPC：193052098443 4.此批单#71172散箱出货； 1PCS/CTN：3PCS AA BATTERIES(INCLUDED) 5.此单需要验货，请自行多备包装物料。 6.产品和包装上要有日期码、MADE IN CHINA和ZURU字样。 7.每PCS要加RFID 贴纸(ZURU提供)，严格按照我们提供的位置图，不可擅自调整位置，贴纸也不可有任何破损或折坏，不可淋湿（如缺数请及时告知） | Z96: Nikki Mo | AA96: 5.916 | AB96: =I96*AA96 -> 3407.616 | AC96: ZB07002-8.17 | AD96: 71172-S002-1L | AE96: 已入 | AO96: =I96 -> 576 | AP96: =I96 -> 576 | AS96: =AP96 -> 576
A97: 46157 | B97: Zuru Poland Sp. Z o.o. | C97: 波兰 | D97: 4500207562 | E97: 5200010084 | F97: 4500207562-140 | G97: 71172-S001-MTS | H97: 大脑 | I97: 500 | J97: 0 | K97: 4 | L97: =I97/K97 -> 125 | M97: 46197 | N97: 46193 | O97: 有 | P97: PASS | Q97: 7/1 SI | T97: 46163 | U97: 46164 | Y97: 日期码格式：ZURU INC(BVI) 标准格式 日期：按实际生产日期 Packaging Info:71172：MA 3L+23L EAN 彩盒+MA 15L 说明书+1*HU 黑白说明贴纸（贴在说明书上）+1*D版 29L WEEE带电池走货说明书 Remark: "1.波兰内销单，需要通过ZURU 验货结果后才能出货 (工厂需要主动提前同ZURU QC预约验货避免延期出货造成不必要麻烦)； 2. 产品如含有化学品，需要无硼无香；无微塑料，如果产品含有Slime、泥、沙子，需要增加一张MTS PO SLIME, DOUGH, SAND 化学品警语多语说明书； 3. 若有特定款有特殊外箱条码要求时,需要明确列出产品款对应的具体外箱条码号码/条码类型 (若无,可以忽略此需求)； 4.所有出口欧洲的产品, 法规规定禁止在包装和共公众用的印刷品中使用矿物油中含有的物质, 包装印刷油墨中含有的MOAH/MOSH的质量浓度不能超过1%, 否则出货 到法国被抽检出现问题, 供应商需要对此负责; 5. date code: 外箱日期码要晚于或等于产品日期码，不能早于产品的日期码； 6. 所有出往波兰的电子产品身上需要加字唛，为ZURU FRANCE 地址，需跟包装上的地址一致 (如无电子产品，产品布标有此地址，或产品太小无法增加可忽略此信 息。如产品无法加字唛，需让对应跟单提供产品贴纸资料) 新地址：ZURU France 33 rue Paul Meurice 75020 Paris, France 旧地址：ZURU France 1/3, Rue d'Argenteuil 95210 SAINT-GRATIEN, FRANCE 7. 装柜时需要按照款式号码从小到大一款款依次装,避免终端仓库卸货混乱.若一个柜子涉及到几个不同国家内销单,装柜时需要一个国家装完后再装另一个国家的 产品,依次装柜,避免终端仓库因不同国家不同库位位置卸货混乱. (此点需要同工厂装柜人员强调)。 8. 所有出往波兰订单的电子产品需增加一张最新版本的欧洲通用WEEE声明说明书，区分带电池和不带电池版本, 如已做客版说明书可忽略此要求。" | Z97: Faye Lei,Amy Xiao | AA97: 9.86 | AB97: =I97*AA97 -> 4930 | AD97: 71172-S001-MTS-3L | AE97: 已入 | AO97: =I97 -> 500 | AQ97: =AO97 -> 500 | AR97: =AO97 -> 500
A98: 46134 | B98: SIPLEC | C98: 法国 | D98: 4500201774 | E98: 1346737 | F98: 4500201774-60 | G98: 71172-S001 | H98: 大脑 | I98: 88 | J98: 0 | K98: 4 | L98: =I98/K98 -> 22 | M98: 46195 | N98: 46195 | O98: 6/30第三方验货+抽板测试 | P98: 第三方抽样，抽板8-10套 | Q98: 7/9 SI | S98: 有 | T98: 46153 | U98: 46157 | W98: 1346737-26 | Y98: 日期码格式：1346737-26 日期： Packaging Info: 71152-S001: 客版彩盒(含客人指定条码/客人指定日期码1346737-26）+ MA 5L+9L B版说明书 + 额外客版黑白说明书 (含PT/SI语言+ FR/ES/PL/PT SI 5L WEEE 不 带电池出货最新版 ）+ 客人指定型号干燥器 71126-S001: MA3L EAN彩卡+客户贴纸(含SI语言+客人指定条码+客人指定日期码1346737-26)+ MA5+9L警语说明书+额外黑白说明书书纸(含PL+SI语言+WEEE不带电池 出货最新版）+客人指定干燥剂 71137-S001: MA23L警语EAN-B版彩盒+客户贴纸(含客户产品条码+指定日期码:1346737-26) + MA 5L B版说明书 + 额外客版黑白说明书 (含PL/PT/SI语言+ FR/ES/PL /PT SI 5L WEEE 不带电池出货最新版 ）+ 客人指定型号干燥器 9561-S001: MA5L+6L B版EAN彩卡+客户贴纸(含PT/PL/SI语言+客人指定条码+客人指定日期码1346737-26)+MA5L收藏指南+MA5L指导书+额外客版黑白收藏指南/指导 书书纸(含PT/PL/SI语言)+MA Slime 袋子+ SLIME 额外贴纸(PL/SI语言)+WEEE带电池出货最新版+客人指定干燥剂 71152-S001: 客版彩盒(含客人指定条码/客人指定日期码1346737-26）+ MA 5L+9L B版说明书 + 额外客版黑白说明书 (含PT/SI语言+ FR/ES/PL/PT SI 5L WEEE 不 带电池出货最新版 ）+ 客人指定型号干燥器 71126-S001: MA3L EAN彩卡+客户贴纸(含SI语言+客人指定条码+客人指定日期码1346737-26)+ MA5+9L警语说明书+额外黑白说明书书纸(含PL+SI语言+WEEE不带电池 出货最新版）+客人指定干燥剂 71137-S001: MA23L警语EAN-B版彩盒+客户贴纸(含客户产品条码+指定日期码:1346737-26) + MA 5L B版说明书 + 额外客版黑白说明书 (含PL/PT/SI语言+ FR/ES/PL /PT SI 5L WEEE 不带电池出货最新版 ）+ 客人指定型号干燥器 9561-S001: MA5L+6L B版EAN彩卡+客户贴纸(含PT/PL/SI语言+客人指定条码+客人指定日期码1346737-26)+MA5L收藏指南+MA5L指导书+额外客版黑白收藏指南/指导 书书纸(含PT/PL/SI语言)+MA Slime 袋子+ SLIME 额外贴纸(PL/SI语言)+WEEE带电池出货最新版+客人指定干燥剂 77772SK1-S002：MA3L EAN收缩膜+2张客户贴纸(含法国回收标+PT/PL/SI语言+客人指定条码+客人指定日期码1346737-26)+MA5L收藏指南+额外收藏指南贴纸(含PT/PL /SI语言）+MA小袋子+MA23L组装说明书+MA3L展示架 77772SK1-S002：MA3L EAN收缩膜+2张客户贴纸(含法国回收标+PT/PL/SI语言+客人指定条码+客人指定日期码1346737-26)+MA5L收藏指南+额外收藏指南贴纸(含PT/ PL/SI语言）+MA小袋子+MA23L组装说明书+MA3L展示架 9296-S001: MA3L+23L警语EAN B版收缩膜+客人贴纸(含指定条码+指定日期码1346737-26）+MA车缝标+MA 3L吊牌+额外吊牌贴纸(含PL/PT/SI语言）+MA9L警示语B版S LIME塑胶袋+额外贴纸(含SL语言)+MA23L B版种子袋子+MA23L 警语收藏指南B版+客人指定干燥剂 9574-S001: MA3L+23L EAN警语彩卡A版+客户贴纸（含客户产品条码+指定日期码:1346737-26)+MA7L说明书B版+额外黑白说明书( 含PT/PL/SI语言+5L WEEE不带电池 出货）+客人指定干燥剂 77858-S001: MA23L 警语EAN彩卡+客户贴纸(含客人指定条码+客人指定日期码1346737-26)+MA5L收藏指南+额外收藏指南黑白书纸(含PT/PL/SI语言）+MA23L电池说明 书+MA袋子+MA贴纸+WEEE不带电池出货最新版+客人指定干燥剂 77711GQ2-S001-INT：MA3L EAN收缩膜+客户贴纸(含法国回收标+PT/PL/SI语言+客人指定条码+客人指定日期码1346737-26)+MA配件卡+MA5L玩法说明书+额外玩法贴 纸(含PT/PL/SI语言）+MA5L UV Glue 贴纸+额外UV Glue 贴纸(PT/PL/SI语言）+MA纸袋+MA配件卡+MA23L说明书+MA3L展示盒 77673TQ1-S002：MA3L EAN彩卡+客户贴纸(含PT/PL/SI语言+客人指定条码+客人指定日期码1346737-26)+MA5L收藏指南+额外收藏指南贴纸(含PT/PL/SI语言）+MA23L 说明书+WEEE带电池出货最新版+MA3L展示盒+客人指定干燥剂 Remark: 1.预计6/24第三方验货+抽板测试，71126/71172 需每款抽板10-12套左右测试，请多备料； 2.交期前两周前准备好2套大货样给SIPLEC HK OFFICE / 实验室 3.指定日期码1346737-26 4.需在checkpoints上采购外箱贴纸, 跟单会通过邮件发送采购指引；. 5. #71152/71126/71137/9561/71172/9296/9574/9574/77858/77673TQ1 - 带电产品每箱放3包透明颗粒状干燥剂(每包约5g)，包干燥剂的袋子要有"SILICA GEL - D O NOT EAT - DESSICANT - THROW AWAY " 字样； 6. 包装禁止使用PVC塑料； 7. 此票出法国，需符合EU标准及微塑料法规，包装需含法国回收logo； | Z98: Ula Zhao | AA98: 9.86 | AB98: =I98*AA98 -> 867.68 | AD98: 71172-S001-3L | AE98: 已入 | AO98: =I98 -> 88 | AQ98: =AO98 -> 88 | AS98: =I98 -> 88
A99: 46134 | B99: SIPLEC | C99: 法国 | D99: 4500201774 | E99: 1346737 | F99: 4500201774-70 | G99: 71172-S001 | H99: 大脑 | I99: 704 | J99: 0 | K99: 4 | L99: =I99/K99 -> 176 | M99: 46195 | N99: 46195 | O99: 6/30第三方验货+抽板测试 | P99: PASS | Q99: 7/9 SI | S99: 有 | T99: 46153 | U99: 46157 | W99: 1346737-26 | Y99: 日期码格式：1346737-26 日期： Packaging Info: 71152-S001: 客版彩盒(含客人指定条码/客人指定日期码1346737-26）+ MA 5L+9L B版说明书 + 额外客版黑白说明书 (含PT/SI语言+ FR/ES/PL/PT SI 5L WEEE 不 带电池出货最新版 ）+ 客人指定型号干燥器 71126-S001: MA3L EAN彩卡+客户贴纸(含SI语言+客人指定条码+客人指定日期码1346737-26)+ MA5+9L警语说明书+额外黑白说明书书纸(含PL+SI语言+WEEE不带电池 出货最新版）+客人指定干燥剂 71137-S001: MA23L警语EAN-B版彩盒+客户贴纸(含客户产品条码+指定日期码:1346737-26) + MA 5L B版说明书 + 额外客版黑白说明书 (含PL/PT/SI语言+ FR/ES/PL /PT SI 5L WEEE 不带电池出货最新版 ）+ 客人指定型号干燥器 9561-S001: MA5L+6L B版EAN彩卡+客户贴纸(含PT/PL/SI语言+客人指定条码+客人指定日期码1346737-26)+MA5L收藏指南+MA5L指导书+额外客版黑白收藏指南/指导 书书纸(含PT/PL/SI语言)+MA Slime 袋子+ SLIME 额外贴纸(PL/SI语言)+WEEE带电池出货最新版+客人指定干燥剂 71152-S001: 客版彩盒(含客人指定条码/客人指定日期码1346737-26）+ MA 5L+9L B版说明书 + 额外客版黑白说明书 (含PT/SI语言+ FR/ES/PL/PT SI 5L WEEE 不 带电池出货最新版 ）+ 客人指定型号干燥器 71126-S001: MA3L EAN彩卡+客户贴纸(含SI语言+客人指定条码+客人指定日期码1346737-26)+ MA5+9L警语说明书+额外黑白说明书书纸(含PL+SI语言+WEEE不带电池 出货最新版）+客人指定干燥剂 71137-S001: MA23L警语EAN-B版彩盒+客户贴纸(含客户产品条码+指定日期码:1346737-26) + MA 5L B版说明书 + 额外客版黑白说明书 (含PL/PT/SI语言+ FR/ES/PL /PT SI 5L WEEE 不带电池出货最新版 ）+ 客人指定型号干燥器 9561-S001: MA5L+6L B版EAN彩卡+客户贴纸(含PT/PL/SI语言+客人指定条码+客人指定日期码1346737-26)+MA5L收藏指南+MA5L指导书+额外客版黑白收藏指南/指导 书书纸(含PT/PL/SI语言)+MA Slime 袋子+ SLIME 额外贴纸(PL/SI语言)+WEEE带电池出货最新版+客人指定干燥剂 77772SK1-S002：MA3L EAN收缩膜+2张客户贴纸(含法国回收标+PT/PL/SI语言+客人指定条码+客人指定日期码1346737-26)+MA5L收藏指南+额外收藏指南贴纸(含PT/PL /SI语言）+MA小袋子+MA23L组装说明书+MA3L展示架 77772SK1-S002：MA3L EAN收缩膜+2张客户贴纸(含法国回收标+PT/PL/SI语言+客人指定条码+客人指定日期码1346737-26)+MA5L收藏指南+额外收藏指南贴纸(含PT/ PL/SI语言）+MA小袋子+MA23L组装说明书+MA3L展示架 9296-S001: MA3L+23L警语EAN B版收缩膜+客人贴纸(含指定条码+指定日期码1346737-26）+MA车缝标+MA 3L吊牌+额外吊牌贴纸(含PL/PT/SI语言）+MA9L警示语B版S LIME塑胶袋+额外贴纸(含SL语言)+MA23L B版种子袋子+MA23L 警语收藏指南B版+客人指定干燥剂 9574-S001: MA3L+23L EAN警语彩卡A版+客户贴纸（含客户产品条码+指定日期码:1346737-26)+MA7L说明书B版+额外黑白说明书( 含PT/PL/SI语言+5L WEEE不带电池 出货）+客人指定干燥剂 77858-S001: MA23L 警语EAN彩卡+客户贴纸(含客人指定条码+客人指定日期码1346737-26)+MA5L收藏指南+额外收藏指南黑白书纸(含PT/PL/SI语言）+MA23L电池说明 书+MA袋子+MA贴纸+WEEE不带电池出货最新版+客人指定干燥剂 77711GQ2-S001-INT：MA3L EAN收缩膜+客户贴纸(含法国回收标+PT/PL/SI语言+客人指定条码+客人指定日期码1346737-26)+MA配件卡+MA5L玩法说明书+额外玩法贴 纸(含PT/PL/SI语言）+MA5L UV Glue 贴纸+额外UV Glue 贴纸(PT/PL/SI语言）+MA纸袋+MA配件卡+MA23L说明书+MA3L展示盒 77673TQ1-S002：MA3L EAN彩卡+客户贴纸(含PT/PL/SI语言+客人指定条码+客人指定日期码1346737-26)+MA5L收藏指南+额外收藏指南贴纸(含PT/PL/SI语言）+MA23L 说明书+WEEE带电池出货最新版+MA3L展示盒+客人指定干燥剂 Remark: 1.预计6/24第三方验货+抽板测试，71126/71172 需每款抽板10-12套左右测试，请多备料； 2.交期前两周前准备好2套大货样给SIPLEC HK OFFICE / 实验室 3.指定日期码1346737-26 4.需在checkpoints上采购外箱贴纸, 跟单会通过邮件发送采购指引；. 5. #71152/71126/71137/9561/71172/9296/9574/9574/77858/77673TQ1 - 带电产品每箱放3包透明颗粒状干燥剂(每包约5g)，包干燥剂的袋子要有"SILICA GEL - D O NOT EAT - DESSICANT - THROW AWAY " 字样； 6. 包装禁止使用PVC塑料； 7. 此票出法国，需符合EU标准及微塑料法规，包装需含法国回收logo； | Z99: Ula Zhao | AA99: 9.86 | AB99: =I99*AA99 -> 6941.44 | AD99: 71172-S001-3L | AE99: 已入 | AO99: =I99 -> 704 | AQ99: =AO99 -> 704 | AS99: =AO99 -> 704
A100: 46134 | B100: SIPLEC | C100: 法国 | D100: 4500201727 | E100: 1346748 | F100: 4500201727-50 | G100: 71172-S001 | H100: 大脑 | I100: 48 | J100: 0 | K100: 4 | L100: =I100/K100 -> 12 | M100: 46195 | N100: 46195 | O100: 6/30第三方验货+抽板测试 | P100: 第三方验货+抽办8-10套左右测试, | Q100: 8/11装柜 | S100: 有 | T100: 46153 | U100: 46153 | W100: 1346737-26 | Y100: 日期码格式：1346737-26 日期： Packaging Info: 71152-S001: 客版彩盒(含客人指定条码/客人指定日期码1346737-26）+ MA 5L+9L B版说明书 + 额外客版黑白说明书 (含PT/SI语言+ FR/ES/PL/PT SI 5L WEEE 不 带电池出货最新版 ）+ 客人指定型号干燥器 71126-S001: MA3L EAN彩卡+客户贴纸(含SI语言+客人指定条码+客人指定日期码1346737-26)+ MA5+9L警语说明书+额外黑白说明书书纸(含PL+SI语言+WEEE不带电池 出货最新版）+客人指定干燥剂 71137-S001: MA23L警语EAN-B版彩盒+客户贴纸(含客户产品条码+指定日期码:1346737-26) + MA 5L B版说明书 + 额外客版黑白说明书 (含PL/PT/SI语言+ FR/ES/PL /PT SI 5L WEEE 不带电池出货最新版 ）+ 客人指定型号干燥器 9561-S001: MA5L+6L B版EAN彩卡+客户贴纸(含PT/PL/SI语言+客人指定条码+客人指定日期码1346737-26)+MA5L收藏指南+MA5L指导书+额外客版黑白收藏指南/指导 书书纸(含PT/PL/SI语言)+MA Slime 袋子+ SLIME 额外贴纸(PL/SI语言)+WEEE带电池出货最新版+客人指定干燥剂 9296-S001: MA3L+23L警语EAN B版收缩膜+客人贴纸(含指定条码+指定日期码1346737-26）+MA车缝标+MA 3L吊牌+额外吊牌贴纸(含PL/PT/SI语言）+MA9L警示语B版SL IME塑胶袋+额外贴纸(含SL语言)+MA23L B版种子袋子+MA23L 警语收藏指南B版+客人指定干燥剂 9574-S001: MA3L+23L EAN警语彩卡A版+客户贴纸（含客户产品条码+指定日期码:1346737-26)+MA7L说明书B版+额外黑白说明书( 含PT/PL/SI语言+5L WEEE不带电池 出货）+客人指定干燥剂 77772GQ2-S001: MA3L EAN收缩膜+2张客户贴纸(含法国回收标+PT/PL/SI语言+客人指定条码+客人指定日期码1346737-26)+MA5L收藏指南+额外收藏指南贴纸(含PT/PL /SI语言）+MA小袋子+MA23L组装说明书+MA3L展示盒 77794UQ1-S001: 客版彩卡(含FR/ES/PT/PL/SI语言+客人指定条码+客人指定日期码1346737-26)+MA5L+23L警语收藏指南+MA小袋子+MA23L 使用说明书+MA23L锂电池说 明书+MA23L说明书+MA23L组装说明书+WEEE 带电池出货最新版+MA3L展示盒+客人指定干燥剂 77858-S001: MA23L 警语EAN彩卡+客户贴纸(含客人指定条码+客人指定日期码1346737-26)+MA5L收藏指南+额外收藏指南黑白书纸(含PT/PL/SI语言）+MA23L电池说明 书+MA袋子+MA贴纸+WEEE不带电池出货最新版+客人指定干燥剂 77711GQ2-S001-INT：MA3L EAN收缩膜+客户贴纸(含法国回收标+PT/PL/SI语言+客人指定条码+客人指定日期码1346737-26)+MA配件卡+MA5L玩法说明书+额外玩法贴 纸(含PT/PL/SI语言）+MA5L UV Glue 贴纸+额外UV Glue 贴纸(PT/PL/SI语言）+MA纸袋+MA配件卡+MA23L说明书+MA3L展示盒 77673TQ1-S002：MA3L EAN彩卡+客户贴纸(含PT/PL/SI语言+客人指定条码+客人指定日期码1346737-26)+MA5L收藏指南+额外收藏指南贴纸(含PT/PL/SI语言）+MA23L 说明书+WEEE带电池出货最新版+MA3L展示盒+客人指定干燥剂 77772SK1-S002：MA3L EAN收缩膜+2张客户贴纸(含法国回收标+PT/PL/SI语言+客人指定条码+客人指定日期码1346737-26)+MA5L收藏指南+额外收藏指南贴纸(含PT/PL /SI语言）+MA小袋子+MA23L组装说明书+MA3L展示架 71172-S001：MA23L警语EAN-A版彩盒+客户贴纸(含客户产品条码+指定日期码:1346737-26) + MA 15L B版说明书 + WEEE 带电池出货最新版+ 客人指定型号干燥剂 Remark: 1.预计6/24第三方验货+抽板测试，71126/71172 每款抽板10-12套左右测试，请多备料； 2.交期前两周前准备好2套大货样给SIPLEC HK OFFICE / 实验室签板； 3.指定日期码1346737-26 4.需在checkpoints上采购外箱贴纸, 跟单会通过邮件发送采购指引；. 5. #71152/71126/71137/9561/71172/9296/9574/77794UQ1/77858/77673TQ1 带电产品每箱放3包透明颗粒状干燥剂(每包约5g)，包干燥剂的袋子要有"SILICA GEL - DO NOT EAT - DESSICANT - THROW AWAY " 字样； 6. 包装禁止使用PVC塑料； 7. 此票出法国，需符合EU标准及微塑料法规，包装需含法国回收logo； | Z100: Ula Zhao | AA100: 9.7 | AB100: =I100*AA100 -> 465.6 | AD100: 71172-S001-3L | AE100: 已入 | AO100: =I100 -> 48 | AQ100: =AO100 -> 48 | AS100: =I100 -> 48
...

Sheet 彩盒MA
B2: 71172大脑 彩盒、说明书MA剩余表
A3: 放订人 | B3: 放MA日期 | C3: PO号码 | D3: MA订单号码 | E3: 货号 | F3: 数量 | G3: 名称 | H3: 版本号 | I3: 语言 | J3: MA 1L彩盒 | K3: MA 3L彩盒 | L3: 15L说明书A | M3: 15L说明书B | N3: 客版说明书 | O3: 71172EC展示架24个装 | P3: 客版包材 | Q3: 备注
A4: Minny | B4: 46080 | D4: 1000036614 | E4: 71172 | F4: 50000 | G4: 彩盒 | H4: A | I4: 1L | J4: =F4 -> 50000
A5: Minny | B5: 46080 | D5: 1000036615 | E5: 71172 | F5: 20000 | G5: 彩盒 | H5: A | I5: 3L | K5: =F5 -> 20000
A6: Minny | B6: 46080 | D6: 1000036616 | E6: 71172 | F6: 70000 | G6: 说明书 | H6: A | I6: 5L | L6: =F6 -> 70000
A7: Minny | B7: 46154 | D7: 1000039941 | E7: 71172 | F7: 40000 | G7: 彩盒 | H7: A | I7: 1L | J7: =F7 -> 40000
A8: Minny | B8: 46154 | D8: 1000039942 | E8: 71172 | F8: 20000 | G8: 彩盒 | H8: A | I8: 3L | K8: =F8 -> 20000
A9: Minny | B9: 46154 | D9: 1000039943 | E9: 71172 | F9: 60000 | G9: 说明书 | H9: B | I9: 2L+5L | M9: =F9 -> 60000
A10: Minny | B10: 46184 | D10: 1000041297 | E10: 71172 | F10: 11216 | G10: 说明书 | H10: A | I10: 2L(ES+PT) | N10: =F10 -> 11216 | Q10: 1.Eva4392PCS 用于CANDIDE PO 4500206011-1000PCS/4500210935-3152PCS/UNIVERSA PO 4500203841 -240PCS 2.Lilly Xiao 5536PCS用于 ARCHIBRAND PO4500210225-200PCS/4500210228-116PCS/ 4500210229-300PCS/SEARS PO 4500207499- 420PCS/WM MX PO-4500210269 4500PCS 3.Sandy 340PCS 用于LIVERPOOL PO 4500199969-300pcs，4500205041-40pcs 4.Aimee 948PCS 用于 EL ROSADO PO4500208470-400PCS /NASA PO 4500203219-116PCS/4500203233-60PCS/CHEDRAUI PO待定-372PCS
A11: Minny | B11: 46190 | D11: 1000041517 | E11: 71172 | F11: 50000 | G11: 彩盒 | H11: A | I11: 1L | J11: 50000
A12: Minny | B12: 46190 | D12: 1000041518 | E12: 71172 | F12: 30000 | G12: 说明书 | H12: B | I12: 2L+5L | M12: 30000
A13: Minny | B13: 46230 | D13: 1000043203 | E13: 71172 | F13: 20000 | G13: 彩盒 | I13: 1L | J13: =F13 -> 20000
A14: Minny | B14: 46230 | D14: 1000043204 | E14: 71172 | F14: 20000 | G14: 说明书 | I14: 2L+5L | M14: =F14 -> 20000
G17: 合计 | J17: =SUM(J4:J16) -> 160000 | K17: =SUM(K4:K16) -> 40000 | L17: =SUM(L4:L16) -> 70000 | M17: =SUM(M4:M16) -> 110000 | N17: =SUM(N4:N16) -> 11216 | O17: =SUM(O4:O16) -> 0
G18: 接单总数 | J18: ='71172大脑'!AP298 -> 148256 | K18: ='71172大脑'!AQ298 -> 36304 | L18: ='71172大脑'!AR298 -> 69892 | M18: ='71172大脑'!AS298 -> 95732 | N18: ='71172大脑'!AT298 -> 10668 | O18: =SUM(O5:O17) -> 0
G19: 彩盒MA剩余 | J19: =J17-J18 -> 11744 | K19: =K17-K18 -> 3696 | L19: =L17-L18 -> 108 | M19: =M17-M18 -> 14268 | N19: =N17-N18 -> 548 | O19: =O17-O18 -> 0

Sheet 产品MA
B1: 大脑半成品生产MA
B2: 日期 | C2: MA订单号码 | D2: ITEM | E2: 名称 | F2: 数量 | G2: 要求完成日期 | H2: 备注
B4: 46036 | C4: MA_RR_2073 | D4: 71172 | E4: 大脑 | F4: 60000 | G4: 46150
B5: 46093 | C5: MA_RR_2191 | D5: 71172 | E5: 大脑 | F5: 60000 | G5: 46148
B6: 46169 | C6: MA_RR_2319 | D6: 71172 | E6: 大脑 | F6: 80000 | G6: 46265
B7: 46233 | C7: MA_RR_2441 | D7: 71172 | E7: 大脑 | F7: 50000 | G7: 46288
E9: MA合计 | F9: =SUM(F4:F8) -> 250000
E10: 接单总数 | F10: ='71172大脑'!I298 -> 185092
E11: MA剩余 | F11: =F9-F10 -> 64908
B15: 大脑IC MA
B16: 日期 | C16: MA订单号码 | D16: ITEM | E16: 名称 | F16: 71172 | G16: 要求完成日期 | H16: 备注
F17: 大脑
B18: 45975 | C18: MA_RR_1967 | D18: 71172 | E18: 大脑 | F18: 4000 | G18: 45990 | H18: HY2410082-30/HY2410082-F9 华远科创
B19: 45989 | C19: MA_RR_1985 | D19: 71172 | E19: 大脑 | F19: 40000 | G19: 46004 | H19: HY2410082-30/HY2410082-F9 华远科创
B20: 46016 | C20: MA_RR_2023 | D20: 71172 | E20: 大脑 | F20: 12000 | G20: 46051 | H20: HY2410082-30/HY2410082-F9 华远科创
B21: 46031 | C21: MA_RR_2046 | D21: 71172 | E21: 大脑 | F21: 72000 | G21: 46046 | H21: HY2410082-30/HY2410082-F9 华远科创
B22: 46062 | C22: MA_RR_2120 | D22: 71172 | E22: 大脑 | F22: 12000 | G22: 46112 | H22: HY2410082-30/HY2410082-F9 华远科创
B23: 46090 | C23: MA_RR_2166 | D23: 71172 | E23: 大脑 | F23: 20000 | G23: 3/24,4/15 | H23: HY2410082-30/HY2410082-F9 华远科创
B24: 46125 | C24: MA_RR_2246 | D24: 71172 | E24: 大脑 | F24: 52000 | G24: 5/18,4/28 | H24: HY2410082-30/HY2410082-F9 华远科创
B25: 46157 | C25: MA-RR-2302 | D25: 71172 | E25: 大脑 | F25: 20000 | G25: 6/19,5/30 | H25: HY2410082-30/HY2410082-F9 华远科创
B26: 46169 | C26: MA_RR_2329 | D26: 71172 | E26: 大脑 | F26: 20000 | G26: 46184 | H26: HY2410082-30/HY2410082-F9 华远科创
B27: 46189 | C27: MA_RR_2375 | D27: 71172 | E27: 大脑 | F27: 20000 | G27: 7/21,7/1 | H27: HY2410082-30/HY2410082-F9 华远科创
B28: 46205 | C28: MA_RR_2407 | D28: 71172 | E28: 大脑 | F28: 60000 | G28: 8/6,7/17 | H28: HY2410082-30/HY2410082-F9 华远科创
B29: 46232 | C29: MA_RR_2443 | D29: 71172 | E29: 大脑 | F29: 48000 | G29: 未经烧录的IC空白片 | H29: HY2410082-30(IC母体:DSP-QFN32)/HY2410082-F9(IC母体:Flash-8Mb) 华远科创
F32: =SUM(F18:F31) -> 380000
B33: 接单总数 | F33: =F10 -> 185092
B34: 按接单IC 剩余数 | F34: =F32-F33 -> 194908
B35: 除去MA半成品 剩余数 | F35: =F32-F9 -> 130000

Sheet 客版MA

Sheet 取消单
A1: 接单期 | B1: 第三方客户名称 | C1: 国家 | D1: PO号 | E1: 第三方客户 PO NO# | F1: SKU | G1: 货号 | H1: 名称 | I1: PO数量(只) | J1: 内箱装箱数量(只) | K1: 外箱装箱数量(只) | L1: 总箱数 | M1: 客PO期 | N1: 计划验货期 | O1: 第三方验货期 | P1: 验货结果 | Q1: 船期SO | R1: 蓝色表示寄出 黄色表示出单 | S1: 是否有外箱贴纸 | T1: 箱唛资料 | U1: 客贴纸 | V1: 其他物料 | W1: 日期码 | Y1: 备注 | Z1: 客跟单 | AA1: 单价USD | AB1: 金额USD | AC1: 发票号 | AD1: 系统货号 | AE1: 是否已入系统 | AF1: 已完成数量 | AG1: 欠数 | AH1: 贴纸情况 | AI1: 是否已入系统 | AJ1: 包装 | AK1: 标准=0,客版=1 | AL1: 说明书 | AM1: 标准=0,客版=1 | AN1: 走货情况(离厂日期) | AO1: 71172 产品数 | AP1: 71172 MA 1L彩盒 | AQ1: 71172 MA 3L彩盒 | AR1: 71172 MA 15L说明书A版 | AS1: 71172 MA15L说明书B版 | AT1: 客版 | AU1: 取消日期
A2: 46122 | B2: DM LLC | C2: 俄罗斯 | D2: 4500200893 | E2: order 5377Bekasovo 2 | F2: 4500200893-80 | G2: 71172-S001 | H2: 大脑 | I2: 936 | J2: 0 | K2: 4 | L2: =I2/K2 -> 234 | M2: 46202 | N2: 46198 | T2: 46127 | U2: 46135 | Y2: 日期码格式：外包装/外箱不要打ZURU标准日期 日期： Packaging Info: 注意: 除了71172 ，其他item的进口商贴纸，EAN条码贴纸（如有）翻4500200846 。 1. 外包装(指:收缩膜/彩卡/铝箔袋/挂卡/PDQ)/外箱不要打ZURU标准日期码!胶件可以打日期码。 2. 零售包装上的QR code贴纸（要求一物一码，每PCS的二维码不一样，二维码可扫描区域尺寸要大于15x15mm ， 整张贴纸尺寸25X40MM <(><<)>含二维码下序列号 /Art/size等,可以按包装需求自行调整-确保可扫>,白底黑字，分辨率要大于300dpi，位置要远离条码。 可贴零售包装的侧面右下角/背面的右上角/挂卡的背面/正 面的右上角，距离边距5mm）; 3 .外箱四面右上角需要加SSCC label （标准尺寸是16X5CM,可调整但是需要确保可扫）； 4. MA UPC 彩卡或者收缩膜+进口商贴纸+EAN条码贴纸+QR code 贴纸 （一物一码），MA 说明书/指南（如有） Remark: 客户DM订单注意事项: 1. 标准配比 2. 请按期完货， 会有罚金。 3. 出仓库-Bekasovo 2 。 4. 外包装(指:收缩膜/彩卡/铝箔袋/挂卡/PDQ)/外箱不要打ZURU标准日期码!胶件可以打日期码。 5. 零售包装上的QR code贴纸（要求一物一码，每PCS的二维码不一样，二维码可扫描区域尺寸要大于15x15mm ， 整张贴纸尺寸25X40MM <(><<)>含二维码下序列号 /Art/size等>,白底黑字，分辨率要大于300dpi，位置要远离条码。 可贴零售 包装的侧面右下角/背面的右上角/挂卡的背面/正面的右上角，距离边距5mm）; ----QR 二维码格式要求： DATA MATRIX GS1 . 6 .外箱四面左下角需要加SSCC label （标准尺寸是16X5CM,可调整但是需要确保可扫）； 7. 出货前需要按船务的指示提供零售包装上QR CODE 入外箱以及入货柜的明细清单供客户清关使用--用客户的模板（追踪到箱/到柜）； 8. 需要通过ZURU 验货结果后才能出货 (工厂需要主动提前同ZURU QC预约验货避免延期出货造成不必要麻烦)； | Z2: Amy xiao | AA2: 9.86 | AB2: =I2*AA2 -> 9228.96 | AO2: =I2 -> 936 | AP2: =I2 -> 936 | AR2: =I2 -> 936 | AU2: 46162
A3: 46122 | B3: DM LLC | C3: 俄罗斯 | D3: 4500200937 | E3: order 5377Ural | F3: 4500200937-80 | G3: 71172-S001 | H3: 大脑 | I3: 368 | J3: 0 | K3: 4 | L3: =I3/K3 -> 92 | M3: 46202 | N3: 46198 | T3: 46127 | U3: 46135 | Y3: 日期码格式：外包装/外箱不要打ZURU标准日期 日期： Packaging Info: 注意: 71172 的进口商贴纸，EAN条码贴纸（如有）翻4500200893； 其他 item 的进口商贴纸，EAN条码贴纸（如有）翻4500200846 。 1. 外包装(指:收缩膜/彩卡/铝箔袋/挂卡/PDQ)/外箱不要打ZURU标准日期码!胶件可以打日期码。 2. 零售包装上的QR code贴纸（要求一物一码，每PCS的二维码不一样，二维码可扫描区域尺寸要大于15x15mm ， 整张贴纸尺寸25X40MM <(><<)>含二维码下序列号 /Art/size等,可以按包装需求自行调整-确保可扫>,白底黑字，分辨率要大于300dpi，位置要远离条码。 可贴零售包装的侧面右下角/背面的右上角/挂卡的背面/正 面的右上角，距离边距5mm）; 3 .外箱四面右上角需要加SSCC label （标准尺寸是16X5CM,可调整但是需要确保可扫）； 4. MA UPC 彩卡或者收缩膜+进口商贴纸+EAN条码贴纸+QR code 贴纸 （一物一码），MA 说明书/指南（如有） Remark: 客户DM订单注意事项: 1. 标准配比 2. 请按期完货， 会有罚金。 3. 出仓库- Ural 。 4. 外包装(指:收缩膜/彩卡/铝箔袋/挂卡/PDQ)/外箱不要打ZURU标准日期码!胶件可以打日期码。 5. 零售包装上的QR code贴纸（要求一物一码，每PCS的二维码不一样，二维码可扫描区域尺寸要大于15x15mm ， 整张贴纸尺寸25X40MM <(><<)>含二维码下序列号 /Art/size等>,白底黑字，分辨率要大于300dpi，位置要远离条码。 可贴零售 包装的侧面右下角/背面的右上角/挂卡的背面/正面的右上角，距离边距5mm）; ----QR 二维码格式要求： DATA MATRIX GS1 . 6 .外箱四面左下角需要加SSCC label （标准尺寸是16X5CM,可调整但是需要确保可扫）； 7. 出货前需要按船务的指示提供零售包装上QR CODE 入外箱以及入货柜的明细清单供客户清关使用--用客户的模板（追踪到箱/到柜）； 8. 需要通过ZURU 验货结果后才能出货 (工厂需要主动提前同ZURU QC预约验货避免延期出货造成不必要麻烦)； | Z3: Amy xiao | AA3: 9.86 | AB3: =I3*AA3 -> 3628.48 | AO3: =I3 -> 368 | AP3: =I3 -> 368 | AR3: =I3 -> 368 | AU3: 46162
A4: 46122 | B4: DM LLC | C4: 俄罗斯 | D4: 4500200968 | E4: order 5377Bekasovo 2 | F4: 4500200968-80 | G4: 71172-S001 | H4: 大脑 | I4: 468 | J4: 0 | K4: 4 | L4: =I4/K4 -> 117 | M4: 46227 | N4: 46223 | T4: 46127 | U4: 46135 | Y4: 日期码格式：外包装/外箱不要打ZURU标准日期 日期： Packaging Info: 注意: 71172 的进口商贴纸，EAN条码贴纸（如有）翻4500200893； 其他 item 的进口商贴纸，EAN条码贴纸（如有）翻4500200846 。 1. 外包装(指:收缩膜/彩卡/铝箔袋/挂卡/PDQ)/外箱不要打ZURU标准日期码!胶件可以打日期码。 2. 零售包装上的QR code贴纸（要求一物一码，每PCS的二维码不一样，二维码可扫描区域尺寸要大于15x15mm ， 整张贴纸尺寸25X40MM <(><<)>含二维码下序列号 /Art/size等,可以按包装需求自行调整-确保可扫>,白底黑字，分辨率要大于300dpi，位置要远离条码。 可贴零售包装的侧面右下角/背面的右上角/挂卡的背面/正 面的右上角，距离边距5mm）; 3 .外箱四面右上角需要加SSCC label （标准尺寸是16X5CM,可调整但是需要确保可扫）； 4. MA UPC 彩卡或者收缩膜+进口商贴纸+EAN条码贴纸+QR code 贴纸 （一物一码），MA 说明书/指南（如有） Remark: 客户DM订单注意事项: 1. 标准配比 2. 请按期完货， 会有罚金。 3. 出仓库-Bekasovo 2。 4. 外包装(指:收缩膜/彩卡/铝箔袋/挂卡/PDQ)/外箱不要打ZURU标准日期码!胶件可以打日期码。 5. 零售包装上的QR code贴纸（要求一物一码，每PCS的二维码不一样，二维码可扫描区域尺寸要大于15x15mm ， 整张贴纸尺寸25X40MM <(><<)>含二维码下序列号 /Art/size等>,白底黑字，分辨率要大于300dpi，位置要远离条码。 可贴零售 包装的侧面右下角/背面的右上角/挂卡的背面/正面的右上角，距离边距5mm）; ----QR 二维码格式要求： DATA MATRIX GS1 . 6 .外箱四面左下角需要加SSCC label （标准尺寸是16X5CM,可调整但是需要确保可扫）； 7. 出货前需要按船务的指示提供零售包装上QR CODE 入外箱以及入货柜的明细清单供客户清关使用--用客户的模板（追踪到箱/到柜）； 8. 需要通过ZURU 验货结果后才能出货 (工厂需要主动提前同ZURU QC预约验货避免延期出货造成不必要麻烦)； | Z4: Amy xiao | AA4: 9.86 | AB4: =I4*AA4 -> 4614.48 | AO4: =I4 -> 468 | AP4: =I4 -> 468 | AR4: =I4 -> 468 | AU4: 46162
A5: 46122 | B5: DM LLC | C5: 俄罗斯 | D5: 4500201001 | E5: order 5377Ural | F5: 4500201001-80 | G5: 71172-S001 | H5: 大脑 | I5: 184 | J5: 0 | K5: 4 | L5: =I5/K5 -> 46 | M5: 46227 | N5: 46223 | T5: 46127 | U5: 46135 | Y5: 日期码格式：外包装/外箱不要打ZURU标准日期 日期： Packaging Info: 注意: 71172 的进口商贴纸，EAN条码贴纸（如有）翻4500200893； 其他 item 的进口商贴纸，EAN条码贴纸（如有）翻4500200846 。 1. 外包装(指:收缩膜/彩卡/铝箔袋/挂卡/PDQ)/外箱不要打ZURU标准日期码!胶件可以打日期码。 2. 零售包装上的QR code贴纸（要求一物一码，每PCS的二维码不一样，二维码可扫描区域尺寸要大于15x15mm ， 整张贴纸尺寸25X40MM <(><<)>含二维码下序列号 /Art/size等,可以按包装需求自行调整-确保可扫>,白底黑字，分辨率要大于300dpi，位置要远离条码。 可贴零售包装的侧面右下角/背面的右上角/挂卡的背面/正 面的右上角，距离边距5mm）; 3 .外箱四面右上角需要加SSCC label （标准尺寸是16X5CM,可调整但是需要确保可扫）； 4. MA UPC 彩卡或者收缩膜+进口商贴纸+EAN条码贴纸+QR code 贴纸 （一物一码），MA 说明书/指南（如有） Remark: 客户DM订单注意事项: 1. 标准配比 2. 请按期完货， 会有罚金。 3. 出仓库- Ural 。 4. 外包装(指:收缩膜/彩卡/铝箔袋/挂卡/PDQ)/外箱不要打ZURU标准日期码!胶件可以打日期码。 5. 零售包装上的QR code贴纸（要求一物一码，每PCS的二维码不一样，二维码可扫描区域尺寸要大于15x15mm ， 整张贴纸尺寸25X40MM <(><<)>含二维码下序列号 /Art/size等>,白底黑字，分辨率要大于300dpi，位置要远离条码。 可贴零售 包装的侧面右下角/背面的右上角/挂卡的背面/正面的右上角，距离边距5mm）; ----QR 二维码格式要求： DATA MATRIX GS1 . 6 .外箱四面左下角需要加SSCC label （标准尺寸是16X5CM,可调整但是需要确保可扫）； 7. 出货前需要按船务的指示提供零售包装上QR CODE 入外箱以及入货柜的明细清单供客户清关使用--用客户的模板（追踪到箱/到柜）； 8. 需要通过ZURU 验货结果后才能出货 (工厂需要主动提前同ZURU QC预约验货避免延期出货造成不必要麻烦)； | Z5: Ann | AA5: 9.86 | AB5: =I5*AA5 -> 1814.24 | AO5: =I5 -> 184 | AP5: =I5 -> 184 | AR5: =I5 -> 184 | AU5: 46162
A6: 46112 | B6: AMAZON UK | C6: 英国 | D6: 4500199193 | E6: 6MTFVO4E | F6: 4500199193-40 | G6: 71172-S003-MB | H6: 大脑（邮包盒装） | I6: 532 | J6: 0 | K6: 4 | L6: =I6/K6 -> 133 | M6: 46240 | N6: 46237 | O6: N/A | S6: 有 | T6: 46112 | U6: 无 | Y6: 日期码格式：ZURU INC(BVI) 标准格式 日期：按实际生产日期 Packaging Info: Amazon UK: 8WX462WO/6MTFVO4E/795E945F Amazon UK(15780BD/71172/77876/77878/92146BG) 1. 15780BD: ---15780B: 1pc 15780B(Sasquoosh/Stinkface/Squooshface) in window box, then into polybag,12polybags/ctn; MA 5L(5L warning UPC)B开窗彩盒+MA其它最 新配套包装+客版透明胶袋(含英法德意西荷兰警告语+双面打孔+塑料循环标,参考翻单PO#4500198640)+1张贴纸(含UPC#+IT环保标+ES洗涤说明, 参考翻单PO#450019 8640); ---15780D: 1pc 15780D(Munch Munch/Reek-o/Munch-o) in window box, then into polybag,12polybags/ctn; MA 5L(5L warning UPC)B开窗彩盒+MA其它最新配套 包装+客版透明胶袋(含英法德意西荷兰警告语+双面打孔+塑料循环标,参考翻单PO#4500198640)+1张贴纸(含UPC#+IT环保标+ES洗涤说明, 参考翻单PO#4500198640); 2. 92146BG: ---92146B: 1pc 92146B SMALL(Raccoon) into shrink wraps,24pcs/ctn;Bubble powder;NO Boron; MA 3L(8L warning EAN)A收缩膜+MA其它最新配套包装+MA 5L( 19L warning)A收藏指南+1张贴纸(1张UPC+IT环保标+ES洗涤说明贴纸，参考翻单PO#4500198640); ---92146G: 1pc 92146G SMALL(Pigeon) into shrink wraps,24pcs/ctn;Bubble powder;NO Boron; MA 3L(8L warning EAN)A收缩膜+MA其它最新配套包装+MA 5L(19 L warning)A收藏指南+1张贴纸(1张UPC+IT环保标+ES洗涤说明贴纸，参考翻单PO#4500198640); 3. 71172: 1pc 71172 BRIAN THE BRAIN into open box, then into mailbox, 4mailboxes/ctn; 3PCS AA BATTERIES(INCLUDED); MA 1L(23L warning UPC)A开口彩 盒+MA 15L A说明书+客版邮包盒(参考Amazon US翻单PO#4500192525)+WEEE_带电池走货 _ 说明书欧洲EN+30L_B版; 4. 77876: 2pk 77772 VINYL into PVC tube,12tubes/ctn; 77772: 4 mini vinyls,1 accessory; 客版 3L(3L warning 无条码)A收缩膜(参考翻单PO#4500198642, 新UK地址)+MA 23L warning A组装黑白说明书+MA其它最新配套包装+客版3L(3L warning UPC)A彩卡(参考翻单PO#4500198642，新UK地址)+1张贴纸(含DE/IT警告语+ IT环保标, 参考翻单PO#4500198642); 5. 77878: 2pk 77843 in PVC tube,12tubes/ctn;Contain Sand, UV Glue and Cream Glue; SUSHI and RAINBOW CAKE(Rare) without batteries, other assortme nts: 6PCS AG13 BATTERIES(INCLUDED); Ratio: PIZZA: HAMBURGER: PANCAKES: BUBBLE TEA: Matcha TEA: TACO: SUSHI: DONUT: Charcuterie Board: RAINBOW C AKE(Rare)=10.88%: 10.88%: 10.88%: 10.88%: 10.88%: 10.88%: 10.88%: 10.88%: 10.88%: 2.08%=68:68:68:68:68:68:68:68:68:13; MA 1L(1L Warning UPC)A收 缩膜+1张空白贴纸(覆盖收缩上条码, 参考Amazon US翻单PO#4500192514)+MA 5L A收藏指南+MA 23L warning A SUSHI <(>&<)> RAINBOW CAKE说明书+MA 23L warni ng A UV Glue说明书+客版3L(3L warning UPC)A彩卡(参考Amazon US翻单PO#4500192514.,新UK地址)+1张贴纸(含DE/IT警告语+IT环保标,参考翻单PO#4500198640)+W EEE_带电池走货 _ 说明书欧洲EN+30L_B版; 6. 验货时间不迟于2026/8/7. Remark: 1.空白外箱（加印带Zuru字样的最新logo，除了邮包盒直接做外箱的产品） + SSCC LABEL一张, 无箱唛，MADE IN CHINA 外箱只印一正一侧。箱唛资料按照给定的 标准去做即可，无需发回我方再行审批(新标准将另行通知)。 (SSCC LABEL竖贴在外箱正面的正中间，贴一面即可,贴纸离外箱边距必须至少3.2CM。如竖贴无法满足要求，则横贴。如横贴也无法满足要求，则竖贴，遮到ZURU lo go无影响), SSCC贴纸由工厂直接跟勤得采购或者工厂自行采购，每一张SSCC Label都是唯一且有不同流水及条码，且需要检查条码是否能正常扫描，另外，此贴纸 印刷不可出现模糊，溢出及粘胶不牢易脱落等现象，如工厂不按此要求导致贴纸有任何问题产生的罚款将由工厂承担一切责任 ,<(>,<)> 此要求只适用Amazon UK/DE /FR/ES/IT,不适用Amazon GPE，Amazon GPE无SSCC label, 但是有对应箱唛，需印刷到外箱 。 2.出往UK的产品+包装务必打上UKCA logo ，否则客人会退货且当地会有罚款。Amazon GPE（包含UK/FR/ES/DE/IT）的订单也需满足此要求。 3.订单必须经过ZURU QC验货或者工厂自检通过后方可出货，不涉及第三方验货。 4.法国订单要求包装不使用矿物油，请按要求提供以下其中一份文件再出货 ，产品出到法国被相关部门抽检出现包装不符合此要求的，供应商需要为此承担责任， 故此请严格把关。Amazon GPE（包含UK/FR/ES/DE/IT）的订单也需满足此要求。 -油墨物质""""""""由1 ~ 7个芳香环组成的MOAH""""""""的包装检测报告，要求限值≤1.0%； -包装材料清单，包括包装油墨或物质的信息； -油墨制造商的证书； 5.每一批次出货只能有一个生产日期，不可多个生产日期混在同一批次出货；且零售包装上必须统一加上日期码；外箱对于日期码没有硬性规定； 6.涉及到相关款式会有闪粉的或者微塑料的，请统一默认出无闪粉或者不含微塑料版本； 7.邮包盒及外箱封箱必须是工字型封箱方式； 8.5 Surprise or Mini Brands涉及包装是2个及2个以上的球入PVC桶包装时，单个球上若有UPC#或者EAN#，请用空白贴纸覆盖住，贴纸尺寸自行测量能覆盖原条码即 可； 9. 无论是工厂自检还是ZURU验货，验货报告中必须有产品6面图(正面/背面/左面/右面/顶部/底部，不带包装); 10. 按空海运鉴定报告的要求，只要带锂电池出货，都需要加贴UN贴纸； 11. 所有出往GAS市场(德国/奥地利/瑞士)的电子产品身上需要加字唛，为ZURU FRANCE 地址，需跟包装上的地址一致 (如无电子产品，产品布标有此地址，或产品 太小无法增加可忽略此信息。如产品无法加字唛，需让对应跟单提供产品贴纸资料);（Amazon GPE的订单也需满足此要求） 12. 所有出往GAS德国 (瑞士，奥地利)。水弹枪系列必须使用EN71版本（电子和非电子水弹枪系列都需要符合); 护目镜需打日期码, 格式跟ZURU标准格式一样; 枪 身上增加ZURU FRANCE公司名和地址。使用贴纸和辐射上去都可以。如果有位置，最好增加ZURU Represented by: (此最好翻译德语，如果位置不允许，那么就只增 加ZURU法国和地址)。使用最新的EN71版包装和说明书）。Amazon GPE（包含UK/FR/ES/DE/IT）的订单也需满足此要求。 | Z6: Luna Lin | AA6: 9.86 | AB6: =I6*AA6 -> 5245.52 | AD6: 71172-S003-MB-1L | AE6: 已入 | AO6: =I6 -> 532 | AP6: =I6 -> 532 | AR6: =I6 -> 532 | AU6: 46185
A7: 46112 | B7: AMAZON UK | C7: 英国 | D7: 4500199191 | E7: 3WDKG8LJ | F7: 4500199191-100 | G7: 71172-S003-MB | H7: 大脑（邮包盒装） | I7: 532 | J7: 0 | K7: 4 | L7: =I7/K7 -> 133 | M7: 46205 | N7: 46202 | O7: N/A | S7: 有 | T7: 46112 | U7: 无 | Y7: 日期码格式：ZURU INC(BVI) 标准格式 日期：按实际生产日期 Packaging Info: Amazon UK: 6FFPTG1N/3WDKG8LJ/7OUSHCDE Amazon UK(15780BD/71172/77876/77878/92146BDG/92147E) 1. 15780BD: ---15780B: 1pc 15780B(Sasquoosh/Stinkface/Squooshface) in window box, then into polybag,12polybags/ctn; MA 5L(5L warning UPC)B开窗彩盒+MA其它最 新配套包装+客版透明胶袋(含英法德意西荷兰警告语+双面打孔+塑料循环标,参考翻单PO#4500198640)+1张贴纸(含UPC#+IT环保标+ES洗涤说明, 参考翻单PO#450019 8640); ---15780D: 1pc 15780D(Munch Munch/Reek-o/Munch-o) in window box, then into polybag,12polybags/ctn; MA 5L(5L warning UPC)B开窗彩盒+MA其它最新配套 包装+客版透明胶袋(含英法德意西荷兰警告语+双面打孔+塑料循环标,参考翻单PO#4500198640)+1张贴纸(含UPC#+IT环保标+ES洗涤说明, 参考翻单PO#4500198640); 2. 71172: 1pc 71172 BRIAN THE BRAIN into open box, then into mailbox, 4mailboxes/ctn; 3PCS AA BATTERIES( INCLUDED); MA 1L(23L warning UPC)A开口 彩盒+MA 15L A说明书+客版邮包盒(参考Amazon US翻单PO#4500192525)+WEEE_带电池走货 _ 说明书欧洲EN+30L_B版; 3. 77876: 2pk 77772 VINYL into PVC tube,12tubes/ctn; 77772: 4 mini vinyls,1 accessory; 客版 3L(3L warning 无条码)A收缩膜(参考翻单PO#4500198642, 新UK地址)+MA 23L warning A组装黑白说明书+MA其它最新配套包装+客版3L(3L warning UPC)A彩卡(参考翻单PO#4500198642，新UK地址)+1张贴纸(含DE/IT警告语+ IT环保标, 参考翻单PO#4500198642); 4. 77878: 2pk 77843 in PVC tube,12tubes/ctn;Contain Sand, UV Glue and Cream Glue; SUSHI and RAINBOW CAKE(Rare) without batteries, other assortme nts: 6PCS AG13 BATTERIES(INCLUDED); Ratio: PIZZA: HAMBURGER: PANCAKES: BUBBLE TEA: Matcha TEA: TACO: SUSHI: DONUT: Charcuterie Board: RAINBOW C AKE(Rare)=10.88%: 10.88%: 10.88%: 10.88%: 10.88%: 10.88%: 10.88%: 10.88%: 10.88%: 2.08%=68:68:68:68:68:68:68:68:68:13; MA 1L(1L Warning UPC)A收 缩膜+1张空白贴纸(覆盖收缩上条码, 参考Amazon US翻单PO#4500192514)+MA 5L A收藏指南+MA 23L warning A SUSHI <(>&<)> RAINBOW CAKE说明书+MA 23L warni ng A UV Glue说明书+客版3L(3L warning UPC)A彩卡(参考Amazon US翻单PO#4500192514.,新UK地址)+1张贴纸(含DE/IT警告语+IT环保标,参考翻单PO#4500198640)+W EEE_带电池走货 _ 说明书欧洲EN+30L_B版; 5. 92146BDG: ---92146B: 1pc 92146B SMALL(Raccoon) into shrink wraps,24pcs/ctn;Bubble powder;NO Boron; MA 3L(8L warning EAN)A收缩膜+MA其它最新配套包装+MA 5L( 19L warning)A收藏指南+1张贴纸(1张UPC+IT环保标+ES洗涤说明贴纸，参考翻单PO#4500198640); ---92146D: 1pc 92146D SMALL(Deer) into shrink wraps,24pcs/ctn;Bubble powder;NO Boron; MA 3L(8L warning EAN)A收缩膜+MA其它最新配套包装+MA 5L(19L warning)A收藏指南+1张贴纸(1张UPC+IT环保标+ES洗涤说明贴纸，参考翻单PO#4500198640); ---92146G: 1pc 92146G SMALL(Pigeon) into shrink wraps,24pcs/ctn;Bubble powder;NO Boron; MA 3L(8L warning EAN)A收缩膜+MA其它最新配套包装+MA 5L(19 L warning)A收藏指南+1张贴纸(1张UPC+IT环保标+ES洗涤说明贴纸，参考翻单PO#4500198640); 6. 92147E: 1pc 92147E LARGE(Unicorn) into shrink wrap, then into mailbox, 4mailboxes/ctn; MA 3L(8L warning EAN)A收缩膜+MA 5L(19L warning)A收藏指 南+MA 5L(19L warning)A Magic guide book说明书+MA其它最新配套包装+客版邮包盒(参考翻单PO#4500198640); 7. 验货时间不迟于2026/7/3. Remark: 1.空白外箱（加印带Zuru字样的最新logo，除了邮包盒直接做外箱的产品） + SSCC LABEL一张, 无箱唛，MADE IN CHINA 外箱只印一正一侧。箱唛资料按照给定的 标准去做即可，无需发回我方再行审批(新标准将另行通知)。 (SSCC LABEL竖贴在外箱正面的正中间，贴一面即可,贴纸离外箱边距必须至少3.2CM。如竖贴无法满足要求，则横贴。如横贴也无法满足要求，则竖贴，遮到ZURU lo go无影响), SSCC贴纸由工厂直接跟勤得采购或者工厂自行采购，每一张SSCC Label都是唯一且有不同流水及条码，且需要检查条码是否能正常扫描，另外，此贴纸 印刷不可出现模糊，溢出及粘胶不牢易脱落等现象，如工厂不按此要求导致贴纸有任何问题产生的罚款将由工厂承担一切责任 ,<(>,<)> 此要求只适用Amazon UK/DE /FR/ES/IT,不适用Amazon GPE，Amazon GPE无SSCC label, 但是有对应箱唛，需印刷到外箱 。 2.出往UK的产品+包装务必打上UKCA logo ，否则客人会退货且当地会有罚款。Amazon GPE（包含UK/FR/ES/DE/IT）的订单也需满足此要求。 3.订单必须经过ZURU QC验货或者工厂自检通过后方可出货，不涉及第三方验货。 4.法国订单要求包装不使用矿物油，请按要求提供以下其中一份文件再出货 ，产品出到法国被相关部门抽检出现包装不符合此要求的，供应商需要为此承担责任， 故此请严格把关。Amazon GPE（包含UK/FR/ES/DE/IT）的订单也需满足此要求。 -油墨物质""""""""由1 ~ 7个芳香环组成的MOAH""""""""的包装检测报告，要求限值≤1.0%； -包装材料清单，包括包装油墨或物质的信息； -油墨制造商的证书； 5.每一批次出货只能有一个生产日期，不可多个生产日期混在同一批次出货；且零售包装上必须统一加上日期码；外箱对于日期码没有硬性规定； 6.涉及到相关款式会有闪粉的或者微塑料的，请统一默认出无闪粉或者不含微塑料版本； 7.邮包盒及外箱封箱必须是工字型封箱方式； 8.5 Surprise or Mini Brands涉及包装是2个及2个以上的球入PVC桶包装时，单个球上若有UPC#或者EAN#，请用空白贴纸覆盖住，贴纸尺寸自行测量能覆盖原条码即 可； 9. 无论是工厂自检还是ZURU验货，验货报告中必须有产品6面图(正面/背面/左面/右面/顶部/底部，不带包装); 10. 按空海运鉴定报告的要求，只要带锂电池出货，都需要加贴UN贴纸； 11. 所有出往GAS市场(德国/奥地利/瑞士)的电子产品身上需要加字唛，为ZURU FRANCE 地址，需跟包装上的地址一致 (如无电子产品，产品布标有此地址，或产品 太小无法增加可忽略此信息。如产品无法加字唛，需让对应跟单提供产品贴纸资料);（Amazon GPE的订单也需满足此要求） 12. 所有出往GAS德国 (瑞士，奥地利)。水弹枪系列必须使用EN71版本（电子和非电子水弹枪系列都需要符合); 护目镜需打日期码, 格式跟ZURU标准格式一样; 枪 身上增加ZURU FRANCE公司名和地址。使用贴纸和辐射上去都可以。如果有位置，最好增加ZURU Represented by: (此最好翻译德语，如果位置不允许，那么就只增 加ZURU法国和地址)。使用最新的EN71版包装和说明书）。Amazon GPE（包含UK/FR/ES/DE/IT）的订单也需满足此要求。 | Z7: Luna Lin | AA7: 9.86 | AB7: =I7*AA7 -> 5245.52 | AD7: 71172-S003-MB-1L | AE7: 已入 | AO7: =I7 -> 532 | AP7: =I7 -> 532 | AR7: =AO7 -> 532 | AU7: 46185
A8: 46178 | B8: THE FARMERS' TRADING COMPANY LIMITE | C8: 新西兰 | D8: 4500210838 | F8: 4500210838-10 | G8: 71172-S001 | H8: 大脑 | I8: 320 | J8: 0 | K8: 4 | L8: =I8/K8 -> 80 | M8: 46255 | N8: 46251 | T8: 46202 | U8: 6/29收到价钱贴，欠 | Y8: 日期码格式：ZURU INC(BVI) 标准格式 日期：按实际生产日期 Packaging Info: 1. 71172:MA 1L A版 UPC PKG + MA B版多语说明书 +(带客人新logo）可移动材质的价格贴纸（价格贴纸要切易撕线）+新的客人纽扣电池警告语贴纸（包装用新的 纽扣电池警告语贴纸，说明书用旧的大的警告语贴纸）新的警告语贴纸邮件后复 Remark: 1.此单出新西兰 2.CRD日期基于我司 QC完成验货; 3.请确保发货100%的订单数量/ sku; 4.箱唛请按邮件确认的文档 5.我司验货日期(请联系Mia Yu Mia.yu@zuru.com提前预定验货日期)，预约验货至少需在完货日期前一周申请 | Z8: Jess Huang | AA8: 11.9558 | AB8: =I8*AA8 -> 3825.856 | AD8: 71172-S002-1L | AE8: 已入 | AO8: =I8 -> 320 | AP8: =AO8 -> 320 | AS8: =AO8 -> 320 | AU8: 46219
A9: 46233 | B9: TARGET US | C9: 美国 | D9: 4500218205 | E9: 10001860092-3890 | F9: 4500218205-10 | G9: 71172-S001 | H9: 大脑 | I9: 2920 | J9: 0 | K9: 4 | L9: =I9/K9 -> 730 | M9: 46282 | N9: 46279 | S9: 有 | T9: 欠 | U9: 欠 | Y9: 日期码格式：ZURU INC(BVI) 标准格式 日期：按实际生产日期 Packaging Info: 产品包装MA 1L彩盒 Remark: 1. 71172-S001-ROBO ALIVE-BRAIN-SERIES 1-BRIAN THE BRAIN-OPEN BOX-4PCS/CTN 2. 产品包装MA 1L彩盒；彩盒上的UPC显示193052098443； 3. 每个外箱正唛箱唛信息左上方位置粘贴条码箱贴纸，每箱只贴一张; 由ZURU向艾利订购， 对应的外箱贴DPCI：087-02-9468, UPC显示10193052098440 ； 4. 产品和包装上要印刷tracking code信息，格式为ZURU常规； 5. 出货方式：货代自提 | Z9: Holly Zheng | AA9: 6.6478 | AB9: =I9*AA9 -> 19411.576 | AD9: 71172-S001-1L | AE9: 已入 | AO9: =I9 -> 2920 | AP9: =I9 -> 2920 | AS9: =AO9 -> 2920 | AU9: 46244
