Workbook

Sheet 77858厨房套装
A1: ZURU （77858 厨房套装）生产排期表
A3: 香港接单日期 | B3: 第三方客户名称 | C3: 走货国家 | D3: ZURU PO NO# | E3: 第三方客户 PO NO# | F3: SKU | G3: ITEM# | H3: 中文名 | I3: PO数量 (pcs) | J3: 内箱装箱数量(pcs) | K3: 外箱装箱数量(pcs) | L3: 总箱数 | M3: 客PO期 | N3: 验货期 | O3: 第三方验货期 | P3: 验货结果 | Q3: S/0船期 | R3: 箱唛确认 | S3: 箱唛资料(收到日期) | T3: 外箱贴纸 | U3: 客供贴纸AI(收到日期) | V3: 客供物料 | W3: 备注 | X3: ZURU 跟单 | Y3: 单价USD | Z3: 金额USD | AA3: 發票號 | AB3: 系统货号 | AC3: 是否入系统 | AD3: 系统出单 | AE3: 送货情况 | AF3: 欠数 | AG3: 贴纸 | AH3: 生产地 | AI3: MA 1L彩盒 | AJ3: 客版 3L彩盒 | AK3: 客版 3L彩盒（COSTCO AU/NA） | AL3: MA 3L彩盒 | AM3: 黑白警语说明书 | AN3: 客版黑白警语说明书 | AO3: 不带电WEE说明书 | AP3: 客版5L 收藏指南 | AQ3: 5L A版收藏指南 | AR3: 5L B版收藏指南 | AS3: 客版PDQ
A4: 45989 | B4: ZURU | C4: 中国 | D4: #ZPO2511013 | E4: 工程安排 | G4: 77858-S001 | H4: 厨房套装 | I4: 300 | J4: 0 | K4: 3 | L4: =I4/K4 -> 100 | M4: 45666 | N4: 45666 | P4: OK | S4: 空白箱 | T4: 无 | U4: 无 | W4: PP 样品：QA Testing Samples ，数量：6，地址：深圳市罗湖区东门南路1006号口岸大楼17B.Sally ,13418550560 备注2箱bulk pack需正确纸箱做运输测试+8套散件。 PP 样品：UL SZ Sample，数量：6，地址：Joyce Yao 电话：+ 86 755 8120 2849 优力胜邦质量检测（上海）有限公司深圳分公司 深圳市宝安区西乡街道航城大道一号中德欧产业园B 栋4 楼， 邮编：518126（寄出时请告知快递单号方便快速处理）包装完整成品 PP 样品：Internal Samples/Sample，数量：8/12,地址：深圳市罗湖区东门南路1006号口岸大楼A栋3楼，Shirley 18819441898 PP 样品：Signed Sample room/show room,数量：220/24,东莞市库有实业有限公司, 地址：东莞市清溪镇香芒西路213号 收件人：Jessica,电话：15999542773 PP 样品：Fast star sample,数量：24，地址：TBD （请留意保留好此PP 样板，跟单会补下PO 单扣减此数量），需空运到新西兰做上架试卖，务必保证外观功能ok | AB4: 77858-S001 | AC4: 已入
A5: 46021 | D5: ZMPO251171 | G5: 77858-S001 | H5: 厨房套装 | I5: 498 | J5: 0 | K5: 3 | L5: =I5/K5 -> 166 | M5: 46038 | N5: 46038 | P5: OK | S5: 46386 | T5: 无 | U5: 无 | W5: Remark:跟PP订单一起安排/大货标准箱装箱/箱唛请参照邮件附件 备注：收到样品订单后尽快安排 ，注意样板品质质量要求要高于大货品质要求 ，送货时必须要附带送货单(没有送货单和QC检验合格报告的仓库一律拒绝收货)，请知悉，谢谢！ | AB5: 77858-S001 | AC5: 已入 | AE5: 车间生产+包装
A6: 46045 | B6: ZURU NEW ZEALAND LIMITED | C6: 新西兰 | D6: 4500192110 | E6: 从PP中扣数 | F6: 4500192110-10 | G6: 77858-S001-FS | H6: 厨房套装 | I6: 24 | J6: 0 | K6: 3 | L6: =I6/K6 -> 8 | M6: 46052 | N6: 46048 | R6: 是 | S6: 46045 | T6: 有 | U6: 1/23黄色贴纸 | W6: 日期码格式：ZURU INC(BVI) 标准格式 日期：按实际生产日期 Packaging Info: Remark: NZ Fast Start Order, 从PP PO中扣数，需要更换为fast start专属UPC，外箱除常规箱唛外，还需要加贴一张黄色贴纸，印“fast start". | X6: Ivy Li | Y6: 8.5 | Z6: =I6*Y6 -> 204 | AB6: 77858-S001 | AC6: 已入 | AE6: 车间生产+包装
A7: 46059 | B7: TARGET US | C7: 美国 | D7: 4500190738 | E7: 10001661694-3891 | F7: 4500190738-30 | G7: 77858-S001 | H7: 厨房套装 | I7: 2442 | J7: 0 | K7: 3 | L7: =I7/K7 -> 814 | M7: 46119 | N7: 46118 | P7: OK | Q7: 46133 | R7: 是 | S7: 46081 | T7: 有 | U7: 3/25条码箱贴纸+2/10Event label | W7: 日期码格式：ZURU INC(BVI) 标准格式 日期：按实际生产日期 Packaging Info: 77858： 产品包装 MA 1L 彩盒，彩盒上的UPC显示193052100238; Remark: 77858： 1. 77858-S001-MINI BRANDS-MAGIC COOK KITCHEN PLAYSET-SERIES 1-WINDOW BOX,3PCS/CTN; 2. 产品包装 MA 1L 彩盒，彩盒上的UPC显示193052100238; 3. 外箱正唛左上角位置粘贴条码箱贴纸，每箱只贴一张，由ZURU订购。来料贴纸上显示的客户DPCI: 086-02-5654, UPC显示10193052100235; 4. 每个外箱正唛箱唛内容右侧需贴一张Event label，内容显示 7/19 TRANSITION TOYS Set Date 7/19/2026，工厂自行订购; 以上Items： 1. 产品和包装上均要印刷tracking code信息，格式为ZURU常规格式； 2. 需要我司QC验货之后才能安排出货 3. 出货方式： 货代自提 | X7: Holly Zheng | Y7: 5.9383 | Z7: =I7*Y7 -> 14501.329 | AB7: 77858-S001 | AC7: 已入 | AE7: 车间生产+包装 | AI7: =I7 -> 2442 | AM7: =I7 -> 2442 | AQ7: =I7 -> 2442
A8: 46055 | B8: SMYTHS TOYS HQ UC UK | C8: 英国 | D8: 4500192931 | E8: 4400537129 | F8: 4500192931-10 | G8: 77858-S001 | H8: 厨房套装 | I8: 3000 | J8: 0 | K8: 3 | L8: =I8/K8 -> 1000 | M8: 46122 | N8: 46120 | P8: OK | Q8: 46125 | R8: 是 | S8: 46083 | T8: 无 | U8: MA蔬菜盒子贴纸 | W8: 日期码格式：ZURU INC(BVI) 标准格式 日期：按实际生产日期 Packaging Info: "77858: 最新MA3L-23Lwarning EAN彩盒+MA蔬菜盒子贴纸+MA复合袋+MA23L说明书+MA5L收藏指南+B版WEEE声明(不带电池)走货欧洲通用30L说明书 EAN#4894680058729" "92146TQ1: MA3L-13Lwarning收缩膜+MA布标+MA贴纸+MA5L-19L收藏指南 Ratio: Cat:Raccoon:Deer:Tiger:Pigeon:Owl=1:1:1:1:1:1" 25282D: 最新MA3L+23L警告语 MA彩盒+一张新的UPC条码贴纸(25282D#193052063199; 翻PO#4500116913)+MA 9L说明书+WEEE声明通用30L-B版说明书（带电池） 25282A: 最新MA3L+23L警告语 MA彩盒+一张新的UPC条码贴纸(25282A#193052062611; 本单放稿)+MA 9L说明书+WEEE声明通用30L-B版说明书（带电池） 25282B: 最新MA3L+23L警告语 MA彩盒+一张新的UPC条码贴纸(25282B#193052063182; 翻PO#4500116913)+MA 9L说明书+WEEE声明通用30L-B版说明书（带电池） "15788B: 最新MA 5L UPC彩盒+MA布标 UPC#193052099600 *外箱四面需要贴一张限制上架日期贴纸(GLOBAL ONSHELF DATE:2026/7/9), 翻PO#4500192931*" "15788D: 最新MA 5L UPC彩盒+MA布标 UPC#193052099617 *外箱四面需要贴一张限制上架日期贴纸(GLOBAL ONSHELF DATE:2026/7/9), 翻PO#4500192931*" "15788G: 最新MA 5L UPC彩盒+MA布标 UPC#193052099631 *外箱四面需要贴一张限制上架日期贴纸(GLOBAL ONSHELF DATE:2026/7/9), 翻PO#4500192931*" "15788H: 最新MA 5L UPC彩盒+MA布标 UPC#193052099648 *外箱四面需要贴一张限制上架日期贴纸(GLOBAL ONSHELF DATE:2026/7/9), 翻PO#4500192931*" "15783UQ1: MA 5L PDQ+MA 5L UPC彩盒+MA 角色卡+MA通用纸袋+MA布标 UPC#193052099693 7 Assortments; Rare assortment 1/24, others even ratio *外箱四面需要贴一张限制上架日期贴纸(GLOBAL ONSHELF DATE:2026/6/14)*" Remark: Smyths 英国/爱尔兰 1. 请准时出货，推期会有罚款； 2. 所有产品按符合欧洲标准走货，需要是不含微塑料版本。 3.包装日期码按ZURU格式即可，请确保不迟于外箱日期码，可等于或者早于外箱日期码，必须为法定工作日，印刷前请先检查外箱日期码。 4.请注意检查产品及包装应带UKCA图标（14+产品除外），包装显示ZURU UK LTD/ZURU France地址信息，QC部门请查核，如有问题与跟单确认 5.电子产品需增加一张WEEE声明30L通用黑白说明书(不接受A版本，翻译有误)，区分带电池和不带电池出货版本, 如已做客版说明书可忽略此要求； 6.订单备注显示有分批的（不同仓库/订单号） ，注意分开做货出货，否则会导致罚款 。 7.做货前请先复核包装条码与订单是否一致再安排，对不上的需与ZURU跟单确认再安排。 | X8: Sherry Lu | Y8: 8.8 | Z8: =I8*Y8 -> 26400 | AB8: 77858-S001-1 | AC8: 已入 | AE8: 车间生产+包装 | AL8: =I8 -> 3000 | AM8: =I8 -> 3000 | AO8: 30L | AQ8: =I8 -> 3000
A9: 46055 | B9: SMYTHS TOYS EU HQ UC | C9: 德国 | D9: 4500192949 | E9: 4400537136 | F9: 4500192949-10 | G9: 77858-S001 | H9: 厨房套装 | I9: 840 | J9: 0 | K9: 3 | L9: =I9/K9 -> 280 | M9: 46122 | N9: 46120 | P9: OK | Q9: 46133 | R9: 是 | S9: 46083 | T9: 无 | U9: 2/10德语callout贴纸(本单放稿)+MA蔬菜盒子贴纸 | V9: 需要加字唛 | W9: 日期码格式：ZURU INC(BVI) 标准格式 日期：按实际生产日期 Packaging Info: "77858: 最新MA3L-23Lwarning EAN彩盒+1张德语callout贴纸(本单放稿)+MA蔬菜盒子贴纸+MA复合袋+MA23L说明书+MA5L收藏指南+B版WEEE声明(不带电池)走货欧洲 通用30L说明书 EAN#4894680058729" Remark: Smyths 德国 1. 请准时出货，推期会有罚款； 2. 所有产品按符合欧洲标准走货，需要是不含微塑料版本。 3. 所有电子产品身上需要加字唛，为ZURU FRANCE 地址 (如无电子产品，产品布标有此地址，或产品太小无法增加可忽略此信息)，新地址ZURU FRANCE.33 rue Pa ul Meurice 75020 Paris, France. 4. 电子产品需增加一张WEEE声明30L通用黑白说明书(不接受A版本，翻译有误)，区分带电池和不带电池出货版本, 如已做客版说明书可忽略此要求； 5.所有出往德国市场有关slime和带香味的都需要出无硼无香版本； 6.订单备注显示有分批的（不同仓库/订单号） ，注意分开做货出货，否则会导致罚款 。 7.包装日期码按ZURU格式即可，请确保不迟于外箱日期码，可等于或者早于外箱日期码，必须为法定工作日。 8.做货前请先复核包装条码与订单是否一致再安排，对不上的需与ZURU跟单确认再安排。 9.包装必须含法国Sorting Label信息，如没有，请提醒跟单提供贴纸资料。 | X9: Sherry Lu | Y9: 8.8 | Z9: =I9*Y9 -> 7392 | AB9: 77858-S001-1 | AC9: 已入 | AE9: 车间生产+包装 | AL9: =I9 -> 840 | AM9: =I9 -> 840 | AO9: 30L | AQ9: =I9 -> 840
A10: 46055 | B10: SMYTHS TOYS EU HQ UC | C10: 德国 | D10: 4500192949 | E10: 4400537151 | F10: 4500192949-20 | G10: 77858-S001 | H10: 厨房套装 | I10: 660 | J10: 0 | K10: 3 | L10: =I10/K10 -> 220 | M10: 46122 | N10: 46120 | P10: OK | Q10: 46133 | R10: 是 | S10: 46083 | T10: 无 | U10: 2/10德语callout贴纸(本单放稿)+MA蔬菜盒子贴纸 | V10: 需要加字唛 | W10: 日期码格式：ZURU INC(BVI) 标准格式 日期：按实际生产日期 Packaging Info: "77858: 最新MA3L-23Lwarning EAN彩盒+1张德语callout贴纸(本单放稿)+MA蔬菜盒子贴纸+MA复合袋+MA23L说明书+MA5L收藏指南+B版WEEE声明(不带电池)走货欧洲 通用30L说明书 EAN#4894680058729" Remark: Smyths 德国 1. 请准时出货，推期会有罚款； 2. 所有产品按符合欧洲标准走货，需要是不含微塑料版本。 3. 所有电子产品身上需要加字唛，为ZURU FRANCE 地址 (如无电子产品，产品布标有此地址，或产品太小无法增加可忽略此信息)，新地址ZURU FRANCE.33 rue Pa ul Meurice 75020 Paris, France. 4. 电子产品需增加一张WEEE声明30L通用黑白说明书(不接受A版本，翻译有误)，区分带电池和不带电池出货版本, 如已做客版说明书可忽略此要求； 5.所有出往德国市场有关slime和带香味的都需要出无硼无香版本； 6.订单备注显示有分批的（不同仓库/订单号） ，注意分开做货出货，否则会导致罚款 。 7.包装日期码按ZURU格式即可，请确保不迟于外箱日期码，可等于或者早于外箱日期码，必须为法定工作日。 8.做货前请先复核包装条码与订单是否一致再安排，对不上的需与ZURU跟单确认再安排。 9.包装必须含法国Sorting Label信息，如没有，请提醒跟单提供贴纸资料。 | X10: Sherry Lu | Y10: 8.8 | Z10: =I10*Y10 -> 5808 | AB10: 77858-S001-1 | AC10: 已入 | AE10: 车间生产+包装 | AL10: =I10 -> 660 | AM10: =I10 -> 660 | AO10: 30L | AQ10: =I10 -> 660
A11: 46080 | B11: THE ENTERTAINER | C11: 英国 | D11: 4500194581 | E11: FB14546 | F11: 4500194581-10 | G11: 77858-S001 | H11: 厨房套装 | I11: 975 | J11: 0 | K11: 3 | L11: =I11/K11 -> 325 | M11: 46122 | N11: 46120 | P11: OK | Q11: 46194 | R11: 自行排版 | S11: 46093 | T11: 无 | U11: 无 | W11: 日期码格式：ZURU INC(BVI) 标准格式 日期：按实际生产日期 Packaging Info: 77858-S001：MA A版1L UPC包装+C版29L不含电池出货版本WEEE说明书 Remark: "MA版本按工厂现有最新库存即可，订单出英国，请注意检查产品及包装应带UKCA以及CE图标，包装显示ZURU UK LTD信息，QC同事请查核，如有问题与跟单确认 *生产日期按实际（法定工作日），按ZURU标准格式即可 ，但是请知悉包装日期码需要早于或者等于外箱日期码 ，不能晚于外箱日期码 *请注意所有订单都需要经过ZURU QC验货并且通过后方可出货 *所有产品按符合欧洲标准走货，需要是不含微塑料版本 。 *涉及到硼的，如可选择情况下应使用低硼版本 （slime 类别低硼一般低于300ppm)，无选择的应与跟单复核再安排 。 *如果出运产品属于电子类产品需要在ZURU 包装基础上额外添加一张ZURU 标准30L通用WEEE 电子产品说明书,带电池出货的加带电池出货版本通用30L的说明书，不 带电池出货的产品用不带电池出货版本的说明书. *根据客人最新的包装要求，所有多个PDQ盒子(TQ,UQ,GQ）入1外箱的都需要在PDQ顶部右上角加上数量贴纸标明里面的数量。最小字体：36pts, 字体：Calibri（bo ld), 具体要求以及位置见文件. *订单对应客户PO号 ，备注有显示 ，注意分开做货/验货/装柜 ，混装有罚款。 * 大货样： 新款请在CRD前10天寄出每款2整套大货样到罗湖办公室7B Meyya Liu 收，翻单不用寄。" | X11: Meyya Liu | Y11: 10.2316 | Z11: =I11*Y11 -> 9975.81 | AB11: 77858-S001 | AC11: 已入 | AE11: 车间生产+包装 | AI11: =I11 -> 975 | AM11: =I11 -> 975 | AO11: 29L | AQ11: =I11 -> 975
A12: 46055 | B12: SMYTHS TOYS HQ UC IE | C12: 爱尔兰 | D12: 4500192938 | E12: 4400537132 | F12: 4500192938-10 | G12: 77858-S001 | H12: 厨房套装 | I12: 1002 | J12: 0 | K12: 3 | L12: =I12/K12 -> 334 | M12: 46122 | N12: 46120 | P12: OK | Q12: 46127 | R12: 是 | S12: 46083 | T12: 无 | U12: MA蔬菜盒子贴纸 | W12: 日期码格式：ZURU INC(BVI) 标准格式 日期：按实际生产日期 Packaging Info: "77858: 最新MA3L-23Lwarning EAN彩盒+MA蔬菜盒子贴纸+MA复合袋+MA23L说明书+MA5L收藏指南+B版WEEE声明(不带电池)走货欧洲通用30L说明书 EAN#4894680058729" Remark: Smyths 英国/爱尔兰 1. 请准时出货，推期会有罚款； 2. 所有产品按符合欧洲标准走货，需要是不含微塑料版本。 3.包装日期码按ZURU格式即可，请确保不迟于外箱日期码，可等于或者早于外箱日期码，必须为法定工作日，印刷前请先检查外箱日期码。 4.请注意检查产品及包装应带UKCA图标（14+产品除外），包装显示ZURU UK LTD/ZURU France地址信息，QC部门请查核，如有问题与跟单确认 5.电子产品需增加一张WEEE声明30L通用黑白说明书(不接受A版本，翻译有误)，区分带电池和不带电池出货版本, 如已做客版说明书可忽略此要求； 6.订单备注显示有分批的（不同仓库/订单号） ，注意分开做货出货，否则会导致罚款 。 7.做货前请先复核包装条码与订单是否一致再安排，对不上的需与ZURU跟单确认再安排。 | X12: Sherry Lu | Y12: 8.8 | Z12: =I12*Y12 -> 8817.6 | AB12: 77858-S001-1 | AC12: 已入 | AE12: 车间生产+包装 | AL12: =I12 -> 1002 | AM12: =I12 -> 1002 | AO12: 30L | AQ12: =I12 -> 1002
A13: 46055 | B13: SMYTHS TOYS EU HQ UNLIMITED COMPANY | C13: 法国 | D13: 4500192944 | E13: 4400536944 | F13: 4500192944-10 | G13: 77858-S001 | H13: 厨房套装 | I13: 561 | J13: 0 | K13: 3 | L13: =I13/K13 -> 187 | M13: 46122 | N13: 46120 | P13: OK | Q13: 46132 | R13: 是 | S13: 46083 | T13: 无 | U13: MA蔬菜盒子贴纸 | W13: 日期码格式：ZURU INC(BVI) 标准格式 日期：按实际生产日期 Packaging Info: "77858: 最新MA3L-23Lwarning EAN彩盒+MA蔬菜盒子贴纸+MA复合袋+MA23L说明书+MA5L收藏指南+B版WEEE声明(不带电池)走货欧洲通用30L说明书 EAN#4894680058729" "15788B: 最新MA 5L UPC彩盒+MA布标 UPC#193052099600 *外箱四面需要贴一张限制上架日期贴纸(GLOBAL ONSHELF DATE:2026/7/9), 翻PO#4500192931*" "15788D: 最新MA 5L UPC彩盒+MA布标 UPC#193052099617 *外箱四面需要贴一张限制上架日期贴纸(GLOBAL ONSHELF DATE:2026/7/9), 翻PO#4500192931*" "15788H: 最新MA 5L UPC彩盒+MA布标 UPC#193052099648 *外箱四面需要贴一张限制上架日期贴纸(GLOBAL ONSHELF DATE:2026/7/9), 翻PO#4500192931*" "15788G: 最新MA 5L UPC彩盒+MA布标 UPC#193052099631 *外箱四面需要贴一张限制上架日期贴纸(GLOBAL ONSHELF DATE:2026/7/9), 翻PO#4500192931*" "77711GQ2: 最新MA PDQ(优先3L)+MA-3L EAN收缩膜+1张法国sorting label贴纸(翻PO#4500182619) + MA-23L说明书 + MA-5-23L警语收藏指南 + MA-5L creative 说明书 EAN: 4894680043350" "77673TQ1: 最新MA 3L EAN配套包装+WEEE声明(带电池)走货欧洲通用30L-B版说明书 EAN: 4894680042773" Remark: Smyths 法国 1. 请准时出货，推期会有罚款； 2. 所有产品按符合欧洲标准走货，需要是不含微塑料版本。 3. 电子产品需增加一张WEEE声明30L通用黑白说明书(不接受A版本，翻译有误)，区分带电池和不带电池出货版本, 如已做客版说明书可忽略此要求； 4. 出口法国的产品, 法规规定禁止在包装和共公众用的印刷品中使用矿物油中含有的物质, 包装印刷油墨中含有的MOAH/MOSH的质量浓度不能超过1%, 否则出货到 法国被抽检出现问题, 供应商需要对此负责; 5.订单备注显示有分批的（不同仓库/订单号） ，注意分开做货出货，否则会导致罚款 。 6.包装日期码按ZURU格式即可，请确保不迟于外箱日期码，可等于或者早于外箱日期码，必须为法定工作日。 7.做货前请先复核包装条码与订单是否一致再安排，对不上的需与ZURU跟单确认再安排。 | X13: Sherry Lu | Y13: 8.8 | Z13: =I13*Y13 -> 4936.8 | AB13: 77858-S001-1 | AC13: 已入 | AE13: 车间生产+包装 | AL13: =I13 -> 561 | AM13: =I13 -> 561 | AO13: 30L | AQ13: =I13 -> 561
A14: 46055 | B14: SMYTHS TOYS EU HQ UNLIMITED COMPANY | C14: 法国 | D14: 4500192944 | E14: 4400536950 | F14: 4500192944-20 | G14: 77858-S001 | H14: 厨房套装 | I14: 240 | J14: 0 | K14: 3 | L14: =I14/K14 -> 80 | M14: 46122 | N14: 46120 | P14: OK | Q14: 46132 | R14: 是 | S14: 46083 | T14: 无 | U14: MA蔬菜盒子贴纸 | W14: 日期码格式：ZURU INC(BVI) 标准格式 日期：按实际生产日期 Packaging Info: "77858: 最新MA3L-23Lwarning EAN彩盒+MA蔬菜盒子贴纸+MA复合袋+MA23L说明书+MA5L收藏指南+B版WEEE声明(不带电池)走货欧洲通用30L说明书 EAN#4894680058729" "15788B: 最新MA 5L UPC彩盒+MA布标 UPC#193052099600 *外箱四面需要贴一张限制上架日期贴纸(GLOBAL ONSHELF DATE:2026/7/9), 翻PO#4500192931*" "15788D: 最新MA 5L UPC彩盒+MA布标 UPC#193052099617 *外箱四面需要贴一张限制上架日期贴纸(GLOBAL ONSHELF DATE:2026/7/9), 翻PO#4500192931*" "15788H: 最新MA 5L UPC彩盒+MA布标 UPC#193052099648 *外箱四面需要贴一张限制上架日期贴纸(GLOBAL ONSHELF DATE:2026/7/9), 翻PO#4500192931*" "15788G: 最新MA 5L UPC彩盒+MA布标 UPC#193052099631 *外箱四面需要贴一张限制上架日期贴纸(GLOBAL ONSHELF DATE:2026/7/9), 翻PO#4500192931*" "77711GQ2: 最新MA PDQ(优先3L)+MA-3L EAN收缩膜+1张法国sorting label贴纸(翻PO#4500182619) + MA-23L说明书 + MA-5-23L警语收藏指南 + MA-5L creative 说明书 EAN: 4894680043350" "77673TQ1: 最新MA 3L EAN配套包装+WEEE声明(带电池)走货欧洲通用30L-B版说明书 EAN: 4894680042773" Remark: Smyths 法国 1. 请准时出货，推期会有罚款； 2. 所有产品按符合欧洲标准走货，需要是不含微塑料版本。 3. 电子产品需增加一张WEEE声明30L通用黑白说明书(不接受A版本，翻译有误)，区分带电池和不带电池出货版本, 如已做客版说明书可忽略此要求； 4. 出口法国的产品, 法规规定禁止在包装和共公众用的印刷品中使用矿物油中含有的物质, 包装印刷油墨中含有的MOAH/MOSH的质量浓度不能超过1%, 否则出货到 法国被抽检出现问题, 供应商需要对此负责; 5.订单备注显示有分批的（不同仓库/订单号） ，注意分开做货出货，否则会导致罚款 。 6.包装日期码按ZURU格式即可，请确保不迟于外箱日期码，可等于或者早于外箱日期码，必须为法定工作日。 7.做货前请先复核包装条码与订单是否一致再安排，对不上的需与ZURU跟单确认再安排。 | X14: Sherry Lu | Y14: 8.8 | Z14: =I14*Y14 -> 2112 | AB14: 77858-S001-1 | AC14: 已入 | AE14: 车间生产+包装 | AL14: =I14 -> 240 | AM14: =I14 -> 240 | AO14: 30L | AQ14: =I14 -> 240
A15: 46064 | B15: LEKIA AB | C15: 瑞典 | D15: 4500193679 | F15: 4500193679-10 | G15: 77858-S001 | H15: 厨房套装 | I15: 2502 | J15: 0 | K15: 3 | L15: =I15/K15 -> 834 | M15: 46128 | N15: 46126 | P15: OK | Q15: 46133 | R15: 是 | S15: 46093 | T15: 无 | U15: 无 | W15: 日期码格式：ZURU INC(BVI) 标准格式 日期：按实际生产日期 Packaging Info: 1. 77858: MA A3L(23L warning) EAN版彩盒+MA A23L黑白电池说明书+MA A版收藏指南+WEEE_不带电池走货 _ 说明书欧洲EN+29L_C版 Remark: 1. 包装如含PVC,请改为PET 2. 产品/包装要求无硼无香； 3. 出欧洲，微塑料需合规。 4.带电池出货的产品所用到的电池需要符合欧洲电池新规(EU) 2023-1542 5.产品/包装不含PFAS and/or Bisfenol成分 6. 产品条码如下: 请先检查条码是否正确再安排做货，如有问题请告知: 77858-S001:4894680058729 | X15: Sheba Ye | Y15: 8.8 | Z15: =I15*Y15 -> 22017.6 | AB15: 77858-S001-1 | AC15: 已入 | AE15: 湖南提供半成品 | AL15: =I15 -> 2502 | AM15: =I15 -> 2502 | AO15: 29L | AQ15: =I15 -> 2502
A16: 46079 | B16: TARGET US | C16: 美国 | D16: 4500194297 | E16: 10001661693-3890 | F16: 4500194297-30 | G16: 77858-S001 | H16: 厨房套装 | I16: 3366 | J16: 0 | K16: 3 | L16: =I16/K16 -> 1122 | M16: 46132 | N16: 46129 | P16: OK | Q16: 46142 | R16: 是 | S16: 46101 | T16: 有 | U16: 3/31条码箱贴纸+2/26 Event label | W16: 日期码格式：ZURU INC(BVI) 标准格式 日期：按实际生产日期 Packaging Info: 77858：产品包装 MA 1L 彩盒； Remark: 77858： 1. 77858-S001-MINI BRANDS-MAGIC COOK KITCHEN PLAYSET-SERIES 1-WINDOW BOX,3PCS/CTN; 2. 产品包装 MA 1L 彩盒，彩盒上的UPC显示193052100238; 3. 外箱正唛左上角位置粘贴条码箱贴纸，每箱只贴一张，由ZURU订购。来料贴纸上显示的客户DPCI: 086-02-5654, UPC显示10193052100235; 4. 每个外箱正唛箱唛内容右侧需贴一张Event label，内容显示 7/19 TRANSITION TOYS Set Date 7/19/2026，工厂自行订购; 以上Items： 1. 产品和包装上均要印刷tracking code信息，格式为ZURU常规格式； 2. 需要我司QC验货之后才能安排出货 3. 出货方式： 货代自提 | X16: Holly Zheng | Y16: 5.28 | Z16: =I16*Y16 -> 17772.48 | AB16: 77858-S001 | AC16: 已入 | AE16: 湖南提供半成品 | AI16: =I16 -> 3366 | AM16: =I16 -> 3366 | AQ16: =I16 -> 3366
A17: 46087 | B17: WALMART INC. | C17: 美国 | D17: 4500195615 | E17: 0983717776 | F17: 4500195615-10 | G17: 77858-S002 | H17: 厨房套装 | I17: 500 | J17: 0 | K17: 2 | L17: =I17/K17 -> 250 | M17: 46135 | N17: 46133 | O17: 5/11第三方 4/23抽板 | P17: OK | Q17: 46174 | R17: 是 | S17: 46087 | T17: 无 | U17: 3/6RFID贴纸 | W17: 日期码格式：ZURU DGYYYYMMDD CHINA(日期避开周末和法定节假日即可） 日期：按实际生产日期 Packaging Info: 77858-S002 1. 包装要求： 77858：MA 1L A版 playset +MA 5L A版收藏指南+MA 23L A版说明书+MA A版纸袋+MA 贴纸 每pcs产品要贴一张RFID贴纸，RFID贴纸由ZURU提供，贴纸位置要严格按照客人签板 Remark: 77858-S002 1. 包装要求： 77858：MA 1L A版 playset +MA 5L A版收藏指南+MA 23L A版说明书+MA A版纸袋+MA 贴纸 每pcs产品要贴一张RFID贴纸，RFID贴纸由ZURU提供，贴纸位置要严格按照客人签板 2. 外箱印刷带条码的RFID箱唛：RFID紫色色带+WM Dept.图标+RFID图标+ITF-14条码，四面右下角印刷ZURU logo, ITFF条码只印刷在正唛一面，在加印的时候确保 条形码能扫描出来，外箱侧面任一角落加印："MADE IN CHINA" 字样； 3. 在产品上和包装上要有日期码、以及要有MADE IN CHINA和ZURU字样； 4. 产品如有扎带口要剪平，不能刮手。 5. 此单需要抽板和验货，抽板时间预计4/23，请多备料 6. 此单以loose carton出货，2pcs/CTN | X17: Maggie Xie | Y17: 6.5485 | Z17: =Y17*I17 -> 3274.25 | AB17: 77858-S002 | AC17: 已入 | AE17: 湖南提供半成品 | AI17: =I17 -> 500 | AM17: =I17 -> 500 | AQ17: =I17 -> 500
A18: 46079 | B18: TARGET US | C18: 美国 | D18: 4500194290 | E18: 10001708292-0 581 | F18: 4500194290-10 | G18: 77858-S001 | H18: 厨房套装 | I18: 375 | J18: 0 | K18: 3 | L18: =I18/K18 -> 125 | M18: 46136 | N18: 46132 | P18: OK | Q18: 46143 | R18: 是 | S18: 46105 | T18: 有 | U18: 4/2 条码箱贴纸 | W18: 日期码格式：ZURU INC(BVI) 标准格式 日期：按实际生产日期 Packaging Info: 77858：产品包装 MA 1L 彩盒； Remark: 77858： 1. 77858-S001-MINI BRANDS-MAGIC COOK KITCHEN PLAYSET-SERIES 1-WINDOW BOX,3PCS/CTN; 2. 产品包装 MA 1L 彩盒，彩盒上的UPC显示193052100238; 3. 外箱正唛左上角位置粘贴条码箱贴纸，每箱只贴一张，由ZURU订购。来料贴纸上显示的客户DPCI: 086-02-5654, UPC显示10193052100235; 以上Items： 1. 产品和包装上均要印刷tracking code信息，格式为ZURU常规格式； 2. 需要我司QC验货之后才能安排出货 3. 出货方式： 货代自提 | X18: Holly Zheng | Y18: 5.28 | Z18: =I18*Y18 -> 1980 | AB18: 77858-S001 | AC18: 已入 | AE18: 湖南提供半成品 | AI18: =I18 -> 375 | AM18: =I18 -> 375 | AQ18: =I18 -> 375
A19: 46079 | B19: TARGET US | C19: 美国 | D19: 4500194303 | E19: 10001661762-3 891 | F19: 4500194303-20 | G19: 77858-S001 | H19: 厨房套装 | I19: 1764 | J19: 0 | K19: 3 | L19: =I19/K19 -> 588 | M19: 46141 | N19: 46139 | P19: OK | Q19: 46153 | R19: 是 | S19: 46108 | T19: 有 | U19: 4/8条码箱贴纸 | W19: 日期码格式：ZURU INC(BVI) 标准格式 日期：按实际生产日期 Packaging Info: 77858：产品包装 MA 1L 彩盒； Remark: 77858： 1. 77858-S001-MINI BRANDS-MAGIC COOK KITCHEN PLAYSET-SERIES 1-WINDOW BOX,3PCS/CTN; 2. 产品包装 MA 1L 彩盒，彩盒上的UPC显示193052100238; 3. 外箱正唛左上角位置粘贴条码箱贴纸，每箱只贴一张，由ZURU订购。来料贴纸上显示的客户DPCI: 086-02-5654, UPC显示10193052100235; 以上Items： 1. 产品和包装上均要印刷tracking code信息，格式为ZURU常规格式； 2. 需要我司QC验货之后才能安排出货 3. 出货方式： 货代自提 | X19: Holly Zheng | Y19: 5.9555 | Z19: =I19*Y19 -> 10505.502 | AB19: 77858-S001 | AC19: 已入 | AE19: 湖南提供半成品 | AI19: =I19 -> 1764 | AM19: =I19 -> 1764 | AQ19: =I19 -> 1764
A20: 46080 | B20: MEIJER DISTRIBUTION, INC. | C20: 美国 | D20: 4500194442 | E20: 219072775 | F20: 4500194442-70 | G20: 77858-S001 | H20: 厨房套装 | I20: 570 | J20: 0 | K20: 3 | L20: =I20/K20 -> 190 | M20: 46142 | N20: 46140 | P20: OK | Q20: 46152 | R20: 是 | S20: 46098 | T20: 无 | U20: 无 | W20: 日期码格式：ZURU INC(BVI) 标准格式 日期： Packaging Info: 1. 通用PDQ, 产品MA UPC包装（优先1L）出美国 2. 客人指定箱唛排版 Remark: 出货前 Zuru QC 验货 | X20: Agnes Zheng | Y20: 5.28 | Z20: =I20*Y20 -> 3009.6 | AB20: 77858-S001 | AC20: 已入 | AE20: 湖南提供半成品 | AI20: =I20 -> 570 | AM20: =I20 -> 570 | AQ20: =I20 -> 570
A21: 46080 | B21: MEIJER DISTRIBUTION, INC. | C21: 美国 | D21: 4500194442 | E21: 219072771 | F21: 4500194442-80 | G21: 77858-S001 | H21: 厨房套装 | I21: 402 | J21: 0 | K21: 3 | L21: =I21/K21 -> 134 | M21: 46142 | N21: 46140 | P21: OK | Q21: 46152 | R21: 是 | S21: 46098 | T21: 无 | U21: 无 | W21: 日期码格式：ZURU INC(BVI) 标准格式 日期： Packaging Info: 1. 通用PDQ, 产品MA UPC包装（优先1L）出美国 2. 客人指定箱唛排版 Remark: 出货前 Zuru QC 验货 | X21: Agnes Zheng | Y21: 5.28 | Z21: =I21*Y21 -> 2122.56 | AB21: 77858-S001 | AC21: 已入 | AE21: 湖南提供半成品 | AI21: =I21 -> 402 | AM21: =I21 -> 402 | AQ21: =I21 -> 402
A22: 46093 | B22: WONDERLAND TOYS, INC. | C22: 美国 | D22: 4500196264 | E22: 5167 | F22: 4500196264-40 | G22: 77858-S001 | H22: 厨房套装 | I22: 144 | J22: 0 | K22: 3 | L22: =I22/K22 -> 48 | M22: 46142 | N22: 46140 | P22: OK | Q22: 46154 | R22: 是 | S22: 46098 | T22: 无 | U22: 无 | W22: 日期码格式：ZURU INC(BVI) 标准格式 日期：按实际生产日期 Packaging Info: 1. 出口美国，MA UPC 版本包装，优先1L。 5. Item 77858 UPC#193052100238. 出货不含电池。 Remark: 8. ZURU QC 验货即可。 | X22: Abby Mai,Lluvia Zeng | Y22: 6.139 | Z22: =I22*Y22 -> 884.016 | AB22: 77858-S001 | AC22: 已入 | AE22: 湖南提供半成品 | AI22: =I22 -> 144 | AM22: =I22 -> 144 | AQ22: =I22 -> 144
A23: 46094 | B23: KANDYTOYS LIMITED | C23: 英国 | D23: 4500196850 | E23: AS191225ZUR15 274 | F23: 4500196850-20 | G23: 77858-S001 | H23: 厨房套装 | I23: 750 | J23: 0 | K23: 3 | L23: =I23/K23 -> 250 | M23: 46147 | N23: 46143 | P23: OK | Q23: 46160 | R23: 是 | S23: 46115 | T23: 无 | U23: 无 | W23: 日期码格式：ZURU INC(BVI) 标准格式 日期：按实际生产日期 Packaging Info: 77858: MA UPC 1L+WEEE 30L B 不含电池说明书 Remark: 1.订单出英国，请注意检查产品及包装应带UKCA图标，包装需要显示ZURU UK LTD/ZURU France地址信息，QC同事请查核，如有问题与跟单确认。 2.生产日期按实际的（法定工作日），按ZURU标准格式即可 ，并需要在出货前提供每个产品外包上对应的生产日期明细 3.请注意所有订单都需要经过ZURU QC验货并且通过后方可出货 4.一个产品的条码请允许有一个，混款并每个款不同条码的需要加条码贴纸覆盖 5.外箱上的条码请确保清晰可扫描，有PDQ， 需要在PDQ底部贴一张带条码并可扫描的贴纸(ZURU 跟单提供模板）。 6.所有产品按符合欧洲标准走货，微塑料需合规并增加IFUD声明，含电池的需要增加WEEE说明书。 7.硼限值要低于300ppm | X23: Zoe Zhou | Y23: 9.9425 | Z23: =I23*Y23 -> 7456.875 | AB23: 77858-S001 | AC23: 已入 | AI23: =I23 -> 750 | AM23: =I23 -> 750 | AO23: 30L | AQ23: =I23 -> 750
A24: 46106 | B24: WALMART INC. | C24: 美国 | D24: 4500197934 | E24: 0983717796 | F24: 4500197934-20 | G24: 77858-S002 | H24: 厨房套装 | I24: 500 | J24: 0 | K24: 2 | L24: =I24/K24 -> 250 | M24: 46149 | N24: 46146 | O24: 46153 | P24: OK | Q24: 46160 | R24: 是 | S24: 翻4500195615 | T24: 无 | U24: 4/8RFID贴纸 | W24: 日期码格式：ZURU DGYYMMDD CHINA(日期避开周末和法定节假日即可） 日期：按实际生产日期 Packaging Info: 77843SLB-S001 1. 包装要求： 77858-S002 1. 包装要求： 77858：MA 1L A版 playset +MA 5L A版收藏指南+MA 23L A版说明书+MA A版纸袋+MA 贴纸 每pcs产品要贴一张RFID贴纸，RFID贴纸由ZURU提供，贴纸位置要严格按照客人签板 77858-S002 1. 包装要求： 77858：MA 1L A版 playset +MA 5L A版收藏指南+MA 23L A版说明书+MA A版纸袋+MA 贴纸 每pcs产品要贴一张RFID贴纸，RFID贴纸由ZURU提供，贴纸位置要严格按照客人签板 2. 外箱印刷带条码的RFID箱唛：RFID紫色色带+WM Dept.图标+RFID图标+ITF-14条码，四面右下角印刷ZURU logo, ITFF条码只印刷在正唛一面，在加印的时候确保 条形码能扫描出来，外箱侧面任一角落加印："MADE IN CHINA" 字样； 3. 在产品上和包装上要有日期码、以及要有MADE IN CHINA和ZURU字样； 4. 产品如有扎带口要剪平，不能刮手。 5. 此单需要验货，请多备料 6. 此单以loose carton出货，2pcs/CTN | X24: Maggie Xie | Y24: 6.5485 | Z24: =I24*Y24 -> 3274.25 | AB24: 77858-S002 | AC24: 已入 | AI24: =I24 -> 500 | AM24: =I24 -> 500 | AQ24: =I24 -> 500
A25: 46112 | B25: ZURU LLC | C25: 美国 | D25: 4500199495 | E25: 5200009500 | F25: 4500199495-10 | G25: 77858-S003-MB-MTS | H25: 厨房套装 | I25: 480 | J25: 0 | K25: 3 | L25: =I25/K25 -> 160 | M25: 46149 | N25: 46147 | P25: OK | Q25: 46157 | R25: 是 | S25: 46113 | T25: 无 | U25: 无 | V25: 邮包盒图稿翻单4500194000 | W25: 日期码格式：ZURU INC(BVI) 标准格式 日期：按实际生产日期 Packaging Info: #77858: STD 77858带MA包装入邮包盒，邮包盒图稿翻单4500194000。 Remark: 1.TikTok US订单。出口美国。外箱尺寸不能超过26*26*26" ，不符合要求的大货，一律不接受。 2.无第三方验货/测试要求。 3. 日期码使用ZURU标准版本。 4.如果大货有要求入邮包盒，则对应的邮包盒上面要打上日期码。 | X25: Kelly Shen | Y25: 7.3813 | Z25: =Y25*L25 -> 1181.008 | AB25: 77858-S003-MB | AC25: 已入 | AI25: =I25 -> 480 | AM25: =I25 -> 480 | AQ25: =I25 -> 480
A26: 46108 | B26: TARGET US | C26: 美国 | D26: 4500199055 | E26: 10001661761-3890 | F26: 4500199055-20 | G26: 77858-S001 | H26: 厨房套装 | I26: 2430 | J26: 0 | K26: 3 | L26: =I26/K26 -> 810 | M26: 46150 | N26: 46148 | P26: OK | Q26: 46163 | R26: 是 | S26: 46120 | T26: 有 | U26: 4/23条码箱贴纸 | W26: 日期码格式：ZURU INC(BVI) 标准格式 日期：按实际生产日期 Packaging Info: 77673TQ1：产品包装 客版收缩膜(C版)+客版收藏指南+MA说明书+ MA 1L PDQ；客版收缩膜(C版）翻单4500183607；客版收藏指南翻单4500174008； 77858：产品包装 MA 1L 彩盒； 77772GQ5：产品包装MA 1L 收缩膜+MA 5L 收藏指南+MA 23L 组装说明+客版PDQ；客版PDQ翻单4500189603； 77794UQ1：产品包装 MA 1L黑白警告语说明书+MA 1L 彩盒+MA 1L PDQ+锂电池标签纸 Remark: 77673TQ1： 1. 77673TQ1-S001-CC-MINI BRANDS-FILL THE FRIDGE PLAYSET-SERIES 1-SHRINK WRAP,4PCS/PDQ,4PCS/PDQ/CTN; 2. 产品包装 客版收缩膜(C版)+客版收藏指南+MA说明书+ MA 1L PDQ；客版收缩膜上的UPC显示193052079404；客版收缩膜(C版）翻单4500183607；客版收藏指南翻 单4500174008； 3. 外箱正唛左上角位置粘贴条码箱贴纸，每箱只贴一张，由ZURU订购。来料贴纸上显示的客户DPCI# 086-02-3468， UPC显示10193052079401; 77858： 1. 77858-S001-MINI BRANDS-MAGIC COOK KITCHEN PLAYSET-SERIES 1-WINDOW BOX,3PCS/CTN; 2. 产品包装 MA 1L 彩盒，彩盒上的UPC显示193052100238; 3. 外箱正唛左上角位置粘贴条码箱贴纸，每箱只贴一张，由ZURU订购。来料贴纸上显示的客户DPCI: 086-02-5654, UPC显示10193052100235; 77772GQ5： 1.77772GQ5-S001-MINI BRANDS-VINYL-SERIES 1-CAPSULE,WITH DEMO,25PCS/GRAVITY PDQ,25PCS/PDQ/CTN; 2.产品包装MA 1L 收缩膜+MA 5L 收藏指南+MA 23L 组装说明+客版PDQ；客版PDQ翻单4500189603；收缩膜上的UPC显示193052090065; 4 mini vinyls(1 Target US Exclusive),1 accessory; 3. 外箱正唛左上角位置粘贴条码箱贴纸，每箱只贴一张，由ZURU订购。来料贴纸上显示的客户DPCI# 086-02-8931, UPC显示10193052090062; 77794UQ1： 1.77794UQ1-S002-MINI BRANDS-VINYL-PLAYSET-SERIES 1-CUBE,8PCS/PDQ,8PCS/PDQ/CTN; 2. 产品包装 MA 1L黑白警告语说明书+MA 1L 彩盒+MA 1L PDQ+锂电池标签纸; 彩盒上的UPC显示193052090409; 3. 外箱正唛左上角位置粘贴条码箱贴纸，每箱只贴一张，由ZURU订购。来料贴纸上显示的客户DPCI# 086-02-4085, UPC显示10193052090406; 4. 带锂电池出货，需在外箱正面或者侧面合适位置上加贴一张贴锂电池标签纸，由工厂订购 以上Items： 1. 产品和包装上均要印刷tracking code信息，格式为ZURU常规格式； 2. 需要我司QC验货之后才能安排出货 3. 出货方式： 货代自提 | X26: Holly Zheng | Y26: 5.9383 | Z26: =I26*Y26 -> 14430.069 | AB26: 77858-S001 | AC26: 已入 | AI26: =I26 -> 2430 | AM26: =I26 -> 2430 | AQ26: =I26 -> 2430
A27: 46108 | B27: AMAZON EU SARL, NDL DEUTSCHLAND | C27: 西班牙 | D27: 4500198640 | E27: 53YR16IV | F27: 4500198640-100 | G27: 77858-S003-MB | H27: 厨房套装 | I27: 501 | J27: 0 | K27: 3 | L27: =I27/K27 -> 167 | M27: 46150 | N27: 46148 | P27: OK | Q27: 46159 | S27: 空白外箱（加印带Zuru字样的最新logo，除了邮包盒直接做外箱的产品） | T27: 有 | U27: 4/24条码箱贴纸 | V27: 客版邮包盒翻单4500192979 | W27: 日期码格式：ZURU INC(BVI) 标准格式 日期：按实际生产日期 Packaging Info: Amazon UK: 5TKIJIXX/3O77XWME/2EIMZ29W/1VCZUJZI/7N1D8FUG/5Z2UXPOL/5PNQ9H8L Amazon DE: 4EO3QWQS/3LFCI9MA/115AX8DW Amazon FR: 6VRKJU2V Amazon ES: 53YR16IV Amazon IT: 5D2ZS8EV Amazon UK(157114DG/157140/157143/15780ABD/15788G/71172/77878/92146BDG/92147E)/DE(157114G/15788BG/92146GH/92147E)/FR(92146G)/ES(157143/77858)/IT( 157140/157143/92146G) 10. 77858: 1pc 77858 playset into mailbox, 3mailboxes/ctn; Including magnets; 3PCS AA BATTERIES(NOT INCLUDED); MA 3L(23L warning EAN)A 透明PVC窗 彩盒+MA 23L warning A 电池黑白说明书+MA 5L A收藏指南+MA其它最新配套包装+客版邮包盒(参考Amazon US翻单PO#4500192979)+WEEE_不带电池走货 _ 说明书欧 洲EN+30L_B版 11.验货时间不迟于2026/5/11. 注意：77858需将邮包盒尺寸图<(>&<)>重量图放进验货报告； Remark: 1.空白外箱（加印带Zuru字样的最新logo，除了邮包盒直接做外箱的产品） + SSCC LABEL一张, 无箱唛，MADE IN CHINA 外箱只印一正一侧。箱唛资料按照给定的 标准去做即可，无需发回我方再行审批(新标准将另行通知)。 (SSCC LABEL竖贴在外箱正面的正中间，贴一面即可,贴纸离外箱边距必须至少3.2CM。如竖贴无法满足要求，则横贴。如横贴也无法满足要求，则竖贴，遮到ZURU lo go无影响), SSCC贴纸由工厂直接跟勤得采购或者工厂自行采购，每一张SSCC Label都是唯一且有不同流水及条码，且需要检查条码是否能正常扫描，另外，此贴纸 印刷不可出现模糊，溢出及粘胶不牢易脱落等现象，如工厂不按此要求导致贴纸有任何问题产生的罚款将由工厂承担一切责任 ,<(>,<)> 此要求只适用Amazon UK/DE /FR/ES/IT,不适用Amazon GPE，Amazon GPE无SSCC label, 但是有对应箱唛，需印刷到外箱 。 2.出往UK的产品+包装务必打上UKCA logo ，否则客人会退货且当地会有罚款。 3.订单必须经过ZURU QC验货或者工厂自检通过后方可出货，不涉及第三方验货。 4.法国订单要求包装不使用矿物油，请按要求提供以下其中一份文件再出货 ，产品出到法国被相关部门抽检出现包装不符合此要求的，供应商需要为此承担责任， 故此请严格把关。 -油墨物质""""由1 ~ 7个芳香环组成的MOAH""""的包装检测报告，要求限值≤1.0%； -包装材料清单，包括包装油墨或物质的信息； -油墨制造商的证书； 5.每一批次出货只能有一个生产日期，不可多个生产日期混在同一批次出货；且零售包装上必须统一加上日期码；外箱对于日期码没有硬性规定； 6.涉及到相关款式会有闪粉的或者微塑料的，请统一默认出无闪粉或者不含微塑料版本； 7.邮包盒及外箱封箱必须是工字型封箱方式； 8.5 Surprise or Mini Brands涉及包装是2个及2个以上的球入PVC桶包装时，单个球上若有UPC#或者EAN#，请用空白贴纸覆盖住，贴纸尺寸自行测量能覆盖原条码即 可； 9. 无论是工厂自检还是ZURU验货，验货报告中必须有产品6面图(正面/背面/左面/右面/顶部/底部，不带包装); 10. 按空海运鉴定报告的要求，只要带锂电池出货，都需要加贴UN贴纸； 11. 所有出往GAS市场(德国/奥地利/瑞士)的电子产品身上需要加字唛，为ZURU FRANCE 地址，需跟包装上的地址一致 (如无电子产品，产品布标有此地址，或产品 太小无法增加可忽略此信息。如产品无法加字唛，需让对应跟单提供产品贴纸资料); 12. 所有出往GAS德国 (瑞士，奥地利)。水弹枪系列必须使用EN71版本（电子和非电子水弹枪系列都需要符合); 护目镜需打日期码, 格式跟ZURU标准格式一样; 枪 身上增加ZURU FRANCE公司名和地址。使用贴纸和辐射上去都可以。如果有位置，最好增加ZURU Represented by: (此最好翻译德语，如果位置不允许，那么就只增 加ZURU法国和地址)。使用最新的EN71版包装和说明书）. | X27: Luna Lin | Y27: 12.65 | Z27: =Y27*I27 -> 6337.65 | AB27: 77858-S003-MB-1 | AC27: 已入 | AL27: =I27 -> 501 | AM27: =I27 -> 501 | AO27: 29L | AQ27: =I27 -> 501
A28: 46106 | B28: WALMART INC. | C28: 美国 | D28: 4500198118 | E28: 0983717761 | F28: 4500198118-20 | G28: 77858-S002 | H28: 厨房套装 | I28: 500 | J28: 0 | K28: 2 | L28: =I28/K28 -> 250 | M28: 46153 | N28: 46149 | O28: 46156 | P28: OK | Q28: 46174 | R28: 是 | S28: 翻4500195615 | T28: 无 | U28: 4/8RFID贴纸 | W28: 日期码格式：ZURU DGYYMMDD CHINA(日期避开周末和法定节假日即可） 日期：按实际生产日期 Packaging Info: 77843SLB-S001 1. 包装要求： 77858-S002 1. 包装要求： 77858：MA 1L A版 playset +MA 5L A版收藏指南+MA 23L A版说明书+MA A版纸袋+MA 贴纸 每pcs产品要贴一张RFID贴纸，RFID贴纸由ZURU提供，贴纸位置要严格按照客人签板 77858-S002 1. 包装要求： 77858：MA 1L A版 playset +MA 5L A版收藏指南+MA 23L A版说明书+MA A版纸袋+MA 贴纸 每pcs产品要贴一张RFID贴纸，RFID贴纸由ZURU提供，贴纸位置要严格按照客人签板 2. 外箱印刷带条码的RFID箱唛：RFID紫色色带+WM Dept.图标+RFID图标+ITF-14条码，四面右下角印刷ZURU logo, ITFF条码只印刷在正唛一面，在加印的时候确保 条形码能扫描出来，外箱侧面任一角落加印："MADE IN CHINA" 字样； 3. 在产品上和包装上要有日期码、以及要有MADE IN CHINA和ZURU字样； 4. 产品如有扎带口要剪平，不能刮手。 5. 此单需要验货，请多备料 6. 此单以loose carton出货，2pcs/CTN | X28: Maggie Xie | Y28: 6.5485 | Z28: =I28*Y28 -> 3274.25 | AB28: 77858-S002 | AC28: 已入 | AI28: =I28 -> 500 | AM28: =I28 -> 500 | AQ28: =I28 -> 500
A29: 46106 | B29: WALMART INC. | C29: 美国 | D29: 4500198126 | E29: 0983717783 | F29: 4500198126-20 | G29: 77858-S002 | H29: 厨房套装 | I29: 500 | J29: 0 | K29: 2 | L29: =I29/K29 -> 250 | M29: 46153 | N29: 46149 | O29: 46156 | P29: OK | Q29: 46163 | R29: 是 | S29: 翻4500195615 | T29: 无 | U29: 4/8RFID贴纸 | W29: 日期码格式：ZURU DGYYMMDD CHINA(日期避开周末和法定节假日即可） 日期：按实际生产日期 Packaging Info: 77843SLB-S001 1. 包装要求： 77858-S002 1. 包装要求： 77858：MA 1L A版 playset +MA 5L A版收藏指南+MA 23L A版说明书+MA A版纸袋+MA 贴纸 每pcs产品要贴一张RFID贴纸，RFID贴纸由ZURU提供，贴纸位置要严格按照客人签板 77858-S002 1. 包装要求： 77858：MA 1L A版 playset +MA 5L A版收藏指南+MA 23L A版说明书+MA A版纸袋+MA 贴纸 每pcs产品要贴一张RFID贴纸，RFID贴纸由ZURU提供，贴纸位置要严格按照客人签板 2. 外箱印刷带条码的RFID箱唛：RFID紫色色带+WM Dept.图标+RFID图标+ITF-14条码，四面右下角印刷ZURU logo, ITFF条码只印刷在正唛一面，在加印的时候确保 条形码能扫描出来，外箱侧面任一角落加印："MADE IN CHINA" 字样； 3. 在产品上和包装上要有日期码、以及要有MADE IN CHINA和ZURU字样； 4. 产品如有扎带口要剪平，不能刮手。 5. 此单需要验货，请多备料 6. 此单以loose carton出货，2pcs/CTN | X29: Maggie Xie | Y29: 6.5485 | Z29: =I29*Y29 -> 3274.25 | AB29: 77858-S002 | AC29: 已入 | AI29: =I29 -> 500 | AM29: =I29 -> 500 | AQ29: =I29 -> 500
A30: 46095 | B30: TARGET AUSTRALIA PTY LTD | C30: 澳大利亚 | D30: 4500196881 | E30: 2599186 | F30: 4500196881-20 | G30: 77858-S001 | H30: 厨房套装 | I30: 1500 | J30: 0 | K30: 3 | L30: =I30/K30 -> 500 | M30: 46153 | N30: 46150 | P30: OK | Q30: 46155 | R30: 是 | S30: 46097 | T30: 有 | U30: 4/22外箱贴纸SSCC label | W30: 日期码格式：ZURU INC(BVI) 标准格式 日期：按实际生产日期 Packaging Info: 2. 77858：英文MA包装UPC版本（首选1L，无1L可选多语）+箱唛+ 外箱贴纸SSCC label； Remark: 1. 客人要求箱唛不可出现任何手写内容，重量与实际一致且不可手写; 2. 此单去澳大利亚，请按相应澳新标准生产; 3. 取消使用TARGET新版封箱胶封顶，外箱全部使用普通透明封箱胶纸(客版胶纸如还有库存，可先消耗库存)； 4. 外箱需要贴Target SSCC LABEL,客供PDF文档，工厂自行订购。请贴在正唛右下角（一箱一张，贴1面正唛右下角,封箱胶纸不能挡住贴纸内容。)；外箱贴纸距离 外箱边缘应在2cm以上。如果正唛无位置可以贴在侧唛； 5. SSCC LABEL要求：贴纸内容，条形码印刷不完整/不清晰或有划痕/缺失，贴纸脏污、破损、条形码折叠、翘起、重复或者丢失，以及封箱胶盖住贴纸任何位置的 ，客户都不能接受，如有发现以上异常，须返工重新贴； 6. 外箱材质为ZURU标准； 7. 产品和包装上要有tracking label信息：格式为Zuru标准格式（可以自行调整具体年月日生产日期,避开节假期日）； 8. SSCC Label 尺寸更新为：4x4 inch。 | X30: Christine Liao | Y30: 9.9259 | Z30: =I30*Y30 -> 14888.85 | AB30: 77858-S001 | AC30: 已入 | AI30: =I30 -> 1500 | AM30: =I30 -> 1500 | AQ30: =I30 -> 1500
A31: 46094 | B31: WALMART INC. | C31: 美国 | D31: 4500196792 | E31: 0980444054 | F31: 4500196792-10 | G31: 77858-S002 | H31: 厨房套装 | I31: 1216 | J31: 0 | K31: 2 | L31: =I31/K31 -> 608 | M31: 46153 | N31: 46150 | O31: 46156 | P31: OK | Q31: 46174 | R31: 是 | S31: 46094 | T31: 有 | U31: 3/24RFID贴纸+粉色艾利贴纸+MA 贴纸 | W31: 日期码格式：ZURU DGMMDD CHINA(日期避开周末和法定节假日即可） 日期：按实际生产日期 Packaging Info: 77858-S002 1. 包装要求： 77858：MA 1L A版 playset +MA 5L A版收藏指南+MA 23L A版说明书+MA A版纸袋+MA 贴纸 每pcs产品要贴一张RFID贴纸，RFID贴纸由ZURU提供，贴纸位置要严格按照客人签板 Remark: 77858-S002 1. 包装要求： 77858：MA 1L A版 playset +MA 5L A版收藏指南+MA 23L A版说明书+MA A版纸袋+MA 贴纸 每pcs产品要贴一张RFID贴纸，RFID贴纸由ZURU提供，贴纸位置要严格按照客人签板 2. 外箱印刷带条码的RFID箱唛：RFID紫色色带+WM Dept.图标+RFID图标+ITF-14条码+粉色艾利贴纸（不干胶打印），四面右下角印刷ZURU logo, ITFF条码只印刷在 正唛一面，在加印的时候确保条形码能扫描出来，1张粉红色贴纸贴在正唛对角线，外箱侧面任一角落加印："MADE IN CHINA" 字样； 3. 在产品上和包装上要有日期码、以及要有MADE IN CHINA和ZURU字样； 4. 产品如有扎带口要剪平，不能刮手。 5. 此单需要验货，请多备料 6. 此单以loose carton出货，2pcs/CTN | X31: Maggie Xie | Y31: 6.5485 | Z31: =I31*Y31 -> 7962.976 | AB31: 77858-S002 | AC31: 已入 | AI31: =I31 -> 1216 | AM31: =I31 -> 1216 | AQ31: =I31 -> 1216
A32: 46094 | B32: WALMART INC. | C32: 美国 | D32: 4500196792 | E32: 0980444062 | F32: 4500196792-20 | G32: 77858-S002 | H32: 厨房套装 | I32: 1264 | J32: 0 | K32: 2 | L32: =I32/K32 -> 632 | M32: 46153 | N32: 46150 | O32: 46156 | P32: OK | Q32: 46174 | R32: 是 | S32: 46094 | T32: 有 | U32: 3/24RFID贴纸+粉色艾利贴纸+MA 贴纸 | W32: 日期码格式：ZURU DGMMDD CHINA(日期避开周末和法定节假日即可） 日期：按实际生产日期 Packaging Info: 77858-S002 1. 包装要求： 77858：MA 1L A版 playset +MA 5L A版收藏指南+MA 23L A版说明书+MA A版纸袋+MA 贴纸 每pcs产品要贴一张RFID贴纸，RFID贴纸由ZURU提供，贴纸位置要严格按照客人签板 Remark: 77858-S002 1. 包装要求： 77858：MA 1L A版 playset +MA 5L A版收藏指南+MA 23L A版说明书+MA A版纸袋+MA 贴纸 每pcs产品要贴一张RFID贴纸，RFID贴纸由ZURU提供，贴纸位置要严格按照客人签板 2. 外箱印刷带条码的RFID箱唛：RFID紫色色带+WM Dept.图标+RFID图标+ITF-14条码+粉色艾利贴纸（不干胶打印），四面右下角印刷ZURU logo, ITFF条码只印刷在 正唛一面，在加印的时候确保条形码能扫描出来，1张粉红色贴纸贴在正唛对角线，外箱侧面任一角落加印："MADE IN CHINA" 字样； 3. 在产品上和包装上要有日期码、以及要有MADE IN CHINA和ZURU字样； 4. 产品如有扎带口要剪平，不能刮手。 5. 此单需要验货，请多备料 6. 此单以loose carton出货，2pcs/CTN | X32: Maggie Xie | Y32: 6.5485 | Z32: =I32*Y32 -> 8277.304 | AB32: 77858-S002 | AC32: 已入 | AI32: =I32 -> 1264 | AM32: =I32 -> 1264 | AQ32: =I32 -> 1264
A33: 46108 | B33: ASIA GOAL LIMITED | C33: 香港 | D33: 4500198855 | E33: AG250415-HK | F33: 4500198855-10 | G33: 77858-S001 | H33: 厨房套装 | I33: 120 | J33: 0 | K33: 3 | L33: =I33/K33 -> 40 | M33: 46154 | N33: 46153 | P33: OK | Q33: 46164 | R33: 是 | S33: 46108 | T33: 无 | U33: 4/10 HK客供警语贴纸（2 张HK客供警语贴纸，1张贴彩盒背面，1张贴说明书，贴纸内容不一样,详情参考HK客供警语贴纸位置图） | W33: 日期码格式：ZURU INC(BVI) 标准格式 日期：按实际生产日期 Packaging Info: 此单出HK, 77858: MA PKG , 优先1L+ HK客供警语贴纸（2 张HK客供警语贴纸，1张贴彩盒背面，1张贴说明书，贴纸内容不一样,详情参考HK客供警语贴纸位置图） Remark: | X33: Chelsea Luo | Y33: 9.9425 | Z33: =Y33*I33 -> 1193.1 | AB33: 77858-S001 | AC33: 已入 | AI33: =I33 -> 120 | AM33: =I33 -> 120 | AQ33: =I33 -> 120
A34: 46108 | B34: ASIA GOAL LIMITED TAIWAN BRANCH (H. | C34: 台湾 | D34: 4500198860 | E34: AG250416-TW | F34: 4500198860-10 | G34: 77858-S001 | H34: 厨房套装 | I34: 120 | J34: 0 | K34: 3 | L34: =I34/K34 -> 40 | M34: 46154 | N34: 46153 | P34: OK | Q34: 46172 | R34: 是 | S34: 46108 | T34: 无 | U34: 4/21警语贴纸 | W34: 日期码格式：ZURU INC(BVI) 标准格式 日期：按实际生产日期 Packaging Info: 此单出TW 77858: MA PKG , 优先1L+ 1张警语贴纸 Remark: | X34: Chelsea Luo | Y34: 10.2316 | Z34: =Y34*I34 -> 1227.792 | AB34: 77858-S001 | AC34: 已入 | AI34: =I34 -> 120 | AM34: =I34 -> 120 | AQ34: =I34 -> 120
A35: 46106 | B35: WALMART INC. | C35: 美国 | D35: 4500198129 | E35: 0983717723 | F35: 4500198129-20 | G35: 77858-S002 | H35: 厨房套装 | I35: 500 | J35: 0 | K35: 2 | L35: =I35/K35 -> 250 | M35: 46156 | N35: 46154 | O35: 5/18自检 | P35: OK | Q35: 46179 | R35: 是 | S35: 翻4500195615 | T35: 无 | U35: 4/8RFID贴纸 | W35: 日期码格式：ZURU DGYYMMDD CHINA(日期避开周末和法定节假日即可） 日期：按实际生产日期 77858-S002 1. 包装要求： 77858：MA 1L A版 playset +MA 5L A版收藏指南+MA 23L A版说明书+MA A版纸袋+MA 贴纸 每pcs产品要贴一张RFID贴纸，RFID贴纸由ZURU提供，贴纸位置要严格按照客人签板 77858-S002 1. 包装要求： 77858：MA 1L A版 playset +MA 5L A版收藏指南+MA 23L A版说明书+MA A版纸袋+MA 贴纸 每pcs产品要贴一张RFID贴纸，RFID贴纸由ZURU提供，贴纸位置要严格按照客人签板 2. 外箱印刷带条码的RFID箱唛：RFID紫色色带+WM Dept.图标+RFID图标+ITF-14条码，四面右下角印刷ZURU logo, ITFF条码只印刷在正唛一面，在加印的时候确保 条形码能扫描出来，外箱侧面任一角落加印："MADE IN CHINA" 字样； 3. 在产品上和包装上要有日期码、以及要有MADE IN CHINA和ZURU字样； 4. 产品如有扎带口要剪平，不能刮手。 5. 此单需要验货，请多备料 6. 此单以loose carton出货，2pcs/CTN | X35: Maggie Xie | Y35: 6.5485 | Z35: =I35*Y35 -> 3274.25 | AB35: 77858-S002 | AC35: 已入 | AI35: =I35 -> 500 | AM35: =I35 -> 500 | AQ35: =I35 -> 500
A36: 46101 | B36: HARVEY WHOLESALE LTD | C36: 新西兰 | D36: 4500197606 | E36: 3108 | F36: 4500197606-10 | G36: 77858-S001 | H36: 厨房套装 | I36: 168 | J36: 0 | K36: 3 | L36: =I36/K36 -> 56 | M36: 46156 | N36: 46154 | P36: OK | Q36: 46165 | R36: 是 | S36: 46101 | T36: 无 | U36: 无 | W36: 日期码格式：ZURU INC(BVI) 标准格式 日期：按实际生产日期 Packaging Info: MA UPC 包装（优先1L，3L/5L也可） Remark: 3PCS AA BATTERIES(NOT INCLUDED) | X36: Ivy Li | Y36: 10.2316 | Z36: =I36*Y36 -> 1718.9088 | AB36: 77858-S001 | AC36: 已入 | AI36: =I36 -> 168 | AM36: =I36 -> 168 | AQ36: =I36 -> 168
A37: 46094 | B37: WALMART INC. | C37: 美国 | D37: 4500196793 | E37: 0980444051 | F37: 4500196793-10 | G37: 77858-S002 | H37: 厨房套装 | I37: 960 | J37: 0 | K37: 2 | L37: =I37/K37 -> 480 | M37: 46156 | N37: 46154 | O37: 5/18自检 | P37: OK | Q37: 46165 | R37: 是 | S37: 46094 | T37: 有 | U37: 3/24RFID贴纸+粉色艾利贴纸+MA 贴纸 | W37: 日期码格式：ZURU DGMMDD CHINA(日期避开周末和法定节假日即可） 日期：按实际生产日期 Packaging Info: 77858-S002 1. 包装要求： 77858：MA 1L A版 playset +MA 5L A版收藏指南+MA 23L A版说明书+MA A版纸袋+MA 贴纸 每pcs产品要贴一张RFID贴纸，RFID贴纸由ZURU提供，贴纸位置要严格按照客人签板 Remark: 77858-S002 1. 包装要求： 77858：MA 1L A版 playset +MA 5L A版收藏指南+MA 23L A版说明书+MA A版纸袋+MA 贴纸 每pcs产品要贴一张RFID贴纸，RFID贴纸由ZURU提供，贴纸位置要严格按照客人签板 2. 外箱印刷带条码的RFID箱唛：RFID紫色色带+WM Dept.图标+RFID图标+ITF-14条码+粉色艾利贴纸（不干胶打印），四面右下角印刷ZURU logo, ITFF条码只印刷在 正唛一面，在加印的时候确保条形码能扫描出来，1张粉红色贴纸贴在正唛对角线，外箱侧面任一角落加印："MADE IN CHINA" 字样； 3. 在产品上和包装上要有日期码、以及要有MADE IN CHINA和ZURU字样； 4. 产品如有扎带口要剪平，不能刮手。 5. 此单需要验货，请多备料 6. 此单以loose carton出货，2pcs/CTN | X37: Maggie Xie | Y37: 6.5485 | Z37: =I37*Y37 -> 6286.56 | AB37: 77858-S002 | AC37: 已入 | AI37: =I37 -> 960 | AM37: =I37 -> 960 | AQ37: =I37 -> 960
A38: 46112 | B38: AMAZON UK | C38: 英国 | D38: 4500198642 | E38: 3UI85QUZ | F38: 4500198642-150 | G38: 77858-S003 -MB | H38: 厨房套装 | I38: 978 | J38: 0 | K38: 3 | L38: =I38/K38 -> 326 | M38: 46156 | N38: 46154 | P38: OK | Q38: 46158 | S38: 空白外箱（加印带Zuru字样的最新logo，除了邮包盒直接做外箱的产品） | T38: 有 | U38: 4/24外箱贴纸SSCC label | V38: 客版邮包盒(参考翻单PO#4500198640) | W38: 日期码格式：ZURU INC(BVI) 标准格式 日期：按实际生产日期 Packaging Info: Amazon UK: 5TKIJIXX/3O77XWME/7N1D8FUG/7H6BABTK/5Z2UXPOL/3UI85QUZ Amazon UK(77858/77876/77878/157124/157142) 1. 77858: 1pc 77858 playset into mailbox, 3mailboxes/ctn; Including magnets; 3PCS AA BATTERIES(NOT INCLUDED); MA 3L(23L warning EAN)A 透明PVC窗 彩盒+MA 23L warning A 电池黑白说明书+MA 5L A收藏指南+MA其它最新配套包装+客版邮包盒(Amazon US PO#4500192979)+WEEE_不带电池走货 _ 说明书欧洲EN+29L _C版 6.验货时间不迟于2026/5/15. 注意：77858需将邮包盒尺寸图片<(>&<)>重量图片放进验货报告。 Remark: 1.空白外箱（加印带Zuru字样的最新logo，除了邮包盒直接做外箱的产品） + SSCC LABEL一张, 无箱唛，MADE IN CHINA 外箱只印一正一侧。箱唛资料按照给定的 标准去做即可，无需发回我方再行审批(新标准将另行通知)。 (SSCC LABEL竖贴在外箱正面的正中间，贴一面即可,贴纸离外箱边距必须至少3.2CM。如竖贴无法满足要求，则横贴。如横贴也无法满足要求，则竖贴，遮到ZURU lo go无影响), SSCC贴纸由工厂直接跟勤得采购或者工厂自行采购，每一张SSCC Label都是唯一且有不同流水及条码，且需要检查条码是否能正常扫描，另外，此贴纸 印刷不可出现模糊，溢出及粘胶不牢易脱落等现象，如工厂不按此要求导致贴纸有任何问题产生的罚款将由工厂承担一切责任 ,<(>,<)> 此要求只适用Amazon UK/DE /FR/ES/IT,不适用Amazon GPE，Amazon GPE无SSCC label, 但是有对应箱唛，需印刷到外箱 。 2.出往UK的产品+包装务必打上UKCA logo ，否则客人会退货且当地会有罚款。 3.订单必须经过ZURU QC验货或者工厂自检通过后方可出货，不涉及第三方验货。 4.法国订单要求包装不使用矿物油，请按要求提供以下其中一份文件再出货 ，产品出到法国被相关部门抽检出现包装不符合此要求的，供应商需要为此承担责任， 故此请严格把关。 -油墨物质""""由1 ~ 7个芳香环组成的MOAH""""的包装检测报告，要求限值≤1.0%； -包装材料清单，包括包装油墨或物质的信息； -油墨制造商的证书； 5.每一批次出货只能有一个生产日期，不可多个生产日期混在同一批次出货；且零售包装上必须统一加上日期码；外箱对于日期码没有硬性规定； 6.涉及到相关款式会有闪粉的或者微塑料的，请统一默认出无闪粉或者不含微塑料版本； 7.邮包盒及外箱封箱必须是工字型封箱方式； 8.5 Surprise or Mini Brands涉及包装是2个及2个以上的球入PVC桶包装时，单个球上若有UPC#或者EAN#，请用空白贴纸覆盖住，贴纸尺寸自行测量能覆盖原条码即 可； 9. 无论是工厂自检还是ZURU验货，验货报告中必须有产品6面图(正面/背面/左面/右面/顶部/底部，不带包装); 10. 按空海运鉴定报告的要求，只要带锂电池出货，都需要加贴UN贴纸； 11. 所有出往GAS市场(德国/奥地利/瑞士)的电子产品身上需要加字唛，为ZURU FRANCE 地址，需跟包装上的地址一致 (如无电子产品，产品布标有此地址，或产品 太小无法增加可忽略此信息。如产品无法加字唛，需让对应跟单提供产品贴纸资料); 12. 所有出往GAS德国 (瑞士，奥地利)。水弹枪系列必须使用EN71版本（电子和非电子水弹枪系列都需要符合); 护目镜需打日期码, 格式跟ZURU标准格式一样; 枪 身上增加ZURU FRANCE公司名和地址。使用贴纸和辐射上 | X38: Luna Lin | Y38: 12.65 | Z38: =Y38*I38 -> 12371.7 | AB38: 77858-S003-MB-1 | AC38: 已入 | AL38: =I38 -> 978 | AM38: =I38 -> 978 | AO38: 29L | AQ38: =I38 -> 978
A39: 46094 | B39: WALMART INC. | C39: 美国 | D39: 4500196793 | E39: 0980444049 | F39: 4500196793-20 | G39: 77858-S002 | H39: 厨房套装 | I39: 1356 | J39: 0 | K39: 2 | L39: =I39/K39 -> 678 | M39: 46156 | N39: 46154 | O39: 5/18自检 | P39: OK | Q39: 46165 | R39: 是 | S39: 46094 | T39: 有 | U39: 3/24RFID贴纸+粉色艾利贴纸+MA 贴纸 | W39: 日期码格式：ZURU DGMMDD CHINA(日期避开周末和法定节假日即可） 日期：按实际生产日期 Packaging Info: 77858-S002 1. 包装要求： 77858：MA 1L A版 playset +MA 5L A版收藏指南+MA 23L A版说明书+MA A版纸袋+MA 贴纸 每pcs产品要贴一张RFID贴纸，RFID贴纸由ZURU提供，贴纸位置要严格按照客人签板 Remark: 77858-S002 1. 包装要求： 77858：MA 1L A版 playset +MA 5L A版收藏指南+MA 23L A版说明书+MA A版纸袋+MA 贴纸 每pcs产品要贴一张RFID贴纸，RFID贴纸由ZURU提供，贴纸位置要严格按照客人签板 2. 外箱印刷带条码的RFID箱唛：RFID紫色色带+WM Dept.图标+RFID图标+ITF-14条码+粉色艾利贴纸（不干胶打印），四面右下角印刷ZURU logo, ITFF条码只印刷在 正唛一面，在加印的时候确保条形码能扫描出来，1张粉红色贴纸贴在正唛对角线，外箱侧面任一角落加印："MADE IN CHINA" 字样； 3. 在产品上和包装上要有日期码、以及要有MADE IN CHINA和ZURU字样； 4. 产品如有扎带口要剪平，不能刮手。 5. 此单需要验货，请多备料 6. 此单以loose carton出货，2pcs/CTN | X39: Maggie Xie | Y39: 6.5485 | Z39: =I39*Y39 -> 8879.766 | AB39: 77858-S002 | AC39: 已入 | AI39: =I39 -> 1356 | AM39: =I39 -> 1356 | AQ39: =I39 -> 1356
A40: 46107 | B40: CONTINENTE S.A. | C40: 哥伦比亚 | D40: 4500198705 | F40: 4500198705-90 | G40: 77858-S001 | H40: 厨房套装 | I40: 801 | J40: 0 | K40: 3 | L40: =I40/K40 -> 267 | M40: 46157 | N40: 46155 | P40: OK | Q40: 46187 | R40: 是 | S40: 46127 | T40: 无 | U40: 4/29进口商贴纸+UPC贴纸 | W40: 日期码格式：DG20260515 日期： Packaging Info: 7132:MA 多语包装+ UPC贴纸+进口商贴纸+箱唛 15789UQ1、15782UQ1:MA 多语包装+进口商贴纸+箱唛 15750、15788、15746:MA 多语包装+进口商贴纸+箱唛（进口商贴纸和mother UPC贴纸合并为一张） 其余item：MA 多语包装+进口商贴纸+UPC贴纸+箱唛 Remark: 1.包装/产品/外箱/进口商贴纸 指定日期码为DG20260515 .所有item包装上的条码必须是UPC，如果已将进口商贴纸和UPC条码合并到一张，则不需再订购UPC贴纸，仅订购一张进口商贴纸即可。 | X40: Ava Liang | Y40: 10.2316 | Z40: =I40*Y40 -> 8195.5116 | AB40: 77858-S001-1 | AC40: 已入 | AL40: =I40 -> 801 | AM40: =I40 -> 801 | AQ40: =I40 -> 801
A41: 46105 | B41: ASIA GOAL LIMITED | C41: 香港 | D41: 4500198401 | E41: AG250501-HK | F41: 4500198401-10 | G41: 77858-S001 | H41: 厨房套装 | I41: 120 | J41: 0 | K41: 3 | L41: =I41/K41 -> 40 | M41: 46157 | N41: 46155 | P41: OK | Q41: 46164 | R41: 是 | S41: 46105 | T41: 无 | U41: 4/3 HK客供警语贴纸（2 张HK客供警语贴纸，1张贴彩盒背面，1张贴说明书，贴纸内容不一样） | W41: 日期码格式：ZURU INC(BVI) 标准格式 日期：按实际生产日期 Packaging Info: 此单出HK, 77858: MA PKG , 优先1L+ HK客供警语贴纸（2 张HK客供警语贴纸，1张贴彩盒背面，1张贴说明书，贴纸内容不一样） | X41: Chelsea Luo | Y41: 9.9425 | Z41: =I41*Y41 -> 1193.1 | AB41: 77858-S001 | AC41: 已入 | AI41: =I41 -> 120 | AM41: =I41 -> 120 | AQ41: =I41 -> 120
A42: 46128 | B42: ROYAL REGENT PRODUCTS(ASIA) LIMITED | C42: 乌克兰 | D42: MPO10299 | E42: 4500202224- 00010-20260526 | F42: MPO10299-10 | G42: 77858 | H42: 厨房套装 | I42: 300 | J42: 0 | K42: 3 | L42: =I42/K42 -> 100 | M42: 46157 | N42: 46155 | O42: 送超邦工厂组装混装展架 | P42: OK | Q42: =SUM(Q6:Q8) -> 92258 | U42: 进⼝商贴纸翻4500201931+3张乌克兰警告语贴纸覆盖零售包装上的俄罗斯语⾔（翻4500201931） | V42: MA 收藏指南/客版不含俄罗斯 语⾔的电池说明书（含不带电池⾛货WEEE说明书内容）（翻4500201931） | W42: Remark: 1.77858：A 版3L MA EAN 包装+进⼝商贴纸（翻4500201931）+3张乌克兰警告语贴纸覆盖零售包装上的俄罗斯语⾔（翻4500201931）；A 版5L MA 收藏指南/客版不含俄罗斯 语⾔的电池说明书（含不带电池⾛货WEEE说明书内容）（翻4500201931） 2.ZURU QC 会在组装⼚安排最终验货，请准备好备品，验货后需要⻢上安排补货，请务必按时送货到超邦⼚ 3.订单的所有测试与样品要求以跟单的要求为准，且为了避免QC验货拆货来不及补货，请准备适量的贴纸和产品备品。此订单数量只作为⼤货⽣产，不包含样板与备品。 4.请贵司确保交货数量准确，与收货⽅交收清楚，如收货⽅提出任何异常，请⽴即安排处理解决。 5.关于混装展⽰架，各⼯⼚交⼦件到最终⺟件⼯⼚时，务必要 "带卡板出+围好围膜"。 如果没按要求的，请各⼯⼚⾃⾏安排⼈⼿卸货。 | X42: Snowy Wu | Y42: 9.7428 | Z42: =I42*Y42 -> 2922.84 | AB42: 77858-S001-1 | AC42: 已入 | AL42: =I42 -> 300 | AM42: =I42 -> 300 | AQ42: =I42 -> 300
A43: 46094 | B43: SIDJ JOUECLUB | C43: 法国 | D43: 4500196797 | E43: 26000056 | F43: 4500196797-20 | G43: 77858-S001 | H43: 厨房套装 | I43: 600 | J43: 0 | K43: 3 | L43: =I43/K43 -> 200 | M43: 46157 | N43: 46155 | O43: 请准备每款5pcs包装备品，和大货一起出（以备到客户仓库后有破损的包装） | P43: OK | Q43: 46188 | R43: 自行比对 | S43: 46113 | T43: 无 | U43: 4/1额外贴纸(含AR警语+客人信息+意大利回收标+CMIM logo)+MA贴纸 | V43: 4/15 1张额外的客版黑白说明书(含AR电池 说明+5LWEEE 不带电池出货) | W43: 日期码格式：2042026 日期： Packaging Info: 77858:MA23L EAN彩盒+额外贴纸(含AR警语+客人信息+CMIM logo)+MA 袋子+MA贴纸+ML 5L收藏指南+MA23L说明书+1张额外的客版黑白说明书(含AR电池 说明+5LWEEE 不带电池出货) Remark: 1.此票无需客户验货，请多备料1套左右 2.请准备每款5pcs包装备品，和大货一起出（以备到客户仓库后有破损的包装） 3.所有出口法国的产品, 法规规定禁止在包装和共公众用的印刷品中使用矿物油中含有的物质, 包装印刷油墨中含有的MOAH/MOSH的质量浓度不能超过1%, 否则出货 到法国被抽检出现问题, 供应商需要对此负责; 4.出口法国请确保产品符合EU微塑料法规，包装需显示法国回收logo; | X43: Ula Zhao | Y43: 10.2316 | Z43: =I43*Y43 -> 6138.96 | AB43: 77858-S001-1 | AC43: 已入 | AL43: =I43 -> 600 | AM43: =I43 -> 600 | AO43: 客版黑白说明书(含AR电池 说明+5LWEEE 不带电池出货) | AQ43: =I43 -> 600
A44: 46122 | B44: ROYAL REGENT PRODUCTS(ASIA) LIMITED | C44: 法国 | D44: MPO10280 | E44: 4500200738- 00010- 20260525 | F44: MPO10280-10 | G44: 77858 | H44: 厨房套装 | I44: 576 | J44: 0 | K44: 3 | L44: =I44/K44 -> 192 | M44: 46161 | N44: 46160 | O44: 送超邦工厂组装混装展架 | P44: OK | W44: Remark: 1.包装：77858(MEC417): MA 3L+23 警语 EAN (4894680058729) 彩盒，MA 5L收藏指南，MMA 内袋， MA贴纸，MA 23L ⿊⽩说明书+MA最新版WEEE_不带电池⾛货 _ 说明书 欧洲EN+ 2. 订单的所有测试与样品要求以跟单的要求为准，且为了避免QC验货拆货来不及补货，请准备适量的贴纸和产品备品。此订单数量只作为⼤货⽣产，不包含样板与备品。 3.请贵司确保交货数量准确，与收货⽅交收清楚，如收货⽅提出任何异常，请⽴即安排处理解决。 4.关于混装展⽰架，各⼯⼚交⼦件到最终⺟件⼯⼚时，务必要 "带卡板出+围好围膜"。 如果没按要求的，请各⼯⼚⾃⾏安排⼈⼿卸货。Remark: 1.包装：77858(MEC417): MA 3L+23 警语 EAN (4894680058729) 彩盒，MA 5L收藏指南，MMA 内袋， MA贴纸，MA 23L ⿊⽩说明书+MA最新版WEEE_不带电池⾛货 _ 说明书 欧洲EN+ 2. 订单的所有测试与样品要求以跟单的要求为准，且为了避免QC验货拆货来不及补货，请准备适量的贴纸和产品备品。此订单数量只作为⼤货⽣产，不包含样板与备品。 3.请贵司确保交货数量准确，与收货⽅交收清楚，如收货⽅提出任何异常，请⽴即安排处理解决。 4.关于混装展⽰架，各⼯⼚交⼦件到最终⺟件⼯⼚时，务必要 "带卡板出+围好围膜"。 如果没按要求的，请各⼯⼚⾃⾏安排⼈⼿卸货。Remark: 1.包装：77858(MEC417): MA 3L+23 警语 EAN (4894680058729) 彩盒，MA 5L收藏指南，MMA 内袋， MA贴纸，MA 23L ⿊⽩说明书+MA最新版WEEE_不带电池⾛货 _ 说明书 欧洲EN+ 2. 订单的所有测试与样品要求以跟单的要求为准，且为了避免QC验货拆货来不及补货，请准备适量的贴纸和产品备品。此订单数量只作为⼤货⽣产，不包含样板与备品。 3.请贵司确保交货数量准确，与收货⽅交收清楚，如收货⽅提出任何异常，请⽴即安排处理解决。 4.关于混装展⽰架，各⼯⼚交⼦件到最终⺟件⼯⼚时，务必要 "带卡板出+围好围膜"。 如果没按要求的，请各⼯⼚⾃⾏安排⼈⼿卸货。Remark: 1.包装：77858(MEC417): MA 3L+23 警语 EAN (4894680058729) 彩盒，MA 5L收藏指南，MMA 内袋， MA贴纸，MA 23L ⿊⽩说明书+MA最新版WEEE_不带电池⾛货 _ 说明书 欧洲EN+ 2. 订单的所有测试与样品要求以跟单的要求为准，且为了避免QC验货拆货来不及补货，请准备适量的贴纸和产品备品。此订单数量只作为⼤货⽣产，不包含样板与备品。 3.请贵司确保交货数量准确，与收货⽅交收清楚，如收货⽅提出任何异常，请⽴即安排处理解决。 4.关于混装展⽰架，各⼯⼚交⼦件到最终⺟件⼯⼚时，务必要 "带卡板出+围好围膜"。 如果没按要求的，请各⼯⼚⾃⾏安排⼈⼿卸货。Remark: 1.包装：77858(MEC417): MA 3L+23 警语 EAN (4894680058729) 彩盒，MA 5L收藏指南，MMA 内袋， MA贴纸，MA 23L ⿊⽩说明书+MA最新版WEEE_不带电池⾛货 _ 说明书 欧洲EN+ 2. 订单的所有测试与样品要求以跟单的要求为准，且为了避免QC验货拆货来不及补货，请准备适量的贴纸和产品备品。此订单数量只作为⼤货⽣产，不包含样板与备品。 3.请贵司确保交货数量准确，与收货⽅交收清楚，如收货⽅提出任何异常，请⽴即安排处理解决。 4.关于混装展⽰架，各⼯⼚交⼦件到最终⺟件⼯⼚时，务必要 "带卡板出+围好围膜"。 如果没按要求的，请各⼯⼚⾃⾏安排⼈⼿卸货。Remark: 1.包装：77858(MEC417): MA 3L+23 警语 EAN (4894680058729) 彩盒，MA 5L收藏指南，MMA 内袋， MA贴纸，MA 23L ⿊⽩说明书+MA最新版WEEE_不带电池⾛货 _ 说明书 欧洲EN+ 2. 订单的所有测试与样品要求以跟单的要求为准，且为了避免QC验货拆货来不及补货，请准备适量的贴纸和产品备品。此订单数量只作为⼤货⽣产，不包含样板与备品。 3.请贵司确保交货数量准确，与收货⽅交收清楚，如收货⽅提出任何异常，请⽴即安排处理解决。 4.关于混装展⽰架，各⼯⼚交⼦件到最终⺟件⼯⼚时，务必要 "带卡板出+围好围膜"。 如果没按要求的，请各⼯⼚⾃⾏安排⼈⼿卸货。Remark: 1.包装：77858(MEC417): MA 3L+23 警语 EAN (4894680058729) 彩盒，MA 5L收藏指南，MMA 内袋， MA贴纸，MA 23L ⿊⽩说明书+MA最新版WEEE_不带电池⾛货 _ 说明书 欧洲EN+ 2. 订单的所有测试与样品要求以跟单的要求为准，且为了避免QC验货拆货来不及补货，请准备适量的贴纸和产品备品。此订单数量只作为⼤货⽣产，不包含样板与备品。 3.请贵司确保交货数量准确，与收货⽅交收清楚，如收货⽅提出任何异常，请⽴即安排处理解决。 4.关于混装展⽰架，各⼯⼚交⼦件到最终⺟件⼯⼚时，务必要 "带卡板出+围好围膜"。 如果没按要求的，请各⼯⼚⾃⾏安排⼈⼿卸货。Remark: 1.包装：77858(MEC417): MA 3L+23 警语 EAN (4894680058729) 彩盒，MA 5L收藏指南，MMA 内袋， MA贴纸，MA 23L ⿊⽩说明书+MA最新版WEEE_不带电池⾛货 _ 说明书 欧洲EN+ 2. 订单的所有测试与样品要求以跟单的要求为准，且为了避免QC验货拆货来不及补货，请准备适量的贴纸和产品备品。此订单数量只作为⼤货⽣产，不包含样板与备品。 3.请贵司确保交货数量准确，与收货⽅交收清楚，如收货⽅提出任何异常，请⽴即安排处理解决。 4.关于混装展⽰架，各⼯⼚交⼦件到最终⺟件⼯⼚时，务必要 "带卡板出+围好围膜"。 如果没按要求的，请各⼯⼚⾃⾏安排⼈⼿卸货。Remark: 1.包装：77858(MEC417): MA 3L+23 警语 EAN (4894680058729) 彩盒，MA 5L收藏指南，MMA 内袋， MA贴纸，MA 23L ⿊⽩说明书+MA最新版WEEE_不带电池⾛货 _ 说明书 欧洲EN+ 2. 订单的所有测试与样品要求以跟单的要求为准，且为了避免QC验货拆货来不及补货，请准备适量的贴纸和产品备品。此订单数量只作为⼤货⽣产，不包含样板与备品。 3.请贵司确保交货数量准确，与收货⽅交收清楚，如收货⽅提出任何异常，请⽴即安排处理解决。 4.关于混装展⽰架，各⼯⼚交⼦件到最终⺟件⼯⼚时，务必要 "带卡板出+围好围膜"。 如果没按要求的，请各⼯⼚⾃⾏安排⼈⼿卸货。Remark: 1.包装：77858(MEC417): MA 3L+23 警语 EAN (4894680058729) 彩盒，MA 5L收藏指南，MMA 内袋， MA贴纸，MA 23L ⿊⽩说明书+MA最新版WEEE_不带电池⾛货 _ 说明书 欧洲EN+ 2. 订单的所有测试与样品要求以跟单的要求为准，且为了避免QC验货拆货来不及补货，请准备适量的贴纸和产品备品。此订单数量只作为⼤货⽣产，不包含样板与备品。 3.请贵司确保交货数量准确，与收货⽅交收清楚，如收货⽅提出任何异常，请⽴即安排处理解决。 4.关于混装展⽰架，各⼯⼚交⼦件到最终⺟件⼯⼚时，务必要 "带卡板出+围好围膜"。 如果没按要求的，请各⼯⼚⾃⾏安排⼈⼿卸货。Remark: 1.包装：77858(MEC417): MA 3L+23 警语 EAN (4894680058729) 彩盒，MA 5L收藏指南，MMA 内袋， MA贴纸，MA 23L ⿊⽩说明书+MA最新版WEEE_不带电池⾛货 _ 说明书 欧洲EN+ 2. 订单的所有测试与样品要求以跟单的要求为准，且为了避免QC验货拆货来不及补货，请准备适量的贴纸和产品备品。此订单数量只作为⼤货⽣产，不包含样板与备品。 3.请贵司确保交货数量准确，与收货⽅交收清楚，如收货⽅提出任何异常，请⽴即安排处理解决。 4.关于混装展⽰架，各⼯⼚交⼦件到最终⺟件⼯⼚时，务必要 "带卡板出+围好围膜"。 如果没按要求的，请各⼯⼚⾃⾏安排⼈⼿卸货。Remark: 1.包装：77858(MEC417): MA 3L+23 警语 EAN (4894680058729) 彩盒，MA 5L收藏指南，MMA 内袋， MA贴纸，MA 23L ⿊⽩说明书+MA最新版WEEE_不带电池⾛货 _ 说明书 欧洲EN+ 2. 订单的所有测试与样品要求以跟单的要求为准，且为了避免QC验货拆货来不及补货，请准备适量的贴纸和产品备品。此订单数量只作为⼤货⽣产，不包含样板与备品。 3.请贵司确保交货数量准确，与收货⽅交收清楚，如收货⽅提出任何异常，请⽴即安排处理解决。 4.关于混装展⽰架，各⼯⼚交⼦件到最终⺟件⼯⼚时，务必要 "带卡板出+围好围膜"。 如果没按要求的，请各⼯⼚⾃⾏安排⼈⼿卸货。 | X44: Amber Zhang/Kico Zang | Y44: 9.7428 | Z44: =G44*Y44 -> 758554.92 | AB44: 77858-S001-1 | AC44: 已入 | AL44: =I44 -> 576 | AM44: =I44 -> 576 | AO44: 23L | AQ44: =I44 -> 576
A45: 46134 | D45: ZMPO260437 | F45: ZMPO260437-20 | G45: 77858-S001 | H45: 厨房套装 | I45: 222 | J45: 0 | K45: 3 | L45: =I45/K45 -> 74 | M45: 46162 | N45: 46158 | P45: OK | S45: 46134 | W45: Remark；大货版本/大货标准箱装箱/箱唛请参照邮件附件；备注： 收到样品订单后尽快安排 ，注意样板品质质量要求要高于大货品质要求 ，送货时必须要附带送货单(没有送货单和QC检验合格报告的仓库一律拒绝收货)，请知悉，谢谢！ | X45: Angus | AB45: 77858-S001 | AC45: 已入 | AI45: =I45 -> 222 | AM45: =I45 -> 222 | AQ45: =I45 -> 222
A46: 46114 | B46: NUEVOS ALMACENES, S.A. | C46: 危地马拉 | D46: 4500199843 | E46: 4504719305 | F46: 4500199843-20 | G46: 77858-S001 | H46: 厨房套装 | I46: 360 | J46: 0 | K46: 3 | L46: =I46/K46 -> 120 | M46: 46162 | N46: 46160 | P46: OK | Q46: 46166 | R46: 是 | S46: 46127 | T46: 无 | U46: 4/25 UPC贴纸 | W46: 日期码格式：ZURU INC(BVI) 标准格式 日期： Packaging Info: MA 多语包装+UPC贴纸+箱唛，无客户贴纸 Remark: 订单需提交自检报告，客户审核通过才可以出货。 外箱上的箱唛资料显示客户指定日期30-MAY-2026,产品/包装/外箱可以按ZURU 标准日期码打，也可以跟回外箱日期码，工厂自行选择,两者均可接受 | X46: Ava Liang | Y46: 10.2316 | Z46: =I46*Y46 -> 3683.376 | AB46: 77858-S001-1 | AC46: 已入 | AL46: =I46 -> 360 | AM46: =I46 -> 360 | AQ46: =I46 -> 360
A47: 46106 | B47: WALMART INC. | C47: 美国 | D47: 4500198130 | E47: 0983717820 | F47: 4500198130-20 | G47: 77858-S002 | H47: 厨房套装 | I47: 500 | J47: 0 | K47: 2 | L47: =I47/K47 -> 250 | M47: 46162 | N47: 46160 | O47: 46164 | P47: OK | R47: 是 | S47: 翻4500195615 | T47: 无 | U47: 4/8RFID贴纸 | W47: 日期码格式：ZURU DGYYMMDD CHINA(日期避开周末和法定节假日即可） 日期：按实际生产日期 77858-S002 1. 包装要求： 77858：MA 1L A版 playset +MA 5L A版收藏指南+MA 23L A版说明书+MA A版纸袋+MA 贴纸 每pcs产品要贴一张RFID贴纸，RFID贴纸由ZURU提供，贴纸位置要严格按照客人签板 77858-S002 1. 包装要求： 77858：MA 1L A版 playset +MA 5L A版收藏指南+MA 23L A版说明书+MA A版纸袋+MA 贴纸 每pcs产品要贴一张RFID贴纸，RFID贴纸由ZURU提供，贴纸位置要严格按照客人签板 2. 外箱印刷带条码的RFID箱唛：RFID紫色色带+WM Dept.图标+RFID图标+ITF-14条码，四面右下角印刷ZURU logo, ITFF条码只印刷在正唛一面，在加印的时候确保 条形码能扫描出来，外箱侧面任一角落加印："MADE IN CHINA" 字样； 3. 在产品上和包装上要有日期码、以及要有MADE IN CHINA和ZURU字样； 4. 产品如有扎带口要剪平，不能刮手。 5. 此单需要验货，请多备料 6. 此单以loose carton出货，2pcs/CTN | X47: Maggie Xie | Y47: 6.5485 | Z47: =I47*Y47 -> 3274.25 | AB47: 77858-S002 | AC47: 已入 | AI47: =I47 -> 500 | AM47: =I47 -> 500 | AQ47: =I47 -> 500
A48: 46115 | B48: AMAZON.COM SERVICES LLC | C48: 美国 | D48: 4500200214 | E48: 657D1AAZ | F48: 4500200214-220 | G48: 77858-S003-MB | H48: 厨房套装 | I48: 321 | J48: 0 | K48: 3 | L48: =I48/K48 -> 107 | M48: 46162 | N48: 46160 | P48: OK | R48: 自行排版 | S48: 46115 | T48: 有 | U48: 4/28SSCC Label | V48: 邮包盒图稿翻单4500195266 | W48: 日期码格式：ZURU INC(BVI) 标准格式 日期：按实际生产日期 Packaging Info: #77858: STD 77858带MA包装入邮包盒，邮包盒图稿翻单4500195266。 Remark: 1. Amazon MDDP订单，出口US。 2. 日期码使用ZURU标准版本。 3. 如果大货有要求入邮包盒，则对应的邮包盒上面要打上日期码。 4. 箱尺寸要求：外箱最长边不能超过25"(超过了，case pack只能为1)，不符合要求的大货，一律不接受。 5. 外箱箱唛要求： ①外箱正面印ZURU Logo+SSCC Label(客供贴纸，由跟单订购)。关于 SSCC Label 请注意： SSCC Label显示的是客人自己的item#。每一张SSCC label都是唯一且有不同流水及条码的，没有损耗，绝对不可贴错。如果贴错或损坏任何一张，都会导致全部都 错，千万要注意！SSCC Label必须贴在外箱正面的正中间位置(贴一面即可)，并且贴纸离外箱边距必须至少3cm(可以覆盖Logo<(>&<)>箱唛)，否则会影响到客户那边 仓库的扫描识别。 ②外箱侧面印item#(订单上显示的SKU#)+carton size(以工厂实际尺寸为准，单位: inch)+MADE IN CHINA，日期使用ZURU 标准版本。 6. 装柜要求：按照客户PO#装柜/箱号顺序装柜，跟单会提前给到装柜计划。 在大货生产/仓库存放时，请留意该装柜要求，以便装柜时不混乱(避免装错/装漏/找不到货号等)。 | X48: Kelly Shen/Mia Pan/P | Y48: 7.59 | Z48: =Y48*I48 -> 2436.39 | AB48: 77858-S003-MB | AC48: 已入 | AI48: =I48 -> 321 | AM48: =I48 -> 321 | AQ48: =I48 -> 321
A49: 46106 | B49: WALMART INC. | C49: 美国 | D49: 4500198134 | E49: 0983717750 | F49: 4500198134-10 | G49: 77858-S002 | H49: 厨房套装 | I49: 500 | J49: 0 | K49: 2 | L49: =I49/K49 -> 250 | M49: 46162 | N49: 46160 | O49: 5/25自检 | P49: OK | Q49: 46174 | R49: 是 | S49: 翻4500195615 | T49: 无 | U49: 4/8RFID贴纸 | W49: 日期码格式：ZURU DGYYMMDD CHINA(日期避开周末和法定节假日即可） 日期：按实际生产日期 Packaging Info: 77858-S002 1. 包装要求： 77858：MA 1L A版 playset +MA 5L A版收藏指南+MA 23L A版说明书+MA A版纸袋+MA 贴纸 每pcs产品要贴一张RFID贴纸，RFID贴纸由ZURU提供，贴纸位置要严格按照客人签板 Remark: 77858-S002 1. 包装要求： 77858：MA 1L A版 playset +MA 5L A版收藏指南+MA 23L A版说明书+MA A版纸袋+MA 贴纸 每pcs产品要贴一张RFID贴纸，RFID贴纸由ZURU提供，贴纸位置要严格按照客人签板 2. 外箱印刷带条码的RFID箱唛：RFID紫色色带+WM Dept.图标+RFID图标+ITF-14条码，四面右下角印刷ZURU logo, ITFF条码只印刷在正唛一面，在加印的时候确保 条形码能扫描出来，外箱侧面任一角落加印："MADE IN CHINA" 字样； 3. 在产品上和包装上要有日期码、以及要有MADE IN CHINA和ZURU字样； 4. 产品如有扎带口要剪平，不能刮手。 5. 此单需要验货，请多备料 6. 此单以loose carton出货，2pcs/CTN | X49: Maggie Xie | Y49: 6.3555 | Z49: =I49*Y49 -> 3177.75 | AB49: 77858-S002 | AC49: 已入 | AI49: =I49 -> 500 | AM49: =I49 -> 500 | AQ49: =I49 -> 500
A50: 46106 | B50: WALMART INC. | C50: 美国 | D50: 4500198134 | E50: 0983717811 | F50: 4500198134-20 | G50: 77858-S002 | H50: 厨房套装 | I50: 500 | J50: 0 | K50: 2 | L50: =I50/K50 -> 250 | M50: 46162 | N50: 46160 | O50: 5/25自检 | P50: OK | Q50: 46174 | R50: 是 | S50: 翻4500195615 | T50: 无 | U50: 4/8RFID贴纸 | W50: 日期码格式：ZURU DGYYMMDD CHINA(日期避开周末和法定节假日即可） 日期：按实际生产日期 Packaging Info: 77858-S002 1. 包装要求： 77858：MA 1L A版 playset +MA 5L A版收藏指南+MA 23L A版说明书+MA A版纸袋+MA 贴纸 每pcs产品要贴一张RFID贴纸，RFID贴纸由ZURU提供，贴纸位置要严格按照客人签板 Remark: 77858-S002 1. 包装要求： 77858：MA 1L A版 playset +MA 5L A版收藏指南+MA 23L A版说明书+MA A版纸袋+MA 贴纸 每pcs产品要贴一张RFID贴纸，RFID贴纸由ZURU提供，贴纸位置要严格按照客人签板 2. 外箱印刷带条码的RFID箱唛：RFID紫色色带+WM Dept.图标+RFID图标+ITF-14条码，四面右下角印刷ZURU logo, ITFF条码只印刷在正唛一面，在加印的时候确保 条形码能扫描出来，外箱侧面任一角落加印："MADE IN CHINA" 字样； 3. 在产品上和包装上要有日期码、以及要有MADE IN CHINA和ZURU字样； 4. 产品如有扎带口要剪平，不能刮手。 5. 此单需要验货，请多备料 6. 此单以loose carton出货，2pcs/CTN | X50: Maggie Xie | Y50: 6.5485 | Z50: =I50*Y50 -> 3274.25 | AB50: 77858-S002 | AC50: 已入 | AI50: =I50 -> 500 | AM50: =I50 -> 500 | AQ50: =I50 -> 500
A51: 46115 | B51: AMAZON.COM SERVICES LLC | C51: 美国 | D51: 4500200222 | E51: 7KK8YPTZ | F51: 4500200222-200 | G51: 77858-S003-MB | H51: 厨房套装 | I51: 426 | J51: 0 | K51: 3 | L51: =I51/K51 -> 142 | M51: 46162 | N51: 46160 | P51: OK | Q51: 46170 | R51: 自行排版 | S51: 46115 | T51: 有 | U51: 4/28SSCC Label | V51: 邮包盒图稿翻单4500195266 | W51: 日期码格式：ZURU INC(BVI) 标准格式 日期：按实际生产日期 Packaging Info: #77858: STD 77858带MA包装入邮包盒，邮包盒图稿翻单4500195266。 Remark: 1. Amazon MDDP订单，出口US。 2. 日期码使用ZURU标准版本。 3. 如果大货有要求入邮包盒，则对应的邮包盒上面要打上日期码。 4. 箱尺寸要求：外箱最长边不能超过25"(超过了，case pack只能为1)，不符合要求的大货，一律不接受。 5. 外箱箱唛要求： ①外箱正面印ZURU Logo+SSCC Label(客供贴纸，由跟单订购)。关于 SSCC Label 请注意： SSCC Label显示的是客人自己的item#。每一张SSCC label都是唯一且有不同流水及条码的，没有损耗，绝对不可贴错。如果贴错或损坏任何一张，都会导致全部都 错，千万要注意！SSCC Label必须贴在外箱正面的正中间位置(贴一面即可)，并且贴纸离外箱边距必须至少3cm(可以覆盖Logo<(>&<)>箱唛)，否则会影响到客户那边 仓库的扫描识别。 ②外箱侧面印item#(订单上显示的SKU#)+carton size(以工厂实际尺寸为准，单位: inch)+MADE IN CHINA，日期使用ZURU 标准版本。 6. 装柜要求：按照客户PO#装柜/箱号顺序装柜，跟单会提前给到装柜计划。 在大货生产/仓库存放时，请留意该装柜要求，以便装柜时不混乱(避免装错/装漏/找不到货号等)。 | X51: Kelly Shen/Mia Pan/P | Y51: 7.59 | Z51: =Y51*I51 -> 3233.34 | AB51: 77858-S003-MB | AC51: 已入 | AI51: =I51 -> 426 | AM51: =I51 -> 426 | AQ51: =I51 -> 426
A52: 46115 | B52: AMAZON.COM SERVICES LLC | C52: 美国 | D52: 4500200226 | E52: 5VINHCNE | F52: 4500200226-340 | G52: 77858-S003-MB | H52: 厨房套装 | I52: 252 | J52: 0 | K52: 3 | L52: =I52/K52 -> 84 | M52: 46162 | N52: 46160 | P52: OK | Q52: 46184 | R52: 自行排版 | S52: 46115 | T52: 有 | U52: 4/28SSCC Label | V52: 邮包盒图稿翻单4500195266 | W52: 日期码格式：ZURU INC(BVI) 标准格式 日期：按实际生产日期 Packaging Info: #77858: STD 77858带MA包装入邮包盒，邮包盒图稿翻单4500195266。 Remark: 1. Amazon MDDP订单，出口US。 2. 日期码使用ZURU标准版本。 3. 如果大货有要求入邮包盒，则对应的邮包盒上面要打上日期码。 4. 箱尺寸要求：外箱最长边不能超过25"(超过了，case pack只能为1)，不符合要求的大货，一律不接受。 5. 外箱箱唛要求： ①外箱正面印ZURU Logo+SSCC Label(客供贴纸，由跟单订购)。关于 SSCC Label 请注意： SSCC Label显示的是客人自己的item#。每一张SSCC label都是唯一且有不同流水及条码的，没有损耗，绝对不可贴错。如果贴错或损坏任何一张，都会导致全部都 错，千万要注意！SSCC Label必须贴在外箱正面的正中间位置(贴一面即可)，并且贴纸离外箱边距必须至少3cm(可以覆盖Logo<(>&<)>箱唛)，否则会影响到客户那边 仓库的扫描识别。 ②外箱侧面印item#(订单上显示的SKU#)+carton size(以工厂实际尺寸为准，单位: inch)+MADE IN CHINA，日期使用ZURU 标准版本。 6. 装柜要求：按照客户PO#装柜/箱号顺序装柜，跟单会提前给到装柜计划。 在大货生产/仓库存放时，请留意该装柜要求，以便装柜时不混乱(避免装错/装漏/找不到货号等)。 | X52: Kelly Shen/Mia Pan/P | Y52: 7.59 | Z52: =Y52*I52 -> 1912.68 | AB52: 77858-S003-MB | AC52: 已入 | AI52: =I52 -> 252 | AM52: =I52 -> 252 | AQ52: =I52 -> 252
A53: 46115 | B53: AMAZON.COM SERVICES LLC | C53: 美国 | D53: 4500200226 | E53: 8TY69JNQ | F53: 4500200226-350 | G53: 77858-S003-MB | H53: 厨房套装 | I53: 402 | J53: 0 | K53: 3 | L53: =I53/K53 -> 134 | M53: 46162 | N53: 46160 | P53: OK | Q53: 46184 | R53: 自行排版 | S53: 46115 | T53: 有 | U53: 4/28SSCC Label | V53: 邮包盒图稿翻单4500195266 | W53: 日期码格式：ZURU INC(BVI) 标准格式 日期：按实际生产日期 Packaging Info: #77858: STD 77858带MA包装入邮包盒，邮包盒图稿翻单4500195266。 Remark: 1. Amazon MDDP订单，出口US。 2. 日期码使用ZURU标准版本。 3. 如果大货有要求入邮包盒，则对应的邮包盒上面要打上日期码。 4. 箱尺寸要求：外箱最长边不能超过25"(超过了，case pack只能为1)，不符合要求的大货，一律不接受。 5. 外箱箱唛要求： ①外箱正面印ZURU Logo+SSCC Label(客供贴纸，由跟单订购)。关于 SSCC Label 请注意： SSCC Label显示的是客人自己的item#。每一张SSCC label都是唯一且有不同流水及条码的，没有损耗，绝对不可贴错。如果贴错或损坏任何一张，都会导致全部都 错，千万要注意！SSCC Label必须贴在外箱正面的正中间位置(贴一面即可)，并且贴纸离外箱边距必须至少3cm(可以覆盖Logo<(>&<)>箱唛)，否则会影响到客户那边 仓库的扫描识别。 ②外箱侧面印item#(订单上显示的SKU#)+carton size(以工厂实际尺寸为准，单位: inch)+MADE IN CHINA，日期使用ZURU 标准版本。 6. 装柜要求：按照客户PO#装柜/箱号顺序装柜，跟单会提前给到装柜计划。 在大货生产/仓库存放时，请留意该装柜要求，以便装柜时不混乱(避免装错/装漏/找不到货号等)。 | X53: Kelly Shen/Mia Pan/P | Y53: 7.59 | Z53: =Y53*I53 -> 3051.18 | AB53: 77858-S003-MB | AC53: 已入 | AI53: =I53 -> 402 | AM53: =I53 -> 402 | AQ53: =I53 -> 402
A54: 46094 | B54: WALMART INC. | C54: 美国 | D54: 4500196794 | E54: 0980444047 | F54: 4500196794-10 | G54: 77858-S002 | H54: 厨房套装 | I54: 1768 | J54: 0 | K54: 2 | L54: =I54/K54 -> 884 | M54: 46162 | N54: 46160 | O54: 46164 | P54: OK | Q54: 46181 | R54: 是 | S54: 46094 | T54: 有 | U54: 3/24RFID贴纸+粉色艾利贴纸+MA 贴纸 | W54: 日期码格式：ZURU DGMMDD CHINA(日期避开周末和法定节假日即可） 日期：按实际生产日期 Packaging Info: 77858-S002 1. 包装要求： 77858：MA 1L A版 playset +MA 5L A版收藏指南+MA 23L A版说明书+MA A版纸袋+MA 贴纸 每pcs产品要贴一张RFID贴纸，RFID贴纸由ZURU提供，贴纸位置要严格按照客人签板 Remark: 77858-S002 1. 包装要求： 77858：MA 1L A版 playset +MA 5L A版收藏指南+MA 23L A版说明书+MA A版纸袋+MA 贴纸 每pcs产品要贴一张RFID贴纸，RFID贴纸由ZURU提供，贴纸位置要严格按照客人签板 2. 外箱印刷带条码的RFID箱唛：RFID紫色色带+WM Dept.图标+RFID图标+ITF-14条码+粉色艾利贴纸（不干胶打印），四面右下角印刷ZURU logo, ITFF条码只印刷在 正唛一面，在加印的时候确保条形码能扫描出来，1张粉红色贴纸贴在正唛对角线，外箱侧面任一角落加印："MADE IN CHINA" 字样； 3. 在产品上和包装上要有日期码、以及要有MADE IN CHINA和ZURU字样； 4. 产品如有扎带口要剪平，不能刮手。 5. 此单需要验货，请多备料 6. 此单以loose carton出货，2pcs/CTN | X54: Maggie Xie | Y54: 6.5485 | Z54: =I54*Y54 -> 11577.748 | AB54: 77858-S002 | AC54: 已入 | AI54: =I54 -> 1768 | AM54: =I54 -> 1768 | AQ54: =I54 -> 1768
A55: 46120 | B55: SUCKOT SAC | C55: 秘鲁 | D55: 4500200402 | F55: 4500200402-60 | G55: 77858-S001 | H55: 厨房套装 | I55: 480 | J55: 0 | K55: 3 | L55: =I55/K55 -> 160 | M55: 46162 | N55: 46160 | P55: OK | Q55: 46171 | R55: 是 | S55: 46128 | T55: 无 | U55: 4/29进口商贴纸+UPC贴纸 | W55: 日期码格式：ZURU INC(BVI) 标准格式 日期：按实际生产日期 Packaging Info: 77782GQ1:客版收缩膜+客版收藏指南+客版PDQ+进口商贴纸+箱唛，客版物料翻单PO4500161302,进口商贴纸翻单PO4500183983 77785:客版彩盒+进口商贴纸+箱唛（77673:MA 多语收缩膜/77711：MA 多语收缩膜+空白贴纸）,客版彩盒翻单PO4500194447 7151、7152：MA 1L包装+MA多语说明书+进口商贴纸+箱唛，进口商贴纸翻单PO4500165899 9543GQ1:MA 多语包装+进口商贴纸+UPC贴纸+箱唛，进口商贴纸翻单PO4500165899 71126:MA 多语包装+进口商贴纸+箱唛，进口商贴纸翻单PO4500166157 77673:MA 多语包装+进口商贴纸+UPC贴纸+箱唛，进口商贴纸翻单PO4500183983 15789UQ1:MA 多语包装+进口商贴纸+箱唛 其余item：MA多语包装+进口商贴纸+UPC贴纸+箱唛 | X55: Ava Liang | Y55: 10.2316 | Z55: =I55*Y55 -> 4911.168 | AB55: 77858-S001-1 | AC55: 已入 | AL55: =I55 -> 480 | AM55: =I55 -> 480 | AQ55: =I55 -> 480
A56: 46104 | B56: UPD, INC. | C56: 美国 | D56: 4500198024 | E56: 36245 | F56: 4500198024-80 | G56: 77858-S001 | H56: 厨房套装 | I56: 240 | J56: 0 | K56: 3 | L56: =I56/K56 -> 80 | M56: 46164 | N56: 46160 | P56: OK | Q56: 46167 | R56: 自行排版 | S56: 46133 | T56: 无 | U56: 无 | W56: 日期码格式：ZURU INC(BVI) 标准格式 日期：按实际生产日期 Packaging Info: 1. 包装方式：MA UPC 优先1L 最新包装，出口美国 Remark: 2. 外箱箱唛红色和黑色双色印刷 3. 产品和包装上印刷tracking code信息，格式为ZURU常规 | X56: Angel Lin | Y56: 6.139 | Z56: =I56*Y56 -> 1473.36 | AB56: 77858-S001 | AC56: 已入 | AI56: =I56 -> 240 | AM56: =I56 -> 240 | AQ56: =I56 -> 240
A57: 46098 | B57: SCHEEL'S ALL SPORTS, INC. | C57: 美国 | D57: 4500195170 | E57: 021873145 | F57: 4500195170-70 | G57: 77858-S001 | H57: 厨房套装 | I57: 1002 | J57: 0 | K57: 3 | L57: =I57/K57 -> 334 | M57: 46164 | N57: 46160 | P57: OK | Q57: 46173 | R57: 是 | S57: 46104 | T57: 无 | U57: 无 | W57: 日期码格式：ZURU INC(BVI) 标准格式 日期：按实际生产日期 Packaging Info: 1. 包装：ZURU MA 1L 最新UPC版本；出口美国<(>&<)>CA； Remark: 2. 日期跟踪码：产品包装及产品本身都必须有日期跟踪码，并且确保两者的日期跟踪码要一致；ZURU标准格式日期码(请自行调整具体年月日生产期，但不能为周 末）。 3.. 出货配比: Zuru 标版配比。 Order Modifiable Records Revision # Date: Comment: 1 2026-03-06 00:00:00 REV.1.更新77711GQ1 工厂交期4.30 2 2026-03-16 00:00:00 REV.2.增加50-110行 3 2026-03-17 00:00:00 REV.3.增加9565 Special Requirments 1.Factory is required to confirm the PO with all the details within 2 working days once upon receipt of ZURU PO. Or order will be treated as accepted. 贵司收到 ZURU 订单请在2个工作日内确认订单，否则将视为默认接受； 2.Fulfill US, EU, AUS, NZ and CAN latest safety requirements, such as EN71, ASTM F963, AS / NZS ISO8124, Reach, requirements of EC directive 2009/48/EC/Phthalates/PAH/lead/cadmium/Azo/Formaldehyde/USP51/USP61/62 and other applicative regulation in toys; EN62115/ROHS/EMC/FCC/ICES-003/RCM/2006/66/EC for Electronic toys. 产品及大货需要满足US, EU, AUS, NZ 和CAN的最新玩具安全要求以及符合玩具的相关测试标准（例如：EN71, ASTM F963, AS / NZS ISO8124, Reach, requirements of EC directive 2009/48/EC/Phthalates/PAH/lead/cadmium/Azo/Formaldehyde/USP51/USP61/62 和其他适用的规定等等; 电子类玩具还需要满足EN62115/ROHS/EMC/FCC/ICES-003/RCM/2006/66/EC等等）； 3.Please prepare extra quantity for photography purpose sample, sign-off sample, sample drawing, testing, and inspection (AQL standard). 由于涉及到拍照用途的样品、签样、抽样、测试以及验货（按照AQL标准），请额外备足够的数量； 4.ZURU carton standard should be 单坑 requirement for those carton weight less than 5KG. Otherwise, A=B requirement is required. 外箱重量低于5kg的标准的外箱材质要求是单坑，否则要求A=B； 5.Factory is required to reconfirm order carton details including dimension, weight, pack size etc.. Please inform ZURU team if any update. 要求工厂确认好外箱的信息，例如：尺寸、毛重、净重、装箱数等； 如有任何更新请及时通知； 6.Date code is required for product, retail packaging and master carton. If there's NO customer assigned date code format, please use ZURU standard format and it should be "GZYYYYMMDD". (ATTN: GZ is city code of production factory (e.g. Guangzhou = GZ), YYYYMMDD is production year, month and date.). "©ZURU" and"Made in China" are required to show on the product. Please further check with ZURU QA team if you have any questions. 产品，零售包装以及外箱上需要显示生产日期；如果客人没有指定的日期码格式，请用 ZURU 标准日期码格式，如：GZYYYYMMDD（注意：GZ是生产工厂的城市代码缩写，例如："广州"，Gua ngzhou = GZ；YYYYMMDD是生产年、月和日）；产品上需要有"©ZURU"和"Made inChina"的字样；以上，对此有疑问请联系 ZURU QA team； 7.Date code on product should be earlier or equal to date on packaging; Date code on packaging should be earlier or equal to master carton (Date code on retail packaging must be readable without opening the retail packaging.). 产品上日期码的日期应早于或等于包装上日期码的日期；包装上日期码的日期应早于或等于外箱上日期码的日期（注意：零售包装上的日期码要在无需拆开包装的前提下可直接看到）； 8.All the change on production/packaging must inform ZURU team and ask confirmation in advance. 若产品/大货或包装有任何变更，请务必通知 ZURU 相关团队并提前确认好以免影响订单交付； 9.If ZURU re-inspection is required caused by factory's problem, the re-inspection fee of CNY 1000 and travel expenses will be at production factory's expense. 若因工厂原因导致的 ZURU QC重验，工厂需要承担CNY1000重验费以及相关差旅费； 10.ZURU Final inspection application is required to submit to ZURU OQC team 7 days before inspection date with order qty 100% finished. And all shipments should be pass ZURU OQC inspection before delivery. 烦请验货前至少7天与 ZURU 验货团队预约验货，并确保验货当天是100%完成大货；所有出货前要有 ZURU 验货通过的报告； 11.All barcodes should be scannable and readable. 所有条码确保可扫描以及可读； 12.ZURU logo is required for master carton as large as possible in the condition of NO impact shipping mark information. 外箱上需要印有 ZURU 符号并且在不影响箱唛的情况下，ZURU 符号应尽可能放大； 13.Above are ZURU STD requirements. If there are customer or other requirements, please further follow it as per PO remark or email notification. 以上均为 ZURU 标准要求，如果有任何客人或其他要求，请查看PO上的备注以及注意邮件通知。 Additional Clause 1.As agreed above, ZURU reserves the right to claim the penalties of shipment delay which caused by factory as following terms: ·Will charge 5% of PO total amount for 1-7 days (incl. 7days) of the shipment delay. ·Will charge 7% of PO total amount for 7-14 days (incl. 14days) of the shipment delay. ·Will charge 10% of PO total amount for over 14 days of the shipment delay. · If customer required to air ship or penalty for shipment delay, the air cost and penalty will be at factory's expense. 如果同意以上交货期到 ZURU 公司但是最后由于供应商原因无法交货，ZURU 公司保留以下的罚款条款： * 1-7（含第七天）天内延迟出货罚款为合同总金额的百分之五， * 7-14（含第十四天）天内延迟出货罚款为合同总金额的百分之七， * 如果超过14天将扣合同金额的百分之十， * 如产生客人对 ZURU 公司罚款或产生空运费，罚款金额需供应商全额承担； 2.Factory is required to bear relevant cost or penalty of customer or 3rd party's failed result which caused by factory. 如遇到由工厂导致的客人或第三方的验货、测试不过等要求重验或重测以及涉及罚款的，工厂需要承担相关费用； 3.If the quality cannot meet ZURU standard or requirements, factory is required to improve or rework till it could meet ZURU standard or requirements. All costs including rework fee, shipment delay fee or penalty are at factory's expense. 如果因为质量不符合 ZURU 公司要求的标准，供应商必须改进产品以达到标准并支付返工费用及以上出货延迟费用； 4.Please be subject to the final revision/update of PO and adjust the production if needs. 订单细节会不时进行修改，请以最后一次修改订单为准并及时协调生产； 5.Please contact relevant merchandiser within 2 working days if you have any questions of the order. Or order will be treated as accepted. 如果对订单细节有任何疑问，请在2个工作日内直接回复给对应跟单；如果没有回复，那么将被认为所有订单细节包括交期在内都被接受； 6.Factory is required to provide the commodity inspection (if needs), customs clearance documents and complete the trade term responsibilities. Or please further check with ZURU Company team 20 days ahead of shipment. And the order will be settled by CNY and required factory to raise 13% VAT invoice after confirmation. 该订单将需要贵司提供相关的商检及报关单证，若贵司不能提供相关单证且需要用到我司单证出货，要求于出货20日前与我司确认，该订单将以人民币结算并需要贵司开出13%税率VAT增值 税发票； Confirmed And Accepted By: Issued By: Signature & Company Chop | X57: Mila Yao | Y57: 6.129 | Z57: =I57*Y57 -> 6141.258 | AB57: 77858-S001 | AC57: 已入 | AI57: =I57 -> 1002 | AM57: =I57 -> 1002 | AQ57: =I57 -> 1002
A58: 46114 | B58: MILLS FLEET FARM | C58: 美国 | D58: 4500199572 | E58: 4891185 | F58: 4500199572-130 | G58: 77858-S001 | H58: 厨房套装 | I58: 600 | J58: 0 | K58: 3 | L58: =I58/K58 -> 200 | M58: 46164 | N58: 46162 | P58: OK | Q58: 46168 | R58: 是 | S58: 46132 | T58: 无 | U58: 无 | W58: 日期码格式：ZURU INC(BVI) 标准格式 日期：按实际生产日期 Packaging Info: 1. 包装：ZURU MA 1L UPC版本最新包装；出口美国; Remark: 2. 日期跟踪码：产品包装及产品本身都必须有日期跟踪码，并且确保两者的日期跟踪码要一致；ZURU标准格式日期码(请自行调整具体年月日生产期，但不能为周 末）。 3. 出货配比: Zuru 标准 配比 | X58: Mila Yao | Y58: 6.139 | Z58: =Y58*I58 -> 3683.4 | AB58: 77858-S001 | AC58: 已入 | AI58: =I58 -> 600 | AM58: =I58 -> 600 | AQ58: =I58 -> 600
A59: 46108 | B59: TOYZOONA LIMITED | C59: 肯尼亚 | D59: 4500199109 | F59: 4500199109-10 | G59: 77858-S001 | H59: 厨房套装 | I59: 510 | J59: 0 | K59: 3 | L59: =I59/K59 -> 170 | M59: 46165 | N59: 46163 | P59: OK | Q59: 46181 | R59: 是 | S59: 46122 | T59: 无 | U59: 无 | W59: 日期码格式：ZURU INC(BVI) 标准格式 日期：按实际生产日期 Packaging Info: MA 1L PKG Remark: | X59: Chelsea Luo | Y59: 9.9425 | Z59: =Y59*I59 -> 5070.675 | AB59: 77858-S001 | AC59: 已入 | AI59: =I59 -> 510 | AM59: =I59 -> 510 | AQ59: =I59 -> 510
A60: 46106 | B60: WALMART INC. | C60: 美国 | D60: 4500198135 | E60: 0983717752 | F60: 4500198135-10 | G60: 77858-S002 | H60: 厨房套装 | I60: 500 | J60: 0 | K60: 2 | L60: =I60/K60 -> 250 | M60: 46167 | N60: 46163 | O60: 5/28自检 | P60: OK | Q60: 46178 | R60: 是 | S60: 翻4500195615 | T60: 无 | U60: 4/8RFID贴纸 | W60: 日期码格式：ZURU DGYYMMDD CHINA(日期避开周末和法定节假日即可） 日期：按实际生产日期 77858-S002 1. 包装要求： 77858：MA 1L A版 playset +MA 5L A版收藏指南+MA 23L A版说明书+MA A版纸袋+MA 贴纸 每pcs产品要贴一张RFID贴纸，RFID贴纸由ZURU提供，贴纸位置要严格按照客人签板 77858-S002 1. 包装要求： 77858：MA 1L A版 playset +MA 5L A版收藏指南+MA 23L A版说明书+MA A版纸袋+MA 贴纸 每pcs产品要贴一张RFID贴纸，RFID贴纸由ZURU提供，贴纸位置要严格按照客人签板 2. 外箱印刷带条码的RFID箱唛：RFID紫色色带+WM Dept.图标+RFID图标+ITF-14条码，四面右下角印刷ZURU logo, ITFF条码只印刷在正唛一面，在加印的时候确保 条形码能扫描出来，外箱侧面任一角落加印："MADE IN CHINA" 字样； 3. 在产品上和包装上要有日期码、以及要有MADE IN CHINA和ZURU字样； 4. 产品如有扎带口要剪平，不能刮手。 5. 此单需要验货，请多备料 6. 此单以loose carton出货，2pcs/CTN | X60: Maggie Xie | Y60: 6.5485 | Z60: =I60*Y60 -> 3274.25 | AB60: 77858-S002 | AC60: 已入 | AI60: =I60 -> 500 | AM60: =I60 -> 500 | AQ60: =I60 -> 500
A61: 46106 | B61: WALMART INC. | C61: 美国 | D61: 4500198141 | E61: 0983717856 | F61: 4500198141-10 | G61: 77858-S002 | H61: 厨房套装 | I61: 500 | J61: 0 | K61: 2 | L61: =I61/K61 -> 250 | M61: 46167 | N61: 46163 | O61: 46174 | P61: OK | Q61: 46181 | R61: 是 | S61: 翻4500195615 | T61: 无 | U61: 4/8RFID贴纸 | W61: 日期码格式：ZURU DGYYMMDD CHINA(日期避开周末和法定节假日即可） 日期：按实际生产日期 Packaging Info: 包装要求： 77858：MA 1L A版 playset +MA 5L A版收藏指南+MA 23L A版说明书+MA A版纸袋+MA 贴纸 每pcs产品要贴一张RFID贴纸，RFID贴纸由ZURU提供，贴纸位置要严格按照客人签板 Remark: 77858-S002 1. 包装要求： 77858：MA 1L A版 playset +MA 5L A版收藏指南+MA 23L A版说明书+MA A版纸袋+MA 贴纸 每pcs产品要贴一张RFID贴纸，RFID贴纸由ZURU提供，贴纸位置要严格按照客人签板 2. 外箱印刷带条码的RFID箱唛：RFID紫色色带+WM Dept.图标+RFID图标+ITF-14条码，四面右下角印刷ZURU logo, ITFF条码只印刷在正唛一面，在加印的时候确保 条形码能扫描出来，外箱侧面任一角落加印："MADE IN CHINA" 字样； 3. 在产品上和包装上要有日期码、以及要有MADE IN CHINA和ZURU字样； 4. 产品如有扎带口要剪平，不能刮手。 5. 此单需要验货，请多备料 6. 此单以loose carton出货，2pcs/CTN | X61: Maggie Xie | Y61: 6.5485 | Z61: =I61*Y61 -> 3274.25 | AB61: 77858-S002 | AC61: 已入 | AI61: =I61 -> 500 | AM61: =I61 -> 500 | AQ61: =I61 -> 500
A62: 46052 | B62: 360 SALES SOLUTIONS INC | C62: 加拿大 | D62: 4500192784 | E62: 2026ZURU02 | F62: 4500192784-20 | G62: 77858-S001 | H62: 厨房套装 | I62: 714 | J62: 0 | K62: 3 | L62: =I62/K62 -> 238 | M62: 46167 | N62: 46163 | P62: OK | Q62: 46173 | R62: 是 | S62: 46052 | T62: 无 | U62: 3/3UPC贴纸包装193052100238 | W62: 日期码格式： 标准格式 日期：按实际生产日期 Packaging Info: 77858 MA 多语EAN+UPC贴纸包装193052100238 Remark: 出加拿大 Zuru验货.日期跟踪码：产品外包装及产品本身都必须有日期跟踪码，ZURU标准格式日期码。（箱唛日期码按跟单提供格式） | X62: Bella Tan | Y62: 10.215 | Z62: =I62*Y62 -> 7293.51 | AB62: 77858-S001-1 | AC62: 已入 | AL62: =I62 -> 714 | AM62: =I62 -> 714 | AQ62: =I62 -> 714
A63: 46106 | B63: WALMART INC. | C63: 美国 | D63: 4500198137 | E63: 0983717757 | F63: 4500198137-20 | G63: 77858-S002 | H63: 厨房套装 | I63: 500 | J63: 0 | K63: 2 | L63: =I63/K63 -> 250 | M63: 46167 | N63: 46163 | O63: 6/1 BV到厂 | P63: OK | Q63: 46185 | R63: 是 | S63: 翻4500195615 | T63: 无 | U63: 4/8RFID贴纸 | W63: 日期码格式：ZURU DGYYMMDD CHINA(日期避开周末和法定节假日即可） 日期：按实际生产日期 77858-S002 1. 包装要求： 77858：MA 1L A版 playset +MA 5L A版收藏指南+MA 23L A版说明书+MA A版纸袋+MA 贴纸 每pcs产品要贴一张RFID贴纸，RFID贴纸由ZURU提供，贴纸位置要严格按照客人签板 77858-S002 1. 包装要求： 77858：MA 1L A版 playset +MA 5L A版收藏指南+MA 23L A版说明书+MA A版纸袋+MA 贴纸 每pcs产品要贴一张RFID贴纸，RFID贴纸由ZURU提供，贴纸位置要严格按照客人签板 2. 外箱印刷带条码的RFID箱唛：RFID紫色色带+WM Dept.图标+RFID图标+ITF-14条码，四面右下角印刷ZURU logo, ITFF条码只印刷在正唛一面，在加印的时候确保 条形码能扫描出来，外箱侧面任一角落加印："MADE IN CHINA" 字样； 3. 在产品上和包装上要有日期码、以及要有MADE IN CHINA和ZURU字样； 4. 产品如有扎带口要剪平，不能刮手。 5. 此单需要验货，请多备料 6. 此单以loose carton出货，2pcs/CTN | X63: Maggie Xie | Y63: 6.5485 | Z63: =I63*Y63 -> 3274.25 | AB63: 77858-S002 | AC63: 已入 | AI63: =I63 -> 500 | AM63: =I63 -> 500 | AQ63: =I63 -> 500
A64: 46106 | B64: WALMART INC. | C64: 美国 | D64: 4500198137 | E64: 0983717887 | F64: 4500198137-30 | G64: 77858-S002 | H64: 厨房套装 | I64: 500 | J64: 0 | K64: 2 | L64: =I64/K64 -> 250 | M64: 46167 | N64: 46163 | O64: 5/28自检 | P64: OK | Q64: 46183 | R64: 是 | S64: 翻4500195615 | T64: 无 | U64: 4/8RFID贴纸 | W64: 日期码格式：ZURU DGYYMMDD CHINA(日期避开周末和法定节假日即可） 日期：按实际生产日期 77858-S002 1. 包装要求： 77858：MA 1L A版 playset +MA 5L A版收藏指南+MA 23L A版说明书+MA A版纸袋+MA 贴纸 每pcs产品要贴一张RFID贴纸，RFID贴纸由ZURU提供，贴纸位置要严格按照客人签板 77858-S002 1. 包装要求： 77858：MA 1L A版 playset +MA 5L A版收藏指南+MA 23L A版说明书+MA A版纸袋+MA 贴纸 每pcs产品要贴一张RFID贴纸，RFID贴纸由ZURU提供，贴纸位置要严格按照客人签板 2. 外箱印刷带条码的RFID箱唛：RFID紫色色带+WM Dept.图标+RFID图标+ITF-14条码，四面右下角印刷ZURU logo, ITFF条码只印刷在正唛一面，在加印的时候确保 条形码能扫描出来，外箱侧面任一角落加印："MADE IN CHINA" 字样； 3. 在产品上和包装上要有日期码、以及要有MADE IN CHINA和ZURU字样； 4. 产品如有扎带口要剪平，不能刮手。 5. 此单需要验货，请多备料 6. 此单以loose carton出货，2pcs/CTN | X64: Maggie Xie | Y64: 6.5485 | Z64: =I64*Y64 -> 3274.25 | AB64: 77858-S002 | AC64: 已入 | AI64: =I64 -> 500 | AM64: =I64 -> 500 | AQ64: =I64 -> 500
A65: 46126 | B65: SIDJ JOUECLUB | C65: 法国 | D65: 4500201678 | E65: 26000056-L | F65: 4500201678-10 | G65: 77858-S001 | H65: 厨房套装 | I65: 1200 | J65: 0 | K65: 3 | L65: =I65/K65 -> 400 | M65: 46167 | N65: 46164 | P65: OK | Q65: 46170 | R65: 自行排版 | S65: 46135 | T65: 无 | U65: 额外贴纸(翻4500196797) | V65: 额外的客版黑白说明书((翻4500196797) | W65: 日期码格式：2052526 日期： Packaging Info: MA23L EAN彩盒+额外贴纸(翻4500196797)+MA 袋子+MA贴纸+ML 5L收藏指南+MA23L说明书+1张额外的客版黑白说明书((翻4500196797) Remark: 1.此票无需客户验货 2.所有出口法国的产品, 法规规定禁止在包装和共公众用的印刷品中使用矿物油中含有的物质, 包装印刷油墨中含有的MOAH/MOSH的质量浓度不能超过1%, 否则出货 到法国被抽检出现问题, 供应商需要对此负责; 3.出口法国请确保产品符合EU微塑料法规，包装需显示法国回收logo; | X65: Ula Zhao | Y65: 10.215 | Z65: =Y65*L65 -> 4086 | AB65: 77858-S001-1 | AC65: 已入 | AL65: =I65 -> 1200 | AM65: =I65 -> 1200 | AQ65: =I65 -> 1200
A66: 46125 | B66: AMAZON EU SARL, NDL DEUTSCHLAND | C66: 德国 | D66: 4500201268 | E66: 524LKUVU | F66: 4500201268-40 | G66: 77858-S003-MB | H66: 厨房套装 | I66: 714 | J66: 0 | K66: 3 | L66: =I66/K66 -> 238 | M66: 46167 | N66: 46164 | P66: OK | Q66: 46170 | R66: 自行排版 | S66: 空白外箱（加印带Zuru字样的最新logo，除了邮包盒直接做外箱的产品） | T66: 有 | U66: 4/29 SSCC Label+ZURU FRANCE 地址贴 | V66: 客版邮包盒(参考翻单PO#4500192979) | W66: 日期码格式：ZURU INC(BVI) 标准格式 日期：按实际生产日期 Packaging Info: Amazon DE:77EBUZMB/5NJQ3IYM/524LKUVU Amazon ES:5DTE4VLV Amazon FR:5X8Z857H/32CZCE8A/2RYJSVMM Amazon IT:5Z9TYR1E Amazon UK:7XAFEJ2S/5BSUPH4P/3P6NUAFE/3OUVPHYB DE(157114B/157140/9574/77858)/ES(157140/9574/15788G)/FR(9574/157143/157140/77858)/IT(77858)/UK(157114H/9574/77858/92146E) 5. 77858:1pc 77858 playset into mailbox, 3mailboxes/ctn; Including magnets; 3PCS AA BATTERIES(NOT INCLUDED); MA 3L(23L warning EAN)A 透明PVC窗彩 盒+MA 23L warning A 电池黑白说明书+MA 5L A收藏指南+MA其它最新配套包装+客版邮包盒(参考翻单PO#4500192979)+WEEE_不带电池走货 _ 说明书欧洲EN+30L_B版 8. 最迟验货不得晚于5/26 9. 77858验货时需要将产品六面图， 邮包盒(含产品)测量尺寸图片<(>&<)>重量图片放进验货报告 Remark: 1.空白外箱（加印带Zuru字样的最新logo，除了邮包盒直接做外箱的产品） + SSCC LABEL一张, 无箱唛，MADE IN CHINA 外箱只印一正一侧。箱唛资料按照给定的 标准去做即可，无需发回我方再行审批(新标准将另行通知)。 (SSCC LABEL竖贴在外箱正面的正中间，贴一面即可,贴纸离外箱边距必须至少3.2CM。如竖贴无法满足要求，则横贴。如横贴也无法满足要求，则竖贴，遮到ZURU lo go无影响), SSCC贴纸由工厂直接跟勤得采购或者工厂自行采购，每一张SSCC Label都是唯一且有不同流水及条码，且需要检查条码是否能正常扫描，另外，此贴纸 印刷不可出现模糊，溢出及粘胶不牢易脱落等现象，如工厂不按此要求导致贴纸有任何问题产生的罚款将由工厂承担一切责任 ,<(>,<)> 此要求只适用Amazon UK/DE /FR/ES/IT,不适用Amazon GPE，Amazon GPE无SSCC label, 但是有对应箱唛，需印刷到外箱 。 2.出往UK的产品+包装务必打上UKCA logo ，否则客人会退货且当地会有罚款。Amazon GPE（包含UK/FR/ES/DE/IT）的订单也需满足此要求。 3.订单必须经过ZURU QC验货或者工厂自检通过后方可出货，不涉及第三方验货。 4.法国订单要求包装不使用矿物油，请按要求提供以下其中一份文件再出货 ，产品出到法国被相关部门抽检出现包装不符合此要求的，供应商需要为此承担责任， 故此请严格把关。Am~azon GPE（包含UK/FR/ES/DE/IT）的订单也需满足此要求。 -油墨物质""""由1 7个芳香环组成的MOAH""""的包装检测报告，要求限值≤1.0%； -包装材料清单，包括包装油墨或物质的信息； -油墨制造商的证书； 5.每一批次出货只能有一个生产日期，不可多个生产日期混在同一批次出货；且零售包装上必须统一加上日期码；外箱对于日期码没有硬性规定； 6.涉及到相关款式会有闪粉的或者微塑料的，请统一默认出无闪粉或者不含微塑料版本； 7.邮包盒及外箱封箱必须是工字型封箱方式； 8.5 Surprise or Mini Brands涉及包装是2个及2个以上的球入PVC桶包装时，单个球上若有UPC#或者EAN#，请用空白贴纸覆盖住，贴纸尺寸自行测量能覆盖原条码即 可； 9. 无论是工厂自检还是ZURU验货，验货报告中必须有产品6面图(正面/背面/左面/右面/顶部/底部，不带包装); 10. 按空海运鉴定报告的要求，只要带锂电池出货，都需要加贴UN贴纸； 11. 所有出往GAS市场(德国/奥地利/瑞士)的电子产品身上需要加字唛，为ZURU FRANCE 地址，需跟包装上的地址一致 (如无电子产品，产品布标有此地址，或产品 太小无法增加可忽略此信息。如产品无法加字唛，需让对应跟单提供产品贴纸资料);（Amazon GPE的订单也需满足此要求） 12. 所有出往GAS德国 (瑞士，奥地利)。水弹枪系列必须使用EN71版本（电子和非电子水弹枪系列都需要符合); 护目镜需打日期码, 格式跟ZURU标准格式一样; 枪 身上增加ZURU FRANCE公司名和地址。使用贴纸和辐射上去都可以。如果有位置，最好增加ZURU Represented by: (此最好翻译德语，如果位置不允许，那么就只增 加ZURU法国和地址)。使用最新的EN71版包装和说明书）。Amazon GPE（包含UK/FR/ES/DE/IT）的订单也需满足此要求。 | X66: Crystal Chen | Y66: 12.65 | Z66: =Y66*L66 -> 3010.7 | AB66: 77858-S003-MB-1 | AC66: 已入 | AL66: =I66 -> 714 | AM66: =I66 -> 714 | AO66: 30L | AQ66: =I66 -> 714
A67: 46125 | B67: AMAZON EU SARL, NDL DEUTSCHLAND | C67: 法国 | D67: 4500201268 | E67: 2RYJSVMM | F67: 4500201268-120 | G67: 77858-S003-MB | H67: 厨房套装 | I67: 501 | J67: 0 | K67: 3 | L67: =I67/K67 -> 167 | M67: 46167 | N67: 46164 | P67: OK | Q67: 46170 | R67: 自行排版 | S67: 空白外箱（加印带Zuru字样的最新logo，除了邮包盒直接做外箱的产品） | T67: 有 | U67: 4/29 SSCC Label | V67: 客版邮包盒(参考翻单PO#4500192979) | W67: 日期码格式：ZURU INC(BVI) 标准格式 日期：按实际生产日期 Packaging Info: Amazon DE:77EBUZMB/5NJQ3IYM/524LKUVU Amazon ES:5DTE4VLV Amazon FR:5X8Z857H/32CZCE8A/2RYJSVMM Amazon IT:5Z9TYR1E Amazon UK:7XAFEJ2S/5BSUPH4P/3P6NUAFE/3OUVPHYB DE(157114B/157140/9574/77858)/ES(157140/9574/15788G)/FR(9574/157143/157140/77858)/IT(77858)/UK(157114H/9574/77858/92146E) 1. 157114BH: --157114B:1pc 15787B 9"(Wrinkle McStinkles) into mailbox, 12mailboxes/ctn; 客版邮包盒(参考Amazon US翻单PO#4500192979); --157114H:1pc 15787H 9"(Sasquoosh) into mailbox, 12mailboxes/ctn; 客版邮包盒(参考Amazon US翻单PO#4500192979); 2. 157140:2PK 15774 into window box respectively, then into polybag, 6polybags/ctn, MA 5L(5L warning UPC)B 开窗彩盒+1张贴纸(含IT环保标+西班牙洗 涤说明,参考翻单PO#4500198613)+客版透明胶袋(双面打孔+含英法德意西警告语+塑料循环标, 参考翻单PO#4500166364)+1张UPC#贴纸(贴在胶袋上,参考翻单PO#450 0198613)+1张空白贴纸(贴在彩盒条码位置, 参考翻单PO#4500198613); 3. 157143;8PK 157117 IN MAIL BOX,12mailboxes/ctn; 8 Assortment=1:1:1:1:1:1:1:1; 客版邮包盒(参考Amazon US翻单PO#4500195274); 4. 15788G:1pc 15788G 9"(Sir Belch) in window box,then into polybag, 12polybags/ctn; Global onshelf date after 2026/7/9; MA 5L(5L warning UPC)A开 窗彩盒+MA其它最新配套包装+客版胶袋(含英法德意西荷兰警告语+双面打孔+塑料循环标,参考翻单PO#4500164364)+2张贴纸(1张含UPC#<(>&<)>IT环保标<(>&<)>ES 洗涤说明贴纸,参考翻单PO#4500198640+1张上架日期贴纸, 参考翻单PO#4500198640) 5. 77858:1pc 77858 playset into mailbox, 3mailboxes/ctn; Including magnets; 3PCS AA BATTERIES(NOT INCLUDED); MA 3L(23L warning EAN)A 透明PVC窗彩 盒+MA 23L warning A 电池黑白说明书+MA 5L A收藏指南+MA其它最新配套包装+客版邮包盒(参考翻单PO#4500192979)+WEEE_不带电池走货 _ 说明书欧洲EN+30L_B版 6. 92146E:1pc 92146E SMALL(Tiger) into shrink wraps,24pcs/ctn;Bubble powder;NO Boron; MA 3L(8L warning EAN)A收缩膜+MA其它最新配套包装+MA 5L(19L warning)A收藏指南+1张贴纸(1张UPC+IT环保标+ES洗涤说明贴纸贴纸，参考翻单PO#4500198640); 7. 9574:3-4pcs magnets included, compounds not included; 2pcs baby capybara: 3pcs baby capybara= 5:1; 3PCS AAA BATTERIES(NOT INCLUDED); 4PCS/CTN ; MA 3L(23 warning EAN) A版彩盒+MA5L(9L warning) A版说明书+2张贴纸(1张#UPC, 1张IT环保标; 贴纸翻单PO#)+WEEE_不带电池走货 _ 说明书欧洲EN+30L_B版 8. 最迟验货不得晚于5/26 9. 77858验货时需要将产品六面图， 邮包盒(含产品)测量尺寸图片<(>&<)>重量图片放进验货报告 Remark: 1.空白外箱（加印带Zuru字样的最新logo，除了邮包盒直接做外箱的产品） + SSCC LABEL一张, 无箱唛，MADE IN CHINA 外箱只印一正一侧。箱唛资料按照给定的 标准去做即可，无需发回我方再行审批(新标准将另行通知)。 (SSCC LABEL竖贴在外箱正面的正中间，贴一面即可,贴纸离外箱边距必须至少3.2CM。如竖贴无法满足要求，则横贴。如横贴也无法满足要求，则竖贴，遮到ZURU lo go无影响), SSCC贴纸由工厂直接跟勤得采购或者工厂自行采购，每一张SSCC Label都是唯一且有不同流水及条码，且需要检查条码是否能正常扫描，另外，此贴纸 印刷不可出现模糊，溢出及粘胶不牢易脱落等现象，如工厂不按此要求导致贴纸有任何问题产生的罚款将由工厂承担一切责任 ,<(>,<)> 此要求只适用Amazon UK/DE /FR/ES/IT,不适用Amazon GPE，Amazon GPE无SSCC label, 但是有对应箱唛，需印刷到外箱 。 2.出往UK的产品+包装务必打上UKCA logo ，否则客人会退货且当地会有罚款。Amazon GPE（包含UK/FR/ES/DE/IT）的订单也需满足此要求。 3.订单必须经过ZURU QC验货或者工厂自检通过后方可出货，不涉及第三方验货。 4.法国订单要求包装不使用矿物油，请按要求提供以下其中一份文件再出货 ，产品出到法国被相关部门抽检出现包装不符合此要求的，供应商需要为此承担责任， 故此请严格把关。Am~azon GPE（包含UK/FR/ES/DE/IT）的订单也需满足此要求。 -油墨物质""""由1 7个芳香环组成的MOAH""""的包装检测报告，要求限值≤1.0%； -包装材料清单，包括包装油墨或物质的信息； -油墨制造商的证书； 5.每一批次出货只能有一个生产日期，不可多个生产日期混在同一批次出货；且零售包装上必须统一加上日期码；外箱对于日期码没有硬性规定； 6.涉及到相关款式会有闪粉的或者微塑料的，请统一默认出无闪粉或者不含微塑料版本； 7.邮包盒及外箱封箱必须是工字型封箱方式； 8.5 Surprise or Mini Brands涉及包装是2个及2个以上的球入PVC桶包装时，单个球上若有UPC#或者EAN#，请用空白贴纸覆盖住，贴纸尺寸自行测量能覆盖原条码即 可； 9. 无论是工厂自检还是ZURU验货，验货报告中必须有产品6面图(正面/背面/左面/右面/顶部/底部，不带包装); 10. 按空海运鉴定报告的要求，只要带锂电池出货，都需要加贴UN贴纸； 11. 所有出往GAS市场(德国/奥地利/瑞士)的电子产品身上需要加字唛，为ZURU FRANCE 地址，需跟包装上的地址一致 (如无电子产品，产品布标有此地址，或产品 太小无法增加可忽略此信息。如产品无法加字唛，需让对应跟单提供产品贴纸资料);（Amazon GPE的订单也需满足此要求） 12. 所有出往GAS德国 (瑞士，奥地利)。水弹枪系列必须使用EN71版本（电子和非电子水弹枪系列都需要符合); 护目镜需打日期码, 格式跟ZURU标准格式一样; 枪 身上增加ZURU FRANCE公司名和地址。使用贴纸和辐射上去都可以。如果有位置，最好增加ZURU Represented by: (此最好翻译德语，如果位置不允许，那么就只增 加ZURU法国和地址)。使用最新的EN71版包装和说明书）。Amazon GPE（包含UK/FR/ES/DE/IT）的订单也需满足此要求。 | X67: Crystal Chen | Y67: 12.65 | Z67: =Y67*L67 -> 2112.55 | AB67: 77858-S003-MB-1 | AC67: 已入 | AL67: =I67 -> 501 | AM67: =I67 -> 501 | AO67: 30L | AQ67: =I67 -> 501
A68: 46125 | B68: AMAZON EU SARL, NDL DEUTSCHLAND | C68: 英国 | D68: 4500201268 | E68: 3P6NUAFE | F68: 4500201268-150 | G68: 77858-S003-MB | H68: 厨房套装 | I68: 636 | J68: 0 | K68: 3 | L68: =I68/K68 -> 212 | M68: 46167 | N68: 46164 | P68: OK | Q68: 46170 | R68: 自行排版 | S68: 空白外箱（加印带Zuru字样的最新logo，除了邮包盒直接做外箱的产品） | T68: 有 | U68: 4/29 SSCC Label | V68: 客版邮包盒(参考翻单PO#4500192979) | W68: 日期码格式：ZURU INC(BVI) 标准格式 日期：按实际生产日期 Packaging Info: Amazon DE:77EBUZMB/5NJQ3IYM/524LKUVU Amazon ES:5DTE4VLV Amazon FR:5X8Z857H/32CZCE8A/2RYJSVMM Amazon IT:5Z9TYR1E Amazon UK:7XAFEJ2S/5BSUPH4P/3P6NUAFE/3OUVPHYB DE(157114B/157140/9574/77858)/ES(157140/9574/15788G)/FR(9574/157143/157140/77858)/IT(77858)/UK(157114H/9574/77858/92146E) 1. 157114BH: --157114B:1pc 15787B 9"(Wrinkle McStinkles) into mailbox, 12mailboxes/ctn; 客版邮包盒(参考Amazon US翻单PO#4500192979); --157114H:1pc 15787H 9"(Sasquoosh) into mailbox, 12mailboxes/ctn; 客版邮包盒(参考Amazon US翻单PO#4500192979); 2. 157140:2PK 15774 into window box respectively, then into polybag, 6polybags/ctn, MA 5L(5L warning UPC)B 开窗彩盒+1张贴纸(含IT环保标+西班牙洗 涤说明,参考翻单PO#4500198613)+客版透明胶袋(双面打孔+含英法德意西警告语+塑料循环标, 参考翻单PO#4500166364)+1张UPC#贴纸(贴在胶袋上,参考翻单PO#450 0198613)+1张空白贴纸(贴在彩盒条码位置, 参考翻单PO#4500198613); 3. 157143;8PK 157117 IN MAIL BOX,12mailboxes/ctn; 8 Assortment=1:1:1:1:1:1:1:1; 客版邮包盒(参考Amazon US翻单PO#4500195274); 4. 15788G:1pc 15788G 9"(Sir Belch) in window box,then into polybag, 12polybags/ctn; Global onshelf date after 2026/7/9; MA 5L(5L warning UPC)A开 窗彩盒+MA其它最新配套包装+客版胶袋(含英法德意西荷兰警告语+双面打孔+塑料循环标,参考翻单PO#4500164364)+2张贴纸(1张含UPC#<(>&<)>IT环保标<(>&<)>ES 洗涤说明贴纸,参考翻单PO#4500198640+1张上架日期贴纸, 参考翻单PO#4500198640) 5. 77858:1pc 77858 playset into mailbox, 3mailboxes/ctn; Including magnets; 3PCS AA BATTERIES(NOT INCLUDED); MA 3L(23L warning EAN)A 透明PVC窗彩 盒+MA 23L warning A 电池黑白说明书+MA 5L A收藏指南+MA其它最新配套包装+客版邮包盒(参考翻单PO#4500192979)+WEEE_不带电池走货 _ 说明书欧洲EN+30L_B版 6. 92146E:1pc 92146E SMALL(Tiger) into shrink wraps,24pcs/ctn;Bubble powder;NO Boron; MA 3L(8L warning EAN)A收缩膜+MA其它最新配套包装+MA 5L(19L warning)A收藏指南+1张贴纸(1张UPC+IT环保标+ES洗涤说明贴纸贴纸，参考翻单PO#4500198640); 7. 9574:3-4pcs magnets included, compounds not included; 2pcs baby capybara: 3pcs baby capybara= 5:1; 3PCS AAA BATTERIES(NOT INCLUDED); 4PCS/CTN ; MA 3L(23 warning EAN) A版彩盒+MA5L(9L warning) A版说明书+2张贴纸(1张#UPC, 1张IT环保标; 贴纸翻单PO#)+WEEE_不带电池走货 _ 说明书欧洲EN+30L_B版 8. 最迟验货不得晚于5/26 9. 77858验货时需要将产品六面图， 邮包盒(含产品)测量尺寸图片<(>&<)>重量图片放进验货报告 Remark: 1.空白外箱（加印带Zuru字样的最新logo，除了邮包盒直接做外箱的产品） + SSCC LABEL一张, 无箱唛，MADE IN CHINA 外箱只印一正一侧。箱唛资料按照给定的 标准去做即可，无需发回我方再行审批(新标准将另行通知)。 (SSCC LABEL竖贴在外箱正面的正中间，贴一面即可,贴纸离外箱边距必须至少3.2CM。如竖贴无法满足要求，则横贴。如横贴也无法满足要求，则竖贴，遮到ZURU lo go无影响), SSCC贴纸由工厂直接跟勤得采购或者工厂自行采购，每一张SSCC Label都是唯一且有不同流水及条码，且需要检查条码是否能正常扫描，另外，此贴纸 印刷不可出现模糊，溢出及粘胶不牢易脱落等现象，如工厂不按此要求导致贴纸有任何问题产生的罚款将由工厂承担一切责任 ,<(>,<)> 此要求只适用Amazon UK/DE /FR/ES/IT,不适用Amazon GPE，Amazon GPE无SSCC label, 但是有对应箱唛，需印刷到外箱 。 2.出往UK的产品+包装务必打上UKCA logo ，否则客人会退货且当地会有罚款。Amazon GPE（包含UK/FR/ES/DE/IT）的订单也需满足此要求。 3.订单必须经过ZURU QC验货或者工厂自检通过后方可出货，不涉及第三方验货。 4.法国订单要求包装不使用矿物油，请按要求提供以下其中一份文件再出货 ，产品出到法国被相关部门抽检出现包装不符合此要求的，供应商需要为此承担责任， 故此请严格把关。Am~azon GPE（包含UK/FR/ES/DE/IT）的订单也需满足此要求。 -油墨物质""""由1 7个芳香环组成的MOAH""""的包装检测报告，要求限值≤1.0%； -包装材料清单，包括包装油墨或物质的信息； -油墨制造商的证书； 5.每一批次出货只能有一个生产日期，不可多个生产日期混在同一批次出货；且零售包装上必须统一加上日期码；外箱对于日期码没有硬性规定； 6.涉及到相关款式会有闪粉的或者微塑料的，请统一默认出无闪粉或者不含微塑料版本； 7.邮包盒及外箱封箱必须是工字型封箱方式； 8.5 Surprise or Mini Brands涉及包装是2个及2个以上的球入PVC桶包装时，单个球上若有UPC#或者EAN#，请用空白贴纸覆盖住，贴纸尺寸自行测量能覆盖原条码即 可； 9. 无论是工厂自检还是ZURU验货，验货报告中必须有产品6面图(正面/背面/左面/右面/顶部/底部，不带包装); 10. 按空海运鉴定报告的要求，只要带锂电池出货，都需要加贴UN贴纸； 11. 所有出往GAS市场(德国/奥地利/瑞士)的电子产品身上需要加字唛，为ZURU FRANCE 地址，需跟包装上的地址一致 (如无电子产品，产品布标有此地址，或产品 太小无法增加可忽略此信息。如产品无法加字唛，需让对应跟单提供产品贴纸资料);（Amazon GPE的订单也需满足此要求） 12. 所有出往GAS德国 (瑞士，奥地利)。水弹枪系列必须使用EN71版本（电子和非电子水弹枪系列都需要符合); 护目镜需打日期码, 格式跟ZURU标准格式一样; 枪 身上增加ZURU FRANCE公司名和地址。使用贴纸和辐射上去都可以。如果有位置，最好增加ZURU Represented by: (此最好翻译德语，如果位置不允许，那么就只增 加ZURU法国和地址)。使用最新的EN71版包装和说明书）。Amazon GPE（包含UK/FR/ES/DE/IT）的订单也需满足此要求。 | X68: Crystal Chen | Y68: 12.65 | Z68: =Y68*L68 -> 2681.8 | AB68: 77858-S003-MB-1 | AC68: 已入 | AL68: =I68 -> 636 | AM68: =I68 -> 636 | AO68: 30L | AQ68: =I68 -> 636
A69: 46125 | B69: AMAZON EU SARL, NDL DEUTSCHLAND | C69: 意大利 | D69: 4500201268 | E69: 5Z9TYR1E | F69: 4500201268-170 | G69: 77858-S003-MB | H69: 厨房套装 | I69: 501 | J69: 0 | K69: 3 | L69: =I69/K69 -> 167 | M69: 46167 | N69: 46164 | P69: OK | Q69: 46170 | R69: 自行排版 | S69: 空白外箱（加印带Zuru字样的最新logo，除了邮包盒直接做外箱的产品） | T69: 有 | U69: 4/29 SSCC Label | V69: 客版邮包盒(参考翻单PO#4500192979) | W69: 日期码格式：ZURU INC(BVI) 标准格式 日期：按实际生产日期 Packaging Info: Amazon DE:77EBUZMB/5NJQ3IYM/524LKUVU Amazon ES:5DTE4VLV Amazon FR:5X8Z857H/32CZCE8A/2RYJSVMM Amazon IT:5Z9TYR1E Amazon UK:7XAFEJ2S/5BSUPH4P/3P6NUAFE/3OUVPHYB DE(157114B/157140/9574/77858)/ES(157140/9574/15788G)/FR(9574/157143/157140/77858)/IT(77858)/UK(157114H/9574/77858/92146E) 1. 157114BH: --157114B:1pc 15787B 9"(Wrinkle McStinkles) into mailbox, 12mailboxes/ctn; 客版邮包盒(参考Amazon US翻单PO#4500192979); --157114H:1pc 15787H 9"(Sasquoosh) into mailbox, 12mailboxes/ctn; 客版邮包盒(参考Amazon US翻单PO#4500192979); 2. 157140:2PK 15774 into window box respectively, then into polybag, 6polybags/ctn, MA 5L(5L warning UPC)B 开窗彩盒+1张贴纸(含IT环保标+西班牙洗 涤说明,参考翻单PO#4500198613)+客版透明胶袋(双面打孔+含英法德意西警告语+塑料循环标, 参考翻单PO#4500166364)+1张UPC#贴纸(贴在胶袋上,参考翻单PO#450 0198613)+1张空白贴纸(贴在彩盒条码位置, 参考翻单PO#4500198613); 3. 157143;8PK 157117 IN MAIL BOX,12mailboxes/ctn; 8 Assortment=1:1:1:1:1:1:1:1; 客版邮包盒(参考Amazon US翻单PO#4500195274); 4. 15788G:1pc 15788G 9"(Sir Belch) in window box,then into polybag, 12polybags/ctn; Global onshelf date after 2026/7/9; MA 5L(5L warning UPC)A开 窗彩盒+MA其它最新配套包装+客版胶袋(含英法德意西荷兰警告语+双面打孔+塑料循环标,参考翻单PO#4500164364)+2张贴纸(1张含UPC#<(>&<)>IT环保标<(>&<)>ES 洗涤说明贴纸,参考翻单PO#4500198640+1张上架日期贴纸, 参考翻单PO#4500198640) 5. 77858:1pc 77858 playset into mailbox, 3mailboxes/ctn; Including magnets; 3PCS AA BATTERIES(NOT INCLUDED); MA 3L(23L warning EAN)A 透明PVC窗彩 盒+MA 23L warning A 电池黑白说明书+MA 5L A收藏指南+MA其它最新配套包装+客版邮包盒(参考翻单PO#4500192979)+WEEE_不带电池走货 _ 说明书欧洲EN+30L_B版 6. 92146E:1pc 92146E SMALL(Tiger) into shrink wraps,24pcs/ctn;Bubble powder;NO Boron; MA 3L(8L warning EAN)A收缩膜+MA其它最新配套包装+MA 5L(19L warning)A收藏指南+1张贴纸(1张UPC+IT环保标+ES洗涤说明贴纸贴纸，参考翻单PO#4500198640); 7. 9574:3-4pcs magnets included, compounds not included; 2pcs baby capybara: 3pcs baby capybara= 5:1; 3PCS AAA BATTERIES(NOT INCLUDED); 4PCS/CTN ; MA 3L(23 warning EAN) A版彩盒+MA5L(9L warning) A版说明书+2张贴纸(1张#UPC, 1张IT环保标; 贴纸翻单PO#)+WEEE_不带电池走货 _ 说明书欧洲EN+30L_B版 8. 最迟验货不得晚于5/26 9. 77858验货时需要将产品六面图， 邮包盒(含产品)测量尺寸图片<(>&<)>重量图片放进验货报告 Remark: 1.空白外箱（加印带Zuru字样的最新logo，除了邮包盒直接做外箱的产品） + SSCC LABEL一张, 无箱唛，MADE IN CHINA 外箱只印一正一侧。箱唛资料按照给定的 标准去做即可，无需发回我方再行审批(新标准将另行通知)。 (SSCC LABEL竖贴在外箱正面的正中间，贴一面即可,贴纸离外箱边距必须至少3.2CM。如竖贴无法满足要求，则横贴。如横贴也无法满足要求，则竖贴，遮到ZURU lo go无影响), SSCC贴纸由工厂直接跟勤得采购或者工厂自行采购，每一张SSCC Label都是唯一且有不同流水及条码，且需要检查条码是否能正常扫描，另外，此贴纸 印刷不可出现模糊，溢出及粘胶不牢易脱落等现象，如工厂不按此要求导致贴纸有任何问题产生的罚款将由工厂承担一切责任 ,<(>,<)> 此要求只适用Amazon UK/DE /FR/ES/IT,不适用Amazon GPE，Amazon GPE无SSCC label, 但是有对应箱唛，需印刷到外箱 。 2.出往UK的产品+包装务必打上UKCA logo ，否则客人会退货且当地会有罚款。Amazon GPE（包含UK/FR/ES/DE/IT）的订单也需满足此要求。 3.订单必须经过ZURU QC验货或者工厂自检通过后方可出货，不涉及第三方验货。 4.法国订单要求包装不使用矿物油，请按要求提供以下其中一份文件再出货 ，产品出到法国被相关部门抽检出现包装不符合此要求的，供应商需要为此承担责任， 故此请严格把关。Am~azon GPE（包含UK/FR/ES/DE/IT）的订单也需满足此要求。 -油墨物质""""由1 7个芳香环组成的MOAH""""的包装检测报告，要求限值≤1.0%； -包装材料清单，包括包装油墨或物质的信息； -油墨制造商的证书； 5.每一批次出货只能有一个生产日期，不可多个生产日期混在同一批次出货；且零售包装上必须统一加上日期码；外箱对于日期码没有硬性规定； 6.涉及到相关款式会有闪粉的或者微塑料的，请统一默认出无闪粉或者不含微塑料版本； 7.邮包盒及外箱封箱必须是工字型封箱方式； 8.5 Surprise or Mini Brands涉及包装是2个及2个以上的球入PVC桶包装时，单个球上若有UPC#或者EAN#，请用空白贴纸覆盖住，贴纸尺寸自行测量能覆盖原条码即 可； 9. 无论是工厂自检还是ZURU验货，验货报告中必须有产品6面图(正面/背面/左面/右面/顶部/底部，不带包装); 10. 按空海运鉴定报告的要求，只要带锂电池出货，都需要加贴UN贴纸； 11. 所有出往GAS市场(德国/奥地利/瑞士)的电子产品身上需要加字唛，为ZURU FRANCE 地址，需跟包装上的地址一致 (如无电子产品，产品布标有此地址，或产品 太小无法增加可忽略此信息。如产品无法加字唛，需让对应跟单提供产品贴纸资料);（Amazon GPE的订单也需满足此要求） 12. 所有出往GAS德国 (瑞士，奥地利)。水弹枪系列必须使用EN71版本（电子和非电子水弹枪系列都需要符合); 护目镜需打日期码, 格式跟ZURU标准格式一样; 枪 身上增加ZURU FRANCE公司名和地址。使用贴纸和辐射上去都可以。如果有位置，最好增加ZURU Represented by: (此最好翻译德语，如果位置不允许，那么就只增 加ZURU法国和地址)。使用最新的EN71版包装和说明书）。Amazon GPE（包含UK/FR/ES/DE/IT）的订单也需满足此要求。 | X69: Crystal Chen | Y69: 12.65 | Z69: =Y69*L69 -> 2112.55 | AB69: 77858-S003-MB-1 | AC69: 已入 | AL69: =I69 -> 501 | AM69: =I69 -> 501 | AO69: 30L | AQ69: =I69 -> 501
A70: 46113 | B70: KING JOUET LOGISTIQUE | C70: 法国 | D70: 4500199651 | E70: 2000009878 | F70: 4500199651-10 | G70: 77858-S001 | H70: 厨房套装 | I70: 1452 | J70: 0 | K70: 3 | L70: =I70/K70 -> 484 | M70: 46167 | N70: 46164 | O70: 5/30 验货后还会抽办1套/item，请多备料 | P70: OK | R70: 是 | S70: 46127 | T70: 无 | U70: 4/30进口商贴纸+一张产品贴纸+一张法语weee说明书纸 | W70: 日期码格式：LOT2622 日期： Packaging Info: 1. 77858：EAN彩盒+最新MA 5L收藏指南+最新MA 23L说明书+一张进口商贴纸+一张产品贴纸+一张法语weee说明书纸 Remark: 1. 大货样品2套/item，用于客人验货签板。验货后还会抽办1套/item，请多备料； 2. 客版日期码LOT2622, 包装（含收缩膜等）/产品/外箱 请保持一致。 3. 全部ITEM都用EAN条码, 全部用Mother EAN; 4. 包装必须含法国回收logo标识, 最新版ZURU logo； 5. 出法国的产品需无闪粉/不含微塑料； 6. 所有出口法国的产品, 法规规定禁止在包装和共公众用的印刷品中使用矿物油中含有的物质, 包装印刷油墨中含有的MOAH/MOSH的质量浓度不能超过1%, 否则出 货到法国被抽检出现问题, 供应商需要对此负责; 7. 所有带电产品请复核跟单是否有提供客人指定内容的WEEE说明书（非通用29L版本）；如果做了客版说明书，则会将weee说明加进客版说明书中 8. 此客户需要第三方验货，请在约三方验货前必须PASS ZURU验货。 | X70: Christine He | Y70: 9.9259 | Z70: =Y70*L70 -> 4804.1356 | AB70: 77858-S001-1 | AC70: 已入 | AL70: =I70 -> 1452 | AM70: =I70 -> 1452 | AQ70: =I70 -> 1452
A71: 46115 | B71: T. PLANET SHOPS SL | C71: 西班牙 | D71: 4500200146 | E71: 22362602 | F71: 4500200146-30 | G71: 77858-S001 | H71: 厨房套装 | I71: 3000 | J71: 0 | K71: 3 | L71: =I71/K71 -> 1000 | M71: 46167 | N71: 46164 | P71: OK | Q71: 46186 | R71: 是 | S71: 46126 | T71: 无 | U71: 4/22进口商贴纸 | W71: 日期码格式：202602 日期： Packaging Info: 1.77711GQ2：【MA 3L EAN版本包装+一张客户进口商贴纸（含西班牙环保标)】+MA 收藏指南+MA 23L说明书+MA 3L PDQ； 2.77673：【MA 3L EAN版本包装+一张客户进口商贴纸】+一张产品贴纸+MA 23L说明书+WEEE带电池走货欧洲29L通用黑白说明书； 3.77858：【MA 3L EAN版本包装+一张客户进口商贴纸】+MA 23L说明书+MA 5L收藏指南+WEEE不带电池走货欧洲29L通用黑白说明书； Remark: 1. 此单出西班牙，需满足EU测试标准要求，另外微塑料需符合EU法规； 2. 标准配比； 3.根据新电池法规（EU） 2023/1542，所有走欧洲市场的电子产品，都需要增加WEEE通用29L说明书（分带电池走货和不带电池走货两种），如工厂没有此文件，可 以找我们跟单提供； 4. 准时完货，需安排ZURU OQC验货并要求提供客户格式的自检报告给到客户审批放货。 另外，包装贴纸上面的警告语不可以覆盖西班牙警告语。 5. 此单需要每款准备3套大货样，请注意备料； 6.注意： 同款产品含PDQ /展示架的外箱条码需要跟item包装条码不一样; 7.此单客户指定日期码：202602 | X71: Mary Zhong | Y71: 10.1862 | Z71: =I71*Y71 -> 30558.6 | AB71: 77858-S001-1 | AC71: 已入 | AL71: =I71 -> 3000 | AM71: =I71 -> 3000 | AO71: 29L | AQ71: =I71 -> 3000
A72: 46094 | B72: WALMART INC. | C72: 美国 | D72: 4500196796 | E72: 0980444033 | F72: 4500196796-10 | G72: 77858-S002 | H72: 厨房套装 | I72: 1176 | J72: 0 | K72: 2 | L72: =I72/K72 -> 588 | M72: 46167 | N72: 46182 | O72: 5/28自检 | P72: OK | Q72: 6/10吊柜补料 | R72: 是 | S72: 46094 | T72: 有 | U72: 3/24RFID贴纸+粉色艾利贴纸 | W72: 日期码格式：ZURU DGMMDD CHINA(日期避开周末和法定节假日即可） 日期：按实际生产日期 Packaging Info: 77858-S002 1. 包装要求： 77858：MA 1L A版 playset +MA 5L A版收藏指南+MA 23L A版说明书+MA A版纸袋+MA 贴纸 每pcs产品要贴一张RFID贴纸，RFID贴纸由ZURU提供，贴纸位置要严格按照客人签板 Remark: 77858-S002 1. 包装要求： 77858：MA 1L A版 playset +MA 5L A版收藏指南+MA 23L A版说明书+MA A版纸袋+MA 贴纸 每pcs产品要贴一张RFID贴纸，RFID贴纸由ZURU提供，贴纸位置要严格按照客人签板 2. 外箱印刷带条码的RFID箱唛：RFID紫色色带+WM Dept.图标+RFID图标+ITF-14条码+粉色艾利贴纸（不干胶打印），四面右下角印刷ZURU logo, ITFF条码只印刷在 正唛一面，在加印的时候确保条形码能扫描出来，1张粉红色贴纸贴在正唛对角线，外箱侧面任一角落加印："MADE IN CHINA" 字样； 3. 在产品上和包装上要有日期码、以及要有MADE IN CHINA和ZURU字样； 4. 产品如有扎带口要剪平，不能刮手。 5. 此单需要验货，请多备料 6. 此单以loose carton出货，2pcs/CTN | X72: Maggie Xie | Y72: 6.5485 | Z72: =I72*Y72 -> 7701.036 | AB72: 77858-S002 | AC72: 已入 | AI72: =I72 -> 1176 | AM72: =I72 -> 1176 | AQ72: =I72 -> 1176
A73: 46094 | B73: WALMART INC. | C73: 美国 | D73: 4500196796 | E73: 0980444039 | F73: 4500196796-20 | G73: 77858-S002 | H73: 厨房套装 | I73: 1128 | J73: 0 | K73: 2 | L73: =I73/K73 -> 564 | M73: 46167 | N73: 46182 | O73: 5/28自检 | P73: OK | Q73: 6/10吊柜补料 | R73: 是 | S73: 46094 | T73: 有 | U73: 3/24RFID贴纸+粉色艾利贴纸 | W73: 日期码格式：ZURU DGMMDD CHINA(日期避开周末和法定节假日即可） 日期：按实际生产日期 Packaging Info: 77858-S002 1. 包装要求： 77858：MA 1L A版 playset +MA 5L A版收藏指南+MA 23L A版说明书+MA A版纸袋+MA 贴纸 每pcs产品要贴一张RFID贴纸，RFID贴纸由ZURU提供，贴纸位置要严格按照客人签板 Remark: 77858-S002 1. 包装要求： 77858：MA 1L A版 playset +MA 5L A版收藏指南+MA 23L A版说明书+MA A版纸袋+MA 贴纸 每pcs产品要贴一张RFID贴纸，RFID贴纸由ZURU提供，贴纸位置要严格按照客人签板 2. 外箱印刷带条码的RFID箱唛：RFID紫色色带+WM Dept.图标+RFID图标+ITF-14条码+粉色艾利贴纸（不干胶打印），四面右下角印刷ZURU logo, ITFF条码只印刷在 正唛一面，在加印的时候确保条形码能扫描出来，1张粉红色贴纸贴在正唛对角线，外箱侧面任一角落加印："MADE IN CHINA" 字样； 3. 在产品上和包装上要有日期码、以及要有MADE IN CHINA和ZURU字样； 4. 产品如有扎带口要剪平，不能刮手。 5. 此单需要验货，请多备料 6. 此单以loose carton出货，2pcs/CTN | X73: Maggie Xie | Y73: 6.5485 | Z73: =I73*Y73 -> 7386.708 | AB73: 77858-S002 | AC73: 已入 | AI73: =I73 -> 1128 | AM73: =I73 -> 1128 | AQ73: =I73 -> 1128
A74: 46115 | B74: DISTRIBUIDORA LIVERPOOL S.A DE C.V. | C74: 墨西哥 | D74: 4500199969 | E74: 62100056 | F74: 4500199969-100 | G74: 77858-S001 | H74: 厨房套装 | I74: 6000 | J74: 0 | K74: 3 | L74: =I74/K74 -> 2000 | M74: 46167 | N74: 46234 | O74: 此单有第三方监柜 | P74: OK | Q74: 46236 | R74: 是 | S74: 46139 | T74: 无 | U74: 6/26进口商贴纸+5/14价标贴纸 | V74: 6/26保证书 | W74: 日期码格式：ZURU INC(BVI) 标准格式 日期：按实际生产日期 Packaging Info: 77858/77773GQ2/9574:MA多语 包装+MA 多语说明书（含西语）+进口商贴纸+价标贴纸+保证书，包装/说明书都需要贴一张进口商贴纸 Remark: 1.此单价格贴纸（ZURU定购).-无位置图，价标贴纸贴于产品背面右上角空白处（不遮挡西班牙语处），如有特殊情况，请重新确认位置图。 2.此单有第三方监柜，不用额外准备备品，会在大货中每款拆1pc，拆了包装的产品会由监装员用客供胶带封好或在外箱上写上""opened by telescope" | X74: Ava Liang | Y74: 10.1135 | Z74: =Y74*L74 -> 20227 | AB74: 77858-S001-1 | AC74: 已入 | AL74: =I74 -> 6000 | AM74: =I74 -> 6000 | AQ74: =I74 -> 6000
A75: 46126 | B75: YUG CONTRACT | C75: 乌克兰 | D75: 4500201931 | F75: 4500201931-10 | G75: 77858-S001 | H75: 厨房套装 | I75: 600 | J75: 0 | K75: 3 | L75: =I75/K75 -> 200 | M75: 46168 | N75: 46167 | P75: OK | Q75: 46175 | R75: 是 | S75: 46139 | T75: 无 | U75: 4/29进口商贴纸+3张乌克兰警告语贴纸覆盖零售包装上的俄罗斯语言 | V75: 4/29客版不含俄罗斯语言的电池说明书（含不带电池走货WEEE说明书内容） | W75: 日期码格式：ZURU INC(BVI) 标准格式 日期：按实际生产日期 Packaging Info: 77858：A 版 3L MA EAN 包装+进口商贴纸+3张乌克兰警告语贴纸覆盖零售包装上的俄罗斯语言 ；A 版 5L MA 收藏指南/客版不含俄罗斯语言的电池说明书（含不 带电池走货WEEE说明书内容） Remark: 1、此单出欧洲需满足EU测试标准要求，另外不能出闪粉（若产品本身不含闪粉则忽略这句话），电池产品（带电池/不带电池走货）需要添加WEEE通用说明书(不含 俄罗斯语言版本) 2.若产品有比例请使用标准比例 3.此单客户的包装/说明书/收藏指南/slime polybag上均不可出现俄罗斯语言，若有我遗漏的地方请务必告知 | X75: Snowy Wu | Y75: 10.2316 | Z75: =Y75*L75 -> 2046.32 | AB75: 77858-S001-1 | AC75: 已入 | AL75: =I75 -> 600 | AM75: =I75 -> 600 | AQ75: =I75 -> 600
A76: 46129 | B76: ASMODEE ROMANIA SRL | C76: 罗马尼亚 | D76: 4500202795 | F76: 4500202795-10 | G76: 77858-S001 | H76: 厨房套装 | I76: 600 | J76: 0 | K76: 3 | L76: =I76/K76 -> 200 | M76: 46169 | N76: 46188 | P76: OK | Q76: SI 6/17 | R76: 是 | S76: 46142 | T76: 无 | U76: 5/8进口商贴纸 | W76: 日期码格式：ZURU INC(BVI) 标准格式 日期：按实际生产日期 Packaging Info: 77858：A 版 1L MA包装+进口商贴纸 ；A 版 5L MA 收藏指南/A 版 23L MA说明书+C 版 29L 不带电池走货WEEE通用说明书 Remark: 1、若产品有比例使用ZURU STD 比例 2、所有item 均用MA UPC 条码，若包装不是UPC 条码的请告知 mother UPC:193052099587 ,, 3、此单出欧洲需满足EU测试标准要求 | X76: Snowy | Y76: 10.2316 | Z76: 2046.32 | AB76: 77858-S001 | AC76: 已入 | AI76: 600 | AM76: 600 | AO76: 29L | AQ76: 600
A77: 46094 | B77: SUOMEN OSUUSKAUPPOJEN KESKUSKUNTA | C77: 芬兰 | D77: 4500196453 | E77: 188529 | F77: 4500196453-90 | G77: 77858-S001 | H77: 厨房套装 | I77: 51 | J77: 0 | K77: 3 | L77: =I77/K77 -> 17 | M77: 46170 | N77: 46167 | P77: OK | Q77: 46177 | R77: 是 | S77: 46127 | T77: 无 | U77: 4/21贴纸 | W77: 日期码格式：ZURU INC(BVI) 标准格式 日期：按实际生产日期 Packaging Info: 9. 77858: MA A3L(23L warning) EAN版彩盒+警告语/电池信息/MADE IN CHINA以上全部信息翻译成爱沙尼亚语做成贴纸贴在彩盒上+MA A23L黑白电池说明书+chang e the batteries/battery safety information/警告语翻译成爱沙尼亚语做成贴纸贴在说明书上(不能覆盖英语丹麦瑞典芬兰挪威语)+MA A版收藏指南+WEEE_不带 电池走货 _ 说明书欧洲EN+29L_C版 per bag+瑞典芬兰爱沙尼亚语警告语贴在纸袋子上(贴纸和位置图翻SOK PO#4500160378)+MA 3L PDQ+MA 5L(23L warning)收藏指南+MA 23L说明书 Remark: *. 92147+92146TQ1+9574+77843GQ1+77794UQ1+77772GQ1+77858 新款: 请在5/15各提供三套大货样给客人留底 *. 包装如含PVC,请改为PET并第一时间通知跟单 *. 产品/包装要求无硼无香，出欧洲，微塑料需合规。 *.带电池出货的产品所用到的电池需要符合欧洲电池新规(EU) 2023-1542 *.有胶袋的产品：要求产品的胶袋厚度要大于等于0.05mm *.关于贴纸，如果贴纸位置图的包装版本与大货不一致，请工厂第一时间提前提出。跟单会重新调整确认是否更新贴纸或调整位置图 *.产品/包装不含PFAS and/or Bisfenol成分, 以及不含石棉成分 *.产品条码如下: 请先检查条码是否正确再安排做货，如有问题请告知 ZURU ITEM#<(>&<)>EAN 77858-S001:4894680058729 | X77: Sheba | Y77: 10.2316 | Z77: =I77*Y77 -> 521.8116 | AB77: 77858-S001-1 | AC77: 已入 | AL77: =I77 -> 51 | AM77: =I77 -> 51 | AQ77: =I77 -> 51
A78: 46133 | B78: SMYTHS TOYS EU HQ UC | C78: 德国 | D78: 4500203141 | E78: 4400559987 | F78: 4500203141-10 | G78: 77858-S001 | H78: 厨房套装 | I78: 501 | J78: 0 | K78: 3 | L78: =I78/K78 -> 167 | M78: 46171 | N78: 46169 | P78: OK | Q78: 46177 | R78: 是 | S78: 46141 | T78: 无 | U78: 德语callout贴纸(翻PO#4500192949 )+ZURU FRANCE 地址贴 | W78: 日期码格式：ZURU INC(BVI) 标准格式 日期：按实际生产日期 Packaging Info: "77858: 最新MA3L-23Lwarning EAN彩盒+1张德语callout贴纸(翻PO#4500192949 )+MA蔬菜盒子贴纸+MA复合袋+MA23L说明书+MA5L收藏指南+C版WEEE声明(不带电池) 走货欧洲通用29L说明书 EAN#4894680058729" Remark: Smyths 德国 1. 请准时出货，推期会有罚款； 2. 所有产品按符合欧洲标准走货，需要是不含微塑料版本。 3. 所有电子产品身上需要加字唛，为ZURU FRANCE 地址 (如无电子产品，产品布标有此地址，或产品太小无法增加可忽略此信息)，新地址ZURU FRANCE.33 rue Pa ul Meurice 75020 Paris, France. 4. 包装/说明书(如有)/产品(如有)上的法国地址信息必须保持一致，不可出现包装上是新地址，说明书上是旧地址；如地址信息不一致请通知跟单更新文件； 5. 电子产品需增加一张C版WEEE声明29L通用黑白说明书(不接受A版本，翻译有误)，区分带电池和不带电池出货版本, 如已做客版说明书可忽略此要求；如包装备注 上缺少此部分信息，请提醒跟单更新备注。 6.所有出往德国市场有关slime和带香味的都需要出无硼无香版本； 7.订单备注显示有分批的(不同仓库/订单号), 一定要区分客户订单号做货出货，否则会导致罚款 。 8.包装日期码按ZURU格式即可，请确保不迟于外箱日期码，可等于或者早于外箱日期码，必须为法定工作日。 9.做货前请先复核包装条码与订单是否一致再安排，对不上的需与ZURU跟单确认再安排。 10.包装必须含法国回收标(Sorting Label)，如没有，请提醒跟单提供贴纸资料。 | X78: Sherry Lu | Y78: 10.2316 | Z78: 1708.6772 | AB78: 77858-S001-1 | AC78: 已入 | AL78: 501 | AM78: 501 | AO78: 29L | AQ78: 501
A79: 46115 | B79: PT. STAKOM TRIJAYA ANDALA | C79: 印度尼西亚 | D79: 4500200184 | F79: 4500200184-30 | G79: 77858-S001 | H79: 厨房套装 | I79: 300 | J79: 0 | K79: 3 | L79: =I79/K79 -> 100 | M79: 46171 | N79: 46169 | P79: OK | Q79: 46176 | R79: 是 | S79: 46125 | T79: 无 | U79: 5/8 SNI label | W79: 日期码格式：ZURU INC(BVI) 标准格式 日期：按实际生产日期 Packaging Info: 1.MA UPC(优先1L) package+SNI label;贴纸资料待提供; 2.此单是交SZ 普通仓库跟客人其他货一起拼柜,无散货进仓费,是按照整柜的本地费收费标准; PO先开出厂价,发票请按照出厂价开,如有问题,请在出发票前同我沟通以防后续修改事项; 3.可能会需样板做测试, 也有可能有第三方验货,请等我们进一步通知; 4.玩具订单一般都是第三方视频验货,实际不会有第三方的人到厂验货; 需按照客人要求提供2轮照片; 第一轮是产品包装/纸箱/堆码等情况下的照片; 第二轮是VO number打印出来,站在货物前的照片;待提供VO number,靠近货期才有; 照片标准可参考此客人前期出货的订单,做完货请帮忙同步提供照片; Remark: 77843GQ1-Ratio: PIZZA: HAMBURGER: PANCAKES: BUBBLE TEA: Matcha TEA: TACO: SUSHI: DONUT: Charcuterie Board: RAINBOW CAKE(Rare)=10.88%: 10.88%: 1 0.88%: 10.88%: 10.88%: 10.88%: 10.88%: 10.88%: 10.88%: 2.08%=68:68:68:68:68:68:68:68:68:13 77772GQ1-4 mini vinyls,1 accessory | X79: Emma Wu | Y79: 10.2316 | Z79: =I79*Y79 -> 3069.48 | AB79: 77858-S001 | AC79: 已入 | AI79: =I79 -> 300 | AM79: =I79 -> 300 | AQ79: =I79 -> 300
A80: 46129 | B80: ESAL ENTERPRISES FZC | C80: 沙特 | D80: 4500202631 | F80: 4500202631-50 | G80: 77858-S001 | H80: 厨房套装 | I80: 600 | J80: 0 | K80: 3 | L80: =I80/K80 -> 200 | M80: 46171 | N80: 46185 | P80: OK | Q80: 最晚6/15完货 | R80: 是 | S80: 46132 | T80: 无 | U80: 5/11进口商贴纸 (含G Mark, QR code, 阿拉伯警语)AW翻单4500202382。 | W80: 日期码格式：ZURU INC(BVI) 标准格式 日期：按实际生产日期 Packaging Info: 出KSA, 所有包装不能有希伯来语（HE), 所有RBC的产品（内外）包装上都不能有彩虹 所有包装含说明书，说明书上都需要有阿拉伯语（AR)， 或者带单独的阿拉伯语（AR)说明书出货。 77858:MA 1L PKG+进口商贴纸 (含G Mark, QR code, 阿拉伯警语); 贴纸上的QR code需微信可扫; 扫描结果另外通知； UPC条码显示193052100238；含MA说明书， 需加一张黑白印刷的阿拉伯语说明纸一起出货， AW翻单4500202382。 客人箱唛排版，印4面，条码内容193052100238 Remark: | X80: Doris Shou | Y80: 10.2316 | Z80: 6138.96 | AB80: 77858-S001 | AC80: 已入 | AI80: 600 | AM80: 600 | AQ80: 600
A81: 46122 | B81: TARGET AUSTRALIA PTY LTD | C81: 澳大利亚 | D81: 4500200900 | E81: 2609268 | F81: 4500200900-10 | G81: 77858-S001 | H81: 厨房套装 | I81: 1500 | J81: 0 | K81: 3 | L81: =I81/K81 -> 500 | M81: 46174 | N81: =M81-4 -> 46170 | P81: OK | Q81: 46176 | R81: 是 | S81: 46122 | T81: 有 | U81: 5/20外箱SSCC label | W81: 日期码格式：ZURU INC(BVI) 标准格式 日期：按实际生产日期 Packaging Info: 77858：英文MA包装UPC版本（首选1L，无1L可选多语）+ 外箱SSCC label； Rare: 1/48 Common: Equal ratio" Remark: 1. 客人要求箱唛不可出现任何手写内容，重量与实际一致且不可手写; 2. 此单去澳大利亚，请按相应澳新标准生产; 3. 取消使用TARGET新版封箱胶封顶，外箱全部使用普通透明封箱胶纸(客版胶纸如还有库存，可先消耗库存)； 4. 外箱需要贴Target SSCC LABEL,客供PDF文档，工厂自行订购。请贴在正唛右下角（一箱一张，贴1面正唛右下角,封箱胶纸不能挡住贴纸内容。)；外箱贴纸距离 外箱边缘应在2cm以上。如果正唛无位置可以贴在侧唛； 5. SSCC LABEL要求：贴纸内容，条形码印刷不完整/不清晰或有划痕/缺失，贴纸脏污、破损、条形码折叠、翘起、重复或者丢失，以及封箱胶盖住贴纸任何位置的 ,客户都不能接受，如有发现以上异常，须返工重新贴； 6. 外箱材质为ZURU标准； 7. 产品和包装上要有tracking label信息：格式为Zuru标准格式（可以自行调整具体年月日生产日期,避开节假期日）； 8. SSCC Label 尺寸更新为：4x4 inch。 | X81: Christine Liao | Y81: 9.9259 | Z81: =I81*Y81 -> 14888.85 | AB81: 77858-S001 | AC81: 已入 | AI81: =I81 -> 1500 | AM81: =I81 -> 1500 | AQ81: =I81 -> 1500
A82: 46133 | B82: TARGET US | C82: 美国 | D82: 4500203038 | E82: 10001846427-0581 | F82: 4500203038-10 | G82: 77858-S001 | H82: 厨房套装 | I82: 10002 | J82: 0 | K82: 3 | L82: =I82/K82 -> 3334 | M82: 46176 | N82: 46174 | P82: OK | Q82: 46183 | R82: 是 | S82: 46140 | T82: 无 | U82: 5/9条码贴纸 | W82: 日期码格式：ZURU INC(BVI) 标准格式 日期：按实际生产日期 Packaging Info: 产品包装 MA 1L 彩盒 Remark: 1. 77858-S001-MINI BRANDS-MAGIC COOK KITCHEN PLAYSET-SERIES 1-WINDOW BOX,3PCS/CTN; 2. 产品包装 MA 1L 彩盒，彩盒上的UPC显示193052100238; 3. 外箱正唛左上角位置粘贴条码箱贴纸，每箱只贴一张，由ZURU订购。来料贴纸上显示的客户DPCI: 086-02-5654, UPC显示10193052100235; 4. 产品和包装上均要印刷tracking code信息，格式为ZURU常规格式； 5. 需要我司QC验货之后才能安排出货 6. 出货方式： 货代自提 | X82: Holly Zheng | Y82: 5.87 | Z82: 58711.74 | AB82: 77858-S001 | AC82: 已入 | AI82: =I82 -> 10002 | AM82: =I82 -> 10002 | AQ82: =I82 -> 10002
A83: 46136 | B83: WALMART INC. | C83: 美国 | D83: 4500203516 | E83: 0983717805 | F83: 4500203516-30 | G83: 77858-S002 | H83: 厨房套装 | I83: 500 | J83: 0 | K83: 2 | L83: =I83/K83 -> 250 | M83: 46176 | N83: 46183 | O83: 6/12自检 | P83: OK | S83: 箱唛翻单：4500195615 | T83: 无 | U83: 5/7RFID贴纸 | W83: 日期码格式：ZURU DGYYMMDD CHINA(日期避开周末和法定节假日即可） 日期：按实际生产日期 Packaging Info: 77858-S002 1. 包装要求： 77858：MA 1L A版 playset +MA 5L A版收藏指南+MA 23L A版说明书+MA A版纸袋+MA 贴纸 每pcs产品要贴一张RFID贴纸，RFID贴纸由ZURU提供，贴纸位置要严格按照客人签板 Remark: 77858-S002 1. 包装要求： 77858：MA 1L A版 playset +MA 5L A版收藏指南+MA 23L A版说明书+MA A版纸袋+MA 贴纸 每pcs产品要贴一张RFID贴纸，RFID贴纸由ZURU提供，贴纸位置要严格按照客人签板 2. 外箱印刷带条码的RFID箱唛：RFID紫色色带+WM Dept.图标+RFID图标+ITF-14条码，四面右下角印刷ZURU logo, ITFF条码只印刷在正唛一面，在加印的时候确保 条形码能扫描出来，外箱侧面任一角落加印："MADE IN CHINA" 字样；箱唛翻单：4500195615 3. 在产品上和包装上要有日期码、以及要有MADE IN CHINA和ZURU字样； 4. 产品如有扎带口要剪平，不能刮手。 5. 此单需要验货，请多备料 6. 此单以loose carton出货，2pcs/CTN | X83: Maggie Xie | Y83: 6.5485 | Z83: =I83*Y83 -> 3274.25 | AB83: 77858-S002 | AC83: 已入 | AI83: =I83 -> 500 | AM83: =I83 -> 500 | AQ83: =I83 -> 500
A84: 46136 | B84: WALMART INC. | C84: 美国 | D84: 4500203516 | E84: 0983717810 | F84: 4500203516-10 | G84: 77858-S002 | H84: 厨房套装 | I84: 500 | J84: 0 | K84: 2 | L84: =I84/K84 -> 250 | M84: 46176 | N84: 46184 | O84: 6/12自检 | P84: OK | Q84: 46188 | S84: 箱唛翻单：4500195615 | T84: 无 | U84: 5/7RFID贴纸 | W84: 日期码格式：ZURU DGYYMMDD CHINA(日期避开周末和法定节假日即可） 日期：按实际生产日期 Packaging Info: 77858-S002 1. 包装要求： 77858：MA 1L A版 playset +MA 5L A版收藏指南+MA 23L A版说明书+MA A版纸袋+MA 贴纸 每pcs产品要贴一张RFID贴纸，RFID贴纸由ZURU提供，贴纸位置要严格按照客人签板 Remark: 77858-S002 1. 包装要求： 77858：MA 1L A版 playset +MA 5L A版收藏指南+MA 23L A版说明书+MA A版纸袋+MA 贴纸 每pcs产品要贴一张RFID贴纸，RFID贴纸由ZURU提供，贴纸位置要严格按照客人签板 2. 外箱印刷带条码的RFID箱唛：RFID紫色色带+WM Dept.图标+RFID图标+ITF-14条码，四面右下角印刷ZURU logo, ITFF条码只印刷在正唛一面，在加印的时候确保 条形码能扫描出来，外箱侧面任一角落加印："MADE IN CHINA" 字样；箱唛翻单：4500195615 3. 在产品上和包装上要有日期码、以及要有MADE IN CHINA和ZURU字样； 4. 产品如有扎带口要剪平，不能刮手。 5. 此单需要验货，请多备料 6. 此单以loose carton出货，2pcs/CTN | X84: Maggie Xie | Y84: 6.5485 | Z84: =I84*Y84 -> 3274.25 | AB84: 77858-S002 | AC84: 已入 | AI84: =I84 -> 500 | AM84: =I84 -> 500 | AQ84: =I84 -> 500
A85: 46136 | B85: WALMART INC. | C85: 美国 | D85: 4500203516 | E85: 0983717839 | F85: 4500203516-20 | G85: 77858-S002 | H85: 厨房套装 | I85: 500 | J85: 0 | K85: 2 | L85: =I85/K85 -> 250 | M85: 46176 | N85: 46185 | O85: 46188 | P85: OK | Q85: 46202 | S85: 箱唛翻单：4500195615 | T85: 无 | U85: 5/7RFID贴纸 | W85: 日期码格式：ZURU DGYYMMDD CHINA(日期避开周末和法定节假日即可） 日期：按实际生产日期 Packaging Info: 77858-S002 1. 包装要求： 77858：MA 1L A版 playset +MA 5L A版收藏指南+MA 23L A版说明书+MA A版纸袋+MA 贴纸 每pcs产品要贴一张RFID贴纸，RFID贴纸由ZURU提供，贴纸位置要严格按照客人签板 Remark: 77858-S002 1. 包装要求： 77858：MA 1L A版 playset +MA 5L A版收藏指南+MA 23L A版说明书+MA A版纸袋+MA 贴纸 每pcs产品要贴一张RFID贴纸，RFID贴纸由ZURU提供，贴纸位置要严格按照客人签板 2. 外箱印刷带条码的RFID箱唛：RFID紫色色带+WM Dept.图标+RFID图标+ITF-14条码，四面右下角印刷ZURU logo, ITFF条码只印刷在正唛一面，在加印的时候确保 条形码能扫描出来，外箱侧面任一角落加印："MADE IN CHINA" 字样；箱唛翻单：4500195615 3. 在产品上和包装上要有日期码、以及要有MADE IN CHINA和ZURU字样； 4. 产品如有扎带口要剪平，不能刮手。 5. 此单需要验货，请多备料 6. 此单以loose carton出货，2pcs/CTN | X85: Maggie Xie | Y85: 6.5485 | Z85: =I85*Y85 -> 3274.25 | AB85: 77858-S002 | AC85: 已入 | AI85: =I85 -> 500 | AM85: =I85 -> 500 | AQ85: =I85 -> 500
A86: 46140 | B86: ASIA GOAL LIMITED | C86: 香港 | D86: 4500204383 | E86: AG260022-HK | F86: 4500204383-70 | G86: 77858-S001 | H86: 厨房套装 | I86: 240 | J86: 0 | K86: 3 | L86: =I86/K86 -> 80 | M86: 46178 | N86: 46188 | P86: OK | Q86: 6/18送外厂 | R86: 是 | S86: 46140 | T86: 无 | U86: 5/13HK客供警语贴纸+1张HK电池警语贴纸（都贴彩盒背面）+1张HK客供中文说明书 | V86: 5/13客供中文说明书 | W86: 日期码格式：ZURU INC(BVI) 标准格式 日期：按实际生产日期 Packaging Info: 77858: MA PKG , 优先1L+ 1张HK客供警语贴纸+1张HK电池警语贴纸（都贴彩盒背面）+1张HK客供中文说明书 所有贴纸不得遮挡日期码 Remark: 此单出HK | X86: Chelsea Luo | Y86: 9.9425 | Z86: =I86*Y86 -> 2386.2 | AB86: 77858-S001 | AC86: 已入 | AI86: =I86 -> 240 | AM86: =I86 -> 240 | AQ86: =I86 -> 240
A87: 46127 | B87: KING JOUET LOGISTIQUE | C87: 法国 | D87: 4500202216 | E87: 2000010089 | F87: 4500202216-10 | G87: 77858-S001 | H87: 厨房套装 | I87: 1299 | J87: 0 | K87: 3 | L87: =I87/K87 -> 433 | M87: 46178 | N87: 46189 | O87: 46191 | P87: OK | Q87: 46218 | R87: 是 | S87: 46149 | T87: 无 | U87: 进口商贴纸+一张产品贴纸+一张法语weee说明书纸，都翻4500199651 | W87: 日期码格式：LOT2623 日期： Packaging Info: 1. 77858：最新MA 3L EAN彩盒+最新MA 5L收藏指南+最新MA 23L说明书+一张进口商贴纸+一张产品贴纸+一张法语weee说明书纸，都翻4500199651 2. 客版日期码LOT2623, 包装（含收缩膜等）/产品/外箱 请保持一致。 3. 全部ITEM都用EAN条码, 全部用Mother EAN; 4. 包装必须含法国回收logo标识, 最新版ZURU logo； 5. 出法国的产品需无闪粉/不含微塑料； 6. 所有出口法国的产品, 法规规定禁止在包装和共公众用的印刷品中使用矿物油中含有的物质, 包装印刷油墨中含有的MOAH/MOSH的质量浓度不能超过1%, 否则出 货到法国被抽检出现问题, 供应商需要对此负责; 7. 所有带电产品请复核跟单是否有提供客人指定内容的WEEE说明书（非通用29L版本）；如果做了客版说明书，则会将weee说明加进客版说明书中 8. 此客户需要第三方验货，请在约三方验货前必须PASS ZURU验货。 | X87: Christine He | Y87: 9.9259 | Z87: =Y87*L87 -> 4297.9147 | AB87: 77858-S001-1 | AC87: 已入 | AL87: =I87 -> 1299 | AM87: =I87 -> 1299 | AQ87: =I87 -> 1299
A88: 46129 | B88: TESCO CE | C88: 斯洛伐克 | D88: 4500202652 | E88: 999-81742 | F88: 4500202652-50 | G88: 77858-S001 | H88: 厨房套装 | I88: 651 | J88: 0 | K88: 3 | L88: =I88/K88 -> 217 | M88: 46181 | N88: 46177 | P88: OK | Q88: 46203 | R88: 是 | S88: 46163 | T88: 无 | U88: 5/8条码贴纸 | W88: 日期码格式：ZURU INC(BVI) 标准格式 日期：按实际生产日期 Packaging Info: "77858：MA 最新3L包装含四国警告语贴纸Czech-Hugarian-Polish-Slovak)+1张UPC条码贴纸，MA最新黑白说明书+WEEE不带电池走货欧洲29语通用黑白说明书+MA最 新收藏指南+MA内袋/贴纸； UPC#193052100238，请先检查包装条码是否正确再安排做货；" Remark: 1.此单出欧洲国家，需满足EU测试标准，微塑料需满足EU法规要求； 2.产品及包装需要印CE <(>&<)> UKCA图标，包装需要有ZURU UK LTD/ZURU France地址信息，QC同事请核查，如有问题与跟单确认； 3.裝櫃必須按TPND順序(TPND的号码由大到小或由小到大) (條形碼貼紙或正嘜必須要朝外向車門外)； 4. 外箱上有条码要求，排版时请留意并请确保条码清晰可扫描（封箱胶不要黏到条码上), 否则客人会有罚款； 5.如含硼的话， 需用低硼版本(小于300ppm),硼含量需要符合欧洲标准,否则客人会退货有罚款产生; 6.标准配比； 7.货物不能用打包带缠绕外箱，否则会影响目的港派送及可能产生额外的拆打包带费用 8.请多备料，需安排2套大货样寄到深圳办公室 | X88: Mary Zhong | Y88: 10.2316 | Z88: 6660.7716 | AB88: 77858-S001-1 | AC88: 已入 | AL88: =I88 -> 651 | AM88: 651 | AO88: 29L | AQ88: 651
A89: 46129 | B89: UNFI WHOLESALE INC | C89: 美国 | D89: 4500198397 | E89: R25654196111826 | F89: 4500198397-60 | G89: 77858-S001 | H89: 厨房套装 | I89: 30 | J89: 0 | K89: 3 | L89: =I89/K89 -> 10 | M89: 46181 | N89: 46178 | P89: OK | Q89: 46238 | R89: 是 | S89: 46154 | T89: 无 | U89: 无 | W89: 日期码格式：ZURU INC(BVI) 标准格式 日期：按实际生产日期 Packaging Info: 优先ZURU MA 1L包装，显示ZURU UPC条码，出口美国 Remark: 1、无第三方测试和验货；Zuru QC 验货即可出货； 2、如果产品含塑胶袋，厚度小于1/1000 inch（0.0254 毫米），需印警告语 | X89: Angel Lin | Y89: 6.139 | Z89: 184.17 | AB89: 77858-S001 | AC89: 已入 | AI89: 30 | AM89: 30 | AQ89: 30
A90: 46129 | B90: UNFI WHOLESALE INC | C90: 美国 | D90: 4500202661 | E90: R25654291176483 | F90: 4500202661-60 | G90: 77858-S001 | H90: 厨房套装 | I90: 3 | J90: 0 | K90: 3 | L90: =I90/K90 -> 1 | M90: 46181 | N90: 46178 | P90: OK | Q90: 46202 | R90: 是 | S90: 46154 | T90: 无 | U90: 无 | W90: 日期码格式：ZURU INC(BVI) 标准格式 日期：按实际生产日期 Packaging Info: 优先ZURU MA 1L包装，显示ZURU UPC条码，出口美国 Remark: 1、无第三方测试和验货；Zuru QC 验货即可出货； 2、如果产品含塑胶袋，厚度小于1/1000 inch（0.0254 毫米），需印警告语 | X90: Angel Lin | Y90: 6.1367 | Z90: 18.4101 | AB90: 77858-S001 | AC90: 已入 | AI90: 3 | AM90: 3 | AQ90: 3
A91: 46122 | B91: SMYTHS TOYS EU HQ UNLIMITED COMPANY | C91: 法国 | D91: 4500201090 | E91: 4400555640 | F91: 4500201090-50 | G91: 77858-S001 | H91: 厨房套装 | I91: 402 | J91: 0 | K91: 3 | L91: =I91/K91 -> 134 | M91: 46181 | N91: 46182 | P91: OK | Q91: 6/10送外厂 | R91: 是 | S91: 46128 | T91: 无 | U91: MA蔬菜盒子贴纸 | W91: 日期码格式：ZURU INC(BVI) 标准格式 日期：按实际生产日期 Packaging Info: "77858: 最新MA3L-23Lwarning EAN彩盒+MA蔬菜盒子贴纸+MA复合袋+MA23L说明书+MA5L收藏指南+C版WEEE声明(不带电池)走货欧洲通用29L说明书 EAN#4894680058729" Remark: Smyths 法国 1. 请准时出货，推期会有罚款； 2. 所有产品按符合欧洲标准走货，需要是不含微塑料版本。 3. 电子产品需增加一张C版WEEE声明29L通用黑白说明书(不接受A版本，翻译有误)，区分带电池和不带电池出货版本, 如已做客版说明书可忽略此要求；如包装备注 上缺少此部分信息，请提醒跟单更新备注。 4. 出口法国的产品, 法规规定禁止在包装和共公众用的印刷品中使用矿物油中含有的物质, 包装印刷油墨中含有的MOAH/MOSH的质量浓度不能超过0.1%, 否则出货 到法国被抽检出现问题, 供应商需要对此负责; 5.订单备注显示有分批的(不同仓库/订单号), 一定要区分客户订单号做货出货，否则会导致罚款 。 6.包装日期码按ZURU格式即可，请确保不迟于外箱日期码，可等于或者早于外箱日期码，必须为法定工作日。 7.做货前请先复核包装条码与订单是否一致再安排，对不上的需与ZURU跟单确认再安排。 8.包装必须含法国回收标(Sorting Label)，如没有，请提醒跟单提供贴纸资料。 | X91: Sherry Lu | Y91: 10.2316 | Z91: =I91*Y91 -> 4113.1032 | AB91: 77858-S001-1 | AC91: 已入 | AL91: =I91 -> 402 | AM91: =I91 -> 402 | AO91: 29L | AQ91: =I91 -> 402
A92: 46122 | B92: SMYTHS TOYS EU HQ UNLIMITED COMPANY | C92: 法国 | D92: 4500201090 | E92: 4400555641 | F92: 4500201090-90 | G92: 77858-S001 | H92: 厨房套装 | I92: 201 | J92: 0 | K92: 3 | L92: =I92/K92 -> 67 | M92: 46181 | N92: 46182 | P92: OK | Q92: 6/10送外厂 | R92: 是 | S92: 46128 | T92: 无 | U92: MA蔬菜盒子贴纸 | W92: 日期码格式：ZURU INC(BVI) 标准格式 日期：按实际生产日期 Packaging Info: "77858: 最新MA3L-23Lwarning EAN彩盒+MA蔬菜盒子贴纸+MA复合袋+MA23L说明书+MA5L收藏指南+C版WEEE声明(不带电池)走货欧洲通用29L说明书 EAN#4894680058729" Remark: Smyths 法国 1. 请准时出货，推期会有罚款； 2. 所有产品按符合欧洲标准走货，需要是不含微塑料版本。 3. 电子产品需增加一张C版WEEE声明29L通用黑白说明书(不接受A版本，翻译有误)，区分带电池和不带电池出货版本, 如已做客版说明书可忽略此要求；如包装备注 上缺少此部分信息，请提醒跟单更新备注。 4. 出口法国的产品, 法规规定禁止在包装和共公众用的印刷品中使用矿物油中含有的物质, 包装印刷油墨中含有的MOAH/MOSH的质量浓度不能超过0.1%, 否则出货 到法国被抽检出现问题, 供应商需要对此负责; 5.订单备注显示有分批的(不同仓库/订单号), 一定要区分客户订单号做货出货，否则会导致罚款 。 6.包装日期码按ZURU格式即可，请确保不迟于外箱日期码，可等于或者早于外箱日期码，必须为法定工作日。 7.做货前请先复核包装条码与订单是否一致再安排，对不上的需与ZURU跟单确认再安排。 8.包装必须含法国回收标(Sorting Label)，如没有，请提醒跟单提供贴纸资料。 | X92: Sherry Lu | Y92: 10.2316 | Z92: =I92*Y92 -> 2056.5516 | AB92: 77858-S001-1 | AC92: 已入 | AL92: =I92 -> 201 | AM92: =I92 -> 201 | AO92: 29L | AQ92: =I92 -> 201
A93: 46129 | B93: UNFI WHOLESALE INC | C93: 美国 | D93: 4500202682 | E93: R25654343377912 | F93: 4500202682-60 | G93: 77858-S001 | H93: 厨房套装 | I93: 3 | J93: 0 | K93: 3 | L93: =I93/K93 -> 1 | M93: 46181 | N93: 46182 | P93: OK | Q93: 46183 | R93: 是 | S93: 46151 | T93: 无 | U93: 无 | W93: 日期码格式：ZURU INC(BVI) 标准格式 日期：按实际生产日期 Packaging Info: 优先ZURU MA 1L包装，显示ZURU UPC条码，出口美国 Remark: 1、无第三方测试和验货；Zuru QC 验货即可出货； 2、如果产品含塑胶袋，厚度小于1/1000 inch（0.0254 毫米），需印警告语 | X93: Angel Lin | Y93: 5.9667 | Z93: 17.9001 | AB93: 77858-S001 | AC93: 已入 | AI93: 3 | AM93: 3 | AQ93: 3
A94: 46134 | B94: IMPERIAL DISTRIBUTOR | C94: 美国 | D94: 4500203270 | E94: 660860 | F94: 4500203270-30 | G94: 77858-S001 | H94: 厨房套装 | I94: 24 | J94: 0 | K94: 3 | L94: =I94/K94 -> 8 | M94: 46181 | N94: 46189 | P94: OK | Q94: 46191 | R94: 是 | S94: 46136 | T94: 无 | U94: 无 | W94: 日期码格式：ZURU INC(BVI) 标准格式 日期：按实际生产日期 Packaging Info: 1. ZURU MA UPC 优先1L 最新包装，版本统一，不得混包材， 出口美国 2. 产品和包装需有日期码, ZURU标准日期码格式, 按照实际生产自行调整日期,但不能为周末,日期保持一致。 Remark: 1. ZURU MA UPC 优先1L 最新包装，版本统一，不得混包材， 出口美国 2. 产品和包装需有日期码, ZURU标准日期码格式, 按照实际生产自行调整日期,但不能为周末,日期保持一致。 "3. 大货配比：产品配比按照MA标准配比执行。 GTIN: 15783UQ1-S002：101-93052-09969-0 15785-S001：101-93052-09946-1 77858-S001：101-93052-10023-5 77711GQ2-S002-NA：101-93052-08012-4 77673TQ1-S001：101-93052-07940-1 | X94: Yvonne Feng | Y94: 6.1392 | Z94: 147.3408 | AB94: 77858-S001 | AC94: 已入 | AI94: 24 | AM94: 24 | AQ94: 24
A95: 46136 | B95: WALMART INC. | C95: 美国 | D95: 4500203539 | E95: 0983717813 | F95: 4500203539-20 | G95: 77858-S002 | H95: 厨房套装 | I95: 500 | J95: 0 | K95: 2 | L95: =I95/K95 -> 250 | M95: 46182 | N95: 46185 | O95: 46188 | P95: OK | Q95: 46191 | S95: 箱唛翻单：4500195615 | T95: 无 | U95: 5/7RFID贴纸 | W95: 日期码格式：ZURU DGYYMMDD CHINA(日期避开周末和法定节假日即可） 日期：按实际生产日期 Packaging Info: 77858-S002 1. 包装要求： 77858：MA 1L A版 playset +MA 5L A版收藏指南+MA 23L A版说明书+MA A版纸袋+MA 贴纸 每pcs产品要贴一张RFID贴纸，RFID贴纸由ZURU提供，贴纸位置要严格按照客人签板 Remark: 77858-S002 1. 包装要求： 77858：MA 1L A版 playset +MA 5L A版收藏指南+MA 23L A版说明书+MA A版纸袋+MA 贴纸 每pcs产品要贴一张RFID贴纸，RFID贴纸由ZURU提供，贴纸位置要严格按照客人签板 2. 外箱印刷带条码的RFID箱唛：RFID紫色色带+WM Dept.图标+RFID图标+ITF-14条码，四面右下角印刷ZURU logo, ITFF条码只印刷在正唛一面，在加印的时候确保 条形码能扫描出来，外箱侧面任一角落加印："MADE IN CHINA" 字样；箱唛翻单：4500195615 3. 在产品上和包装上要有日期码、以及要有MADE IN CHINA和ZURU字样； 4. 产品如有扎带口要剪平，不能刮手。 5. 此单需要验货，请多备料 6. 此单以loose carton出货，2pcs/CTN | X95: Maggie Xie | Y95: 6.5485 | Z95: =I95*Y95 -> 3274.25 | AB95: 77858-S002 | AC95: 已入 | AI95: =I95 -> 500 | AM95: =I95 -> 500 | AQ95: =I95 -> 500
A96: 46136 | B96: WALMART INC. | C96: 美国 | D96: 4500203539 | E96: 0983717941 | F96: 4500203539-30 | G96: 77858-S002 | H96: 厨房套装 | I96: 500 | J96: 0 | K96: 2 | L96: =I96/K96 -> 250 | M96: 46182 | N96: 46185 | O96: 46188 | P96: OK | Q96: 46190 | S96: 箱唛翻单：4500195615 | T96: 无 | U96: 5/7RFID贴纸 | W96: 日期码格式：ZURU DGYYMMDD CHINA(日期避开周末和法定节假日即可） 日期：按实际生产日期 Packaging Info: 77858-S002 1. 包装要求： 77858：MA 1L A版 playset +MA 5L A版收藏指南+MA 23L A版说明书+MA A版纸袋+MA 贴纸 每pcs产品要贴一张RFID贴纸，RFID贴纸由ZURU提供，贴纸位置要严格按照客人签板 Remark: 77858-S002 1. 包装要求： 77858：MA 1L A版 playset +MA 5L A版收藏指南+MA 23L A版说明书+MA A版纸袋+MA 贴纸 每pcs产品要贴一张RFID贴纸，RFID贴纸由ZURU提供，贴纸位置要严格按照客人签板 2. 外箱印刷带条码的RFID箱唛：RFID紫色色带+WM Dept.图标+RFID图标+ITF-14条码，四面右下角印刷ZURU logo, ITFF条码只印刷在正唛一面，在加印的时候确保 条形码能扫描出来，外箱侧面任一角落加印："MADE IN CHINA" 字样；箱唛翻单：4500195615 3. 在产品上和包装上要有日期码、以及要有MADE IN CHINA和ZURU字样； 4. 产品如有扎带口要剪平，不能刮手。 5. 此单需要验货，请多备料 6. 此单以loose carton出货，2pcs/CTN | X96: Maggie Xie | Y96: 6.5485 | Z96: =I96*Y96 -> 3274.25 | AB96: 77858-S002 | AC96: 已入 | AI96: =I96 -> 500 | AM96: =I96 -> 500 | AQ96: =I96 -> 500
A97: 46136 | B97: WALMART INC. | C97: 美国 | D97: 4500203539 | E97: 0983717769 | F97: 4500203539-10 | G97: 77858-S002 | H97: 厨房套装 | I97: 500 | J97: 0 | K97: 2 | L97: =I97/K97 -> 250 | M97: 46182 | N97: 46189 | O97: 46191 | P97: OK | Q97: 46200 | S97: 箱唛翻单：4500195615 | T97: 无 | U97: 5/7RFID贴纸 | W97: 日期码格式：ZURU DGYYMMDD CHINA(日期避开周末和法定节假日即可） 日期：按实际生产日期 Packaging Info: 77858-S002 1. 包装要求： 77858：MA 1L A版 playset +MA 5L A版收藏指南+MA 23L A版说明书+MA A版纸袋+MA 贴纸 每pcs产品要贴一张RFID贴纸，RFID贴纸由ZURU提供，贴纸位置要严格按照客人签板 Remark: 77858-S002 1. 包装要求： 77858：MA 1L A版 playset +MA 5L A版收藏指南+MA 23L A版说明书+MA A版纸袋+MA 贴纸 每pcs产品要贴一张RFID贴纸，RFID贴纸由ZURU提供，贴纸位置要严格按照客人签板 2. 外箱印刷带条码的RFID箱唛：RFID紫色色带+WM Dept.图标+RFID图标+ITF-14条码，四面右下角印刷ZURU logo, ITFF条码只印刷在正唛一面，在加印的时候确保 条形码能扫描出来，外箱侧面任一角落加印："MADE IN CHINA" 字样；箱唛翻单：4500195615 3. 在产品上和包装上要有日期码、以及要有MADE IN CHINA和ZURU字样； 4. 产品如有扎带口要剪平，不能刮手。 5. 此单需要验货，请多备料 6. 此单以loose carton出货，2pcs/CTN | X97: Maggie Xie | Y97: 6.5485 | Z97: =I97*Y97 -> 3274.25 | AB97: 77858-S002 | AC97: 已入 | AI97: =I97 -> 500 | AM97: =I97 -> 500 | AQ97: =I97 -> 500
A98: 46136 | B98: WALMART INC. | C98: 美国 | D98: 4500203539 | E98: 0983718031 | F98: 4500203539-40 | G98: 77858-S002 | H98: 厨房套装 | I98: 500 | J98: 0 | K98: 2 | L98: =I98/K98 -> 250 | M98: 46182 | N98: 46189 | O98: 46191 | P98: OK | Q98: 46197 | S98: 箱唛翻单：4500195615 | T98: 无 | U98: 5/7RFID贴纸 | W98: 日期码格式：ZURU DGYYMMDD CHINA(日期避开周末和法定节假日即可） 日期：按实际生产日期 Packaging Info: 77858-S002 1. 包装要求： 77858：MA 1L A版 playset +MA 5L A版收藏指南+MA 23L A版说明书+MA A版纸袋+MA 贴纸 每pcs产品要贴一张RFID贴纸，RFID贴纸由ZURU提供，贴纸位置要严格按照客人签板 Remark: 77858-S002 1. 包装要求： 77858：MA 1L A版 playset +MA 5L A版收藏指南+MA 23L A版说明书+MA A版纸袋+MA 贴纸 每pcs产品要贴一张RFID贴纸，RFID贴纸由ZURU提供，贴纸位置要严格按照客人签板 2. 外箱印刷带条码的RFID箱唛：RFID紫色色带+WM Dept.图标+RFID图标+ITF-14条码，四面右下角印刷ZURU logo, ITFF条码只印刷在正唛一面，在加印的时候确保 条形码能扫描出来，外箱侧面任一角落加印："MADE IN CHINA" 字样；箱唛翻单：4500195615 3. 在产品上和包装上要有日期码、以及要有MADE IN CHINA和ZURU字样； 4. 产品如有扎带口要剪平，不能刮手。 5. 此单需要验货，请多备料 6. 此单以loose carton出货，2pcs/CTN | X98: Maggie Xie | Y98: 6.5485 | Z98: =I98*Y98 -> 3274.25 | AB98: 77858-S002 | AC98: 已入 | AI98: =I98 -> 500 | AM98: =I98 -> 500 | AQ98: =I98 -> 500
A99: 46115 | B99: AMBIENTAL PARAGUAY | C99: 巴拉圭 | D99: 4500199984 | F99: 4500199984-50 | G99: 77858-S001 | H99: 厨房套装 | I99: 300 | J99: 0 | K99: 3 | L99: =I99/K99 -> 100 | M99: 46183 | N99: 46183 | P99: OK | Q99: 6/12截SI | R99: 是 | S99: 46139 | T99: 无 | U99: 4/27进口商贴纸+UPC贴纸 | W99: 日期码格式：ZURU INC(BVI) 标准格式 日期：按实际生产日期 Packaging Info: 77782GQ1:客版收缩膜+客版收藏指南+客版PDQ+进口商贴纸+箱唛，客版物料翻单PO 4500161302 15789UQ1:MA 多语 UPC包装+进口商贴纸+箱唛 15787:MA 多语 UPC包装+MOTHER UPC贴纸+进口商贴纸+箱唛 其余item:MA 多语包装+进口商贴纸+UPC贴纸+箱唛 | X99: Ava Liang | Y99: 10.2316 | Z99: =I99*Y99 -> 3069.48 | AB99: 77858-S001-1 | AC99: 已入 | AL99: =I99 -> 300 | AM99: =I99 -> 300 | AQ99: =I99 -> 300
A100: 46126 | B100: MID-STATES DISTRIBUTING, LLC | C100: 美国 | D100: 4500201308 | E100: 1736153-99 | F100: 4500201308-760 | G100: 77858-S001 | H100: 厨房套装 | I100: 81 | J100: 0 | K100: 3 | L100: =I100/K100 -> 27 | M100: 46183 | N100: 46199 | P100: OK | Q100: 最晚6/30完货 | R100: 是 | S100: 46136 | T100: 无 | U100: 无 | W100: 日期码格式：ZURU INC(BVI) 标准格式 日期：按实际生产日期 Packaging Info: 1.使用 MA UPC版本包装，优先1L，出口美国。 Remark: 1.产品和包装上印刷tracking code信息，格式为ZURU常规。 2.ZURU QC验货 | X100: Cara Li | Y100: 6.139 | Z100: =Y100*L100 -> 165.753 | AB100: 77858-S001 | AC100: 已入 | AI100: =I100 -> 81 | AM100: =I100 -> 81 | AQ100: =I100 -> 81
A101: 46140 | B101: AMAZON.COM SERVICES LLC | C101: 美国 | D101: 4500203137 | E101: 7BPCSNBW | F101: 4500203137-50 | G101: 77858-S003-MB | H101: 厨房套装 | I101: 321 | J101: 0 | K101: 3 | L101: =I101/K101 -> 107 | M101: 46184 | N101: 46192 | P101: OK | Q101: 6/23截关 | R101: 自行排版 | S101: 46141 | T101: 有 | U101: 5/29条码箱贴纸 | V101: 邮包盒图稿翻单4500195266 | W101: 日期码格式：ZURU INC(BVI) 标准格式 日期：按实际生产日期 Packaging Info: #77858: STD 77858带MA包装入邮包盒，邮包盒图稿翻单4500195266。 Remark: 1. Amazon MDDP订单，出口US。 2. 日期码使用ZURU标准版本。 3. 如果大货有要求入邮包盒，则对应的邮包盒上面要打上日期码。 4. 箱尺寸要求：外箱最长边不能超过25"(超过了，case pack只能为1)，不符合要求的大货，一律不接受。 5. 外箱箱唛要求： ①外箱正面印ZURU Logo+SSCC Label(客供贴纸，由跟单订购)。关于 SSCC Label 请注意： SSCC Label显示的是客人自己的item#。每一张SSCC label都是唯一且有不同流水及条码的，没有损耗，绝对不可贴错。如果贴错或损坏任何一张，都会导致全部都 错，千万要注意！SSCC Label必须贴在外箱正面的正中间位置(贴一面即可)，并且贴纸离外箱边距必须至少3cm(可以覆盖Logo<(>&<)>箱唛)，否则会影响到客户那边 仓库的扫描识别。 ②外箱侧面印item#(订单上显示的SKU#)+carton size(以工厂实际尺寸为准，单位: inch)+MADE IN CHINA，日期使用ZURU 标准版本。 6. 装柜要求：按照客户PO#装柜/箱号顺序装柜，跟单会提前给到装柜计划。 在大货生产/仓库存放时，请留意该装柜要求，以便装柜时不混乱(避免装错/装漏/找不到货号等)。 | X101: Kelly Shen/Mia Pan/P | Y101: 7.59 | Z101: =Y101*L101 -> 812.13 | AB101: 77858-S003-MB | AC101: 已入 | AI101: =I101 -> 321 | AM101: =I101 -> 321 | AQ101: =I101 -> 321
...

Sheet 生产MA
A1: MA Order No. : | D1: MA-RR-2075 | E1: MA-RR-2166 | F1: MA-RR-2400 | G1: MA-RR-2477 | H1: MA-RR- | I1: MA-RR- | J1: Grand Total | K1: 实际订单 | L1: 剩余MA
A2: Order Date: | D2: 46041 | E2: 46113 | F2: 46203 | G2: 46246
A3: Required CRD: | D3: 46101 | E3: 46155 | F3: 46241 | G3: 46288
A4: Capsule 77858 | D4: 78000 | E4: 242000 | F4: 160000 | G4: 40000 | J4: =SUM(D4:I4) -> 520000 | K4: ='77858厨房套装'!I379 -> 377830 | L4: =J4-K4 -> 142170

Sheet 布料 IC MA
A1: MA NO. | B1: IC No. | C1: IC Supplier | D1: IC Wafer | E1: L/T | F1: MOQ | G1: Unit Price | H1: MFQ QTY | I1: MA-RR-1983 | J1: MA-RR-2025 | K1: MA-RR-2045 | L1: MA-RR-2119 | M1: MA-RR-2171 | N1: MA-RR-2227 | O1: MA-RR-2377 | P1: MA-RR-2403 | Q1: MA_RR_2445母体IC | R1: MA订单累计 Cumulative Total
A2: Ordered Date | I2: 45989 | J2: 46016 | K2: 46031 | L2: 46056 | M2: 46090 | N2: 46113 | O2: 46190 | P2: 46204 | Q2: 46231
A3: Required Delivery Date | I3: 46041 | J3: =J2+25 -> 46041 | K3: =K2+25 -> 46056 | L3: 46084 | M3: 46135 | N3: 46158 | O3: 46235 | P3: 46249
A4: 供应商回复货期
A6: MB-Magic Cook Kitchen Playset S1 #77858 | B6: HY2409148-6 | C6: 华远科创 | E6: 15 | F6: 4000 | G6: 0.46 | I6: 80000 | K6: 64000 | L6: 24000 | M6: 140000 | N6: 100000 | O6: 72000 | P6: 120000 | Q6: 124000 | R6: =SUM(I6:Q6) -> 724000
A7: MB-Magic Cook Kitchen Playset S1 #77858 | B7: ZJ-3718L-1511 (安规雾化片) | C7: 东莞市智杰电子科技有限公司 | E7: 25 | F7: 1000 | G7: 2.49 | I7: 0 | J7: 80000 | K7: 64000 | L7: 24000 | M7: 140000 | N7: 100000 | O7: 72000 | P7: 120000 | Q7: 0 | R7: =SUM(I7:Q7) -> 600000
B8: Running Sum | I8: =SUM(I6:I7) -> 80000 | J8: =SUM(J6:J7) -> 80000 | K8: =SUM(K6:K7) -> 128000 | L8: =SUM(L6:L7) -> 48000 | M8: =SUM(M6:M7) -> 280000 | N8: =SUM(N6:N7) -> 200000 | O8: =SUM(O6:O7) -> 144000 | P8: =SUM(P6:P7) -> 240000 | ... R8: =SUM(R6:R7) -> 1324000
L20: 放定日期 | M20: 45961 | N20: 46014 | O20: 46050 | P20: 46113 | Q20: 46203 | R20: 46246
L21: 到料日期 | M21: =M20+35 -> 45996 | N21: =N20+35 -> 46049 | O21: 46105 | P21: 46173 | Q21: 46241 | R21: 46288
I22: Damand FCST by 2025-10-27 | K22: 265611 | L22: MA No. | M22: MA-RR-1957 | O22: MA-RR-2089 | P22: MA-RR-2172 | Q22: MA-RR-2399 | R22: MA-RR-2476 | W22: MA | X22: 39183.673
A23: 图片 | B23: 名称 | C23: Ratio | D23: 布料名称 | E23: 部位 | F23: MOQ | G23: 用量 | H23: 可生产item数量(PCS) | I23: 单价 (RMB) | J23: 布料生產期單位(天)+测试 | K23: MOQ可生产球的数量 | L23: FCST布料需求量 | M23: 新购买 | N23: 新购买 | O23: 新购买 | P23: 新购买 | Q23: 新购买 | R23: 新购买 | T23: 累计购买金额 | U23: 总放定布料数 | V23: 总放定布料可生产数 | W23: 此款需求数(按Playset MA数量) | X23: 此款布料需求(按球MA数量) | Y23: 库存剩余数量 | Z23: 剩余布料可生产球数
B24: 橙色格子帘布 | C24: 1 | D24: 60"200G不防水白色四面弹斜纹布+数码满地印红橙格子+正反折皱 | E24: 帘子 | F24: 500 | G24: 0.012760417 | H24: =F24/G24 -> 39183.673 | I24: 22.1 | J24: 35+7天 | K24: =F24/G24/C24 -> 39183.673 | L24: =C24*K22*G24 -> 3389.307 | M24: 500 | N24: 500 | O24: 532 | P24: 2552 | Q24: 2042 | R24: 511 | T24: =SUM(M24:S24)*I24 -> 146677.7 | U24: =SUM(M24:Q24) -> 6126 | V24: =U24/G24 -> 480078.37 | W24: =X22*C24 -> 39183.673 | X24: =W24*G24 -> 500 | Y24: =U24-X24 -> 5626 | Z24: =Y24/G24/C24 -> 440894.69

Sheet 包材MA
A1: 77858包装MA
A2: 放MA日期 | B2: 货号 | C2: 负责 | D2: MA订单号码 | E2: 彩盒 | F2: 彩盒 | G2: 收藏指南 | I2: 客版彩盒 | J2: 客版PDQ | K2: 客版收藏指南 | L2: 客版黑白警语说明书 | M2: 备注
E3: 1L A版 | F3: 3L A版 | G3: 5L A版 | H3: 5L B版 | I3: 3L | J3: 3L | K3: 5L | L3: 3L
A5: 46081 | B5: 77858 | C5: Jasmine Huang | D5: 1000036716 | E5: 30000
A6: 46081 | B6: 77858 | C6: Jasmine Huang | D6: 1000036717 | F6: 15000
A7: 46081 | B7: 77858 | C7: Jasmine Huang | D7: 1000036718 | G7: 50000
A8: 46127 | B8: 77858 | C8: Jasmine Huang | D8: 1000038697 | E8: 20000
A9: 46127 | B9: 77858 | C9: Jasmine Huang | D9: 1000038698 | F9: 20000
A10: 46127 | B10: 77858 | C10: Jasmine Huang | D10: 1000038699 | G10: 30000
A11: 46134 | B11: 77889SLT | C11: Violet Chen | D11: 1000039096 | I11: =36*54*7+36*54*10 -> 33048 | M11: Cherish用于Costco USA 订单明细如下, 一共10张单, CRD 6/18-6/29；Costco CA 订单明细如下, 一共7张单, CRD 6/29-7/9 4500199798/4500199804/4500199805 4500199806 4500199807 4500199809 4500199810 4500199811 4500199814 4500199817/4500199850 4500199853 4500199854 4500199855 4500199856 4500199857 4500199858
A12: 46134 | B12: 77889SLT | C12: Violet Chen | D12: 1000039098 | J12: =36*17*18 -> 11016 | M12: 4500199798 4500199804 4500199805 4500199806 4500199807 4500199809 4500199810 4500199811 4500199814 4500199817/4500199850 4500199853 4500199854 4500199855 4500199856 4500199857 4500199858
A13: 46134 | B13: 77889SLT | C13: Violet Chen | D13: 1000039099 | K13: =36*54*7+36*54*10 -> 33048 | M13: 4500199798 4500199804 4500199805 4500199806 4500199807 4500199809 4500199810 4500199811 4500199814 4500199817/4500199850 4500199853 4500199854 4500199855 4500199856 4500199857 4500199858
A14: 46134 | B14: 77889SLT | C14: Violet Chen | D14: 1000039100 | L14: =36*54*7+36*54*10 -> 33048 | M14: 4500199798 4500199804 4500199805 4500199806 4500199807 4500199809 4500199810 4500199811 4500199814 4500199817/4500199850 4500199853 4500199854 4500199855 4500199856 4500199857 4500199858
A15: 46142 | B15: 77858 | C15: Jasmine Huang | D15: 1000039528 | E15: 20000
A16: 46142 | B16: 77858 | C16: Jasmine Huang | D16: 1000039529 | F16: 20000
A17: 46142 | B17: 77858 | C17: Jasmine Huang | D17: 1000039530 | G17: 50000
A18: 46156 | B18: 77889SLT | C18: Violet Chen | D18: 1000040017 | I18: =17*54*36 -> 33048 | M18: Cynthia用于Costco USA 订单明细如下, 一共14张单, CRD2026/7/1—2026/7/15；Costco CA 订单明细如下, 一共3张单,4500206634 4500206635 4500206637 4500206638 4500206639 4500206641 4500206643 4500206645 4500206646 4500206648 4500206650 4500206651 4500206652 4500206653/4500199859 4500199860 4500199861
A19: 46156 | B19: 77889SLT | C19: Violet Chen | D19: 1000040018 | J19: =17*18*36 -> 11016 | M19: Cynthia用于Costco USA 订单明细如下, 一共14张单, CRD2026/7/1—2026/7/15；Costco CA 订单明细如下, 一共3张单,4500206634 4500206635 4500206637 4500206638 4500206639 4500206641 4500206643 4500206645 4500206646 4500206648 4500206650 4500206651 4500206652 4500206653/4500199859 4500199860 4500199861
A20: 46156 | B20: 77889SLT | C20: Violet Chen | D20: 1000040019 | K20: =17*54*36 -> 33048 | M20: Cynthia用于Costco USA 订单明细如下, 一共14张单, CRD2026/7/1—2026/7/15；Costco CA 订单明细如下, 一共3张单,4500206634 4500206635 4500206637 4500206638 4500206639 4500206641 4500206643 4500206645 4500206646 4500206648 4500206650 4500206651 4500206652 4500206653/4500199859 4500199860 4500199861
A21: 46156 | B21: 77889SLT | C21: Violet Chen | D21: 1000040020 | L21: =17*54*36 -> 33048 | M21: Cynthia用于Costco USA 订单明细如下, 一共14张单, CRD2026/7/1—2026/7/15；Costco CA 订单明细如下, 一共3张单,4500206634 4500206635 4500206637 4500206638 4500206639 4500206641 4500206643 4500206645 4500206646 4500206648 4500206650 4500206651 4500206652 4500206653/4500199859 4500199860 4500199861
A22: 46182 | B22: 77889SLT | C22: Violet Chen | D22: 1000041170 | I22: =17*54*36 -> 33048 | M22: 4500208877/4500208878/4500208879/4500208880/4500208881/4500208882/4500208883/4500208884/4500208885/4500208886/4500208887/4500208888/4500208889/4500208890/4500199862/4500199863/4500199864
A23: 46182 | B23: 77889SLT | C23: Violet Chen | D23: 1000041171 | J23: =17*18*36 -> 11016 | M23: 4500208877/4500208878/4500208879/4500208880/4500208881/4500208882/4500208883/4500208884/4500208885/4500208886/4500208887/4500208888/4500208889/4500208890/4500199862/4500199863/4500199864
A24: 46182 | B24: 77889SLT | C24: Violet Chen | D24: 1000041172 | K24: =17*54*36 -> 33048 | M24: 4500208877/4500208878/4500208879/4500208880/4500208881/4500208882/4500208883/4500208884/4500208885/4500208886/4500208887/4500208888/4500208889/4500208890/4500199862/4500199863/4500199864
A25: 46182 | B25: 77889SLT | C25: Violet Chen | D25: 1000041173 | L25: =17*54*36 -> 33048 | M25: 4500208877/4500208878/4500208879/4500208880/4500208881/4500208882/4500208883/4500208884/4500208885/4500208886/4500208887/4500208888/4500208889/4500208890/4500199862/4500199863/4500199864
A26: 46188 | B26: 77858 | C26: Jasmine Huang | D26: 1000041485 | E26: 30000 | M26: A版本
A27: 46188 | B27: 77858 | C27: Jasmine Huang | D27: 1000041486 | F27: 20000 | M27: A版本
A28: 46188 | B28: 77858 | C28: Jasmine Huang | D28: 1000041487 | H28: 40000 | M28: B版本
A29: 46205 | B29: 77889SLT | C29: Ariel Peng | D29: 1000042123 | I29: 11664 | M29: Eva 用于COSTCO MX 4500198844+4500198845+4500198846+4500198848+4500198849+4500198850
A30: 46205 | B30: 77889SLT | C30: Ariel Peng | D30: 1000042124 | J30: 3888 | M30: Eva 用于COSTCO MX 4500198844+4500198845+4500198846+4500198848+4500198849+4500198850
A31: 46205 | B31: 77889SLT | C31: Ariel Peng | D31: 1000042125 | K31: 11664 | M31: Eva 用于COSTCO MX 4500198844+4500198845+4500198846+4500198848+4500198849+4500198850
A32: 46205 | B32: 77889SLT | C32: Ariel Peng | D32: 1000042126 | L32: 11664 | M32: Eva 用于COSTCO MX 4500198844+4500198845+4500198846+4500198848+4500198849+4500198850
A33: 46205 | B33: 77889SLT | C33: Babbit Zhong | D33: 1000042139 | I33: 7560 | M33: Zoe-4500208477&4500206719
A34: 46205 | B34: 77889SLT | C34: Babbit Zhong | D34: 1000042140 | J34: 140 | M34: Zoe-4500208477&4500206719
A35: 46205 | B35: 77889SLT | C35: Babbit Zhong | D35: 1000042141 | K35: 7560 | M35: Zoe-4500208477&4500206719
A36: 46205 | B36: 77889SLT | C36: Babbit Zhong | D36: 1000042142 | L36: 7560 | M36: Zoe-4500208477&4500206719
A37: 46220 | B37: 77858 | C37: Jasmine Huang | D37: 1000042812 | E37: 20000 | M37: A版本
A38: 46220 | B38: 77858 | C38: Jasmine Huang | D38: 1000042813 | F38: 10000 | M38: A版本
A39: 46220 | B39: 77858 | C39: Jasmine Huang | D39: 1000042814 | H39: 30000 | M39: B版本
A40: 46232 | B40: 77858 | C40: Jasmine Huang | D40: 1000043316 | E40: 20000 | M40: A版本
A41: 46245 | B41: 77858 | C41: Chelsie Chen | D41: 1000043884 | E41: 20000
A42: 46245 | B42: 77858 | C42: Chelsie Chen | D42: 1000043885 | H42: 30000
A43: 46248 | B43: 77858 | C43: Chelsie Chen | D43: 1000044066 | E43: 20000 | M43: A版本
C44: MA合計 | E44: =SUM(E5:E43) -> 180000 | F44: =SUM(F5:F43) -> 85000 | G44: =SUM(G5:G43) -> 130000 | H44: =SUM(H5:H43) -> 100000 | I44: =SUM(I5:I43) -> 118368 | J44: =SUM(J5:J43) -> 37076 | K44: =SUM(K5:K43) -> 118368 | L44: =SUM(L5:L43) -> 118368
C45: 接單數量 | E45: ='77858厨房套装'!AI378 -> 174112 | F45: ='77858厨房套装'!AL378 -> 82584 | G45: ='77858厨房套装'!AQ378 -> 128510 | H45: ='77858厨房套装'!AR378 -> 98981 | I45: ='77858厨房套装'!AJ378 -> 118368 | J45: ='77858厨房套装'!AS378 -> 40104 | K45: ='77858厨房套装'!AP378 -> 120996 | L45: ='77858厨房套装'!AN378 -> 122465
C46: 包装MA剩餘數 | E46: =E44-E45 -> 5888 | F46: =F44-F45 -> 2416 | G46: =G44-G45 -> 1490 | H46: =H44-H45 -> 1019 | I46: =I44-I45 -> 0 | J46: =J44-J45 -> -3028 | K46: =K44-K45 -> -2628 | L46: =L44-L45 -> -4097

Sheet 取消单
A1: 香港接单日期 | B1: 第三方客户名称 | C1: 走货国家 | D1: ZURU PO NO# | E1: 第三方客户 PO NO# | F1: SKU | G1: ITEM# | H1: 中文名 | I1: PO数量 (pcs) | J1: 内箱装箱数量(pcs) | K1: 外箱装箱数量(pcs) | L1: 总箱数 | M1: 客PO期 | N1: 验货期 | O1: 第三方验货期 | P1: 验货结果 | Q1: S/0船期 | R1: 箱唛确认 | S1: 箱唛资料(收到日期) | T1: 外箱贴纸 | U1: 客供贴纸AI(收到日期) | V1: 客供物料 | W1: 备注 | X1: ZURU 跟单 | Y1: 单价USD | Z1: 金额USD | AA1: 發票號 | AB1: 系统货号 | AC1: 是否入系统 | AD1: 系统出单 | AE1: 送货情况 | AF1: 欠数 | AG1: 贴纸 | AH1: MA 1L彩盒 | AI1: 客版 3L彩盒 | AJ1: 客版 3L彩盒（COSTCO AU/NA） | AK1: MA 3L彩盒 | AL1: 黑白警语说明书 | AM1: 客版黑白警语说明书 | AN1: 不带电WEE说明书 | AO1: 客版5L 收藏指南 | AP1: 5L 收藏指南 | AQ1: 客版PDQ
A2: 46056 | B2: ZURU LLC | C2: ZURU LLC | D2: 美国 | E2: 4500192979 | F2: 5200008906 | G2: 4500192979-120 | H2: 77858-S003-MB-MTS | J2: 3999 | K2: 0 | L2: 3 | M2: =J2/L2 -> 1333 | N2: 46132 | O2: 46128 | P2: 转单4500192979 | T2: 46056 | U2: 无 | V2: 无 | W2: 邮包盒 | X2: 日期码格式：ZURU INC(BVI) 标准格式 日期：按实际生产日期 Packaging Info: #77858: STD 77858带MA包装入邮包盒，邮包盒图稿跟单提供。首单需要提供大货样1PC(含邮包盒+产品)，测试样规格和大货一样，用于测ISTA6. Remark: 1.Amazon domestic 订单。出口美国。外箱最长边不能超过25" （超过了，case pack只能为1），不符合要求的大货，一律不接受。 2.无第三方验货/测试要求。 3.日期码使用ZURU标准版本。 4.如果大货有要求入邮包盒，则对应的邮包盒上面要打上日期码。 | Y2: Kelly Shen/Mia Pan/P | Z2: 7.59 | AA2: =J2*Z2 -> 30352.41 | AC2: 77858-S003-MB-MTS | AD2: 无bom
A3: 46067 | C3: AMAZON.COM SERVICES LLC | D3: 美国 | E3: 4500193997 | F3: 6FOAAL4E | G3: 4500193997-10 | H3: 77858-S003-MB | J3: 192 | K3: 0 | L3: 3 | M3: =J3/L3 -> 64 | N3: 46125 | O3: 46121 | T3: 46067 | U3: 有 | V3: 欠SSCC Label | W3: 邮包盒图稿翻单4500192979 | X3: 日期码格式：ZURU INC(BVI) 标准格式 日期：按实际生产日期 Packaging Info: #77858: STD 77858带MA包装入邮包盒，邮包盒图稿翻单4500192979。 Remark: 1. Amazon MDDP订单，出口US。 2. 日期码使用ZURU标准版本。 3. 如果大货有要求入邮包盒，则对应的邮包盒上面要打上日期码。 4. 箱尺寸要求：外箱最长边不能超过25"(超过了，case pack只能为1)，不符合要求的大货，一律不接受。 5. 外箱箱唛要求： ①外箱正面印ZURU Logo+SSCC Label(客供贴纸，由跟单订购)。关于 SSCC Label 请注意： SSCC Label显示的是客人自己的item#。每一张SSCC label都是唯一且有不同流水及条码的，没有损耗，绝对不可贴错。如果贴错或损坏任何一张，都会导致全部都 错，千万要注意！SSCC Label必须贴在外箱正面的正中间位置(贴一面即可)，并且贴纸离外箱边距必须至少3cm(可以覆盖Logo<(>&<)>箱唛)，否则会影响到客户那边 仓库的扫描识别。 ②外箱侧面印item#(订单上显示的SKU#)+carton size(以工厂实际尺寸为准，单位: inch)+MADE IN CHINA，日期使用ZURU 标准版本。 6. 装柜要求：按照客户PO#装柜/箱号顺序装柜，跟单会提前给到装柜计划。 在大货生产/仓库存放时，请留意该装柜要求，以便装柜时不混乱(避免装错/装漏/找不到货号等)。 | Y3: Kelly Shen/Mia Pan/P | Z3: 7.3813 | AA3: =J3*Z3 -> 1417.2096
A4: 46067 | C4: AMAZON.COM SERVICES LLC | D4: 美国 | E4: 4500194000 | F4: 2FJ8CEIC | G4: 4500194000-10 | H4: 77858-S003-MB | J4: 96 | K4: 0 | L4: 3 | M4: =J4/L4 -> 32 | N4: 46125 | O4: 46121 | T4: 46067 | U4: 有 | V4: 欠SSCC Label | W4: 邮包盒图稿翻单4500192979 | X4: 日期码格式：ZURU INC(BVI) 标准格式 日期：按实际生产日期 Packaging Info: #77858: STD 77858带MA包装入邮包盒，邮包盒图稿翻单4500192979。 Remark: 1. Amazon MDDP订单，出口US。 2. 日期码使用ZURU标准版本。 3. 如果大货有要求入邮包盒，则对应的邮包盒上面要打上日期码。 4. 箱尺寸要求：外箱最长边不能超过25"(超过了，case pack只能为1)，不符合要求的大货，一律不接受。 5. 外箱箱唛要求： ①外箱正面印ZURU Logo+SSCC Label(客供贴纸，由跟单订购)。关于 SSCC Label 请注意： SSCC Label显示的是客人自己的item#。每一张SSCC label都是唯一且有不同流水及条码的，没有损耗，绝对不可贴错。如果贴错或损坏任何一张，都会导致全部都 错，千万要注意！SSCC Label必须贴在外箱正面的正中间位置(贴一面即可)，并且贴纸离外箱边距必须至少3cm(可以覆盖Logo<(>&<)>箱唛)，否则会影响到客户那边 仓库的扫描识别。 ②外箱侧面印item#(订单上显示的SKU#)+carton size(以工厂实际尺寸为准，单位: inch)+MADE IN CHINA，日期使用ZURU 标准版本。 6. 装柜要求：按照客户PO#装柜/箱号顺序装柜，跟单会提前给到装柜计划。 在大货生产/仓库存放时，请留意该装柜要求，以便装柜时不混乱(避免装错/装漏/找不到货号等)。 | Y4: Kelly Shen/Mia Pan/P | Z4: 7.59 | AA4: =J4*Z4 -> 728.64
A5: 46087 | C5: AMAZON.COM SERVICES LLC | D5: 美国 | E5: 4500195252 | F5: 4ZTS3SGW | G5: 4500195252-170 | H5: 77858-S003-MB | I5: 厨房套装 | J5: 3402 | K5: 0 | L5: 3 | M5: =J5/L5 -> 1134 | N5: 46136 | O5: 46132 | P5: 3402PCS由Domestic PO4500192979转单 | S5: 自行排版 | T5: 46087 | U5: 有 | V5: 欠SSCC Label | W5: 邮包盒图稿翻单4500194000 | X5: 日期码格式：ZURU INC(BVI) 标准格式 日期：按实际生产日期 Packaging Info: #77858: STD 77858带MA包装入邮包盒，邮包盒图稿翻单4500194000。 其中207PCS由Domestic PO4500192979转单. Remark: 1. Amazon MDDP订单，出口US。 2. 日期码使用ZURU标准版本。 3. 如果大货有要求入邮包盒，则对应的邮包盒上面要打上日期码。 4. 箱尺寸要求：外箱最长边不能超过25"(超过了，case pack只能为1)，不符合要求的大货，一律不接受。 5. 外箱箱唛要求： ①外箱正面印ZURU Logo+SSCC Label(客供贴纸，由跟单订购)。关于 SSCC Label 请注意： SSCC Label显示的是客人自己的item#。每一张SSCC label都是唯一且有不同流水及条码的，没有损耗，绝对不可贴错。如果贴错或损坏任何一张，都会导致全部都 错，千万要注意！SSCC Label必须贴在外箱正面的正中间位置(贴一面即可)，并且贴纸离外箱边距必须至少3cm(可以覆盖Logo<(>&<)>箱唛)，否则会影响到客户那边 仓库的扫描识别。 ②外箱侧面印item#(订单上显示的SKU#)+carton size(以工厂实际尺寸为准，单位: inch)+MADE IN CHINA，日期使用ZURU 标准版本。 6. 装柜要求：按照客户PO#装柜/箱号顺序装柜，跟单会提前给到装柜计划。 在大货生产/仓库存放时，请留意该装柜要求，以便装柜时不混乱(避免装错/装漏/找不到货号等)。 | Y5: Kelly Shen/Mia Pan/P | Z5: 7.59 | AA5: =J5*Z5 -> 25821.18 | AC5: 77858-S003-MB | AD5: 已入 | AF5: 湖南提供半成品 | AI5: =J5 -> 3402
A6: 46087 | C6: AMAZON.COM SERVICES LLC | D6: 美国 | E6: 4500195258 | F6: 1HDMJUXJ | G6: 4500195258-130 | H6: 77858-S003-MB | I6: 厨房套装 | J6: 1800 | K6: 0 | L6: 3 | M6: =J6/L6 -> 600 | N6: 46136 | O6: 46132 | P6: 207PCS 由Domestic PO4500192979转单 | S6: 自行排版 | T6: 46087 | U6: 有 | V6: 欠SSCC Label | W6: 邮包盒图稿翻单4500194000 | X6: 日期码格式：ZURU INC(BVI) 标准格式 日期：按实际生产日期 Packaging Info: #77858: STD 77858带MA包装入邮包盒，邮包盒图稿翻单4500194000。 其中207PCS由Domestic PO4500192979转单. Remark: 1. Amazon MDDP订单，出口US。 2. 日期码使用ZURU标准版本。 3. 如果大货有要求入邮包盒，则对应的邮包盒上面要打上日期码。 4. 箱尺寸要求：外箱最长边不能超过25"(超过了，case pack只能为1)，不符合要求的大货，一律不接受。 5. 外箱箱唛要求： ①外箱正面印ZURU Logo+SSCC Label(客供贴纸，由跟单订购)。关于 SSCC Label 请注意： SSCC Label显示的是客人自己的item#。每一张SSCC label都是唯一且有不同流水及条码的，没有损耗，绝对不可贴错。如果贴错或损坏任何一张，都会导致全部都 错，千万要注意！SSCC Label必须贴在外箱正面的正中间位置(贴一面即可)，并且贴纸离外箱边距必须至少3cm(可以覆盖Logo<(>&<)>箱唛)，否则会影响到客户那边 仓库的扫描识别。 ②外箱侧面印item#(订单上显示的SKU#)+carton size(以工厂实际尺寸为准，单位: inch)+MADE IN CHINA，日期使用ZURU 标准版本。 6. 装柜要求：按照客户PO#装柜/箱号顺序装柜，跟单会提前给到装柜计划。 在大货生产/仓库存放时，请留意该装柜要求，以便装柜时不混乱(避免装错/装漏/找不到货号等)。 | Y6: Kelly Shen/Mia Pan/P | Z6: 7.59 | AA6: =J6*Z6 -> 13662 | AC6: 77858-S003-MB | AD6: 已入 | AF6: 湖南提供半成品 | AI6: =J6 -> 1800
A7: 46087 | C7: AMAZON.COM SERVICES LLC | D7: 美国 | E7: 4500195261 | F7: 4R27O4WC | G7: 4500195261-130 | H7: 77858-S003-MB | I7: 厨房套装 | J7: 2478 | K7: 0 | L7: 3 | M7: =J7/L7 -> 826 | N7: 46136 | O7: 46132 | S7: 自行排版 | T7: 46087 | U7: 有 | V7: 欠SSCC Label | W7: 邮包盒图稿翻单4500194000 | X7: 日期码格式：ZURU INC(BVI) 标准格式 日期：按实际生产日期 Packaging Info: #77858: STD 77858带MA包装入邮包盒，邮包盒图稿翻单4500194000。 其中207PCS由Domestic PO4500192979转单. Remark: 1. Amazon MDDP订单，出口US。 2. 日期码使用ZURU标准版本。 3. 如果大货有要求入邮包盒，则对应的邮包盒上面要打上日期码。 4. 箱尺寸要求：外箱最长边不能超过25"(超过了，case pack只能为1)，不符合要求的大货，一律不接受。 5. 外箱箱唛要求： ①外箱正面印ZURU Logo+SSCC Label(客供贴纸，由跟单订购)。关于 SSCC Label 请注意： SSCC Label显示的是客人自己的item#。每一张SSCC label都是唯一且有不同流水及条码的，没有损耗，绝对不可贴错。如果贴错或损坏任何一张，都会导致全部都 错，千万要注意！SSCC Label必须贴在外箱正面的正中间位置(贴一面即可)，并且贴纸离外箱边距必须至少3cm(可以覆盖Logo<(>&<)>箱唛)，否则会影响到客户那边 仓库的扫描识别。 ②外箱侧面印item#(订单上显示的SKU#)+carton size(以工厂实际尺寸为准，单位: inch)+MADE IN CHINA，日期使用ZURU 标准版本。 6. 装柜要求：按照客户PO#装柜/箱号顺序装柜，跟单会提前给到装柜计划。 在大货生产/仓库存放时，请留意该装柜要求，以便装柜时不混乱(避免装错/装漏/找不到货号等)。 | Y7: Kelly Shen/Mia Pan/P | Z7: 7.59 | AA7: =J7*Z7 -> 18808.02 | AC7: 77858-S003-MB | AD7: 已入 | AF7: 湖南提供半成品 | AI7: =J7 -> 2478
A8: 46087 | C8: AMAZON.COM SERVICES LLC | D8: 美国 | E8: 4500195264 | F8: 4IV6J1AO | G8: 4500195264-140 | H8: 77858-S003-MB | I8: 厨房套装 | J8: 2748 | K8: 0 | L8: 3 | M8: =J8/L8 -> 916 | N8: 46136 | O8: 46132 | S8: 自行排版 | T8: 46087 | U8: 有 | V8: 欠SSCC Label | W8: 邮包盒图稿翻单4500194000 | X8: 日期码格式：ZURU INC(BVI) 标准格式 日期：按实际生产日期 Packaging Info: #77858: STD 77858带MA包装入邮包盒，邮包盒图稿翻单4500194000。 其中207PCS由Domestic PO4500192979转单. Remark: 1. Amazon MDDP订单，出口US。 2. 日期码使用ZURU标准版本。 3. 如果大货有要求入邮包盒，则对应的邮包盒上面要打上日期码。 4. 箱尺寸要求：外箱最长边不能超过25"(超过了，case pack只能为1)，不符合要求的大货，一律不接受。 5. 外箱箱唛要求： ①外箱正面印ZURU Logo+SSCC Label(客供贴纸，由跟单订购)。关于 SSCC Label 请注意： SSCC Label显示的是客人自己的item#。每一张SSCC label都是唯一且有不同流水及条码的，没有损耗，绝对不可贴错。如果贴错或损坏任何一张，都会导致全部都 错，千万要注意！SSCC Label必须贴在外箱正面的正中间位置(贴一面即可)，并且贴纸离外箱边距必须至少3cm(可以覆盖Logo<(>&<)>箱唛)，否则会影响到客户那边 仓库的扫描识别。 ②外箱侧面印item#(订单上显示的SKU#)+carton size(以工厂实际尺寸为准，单位: inch)+MADE IN CHINA，日期使用ZURU 标准版本。 6. 装柜要求：按照客户PO#装柜/箱号顺序装柜，跟单会提前给到装柜计划。 在大货生产/仓库存放时，请留意该装柜要求，以便装柜时不混乱(避免装错/装漏/找不到货号等)。 | Y8: Kelly Shen/Mia Pan/P | Z8: 7.59 | AA8: =J8*Z8 -> 20857.32 | AC8: 77858-S003-MB | AD8: 已入 | AF8: 湖南提供半成品 | AI8: =J8 -> 2748
A9: 46087 | C9: AMAZON.COM SERVICES LLC | D9: 美国 | E9: 4500195266 | F9: 84NHDFGJ | G9: 4500195266-90 | H9: 77858-S003-MB | I9: 厨房套装 | J9: 339 | K9: 0 | L9: 3 | M9: =J9/L9 -> 113 | N9: 46136 | O9: 46132 | P9: 390PCS 由Domestic PO4500192979转单 | S9: 自行排版 | T9: 46087 | U9: 有 | V9: 欠SSCC Label | W9: 邮包盒图稿翻单4500194000 | X9: 日期码格式：ZURU INC(BVI) 标准格式 日期：按实际生产日期 Packaging Info: #77858: STD 77858带MA包装入邮包盒，邮包盒图稿翻单4500194000。 其中207PCS由Domestic PO4500192979转单. Remark: 1. Amazon MDDP订单，出口US。 2. 日期码使用ZURU标准版本。 3. 如果大货有要求入邮包盒，则对应的邮包盒上面要打上日期码。 4. 箱尺寸要求：外箱最长边不能超过25"(超过了，case pack只能为1)，不符合要求的大货，一律不接受。 5. 外箱箱唛要求： ①外箱正面印ZURU Logo+SSCC Label(客供贴纸，由跟单订购)。关于 SSCC Label 请注意： SSCC Label显示的是客人自己的item#。每一张SSCC label都是唯一且有不同流水及条码的，没有损耗，绝对不可贴错。如果贴错或损坏任何一张，都会导致全部都 错，千万要注意！SSCC Label必须贴在外箱正面的正中间位置(贴一面即可)，并且贴纸离外箱边距必须至少3cm(可以覆盖Logo<(>&<)>箱唛)，否则会影响到客户那边 仓库的扫描识别。 ②外箱侧面印item#(订单上显示的SKU#)+carton size(以工厂实际尺寸为准，单位: inch)+MADE IN CHINA，日期使用ZURU 标准版本。 6. 装柜要求：按照客户PO#装柜/箱号顺序装柜，跟单会提前给到装柜计划。 在大货生产/仓库存放时，请留意该装柜要求，以便装柜时不混乱(避免装错/装漏/找不到货号等)。 | Y9: Kelly Shen/Mia Pan/P | Z9: 7.59 | AA9: =J9*Z9 -> 2573.01 | AC9: 77858-S003-MB | AD9: 已入 | AF9: 湖南提供半成品 | AI9: =J9 -> 339
A10: 46087 | C10: AMAZON.COM SERVICES LLC | D10: 美国 | E10: 4500195266 | F10: 8B57DIII | G10: 4500195266-160 | H10: 77858-S003-MB | I10: 厨房套装 | J10: 51 | K10: 0 | L10: 3 | M10: =J10/L10 -> 17 | N10: 46136 | O10: 46132 | S10: 自行排版 | T10: 46087 | U10: 有 | V10: 欠SSCC Label | W10: 邮包盒图稿翻单4500194000 | X10: 日期码格式：ZURU INC(BVI) 标准格式 日期：按实际生产日期 Packaging Info: #77858: STD 77858带MA包装入邮包盒，邮包盒图稿翻单4500194000。 其中207PCS由Domestic PO4500192979转单. Remark: 1. Amazon MDDP订单，出口US。 2. 日期码使用ZURU标准版本。 3. 如果大货有要求入邮包盒，则对应的邮包盒上面要打上日期码。 4. 箱尺寸要求：外箱最长边不能超过25"(超过了，case pack只能为1)，不符合要求的大货，一律不接受。 5. 外箱箱唛要求： ①外箱正面印ZURU Logo+SSCC Label(客供贴纸，由跟单订购)。关于 SSCC Label 请注意： SSCC Label显示的是客人自己的item#。每一张SSCC label都是唯一且有不同流水及条码的，没有损耗，绝对不可贴错。如果贴错或损坏任何一张，都会导致全部都 错，千万要注意！SSCC Label必须贴在外箱正面的正中间位置(贴一面即可)，并且贴纸离外箱边距必须至少3cm(可以覆盖Logo<(>&<)>箱唛)，否则会影响到客户那边 仓库的扫描识别。 ②外箱侧面印item#(订单上显示的SKU#)+carton size(以工厂实际尺寸为准，单位: inch)+MADE IN CHINA，日期使用ZURU 标准版本。 6. 装柜要求：按照客户PO#装柜/箱号顺序装柜，跟单会提前给到装柜计划。 在大货生产/仓库存放时，请留意该装柜要求，以便装柜时不混乱(避免装错/装漏/找不到货号等)。 | Y10: Kelly Shen/Mia Pan/P | Z10: 7.59 | AA10: =J10*Z10 -> 387.09 | AC10: 77858-S003-MB | AD10: 已入 | AF10: 湖南提供半成品 | AI10: =J10 -> 51
A11: 46087 | C11: AMAZON.COM SERVICES LLC | D11: 美国 | E11: 4500195259 | F11: 4PSZCKYT | G11: 4500195259-10 | H11: 77858-S003-MB | I11: 厨房套装 | J11: 4182 | K11: 0 | L11: 3 | M11: =J11/L11 -> 1394 | N11: 46136 | O11: 46132 | S11: 自行排版 | T11: 46087 | U11: 有 | V11: 欠SSCC Label | W11: 邮包盒图稿翻单4500194000 | X11: 日期码格式：ZURU INC(BVI) 标准格式 日期：按实际生产日期 Packaging Info: #77858: STD 77858带MA包装入邮包盒，邮包盒图稿翻单4500194000。 Remark: 1. Amazon MDDP订单，出口US。 2. 日期码使用ZURU标准版本。 3. 如果大货有要求入邮包盒，则对应的邮包盒上面要打上日期码。 4. 箱尺寸要求：外箱最长边不能超过25"(超过了，case pack只能为1)，不符合要求的大货，一律不接受。 5. 外箱箱唛要求： ①外箱正面印ZURU Logo+SSCC Label(客供贴纸，由跟单订购)。关于 SSCC Label 请注意： SSCC Label显示的是客人自己的item#。每一张SSCC label都是唯一且有不同流水及条码的，没有损耗，绝对不可贴错。如果贴错或损坏任何一张，都会导致全部都 错，千万要注意！SSCC Label必须贴在外箱正面的正中间位置(贴一面即可)，并且贴纸离外箱边距必须至少3cm(可以覆盖Logo<(>&<)>箱唛)，否则会影响到客户那边 仓库的扫描识别。 ②外箱侧面印item#(订单上显示的SKU#)+carton size(以工厂实际尺寸为准，单位: inch)+MADE IN CHINA，日期使用ZURU 标准版本。 6. 装柜要求：按照客户PO#装柜/箱号顺序装柜，跟单会提前给到装柜计划。 在大货生产/仓库存放时，请留意该装柜要求，以便装柜时不混乱(避免装错/装漏/找不到货号等)。 | Y11: Kelly Shen/Mia Pan/P | Z11: 7.59 | AA11: =J11*Z11 -> 31741.38 | AC11: 77858-S003-MB | AD11: 已入 | AF11: 湖南提供半成品 | AI11: =J11 -> 4182
A12: 46178 | B12: BOL.COM | C12: 荷兰 | D12: 4500210646 | E12: P2607944 | F12: 4500210646-10 | G12: 77858-S001 | H12: 厨房套装 | I12: 180 | J12: 0 | K12: 3 | L12: =I12/K12 -> 60 | M12: 46244 | N12: 46241 | S12: 欠 | T12: 无 | U12: 欠1张贴纸（含NL警告语） | W12: 日期码格式：ZURU INC(BVI) 标准格式 日期：按实际生产日期 Packaging Info: BOL.COM(77858) 1. 77858:1pc 77858 playset into mailbox, 3mailboxes/ctn; Including magnets; 3PCS AA BATTERIES(NOT INCLUDED); MA 3L(23L warning EAN)A 透明PVC窗彩 盒+MA 23L warning A 电池黑白说明书+MA 5L A收藏指南+MA其它最新配套包装+1张贴纸（含NL警告语）+WEEE_不带电池走货 _ 说明书欧洲EN+29L_C版 2. 最晚验货时间8/11 Remark: 1. 出欧洲产品不可含闪粉或者微塑料，若所涉产品无闪粉或不含微塑料可忽略此点； 2. 5 Surprise or Mini Brands涉及包装是2个及2个以上的球入PVC桶包装时，单个球上若有UPC#或者EAN#，请用白色贴纸覆盖住； 3. 箱唛资料按照提供的要求去做即可，无需再发回我方确认； 4.柜货产品务必拉网且要拉紧，拉网要求： A: 网要结实同时网格要细，纸箱不能从网格处跌落下来 B: 打网固定8-10个点。请提供拉网的装柜照片给船务确认 后柜子再离厂。 | X12: Luna Lin | Y12: 10.4985 | Z12: 1889.73 | AB12: 77858-S001-1 | AC12: 已入 | AK12: =I12 -> 180 | AL12: =I12 -> 180 | AN12: 29L | AP12: =I12 -> 180
A13: 46217 | B13: COMERCIALIZADORA MEXICO AMERICANA S | C13: 墨西哥 | D13: 4500216463 | F13: 4500216463-30 | G13: 77858-S001 | H13: 厨房套装 | I13: 2319 | J13: 0 | K13: 3 | L13: =I13/K13 -> 773 | M13: 46258 | N13: 46255 | O13: 此单有第三方监柜，至少多备一套完整的物料用于监柜 | S13: 欠 | T13: 无 | U13: 贴纸和保证书都翻单4500205972 | V13: 保证书翻单4500205972，每箱放置6小包干燥剂，每包重2-3g | W13: 日期码格式：LOT+ZURU标准日期码格式 日期：按实际生产日期 Packaging Info: 77858 MA 3L EAN 包装+UPC 条码+进口商贴纸+产品贴纸+说明书贴纸+保证书+箱唛，所有贴纸和保证书都翻单4500205972 Remark: 1. 客版日期码要求：LOT+ZURU标准日期码格式。举例东莞生产的格式：LOTDGYYYYMMDD, DG是东莞拼音首字母，YYYYMMDD是实际的年月日，例如(LOTDG20240920) 2. 此单有第三方监柜，至少多备一套完整的物料用于监柜，请多备料 3. WM墨西哥防霉的新要求:货物必须在出货主箱和集装箱中按要求放置干燥剂，干燥剂指定品牌干霸 4. 77772GQ2/77858/77794UQ1： 每箱放置6小包干燥剂，每包重2-3g； 5. 如走柜货等loading plan 确认后再通知集装箱干燥剂数量 | X13: Ever Li | Y13: 10.452 | Z13: =I13*Y13 -> 24238.188 | AB13: 77858-S001-1 | AC13: 已入 | AK13: =I13 -> 2319 | AL13: =I13 -> 2319 | AP13: =I13 -> 2319
A14: 46219 | B14: AMAZON UK | C14: 英国 | D14: 4500216744 | E14: 69ET8HJN | F14: 4500216744-20 | G14: 77858-S003-MB | H14: 厨房套装 | I14: 501 | J14: 0 | K14: 3 | L14: =I14/K14 -> 167 | M14: 46269 | N14: 46267 | S14: 空白外箱（加印带Zuru字样的最新logo，印ZURU地址） | T14: 有 | U14: 欠SSCC Label | V14: 客版邮包盒(参考翻单4500209704) | W14: 日期码格式：ZURU INC(BVI) 标准格式 日期：按实际生产日期 Packaging Info: Amazon UK: 852HAG3K/69ET8HJN/1I8FZV2Y UK(92146BG/77858) 1. 77858: 1pc 77858 playset into mailbox, 3mailboxes/ctn; Including magnets; 3PCS AA BATTERIES(NOT INCLUDED); MA 3L(23L warning EAN)A 透明PVC窗 彩盒+MA 23L warning A 电池黑白说明书+MA 5L B收藏指南+MA其它最新配套包装+客版邮包盒(参考翻单4500209704)+WEEE_不带电池走货 _ 说明书欧洲EN+29L_C版 3. 验货时间不晚于2026/09/07 4. 77858 验货时需要将产品六面图， 邮包盒(含产品)测量尺寸图片<(>&<)>重量图片放进验货报告 Remark: 1.空白外箱（加印带Zuru字样的最新logo，除了邮包盒直接做外箱的产品） + SSCC LABEL一张, 无箱唛，MADE IN CHINA 外箱只印一正一侧。箱唛资料按照给定的 标准去做即可，无需发回我方再行审批(新标准将另行通知)。 (SSCC LABEL竖贴在外箱正面的正中间，贴一面即可,贴纸离外箱边距必须至少3.2CM。如竖贴无法满足要求，则横贴。如横贴也无法满足要求，则竖贴，遮到ZURU lo go无影响), SSCC贴纸由工厂直接跟勤得采购或者工厂自行采购，每一张SSCC Label都是唯一且有不同流水及条码，且需要检查条码是否能正常扫描，另外，此贴纸 印刷不可出现模糊，溢出及粘胶不牢易脱落等现象，如工厂不按此要求导致贴纸有任何问题产生的罚款将由工厂承担一切责任 ,<(>,<)> 此要求只适用Amazon UK/DE /FR/ES/IT,不适用Amazon GPE，Amazon GPE无SSCC label, 但是有对应箱唛，需印刷到外箱 。 2.出往UK的产品+包装务必打上UKCA logo ，否则客人会退货且当地会有罚款。Amazon GPE（包含UK/FR/ES/DE/IT）的订单也需满足此要求。 3.订单必须经过ZURU QC验货或者工厂自检通过后方可出货，不涉及第三方验货。 4.法国订单要求包装不使用矿物油，请按要求提供以下其中一份文件再出货 ，产品出到法国被相关部门抽检出现包装不符合此要求的，供应商需要为此承担责任， 故此请严格把关。Am~azon GPE（包含UK/FR/ES/DE/IT）的订单也需满足此要求。 -油墨物质""""由1 7个芳香环组成的MOAH""""的包装检测报告，要求限值≤1.0%； -包装材料清单，包括包装油墨或物质的信息； -油墨制造商的证书； 5.每一批次出货只能有一个生产日期，不可多个生产日期混在同一批次出货；且零售包装上必须统一加上日期码；外箱对于日期码没有硬性规定； 6.涉及到相关款式会有闪粉的或者微塑料的，请统一默认出无闪粉或者不含微塑料版本； 7.邮包盒及外箱封箱必须是工字型封箱方式； 8.5 Surprise or Mini Brands涉及包装是2个及2个以上的球入PVC桶包装时，单个球上若有UPC#或者EAN#，请用空白贴纸覆盖住，贴纸尺寸自行测量能覆盖原条码即 可； 9. 无论是工厂自检还是ZURU验货，验货报告中必须有产品6面图(正面/背面/左面/右面/顶部/底部，不带包装); 10. 按空海运鉴定报告的要求，只要带锂电池出货，都需要加贴UN贴纸； 11. 所有出往GAS市场(德国/奥地利/瑞士)的电子产品身上需要加字唛，为ZURU FRANCE 地址，需跟包装上的地址一致 (如无电子产品，产品布标有此地址，或产品 太小无法增加可忽略此信息。如产品无法加字唛，需让对应跟单提供产品贴纸资料);（Amazon GPE的订单也需满足此要求） 12. 所有出往GAS德国 (瑞士，奥地利)。水弹枪系列必须使用EN71版本（电子和非电子水弹枪系列都需要符合); 护目镜需打日期码, 格式跟ZURU标准格式一样; 枪 身上增加ZURU FRANCE公司名和地址。使用贴纸和辐射上去都可以。如果有位置，最好增加ZURU Represented by: (此最好翻译德语，如果位置不允许，那么就只增 加ZURU法国和地址)。使用最新的EN71版包装和说明书）。Amazon GPE（包含UK/FR/ES/DE/IT）的订单也需满足此要求。 | X14: Luna Lin | Y14: 10.8403 | Z14: =Y14*L14 -> 1810.3301 | AB14: 77858-S003-MB-1 | AC14: 已入 | AK14: =I14 -> 501 | AL14: =I14 -> 501 | AN14: 29L | AP14: =I14 -> 501
