Workbook
Name bos: #REF!
Name Code: '[1]CQS Code(rev 38)'!$B$7:$E$1000
Name bos: #REF!
Name bos: #REF!

Sheet 9259
AZ1: 1-2前入单配比： | BC1: 8 | BD1: 1 | BE1: 3 | BF1: 19 | BG1: 8 | BH1: 18 | BI1: 3 | BJ1: =SUBTOTAL(9,BC1:BI1) -> 60
A2: ZURU Rainbocorn 猫蛋毛絨公仔生产排期表 #9259 | AZ2: 1-2后入单新配比： | BC2: 20 | BD2: 12 | BE2: 1 | BF2: 25 | BG2: 20 | BH2: 25 | BI2: 17 | BJ2: =SUBTOTAL(9,BC2:BI2) -> 120
A3: =#REF! -> #REF! | I3: （黃色表示更改或增加） | L3: （蓝色表示已完货） | P3: （綠色表示調整貨期） | AG3: 收縮膜 | AK3: 說明書 | BC3: A | BD3: E | BE3: B | BF3: D | BG3: G | BI3: H
A4: 接单期 | B4: 第三方客户名称 | C4: 国家 | D4: PO号 | E4: 客户PO号 | F4: SKU号 | G4: 系统货号 | H4: 货号 | I4: 名称 | J4: 数量 | K4: 内箱装箱数量(pcs) | L4: 装箱数（PCS） | M4: 总箱数 | N4: 计划出货期 | O4: 计划验货期 | P4: 第三方验货期 | Q4: 驗貨結果 | R4: 送货情况 | S4: 欠数 | T4: 船期SO | U4: 箱唛资料(收到日期) | V4: 外箱贴纸 | W4: 贴纸AI(收到日期) | Y4: 客供物料 | Z4: 日期码 | AA4: 备注 | AB4: ZURU 跟单 | AC4: 单价USD | AD4: 金额USD | AE4: 發票號 | AF4: 是否入系统 | AG4: MA 1語收縮膜 A版本 | AH4: MA 3语收缩膜 | AI4: EU 5L 收缩膜 | AJ4: 客版收縮膜 | AK4: MA 1語收藏指南 A版本 | AL4: MA 3语 收藏指南 A版本 | AM4: EU 5L 收藏指南 | AN4: 客版收藏指南 | AO4: MA口水胶 | AP4: 客版口水胶 | AQ4: 无闪粉口水胶 | AR4: PDQ SQ1-S001-S002 IL | AS4: PDQ SQ1-S001 3L | AT4: PDQ TQ1-S001 WM客版 1L | AU4: PDQ TQ1-S001-CA客版 2L | AV4: PDQ TQ2-S001 -S002 客版 | AW4: PDQ TQ3-S001 TG客版 | AX4: EC 展示架 | AY4: 中国单客办PDQ | AZ4: 客办PDQ | BA4: 无闪粉毛绒 | BB4: 布標 | BC4: 暹罗猫SIAMESE CAT | BD4: 孟加拉猫BENAL CAT | BE4: 美国猫AMERICAN SHORTHIR | BF4: 花斑猫CALICO CAT | BG4: 加菲猫EXOTIC CAT | BH4: 黑猫BLKCK CAT | BI4: 白猫CHNCHILLA CAT | BJ4: 总数 | BK4: 相差 | BL4: 入共享
A5: 45506 | B5: ACTION SERVICE & DISTRIBUTIE B.V. | C5: 荷兰 | D5: 4500141955 | E5: 4400438266 | F5: 4500141955-170 | H5: MB83-S002-9259 | I5: 混装（9259+9269各6PCS） | J5: 11280 | K5: 0 | L5: 6 | M5: =J5/L5 -> 1880 | N5: 45625 | O5: 45621 | Q5: PASS | U5: 8/2收到 | W5: 8/8收到 15L 黑白书纸 for slime bag+9/5收到西班牙环保标贴纸 | Y5: 8/8已收到客办包装资料 | AA5: 日期码格式：ZURU INC(BVI) 标准格式 日期：按实际生产日期 Packaging Info: 客版15L包装（收缩膜+西班牙环保标贴纸，收藏指南，15L 黑白书纸 for slime bag）+MA布标 Remark: 客人款号：3009949 1. 此单是子母件，贵司是母件工厂，需要负责组装入箱：一共2款，每款6pcs ，共12pcs 入一外箱。子件9259 工厂是兴信，子件9269 工厂是华康。子件CRD 是贵 司CRD -7天，会按时/提前送货到贵司组装。 2. 订单总数量496,320 pcs, 共分为22个柜子，请按期完货. 3. 所有产品按符合欧洲标准走货，微塑料需合规。 4. 所有包装材料都不允许PVC, 请用PET代替 5. 此单需要4套产前样及4套大货样，样板请寄到罗湖办公室Eddie收。 | AB5: Sandy Shao | AC5: 1.646 | AD5: =AC5*J5 -> 18566.88 | AE5: 88828-1.2 | AJ5: =J5 -> 11280 | AN5: =J5 -> 11280 | AQ5: =J5 -> 11280 | BB5: MA布标 | BC5: =J5/4 -> 2820 | BD5: =J5/4 -> 2820 | BE5: =J5/4 -> 2820 | BG5: =J5/4 -> 2820 | BJ5: =SUM(BC5:BI5) -> 11280 | BK5: =J5-BJ5 -> 0
A6: 45586 | B6: TJX COMPANIES, INC | C6: 美国 | D6: 4500147789 | E6: Marshalls DC#881-120PCS , DC#884-96PCS, DC#886-144PCS , DC#887-120PCS , DC#888-120PCS | F6: 4500147789-60 | H6: 9259-S001 | I6: 猫蛋 | J6: 600 | K6: 0 | L6: 24 | M6: =J6/L6 -> 25 | N6: 45649 | O6: 45645 | Q6: PASS | T6: 1/2出 | U6: 11/4收到 | W6: 无 | Y6: 11/16收到客供价格贴纸 | AA6: 日期码格式：ZURU INC(BVI) 标准格式 日期：按实际生产日期 Packaging Info: MA UPC包装+价格贴纸，价格贴纸客供。 Remark: 1. 产品和包装上印刷tracking code信息，格式为ZURU常规格式。 2. 分5个DC出货，每款产品每个DC的箱唛资料不同。具体分DC数量，请参考后面行项目备注。 3. ZURU QC验货。 | AB6: Emily Wu | AC6: 2.2472 | AD6: =J6*AC6 -> 1348.32 | AE6: 94169-1.23 | AG6: =J6 -> 600 | AL6: =J6 -> 600 | AQ6: =J6 -> 600 | BB6: MA布标 | BC6: =J6/4 -> 150 | BD6: =J6/4 -> 150 | BE6: =J6/4 -> 150 | BG6: =J6/4 -> 150 | BJ6: =SUM(BC6:BI6) -> 600 | BK6: =J6-BJ6 -> 0
A7: 45506 | B7: ACTION SERVICE & DISTRIBUTIE B.V. | C7: 荷兰 | D7: 4500141955 | E7: 4400926975 | F7: 4500141955-180 | H7: MB83-S002-9259 | I7: 混装（9259+9269各6PCS） | J7: 11280 | K7: 0 | L7: 6 | M7: =J7/L7 -> 1880 | N7: 45650 | O7: 45646 | Q7: PASS | T7: 12/30出 | U7: 8/2收到 | W7: 8/8收到 15L 黑白书纸 for slime bag+9/5收到西班牙环保标贴纸 | Y7: 8/8已收到客办包装资料 | AA7: 日期码格式：ZURU INC(BVI) 标准格式 日期：按实际生产日期 Packaging Info: 客版15L包装（收缩膜+西班牙环保标贴纸，收藏指南，15L 黑白书纸 for slime bag）+MA布标 Remark: 客人款号：3009949 1. 此单是子母件，贵司是母件工厂，需要负责组装入箱：一共2款，每款6pcs ，共12pcs 入一外箱。子件9259 工厂是兴信，子件9269 工厂是华康。子件CRD 是贵 司CRD -7天，会按时/提前送货到贵司组装。 2. 订单总数量496,320 pcs, 共分为22个柜子，请按期完货. 3. 所有产品按符合欧洲标准走货，微塑料需合规。 4. 所有包装材料都不允许PVC, 请用PET代替 5. 此单需要4套产前样及4套大货样，样板请寄到罗湖办公室Eddie收。 | AB7: Sandy Shao | AC7: 1.646 | AD7: =AC7*J7 -> 18566.88 | AE7: 94228-2.12 | AJ7: =J7 -> 11280 | AN7: =J7 -> 11280 | AQ7: =J7 -> 11280 | BB7: MA布标 | BC7: =J7/4 -> 2820 | BD7: =J7/4 -> 2820 | BE7: =J7/4 -> 2820 | BG7: =J7/4 -> 2820 | BJ7: =SUM(BC7:BI7) -> 11280 | BK7: =J7-BJ7 -> 0
A8: 45506 | B8: ACTION SERVICE & DISTRIBUTIE B.V. | C8: 荷兰 | D8: 4500141955 | E8: 4400909714 | F8: 4500141955-210 | H8: MB83-S002-9259 | I8: 混装（9259+9269各6PCS） | J8: 11280 | K8: 0 | L8: 6 | M8: =J8/L8 -> 1880 | N8: 45653 | O8: 45649 | Q8: PASS | T8: 1/3出 | U8: 8/2收到 | W8: 8/8收到 15L 黑白书纸 for slime bag+9/5收到西班牙环保标贴纸 | Y8: 8/8已收到客办包装资料 | AA8: 日期码格式：ZURU INC(BVI) 标准格式 日期：按实际生产日期 Packaging Info: 客版15L包装（收缩膜+西班牙环保标贴纸，收藏指南，15L 黑白书纸 for slime bag）+MA布标 Remark: 客人款号：3009949 1. 此单是子母件，贵司是母件工厂，需要负责组装入箱：一共2款，每款6pcs ，共12pcs 入一外箱。子件9259 工厂是兴信，子件9269 工厂是华康。子件CRD 是贵 司CRD -7天，会按时/提前送货到贵司组装。 2. 订单总数量496,320 pcs, 共分为22个柜子，请按期完货. 3. 所有产品按符合欧洲标准走货，微塑料需合规。 4. 所有包装材料都不允许PVC, 请用PET代替 5. 此单需要4套产前样及4套大货样，样板请寄到罗湖办公室Eddie收。 | AB8: Sandy Shao | AC8: 1.646 | AD8: =AC8*J8 -> 18566.88 | AJ8: =J8 -> 11280 | AN8: =J8 -> 11280 | AQ8: =J8 -> 11280 | BB8: MA布标 | BC8: =J8/4 -> 2820 | BD8: =J8/4 -> 2820 | BE8: =J8/4 -> 2820 | BG8: =J8/4 -> 2820 | BJ8: =SUM(BC8:BI8) -> 11280 | BK8: =J8-BJ8 -> 0
A9: 45586 | B9: TJX COMPANIES, INC | C9: 美国 | D9: 4500147796 | E9: TJ MAXX DC#891-168PCS , DC#894-144PCS , DC#896-120PCS , DC#897-240PCS , DC#898-120PCS | F9: 4500147796-80 | H9: 9259-S001 | I9: 猫蛋 | J9: 792 | K9: 0 | L9: 24 | M9: =J9/L9 -> 33 | N9: 45656 | O9: 45652 | Q9: PASS | T9: 1/8出 | U9: 11/4收到 | W9: 无 | Y9: 12-6客供价格贴纸 | AA9: 日期码格式：ZURU INC(BVI) 标准格式 日期：按实际生产日期 Packaging Info: MA UPC包装+价格贴纸，价格贴纸客供。 Remark: 1. 产品和包装上印刷tracking code信息，格式为ZURU常规格式。 2. 分5个DC出货，每款产品每个DC的箱唛资料不同。具体分DC数量，请参考后面行项目备注。 3. ZURU QC验货。 | AB9: Emily Wu | AC9: 2.2472 | AD9: =J9*AC9 -> 1779.7824 | AE9: 94170-1.23 | AG9: =J9 -> 792 | AL9: =J9 -> 792 | AQ9: =J9 -> 792 | BB9: MA布标 | BC9: =J9/4 -> 198 | BD9: =J9/4 -> 198 | BE9: =J9/4 -> 198 | BG9: =J9/4 -> 198 | BJ9: =SUM(BC9:BI9) -> 792 | BK9: =J9-BJ9 -> 0
A10: 45586 | B10: TJX COMPANIES, INC | C10: 美国 | D10: 4500147795 | E10: TJ MAXX DC#891-168PCS , DC#894-144PCS , DC#896-120PCS , DC#897-240PCS , DC#898-120PCS | F10: 4500147795-60 | H10: 9259-S001 | I10: 猫蛋 | J10: 792 | K10: 0 | L10: 24 | M10: =J10/L10 -> 33 | N10: 45656 | O10: 45652 | Q10: PASS | T10: 1/8出 | U10: 11/4收到 | W10: 无 | Y10: 12-6客供价格贴纸 | AA10: 日期码格式：ZURU INC(BVI) 标准格式 日期：按实际生产日期 Packaging Info: MA UPC包装+价格贴纸，价格贴纸客供。 Remark: 1. 产品和包装上印刷tracking code信息，格式为ZURU常规格式。 2. 分5个DC出货，每款产品每个DC的箱唛资料不同。具体分DC数量，请参考后面行项目备注。 3. ZURU QC验货。 | AB10: Emily Wu | AC10: 2.2472 | AD10: =J10*AC10 -> 1779.7824 | AE10: 94175-1.23 | AG10: =J10 -> 792 | AL10: =J10 -> 792 | AQ10: =J10 -> 792 | BB10: MA布标 | BC10: =J10/4 -> 198 | BD10: =J10/4 -> 198 | BE10: =J10/4 -> 198 | BG10: =J10/4 -> 198 | BJ10: =SUM(BC10:BI10) -> 792 | BK10: =J10-BJ10 -> 0
A11: 45586 | B11: TJX COMPANIES, INC | C11: 美国 | D11: 4500147793 | E11: Marshalls DC#881-120PCS , DC#884-96PCS, DC#886-144PCS , DC#887-120PCS , DC#888-120PCS | F11: 4500147793-80 | H11: 9259-S001 | I11: 猫蛋 | J11: 600 | K11: 0 | L11: 24 | M11: =J11/L11 -> 25 | N11: 45656 | O11: 45652 | Q11: PASS | T11: 1/9出 | U11: 11/4收到 | W11: 无 | Y11: 12-6客供价格贴纸 | AA11: 日期码格式：ZURU INC(BVI) 标准格式 日期：按实际生产日期 Packaging Info: MA UPC包装+价格贴纸，价格贴纸客供。 Remark: 1. 产品和包装上印刷tracking code信息，格式为ZURU常规格式。 2. 分5个DC出货，每款产品每个DC的箱唛资料不同。具体分DC数量，请参考后面行项目备注。 3. ZURU QC验货。 | AB11: Emily Wu | AC11: 2.2472 | AD11: =J11*AC11 -> 1348.32 | AE11: 94171-1.23 | AG11: =J11 -> 600 | AL11: =J11 -> 600 | AQ11: =J11 -> 600 | BB11: MA布标 | BC11: =J11/4 -> 150 | BD11: =J11/4 -> 150 | BE11: =J11/4 -> 150 | BG11: =J11/4 -> 150 | BJ11: =SUM(BC11:BI11) -> 600 | BK11: =J11-BJ11 -> 0
A12: 45586 | B12: TJX COMPANIES, INC | C12: 美国 | D12: 4500147792 | E12: Marshalls DC#881-120PCS , DC#884-96PCS, DC#886-144PCS , DC#887-120PCS , DC#888-120PCS | F12: 4500147792-60 | H12: 9259-S001 | I12: 猫蛋 | J12: 600 | K12: 0 | L12: 24 | M12: =J12/L12 -> 25 | N12: 45656 | O12: 45652 | Q12: PASS | T12: 1/9出 | U12: 11/4收到 | W12: 无 | Y12: 12-6客供价格贴纸 | AA12: 日期码格式：ZURU INC(BVI) 标准格式 日期：按实际生产日期 Packaging Info: MA UPC包装+价格贴纸，价格贴纸客供。 Remark: 1. 产品和包装上印刷tracking code信息，格式为ZURU常规格式。 2. 分5个DC出货，每款产品每个DC的箱唛资料不同。具体分DC数量，请参考后面行项目备注。 3. ZURU QC验货。 | AB12: Emily Wu | AC12: 2.2472 | AD12: =J12*AC12 -> 1348.32 | AE12: 94166-1.23 | AG12: =J12 -> 600 | AL12: =J12 -> 600 | AQ12: =J12 -> 600 | BB12: MA布标 | BC12: =J12/4 -> 150 | BD12: =J12/4 -> 150 | BE12: =J12/4 -> 150 | BG12: =J12/4 -> 150 | BJ12: =SUM(BC12:BI12) -> 600 | BK12: =J12-BJ12 -> 0
A13: 45586 | B13: TJX COMPANIES, INC | C13: 美国 | D13: 4500147798 | E13: TJ MAXX DC#891-240PCS , DC#894-192PCS , DC#896-192PCS , DC#897-384PCS , DC#898-192PCS | F13: 4500147798-90 | H13: 9259-S001 | I13: 猫蛋 | J13: 1200 | K13: 0 | L13: 24 | M13: =J13/L13 -> 50 | N13: 45657 | O13: 45653 | Q13: PASS | T13: 1/8出 | U13: 11/4收到 | W13: 无 | Y13: 12-6客供价格贴纸 | AA13: 日期码格式：ZURU INC(BVI) 标准格式 日期：按实际生产日期 Packaging Info: MA UPC包装+价格贴纸，价格贴纸客供。 Remark: 1. 产品和包装上印刷tracking code信息，格式为ZURU常规格式。 2. 分5个DC出货，每款产品每个DC的箱唛资料不同。具体分DC数量，请参考后面行项目备注。 3. ZURU QC验货。 | AB13: Emily Wu | AC13: 2.2427 | AD13: =J13*AC13 -> 2691.24 | AE13: 94174-1.23 | AG13: =J13 -> 1200 | AL13: =J13 -> 1200 | AQ13: =J13 -> 1200 | BB13: MA布标 | BC13: =J13/4 -> 300 | BD13: =J13/4 -> 300 | BE13: =J13/4 -> 300 | BG13: =J13/4 -> 300 | BJ13: =SUM(BC13:BI13) -> 1200 | BK13: =J13-BJ13 -> 0
A14: 45586 | B14: TJX COMPANIES, INC | C14: 美国 | D14: 4500147794 | E14: Marshalls DC#881-216PCS , DC#884-168PCS , DC#886-240PCS , DC#887-192PCS , DC#888-192PCS | F14: 4500147794-90 | H14: 9259-S001 | I14: 猫蛋 | J14: 1008 | K14: 0 | L14: 24 | M14: =J14/L14 -> 42 | N14: 45657 | O14: 45653 | Q14: PASS | T14: 1/9出 | U14: 11/4收到 | W14: 无 | Y14: 12-6客供价格贴纸 | AA14: 日期码格式：ZURU INC(BVI) 标准格式 日期：按实际生产日期 Packaging Info: MA UPC包装+价格贴纸，价格贴纸客供。 Remark: 1. 产品和包装上印刷tracking code信息，格式为ZURU常规格式。 2. 分5个DC出货，每款产品每个DC的箱唛资料不同。具体分DC数量，请参考后面行项目备注。 3. ZURU QC验货。 | AB14: Emily Wu | AC14: 2.2427 | AD14: =J14*AC14 -> 2260.6416 | AE14: 94176-1.23 | AG14: =J14 -> 1008 | AL14: =J14 -> 1008 | AQ14: =J14 -> 1008 | BB14: MA布标 | BC14: =J14/4 -> 252 | BD14: =J14/4 -> 252 | BE14: =J14/4 -> 252 | BG14: =J14/4 -> 252 | BJ14: =SUM(BC14:BI14) -> 1008 | BK14: =J14-BJ14 -> 0
A15: 45574 | B15: ACTION SERVICE & DISTRIBUTIE B.V. | C15: 荷兰 | D15: 4500146851 | E15: 4400925116 | F15: 4500146851-260 | H15: MB83-S002-9259 | I15: 混装（9259+9269各6PCS） | J15: 11862 | K15: 0 | L15: 6 | M15: =J15/L15 -> 1977 | N15: 45661 | O15: 45657 | Q15: PASS | T15: 1/16出 | U15: 10/9收到 | W15: 黑白书纸 for slime bag | AA15: 日期码格式：ZURU INC(BVI) 标准格式 日期：按实际生产日期 Packaging Info: 客版15L包装（收缩膜，收藏指南，15L 黑白书纸 for slime bag）+MA布标 Remark: 客人款号：3009949 1. 此单是子母件，贵司是母件工厂，需要负责组装入箱：一共2款，每款6pcs ，共12pcs 入一外箱。子件9259 工厂是兴信，子件9269 工厂是华康。子件CRD 是贵司CRD -7天，会按时/提前送货到贵司组装。 2. 订单总数量782,892 pcs, 共分为33个柜子，请按期完货. 3. 所有产品按符合欧洲标准走货，微塑料需合规。 4. 所有包装材料都不允许PVC, 请用PET代替 5. 此单需要4套产前样及4套大货样，样板请寄到罗湖办公室Eddie收。 | AB15: Becky Yang | AC15: 14.5047 | AD15: =AC15*M15 -> 28675.792 | AE15: 88972-1.10 | AJ15: =J15 -> 11862 | AN15: =J15 -> 11862 | AQ15: =J15 -> 11862 | BB15: MA布标 | BC15: =J15/4 -> 2965.5 | BD15: =J15/4 -> 2965.5 | BE15: =J15/4 -> 2965.5 | BG15: =J15/4 -> 2965.5 | BJ15: =SUM(BC15:BI15) -> 11862 | BK15: =J15-BJ15 -> 0
A16: 45574 | B16: ACTION SERVICE & DISTRIBUTIE B.V. | C16: 荷兰 | D16: 4500146851 | E16: 4400923138 | F16: 4500146851-240 | H16: MB83-S002-9259 | I16: 混装（9259+9269各6PCS） | J16: 11862 | K16: 0 | L16: 6 | M16: =J16/L16 -> 1977 | N16: 45661 | O16: 45657 | Q16: PASS | T16: 1/8出 | U16: 10/9收到 | W16: 黑白书纸 for slime bag | AA16: 日期码格式：ZURU INC(BVI) 标准格式 日期：按实际生产日期 Packaging Info: 客版15L包装（收缩膜，收藏指南，15L 黑白书纸 for slime bag）+MA布标 Remark: 客人款号：3009949 1. 此单是子母件，贵司是母件工厂，需要负责组装入箱：一共2款，每款6pcs ，共12pcs 入一外箱。子件9259 工厂是兴信，子件9269 工厂是华康。子件CRD 是贵司CRD -7天，会按时/提前送货到贵司组装。 2. 订单总数量782,892 pcs, 共分为33个柜子，请按期完货. 3. 所有产品按符合欧洲标准走货，微塑料需合规。 4. 所有包装材料都不允许PVC, 请用PET代替 5. 此单需要4套产前样及4套大货样，样板请寄到罗湖办公室Eddie收。 | AB16: Becky Yang | AC16: 14.8323 | AD16: =AC16*M16 -> 29323.457 | AE16: 88987-1.11 | AJ16: =J16 -> 11862 | AN16: =J16 -> 11862 | AQ16: =J16 -> 11862 | BB16: MA布标 | BC16: =J16/4 -> 2965.5 | BD16: =J16/4 -> 2965.5 | BE16: =J16/4 -> 2965.5 | BG16: =J16/4 -> 2965.5 | BJ16: =SUM(BC16:BI16) -> 11862 | BK16: =J16-BJ16 -> 0
A17: 45574 | B17: ACTION SERVICE & DISTRIBUTIE B.V. | C17: 荷兰 | D17: 4500146851 | E17: 4400952460 | F17: 4500146851-280 | H17: MB83-S002-9259 | I17: 混装（9259+9269各6PCS） | J17: 11862 | K17: 0 | L17: 6 | M17: =J17/L17 -> 1977 | N17: 45666 | O17: 45663 | Q17: PASS | U17: 10/9收到 | W17: 黑白书纸 for slime bag | AA17: 日期码格式：ZURU INC(BVI) 标准格式 日期：按实际生产日期 Packaging Info: 客版15L包装（收缩膜，收藏指南，15L 黑白书纸 for slime bag）+MA布标 Remark: 客人款号：3009949 1. 此单是子母件，贵司是母件工厂，需要负责组装入箱：一共2款，每款6pcs ，共12pcs 入一外箱。子件9259 工厂是兴信，子件9269 工厂是华康。子件CRD 是贵司CRD -7天，会按时/提前送货到贵司组装。 2. 订单总数量782,892 pcs, 共分为33个柜子，请按期完货. 3. 所有产品按符合欧洲标准走货，微塑料需合规。 4. 所有包装材料都不允许PVC, 请用PET代替 5. 此单需要4套产前样及4套大货样，样板请寄到罗湖办公室Eddie收。 | AB17: Becky Yang | AC17: 14.5074 | AD17: =AC17*M17 -> 28681.13 | AE17: 94026-1.14 | AJ17: =J17 -> 11862 | AN17: =J17 -> 11862 | AQ17: =J17 -> 11862 | BB17: MA布标 | BC17: =J17/4 -> 2965.5 | BD17: =J17/4 -> 2965.5 | BE17: =J17/4 -> 2965.5 | BG17: =J17/4 -> 2965.5 | BJ17: =SUM(BC17:BI17) -> 11862 | BK17: =J17-BJ17 -> 0
A18: 45574 | B18: ACTION SERVICE & DISTRIBUTIE B.V. | C18: 荷兰 | D18: 4500146851 | E18: 4400631850 | F18: 4500146851-110 | H18: MB83-S002-9259 | I18: 混装（9259+9269各6PCS） | J18: 11862 | K18: 0 | L18: 6 | M18: =J18/L18 -> 1977 | N18: 45668 | O18: 45664 | Q18: PASS | T18: 1/20出 | U18: 10/9收到 | W18: 黑白书纸 for slime bag | AA18: 日期码格式：ZURU INC(BVI) 标准格式 日期：按实际生产日期 Packaging Info: 客版15L包装（收缩膜，收藏指南，15L 黑白书纸 for slime bag）+MA布标 Remark: 客人款号：3009949 1. 此单是子母件，贵司是母件工厂，需要负责组装入箱：一共2款，每款6pcs ，共12pcs 入一外箱。子件9259 工厂是兴信，子件9269 工厂是华康。子件CRD 是贵司CRD -7天，会按时/提前送货到贵司组装。 2. 订单总数量782,892 pcs, 共分为33个柜子，请按期完货. 3. 所有产品按符合欧洲标准走货，微塑料需合规。 4. 所有包装材料都不允许PVC, 请用PET代替 5. 此单需要4套产前样及4套大货样，样板请寄到罗湖办公室Eddie收。 | AB18: Becky Yang | AC18: 14.541 | AD18: =AC18*M18 -> 28747.557 | AE18: 94091-1.18 | AJ18: =J18 -> 11862 | AN18: =J18 -> 11862 | AQ18: =J18 -> 11862 | BB18: MA布标 | BC18: =J18/4 -> 2965.5 | BD18: =J18/4 -> 2965.5 | BE18: =J18/4 -> 2965.5 | BG18: =J18/4 -> 2965.5 | BJ18: =SUM(BC18:BI18) -> 11862 | BK18: =J18-BJ18 -> 0
A19: 45586 | B19: TJX COMPANIES, INC | C19: 美国 | D19: 4500147799 | E19: Marshalls DC#881-120PCS , DC#884-96PCS, DC#886-144PCS , DC#887-120PCS , DC#888-120PCS | F19: 4500147799-70 | H19: 9259-S001 | I19: 猫蛋 | J19: 600 | K19: 0 | L19: 24 | M19: =J19/L19 -> 25 | N19: 45677 | O19: 45673 | Q19: PASS | T19: 2/14出 | U19: 11/4收到 | W19: 无 | Y19: 12/20-客供价格贴纸 | AA19: 日期码格式：ZURU INC(BVI) 标准格式 日期：按实际生产日期 Packaging Info: MA UPC包装+价格贴纸，价格贴纸客供。 Remark: 1. 产品和包装上印刷tracking code信息，格式为ZURU常规格式。 2. 分5个DC出货，每款产品每个DC的箱唛资料不同。具体分DC数量，请参考后面行项目备注。 3. ZURU QC验货。 | AB19: Emily Wu | AC19: 2.2421 | AD19: =J19*AC19 -> 1345.26 | AG19: =J19 -> 600 | AL19: =J19 -> 600 | AQ19: =J19 -> 600 | BB19: MA布标 | BC19: =J19/4 -> 150 | BD19: =J19/4 -> 150 | BE19: =J19/4 -> 150 | BG19: =J19/4 -> 150 | BJ19: =SUM(BC19:BI19) -> 600 | BK19: =J19-BJ19 -> 0
A20: 45586 | B20: TJX COMPANIES, INC | C20: 美国 | D20: 4500147801 | E20: TJ MAXX DC#891-168PCS , DC#894-144PCS , DC#896-120PCS , DC#897-240PCS , DC#898-120PCS | F20: 4500147801-70 | H20: 9259-S001 | I20: 猫蛋 | J20: 792 | K20: 0 | L20: 24 | M20: =J20/L20 -> 33 | N20: 45677 | O20: 45673 | Q20: PASS | T20: 2/11出 | U20: 11/4收到 | W20: 无 | Y20: 12/20-客供价格贴纸 | AA20: 日期码格式：ZURU INC(BVI) 标准格式 日期：按实际生产日期 Packaging Info: MA UPC包装+价格贴纸，价格贴纸客供。 Remark: 1. 产品和包装上印刷tracking code信息，格式为ZURU常规格式。 2. 分5个DC出货，每款产品每个DC的箱唛资料不同。具体分DC数量，请参考后面行项目备注。 3. ZURU QC验货。 | AB20: Emily Wu | AC20: 2.2472 | AD20: =J20*AC20 -> 1779.7824 | AG20: =J20 -> 792 | AL20: =J20 -> 792 | AQ20: =J20 -> 792 | BB20: MA布标 | BC20: =J20/4 -> 198 | BD20: =J20/4 -> 198 | BE20: =J20/4 -> 198 | BG20: =J20/4 -> 198 | BJ20: =SUM(BC20:BI20) -> 792 | BK20: =J20-BJ20 -> 0
A21: 45586 | B21: TJX COMPANIES, INC | C21: 美国 | D21: 4500147803 | E21: TJ MAXX DC#891-240PCS , DC#894-216PCS , DC#896-192PCS , DC#897-360PCS , DC#898-192PCS | F21: 4500147803-90 | H21: 9259-S001 | I21: 猫蛋 | J21: 1200 | K21: 0 | L21: 24 | M21: =J21/L21 -> 50 | N21: 45677 | O21: 45673 | Q21: PASS | T21: 2/13出 | U21: 11/4收到 | W21: 无 | Y21: 12/20-客供价格贴纸 | AA21: 日期码格式：ZURU INC(BVI) 标准格式 日期：按实际生产日期 Packaging Info: MA UPC包装+价格贴纸，价格贴纸客供。 Remark: 1. 产品和包装上印刷tracking code信息，格式为ZURU常规格式。 2. 分5个DC出货，每款产品每个DC的箱唛资料不同。具体分DC数量，请参考后面行项目备注。 3. ZURU QC验货。 | AB21: Emily Wu | AC21: 2.2427 | AD21: =J21*AC21 -> 2691.24 | AG21: =J21 -> 1200 | AL21: =J21 -> 1200 | AQ21: =J21 -> 1200 | BB21: MA布标 | BC21: =J21/4 -> 300 | BD21: =J21/4 -> 300 | BE21: =J21/4 -> 300 | BG21: =J21/4 -> 300 | BJ21: =SUM(BC21:BI21) -> 1200 | BK21: =J21-BJ21 -> 0
A22: 45586 | B22: TJX COMPANIES, INC | C22: 美国 | D22: 4500147800 | E22: Marshalls DC#881-216PCS , DC#884-168PCS , DC#886-216PCS , DC#887-192PCS , DC#888-216PCS | F22: 4500147800-90 | H22: 9259-S001 | I22: 猫蛋 | J22: 1008 | K22: 0 | L22: 24 | M22: =J22/L22 -> 42 | N22: 45677 | O22: 45673 | Q22: PASS | T22: 2/14出 | U22: 11/4收到 | W22: 无 | Y22: 12/20-客供价格贴纸 | AA22: 日期码格式：ZURU INC(BVI) 标准格式 日期：按实际生产日期 Packaging Info: MA UPC包装+价格贴纸，价格贴纸客供。 Remark: 1. 产品和包装上印刷tracking code信息，格式为ZURU常规格式。 2. 分5个DC出货，每款产品每个DC的箱唛资料不同。具体分DC数量，请参考后面行项目备注。 3. ZURU QC验货。 | AB22: Emily Wu | AC22: 2.2427 | AD22: =J22*AC22 -> 2260.6416 | AG22: =J22 -> 1008 | AL22: =J22 -> 1008 | AQ22: =J22 -> 1008 | BB22: MA布标 | BC22: =J22/4 -> 252 | BD22: =J22/4 -> 252 | BE22: =J22/4 -> 252 | BG22: =J22/4 -> 252 | BJ22: =SUM(BC22:BI22) -> 1008 | BK22: =J22-BJ22 -> 0
A23: 45574 | B23: ACTION SERVICE & DISTRIBUTIE B.V. | C23: 荷兰 | D23: 4500146851 | E23: 4400923139 | F23: 4500146851-250 | H23: MB83-S002-9259 | I23: 混装（9259+9269各6PCS） | J23: 11862 | K23: 0 | L23: 6 | M23: =J23/L23 -> 1977 | N23: 45677 | O23: 45673 | Q23: PASS | T23: 1/26出 | U23: 10/9收到 | W23: 黑白书纸 for slime bag | AA23: 日期码格式：ZURU INC(BVI) 标准格式 日期：按实际生产日期 Packaging Info: 客版15L包装（收缩膜，收藏指南，15L 黑白书纸 for slime bag）+MA布标 Remark: 客人款号：3009949 1. 此单是子母件，贵司是母件工厂，需要负责组装入箱：一共2款，每款6pcs ，共12pcs 入一外箱。子件9259 工厂是兴信，子件9269 工厂是华康。子件CRD 是贵司CRD -7天，会按时/提前送货到贵司组装。 2. 订单总数量782,892 pcs, 共分为33个柜子，请按期完货. 3. 所有产品按符合欧洲标准走货，微塑料需合规。 4. 所有包装材料都不允许PVC, 请用PET代替 5. 此单需要4套产前样及4套大货样，样板请寄到罗湖办公室Eddie收。 | AB23: Becky Yang | AC23: 14.541 | AD23: =AC23*M23 -> 28747.557 | AE23: 94091-1.18 | AJ23: =J23 -> 11862 | AN23: =J23 -> 11862 | AQ23: =J23 -> 11862 | BB23: MA布标 | BC23: =J23/4 -> 2965.5 | BD23: =J23/4 -> 2965.5 | BE23: =J23/4 -> 2965.5 | BG23: =J23/4 -> 2965.5 | BJ23: =SUM(BC23:BI23) -> 11862 | BK23: =J23-BJ23 -> 0
A24: 45574 | B24: ACTION SERVICE & DISTRIBUTIE B.V. | C24: 荷兰 | D24: 4500146851 | E24: 4400393637 | F24: 4500146851-70 | H24: MB83-S002-9259 | I24: 混装（9259+9269各6PCS） | J24: 11862 | K24: 0 | L24: 6 | M24: =J24/L24 -> 1977 | N24: 45691 | O24: 45687 | Q24: PASS | T24: 2/6出 | U24: 10/9收到 | W24: 黑白书纸 for slime bag | AA24: 日期码格式：ZURU INC(BVI) 标准格式 日期：按实际生产日期 Packaging Info: 客版15L包装（收缩膜，收藏指南，15L 黑白书纸 for slime bag）+MA布标 Remark: 客人款号：3009949 1. 此单是子母件，贵司是母件工厂，需要负责组装入箱：一共2款，每款6pcs ，共12pcs 入一外箱。子件9259 工厂是兴信，子件9269 工厂是华康。子件CRD 是贵司CRD -7天，会按时/提前送货到贵司组装。 2. 订单总数量782,892 pcs, 共分为33个柜子，请按期完货. 3. 所有产品按符合欧洲标准走货，微塑料需合规。 4. 所有包装材料都不允许PVC, 请用PET代替 5. 此单需要4套产前样及4套大货样，样板请寄到罗湖办公室Eddie收。 | AB24: Becky Yang | AC24: 14.541 | AD24: =AC24*M24 -> 28747.557 | AE24: 94182-2.6 | AJ24: =J24 -> 11862 | AN24: =J24 -> 11862 | AQ24: =J24 -> 11862 | BB24: MA布标 | BC24: =J24/4 -> 2965.5 | BD24: =J24/4 -> 2965.5 | BE24: =J24/4 -> 2965.5 | BG24: =J24/4 -> 2965.5 | BJ24: =SUM(BC24:BI24) -> 11862 | BK24: =J24-BJ24 -> 0
A25: 45586 | B25: TJX COMPANIES, INC | C25: 美国 | D25: 4500147804 | E25: Marshalls DC#881-120PCS , DC#884-96PCS, DC#886-144PCS , DC#887-120PCS , DC#888-120PCS | F25: 4500147804-80 | H25: 9259-S001 | I25: 猫蛋 | J25: 600 | K25: 0 | L25: 24 | M25: =J25/L25 -> 25 | N25: 45698 | O25: 45694 | Q25: PASS | T25: 2/18出 | U25: 11/4收到 | W25: 无 | Y25: 12/20-客供价格贴纸 | AA25: 日期码格式：ZURU INC(BVI) 标准格式 日期：按实际生产日期 Packaging Info: MA UPC包装+价格贴纸，价格贴纸客供。 Remark: 1. 产品和包装上印刷tracking code信息，格式为ZURU常规格式。 2. 分5个DC出货，每款产品每个DC的箱唛资料不同。具体分DC数量，请参考后面行项目备注。 3. ZURU QC验货。 | AB25: Emily Wu | AC25: 2.2472 | AD25: =J25*AC25 -> 1348.32 | AE25: 94381-2.27 | AG25: =J25 -> 600 | AL25: =J25 -> 600 | AQ25: =J25 -> 600 | BB25: MA布标 | BC25: =J25/4 -> 150 | BD25: =J25/4 -> 150 | BE25: =J25/4 -> 150 | BG25: =J25/4 -> 150 | BJ25: =SUM(BC25:BI25) -> 600 | BK25: =J25-BJ25 -> 0
A26: 45586 | B26: TJX COMPANIES, INC | C26: 美国 | D26: 4500147806 | E26: TJ MAXX DC#891-168PCS , DC#894-144PCS , DC#896-120PCS , DC#897-240PCS , DC#898-120PCS | F26: 4500147806-80 | H26: 9259-S001 | I26: 猫蛋 | J26: 792 | K26: 0 | L26: 24 | M26: =J26/L26 -> 33 | N26: 45698 | O26: 45694 | Q26: PASS | T26: 2/21出 | U26: 11/4收到 | W26: 无 | Y26: 12/20-客供价格贴纸 | AA26: 日期码格式：ZURU INC(BVI) 标准格式 日期：按实际生产日期 Packaging Info: MA UPC包装+价格贴纸，价格贴纸客供。 Remark: 1. 产品和包装上印刷tracking code信息，格式为ZURU常规格式。 2. 分5个DC出货，每款产品每个DC的箱唛资料不同。具体分DC数量，请参考后面行项目备注。 3. ZURU QC验货。 | AB26: Emily Wu | AC26: 2.2472 | AD26: =J26*AC26 -> 1779.7824 | AE26: 94380-2.27 | AG26: =J26 -> 792 | AL26: =J26 -> 792 | AQ26: =J26 -> 792 | BB26: MA布标 | BC26: =J26/4 -> 198 | BD26: =J26/4 -> 198 | BE26: =J26/4 -> 198 | BG26: =J26/4 -> 198 | BJ26: =SUM(BC26:BI26) -> 792 | BK26: =J26-BJ26 -> 0
A27: 45506 | B27: ACTION SERVICE & DISTRIBUTIE B.V. | C27: 荷兰 | D27: 4500141955 | E27: 4400919336 | F27: 4500141955-220 | H27: MB83-S002-9259 | I27: 混装（9259+9269各6PCS） | J27: 11280 | K27: 0 | L27: 6 | M27: =J27/L27 -> 1880 | N27: 45692 | O27: 45322 | Q27: PASS | T27: 2/12出 | U27: 8/2收到 | W27: 8/8收到 15L 黑白书纸 for slime bag+9/5收到西班牙环保标贴纸 | Y27: 8/8已收到客办包装资料 | AA27: 日期码格式：ZURU INC(BVI) 标准格式 日期：按实际生产日期 Packaging Info: 客版15L包装（收缩膜+西班牙环保标贴纸，收藏指南，15L 黑白书纸 for slime bag）+MA布标 Remark: 客人款号：3009949 1. 此单是子母件，贵司是母件工厂，需要负责组装入箱：一共2款，每款6pcs ，共12pcs 入一外箱。子件9259 工厂是兴信，子件9269 工厂是华康。子件CRD 是贵 司CRD -7天，会按时/提前送货到贵司组装。 2. 订单总数量496,320 pcs, 共分为22个柜子，请按期完货. 3. 所有产品按符合欧洲标准走货，微塑料需合规。 4. 所有包装材料都不允许PVC, 请用PET代替 5. 此单需要4套产前样及4套大货样，样板请寄到罗湖办公室Eddie收。 | AB27: Sandy Shao | AC27: 1.646 | AD27: =AC27*J27 -> 18566.88 | AJ27: =J27 -> 11280 | AN27: =J27 -> 11280 | AQ27: =J27 -> 11280 | BB27: MA布标 | BC27: =J27/4 -> 2820 | BD27: =J27/4 -> 2820 | BE27: =J27/4 -> 2820 | BG27: =J27/4 -> 2820 | BJ27: =SUM(BC27:BI27) -> 11280 | BK27: =J27-BJ27 -> 0
A28: 45574 | B28: ACTION SERVICE & DISTRIBUTIE B.V. | C28: 荷兰 | D28: 4500146851 | E28: 4400907403 | F28: 4500146851-190 | H28: MB83-S002-9259 | I28: 混装（9259+9269各6PCS） | J28: 11862 | K28: 0 | L28: 6 | M28: =J28/L28 -> 1977 | N28: 45696 | O28: 45692 | Q28: PASS | T28: 2/11出 | U28: 10/9收到 | W28: 黑白书纸 for slime bag | AA28: 日期码格式：ZURU INC(BVI) 标准格式 日期：按实际生产日期 Packaging Info: 客版15L包装（收缩膜，收藏指南，15L 黑白书纸 for slime bag）+MA布标 Remark: 客人款号：3009949 1. 此单是子母件，贵司是母件工厂，需要负责组装入箱：一共2款，每款6pcs ，共12pcs 入一外箱。子件9259 工厂是兴信，子件9269 工厂是华康。子件CRD 是贵司CRD -7天，会按时/提前送货到贵司组装。 2. 订单总数量782,892 pcs, 共分为33个柜子，请按期完货. 3. 所有产品按符合欧洲标准走货，微塑料需合规。 4. 所有包装材料都不允许PVC, 请用PET代替 5. 此单需要4套产前样及4套大货样，样板请寄到罗湖办公室Eddie收。 | AB28: Becky Yang | AC28: 14.5074 | AD28: =M28*AC28 -> 28681.13 | AE28: 94211-2.11 | AJ28: =J28 -> 11862 | AN28: =J28 -> 11862 | AQ28: =J28 -> 11862 | BB28: MA布标 | BC28: =J28/4 -> 2965.5 | BD28: =J28/4 -> 2965.5 | BE28: =J28/4 -> 2965.5 | BG28: =J28/4 -> 2965.5 | BJ28: =SUM(BC28:BI28) -> 11862 | BK28: =J28-BJ28 -> 0
A29: 45574 | B29: ACTION SERVICE & DISTRIBUTIE B.V. | C29: 荷兰 | D29: 4500146851 | E29: 4400328861 | F29: 4500146851-30 | H29: MB83-S002-9259 | I29: 混装（9259+9269各6PCS） | J29: 11862 | K29: 0 | L29: 6 | M29: =J29/L29 -> 1977 | N29: 45724 | O29: 45720 | Q29: PASS | T29: 3/18出 | U29: 10/9收到 | W29: 黑白书纸 for slime bag | AA29: 日期码格式：ZURU INC(BVI) 标准格式 日期：按实际生产日期 Packaging Info: 客版15L包装（收缩膜，收藏指南，15L 黑白书纸 for slime bag）+MA布标 Remark: 客人款号：3009949 1. 此单是子母件，贵司是母件工厂，需要负责组装入箱：一共2款，每款6pcs ，共12pcs 入一外箱。子件9259 工厂是兴信，子件9269 工厂是华康。子件CRD 是贵司CRD -7天，会按时/提前送货到贵司组装。 2. 订单总数量782,892 pcs, 共分为33个柜子，请按期完货. 3. 所有产品按符合欧洲标准走货，微塑料需合规。 4. 所有包装材料都不允许PVC, 请用PET代替 5. 此单需要4套产前样及4套大货样，样板请寄到罗湖办公室Eddie收。 | AB29: Becky Yang | AC29: 0.4654 | AD29: =AC29*M29 -> 920.0958 | AE29: 94584-3.20 | AJ29: =J29 -> 11862 | AN29: =J29 -> 11862 | AQ29: =J29 -> 11862 | BB29: MA布标 | BC29: =J29/4 -> 2965.5 | BD29: =J29/4 -> 2965.5 | BE29: =J29/4 -> 2965.5 | BG29: =J29/4 -> 2965.5 | BJ29: =SUM(BC29:BI29) -> 11862 | BK29: =J29-BJ29 -> 0
A30: 45574 | B30: ACTION SERVICE & DISTRIBUTIE B.V. | C30: 荷兰 | D30: 4500146851 | E30: 4400393638 | F30: 4500146851-80 | H30: MB83-S002-9259 | I30: 混装（9259+9269各6PCS） | J30: 11862 | K30: 0 | L30: 6 | M30: =J30/L30 -> 1977 | N30: 45736 | O30: 45731 | Q30: PASS | T30: 3/22出 | U30: 10/9收到 | W30: 黑白书纸 for slime bag | AA30: 日期码格式：ZURU INC(BVI) 标准格式 日期：按实际生产日期 Packaging Info: 客版15L包装（收缩膜，收藏指南，15L 黑白书纸 for slime bag）+MA布标 Remark: 客人款号：3009949 1. 此单是子母件，贵司是母件工厂，需要负责组装入箱：一共2款，每款6pcs ，共12pcs 入一外箱。子件9259 工厂是兴信，子件9269 工厂是华康。子件CRD 是贵司CRD -7天，会按时/提前送货到贵司组装。 2. 订单总数量782,892 pcs, 共分为33个柜子，请按期完货. 3. 所有产品按符合欧洲标准走货，微塑料需合规。 4. 所有包装材料都不允许PVC, 请用PET代替 5. 此单需要4套产前样及4套大货样，样板请寄到罗湖办公室Eddie收。 | AB30: Becky Yang | AC30: 1.6548 | AD30: =AC30*M30 -> 3271.5396 | AE30: 94627-3.25 | AJ30: =J30 -> 11862 | AN30: =J30 -> 11862 | AQ30: =J30 -> 11862 | BB30: MA布标 | BC30: =J30/4 -> 2965.5 | BD30: =J30/4 -> 2965.5 | BE30: =J30/4 -> 2965.5 | BG30: =J30/4 -> 2965.5 | BJ30: =SUM(BC30:BI30) -> 11862 | BK30: =J30-BJ30 -> 0
A31: 45574 | B31: ACTION SERVICE & DISTRIBUTIE B.V. | C31: 荷兰 | D31: 4500146851 | E31: 4400650967 | F31: 4500146851-130 | H31: MB83-S002-9259 | I31: 混装（9259+9269各6PCS） | J31: 11862 | K31: 0 | L31: 6 | M31: =J31/L31 -> 1977 | N31: 45738 | O31: 45734 | Q31: PASS | T31: 3/25出 | U31: 10/9收到 | W31: 黑白书纸 for slime bag | AA31: 日期码格式：ZURU INC(BVI) 标准格式 日期：按实际生产日期 Packaging Info: 客版15L包装（收缩膜，收藏指南，15L 黑白书纸 for slime bag）+MA布标 Remark: 客人款号：3009949 1. 此单是子母件，贵司是母件工厂，需要负责组装入箱：一共2款，每款6pcs ，共12pcs 入一外箱。子件9259 工厂是兴信，子件9269 工厂是华康。子件CRD 是贵司CRD -7天，会按时/提前送货到贵司组装。 2. 订单总数量782,892 pcs, 共分为33个柜子，请按期完货. 3. 所有产品按符合欧洲标准走货，微塑料需合规。 4. 所有包装材料都不允许PVC, 请用PET代替 5. 此单需要4套产前样及4套大货样，样板请寄到罗湖办公室Eddie收。 | AB31: Becky Yang | AC31: 1.6548 | AD31: =AC31*M31 -> 3271.5396 | AE31: 94668-3.29 | AJ31: =J31 -> 11862 | AN31: =J31 -> 11862 | AQ31: =J31 -> 11862 | BB31: MA布标 | BC31: =J31/4 -> 2965.5 | BD31: =J31/4 -> 2965.5 | BE31: =J31/4 -> 2965.5 | BG31: =J31/4 -> 2965.5 | BJ31: =SUM(BC31:BI31) -> 11862 | BK31: =J31-BJ31 -> 0
A32: 45574 | B32: ACTION SERVICE & DISTRIBUTIE B.V. | C32: 荷兰 | D32: 4500146851 | E32: 4400393639 | F32: 4500146851-90 | H32: MB83-S002-9259 | I32: 混装（9259+9269各6PCS） | J32: 11862 | K32: 0 | L32: 6 | M32: =J32/L32 -> 1977 | N32: 45745 | O32: 45741 | Q32: PASS | T32: 3/31出 | U32: 10/9收到 | W32: 黑白书纸 for slime bag | AA32: 日期码格式：ZURU INC(BVI) 标准格式 日期：按实际生产日期 Packaging Info: 客版15L包装（收缩膜，收藏指南，15L 黑白书纸 for slime bag）+MA布标 Remark: 客人款号：3009949 1. 此单是子母件，贵司是母件工厂，需要负责组装入箱：一共2款，每款6pcs ，共12pcs 入一外箱。子件9259 工厂是兴信，子件9269 工厂是华康。子件CRD 是贵司CRD -7天，会按时/提前送货到贵司组装。 2. 订单总数量782,892 pcs, 共分为33个柜子，请按期完货. 3. 所有产品按符合欧洲标准走货，微塑料需合规。 4. 所有包装材料都不允许PVC, 请用PET代替 5. 此单需要4套产前样及4套大货样，样板请寄到罗湖办公室Eddie收。 | AB32: Becky Yang | AC32: 0.4654 | AD32: =AC32*M32 -> 920.0958 | AE32: 94919-5.5 | AJ32: =J32 -> 11862 | AN32: =J32 -> 11862 | AQ32: =J32 -> 11862 | BB32: MA布标 | BC32: =J32/4 -> 2965.5 | BD32: =J32/4 -> 2965.5 | BE32: =J32/4 -> 2965.5 | BG32: =J32/4 -> 2965.5 | BJ32: =SUM(BC32:BI32) -> 11862 | BK32: =J32-BJ32 -> 0
A33: 45574 | B33: ACTION SERVICE & DISTRIBUTIE B.V. | C33: 荷兰 | D33: 4500146851 | E33: 4400631849 | F33: 4500146851-100 | H33: MB83-S002-9259 | I33: 混装（9259+9269各6PCS） | J33: 11862 | K33: 0 | L33: 6 | M33: =J33/L33 -> 1977 | N33: 45753 | O33: 45749 | Q33: PASS | U33: 10/9收到 | W33: 黑白书纸 for slime bag | AA33: 日期码格式：ZURU INC(BVI) 标准格式 日期：按实际生产日期 Packaging Info: 客版15L包装（收缩膜，收藏指南，15L 黑白书纸 for slime bag）+MA布标 Remark: 客人款号：3009949 1. 此单是子母件，贵司是母件工厂，需要负责组装入箱：一共2款，每款6pcs ，共12pcs 入一外箱。子件9259 工厂是兴信，子件9269 工厂是华康。子件CRD 是贵司CRD -7天，会按时/提前送货到贵司组装。 2. 订单总数量782,892 pcs, 共分为33个柜子，请按期完货. 3. 所有产品按符合欧洲标准走货，微塑料需合规。 4. 所有包装材料都不允许PVC, 请用PET代替 5. 此单需要4套产前样及4套大货样，样板请寄到罗湖办公室Eddie收。 | AB33: Becky Yang | AC33: 1.6548 | AD33: =AC33*M33 -> 3271.5396 | AE33: 94927-5.6 | AJ33: =J33 -> 11862 | AN33: =J33 -> 11862 | AQ33: =J33 -> 11862 | BB33: MA布标 | BC33: =J33/4 -> 2965.5 | BD33: =J33/4 -> 2965.5 | BE33: =J33/4 -> 2965.5 | BG33: =J33/4 -> 2965.5 | BJ33: =SUM(BC33:BI33) -> 11862 | BK33: =J33-BJ33 -> 0
A34: 45574 | B34: ACTION SERVICE & DISTRIBUTIE B.V. | C34: 荷兰 | D34: 4500146851 | E34: 4400952458 | F34: 4500146851-270 | H34: MB83-S002-9259 | I34: 混装（9259+9269各6PCS） | J34: 11862 | K34: 0 | L34: 6 | M34: =J34/L34 -> 1977 | N34: 45758 | O34: 45754 | Q34: PASS | T34: 4/15出 | U34: 10/9收到 | W34: 黑白书纸 for slime bag | AA34: 日期码格式：ZURU INC(BVI) 标准格式 日期：按实际生产日期 Packaging Info: 客版15L包装（收缩膜，收藏指南，15L 黑白书纸 for slime bag）+MA布标 Remark: 客人款号：3009949 1. 此单是子母件，贵司是母件工厂，需要负责组装入箱：一共2款，每款6pcs ，共12pcs 入一外箱。子件9259 工厂是兴信，子件9269 工厂是华康。子件CRD 是贵司CRD -7天，会按时/提前送货到贵司组装。 2. 订单总数量782,892 pcs, 共分为33个柜子，请按期完货. 3. 所有产品按符合欧洲标准走货，微塑料需合规。 4. 所有包装材料都不允许PVC, 请用PET代替 5. 此单需要4套产前样及4套大货样，样板请寄到罗湖办公室Eddie收。 | AB34: Becky Yang | AC34: 14.6964 | AD34: =AC34*M34 -> 29054.783 | AE34: 94766-4.15 | AJ34: =J34 -> 11862 | AN34: =J34 -> 11862 | AQ34: =J34 -> 11862 | BB34: MA布标 | BC34: =J34/4 -> 2965.5 | BD34: =J34/4 -> 2965.5 | BE34: =J34/4 -> 2965.5 | BG34: =J34/4 -> 2965.5 | BJ34: =SUM(BC34:BI34) -> 11862 | BK34: =J34-BJ34 -> 0
A35: 45574 | B35: ACTION SERVICE & DISTRIBUTIE B.V. | C35: 荷兰 | D35: 4500146851 | E35: 4400902197 | F35: 4500146851-180 | H35: MB83-S002-9259 | I35: 混装（9259+9269各6PCS） | J35: 11862 | K35: 0 | L35: 6 | M35: =J35/L35 -> 1977 | N35: 45762 | O35: 45758 | Q35: PASS | T35: 4/19出 | U35: 10/9收到 | W35: 黑白书纸 for slime bag | AA35: 日期码格式：ZURU INC(BVI) 标准格式 日期：按实际生产日期 Packaging Info: 客版15L包装（收缩膜，收藏指南，15L 黑白书纸 for slime bag）+MA布标 Remark: 客人款号：3009949 1. 此单是子母件，贵司是母件工厂，需要负责组装入箱：一共2款，每款6pcs ，共12pcs 入一外箱。子件9259 工厂是兴信，子件9269 工厂是华康。子件CRD 是贵司CRD -7天，会按时/提前送货到贵司组装。 2. 订单总数量782,892 pcs, 共分为33个柜子，请按期完货. 3. 所有产品按符合欧洲标准走货，微塑料需合规。 4. 所有包装材料都不允许PVC, 请用PET代替 5. 此单需要4套产前样及4套大货样，样板请寄到罗湖办公室Eddie收。 | AB35: Becky Yang | AC35: 1.6548 | AD35: =AC35*M35 -> 3271.5396 | AE35: 94766-4.15 | AJ35: =J35 -> 11862 | AN35: =J35 -> 11862 | AQ35: =J35 -> 11862 | BB35: MA布标 | BC35: =J35/4 -> 2965.5 | BD35: =J35/4 -> 2965.5 | BE35: =J35/4 -> 2965.5 | BG35: =J35/4 -> 2965.5 | BJ35: =SUM(BC35:BI35) -> 11862 | BK35: =J35-BJ35 -> 0
A36: 45574 | B36: ACTION SERVICE & DISTRIBUTIE B.V. | C36: 荷兰 | D36: 4500146851 | E36: 4400907404 | F36: 4500146851-200 | H36: MB83-S002-9259 | I36: 混装（9259+9269各6PCS） | J36: 11862 | K36: 0 | L36: 6 | M36: =J36/L36 -> 1977 | N36: 45776 | O36: 45772 | Q36: PASS | T36: 5/5出 | U36: 10/9收到 | W36: 黑白书纸 for slime bag | AA36: 日期码格式：ZURU INC(BVI) 标准格式 日期：按实际生产日期 Packaging Info: 客版15L包装（收缩膜，收藏指南，15L 黑白书纸 for slime bag）+MA布标 Remark: 客人款号：3009949 1. 此单是子母件，贵司是母件工厂，需要负责组装入箱：一共2款，每款6pcs ，共12pcs 入一外箱。子件9259 工厂是兴信，子件9269 工厂是华康。子件CRD 是贵司CRD -7天，会按时/提前送货到贵司组装。 2. 订单总数量782,892 pcs, 共分为33个柜子，请按期完货. 3. 所有产品按符合欧洲标准走货，微塑料需合规。 4. 所有包装材料都不允许PVC, 请用PET代替 5. 此单需要4套产前样及4套大货样，样板请寄到罗湖办公室Eddie收。 | AB36: Becky Yang | AC36: 1.6548 | AD36: =AC36*M36 -> 3271.5396 | AE36: 94565-3.17 | AJ36: =J36 -> 11862 | AN36: =J36 -> 11862 | AQ36: =J36 -> 11862 | BB36: MA布标 | BC36: =J36/4 -> 2965.5 | BD36: =J36/4 -> 2965.5 | BE36: =J36/4 -> 2965.5 | BG36: =J36/4 -> 2965.5 | BJ36: =SUM(BC36:BI36) -> 11862 | BK36: =J36-BJ36 -> 0
A37: 45574 | B37: ACTION SERVICE & DISTRIBUTIE B.V. | C37: 荷兰 | D37: 4500146851 | E37: 4400908273 | F37: 4500146851-220 | H37: MB83-S002-9259 | I37: 混装（9259+9269各6PCS） | J37: 11862 | K37: 0 | L37: 6 | M37: =J37/L37 -> 1977 | N37: 45782 | O37: 45778 | Q37: PASS | T37: 5/6出 | U37: 10/9收到 | W37: 黑白书纸 for slime bag | AA37: 日期码格式：ZURU INC(BVI) 标准格式 日期：按实际生产日期 Packaging Info: 客版15L包装（收缩膜，收藏指南，15L 黑白书纸 for slime bag）+MA布标 Remark: 客人款号：3009949 1. 此单是子母件，贵司是母件工厂，需要负责组装入箱：一共2款，每款6pcs ，共12pcs 入一外箱。子件9259 工厂是兴信，子件9269 工厂是华康。子件CRD 是贵司CRD -7天，会按时/提前送货到贵司组装。 2. 订单总数量782,892 pcs, 共分为33个柜子，请按期完货. 3. 所有产品按符合欧洲标准走货，微塑料需合规。 4. 所有包装材料都不允许PVC, 请用PET代替 5. 此单需要4套产前样及4套大货样，样板请寄到罗湖办公室Eddie收。 | AB37: Becky Yang | AC37: 1.6548 | AD37: =AC37*M37 -> 3271.5396 | AE37: 94803-4.21 | AJ37: =J37 -> 11862 | AN37: =J37 -> 11862 | AQ37: =J37 -> 11862 | BB37: MA布标 | BC37: =J37/4 -> 2965.5 | BD37: =J37/4 -> 2965.5 | BE37: =J37/4 -> 2965.5 | BG37: =J37/4 -> 2965.5 | BJ37: =SUM(BC37:BI37) -> 11862 | BK37: =J37-BJ37 -> 0
A38: 45574 | B38: ACTION SERVICE & DISTRIBUTIE B.V. | C38: 荷兰 | D38: 4500146851 | E38: 4400341178 | F38: 4500146851-40 | H38: MB83-S002-9259 | I38: 混装（9259+9269各6PCS） | J38: 11862 | K38: 0 | L38: 6 | M38: =J38/L38 -> 1977 | N38: 45810 | O38: =N38-4 -> 45806 | Q38: PASS | T38: 6/12出 | U38: 10/9收到 | W38: 黑白书纸 for slime bag | AA38: 日期码格式：ZURU INC(BVI) 标准格式 日期：按实际生产日期 Packaging Info: 客版15L包装（收缩膜，收藏指南，15L 黑白书纸 for slime bag）+MA布标 Remark: 客人款号：3009949 1. 此单是子母件，贵司是母件工厂，需要负责组装入箱：一共2款，每款6pcs ，共12pcs 入一外箱。子件9259 工厂是兴信，子件9269 工厂是华康。子件CRD 是贵司CRD -7天，会按时/提前送货到贵司组装。 2. 订单总数量782,892 pcs, 共分为33个柜子，请按期完货. 3. 所有产品按符合欧洲标准走货，微塑料需合规。 4. 所有包装材料都不允许PVC, 请用PET代替 5. 此单需要4套产前样及4套大货样，样板请寄到罗湖办公室Eddie收。 | AB38: Becky Yang | AC38: 14.6964 | AD38: =AC38*M38 -> 29054.783 | AE38: 95517-7.1 | AJ38: =J38 -> 11862 | AN38: =J38 -> 11862 | AQ38: =J38 -> 11862 | BB38: MA布标 | BC38: =J38/4 -> 2965.5 | BD38: =J38/4 -> 2965.5 | BE38: =J38/4 -> 2965.5 | BG38: =J38/4 -> 2965.5 | BJ38: =SUM(BC38:BI38) -> 11862 | BK38: =J38-BJ38 -> 0
A39: 45574 | B39: ACTION SERVICE & DISTRIBUTIE B.V. | C39: 荷兰 | D39: 4500146851 | E39: 4400982509 | F39: 4500146851-320 | H39: MB83-S002-9259 | I39: 混装（9259+9269各6PCS） | J39: 11862 | K39: 0 | L39: 6 | M39: =J39/L39 -> 1977 | N39: 45818 | O39: 45814 | Q39: PASS | T39: 6/13出 | U39: 10/9收到 | W39: 黑白书纸 for slime bag | AA39: 日期码格式：ZURU INC(BVI) 标准格式 日期：按实际生产日期 Packaging Info: 客版15L包装（收缩膜，收藏指南，15L 黑白书纸 for slime bag）+MA布标 Remark: 客人款号：3009949 1. 此单是子母件，贵司是母件工厂，需要负责组装入箱：一共2款，每款6pcs ，共12pcs 入一外箱。子件9259 工厂是兴信，子件9269 工厂是华康。子件CRD 是贵司CRD -7天，会按时/提前送货到贵司组装。 2. 订单总数量782,892 pcs, 共分为33个柜子，请按期完货. 3. 所有产品按符合欧洲标准走货，微塑料需合规。 4. 所有包装材料都不允许PVC, 请用PET代替 5. 此单需要4套产前样及4套大货样，样板请寄到罗湖办公室Eddie收。 | AB39: Becky Yang | AC39: 1.6548 | AD39: =AC39*M39 -> 3271.5396 | AE39: 95579-7.7 | AJ39: =J39 -> 11862 | AN39: =J39 -> 11862 | AQ39: =J39 -> 11862 | BB39: MA布标 | BC39: =J39/4 -> 2965.5 | BD39: =J39/4 -> 2965.5 | BE39: =J39/4 -> 2965.5 | BG39: =J39/4 -> 2965.5 | BJ39: =SUM(BC39:BI39) -> 11862 | BK39: =J39-BJ39 -> 0
A40: 45574 | B40: ACTION SERVICE & DISTRIBUTIE B.V. | C40: 荷兰 | D40: 4500146851 | E40: 4400974042 | F40: 4500146851-290 | H40: MB83-S002-9259 | I40: 混装（9259+9269各6PCS） | J40: 11862 | K40: 0 | L40: 6 | M40: =J40/L40 -> 1977 | N40: 45824 | O40: 45820 | Q40: PASS | T40: 6/28出 | U40: 10/9收到 | W40: 黑白书纸 for slime bag | AA40: 日期码格式：ZURU INC(BVI) 标准格式 日期：按实际生产日期 Packaging Info: 客版15L包装（收缩膜，收藏指南，15L 黑白书纸 for slime bag）+MA布标 Remark: 客人款号：3009949 1. 此单是子母件，贵司是母件工厂，需要负责组装入箱：一共2款，每款6pcs ，共12pcs 入一外箱。子件9259 工厂是兴信，子件9269 工厂是华康。子件CRD 是贵司CRD -7天，会按时/提前送货到贵司组装。 2. 订单总数量782,892 pcs, 共分为33个柜子，请按期完货. 3. 所有产品按符合欧洲标准走货，微塑料需合规。 4. 所有包装材料都不允许PVC, 请用PET代替 5. 此单需要4套产前样及4套大货样，样板请寄到罗湖办公室Eddie收。 | AB40: Becky Yang | AC40: 1.6548 | AD40: =AC40*M40 -> 3271.5396 | AE40: 95647-7.15 | AJ40: =J40 -> 11862 | AN40: =J40 -> 11862 | AQ40: =J40 -> 11862 | BB40: MA布标 | BC40: =J40/4 -> 2965.5 | BD40: =J40/4 -> 2965.5 | BE40: =J40/4 -> 2965.5 | BG40: =J40/4 -> 2965.5 | BJ40: =SUM(BC40:BI40) -> 11862 | BK40: =J40-BJ40 -> 0
A41: 45574 | B41: ACTION SERVICE & DISTRIBUTIE B.V. | C41: 荷兰 | D41: 4500146851 | E41: 4400983003 | F41: 4500146851-330 | H41: MB83-S002-9259 | I41: 混装（9259+9269各6PCS） | J41: 11862 | K41: 0 | L41: 6 | M41: =J41/L41 -> 1977 | N41: 45832 | O41: 45828 | Q41: PASS | T41: 7/1出 | U41: 10/9收到 | W41: 黑白书纸 for slime bag | AA41: 日期码格式：ZURU INC(BVI) 标准格式 日期：按实际生产日期 Packaging Info: 客版15L包装（收缩膜，收藏指南，15L 黑白书纸 for slime bag）+MA布标 Remark: 客人款号：3009949 1. 此单是子母件，贵司是母件工厂，需要负责组装入箱：一共2款，每款6pcs ，共12pcs 入一外箱。子件9259 工厂是兴信，子件9269 工厂是华康。子件CRD 是贵司CRD -7天，会按时/提前送货到贵司组装。 2. 订单总数量782,892 pcs, 共分为33个柜子，请按期完货. 3. 所有产品按符合欧洲标准走货，微塑料需合规。 4. 所有包装材料都不允许PVC, 请用PET代替 5. 此单需要4套产前样及4套大货样，样板请寄到罗湖办公室Eddie收。 | AB41: Becky Yang | AC41: 14.6964 | AD41: =AC41*M41 -> 29054.783 | AE41: 95781-7.26 | AJ41: =J41 -> 11862 | AN41: =J41 -> 11862 | AQ41: =J41 -> 11862 | BB41: MA布标 | BC41: =J41/4 -> 2965.5 | BD41: =J41/4 -> 2965.5 | BE41: =J41/4 -> 2965.5 | BG41: =J41/4 -> 2965.5 | BJ41: =SUM(BC41:BI41) -> 11862 | BK41: =J41-BJ41 -> 0
A42: 45574 | B42: ACTION SERVICE & DISTRIBUTIE B.V. | C42: 荷兰 | D42: 4500146851 | E42: 4400898661 | F42: 4500146851-170 | H42: MB83-S002-9259 | I42: 混装（9259+9269各6PCS） | J42: 11862 | K42: 0 | L42: 6 | M42: =J42/L42 -> 1977 | N42: 45839 | O42: =N42-4 -> 45835 | Q42: PASS | T42: 7/7出 | U42: 10/9收到 | W42: 黑白书纸 for slime bag | AA42: 日期码格式：ZURU INC(BVI) 标准格式 日期：按实际生产日期 Packaging Info: 客版15L包装（收缩膜，收藏指南，15L 黑白书纸 for slime bag）+MA布标 Remark: 客人款号：3009949 1. 此单是子母件，贵司是母件工厂，需要负责组装入箱：一共2款，每款6pcs ，共12pcs 入一外箱。子件9259 工厂是兴信，子件9269 工厂是华康。子件CRD 是贵司CRD -7天，会按时/提前送货到贵司组装。 2. 订单总数量782,892 pcs, 共分为33个柜子，请按期完货. 3. 所有产品按符合欧洲标准走货，微塑料需合规。 4. 所有包装材料都不允许PVC, 请用PET代替 5. 此单需要4套产前样及4套大货样，样板请寄到罗湖办公室Eddie收。 | AB42: Becky Yang | AC42: 14.6964 | AD42: =AC42*M42 -> 29054.783 | AE42: 95812-7.29 | AJ42: =J42 -> 11862 | AN42: =J42 -> 11862 | AQ42: =J42 -> 11862 | BB42: MA布标 | BC42: =J42/4 -> 2965.5 | BD42: =J42/4 -> 2965.5 | BE42: =J42/4 -> 2965.5 | BG42: =J42/4 -> 2965.5 | BJ42: =SUM(BC42:BI42) -> 11862 | BK42: =J42-BJ42 -> 0
A43: 45574 | B43: ACTION SERVICE & DISTRIBUTIE B.V. | C43: 荷兰 | D43: 4500146851 | E43: 4400650966 | F43: 4500146851-120 | H43: MB83-S002-9259 | I43: 混装（9259+9269各6PCS） | J43: 11862 | K43: 0 | L43: 6 | M43: =J43/L43 -> 1977 | N43: 45845 | O43: 45841 | Q43: PASS | T43: 7/15出 | U43: 10/9收到 | W43: 黑白书纸 for slime bag | AA43: 日期码格式：ZURU INC(BVI) 标准格式 日期：按实际生产日期 Packaging Info: 客版15L包装（收缩膜，收藏指南，15L 黑白书纸 for slime bag）+MA布标 Remark: 客人款号：3009949 1. 此单是子母件，贵司是母件工厂，需要负责组装入箱：一共2款，每款6pcs ，共12pcs 入一外箱。子件9259 工厂是兴信，子件9269 工厂是华康。子件CRD 是贵司CRD -7天，会按时/提前送货到贵司组装。 2. 订单总数量782,892 pcs, 共分为33个柜子，请按期完货. 3. 所有产品按符合欧洲标准走货，微塑料需合规。 4. 所有包装材料都不允许PVC, 请用PET代替 5. 此单需要4套产前样及4套大货样，样板请寄到罗湖办公室Eddie收。 | AB43: Becky Yang | AC43: 1.6548 | AD43: =AC43*M43 -> 3271.5396 | AE43: 95812-7.29 | AJ43: =J43 -> 11862 | AN43: =J43 -> 11862 | AQ43: =J43 -> 11862 | BB43: MA布标 | BC43: =J43/4 -> 2965.5 | BD43: =J43/4 -> 2965.5 | BE43: =J43/4 -> 2965.5 | BG43: =J43/4 -> 2965.5 | BJ43: =SUM(BC43:BI43) -> 11862 | BK43: =J43-BJ43 -> 0
A44: 45574 | B44: ACTION SERVICE & DISTRIBUTIE B.V. | C44: 荷兰 | D44: 4500146851 | E44: 4400895116 | F44: 4500146851-160 | H44: MB83-S002-9259 | I44: 混装（9259+9269各6PCS） | J44: 11862 | K44: 0 | L44: 6 | M44: =J44/L44 -> 1977 | N44: 45860 | O44: 45856 | Q44: PASS | T44: 7/29出 | U44: 10/9收到 | W44: 黑白书纸 for slime bag | AA44: 日期码格式：ZURU INC(BVI) 标准格式 日期：按实际生产日期 Packaging Info: 客版15L包装（收缩膜，收藏指南，15L 黑白书纸 for slime bag）+MA布标 Remark: 客人款号：3009949 1. 此单是子母件，贵司是母件工厂，需要负责组装入箱：一共2款，每款6pcs ，共12pcs 入一外箱。子件9259 工厂是兴信，子件9269 工厂是华康。子件CRD 是贵司CRD -7天，会按时/提前送货到贵司组装。 2. 订单总数量782,892 pcs, 共分为33个柜子，请按期完货. 3. 所有产品按符合欧洲标准走货，微塑料需合规。 4. 所有包装材料都不允许PVC, 请用PET代替 5. 此单需要4套产前样及4套大货样，样板请寄到罗湖办公室Eddie收。 | AB44: Becky Yang | AC44: 14.6964 | AD44: =AC44*M44 -> 29054.783 | AE44: 95837-7.31 | AJ44: =J44 -> 11862 | AN44: =J44 -> 11862 | AQ44: =J44 -> 11862 | BB44: MA布标 | BC44: =J44/4 -> 2965.5 | BD44: =J44/4 -> 2965.5 | BE44: =J44/4 -> 2965.5 | BG44: =J44/4 -> 2965.5 | BJ44: =SUM(BC44:BI44) -> 11862 | BK44: =J44-BJ44 -> 0
A45: 45574 | B45: ACTION SERVICE & DISTRIBUTIE B.V. | C45: 荷兰 | D45: 4500146851 | E45: 4400654434 | F45: 4500146851-140 | H45: MB83-S002-9259 | I45: 混装（9259+9269各6PCS） | J45: 11862 | K45: 0 | L45: 6 | M45: =J45/L45 -> 1977 | N45: 45863 | O45: 45859 | Q45: PASS | T45: 8/4出 | U45: 10/9收到 | W45: 黑白书纸 for slime bag | AA45: 日期码格式：ZURU INC(BVI) 标准格式 日期：按实际生产日期 Packaging Info: 客版15L包装（收缩膜，收藏指南，15L 黑白书纸 for slime bag）+MA布标 Remark: 客人款号：3009949 1. 此单是子母件，贵司是母件工厂，需要负责组装入箱：一共2款，每款6pcs ，共12pcs 入一外箱。子件9259 工厂是兴信，子件9269 工厂是华康。子件CRD 是贵司CRD -7天，会按时/提前送货到贵司组装。 2. 订单总数量782,892 pcs, 共分为33个柜子，请按期完货. 3. 所有产品按符合欧洲标准走货，微塑料需合规。 4. 所有包装材料都不允许PVC, 请用PET代替 5. 此单需要4套产前样及4套大货样，样板请寄到罗湖办公室Eddie收。 | AB45: Becky Yang | AC45: 14.6964 | AD45: =AC45*M45 -> 29054.783 | AJ45: =J45 -> 11862 | AN45: =J45 -> 11862 | AQ45: =J45 -> 11862 | BB45: MA布标 | BC45: =J45/4 -> 2965.5 | BD45: =J45/4 -> 2965.5 | BE45: =J45/4 -> 2965.5 | BG45: =J45/4 -> 2965.5 | BJ45: =SUM(BC45:BI45) -> 11862 | BK45: =J45-BJ45 -> 0
A46: 45574 | B46: ACTION SERVICE & DISTRIBUTIE B.V. | C46: 荷兰 | D46: 4500146851 | E46: 4400381064 | F46: 4500146851-60 | H46: MB83-S002-9259 | I46: 混装（9259+9269各6PCS） | J46: 11862 | K46: 0 | L46: 6 | M46: =J46/L46 -> 1977 | N46: 45866 | O46: 45862 | Q46: PASS | T46: 7/28出 | U46: 10/9收到 | W46: 黑白书纸 for slime bag | AA46: 日期码格式：ZURU INC(BVI) 标准格式 日期：按实际生产日期 Packaging Info: 客版15L包装（收缩膜，收藏指南，15L 黑白书纸 for slime bag）+MA布标 Remark: 客人款号：3009949 1. 此单是子母件，贵司是母件工厂，需要负责组装入箱：一共2款，每款6pcs ，共12pcs 入一外箱。子件9259 工厂是兴信，子件9269 工厂是华康。子件CRD 是贵司CRD -7天，会按时/提前送货到贵司组装。 2. 订单总数量782,892 pcs, 共分为33个柜子，请按期完货. 3. 所有产品按符合欧洲标准走货，微塑料需合规。 4. 所有包装材料都不允许PVC, 请用PET代替 5. 此单需要4套产前样及4套大货样，样板请寄到罗湖办公室Eddie收。 | AB46: Becky Yang | AC46: 14.6964 | AD46: =AC46*M46 -> 29054.783 | AJ46: =J46 -> 11862 | AN46: =J46 -> 11862 | AQ46: =J46 -> 11862 | BB46: MA布标 | BC46: =J46/4 -> 2965.5 | BD46: =J46/4 -> 2965.5 | BE46: =J46/4 -> 2965.5 | BG46: =J46/4 -> 2965.5 | BJ46: =SUM(BC46:BI46) -> 11862 | BK46: =J46-BJ46 -> 0
A47: 45574 | B47: ACTION SERVICE & DISTRIBUTIE B.V. | C47: 荷兰 | D47: 4500146851 | E47: 4400379722 | F47: 4500146851-50 | H47: MB83-S002-9259 | I47: 混装（9259+9269各6PCS） | J47: 11862 | K47: 0 | L47: 6 | M47: =J47/L47 -> 1977 | N47: 45859 | O47: =N47-4 -> 45855 | Q47: PASS | T47: 7/28出 | U47: 10/9收到 | W47: 黑白书纸 for slime bag | AA47: 日期码格式：ZURU INC(BVI) 标准格式 日期：按实际生产日期 Packaging Info: 客版15L包装（收缩膜，收藏指南，15L 黑白书纸 for slime bag）+MA布标 Remark: 客人款号：3009949 1. 此单是子母件，贵司是母件工厂，需要负责组装入箱：一共2款，每款6pcs ，共12pcs 入一外箱。子件9259 工厂是兴信，子件9269 工厂是华康。子件CRD 是贵司CRD -7天，会按时/提前送货到贵司组装。 2. 订单总数量782,892 pcs, 共分为33个柜子，请按期完货. 3. 所有产品按符合欧洲标准走货，微塑料需合规。 4. 所有包装材料都不允许PVC, 请用PET代替 5. 此单需要4套产前样及4套大货样，样板请寄到罗湖办公室Eddie收。 | AB47: Becky Yang | AC47: 14.6964 | AD47: =AC47*M47 -> 29054.783 | AJ47: =J47 -> 11862 | AN47: =J47 -> 11862 | AQ47: =J47 -> 11862 | BB47: MA布标 | BC47: =J47/4 -> 2965.5 | BD47: =J47/4 -> 2965.5 | BE47: =J47/4 -> 2965.5 | BG47: =J47/4 -> 2965.5 | BJ47: =SUM(BC47:BI47) -> 11862 | BK47: =J47-BJ47 -> 0
A48: 45574 | B48: ACTION SERVICE & DISTRIBUTIE B.V. | C48: 荷兰 | D48: 4500146851 | E48: 4400325918 | F48: 4500146851-20 | H48: MB83-S002-9259 | I48: 混装（9259+9269各6PCS） | J48: 11862 | K48: 0 | L48: 6 | M48: =J48/L48 -> 1977 | N48: 45867 | O48: 45863 | Q48: PASS | T48: 7/30出 | U48: 10/9收到 | W48: 黑白书纸 for slime bag | AA48: 日期码格式：ZURU INC(BVI) 标准格式 日期：按实际生产日期 Packaging Info: 客版15L包装（收缩膜，收藏指南，15L 黑白书纸 for slime bag）+MA布标 Remark: 客人款号：3009949 1. 此单是子母件，贵司是母件工厂，需要负责组装入箱：一共2款，每款6pcs ，共12pcs 入一外箱。子件9259 工厂是兴信，子件9269 工厂是华康。子件CRD 是贵司CRD -7天，会按时/提前送货到贵司组装。 2. 订单总数量782,892 pcs, 共分为33个柜子，请按期完货. 3. 所有产品按符合欧洲标准走货，微塑料需合规。 4. 所有包装材料都不允许PVC, 请用PET代替 5. 此单需要4套产前样及4套大货样，样板请寄到罗湖办公室Eddie收。 | AB48: Becky Yang | AC48: 14.6964 | AD48: =AC48*M48 -> 29054.783 | AJ48: =J48 -> 11862 | AN48: =J48 -> 11862 | AQ48: =J48 -> 11862 | BB48: MA布标 | BC48: =J48/4 -> 2965.5 | BD48: =J48/4 -> 2965.5 | BE48: =J48/4 -> 2965.5 | BG48: =J48/4 -> 2965.5 | BJ48: =SUM(BC48:BI48) -> 11862 | BK48: =J48-BJ48 -> 0
A49: 45574 | B49: ACTION SERVICE & DISTRIBUTIE B.V. | C49: 荷兰 | D49: 4500146851 | E49: 4400982508 | F49: 4500146851-310 | H49: MB83-S002-9259 | I49: 混装（9259+9269各6PCS） | J49: 11862 | K49: 0 | L49: 6 | M49: =J49/L49 -> 1977 | N49: 45873 | O49: 45869 | Q49: PASS | T49: 8/12出 | U49: 10/9收到 | W49: 黑白书纸 for slime bag | AA49: 日期码格式：ZURU INC(BVI) 标准格式 日期：按实际生产日期 Packaging Info: 客版15L包装（收缩膜，收藏指南，15L 黑白书纸 for slime bag）+MA布标 Remark: 客人款号：3009949 1. 此单是子母件，贵司是母件工厂，需要负责组装入箱：一共2款，每款6pcs ，共12pcs 入一外箱。子件9259 工厂是兴信，子件9269 工厂是华康。子件CRD 是贵司CRD -7天，会按时/提前送货到贵司组装。 2. 订单总数量782,892 pcs, 共分为33个柜子，请按期完货. 3. 所有产品按符合欧洲标准走货，微塑料需合规。 4. 所有包装材料都不允许PVC, 请用PET代替 5. 此单需要4套产前样及4套大货样，样板请寄到罗湖办公室Eddie收。 | AB49: Becky Yang | AC49: 1.6548 | AD49: =AC49*M49 -> 3271.5396 | AJ49: =J49 -> 11862 | AN49: =J49 -> 11862 | AQ49: =J49 -> 11862 | BB49: MA布标 | BC49: =J49/4 -> 2965.5 | BD49: =J49/4 -> 2965.5 | BE49: =J49/4 -> 2965.5 | BG49: =J49/4 -> 2965.5 | BJ49: =SUM(BC49:BI49) -> 11862 | BK49: =J49-BJ49 -> 0
A50: 45574 | B50: ACTION SERVICE & DISTRIBUTIE B.V. | C50: 荷兰 | D50: 4500146851 | E50: 4400914154 | F50: 4500146851-230 | H50: MB83-S002-9259 | I50: 混装（9259+9269各6PCS） | J50: 11862 | K50: 0 | L50: 6 | M50: =J50/L50 -> 1977 | N50: 45877 | O50: 45873 | Q50: PASS | T50: 8/11出 | U50: 10/9收到 | W50: 黑白书纸 for slime bag | AA50: 日期码格式：ZURU INC(BVI) 标准格式 日期：按实际生产日期 Packaging Info: 客版15L包装（收缩膜，收藏指南，15L 黑白书纸 for slime bag）+MA布标 Remark: 客人款号：3009949 1. 此单是子母件，贵司是母件工厂，需要负责组装入箱：一共2款，每款6pcs ，共12pcs 入一外箱。子件9259 工厂是兴信，子件9269 工厂是华康。子件CRD 是贵司CRD -7天，会按时/提前送货到贵司组装。 2. 订单总数量782,892 pcs, 共分为33个柜子，请按期完货. 3. 所有产品按符合欧洲标准走货，微塑料需合规。 4. 所有包装材料都不允许PVC, 请用PET代替 5. 此单需要4套产前样及4套大货样，样板请寄到罗湖办公室Eddie收。 | AB50: Becky Yang | AC50: 14.6964 | AD50: =AC50*M50 -> 29054.783 | AJ50: =J50 -> 11862 | AN50: =J50 -> 11862 | AQ50: =J50 -> 11862 | BB50: MA布标 | BC50: =J50/4 -> 2965.5 | BD50: =J50/4 -> 2965.5 | BE50: =J50/4 -> 2965.5 | BG50: =J50/4 -> 2965.5 | BJ50: =SUM(BC50:BI50) -> 11862 | BK50: =J50-BJ50 -> 0
A51: 45574 | B51: ACTION SERVICE & DISTRIBUTIE B.V. | C51: 荷兰 | D51: 4500146851 | E51: 4400654435 | F51: 4500146851-150 | H51: MB83-S002-9259 | I51: 混装（9259+9269各6PCS） | J51: 11862 | K51: 0 | L51: 6 | M51: =J51/L51 -> 1977 | N51: 45880 | O51: 45876 | Q51: PASS | T51: 8/25出 | U51: 10/9收到 | W51: 黑白书纸 for slime bag | AA51: 日期码格式：ZURU INC(BVI) 标准格式 日期：按实际生产日期 Packaging Info: 客版15L包装（收缩膜，收藏指南，15L 黑白书纸 for slime bag）+MA布标 Remark: 客人款号：3009949 1. 此单是子母件，贵司是母件工厂，需要负责组装入箱：一共2款，每款6pcs ，共12pcs 入一外箱。子件9259 工厂是兴信，子件9269 工厂是华康。子件CRD 是贵司CRD -7天，会按时/提前送货到贵司组装。 2. 订单总数量782,892 pcs, 共分为33个柜子，请按期完货. 3. 所有产品按符合欧洲标准走货，微塑料需合规。 4. 所有包装材料都不允许PVC, 请用PET代替 5. 此单需要4套产前样及4套大货样，样板请寄到罗湖办公室Eddie收。 | AB51: Becky Yang | AC51: 14.6964 | AD51: =AC51*M51 -> 29054.783 | AJ51: =J51 -> 11862 | AN51: =J51 -> 11862 | AQ51: =J51 -> 11862 | BB51: MA布标 | BC51: =J51/4 -> 2965.5 | BD51: =J51/4 -> 2965.5 | BE51: =J51/4 -> 2965.5 | BG51: =J51/4 -> 2965.5 | BJ51: =SUM(BC51:BI51) -> 11862 | BK51: =J51-BJ51 -> 0
A52: 45574 | B52: ACTION SERVICE & DISTRIBUTIE B.V. | C52: 荷兰 | D52: 4500146851 | E52: 4400979518 | F52: 4500146851-300 | H52: MB83-S002-9259 | I52: 混装（9259+9269各6PCS） | J52: 11862 | K52: 0 | L52: 6 | M52: =J52/L52 -> 1977 | N52: 45881 | O52: 45877 | Q52: PASS | T52: 8/14出 | U52: 10/9收到 | W52: 黑白书纸 for slime bag | AA52: 日期码格式：ZURU INC(BVI) 标准格式 日期：按实际生产日期 Packaging Info: 客版15L包装（收缩膜，收藏指南，15L 黑白书纸 for slime bag）+MA布标 Remark: 客人款号：3009949 1. 此单是子母件，贵司是母件工厂，需要负责组装入箱：一共2款，每款6pcs ，共12pcs 入一外箱。子件9259 工厂是兴信，子件9269 工厂是华康。子件CRD 是贵司CRD -7天，会按时/提前送货到贵司组装。 2. 订单总数量782,892 pcs, 共分为33个柜子，请按期完货. 3. 所有产品按符合欧洲标准走货，微塑料需合规。 4. 所有包装材料都不允许PVC, 请用PET代替 5. 此单需要4套产前样及4套大货样，样板请寄到罗湖办公室Eddie收。 | AB52: Becky Yang | AC52: 1.6548 | AD52: =AC52*M52 -> 3271.5396 | AJ52: =J52 -> 11862 | AN52: =J52 -> 11862 | AQ52: =J52 -> 11862 | BB52: MA布标 | BC52: =J52/4 -> 2965.5 | BD52: =J52/4 -> 2965.5 | BE52: =J52/4 -> 2965.5 | BG52: =J52/4 -> 2965.5 | BJ52: =SUM(BC52:BI52) -> 11862 | BK52: =J52-BJ52 -> 0
A53: 45574 | B53: ACTION SERVICE & DISTRIBUTIE B.V. | C53: 荷兰 | D53: 4500146851 | E53: 4400907405 | F53: 4500146851-210 | H53: MB83-S002-9259 | I53: 混装（9259+9269各6PCS） | J53: 11862 | K53: 0 | L53: 6 | M53: =J53/L53 -> 1977 | N53: 45881 | O53: 45877 | Q53: PASS | U53: 10/9收到 | W53: 黑白书纸 for slime bag | AA53: 日期码格式：ZURU INC(BVI) 标准格式 日期：按实际生产日期 Packaging Info: 客版15L包装（收缩膜，收藏指南，15L 黑白书纸 for slime bag）+MA布标 Remark: 客人款号：3009949 1. 此单是子母件，贵司是母件工厂，需要负责组装入箱：一共2款，每款6pcs ，共12pcs 入一外箱。子件9259 工厂是兴信，子件9269 工厂是华康。子件CRD 是贵司CRD -7天，会按时/提前送货到贵司组装。 2. 订单总数量782,892 pcs, 共分为33个柜子，请按期完货. 3. 所有产品按符合欧洲标准走货，微塑料需合规。 4. 所有包装材料都不允许PVC, 请用PET代替 5. 此单需要4套产前样及4套大货样，样板请寄到罗湖办公室Eddie收。 | AB53: Becky Yang | AC53: 14.6964 | AD53: =AC53*M53 -> 29054.783 | AJ53: =J53 -> 11862 | AN53: =J53 -> 11862 | AQ53: =J53 -> 11862 | BB53: MA布标 | BC53: =J53/4 -> 2965.5 | BD53: =J53/4 -> 2965.5 | BE53: =J53/4 -> 2965.5 | BG53: =J53/4 -> 2965.5 | BJ53: =SUM(BC53:BI53) -> 11862 | BK53: =J53-BJ53 -> 0
A54: 45574 | B54: ACTION SERVICE & DISTRIBUTIE B.V. | C54: 荷兰 | D54: 4500146851 | E54: 4400324878 | F54: 4500146851-10 | H54: MB83-S002-9259 | I54: 混装（9259+9269各6PCS） | J54: 11862 | K54: 0 | L54: 6 | M54: =J54/L54 -> 1977 | N54: 45887 | O54: 45883 | Q54: PASS | T54: 8/25出 | U54: 10/9收到 | W54: 黑白书纸 for slime bag | AA54: 日期码格式：ZURU INC(BVI) 标准格式 日期：按实际生产日期 Packaging Info: 客版15L包装（收缩膜，收藏指南，15L 黑白书纸 for slime bag）+MA布标 Remark: 客人款号：3009949 1. 此单是子母件，贵司是母件工厂，需要负责组装入箱：一共2款，每款6pcs ，共12pcs 入一外箱。子件9259 工厂是兴信，子件9269 工厂是华康。子件CRD 是贵司CRD -7天，会按时/提前送货到贵司组装。 2. 订单总数量782,892 pcs, 共分为33个柜子，请按期完货. 3. 所有产品按符合欧洲标准走货，微塑料需合规。 4. 所有包装材料都不允许PVC, 请用PET代替 5. 此单需要4套产前样及4套大货样，样板请寄到罗湖办公室Eddie收。 | AB54: Becky Yang | AC54: 14.6964 | AD54: =AC54*M54 -> 29054.783 | AJ54: =J54 -> 11862 | AN54: =J54 -> 11862 | AQ54: =J54 -> 11862 | BB54: MA布标 | BC54: =J54/4 -> 2965.5 | BD54: =J54/4 -> 2965.5 | BE54: =J54/4 -> 2965.5 | BG54: =J54/4 -> 2965.5 | BJ54: =SUM(BC54:BI54) -> 11862 | BK54: =J54-BJ54 -> 0
A55: 45796 | B55: ACTION SERVICE & DISTRIBUTIE B.V. | C55: 荷兰 | D55: 4500166812 | E55: 4401018162 | F55: 4500166812-130 | H55: MB83-S002-9259 | I55: 混装（9259+9269各6PCS） | J55: 11862 | K55: 0 | L55: 6 | M55: =J55/L55 -> 1977 | N55: 45894 | O55: =N55-4 -> 45890 | Q55: PASS | T55: 8/28出 | U55: 5/19收到 | W55: 警语书纸翻PO#4500141955 | Z55: （注意：零售包装上的日期码要在无需拆开包装的前提下可直接看到） | AA55: 日期码格式：ZURU INC(BVI) 标准格式 日期：按实际生产日期 Packaging Info: 客版15L 收缩膜 翻PO#4500146851， 客版15L收藏指南翻PO#4500141955, MA 多语 slime bag+客版15L slime bag 警语书纸翻PO#4500141955, MA最新版布标，MA 最新版多语stiker. Remark: 客人款号：3009949 1. 订单总数量593100pcs, 共分为25个柜子，请按期完货. 2. 所有产品按符合欧洲标准走货，微塑料需合规。 3. 所有包装材料都不允许PVC, 请用PET代替 4. 此单需要4套产前样及4套大货样，样板请寄到罗湖办公室Amber Zhang 收 Baby EAN code: #9259 : 4894680021402 #9269 : 4894680023543 | AB55: Amber zhang | AC55: 14.6964 | AD55: =AC55*M55 -> 29054.783 | AE55: A96613-10.8 | AJ55: =J55 -> 11862 | AN55: =J55 -> 11862 | AQ55: =J55 -> 11862 | BB55: MA布标 | BC55: =J55/4 -> 2965.5 | BD55: =J55/4 -> 2965.5 | BE55: =J55/4 -> 2965.5 | BG55: =J55/4 -> 2965.5 | BJ55: =SUM(BC55:BI55) -> 11862 | BK55: =J55-BJ55 -> 0
A56: 45796 | B56: ACTION SERVICE & DISTRIBUTIE B.V. | C56: 荷兰 | D56: 4500166812 | E56: 4401018172 | F56: 4500166812-230 | H56: MB83-S002-9259 | I56: 混装（9259+9269各6PCS） | J56: 11862 | K56: 0 | L56: 6 | M56: =J56/L56 -> 1977 | N56: 45896 | O56: 45892 | Q56: PASS | T56: 9/1出 | U56: 5/19收到 | W56: 警语书纸翻PO#4500141955 | Z56: （注意：零售包装上的日期码要在无需拆开包装的前提下可直接看到） | AA56: 日期码格式：ZURU INC(BVI) 标准格式 日期：按实际生产日期 Packaging Info: 客版15L 收缩膜 翻PO#4500146851， 客版15L收藏指南翻PO#4500141955, MA 多语 slime bag+客版15L slime bag 警语书纸翻PO#4500141955, MA最新版布标，MA 最新版多语stiker. Remark: 客人款号：3009949 1. 订单总数量593100pcs, 共分为25个柜子，请按期完货. 2. 所有产品按符合欧洲标准走货，微塑料需合规。 3. 所有包装材料都不允许PVC, 请用PET代替 4. 此单需要4套产前样及4套大货样，样板请寄到罗湖办公室Amber Zhang 收 Baby EAN code: #9259 : 4894680021402 #9269 : 4894680023543 | AB56: Amber zhang | AC56: 14.6964 | AD56: =AC56*M56 -> 29054.783 | AE56: A96613-10.8 | AJ56: =J56 -> 11862 | AN56: =J56 -> 11862 | AQ56: =J56 -> 11862 | BB56: MA布标 | BC56: =J56/4 -> 2965.5 | BD56: =J56/4 -> 2965.5 | BE56: =J56/4 -> 2965.5 | BG56: =J56/4 -> 2965.5 | BJ56: =SUM(BC56:BI56) -> 11862 | BK56: =J56-BJ56 -> 0
A57: 45796 | B57: ACTION SERVICE & DISTRIBUTIE B.V. | C57: 荷兰 | D57: 4500166812 | E57: 4401018158 | F57: 4500166812-90 | H57: MB83-S002-9259 | I57: 混装（9259+9269各6PCS） | J57: 11862 | K57: 0 | L57: 6 | M57: =J57/L57 -> 1977 | N57: 45897 | O57: 45894 | Q57: PASS | T57: 9/1出 | U57: 5/19收到 | W57: 警语书纸翻PO#4500141955 | Z57: （注意：零售包装上的日期码要在无需拆开包装的前提下可直接看到） | AA57: 日期码格式：ZURU INC(BVI) 标准格式 日期：按实际生产日期 Packaging Info: 客版15L 收缩膜 翻PO#4500146851， 客版15L收藏指南翻PO#4500141955, MA 多语 slime bag+客版15L slime bag 警语书纸翻PO#4500141955, MA最新版布标，MA 最新版多语stiker. Remark: 客人款号：3009949 1. 订单总数量593100pcs, 共分为25个柜子，请按期完货. 2. 所有产品按符合欧洲标准走货，微塑料需合规。 3. 所有包装材料都不允许PVC, 请用PET代替 4. 此单需要4套产前样及4套大货样，样板请寄到罗湖办公室Amber Zhang 收 Baby EAN code: #9259 : 4894680021402 #9269 : 4894680023543 | AB57: Amber zhang | AC57: 14.6964 | AD57: =AC57*M57 -> 29054.783 | AE57: A96643-10.14 | AJ57: =J57 -> 11862 | AN57: =J57 -> 11862 | AQ57: =J57 -> 11862 | BB57: MA布标 | BC57: =J57/4 -> 2965.5 | BD57: =J57/4 -> 2965.5 | BE57: =J57/4 -> 2965.5 | BG57: =J57/4 -> 2965.5 | BJ57: =SUM(BC57:BI57) -> 11862 | BK57: =J57-BJ57 -> 0
A58: 45796 | B58: ACTION SERVICE & DISTRIBUTIE B.V. | C58: 荷兰 | D58: 4500166812 | E58: 4401018163 | F58: 4500166812-140 | H58: MB83-S002-9259 | I58: 混装（9259+9269各6PCS） | J58: 11862 | K58: 0 | L58: 6 | M58: =J58/L58 -> 1977 | N58: 45903 | O58: =N58-4 -> 45899 | Q58: PASS | T58: 9/8出 | U58: 5/19收到 | W58: 警语书纸翻PO#4500141955 | Z58: （注意：零售包装上的日期码要在无需拆开包装的前提下可直接看到） | AA58: 日期码格式：ZURU INC(BVI) 标准格式 日期：按实际生产日期 Packaging Info: 客版15L 收缩膜 翻PO#4500146851， 客版15L收藏指南翻PO#4500141955, MA 多语 slime bag+客版15L slime bag 警语书纸翻PO#4500141955, MA最新版布标，MA 最新版多语stiker. Remark: 客人款号：3009949 1. 订单总数量593100pcs, 共分为25个柜子，请按期完货. 2. 所有产品按符合欧洲标准走货，微塑料需合规。 3. 所有包装材料都不允许PVC, 请用PET代替 4. 此单需要4套产前样及4套大货样，样板请寄到罗湖办公室Amber Zhang 收 Baby EAN code: #9259 : 4894680021402 #9269 : 4894680023543 | AB58: Amber zhang | AC58: 14.6964 | AD58: =AC58*M58 -> 29054.783 | AE58: A96730-10.27 | AJ58: =J58 -> 11862 | AN58: =J58 -> 11862 | AQ58: =J58 -> 11862 | BB58: MA布标 | BC58: =J58/4 -> 2965.5 | BD58: =J58/4 -> 2965.5 | BE58: =J58/4 -> 2965.5 | BG58: =J58/4 -> 2965.5 | BJ58: =SUM(BC58:BI58) -> 11862 | BK58: =J58-BJ58 -> 0
A59: 45796 | B59: ACTION SERVICE & DISTRIBUTIE B.V. | C59: 荷兰 | D59: 4500166812 | E59: 4401018157 | F59: 4500166812-80 | H59: MB83-S002-9259 | I59: 混装（9259+9269各6PCS） | J59: 11862 | K59: 0 | L59: 6 | M59: =J59/L59 -> 1977 | N59: 45905 | O59: =N59-4 -> 45901 | Q59: PASS | T59: 9/11出 | U59: 5/19收到 | W59: 警语书纸翻PO#4500141955 | Z59: （注意：零售包装上的日期码要在无需拆开包装的前提下可直接看到） | AA59: 日期码格式：ZURU INC(BVI) 标准格式 日期：按实际生产日期 Packaging Info: 客版15L 收缩膜 翻PO#4500146851， 客版15L收藏指南翻PO#4500141955, MA 多语 slime bag+客版15L slime bag 警语书纸翻PO#4500141955, MA最新版布标，MA 最新版多语stiker. Remark: 客人款号：3009949 1. 订单总数量593100pcs, 共分为25个柜子，请按期完货. 2. 所有产品按符合欧洲标准走货，微塑料需合规。 3. 所有包装材料都不允许PVC, 请用PET代替 4. 此单需要4套产前样及4套大货样，样板请寄到罗湖办公室Amber Zhang 收 Baby EAN code: #9259 : 4894680021402 #9269 : 4894680023543 | AB59: Amber zhang | AC59: 14.6964 | AD59: =AC59*M59 -> 29054.783 | AE59: A96759-10.30 | AJ59: =J59 -> 11862 | AN59: =J59 -> 11862 | AQ59: =J59 -> 11862 | BB59: MA布标 | BC59: =J59/4 -> 2965.5 | BD59: =J59/4 -> 2965.5 | BE59: =J59/4 -> 2965.5 | BG59: =J59/4 -> 2965.5 | BJ59: =SUM(BC59:BI59) -> 11862 | BK59: =J59-BJ59 -> 0
A60: 45796 | B60: ACTION SERVICE & DISTRIBUTIE B.V. | C60: 荷兰 | D60: 4500166812 | E60: 4401018160 | F60: 4500166812-110 | H60: MB83-S002-9259 | I60: 混装（9259+9269各6PCS） | J60: 11862 | K60: 0 | L60: 6 | M60: =J60/L60 -> 1977 | N60: 45908 | O60: =N60-4 -> 45904 | Q60: PASS | T60: 9/11出 | U60: 5/19收到 | W60: 警语书纸翻PO#4500141955 | Z60: （注意：零售包装上的日期码要在无需拆开包装的前提下可直接看到） | AA60: 日期码格式：ZURU INC(BVI) 标准格式 日期：按实际生产日期 Packaging Info: 客版15L 收缩膜 翻PO#4500146851， 客版15L收藏指南翻PO#4500141955, MA 多语 slime bag+客版15L slime bag 警语书纸翻PO#4500141955, MA最新版布标，MA 最新版多语stiker. Remark: 客人款号：3009949 1. 订单总数量593100pcs, 共分为25个柜子，请按期完货. 2. 所有产品按符合欧洲标准走货，微塑料需合规。 3. 所有包装材料都不允许PVC, 请用PET代替 4. 此单需要4套产前样及4套大货样，样板请寄到罗湖办公室Amber Zhang 收 Baby EAN code: #9259 : 4894680021402 #9269 : 4894680023543 | AB60: Amber zhang | AC60: 14.6964 | AD60: =AC60*M60 -> 29054.783 | AE60: 95279-9.1 | AJ60: =J60 -> 11862 | AN60: =J60 -> 11862 | AQ60: =J60 -> 11862 | BB60: MA布标 | BC60: =J60/4 -> 2965.5 | BD60: =J60/4 -> 2965.5 | BE60: =J60/4 -> 2965.5 | BG60: =J60/4 -> 2965.5 | BJ60: =SUM(BC60:BI60) -> 11862 | BK60: =J60-BJ60 -> 0
A61: 45796 | B61: ACTION SERVICE & DISTRIBUTIE B.V. | C61: 荷兰 | D61: 4500166812 | E61: 4401018165 | F61: 4500166812-160 | H61: MB83-S002-9259 | I61: 混装（9259+9269各6PCS） | J61: 11862 | K61: 0 | L61: 6 | M61: =J61/L61 -> 1977 | N61: 45910 | O61: 45906 | Q61: PASS | R61: =2928+350 -> 3278 | S61: =J61-R61 -> 8584 | T61: 9/19出 | U61: 5/19收到 | W61: 警语书纸翻PO#4500141955 | Z61: （注意：零售包装上的日期码要在无需拆开包装的前提下可直接看到） | AA61: 日期码格式：ZURU INC(BVI) 标准格式 日期：按实际生产日期 Packaging Info: 客版15L 收缩膜 翻PO#4500146851， 客版15L收藏指南翻PO#4500141955, MA 多语 slime bag+客版15L slime bag 警语书纸翻PO#4500141955, MA最新版布标，MA 最新版多语stiker. Remark: 客人款号：3009949 1. 订单总数量593100pcs, 共分为25个柜子，请按期完货. 2. 所有产品按符合欧洲标准走货，微塑料需合规。 3. 所有包装材料都不允许PVC, 请用PET代替 4. 此单需要4套产前样及4套大货样，样板请寄到罗湖办公室Amber Zhang 收 Baby EAN code: #9259 : 4894680021402 #9269 : 4894680023543 | AB61: Amber zhang | AC61: 14.6964 | AD61: =AC61*M61 -> 29054.783 | AE61: 95279-9.1 | AJ61: =J61 -> 11862 | AN61: =J61 -> 11862 | AQ61: =J61 -> 11862 | BB61: MA布标 | BC61: =J61/4 -> 2965.5 | BD61: =J61/4 -> 2965.5 | BE61: =J61/4 -> 2965.5 | BG61: =J61/4 -> 2965.5 | BJ61: =SUM(BC61:BI61) -> 11862 | BK61: =J61-BJ61 -> 0
A62: 45796 | B62: ACTION SERVICE & DISTRIBUTIE B.V. | C62: 荷兰 | D62: 4500166812 | E62: 4401018174 | F62: 4500166812-250 | H62: MB83-S002-9259 | I62: 混装（9259+9269各6PCS） | J62: 11862 | K62: 0 | L62: 6 | M62: =J62/L62 -> 1977 | N62: 45917 | O62: 45913 | Q62: PASS | R62: =840+960+2966+2966+2126+2006 -> 11864 | S62: =J62-R62 -> -2 | T62: 9/24出 | U62: 5/19收到 | W62: 警语书纸翻PO#4500141955 | Z62: （注意：零售包装上的日期码要在无需拆开包装的前提下可直接看到） | AA62: 日期码格式：ZURU INC(BVI) 标准格式 日期：按实际生产日期 Packaging Info: 客版15L 收缩膜 翻PO#4500146851， 客版15L收藏指南翻PO#4500141955, MA 多语 slime bag+客版15L slime bag 警语书纸翻PO#4500141955, MA最新版布标，MA 最新版多语stiker. Remark: 客人款号：3009949 1. 订单总数量593100pcs, 共分为25个柜子，请按期完货. 2. 所有产品按符合欧洲标准走货，微塑料需合规。 3. 所有包装材料都不允许PVC, 请用PET代替 4. 此单需要4套产前样及4套大货样，样板请寄到罗湖办公室Amber Zhang 收 Baby EAN code: #9259 : 4894680021402 #9269 : 4894680023543 | AB62: Amber zhang | AC62: 14.6964 | AD62: =AC62*M62 -> 29054.783 | AE62: 96871-11.5 | AJ62: =J62 -> 11862 | AN62: =J62 -> 11862 | AQ62: =J62 -> 11862 | BB62: MA布标 | BC62: =J62/4 -> 2965.5 | BD62: =J62/4 -> 2965.5 | BE62: =J62/4 -> 2965.5 | BG62: =J62/4 -> 2965.5 | BJ62: =SUM(BC62:BI62) -> 11862 | BK62: =J62-BJ62 -> 0
A63: 45796 | B63: ACTION SERVICE & DISTRIBUTIE B.V. | C63: 荷兰 | D63: 4500166812 | E63: 4401018164 | F63: 4500166812-150 | H63: MB83-S002-9259 | I63: 混装（9259+9269各6PCS） | J63: 11862 | K63: 0 | L63: 6 | M63: =J63/L63 -> 1977 | N63: 45919 | O63: =N63-4 -> 45915 | Q63: PASS | R63: =1520+1740+8602 -> 11862 | S63: =J63-R63 -> 0 | T63: 9/24出 | U63: 5/19收到 | W63: 警语书纸翻PO#4500141955 | Z63: （注意：零售包装上的日期码要在无需拆开包装的前提下可直接看到） | AA63: 日期码格式：ZURU INC(BVI) 标准格式 日期：按实际生产日期 Packaging Info: 客版15L 收缩膜 翻PO#4500146851， 客版15L收藏指南翻PO#4500141955, MA 多语 slime bag+客版15L slime bag 警语书纸翻PO#4500141955, MA最新版布标，MA 最新版多语stiker. Remark: 客人款号：3009949 1. 订单总数量593100pcs, 共分为25个柜子，请按期完货. 2. 所有产品按符合欧洲标准走货，微塑料需合规。 3. 所有包装材料都不允许PVC, 请用PET代替 4. 此单需要4套产前样及4套大货样，样板请寄到罗湖办公室Amber Zhang 收 Baby EAN code: #9259 : 4894680021402 #9269 : 4894680023543 | AB63: Amber zhang | AC63: 14.6964 | AD63: =AC63*M63 -> 29054.783 | AJ63: =J63 -> 11862 | AN63: =J63 -> 11862 | AQ63: =J63 -> 11862 | BB63: MA布标 | BC63: =J63/4 -> 2965.5 | BD63: =J63/4 -> 2965.5 | BE63: =J63/4 -> 2965.5 | BG63: =J63/4 -> 2965.5 | BJ63: =SUM(BC63:BI63) -> 11862 | BK63: =J63-BJ63 -> 0
A64: 45796 | B64: ACTION SERVICE & DISTRIBUTIE B.V. | C64: 荷兰 | D64: 4500166812 | E64: 4401018159 | F64: 4500166812-100 | H64: MB83-S002-9259 | I64: 混装（9259+9269各6PCS） | J64: 11862 | K64: 0 | L64: 6 | M64: =J64/L64 -> 1977 | N64: 45922 | O64: =N64-4 -> 45918 | Q64: PASS | R64: 11862 | S64: =J64-R64 -> 0 | T64: 9/25出 | U64: 5/19收到 | W64: 警语书纸翻PO#4500141955 | Z64: （注意：零售包装上的日期码要在无需拆开包装的前提下可直接看到） | AA64: 日期码格式：ZURU INC(BVI) 标准格式 日期：按实际生产日期 Packaging Info: 客版15L 收缩膜 翻PO#4500146851， 客版15L收藏指南翻PO#4500141955, MA 多语 slime bag+客版15L slime bag 警语书纸翻PO#4500141955, MA最新版布标，MA 最新版多语stiker. Remark: 客人款号：3009949 1. 订单总数量593100pcs, 共分为25个柜子，请按期完货. 2. 所有产品按符合欧洲标准走货，微塑料需合规。 3. 所有包装材料都不允许PVC, 请用PET代替 4. 此单需要4套产前样及4套大货样，样板请寄到罗湖办公室Amber Zhang 收 Baby EAN code: #9259 : 4894680021402 #9269 : 4894680023543 | AB64: Amber zhang | AC64: 14.6964 | AD64: =AC64*M64 -> 29054.783 | AJ64: =J64 -> 11862 | AN64: =J64 -> 11862 | AQ64: =J64 -> 11862 | BB64: MA布标 | BC64: =J64/4 -> 2965.5 | BD64: =J64/4 -> 2965.5 | BE64: =J64/4 -> 2965.5 | BG64: =J64/4 -> 2965.5 | BJ64: =SUM(BC64:BI64) -> 11862 | BK64: =J64-BJ64 -> 0
A65: 45796 | B65: ACTION SERVICE & DISTRIBUTIE B.V. | C65: 荷兰 | D65: 4500166812 | E65: 4401018161 | F65: 4500166812-120 | H65: MB83-S002-9259 | I65: 混装（9259+9269各6PCS） | J65: 11862 | K65: 0 | L65: 6 | M65: =J65/L65 -> 1977 | N65: 45924 | O65: =N65-4 -> 45920 | Q65: PASS | R65: 11862 | S65: =J65-R65 -> 0 | T65: 9/29出 | U65: 5/19收到 | W65: 警语书纸翻PO#4500141955 | Z65: （注意：零售包装上的日期码要在无需拆开包装的前提下可直接看到） | AA65: 日期码格式：ZURU INC(BVI) 标准格式 日期：按实际生产日期 Packaging Info: 客版15L 收缩膜 翻PO#4500146851， 客版15L收藏指南翻PO#4500141955, MA 多语 slime bag+客版15L slime bag 警语书纸翻PO#4500141955, MA最新版布标，MA 最新版多语stiker. Remark: 客人款号：3009949 1. 订单总数量593100pcs, 共分为25个柜子，请按期完货. 2. 所有产品按符合欧洲标准走货，微塑料需合规。 3. 所有包装材料都不允许PVC, 请用PET代替 4. 此单需要4套产前样及4套大货样，样板请寄到罗湖办公室Amber Zhang 收 Baby EAN code: #9259 : 4894680021402 #9269 : 4894680023543 | AB65: Amber zhang | AC65: 14.6964 | AD65: =AC65*M65 -> 29054.783 | AJ65: =J65 -> 11862 | AN65: =J65 -> 11862 | AQ65: =J65 -> 11862 | BB65: MA布标 | BC65: =J65/4 -> 2965.5 | BD65: =J65/4 -> 2965.5 | BE65: =J65/4 -> 2965.5 | BG65: =J65/4 -> 2965.5 | BJ65: =SUM(BC65:BI65) -> 11862 | BK65: =J65-BJ65 -> 0
A66: 45796 | B66: ACTION SERVICE & DISTRIBUTIE B.V. | C66: 荷兰 | D66: 4500166812 | E66: 4401018153 | F66: 4500166812-40 | H66: MB83-S002-9259 | I66: 混装（9259+9269各6PCS） | J66: 11862 | K66: 0 | L66: 6 | M66: =J66/L66 -> 1977 | N66: 45929 | O66: =N66-4 -> 45925 | Q66: PASS | R66: =2816+1792+7254 -> 11862 | S66: =J66-R66 -> 0 | T66: 10/3出 | U66: 5/19收到 | W66: 警语书纸翻PO#4500141955 | Z66: （注意：零售包装上的日期码要在无需拆开包装的前提下可直接看到） | AA66: 日期码格式：ZURU INC(BVI) 标准格式 日期：按实际生产日期 Packaging Info: 客版15L 收缩膜 翻PO#4500146851， 客版15L收藏指南翻PO#4500141955, MA 多语 slime bag+客版15L slime bag 警语书纸翻PO#4500141955, MA最新版布标，MA 最新版多语stiker. Remark: 客人款号：3009949 1. 订单总数量593100pcs, 共分为25个柜子，请按期完货. 2. 所有产品按符合欧洲标准走货，微塑料需合规。 3. 所有包装材料都不允许PVC, 请用PET代替 4. 此单需要4套产前样及4套大货样，样板请寄到罗湖办公室Amber Zhang 收 Baby EAN code: #9259 : 4894680021402 #9269 : 4894680023543 | AB66: Amber zhang | AC66: 14.6964 | AD66: =AC66*M66 -> 29054.783 | AJ66: =J66 -> 11862 | AN66: =J66 -> 11862 | AQ66: =J66 -> 11862 | BB66: MA布标 | BC66: =J66/4 -> 2965.5 | BD66: =J66/4 -> 2965.5 | BE66: =J66/4 -> 2965.5 | BG66: =J66/4 -> 2965.5 | BJ66: =SUM(BC66:BI66) -> 11862 | BK66: =J66-BJ66 -> 0
A67: 45796 | B67: ACTION SERVICE & DISTRIBUTIE B.V. | C67: 荷兰 | D67: 4500166812 | E67: 4401018156 | F67: 4500166812-70 | H67: MB83-S002-9259 | I67: 混装（9259+9269各6PCS） | J67: 11862 | K67: 0 | L67: 6 | M67: =J67/L67 -> 1977 | N67: 45931 | O67: =N67-4 -> 45927 | Q67: PASS | R67: 11862 | S67: =J67-R67 -> 0 | T67: 10/7出 | U67: 5/19收到 | W67: 警语书纸翻PO#4500141955 | Z67: （注意：零售包装上的日期码要在无需拆开包装的前提下可直接看到） | AA67: 日期码格式：ZURU INC(BVI) 标准格式 日期：按实际生产日期 Packaging Info: 客版15L 收缩膜 翻PO#4500146851， 客版15L收藏指南翻PO#4500141955, MA 多语 slime bag+客版15L slime bag 警语书纸翻PO#4500141955, MA最新版布标，MA 最新版多语stiker. Remark: 客人款号：3009949 1. 订单总数量593100pcs, 共分为25个柜子，请按期完货. 2. 所有产品按符合欧洲标准走货，微塑料需合规。 3. 所有包装材料都不允许PVC, 请用PET代替 4. 此单需要4套产前样及4套大货样，样板请寄到罗湖办公室Amber Zhang 收 Baby EAN code: #9259 : 4894680021402 #9269 : 4894680023543 | AB67: Amber zhang | AC67: 14.6964 | AD67: =AC67*M67 -> 29054.783 | AJ67: =J67 -> 11862 | AN67: =J67 -> 11862 | AQ67: =J67 -> 11862 | BB67: MA布标 | BC67: =J67/4 -> 2965.5 | BD67: =J67/4 -> 2965.5 | BE67: =J67/4 -> 2965.5 | BG67: =J67/4 -> 2965.5 | BJ67: =SUM(BC67:BI67) -> 11862 | BK67: =J67-BJ67 -> 0
A68: 45796 | B68: ACTION SERVICE & DISTRIBUTIE B.V. | C68: 荷兰 | D68: 4500166812 | E68: 4401018155 | F68: 4500166812-60 | H68: MB83-S002-9259 | I68: 混装（9259+9269各6PCS） | J68: 11862 | K68: 0 | L68: 6 | M68: =J68/L68 -> 1977 | N68: 45932 | O68: =N68-3 -> 45929 | Q68: PASS | R68: 11862 | S68: =J68-R68 -> 0 | T68: 10/9出 | U68: 5/19收到 | W68: 警语书纸翻PO#4500141955 | Z68: （注意：零售包装上的日期码要在无需拆开包装的前提下可直接看到） | AA68: 日期码格式：ZURU INC(BVI) 标准格式 日期：按实际生产日期 Packaging Info: 客版15L 收缩膜 翻PO#4500146851， 客版15L收藏指南翻PO#4500141955, MA 多语 slime bag+客版15L slime bag 警语书纸翻PO#4500141955, MA最新版布标，MA 最新版多语stiker. Remark: 客人款号：3009949 1. 订单总数量593100pcs, 共分为25个柜子，请按期完货. 2. 所有产品按符合欧洲标准走货，微塑料需合规。 3. 所有包装材料都不允许PVC, 请用PET代替 4. 此单需要4套产前样及4套大货样，样板请寄到罗湖办公室Amber Zhang 收 Baby EAN code: #9259 : 4894680021402 #9269 : 4894680023543 | AB68: Amber zhang | AC68: 14.6964 | AD68: =AC68*M68 -> 29054.783 | AJ68: =J68 -> 11862 | AN68: =J68 -> 11862 | AQ68: =J68 -> 11862 | BB68: MA布标 | BC68: =J68/4 -> 2965.5 | BD68: =J68/4 -> 2965.5 | BE68: =J68/4 -> 2965.5 | BG68: =J68/4 -> 2965.5 | BJ68: =SUM(BC68:BI68) -> 11862 | BK68: =J68-BJ68 -> 0
A69: 45796 | B69: ACTION SERVICE & DISTRIBUTIE B.V. | C69: 荷兰 | D69: 4500166812 | E69: 4401018170 | F69: 4500166812-210 | H69: MB83-S002-9259 | I69: 混装（9259+9269各6PCS） | J69: 11862 | K69: 0 | L69: 6 | M69: =J69/L69 -> 1977 | N69: 45943 | O69: 45939 | Q69: PASS | R69: =2910+2964+2246+2964+708 -> 11792 | S69: =J69-R69 -> 70 | U69: 5/19收到 | W69: 警语书纸翻PO#4500141955 | Z69: （注意：零售包装上的日期码要在无需拆开包装的前提下可直接看到） | AA69: 日期码格式：ZURU INC(BVI) 标准格式 日期：按实际生产日期 Packaging Info: 客版15L 收缩膜 翻PO#4500146851， 客版15L收藏指南翻PO#4500141955, MA 多语 slime bag+客版15L slime bag 警语书纸翻PO#4500141955, MA最新版布标，MA 最新版多语stiker. Remark: 客人款号：3009949 1. 订单总数量593100pcs, 共分为25个柜子，请按期完货. 2. 所有产品按符合欧洲标准走货，微塑料需合规。 3. 所有包装材料都不允许PVC, 请用PET代替 4. 此单需要4套产前样及4套大货样，样板请寄到罗湖办公室Amber Zhang 收 Baby EAN code: #9259 : 4894680021402 #9269 : 4894680023543 | AB69: Amber zhang | AC69: 14.6964 | AD69: =AC69*M69 -> 29054.783 | AJ69: =J69 -> 11862 | AN69: =J69 -> 11862 | AQ69: =J69 -> 11862 | BB69: MA布标 | BC69: =J69/4 -> 2965.5 | BD69: =J69/4 -> 2965.5 | BE69: =J69/4 -> 2965.5 | BG69: =J69/4 -> 2965.5 | BJ69: =SUM(BC69:BI69) -> 11862 | BK69: =J69-BJ69 -> 0
A70: 45796 | B70: ACTION SERVICE & DISTRIBUTIE B.V. | C70: 荷兰 | D70: 4500166812 | E70: 4401018169 | F70: 4500166812-200 | H70: MB83-S002-9259 | I70: 混装（9259+9269各6PCS） | J70: 11862 | K70: 0 | L70: 6 | M70: =J70/L70 -> 1977 | N70: 45952 | O70: 45948 | Q70: PASS | R70: =2760+960 -> 3720 | S70: =J70-R70 -> 8142 | T70: 10/27出 | U70: 5/19收到 | W70: 警语书纸翻PO#4500141955 | Z70: （注意：零售包装上的日期码要在无需拆开包装的前提下可直接看到） | AA70: 日期码格式：ZURU INC(BVI) 标准格式 日期：按实际生产日期 Packaging Info: 客版15L 收缩膜 翻PO#4500146851， 客版15L收藏指南翻PO#4500141955, MA 多语 slime bag+客版15L slime bag 警语书纸翻PO#4500141955, MA最新版布标，MA 最新版多语stiker. Remark: 客人款号：3009949 1. 订单总数量593100pcs, 共分为25个柜子，请按期完货. 2. 所有产品按符合欧洲标准走货，微塑料需合规。 3. 所有包装材料都不允许PVC, 请用PET代替 4. 此单需要4套产前样及4套大货样，样板请寄到罗湖办公室Amber Zhang 收 Baby EAN code: #9259 : 4894680021402 #9269 : 4894680023543 | AB70: Amber zhang | AC70: 14.6964 | AD70: =AC70*M70 -> 29054.783 | AJ70: =J70 -> 11862 | AN70: =J70 -> 11862 | AQ70: =J70 -> 11862 | BB70: MA布标 | BC70: =J70/4 -> 2965.5 | BD70: =J70/4 -> 2965.5 | BE70: =J70/4 -> 2965.5 | BG70: =J70/4 -> 2965.5 | BJ70: =SUM(BC70:BI70) -> 11862 | BK70: =J70-BJ70 -> 0
A71: 45796 | B71: ACTION SERVICE & DISTRIBUTIE B.V. | C71: 荷兰 | D71: 4500166812 | E71: 4401018152 | F71: 4500166812-30 | H71: MB83-S002-9259 | I71: 混装（9259+9269各6PCS） | J71: 11862 | K71: 0 | L71: 6 | M71: =J71/L71 -> 1977 | N71: 45957 | O71: =N71-4 -> 45953 | Q71: PASS | S71: =J71-R71 -> 11862 | T71: 11/3出 | U71: 5/19收到 | W71: 警语书纸翻PO#4500141955 | Z71: （注意：零售包装上的日期码要在无需拆开包装的前提下可直接看到） | AA71: 日期码格式：ZURU INC(BVI) 标准格式 日期：按实际生产日期 Packaging Info: 客版15L 收缩膜 翻PO#4500146851， 客版15L收藏指南翻PO#4500141955, MA 多语 slime bag+客版15L slime bag 警语书纸翻PO#4500141955, MA最新版布标，MA 最新版多语stiker. Remark: 客人款号：3009949 1. 订单总数量593100pcs, 共分为25个柜子，请按期完货. 2. 所有产品按符合欧洲标准走货，微塑料需合规。 3. 所有包装材料都不允许PVC, 请用PET代替 4. 此单需要4套产前样及4套大货样，样板请寄到罗湖办公室Amber Zhang 收 Baby EAN code: #9259 : 4894680021402 #9269 : 4894680023543 | AB71: Amber zhang | AC71: 14.6964 | AD71: =AC71*M71 -> 29054.783 | AJ71: =J71 -> 11862 | AN71: =J71 -> 11862 | AQ71: =J71 -> 11862 | BB71: MA布标 | BC71: =J71/4 -> 2965.5 | BD71: =J71/4 -> 2965.5 | BE71: =J71/4 -> 2965.5 | BG71: =J71/4 -> 2965.5 | BJ71: =SUM(BC71:BI71) -> 11862 | BK71: =J71-BJ71 -> 0
A72: 45796 | B72: ACTION SERVICE & DISTRIBUTIE B.V. | C72: 荷兰 | D72: 4500166812 | E72: 4401018150 | F72: 4500166812-10 | H72: MB83-S002-9259 | I72: 混装（9259+9269各6PCS） | J72: 11862 | K72: 0 | L72: 6 | M72: =J72/L72 -> 1977 | N72: 45960 | O72: 45957 | Q72: PASS | S72: =J72-R72 -> 11862 | T72: 11/6出 | U72: 5/19收到 | W72: 警语书纸翻PO#4500141955 | Z72: （注意：零售包装上的日期码要在无需拆开包装的前提下可直接看到） | AA72: 日期码格式：ZURU INC(BVI) 标准格式 日期：按实际生产日期 Packaging Info: 客版15L 收缩膜 翻PO#4500146851， 客版15L收藏指南翻PO#4500141955, MA 多语 slime bag+客版15L slime bag 警语书纸翻PO#4500141955, MA最新版布标，MA 最新版多语stiker. Remark: 客人款号：3009949 1. 订单总数量593100pcs, 共分为25个柜子，请按期完货. 2. 所有产品按符合欧洲标准走货，微塑料需合规。 3. 所有包装材料都不允许PVC, 请用PET代替 4. 此单需要4套产前样及4套大货样，样板请寄到罗湖办公室Amber Zhang 收 Baby EAN code: #9259 : 4894680021402 #9269 : 4894680023543 | AB72: Amber zhang | AC72: 14.6964 | AD72: =AC72*M72 -> 29054.783 | AJ72: =J72 -> 11862 | AN72: =J72 -> 11862 | AQ72: =J72 -> 11862 | BB72: MA布标 | BC72: =J72/4 -> 2965.5 | BD72: =J72/4 -> 2965.5 | BE72: =J72/4 -> 2965.5 | BG72: =J72/4 -> 2965.5 | BJ72: =SUM(BC72:BI72) -> 11862 | BK72: =J72-BJ72 -> 0
A73: 45796 | B73: ACTION SERVICE & DISTRIBUTIE B.V. | C73: 荷兰 | D73: 4500166812 | E73: 4401018151 | F73: 4500166812-20 | H73: MB83-S002-9259 | I73: 混装（9259+9269各6PCS） | J73: 11862 | K73: 0 | L73: 6 | M73: =J73/L73 -> 1977 | N73: 46142 | O73: =N73-3 -> 46139 | P73: 11862 | Q73: PASS | S73: =J73-R73 -> 11862 | T73: 5/18出 | U73: 5/19收到 | W73: 警语书纸翻PO#4500141955 | Z73: （注意：零售包装上的日期码要在无需拆开包装的前提下可直接看到） | AA73: 日期码格式：ZURU INC(BVI) 标准格式 日期：按实际生产日期 Packaging Info: 客版15L 收缩膜 翻PO#4500146851， 客版15L收藏指南翻PO#4500141955, MA 多语 slime bag+客版15L slime bag 警语书纸翻PO#4500141955, MA最新版布标，MA 最新版多语stiker. Remark: 客人款号：3009949 1. 订单总数量593100pcs, 共分为25个柜子，请按期完货. 2. 所有产品按符合欧洲标准走货，微塑料需合规。 3. 所有包装材料都不允许PVC, 请用PET代替 4. 此单需要4套产前样及4套大货样，样板请寄到罗湖办公室Amber Zhang 收 Baby EAN code: #9259 : 4894680021402 #9269 : 4894680023543 | AB73: Amber zhang | AC73: 14.6964 | AD73: =AC73*M73 -> 29054.783 | AJ73: =J73 -> 11862 | AN73: =J73 -> 11862 | AQ73: =J73 -> 11862 | BB73: MA布标 | BC73: =J73/4 -> 2965.5 | BD73: =J73/4 -> 2965.5 | BE73: =J73/4 -> 2965.5 | BG73: =J73/4 -> 2965.5 | BJ73: =SUM(BC73:BI73) -> 11862 | BK73: =J73-BJ73 -> 0
A74: 45796 | B74: ACTION SERVICE & DISTRIBUTIE B.V. | C74: 荷兰 | D74: 4500166812 | E74: 4401018167 | F74: 4500166812-180 | H74: MB83-S002-9259 | I74: 混装（9259+9269各6PCS） | J74: 11862 | K74: 0 | L74: 6 | M74: =J74/L74 -> 1977 | N74: 46149 | O74: =N74-3 -> 46146 | P74: 11903 | Q74: PASS | S74: =J74-R74 -> 11862 | T74: 5/14出 | U74: 5/19收到 | W74: 警语书纸翻PO#4500141955 | Z74: （注意：零售包装上的日期码要在无需拆开包装的前提下可直接看到）5/18 | AA74: 日期码格式：ZURU INC(BVI) 标准格式 日期：按实际生产日期 Packaging Info: 客版15L 收缩膜 翻PO#4500146851， 客版15L收藏指南翻PO#4500141955, MA 多语 slime bag+客版15L slime bag 警语书纸翻PO#4500141955, MA最新版布标，MA 最新版多语stiker. Remark: 客人款号：3009949 1. 订单总数量593100pcs, 共分为25个柜子，请按期完货. 2. 所有产品按符合欧洲标准走货，微塑料需合规。 3. 所有包装材料都不允许PVC, 请用PET代替 4. 此单需要4套产前样及4套大货样，样板请寄到罗湖办公室Amber Zhang 收 Baby EAN code: #9259 : 4894680021402 #9269 : 4894680023543 | AB74: Amber zhang | AC74: 14.6964 | AD74: =AC74*M74 -> 29054.783 | AJ74: =J74 -> 11862 | AN74: =J74 -> 11862 | AQ74: =J74 -> 11862 | BB74: MA布标 | BC74: =J74/4 -> 2965.5 | BD74: =J74/4 -> 2965.5 | BE74: =J74/4 -> 2965.5 | BG74: =J74/4 -> 2965.5 | BJ74: =SUM(BC74:BI74) -> 11862 | BK74: =J74-BJ74 -> 0
A75: 45796 | B75: ACTION SERVICE & DISTRIBUTIE B.V. | C75: 荷兰 | D75: 4500166812 | E75: 4401018154 | F75: 4500166812-50 | H75: MB83-S002-9259 | I75: 混装（9259+9269各6PCS） | J75: 11862 | K75: 0 | L75: 6 | M75: =J75/L75 -> 1977 | N75: 46152 | O75: =N75-3 -> 46149 | P75: 11862 | Q75: PASS | S75: =J75-R75 -> 11862 | U75: 5/19收到 | W75: 警语书纸翻PO#4500141955 | Z75: （注意：零售包装上的日期码要在无需拆开包装的前提下可直接看到） | AA75: 日期码格式：ZURU INC(BVI) 标准格式 日期：按实际生产日期 Packaging Info: 客版15L 收缩膜 翻PO#4500146851， 客版15L收藏指南翻PO#4500141955, MA 多语 slime bag+客版15L slime bag 警语书纸翻PO#4500141955, MA最新版布标，MA 最新版多语stiker. Remark: 客人款号：3009949 1. 订单总数量593100pcs, 共分为25个柜子，请按期完货. 2. 所有产品按符合欧洲标准走货，微塑料需合规。 3. 所有包装材料都不允许PVC, 请用PET代替 4. 此单需要4套产前样及4套大货样，样板请寄到罗湖办公室Amber Zhang 收 Baby EAN code: #9259 : 4894680021402 #9269 : 4894680023543 | AB75: Amber zhang | AC75: 14.6964 | AD75: =AC75*M75 -> 29054.783 | AJ75: =J75 -> 11862 | AN75: =J75 -> 11862 | AQ75: =J75 -> 11862 | BB75: MA布标 | BC75: =J75/4 -> 2965.5 | BD75: =J75/4 -> 2965.5 | BE75: =J75/4 -> 2965.5 | BG75: =J75/4 -> 2965.5 | BJ75: =SUM(BC75:BI75) -> 11862 | BK75: =J75-BJ75 -> 0
A76: 45796 | B76: ACTION SERVICE & DISTRIBUTIE B.V. | C76: 荷兰 | D76: 4500166812 | E76: 4401018171 | F76: 4500166812-220 | H76: MB83-S002-9259 | I76: 混装（9259+9269各6PCS） | J76: 11862 | K76: 0 | L76: 6 | M76: =J76/L76 -> 1977 | N76: 46175 | O76: =N76-3 -> 46172 | Q76: PASS | S76: =J76-R76 -> 11862 | T76: 6/5出 | U76: 5/19收到 | W76: 警语书纸翻PO#4500141955 | Z76: （注意：零售包装上的日期码要在无需拆开包装的前提下可直接看到） | AA76: 日期码格式：ZURU INC(BVI) 标准格式 日期：按实际生产日期 Packaging Info: 客版15L 收缩膜 翻PO#4500146851， 客版15L收藏指南翻PO#4500141955, MA 多语 slime bag+客版15L slime bag 警语书纸翻PO#4500141955, MA最新版布标，MA 最新版多语stiker. Remark: 客人款号：3009949 1. 订单总数量593100pcs, 共分为25个柜子，请按期完货. 2. 所有产品按符合欧洲标准走货，微塑料需合规。 3. 所有包装材料都不允许PVC, 请用PET代替 4. 此单需要4套产前样及4套大货样，样板请寄到罗湖办公室Amber Zhang 收 Baby EAN code: #9259 : 4894680021402 #9269 : 4894680023543 | AB76: Amber zhang | AC76: 14.6964 | AD76: =AC76*M76 -> 29054.783 | AJ76: =J76 -> 11862 | AN76: =J76 -> 11862 | AQ76: =J76 -> 11862 | BB76: MA布标 | BC76: =J76/4 -> 2965.5 | BD76: =J76/4 -> 2965.5 | BE76: =J76/4 -> 2965.5 | BG76: =J76/4 -> 2965.5 | BJ76: =SUM(BC76:BI76) -> 11862 | BK76: =J76-BJ76 -> 0
A77: 45796 | B77: ACTION SERVICE & DISTRIBUTIE B.V. | C77: 荷兰 | D77: 4500166812 | E77: 4401018168 | F77: 4500166812-190 | H77: MB83-S002-9259 | I77: 混装（9259+9269各6PCS） | J77: 11862 | K77: 0 | L77: 6 | M77: =J77/L77 -> 1977 | N77: 46175 | O77: =N77-3 -> 46172 | Q77: PASS | S77: =J77-R77 -> 11862 | T77: 6/11出 | U77: 5/19收到 | W77: 警语书纸翻PO#4500141955 | Z77: （注意：零售包装上的日期码要在无需拆开包装的前提下可直接看到） | AA77: 日期码格式：ZURU INC(BVI) 标准格式 日期：按实际生产日期 Packaging Info: 客版15L 收缩膜 翻PO#4500146851， 客版15L收藏指南翻PO#4500141955, MA 多语 slime bag+客版15L slime bag 警语书纸翻PO#4500141955, MA最新版布标，MA 最新版多语stiker. Remark: 客人款号：3009949 1. 订单总数量593100pcs, 共分为25个柜子，请按期完货. 2. 所有产品按符合欧洲标准走货，微塑料需合规。 3. 所有包装材料都不允许PVC, 请用PET代替 4. 此单需要4套产前样及4套大货样，样板请寄到罗湖办公室Amber Zhang 收 Baby EAN code: #9259 : 4894680021402 #9269 : 4894680023543 | AB77: Amber zhang | AC77: 14.6964 | AD77: =AC77*M77 -> 29054.783 | AJ77: =J77 -> 11862 | AN77: =J77 -> 11862 | AQ77: =J77 -> 11862 | BB77: MA布标 | BC77: =J77/4 -> 2965.5 | BD77: =J77/4 -> 2965.5 | BE77: =J77/4 -> 2965.5 | BG77: =J77/4 -> 2965.5 | BJ77: =SUM(BC77:BI77) -> 11862 | BK77: =J77-BJ77 -> 0
A78: 45796 | B78: ACTION SERVICE & DISTRIBUTIE B.V. | C78: 荷兰 | D78: 4500166812 | E78: 4401018166 | F78: 4500166812-170 | H78: MB83-S002-9259 | I78: 混装（9259+9269各6PCS） | J78: 11862 | K78: 0 | L78: 6 | M78: =J78/L78 -> 1977 | N78: 46175 | O78: =N78-3 -> 46172 | Q78: PASS | S78: =J78-R78 -> 11862 | T78: 6/6出 | U78: 5/19收到 | W78: 警语书纸翻PO#4500141955 | Z78: （注意：零售包装上的日期码要在无需拆开包装的前提下可直接看到） | AA78: 日期码格式：ZURU INC(BVI) 标准格式 日期：按实际生产日期 Packaging Info: 客版15L 收缩膜 翻PO#4500146851， 客版15L收藏指南翻PO#4500141955, MA 多语 slime bag+客版15L slime bag 警语书纸翻PO#4500141955, MA最新版布标，MA 最新版多语stiker. Remark: 客人款号：3009949 1. 订单总数量593100pcs, 共分为25个柜子，请按期完货. 2. 所有产品按符合欧洲标准走货，微塑料需合规。 3. 所有包装材料都不允许PVC, 请用PET代替 4. 此单需要4套产前样及4套大货样，样板请寄到罗湖办公室Amber Zhang 收 Baby EAN code: #9259 : 4894680021402 #9269 : 4894680023543 | AB78: Amber zhang | AC78: 14.6964 | AD78: =AC78*M78 -> 29054.783 | AJ78: =J78 -> 11862 | AN78: =J78 -> 11862 | AQ78: =J78 -> 11862 | BB78: MA布标 | BC78: =J78/4 -> 2965.5 | BD78: =J78/4 -> 2965.5 | BE78: =J78/4 -> 2965.5 | BG78: =J78/4 -> 2965.5 | BJ78: =SUM(BC78:BI78) -> 11862 | BK78: =J78-BJ78 -> 0
A79: 45796 | B79: ACTION SERVICE & DISTRIBUTIE B.V. | C79: 荷兰 | D79: 4500166812 | E79: 4401018173 | F79: 4500166812-240 | H79: MB83-S002-9259 | I79: 混装（9259+9269各6PCS） | J79: 11862 | K79: 0 | L79: 6 | M79: =J79/L79 -> 1977 | N79: 46175 | O79: =N79-3 -> 46172 | Q79: PASS | S79: =J79-R79 -> 11862 | T79: 6/5出 | U79: 5/19收到 | W79: 警语书纸翻PO#4500141955 | Z79: （注意：零售包装上的日期码要在无需拆开包装的前提下可直接看到） | AA79: 日期码格式：ZURU INC(BVI) 标准格式 日期：按实际生产日期 Packaging Info: 客版15L 收缩膜 翻PO#4500146851， 客版15L收藏指南翻PO#4500141955, MA 多语 slime bag+客版15L slime bag 警语书纸翻PO#4500141955, MA最新版布标，MA 最新版多语stiker. Remark: 客人款号：3009949 1. 订单总数量593100pcs, 共分为25个柜子，请按期完货. 2. 所有产品按符合欧洲标准走货，微塑料需合规。 3. 所有包装材料都不允许PVC, 请用PET代替 4. 此单需要4套产前样及4套大货样，样板请寄到罗湖办公室Amber Zhang 收 Baby EAN code: #9259 : 4894680021402 #9269 : 4894680023543 | AB79: Amber zhang | AC79: 14.6964 | AD79: =AC79*M79 -> 29054.783 | AJ79: =J79 -> 11862 | AN79: =J79 -> 11862 | AQ79: =J79 -> 11862 | BB79: MA布标 | BC79: =J79/4 -> 2965.5 | BD79: =J79/4 -> 2965.5 | BE79: =J79/4 -> 2965.5 | BG79: =J79/4 -> 2965.5 | BJ79: =SUM(BC79:BI79) -> 11862 | BK79: =J79-BJ79 -> 0
BK82: =J82-BJ82 -> 0
BK83: =J83-BJ83 -> 0
H84: Total: | J84: =SUBTOTAL(9,J5:J83) -> 743700 | AD84: =SUM(AD5:AD83) -> 1441542 | AG84: =SUM(AG5:AG83) -> 10584 | AH84: =SUM(AH5:AH83) -> 0 | AI84: =SUM(AI5:AI83) -> 0 | AJ84: =SUM(AJ5:AJ83) -> 733116 | AK84: =SUM(AK5:AK83) -> 0 | AL84: =SUM(AL5:AL83) -> 10584 | AM84: =SUM(AM5:AM83) -> 0 | AN84: =SUM(AN5:AN83) -> 733116 | ... BJ84: =SUM(BJ5:BJ83) -> 743700

Sheet 9279
A1: ZURU Rainbocorn 猫蛋二代毛絨公仔生产排期表 #9279 | BL1: 无闪粉毛绒 | BS1: 有闪粉毛绒
A2: =#REF! -> #REF! | F2: 0 | I2: （黃色表示更改或增加） | L2: （蓝色表示已完货） | P2: （綠色表示調整貨期） | AH2: 收縮膜 | AN2: 收藏指南 | AQ2: 口水胶 | BL2: 1 | BM2: 9 | BN2: 10 | BO2: 10 | BP2: 10 | BQ2: 10 | BR2: 10 | BT2: 9 | BU2: 10 | BV2: 10 | BW2: 10 | BX2: 10 | BY2: 10
A3: 接单期 | B3: 第三方客户名称 | C3: 国家 | D3: PO号 | E3: 客户PO号 | F3: SKU号 | G3: 系统货号 | H3: 货号 | I3: 名称 | J3: 数量 | K3: 内箱装箱数量(pcs) | L3: 装箱数（PCS） | M3: 总箱数 | N3: 计划出货期 | O3: 计划验货期 | P3: 第三方验货期 | Q3: 驗貨結果 | R3: 送货情况 | S3: 欠数 | T3: 贴纸 | U3: 船期SO | V3: 箱唛资料(收到日期) | W3: 外箱贴纸 | X3: 贴纸AI(收到日期) | Y3: 贴纸订购与回货时间 | Z3: 客供物料 | AA3: 日期码 | AB3: 备注 | AC3: ZURU 跟单 | AD3: 单价USD | AE3: 金额USD | AF3: 發票號 | AG3: 是否入系统 | AH3: MA 1語收縮膜 A版本 | AI3: MA 1語收縮膜 B版本 | AJ3: MA 3语收缩膜 A版本 | AK3: MA 3语收缩膜 B版本 | AL3: EU-3L收缩膜 | AM3: 客版收縮膜 | AN3: MA 5语 收藏指南 A版本 | AO3: MA 5语 收藏指南 B版本 | AP3: 客版收藏指南 | AQ3: MA口水胶-A版本 | AR3: MA口水胶-B版本 | AS3: MA口水胶-无闪粉有硼 | AT3: MA口水胶-无闪粉无硼 | AU3: 客版无硼口水胶 | AV3: PDQ SQ1-S001-S002 IL | AW3: PDQ SQ1-S001 3L | AX3: SQ1-PDQ-1L-3L （共用） | AY3: PDQ TQ1-1L | AZ3: PDQ TQ1-3L | BA3: PDQ TQ1-1L-3L B版本 (通用） | BB3: PDQ TQ2-WM单 | BC3: PDQ TQ3-WM莫里森-A版本 | BD3: PDQ TQ3-WM莫里森-B版本 | BE3: PDQ TQ5-1L | BF3: PDQ TQ5-WMCA-2L | BG3: F 展示架 1L | BH3: 客办PDQ | BI3: 客办展示架 | BJ3: 无闪粉毛绒 | BK3: 布標 | BL3: 布偶猫/Ragdoll cat | BM3: 美国猫/American Cat(A) | BN3: 孟加拉猫/Bengal cat（E) | BO3: 加菲猫EXOTIC CAT(G) | BP3: 花斑猫CALICO CAT(B) | BQ3: 黑猫BLKCK CAT(D) | BR3: 粉色猫/Chinchilla cat(H) | BS3: 布偶猫/Ragdoll cat | BT3: 美国猫/American Cat(A) | BU3: 孟加拉猫/Bengal cat（E) | BV3: 加菲猫EXOTIC CAT(G) | BW3: 花斑猫CALICO CAT(B) | BX3: 黑猫BLKCK CAT(D) | BY3: 粉色猫/Chinchilla cat(H) | BZ3: 总数 | CA3: 相差 | CB3: 客户回复最晚货期 | CC3: 测试口水胶问题批次 | CD3: 送货情况 | CE3: 系统出单 | CF3: 贴纸情况
A4: 45454 | B4: ZURU | C4: 库有 | D4: ZMPO24455 | G4: 过渡 | H4: 9279SQ1-S001 | I4: 猫蛋二代 | J4: 50个空PDQ | K4: 0 | L4: 12 | M4: 0 | N4: 45462 | O4: 45458 | V4: 无 | X4: 无 | AB4: 大货最新版本/可打平包;备注： 收到样品订单后尽快安排 ，注意样板品质质量要求要高于大货品质要求 ，送货时必须要附带送货单(没有送货单和QC检验合格报告的仓库一律拒绝收货)，请知悉，谢谢！ | AG4: 过渡 | AX4: =50 -> 50
A5: 45594 | B5: TESCO CE | D5: MPO02973 | G5: 9279-S001 | H5: 9279-S001 | I5: 猫蛋二代 | J5: 2080 | K5: 0 | L5: 8 | M5: =J5/L5 -> 260 | N5: 45632 | O5: 45628 | Q5: PASS | U5: 12/6送外厂 | V5: 周转箱 | X5: 10/30收到CZ/HU/PL/SK警语贴纸 | AB5: Remark: 1. 此单出EU，需满足EU测试标准要求，不含微塑料。 2. 产品及包装需要印UKCA图标，包装需要有ZURU UK LTD/ZURU France地址信息，QC同事请核查，如有问题与跟单确认。 3.可用空白周转箱 4. 如含硼的话， 需用低硼版本(小于300ppm),硼含量需要符合欧洲标准,否则客人会退货有罚款产生 5. 子件送泰亨组装 9279：最新版MA 1L UPC收缩膜+一张CZ/HU/PL/SK警语贴纸 | AC5: Eddie Huang | AD5: 2.0411 | AE5: =J5*AD5 -> 4245.488 | AF5: 94204-2.10 | AI5: =J5 -> 2080 | AO5: =J5 -> 2080 | AS5: =J5 -> 2080 | BK5: MA布标 | BL5: =J5/60*1 -> 34.666667 | BM5: =J5/60*9 -> 312 | BN5: =J5/60*10 -> 346.66667 | BO5: =J5/60*10 -> 346.66667 | BP5: =J5/60*10 -> 346.66667 | BQ5: =J5/60*10 -> 346.66667 | BR5: =J5/60*10 -> 346.66667 | BZ5: =SUM(BL5:BY5) -> 2080 | CA5: =J5-BZ5 -> 0
A6: 45597 | B6: ARGOS LIMITED | C6: 英国 | D6: 4500149875 | E6: PO#361490-SKU #2259433 | F6: 4500149875-10 | G6: 9279-S001 | H6: 9279-S001 | I6: 猫蛋二代 | J6: 1512 | K6: 0 | L6: 24 | M6: =J6/L6 -> 63 | N6: 45644 | O6: 45640 | Q6: PASS | U6: 12/18出 | V6: 11/5收到 | X6: 11/6收到客人白色Cat.label | AB6: 日期码格式：ZURU INC(BVI) 标准格式 日期：按实际生产日期 Packaging Info: -MA -1L 包装+客人白色Cat.label 1张覆盖ZURU条码 -注意Cat.label (要求易撕类贴纸，但是粘性不能过低），同时此贴纸每个订单都是不相同的(会显示客户对应的订单号），切勿翻旧订单购买，该贴纸由工厂自行 购买。 -订单对应客户2个PO号 ，备注有显示 ，注意分开做货/验货/装柜 ，混装有罚款。 Remark: *MA包装按最新版本安排即可 *包装日期码按ZURU格式即可，请确保不迟于外箱日期码，可等于或者早于外箱日期码，必须为法定工作日。 *外箱尺寸任何一条边长度超过75cm或者每箱重量超过10KG,需要在外箱上加三脚架符号，有问题请与ZURU跟单同事核实。 *订单必须经过ZURU QC验货并且通过后方可出货。 *订单出英国，请注意检查产品及包装应带UKCA图标，包装显示ZURU UK LTD信息，QC同事请查核，如有问题与跟单确认。 *条码扫描会显示客户7位数产品号 ，忽略订单显示的MA条码 *所有产品按符合欧洲标准走货，需要是不含微塑料版本 。 *涉及到硼的，请使用低硼版本 *客户不接受PVC材质包装 | AC6: Zoe Chen | AD6: 2.1295 | AE6: =J6*AD6 -> 3219.804 | AF6: 88854-1.3 | AI6: =J6 -> 1512 | AO6: =J6 -> 1512 | AS6: =J6 -> 1512 | BK6: MA布标 | BL6: =J6/60*1 -> 25.2 | BM6: =J6/60*9 -> 226.8 | BN6: =J6/60*10 -> 252 | BO6: =J6/60*10 -> 252 | BP6: =J6/60*10 -> 252 | BQ6: =J6/60*10 -> 252 | BR6: =J6/60*10 -> 252 | BZ6: =SUM(BL6:BY6) -> 1512 | CA6: =J6-BZ6 -> 0
A7: 45604 | B7: Inventive Toys | C7: 俄罗斯联邦 | D7: 4500150797 | F7: 4500150797-30 | G7: 9279-S001 | H7: 9279-S001 | I7: 猫蛋二代 | J7: 5040 | K7: 0 | L7: 24 | M7: =J7/L7 -> 210 | N7: 45649 | O7: 45645 | Q7: PASS | U7: 1/3出 | V7: 11/26收到 | X7: 12/9-进口商贴纸+ EAN 条码贴纸 | AA7: 外包装/外箱不要打ZURU标准日期码 | AB7: 日期码格式：外包装/外箱不要打ZURU标准日期码 日期： Packaging Info: 注意 ：外包装 (指: 收缩膜/彩卡/铝箔袋/挂卡/PDQ) /外箱不要打ZURU标准日期码！胶件可以打日期码。 外包装（包括收缩膜/彩卡/PDQ）都不能含Instagram and facebook logo等社交logo; 1L MA 收缩膜+ 进口商贴纸； MA PDQ+ EAN 条码贴纸 ， MA 指南/说明书（如有） Remark: 标准配比 ； | AC7: Ann Zhang | AD7: 2.0623 | AE7: =J7*AD7 -> 10393.992 | AF7: 94064-1.16 | AI7: =J7 -> 5040 | AO7: =J7 -> 5040 | AS7: =J7 -> 5040 | BK7: MA布标 | BL7: =J7/60*1 -> 84 | BM7: =J7/60*9 -> 756 | BN7: =J7/60*10 -> 840 | BO7: =J7/60*10 -> 840 | BP7: =J7/60*10 -> 840 | BQ7: =J7/60*10 -> 840 | BR7: =J7/60*10 -> 840 | BZ7: =SUM(BL7:BY7) -> 5040 | CA7: =J7-BZ7 -> 0
A8: 45604 | B8: Inventive Toys | C8: 俄罗斯联邦 | D8: 4500150797 | F8: 4500150797-80 | G8: 9279SQ1-S001-1L | H8: 9279SQ1-S001 | I8: 猫蛋二代 | J8: 2400 | K8: 0 | L8: 12 | M8: =J8/L8 -> 200 | N8: 45649 | O8: 45645 | Q8: PASS | U8: 1/3出 | V8: 11/26收到 | X8: 12/9-进口商贴纸+ EAN 条码贴纸 | AA8: 外包装/外箱不要打ZURU标准日期码 | AB8: 日期码格式：外包装/外箱不要打ZURU标准日期码 日期： Packaging Info: 注意 ：外包装 (指: 收缩膜/彩卡/铝箔袋/挂卡/PDQ) /外箱不要打ZURU标准日期码！胶件可以打日期码。 外包装（包括收缩膜/彩卡/PDQ）都不能含Instagram and facebook logo等社交logo; 1L MA 收缩膜+ 进口商贴纸； MA PDQ+ EAN 条码贴纸 ， MA 指南/说明书（如有） Remark: 标准配比 ； | AC8: Ann Zhang | AD8: 2.2044 | AE8: =J8*AD8 -> 5290.56 | AF8: 94064-1.16 | AI8: =J8 -> 2400 | AO8: =J8 -> 2400 | AS8: =J8 -> 2400 | AX8: =J8/6 -> 400 | BK8: MA布标 | BL8: =J8/60*1 -> 40 | BM8: =J8/60*9 -> 360 | BN8: =J8/60*10 -> 400 | BO8: =J8/60*10 -> 400 | BP8: =J8/60*10 -> 400 | BQ8: =J8/60*10 -> 400 | BR8: =J8/60*10 -> 400 | BZ8: =SUM(BL8:BY8) -> 2400 | CA8: =J8-BZ8 -> 0
A9: 45604 | B9: AMAZON.COM.DEDC,LLC | C9: 美国 | D9: 4500150761 | E9: 647ZE1UJ | F9: 4500150761-70 | G9: 9279G-S001 | H9: 9279G-S001 | I9: 猫蛋二代 | J9: 144 | K9: 0 | L9: 12 | M9: =J9/L9 -> 12 | N9: 45650 | O9: 45646 | Q9: PASS | U9: 12/30出 | V9: 11/8收到 | X9: UPC贴纸翻4500097545 | Z9: 12/2-外箱贴纸 | AB9: 日期码格式：ZURU INC(BVI) 标准格式 日期：按实际生产日期 Packaging Info: #9279：MA 1L 加UPC贴纸, UPC贴纸图稿跟返单4500097545.9279G: 193052054753. Remark: 1. Amazon FOB订单，出口US。 2. 日期码使用ZURU标准版本。 3. 如果大货有要求入邮包盒，则对应的邮包盒上面要打上日期码。 4. 箱尺寸要求：外箱最长边不能超过25" （超过了，case pack只能为1），不符合要求的大货，一律不接受。 5. 外箱箱唛要求： ①外箱正面印ZURU Logo+SSCC Label（客供贴纸，由跟单订购)。关于 SSCC Label 请注意： SSCC Label 显示的是客人自己的item#。每一张SSCC label 都是唯一且有不同流水及条码的，没有损耗，绝对不可贴错 。如果贴错或损坏任何一张，都会导致全 部都错，千万要注意！ SSCC Label 必须贴在外箱正面的正中间位置（贴一面即可），并且贴纸离外箱边距必须至少3cm(可以覆盖Logo<(>&<)>箱唛)，否则会影响到客户那边仓库的扫描识 别。 ②外箱侧面印item#（订单上显示的SKU#)+carton size(以工厂实际尺寸为准,单位: inch) +MADE IN CHINA,日期使用ZURU 标准版本。 6. 装柜要求：按照客户PO# 装柜/箱号顺序装柜，跟单会提前给到装柜计划。 在大货生产/仓库存放时，请留意该装柜要求，以便装柜时不混乱（避免装错/装漏/找不到货号等）。 | AC9: Kelly Shen | AD9: 2.139 | AE9: =J9*AD9 -> 308.016 | AF9: 88846-1.2 | AI9: =J9 -> 144 | AO9: =J9 -> 144 | AS9: =J9 -> 144 | BK9: MA布标 | BO9: =J9 -> 144 | BZ9: =SUM(BL9:BY9) -> 144 | CA9: =J9-BZ9 -> 0
A10: 45595 | B10: AMAZON UK | C10: 英国 | D10: 4500149496 | E10: Amazon UK: 5J18RF7X | F10: 4500149496-10 | G10: 9279H-S001-3L | H10: 9279H-S001 | I10: 猫蛋二代 | J10: 912 | K10: 0 | L10: 12 | M10: =J10/L10 -> 76 | N10: 45651 | O10: 45647 | Q10: PASS | V10: 空白外箱（加印带Zuru字样的最新logo，除了邮包盒直接做外箱的产品） + SSCC LABEL一张, 无箱唛。MADE IN CHINA 外箱只印一正一侧 | X10: UPC#+IT sorting label翻4500124528+ES回收标翻单4500149035 | Z10: 11/29-外箱贴纸 | AB10: 日期码格式：ZURU INC(BVI) 标准格式 日期：按实际生产日期 Packaging Info: Amazon UK(9279H, 9283B, 9281A, 9298B, 71109B) 1. 9279H：9279H 12pcs/ctn, no inner,CHINCHILLA CAT; CTN Loading: 4W*3D=12pcs/CTN; MA 3L(23L warning)B收缩膜+ 2张贴纸(1张UPC#+IT sorting label <(>,<)>参考翻单PO#4500124528；1张ES回收标，参考翻单PO#4500149035)+MA 最新版布标+MA 5L(23L warning) C收藏指南+其他MA最新版包装； 6. 最迟验货不得晚于2024/12/26; Remark: 1.空白外箱（加印带Zuru字样的最新logo，除了邮包盒直接做外箱的产品） + SSCC LABEL一张, 无箱唛。 (SSCC LABEL贴在外箱正面的正中间，贴一面即可,贴纸离外箱边距必须至少3.2CM), SSCC贴纸由工厂直接跟勤得采购或者工厂自行采购，每一张SSCC Label都是唯一 且有不同流水及条码，且需要检查条码是否能正常扫描，另外，此贴纸印刷不可出现模糊，溢出及粘胶不牢易脱落等现象，如工厂不按此要求导致贴纸有任何问题产 生的罚款将由工厂承担一切责任 。’MADE IN CHINA 外箱只印一正一侧。 2.出往UK的产品+包装务必打上UKCA logo ，否则客人会退货且当地会有罚款。 3.订单必须经过ZURU QC验货并且通过后方可出货。 4.法国订单要求包装不使用矿物油，请按要求提供以下其中一份文件再出货 ，产品出到法国被相关部门抽检出现包装不符合此要求的，供应商需要为此承担责任， 故此请严格把关。 -油墨物质""由1 ~ 7个芳香环组成的MOAH""的包装检测报告，要求限值≤1.0%； -包装材料清单，包括包装油墨或物质的信息； -油墨制造商的证书； 5.每一批次出货只能有一个生产日期，不可多个生产日期混在同一批次出货；且邮包盒上必须统一加上日期码； 6.涉及到相关款式会有闪粉的或者微塑料的，请统一默认出无闪粉或者不含微塑料版本； 7.邮包盒及外箱封箱必须是工字型封箱方式； 8.5 Surprise or Mini Brands涉及包装是2个及2个以上的球入PVC桶包装时，单个球上若有UPC#或者EAN#，请用白色贴纸覆盖住； 9.箱唛资料按照给定的标准去做即可，无需发回我方再行审批(新标准将另行通知); | AC10: Crystal Chen | AD10: 2.139 | AE10: =J10*AD10 -> 1950.768 | AF10: 88934-1.8 | AK10: =J10 -> 912 | AO10: =J10 -> 912 | AS10: =J10 -> 912 | BK10: MA布标 | BR10: =J10-BS10 -> 912 | BZ10: =SUM(BL10:BY10) -> 912 | CA10: =J10-BZ10 -> 0
A11: 45623 | B11: TJX COMPANIES, INC | C11: 美国 | D11: 4500152570 | E11: Marshalls DC#881-384PCS , DC#884-288PCS , DC#886-408PCS , DC#887-360PCS , DC#888-360PCS | F11: 4500152570-30 | G11: 9279-S001 | H11: 9279-S001 | I11: 猫蛋二代 | J11: 1800 | K11: 0 | L11: 24 | M11: 75 | N11: 45651 | O11: 45647 | Q11: PASS | U11: 1/2出 | V11: 11/27收到 | X11: 无 | Z11: 12/6-价格贴纸 | AB11: 日期码格式：ZURU INC(BVI) 标准格式 日期：按实际生产日期 Packaging Info: MA UPC包装+价格贴纸，价格贴纸客供。 Remark: 1. 产品和包装上印刷tracking code信息，格式为ZURU常规格式。 2. 分5个DC出货，每款产品每个DC的箱唛资料不同。具体分DC数量，请参考后面行项目备注。 3. ZURU QC验货。 | AC11: Emily Wu | AD11: 2.1295 | AE11: 3833.1 | AF11: 94168-1.23 | AI11: 1800 | AO11: 1800 | AS11: =J11 -> 1800 | BK11: MA布标 | BM11: =J11/60*9 -> 270 | BN11: =J11/60*10 -> 300 | BO11: =J11/60*10 -> 300 | BP11: =J11/60*10 -> 300 | BQ11: =J11/60*10 -> 300 | BR11: =J11/60*10 -> 300 | BS11: =J11/60*1 -> 30 | BZ11: =SUM(BL11:BY11) -> 1800 | CA11: =J11-BZ11 -> 0
A12: 45601 | B12: DD’S DISCOUNTS | C12: 美国 | D12: 4500150187 | E12: 70054066 | F12: 4500150187-20 | G12: 9279-S001 | H12: 9279-S001 | I12: 猫蛋二代 | J12: 360 | K12: 0 | L12: 24 | M12: =J12/L12 -> 15 | N12: 45653 | O12: 45649 | Q12: PASS | U12: 1/7出 | V12: ROSS指定箱唛格式 | X12: 无 | Z12: 11/20-客供价格贴纸 | AB12: 日期码格式：ZURU INC(BVI) 标准格式 日期：按实际生产日期 Packaging Info: 1.ZURU MA UPC 现有版本包装 + 客供价格贴纸，出口美国 , 优先使用MA 1L 最新版本 。 Remark: 1.ZURU MA UPC 现有版本包装 + 客供价格贴纸，出口美国 , 优先使用MA 1L 最新版本 。 2.价格贴纸位于包装正面右下角，不挡住重要信息即可，可适当调整 ，价格贴纸由跟单提供。 3.标准日期码格式，产品和包装必须有日期码 。 4.同个产品同个货期不可出现不同的包装。 5. 跟单提供ROSS通用的箱唛模版，工厂按实际45 PO上客户PO/Item号/装箱数 提供箱唛排版来确认。 | AC12: Taylor Liao | AD12: 2.1341 | AE12: =J12*AD12 -> 768.276 | AF12: 88917-1.7 | AI12: =J12 -> 360 | AO12: =J12 -> 360 | AS12: =J12 -> 360 | BK12: MA布标 | BL12: =J12/60*1 -> 6 | BM12: =J12/60*9 -> 54 | BN12: =J12/60*10 -> 60 | BO12: =J12/60*10 -> 60 | BP12: =J12/60*10 -> 60 | BQ12: =J12/60*10 -> 60 | BR12: =J12/60*10 -> 60 | BZ12: =SUM(BL12:BY12) -> 360 | CA12: =J12-BZ12 -> 0
A13: 45608 | B13: CMS FAMOUS TOYS | C13: 加拿大 | D13: 4500151018 | E13: PO0000475 | F13: 4500151018-10 | G13: 9279SQ1-S002-NB | H13: 9279SQ1-S002-NB | I13: 猫蛋二代（无闪粉) | J13: 372 | K13: 0 | L13: 6 | M13: =J13/L13 -> 62 | N13: 45651 | O13: 45647 | Q13: PASS | U13: 收到SO | V13: 11/25收到 | X13: 11/19收到进口商贴纸 | AB13: 日期码格式： 标准格式 日期：按实际生产日期 Packaging Info:9279SQ1 MA 3L UPC包装 ,无硼版本。UPC号码193052050014 Remark: 出加拿大 每款产品都需要加进口商贴纸 Zuru验货.日期跟踪码：产品外包装及产品本身都必须有日期跟踪码，ZURU标准格式日期码 | AC13: Summer Mo | AD13: 2.1581 | AE13: =J13*AD13 -> 802.8132 | AF13: 88842-1.2 | AK13: =J13 -> 372 | AO13: =J13 -> 372 | AT13: =J13 -> 372 | AX13: =J13/6 -> 62 | BK13: MA布标 | BL13: =J13/60*1 -> 6.2 | BM13: =J13/60*9 -> 55.8 | BN13: =J13/60*10 -> 62 | BO13: =J13/60*10 -> 62 | BP13: =J13/60*10 -> 62 | BQ13: =J13/60*10 -> 62 | BR13: =J13/60*10 -> 62 | BZ13: =SUM(BL13:BY13) -> 372 | CA13: =J13-BZ13 -> 0
A14: 45587 | B14: ROSS PROCUREMENT.INC | C14: 美国 | D14: 4500147716 | E14: 60190663 | F14: 4500147716-80 | G14: 92114-S001 | H14: 92114-S001 | I14: 猫蛋二代(9279+9269)组装 | J14: 2796 | K14: 0 | L14: 12 | M14: =J14/L14 -> 233 | N14: 45653 | O14: 45649 | Q14: PASS | U14: 1/3出 | V14: 指定箱唛格式 | X14: 无 | Z14: 11/20-客供价格贴纸 | AA14: DG20241120 | AB14: 日期码格式： 标准格式 日期：按实际生产日期 Packaging Info: 1.ZURU MA UPC 现有版本包装 + 客供价格贴纸，出口美国 , 优先使用MA 1L 最新版本 。 Remark: 1.ZURU MA UPC 现有版本包装 + 客供价格贴纸，出口美国 , 优先使用MA 1L 最新版本 。 2.价格贴纸位于包装正面右下角，不挡住重要信息即可，可适当调整 ，价格贴纸由跟单提供。 3.标准日期码格式，产品和包装必须有日期码 。 4.同个产品同个货期不可出现不同的包装。 5. 跟单提供ROSS通用的箱唛模版，工厂按实际45 PO上客户PO/Item号/装箱数 提供箱唛排版来确认 | AC14: Sophia Zhou | AD14: 2.7175 | AE14: =J14*AD14 -> 7598.13 | AF14: 88881-1.6 | AG14: 已入 | AI14: =J14 -> 2796 | AO14: =J14 -> 2796 | AS14: =J14 -> 2796 | BH14: =J14 -> 2796 | BK14: MA布标 | BM14: =J14/60*9 -> 419.4 | BN14: =J14/60*10 -> 466 | BO14: =J14/60*10 -> 466 | BP14: =J14/60*10 -> 466 | BQ14: =J14/60*10 -> 466 | BR14: =J14/60*10 -> 466 | BS14: =J14/60*1 -> 46.6 | BZ14: =SUM(BL14:BY14) -> 2796 | CA14: =J14-BZ14 -> 0
A15: 45594 | B15: ALDI UK | C15: 英国 | D15: 4500149353 | F15: 4500149353-10 | G15: MFD154-S001 | H15: MFD154-S001 | I15: 猫蛋二代 | J15: 19242 | K15: 0 | L15: 18 | M15: =J15/L15 -> 1069 | N15: 45653 | O15: 45649 | P15: 1/8 第三方 | Q15: PASS | U15: 1/16出 | V15: 11/15收到 | X15: UPC条码翻4500117789 | AB15: 日期码格式：ZURU INC(BVI) 标准格式 日期：按实际生产日期 Packaging Info: 1.MFD154: 客版展示架 9269 Puppycorn 3W*3D*1H=9pcs ratio ：Husky：Dalmatian：Labrador：Chihuahua=1：1：1：1 9279 Kittycorn 3W*3D*2H=18pcs ratio ：同MA 7456 Mini Ice Age 3W*3D*1H=9pcs ratio ：同MA 74107 Mini Jurassic 3W*3D*1H=9pcs ratio ：同MA Total: 45pcs/FSDU 请务必按照上面列出的配比装箱，否则第三方验货会不合格不能安排出货； 2. 子件7456 和 74107 :泰亨客供带包装成品给兴信组装，子件9269: 华康客供带包装成品给兴信组装，由ZURU DCP下单给泰亨/华康，预计12月16日送货到兴信厂 ； 包装版本: 兴信子件①：9279 MA 1L B版收缩膜+一张符合客户要求的UPC条码(UPC#193052050014)贴在原条码上（原条码请打叉）+MA 收藏指南5L C版+MA B版布标+MA 5L C版 poop polybag, 贴纸翻PO#4500117789 华康子件②：9269 MA 1L 无闪粉版收缩膜+一张符合客户要求的UPC条码(UPC#193052043252)贴在原条码上（原条码请打叉）+MA 收藏指南5L B版+MA B版布标+MA 5L B版 poop polybag 泰亨子件③：7456 MA 1L C版收缩膜+ 一张符合客户要求的UPC条码(UPC#193052018083)贴在原条码上（原条码请打叉）+MA收藏指南D 5L版+MA 说明书 C 版本, 贴 纸翻PO#4500117789 泰亨子件④：74107 MA 1L B版收缩膜+一张符合客户要求的UPC条码(UPC#193052051363)贴在原条码上（原条码请打叉）+MA 说明书 B 版本+MA B bag, 贴纸翻PO#45 00117789 Remark: 1.展示架需要加塑料托盘出货，托盘尺寸600*400*120mm； 2.每座展示架一共需要5个价格牌贴在展示架上； 3.第三方验货时间: 12/31日，请多备料； 4.请在10/29日寄1套带包装的产前样板+1套完整assortment的散配件装在袋子里面，给客人审批了才能做大货，包装版本需要同大货一致，请按时寄出； 5.请在11/11提供一箱完整的展示架大货样给我们寄给英国，装在UK订单箱唛的箱子上，外面还需要另外再套一个箱子保护这箱大货样； 6.请在11/4提供1个空展示架+各5套带包装的样板+5整套所有assortment公仔，每一套assortment装在一个袋子中给客人审批了才能安排验货，所有样板需要同大货 一致，否则第三方验货会不合格，请务必按时寄出所有样板； 所有样板需要同大货一致，否则第三方验货会不合格，请务必按时寄出所有样板； 7.上下工字型封箱 8.整柜需要加白色安全网，具体数量以船务通知为准，一般会提前一个月通知，需要一并提供装柜图片给客人参考； 9.Stick a completed "Container Loading Plan form" at the container door（船务需要提醒装柜人员需要在柜门出贴一张container loading plan form) 10.产品及包装需要印UKCA图标，包装需要有ZURU UK LTD/ZURU France地址信息，QC同事请核查，如有问题与跟单确认。 11.需要符合欧洲标准不能含有闪粉和微塑料，否则不符合法规会有客诉产生 12.行项目10出英国，行项目20出爱尔兰，两者的箱唛不一样请不要混淆 | AC15: Sheba Ye | AD15: 54.8797 | AE15: =AD15*M15 -> 58666.399 | AF15: 94037-1.15 | AI15: =J15 -> 19242 | AO15: =J15 -> 19242 | AS15: =J15 -> 19242 | BI15: =J15/18 -> 1069 | BK15: MA布标 | BL15: =J15/60*1 -> 320.7 | BM15: =J15/60*9 -> 2886.3 | BN15: =J15/60*10 -> 3207 | BO15: =J15/60*10 -> 3207 | BP15: =J15/60*10 -> 3207 | BQ15: =J15/60*10 -> 3207 | BR15: =J15/60*10 -> 3207 | BZ15: =SUM(BL15:BY15) -> 19242 | CA15: =J15-BZ15 -> 0
A16: 45594 | B16: ALDI UK | C16: 英国 | D16: 4500149354 | F16: 4500149354-10 | G16: MFD154-S001 | H16: MFD154-S001 | I16: 猫蛋二代 | J16: 3240 | K16: 0 | L16: 18 | M16: =J16/L16 -> 180 | N16: 45653 | O16: 45649 | P16: 1/8 第三方 | Q16: PASS | U16: 1/13出 | V16: 11/15收到 | X16: UPC条码翻4500117789 | AB16: 日期码格式：ZURU INC(BVI) 标准格式 日期：按实际生产日期 Packaging Info: 1.MFD154: 客版展示架 9269 Puppycorn 3W*3D*1H=9pcs ratio ：Husky：Dalmatian：Labrador：Chihuahua=1：1：1：1 9279 Kittycorn 3W*3D*2H=18pcs ratio ：同MA 7456 Mini Ice Age 3W*3D*1H=9pcs ratio ：同MA 74107 Mini Jurassic 3W*3D*1H=9pcs ratio ：同MA Total: 45pcs/FSDU 请务必按照上面列出的配比装箱，否则第三方验货会不合格不能安排出货； 2. 子件7456 和 74107 :泰亨客供带包装成品给兴信组装，子件9269: 华康客供带包装成品给兴信组装，由ZURU DCP下单给泰亨/华康，预计12月16日送货到兴信厂 ； 包装版本: 兴信子件①：9279 MA 1L B版收缩膜+一张符合客户要求的UPC条码(UPC#193052050014)贴在原条码上（原条码请打叉）+MA 收藏指南5L C版+MA B版布标+MA 5L C版 poop polybag, 贴纸翻PO#4500117789 华康子件②：9269 MA 1L 无闪粉版收缩膜+一张符合客户要求的UPC条码(UPC#193052043252)贴在原条码上（原条码请打叉）+MA 收藏指南5L B版+MA B版布标+MA 5L B版 poop polybag 泰亨子件③：7456 MA 1L C版收缩膜+ 一张符合客户要求的UPC条码(UPC#193052018083)贴在原条码上（原条码请打叉）+MA收藏指南D 5L版+MA 说明书 C 版本, 贴 纸翻PO#4500117789 泰亨子件④：74107 MA 1L B版收缩膜+一张符合客户要求的UPC条码(UPC#193052051363)贴在原条码上（原条码请打叉）+MA 说明书 B 版本+MA B bag, 贴纸翻PO#45 00117789 Remark: 1.展示架需要加塑料托盘出货，托盘尺寸600*400*120mm； 2.每座展示架一共需要5个价格牌贴在展示架上； 3.第三方验货时间: 12/31日，请多备料； 4.请在10/29日寄1套带包装的产前样板+1套完整assortment的散配件装在袋子里面，给客人审批了才能做大货，包装版本需要同大货一致，请按时寄出； 5.请在11/11提供一箱完整的展示架大货样给我们寄给英国，装在UK订单箱唛的箱子上，外面还需要另外再套一个箱子保护这箱大货样； 6.请在11/4提供1个空展示架+各5套带包装的样板+5整套所有assortment公仔，每一套assortment装在一个袋子中给客人审批了才能安排验货，所有样板需要同大货 一致，否则第三方验货会不合格，请务必按时寄出所有样板； 所有样板需要同大货一致，否则第三方验货会不合格，请务必按时寄出所有样板； 7.上下工字型封箱 8.整柜需要加白色安全网，具体数量以船务通知为准，一般会提前一个月通知，需要一并提供装柜图片给客人参考； 9.Stick a completed "Container Loading Plan form" at the container door（船务需要提醒装柜人员需要在柜门出贴一张container loading plan form) 10.产品及包装需要印UKCA图标，包装需要有ZURU UK LTD/ZURU France地址信息，QC同事请核查，如有问题与跟单确认。 11.需要符合欧洲标准不能含有闪粉和微塑料，否则不符合法规会有客诉产生 12.出爱尔兰，两者的箱唛不一样请不要混淆 | AC16: Sheba Ye | AD16: 55.1281 | AE16: =AD16*M16 -> 9923.058 | AF16: 94004-1.13 | AI16: =J16 -> 3240 | AO16: =J16 -> 3240 | AS16: =J16 -> 3240 | BI16: =J16/18 -> 180 | BK16: MA布标 | BL16: =J16/60*1 -> 54 | BM16: =J16/60*9 -> 486 | BN16: =J16/60*10 -> 540 | BO16: =J16/60*10 -> 540 | BP16: =J16/60*10 -> 540 | BQ16: =J16/60*10 -> 540 | BR16: =J16/60*10 -> 540 | BZ16: =SUM(BL16:BY16) -> 3240 | CA16: =J16-BZ16 -> 0
A17: 45586 | B17: TJX COMPANIES, INC | C17: 美国 | D17: 4500147792 | E17: Marshalls DC#881-120PCS , DC#884-96PCS, DC#886-144PCS , DC#887-120PCS , DC#888-120PCS | F17: 4500147792-50 | G17: 92114-S001 | H17: 92114-S001 | I17: 猫蛋二代(9279+9269)组装 | J17: 600 | K17: 0 | L17: 12 | M17: =J17/L17 -> 50 | N17: 45656 | O17: 45652 | Q17: PASS | U17: 1/9出 | V17: 11/4收到 | X17: 无 | Z17: 12/6-客供价格贴纸 | AB17: 日期码格式：ZURU INC(BVI) 标准格式 日期：按实际生产日期 Packaging Info: MA UPC包装+价格贴纸，价格贴纸客供。 #92114 是combo pack, 混装了 9269（华康生产）+9279（兴信生产），在兴信组装 。 Remark: 1. 产品和包装上印刷tracking code信息，格式为ZURU常规格式。 2. 分5个DC出货，每款产品每个DC的箱唛资料不同。具体分DC数量，请参考后面行项目备注。 3. ZURU QC验货。 | AC17: Emily Wu | AD17: 2.8218 | AE17: =J17*AD17 -> 1693.08 | AF17: 94166-1.23 | AG17: 已入 | AI17: =J17 -> 600 | AO17: =J17 -> 600 | AS17: =J17 -> 600 | BH17: =J17 -> 600 | BK17: MA布标 | BM17: =J17/60*9 -> 90 | BN17: =J17/60*10 -> 100 | BO17: =J17/60*10 -> 100 | BP17: =J17/60*10 -> 100 | BQ17: =J17/60*10 -> 100 | BR17: =J17/60*10 -> 100 | BS17: =J17/60*1 -> 10 | BZ17: =SUM(BL17:BY17) -> 600 | CA17: =J17-BZ17 -> 0
A18: 45586 | B18: TJX COMPANIES, INC | C18: 美国 | D18: 4500147793 | E18: Marshalls DC#881-120PCS , DC#884-96PCS, DC#886-132PCS , DC#887-120PCS , DC#888-132PCS | F18: 4500147793-60 | G18: 92114-S001 | H18: 92114-S001 | I18: 猫蛋二代(9279+9269)组装 | J18: 600 | K18: 0 | L18: 12 | M18: =J18/L18 -> 50 | N18: 45656 | O18: 45652 | Q18: PASS | U18: 1/9出 | V18: 11/4收到 | X18: 无 | Z18: 12/6-客供价格贴纸 | AB18: 日期码格式：ZURU INC(BVI) 标准格式 日期：按实际生产日期 Packaging Info: MA UPC包装+价格贴纸，价格贴纸客供。 #92114 是combo pack, 混装了 9269（华康生产）+9279（兴信生产），在兴信组装 。 Remark: 1. 产品和包装上印刷tracking code信息，格式为ZURU常规格式。 2. 分5个DC出货，每款产品每个DC的箱唛资料不同。具体分DC数量，请参考后面行项目备注。 3. ZURU QC验货。 | AC18: Emily Wu | AD18: 2.8218 | AE18: =J18*AD18 -> 1693.08 | AF18: 94171-1.23 | AG18: 已入 | AI18: =J18 -> 600 | AO18: =J18 -> 600 | AS18: =J18 -> 600 | BH18: =J18 -> 600 | BK18: MA布标 | BM18: =J18/60*9 -> 90 | BN18: =J18/60*10 -> 100 | BO18: =J18/60*10 -> 100 | BP18: =J18/60*10 -> 100 | BQ18: =J18/60*10 -> 100 | BR18: =J18/60*10 -> 100 | BS18: =J18/60*1 -> 10 | BZ18: =SUM(BL18:BY18) -> 600 | CA18: =J18-BZ18 -> 0
A19: 45586 | B19: TJX COMPANIES, INC | C19: 美国 | D19: 4500147795 | E19: TJ MAXX DC#891-156PCS , DC#894-132PCS , DC#896-132PCS , DC#897-252PCS , DC#898-132PCS | F19: 4500147795-50 | G19: 92114-S001 | H19: 92114-S001 | I19: 猫蛋二代(9279+9269)组装 | J19: 804 | K19: 0 | L19: 12 | M19: =J19/L19 -> 67 | N19: 45656 | O19: 45652 | Q19: PASS | U19: 1/8出 | V19: 11/4收到 | X19: 无 | Z19: 12-6客供价格贴纸 | AB19: 日期码格式：ZURU INC(BVI) 标准格式 日期：按实际生产日期 Packaging Info: MA UPC包装+价格贴纸，价格贴纸客供。 #92114 是combo pack, 混装了 9269（华康生产）+9279（兴信生产），在兴信组装 。 Remark: 1. 产品和包装上印刷tracking code信息，格式为ZURU常规格式。 2. 分5个DC出货，每款产品每个DC的箱唛资料不同。具体分DC数量，请参考后面行项目备注。 3. ZURU QC验货。 | AC19: Emily Wu | AD19: 2.8218 | AE19: =J19*AD19 -> 2268.7272 | AF19: 94175-1.23 | AG19: 已入 | AI19: =J19 -> 804 | AO19: =J19 -> 804 | AS19: =J19 -> 804 | BH19: =J19 -> 804 | BK19: MA布标 | BM19: =J19/60*9 -> 120.6 | BN19: =J19/60*10 -> 134 | BO19: =J19/60*10 -> 134 | BP19: =J19/60*10 -> 134 | BQ19: =J19/60*10 -> 134 | BR19: =J19/60*10 -> 134 | BS19: =J19/60*1 -> 13.4 | BZ19: =SUM(BL19:BY19) -> 804 | CA19: =J19-BZ19 -> 0
A20: 45586 | B20: TJX COMPANIES, INC | C20: 美国 | D20: 4500147796 | E20: TJ MAXX DC#891-168PCS , DC#894-144PCS , DC#896-120PCS , DC#897-240PCS , DC#898-120PCS | F20: 4500147796-60 | G20: 92114-S001 | H20: 92114-S001 | I20: 猫蛋二代(9279+9269)组装 | J20: 804 | K20: 0 | L20: 12 | M20: =J20/L20 -> 67 | N20: 45656 | O20: 45652 | Q20: PASS | U20: 1/8出 | V20: 11/4收到 | X20: 无 | Z20: 12-6客供价格贴纸 | AB20: 日期码格式：ZURU INC(BVI) 标准格式 日期：按实际生产日期 Packaging Info: MA UPC包装+价格贴纸，价格贴纸客供。 #92114 是combo pack, 混装了 9269（华康生产）+9279（兴信生产），在兴信组装 。 Remark: 1. 产品和包装上印刷tracking code信息，格式为ZURU常规格式。 2. 分5个DC出货，每款产品每个DC的箱唛资料不同。具体分DC数量，请参考后面行项目备注。 3. ZURU QC验货。 | AC20: Emily Wu | AD20: 2.8218 | AE20: =J20*AD20 -> 2268.7272 | AF20: 94170-1.23 | AG20: 已入 | AI20: =J20 -> 804 | AO20: =J20 -> 804 | AS20: =J20 -> 804 | BH20: =J20 -> 804 | BK20: MA布标 | BM20: =J20/60*9 -> 120.6 | BN20: =J20/60*10 -> 134 | BO20: =J20/60*10 -> 134 | BP20: =J20/60*10 -> 134 | BQ20: =J20/60*10 -> 134 | BR20: =J20/60*10 -> 134 | BS20: =J20/60*1 -> 13.4 | BZ20: =SUM(BL20:BY20) -> 804 | CA20: =J20-BZ20 -> 0
A21: 45622 | B21: I-VISION TOYS.INC | C21: 韩国 | D21: 4500152350 | E21: IVI-1114EK | F21: 4500152350-10 | G21: 9279SQ1-S001-1L-NB-1 | H21: 9279SQ1-S001-NB | I21: 猫蛋二代 | J21: 5340 | K21: 0 | L21: 12 | M21: =J21/L21 -> 445 | N21: 45656 | O21: 45652 | Q21: PASS | U21: 1/3出 | V21: 箱唛翻单4500144362 | X21: 11/26-韩语贴纸（新稿） + 蛋壳底部彩色圆贴翻4500121660 | AA21: 客版收藏指南（翻单4500144362） | AB21: 日期码格式：ZURU INC(BVI) 标准格式 日期：按实际生产日期 Tracking Code: Packaging Info: （1）9279SQ1的口水胶必须出无硼，无MIT 版本。产品需符合韩国KC测试标准。 （2）9279SQ1: MA PKG(优先1L）+1张韩语贴纸（新稿） + 蛋壳底部按客户要求需加1张彩色圆贴（翻单4500121660），箱唛翻单4500144362；客版收藏指南（翻单4 500144362） Remark: 由于韩国法律法规要求，吸塑需PET材质，产品需符合韩国KC测试标准。 9279SQ1:9279SQ1的口水胶必须出无硼，无MIT 版本 | AC21: Doris Shou | AD21: 2.1849 | AE21: =J21*AD21 -> 11667.366 | AF21: 88826-1.2 | AI21: 5340 | AP21: =J21 -> 5340 | AT21: =J21 -> 5340 | AX21: =J21/6 -> 890 | BK21: MA布标 | BL21: =J21/60*1 -> 89 | BM21: =J21/60*9 -> 801 | BN21: =J21/60*10 -> 890 | BO21: =J21/60*10 -> 890 | BP21: =J21/60*10 -> 890 | BQ21: =J21/60*10 -> 890 | BR21: =J21/60*10 -> 890 | BZ21: =SUM(BL21:BY21) -> 5340 | CA21: =J21-BZ21 -> 0
A22: 45586 | B22: TJX COMPANIES, INC | C22: 美国 | D22: 4500147798 | E22: TJ MAXX DC#891-156PCS , DC#894-132PCS , DC#896-132PCS , DC#897-252PCS , DC#898-132PCS | F22: 4500147798-50 | G22: 92114-S001 | H22: 92114-S001 | I22: 猫蛋二代(9279+9269)组装 | J22: 804 | K22: 0 | L22: 12 | M22: =J22/L22 -> 67 | N22: 45657 | O22: 45653 | Q22: PASS | U22: 1/8出 | V22: 11/4收到 | X22: 无 | Z22: 12-6客供价格贴纸 | AB22: 日期码格式：ZURU INC(BVI) 标准格式 日期：按实际生产日期 Packaging Info: MA UPC包装+价格贴纸，价格贴纸客供。 #92114 是combo pack, 混装了 9269（华康生产）+9279（兴信生产），在兴信组装 。 Remark: 1. 产品和包装上印刷tracking code信息，格式为ZURU常规格式。 2. 分5个DC出货，每款产品每个DC的箱唛资料不同。具体分DC数量，请参考后面行项目备注。 3. ZURU QC验货。 | AC22: Emily Wu | AD22: 2.8218 | AE22: =J22*AD22 -> 2268.7272 | AF22: 94174-1.23 | AG22: 已入 | AI22: =J22 -> 804 | AO22: =J22 -> 804 | AS22: =J22 -> 804 | BH22: =J22 -> 804 | BK22: MA布标 | BM22: =J22/60*9 -> 120.6 | BN22: =J22/60*10 -> 134 | BO22: =J22/60*10 -> 134 | BP22: =J22/60*10 -> 134 | BQ22: =J22/60*10 -> 134 | BR22: =J22/60*10 -> 134 | BS22: =J22/60*1 -> 13.4 | BZ22: =SUM(BL22:BY22) -> 804 | CA22: =J22-BZ22 -> 0
A23: 45586 | B23: TJX COMPANIES, INC | C23: 美国 | D23: 4500147794 | E23: Marshalls DC#881-120PCS , DC#884-96PCS, DC#886-144PCS , DC#887-120PCS , DC#888-120PCS | F23: 4500147794-50 | G23: 92114-S001 | H23: 92114-S001 | I23: 猫蛋二代(9279+9269)组装 | J23: 600 | K23: 0 | L23: 12 | M23: =J23/L23 -> 50 | N23: 45657 | O23: 45653 | Q23: PASS | U23: 1/9出 | V23: 11/4收到 | X23: 无 | Z23: 12-6客供价格贴纸 | AB23: 日期码格式：ZURU INC(BVI) 标准格式 日期：按实际生产日期 Packaging Info: MA UPC包装+价格贴纸，价格贴纸客供。 #92114 是combo pack, 混装了 9269（华康生产）+9279（兴信生产），在兴信组装 。 Remark: 1. 产品和包装上印刷tracking code信息，格式为ZURU常规格式。 2. 分5个DC出货，每款产品每个DC的箱唛资料不同。具体分DC数量，请参考后面行项目备注。 3. ZURU QC验货。 | AC23: Emily Wu | AD23: 2.8218 | AE23: =J23*AD23 -> 1693.08 | AF23: 94176-1.23 | AG23: 已入 | AI23: =J23 -> 600 | AO23: =J23 -> 600 | AS23: =J23 -> 600 | BH23: =J23 -> 600 | BK23: MA布标 | BM23: =J23/60*9 -> 90 | BN23: =J23/60*10 -> 100 | BO23: =J23/60*10 -> 100 | BP23: =J23/60*10 -> 100 | BQ23: =J23/60*10 -> 100 | BR23: =J23/60*10 -> 100 | BS23: =J23/60*1 -> 10 | BZ23: =SUM(BL23:BY23) -> 600 | CA23: =J23-BZ23 -> 0
A24: 45573 | B24: Ansaldo Chile | C24: 智利 | D24: 4500146540 | F24: 4500146540-10 | G24: 9279SQ1-S001 | H24: 9279SQ1-S001 | I24: 猫蛋二代 | J24: 4800 | K24: 0 | L24: 12 | M24: =J24/L24 -> 400 | N24: 45659 | O24: 45654 | Q24: PASS | U24: 1/10出 | V24: 10/15收到 | X24: 进口商贴纸翻PO4500146361 | AB24: 日期码格式：ZURU INC(BVI) 标准格式 日期：按实际生产日期 Packaging Info: 9279SQ1:MA 3L UPC包装+进口商贴纸+箱唛,进口商贴纸翻单PO4500146361 Remark: | AC24: Ava Liang | AD24: 2.2008 | AE24: =J24*AD24 -> 10563.84 | AF24: 88980-1.10 | AK24: =J24 -> 4800 | AO24: =J24 -> 4800 | AS24: =J24 -> 4800 | AX24: =J24/6 -> 800 | BK24: MA布标 | BL24: =J24/60*1 -> 80 | BM24: =J24/60*9 -> 720 | BN24: =J24/60*10 -> 800 | BO24: =J24/60*10 -> 800 | BP24: =J24/60*10 -> 800 | BQ24: =J24/60*10 -> 800 | BR24: =J24/60*10 -> 800 | BZ24: =SUM(BL24:BY24) -> 4800 | CA24: =J24-BZ24 -> 0
A25: 45625 | B25: TJX UK | C25: 英国 | D25: 4500152937 | E25: TJX UK: PO#50343392 | F25: 4500152937-70 | G25: 9279-S001-3L | H25: 9279-S001 | I25: 猫蛋二代 | J25: 1248 | K25: 0 | L25: 24 | M25: =J25/L25 -> 52 | N25: 45660 | O25: 45656 | Q25: PASS | U25: 1/10出 | V25: 12/5收到 | X25: 无 | Z25: 12/6-价格贴纸 | AB25: 日期码格式：ZURU INC(BVI) 标准格式 日期：按实际生产日期 Packaging Info: TJX UK: PO#50343294(9283) <(>&<)> PO#50343296(9258) <(>&<)> PO#50343296(9281) <(>&<)> PO#50343305(9298) <(>&<)> PO#50343349(7132) <(>&<)> PO#503 43349(92107) <(>&<)> PO#50343392(9279) <(>&<)> PO#50343399(9279) 7) 9279: MA 3L(23Lwarning) B版收缩膜+其他最新MA配套包装+1张客供价格贴纸 8) 最迟验货时间不得晚于1/4 Remark: 1. 出往UK的产品+包装务必打上UKCA logo ，否则客人会退货且当地会有罚款； 2. 订单必须经过ZURU QC验货并且通过后方可出货； 3. 订单每行对应客人不同的PO， 箱唛也有不同，做货的时候请分开堆放； 4. 订单每行对应客人不同的PO，即同款item的价格贴纸都不相同，请注意收到贴纸后不要弄混!（客人PO号请参考PO最后一栏remark）； 5. 价格贴纸位置为产品正面右上角，不能遮住产品信息，大货生产前，请把贴纸位置先发给跟单确认 6. 涉及到相关款式会有闪粉的或 者微塑料的，请统一默认出无闪粉或者不含微塑料 版本; 7. 外箱封箱必须是工字型封箱方式； | AC25: Zoe Chen | AD25: 2.1295 | AE25: =J25*AD25 -> 2657.616 | AF25: 88937-1.8 | AK25: =J25 -> 1248 | AO25: 1992 | AS25: =J25 -> 1248 | BK25: MA布标 | BL25: =J25/60*1 -> 20.8 | BM25: =J25/60*9 -> 187.2 | BN25: =J25/60*10 -> 208 | BO25: =J25/60*10 -> 208 | BP25: =J25/60*10 -> 208 | BQ25: =J25/60*10 -> 208 | BR25: =J25/60*10 -> 208 | BZ25: =SUM(BL25:BY25) -> 1248 | CA25: =J25-BZ25 -> 0
A26: 45625 | B26: TJX UK | C26: 英国 | D26: 4500152937 | E26: TJX UK: PO#50343399 | F26: 4500152937-80 | G26: 9279-S001-3L | H26: 9279-S001 | I26: 猫蛋二代 | J26: 1272 | K26: 0 | L26: 24 | M26: =J26/L26 -> 53 | N26: 45660 | O26: 45656 | Q26: PASS | U26: 1/10出 | V26: 12/5收到 | X26: 无 | Z26: 12/6-价格贴纸 | AB26: 日期码格式：ZURU INC(BVI) 标准格式 日期：按实际生产日期 Packaging Info: TJX UK: PO#50343294(9283) <(>&<)> PO#50343296(9258) <(>&<)> PO#50343296(9281) <(>&<)> PO#50343305(9298) <(>&<)> PO#50343349(7132) <(>&<)> PO#503 43349(92107) <(>&<)> PO#50343392(9279) <(>&<)> PO#50343399(9279) 7) 9279: MA 3L(23Lwarning) B版收缩膜+其他最新MA配套包装+1张客供价格贴纸 8) 最迟验货时间不得晚于1/4 Remark: 1. 出往UK的产品+包装务必打上UKCA logo ，否则客人会退货且当地会有罚款； 2. 订单必须经过ZURU QC验货并且通过后方可出货； 3. 订单每行对应客人不同的PO， 箱唛也有不同，做货的时候请分开堆放； 4. 订单每行对应客人不同的PO，即同款item的价格贴纸都不相同，请注意收到贴纸后不要弄混!（客人PO号请参考PO最后一栏remark）； 5. 价格贴纸位置为产品正面右上角，不能遮住产品信息，大货生产前，请把贴纸位置先发给跟单确认 6. 涉及到相关款式会有闪粉的或 者微塑料的，请统一默认出无闪粉或者不含微塑料 版本; 7. 外箱封箱必须是工字型封箱方式； | AC26: Zoe Chen | AD26: 2.1295 | AE26: =J26*AD26 -> 2708.724 | AF26: 88937-1.8 | AK26: =J26 -> 1272 | AO26: 1992 | AS26: =J26 -> 1272 | BK26: MA布标 | BL26: =J26/60*1 -> 21.2 | BM26: =J26/60*9 -> 190.8 | BN26: =J26/60*10 -> 212 | BO26: =J26/60*10 -> 212 | BP26: =J26/60*10 -> 212 | BQ26: =J26/60*10 -> 212 | BR26: =J26/60*10 -> 212 | BZ26: =SUM(BL26:BY26) -> 1272 | CA26: =J26-BZ26 -> 0
A27: 45625 | B27: TJX UK c/o TJX Distribution Ltd & C | C27: 德国 | D27: 4500152906 | E27: TJX Europe(DE): PO#55343844 | F27: 4500152906-100 | G27: 9279-S001-3L | H27: 9279-S001 | I27: 猫蛋二代 | J27: 840 | K27: 0 | L27: 24 | M27: =J27/L27 -> 35 | N27: 45660 | O27: 45656 | Q27: PASS | U27: 1/9出 | V27: 12/5收到 | X27: 无 | Z27: 12/6-价格贴纸 | AB27: 日期码格式：ZURU INC(BVI) 标准格式 日期：按实际生产日期 Packaging Info: TJX Europe(DE): PO#55343895(9283) <(>&<)> PO#55343898(9258) <(>&<)> PO#55343898(9281) <(>&<)> PO#55343901(9281) <(>&<)> PO#55343906(9298) <(>& <)> PO#55343909(9298) <(>&<)> PO#55343918(7132) <(>&<)> PO#55343920(7132) <(>&<)> PO#55343920(92107) <(>&<)> PO#55343844(9279) <(>&<)> PO#553438 77(9279) 7) 9279：MA 3L(23Lwarning) B版收缩膜+其他最新MA配套包装+1张客供价格贴纸 8) 最迟验货时间不得晚于1/4 Remark: 1. 出往UK的产品+包装务必打上UKCA logo ，否则客人会退货且当地会有罚款； 2.订单必须经过ZURU QC验货并且通过后方可出货； 3. 订单每行对应客人不同的PO， 箱唛也有不同，做货的时候请分开堆放； 4. 订单每行对应客人不同的PO，即同款item的价格贴纸都不相同，请注意收到贴纸后不要弄混!（客人PO号请参考PO最后一栏remark）； 5. 价格贴纸位置为产品正面右上角，不能遮住产品信息，大货生产前，请把贴纸位置先发给跟单确认 6. 涉及到相关款式会有闪粉的或者微塑料的，请统一默认出无闪粉或者不含微塑料版本; 7. 外箱封箱必须是工字型封箱方式； | AC27: Zoe Chen | AD27: 2.1295 | AE27: =J27*AD27 -> 1788.78 | AF27: 88936-1.8 | AK27: =J27 -> 840 | AO27: 1992 | AS27: =J27 -> 840 | BK27: MA布标 | BL27: =J27/60*1 -> 14 | BM27: =J27/60*9 -> 126 | BN27: =J27/60*10 -> 140 | BO27: =J27/60*10 -> 140 | BP27: =J27/60*10 -> 140 | BQ27: =J27/60*10 -> 140 | BR27: =J27/60*10 -> 140 | BZ27: =SUM(BL27:BY27) -> 840 | CA27: =J27-BZ27 -> 0
A28: 45625 | B28: TJX UK c/o TJX Distribution Ltd & C | C28: 德国 | D28: 4500152906 | E28: TJX Europe(DE): PO#55343877 | F28: 4500152906-110 | G28: 9279-S001-3L | H28: 9279-S001 | I28: 猫蛋二代 | J28: 864 | K28: 0 | L28: 24 | M28: =J28/L28 -> 36 | N28: 45660 | O28: 45656 | Q28: PASS | U28: 1/9出 | V28: 12/5收到 | X28: 无 | Z28: 12/6-价格贴纸 | AB28: 日期码格式：ZURU INC(BVI) 标准格式 日期：按实际生产日期 Packaging Info: TJX Europe(DE): PO#55343895(9283) <(>&<)> PO#55343898(9258) <(>&<)> PO#55343898(9281) <(>&<)> PO#55343901(9281) <(>&<)> PO#55343906(9298) <(>& <)> PO#55343909(9298) <(>&<)> PO#55343918(7132) <(>&<)> PO#55343920(7132) <(>&<)> PO#55343920(92107) <(>&<)> PO#55343844(9279) <(>&<)> PO#553438 77(9279) 7) 9279：MA 3L(23Lwarning) B版收缩膜+其他最新MA配套包装+1张客供价格贴纸 8) 最迟验货时间不得晚于1/4 Remark: 1. 出往UK的产品+包装务必打上UKCA logo ，否则客人会退货且当地会有罚款； 2.订单必须经过ZURU QC验货并且通过后方可出货； 3. 订单每行对应客人不同的PO， 箱唛也有不同，做货的时候请分开堆放； 4. 订单每行对应客人不同的PO，即同款item的价格贴纸都不相同，请注意收到贴纸后不要弄混!（客人PO号请参考PO最后一栏remark）； 5. 价格贴纸位置为产品正面右上角，不能遮住产品信息，大货生产前，请把贴纸位置先发给跟单确认 6. 涉及到相关款式会有闪粉的或者微塑料的，请统一默认出无闪粉或者不含微塑料版本; 7. 外箱封箱必须是工字型封箱方式； | AC28: Zoe Chen | AD28: 2.1295 | AE28: =J28*AD28 -> 1839.888 | AF28: 88936-1.8 | AK28: =J28 -> 864 | AO28: 1992 | AS28: =J28 -> 864 | BK28: MA布标 | BL28: =J28/60*1 -> 14.4 | BM28: =J28/60*9 -> 129.6 | BN28: =J28/60*10 -> 144 | BO28: =J28/60*10 -> 144 | BP28: =J28/60*10 -> 144 | BQ28: =J28/60*10 -> 144 | BR28: =J28/60*10 -> 144 | BZ28: =SUM(BL28:BY28) -> 864 | CA28: =J28-BZ28 -> 0
A29: 45623 | B29: TJX COMPANIES, INC | C29: 美国 | D29: 4500152574 | E29: Marshalls DC#881-384PCS , DC#884-288PCS , DC#886-408PCS , DC#887-360PCS , DC#888-360PCS | F29: 4500152574-30 | G29: 9279-S001 | H29: 9279-S001 | I29: 猫蛋二代 | J29: 1800 | K29: 0 | L29: 24 | M29: 75 | N29: 45657 | O29: 45653 | Q29: PASS | U29: 1/9出 | V29: 11/27收到 | X29: 无 | Z29: 12-6客供价格贴纸 | AB29: 日期码格式：ZURU INC(BVI) 标准格式 日期：按实际生产日期 Packaging Info: MA UPC包装+价格贴纸，价格贴纸客供。 Remark: 1. 产品和包装上印刷tracking code信息，格式为ZURU常规格式。 2. 分5个DC出货，每款产品每个DC的箱唛资料不同。具体分DC数量，请参考后面行项目备注。 3. ZURU QC验货。 | AC29: Emily Wu | AD29: 2.1295 | AE29: 3833.1 | AF29: 94167-1.23 | AI29: 1800 | AO29: 1800 | AS29: =J29 -> 1800 | BK29: MA布标 | BM29: =J29/60*9 -> 270 | BN29: =J29/60*10 -> 300 | BO29: =J29/60*10 -> 300 | BP29: =J29/60*10 -> 300 | BQ29: =J29/60*10 -> 300 | BR29: =J29/60*10 -> 300 | BS29: =J29/60*1 -> 30 | BZ29: =SUM(BL29:BY29) -> 1800 | CA29: =J29-BZ29 -> 0
A30: 45623 | B30: TJX COMPANIES, INC | C30: 美国 | D30: 4500152572 | E30: Marshalls DC#881-384PCS , DC#884-288PCS , DC#886-408PCS , DC#887-360PCS , DC#888-360PCS | F30: 4500152572-20 | G30: 9279-S001 | H30: 9279-S001 | I30: 猫蛋二代 | J30: 1800 | K30: 0 | L30: 24 | M30: 75 | N30: 45657 | O30: 45653 | Q30: PASS | U30: 1/9出 | V30: 11/27收到 | X30: 无 | Z30: 12-6客供价格贴纸 | AB30: 日期码格式：ZURU INC(BVI) 标准格式 日期：按实际生产日期 Packaging Info: MA UPC包装+价格贴纸，价格贴纸客供。 Remark: 1. 产品和包装上印刷tracking code信息，格式为ZURU常规格式。 2. 分5个DC出货，每款产品每个DC的箱唛资料不同。具体分DC数量，请参考后面行项目备注。 3. ZURU QC验货。 | AC30: Emily Wu | AD30: 2.1295 | AE30: 3833.1 | AF30: 94165-1.23 | AI30: 1800 | AO30: 1800 | AS30: =J30 -> 1800 | BK30: MA布标 | BM30: =J30/60*9 -> 270 | BN30: =J30/60*10 -> 300 | BO30: =J30/60*10 -> 300 | BP30: =J30/60*10 -> 300 | BQ30: =J30/60*10 -> 300 | BR30: =J30/60*10 -> 300 | BS30: =J30/60*1 -> 30 | BZ30: =SUM(BL30:BY30) -> 1800 | CA30: =J30-BZ30 -> 0
A31: 45623 | B31: TJX COMPANIES, INC | C31: 美国 | D31: 4500152573 | E31: TJ MAXX DC#891-408PCS , DC#894-336PCS , DC#896-312PCS , DC#897-624PCS , DC#898-312PCS | F31: 4500152573-20 | G31: 9279-S001 | H31: 9279-S001 | I31: 猫蛋二代 | J31: 1992 | K31: 0 | L31: 24 | M31: 83 | N31: 45657 | O31: 45653 | Q31: PASS | V31: 11/27收到 | X31: 无 | Z31: 12-6客供价格贴纸 | AB31: 日期码格式：ZURU INC(BVI) 标准格式 日期：按实际生产日期 Packaging Info: MA UPC包装+价格贴纸，价格贴纸客供。 Remark: 1. 产品和包装上印刷tracking code信息，格式为ZURU常规格式。 2. 分5个DC出货，每款产品每个DC的箱唛资料不同。具体分DC数量，请参考后面行项目备注。 3. ZURU QC验货。 | AC31: Emily Wu | AD31: 2.1295 | AE31: 4241.964 | AF31: 94173-1.23 | AI31: 1992 | AO31: 1992 | AS31: =J31 -> 1992 | BK31: MA布标 | BM31: =J31/60*9 -> 298.8 | BN31: =J31/60*10 -> 332 | BO31: =J31/60*10 -> 332 | BP31: =J31/60*10 -> 332 | BQ31: =J31/60*10 -> 332 | BR31: =J31/60*10 -> 332 | BS31: =J31/60*1 -> 33.2 | BZ31: =SUM(BL31:BY31) -> 1992 | CA31: =J31-BZ31 -> 0
A32: 45623 | B32: TJX COMPANIES, INC | C32: 美国 | D32: 4500152575 | E32: TJ MAXX DC#891-408PCS , DC#894-336PCS , DC#896-312PCS , DC#897-624PCS , DC#898-312PCS | F32: 4500152575-30 | G32: 9279-S001 | H32: 9279-S001 | I32: 猫蛋二代 | J32: 1992 | K32: 0 | L32: 24 | M32: 83 | N32: 45657 | O32: 45653 | Q32: PASS | V32: 11/27收到 | X32: 无 | Z32: 12-6客供价格贴纸 | AB32: 日期码格式：ZURU INC(BVI) 标准格式 日期：按实际生产日期 Packaging Info: MA UPC包装+价格贴纸，价格贴纸客供。 Remark: 1. 产品和包装上印刷tracking code信息，格式为ZURU常规格式。 2. 分5个DC出货，每款产品每个DC的箱唛资料不同。具体分DC数量，请参考后面行项目备注。 3. ZURU QC验货。 | AC32: Emily Wu | AD32: 2.1295 | AE32: 4241.964 | AF32: 94172-1.23 | AI32: 1992 | AO32: 1992 | AS32: =J32 -> 1992 | BK32: MA布标 | BM32: =J32/60*9 -> 298.8 | BN32: =J32/60*10 -> 332 | BO32: =J32/60*10 -> 332 | BP32: =J32/60*10 -> 332 | BQ32: =J32/60*10 -> 332 | BR32: =J32/60*10 -> 332 | BS32: =J32/60*1 -> 33.2 | BZ32: =SUM(BL32:BY32) -> 1992 | CA32: =J32-BZ32 -> 0
A33: 45624 | B33: «Market Group» LLC | C33: 俄罗斯联邦 | D33: 4500152880 | F33: 4500152880-20 | G33: 9279SQ1-S001-1L | H33: 9279SQ1-S001 | I33: 猫蛋二代 | J33: 4320 | K33: 0 | L33: 12 | M33: =J33/L33 -> 360 | N33: 45657 | O33: 45653 | Q33: PASS | U33: 1/2出 | V33: 11/29收到 | X33: 12/6-进口商贴纸+ EAN条码贴纸 | AB33: 日期码格式：ZURU INC(BVI) 标准格式 日期：按实际生产日期 Packaging Info: 1.9279SQ1 : 1L MA 收缩膜 or 彩卡 + 进口商贴纸+ EAN条码贴纸，MA 指南 /说明书/PDQ 如有; 2. 货期不能延后，客人有罚金。 3. 需要安排3套大货样，请多备料。 Remark: 标准配比 | AC33: Ann Zhang | AD33: 2.2008 | AE33: =J33*AD33 -> 9507.456 | AF33: 88935-1.8 | AI33: =J33 -> 4320 | AO33: =J33 -> 4320 | AS33: =J33 -> 4320 | AX33: =J33/6 -> 720 | BK33: MA布标 | BL33: =J33/60*1 -> 72 | BM33: =J33/60*9 -> 648 | BN33: =J33/60*10 -> 720 | BO33: =J33/60*10 -> 720 | BP33: =J33/60*10 -> 720 | BQ33: =J33/60*10 -> 720 | BR33: =J33/60*10 -> 720 | BZ33: =SUM(BL33:BY33) -> 4320 | CA33: =J33-BZ33 -> 0
A34: 45614 | B34: BURLINGTON COAT FACTORY | C34: 美国 | D34: 4500151472 | E34: 客户PO#383017 502 | F34: 4500151472-10 | G34: 9279-S004 | H34: 9279-S004 | I34: 猫蛋二代 | J34: 3600 | K34: 0 | L34: 6 | M34: =J34/L34 -> 600 | N34: 45663 | O34: 45659 | Q34: PASS | V34: 11/18收到 | X34: 12/13-客供价格贴纸+12/12-外箱贴纸 | AB34: 日期码格式：ZURU INC(BVI) 标准格式 日期：按实际生产日期 Packaging Info: 1，ZURU MA （首选1L）UPC版本+客供价格贴纸+外箱贴纸，出口美国 有PVC桶的价格贴纸贴在PVC桶上面 Remark: 2，产品和包装上印刷ZURU 标准日期码； 3，纸箱中间靠上沿印刷ZURU LOGO，见箱唛资料 4、外箱UCC 条码贴纸，尺寸: 4*6inch，贴在其中一面正唛右下角，贴纸距离外箱底部3.5cm, 侧边距离3.5cm。外箱贴纸由跟单提供电子版, 工厂自行安排，不可用 封箱胶覆盖贴纸条码，贴纸需要可以扫描且无损坏. 5，每个产品有一个价格贴纸， 价格贴纸覆盖UPC条码上 （若UPC 条码太大，可以露出ITEM#, 覆盖条码即可），若价格贴纸覆盖UPC 会挡住文字/图案，在产品背面 找空白处粘贴价格贴纸即可。贴的时候要是会覆盖包装上重要的信息和图案，需要告知跟单。 | AC34: Jessi Xu | AD34: 2.1394 | AE34: =J34*AD34 -> 7701.84 | AF34: 88988-1.11 | AI34: =J34 -> 3600 | AO34: =J34 -> 3600 | AS34: =J34 -> 3600 | BK34: MA布标 | BL34: =J34/60*1 -> 60 | BM34: =J34/60*9 -> 540 | BN34: =J34/60*10 -> 600 | BO34: =J34/60*10 -> 600 | BP34: =J34/60*10 -> 600 | BQ34: =J34/60*10 -> 600 | BR34: =J34/60*10 -> 600 | BZ34: =SUM(BL34:BY34) -> 3600 | CA34: =J34-BZ34 -> 0
A35: 45614 | B35: BURLINGTON COAT FACTORY | C35: 美国 | D35: 4500151472 | E35: 客户PO#383019 402 | F35: 4500151472-60 | G35: 9279-S004 | H35: 9279-S004 | I35: 猫蛋二代 | J35: 6000 | K35: 0 | L35: 6 | M35: =J35/L35 -> 1000 | N35: 45663 | O35: 45659 | Q35: PASS | V35: 11/18收到 | X35: 12/13-客供价格贴纸+12/12-外箱贴纸 | AB35: 日期码格式：ZURU INC(BVI) 标准格式 日期：按实际生产日期 Packaging Info: 1，ZURU MA （首选1L）UPC版本+客供价格贴纸+外箱贴纸，出口美国 有PVC桶的价格贴纸贴在PVC桶上面 Remark: 2，产品和包装上印刷ZURU 标准日期码； 3，纸箱中间靠上沿印刷ZURU LOGO，见箱唛资料 4、外箱UCC 条码贴纸，尺寸: 4*6inch，贴在其中一面正唛右下角，贴纸距离外箱底部3.5cm, 侧边距离3.5cm。外箱贴纸由跟单提供电子版, 工厂自行安排，不可用 封箱胶覆盖贴纸条码，贴纸需要可以扫描且无损坏. 5，每个产品有一个价格贴纸， 价格贴纸覆盖UPC条码上 （若UPC 条码太大，可以露出ITEM#, 覆盖条码即可），若价格贴纸覆盖UPC 会挡住文字/图案，在产品背面 找空白处粘贴价格贴纸即可。贴的时候要是会覆盖包装上重要的信息和图案，需要告知跟单。 | AC35: Jessi Xu | AD35: 2.1291 | AE35: =J35*AD35 -> 12774.6 | AF35: 88981-1.10 | AI35: =J35 -> 6000 | AO35: =J35 -> 6000 | AS35: =J35 -> 6000 | BK35: MA布标 | BL35: =J35/60*1 -> 100 | BM35: =J35/60*9 -> 900 | BN35: =J35/60*10 -> 1000 | BO35: =J35/60*10 -> 1000 | BP35: =J35/60*10 -> 1000 | BQ35: =J35/60*10 -> 1000 | BR35: =J35/60*10 -> 1000 | BZ35: =SUM(BL35:BY35) -> 6000 | CA35: =J35-BZ35 -> 0
A36: 45621 | B36: KMART AUSTRALIA LTD | C36: 澳大利亚 | D36: 4500152292 | E36: 20357441 | F36: 4500152292-30 | G36: 9279SQ1-S002 | H36: 9279SQ1-S002 | I36: 猫蛋二代 | J36: 2040 | K36: 0 | L36: 6 | M36: 340 | N36: 45663 | O36: 45659 | Q36: PASS | U36: 1/8-1/10出 | V36: 12/3收到 | X36: 12/13-防盗贴纸+12/16-外箱贴纸 | AB36: 日期码格式：ZURU INC(BVI) 标准格式 日期：按实际生产日期 Tracking Code: Packaging Info: 9279SQ1: MA英语UPC版本包装（收缩膜和说明书, MA首选1L，如无1L可用多语且含英语的配套多语包装) + 1张防盗贴纸 (贴纸以及位置图翻单PO#4500095104）+ 箱 唛 + 外箱SSCC Label Remark: 1.请务必按时完货，验货。并且按期送货入货代指定仓库，如果晚了导致船期Delay将会有罚金产生或者客户要求空运，所产生的罚金和空运费由工厂承担。 2.SSCC 外箱贴纸请同纸箱瓦楞纸方向（竖纹向）垂直，即外箱贴纸横着贴(注意条码不要被胶带粘住），贴1pc，贴1面正唛，封箱胶纸不能挡住贴纸内容。外箱贴纸 离外箱边距离不少于2cm。 3.外箱材质为ZURU标准； 4.此单需使用KMART封箱胶上下工字型封箱;从2019年6月开始，要用KMART 新版封箱胶带，此单要用"ANKO"封箱胶带 5.此单出口澳大利亚，请按相应的澳新标准生产； 6.产品和包装上生产批号的显示格式ZURU标准日期码格式 7.外箱信息不可手写，重量和体积需要与实际的一致(不可手写） 8. 每款item装箱后的G.W.超过10KG或者CBM超过0.13,(9.5KG或者以上，四舍五入后也属于10KG) 需在外箱上加印超 重或者Bulky LOGO，若发现我们资料没有，请 帮忙提醒 1)重量超过10kg但不超过16kg且CBM不超过0.13,10-16kg 超重logo 2）CBM超过0.13且重量少于17kg，bulky logo 3）不属于以上两种情况，需要使用相应重量范围内的超重logo 4）超重logo需要在外箱四面都印刷(箱唛右上角，两面侧唛超重logo需要尽量靠近毛重)，尺寸为:110mm height* 95mm width 9. 实际外箱重量跟印在箱唛上的数据差异不能超3%，尺寸按实际数据印刷 | AC36: Lydia Wu | AD36: 2.3594 | AE36: 4813.176 | AF36: 88993-1.11 | AI36: 2040 | AO36: 2040 | AS36: =J36 -> 2040 | AX36: 340 | BK36: MA布标 | BL36: =J36/60*1 -> 34 | BM36: =J36/60*9 -> 306 | BN36: =J36/60*10 -> 340 | BO36: =J36/60*10 -> 340 | BP36: =J36/60*10 -> 340 | BQ36: =J36/60*10 -> 340 | BR36: =J36/60*10 -> 340 | BZ36: =SUM(BL36:BY36) -> 2040 | CA36: =J36-BZ36 -> 0
A37: 45621 | B37: SUCKOT SAC | C37: 秘鲁 | D37: 4500152261 | F37: 4500152261-10 | G37: 9279SQ1-S001 | H37: 9279SQ1-S001 | I37: 猫蛋二代 | J37: 6000 | K37: 0 | L37: 12 | M37: =J37/L37 -> 500 | N37: 45663 | O37: 45659 | Q37: PASS | U37: 1/6出 | V37: 11/26收到 | X37: 12/19-进口商贴纸 | AB37: 日期码格式：ZURU INC(BVI) 标准格式 日期：按实际生产日期 Packaging Info: 9279SQ1：MA 3L UPC包装+MA PDQ包装+MA 多语收藏指南+进口商贴纸+箱唛 Remark: 9279SQ1: 7 assortment (6 common + 1 rare); RAGDOLL CA (RARE): AMERICAN SHORTHAIR: CALICO CAT: BLACK CAT: BENGAL CAT: EXOTIC CAT: CHINCHILLA CAT= 1:9:10:10:10: 10:10; 出货前要提供大货照片给客户确认后才能出货，请按期完货 | AC37: Zoe Luo | AD37: 2.1849 | AE37: =J37*AD37 -> 13109.4 | AF37: 88921-1.7 | AK37: =J37 -> 6000 | AO37: =J37 -> 6000 | AS37: =J37 -> 6000 | AX37: =J37/6 -> 1000 | BK37: MA布标 | BL37: =J37/60*1 -> 100 | BM37: =J37/60*9 -> 900 | BN37: =J37/60*10 -> 1000 | BO37: =J37/60*10 -> 1000 | BP37: =J37/60*10 -> 1000 | BQ37: =J37/60*10 -> 1000 | BR37: =J37/60*10 -> 1000 | BZ37: =SUM(BL37:BY37) -> 6000 | CA37: =J37-BZ37 -> 0
A38: 45622 | B38: MCD BRANDS SAS | C38: 乌拉圭 | D38: 4500152326 | F38: 4500152326-10 | G38: 9279SQ1-S001 | H38: 9279SQ1-S001 | I38: 猫蛋二代 | J38: 360 | K38: 0 | L38: 12 | M38: =J38/L38 -> 30 | N38: 45663 | O38: 45659 | Q38: PASS | U38: 1/9出 | V38: 箱唛翻4500123283 | X38: 进口商贴纸/EAN贴纸翻4500123283 | AB38: 日期码格式：ZURU INC(BVI) 标准格式 日期：按实际生产日期 Packaging Info:9279SQ1:MA 3L包装+进口商贴纸+箱唛 +EAN贴纸，进口商贴纸/箱唛/EAN贴纸翻单PO4500123283 Remark: 进口商贴纸请多备料5pcs,出货后需要寄给客户 | AC38: Ava Liang | AD38: 2.209 | AE38: =J38*AD38 -> 795.24 | AF38: 88941-1.8 | AK38: =J38 -> 360 | AO38: =J38 -> 360 | AS38: =J38 -> 360 | AX38: =J38/6 -> 60 | BK38: MA布标 | BL38: =J38/60*1 -> 6 | BM38: =J38/60*9 -> 54 | BN38: =J38/60*10 -> 60 | BO38: =J38/60*10 -> 60 | BP38: =J38/60*10 -> 60 | BQ38: =J38/60*10 -> 60 | BR38: =J38/60*10 -> 60 | BZ38: =SUM(BL38:BY38) -> 360 | CA38: =J38-BZ38 -> 0
A39: 45623 | B39: AMAZON.COM.DEDC,LLC | C39: 美国 | D39: 4500152657 | E39: 6O9PKONI | F39: 4500152657-80 | G39: 9279G-S001 | H39: 9279G-S001 | I39: 猫蛋二代 | J39: 168 | K39: 0 | L39: 12 | M39: 14 | N39: 45664 | O39: 45660 | Q39: PASS | U39: 2/13出 | V39: 11/27收到 | X39: UPC贴纸翻4500097545 | Z39: 12/20-外箱贴纸 | AB39: 日期码格式： 标准格式 日期：按实际生产日期 Packaging Info: #9279：MA 1L 加UPC贴纸, UPC贴纸图稿跟返单4500097545.9279G: 193052054753 Remark: 1. Amazon FOB订单，出口US。 2. 日期码使用ZURU标准版本。 3. 如果大货有要求入邮包盒，则对应的邮包盒上面要打上日期码。 4. 箱尺寸要求：外箱最长边不能超过25" （超过了，case pack只能为1），不符合要求的大货，一律不接受。 5. 外箱箱唛要求： ①外箱正面印ZURU Logo+SSCC Label（客供贴纸，由跟单订购)。关于 SSCC Label 请注意： SSCC Label 显示的是客人自己的item#。每一张SSCC label 都是唯一且有不同流水及条码的，没有损耗，绝对不可贴错 。如果贴错或损坏任何一张，都会导致全 部都错，千万要注意！ SSCC Label 必须贴在外箱正面的正中间位置（贴一面即可），并且贴纸离外箱边距必须至少3cm(可以覆盖Logo<(>&<)>箱唛)，否则会影响到客户那边仓库的扫描识 别。 ②外箱侧面印item#（订单上显示的SKU#)+carton size(以工厂实际尺寸为准,单位: inch) +MADE IN CHINA,日期使用ZURU 标准版本。 6. 装柜要求：按照客户PO# 装柜/箱号顺序装柜，跟单会提前给到装柜计划。 在大货生产/仓库存放时，请留意该装柜要求，以便装柜时不混乱（避免装错/装漏/找不到货号等）。 | AC39: Kelly Shen | AD39: 2.139 | AE39: 359.352 | AF39: 94229-2.12 | AI39: 168 | AO39: 168 | AS39: =J39 -> 168 | BK39: MA布标 | BO39: =J39 -> 168 | BZ39: =SUM(BL39:BY39) -> 168 | CA39: =J39-BZ39 -> 0
A40: 45623 | B40: AMAZON.COM.DEDC,LLC | C40: 美国 | D40: 4500152657 | E40: 2CNPFRXG | F40: 4500152657-90 | G40: 9279H-S001 | H40: 9279H-S001 | I40: 猫蛋二代 | J40: 216 | K40: 0 | L40: 12 | M40: 18 | N40: 45664 | O40: 45660 | Q40: PASS | U40: 2/13出 | V40: 11/27收到 | X40: UPC贴纸翻4500097545 | Z40: 12/20-外箱贴纸 | AB40: 日期码格式： 标准格式 日期：按实际生产日期 Packaging Info: #9279：MA 1L 加UPC贴纸, UPC贴纸图稿跟返单4500097545.9279H: 193052054760. Remark: 1. Amazon FOB订单，出口US。 2. 日期码使用ZURU标准版本。 3. 如果大货有要求入邮包盒，则对应的邮包盒上面要打上日期码。 4. 箱尺寸要求：外箱最长边不能超过25" （超过了，case pack只能为1），不符合要求的大货，一律不接受。 5. 外箱箱唛要求： ①外箱正面印ZURU Logo+SSCC Label（客供贴纸，由跟单订购)。关于 SSCC Label 请注意： SSCC Label 显示的是客人自己的item#。每一张SSCC label 都是唯一且有不同流水及条码的，没有损耗，绝对不可贴错 。如果贴错或损坏任何一张，都会导致全部都错，千万要注意！ SSCC Label 必须贴在外箱正面的正中间位置（贴一面即可），并且贴纸离外箱边距必须至少3cm(可以覆盖Logo<(>&<)>箱唛)，否则会影响到客户那边仓库的扫描识别。 ②外箱侧面印item#（订单上显示的SKU#)+carton size(以工厂实际尺寸为准,单位: inch) +MADE IN CHINA,日期使用ZURU 标准版本。 6. 装柜要求：按照客户PO# 装柜/箱号顺序装柜，跟单会提前给到装柜计划。 在大货生产/仓库存放时，请留意该装柜要求，以便装柜时不混乱（避免装错/装漏/找不到货号等）。 | AC40: Kelly Shen | AD40: 2.139 | AE40: 462.024 | AF40: 94229-2.12 | AI40: 216 | AO40: 216 | AS40: =J40 -> 216 | BK40: MA布标 | BR40: =J40 -> 216 | BZ40: =SUM(BL40:BY40) -> 216 | CA40: =J40-BZ40 -> 0
A41: 45623 | B41: AMAZON.COM.DEDC,LLC | C41: 美国 | D41: 4500152379 | E41: 3RGN6C4F | F41: 4500152379-280 | G41: 9279G-S001 | H41: 9279G-S001 | I41: 猫蛋二代 | J41: 48 | K41: 0 | L41: 12 | M41: 4 | N41: 45664 | O41: 45660 | Q41: PASS | U41: 2/7出 | V41: 11/27收到 | X41: UPC贴纸翻4500097545 | Z41: 12/20-外箱贴纸 | AB41: 日期码格式： 标准格式 日期：按实际生产日期 Packaging Info: #9279：MA 1L 加UPC贴纸, UPC贴纸图稿跟返单4500097545.9279G: 193052054753, 9279H: 193052054760. Remark: 1. Amazon FOB订单，出口US。 2. 日期码使用ZURU标准版本。 3. 如果大货有要求入邮包盒，则对应的邮包盒上面要打上日期码。 4. 箱尺寸要求：外箱最长边不能超过25" （超过了，case pack只能为1），不符合要求的大货，一律不接受。 5. 外箱箱唛要求： ①外箱正面印ZURU Logo+SSCC Label（客供贴纸，由跟单订购)。关于 SSCC Label 请注意： SSCC Label 显示的是客人自己的item#。每一张SSCC label 都是唯一且有不同流水及条码的，没有损耗，绝对不可贴错 。如果贴错或损坏任何一张，都会导致全 部都错，千万要注意！ SSCC Label 必须贴在外箱正面的正中间位置（贴一面即可），并且贴纸离外箱边距必须至少3cm(可以覆盖Logo<(>&<)>箱唛)，否则会影响到客户那边仓库的扫描识 别。 ②外箱侧面印item#（订单上显示的SKU#)+carton size(以工厂实际尺寸为准,单位: inch) +MADE IN CHINA,日期使用ZURU 标准版本。 6. 装柜要求：按照客户PO# 装柜/箱号顺序装柜，跟单会提前给到装柜计划。 在大货生产/仓库存放时，请留意该装柜要求，以便装柜时不混乱（避免装错/装漏/找不到货号等）。 | AC41: Kelly Shen | AD41: 2.139 | AE41: 102.672 | AF41: 94201-2.10 | AI41: 48 | AO41: 48 | AS41: =J41 -> 48 | BK41: MA布标 | BO41: =J41 -> 48 | BZ41: =SUM(BL41:BY41) -> 48 | CA41: =J41-BZ41 -> 0
A42: 45623 | B42: AMAZON.COM.DEDC,LLC | C42: 美国 | D42: 4500152379 | E42: 5VQT2Y9T | F42: 4500152379-290 | G42: 9279G-S001 | H42: 9279G-S001 | I42: 猫蛋二代 | J42: 12 | K42: 0 | L42: 12 | M42: 1 | N42: 45664 | O42: 45660 | Q42: PASS | U42: 2/7出 | V42: 11/27收到 | X42: UPC贴纸翻4500097545 | Z42: 12/20-外箱贴纸 | AB42: 日期码格式： 标准格式 日期：按实际生产日期 Packaging Info: #9279：MA 1L 加UPC贴纸, UPC贴纸图稿跟返单4500097545.9279G: 193052054753, 9279H: 193052054760. Remark: 1. Amazon FOB订单，出口US。 2. 日期码使用ZURU标准版本。 3. 如果大货有要求入邮包盒，则对应的邮包盒上面要打上日期码。 4. 箱尺寸要求：外箱最长边不能超过25" （超过了，case pack只能为1），不符合要求的大货，一律不接受。 5. 外箱箱唛要求： ①外箱正面印ZURU Logo+SSCC Label（客供贴纸，由跟单订购)。关于 SSCC Label 请注意： SSCC Label 显示的是客人自己的item#。每一张SSCC label 都是唯一且有不同流水及条码的，没有损耗，绝对不可贴错 。如果贴错或损坏任何一张，都会导致全 部都错，千万要注意！ SSCC Label 必须贴在外箱正面的正中间位置（贴一面即可），并且贴纸离外箱边距必须至少3cm(可以覆盖Logo<(>&<)>箱唛)，否则会影响到客户那边仓库的扫描识 别。 ②外箱侧面印item#（订单上显示的SKU#)+carton size(以工厂实际尺寸为准,单位: inch) +MADE IN CHINA,日期使用ZURU 标准版本。 6. 装柜要求：按照客户PO# 装柜/箱号顺序装柜，跟单会提前给到装柜计划。 在大货生产/仓库存放时，请留意该装柜要求，以便装柜时不混乱（避免装错/装漏/找不到货号等）。 | AC42: Kelly Shen | AD42: 2.139 | AE42: 25.668 | AF42: 94201-2.10 | AI42: 12 | AO42: 12 | AS42: =J42 -> 12 | BK42: MA布标 | BO42: =J42 -> 12 | BZ42: =SUM(BL42:BY42) -> 12 | CA42: =J42-BZ42 -> 0
A43: 45623 | B43: AMAZON.COM.DEDC,LLC | C43: 美国 | D43: 4500152379 | E43: 2PWSSCEK | F43: 4500152379-300 | G43: 9279G-S001 | H43: 9279G-S001 | I43: 猫蛋二代 | J43: 84 | K43: 0 | L43: 12 | M43: 7 | N43: 45664 | O43: 45660 | Q43: PASS | U43: 2/7出 | V43: 11/27收到 | X43: UPC贴纸翻4500097545 | Z43: 12/20-外箱贴纸 | AB43: 日期码格式： 标准格式 日期：按实际生产日期 Packaging Info: #9279：MA 1L 加UPC贴纸, UPC贴纸图稿跟返单4500097545.9279G: 193052054753, 9279H: 193052054760. Remark: 1. Amazon FOB订单，出口US。 2. 日期码使用ZURU标准版本。 3. 如果大货有要求入邮包盒，则对应的邮包盒上面要打上日期码。 4. 箱尺寸要求：外箱最长边不能超过25" （超过了，case pack只能为1），不符合要求的大货，一律不接受。 5. 外箱箱唛要求： ①外箱正面印ZURU Logo+SSCC Label（客供贴纸，由跟单订购)。关于 SSCC Label 请注意： SSCC Label 显示的是客人自己的item#。每一张SSCC label 都是唯一且有不同流水及条码的，没有损耗，绝对不可贴错 。如果贴错或损坏任何一张，都会导致全 部都错，千万要注意！ SSCC Label 必须贴在外箱正面的正中间位置（贴一面即可），并且贴纸离外箱边距必须至少3cm(可以覆盖Logo<(>&<)>箱唛)，否则会影响到客户那边仓库的扫描识 别。 ②外箱侧面印item#（订单上显示的SKU#)+carton size(以工厂实际尺寸为准,单位: inch) +MADE IN CHINA,日期使用ZURU 标准版本。 6. 装柜要求：按照客户PO# 装柜/箱号顺序装柜，跟单会提前给到装柜计划。 在大货生产/仓库存放时，请留意该装柜要求，以便装柜时不混乱（避免装错/装漏/找不到货号等）。 | AC43: Kelly Shen | AD43: 2.139 | AE43: 179.676 | AF43: 94201-2.10 | AI43: 84 | AO43: 84 | AS43: =J43 -> 84 | BK43: MA布标 | BO43: =J43 -> 84 | BZ43: =SUM(BL43:BY43) -> 84 | CA43: =J43-BZ43 -> 0
A44: 45623 | B44: AMAZON.COM.DEDC,LLC | C44: 美国 | D44: 4500152379 | E44: 5F9F42TO | F44: 4500152379-310 | G44: 9279H-S001 | H44: 9279H-S001 | I44: 猫蛋二代 | J44: 12 | K44: 0 | L44: 12 | M44: 1 | N44: 45664 | O44: 45660 | Q44: PASS | U44: 2/7出 | V44: 11/27收到 | X44: UPC贴纸翻4500097545 | Z44: 12/20-外箱贴纸 | AB44: 日期码格式： 标准格式 日期：按实际生产日期 Packaging Info: #9279：MA 1L 加UPC贴纸, UPC贴纸图稿跟返单4500097545.9279G: 193052054753, 9279H: 193052054760. Remark: 1. Amazon FOB订单，出口US。 2. 日期码使用ZURU标准版本。 3. 如果大货有要求入邮包盒，则对应的邮包盒上面要打上日期码。 4. 箱尺寸要求：外箱最长边不能超过25" （超过了，case pack只能为1），不符合要求的大货，一律不接受。 5. 外箱箱唛要求： ①外箱正面印ZURU Logo+SSCC Label（客供贴纸，由跟单订购)。关于 SSCC Label 请注意： SSCC Label 显示的是客人自己的item#。每一张SSCC label 都是唯一且有不同流水及条码的，没有损耗，绝对不可贴错 。如果贴错或损坏任何一张，都会导致全 部都错，千万要注意！ SSCC Label 必须贴在外箱正面的正中间位置（贴一面即可），并且贴纸离外箱边距必须至少3cm(可以覆盖Logo<(>&<)>箱唛)，否则会影响到客户那边仓库的扫描识 别。 ②外箱侧面印item#（订单上显示的SKU#)+carton size(以工厂实际尺寸为准,单位: inch) +MADE IN CHINA,日期使用ZURU 标准版本。 6. 装柜要求：按照客户PO# 装柜/箱号顺序装柜，跟单会提前给到装柜计划。 在大货生产/仓库存放时，请留意该装柜要求，以便装柜时不混乱（避免装错/装漏/找不到货号等）。 | AC44: Kelly Shen | AD44: 2.139 | AE44: 25.668 | AF44: 94201-2.10 | AI44: 12 | AO44: 12 | AS44: =J44 -> 12 | BK44: MA布标 | BR44: =J44 -> 12 | BZ44: =SUM(BL44:BY44) -> 12 | CA44: =J44-BZ44 -> 0
A45: 45623 | B45: AMAZON.COM.DEDC,LLC | C45: 美国 | D45: 4500152379 | E45: 34MYNFWB | F45: 4500152379-320 | G45: 9279H-S001 | H45: 9279H-S001 | I45: 猫蛋二代 | J45: 156 | K45: 0 | L45: 12 | M45: 13 | N45: 45664 | O45: 45660 | Q45: PASS | U45: 2/7出 | V45: 11/27收到 | X45: UPC贴纸翻4500097545 | Z45: 12/20-外箱贴纸 | AB45: 日期码格式： 标准格式 日期：按实际生产日期 Packaging Info: #9279：MA 1L 加UPC贴纸, UPC贴纸图稿跟返单4500097545.9279G: 193052054753, 9279H: 193052054760. Remark: 1. Amazon FOB订单，出口US。 2. 日期码使用ZURU标准版本。 3. 如果大货有要求入邮包盒，则对应的邮包盒上面要打上日期码。 4. 箱尺寸要求：外箱最长边不能超过25" （超过了，case pack只能为1），不符合要求的大货，一律不接受。 5. 外箱箱唛要求： ①外箱正面印ZURU Logo+SSCC Label（客供贴纸，由跟单订购)。关于 SSCC Label 请注意： SSCC Label 显示的是客人自己的item#。每一张SSCC label 都是唯一且有不同流水及条码的，没有损耗，绝对不可贴错 。如果贴错或损坏任何一张，都会导致全 部都错，千万要注意！ SSCC Label 必须贴在外箱正面的正中间位置（贴一面即可），并且贴纸离外箱边距必须至少3cm(可以覆盖Logo<(>&<)>箱唛)，否则会影响到客户那边仓库的扫描识 别。 ②外箱侧面印item#（订单上显示的SKU#)+carton size(以工厂实际尺寸为准,单位: inch) +MADE IN CHINA,日期使用ZURU 标准版本。 6. 装柜要求：按照客户PO# 装柜/箱号顺序装柜，跟单会提前给到装柜计划。 在大货生产/仓库存放时，请留意该装柜要求，以便装柜时不混乱（避免装错/装漏/找不到货号等）。 | AC45: Kelly Shen | AD45: 2.139 | AE45: 333.684 | AF45: 94201-2.10 | AI45: 156 | AO45: 156 | AS45: =J45 -> 156 | BK45: MA布标 | BR45: =J45 -> 156 | BZ45: =SUM(BL45:BY45) -> 156 | CA45: =J45-BZ45 -> 0
A46: 45623 | B46: AMAZON.COM.DEDC,LLC | C46: 美国 | D46: 4500152379 | E46: 3TBERFYU | F46: 4500152379-330 | G46: 9279H-S001 | H46: 9279H-S001 | I46: 猫蛋二代 | J46: 132 | K46: 0 | L46: 12 | M46: 11 | N46: 45664 | O46: 45660 | Q46: PASS | U46: 2/7出 | V46: 11/27收到 | X46: UPC贴纸翻4500097545 | Z46: 12/20-外箱贴纸 | AB46: 日期码格式： 标准格式 日期：按实际生产日期 Packaging Info: #9279：MA 1L 加UPC贴纸, UPC贴纸图稿跟返单4500097545.9279G: 193052054753, 9279H: 193052054760. Remark: 1. Amazon FOB订单，出口US。 2. 日期码使用ZURU标准版本。 3. 如果大货有要求入邮包盒，则对应的邮包盒上面要打上日期码。 4. 箱尺寸要求：外箱最长边不能超过25" （超过了，case pack只能为1），不符合要求的大货，一律不接受。 5. 外箱箱唛要求： ①外箱正面印ZURU Logo+SSCC Label（客供贴纸，由跟单订购)。关于 SSCC Label 请注意： SSCC Label 显示的是客人自己的item#。每一张SSCC label 都是唯一且有不同流水及条码的，没有损耗，绝对不可贴错 。如果贴错或损坏任何一张，都会导致全 部都错，千万要注意！ SSCC Label 必须贴在外箱正面的正中间位置（贴一面即可），并且贴纸离外箱边距必须至少3cm(可以覆盖Logo<(>&<)>箱唛)，否则会影响到客户那边仓库的扫描识 别。 ②外箱侧面印item#（订单上显示的SKU#)+carton size(以工厂实际尺寸为准,单位: inch) +MADE IN CHINA,日期使用ZURU 标准版本。 6. 装柜要求：按照客户PO# 装柜/箱号顺序装柜，跟单会提前给到装柜计划。 在大货生产/仓库存放时，请留意该装柜要求，以便装柜时不混乱（避免装错/装漏/找不到货号等）。 | AC46: Kelly Shen | AD46: 2.139 | AE46: 282.348 | AF46: 94201-2.10 | AI46: 132 | AO46: 132 | AS46: =J46 -> 132 | BK46: MA布标 | BR46: =J46 -> 132 | BZ46: =SUM(BL46:BY46) -> 132 | CA46: =J46-BZ46 -> 0
A47: 45621 | B47: ATLAS AMBASSADOR | C47: 摩洛哥 | D47: 4500152205 | F47: 4500152205-40 | G47: 9279SQ1-S001-1L | H47: 9279SQ1-S001 | I47: 猫蛋二代 | J47: 504 | K47: 0 | L47: 12 | M47: =J47/L47 -> 42 | N47: 45667 | O47: 45663 | Q47: PASS | U47: 1/15出 | V47: 11/25收到 | X47: 12/11-进口商贴纸 | AB47: 日期码格式：ZURU INC(BVI) 标准格式 日期：按实际生产日期 Packaging Info: 9279SQ1:1L MA收缩膜+进口商贴纸;MA指南;MA PDQ 2.此客户需要进行COC认证，装柜前在主拼工厂会有第三方验货，每款item需备2pcs 验货备品。 Remark: 标准产品标准配比 | AC47: Lena Huang | AD47: 2.209 | AE47: =J47*AD47 -> 1113.336 | AF47: 94106-1.18 | AI47: =J47 -> 504 | AO47: =J47 -> 504 | AS47: =J47 -> 504 | AX47: =J47/6 -> 84 | BK47: MA布标 | BL47: =J47/60*1 -> 8.4 | BM47: =J47/60*9 -> 75.6 | BN47: =J47/60*10 -> 84 | BO47: =J47/60*10 -> 84 | BP47: =J47/60*10 -> 84 | BQ47: =J47/60*10 -> 84 | BR47: =J47/60*10 -> 84 | BZ47: =SUM(BL47:BY47) -> 504 | CA47: =J47-BZ47 -> 0
A48: 45631 | B48: Ambiental Paraguay | C48: 巴拉圭 | D48: 4500153347 | F48: 4500153347-30 | G48: 9279SQ1-S001-1L | H48: 9279SQ1-S001 | I48: 猫蛋二代 | J48: 1008 | K48: 0 | L48: 12 | M48: =J48/L48 -> 84 | N48: 45667 | O48: 45663 | Q48: PASS | U48: 1/11出 | V48: 12/5收到 | X48: 12/5-进口商贴纸 | AB48: 日期码格式：ZURU INC(BVI) 标准格式 日期：按实际生产日期 Packaging Info: 9279SQ1:MA 1LUPC 包装+进口商贴纸+箱唛，进口商贴纸贴于位置"B" | AC48: Ava Liang | AD48: 2.2044 | AE48: 282.348 | AF48: 94049-1.15 | AI48: 132 | AO48: 132 | AS48: =J48 -> 1008 | AX48: =J48/6 -> 168 | BK48: MA布标 | BL48: =J48/60*1 -> 16.8 | BM48: =J48/60*9 -> 151.2 | BN48: =J48/60*10 -> 168 | BO48: =J48/60*10 -> 168 | BP48: =J48/60*10 -> 168 | BQ48: =J48/60*10 -> 168 | BR48: =J48/60*10 -> 168 | BZ48: =SUM(BL48:BY48) -> 1008 | CA48: =J48-BZ48 -> 0
A49: 45631 | B49: Prénatal Retail Group Asia Pacific | C49: 意大利 | D49: 4500153302 | E49: 2000006814 | F49: 4500153302-30 | G49: 9279SQ1-S001-3L-NB | H49: 9279SQ1-S001-NB | I49: 猫蛋二代 | J49: 1404 | K49: 0 | L49: 12 | M49: =J49/L49 -> 117 | N49: 45672 | O49: 45668 | P49: 1/17第三方 | Q49: PASS | U49: 1/24出 | V49: 12/11收到 | X49: 12/27-EAN条码贴纸+1*进口商贴纸+1*产品贴纸 | AA49: LOT2503 | AB49: 日期码格式：LOT2503 日期：按实际生产日期 Packaging Info: 9279:最新MA 5L收藏指南+最新MA PDQ+最新 MA 3L收缩膜+最新MA 布标+最新MA 5L SLIME胶带+最新MA 贴纸+一张EAN条码贴纸+1*进口商贴纸+1*产品贴纸 Remark: 1.RATIO 同MA 一致。 2.大货样品2套/item，用于客人验货签板。验货后还会抽办1套/item，请多备料。 3.客人日期码：LOT2503，产品/包装/外箱 请保持一致,无须ZURU日期码 4.产品均符合EU微塑料法规要求：不能含有微塑料/闪粉 5. SMASHERS 或含Slime产品，所有化合物使用无硼版本出意大利。 6. 本订单所有 具有 baby items / assorted items 的款式，零售包装上都要用 母 EAN; 7，此客户需要第三方验货，请在约三方验货前必须PASS ZURU验货。 | AC49: Jade Wang | AD49: 2.1378 | AE49: =J49*AD49 -> 3001.4712 | AF49: 94151-1.22 | AK49: =J49 -> 1404 | AO49: =J49 -> 1404 | AT49: =J49 -> 1404 | AX49: =J49/6 -> 234 | BK49: MA布标 | BL49: =J49/60*1 -> 23.4 | BM49: =J49/60*9 -> 210.6 | BN49: =J49/60*10 -> 234 | BO49: =J49/60*10 -> 234 | BP49: =J49/60*10 -> 234 | BQ49: =J49/60*10 -> 234 | BR49: =J49/60*10 -> 234 | BZ49: =SUM(BL49:BY49) -> 1404 | CA49: =J49-BZ49 -> 0
A50: 45637 | B50: Centro Atacadista Barão Ltda | C50: 巴西 | D50: 4500153685 | F50: 4500153685-10 | G50: 9279SQ1-S001-1L | H50: 9279SQ1-S001 | I50: 猫蛋二代 | J50: 8016 | K50: 0 | L50: 12 | M50: =J50/L50 -> 668 | N50: 45304 | O50: 45666 | Q50: PASS | U50: 1/13出 | V50: 12/11收到 | X50: 12/13-进口商贴纸 | AB50: 日期码格式：ZURU INC(BVI) 标准格式 日期：按实际生产日期 Packaging Info: MA 1L包装+进口商贴纸+箱唛 Remark: | AC50: Ava Liang | AD50: 2.1849 | AE50: =J50*AD50 -> 17514.158 | AF50: 94036-1.15 | AI50: 132 | AO50: =J50 -> 8016 | AS50: =J50 -> 8016 | AX50: =J50/6 -> 1336 | BK50: MA布标 | BL50: =J50/60*1 -> 133.6 | BM50: =J50/60*9 -> 1202.4 | BN50: =J50/60*10 -> 1336 | BO50: =J50/60*10 -> 1336 | BP50: =J50/60*10 -> 1336 | BQ50: =J50/60*10 -> 1336 | BR50: =J50/60*10 -> 1336 | BZ50: =SUM(BL50:BY50) -> 8016 | CA50: =J50-BZ50 -> 0
A51: 45603 | B51: DD’S DISCOUNTS | C51: 美国 | D51: 4500150317 | E51: 70054070 | F51: 4500150317-20 | G51: 9279-S001 | H51: 9279-S001 | I51: 猫蛋二代 | J51: 504 | K51: 0 | L51: 24 | M51: =J51/L51 -> 21 | N51: 45670 | O51: 45666 | Q51: PASS | U51: 1/20出 | V51: 指定箱唛格式 | X51: 无 | Z51: 12/2-客供价格贴纸 | AB51: 日期码格式： 标准格式 日期：按实际生产日期 Packaging Info: 1.ZURU MA UPC 现有版本包装 + 客供价格贴纸，出口美国 , 优先使用MA 1L 最新版本 。 Remark: 1.ZURU MA UPC 现有版本包装 + 客供价格贴纸，出口美国 , 优先使用MA 1L 最新版本 。 2.价格贴纸位于包装正面右下角，不挡住重要信息即可，可适当调整 ，价格贴纸由跟单提供。 3.标准日期码格式，产品和包装必须有日期码 。 4.同个产品同个货期不可出现不同的包装。 5. 跟单提供ROSS通用的箱唛模版，工厂按实际45 PO上客户PO/Item号/装箱数 提供箱唛排版来确认 | AC51: Taylor Liao | AD51: 2.1341 | AE51: =J51*AD51 -> 1075.5864 | AF51: 94129-1.21 | AI51: =J51 -> 504 | AO51: =J51 -> 504 | AS51: =J51 -> 504 | BK51: MA布标 | BL51: =J51/60*1 -> 8.4 | BM51: =J51/60*9 -> 75.6 | BN51: =J51/60*10 -> 84 | BO51: =J51/60*10 -> 84 | BP51: =J51/60*10 -> 84 | BQ51: =J51/60*10 -> 84 | BR51: =J51/60*10 -> 84 | BZ51: =SUM(BL51:BY51) -> 504 | CA51: =J51-BZ51 -> 0
A52: 45610 | B52: RIALTO SPA | C52: 意大利 | D52: 4500151283 | E52: 9412 | F52: 4500151283-10 | G52: 9279F-S001-NB-3L | H52: 9279F-S001-NB | I52: 猫蛋二代 展示架（无闪粉） | J52: 800 | K52: 0 | L52: 40 | M52: =J52/L52 -> 20 | N52: 45672 | O52: 45668 | Q52: PASS | U52: 1/20出 | V52: 11/15收到 | X52: 12/2-EAN label +意大利sorting logo含进口商地址 | AB52: 日期码格式：ZURU INC(BVI) 标准格式 日期：按实际生产日期 Packaging Info: 9279F MA B 3L+23L 收缩膜（+1*EAN label +1*意大利sorting logo含进口商地址）+MA C 5L POOP BAG+MA C 5L 收藏指南+其他MA 物料 Remark: 1. 此单出意大利，需符合EU标准，不含微塑料，如果含slime等化学品，需要不含硼 2. 需保证按期1/15前完货，延期罚款 3.贴纸切勿盖住意大利警告语 | AC52: Amy Xiao | AD52: 23.3446 | AE52: =M52*AD52 -> 466.892 | AF52: 94089-1.18 | AK52: =J52 -> 800 | AO52: =J52 -> 800 | AT52: =J52 -> 800 | BG52: =J52/40 -> 20 | BK52: MA布标 | BL52: =J52/60*1 -> 13.333333 | BM52: =J52/60*9 -> 120 | BN52: =J52/60*10 -> 133.33333 | BO52: =J52/60*10 -> 133.33333 | BP52: =J52/60*10 -> 133.33333 | BQ52: =J52/60*10 -> 133.33333 | BR52: =J52/60*10 -> 133.33333 | BZ52: =SUM(BL52:BY52) -> 800 | CA52: =J52-BZ52 -> 0
A53: 45616 | B53: MAGGIO 3 SRL | C53: 意大利 | D53: 4500151811 | F53: 4500151811-10 | G53: 9279F-S001-NB-3L | H53: 9279F-S001-NB | I53: 猫蛋二代 展示架（无闪粉） | J53: 4000 | K53: 0 | L53: 40 | M53: =J53/L53 -> 100 | N53: 45672 | O53: 45668 | Q53: PASS | U53: 1/15出 | V53: 11/22收到 | X53: 12/12-EAN 贴纸+意大利sorting logo含进口商地址贴纸+展示架条码贴纸 | AB53: 日期码格式：ZURU INC(BVI) 标准格式 日期：按实际生产日期 Packaging Info: 9279F-MA 3L+23L B 收缩膜（+1*EAN意大利sorting logo含进口商地址贴纸）+MA 5L C Poop Polybag +MA C 5L 收藏指南+ MA sewn in label+ MA 展示架(+1*展示架条码贴纸) 产品条码 4894680026780 Remark: 1.此单出意大利，需符合EU标准，不能含微塑料，如果有slime等化学品需要不含硼 2.需保证按期1/15前完货，延期罚款 3.贴纸切勿盖住意大利警告语文字(QC 务必检查） | AC53: Amy Xiao | AD53: 104.7326 | AE53: =M53*AD53 -> 10473.26 | AF53: 94070-1.16 | AK53: =J53 -> 4000 | AO53: =J53 -> 4000 | AT53: =J53 -> 4000 | BG53: =J53/40 -> 100 | BK53: MA布标 | BL53: =J53/60*1 -> 66.666667 | BM53: =J53/60*9 -> 600 | BN53: =J53/60*10 -> 666.66667 | BO53: =J53/60*10 -> 666.66667 | BP53: =J53/60*10 -> 666.66667 | BQ53: =J53/60*10 -> 666.66667 | BR53: =J53/60*10 -> 666.66667 | BZ53: =SUM(BL53:BY53) -> 4000 | CA53: =J53-BZ53 -> 0
A54: 45615 | B54: DD’S DISCOUNTS | C54: 美国 | D54: 4500151497 | E54: 70054076 | F54: 4500151497-20 | G54: 9279-S001 | H54: 9279-S001 | I54: 猫蛋二代 | J54: 504 | K54: 0 | L54: 24 | M54: =J54/L54 -> 21 | N54: 45695 | O54: 45691 | Q54: PASS | V54: ROSS指定箱唛格式 | X54: 无 | Z54: 1/3-客供价格贴纸 | AB54: 日期码格式： 标准格式 日期：按实际生产日期 Packaging Info: 1.ZURU MA UPC 现有版本包装 + 客供价格贴纸，出口美国 , 优先使用MA 1L 最新版本 。 Remark: 1.ZURU MA UPC 现有版本包装 + 客供价格贴纸，出口美国 , 优先使用MA 1L 最新版本 。 2.价格贴纸位于包装正面右下角，不挡住重要信息即可，可适当调整 ，价格贴纸由跟单提供。 3.标准日期码格式，产品和包装必须有日期码 。 4.同个产品同个货期不可出现不同的包装。 5. 跟单提供ROSS通用的箱唛模版，工厂按实际45 PO上客户PO/Item号/装箱数 提供箱唛排版来确认 | AC54: Taylor Liao | AD54: 2.1341 | AE54: =J54*AD54 -> 1075.5864 | AF54: 94554-3.14 | AI54: =J54 -> 504 | AO54: =J54 -> 504 | AS54: =J54 -> 504 | BK54: MA布标 | BL54: =J54/60*1 -> 8.4 | BM54: =J54/60*9 -> 75.6 | BN54: =J54/60*10 -> 84 | BO54: =J54/60*10 -> 84 | BP54: =J54/60*10 -> 84 | BQ54: =J54/60*10 -> 84 | BR54: =J54/60*10 -> 84 | BZ54: =SUM(BL54:BY54) -> 504 | CA54: =J54-BZ54 -> 0
A55: 45629 | B55: HOBBY LOBBY INC. | C55: 美国 | D55: 4500153134 | E55: W0697213 | F55: 4500153134-10 | G55: 9279-S001 | H55: MB121-9279-S001 | I55: 混装（9279+9298） | J55: 3000 | K55: 0 | L55: 12 | M55: =J55/L55 -> 250 | N55: 45698 | O55: 45694 | Q55: PASS | V55: 12/3收到 | X55: 12/3收到-价格贴纸+外箱 贴纸 | AB55: 日期码格式：ZURU INC(BVI) 标准格式 日期：按实际生产日期 Packaging Info: 1. MA UPC版包装，优先1L，需要加贴价格贴纸(价格贴纸文档跟单提供)，出美国。 2. 外箱正唛右下角贴条码贴纸2张，贴纸大小：2.75 x 1.5 inch (跟单提供文档，工厂采购) Remark: 1. 产品外包装及产品本身都必须有日期跟踪码，格式为：ZURU 标准日期码。 2. ZURU QC验货，无测试。 3. #MB121: 混装 #9279 - 12pcs + #9298 - 12pcs 入同一外箱，total 24pcs/ctn。 | AC55: Eleven Zhang | AD55: 51.0846 | AE55: =AD55*M55 -> 12771.15 | AF55: 94307-2.20 | AI55: =J55 -> 3000 | AO55: =J55 -> 3000 | AS55: =J55 -> 3000 | BK55: MA布标 | BL55: =J55/60*1 -> 50 | BM55: =J55/60*9 -> 450 | BN55: =J55/60*10 -> 500 | BO55: =J55/60*10 -> 500 | BP55: =J55/60*10 -> 500 | BQ55: =J55/60*10 -> 500 | BR55: =J55/60*10 -> 500 | BZ55: =SUM(BL55:BY55) -> 3000 | CA55: =J55-BZ55 -> 0
A56: 45642 | B56: TJX UK c/o TJX Distribution Ltd & C | C56: 德国 | D56: 4500154045 | E56: TJX Europe-DE: PO#55471303 | F56: 4500154045-40 | G56: 9279-S001-3L | H56: 9279-S001 | I56: 猫蛋二代 | J56: 840 | K56: 0 | L56: 24 | M56: =J56/L56 -> 35 | N56: 45699 | O56: 45695 | Q56: PASS | U56: 2/17出 | V56: 12/25收到 | X56: 无 | Z56: 1/3-客供价格贴纸 | AB56: 日期码格式：ZURU INC(BVI) 标准格式 日期：按实际生产日期 Packaging Info: TJX Europe-DE: PO#55471297(7132) + PO#55471301(9298) + PO#55471302(9298) + PO#55471303(9279) + PO#55471304(9279) + PO#55471275(92107) 3) 9279: MA 3L(23Lwarning) 最新UPC包装+1张客供价格贴纸 Remark: 1. 出往UK的产品+包装务必打上UKCA logo ，否则客人会退货且当地会有罚款； 2. 订单必须经过ZURU QC验货并且通过后方可出货； 3. 订单每行对应客人不同的PO， 箱唛也有不同，做货的时候请分开堆放； 4. 包装条码请按包装备注上的对应的警示语语种包装，出德国的订单(订单备注为TJX Europe-DE)需要确保有英语+德语+荷兰语+波兰语警示语； 5. 订单每行对应客人不同的PO，即同款item的价格贴纸都不相同，请注意收到贴纸后不要弄混!（客人PO号请参考PO最后一栏remark）； 6. 客供价格贴纸位置为产品正面右上角，不能遮住产品信息，大货生产前，请把贴纸位置先发给跟单确认 7. 涉及到相关款式会有闪粉的或者微塑料的，请统一默认出无闪粉或者不含微塑料版本; 8. 外箱封箱必须是工字型封箱方式； | AC56: Sandy Shao | AD56: 2.1295 | AE56: =J56*AD56 -> 1788.78 | AK56: =J56 -> 840 | AO56: =J56 -> 840 | AS56: =J56 -> 840 | BK56: MA布标 | BL56: =J56/60*1 -> 14 | BM56: =J56/60*9 -> 126 | BN56: =J56/60*10 -> 140 | BO56: =J56/60*10 -> 140 | BP56: =J56/60*10 -> 140 | BQ56: =J56/60*10 -> 140 | BR56: =J56/60*10 -> 140 | BZ56: =SUM(BL56:BY56) -> 840 | CA56: =J56-BZ56 -> 0
A57: 45642 | B57: TJX UK c/o TJX Distribution Ltd & C | C57: 德国 | D57: 4500154045 | E57: TJX Europe-DE: PO#55471304 | F57: 4500154045-50 | G57: 9279-S001-3L | H57: 9279-S001 | I57: 猫蛋二代 | J57: 864 | K57: 0 | L57: 24 | M57: =J57/L57 -> 36 | N57: 45699 | O57: 45695 | Q57: PASS | U57: 2/17出 | V57: 12/25收到 | X57: 无 | Z57: 1/3-客供价格贴纸 | AB57: 日期码格式：ZURU INC(BVI) 标准格式 日期：按实际生产日期 Packaging Info: TJX Europe-DE: PO#55471297(7132) + PO#55471301(9298) + PO#55471302(9298) + PO#55471303(9279) + PO#55471304(9279) + PO#55471275(92107) 3) 9279: MA 3L(23Lwarning) 最新UPC包装+1张客供价格贴纸 Remark: 1. 出往UK的产品+包装务必打上UKCA logo ，否则客人会退货且当地会有罚款； 2. 订单必须经过ZURU QC验货并且通过后方可出货； 3. 订单每行对应客人不同的PO， 箱唛也有不同，做货的时候请分开堆放； 4. 包装条码请按包装备注上的对应的警示语语种包装，出德国的订单(订单备注为TJX Europe-DE)需要确保有英语+德语+荷兰语+波兰语警示语； 5. 订单每行对应客人不同的PO，即同款item的价格贴纸都不相同，请注意收到贴纸后不要弄混!（客人PO号请参考PO最后一栏remark）； 6. 客供价格贴纸位置为产品正面右上角，不能遮住产品信息，大货生产前，请把贴纸位置先发给跟单确认 7. 涉及到相关款式会有闪粉的或者微塑料的，请统一默认出无闪粉或者不含微塑料版本; 8. 外箱封箱必须是工字型封箱方式； | AC57: Sandy Shao | AD57: 2.1295 | AE57: =J57*AD57 -> 1839.888 | AK57: =J57 -> 864 | AO57: =J57 -> 864 | AS57: =J57 -> 864 | BK57: MA布标 | BL57: =J57/60*1 -> 14.4 | BM57: =J57/60*9 -> 129.6 | BN57: =J57/60*10 -> 144 | BO57: =J57/60*10 -> 144 | BP57: =J57/60*10 -> 144 | BQ57: =J57/60*10 -> 144 | BR57: =J57/60*10 -> 144 | BZ57: =SUM(BL57:BY57) -> 864 | CA57: =J57-BZ57 -> 0
A58: 45642 | B58: TJX UK | C58: 英国 | D58: 4500154092 | E58: TJX UK: PO#50471043 | F58: 4500154092-50 | G58: 9279-S001-3L | H58: 9279-S001 | I58: 猫蛋二代 | J58: 1272 | K58: 0 | L58: 24 | M58: =J58/L58 -> 53 | N58: 45699 | O58: 45695 | Q58: PASS | U58: 2/13出 | V58: 12/25收到 | X58: 无 | Z58: 1/3-客供价格贴纸 | AB58: 日期码格式：ZURU INC(BVI) 标准格式 日期：按实际生产日期 Packaging Info: TJX UK: PO#50470844(9281) + PO#50470917(9298) + PO#50470959(9298) + PO#50470960(7132) + PO#50471043(9279) + PO#50471008(9279) 4) 9279: MA 3L(23Lwarning) 最新UPC包装+1张客供价格贴纸 Remark: 1. 出往UK的产品+包装务必打上UKCA logo ，否则客人会退货且当地会有罚款； 2. 订单必须经过ZURU QC验货并且通过后方可出货； 3. 订单每行对应客人不同的PO， 箱唛也有不同，做货的时候请分开堆放； 4. 包装条码请按包装备注上的对应的警示语语种包装，出德国的订单(订单备注为TJX Europe-DE)需要确保有英语+德语+荷兰语+波兰语警示语； 5. 订单每行对应客人不同的PO，即同款item的价格贴纸都不相同，请注意收到贴纸后不要弄混!（客人PO号请参考PO最后一栏remark）； 6. 客供价格贴纸位置为产品正面右上角，不能遮住产品信息，大货生产前，请把贴纸位置先发给跟单确认 7. 涉及到相关款式会有闪粉的或者微 | AC58: Sandy Shao | AD58: 2.1295 | AE58: =J58*AD58 -> 2708.724 | AF58: 94215-2.11 | AK58: =J58 -> 1272 | AO58: =J58 -> 1272 | AS58: =J58 -> 1272 | BK58: MA布标 | BL58: =J58/60*1 -> 21.2 | BM58: =J58/60*9 -> 190.8 | BN58: =J58/60*10 -> 212 | BO58: =J58/60*10 -> 212 | BP58: =J58/60*10 -> 212 | BQ58: =J58/60*10 -> 212 | BR58: =J58/60*10 -> 212 | BZ58: =SUM(BL58:BY58) -> 1272 | CA58: =J58-BZ58 -> 0
A59: 45642 | B59: TJX UK | C59: 英国 | D59: 4500154092 | E59: TJX UK: PO#50471008 | F59: 4500154092-60 | G59: 9279-S001-3L | H59: 9279-S001 | I59: 猫蛋二代 | J59: 1248 | K59: 0 | L59: 24 | M59: =J59/L59 -> 52 | N59: 45699 | O59: 45695 | Q59: PASS | U59: 2/13出 | V59: 12/25收到 | X59: 无 | Z59: 1/3-客供价格贴纸 | AB59: 日期码格式：ZURU INC(BVI) 标准格式 日期：按实际生产日期 Packaging Info: TJX UK: PO#50470844(9281) + PO#50470917(9298) + PO#50470959(9298) + PO#50470960(7132) + PO#50471043(9279) + PO#50471008(9279) 4) 9279: MA 3L(23Lwarning) 最新UPC包装+1张客供价格贴纸 Remark: 1. 出往UK的产品+包装务必打上UKCA logo ，否则客人会退货且当地会有罚款； 2. 订单必须经过ZURU QC验货并且通过后方可出货； 3. 订单每行对应客人不同的PO， 箱唛也有不同，做货的时候请分开堆放； 4. 包装条码请按包装备注上的对应的警示语语种包装，出德国的订单(订单备注为TJX Europe-DE)需要确保有英语+德语+荷兰语+波兰语警示语； 5. 订单每行对应客人不同的PO，即同款item的价格贴纸都不相同，请注意收到贴纸后不要弄混!（客人PO号请参考PO最后一栏remark）； 6. 客供价格贴纸位置为产品正面右上角，不能遮住产品信息，大货生产前，请把贴纸位置先发给跟单确认 7. 涉及到相关款式会有闪粉的或者微 | AC59: Sandy Shao | AD59: 2.1295 | AE59: =J59*AD59 -> 2657.616 | AF59: 94215-2.11 | AK59: =J59 -> 1248 | AO59: =J59 -> 1248 | AS59: =J59 -> 1248 | BK59: MA布标 | BL59: =J59/60*1 -> 20.8 | BM59: =J59/60*9 -> 187.2 | BN59: =J59/60*10 -> 208 | BO59: =J59/60*10 -> 208 | BP59: =J59/60*10 -> 208 | BQ59: =J59/60*10 -> 208 | BR59: =J59/60*10 -> 208 | BZ59: =SUM(BL59:BY59) -> 1248 | CA59: =J59-BZ59 -> 0
A60: 45603 | B60: DD’S DISCOUNTS | C60: 美国 | D60: 4500150534 | E60: 70054074 | F60: 4500150534-20 | G60: 92114-S001 | H60: 92114-S001 | I60: 猫蛋二代(9279+9269)组装 | J60: 300 | K60: 0 | L60: 12 | M60: =J60/L60 -> 25 | N60: 45673 | O60: 45670 | Q60: PASS | V60: 指定箱唛格式 | X60: 无 | Z60: 12/19-客供价格贴纸 | AA60: DG20250115 | AB60: 日期码格式：ZURU INC(BVI) 标准格式 日期：按实际生产日期 Packaging Info: 1.ZURU MA UPC 现有版本包装 + 客供价格贴纸，出口美国 , 优先使用MA 1L 最新版本 。 Remark: 1.ZURU MA UPC 现有版本包装 + 客供价格贴纸，出口美国 , 优先使用MA 1L 最新版本 。 2.价格贴纸位于包装正面右下角，不挡住重要信息即可，可适当调整 ，价格贴纸由跟单提供。 3.标准日期码格式，产品和包装必须有日期码 。 4.同个产品同个货期不可出现不同的包装。 5. 跟单提供ROSS通用的箱唛模版，工厂按实际45 PO上客户PO/Item号/装箱数 提供箱唛排版来确认。 | AC60: Taylor Liao | AD60: 2.7072 | AE60: =J60*AD60 -> 812.16 | AF60: 94534-3.13 | AI60: =J60 -> 300 | AO60: =J60 -> 300 | AS60: =J60 -> 300 | BH60: =J60 -> 300 | BK60: MA布标 | BM60: =J60/60*9 -> 45 | BN60: =J60/60*10 -> 50 | BO60: =J60/60*10 -> 50 | BP60: =J60/60*10 -> 50 | BQ60: =J60/60*10 -> 50 | BR60: =J60/60*10 -> 50 | BS60: =J60/60*1 -> 5 | BZ60: =SUM(BL60:BY60) -> 300 | CA60: =J60-BZ60 -> 0
A61: 45586 | B61: TJX COMPANIES, INC | C61: 美国 | D61: 4500147803 | E61: TJ MAXX DC#891-156PCS , DC#894-132PCS , DC#896-132PCS , DC#897-252PCS , DC#898-132PCS | F61: 4500147803-60 | G61: 92114-S001 | H61: 92114-S001 | I61: 猫蛋二代(9279+9269)组装 | J61: 804 | K61: 0 | L61: 12 | M61: =J61/L61 -> 67 | N61: 45677 | O61: 45673 | Q61: PASS | U61: 2/13出 | V61: 11/4收到 | X61: 无 | Z61: 12/19-客供价格贴纸 | AB61: 日期码格式：ZURU INC(BVI) 标准格式 日期：按实际生产日期 Packaging Info: MA UPC包装+价格贴纸，价格贴纸客供。 #92114 是combo pack, 混装了 9269（华康生产）+9279（兴信生产），在兴信组装 。 Remark: 1. 产品和包装上印刷tracking code信息，格式为ZURU常规格式。 2. 分5个DC出货，每款产品每个DC的箱唛资料不同。具体分DC数量，请参考后面行项目备注。 3. ZURU QC验货。 | AC61: Emily Wu | AD61: 2.8218 | AE61: =J61*AD61 -> 2268.7272 | AI61: =J61 -> 804 | AO61: =J61 -> 804 | AS61: =J61 -> 804 | BH61: =J61 -> 804 | BK61: MA布标 | BM61: =J61/60*9 -> 120.6 | BN61: =J61/60*10 -> 134 | BO61: =J61/60*10 -> 134 | BP61: =J61/60*10 -> 134 | BQ61: =J61/60*10 -> 134 | BR61: =J61/60*10 -> 134 | BS61: =J61/60*1 -> 13.4 | BZ61: =SUM(BL61:BY61) -> 804 | CA61: =J61-BZ61 -> 0
A62: 45586 | B62: TJX COMPANIES, INC | C62: 美国 | D62: 4500147800 | E62: Marshalls DC#881-120PCS , DC#884-96PCS, DC#886-132PCS , DC#887-120PCS , DC#888-132PCS | F62: 4500147800-60 | G62: 92114-S001 | H62: 92114-S001 | I62: 猫蛋二代(9279+9269)组装 | J62: 600 | K62: 0 | L62: 12 | M62: =J62/L62 -> 50 | N62: 45677 | O62: 45673 | Q62: PASS | U62: 2/14出 | V62: 11/4收到 | X62: 无 | Z62: 12/19-客供价格贴纸 | AB62: 日期码格式：ZURU INC(BVI) 标准格式 日期：按实际生产日期 Packaging Info: MA UPC包装+价格贴纸，价格贴纸客供。 #92114 是combo pack, 混装了 9269（华康生产）+9279（兴信生产），在兴信组装 。 Remark: 1. 产品和包装上印刷tracking code信息，格式为ZURU常规格式。 2. 分5个DC出货，每款产品每个DC的箱唛资料不同。具体分DC数量，请参考后面行项目备注。 3. ZURU QC验货。 | AC62: Emily Wu | AD62: 2.8218 | AE62: =J62*AD62 -> 1693.08 | AI62: =J62 -> 600 | AO62: =J62 -> 600 | AS62: =J62 -> 600 | BH62: =J62 -> 600 | BK62: MA布标 | BM62: =J62/60*9 -> 90 | BN62: =J62/60*10 -> 100 | BO62: =J62/60*10 -> 100 | BP62: =J62/60*10 -> 100 | BQ62: =J62/60*10 -> 100 | BR62: =J62/60*10 -> 100 | BS62: =J62/60*1 -> 10 | BZ62: =SUM(BL62:BY62) -> 600 | CA62: =J62-BZ62 -> 0
A63: 45608 | B63: ROSS PROCUREMENT.INC | C63: 美国 | D63: 4500150488 | E63: 60190680 | F63: 4500150488-70 | G63: 92114-S001 | H63: 92114-S001 | I63: 猫蛋二代(9279+9269)组装 | J63: 2004 | K63: 0 | L63: 12 | M63: =J63/L63 -> 167 | N63: 45677 | O63: 45673 | Q63: PASS | U63: 2/11出 | V63: 指定箱唛格式 | X63: 无 | Z63: 12/19-客供价格贴纸 | AA63: DG20250115 | AB63: 日期码格式： 标准格式 日期：按实际生产日期 Packaging Info: 1.ZURU MA UPC 现有版本包装 + 客供价格贴纸，出口美国 , 优先使用MA 1L 最新版本 。 Remark: 1.ZURU MA UPC 现有版本包装 + 客供价格贴纸，出口美国 , 优先使用MA 1L 最新版本 。 2.价格贴纸位于包装正面右下角，不挡住重要信息即可，可适当调整 ，价格贴纸由跟单提供。 3.标准日期码格式，产品和包装必须有日期码 。 4.同个产品同个货期不可出现不同的包装。 5. 跟单提供ROSS通用的箱唛模版，工厂按实际45 PO上客户PO/Item号/装箱数 提供箱唛排版来确认 | AC63: Taylor Liao | AD63: 2.7175 | AE63: =J63*AD63 -> 5445.87 | AF63: 94465-3.6 | AI63: =J63 -> 2004 | AO63: =J63 -> 2004 | AS63: =J63 -> 2004 | BH63: =J63 -> 2004 | BK63: MA布标 | BM63: =J63/60*9 -> 300.6 | BN63: =J63/60*10 -> 334 | BO63: =J63/60*10 -> 334 | BP63: =J63/60*10 -> 334 | BQ63: =J63/60*10 -> 334 | BR63: =J63/60*10 -> 334 | BS63: =J63/60*1 -> 33.4 | BZ63: =SUM(BL63:BY63) -> 2004 | CA63: =J63-BZ63 -> 0
A64: 45632 | B64: AMAZON UK | C64: 英国 | D64: 4500153435 | E64: Amazon UK:PO#5OF9KGS S | F64: 4500153435-30 | G64: 9279B-S001-3L | H64: 9279B-S001 | I64: 猫蛋二代 | J64: 504 | K64: 0 | L64: 12 | M64: =J64/L64 -> 42 | N64: 45681 | O64: 45677 | Q64: PASS | U64: 2/7-2/11出 | V64: 空白外箱（加印带Zuru字样的最新logo，除了邮包盒直接做外箱的产品） + SSCC LABEL一张, 无箱唛. | X64: UPC+IT翻4500124528+ES回收标翻4500149035+ZURU邮箱4500149035 | Z64: 12/18-外箱贴纸 | AB64: 日期码格式：ZURU INC(BVI) 标准格式 日期：按实际生产日期 Packaging Info: Amazon UK/DE (92104HG/9279B/9296A/9543A) 2. 9279B: 9279B 12pcs/ctn, no inner,CALICO CAT; CTN Loading: 4W*3D=12pcs/CTN; MA 3L(23L warning)B收缩膜+ 3张贴纸(1张UPC#+IT sorting label<(>, <)>参 考翻单PO#4500124528；1张ES回收标，参考翻单PO#4500149035；1张ZURU邮箱（参考PO#4500149035)+MA 最新版布标+MA 5L(23L warning) C收藏指南+其他MA最新版 包装； 5. ZURU验货最迟不得晚于2025/1/27 Remark: 1.空白外箱（加印带Zuru字样的最新logo，除了邮包盒直接做外箱的产品） + SSCC LABEL一张, 无箱唛. (SSCC LABEL贴在外箱正面的正中间，贴一面即可,贴纸离外箱边距必须至少3.2CM),SSCC贴纸由工厂直接跟勤得采购或者工厂自行采购，每一张SSCC Label都是唯一 且有不同流水及条码，且需要检查条码是否能正常扫描，另外，此贴纸印刷不可出现模糊，溢出及粘胶不牢易脱落等现象，如工厂不按此要求导致贴纸有任何问题产 生的罚款将由工厂承担一切责任 。’MADE IN CHINA 外箱只印一正一侧。 2. 出往UK的产品+包装务必打上UKCA logo ，否则客人会退货且当地会有罚款。 3.订单必须经过ZURU QC验货并且通过后方可出货。 4.法国订单要求包装不使用矿物油，请按要求提供以下其中一份文件再出货 ，产品出到法国被相关部门抽检出现包装不符合此要求的，供应商需要为此承担责任， 故此请严格把关 。 -油墨物质""由1 ~ 7个芳香环组成的MOAH""的包装检测报告，要求限值≤1.0%; -包装材料清单，包括包装油墨或物质的信息 -油墨制造商的证书。 5 . 每一批次出货只能有一个生产日期，不可多个生产日期混在同一批次出货；且邮包盒上必须统一加上日期码； 6. 涉及到相关款式会有闪粉的或 者微塑料的，请统一默认出无闪粉或者不含微塑料 版本; 7 .邮包盒及外箱封箱必须是工字型封箱方式； 8 . 5 Surprise or Mini Brands涉及包装是2个及2个以上的球入PVC桶包装时，单个球上若有UPC#或者EAN#，请用白色贴纸覆盖住； | AC64: Crystal Chen | AD64: 2.139 | AE64: =J64*AD64 -> 1078.056 | AF64: 94210-2.11 | AK64: =J64 -> 504 | AO64: =J64 -> 504 | AS64: =J64 -> 504 | BK64: MA布标 | BP64: =J64-BS64 -> 504 | BZ64: =SUM(BL64:BY64) -> 504 | CA64: =J64-BZ64 -> 0
A65: 45632 | B65: AMAZON UK | C65: 英国 | D65: 4500153435 | E65: Amazon DE: PO#7PXKV7PP | F65: 4500153435-60 | G65: 9279B-S001-3L | H65: 9279B-S001 | I65: 猫蛋二代 | J65: 504 | K65: 0 | L65: 12 | M65: =J65/L65 -> 42 | N65: 45681 | O65: 45677 | Q65: PASS | U65: 2/7-2/11出 | V65: 空白外箱（加印带Zuru字样的最新logo，除了邮包盒直接做外箱的产品） + SSCC LABEL一张, 无箱唛. | X65: UPC+IT翻4500124528+ES回收标翻4500149035+ZURU邮箱4500149035 | Z65: 12/18-外箱贴纸 | AB65: 日期码格式：ZURU INC(BVI) 标准格式 日期：按实际生产日期 Packaging Info: Amazon UK/DE (92104HG/9279B/9296A/9543A) 2. 9279B: 9279B 12pcs/ctn, no inner,CALICO CAT; CTN Loading: 4W*3D=12pcs/CTN; MA 3L(23L warning)B收缩膜+ 3张贴纸(1张UPC#+IT sorting label<(>, <)>参 考翻单PO#4500124528；1张ES回收标，参考翻单PO#4500149035；1张ZURU邮箱（参考PO#4500149035)+MA 最新版布标+MA 5L(23L warning) C收藏指南+其他MA最新版 包装； 5. ZURU验货最迟不得晚于2025/1/27 Remark: 1.空白外箱（加印带Zuru字样的最新logo，除了邮包盒直接做外箱的产品） + SSCC LABEL一张, 无箱唛. (SSCC LABEL贴在外箱正面的正中间，贴一面即可,贴纸离外箱边距必须至少3.2CM),SSCC贴纸由工厂直接跟勤得采购或者工厂自行采购，每一张SSCC Label都是唯一 且有不同流水及条码，且需要检查条码是否能正常扫描，另外，此贴纸印刷不可出现模糊，溢出及粘胶不牢易脱落等现象，如工厂不按此要求导致贴纸有任何问题产 生的罚款将由工厂承担一切责任 。’MADE IN CHINA 外箱只印一正一侧。 2. 出往UK的产品+包装务必打上UKCA logo ，否则客人会退货且当地会有罚款。 3.订单必须经过ZURU QC验货并且通过后方可出货。 4.法国订单要求包装不使用矿物油，请按要求提供以下其中一份文件再出货 ，产品出到法国被相关部门抽检出现包装不符合此要求的，供应商需要为此承担责任， 故此请严格把关 。 -油墨物质""由1 ~ 7个芳香环组成的MOAH""的包装检测报告，要求限值≤1.0%; -包装材料清单，包括包装油墨或物质的信息 -油墨制造商的证书。 5 . 每一批次出货只能有一个生产日期，不可多个生产日期混在同一批次出货；且邮包盒上必须统一加上日期码； 6. 涉及到相关款式会有闪粉的或 者微塑料的，请统一默认出无闪粉或者不含微塑料 版本; 7 .邮包盒及外箱封箱必须是工字型封箱方式； 8 . 5 Surprise or Mini Brands涉及包装是2个及2个以上的球入PVC桶包装时，单个球上若有UPC#或者EAN#，请用白色贴纸覆盖住； | AC65: Crystal Chen | AD65: 2.139 | AE65: =J65*AD65 -> 1078.056 | AF65: 94210-2.11 | AK65: =J65 -> 504 | AO65: =J65 -> 504 | AS65: =J65 -> 504 | BK65: MA布标 | BP65: =J65-BS65 -> 504 | BZ65: =SUM(BL65:BY65) -> 504 | CA65: =J65-BZ65 -> 0
A66: 45659 | B66: TJX COMPANIES, INC | C66: 美国 | D66: 4500155119 | E66: 325570 | F66: 4500155119-30 | G66: 9279-S001 | H66: 9279-S001 | I66: 猫蛋二代 | J66: 3600 | K66: 0 | L66: 24 | M66: =J66/L66 -> 150 | N66: 45698 | O66: 45694 | Q66: PASS | V66: 1/2收到 | X66: 无 | Z66: 1/10-客供价格贴纸 | AB66: 日期码格式：ZURU INC(BVI) 标准格式 日期：按实际生产日期 Packaging Info: MA UPC包装+价格贴纸，价格贴纸客供。 Remark: 1. 产品和包装上印刷tracking code信息，格式为ZURU常规格式。 2. 1个DC出货: Marshalls DC#882 3. ZURU QC验货。 | AC66: Emily Wu | AD66: 2.0725 | AE66: =J66*AD66 -> 7461 | AI66: =J66 -> 3600 | AO66: =J66 -> 3600 | AS66: =J66 -> 3600 | BK66: MA布标 | BM66: =J66/60*9 -> 540 | BN66: =J66/60*10 -> 600 | BO66: =J66/60*10 -> 600 | BP66: =J66/60*10 -> 600 | BQ66: =J66/60*10 -> 600 | BR66: =J66/60*10 -> 600 | BS66: =J66/60*1 -> 60 | BZ66: =SUM(BL66:BY66) -> 3600 | CA66: =J66-BZ66 -> 0
A67: 45659 | B67: TJX COMPANIES, INC | C67: 美国 | D67: 4500155120 | E67: TJ MAXX DC#891-792PCS , DC#894-696PCS , DC#896-624PCS , DC#897-1248PC S,DC#898-648PCS | F67: 4500155120-30 | G67: 9279-S001 | H67: 9279-S001 | I67: 猫蛋二代 | J67: 4008 | K67: 0 | L67: 24 | M67: =J67/L67 -> 167 | N67: 45698 | O67: 45694 | Q67: PASS | U67: 2/21出 | V67: 1/2收到 | X67: 无 | Z67: 1/10-客供价格贴纸 | AB67: 日期码格式：ZURU INC(BVI) 标准格式 日期：按实际生产日期 Packaging Info: MA UPC包装+价格贴纸，价格贴纸客供。 Remark: 1. 产品和包装上印刷tracking code信息，格式为ZURU常规格式。 2. 分5个DC出货，每款产品每个DC的箱唛资料不同。具体分DC数量，请参考后面行项目备注。 3. ZURU QC验货。 | AC67: Emily Wu | AD67: 2.1259 | AE67: =J67*AD67 -> 8520.6072 | AF67: 94378-2.27 | AI67: =J67 -> 4008 | AO67: =J67 -> 4008 | AS67: =J67 -> 4008 | BK67: MA布标 | BM67: =J67/60*9 -> 601.2 | BN67: =J67/60*10 -> 668 | BO67: =J67/60*10 -> 668 | BP67: =J67/60*10 -> 668 | BQ67: =J67/60*10 -> 668 | BR67: =J67/60*10 -> 668 | BS67: =J67/60*1 -> 66.8 | BZ67: =SUM(BL67:BY67) -> 4008 | CA67: =J67-BZ67 -> 0
A68: 45614 | B68: ARGOS LIMITED | C68: 英国 | D68: 4500150417 | E68: 361486 | F68: 4500150417-40 | G68: 9279-S001 | H68: 9279-S001 | I68: 猫蛋二代 | J68: 1512 | K68: 0 | L68: 24 | M68: =J68/L68 -> 63 | N68: 45702 | O68: 45698 | Q68: PASS | U68: 2/17出 | V68: 12/3收到 | X68: 12/6-客人白色Cat.label | AB68: 日期码格式：ZURU INC(BVI) 标准格式 日期：按实际生产日期 Packaging Info:9279: MA -1L 包装+客人白色Cat.label 1张覆盖ZURU条码 注意Cat.label (要求易撕类贴纸，但是粘性不能过低），同时此贴纸每个订单都是不相同的(会显示客户对应的订单号），切勿翻旧订单购买，该贴纸由工厂自行 购买。 订单对应客户1个PO号 ，备注有显示 Remark: *MA包装按最新版本安排即可 *包装日期码按ZURU格式即可，请确保不迟于外箱日期码，可等于或者早于外箱日期码，必须为法定工作日。 *外箱尺寸任何一条边长度超过75cm或者每箱重量超过10KG,需要在外箱上加三脚架符号，有问题请与ZURU跟单同事核实。 *订单必须经过ZURU QC验货并且通过后方可出货。 *订单出英国，请注意检查产品及包装应带UKCA图标，包装显示ZURU UK LTD信息，QC同事请查核，如有问题与跟单确认。 *条码扫描会显示客户7位数产品号 ，忽略订单显示的MA条码 *所有产品按符合欧洲标准走货，需要是不含微塑料版本 。 *涉及到硼的，请使用低硼版本 *客户不接受PVC材质包装 | AC68: Zoe Chen | AD68: 2.1295 | AE68: =J68*AD68 -> 3219.804 | AI68: =J68 -> 1512 | AO68: =J68 -> 1512 | AS68: =J68 -> 1512 | BK68: MA布标 | BL68: =J68/60*1 -> 25.2 | BM68: =J68/60*9 -> 226.8 | BN68: =J68/60*10 -> 252 | BO68: =J68/60*10 -> 252 | BP68: =J68/60*10 -> 252 | BQ68: =J68/60*10 -> 252 | BR68: =J68/60*10 -> 252 | BZ68: =SUM(BL68:BY68) -> 1512 | CA68: =J68-BZ68 -> 0
A69: 45624 | B69: ARGOS LIMITED | C69: 英国 | D69: 4500151833 | E69: PO#394630-SKU #7269521 | F69: 4500151833-20 | G69: 9279-S001 | H69: 9279-S001 | I69: 猫蛋二代 | J69: 1008 | K69: 0 | L69: 24 | M69: =J69/L69 -> 42 | N69: 45702 | O69: 45698 | Q69: PASS | U69: 2/17出 | V69: 12/16收到 | X69: 12/6-客人白色Cat.label 条码 | AB69: 日期码格式：ZURU INC(BVI) 标准格式 日期：按实际生产日期 Packaging Info: -9279: MA -1L 包装+客人白色Cat.label 1张覆盖ZURU条码 9279:MA-1L 包装加空白条码贴覆盖包装原条码，确保卖场只能扫到92114 的条码 -注意Cat.label (要求易撕类贴纸，但是粘性不能过低），同时此贴纸每个订单都是不相同的(会显示客户对应的订单号），切勿翻旧订单购买，该贴纸由工厂自行 购买。 -订单对应客户2个PO号 ，备注有显示 ，注意分开做货/验货/装柜 ，混装有罚款。 Remark: *MA包装按最新版本安排即可 *包装日期码按ZURU格式即可，请确保不迟于外箱日期码，可等于或者早于外箱日期码，必须为法定工作日。 *外箱尺寸任何一条边长度超过75cm或者每箱重量超过10KG,需要在外箱上加三脚架符号，有问题请与ZURU跟单同事核实。 *订单必须经过ZURU QC验货并且通过后方可出货。 *订单出英国，请注意检查产品及包装应带UKCA图标，包装显示ZURU UK LTD信息，QC同事请查核，如有问题与跟单确认。 *条码扫描会显示客户7位数产品号 ，忽略订单显示的MA条码 *所有产品按符合欧洲标准走货，需要是不含微塑料版本 。 *涉及到硼的，请使用低硼版本 *客户不接受PVC材质包装 | AC69: Zoe Chen | AD69: 2.1295 | AE69: =J69*AD69 -> 2146.536 | AI69: =J69 -> 1008 | AO69: =J69 -> 1008 | AS69: =J69 -> 1008 | BK69: MA布标 | BL69: =J69/60*1 -> 16.8 | BM69: =J69/60*9 -> 151.2 | BN69: =J69/60*10 -> 168 | BO69: =J69/60*10 -> 168 | BP69: =J69/60*10 -> 168 | BQ69: =J69/60*10 -> 168 | BR69: =J69/60*10 -> 168 | BZ69: =SUM(BL69:BY69) -> 1008 | CA69: =J69-BZ69 -> 0
A70: 45659 | B70: TJX COMPANIES, INC | C70: 美国 | D70: 4500155121 | E70: 325571 | F70: 4500155121-30 | G70: 9279-S001 | H70: 9279-S001 | I70: 猫蛋二代 | J70: 3600 | K70: 0 | L70: 24 | M70: =J70/L70 -> 150 | N70: 45702 | O70: 45698 | Q70: PASS | U70: 2/21出 | V70: 1/2收到 | X70: 无 | Z70: 1/10-客供价格贴纸 | AB70: 日期码格式：ZURU INC(BVI) 标准格式 日期：按实际生产日期 Packaging Info: MA UPC包装+价格贴纸，价格贴纸客供。 Remark: 1. 产品和包装上印刷tracking code信息，格式为ZURU常规格式。 2. 1个DC出货: Marshalls DC#882 3. ZURU QC验货。 | AC70: Emily Wu | AD70: 2.1259 | AE70: =J70*AD70 -> 7653.24 | AF70: 94325-2.22 | AI70: =J70 -> 3600 | AO70: =J70 -> 3600 | AS70: =J70 -> 3600 | BK70: MA布标 | BM70: =J70/60*9 -> 540 | BN70: =J70/60*10 -> 600 | BO70: =J70/60*10 -> 600 | BP70: =J70/60*10 -> 600 | BQ70: =J70/60*10 -> 600 | BR70: =J70/60*10 -> 600 | BS70: =J70/60*1 -> 60 | BZ70: =SUM(BL70:BY70) -> 3600 | CA70: =J70-BZ70 -> 0
A71: 45659 | B71: TJX COMPANIES, INC | C71: 美国 | D71: 4500155123 | E71: TJ MAXX DC#891-792PCS , DC#894-696PCS , DC#896-624PCS , DC#897-1248PC S, DC#898-648PCS | F71: 4500155123-30 | G71: 9279-S001 | H71: 9279-S001 | I71: 猫蛋二代 | J71: 4008 | K71: 0 | L71: 24 | M71: =J71/L71 -> 167 | N71: 45702 | O71: 45698 | Q71: PASS | U71: 2/21出 | V71: 1/2收到 | X71: 无 | Z71: 1/10-客供价格贴纸 | AB71: 日期码格式：ZURU INC(BVI) 标准格式 日期：按实际生产日期 Packaging Info: MA UPC包装+价格贴纸，价格贴纸客供。 Remark: 1. 产品和包装上印刷tracking code信息，格式为ZURU常规格式。 2. 分5个DC出货，每款产品每个DC的箱唛资料不同。具体分DC数量，请参考后面行项目备注。 3. ZURU QC验货。 | AC71: Emily Wu | AD71: 2.1259 | AE71: =J71*AD71 -> 8520.6072 | AF71: 94379-2.27 | AI71: =J71 -> 4008 | AO71: =J71 -> 4008 | AS71: =J71 -> 4008 | BK71: MA布标 | BM71: =J71/60*9 -> 601.2 | BN71: =J71/60*10 -> 668 | BO71: =J71/60*10 -> 668 | BP71: =J71/60*10 -> 668 | BQ71: =J71/60*10 -> 668 | BR71: =J71/60*10 -> 668 | BS71: =J71/60*1 -> 66.8 | BZ71: =SUM(BL71:BY71) -> 4008 | CA71: =J71-BZ71 -> 0
A72: 45651 | B72: Zhuyu(Shenzhen)Trading Co.,Ltd. | C72: 中国 | D72: 4500154728 | E72: 5000001743 | F72: 4500154728-50 | G72: 9279SQ1-S002-1 | H72: 9279SQ1-S002 | I72: 猫蛋二代 | J72: 1200 | K72: 0 | L72: 6 | M72: =J72/L72 -> 200 | N72: 45705 | O72: 45701 | Q72: PASS | U72: 2/18出 | V72: 翻4500150993 | X72: 中文3C贴纸+中文布标(可用布标贴纸)+年龄贴纸翻单：4500150993 | Z72: 1/7-芯片码（客供） | AB72: 日期码格式：ZURU INC(BVI) 标准格式 日期：按实际生产日期 Packaging Info: 物料要求 SKU 所有款号务必使用带有CCC 标识的AW 4 9279SQ1 UPC# 193052050014， MA PDQ+中文3C贴纸+中文收藏指南+中文布标(可用布标贴纸)+年龄贴纸+芯片码（客供） 翻单： 4500150993 Remark: 2.外箱材质如下： 1）毛重小于5kg 外箱纸质 K=B 爆破:1000Kpa 边压:4400N/M; 2）毛重大于5kg 外箱纸质 K636K 爆破:1400Kpa 边压:6300N/M; 3. 产品/销售包装/外箱日期码要一致， 4.芯片码横向平贴在上半部分蛋壳/彩盒内侧立面处，注意事项请见跟单提供文档资料。 5.此产品务必满足国内6P 测试标准，因为可能会被市场监督局抽查，如有问题产生，工厂要负全责 6. 这张订单做出厂价，我司自行安排车辆去贵司提货，贵司需要配合提供出口报关 | AC72: Tina Chen | AD72: 2.1973 | AE72: =J72*AD72 -> 2636.76 | AF72: 94384-2.27 | AI72: =J72 -> 1200 | AP72: =J72 -> 1200 | AS72: =J72 -> 1200 | AX72: =J72/6 -> 200 | BK72: MA布标+布标贴纸 | BL72: =J72/60*1 -> 20 | BM72: =J72/60*9 -> 180 | BN72: =J72/60*10 -> 200 | BO72: =J72/60*10 -> 200 | BP72: =J72/60*10 -> 200 | BQ72: =J72/60*10 -> 200 | BR72: =J72/60*10 -> 200 | BZ72: =SUM(BL72:BY72) -> 1200 | CA72: =J72-BZ72 -> 0
A73: 45642 | B73: AMAZON.COM.DEDC,LLC | C73: 美国 | D73: 4500154101 | E73: 44298KQS | F73: 4500154101-70 | G73: 9279D-S001 | H73: 9279D-S001 | I73: 猫蛋二代 | J73: 204 | K73: 0 | L73: 12 | M73: =J73/L73 -> 17 | N73: 45707 | O73: 45703 | Q73: PASS | U73: 2/25出 | V73: 12/16收到 | X73: UPC贴纸翻4500097545 | Z73: 1/17-外箱贴纸 | AB73: 日期码格式： 标准格式 日期：按实际生产日期 Packaging Info: #9279：MA 1L 加UPC贴纸，UPC贴纸图稿跟返单4500097545。G:193052054753，H:193052054760，B:193052054722，D:193052054739。 Remark: 1. Amazon FOB订单，出口US。 2. 日期码使用ZURU标准版本。 3. 如果大货有要求入邮包盒，则对应的邮包盒上面要打上日期码。 4. 箱尺寸要求：外箱最长边不能超过25"(超过了，case pack只能为1)，不符合要求的大货，一律不接受。 5. 外箱箱唛要求： ①外箱正面印ZURU Logo+SSCC Label(客供贴纸，由跟单订购)。关于 SSCC Label 请注意： SSCC Label显示的是客人自己的item#。每一张SSCC label都是唯一且有不同流水及条码的，没有损耗，绝对不可贴错。如果贴错或损坏任何一张，都会导致全部都 错，千万要注意！SSCC Label必须贴在外箱正面的正中间位置(贴一面即可)，并且贴纸离外箱边距必须至少3cm(可以覆盖Logo<(>&<)>箱唛)，否则会影响到客户那边 仓库的扫描识别。 ②外箱侧面印item#(订单上显示的SKU#)+carton size(以工厂实际尺寸为准，单位: inch)+MADE IN CHINA，日期使用ZURU 标准版本。 6. 装柜要求：按照客户PO#装柜/箱号顺序装柜，跟单会提前给到装柜计划。 在大货生产/仓库存放时，请留意该装柜要求，以便装柜时不混乱(避免装错/装漏/找不到货号等)。 | AC73: kelly/Mia | AD73: 2.139 | AE73: =J73*AD73 -> 436.356 | AF73: 94337-2.24 | AI73: =J73 -> 204 | AO73: =J73 -> 204 | AS73: =J73 -> 204 | BK73: MA布标 | BQ73: =J73-BS73 -> 204 | BZ73: =SUM(BL73:BY73) -> 204 | CA73: =J73-BZ73 -> 0
A74: 45642 | B74: AMAZON.COM.DEDC,LLC | C74: 美国 | D74: 4500154101 | E74: 5HW5344B | F74: 4500154101-100 | G74: 9279H-S001 | H74: 9279H-S001 | I74: 猫蛋二代 | J74: 336 | K74: 0 | L74: 12 | M74: =J74/L74 -> 28 | N74: 45707 | O74: 45703 | Q74: PASS | U74: 2/25出 | V74: 12/16收到 | X74: UPC贴纸翻4500097545 | Z74: 1/17-外箱贴纸 | AB74: 日期码格式： 标准格式 日期：按实际生产日期 Packaging Info: #9279：MA 1L 加UPC贴纸，UPC贴纸图稿跟返单4500097545。G:193052054753，H:193052054760，B:193052054722，D:193052054739。 Remark: 1. Amazon FOB订单，出口US。 2. 日期码使用ZURU标准版本。 3. 如果大货有要求入邮包盒，则对应的邮包盒上面要打上日期码。 4. 箱尺寸要求：外箱最长边不能超过25"(超过了，case pack只能为1)，不符合要求的大货，一律不接受。 5. 外箱箱唛要求： ①外箱正面印ZURU Logo+SSCC Label(客供贴纸，由跟单订购)。关于 SSCC Label 请注意： SSCC Label显示的是客人自己的item#。每一张SSCC label都是唯一且有不同流水及条码的，没有损耗，绝对不可贴错。如果贴错或损坏任何一张，都会导致全部都 错，千万要注意！SSCC Label必须贴在外箱正面的正中间位置(贴一面即可)，并且贴纸离外箱边距必须至少3cm(可以覆盖Logo<(>&<)>箱唛)，否则会影响到客户那边 仓库的扫描识别。 ②外箱侧面印item#(订单上显示的SKU#)+carton size(以工厂实际尺寸为准，单位: inch)+MADE IN CHINA，日期使用ZURU 标准版本。 6. 装柜要求：按照客户PO#装柜/箱号顺序装柜，跟单会提前给到装柜计划。 在大货生产/仓库存放时，请留意该装柜要求，以便装柜时不混乱(避免装错/装漏/找不到货号等)。 | AC74: kelly/Mia | AD74: 2.139 | AE74: =J74*AD74 -> 718.704 | AF74: 94337-2.24 | AI74: =J74 -> 336 | AO74: =J74 -> 336 | AS74: =J74 -> 336 | BK74: MA布标 | BR74: =J74 -> 336 | BZ74: =SUM(BL74:BY74) -> 336 | CA74: =J74-BZ74 -> 0
A75: 45642 | B75: AMAZON.COM.DEDC,LLC | C75: 美国 | D75: 4500154101 | E75: 521ADRLC | F75: 4500154101-110 | G75: 9279B-S001 | H75: 9279B-S001 | I75: 猫蛋二代 | J75: 396 | K75: 0 | L75: 12 | M75: =J75/L75 -> 33 | N75: 45707 | O75: 45703 | Q75: PASS | U75: 2/25出 | V75: 12/16收到 | X75: UPC贴纸翻4500097545 | Z75: 1/17-外箱贴纸 | AB75: 日期码格式： 标准格式 日期：按实际生产日期 Packaging Info: #9279：MA 1L 加UPC贴纸，UPC贴纸图稿跟返单4500097545。G:193052054753，H:193052054760，B:193052054722，D:193052054739。 Remark: 1. Amazon FOB订单，出口US。 2. 日期码使用ZURU标准版本。 3. 如果大货有要求入邮包盒，则对应的邮包盒上面要打上日期码。 4. 箱尺寸要求：外箱最长边不能超过25"(超过了，case pack只能为1)，不符合要求的大货，一律不接受。 5. 外箱箱唛要求： ①外箱正面印ZURU Logo+SSCC Label(客供贴纸，由跟单订购)。关于 SSCC Label 请注意： SSCC Label显示的是客人自己的item#。每一张SSCC label都是唯一且有不同流水及条码的，没有损耗，绝对不可贴错。如果贴错或损坏任何一张，都会导致全部都 错，千万要注意！SSCC Label必须贴在外箱正面的正中间位置(贴一面即可)，并且贴纸离外箱边距必须至少3cm(可以覆盖Logo<(>&<)>箱唛)，否则会影响到客户那边 仓库的扫描识别。 ②外箱侧面印item#(订单上显示的SKU#)+carton size(以工厂实际尺寸为准，单位: inch)+MADE IN CHINA，日期使用ZURU 标准版本。 6. 装柜要求：按照客户PO#装柜/箱号顺序装柜，跟单会提前给到装柜计划。 在大货生产/仓库存放时，请留意该装柜要求，以便装柜时不混乱(避免装错/装漏/找不到货号等)。 | AC75: kelly/Mia | AD75: 2.139 | AE75: =J75*AD75 -> 847.044 | AF75: 94337-2.24 | AI75: =J75 -> 396 | AO75: =J75 -> 396 | AS75: =J75 -> 396 | BK75: MA布标 | BP75: =J75-BS75 -> 396 | BZ75: =SUM(BL75:BY75) -> 396 | CA75: =J75-BZ75 -> 0
A76: 45642 | B76: AMAZON.COM.DEDC,LLC | C76: 美国 | D76: 4500154101 | E76: 44D1DD7V | F76: 4500154101-120 | G76: 9279G-S001 | H76: 9279G-S001 | I76: 猫蛋二代 | J76: 24 | K76: 0 | L76: 12 | M76: =J76/L76 -> 2 | N76: 45707 | O76: 45703 | Q76: PASS | U76: 2/25出 | V76: 12/16收到 | X76: UPC贴纸翻4500097545 | Z76: 1/17-外箱贴纸 | AB76: 日期码格式： 标准格式 日期：按实际生产日期 Packaging Info: #9279：MA 1L 加UPC贴纸，UPC贴纸图稿跟返单4500097545。G:193052054753，H:193052054760，B:193052054722，D:193052054739。 Remark: 1. Amazon FOB订单，出口US。 2. 日期码使用ZURU标准版本。 3. 如果大货有要求入邮包盒，则对应的邮包盒上面要打上日期码。 4. 箱尺寸要求：外箱最长边不能超过25"(超过了，case pack只能为1)，不符合要求的大货，一律不接受。 5. 外箱箱唛要求： ①外箱正面印ZURU Logo+SSCC Label(客供贴纸，由跟单订购)。关于 SSCC Label 请注意： SSCC Label显示的是客人自己的item#。每一张SSCC label都是唯一且有不同流水及条码的，没有损耗，绝对不可贴错。如果贴错或损坏任何一张，都会导致全部都 错，千万要注意！SSCC Label必须贴在外箱正面的正中间位置(贴一面即可)，并且贴纸离外箱边距必须至少3cm(可以覆盖Logo<(>&<)>箱唛)，否则会影响到客户那边 仓库的扫描识别。 ②外箱侧面印item#(订单上显示的SKU#)+carton size(以工厂实际尺寸为准，单位: inch)+MADE IN CHINA，日期使用ZURU 标准版本。 6. 装柜要求：按照客户PO#装柜/箱号顺序装柜，跟单会提前给到装柜计划。 在大货生产/仓库存放时，请留意该装柜要求，以便装柜时不混乱(避免装错/装漏/找不到货号等)。 | AC76: kelly/Mia | AD76: 2.139 | AE76: =J76*AD76 -> 51.336 | AF76: 94337-2.24 | AI76: =J76 -> 24 | AO76: =J76 -> 24 | AS76: =J76 -> 24 | BK76: MA布标 | BO76: =J76 -> 24 | BZ76: =SUM(BL76:BY76) -> 24 | CA76: =J76-BZ76 -> 0
A77: 45642 | B77: AMAZON.COM.DEDC,LLC | C77: 美国 | D77: 4500154032 | E77: 5BA3EBVZ | F77: 4500154032-80 | G77: 9279D-S001 | H77: 9279D-S001 | I77: 猫蛋二代 | J77: 48 | K77: 0 | L77: 12 | M77: =J77/L77 -> 4 | N77: 45707 | O77: 45703 | Q77: PASS | U77: 2/21出 | V77: 12/16收到 | X77: UPC贴纸翻4500097545 | Z77: 1/17-外箱贴纸 | AB77: 日期码格式： 标准格式 日期：按实际生产日期 Packaging Info: #9279：MA 1L 加UPC贴纸，UPC贴纸图稿跟返单4500097545。D:193052054739，H:193052054760，B:193052054722，G:193052054753。 Remark: 1. Amazon FOB订单，出口US。 2. 日期码使用ZURU标准版本。 3. 如果大货有要求入邮包盒，则对应的邮包盒上面要打上日期码。 4. 箱尺寸要求：外箱最长边不能超过25"(超过了，case pack只能为1)，不符合要求的大货，一律不接受。 5. 外箱箱唛要求： ①外箱正面印ZURU Logo+SSCC Label(客供贴纸，由跟单订购)。关于 SSCC Label 请注意： SSCC Label显示的是客人自己的item#。每一张SSCC label都是唯一且有不同流水及条码的，没有损耗，绝对不可贴错。如果贴错或损坏任何一张，都会导致全部都 错，千万要注意！SSCC Label必须贴在外箱正面的正中间位置(贴一面即可)，并且贴纸离外箱边距必须至少3cm(可以覆盖Logo<(>&<)>箱唛)，否则会影响到客户那边 仓库的扫描识别。 ②外箱侧面印item#(订单上显示的SKU#)+carton size(以工厂实际尺寸为准，单位: inch)+MADE IN CHINA，日期使用ZURU 标准版本。 6. 装柜要求：按照客户PO#装柜/箱号顺序装柜，跟单会提前给到装柜计划。 在大货生产/仓库存放时，请留意该装柜要求，以便装柜时不混乱(避免装错/装漏/找不到货号等)。 | AC77: kelly/Mia | AD77: 2.0833 | AE77: =J77*AD77 -> 99.9984 | AF77: 94313-2.21 | AI77: =J77 -> 48 | AO77: =J77 -> 48 | AS77: =J77 -> 48 | BK77: MA布标 | BQ77: =J77-BS77 -> 48 | BZ77: =SUM(BL77:BY77) -> 48 | CA77: =J77-BZ77 -> 0
A78: 45642 | B78: AMAZON.COM.DEDC,LLC | C78: 美国 | D78: 4500154032 | E78: 4I8NZHKF | F78: 4500154032-100 | G78: 9279H-S001 | H78: 9279H-S001 | I78: 猫蛋二代 | J78: 72 | K78: 0 | L78: 12 | M78: =J78/L78 -> 6 | N78: 45707 | O78: 45703 | Q78: PASS | U78: 2/21出 | V78: 12/16收到 | X78: UPC贴纸翻4500097545 | Z78: 1/17-外箱贴纸 | AB78: 日期码格式： 标准格式 日期：按实际生产日期 Packaging Info: #9279：MA 1L 加UPC贴纸，UPC贴纸图稿跟返单4500097545。D:193052054739，H:193052054760，B:193052054722，G:193052054753。 Remark: 1. Amazon FOB订单，出口US。 2. 日期码使用ZURU标准版本。 3. 如果大货有要求入邮包盒，则对应的邮包盒上面要打上日期码。 4. 箱尺寸要求：外箱最长边不能超过25"(超过了，case pack只能为1)，不符合要求的大货，一律不接受。 5. 外箱箱唛要求： ①外箱正面印ZURU Logo+SSCC Label(客供贴纸，由跟单订购)。关于 SSCC Label 请注意： SSCC Label显示的是客人自己的item#。每一张SSCC label都是唯一且有不同流水及条码的，没有损耗，绝对不可贴错。如果贴错或损坏任何一张，都会导致全部都 错，千万要注意！SSCC Label必须贴在外箱正面的正中间位置(贴一面即可)，并且贴纸离外箱边距必须至少3cm(可以覆盖Logo<(>&<)>箱唛)，否则会影响到客户那边 仓库的扫描识别。 ②外箱侧面印item#(订单上显示的SKU#)+carton size(以工厂实际尺寸为准，单位: inch)+MADE IN CHINA，日期使用ZURU 标准版本。 6. 装柜要求：按照客户PO#装柜/箱号顺序装柜，跟单会提前给到装柜计划。 在大货生产/仓库存放时，请留意该装柜要求，以便装柜时不混乱(避免装错/装漏/找不到货号等)。 | AC78: kelly/Mia | AD78: 2.0833 | AE78: =J78*AD78 -> 149.9976 | AF78: 94313-2.21 | AI78: =J78 -> 72 | AO78: =J78 -> 72 | AS78: =J78 -> 72 | BK78: MA布标 | BR78: =J78 -> 72 | BZ78: =SUM(BL78:BY78) -> 72 | CA78: =J78-BZ78 -> 0
A79: 45642 | B79: AMAZON.COM.DEDC,LLC | C79: 美国 | D79: 4500154032 | E79: 2TPHLT7S | F79: 4500154032-110 | G79: 9279B-S001 | H79: 9279B-S001 | I79: 猫蛋二代 | J79: 156 | K79: 0 | L79: 12 | M79: =J79/L79 -> 13 | N79: 45707 | O79: 45703 | Q79: PASS | U79: 2/21出 | V79: 12/16收到 | X79: UPC贴纸翻4500097545 | Z79: 1/17-外箱贴纸 | AB79: 日期码格式： 标准格式 日期：按实际生产日期 Packaging Info: #9279：MA 1L 加UPC贴纸，UPC贴纸图稿跟返单4500097545。D:193052054739，H:193052054760，B:193052054722，G:193052054753。 Remark: 1. Amazon FOB订单，出口US。 2. 日期码使用ZURU标准版本。 3. 如果大货有要求入邮包盒，则对应的邮包盒上面要打上日期码。 4. 箱尺寸要求：外箱最长边不能超过25"(超过了，case pack只能为1)，不符合要求的大货，一律不接受。 5. 外箱箱唛要求： ①外箱正面印ZURU Logo+SSCC Label(客供贴纸，由跟单订购)。关于 SSCC Label 请注意： SSCC Label显示的是客人自己的item#。每一张SSCC label都是唯一且有不同流水及条码的，没有损耗，绝对不可贴错。如果贴错或损坏任何一张，都会导致全部都 错，千万要注意！SSCC Label必须贴在外箱正面的正中间位置(贴一面即可)，并且贴纸离外箱边距必须至少3cm(可以覆盖Logo<(>&<)>箱唛)，否则会影响到客户那边 仓库的扫描识别。 ②外箱侧面印item#(订单上显示的SKU#)+carton size(以工厂实际尺寸为准，单位: inch)+MADE IN CHINA，日期使用ZURU 标准版本。 6. 装柜要求：按照客户PO#装柜/箱号顺序装柜，跟单会提前给到装柜计划。 在大货生产/仓库存放时，请留意该装柜要求，以便装柜时不混乱(避免装错/装漏/找不到货号等)。 | AC79: kelly/Mia | AD79: 2.0833 | AE79: =J79*AD79 -> 324.9948 | AF79: 94313-2.21 | AI79: =J79 -> 156 | AO79: =J79 -> 156 | AS79: =J79 -> 156 | BK79: MA布标 | BP79: =J79-BS79 -> 156 | BZ79: =SUM(BL79:BY79) -> 156 | CA79: =J79-BZ79 -> 0
A80: 45642 | B80: AMAZON.COM.DEDC,LLC | C80: 美国 | D80: 4500154032 | E80: 89Q2M2WT | F80: 4500154032-120 | G80: 9279G-S001 | H80: 9279G-S001 | I80: 猫蛋二代 | J80: 12 | K80: 0 | L80: 12 | M80: =J80/L80 -> 1 | N80: 45707 | O80: 45703 | Q80: PASS | U80: 2/21出 | V80: 12/16收到 | X80: UPC贴纸翻4500097545 | Z80: 1/17-外箱贴纸 | AB80: 日期码格式： 标准格式 日期：按实际生产日期 Packaging Info: #9279：MA 1L 加UPC贴纸，UPC贴纸图稿跟返单4500097545。D:193052054739，H:193052054760，B:193052054722，G:193052054753。 Remark: 1. Amazon FOB订单，出口US。 2. 日期码使用ZURU标准版本。 3. 如果大货有要求入邮包盒，则对应的邮包盒上面要打上日期码。 4. 箱尺寸要求：外箱最长边不能超过25"(超过了，case pack只能为1)，不符合要求的大货，一律不接受。 5. 外箱箱唛要求： ①外箱正面印ZURU Logo+SSCC Label(客供贴纸，由跟单订购)。关于 SSCC Label 请注意： SSCC Label显示的是客人自己的item#。每一张SSCC label都是唯一且有不同流水及条码的，没有损耗，绝对不可贴错。如果贴错或损坏任何一张，都会导致全部都 错，千万要注意！SSCC Label必须贴在外箱正面的正中间位置(贴一面即可)，并且贴纸离外箱边距必须至少3cm(可以覆盖Logo<(>&<)>箱唛)，否则会影响到客户那边 仓库的扫描识别。 ②外箱侧面印item#(订单上显示的SKU#)+carton size(以工厂实际尺寸为准，单位: inch)+MADE IN CHINA，日期使用ZURU 标准版本。 6. 装柜要求：按照客户PO#装柜/箱号顺序装柜，跟单会提前给到装柜计划。 在大货生产/仓库存放时，请留意该装柜要求，以便装柜时不混乱(避免装错/装漏/找不到货号等)。 | AC80: kelly/Mia | AD80: 2.0833 | AE80: =J80*AD80 -> 24.9996 | AF80: 94313-2.21 | AI80: =J80 -> 12 | AO80: =J80 -> 12 | AS80: =J80 -> 12 | BK80: MA布标 | BO80: =J80 -> 12 | BZ80: =SUM(BL80:BY80) -> 12 | CA80: =J80-BZ80 -> 0
A81: 45642 | B81: AMAZON.COM.DEDC,LLC | C81: 美国 | D81: 4500154144 | E81: 6WO8ZQJD | F81: 4500154144-80 | G81: 9279D-S001 | H81: 9279D-S001 | I81: 猫蛋二代 | J81: 36 | K81: 0 | L81: 12 | M81: =J81/L81 -> 3 | N81: 45707 | O81: 45703 | Q81: PASS | U81: 2/21出 | V81: 12/16收到 | X81: UPC贴纸翻4500097545 | Z81: 1/17-外箱贴纸 | AB81: 日期码格式： 标准格式 日期：按实际生产日期 Packaging Info: #9279：MA 1L 加UPC贴纸，UPC贴纸图稿跟返单4500097545。H:193052054760，B:193052054722，D:193052054739。 Remark: 1. Amazon FOB订单，出口US。 2. 日期码使用ZURU标准版本。 3. 如果大货有要求入邮包盒，则对应的邮包盒上面要打上日期码。 4. 箱尺寸要求：外箱最长边不能超过25"(超过了，case pack只能为1)，不符合要求的大货，一律不接受。 5. 外箱箱唛要求： ①外箱正面印ZURU Logo+SSCC Label(客供贴纸，由跟单订购)。关于 SSCC Label 请注意： SSCC Label显示的是客人自己的item#。每一张SSCC label都是唯一且有不同流水及条码的，没有损耗，绝对不可贴错。如果贴错或损坏任何一张，都会导致全部都 错，千万要注意！SSCC Label必须贴在外箱正面的正中间位置(贴一面即可)，并且贴纸离外箱边距必须至少3cm(可以覆盖Logo<(>&<)>箱唛)，否则会影响到客户那边 仓库的扫描识别。 ②外箱侧面印item#(订单上显示的SKU#)+carton size(以工厂实际尺寸为准，单位: inch)+MADE IN CHINA，日期使用ZURU 标准版本。 6. 装柜要求：按照客户PO#装柜/箱号顺序装柜，跟单会提前给到装柜计划。 在大货生产/仓库存放时，请留意该装柜要求，以便装柜时不混乱(避免装错/装漏/找不到货号等)。 | AC81: kelly/Mia | AD81: 2.139 | AE81: =J81*AD81 -> 77.004 | AF81: 94314-2.21 | AI81: =J81 -> 36 | AO81: =J81 -> 36 | AS81: =J81 -> 36 | BK81: MA布标 | BQ81: =J81-BS81 -> 36 | BZ81: =SUM(BL81:BY81) -> 36 | CA81: =J81-BZ81 -> 0
A82: 45642 | B82: AMAZON.COM.DEDC,LLC | C82: 美国 | D82: 4500154144 | E82: 4A2MUDXR | F82: 4500154144-100 | G82: 9279H-S001 | H82: 9279H-S001 | I82: 猫蛋二代 | J82: 60 | K82: 0 | L82: 12 | M82: =J82/L82 -> 5 | N82: 45707 | O82: 45703 | Q82: PASS | U82: 2/21出 | V82: 12/16收到 | X82: UPC贴纸翻4500097545 | Z82: 1/17-外箱贴纸 | AB82: 日期码格式： 标准格式 日期：按实际生产日期 Packaging Info: #9279：MA 1L 加UPC贴纸，UPC贴纸图稿跟返单4500097545。H:193052054760，B:193052054722，D:193052054739。 Remark: 1. Amazon FOB订单，出口US。 2. 日期码使用ZURU标准版本。 3. 如果大货有要求入邮包盒，则对应的邮包盒上面要打上日期码。 4. 箱尺寸要求：外箱最长边不能超过25"(超过了，case pack只能为1)，不符合要求的大货，一律不接受。 5. 外箱箱唛要求： ①外箱正面印ZURU Logo+SSCC Label(客供贴纸，由跟单订购)。关于 SSCC Label 请注意： SSCC Label显示的是客人自己的item#。每一张SSCC label都是唯一且有不同流水及条码的，没有损耗，绝对不可贴错。如果贴错或损坏任何一张，都会导致全部都 错，千万要注意！SSCC Label必须贴在外箱正面的正中间位置(贴一面即可)，并且贴纸离外箱边距必须至少3cm(可以覆盖Logo<(>&<)>箱唛)，否则会影响到客户那边 仓库的扫描识别。 ②外箱侧面印item#(订单上显示的SKU#)+carton size(以工厂实际尺寸为准，单位: inch)+MADE IN CHINA，日期使用ZURU 标准版本。 6. 装柜要求：按照客户PO#装柜/箱号顺序装柜，跟单会提前给到装柜计划。 在大货生产/仓库存放时，请留意该装柜要求，以便装柜时不混乱(避免装错/装漏/找不到货号等)。 | AC82: kelly/Mia | AD82: 2.139 | AE82: =J82*AD82 -> 128.34 | AF82: 94314-2.21 | AI82: =J82 -> 60 | AO82: =J82 -> 60 | AS82: =J82 -> 60 | BK82: MA布标 | BR82: =J82 -> 60 | BZ82: =SUM(BL82:BY82) -> 60 | CA82: =J82-BZ82 -> 0
A83: 45642 | B83: AMAZON.COM.DEDC,LLC | C83: 美国 | D83: 4500154144 | E83: 1P7EJLCR | F83: 4500154144-110 | G83: 9279B-S001 | H83: 9279B-S001 | I83: 猫蛋二代 | J83: 132 | K83: 0 | L83: 12 | M83: =J83/L83 -> 11 | N83: 45707 | O83: 45703 | Q83: PASS | U83: 2/21出 | V83: 12/16收到 | X83: UPC贴纸翻4500097545 | Z83: 1/17-外箱贴纸 | AB83: 日期码格式： 标准格式 日期：按实际生产日期 Packaging Info: #9279：MA 1L 加UPC贴纸，UPC贴纸图稿跟返单4500097545。H:193052054760，B:193052054722，D:193052054739。 Remark: 1. Amazon FOB订单，出口US。 2. 日期码使用ZURU标准版本。 3. 如果大货有要求入邮包盒，则对应的邮包盒上面要打上日期码。 4. 箱尺寸要求：外箱最长边不能超过25"(超过了，case pack只能为1)，不符合要求的大货，一律不接受。 5. 外箱箱唛要求： ①外箱正面印ZURU Logo+SSCC Label(客供贴纸，由跟单订购)。关于 SSCC Label 请注意： SSCC Label显示的是客人自己的item#。每一张SSCC label都是唯一且有不同流水及条码的，没有损耗，绝对不可贴错。如果贴错或损坏任何一张，都会导致全部都 错，千万要注意！SSCC Label必须贴在外箱正面的正中间位置(贴一面即可)，并且贴纸离外箱边距必须至少3cm(可以覆盖Logo<(>&<)>箱唛)，否则会影响到客户那边 仓库的扫描识别。 ②外箱侧面印item#(订单上显示的SKU#)+carton size(以工厂实际尺寸为准，单位: inch)+MADE IN CHINA，日期使用ZURU 标准版本。 6. 装柜要求：按照客户PO#装柜/箱号顺序装柜，跟单会提前给到装柜计划。 在大货生产/仓库存放时，请留意该装柜要求，以便装柜时不混乱(避免装错/装漏/找不到货号等)。 | AC83: kelly/Mia | AD83: 2.139 | AE83: =J83*AD83 -> 282.348 | AF83: 94314-2.21 | AI83: =J83 -> 132 | AO83: =J83 -> 132 | AS83: =J83 -> 132 | BK83: MA布标 | BP83: =J83-BS83 -> 132 | BZ83: =SUM(BL83:BY83) -> 132 | CA83: =J83-BZ83 -> 0
A84: 45642 | B84: AMAZON.COM.DEDC,LLC | C84: 美国 | D84: 4500154124 | E84: 6FV2W2NV | F84: 4500154124-60 | G84: 9279D-S001 | H84: 9279D-S001 | I84: 猫蛋二代 | J84: 24 | K84: 0 | L84: 12 | M84: =J84/L84 -> 2 | N84: 45707 | O84: 45703 | Q84: PASS | U84: 2/21出 | V84: 12/16收到 | X84: UPC贴纸翻4500097545 | Z84: 1/17-外箱贴纸 | AB84: 日期码格式：ZURU INC(BVI) 标准格式 日期：按实际生产日期 Packaging Info: #9279：MA 1L 加UPC贴纸，UPC贴纸图稿跟返单4500097545。G:193052054753，H:193052054760，B:193052054722，D:193052054739。 Remark: 1. Amazon FOB订单，出口US。 2. 日期码使用ZURU标准版本。 3. 如果大货有要求入邮包盒，则对应的邮包盒上面要打上日期码。 4. 箱尺寸要求：外箱最长边不能超过25"(超过了，case pack只能为1)，不符合要求的大货，一律不接受。 5. 外箱箱唛要求： ①外箱正面印ZURU Logo+SSCC Label(客供贴纸，由跟单订购)。关于 SSCC Label 请注意： SSCC Label显示的是客人自己的item#。每一张SSCC label都是唯一且有不同流水及条码的，没有损耗，绝对不可贴错。如果贴错或损坏任何一张，都会导致全部都 错，千万要注意！SSCC Label必须贴在外箱正面的正中间位置(贴一面即可)，并且贴纸离外箱边距必须至少3cm(可以覆盖Logo<(>&<)>箱唛)，否则会影响到客户那边 仓库的扫描识别。 ②外箱侧面印item#(订单上显示的SKU#)+carton size(以工厂实际尺寸为准，单位: inch)+MADE IN CHINA，日期使用ZURU 标准版本。 6. 装柜要求：按照客户PO#装柜/箱号顺序装柜，跟单会提前给到装柜计划。 在大货生产/仓库存放时，请留意该装柜要求，以便装柜时不混乱(避免装错/装漏/找不到货号等)。 | AC84: kelly/Mia | AD84: 2.139 | AE84: =J84*AD84 -> 51.336 | AF84: 94315-2.21 | AI84: =J84 -> 24 | AO84: =J84 -> 24 | AS84: =J84 -> 24 | BK84: MA布标 | BQ84: =J84-BS84 -> 24 | BZ84: =SUM(BL84:BY84) -> 24 | CA84: =J84-BZ84 -> 0
A85: 45642 | B85: AMAZON.COM.DEDC,LLC | C85: 美国 | D85: 4500154124 | E85: 2WN13DPQ | F85: 4500154124-80 | G85: 9279H-S001 | H85: 9279H-S001 | I85: 猫蛋二代 | J85: 144 | K85: 0 | L85: 12 | M85: =J85/L85 -> 12 | N85: 45707 | O85: 45703 | Q85: PASS | U85: 2/21出 | V85: 12/16收到 | X85: UPC贴纸翻4500097545 | Z85: 1/17-外箱贴纸 | AB85: 日期码格式：ZURU INC(BVI) 标准格式 日期：按实际生产日期 Packaging Info: #9279：MA 1L 加UPC贴纸，UPC贴纸图稿跟返单4500097545。G:193052054753，H:193052054760，B:193052054722，D:193052054739。 Remark: 1. Amazon FOB订单，出口US。 2. 日期码使用ZURU标准版本。 3. 如果大货有要求入邮包盒，则对应的邮包盒上面要打上日期码。 4. 箱尺寸要求：外箱最长边不能超过25"(超过了，case pack只能为1)，不符合要求的大货，一律不接受。 5. 外箱箱唛要求： ①外箱正面印ZURU Logo+SSCC Label(客供贴纸，由跟单订购)。关于 SSCC Label 请注意： SSCC Label显示的是客人自己的item#。每一张SSCC label都是唯一且有不同流水及条码的，没有损耗，绝对不可贴错。如果贴错或损坏任何一张，都会导致全部都 错，千万要注意！SSCC Label必须贴在外箱正面的正中间位置(贴一面即可)，并且贴纸离外箱边距必须至少3cm(可以覆盖Logo<(>&<)>箱唛)，否则会影响到客户那边 仓库的扫描识别。 ②外箱侧面印item#(订单上显示的SKU#)+carton size(以工厂实际尺寸为准，单位: inch)+MADE IN CHINA，日期使用ZURU 标准版本。 6. 装柜要求：按照客户PO#装柜/箱号顺序装柜，跟单会提前给到装柜计划。 在大货生产/仓库存放时，请留意该装柜要求，以便装柜时不混乱(避免装错/装漏/找不到货号等)。 | AC85: kelly/Mia | AD85: 2.139 | AE85: =J85*AD85 -> 308.016 | AF85: 94315-2.21 | AI85: =J85 -> 144 | AO85: =J85 -> 144 | AS85: =J85 -> 144 | BK85: MA布标 | BR85: =J85 -> 144 | BZ85: =SUM(BL85:BY85) -> 144 | CA85: =J85-BZ85 -> 0
A86: 45642 | B86: AMAZON.COM.DEDC,LLC | C86: 美国 | D86: 4500154124 | E86: 8FACFEHM | F86: 4500154124-90 | G86: 9279B-S001 | H86: 9279B-S001 | I86: 猫蛋二代 | J86: 132 | K86: 0 | L86: 12 | M86: =J86/L86 -> 11 | N86: 45707 | O86: 45703 | Q86: PASS | U86: 2/21出 | V86: 12/16收到 | X86: UPC贴纸翻4500097545 | Z86: 1/17-外箱贴纸 | AB86: 日期码格式：ZURU INC(BVI) 标准格式 日期：按实际生产日期 Packaging Info: #9279：MA 1L 加UPC贴纸，UPC贴纸图稿跟返单4500097545。G:193052054753，H:193052054760，B:193052054722，D:193052054739。 Remark: 1. Amazon FOB订单，出口US。 2. 日期码使用ZURU标准版本。 3. 如果大货有要求入邮包盒，则对应的邮包盒上面要打上日期码。 4. 箱尺寸要求：外箱最长边不能超过25"(超过了，case pack只能为1)，不符合要求的大货，一律不接受。 5. 外箱箱唛要求： ①外箱正面印ZURU Logo+SSCC Label(客供贴纸，由跟单订购)。关于 SSCC Label 请注意： SSCC Label显示的是客人自己的item#。每一张SSCC label都是唯一且有不同流水及条码的，没有损耗，绝对不可贴错。如果贴错或损坏任何一张，都会导致全部都 错，千万要注意！SSCC Label必须贴在外箱正面的正中间位置(贴一面即可)，并且贴纸离外箱边距必须至少3cm(可以覆盖Logo<(>&<)>箱唛)，否则会影响到客户那边 仓库的扫描识别。 ②外箱侧面印item#(订单上显示的SKU#)+carton size(以工厂实际尺寸为准，单位: inch)+MADE IN CHINA，日期使用ZURU 标准版本。 6. 装柜要求：按照客户PO#装柜/箱号顺序装柜，跟单会提前给到装柜计划。 在大货生产/仓库存放时，请留意该装柜要求，以便装柜时不混乱(避免装错/装漏/找不到货号等)。 | AC86: kelly/Mia | AD86: 2.139 | AE86: =J86*AD86 -> 282.348 | AF86: 94315-2.21 | AI86: =J86 -> 132 | AO86: =J86 -> 132 | AS86: =J86 -> 132 | BK86: MA布标 | BP86: =J86-BS86 -> 132 | BZ86: =SUM(BL86:BY86) -> 132 | CA86: =J86-BZ86 -> 0
A87: 45642 | B87: AMAZON.COM.DEDC,LLC | C87: 美国 | D87: 4500154124 | E87: 2AW4FX6V | F87: 4500154124-100 | G87: 9279G-S001 | H87: 9279G-S001 | I87: 猫蛋二代 | J87: 36 | K87: 0 | L87: 12 | M87: =J87/L87 -> 3 | N87: 45707 | O87: 45703 | Q87: PASS | U87: 2/21出 | V87: 12/16收到 | X87: UPC贴纸翻4500097545 | Z87: 1/17-外箱贴纸 | AB87: 日期码格式：ZURU INC(BVI) 标准格式 日期：按实际生产日期 Packaging Info: #9279：MA 1L 加UPC贴纸，UPC贴纸图稿跟返单4500097545。G:193052054753，H:193052054760，B:193052054722，D:193052054739。 Remark: 1. Amazon FOB订单，出口US。 2. 日期码使用ZURU标准版本。 3. 如果大货有要求入邮包盒，则对应的邮包盒上面要打上日期码。 4. 箱尺寸要求：外箱最长边不能超过25"(超过了，case pack只能为1)，不符合要求的大货，一律不接受。 5. 外箱箱唛要求： ①外箱正面印ZURU Logo+SSCC Label(客供贴纸，由跟单订购)。关于 SSCC Label 请注意： SSCC Label显示的是客人自己的item#。每一张SSCC label都是唯一且有不同流水及条码的，没有损耗，绝对不可贴错。如果贴错或损坏任何一张，都会导致全部都 错，千万要注意！SSCC Label必须贴在外箱正面的正中间位置(贴一面即可)，并且贴纸离外箱边距必须至少3cm(可以覆盖Logo<(>&<)>箱唛)，否则会影响到客户那边 仓库的扫描识别。 ②外箱侧面印item#(订单上显示的SKU#)+carton size(以工厂实际尺寸为准，单位: inch)+MADE IN CHINA，日期使用ZURU 标准版本。 6. 装柜要求：按照客户PO#装柜/箱号顺序装柜，跟单会提前给到装柜计划。 在大货生产/仓库存放时，请留意该装柜要求，以便装柜时不混乱(避免装错/装漏/找不到货号等)。 | AC87: kelly/Mia | AD87: 2.139 | AE87: =J87*AD87 -> 77.004 | AF87: 94315-2.21 | AI87: =J87 -> 36 | AO87: =J87 -> 36 | AS87: =J87 -> 36 | BK87: MA布标 | BO87: =J87 -> 36 | BZ87: =SUM(BL87:BY87) -> 36 | CA87: =J87-BZ87 -> 0
A88: 45609 | B88: CMS FAMOUS TOYS | C88: 加拿大 | D88: 4500151019 | E88: PO0000476 | F88: 4500151019-10 | G88: 9279SQ1-S002-NB | H88: 9279SQ1-S002-NB | I88: 猫蛋二代（无闪粉) | J88: 696 | K88: 0 | L88: 6 | M88: =J88/L88 -> 116 | N88: 45709 | O88: 45705 | Q88: PASS | V88: 12/2收到 | X88: 无 | AB88: 日期码格式： 标准格式 日期：按实际生产日期 Packaging Info: 9279SQ1 MA 3L EAN+UPC贴纸 ,无硼版本。UPC号码193052050014 Remark: 出加拿大 每款产品都需要加进口商贴纸 Zuru验货.日期跟踪码：产品外包装及产品本身都必须有日期跟踪码，ZURU标准格式日期码 | AC88: Summer Mo | AD88: 2.1581 | AE88: =J88*AD88 -> 1502.0376 | AF88: 94383-2.27 | AK88: =J88 -> 696 | AO88: =J88 -> 696 | AT88: =J88 -> 696 | AX88: =J88/6 -> 116 | BK88: MA布标 | BL88: =J88/60*1 -> 11.6 | BM88: =J88/60*9 -> 104.4 | BN88: =J88/60*10 -> 116 | BO88: =J88/60*10 -> 116 | BP88: =J88/60*10 -> 116 | BQ88: =J88/60*10 -> 116 | BR88: =J88/60*10 -> 116 | BZ88: =SUM(BL88:BY88) -> 696 | CA88: =J88-BZ88 -> 0
A89: 45586 | B89: TJX COMPANIES, INC | C89: 美国 | D89: 4500147804 | E89: Marshalls DC#881-120PCS , DC#884-96PCS, DC#886-132PCS , DC#887-120PCS , DC#888-132PCS | F89: 4500147804-40 | G89: 92114-S001 | H89: 92114-S001 | I89: 猫蛋二代(9279+9269)组装 | J89: 600 | K89: 0 | L89: 12 | M89: =J89/L89 -> 50 | N89: 45698 | O89: 45694 | Q89: PASS | U89: 2/18出 | V89: 11/4收到 | X89: 无 | Z89: 12/20-客供价格贴纸 | AB89: 日期码格式：ZURU INC(BVI) 标准格式 日期：按实际生产日期 Packaging Info: MA UPC包装+价格贴纸，价格贴纸客供。 #92114 是combo pack, 混装了 9269（华康生产）+9279（兴信生产），在兴信组装 。 Remark: 1. 产品和包装上印刷tracking code信息，格式为ZURU常规格式。 2. 分5个DC出货，每款产品每个DC的箱唛资料不同。具体分DC数量，请参考后面行项目备注。 3. ZURU QC验货。 | AC89: Emily Wu | AD89: 2.8218 | AE89: =J89*AD89 -> 1693.08 | AF89: 94381-2.27 | AI89: =J89 -> 600 | AO89: =J89 -> 600 | AS89: =J89 -> 600 | BH89: =J89 -> 600 | BK89: MA布标 | BM89: =J89/60*9 -> 90 | BN89: =J89/60*10 -> 100 | BO89: =J89/60*10 -> 100 | BP89: =J89/60*10 -> 100 | BQ89: =J89/60*10 -> 100 | BR89: =J89/60*10 -> 100 | BS89: =J89/60*1 -> 10 | BZ89: =SUM(BL89:BY89) -> 600 | CA89: =J89-BZ89 -> 0
A90: 45586 | B90: TJX COMPANIES, INC | C90: 美国 | D90: 4500147806 | E90: TJ MAXX DC#891-156PCS , DC#894-132PCS , DC#896-132PCS , DC#897-252PCS , DC#898-132PCS | F90: 4500147806-40 | G90: 92114-S001 | H90: 92114-S001 | I90: 猫蛋二代(9279+9269)组装 | J90: 804 | K90: 0 | L90: 12 | M90: =J90/L90 -> 67 | N90: 45698 | O90: 45694 | Q90: PASS | U90: 2/21出 | V90: 11/4收到 | X90: 无 | Z90: 12/20-客供价格贴纸 | AB90: 日期码格式：ZURU INC(BVI) 标准格式 日期：按实际生产日期 Packaging Info: MA UPC包装+价格贴纸，价格贴纸客供。 #92114 是combo pack, 混装了 9269（华康生产）+9279（兴信生产），在兴信组装 。 Remark: 1. 产品和包装上印刷tracking code信息，格式为ZURU常规格式。 2. 分5个DC出货，每款产品每个DC的箱唛资料不同。具体分DC数量，请参考后面行项目备注。 3. ZURU QC验货。 | AC90: Emily Wu | AD90: 2.8218 | AE90: =J90*AD90 -> 2268.7272 | AF90: 94380-2.27 | AI90: =J90 -> 804 | AO90: =J90 -> 804 | AS90: =J90 -> 804 | BH90: =J90 -> 804 | BK90: MA布标 | BM90: =J90/60*9 -> 120.6 | BN90: =J90/60*10 -> 134 | BO90: =J90/60*10 -> 134 | BP90: =J90/60*10 -> 134 | BQ90: =J90/60*10 -> 134 | BR90: =J90/60*10 -> 134 | BS90: =J90/60*1 -> 13.4 | BZ90: =SUM(BL90:BY90) -> 804 | CA90: =J90-BZ90 -> 0
A91: 45624 | B91: ARGOS LIMITED | C91: 英国 | D91: 4500151833 | E91: PO#394628-SKU #2259433 | F91: 4500151833-10 | G91: 92114-S001 | H91: 92114-S001 | I91: 猫蛋二代(9279+9269)组装 | J91: 1200 | K91: 0 | L91: 12 | M91: =J91/L91 -> 100 | N91: 45702 | O91: 45698 | Q91: PASS | U91: 2/17出 | V91: 12/16收到 | X91: 12/6-客人白色Cat.label 条码 | AB91: 日期码格式：ZURU INC(BVI) 标准格式 日期：按实际生产日期 Packaging Info: -92114 客版1L包装+客人白色Cat.label 1张覆盖ZURU条码 -注意Cat.label (要求易撕类贴纸，但是粘性不能过低），同时此贴纸每个订单都是不相同的(会显示客户对应的订单号），切勿翻旧订单购买，该贴纸由工厂自行 购买。 -订单对应客户2个PO号 ，备注有显示 ，注意分开做货/验货/装柜 ，混装有罚款。 Remark: *MA包装按最新版本安排即可 *包装日期码按ZURU格式即可，请确保不迟于外箱日期码，可等于或者早于外箱日期码，必须为法定工作日。 *外箱尺寸任何一条边长度超过75cm或者每箱重量超过10KG,需要在外箱上加三脚架符号，有问题请与ZURU跟单同事核实。 *订单必须经过ZURU QC验货并且通过后方可出货。 *订单出英国，请注意检查产品及包装应带UKCA图标，包装显示ZURU UK LTD信息，QC同事请查核，如有问题与跟单确认。 *条码扫描会显示客户7位数产品号 ，忽略订单显示的MA条码 *所有产品按符合欧洲标准走货，需要是不含微塑料版本 。 *涉及到硼的，请使用低硼版本 *客户不接受PVC材质包装 | AC91: Zoe Chen | AD91: 2.7507 | AE91: =J91*AD91 -> 3300.84 | AI91: =J91 -> 1200 | AO91: =J91 -> 1200 | AS91: =J91 -> 1200 | BH91: =J91 -> 1200 | BK91: MA布标 | BL91: =J91/60*1 -> 20 | BM91: =J91/60*9 -> 180 | BN91: =J91/60*10 -> 200 | BO91: =J91/60*10 -> 200 | BP91: =J91/60*10 -> 200 | BQ91: =J91/60*10 -> 200 | BR91: =J91/60*10 -> 200 | BZ91: =SUM(BL91:BY91) -> 1200 | CA91: =J91-BZ91 -> 0
A92: 45594 | B92: Distribuidora Liverpool S.A de C.V. | C92: 墨西哥 | D92: 4500149460 | E92: 61900883 | F92: 4500149460-60 | G92: 9279SQ1-S001 | H92: 9279SQ1-S001 | I92: 猫蛋二代 | J92: 468 | K92: 0 | L92: 12 | M92: =J92/L92 -> 39 | N92: 45708 | O92: 45703 | Q92: PASS | U92: 2/26出 | V92: 1/3收到 | X92: 2/8-进口商贴纸+价标贴纸 | Z92: 2/11-客供价格贴纸 | AB92: 日期码格式：ZURU INC(BVI) 标准格式 日期：按实际生产日期 Packaging Info: 9279SQ1:MA 3L UPC包装+进口商贴纸+价标贴纸+箱唛 Remark: 1. 此单价格贴纸（ZURU定购). 2.此单有第三方监柜，不用额外准备备品，会在大货中每款拆1pc，拆了包装的产品会由监装员用客供胶带封好或在外箱上写上""opened by telescope” | AC92: Ava Liang | AD92: 2.209 | AE92: =J92*AD92 -> 1033.812 | AF92: 94382-2.27 | AK92: =J92 -> 468 | AO92: =J92 -> 468 | AS92: =J92 -> 468 | AX92: =J92/6 -> 78 | BK92: MA布标 | BL92: =J92/60*1 -> 7.8 | BM92: =J92/60*9 -> 70.2 | BN92: =J92/60*10 -> 78 | BO92: =J92/60*10 -> 78 | BP92: =J92/60*10 -> 78 | BQ92: =J92/60*10 -> 78 | BR92: =J92/60*10 -> 78 | BZ92: =SUM(BL92:BY92) -> 468 | CA92: =J92-BZ92 -> 0
A93: 45643 | B93: MCD BRANDS SAS | C93: 乌拉圭 | D93: 4500153776 | F93: 4500153776-30 | G93: 9279SQ1-S001 | H93: 9279SQ1-S001 | I93: 猫蛋二代 | J93: 600 | K93: 0 | L93: 12 | M93: =J93/L93 -> 50 | N93: 45715 | O93: 45712 | Q93: PASS | U93: 收到SO | V93: 箱唛翻4500123283 | X93: 进口商贴纸+EAN贴纸翻4500123283 | AB93: 日期码格式：ZURU INC(BVI) 标准格式 日期：按实际生产日期 Packaging Info: 9279SQ1:MA 3L包装+进口商贴纸+EAN贴纸+箱唛，进口商贴纸/EAN贴纸/箱唛翻单PO4500123283 翻单箱唛请注意ZURU LOGO需要使用最新的 Remark: 进口商贴纸请多备料5pcs,出货后需要寄给客户 | AC93: Ava Liang | AD93: 2.209 | AE93: =J93*AD93 -> 1325.4 | AF93: 94577-3.18 | AK93: =J93 -> 600 | AO93: =J93 -> 600 | AS93: =J93 -> 600 | AX93: =J93/6 -> 100 | BK93: MA布标 | BL93: =J93/60*1 -> 10 | BM93: =J93/60*9 -> 90 | BN93: =J93/60*10 -> 100 | BO93: =J93/60*10 -> 100 | BP93: =J93/60*10 -> 100 | BQ93: =J93/60*10 -> 100 | BR93: =J93/60*10 -> 100 | BZ93: =SUM(BL93:BY93) -> 600 | CA93: =J93-BZ93 -> 0
A94: 45645 | B94: BEALL's OUTLET STORES | C94: 美国 | D94: 4500154420 | E94: PO# 1488610 | F94: 4500154420-10 | G94: 9279-S001 | H94: 9279-S001 | I94: 猫蛋二代 | J94: 744 | K94: 0 | L94: 24 | M94: =J94/L94 -> 31 | N94: 45346 | O94: 45708 | Q94: PASS | U94: 3/4-3/5出 | V94: 12/25收到 | X94: 无 | Z94: 1/3-客供价格贴纸 | AB94: 日期码格式：ZURU INC(BVI) 标准格式 日期：按实际生产日期 Packaging Info: 1.ZURU最新MA UPC包装(优先1L) + 客供价格贴纸（贴在产品包装右下角，跟单找第三方订购贴纸寄到工厂）。 价格贴纸显示以下信息，需按单贴对，不要混了。 Remark: 1.ZURU最新MA UPC包装(优先1L) + 客供价格贴纸（贴在产品包装右下角，跟单找第三方订购贴纸寄到工厂）。 价格贴纸显示以下信息，需按单贴对，不要混了。 9279-S001 $ 12.00/ $ 7.99 SKU #: 88047211 UPC: 300880472110 FINELINE STYLE NO: 9485 2. 配比：7 assortment (6 common + 1 rare); RAGDOLL CA (RARE): AMERICAN SHORTHAIR: CALICO CAT: BLACK CAT: BENGAL CAT: EXOTIC CAT: CHINCHILLA CAT= 1:9:10:10:10: 10:10; 3. 所有产品外包装及产品本身都必须有日期跟踪码(ZURU标准日期码格式，年月日的日期自行调整，但不能为周末)，并且确保产品及外包装的日期跟踪码要一致. 4. 此单包含6张客户PO， 需按照印有不同PO箱唛及箱数的外箱进行包装. 注意：客供贴纸上会显示客户PO号，入箱需要确保产品上的贴纸与外箱上的PO# 一致。 PO# 1488610 SHIP TO: Bealls DIST CENTER #115 2100 47th Ter E Bradenton, FL 34203-3774 PO# 1488633 SHIP TO: Bealls DIST CENTER #115 2100 47th Ter E Bradenton, FL 34203-3774 PO# 1488634 SHIP TO: Bealls DIST CENTER #115 2100 47th Ter E Bradenton, FL 34203-3774 PO# 1488643 SHIP TO: Bealls DIST CENTER #115 2100 47th Ter E Bradenton, FL 34203-3774 PO# 1488644 SHIP TO: Bealls DIST CENTER #115 2100 47th Ter E Bradenton, FL 34203-3774 PO# 1488611 SHIP TO: TX Logistics Support Center #995 506 Beall Blvd. Jacksonville, TX 75766 | AC94: Yoyo Yi | AD94: 2.2394 | AE94: =J94*AD94 -> 1666.1136 | AF94: 94442-3.5 | AI94: =J94 -> 744 | AO94: =J94 -> 744 | AS94: =J94 -> 744 | BK94: MA布标 | BM94: =J94/60*9 -> 111.6 | BN94: =J94/60*10 -> 124 | BO94: =J94/60*10 -> 124 | BP94: =J94/60*10 -> 124 | BQ94: =J94/60*10 -> 124 | BR94: =J94/60*10 -> 124 | BS94: =J94/60*1 -> 12.4 | BZ94: =SUM(BL94:BY94) -> 744 | CA94: =J94-BZ94 -> 0
A95: 45645 | B95: BEALL's OUTLET STORES | C95: 美国 | D95: 4500154420 | E95: PO# 1488633 | F95: 4500154420-20 | G95: 9279-S001 | H95: 9279-S001 | I95: 猫蛋二代 | J95: 744 | K95: 0 | L95: 24 | M95: =J95/L95 -> 31 | N95: 45346 | O95: 45708 | Q95: PASS | U95: 3/4-3/5出 | V95: 12/25收到 | X95: 无 | Z95: 1/3-客供价格贴纸 | AB95: 日期码格式：ZURU INC(BVI) 标准格式 日期：按实际生产日期 Packaging Info: 1.ZURU最新MA UPC包装(优先1L) + 客供价格贴纸（贴在产品包装右下角，跟单找第三方订购贴纸寄到工厂）。 价格贴纸显示以下信息，需按单贴对，不要混了。 Remark: 1.ZURU最新MA UPC包装(优先1L) + 客供价格贴纸（贴在产品包装右下角，跟单找第三方订购贴纸寄到工厂）。 价格贴纸显示以下信息，需按单贴对，不要混了。 9279-S001 $ 12.00/ $ 7.99 SKU #: 88047211 UPC: 300880472110 FINELINE STYLE NO: 9485 2. 配比：7 assortment (6 common + 1 rare); RAGDOLL CA (RARE): AMERICAN SHORTHAIR: CALICO CAT: BLACK CAT: BENGAL CAT: EXOTIC CAT: CHINCHILLA CAT= 1:9:10:10:10: 10:10; 3. 所有产品外包装及产品本身都必须有日期跟踪码(ZURU标准日期码格式，年月日的日期自行调整，但不能为周末)，并且确保产品及外包装的日期跟踪码要一致. 4. 此单包含6张客户PO， 需按照印有不同PO箱唛及箱数的外箱进行包装. 注意：客供贴纸上会显示客户PO号，入箱需要确保产品上的贴纸与外箱上的PO# 一致。 PO# 1488610 SHIP TO: Bealls DIST CENTER #115 2100 47th Ter E Bradenton, FL 34203-3774 PO# 1488633 SHIP TO: Bealls DIST CENTER #115 2100 47th Ter E Bradenton, FL 34203-3774 PO# 1488634 SHIP TO: Bealls DIST CENTER #115 2100 47th Ter E Bradenton, FL 34203-3774 PO# 1488643 SHIP TO: Bealls DIST CENTER #115 2100 47th Ter E Bradenton, FL 34203-3774 PO# 1488644 SHIP TO: Bealls DIST CENTER #115 2100 47th Ter E Bradenton, FL 34203-3774 PO# 1488611 SHIP TO: TX Logistics Support Center #995 506 Beall Blvd. Jacksonville, TX 75766 | AC95: Yoyo Yi | AD95: 2.2394 | AE95: =J95*AD95 -> 1666.1136 | AF95: 94442-3.5 | AI95: =J95 -> 744 | AO95: =J95 -> 744 | AS95: =J95 -> 744 | BK95: MA布标 | BM95: =J95/60*9 -> 111.6 | BN95: =J95/60*10 -> 124 | BO95: =J95/60*10 -> 124 | BP95: =J95/60*10 -> 124 | BQ95: =J95/60*10 -> 124 | BR95: =J95/60*10 -> 124 | BS95: =J95/60*1 -> 12.4 | BZ95: =SUM(BL95:BY95) -> 744 | CA95: =J95-BZ95 -> 0
A96: 45645 | B96: BEALL's OUTLET STORES | C96: 美国 | D96: 4500154420 | E96: PO# 1488634 | F96: 4500154420-30 | G96: 9279-S001 | H96: 9279-S001 | I96: 猫蛋二代 | J96: 480 | K96: 0 | L96: 24 | M96: =J96/L96 -> 20 | N96: 45346 | O96: 45708 | Q96: PASS | U96: 3/4-3/5出 | V96: 12/25收到 | X96: 无 | Z96: 1/3-客供价格贴纸 | AB96: 日期码格式：ZURU INC(BVI) 标准格式 日期：按实际生产日期 Packaging Info: 1.ZURU最新MA UPC包装(优先1L) + 客供价格贴纸（贴在产品包装右下角，跟单找第三方订购贴纸寄到工厂）。 价格贴纸显示以下信息，需按单贴对，不要混了。 Remark: 1.ZURU最新MA UPC包装(优先1L) + 客供价格贴纸（贴在产品包装右下角，跟单找第三方订购贴纸寄到工厂）。 价格贴纸显示以下信息，需按单贴对，不要混了。 9279-S001 $ 12.00/ $ 7.99 SKU #: 88047211 UPC: 300880472110 FINELINE STYLE NO: 9485 2. 配比：7 assortment (6 common + 1 rare); RAGDOLL CA (RARE): AMERICAN SHORTHAIR: CALICO CAT: BLACK CAT: BENGAL CAT: EXOTIC CAT: CHINCHILLA CAT= 1:9:10:10:10: 10:10; 3. 所有产品外包装及产品本身都必须有日期跟踪码(ZURU标准日期码格式，年月日的日期自行调整，但不能为周末)，并且确保产品及外包装的日期跟踪码要一致. 4. 此单包含6张客户PO， 需按照印有不同PO箱唛及箱数的外箱进行包装. 注意：客供贴纸上会显示客户PO号，入箱需要确保产品上的贴纸与外箱上的PO# 一致。 PO# 1488610 SHIP TO: Bealls DIST CENTER #115 2100 47th Ter E Bradenton, FL 34203-3774 PO# 1488633 SHIP TO: Bealls DIST CENTER #115 2100 47th Ter E Bradenton, FL 34203-3774 PO# 1488634 SHIP TO: Bealls DIST CENTER #115 2100 47th Ter E Bradenton, FL 34203-3774 PO# 1488643 SHIP TO: Bealls DIST CENTER #115 2100 47th Ter E Bradenton, FL 34203-3774 PO# 1488644 SHIP TO: Bealls DIST CENTER #115 2100 47th Ter E Bradenton, FL 34203-3774 PO# 1488611 SHIP TO: TX Logistics Support Center #995 506 Beall Blvd. Jacksonville, TX 75766 | AC96: Yoyo Yi | AD96: 2.2394 | AE96: =J96*AD96 -> 1074.912 | AF96: 94442-3.5 | AI96: =J96 -> 480 | AO96: =J96 -> 480 | AS96: =J96 -> 480 | BK96: MA布标 | BM96: =J96/60*9 -> 72 | BN96: =J96/60*10 -> 80 | BO96: =J96/60*10 -> 80 | BP96: =J96/60*10 -> 80 | BQ96: =J96/60*10 -> 80 | BR96: =J96/60*10 -> 80 | BS96: =J96/60*1 -> 8 | BZ96: =SUM(BL96:BY96) -> 480 | CA96: =J96-BZ96 -> 0
A97: 45645 | B97: BEALL's OUTLET STORES | C97: 美国 | D97: 4500154420 | E97: PO# 1488643 | F97: 4500154420-40 | G97: 9279-S001 | H97: 9279-S001 | I97: 猫蛋二代 | J97: 744 | K97: 0 | L97: 24 | M97: =J97/L97 -> 31 | N97: 45346 | O97: 45708 | Q97: PASS | U97: 3/4-3/5出 | V97: 12/25收到 | X97: 无 | Z97: 1/3-客供价格贴纸 | AB97: 日期码格式：ZURU INC(BVI) 标准格式 日期：按实际生产日期 Packaging Info: 1.ZURU最新MA UPC包装(优先1L) + 客供价格贴纸（贴在产品包装右下角，跟单找第三方订购贴纸寄到工厂）。 价格贴纸显示以下信息，需按单贴对，不要混了。 Remark: 1.ZURU最新MA UPC包装(优先1L) + 客供价格贴纸（贴在产品包装右下角，跟单找第三方订购贴纸寄到工厂）。 价格贴纸显示以下信息，需按单贴对，不要混了。 9279-S001 $ 12.00/ $ 7.99 SKU #: 88047211 UPC: 300880472110 FINELINE STYLE NO: 9485 2. 配比：7 assortment (6 common + 1 rare); RAGDOLL CA (RARE): AMERICAN SHORTHAIR: CALICO CAT: BLACK CAT: BENGAL CAT: EXOTIC CAT: CHINCHILLA CAT= 1:9:10:10:10: 10:10; 3. 所有产品外包装及产品本身都必须有日期跟踪码(ZURU标准日期码格式，年月日的日期自行调整，但不能为周末)，并且确保产品及外包装的日期跟踪码要一致. 4. 此单包含6张客户PO， 需按照印有不同PO箱唛及箱数的外箱进行包装. 注意：客供贴纸上会显示客户PO号，入箱需要确保产品上的贴纸与外箱上的PO# 一致。 PO# 1488610 SHIP TO: Bealls DIST CENTER #115 2100 47th Ter E Bradenton, FL 34203-3774 PO# 1488633 SHIP TO: Bealls DIST CENTER #115 2100 47th Ter E Bradenton, FL 34203-3774 PO# 1488634 SHIP TO: Bealls DIST CENTER #115 2100 47th Ter E Bradenton, FL 34203-3774 PO# 1488643 SHIP TO: Bealls DIST CENTER #115 2100 47th Ter E Bradenton, FL 34203-3774 PO# 1488644 SHIP TO: Bealls DIST CENTER #115 2100 47th Ter E Bradenton, FL 34203-3774 PO# 1488611 SHIP TO: TX Logistics Support Center #995 506 Beall Blvd. Jacksonville, TX 75766 | AC97: Yoyo Yi | AD97: 2.2394 | AE97: =J97*AD97 -> 1666.1136 | AF97: 94442-3.5 | AI97: =J97 -> 744 | AO97: =J97 -> 744 | AS97: =J97 -> 744 | BK97: MA布标 | BM97: =J97/60*9 -> 111.6 | BN97: =J97/60*10 -> 124 | BO97: =J97/60*10 -> 124 | BP97: =J97/60*10 -> 124 | BQ97: =J97/60*10 -> 124 | BR97: =J97/60*10 -> 124 | BS97: =J97/60*1 -> 12.4 | BZ97: =SUM(BL97:BY97) -> 744 | CA97: =J97-BZ97 -> 0
A98: 45645 | B98: BEALL's OUTLET STORES | C98: 美国 | D98: 4500154420 | E98: PO# 1488644 | F98: 4500154420-50 | G98: 9279-S001 | H98: 9279-S001 | I98: 猫蛋二代 | J98: 480 | K98: 0 | L98: 24 | M98: =J98/L98 -> 20 | N98: 45346 | O98: 45708 | Q98: PASS | U98: 3/4-3/5出 | V98: 12/25收到 | X98: 无 | Z98: 1/3-客供价格贴纸 | AB98: 日期码格式：ZURU INC(BVI) 标准格式 日期：按实际生产日期 Packaging Info: 1.ZURU最新MA UPC包装(优先1L) + 客供价格贴纸（贴在产品包装右下角，跟单找第三方订购贴纸寄到工厂）。 价格贴纸显示以下信息，需按单贴对，不要混了。 Remark: 1.ZURU最新MA UPC包装(优先1L) + 客供价格贴纸（贴在产品包装右下角，跟单找第三方订购贴纸寄到工厂）。 价格贴纸显示以下信息，需按单贴对，不要混了。 9279-S001 $ 12.00/ $ 7.99 SKU #: 88047211 UPC: 300880472110 FINELINE STYLE NO: 9485 2. 配比：7 assortment (6 common + 1 rare); RAGDOLL CA (RARE): AMERICAN SHORTHAIR: CALICO CAT: BLACK CAT: BENGAL CAT: EXOTIC CAT: CHINCHILLA CAT= 1:9:10:10:10: 10:10; 3. 所有产品外包装及产品本身都必须有日期跟踪码(ZURU标准日期码格式，年月日的日期自行调整，但不能为周末)，并且确保产品及外包装的日期跟踪码要一致. 4. 此单包含6张客户PO， 需按照印有不同PO箱唛及箱数的外箱进行包装. 注意：客供贴纸上会显示客户PO号，入箱需要确保产品上的贴纸与外箱上的PO# 一致。 PO# 1488610 SHIP TO: Bealls DIST CENTER #115 2100 47th Ter E Bradenton, FL 34203-3774 PO# 1488633 SHIP TO: Bealls DIST CENTER #115 2100 47th Ter E Bradenton, FL 34203-3774 PO# 1488634 SHIP TO: Bealls DIST CENTER #115 2100 47th Ter E Bradenton, FL 34203-3774 PO# 1488643 SHIP TO: Bealls DIST CENTER #115 2100 47th Ter E Bradenton, FL 34203-3774 PO# 1488644 SHIP TO: Bealls DIST CENTER #115 2100 47th Ter E Bradenton, FL 34203-3774 PO# 1488611 SHIP TO: TX Logistics Support Center #995 506 Beall Blvd. Jacksonville, TX 75766 | AC98: Yoyo Yi | AD98: 2.2394 | AE98: =J98*AD98 -> 1074.912 | AF98: 94442-3.5 | AI98: =J98 -> 480 | AO98: =J98 -> 480 | AS98: =J98 -> 480 | BK98: MA布标 | BM98: =J98/60*9 -> 72 | BN98: =J98/60*10 -> 80 | BO98: =J98/60*10 -> 80 | BP98: =J98/60*10 -> 80 | BQ98: =J98/60*10 -> 80 | BR98: =J98/60*10 -> 80 | BS98: =J98/60*1 -> 8 | BZ98: =SUM(BL98:BY98) -> 480 | CA98: =J98-BZ98 -> 0
A99: 45645 | B99: BEALL's OUTLET STORES | C99: 美国 | D99: 4500154420 | E99: PO# 1488611 | F99: 4500154420-60 | G99: 9279-S001 | H99: 9279-S001 | I99: 猫蛋二代 | J99: 480 | K99: 0 | L99: 24 | M99: =J99/L99 -> 20 | N99: 45346 | O99: 45708 | Q99: PASS | U99: 3/4-3/5出 | V99: 12/25收到 | X99: 无 | Z99: 1/3-客供价格贴纸 | AB99: 日期码格式：ZURU INC(BVI) 标准格式 日期：按实际生产日期 Packaging Info: 1.ZURU最新MA UPC包装(优先1L) + 客供价格贴纸（贴在产品包装右下角，跟单找第三方订购贴纸寄到工厂）。 价格贴纸显示以下信息，需按单贴对，不要混了。 Remark: 1.ZURU最新MA UPC包装(优先1L) + 客供价格贴纸（贴在产品包装右下角，跟单找第三方订购贴纸寄到工厂）。 价格贴纸显示以下信息，需按单贴对，不要混了。 9279-S001 $ 12.00/ $ 7.99 SKU #: 88047211 UPC: 300880472110 FINELINE STYLE NO: 9485 2. 配比：7 assortment (6 common + 1 rare); RAGDOLL CA (RARE): AMERICAN SHORTHAIR: CALICO CAT: BLACK CAT: BENGAL CAT: EXOTIC CAT: CHINCHILLA CAT= 1:9:10:10:10: 10:10; 3. 所有产品外包装及产品本身都必须有日期跟踪码(ZURU标准日期码格式，年月日的日期自行调整，但不能为周末)，并且确保产品及外包装的日期跟踪码要一致. 4. 此单包含6张客户PO， 需按照印有不同PO箱唛及箱数的外箱进行包装. 注意：客供贴纸上会显示客户PO号，入箱需要确保产品上的贴纸与外箱上的PO# 一致。 PO# 1488610 SHIP TO: Bealls DIST CENTER #115 2100 47th Ter E Bradenton, FL 34203-3774 PO# 1488633 SHIP TO: Bealls DIST CENTER #115 2100 47th Ter E Bradenton, FL 34203-3774 PO# 1488634 SHIP TO: Bealls DIST CENTER #115 2100 47th Ter E Bradenton, FL 34203-3774 PO# 1488643 SHIP TO: Bealls DIST CENTER #115 2100 47th Ter E Bradenton, FL 34203-3774 PO# 1488644 SHIP TO: Bealls DIST CENTER #115 2100 47th Ter E Bradenton, FL 34203-3774 PO# 1488611 SHIP TO: TX Logistics Support Center #995 506 Beall Blvd. Jacksonville, TX 75766 | AC99: Yoyo Yi | AD99: 2.2394 | AE99: =J99*AD99 -> 1074.912 | AF99: 94442-3.5 | AI99: =J99 -> 480 | AO99: =J99 -> 480 | AS99: =J99 -> 480 | BK99: MA布标 | BM99: =J99/60*9 -> 72 | BN99: =J99/60*10 -> 80 | BO99: =J99/60*10 -> 80 | BP99: =J99/60*10 -> 80 | BQ99: =J99/60*10 -> 80 | BR99: =J99/60*10 -> 80 | BS99: =J99/60*1 -> 8 | BZ99: =SUM(BL99:BY99) -> 480 | CA99: =J99-BZ99 -> 0
A100: 45665 | B100: TJX UK | C100: 英国 | D100: 4500155467 | E100: TJX UK: PO#50565028 | F100: 4500155467-70 | G100: 9279-S001-3L | H100: 9279-S001 | I100: 猫蛋二代 | J100: 1248 | K100: 0 | L100: 24 | M100: =J100/L100 -> 52 | N100: 45719 | O100: 45715 | Q100: PASS | U100: 3/13出 | V100: 1/8收到 | X100: 无 | Z100: 1/10-客供价格贴纸 | AB100: 日期码格式：ZURU INC(BVI) 标准格式 日期：按实际生产日期 Packaging Info: TJX UK:PO#50565028(9279) 9279: MA 3L(23Lwarning) 最新UPC包装+1张客供价格贴纸 Remark: 1. 出往UK的产品+包装务必打上UKCA logo ，否则客人会退货且当地会有罚款； 2. 订单必须经过ZURU QC验货并且通过后方可出货； 3. 订单每行对应客人不同的PO， 箱唛也有不同，做货的时候请分开堆放； 4. 订单每行对应客人不同的PO，即同款item的价格贴纸都不相同，请注意收到贴纸后不要弄混!（客人PO号请参考PO最后一栏remark）； 5. 价格贴纸位置为产品正面右上角，不能遮住产品信息，大货生产前，请把贴纸位置先发给跟单确认 6. 涉及到相关款式会有闪粉的或者微塑料的，请统一默认出无闪粉或者不含微塑料版本; 7. 外箱封箱必须是工字型封箱方式； | AC100: Sandy Shao | AD100: 2.1295 | AE100: =J100*AD100 -> 2657.616 | AF100: 94522-3.12 | AK100: =J100 -> 1248 | AO100: =J100 -> 1248 | AS100: =J100 -> 1248 | BK100: MA布标 | BL100: =J100/60*1 -> 20.8 | BM100: =J100/60*9 -> 187.2 | BN100: =J100/60*10 -> 208 | BO100: =J100/60*10 -> 208 | BP100: =J100/60*10 -> 208 | BQ100: =J100/60*10 -> 208 | BR100: =J100/60*10 -> 208 | BZ100: =SUM(BL100:BY100) -> 1248 | CA100: =J100-BZ100 -> 0
...

Sheet 9298
A1: ZURU Rainbocorn 狗蛋四代蛋毛絨公仔生产排期表 #9298 | BH1: 无闪粉毛绒 | BO1: 有闪粉毛绒 | CA1: 贵妇犬(Poodle) B | CB1: 咖啡斑点狗(Brown Dalnatia) G | CC1: 黑白斑点狗(Dalmatian) D | CD1: 猎犬 (Hound dog) H | CE1: 雪纳瑞(Schnauzer)E | CF1: 牧羊犬(Shepherd) A | CG1: 柯基犬（稀有款）
A2: =#REF! -> #REF! | H2: （黃色表示更改或增加） | K2: （蓝色表示已完货） | O2: （綠色表示調整貨期） | AH2: 收縮膜 | AO2: 收藏指南 | AR2: 口水胶 | BH2: 10 | BI2: 10 | BJ2: 10 | BK2: 10 | BL2: 10 | BM2: 8 | BN2: 2 | BO2: 10 | BP2: 10 | BQ2: 10 | BR2: 10 | BS2: 10 | BT2: 8 | BU2: 2
A3: 接单期 | B3: 第三方客户名称 | C3: 国家 | D3: PO号 | E3: 客户PO号 | F3: SKU号 | G3: 货号 | H3: 名称 | I3: 数量 | J3: 内箱装箱数量(pcs) | K3: 装箱数（PCS） | L3: 总箱数 | M3: 计划出货期 | N3: 计划验货期 | O3: 第三方验货期 | P3: 驗貨結果 | Q3: 送货情况 | R3: 欠数 | S3: 贴纸 | T3: 下单情况 | U3: 船期SO | V3: 箱唛资料(收到日期) | W3: 外箱贴纸 | X3: 贴纸AI(收到日期) | Y3: 客供物料 | Z3: 日期码 | AA3: 备注 | AB3: ZURU 跟单 | AC3: 单价USD | AD3: 金额USD | AE3: 發票號 | AF3: 系统货号 | AG3: 是否入系统 | AH3: MA 1語收縮膜 A版本 | AI3: MA 1語收縮膜 B版本 | AJ3: MA 1語收縮膜 C版本 | AK3: MA 3语收缩膜 A版本 | AL3: MA 3语收缩膜 B版本 | AM3: MA 3语收缩膜 C版本 | AN3: 客版收縮膜 | AO3: MA 5语 收藏指南 A版本 | AP3: MA 5语 收藏指南 B版本 | AQ3: 客版收藏指南 | AR3: MA口水胶 | AS3: MA口水胶-无闪粉 | AT3: 客版无硼口水胶 | AU3: 客版无硼口水胶-无闪粉 | AV3: PDQ TQ1-1L （3L通用） | AW3: PDQ TQ1-1L （3L通用）-B版 | AX3: PDQ TQ2-1L （3L通用） | AY3: PDQ TQ2-1L （3L通用）-B版本 | AZ3: PDQ TQ3-WM CA | BA3: PDQ TQ4 | BB3: PDQ TQ5-WM单 | BC3: 客办PDQ | BD3: 托盘 | BE3: 展示架-1L | BF3: 布標 | BG3: 无闪粉毛绒 | BH3: 贵妇犬(Poodle) B | BI3: 咖啡斑点狗(Brown Dalnatia) G | BJ3: 黑白斑点狗(Dalmatian) D | BK3: 猎犬 (Hound dog) H | BL3: 雪纳瑞(Schnauzer)E | BM3: 牧羊犬(Shepherd) A | BN3: 柯基犬（稀有款） | BO3: 贵妇犬(Poodle) B | BP3: 咖啡斑点狗(Brown Dalnatia) G | BQ3: 黑白斑点狗(Dalmatian) D | BR3: 猎犬 (Hound dog) H | BS3: 雪纳瑞(Schnauzer)E | BT3: 牧羊犬(Shepherd) A | BU3: 柯基犬（稀有款） | BV3: 总数 | BW3: 相差 | BX3: 送货情况 | BY3: 系统出单 | BZ3: 贴纸情况 | CA3: 34372 | CB3: 23076 | CC3: 36799 | CD3: 30293 | CE3: 31863 | CF3: 27176 | CG3: 22206
A4: 45418 | B4: ZURU | C4: 库有 | D4: ZMPO24325 | G4: 9298TQ1-S001 | H4: 狗蛋四代PDQ | I4: 50 | J4: 0 | K4: 0 | L4: 0 | M4: 45432 | N4: 45428 | V4: 无 | X4: 无 | AA4: 大货最新版本/只需要空PDQ/不需要里面的产品;备注：收到样品订单后尽快安排 ，注意样板品质质量要求要高于大货品质要求 ，送货时必须要附带送货单(没有送货单和QC检验合格报告的仓库一律拒绝收货)，请知悉，谢谢！ | AF4: 过渡 | AG4: 过渡 | AV4: =I4/6 -> 8.3333333 | BV4: =SUM(BH4:BU4) -> 0 | BW4: 0
A5: 45463 | B5: DM LLC | C5: 俄罗斯 | D5: 4500137881 | E5: Ural | F5: 4500137881-120 | G5: 9298TQ1-S001 | H5: 狗蛋四代PDQ | I5: 5532 | J5: 0 | K5: 12 | L5: =I5/K5 -> 461 | M5: 45498 | N5: 45500 | P5: PASS | U5: 预计7/31出 | V5: 6/26收到 | X5: 7/9收到进口商贴纸+EAN条码贴纸 | AA5: 日期码格式：彩卡/收缩膜/PDQ/外箱不要打ZURU标准日期码！ 日期： Packaging Info: 9298TQ1: 优先1L MA 收缩膜+进口商贴纸+EAN条码贴纸; MA PDQ/指南/说明书(如有); 注意 ：彩卡/收缩膜/PDQ/外箱不要打ZURU标准日期码！！ Remark: 1. 出 Bekasovo 2和Ural; | AB5: Ann Zhang | AC5: 2.1606 | AD5: =AC5*I5 -> 11952.439 | AE5: 88869-1.4 | AF5: 9298TQ1-S001 | AG5: 已入 | AH5: =I5 -> 5532 | AO5: =I5 -> 5532 | AS5: =I5 -> 5532 | AV5: =I5/6 -> 922 | BF5: MA布标 | BH5: =I5/60*10 -> 922 | BI5: =I5/60*10 -> 922 | BJ5: =I5/60*10 -> 922 | BK5: =I5/60*10 -> 922 | BL5: =I5/60*10 -> 922 | BM5: =I5/60*8 -> 737.6 | BU5: =I5/60*2 -> 184.4 | BV5: =SUM(BH5:BU5) -> 5532 | BW5: =I5-BV5 -> 0
A6: 45546 | B6: MEIJER | C6: 美国 | D6: 4500145013 | E6: Meijer客户PO2 16354547 | F6: 4500145013-110 | G6: 9298TQ1-S002 | H6: 狗蛋四代 | I6: 1560 | J6: 0 | K6: 6 | L6: =I6/K6 -> 260 | M6: 45628 | N6: 45624 | P6: PASS | U6: 12/3出 | V6: 10/18收到 | X6: 无 | AA6: 日期码格式： 标准格式 日期：按实际生产日期 Packaging Info: 1. MA 1L 包装 2. 客人指定箱唛排版 Remark: 出货前 Zuru QC 验货 | AB6: Minny Peng | AC6: 2.1991 | AD6: =AC6*I6 -> 3430.596 | AE6: ZB00081-3.31 | AF6: 9298TQ1-S002 | AG6: 已入 | AI6: =I6 -> 1560 | AO6: =I6 -> 1560 | AS6: =I6 -> 1560 | AV6: =I6/6 -> 260 | BF6: MA布标 | BH6: =I6/60*10 -> 260 | BI6: =I6/60*10 -> 260 | BJ6: =I6/60*10 -> 260 | BK6: =I6/60*10 -> 260 | BL6: =I6/60*10 -> 260 | BM6: =I6/60*8 -> 208 | BU6: =I6/60*2 -> 52 | BV6: =SUM(BH6:BU6) -> 1560 | BW6: =I6-BV6 -> 0
A7: 45595 | B7: TIENDAS SORIANA, S.A. DE C.V. | C7: 墨西哥 | D7: 4500149669 | F7: 4500149669-40 | G7: 9298TQ1-S001 | H7: 狗蛋四代PDQ | I7: 3180 | J7: 0 | K7: 12 | L7: =I7/K7 -> 265 | M7: 45642 | N7: 45664 | P7: PASS | U7: 1/14出 | V7: 12/13收到 | X7: 11/27-红色logo贴纸+进口商贴纸 | AA7: 日期码格式：ZURU INC(BVI) 标准格式 日期：按实际生产日期 Packaging Info: 4. 9298TQ1：MA 3L UPC包装+MA 多语收藏指南+MA PDQ包装+1个小的红色logo贴纸+进口商贴纸+箱唛 Remark: 4. 9298：7 assortment (6 common + 1 rare)=CORGI:SHEPHERD:POODLE:DALMATIAN:SCHNAUZER:BROWN DALNATIAN:HOUND DOG=2:8:10:10:10:10:10; 6. 集装箱及装柜要求：集装箱不能有破洞；不能太脏 7.每个item需要放1整箱在每个集装箱门口 8.装柜的时候要前、中、后拍照 | AB7: Ever Li | AC7: 2.1809 | AD7: =AC7*I7 -> 6935.262 | AE7: 94030-1.14 | AF7: 9298TQ1-S001-3L | AG7: 已入 | AK7: =I7 -> 3180 | AO7: =I7 -> 3180 | AS7: =I7 -> 3180 | AV7: =I7/6 -> 530 | BF7: MA布标 | BH7: =I7/60*10 -> 530 | BI7: =I7/60*10 -> 530 | BJ7: =I7/60*10 -> 530 | BK7: =I7/60*10 -> 530 | BL7: =I7/60*10 -> 530 | BM7: =I7/60*8 -> 424 | BN7: =I7/60*2 -> 106 | BV7: =SUM(BH7:BU7) -> 3180 | BW7: =I7-BV7 -> 0
A8: 45596 | B8: DOLLAR GENERAL CORPORATION | C8: 美国 | D8: 4500149775 | E8: PO#待定to DC96630 | F8: 4500149775-10 | G8: 9298-S006-PKC | H8: 狗蛋四代胶袋2只装 | I8: 33684 | J8: 0 | K8: 6 | L8: =I8/K8 -> 5614 | M8: 45646 | N8: 45642 | O8: 12/23 第三方 | P8: PASS | U8: 1/8出 | V8: 11/7收到 | X8: 无 | Z8: 11/8收到客办收缩膜文档 蛋壳日期码：DOLGEN31704302A25 （纸箱无需盖印日期） | AA8: 日期码格式：DOLLAR GENERAL 格式日期码 日期： Packaging Info: 客版1L收缩膜(AWS跟单稍后提供) + 说明书或者收藏指南优先使用ZURU MA 1L的，如没有1L请邮件告知。 Remark: 1.包装： 客版1L收缩膜(AWS跟单稍后提供).说明书或者指南请优先使用ZURU MA 1L。 客户要求： "产品和包装不能含有PFAS 物质以及1,4 dioxane" 客户指定TUV来厂抽样+验货，会做实际测试。请确保产品符合美国测试标准，可以pass测试。 外箱必须是双坑的。 2.日期码：产品和包装上必须有客版格式日期码。 （1）产品上需打客版日期码 内容： DOLGEN31704302A25 A代表ETD 1月。 （2）包装日期码31704302A25（已印在客版包装UPC条码旁竖排文字了，无需额外做日期码在包装上）。 （3）客版UPC#430001805807 3.无价贴 。 4.客户指定TUV做100%大货验货+抽样： 12月23日早上进行客人指定TUV的100%大货验货+CT抽测试样（每款每色各12pcs带包装产品 + 5套RANDOM产品的光身样，可以参考4500144744的抽样标准。请在12 月20日前完成ZURU QC验货，并当天13点前提供验货报告+大货图片给跟单。 5.样板需求，需11月20日前寄出每款每色各6套样板给ZURU跟单转寄客人。 6.箱唛：此客人要求严格，外箱不接受水贴纸，材积以及重量必须按照以下要求，否则不符会导致验货fail从而影响货期而产生罚款。 大货外箱材积绝对不可大于下述数据，材积只接受3%的变小；重量正负不得超过以下列出数据的5%，接受外箱以印章方式印上实际毛 重。 大货外箱尺寸请保持：43.5*22.5*20.5cm ，材积必须不能大于0.7098CubeFeet（0.0201CBM);外箱毛重3.5LBS（1.59KGS）。 如有尺寸变小，请提前通知hailey。 重要提醒：外箱材质必须是双层瓦楞纸，不接受单层，会导致第三方验货fail以及返工和罚款。 7.此客人不接受任何理由的延期，会有高额罚金产生. 8.如散货入仓需在货车上加防护网. 9.出货配比：ZURU MA配比 。 2pcs in one polybag;2pcs入一个内袋，3个内袋6pcs入一 个外箱。 10.内袋需要警示语，内袋需胶纸封口，内袋aws跟单邮件发送 。 | AB8: Hailey Yu | AC8: 2.2102 | AD8: =AC8*I8 -> 74448.377 | AE8: 88947-1.8 | AF8: 9298-S006-PKC | AG8: 过渡 | AN8: =I8 -> 33684 | AO8: =I8 -> 33684 | AS8: =I8 -> 33684 | BF8: MA布标 | BH8: =I8/60*10 -> 5614 | BI8: =I8/60*10 -> 5614 | BJ8: =I8/60*10 -> 5614 | BK8: =I8/60*10 -> 5614 | BL8: =I8/60*10 -> 5614 | BM8: =I8/60*8 -> 4491.2 | BN8: =I8/60*2 -> 1122.8 | BV8: =SUM(BH8:BU8) -> 33684 | BW8: =I8-BV8 -> 0
