Workbook

Sheet 名称
A1: 货号 | B1: 贴纸用量 | C1: 装箱数 | D1: 系列 | E1: 名称 | F1: 车间
A2: SR000 | B2: 3 | C2: 360 | D2: 二代
A3: SR100 | B3: 7 | C3: 12 | D3: 二代 | F3: 湖南
A4: SR100CDU-16 | B4: 7 | C4: 16 | D4: 二代 | F4: 湖南
A5: SR100CDU-24 | B5: 7 | C5: 24 | D5: 二代 | F5: 湖南
A6: SR101CDU | B6: 5 | C6: 24 | D6: 二代 | F6: 湖南
A7: SR160 | B7: 5 | C7: 24 | D7: 二代 | F7: 湖南
A8: SR200 | B8: 12 | C8: 6 | D8: 二代 | F8: 湖南
A9: SR200CO | B9: 12 | C9: 6 | D9: 二代 | F9: 湖南
A10: SR300 | B10: 32 | C10: 4 | D10: 二代 | F10: 湖南
A11: SR460 | B11: 12 | C11: 6 | D11: 二代 | F11: 湖南
A12: SR600 | B12: 16 | C12: 6 | D12: 二代 | F12: 湖南
A13: SR100CDU-9 | B13: 7 | C13: 9 | D13: 二代 | F13: 湖南
A14: SR100- | B14: 7 | C14: 144 | D14: 二代 | E14: 密封盒 | F14: 湖南
A15: SR200- | B15: 12 | C15: 24 | D15: 二代 | E15: 密封盒 | F15: 湖南
A16: SR001 | B16: 3 | C16: 250 | D16: 二代 | F16: 湖南
A17: SR102C | B17: 10 | C17: 16 | D17: 二代 | F17: 湖南
A18: SR102CDU-16 | B18: 7 | C18: 16 | D18: 二代 | F18: 湖南
A19: SR201C | B19: 15 | C19: 6 | D19: 二代 | F19: 湖南
A20: SR301C | B20: 35 | C20: 4 | D20: 二代 | F20: 湖南
A21: JS300 | B21: 3 | C21: 12 | D21: 二代 | F21: 东莞
A22: SR103 | B22: 5 | C22: 24 | D22: 二代 | F22: 湖南
A23: SR103CDU-12 | B23: 5 | C23: 12 | D23: 二代 | F23: 湖南
A24: JS100 | B24: 24 | C24: 24 | D24: 二代 | F24: 东莞
A25: SR130 | B25: 5 | C25: 24 | D25: 二代 | F25: 湖南
A26: SR430 | B26: 12 | C26: 6 | D26: 二代 | F26: 湖南
A27: SR102CDU-24 | B27: 7 | C27: 24 | D27: 二代 | F27: 湖南
... A43: JC140 | B43: 0 | C43: 4 | D43: 蛋糕 | F43: 东莞
A44: JS100CDU-24 | C44: 24 | D44: 二代 | F44: 东莞
A45: JS100CDU-9 | C45: 9 | D45: 二代 | F45: 东莞
A46: SR1023CDU-16 | B46: 7 | C46: 16 | D46: 三代 | F46: 湖南
A47: SR102C-CDU-16 | B47: 10 | C47: 16 | D47: 二代 | F47: 湖南
A48: SR102-F-EC | B48: 7 | C48: 144 | D48: 二代 | F48: 湖南
A49: SR1033CDU-24 | B49: 5 | C49: 24 | D49: 三代 | F49: 湖南
A50: SR1602CDU-12 | B50: 5 | C50: 12 | D50: 三代 | F50: 湖南
A51: SR1602CDU-24 | B51: 5 | C51: 24 | D51: 三代 | F51: 湖南
A52: SR160CDU-24 | B52: 5 | C52: 24 | D52: 二代 | F52: 湖南
A53: SR1802CDU-24 | B53: 5 | C53: 24 | D53: 三代 | F53: 湖南
A54: SR180CDU-24 | B54: 5 | C54: 24 | D54: 二代 | F54: 湖南
A55: SR181CDU-24 | B55: 5 | C55: 24 | D55: 二代 | F55: 湖南
A56: SR2013 | B56: 12 | C56: 6 | D56: 三代 | F56: 湖南
A57: SR2013BULK-6 | B57: 12 | C57: 6 | D57: 三代 | F57: 湖南
... A89: SR1023CDU-24 | B89: 7 | C89: 24 | D89: 三代 | F89: 湖南
A90: JS3003CDU-12 | C90: 12 | D90: 三代 | F90: 东莞
A91: SR3203 | B91: 50 | C91: 2 | D91: 三代 | F91: 湖南
A92: SR1033CDU-12 | B92: 5 | C92: 12 | D92: 三代 | F92: 湖南
A93: SR1023CDU-9 | B93: 7 | C93: 9 | D93: 三代 | F93: 湖南
A94: SRAP4302CDU-6 | B94: 12 | C94: 6 | D94: 三代 | F94: 湖南
A95: SR1802CDU-12 | B95: 5 | C95: 12 | D95: 三代 | F95: 湖南
A96: JC120CDU-9 | C96: 9 | D96: 蛋糕 | F96: 东莞
A97: SR2013CDU-5 | B97: 12 | C97: 5 | D97: 三代 | F97: 湖南
A98: SRBFF3703 | B98: 50 | C98: 4 | D98: 三代 | F98: 东莞
A99: JS1003CDU-24 | C99: 24 | D99: 三代 | F99: 东莞
A100: JSSM100CDU-24 | C100: 24 | D100: 三代 | F100: 东莞
A101: SR3203BULK-2（浅蓝色） | B101: 50 | C101: 2 | D101: 三代 | F101: 湖南
A102: SR3203（浅蓝色） | B102: 50 | C102: 2 | D102: 三代 | F102: 湖南
A103: SR4602CDU-6 | B103: 12 | C103: 6 | D103: 三代 | F103: 湖南
A104: JS1003CDU-9 | C104: 9 | D104: 三代 | F104: 东莞
A105: SRSM102CDU-9 | B105: 7 | C105: 9 | D105: 三代 | F105: 湖南
A106: SR4602CDU-12 | B106: 12 | C106: 12 | D106: 三代 | F106: 湖南
A107: SRAP3202 | B107: 50 | C107: 2 | D107: 三代 | F107: 湖南
A108: SRMC302 | C108: 4 | D108: 三代 | F108: 湖南
A109: SRAP1302CDU-24 | B109: 5 | C109: 24 | D109: 三代 | F109: 湖南
A110: SRAP8002SC-72 | B110: 5 | C110: 72 | D110: 三代 | F110: 湖南
A111: SR1023 | B111: 7 | C111: 12 | D111: 三代 | F111: 湖南
A112: SRMC400CDU-12 | B112: 12 | C112: 12 | D112: 三代 | F112: 东莞
A113: JC100CDU-24 | C113: 24 | D113: 蛋糕 | F113: 东莞
A114: SRAE101CDU-12 | C114: 12 | D114: 三代 | F114: 湖南
A115: SRAP4302CDU-12 | B115: 12 | C115: 12 | D115: 三代 | F115: 湖南
A116: SR3203-COFP | B116: 50 | C116: 40 | D116: 三代 | F116: 东莞
A117: SR3703QP-12 | B117: 50 | C117: 12 | D117: 三代 | F117: 东莞
A118: SRSM400CDU-12 | C118: 12 | D118: 三代 | F118: 东莞
A119: JC120-ECOMM-2PK-A | C119: 36 | D119: 蛋糕 | F119: 东莞
A120: JC120-ECOMM-2PK-B | C120: 36 | D120: 蛋糕 | F120: 东莞
A121: JC120-ECOMM-2PK-C | C121: 36 | D121: 蛋糕 | F121: 东莞
A122: JS6003-ECOMM-A | C122: 12 | D122: 三代 | F122: 东莞
A123: JS6003-ECOMM-B | C123: 12 | D123: 三代 | F123: 东莞
A124: JS6003-ECOMM-C | C124: 12 | D124: 三代 | F124: 东莞
A125: JS6003-ECOMM-D | C125: 12 | D125: 三代 | F125: 东莞
A126: SR1023-ECOMM-A | B126: 5 | C126: 144 | D126: 三代 | F126: 湖南
A127: SR1023-ECOMM-B | B127: 5 | C127: 144 | D127: 三代 | F127: 湖南
A128: SR1023-ECOMM-C | B128: 5 | C128: 144 | D128: 三代 | F128: 湖南
A129: SR1023-ECOMM-D | B129: 5 | C129: 144 | D129: 三代 | F129: 湖南
A130: SR1023-ECOMM-E | B130: 5 | C130: 144 | D130: 三代 | F130: 湖南
A131: SR1023-ECOMM-F | B131: 5 | C131: 144 | D131: 三代 | F131: 湖南
A132: SR2013-ECOMM | B132: 12 | C132: 24 | D132: 三代 | F132: 湖南
A133: SR3013-ECOMM | B133: 32 | C133: 60 | D133: 三代 | F133: 湖南
A134: SR3203-ECOMM-B（蓝色） | B134: 50 | C134: 6 | D134: 三代 | F134: 湖南
A135: SR3203-ECOMM-P（粉色） | B135: 50 | C135: 6 | D135: 三代 | F135: 湖南
A136: SR4003-ECOMM-A | B136: 12 | C136: 96 | D136: 三代 | F136: 湖南
A137: SR4003-ECOMM-B | B137: 12 | C137: 96 | D137: 三代 | F137: 湖南
... A150: SRAE101-ECOMM-A | B150: 5 | C150: 70 | D150: 三代 | F150: 湖南
A151: SRAP3202-ECOMM | C151: 6 | D151: 三代 | F151: 湖南
A152: SRAP4302-ECOMM-A | B152: 12 | C152: 96 | D152: 三代 | F152: 湖南
A153: SRAP4302-ECOMM-B | B153: 12 | C153: 96 | D153: 三代 | F153: 湖南
A154: SRAP4302-ECOMM-C | B154: 12 | C154: 96 | D154: 三代 | F154: 湖南
A155: SRCRP400-ECOMM | C155: 96 | D155: 三代 | F155: 湖南
A156: SRMC103-ECOMM-2PK | B156: 5 | C156: 75 | D156: 三代 | F156: 湖南
A157: SRMC201-ECOMM | B157: 12 | C157: 6 | D157: 三代 | F157: 东莞
A158: SRMC400-ECOMM-A | B158: 12 | C158: 96 | D158: 三代 | F158: 东莞
...

Sheet 总接单
A1: 产品名称 | I1: =TRIM(LEFT(LEFT(LEFT(I2,IFERROR(FIND("/",I2)-1,LEN(I2))),IFERROR(FIND("CDU",I2)-1,LEN(I2))),IFERROR(FIND("-",I2)-1,LEN(I2)))) -> SR001 | J1: =TRIM(LEFT(LEFT(LEFT(J2,IFERROR(FIND("/",J2)-1,LEN(J2))),IFERROR(FIND("CDU",J2)-1,LEN(J2))),IFERROR(FIND("-",J2)-1,LEN(J2)))) -> SR020 | K1: =TRIM(LEFT(LEFT(LEFT(K2,IFERROR(FIND("/",K2)-1,LEN(K2))),IFERROR(FIND("CDU",K2)-1,LEN(K2))),IFERROR(FIND("-",K2)-1,LEN(K2)))) -> SR102 | L1: =TRIM(LEFT(LEFT(LEFT(L2,IFERROR(FIND("/",L2)-1,LEN(L2))),IFERROR(FIND("CDU",L2)-1,LEN(L2))),IFERROR(FIND("-",L2)-1,LEN(L2)))) -> SR102C | M1: =TRIM(LEFT(LEFT(LEFT(M2,IFERROR(FIND("/",M2)-1,LEN(M2))),IFERROR(FIND("CDU",M2)-1,LEN(M2))),IFERROR(FIND("-",M2)-1,LEN(M2)))) -> SR103 | N1: =TRIM(LEFT(LEFT(LEFT(N2,IFERROR(FIND("/",N2)-1,LEN(N2))),IFERROR(FIND("CDU",N2)-1,LEN(N2))),IFERROR(FIND("-",N2)-1,LEN(N2)))) -> SR130 | O1: =TRIM(LEFT(LEFT(LEFT(O2,IFERROR(FIND("/",O2)-1,LEN(O2))),IFERROR(FIND("CDU",O2)-1,LEN(O2))),IFERROR(FIND("-",O2)-1,LEN(O2)))) -> SR160 | P1: =TRIM(LEFT(LEFT(LEFT(P2,IFERROR(FIND("/",P2)-1,LEN(P2))),IFERROR(FIND("CDU",P2)-1,LEN(P2))),IFERROR(FIND("-",P2)-1,LEN(P2)))) -> SR180 | ... BU1: =TRIM(LEFT(LEFT(LEFT(BU2,IFERROR(FIND("/",BU2)-1,LEN(BU2))),IFERROR(FIND("CDU",BU2)-1,LEN(BU2))),IFERROR(FIND("-",BU2)-1,LEN(BU2)))) -> 散装手链
A2: 接单期 | B2: 出货期 | C2: CUSTOMER PO | D2: PO号 | E2: 货号 | F2: 数量 | G2: 包装版 | H2: =VLOOKUP(E2,名称!A:E,4,0) -> 系列 | I2: SR001 | J2: SR020 | K2: SR102/SR102CDU-9/SR102CDU-16/SR102CDU-24/SR102-F-EC | L2: SR102C/SR102C-CDU-16 | M2: SR103CDU-12/SR103CDU-24 | N2: SR130CDU-12/SR130CDU-24 | O2: SR160CDU-24 | P2: SR180CDU-24 | Q2: SR181CDU-24 | R2: SR201 | S2: SR201C/SR201C-CDU-5 | T2: SR301 | U2: SR320 | V2: SR370 | W2: SR400/SR400CDU-6/SR400CDU-12 | X2: SR430/SR430CDU-6/SR430CDU-12/SR430-ECOMM-C1/SR430-ECOMM-C2/SR430-ECOMM-C3 | Y2: SR460/SR460CDU-6/SR460CDU-12/SR460-EC | Z2: SR600/SR600CDU-6 | AA2: JS100CDU-9/JS100CDU-24 | AB2: JS300 | AC2: SR1023/SR1023CDU-9/SR1023CDU-16/SR1023CDU-24 | AD2: SR1033CDU-12/SR1033CDU-24 | AE2: SR1602CDU-12/SR1602CDU-24 | AF2: SR1802CDU-12/SR1802CDU-24 | AG2: SR2013/SR2013BULK-6/SR2013CDU-5 | AH2: SR3013 | AI2: SR3203/SR3203BULK-2/SR3203-COFP | AJ2: SR3703 | AK2: SR3703QP-12 | AL2: SR4003CDU-12 | AM2: SR4602CDU-6/SR4602CDU-12 | AN2: SR8003CDU-12/SR8003CDU-18/SR8003CDU-24 | AO2: SRAE101CDU-12 | AP2: SRAP1302CDU-24 | AQ2: SRAP3202 | AR2: SRAP4302CDU-6/SRAP4302CDU-12 | AS2: SRBFF3703 | AT2: SRMC103CDU-24 | AU2: SRMC201 | AV2: SRMC302 | AW2: SRMC400CDU-6/SRMC400CDU-12 | AX2: SRSM102CDU-9/SRSM102CDU-16 | AY2: SRSM103CDU-12/SRSM103CDU-24 | AZ2: SRSM301 | BA2: SRTD103CDU-12/SRTD103CDU-24 | BB2: SRTD400CDU-12 | BC2: JS1003CDU-9/JS1003CDU-24 | BD2: JS3003CDU-12 | BE2: JSSM100CDU-24 | BF2: JC100CDU-24 | BG2: JC120CDU-9/JC120CDU-18 | BH2: JC140 | BI2: SRSM400CDU-12 | BJ2: SRAP3203-ECOMM | BK2: SRCRP4202-ECOMM | BL2: SRAP8003CDU-18/CDU-24 | BM2: JS6003-ECOMM | BN2: SRBFF1812CDU-12 | BO2: SRSM103SK-72 | BP2: SRAP8002CDU-24 | BQ2: SRSC101CDU-24 | BR2: SR5163-ECOMM | BS2: JCV120CDU-18 （JC120CDU-18） | BU2: 散装手链 | BV2: 单价USD | BW2: 金额USD | BX2: 金额HKD | BY2: 系列
A3: 45744 | B3: 45816 | D3: BO#0001/2025 | E3: SR370 | F3: =150000-90000-5440-5440-5440-5440-5440-5440-5440-5440 -> 16480 | G3: 客版 | H3: =IFERROR(VLOOKUP(E3,名称!A:E,4,0),"") -> 二代 | I3: =IF(OR($E3="",I$1=""),"",IF(TRIM(LEFT($E3,MIN(IFERROR(FIND("CDU",UPPER($E3)),999),IFERROR(FIND("BULK",UPPER($E3)),999),IFERROR(FIND("-",$E3),999),IFERROR(FIND("（",$E3),999))-1))=I$1,$F3,"")) | J3: =IF(OR($E3="",J$1=""),"",IF(TRIM(LEFT($E3,MIN(IFERROR(FIND("CDU",UPPER($E3)),999),IFERROR(FIND("BULK",UPPER($E3)),999),IFERROR(FIND("-",$E3),999),IFERROR(FIND("（",$E3),999))-1))=J$1,$F3,"")) | K3: =IF(OR($E3="",K$1=""),"",IF(TRIM(LEFT($E3,MIN(IFERROR(FIND("CDU",UPPER($E3)),999),IFERROR(FIND("BULK",UPPER($E3)),999),IFERROR(FIND("-",$E3),999),IFERROR(FIND("（",$E3),999))-1))=K$1,$F3,"")) | L3: =IF(OR($E3="",L$1=""),"",IF(TRIM(LEFT($E3,MIN(IFERROR(FIND("CDU",UPPER($E3)),999),IFERROR(FIND("BULK",UPPER($E3)),999),IFERROR(FIND("-",$E3),999),IFERROR(FIND("（",$E3),999))-1))=L$1,$F3,"")) | M3: =IF(OR($E3="",M$1=""),"",IF(TRIM(LEFT($E3,MIN(IFERROR(FIND("CDU",UPPER($E3)),999),IFERROR(FIND("BULK",UPPER($E3)),999),IFERROR(FIND("-",$E3),999),IFERROR(FIND("（",$E3),999))-1))=M$1,$F3,"")) | N3: =IF(OR($E3="",N$1=""),"",IF(TRIM(LEFT($E3,MIN(IFERROR(FIND("CDU",UPPER($E3)),999),IFERROR(FIND("BULK",UPPER($E3)),999),IFERROR(FIND("-",$E3),999),IFERROR(FIND("（",$E3),999))-1))=N$1,$F3,"")) | O3: =IF(OR($E3="",O$1=""),"",IF(TRIM(LEFT($E3,MIN(IFERROR(FIND("CDU",UPPER($E3)),999),IFERROR(FIND("BULK",UPPER($E3)),999),IFERROR(FIND("-",$E3),999),IFERROR(FIND("（",$E3),999))-1))=O$1,$F3,"")) | P3: =IF(OR($E3="",P$1=""),"",IF(TRIM(LEFT($E3,MIN(IFERROR(FIND("CDU",UPPER($E3)),999),IFERROR(FIND("BULK",UPPER($E3)),999),IFERROR(FIND("-",$E3),999),IFERROR(FIND("（",$E3),999))-1))=P$1,$F3,"")) | ... BU3: =IF(OR($E3="",BU$1=""),"",IF(TRIM(LEFT($E3,MIN(IFERROR(FIND("CDU",UPPER($E3)),999),IFERROR(FIND("BULK",UPPER($E3)),999),IFERROR(FIND("-",$E3),999),IFERROR(FIND("（",$E3),999))-1))=BU$1,$F3,"")) | BV3: 6.93 | BW3: =SUM(I3:BU3)*BV3 -> 114206.4 | BX3: =BW3*7.75 -> 885099.6 | BY3: =MID(E3,1,2) -> SR
A4: 45749 | B4: 45758 | C4: OC00004813 | D4: MXFM002 | E4: SR001 | F4: 5000 | G4: 美文版 | H4: =IFERROR(VLOOKUP(E4,名称!A:E,4,0),"") -> 二代 | I4: =IF(OR($E4="",I$1=""),"",IF(TRIM(LEFT($E4,MIN(IFERROR(FIND("CDU",UPPER($E4)),999),IFERROR(FIND("BULK",UPPER($E4)),999),IFERROR(FIND("-",$E4),999),IFERROR(FIND("（",$E4),999))-1))=I$1,$F4,"")) -> 5000 | J4: =IF(OR($E4="",J$1=""),"",IF(TRIM(LEFT($E4,MIN(IFERROR(FIND("CDU",UPPER($E4)),999),IFERROR(FIND("BULK",UPPER($E4)),999),IFERROR(FIND("-",$E4),999),IFERROR(FIND("（",$E4),999))-1))=J$1,$F4,"")) | K4: =IF(OR($E4="",K$1=""),"",IF(TRIM(LEFT($E4,MIN(IFERROR(FIND("CDU",UPPER($E4)),999),IFERROR(FIND("BULK",UPPER($E4)),999),IFERROR(FIND("-",$E4),999),IFERROR(FIND("（",$E4),999))-1))=K$1,$F4,"")) | L4: =IF(OR($E4="",L$1=""),"",IF(TRIM(LEFT($E4,MIN(IFERROR(FIND("CDU",UPPER($E4)),999),IFERROR(FIND("BULK",UPPER($E4)),999),IFERROR(FIND("-",$E4),999),IFERROR(FIND("（",$E4),999))-1))=L$1,$F4,"")) | M4: =IF(OR($E4="",M$1=""),"",IF(TRIM(LEFT($E4,MIN(IFERROR(FIND("CDU",UPPER($E4)),999),IFERROR(FIND("BULK",UPPER($E4)),999),IFERROR(FIND("-",$E4),999),IFERROR(FIND("（",$E4),999))-1))=M$1,$F4,"")) | N4: =IF(OR($E4="",N$1=""),"",IF(TRIM(LEFT($E4,MIN(IFERROR(FIND("CDU",UPPER($E4)),999),IFERROR(FIND("BULK",UPPER($E4)),999),IFERROR(FIND("-",$E4),999),IFERROR(FIND("（",$E4),999))-1))=N$1,$F4,"")) | O4: =IF(OR($E4="",O$1=""),"",IF(TRIM(LEFT($E4,MIN(IFERROR(FIND("CDU",UPPER($E4)),999),IFERROR(FIND("BULK",UPPER($E4)),999),IFERROR(FIND("-",$E4),999),IFERROR(FIND("（",$E4),999))-1))=O$1,$F4,"")) | P4: =IF(OR($E4="",P$1=""),"",IF(TRIM(LEFT($E4,MIN(IFERROR(FIND("CDU",UPPER($E4)),999),IFERROR(FIND("BULK",UPPER($E4)),999),IFERROR(FIND("-",$E4),999),IFERROR(FIND("（",$E4),999))-1))=P$1,$F4,"")) | ... BU4: =IF(OR($E4="",BU$1=""),"",IF(TRIM(LEFT($E4,MIN(IFERROR(FIND("CDU",UPPER($E4)),999),IFERROR(FIND("BULK",UPPER($E4)),999),IFERROR(FIND("-",$E4),999),IFERROR(FIND("（",$E4),999))-1))=BU$1,$F4,"")) | BV4: 0.1 | BW4: =SUM(I4:BU4)*BV4 -> 500 | BX4: =BW4*7.75 -> 3875 | BY4: =MID(E4,1,2) -> SR
A5: 45807 | B5: 45863 | C5: JAZ254714 | D5: CAJZ039 | E5: SR201 | F5: 1002 | G5: Jazwares客版（2L） | H5: =IFERROR(VLOOKUP(E5,名称!A:E,4,0),"") -> 二代 | I5: =IF(OR($E5="",I$1=""),"",IF(TRIM(LEFT($E5,MIN(IFERROR(FIND("CDU",UPPER($E5)),999),IFERROR(FIND("BULK",UPPER($E5)),999),IFERROR(FIND("-",$E5),999),IFERROR(FIND("（",$E5),999))-1))=I$1,$F5,"")) | J5: =IF(OR($E5="",J$1=""),"",IF(TRIM(LEFT($E5,MIN(IFERROR(FIND("CDU",UPPER($E5)),999),IFERROR(FIND("BULK",UPPER($E5)),999),IFERROR(FIND("-",$E5),999),IFERROR(FIND("（",$E5),999))-1))=J$1,$F5,"")) | K5: =IF(OR($E5="",K$1=""),"",IF(TRIM(LEFT($E5,MIN(IFERROR(FIND("CDU",UPPER($E5)),999),IFERROR(FIND("BULK",UPPER($E5)),999),IFERROR(FIND("-",$E5),999),IFERROR(FIND("（",$E5),999))-1))=K$1,$F5,"")) | L5: =IF(OR($E5="",L$1=""),"",IF(TRIM(LEFT($E5,MIN(IFERROR(FIND("CDU",UPPER($E5)),999),IFERROR(FIND("BULK",UPPER($E5)),999),IFERROR(FIND("-",$E5),999),IFERROR(FIND("（",$E5),999))-1))=L$1,$F5,"")) | M5: =IF(OR($E5="",M$1=""),"",IF(TRIM(LEFT($E5,MIN(IFERROR(FIND("CDU",UPPER($E5)),999),IFERROR(FIND("BULK",UPPER($E5)),999),IFERROR(FIND("-",$E5),999),IFERROR(FIND("（",$E5),999))-1))=M$1,$F5,"")) | N5: =IF(OR($E5="",N$1=""),"",IF(TRIM(LEFT($E5,MIN(IFERROR(FIND("CDU",UPPER($E5)),999),IFERROR(FIND("BULK",UPPER($E5)),999),IFERROR(FIND("-",$E5),999),IFERROR(FIND("（",$E5),999))-1))=N$1,$F5,"")) | O5: =IF(OR($E5="",O$1=""),"",IF(TRIM(LEFT($E5,MIN(IFERROR(FIND("CDU",UPPER($E5)),999),IFERROR(FIND("BULK",UPPER($E5)),999),IFERROR(FIND("-",$E5),999),IFERROR(FIND("（",$E5),999))-1))=O$1,$F5,"")) | P5: =IF(OR($E5="",P$1=""),"",IF(TRIM(LEFT($E5,MIN(IFERROR(FIND("CDU",UPPER($E5)),999),IFERROR(FIND("BULK",UPPER($E5)),999),IFERROR(FIND("-",$E5),999),IFERROR(FIND("（",$E5),999))-1))=P$1,$F5,"")) | ... BU5: =IF(OR($E5="",BU$1=""),"",IF(TRIM(LEFT($E5,MIN(IFERROR(FIND("CDU",UPPER($E5)),999),IFERROR(FIND("BULK",UPPER($E5)),999),IFERROR(FIND("-",$E5),999),IFERROR(FIND("（",$E5),999))-1))=BU$1,$F5,"")) | BV5: 2.1 | BW5: =SUM(I5:BU5)*BV5 -> 2104.2 | BX5: =BW5*7.75 -> 16307.55 | BY5: =MID(E5,1,2) -> SR
A6: 45807 | B6: 45863 | C6: JAZ254715 | D6: CAJZ040 | E6: SR201 | F6: =1800-1500 -> 300 | G6: Jazwares客版（2L） | H6: =IFERROR(VLOOKUP(E6,名称!A:E,4,0),"") -> 二代 | I6: =IF(OR($E6="",I$1=""),"",IF(TRIM(LEFT($E6,MIN(IFERROR(FIND("CDU",UPPER($E6)),999),IFERROR(FIND("BULK",UPPER($E6)),999),IFERROR(FIND("-",$E6),999),IFERROR(FIND("（",$E6),999))-1))=I$1,$F6,"")) | J6: =IF(OR($E6="",J$1=""),"",IF(TRIM(LEFT($E6,MIN(IFERROR(FIND("CDU",UPPER($E6)),999),IFERROR(FIND("BULK",UPPER($E6)),999),IFERROR(FIND("-",$E6),999),IFERROR(FIND("（",$E6),999))-1))=J$1,$F6,"")) | K6: =IF(OR($E6="",K$1=""),"",IF(TRIM(LEFT($E6,MIN(IFERROR(FIND("CDU",UPPER($E6)),999),IFERROR(FIND("BULK",UPPER($E6)),999),IFERROR(FIND("-",$E6),999),IFERROR(FIND("（",$E6),999))-1))=K$1,$F6,"")) | L6: =IF(OR($E6="",L$1=""),"",IF(TRIM(LEFT($E6,MIN(IFERROR(FIND("CDU",UPPER($E6)),999),IFERROR(FIND("BULK",UPPER($E6)),999),IFERROR(FIND("-",$E6),999),IFERROR(FIND("（",$E6),999))-1))=L$1,$F6,"")) | M6: =IF(OR($E6="",M$1=""),"",IF(TRIM(LEFT($E6,MIN(IFERROR(FIND("CDU",UPPER($E6)),999),IFERROR(FIND("BULK",UPPER($E6)),999),IFERROR(FIND("-",$E6),999),IFERROR(FIND("（",$E6),999))-1))=M$1,$F6,"")) | N6: =IF(OR($E6="",N$1=""),"",IF(TRIM(LEFT($E6,MIN(IFERROR(FIND("CDU",UPPER($E6)),999),IFERROR(FIND("BULK",UPPER($E6)),999),IFERROR(FIND("-",$E6),999),IFERROR(FIND("（",$E6),999))-1))=N$1,$F6,"")) | O6: =IF(OR($E6="",O$1=""),"",IF(TRIM(LEFT($E6,MIN(IFERROR(FIND("CDU",UPPER($E6)),999),IFERROR(FIND("BULK",UPPER($E6)),999),IFERROR(FIND("-",$E6),999),IFERROR(FIND("（",$E6),999))-1))=O$1,$F6,"")) | P6: =IF(OR($E6="",P$1=""),"",IF(TRIM(LEFT($E6,MIN(IFERROR(FIND("CDU",UPPER($E6)),999),IFERROR(FIND("BULK",UPPER($E6)),999),IFERROR(FIND("-",$E6),999),IFERROR(FIND("（",$E6),999))-1))=P$1,$F6,"")) | ... BU6: =IF(OR($E6="",BU$1=""),"",IF(TRIM(LEFT($E6,MIN(IFERROR(FIND("CDU",UPPER($E6)),999),IFERROR(FIND("BULK",UPPER($E6)),999),IFERROR(FIND("-",$E6),999),IFERROR(FIND("（",$E6),999))-1))=BU$1,$F6,"")) | BV6: 2.1 | BW6: =SUM(I6:BU6)*BV6 -> 630 | BX6: =BW6*7.75 -> 4882.5 | BY6: =MID(E6,1,2) -> SR
A7: 45807 | B7: 45863 | C7: JAZ254716 | D7: CAJZ041 | E7: SR201 | F7: 2004 | G7: Jazwares客版（2L） | H7: =IFERROR(VLOOKUP(E7,名称!A:E,4,0),"") -> 二代 | I7: =IF(OR($E7="",I$1=""),"",IF(TRIM(LEFT($E7,MIN(IFERROR(FIND("CDU",UPPER($E7)),999),IFERROR(FIND("BULK",UPPER($E7)),999),IFERROR(FIND("-",$E7),999),IFERROR(FIND("（",$E7),999))-1))=I$1,$F7,"")) | J7: =IF(OR($E7="",J$1=""),"",IF(TRIM(LEFT($E7,MIN(IFERROR(FIND("CDU",UPPER($E7)),999),IFERROR(FIND("BULK",UPPER($E7)),999),IFERROR(FIND("-",$E7),999),IFERROR(FIND("（",$E7),999))-1))=J$1,$F7,"")) | K7: =IF(OR($E7="",K$1=""),"",IF(TRIM(LEFT($E7,MIN(IFERROR(FIND("CDU",UPPER($E7)),999),IFERROR(FIND("BULK",UPPER($E7)),999),IFERROR(FIND("-",$E7),999),IFERROR(FIND("（",$E7),999))-1))=K$1,$F7,"")) | L7: =IF(OR($E7="",L$1=""),"",IF(TRIM(LEFT($E7,MIN(IFERROR(FIND("CDU",UPPER($E7)),999),IFERROR(FIND("BULK",UPPER($E7)),999),IFERROR(FIND("-",$E7),999),IFERROR(FIND("（",$E7),999))-1))=L$1,$F7,"")) | M7: =IF(OR($E7="",M$1=""),"",IF(TRIM(LEFT($E7,MIN(IFERROR(FIND("CDU",UPPER($E7)),999),IFERROR(FIND("BULK",UPPER($E7)),999),IFERROR(FIND("-",$E7),999),IFERROR(FIND("（",$E7),999))-1))=M$1,$F7,"")) | N7: =IF(OR($E7="",N$1=""),"",IF(TRIM(LEFT($E7,MIN(IFERROR(FIND("CDU",UPPER($E7)),999),IFERROR(FIND("BULK",UPPER($E7)),999),IFERROR(FIND("-",$E7),999),IFERROR(FIND("（",$E7),999))-1))=N$1,$F7,"")) | O7: =IF(OR($E7="",O$1=""),"",IF(TRIM(LEFT($E7,MIN(IFERROR(FIND("CDU",UPPER($E7)),999),IFERROR(FIND("BULK",UPPER($E7)),999),IFERROR(FIND("-",$E7),999),IFERROR(FIND("（",$E7),999))-1))=O$1,$F7,"")) | P7: =IF(OR($E7="",P$1=""),"",IF(TRIM(LEFT($E7,MIN(IFERROR(FIND("CDU",UPPER($E7)),999),IFERROR(FIND("BULK",UPPER($E7)),999),IFERROR(FIND("-",$E7),999),IFERROR(FIND("（",$E7),999))-1))=P$1,$F7,"")) | ... BU7: =IF(OR($E7="",BU$1=""),"",IF(TRIM(LEFT($E7,MIN(IFERROR(FIND("CDU",UPPER($E7)),999),IFERROR(FIND("BULK",UPPER($E7)),999),IFERROR(FIND("-",$E7),999),IFERROR(FIND("（",$E7),999))-1))=BU$1,$F7,"")) | BV7: 2.1 | BW7: =SUM(I7:BU7)*BV7 -> 4208.4 | BX7: =BW7*7.75 -> 32615.1 | BY7: =MID(E7,1,2) -> SR
A8: 45807 | B8: 45863 | C8: JAZ254716 | D8: CAJZ041 | E8: SR201 | F8: 1200 | G8: Jazwares客版（2L） | H8: =IFERROR(VLOOKUP(E8,名称!A:E,4,0),"") -> 二代 | I8: =IF(OR($E8="",I$1=""),"",IF(TRIM(LEFT($E8,MIN(IFERROR(FIND("CDU",UPPER($E8)),999),IFERROR(FIND("BULK",UPPER($E8)),999),IFERROR(FIND("-",$E8),999),IFERROR(FIND("（",$E8),999))-1))=I$1,$F8,"")) | J8: =IF(OR($E8="",J$1=""),"",IF(TRIM(LEFT($E8,MIN(IFERROR(FIND("CDU",UPPER($E8)),999),IFERROR(FIND("BULK",UPPER($E8)),999),IFERROR(FIND("-",$E8),999),IFERROR(FIND("（",$E8),999))-1))=J$1,$F8,"")) | K8: =IF(OR($E8="",K$1=""),"",IF(TRIM(LEFT($E8,MIN(IFERROR(FIND("CDU",UPPER($E8)),999),IFERROR(FIND("BULK",UPPER($E8)),999),IFERROR(FIND("-",$E8),999),IFERROR(FIND("（",$E8),999))-1))=K$1,$F8,"")) | L8: =IF(OR($E8="",L$1=""),"",IF(TRIM(LEFT($E8,MIN(IFERROR(FIND("CDU",UPPER($E8)),999),IFERROR(FIND("BULK",UPPER($E8)),999),IFERROR(FIND("-",$E8),999),IFERROR(FIND("（",$E8),999))-1))=L$1,$F8,"")) | M8: =IF(OR($E8="",M$1=""),"",IF(TRIM(LEFT($E8,MIN(IFERROR(FIND("CDU",UPPER($E8)),999),IFERROR(FIND("BULK",UPPER($E8)),999),IFERROR(FIND("-",$E8),999),IFERROR(FIND("（",$E8),999))-1))=M$1,$F8,"")) | N8: =IF(OR($E8="",N$1=""),"",IF(TRIM(LEFT($E8,MIN(IFERROR(FIND("CDU",UPPER($E8)),999),IFERROR(FIND("BULK",UPPER($E8)),999),IFERROR(FIND("-",$E8),999),IFERROR(FIND("（",$E8),999))-1))=N$1,$F8,"")) | O8: =IF(OR($E8="",O$1=""),"",IF(TRIM(LEFT($E8,MIN(IFERROR(FIND("CDU",UPPER($E8)),999),IFERROR(FIND("BULK",UPPER($E8)),999),IFERROR(FIND("-",$E8),999),IFERROR(FIND("（",$E8),999))-1))=O$1,$F8,"")) | P8: =IF(OR($E8="",P$1=""),"",IF(TRIM(LEFT($E8,MIN(IFERROR(FIND("CDU",UPPER($E8)),999),IFERROR(FIND("BULK",UPPER($E8)),999),IFERROR(FIND("-",$E8),999),IFERROR(FIND("（",$E8),999))-1))=P$1,$F8,"")) | ... BU8: =IF(OR($E8="",BU$1=""),"",IF(TRIM(LEFT($E8,MIN(IFERROR(FIND("CDU",UPPER($E8)),999),IFERROR(FIND("BULK",UPPER($E8)),999),IFERROR(FIND("-",$E8),999),IFERROR(FIND("（",$E8),999))-1))=BU$1,$F8,"")) | BV8: 2.1 | BW8: =SUM(I8:BU8)*BV8 -> 2520 | BX8: =BW8*7.75 -> 19530 | BY8: =MID(E8,1,2) -> SR
A9: 45807 | B9: 45863 | C9: JAZ254717 | D9: CAJZ042 | E9: SR102C-CDU-16 | F9: 2000 | G9: Jazwares客版（2L） | H9: =IFERROR(VLOOKUP(E9,名称!A:E,4,0),"") -> 二代 | I9: =IF(OR($E9="",I$1=""),"",IF(TRIM(LEFT($E9,MIN(IFERROR(FIND("CDU",UPPER($E9)),999),IFERROR(FIND("BULK",UPPER($E9)),999),IFERROR(FIND("-",$E9),999),IFERROR(FIND("（",$E9),999))-1))=I$1,$F9,"")) | J9: =IF(OR($E9="",J$1=""),"",IF(TRIM(LEFT($E9,MIN(IFERROR(FIND("CDU",UPPER($E9)),999),IFERROR(FIND("BULK",UPPER($E9)),999),IFERROR(FIND("-",$E9),999),IFERROR(FIND("（",$E9),999))-1))=J$1,$F9,"")) | K9: =IF(OR($E9="",K$1=""),"",IF(TRIM(LEFT($E9,MIN(IFERROR(FIND("CDU",UPPER($E9)),999),IFERROR(FIND("BULK",UPPER($E9)),999),IFERROR(FIND("-",$E9),999),IFERROR(FIND("（",$E9),999))-1))=K$1,$F9,"")) | L9: =IF(OR($E9="",L$1=""),"",IF(TRIM(LEFT($E9,MIN(IFERROR(FIND("CDU",UPPER($E9)),999),IFERROR(FIND("BULK",UPPER($E9)),999),IFERROR(FIND("-",$E9),999),IFERROR(FIND("（",$E9),999))-1))=L$1,$F9,"")) -> 2000 | M9: =IF(OR($E9="",M$1=""),"",IF(TRIM(LEFT($E9,MIN(IFERROR(FIND("CDU",UPPER($E9)),999),IFERROR(FIND("BULK",UPPER($E9)),999),IFERROR(FIND("-",$E9),999),IFERROR(FIND("（",$E9),999))-1))=M$1,$F9,"")) | N9: =IF(OR($E9="",N$1=""),"",IF(TRIM(LEFT($E9,MIN(IFERROR(FIND("CDU",UPPER($E9)),999),IFERROR(FIND("BULK",UPPER($E9)),999),IFERROR(FIND("-",$E9),999),IFERROR(FIND("（",$E9),999))-1))=N$1,$F9,"")) | O9: =IF(OR($E9="",O$1=""),"",IF(TRIM(LEFT($E9,MIN(IFERROR(FIND("CDU",UPPER($E9)),999),IFERROR(FIND("BULK",UPPER($E9)),999),IFERROR(FIND("-",$E9),999),IFERROR(FIND("（",$E9),999))-1))=O$1,$F9,"")) | P9: =IF(OR($E9="",P$1=""),"",IF(TRIM(LEFT($E9,MIN(IFERROR(FIND("CDU",UPPER($E9)),999),IFERROR(FIND("BULK",UPPER($E9)),999),IFERROR(FIND("-",$E9),999),IFERROR(FIND("（",$E9),999))-1))=P$1,$F9,"")) | ... BU9: =IF(OR($E9="",BU$1=""),"",IF(TRIM(LEFT($E9,MIN(IFERROR(FIND("CDU",UPPER($E9)),999),IFERROR(FIND("BULK",UPPER($E9)),999),IFERROR(FIND("-",$E9),999),IFERROR(FIND("（",$E9),999))-1))=BU$1,$F9,"")) | BV9: 0.98 | BW9: =SUM(I9:BU9)*BV9 -> 1960 | BX9: =BW9*7.75 -> 15190 | BY9: =MID(E9,1,2) -> SR
A10: 45807 | B10: 45863 | C10: JAZ254717 | D10: CAJZ042 | E10: SR102C-CDU-16 | F10: 3600 | G10: Jazwares客版（2L） | H10: =IFERROR(VLOOKUP(E10,名称!A:E,4,0),"") -> 二代 | I10: =IF(OR($E10="",I$1=""),"",IF(TRIM(LEFT($E10,MIN(IFERROR(FIND("CDU",UPPER($E10)),999),IFERROR(FIND("BULK",UPPER($E10)),999),IFERROR(FIND("-",$E10),999),IFERROR(FIND("（",$E10),999))-1))=I$1,$F10,"")) | J10: =IF(OR($E10="",J$1=""),"",IF(TRIM(LEFT($E10,MIN(IFERROR(FIND("CDU",UPPER($E10)),999),IFERROR(FIND("BULK",UPPER($E10)),999),IFERROR(FIND("-",$E10),999),IFERROR(FIND("（",$E10),999))-1))=J$1,$F10,"")) | K10: =IF(OR($E10="",K$1=""),"",IF(TRIM(LEFT($E10,MIN(IFERROR(FIND("CDU",UPPER($E10)),999),IFERROR(FIND("BULK",UPPER($E10)),999),IFERROR(FIND("-",$E10),999),IFERROR(FIND("（",$E10),999))-1))=K$1,$F10,"")) | L10: =IF(OR($E10="",L$1=""),"",IF(TRIM(LEFT($E10,MIN(IFERROR(FIND("CDU",UPPER($E10)),999),IFERROR(FIND("BULK",UPPER($E10)),999),IFERROR(FIND("-",$E10),999),IFERROR(FIND("（",$E10),999))-1))=L$1,$F10,"")) -> 3600 | M10: =IF(OR($E10="",M$1=""),"",IF(TRIM(LEFT($E10,MIN(IFERROR(FIND("CDU",UPPER($E10)),999),IFERROR(FIND("BULK",UPPER($E10)),999),IFERROR(FIND("-",$E10),999),IFERROR(FIND("（",$E10),999))-1))=M$1,$F10,"")) | N10: =IF(OR($E10="",N$1=""),"",IF(TRIM(LEFT($E10,MIN(IFERROR(FIND("CDU",UPPER($E10)),999),IFERROR(FIND("BULK",UPPER($E10)),999),IFERROR(FIND("-",$E10),999),IFERROR(FIND("（",$E10),999))-1))=N$1,$F10,"")) | O10: =IF(OR($E10="",O$1=""),"",IF(TRIM(LEFT($E10,MIN(IFERROR(FIND("CDU",UPPER($E10)),999),IFERROR(FIND("BULK",UPPER($E10)),999),IFERROR(FIND("-",$E10),999),IFERROR(FIND("（",$E10),999))-1))=O$1,$F10,"")) | P10: =IF(OR($E10="",P$1=""),"",IF(TRIM(LEFT($E10,MIN(IFERROR(FIND("CDU",UPPER($E10)),999),IFERROR(FIND("BULK",UPPER($E10)),999),IFERROR(FIND("-",$E10),999),IFERROR(FIND("（",$E10),999))-1))=P$1,$F10,"")) | ... BU10: =IF(OR($E10="",BU$1=""),"",IF(TRIM(LEFT($E10,MIN(IFERROR(FIND("CDU",UPPER($E10)),999),IFERROR(FIND("BULK",UPPER($E10)),999),IFERROR(FIND("-",$E10),999),IFERROR(FIND("（",$E10),999))-1))=BU$1,$F10,"")) | BV10: 0.98 | BW10: =SUM(I10:BU10)*BV10 -> 3528 | BX10: =BW10*7.75 -> 27342 | BY10: =MID(E10,1,2) -> SR
A11: 45807 | B11: 45863 | C11: JAZ254723 | D11: CAJZ048 | E11: SR102 | F11: 1800 | G11: Jazwares客版（2L） | H11: =IFERROR(VLOOKUP(E11,名称!A:E,4,0),"") -> 二代 | I11: =IF(OR($E11="",I$1=""),"",IF(TRIM(LEFT($E11,MIN(IFERROR(FIND("CDU",UPPER($E11)),999),IFERROR(FIND("BULK",UPPER($E11)),999),IFERROR(FIND("-",$E11),999),IFERROR(FIND("（",$E11),999))-1))=I$1,$F11,"")) | J11: =IF(OR($E11="",J$1=""),"",IF(TRIM(LEFT($E11,MIN(IFERROR(FIND("CDU",UPPER($E11)),999),IFERROR(FIND("BULK",UPPER($E11)),999),IFERROR(FIND("-",$E11),999),IFERROR(FIND("（",$E11),999))-1))=J$1,$F11,"")) | K11: =IF(OR($E11="",K$1=""),"",IF(TRIM(LEFT($E11,MIN(IFERROR(FIND("CDU",UPPER($E11)),999),IFERROR(FIND("BULK",UPPER($E11)),999),IFERROR(FIND("-",$E11),999),IFERROR(FIND("（",$E11),999))-1))=K$1,$F11,"")) -> 1800 | L11: =IF(OR($E11="",L$1=""),"",IF(TRIM(LEFT($E11,MIN(IFERROR(FIND("CDU",UPPER($E11)),999),IFERROR(FIND("BULK",UPPER($E11)),999),IFERROR(FIND("-",$E11),999),IFERROR(FIND("（",$E11),999))-1))=L$1,$F11,"")) | M11: =IF(OR($E11="",M$1=""),"",IF(TRIM(LEFT($E11,MIN(IFERROR(FIND("CDU",UPPER($E11)),999),IFERROR(FIND("BULK",UPPER($E11)),999),IFERROR(FIND("-",$E11),999),IFERROR(FIND("（",$E11),999))-1))=M$1,$F11,"")) | N11: =IF(OR($E11="",N$1=""),"",IF(TRIM(LEFT($E11,MIN(IFERROR(FIND("CDU",UPPER($E11)),999),IFERROR(FIND("BULK",UPPER($E11)),999),IFERROR(FIND("-",$E11),999),IFERROR(FIND("（",$E11),999))-1))=N$1,$F11,"")) | O11: =IF(OR($E11="",O$1=""),"",IF(TRIM(LEFT($E11,MIN(IFERROR(FIND("CDU",UPPER($E11)),999),IFERROR(FIND("BULK",UPPER($E11)),999),IFERROR(FIND("-",$E11),999),IFERROR(FIND("（",$E11),999))-1))=O$1,$F11,"")) | P11: =IF(OR($E11="",P$1=""),"",IF(TRIM(LEFT($E11,MIN(IFERROR(FIND("CDU",UPPER($E11)),999),IFERROR(FIND("BULK",UPPER($E11)),999),IFERROR(FIND("-",$E11),999),IFERROR(FIND("（",$E11),999))-1))=P$1,$F11,"")) | ... BU11: =IF(OR($E11="",BU$1=""),"",IF(TRIM(LEFT($E11,MIN(IFERROR(FIND("CDU",UPPER($E11)),999),IFERROR(FIND("BULK",UPPER($E11)),999),IFERROR(FIND("-",$E11),999),IFERROR(FIND("（",$E11),999))-1))=BU$1,$F11,"")) | BV11: 0.87 | BW11: =SUM(I11:BU11)*BV11 -> 1566 | BX11: =BW11*7.75 -> 12136.5 | BY11: =MID(E11,1,2) -> SR
A12: 45807 | B12: 45863 | C12: JAZ254723 | D12: CAJZ048 | E12: SR102 | F12: 384 | G12: Jazwares客版（2L） | H12: =IFERROR(VLOOKUP(E12,名称!A:E,4,0),"") -> 二代 | I12: =IF(OR($E12="",I$1=""),"",IF(TRIM(LEFT($E12,MIN(IFERROR(FIND("CDU",UPPER($E12)),999),IFERROR(FIND("BULK",UPPER($E12)),999),IFERROR(FIND("-",$E12),999),IFERROR(FIND("（",$E12),999))-1))=I$1,$F12,"")) | J12: =IF(OR($E12="",J$1=""),"",IF(TRIM(LEFT($E12,MIN(IFERROR(FIND("CDU",UPPER($E12)),999),IFERROR(FIND("BULK",UPPER($E12)),999),IFERROR(FIND("-",$E12),999),IFERROR(FIND("（",$E12),999))-1))=J$1,$F12,"")) | K12: =IF(OR($E12="",K$1=""),"",IF(TRIM(LEFT($E12,MIN(IFERROR(FIND("CDU",UPPER($E12)),999),IFERROR(FIND("BULK",UPPER($E12)),999),IFERROR(FIND("-",$E12),999),IFERROR(FIND("（",$E12),999))-1))=K$1,$F12,"")) -> 384 | L12: =IF(OR($E12="",L$1=""),"",IF(TRIM(LEFT($E12,MIN(IFERROR(FIND("CDU",UPPER($E12)),999),IFERROR(FIND("BULK",UPPER($E12)),999),IFERROR(FIND("-",$E12),999),IFERROR(FIND("（",$E12),999))-1))=L$1,$F12,"")) | M12: =IF(OR($E12="",M$1=""),"",IF(TRIM(LEFT($E12,MIN(IFERROR(FIND("CDU",UPPER($E12)),999),IFERROR(FIND("BULK",UPPER($E12)),999),IFERROR(FIND("-",$E12),999),IFERROR(FIND("（",$E12),999))-1))=M$1,$F12,"")) | N12: =IF(OR($E12="",N$1=""),"",IF(TRIM(LEFT($E12,MIN(IFERROR(FIND("CDU",UPPER($E12)),999),IFERROR(FIND("BULK",UPPER($E12)),999),IFERROR(FIND("-",$E12),999),IFERROR(FIND("（",$E12),999))-1))=N$1,$F12,"")) | O12: =IF(OR($E12="",O$1=""),"",IF(TRIM(LEFT($E12,MIN(IFERROR(FIND("CDU",UPPER($E12)),999),IFERROR(FIND("BULK",UPPER($E12)),999),IFERROR(FIND("-",$E12),999),IFERROR(FIND("（",$E12),999))-1))=O$1,$F12,"")) | P12: =IF(OR($E12="",P$1=""),"",IF(TRIM(LEFT($E12,MIN(IFERROR(FIND("CDU",UPPER($E12)),999),IFERROR(FIND("BULK",UPPER($E12)),999),IFERROR(FIND("-",$E12),999),IFERROR(FIND("（",$E12),999))-1))=P$1,$F12,"")) | ... BU12: =IF(OR($E12="",BU$1=""),"",IF(TRIM(LEFT($E12,MIN(IFERROR(FIND("CDU",UPPER($E12)),999),IFERROR(FIND("BULK",UPPER($E12)),999),IFERROR(FIND("-",$E12),999),IFERROR(FIND("（",$E12),999))-1))=BU$1,$F12,"")) | BV12: 0.87 | BW12: =SUM(I12:BU12)*BV12 -> 334.08 | BX12: =BW12*7.75 -> 2589.12 | BY12: =MID(E12,1,2) -> SR
A13: 45807 | B13: 45863 | C13: JAZ254724 | D13: CAJZ049 | E13: SR102 | F13: 1800 | G13: Jazwares客版（2L） | H13: =IFERROR(VLOOKUP(E13,名称!A:E,4,0),"") -> 二代 | I13: =IF(OR($E13="",I$1=""),"",IF(TRIM(LEFT($E13,MIN(IFERROR(FIND("CDU",UPPER($E13)),999),IFERROR(FIND("BULK",UPPER($E13)),999),IFERROR(FIND("-",$E13),999),IFERROR(FIND("（",$E13),999))-1))=I$1,$F13,"")) | J13: =IF(OR($E13="",J$1=""),"",IF(TRIM(LEFT($E13,MIN(IFERROR(FIND("CDU",UPPER($E13)),999),IFERROR(FIND("BULK",UPPER($E13)),999),IFERROR(FIND("-",$E13),999),IFERROR(FIND("（",$E13),999))-1))=J$1,$F13,"")) | K13: =IF(OR($E13="",K$1=""),"",IF(TRIM(LEFT($E13,MIN(IFERROR(FIND("CDU",UPPER($E13)),999),IFERROR(FIND("BULK",UPPER($E13)),999),IFERROR(FIND("-",$E13),999),IFERROR(FIND("（",$E13),999))-1))=K$1,$F13,"")) -> 1800 | L13: =IF(OR($E13="",L$1=""),"",IF(TRIM(LEFT($E13,MIN(IFERROR(FIND("CDU",UPPER($E13)),999),IFERROR(FIND("BULK",UPPER($E13)),999),IFERROR(FIND("-",$E13),999),IFERROR(FIND("（",$E13),999))-1))=L$1,$F13,"")) | M13: =IF(OR($E13="",M$1=""),"",IF(TRIM(LEFT($E13,MIN(IFERROR(FIND("CDU",UPPER($E13)),999),IFERROR(FIND("BULK",UPPER($E13)),999),IFERROR(FIND("-",$E13),999),IFERROR(FIND("（",$E13),999))-1))=M$1,$F13,"")) | N13: =IF(OR($E13="",N$1=""),"",IF(TRIM(LEFT($E13,MIN(IFERROR(FIND("CDU",UPPER($E13)),999),IFERROR(FIND("BULK",UPPER($E13)),999),IFERROR(FIND("-",$E13),999),IFERROR(FIND("（",$E13),999))-1))=N$1,$F13,"")) | O13: =IF(OR($E13="",O$1=""),"",IF(TRIM(LEFT($E13,MIN(IFERROR(FIND("CDU",UPPER($E13)),999),IFERROR(FIND("BULK",UPPER($E13)),999),IFERROR(FIND("-",$E13),999),IFERROR(FIND("（",$E13),999))-1))=O$1,$F13,"")) | P13: =IF(OR($E13="",P$1=""),"",IF(TRIM(LEFT($E13,MIN(IFERROR(FIND("CDU",UPPER($E13)),999),IFERROR(FIND("BULK",UPPER($E13)),999),IFERROR(FIND("-",$E13),999),IFERROR(FIND("（",$E13),999))-1))=P$1,$F13,"")) | ... BU13: =IF(OR($E13="",BU$1=""),"",IF(TRIM(LEFT($E13,MIN(IFERROR(FIND("CDU",UPPER($E13)),999),IFERROR(FIND("BULK",UPPER($E13)),999),IFERROR(FIND("-",$E13),999),IFERROR(FIND("（",$E13),999))-1))=BU$1,$F13,"")) | BV13: 0.87 | BW13: =SUM(I13:BU13)*BV13 -> 1566 | BX13: =BW13*7.75 -> 12136.5 | BY13: =MID(E13,1,2) -> SR
A14: 45807 | B14: 45863 | C14: JAZ254725 | D14: CAJZ050 | E14: SR130CDU-24 | F14: =1800-1200 -> 600 | G14: Jazwares客版（2L） | H14: =IFERROR(VLOOKUP(E14,名称!A:E,4,0),"") -> 二代 | I14: =IF(OR($E14="",I$1=""),"",IF(TRIM(LEFT($E14,MIN(IFERROR(FIND("CDU",UPPER($E14)),999),IFERROR(FIND("BULK",UPPER($E14)),999),IFERROR(FIND("-",$E14),999),IFERROR(FIND("（",$E14),999))-1))=I$1,$F14,"")) | J14: =IF(OR($E14="",J$1=""),"",IF(TRIM(LEFT($E14,MIN(IFERROR(FIND("CDU",UPPER($E14)),999),IFERROR(FIND("BULK",UPPER($E14)),999),IFERROR(FIND("-",$E14),999),IFERROR(FIND("（",$E14),999))-1))=J$1,$F14,"")) | K14: =IF(OR($E14="",K$1=""),"",IF(TRIM(LEFT($E14,MIN(IFERROR(FIND("CDU",UPPER($E14)),999),IFERROR(FIND("BULK",UPPER($E14)),999),IFERROR(FIND("-",$E14),999),IFERROR(FIND("（",$E14),999))-1))=K$1,$F14,"")) | L14: =IF(OR($E14="",L$1=""),"",IF(TRIM(LEFT($E14,MIN(IFERROR(FIND("CDU",UPPER($E14)),999),IFERROR(FIND("BULK",UPPER($E14)),999),IFERROR(FIND("-",$E14),999),IFERROR(FIND("（",$E14),999))-1))=L$1,$F14,"")) | M14: =IF(OR($E14="",M$1=""),"",IF(TRIM(LEFT($E14,MIN(IFERROR(FIND("CDU",UPPER($E14)),999),IFERROR(FIND("BULK",UPPER($E14)),999),IFERROR(FIND("-",$E14),999),IFERROR(FIND("（",$E14),999))-1))=M$1,$F14,"")) | N14: =IF(OR($E14="",N$1=""),"",IF(TRIM(LEFT($E14,MIN(IFERROR(FIND("CDU",UPPER($E14)),999),IFERROR(FIND("BULK",UPPER($E14)),999),IFERROR(FIND("-",$E14),999),IFERROR(FIND("（",$E14),999))-1))=N$1,$F14,"")) -> 600 | O14: =IF(OR($E14="",O$1=""),"",IF(TRIM(LEFT($E14,MIN(IFERROR(FIND("CDU",UPPER($E14)),999),IFERROR(FIND("BULK",UPPER($E14)),999),IFERROR(FIND("-",$E14),999),IFERROR(FIND("（",$E14),999))-1))=O$1,$F14,"")) | P14: =IF(OR($E14="",P$1=""),"",IF(TRIM(LEFT($E14,MIN(IFERROR(FIND("CDU",UPPER($E14)),999),IFERROR(FIND("BULK",UPPER($E14)),999),IFERROR(FIND("-",$E14),999),IFERROR(FIND("（",$E14),999))-1))=P$1,$F14,"")) | ... BU14: =IF(OR($E14="",BU$1=""),"",IF(TRIM(LEFT($E14,MIN(IFERROR(FIND("CDU",UPPER($E14)),999),IFERROR(FIND("BULK",UPPER($E14)),999),IFERROR(FIND("-",$E14),999),IFERROR(FIND("（",$E14),999))-1))=BU$1,$F14,"")) | BV14: 0.62 | BW14: =SUM(I14:BU14)*BV14 -> 372 | BX14: =BW14*7.75 -> 2883 | BY14: =MID(E14,1,2) -> SR
A15: 45807 | B15: 45863 | C15: JAZ254725 | D15: CAJZ050 | E15: SR130CDU-24 | F15: 2280 | G15: Jazwares客版（2L） | H15: =IFERROR(VLOOKUP(E15,名称!A:E,4,0),"") -> 二代 | I15: =IF(OR($E15="",I$1=""),"",IF(TRIM(LEFT($E15,MIN(IFERROR(FIND("CDU",UPPER($E15)),999),IFERROR(FIND("BULK",UPPER($E15)),999),IFERROR(FIND("-",$E15),999),IFERROR(FIND("（",$E15),999))-1))=I$1,$F15,"")) | J15: =IF(OR($E15="",J$1=""),"",IF(TRIM(LEFT($E15,MIN(IFERROR(FIND("CDU",UPPER($E15)),999),IFERROR(FIND("BULK",UPPER($E15)),999),IFERROR(FIND("-",$E15),999),IFERROR(FIND("（",$E15),999))-1))=J$1,$F15,"")) | K15: =IF(OR($E15="",K$1=""),"",IF(TRIM(LEFT($E15,MIN(IFERROR(FIND("CDU",UPPER($E15)),999),IFERROR(FIND("BULK",UPPER($E15)),999),IFERROR(FIND("-",$E15),999),IFERROR(FIND("（",$E15),999))-1))=K$1,$F15,"")) | L15: =IF(OR($E15="",L$1=""),"",IF(TRIM(LEFT($E15,MIN(IFERROR(FIND("CDU",UPPER($E15)),999),IFERROR(FIND("BULK",UPPER($E15)),999),IFERROR(FIND("-",$E15),999),IFERROR(FIND("（",$E15),999))-1))=L$1,$F15,"")) | M15: =IF(OR($E15="",M$1=""),"",IF(TRIM(LEFT($E15,MIN(IFERROR(FIND("CDU",UPPER($E15)),999),IFERROR(FIND("BULK",UPPER($E15)),999),IFERROR(FIND("-",$E15),999),IFERROR(FIND("（",$E15),999))-1))=M$1,$F15,"")) | N15: =IF(OR($E15="",N$1=""),"",IF(TRIM(LEFT($E15,MIN(IFERROR(FIND("CDU",UPPER($E15)),999),IFERROR(FIND("BULK",UPPER($E15)),999),IFERROR(FIND("-",$E15),999),IFERROR(FIND("（",$E15),999))-1))=N$1,$F15,"")) -> 2280 | O15: =IF(OR($E15="",O$1=""),"",IF(TRIM(LEFT($E15,MIN(IFERROR(FIND("CDU",UPPER($E15)),999),IFERROR(FIND("BULK",UPPER($E15)),999),IFERROR(FIND("-",$E15),999),IFERROR(FIND("（",$E15),999))-1))=O$1,$F15,"")) | P15: =IF(OR($E15="",P$1=""),"",IF(TRIM(LEFT($E15,MIN(IFERROR(FIND("CDU",UPPER($E15)),999),IFERROR(FIND("BULK",UPPER($E15)),999),IFERROR(FIND("-",$E15),999),IFERROR(FIND("（",$E15),999))-1))=P$1,$F15,"")) | ... BU15: =IF(OR($E15="",BU$1=""),"",IF(TRIM(LEFT($E15,MIN(IFERROR(FIND("CDU",UPPER($E15)),999),IFERROR(FIND("BULK",UPPER($E15)),999),IFERROR(FIND("-",$E15),999),IFERROR(FIND("（",$E15),999))-1))=BU$1,$F15,"")) | BV15: 0.62 | BW15: =SUM(I15:BU15)*BV15 -> 1413.6 | BX15: =BW15*7.75 -> 10955.4 | BY15: =MID(E15,1,2) -> SR
A16: 45807 | B16: 45863 | C16: JAZ254726 | D16: CAJZ051 | E16: SR130CDU-24 | F16: 2400 | G16: Jazwares客版（2L） | H16: =IFERROR(VLOOKUP(E16,名称!A:E,4,0),"") -> 二代 | I16: =IF(OR($E16="",I$1=""),"",IF(TRIM(LEFT($E16,MIN(IFERROR(FIND("CDU",UPPER($E16)),999),IFERROR(FIND("BULK",UPPER($E16)),999),IFERROR(FIND("-",$E16),999),IFERROR(FIND("（",$E16),999))-1))=I$1,$F16,"")) | J16: =IF(OR($E16="",J$1=""),"",IF(TRIM(LEFT($E16,MIN(IFERROR(FIND("CDU",UPPER($E16)),999),IFERROR(FIND("BULK",UPPER($E16)),999),IFERROR(FIND("-",$E16),999),IFERROR(FIND("（",$E16),999))-1))=J$1,$F16,"")) | K16: =IF(OR($E16="",K$1=""),"",IF(TRIM(LEFT($E16,MIN(IFERROR(FIND("CDU",UPPER($E16)),999),IFERROR(FIND("BULK",UPPER($E16)),999),IFERROR(FIND("-",$E16),999),IFERROR(FIND("（",$E16),999))-1))=K$1,$F16,"")) | L16: =IF(OR($E16="",L$1=""),"",IF(TRIM(LEFT($E16,MIN(IFERROR(FIND("CDU",UPPER($E16)),999),IFERROR(FIND("BULK",UPPER($E16)),999),IFERROR(FIND("-",$E16),999),IFERROR(FIND("（",$E16),999))-1))=L$1,$F16,"")) | M16: =IF(OR($E16="",M$1=""),"",IF(TRIM(LEFT($E16,MIN(IFERROR(FIND("CDU",UPPER($E16)),999),IFERROR(FIND("BULK",UPPER($E16)),999),IFERROR(FIND("-",$E16),999),IFERROR(FIND("（",$E16),999))-1))=M$1,$F16,"")) | N16: =IF(OR($E16="",N$1=""),"",IF(TRIM(LEFT($E16,MIN(IFERROR(FIND("CDU",UPPER($E16)),999),IFERROR(FIND("BULK",UPPER($E16)),999),IFERROR(FIND("-",$E16),999),IFERROR(FIND("（",$E16),999))-1))=N$1,$F16,"")) -> 2400 | O16: =IF(OR($E16="",O$1=""),"",IF(TRIM(LEFT($E16,MIN(IFERROR(FIND("CDU",UPPER($E16)),999),IFERROR(FIND("BULK",UPPER($E16)),999),IFERROR(FIND("-",$E16),999),IFERROR(FIND("（",$E16),999))-1))=O$1,$F16,"")) | P16: =IF(OR($E16="",P$1=""),"",IF(TRIM(LEFT($E16,MIN(IFERROR(FIND("CDU",UPPER($E16)),999),IFERROR(FIND("BULK",UPPER($E16)),999),IFERROR(FIND("-",$E16),999),IFERROR(FIND("（",$E16),999))-1))=P$1,$F16,"")) | ... BU16: =IF(OR($E16="",BU$1=""),"",IF(TRIM(LEFT($E16,MIN(IFERROR(FIND("CDU",UPPER($E16)),999),IFERROR(FIND("BULK",UPPER($E16)),999),IFERROR(FIND("-",$E16),999),IFERROR(FIND("（",$E16),999))-1))=BU$1,$F16,"")) | BV16: 0.62 | BW16: =SUM(I16:BU16)*BV16 -> 1488 | BX16: =BW16*7.75 -> 11532 | BY16: =MID(E16,1,2) -> SR
A17: 45915 | B17: 46087 | C17: JAZ270135 | D17: USJZ141 | E17: SR130CDU-24 | F17: 6216 | G17: Jazwares客版（美文） | H17: =IFERROR(VLOOKUP(E17,名称!A:E,4,0),"") -> 二代 | I17: =IF(OR($E17="",I$1=""),"",IF(TRIM(LEFT($E17,MIN(IFERROR(FIND("CDU",UPPER($E17)),999),IFERROR(FIND("BULK",UPPER($E17)),999),IFERROR(FIND("-",$E17),999),IFERROR(FIND("（",$E17),999))-1))=I$1,$F17,"")) | J17: =IF(OR($E17="",J$1=""),"",IF(TRIM(LEFT($E17,MIN(IFERROR(FIND("CDU",UPPER($E17)),999),IFERROR(FIND("BULK",UPPER($E17)),999),IFERROR(FIND("-",$E17),999),IFERROR(FIND("（",$E17),999))-1))=J$1,$F17,"")) | K17: =IF(OR($E17="",K$1=""),"",IF(TRIM(LEFT($E17,MIN(IFERROR(FIND("CDU",UPPER($E17)),999),IFERROR(FIND("BULK",UPPER($E17)),999),IFERROR(FIND("-",$E17),999),IFERROR(FIND("（",$E17),999))-1))=K$1,$F17,"")) | L17: =IF(OR($E17="",L$1=""),"",IF(TRIM(LEFT($E17,MIN(IFERROR(FIND("CDU",UPPER($E17)),999),IFERROR(FIND("BULK",UPPER($E17)),999),IFERROR(FIND("-",$E17),999),IFERROR(FIND("（",$E17),999))-1))=L$1,$F17,"")) | M17: =IF(OR($E17="",M$1=""),"",IF(TRIM(LEFT($E17,MIN(IFERROR(FIND("CDU",UPPER($E17)),999),IFERROR(FIND("BULK",UPPER($E17)),999),IFERROR(FIND("-",$E17),999),IFERROR(FIND("（",$E17),999))-1))=M$1,$F17,"")) | N17: =IF(OR($E17="",N$1=""),"",IF(TRIM(LEFT($E17,MIN(IFERROR(FIND("CDU",UPPER($E17)),999),IFERROR(FIND("BULK",UPPER($E17)),999),IFERROR(FIND("-",$E17),999),IFERROR(FIND("（",$E17),999))-1))=N$1,$F17,"")) -> 6216 | O17: =IF(OR($E17="",O$1=""),"",IF(TRIM(LEFT($E17,MIN(IFERROR(FIND("CDU",UPPER($E17)),999),IFERROR(FIND("BULK",UPPER($E17)),999),IFERROR(FIND("-",$E17),999),IFERROR(FIND("（",$E17),999))-1))=O$1,$F17,"")) | P17: =IF(OR($E17="",P$1=""),"",IF(TRIM(LEFT($E17,MIN(IFERROR(FIND("CDU",UPPER($E17)),999),IFERROR(FIND("BULK",UPPER($E17)),999),IFERROR(FIND("-",$E17),999),IFERROR(FIND("（",$E17),999))-1))=P$1,$F17,"")) | ... BU17: =IF(OR($E17="",BU$1=""),"",IF(TRIM(LEFT($E17,MIN(IFERROR(FIND("CDU",UPPER($E17)),999),IFERROR(FIND("BULK",UPPER($E17)),999),IFERROR(FIND("-",$E17),999),IFERROR(FIND("（",$E17),999))-1))=BU$1,$F17,"")) | BV17: 0.61 | BW17: =SUM(I17:BU17)*BV17 -> 3791.76 | BX17: =BW17*7.75 -> 29386.14 | BY17: =MID(E17,1,2) -> SR
A18: 45915 | B18: 46045 | C18: JAZ270140 | D18: USJZ140 | E18: SR103CDU-24 | F18: 6048 | G18: Jazwares客版（美文） | H18: =IFERROR(VLOOKUP(E18,名称!A:E,4,0),"") -> 二代 | I18: =IF(OR($E18="",I$1=""),"",IF(TRIM(LEFT($E18,MIN(IFERROR(FIND("CDU",UPPER($E18)),999),IFERROR(FIND("BULK",UPPER($E18)),999),IFERROR(FIND("-",$E18),999),IFERROR(FIND("（",$E18),999))-1))=I$1,$F18,"")) | J18: =IF(OR($E18="",J$1=""),"",IF(TRIM(LEFT($E18,MIN(IFERROR(FIND("CDU",UPPER($E18)),999),IFERROR(FIND("BULK",UPPER($E18)),999),IFERROR(FIND("-",$E18),999),IFERROR(FIND("（",$E18),999))-1))=J$1,$F18,"")) | K18: =IF(OR($E18="",K$1=""),"",IF(TRIM(LEFT($E18,MIN(IFERROR(FIND("CDU",UPPER($E18)),999),IFERROR(FIND("BULK",UPPER($E18)),999),IFERROR(FIND("-",$E18),999),IFERROR(FIND("（",$E18),999))-1))=K$1,$F18,"")) | L18: =IF(OR($E18="",L$1=""),"",IF(TRIM(LEFT($E18,MIN(IFERROR(FIND("CDU",UPPER($E18)),999),IFERROR(FIND("BULK",UPPER($E18)),999),IFERROR(FIND("-",$E18),999),IFERROR(FIND("（",$E18),999))-1))=L$1,$F18,"")) | M18: =IF(OR($E18="",M$1=""),"",IF(TRIM(LEFT($E18,MIN(IFERROR(FIND("CDU",UPPER($E18)),999),IFERROR(FIND("BULK",UPPER($E18)),999),IFERROR(FIND("-",$E18),999),IFERROR(FIND("（",$E18),999))-1))=M$1,$F18,"")) -> 6048 | N18: =IF(OR($E18="",N$1=""),"",IF(TRIM(LEFT($E18,MIN(IFERROR(FIND("CDU",UPPER($E18)),999),IFERROR(FIND("BULK",UPPER($E18)),999),IFERROR(FIND("-",$E18),999),IFERROR(FIND("（",$E18),999))-1))=N$1,$F18,"")) | O18: =IF(OR($E18="",O$1=""),"",IF(TRIM(LEFT($E18,MIN(IFERROR(FIND("CDU",UPPER($E18)),999),IFERROR(FIND("BULK",UPPER($E18)),999),IFERROR(FIND("-",$E18),999),IFERROR(FIND("（",$E18),999))-1))=O$1,$F18,"")) | P18: =IF(OR($E18="",P$1=""),"",IF(TRIM(LEFT($E18,MIN(IFERROR(FIND("CDU",UPPER($E18)),999),IFERROR(FIND("BULK",UPPER($E18)),999),IFERROR(FIND("-",$E18),999),IFERROR(FIND("（",$E18),999))-1))=P$1,$F18,"")) | ... BU18: =IF(OR($E18="",BU$1=""),"",IF(TRIM(LEFT($E18,MIN(IFERROR(FIND("CDU",UPPER($E18)),999),IFERROR(FIND("BULK",UPPER($E18)),999),IFERROR(FIND("-",$E18),999),IFERROR(FIND("（",$E18),999))-1))=BU$1,$F18,"")) | BV18: 0.61 | BW18: =SUM(I18:BU18)*BV18 -> 3689.28 | BX18: =BW18*7.75 -> 28591.92 | BY18: =MID(E18,1,2) -> SR
A19: 45915 | B19: 46045 | C19: JAZ270141 | D19: USJZ139 | E19: SR201C | F19: 2400 | G19: Jazwares客版（美文） | H19: =IFERROR(VLOOKUP(E19,名称!A:E,4,0),"") -> 二代 | I19: =IF(OR($E19="",I$1=""),"",IF(TRIM(LEFT($E19,MIN(IFERROR(FIND("CDU",UPPER($E19)),999),IFERROR(FIND("BULK",UPPER($E19)),999),IFERROR(FIND("-",$E19),999),IFERROR(FIND("（",$E19),999))-1))=I$1,$F19,"")) | J19: =IF(OR($E19="",J$1=""),"",IF(TRIM(LEFT($E19,MIN(IFERROR(FIND("CDU",UPPER($E19)),999),IFERROR(FIND("BULK",UPPER($E19)),999),IFERROR(FIND("-",$E19),999),IFERROR(FIND("（",$E19),999))-1))=J$1,$F19,"")) | K19: =IF(OR($E19="",K$1=""),"",IF(TRIM(LEFT($E19,MIN(IFERROR(FIND("CDU",UPPER($E19)),999),IFERROR(FIND("BULK",UPPER($E19)),999),IFERROR(FIND("-",$E19),999),IFERROR(FIND("（",$E19),999))-1))=K$1,$F19,"")) | L19: =IF(OR($E19="",L$1=""),"",IF(TRIM(LEFT($E19,MIN(IFERROR(FIND("CDU",UPPER($E19)),999),IFERROR(FIND("BULK",UPPER($E19)),999),IFERROR(FIND("-",$E19),999),IFERROR(FIND("（",$E19),999))-1))=L$1,$F19,"")) | M19: =IF(OR($E19="",M$1=""),"",IF(TRIM(LEFT($E19,MIN(IFERROR(FIND("CDU",UPPER($E19)),999),IFERROR(FIND("BULK",UPPER($E19)),999),IFERROR(FIND("-",$E19),999),IFERROR(FIND("（",$E19),999))-1))=M$1,$F19,"")) | N19: =IF(OR($E19="",N$1=""),"",IF(TRIM(LEFT($E19,MIN(IFERROR(FIND("CDU",UPPER($E19)),999),IFERROR(FIND("BULK",UPPER($E19)),999),IFERROR(FIND("-",$E19),999),IFERROR(FIND("（",$E19),999))-1))=N$1,$F19,"")) | O19: =IF(OR($E19="",O$1=""),"",IF(TRIM(LEFT($E19,MIN(IFERROR(FIND("CDU",UPPER($E19)),999),IFERROR(FIND("BULK",UPPER($E19)),999),IFERROR(FIND("-",$E19),999),IFERROR(FIND("（",$E19),999))-1))=O$1,$F19,"")) | P19: =IF(OR($E19="",P$1=""),"",IF(TRIM(LEFT($E19,MIN(IFERROR(FIND("CDU",UPPER($E19)),999),IFERROR(FIND("BULK",UPPER($E19)),999),IFERROR(FIND("-",$E19),999),IFERROR(FIND("（",$E19),999))-1))=P$1,$F19,"")) | ... BU19: =IF(OR($E19="",BU$1=""),"",IF(TRIM(LEFT($E19,MIN(IFERROR(FIND("CDU",UPPER($E19)),999),IFERROR(FIND("BULK",UPPER($E19)),999),IFERROR(FIND("-",$E19),999),IFERROR(FIND("（",$E19),999))-1))=BU$1,$F19,"")) | BV19: 2.14 | BW19: =SUM(I19:BU19)*BV19 -> 5136 | BX19: =BW19*7.75 -> 39804 | BY19: =MID(E19,1,2) -> SR
A20: 45915 | B20: 46045 | C20: JAZ270136 | D20: USJZ138 | E20: SR130CDU-24 | F20: 6216 | G20: Jazwares客版（美文） | H20: =IFERROR(VLOOKUP(E20,名称!A:E,4,0),"") -> 二代 | I20: =IF(OR($E20="",I$1=""),"",IF(TRIM(LEFT($E20,MIN(IFERROR(FIND("CDU",UPPER($E20)),999),IFERROR(FIND("BULK",UPPER($E20)),999),IFERROR(FIND("-",$E20),999),IFERROR(FIND("（",$E20),999))-1))=I$1,$F20,"")) | J20: =IF(OR($E20="",J$1=""),"",IF(TRIM(LEFT($E20,MIN(IFERROR(FIND("CDU",UPPER($E20)),999),IFERROR(FIND("BULK",UPPER($E20)),999),IFERROR(FIND("-",$E20),999),IFERROR(FIND("（",$E20),999))-1))=J$1,$F20,"")) | K20: =IF(OR($E20="",K$1=""),"",IF(TRIM(LEFT($E20,MIN(IFERROR(FIND("CDU",UPPER($E20)),999),IFERROR(FIND("BULK",UPPER($E20)),999),IFERROR(FIND("-",$E20),999),IFERROR(FIND("（",$E20),999))-1))=K$1,$F20,"")) | L20: =IF(OR($E20="",L$1=""),"",IF(TRIM(LEFT($E20,MIN(IFERROR(FIND("CDU",UPPER($E20)),999),IFERROR(FIND("BULK",UPPER($E20)),999),IFERROR(FIND("-",$E20),999),IFERROR(FIND("（",$E20),999))-1))=L$1,$F20,"")) | M20: =IF(OR($E20="",M$1=""),"",IF(TRIM(LEFT($E20,MIN(IFERROR(FIND("CDU",UPPER($E20)),999),IFERROR(FIND("BULK",UPPER($E20)),999),IFERROR(FIND("-",$E20),999),IFERROR(FIND("（",$E20),999))-1))=M$1,$F20,"")) | N20: =IF(OR($E20="",N$1=""),"",IF(TRIM(LEFT($E20,MIN(IFERROR(FIND("CDU",UPPER($E20)),999),IFERROR(FIND("BULK",UPPER($E20)),999),IFERROR(FIND("-",$E20),999),IFERROR(FIND("（",$E20),999))-1))=N$1,$F20,"")) -> 6216 | O20: =IF(OR($E20="",O$1=""),"",IF(TRIM(LEFT($E20,MIN(IFERROR(FIND("CDU",UPPER($E20)),999),IFERROR(FIND("BULK",UPPER($E20)),999),IFERROR(FIND("-",$E20),999),IFERROR(FIND("（",$E20),999))-1))=O$1,$F20,"")) | P20: =IF(OR($E20="",P$1=""),"",IF(TRIM(LEFT($E20,MIN(IFERROR(FIND("CDU",UPPER($E20)),999),IFERROR(FIND("BULK",UPPER($E20)),999),IFERROR(FIND("-",$E20),999),IFERROR(FIND("（",$E20),999))-1))=P$1,$F20,"")) | ... BU20: =IF(OR($E20="",BU$1=""),"",IF(TRIM(LEFT($E20,MIN(IFERROR(FIND("CDU",UPPER($E20)),999),IFERROR(FIND("BULK",UPPER($E20)),999),IFERROR(FIND("-",$E20),999),IFERROR(FIND("（",$E20),999))-1))=BU$1,$F20,"")) | BV20: 0.61 | BW20: =SUM(I20:BU20)*BV20 -> 3791.76 | BX20: =BW20*7.75 -> 29386.14 | BY20: =MID(E20,1,2) -> SR
A21: 45915 | B21: 46045 | C21: JAZ270142 | D21: USJZ137 | E21: SR201C | F21: 2400 | G21: Jazwares客版（美文） | H21: =IFERROR(VLOOKUP(E21,名称!A:E,4,0),"") -> 二代 | I21: =IF(OR($E21="",I$1=""),"",IF(TRIM(LEFT($E21,MIN(IFERROR(FIND("CDU",UPPER($E21)),999),IFERROR(FIND("BULK",UPPER($E21)),999),IFERROR(FIND("-",$E21),999),IFERROR(FIND("（",$E21),999))-1))=I$1,$F21,"")) | J21: =IF(OR($E21="",J$1=""),"",IF(TRIM(LEFT($E21,MIN(IFERROR(FIND("CDU",UPPER($E21)),999),IFERROR(FIND("BULK",UPPER($E21)),999),IFERROR(FIND("-",$E21),999),IFERROR(FIND("（",$E21),999))-1))=J$1,$F21,"")) | K21: =IF(OR($E21="",K$1=""),"",IF(TRIM(LEFT($E21,MIN(IFERROR(FIND("CDU",UPPER($E21)),999),IFERROR(FIND("BULK",UPPER($E21)),999),IFERROR(FIND("-",$E21),999),IFERROR(FIND("（",$E21),999))-1))=K$1,$F21,"")) | L21: =IF(OR($E21="",L$1=""),"",IF(TRIM(LEFT($E21,MIN(IFERROR(FIND("CDU",UPPER($E21)),999),IFERROR(FIND("BULK",UPPER($E21)),999),IFERROR(FIND("-",$E21),999),IFERROR(FIND("（",$E21),999))-1))=L$1,$F21,"")) | M21: =IF(OR($E21="",M$1=""),"",IF(TRIM(LEFT($E21,MIN(IFERROR(FIND("CDU",UPPER($E21)),999),IFERROR(FIND("BULK",UPPER($E21)),999),IFERROR(FIND("-",$E21),999),IFERROR(FIND("（",$E21),999))-1))=M$1,$F21,"")) | N21: =IF(OR($E21="",N$1=""),"",IF(TRIM(LEFT($E21,MIN(IFERROR(FIND("CDU",UPPER($E21)),999),IFERROR(FIND("BULK",UPPER($E21)),999),IFERROR(FIND("-",$E21),999),IFERROR(FIND("（",$E21),999))-1))=N$1,$F21,"")) | O21: =IF(OR($E21="",O$1=""),"",IF(TRIM(LEFT($E21,MIN(IFERROR(FIND("CDU",UPPER($E21)),999),IFERROR(FIND("BULK",UPPER($E21)),999),IFERROR(FIND("-",$E21),999),IFERROR(FIND("（",$E21),999))-1))=O$1,$F21,"")) | P21: =IF(OR($E21="",P$1=""),"",IF(TRIM(LEFT($E21,MIN(IFERROR(FIND("CDU",UPPER($E21)),999),IFERROR(FIND("BULK",UPPER($E21)),999),IFERROR(FIND("-",$E21),999),IFERROR(FIND("（",$E21),999))-1))=P$1,$F21,"")) | ... BU21: =IF(OR($E21="",BU$1=""),"",IF(TRIM(LEFT($E21,MIN(IFERROR(FIND("CDU",UPPER($E21)),999),IFERROR(FIND("BULK",UPPER($E21)),999),IFERROR(FIND("-",$E21),999),IFERROR(FIND("（",$E21),999))-1))=BU$1,$F21,"")) | BV21: 2.14 | BW21: =SUM(I21:BU21)*BV21 -> 5136 | BX21: =BW21*7.75 -> 39804 | BY21: =MID(E21,1,2) -> SR
A22: 45915 | B22: 46045 | C22: JAZ270137 | D22: USJZ136 | E22: SR130CDU-24 | F22: 6216 | G22: Jazwares客版（美文） | H22: =IFERROR(VLOOKUP(E22,名称!A:E,4,0),"") -> 二代 | I22: =IF(OR($E22="",I$1=""),"",IF(TRIM(LEFT($E22,MIN(IFERROR(FIND("CDU",UPPER($E22)),999),IFERROR(FIND("BULK",UPPER($E22)),999),IFERROR(FIND("-",$E22),999),IFERROR(FIND("（",$E22),999))-1))=I$1,$F22,"")) | J22: =IF(OR($E22="",J$1=""),"",IF(TRIM(LEFT($E22,MIN(IFERROR(FIND("CDU",UPPER($E22)),999),IFERROR(FIND("BULK",UPPER($E22)),999),IFERROR(FIND("-",$E22),999),IFERROR(FIND("（",$E22),999))-1))=J$1,$F22,"")) | K22: =IF(OR($E22="",K$1=""),"",IF(TRIM(LEFT($E22,MIN(IFERROR(FIND("CDU",UPPER($E22)),999),IFERROR(FIND("BULK",UPPER($E22)),999),IFERROR(FIND("-",$E22),999),IFERROR(FIND("（",$E22),999))-1))=K$1,$F22,"")) | L22: =IF(OR($E22="",L$1=""),"",IF(TRIM(LEFT($E22,MIN(IFERROR(FIND("CDU",UPPER($E22)),999),IFERROR(FIND("BULK",UPPER($E22)),999),IFERROR(FIND("-",$E22),999),IFERROR(FIND("（",$E22),999))-1))=L$1,$F22,"")) | M22: =IF(OR($E22="",M$1=""),"",IF(TRIM(LEFT($E22,MIN(IFERROR(FIND("CDU",UPPER($E22)),999),IFERROR(FIND("BULK",UPPER($E22)),999),IFERROR(FIND("-",$E22),999),IFERROR(FIND("（",$E22),999))-1))=M$1,$F22,"")) | N22: =IF(OR($E22="",N$1=""),"",IF(TRIM(LEFT($E22,MIN(IFERROR(FIND("CDU",UPPER($E22)),999),IFERROR(FIND("BULK",UPPER($E22)),999),IFERROR(FIND("-",$E22),999),IFERROR(FIND("（",$E22),999))-1))=N$1,$F22,"")) -> 6216 | O22: =IF(OR($E22="",O$1=""),"",IF(TRIM(LEFT($E22,MIN(IFERROR(FIND("CDU",UPPER($E22)),999),IFERROR(FIND("BULK",UPPER($E22)),999),IFERROR(FIND("-",$E22),999),IFERROR(FIND("（",$E22),999))-1))=O$1,$F22,"")) | P22: =IF(OR($E22="",P$1=""),"",IF(TRIM(LEFT($E22,MIN(IFERROR(FIND("CDU",UPPER($E22)),999),IFERROR(FIND("BULK",UPPER($E22)),999),IFERROR(FIND("-",$E22),999),IFERROR(FIND("（",$E22),999))-1))=P$1,$F22,"")) | ... BU22: =IF(OR($E22="",BU$1=""),"",IF(TRIM(LEFT($E22,MIN(IFERROR(FIND("CDU",UPPER($E22)),999),IFERROR(FIND("BULK",UPPER($E22)),999),IFERROR(FIND("-",$E22),999),IFERROR(FIND("（",$E22),999))-1))=BU$1,$F22,"")) | BV22: 0.61 | BW22: =SUM(I22:BU22)*BV22 -> 3791.76 | BX22: =BW22*7.75 -> 29386.14 | BY22: =MID(E22,1,2) -> SR
A23: 45915 | B23: 46045 | C23: JAZ270143 | D23: USJZ135 | E23: SR201C | F23: 2400 | G23: Jazwares客版（美文） | H23: =IFERROR(VLOOKUP(E23,名称!A:E,4,0),"") -> 二代 | I23: =IF(OR($E23="",I$1=""),"",IF(TRIM(LEFT($E23,MIN(IFERROR(FIND("CDU",UPPER($E23)),999),IFERROR(FIND("BULK",UPPER($E23)),999),IFERROR(FIND("-",$E23),999),IFERROR(FIND("（",$E23),999))-1))=I$1,$F23,"")) | J23: =IF(OR($E23="",J$1=""),"",IF(TRIM(LEFT($E23,MIN(IFERROR(FIND("CDU",UPPER($E23)),999),IFERROR(FIND("BULK",UPPER($E23)),999),IFERROR(FIND("-",$E23),999),IFERROR(FIND("（",$E23),999))-1))=J$1,$F23,"")) | K23: =IF(OR($E23="",K$1=""),"",IF(TRIM(LEFT($E23,MIN(IFERROR(FIND("CDU",UPPER($E23)),999),IFERROR(FIND("BULK",UPPER($E23)),999),IFERROR(FIND("-",$E23),999),IFERROR(FIND("（",$E23),999))-1))=K$1,$F23,"")) | L23: =IF(OR($E23="",L$1=""),"",IF(TRIM(LEFT($E23,MIN(IFERROR(FIND("CDU",UPPER($E23)),999),IFERROR(FIND("BULK",UPPER($E23)),999),IFERROR(FIND("-",$E23),999),IFERROR(FIND("（",$E23),999))-1))=L$1,$F23,"")) | M23: =IF(OR($E23="",M$1=""),"",IF(TRIM(LEFT($E23,MIN(IFERROR(FIND("CDU",UPPER($E23)),999),IFERROR(FIND("BULK",UPPER($E23)),999),IFERROR(FIND("-",$E23),999),IFERROR(FIND("（",$E23),999))-1))=M$1,$F23,"")) | N23: =IF(OR($E23="",N$1=""),"",IF(TRIM(LEFT($E23,MIN(IFERROR(FIND("CDU",UPPER($E23)),999),IFERROR(FIND("BULK",UPPER($E23)),999),IFERROR(FIND("-",$E23),999),IFERROR(FIND("（",$E23),999))-1))=N$1,$F23,"")) | O23: =IF(OR($E23="",O$1=""),"",IF(TRIM(LEFT($E23,MIN(IFERROR(FIND("CDU",UPPER($E23)),999),IFERROR(FIND("BULK",UPPER($E23)),999),IFERROR(FIND("-",$E23),999),IFERROR(FIND("（",$E23),999))-1))=O$1,$F23,"")) | P23: =IF(OR($E23="",P$1=""),"",IF(TRIM(LEFT($E23,MIN(IFERROR(FIND("CDU",UPPER($E23)),999),IFERROR(FIND("BULK",UPPER($E23)),999),IFERROR(FIND("-",$E23),999),IFERROR(FIND("（",$E23),999))-1))=P$1,$F23,"")) | ... BU23: =IF(OR($E23="",BU$1=""),"",IF(TRIM(LEFT($E23,MIN(IFERROR(FIND("CDU",UPPER($E23)),999),IFERROR(FIND("BULK",UPPER($E23)),999),IFERROR(FIND("-",$E23),999),IFERROR(FIND("（",$E23),999))-1))=BU$1,$F23,"")) | BV23: 2.14 | BW23: =SUM(I23:BU23)*BV23 -> 5136 | BX23: =BW23*7.75 -> 39804 | BY23: =MID(E23,1,2) -> SR
A24: 45915 | B24: 46045 | C24: JAZ270138 | D24: USJZ134 | E24: SR130CDU-24 | F24: 6216 | G24: Jazwares客版（美文） | H24: =IFERROR(VLOOKUP(E24,名称!A:E,4,0),"") -> 二代 | I24: =IF(OR($E24="",I$1=""),"",IF(TRIM(LEFT($E24,MIN(IFERROR(FIND("CDU",UPPER($E24)),999),IFERROR(FIND("BULK",UPPER($E24)),999),IFERROR(FIND("-",$E24),999),IFERROR(FIND("（",$E24),999))-1))=I$1,$F24,"")) | J24: =IF(OR($E24="",J$1=""),"",IF(TRIM(LEFT($E24,MIN(IFERROR(FIND("CDU",UPPER($E24)),999),IFERROR(FIND("BULK",UPPER($E24)),999),IFERROR(FIND("-",$E24),999),IFERROR(FIND("（",$E24),999))-1))=J$1,$F24,"")) | K24: =IF(OR($E24="",K$1=""),"",IF(TRIM(LEFT($E24,MIN(IFERROR(FIND("CDU",UPPER($E24)),999),IFERROR(FIND("BULK",UPPER($E24)),999),IFERROR(FIND("-",$E24),999),IFERROR(FIND("（",$E24),999))-1))=K$1,$F24,"")) | L24: =IF(OR($E24="",L$1=""),"",IF(TRIM(LEFT($E24,MIN(IFERROR(FIND("CDU",UPPER($E24)),999),IFERROR(FIND("BULK",UPPER($E24)),999),IFERROR(FIND("-",$E24),999),IFERROR(FIND("（",$E24),999))-1))=L$1,$F24,"")) | M24: =IF(OR($E24="",M$1=""),"",IF(TRIM(LEFT($E24,MIN(IFERROR(FIND("CDU",UPPER($E24)),999),IFERROR(FIND("BULK",UPPER($E24)),999),IFERROR(FIND("-",$E24),999),IFERROR(FIND("（",$E24),999))-1))=M$1,$F24,"")) | N24: =IF(OR($E24="",N$1=""),"",IF(TRIM(LEFT($E24,MIN(IFERROR(FIND("CDU",UPPER($E24)),999),IFERROR(FIND("BULK",UPPER($E24)),999),IFERROR(FIND("-",$E24),999),IFERROR(FIND("（",$E24),999))-1))=N$1,$F24,"")) -> 6216 | O24: =IF(OR($E24="",O$1=""),"",IF(TRIM(LEFT($E24,MIN(IFERROR(FIND("CDU",UPPER($E24)),999),IFERROR(FIND("BULK",UPPER($E24)),999),IFERROR(FIND("-",$E24),999),IFERROR(FIND("（",$E24),999))-1))=O$1,$F24,"")) | P24: =IF(OR($E24="",P$1=""),"",IF(TRIM(LEFT($E24,MIN(IFERROR(FIND("CDU",UPPER($E24)),999),IFERROR(FIND("BULK",UPPER($E24)),999),IFERROR(FIND("-",$E24),999),IFERROR(FIND("（",$E24),999))-1))=P$1,$F24,"")) | ... BU24: =IF(OR($E24="",BU$1=""),"",IF(TRIM(LEFT($E24,MIN(IFERROR(FIND("CDU",UPPER($E24)),999),IFERROR(FIND("BULK",UPPER($E24)),999),IFERROR(FIND("-",$E24),999),IFERROR(FIND("（",$E24),999))-1))=BU$1,$F24,"")) | BV24: 0.61 | BW24: =SUM(I24:BU24)*BV24 -> 3791.76 | BX24: =BW24*7.75 -> 29386.14 | BY24: =MID(E24,1,2) -> SR
A25: 45915 | B25: 46031 | C25: JAZ270139 | D25: USJZ133 | E25: SR130CDU-24 | F25: 3000 | G25: Jazwares客版（美文） | H25: =IFERROR(VLOOKUP(E25,名称!A:E,4,0),"") -> 二代 | I25: =IF(OR($E25="",I$1=""),"",IF(TRIM(LEFT($E25,MIN(IFERROR(FIND("CDU",UPPER($E25)),999),IFERROR(FIND("BULK",UPPER($E25)),999),IFERROR(FIND("-",$E25),999),IFERROR(FIND("（",$E25),999))-1))=I$1,$F25,"")) | J25: =IF(OR($E25="",J$1=""),"",IF(TRIM(LEFT($E25,MIN(IFERROR(FIND("CDU",UPPER($E25)),999),IFERROR(FIND("BULK",UPPER($E25)),999),IFERROR(FIND("-",$E25),999),IFERROR(FIND("（",$E25),999))-1))=J$1,$F25,"")) | K25: =IF(OR($E25="",K$1=""),"",IF(TRIM(LEFT($E25,MIN(IFERROR(FIND("CDU",UPPER($E25)),999),IFERROR(FIND("BULK",UPPER($E25)),999),IFERROR(FIND("-",$E25),999),IFERROR(FIND("（",$E25),999))-1))=K$1,$F25,"")) | L25: =IF(OR($E25="",L$1=""),"",IF(TRIM(LEFT($E25,MIN(IFERROR(FIND("CDU",UPPER($E25)),999),IFERROR(FIND("BULK",UPPER($E25)),999),IFERROR(FIND("-",$E25),999),IFERROR(FIND("（",$E25),999))-1))=L$1,$F25,"")) | M25: =IF(OR($E25="",M$1=""),"",IF(TRIM(LEFT($E25,MIN(IFERROR(FIND("CDU",UPPER($E25)),999),IFERROR(FIND("BULK",UPPER($E25)),999),IFERROR(FIND("-",$E25),999),IFERROR(FIND("（",$E25),999))-1))=M$1,$F25,"")) | N25: =IF(OR($E25="",N$1=""),"",IF(TRIM(LEFT($E25,MIN(IFERROR(FIND("CDU",UPPER($E25)),999),IFERROR(FIND("BULK",UPPER($E25)),999),IFERROR(FIND("-",$E25),999),IFERROR(FIND("（",$E25),999))-1))=N$1,$F25,"")) -> 3000 | O25: =IF(OR($E25="",O$1=""),"",IF(TRIM(LEFT($E25,MIN(IFERROR(FIND("CDU",UPPER($E25)),999),IFERROR(FIND("BULK",UPPER($E25)),999),IFERROR(FIND("-",$E25),999),IFERROR(FIND("（",$E25),999))-1))=O$1,$F25,"")) | P25: =IF(OR($E25="",P$1=""),"",IF(TRIM(LEFT($E25,MIN(IFERROR(FIND("CDU",UPPER($E25)),999),IFERROR(FIND("BULK",UPPER($E25)),999),IFERROR(FIND("-",$E25),999),IFERROR(FIND("（",$E25),999))-1))=P$1,$F25,"")) | ... BU25: =IF(OR($E25="",BU$1=""),"",IF(TRIM(LEFT($E25,MIN(IFERROR(FIND("CDU",UPPER($E25)),999),IFERROR(FIND("BULK",UPPER($E25)),999),IFERROR(FIND("-",$E25),999),IFERROR(FIND("（",$E25),999))-1))=BU$1,$F25,"")) | BV25: 0.61 | BW25: =SUM(I25:BU25)*BV25 -> 1830 | BX25: =BW25*7.75 -> 14182.5 | BY25: =MID(E25,1,2) -> SR
A26: 45915 | B26: 46031 | C26: JAZ270144 | D26: USJZ132 | E26: SR201C | F26: 2400 | G26: Jazwares客版（美文） | H26: =IFERROR(VLOOKUP(E26,名称!A:E,4,0),"") -> 二代 | I26: =IF(OR($E26="",I$1=""),"",IF(TRIM(LEFT($E26,MIN(IFERROR(FIND("CDU",UPPER($E26)),999),IFERROR(FIND("BULK",UPPER($E26)),999),IFERROR(FIND("-",$E26),999),IFERROR(FIND("（",$E26),999))-1))=I$1,$F26,"")) | J26: =IF(OR($E26="",J$1=""),"",IF(TRIM(LEFT($E26,MIN(IFERROR(FIND("CDU",UPPER($E26)),999),IFERROR(FIND("BULK",UPPER($E26)),999),IFERROR(FIND("-",$E26),999),IFERROR(FIND("（",$E26),999))-1))=J$1,$F26,"")) | K26: =IF(OR($E26="",K$1=""),"",IF(TRIM(LEFT($E26,MIN(IFERROR(FIND("CDU",UPPER($E26)),999),IFERROR(FIND("BULK",UPPER($E26)),999),IFERROR(FIND("-",$E26),999),IFERROR(FIND("（",$E26),999))-1))=K$1,$F26,"")) | L26: =IF(OR($E26="",L$1=""),"",IF(TRIM(LEFT($E26,MIN(IFERROR(FIND("CDU",UPPER($E26)),999),IFERROR(FIND("BULK",UPPER($E26)),999),IFERROR(FIND("-",$E26),999),IFERROR(FIND("（",$E26),999))-1))=L$1,$F26,"")) | M26: =IF(OR($E26="",M$1=""),"",IF(TRIM(LEFT($E26,MIN(IFERROR(FIND("CDU",UPPER($E26)),999),IFERROR(FIND("BULK",UPPER($E26)),999),IFERROR(FIND("-",$E26),999),IFERROR(FIND("（",$E26),999))-1))=M$1,$F26,"")) | N26: =IF(OR($E26="",N$1=""),"",IF(TRIM(LEFT($E26,MIN(IFERROR(FIND("CDU",UPPER($E26)),999),IFERROR(FIND("BULK",UPPER($E26)),999),IFERROR(FIND("-",$E26),999),IFERROR(FIND("（",$E26),999))-1))=N$1,$F26,"")) | O26: =IF(OR($E26="",O$1=""),"",IF(TRIM(LEFT($E26,MIN(IFERROR(FIND("CDU",UPPER($E26)),999),IFERROR(FIND("BULK",UPPER($E26)),999),IFERROR(FIND("-",$E26),999),IFERROR(FIND("（",$E26),999))-1))=O$1,$F26,"")) | P26: =IF(OR($E26="",P$1=""),"",IF(TRIM(LEFT($E26,MIN(IFERROR(FIND("CDU",UPPER($E26)),999),IFERROR(FIND("BULK",UPPER($E26)),999),IFERROR(FIND("-",$E26),999),IFERROR(FIND("（",$E26),999))-1))=P$1,$F26,"")) | ... BU26: =IF(OR($E26="",BU$1=""),"",IF(TRIM(LEFT($E26,MIN(IFERROR(FIND("CDU",UPPER($E26)),999),IFERROR(FIND("BULK",UPPER($E26)),999),IFERROR(FIND("-",$E26),999),IFERROR(FIND("（",$E26),999))-1))=BU$1,$F26,"")) | BV26: 2.14 | BW26: =SUM(I26:BU26)*BV26 -> 5136 | BX26: =BW26*7.75 -> 39804 | BY26: =MID(E26,1,2) -> SR
... A43: 45953 | B43: 46107 | C43: JAZ275406 | D43: PO0000028-USJZ | E43: SR103CDU-24 | F43: 14016 | G43: Jazwares客版（美文） | H43: =IFERROR(VLOOKUP(E43,名称!A:E,4,0),"") -> 二代 | I43: =IF(OR($E43="",I$1=""),"",IF(TRIM(LEFT($E43,MIN(IFERROR(FIND("CDU",UPPER($E43)),999),IFERROR(FIND("BULK",UPPER($E43)),999),IFERROR(FIND("-",$E43),999),IFERROR(FIND("（",$E43),999))-1))=I$1,$F43,"")) | J43: =IF(OR($E43="",J$1=""),"",IF(TRIM(LEFT($E43,MIN(IFERROR(FIND("CDU",UPPER($E43)),999),IFERROR(FIND("BULK",UPPER($E43)),999),IFERROR(FIND("-",$E43),999),IFERROR(FIND("（",$E43),999))-1))=J$1,$F43,"")) | K43: =IF(OR($E43="",K$1=""),"",IF(TRIM(LEFT($E43,MIN(IFERROR(FIND("CDU",UPPER($E43)),999),IFERROR(FIND("BULK",UPPER($E43)),999),IFERROR(FIND("-",$E43),999),IFERROR(FIND("（",$E43),999))-1))=K$1,$F43,"")) | L43: =IF(OR($E43="",L$1=""),"",IF(TRIM(LEFT($E43,MIN(IFERROR(FIND("CDU",UPPER($E43)),999),IFERROR(FIND("BULK",UPPER($E43)),999),IFERROR(FIND("-",$E43),999),IFERROR(FIND("（",$E43),999))-1))=L$1,$F43,"")) | M43: =IF(OR($E43="",M$1=""),"",IF(TRIM(LEFT($E43,MIN(IFERROR(FIND("CDU",UPPER($E43)),999),IFERROR(FIND("BULK",UPPER($E43)),999),IFERROR(FIND("-",$E43),999),IFERROR(FIND("（",$E43),999))-1))=M$1,$F43,"")) -> 14016 | N43: =IF(OR($E43="",N$1=""),"",IF(TRIM(LEFT($E43,MIN(IFERROR(FIND("CDU",UPPER($E43)),999),IFERROR(FIND("BULK",UPPER($E43)),999),IFERROR(FIND("-",$E43),999),IFERROR(FIND("（",$E43),999))-1))=N$1,$F43,"")) | O43: =IF(OR($E43="",O$1=""),"",IF(TRIM(LEFT($E43,MIN(IFERROR(FIND("CDU",UPPER($E43)),999),IFERROR(FIND("BULK",UPPER($E43)),999),IFERROR(FIND("-",$E43),999),IFERROR(FIND("（",$E43),999))-1))=O$1,$F43,"")) | P43: =IF(OR($E43="",P$1=""),"",IF(TRIM(LEFT($E43,MIN(IFERROR(FIND("CDU",UPPER($E43)),999),IFERROR(FIND("BULK",UPPER($E43)),999),IFERROR(FIND("-",$E43),999),IFERROR(FIND("（",$E43),999))-1))=P$1,$F43,"")) | ... BU43: =IF(OR($E43="",BU$1=""),"",IF(TRIM(LEFT($E43,MIN(IFERROR(FIND("CDU",UPPER($E43)),999),IFERROR(FIND("BULK",UPPER($E43)),999),IFERROR(FIND("-",$E43),999),IFERROR(FIND("（",$E43),999))-1))=BU$1,$F43,"")) | BV43: 0.61 | BW43: =SUM(I43:BU43)*BV43 -> 8549.76 | BX43: =BW43*7.75 -> 66260.64 | BY43: =MID(E43,1,2) -> SR
A44: 45953 | B44: 46107 | C44: JAZ275410 | D44: PO0000029-USJZ | E44: SR201C | F44: =9000-1500+1500 -> 9000 | G44: Jazwares客版（美文） | H44: =IFERROR(VLOOKUP(E44,名称!A:E,4,0),"") -> 二代 | I44: =IF(OR($E44="",I$1=""),"",IF(TRIM(LEFT($E44,MIN(IFERROR(FIND("CDU",UPPER($E44)),999),IFERROR(FIND("BULK",UPPER($E44)),999),IFERROR(FIND("-",$E44),999),IFERROR(FIND("（",$E44),999))-1))=I$1,$F44,"")) | J44: =IF(OR($E44="",J$1=""),"",IF(TRIM(LEFT($E44,MIN(IFERROR(FIND("CDU",UPPER($E44)),999),IFERROR(FIND("BULK",UPPER($E44)),999),IFERROR(FIND("-",$E44),999),IFERROR(FIND("（",$E44),999))-1))=J$1,$F44,"")) | K44: =IF(OR($E44="",K$1=""),"",IF(TRIM(LEFT($E44,MIN(IFERROR(FIND("CDU",UPPER($E44)),999),IFERROR(FIND("BULK",UPPER($E44)),999),IFERROR(FIND("-",$E44),999),IFERROR(FIND("（",$E44),999))-1))=K$1,$F44,"")) | L44: =IF(OR($E44="",L$1=""),"",IF(TRIM(LEFT($E44,MIN(IFERROR(FIND("CDU",UPPER($E44)),999),IFERROR(FIND("BULK",UPPER($E44)),999),IFERROR(FIND("-",$E44),999),IFERROR(FIND("（",$E44),999))-1))=L$1,$F44,"")) | M44: =IF(OR($E44="",M$1=""),"",IF(TRIM(LEFT($E44,MIN(IFERROR(FIND("CDU",UPPER($E44)),999),IFERROR(FIND("BULK",UPPER($E44)),999),IFERROR(FIND("-",$E44),999),IFERROR(FIND("（",$E44),999))-1))=M$1,$F44,"")) | N44: =IF(OR($E44="",N$1=""),"",IF(TRIM(LEFT($E44,MIN(IFERROR(FIND("CDU",UPPER($E44)),999),IFERROR(FIND("BULK",UPPER($E44)),999),IFERROR(FIND("-",$E44),999),IFERROR(FIND("（",$E44),999))-1))=N$1,$F44,"")) | O44: =IF(OR($E44="",O$1=""),"",IF(TRIM(LEFT($E44,MIN(IFERROR(FIND("CDU",UPPER($E44)),999),IFERROR(FIND("BULK",UPPER($E44)),999),IFERROR(FIND("-",$E44),999),IFERROR(FIND("（",$E44),999))-1))=O$1,$F44,"")) | P44: =IF(OR($E44="",P$1=""),"",IF(TRIM(LEFT($E44,MIN(IFERROR(FIND("CDU",UPPER($E44)),999),IFERROR(FIND("BULK",UPPER($E44)),999),IFERROR(FIND("-",$E44),999),IFERROR(FIND("（",$E44),999))-1))=P$1,$F44,"")) | ... BU44: =IF(OR($E44="",BU$1=""),"",IF(TRIM(LEFT($E44,MIN(IFERROR(FIND("CDU",UPPER($E44)),999),IFERROR(FIND("BULK",UPPER($E44)),999),IFERROR(FIND("-",$E44),999),IFERROR(FIND("（",$E44),999))-1))=BU$1,$F44,"")) | BV44: 2.14 | BW44: =SUM(I44:BU44)*BV44 -> 19260 | BX44: =BW44*7.75 -> 149265 | BY44: =MID(E44,1,2) -> SR
A45: 45966 | B45: 46053 | C45: 2916427 | D45: PO0000037-CAJZ | E45: SR103CDU-24 | F45: 1800 | G45: Jazwares客版（2L） | H45: =IFERROR(VLOOKUP(E45,名称!A:E,4,0),"") -> 二代 | I45: =IF(OR($E45="",I$1=""),"",IF(TRIM(LEFT($E45,MIN(IFERROR(FIND("CDU",UPPER($E45)),999),IFERROR(FIND("BULK",UPPER($E45)),999),IFERROR(FIND("-",$E45),999),IFERROR(FIND("（",$E45),999))-1))=I$1,$F45,"")) | J45: =IF(OR($E45="",J$1=""),"",IF(TRIM(LEFT($E45,MIN(IFERROR(FIND("CDU",UPPER($E45)),999),IFERROR(FIND("BULK",UPPER($E45)),999),IFERROR(FIND("-",$E45),999),IFERROR(FIND("（",$E45),999))-1))=J$1,$F45,"")) | K45: =IF(OR($E45="",K$1=""),"",IF(TRIM(LEFT($E45,MIN(IFERROR(FIND("CDU",UPPER($E45)),999),IFERROR(FIND("BULK",UPPER($E45)),999),IFERROR(FIND("-",$E45),999),IFERROR(FIND("（",$E45),999))-1))=K$1,$F45,"")) | L45: =IF(OR($E45="",L$1=""),"",IF(TRIM(LEFT($E45,MIN(IFERROR(FIND("CDU",UPPER($E45)),999),IFERROR(FIND("BULK",UPPER($E45)),999),IFERROR(FIND("-",$E45),999),IFERROR(FIND("（",$E45),999))-1))=L$1,$F45,"")) | M45: =IF(OR($E45="",M$1=""),"",IF(TRIM(LEFT($E45,MIN(IFERROR(FIND("CDU",UPPER($E45)),999),IFERROR(FIND("BULK",UPPER($E45)),999),IFERROR(FIND("-",$E45),999),IFERROR(FIND("（",$E45),999))-1))=M$1,$F45,"")) -> 1800 | N45: =IF(OR($E45="",N$1=""),"",IF(TRIM(LEFT($E45,MIN(IFERROR(FIND("CDU",UPPER($E45)),999),IFERROR(FIND("BULK",UPPER($E45)),999),IFERROR(FIND("-",$E45),999),IFERROR(FIND("（",$E45),999))-1))=N$1,$F45,"")) | O45: =IF(OR($E45="",O$1=""),"",IF(TRIM(LEFT($E45,MIN(IFERROR(FIND("CDU",UPPER($E45)),999),IFERROR(FIND("BULK",UPPER($E45)),999),IFERROR(FIND("-",$E45),999),IFERROR(FIND("（",$E45),999))-1))=O$1,$F45,"")) | P45: =IF(OR($E45="",P$1=""),"",IF(TRIM(LEFT($E45,MIN(IFERROR(FIND("CDU",UPPER($E45)),999),IFERROR(FIND("BULK",UPPER($E45)),999),IFERROR(FIND("-",$E45),999),IFERROR(FIND("（",$E45),999))-1))=P$1,$F45,"")) | ... BU45: =IF(OR($E45="",BU$1=""),"",IF(TRIM(LEFT($E45,MIN(IFERROR(FIND("CDU",UPPER($E45)),999),IFERROR(FIND("BULK",UPPER($E45)),999),IFERROR(FIND("-",$E45),999),IFERROR(FIND("（",$E45),999))-1))=BU$1,$F45,"")) | BV45: 0.65 | BW45: =SUM(I45:BU45)*BV45 -> 1170 | BX45: =BW45*7.75 -> 9067.5 | BY45: =MID(E45,1,2) -> SR
A46: 45978 | B46: 46008 | C46: 4500454656 | D46: PO0000038-POOC | E46: SR102CDU-16 | F46: 12000 | G46: 第二代美文版 | H46: =IFERROR(VLOOKUP(E46,名称!A:E,4,0),"") -> 二代 | I46: =IF(OR($E46="",I$1=""),"",IF(TRIM(LEFT($E46,MIN(IFERROR(FIND("CDU",UPPER($E46)),999),IFERROR(FIND("BULK",UPPER($E46)),999),IFERROR(FIND("-",$E46),999),IFERROR(FIND("（",$E46),999))-1))=I$1,$F46,"")) | J46: =IF(OR($E46="",J$1=""),"",IF(TRIM(LEFT($E46,MIN(IFERROR(FIND("CDU",UPPER($E46)),999),IFERROR(FIND("BULK",UPPER($E46)),999),IFERROR(FIND("-",$E46),999),IFERROR(FIND("（",$E46),999))-1))=J$1,$F46,"")) | K46: =IF(OR($E46="",K$1=""),"",IF(TRIM(LEFT($E46,MIN(IFERROR(FIND("CDU",UPPER($E46)),999),IFERROR(FIND("BULK",UPPER($E46)),999),IFERROR(FIND("-",$E46),999),IFERROR(FIND("（",$E46),999))-1))=K$1,$F46,"")) -> 12000 | L46: =IF(OR($E46="",L$1=""),"",IF(TRIM(LEFT($E46,MIN(IFERROR(FIND("CDU",UPPER($E46)),999),IFERROR(FIND("BULK",UPPER($E46)),999),IFERROR(FIND("-",$E46),999),IFERROR(FIND("（",$E46),999))-1))=L$1,$F46,"")) | M46: =IF(OR($E46="",M$1=""),"",IF(TRIM(LEFT($E46,MIN(IFERROR(FIND("CDU",UPPER($E46)),999),IFERROR(FIND("BULK",UPPER($E46)),999),IFERROR(FIND("-",$E46),999),IFERROR(FIND("（",$E46),999))-1))=M$1,$F46,"")) | N46: =IF(OR($E46="",N$1=""),"",IF(TRIM(LEFT($E46,MIN(IFERROR(FIND("CDU",UPPER($E46)),999),IFERROR(FIND("BULK",UPPER($E46)),999),IFERROR(FIND("-",$E46),999),IFERROR(FIND("（",$E46),999))-1))=N$1,$F46,"")) | O46: =IF(OR($E46="",O$1=""),"",IF(TRIM(LEFT($E46,MIN(IFERROR(FIND("CDU",UPPER($E46)),999),IFERROR(FIND("BULK",UPPER($E46)),999),IFERROR(FIND("-",$E46),999),IFERROR(FIND("（",$E46),999))-1))=O$1,$F46,"")) | P46: =IF(OR($E46="",P$1=""),"",IF(TRIM(LEFT($E46,MIN(IFERROR(FIND("CDU",UPPER($E46)),999),IFERROR(FIND("BULK",UPPER($E46)),999),IFERROR(FIND("-",$E46),999),IFERROR(FIND("（",$E46),999))-1))=P$1,$F46,"")) | ... BU46: =IF(OR($E46="",BU$1=""),"",IF(TRIM(LEFT($E46,MIN(IFERROR(FIND("CDU",UPPER($E46)),999),IFERROR(FIND("BULK",UPPER($E46)),999),IFERROR(FIND("-",$E46),999),IFERROR(FIND("（",$E46),999))-1))=BU$1,$F46,"")) | BV46: 0.86 | BW46: =SUM(I46:BU46)*BV46 -> 10320 | BX46: =BW46*7.75 -> 79980 | BY46: =MID(E46,1,2) -> SR
A47: 45978 | B47: 46008 | C47: 4500454656 | D47: PO0000038-POOC | E47: SR201 | F47: 8004 | G47: 第二代美文版 | H47: =IFERROR(VLOOKUP(E47,名称!A:E,4,0),"") -> 二代 | I47: =IF(OR($E47="",I$1=""),"",IF(TRIM(LEFT($E47,MIN(IFERROR(FIND("CDU",UPPER($E47)),999),IFERROR(FIND("BULK",UPPER($E47)),999),IFERROR(FIND("-",$E47),999),IFERROR(FIND("（",$E47),999))-1))=I$1,$F47,"")) | J47: =IF(OR($E47="",J$1=""),"",IF(TRIM(LEFT($E47,MIN(IFERROR(FIND("CDU",UPPER($E47)),999),IFERROR(FIND("BULK",UPPER($E47)),999),IFERROR(FIND("-",$E47),999),IFERROR(FIND("（",$E47),999))-1))=J$1,$F47,"")) | K47: =IF(OR($E47="",K$1=""),"",IF(TRIM(LEFT($E47,MIN(IFERROR(FIND("CDU",UPPER($E47)),999),IFERROR(FIND("BULK",UPPER($E47)),999),IFERROR(FIND("-",$E47),999),IFERROR(FIND("（",$E47),999))-1))=K$1,$F47,"")) | L47: =IF(OR($E47="",L$1=""),"",IF(TRIM(LEFT($E47,MIN(IFERROR(FIND("CDU",UPPER($E47)),999),IFERROR(FIND("BULK",UPPER($E47)),999),IFERROR(FIND("-",$E47),999),IFERROR(FIND("（",$E47),999))-1))=L$1,$F47,"")) | M47: =IF(OR($E47="",M$1=""),"",IF(TRIM(LEFT($E47,MIN(IFERROR(FIND("CDU",UPPER($E47)),999),IFERROR(FIND("BULK",UPPER($E47)),999),IFERROR(FIND("-",$E47),999),IFERROR(FIND("（",$E47),999))-1))=M$1,$F47,"")) | N47: =IF(OR($E47="",N$1=""),"",IF(TRIM(LEFT($E47,MIN(IFERROR(FIND("CDU",UPPER($E47)),999),IFERROR(FIND("BULK",UPPER($E47)),999),IFERROR(FIND("-",$E47),999),IFERROR(FIND("（",$E47),999))-1))=N$1,$F47,"")) | O47: =IF(OR($E47="",O$1=""),"",IF(TRIM(LEFT($E47,MIN(IFERROR(FIND("CDU",UPPER($E47)),999),IFERROR(FIND("BULK",UPPER($E47)),999),IFERROR(FIND("-",$E47),999),IFERROR(FIND("（",$E47),999))-1))=O$1,$F47,"")) | P47: =IF(OR($E47="",P$1=""),"",IF(TRIM(LEFT($E47,MIN(IFERROR(FIND("CDU",UPPER($E47)),999),IFERROR(FIND("BULK",UPPER($E47)),999),IFERROR(FIND("-",$E47),999),IFERROR(FIND("（",$E47),999))-1))=P$1,$F47,"")) | ... BU47: =IF(OR($E47="",BU$1=""),"",IF(TRIM(LEFT($E47,MIN(IFERROR(FIND("CDU",UPPER($E47)),999),IFERROR(FIND("BULK",UPPER($E47)),999),IFERROR(FIND("-",$E47),999),IFERROR(FIND("（",$E47),999))-1))=BU$1,$F47,"")) | BV47: 2.02 | BW47: =SUM(I47:BU47)*BV47 -> 16168.08 | BX47: =BW47*7.75 -> 125302.62 | BY47: =MID(E47,1,2) -> SR
A48: 45978 | B48: 46008 | C48: 4500454656 | D48: PO0000038-POOC | E48: SR103CDU-24 | F48: 24000 | G48: 第二代美文版 | H48: =IFERROR(VLOOKUP(E48,名称!A:E,4,0),"") -> 二代 | I48: =IF(OR($E48="",I$1=""),"",IF(TRIM(LEFT($E48,MIN(IFERROR(FIND("CDU",UPPER($E48)),999),IFERROR(FIND("BULK",UPPER($E48)),999),IFERROR(FIND("-",$E48),999),IFERROR(FIND("（",$E48),999))-1))=I$1,$F48,"")) | J48: =IF(OR($E48="",J$1=""),"",IF(TRIM(LEFT($E48,MIN(IFERROR(FIND("CDU",UPPER($E48)),999),IFERROR(FIND("BULK",UPPER($E48)),999),IFERROR(FIND("-",$E48),999),IFERROR(FIND("（",$E48),999))-1))=J$1,$F48,"")) | K48: =IF(OR($E48="",K$1=""),"",IF(TRIM(LEFT($E48,MIN(IFERROR(FIND("CDU",UPPER($E48)),999),IFERROR(FIND("BULK",UPPER($E48)),999),IFERROR(FIND("-",$E48),999),IFERROR(FIND("（",$E48),999))-1))=K$1,$F48,"")) | L48: =IF(OR($E48="",L$1=""),"",IF(TRIM(LEFT($E48,MIN(IFERROR(FIND("CDU",UPPER($E48)),999),IFERROR(FIND("BULK",UPPER($E48)),999),IFERROR(FIND("-",$E48),999),IFERROR(FIND("（",$E48),999))-1))=L$1,$F48,"")) | M48: =IF(OR($E48="",M$1=""),"",IF(TRIM(LEFT($E48,MIN(IFERROR(FIND("CDU",UPPER($E48)),999),IFERROR(FIND("BULK",UPPER($E48)),999),IFERROR(FIND("-",$E48),999),IFERROR(FIND("（",$E48),999))-1))=M$1,$F48,"")) -> 24000 | N48: =IF(OR($E48="",N$1=""),"",IF(TRIM(LEFT($E48,MIN(IFERROR(FIND("CDU",UPPER($E48)),999),IFERROR(FIND("BULK",UPPER($E48)),999),IFERROR(FIND("-",$E48),999),IFERROR(FIND("（",$E48),999))-1))=N$1,$F48,"")) | O48: =IF(OR($E48="",O$1=""),"",IF(TRIM(LEFT($E48,MIN(IFERROR(FIND("CDU",UPPER($E48)),999),IFERROR(FIND("BULK",UPPER($E48)),999),IFERROR(FIND("-",$E48),999),IFERROR(FIND("（",$E48),999))-1))=O$1,$F48,"")) | P48: =IF(OR($E48="",P$1=""),"",IF(TRIM(LEFT($E48,MIN(IFERROR(FIND("CDU",UPPER($E48)),999),IFERROR(FIND("BULK",UPPER($E48)),999),IFERROR(FIND("-",$E48),999),IFERROR(FIND("（",$E48),999))-1))=P$1,$F48,"")) | ... BU48: =IF(OR($E48="",BU$1=""),"",IF(TRIM(LEFT($E48,MIN(IFERROR(FIND("CDU",UPPER($E48)),999),IFERROR(FIND("BULK",UPPER($E48)),999),IFERROR(FIND("-",$E48),999),IFERROR(FIND("（",$E48),999))-1))=BU$1,$F48,"")) | BV48: 0.61 | BW48: =SUM(I48:BU48)*BV48 -> 14640 | BX48: =BW48*7.75 -> 113460 | BY48: =MID(E48,1,2) -> SR
A49: 45978 | B49: 46008 | C49: 4500454656 | D49: PO0000038-POOC | E49: SR301 | F49: 6000 | G49: 第二代美文版 | H49: =IFERROR(VLOOKUP(E49,名称!A:E,4,0),"") -> 二代 | I49: =IF(OR($E49="",I$1=""),"",IF(TRIM(LEFT($E49,MIN(IFERROR(FIND("CDU",UPPER($E49)),999),IFERROR(FIND("BULK",UPPER($E49)),999),IFERROR(FIND("-",$E49),999),IFERROR(FIND("（",$E49),999))-1))=I$1,$F49,"")) | J49: =IF(OR($E49="",J$1=""),"",IF(TRIM(LEFT($E49,MIN(IFERROR(FIND("CDU",UPPER($E49)),999),IFERROR(FIND("BULK",UPPER($E49)),999),IFERROR(FIND("-",$E49),999),IFERROR(FIND("（",$E49),999))-1))=J$1,$F49,"")) | K49: =IF(OR($E49="",K$1=""),"",IF(TRIM(LEFT($E49,MIN(IFERROR(FIND("CDU",UPPER($E49)),999),IFERROR(FIND("BULK",UPPER($E49)),999),IFERROR(FIND("-",$E49),999),IFERROR(FIND("（",$E49),999))-1))=K$1,$F49,"")) | L49: =IF(OR($E49="",L$1=""),"",IF(TRIM(LEFT($E49,MIN(IFERROR(FIND("CDU",UPPER($E49)),999),IFERROR(FIND("BULK",UPPER($E49)),999),IFERROR(FIND("-",$E49),999),IFERROR(FIND("（",$E49),999))-1))=L$1,$F49,"")) | M49: =IF(OR($E49="",M$1=""),"",IF(TRIM(LEFT($E49,MIN(IFERROR(FIND("CDU",UPPER($E49)),999),IFERROR(FIND("BULK",UPPER($E49)),999),IFERROR(FIND("-",$E49),999),IFERROR(FIND("（",$E49),999))-1))=M$1,$F49,"")) | N49: =IF(OR($E49="",N$1=""),"",IF(TRIM(LEFT($E49,MIN(IFERROR(FIND("CDU",UPPER($E49)),999),IFERROR(FIND("BULK",UPPER($E49)),999),IFERROR(FIND("-",$E49),999),IFERROR(FIND("（",$E49),999))-1))=N$1,$F49,"")) | O49: =IF(OR($E49="",O$1=""),"",IF(TRIM(LEFT($E49,MIN(IFERROR(FIND("CDU",UPPER($E49)),999),IFERROR(FIND("BULK",UPPER($E49)),999),IFERROR(FIND("-",$E49),999),IFERROR(FIND("（",$E49),999))-1))=O$1,$F49,"")) | P49: =IF(OR($E49="",P$1=""),"",IF(TRIM(LEFT($E49,MIN(IFERROR(FIND("CDU",UPPER($E49)),999),IFERROR(FIND("BULK",UPPER($E49)),999),IFERROR(FIND("-",$E49),999),IFERROR(FIND("（",$E49),999))-1))=P$1,$F49,"")) | ... BU49: =IF(OR($E49="",BU$1=""),"",IF(TRIM(LEFT($E49,MIN(IFERROR(FIND("CDU",UPPER($E49)),999),IFERROR(FIND("BULK",UPPER($E49)),999),IFERROR(FIND("-",$E49),999),IFERROR(FIND("（",$E49),999))-1))=BU$1,$F49,"")) | BV49: 3.09 | BW49: =SUM(I49:BU49)*BV49 -> 18540 | BX49: =BW49*7.75 -> 143685 | BY49: =MID(E49,1,2) -> SR
A50: 45978 | B50: 46008 | C50: 4500454656 | D50: PO0000038-POOC | E50: SR160CDU-24 | F50: 3600 | G50: 第二代美文版 | H50: =IFERROR(VLOOKUP(E50,名称!A:E,4,0),"") -> 二代 | I50: =IF(OR($E50="",I$1=""),"",IF(TRIM(LEFT($E50,MIN(IFERROR(FIND("CDU",UPPER($E50)),999),IFERROR(FIND("BULK",UPPER($E50)),999),IFERROR(FIND("-",$E50),999),IFERROR(FIND("（",$E50),999))-1))=I$1,$F50,"")) | J50: =IF(OR($E50="",J$1=""),"",IF(TRIM(LEFT($E50,MIN(IFERROR(FIND("CDU",UPPER($E50)),999),IFERROR(FIND("BULK",UPPER($E50)),999),IFERROR(FIND("-",$E50),999),IFERROR(FIND("（",$E50),999))-1))=J$1,$F50,"")) | K50: =IF(OR($E50="",K$1=""),"",IF(TRIM(LEFT($E50,MIN(IFERROR(FIND("CDU",UPPER($E50)),999),IFERROR(FIND("BULK",UPPER($E50)),999),IFERROR(FIND("-",$E50),999),IFERROR(FIND("（",$E50),999))-1))=K$1,$F50,"")) | L50: =IF(OR($E50="",L$1=""),"",IF(TRIM(LEFT($E50,MIN(IFERROR(FIND("CDU",UPPER($E50)),999),IFERROR(FIND("BULK",UPPER($E50)),999),IFERROR(FIND("-",$E50),999),IFERROR(FIND("（",$E50),999))-1))=L$1,$F50,"")) | M50: =IF(OR($E50="",M$1=""),"",IF(TRIM(LEFT($E50,MIN(IFERROR(FIND("CDU",UPPER($E50)),999),IFERROR(FIND("BULK",UPPER($E50)),999),IFERROR(FIND("-",$E50),999),IFERROR(FIND("（",$E50),999))-1))=M$1,$F50,"")) | N50: =IF(OR($E50="",N$1=""),"",IF(TRIM(LEFT($E50,MIN(IFERROR(FIND("CDU",UPPER($E50)),999),IFERROR(FIND("BULK",UPPER($E50)),999),IFERROR(FIND("-",$E50),999),IFERROR(FIND("（",$E50),999))-1))=N$1,$F50,"")) | O50: =IF(OR($E50="",O$1=""),"",IF(TRIM(LEFT($E50,MIN(IFERROR(FIND("CDU",UPPER($E50)),999),IFERROR(FIND("BULK",UPPER($E50)),999),IFERROR(FIND("-",$E50),999),IFERROR(FIND("（",$E50),999))-1))=O$1,$F50,"")) -> 3600 | P50: =IF(OR($E50="",P$1=""),"",IF(TRIM(LEFT($E50,MIN(IFERROR(FIND("CDU",UPPER($E50)),999),IFERROR(FIND("BULK",UPPER($E50)),999),IFERROR(FIND("-",$E50),999),IFERROR(FIND("（",$E50),999))-1))=P$1,$F50,"")) | ... BU50: =IF(OR($E50="",BU$1=""),"",IF(TRIM(LEFT($E50,MIN(IFERROR(FIND("CDU",UPPER($E50)),999),IFERROR(FIND("BULK",UPPER($E50)),999),IFERROR(FIND("-",$E50),999),IFERROR(FIND("（",$E50),999))-1))=BU$1,$F50,"")) | BV50: 0.61 | BW50: =SUM(I50:BU50)*BV50 -> 2196 | BX50: =BW50*7.75 -> 17019 | BY50: =MID(E50,1,2) -> SR
A51: 45980 | B51: 46034 | C51: CANADIAN TIRE PO 01336126 | D51: PO00000041-CAJZ | E51: SR201C | F51: 900 | G51: Jazwares客版（2L） | H51: =IFERROR(VLOOKUP(E51,名称!A:E,4,0),"") -> 二代 | I51: =IF(OR($E51="",I$1=""),"",IF(TRIM(LEFT($E51,MIN(IFERROR(FIND("CDU",UPPER($E51)),999),IFERROR(FIND("BULK",UPPER($E51)),999),IFERROR(FIND("-",$E51),999),IFERROR(FIND("（",$E51),999))-1))=I$1,$F51,"")) | J51: =IF(OR($E51="",J$1=""),"",IF(TRIM(LEFT($E51,MIN(IFERROR(FIND("CDU",UPPER($E51)),999),IFERROR(FIND("BULK",UPPER($E51)),999),IFERROR(FIND("-",$E51),999),IFERROR(FIND("（",$E51),999))-1))=J$1,$F51,"")) | K51: =IF(OR($E51="",K$1=""),"",IF(TRIM(LEFT($E51,MIN(IFERROR(FIND("CDU",UPPER($E51)),999),IFERROR(FIND("BULK",UPPER($E51)),999),IFERROR(FIND("-",$E51),999),IFERROR(FIND("（",$E51),999))-1))=K$1,$F51,"")) | L51: =IF(OR($E51="",L$1=""),"",IF(TRIM(LEFT($E51,MIN(IFERROR(FIND("CDU",UPPER($E51)),999),IFERROR(FIND("BULK",UPPER($E51)),999),IFERROR(FIND("-",$E51),999),IFERROR(FIND("（",$E51),999))-1))=L$1,$F51,"")) | M51: =IF(OR($E51="",M$1=""),"",IF(TRIM(LEFT($E51,MIN(IFERROR(FIND("CDU",UPPER($E51)),999),IFERROR(FIND("BULK",UPPER($E51)),999),IFERROR(FIND("-",$E51),999),IFERROR(FIND("（",$E51),999))-1))=M$1,$F51,"")) | N51: =IF(OR($E51="",N$1=""),"",IF(TRIM(LEFT($E51,MIN(IFERROR(FIND("CDU",UPPER($E51)),999),IFERROR(FIND("BULK",UPPER($E51)),999),IFERROR(FIND("-",$E51),999),IFERROR(FIND("（",$E51),999))-1))=N$1,$F51,"")) | O51: =IF(OR($E51="",O$1=""),"",IF(TRIM(LEFT($E51,MIN(IFERROR(FIND("CDU",UPPER($E51)),999),IFERROR(FIND("BULK",UPPER($E51)),999),IFERROR(FIND("-",$E51),999),IFERROR(FIND("（",$E51),999))-1))=O$1,$F51,"")) | P51: =IF(OR($E51="",P$1=""),"",IF(TRIM(LEFT($E51,MIN(IFERROR(FIND("CDU",UPPER($E51)),999),IFERROR(FIND("BULK",UPPER($E51)),999),IFERROR(FIND("-",$E51),999),IFERROR(FIND("（",$E51),999))-1))=P$1,$F51,"")) | ... BU51: =IF(OR($E51="",BU$1=""),"",IF(TRIM(LEFT($E51,MIN(IFERROR(FIND("CDU",UPPER($E51)),999),IFERROR(FIND("BULK",UPPER($E51)),999),IFERROR(FIND("-",$E51),999),IFERROR(FIND("（",$E51),999))-1))=BU$1,$F51,"")) | BV51: 2.21 | BW51: =SUM(I51:BU51)*BV51 -> 1989 | BX51: =BW51*7.75 -> 15414.75 | BY51: =MID(E51,1,2) -> SR
A52: 45985 | B52: 46031 | C52: GGPL/09/25-26 | D52: PO00000040-INGG | E52: SR102 | F52: 5004 | G52: 第二代美文版 | H52: =IFERROR(VLOOKUP(E52,名称!A:E,4,0),"") -> 二代 | I52: =IF(OR($E52="",I$1=""),"",IF(TRIM(LEFT($E52,MIN(IFERROR(FIND("CDU",UPPER($E52)),999),IFERROR(FIND("BULK",UPPER($E52)),999),IFERROR(FIND("-",$E52),999),IFERROR(FIND("（",$E52),999))-1))=I$1,$F52,"")) | J52: =IF(OR($E52="",J$1=""),"",IF(TRIM(LEFT($E52,MIN(IFERROR(FIND("CDU",UPPER($E52)),999),IFERROR(FIND("BULK",UPPER($E52)),999),IFERROR(FIND("-",$E52),999),IFERROR(FIND("（",$E52),999))-1))=J$1,$F52,"")) | K52: =IF(OR($E52="",K$1=""),"",IF(TRIM(LEFT($E52,MIN(IFERROR(FIND("CDU",UPPER($E52)),999),IFERROR(FIND("BULK",UPPER($E52)),999),IFERROR(FIND("-",$E52),999),IFERROR(FIND("（",$E52),999))-1))=K$1,$F52,"")) -> 5004 | L52: =IF(OR($E52="",L$1=""),"",IF(TRIM(LEFT($E52,MIN(IFERROR(FIND("CDU",UPPER($E52)),999),IFERROR(FIND("BULK",UPPER($E52)),999),IFERROR(FIND("-",$E52),999),IFERROR(FIND("（",$E52),999))-1))=L$1,$F52,"")) | M52: =IF(OR($E52="",M$1=""),"",IF(TRIM(LEFT($E52,MIN(IFERROR(FIND("CDU",UPPER($E52)),999),IFERROR(FIND("BULK",UPPER($E52)),999),IFERROR(FIND("-",$E52),999),IFERROR(FIND("（",$E52),999))-1))=M$1,$F52,"")) | N52: =IF(OR($E52="",N$1=""),"",IF(TRIM(LEFT($E52,MIN(IFERROR(FIND("CDU",UPPER($E52)),999),IFERROR(FIND("BULK",UPPER($E52)),999),IFERROR(FIND("-",$E52),999),IFERROR(FIND("（",$E52),999))-1))=N$1,$F52,"")) | O52: =IF(OR($E52="",O$1=""),"",IF(TRIM(LEFT($E52,MIN(IFERROR(FIND("CDU",UPPER($E52)),999),IFERROR(FIND("BULK",UPPER($E52)),999),IFERROR(FIND("-",$E52),999),IFERROR(FIND("（",$E52),999))-1))=O$1,$F52,"")) | P52: =IF(OR($E52="",P$1=""),"",IF(TRIM(LEFT($E52,MIN(IFERROR(FIND("CDU",UPPER($E52)),999),IFERROR(FIND("BULK",UPPER($E52)),999),IFERROR(FIND("-",$E52),999),IFERROR(FIND("（",$E52),999))-1))=P$1,$F52,"")) | ... BU52: =IF(OR($E52="",BU$1=""),"",IF(TRIM(LEFT($E52,MIN(IFERROR(FIND("CDU",UPPER($E52)),999),IFERROR(FIND("BULK",UPPER($E52)),999),IFERROR(FIND("-",$E52),999),IFERROR(FIND("（",$E52),999))-1))=BU$1,$F52,"")) | BV52: 0.78 | BW52: =SUM(I52:BU52)*BV52 -> 3903.12 | BX52: =BW52*7.75 -> 30249.18 | BY52: =MID(E52,1,2) -> SR
A53: 45985 | B53: 46031 | C53: GGPL/09/25-26 | D53: PO00000040-INGG | E53: SR201 | F53: 3000 | G53: 第二代美文版 | H53: =IFERROR(VLOOKUP(E53,名称!A:E,4,0),"") -> 二代 | I53: =IF(OR($E53="",I$1=""),"",IF(TRIM(LEFT($E53,MIN(IFERROR(FIND("CDU",UPPER($E53)),999),IFERROR(FIND("BULK",UPPER($E53)),999),IFERROR(FIND("-",$E53),999),IFERROR(FIND("（",$E53),999))-1))=I$1,$F53,"")) | J53: =IF(OR($E53="",J$1=""),"",IF(TRIM(LEFT($E53,MIN(IFERROR(FIND("CDU",UPPER($E53)),999),IFERROR(FIND("BULK",UPPER($E53)),999),IFERROR(FIND("-",$E53),999),IFERROR(FIND("（",$E53),999))-1))=J$1,$F53,"")) | K53: =IF(OR($E53="",K$1=""),"",IF(TRIM(LEFT($E53,MIN(IFERROR(FIND("CDU",UPPER($E53)),999),IFERROR(FIND("BULK",UPPER($E53)),999),IFERROR(FIND("-",$E53),999),IFERROR(FIND("（",$E53),999))-1))=K$1,$F53,"")) | L53: =IF(OR($E53="",L$1=""),"",IF(TRIM(LEFT($E53,MIN(IFERROR(FIND("CDU",UPPER($E53)),999),IFERROR(FIND("BULK",UPPER($E53)),999),IFERROR(FIND("-",$E53),999),IFERROR(FIND("（",$E53),999))-1))=L$1,$F53,"")) | M53: =IF(OR($E53="",M$1=""),"",IF(TRIM(LEFT($E53,MIN(IFERROR(FIND("CDU",UPPER($E53)),999),IFERROR(FIND("BULK",UPPER($E53)),999),IFERROR(FIND("-",$E53),999),IFERROR(FIND("（",$E53),999))-1))=M$1,$F53,"")) | N53: =IF(OR($E53="",N$1=""),"",IF(TRIM(LEFT($E53,MIN(IFERROR(FIND("CDU",UPPER($E53)),999),IFERROR(FIND("BULK",UPPER($E53)),999),IFERROR(FIND("-",$E53),999),IFERROR(FIND("（",$E53),999))-1))=N$1,$F53,"")) | O53: =IF(OR($E53="",O$1=""),"",IF(TRIM(LEFT($E53,MIN(IFERROR(FIND("CDU",UPPER($E53)),999),IFERROR(FIND("BULK",UPPER($E53)),999),IFERROR(FIND("-",$E53),999),IFERROR(FIND("（",$E53),999))-1))=O$1,$F53,"")) | P53: =IF(OR($E53="",P$1=""),"",IF(TRIM(LEFT($E53,MIN(IFERROR(FIND("CDU",UPPER($E53)),999),IFERROR(FIND("BULK",UPPER($E53)),999),IFERROR(FIND("-",$E53),999),IFERROR(FIND("（",$E53),999))-1))=P$1,$F53,"")) | ... BU53: =IF(OR($E53="",BU$1=""),"",IF(TRIM(LEFT($E53,MIN(IFERROR(FIND("CDU",UPPER($E53)),999),IFERROR(FIND("BULK",UPPER($E53)),999),IFERROR(FIND("-",$E53),999),IFERROR(FIND("（",$E53),999))-1))=BU$1,$F53,"")) | BV53: 2.04 | BW53: =SUM(I53:BU53)*BV53 -> 6120 | BX53: =BW53*7.75 -> 47430 | BY53: =MID(E53,1,2) -> SR
A54: 45985 | B54: 46031 | C54: GGPL/09/25-26 | D54: PO00000040-INGG | E54: SR400 | F54: 5004 | G54: 第二代美文版 | H54: =IFERROR(VLOOKUP(E54,名称!A:E,4,0),"") -> 二代 | I54: =IF(OR($E54="",I$1=""),"",IF(TRIM(LEFT($E54,MIN(IFERROR(FIND("CDU",UPPER($E54)),999),IFERROR(FIND("BULK",UPPER($E54)),999),IFERROR(FIND("-",$E54),999),IFERROR(FIND("（",$E54),999))-1))=I$1,$F54,"")) | J54: =IF(OR($E54="",J$1=""),"",IF(TRIM(LEFT($E54,MIN(IFERROR(FIND("CDU",UPPER($E54)),999),IFERROR(FIND("BULK",UPPER($E54)),999),IFERROR(FIND("-",$E54),999),IFERROR(FIND("（",$E54),999))-1))=J$1,$F54,"")) | K54: =IF(OR($E54="",K$1=""),"",IF(TRIM(LEFT($E54,MIN(IFERROR(FIND("CDU",UPPER($E54)),999),IFERROR(FIND("BULK",UPPER($E54)),999),IFERROR(FIND("-",$E54),999),IFERROR(FIND("（",$E54),999))-1))=K$1,$F54,"")) | L54: =IF(OR($E54="",L$1=""),"",IF(TRIM(LEFT($E54,MIN(IFERROR(FIND("CDU",UPPER($E54)),999),IFERROR(FIND("BULK",UPPER($E54)),999),IFERROR(FIND("-",$E54),999),IFERROR(FIND("（",$E54),999))-1))=L$1,$F54,"")) | M54: =IF(OR($E54="",M$1=""),"",IF(TRIM(LEFT($E54,MIN(IFERROR(FIND("CDU",UPPER($E54)),999),IFERROR(FIND("BULK",UPPER($E54)),999),IFERROR(FIND("-",$E54),999),IFERROR(FIND("（",$E54),999))-1))=M$1,$F54,"")) | N54: =IF(OR($E54="",N$1=""),"",IF(TRIM(LEFT($E54,MIN(IFERROR(FIND("CDU",UPPER($E54)),999),IFERROR(FIND("BULK",UPPER($E54)),999),IFERROR(FIND("-",$E54),999),IFERROR(FIND("（",$E54),999))-1))=N$1,$F54,"")) | O54: =IF(OR($E54="",O$1=""),"",IF(TRIM(LEFT($E54,MIN(IFERROR(FIND("CDU",UPPER($E54)),999),IFERROR(FIND("BULK",UPPER($E54)),999),IFERROR(FIND("-",$E54),999),IFERROR(FIND("（",$E54),999))-1))=O$1,$F54,"")) | P54: =IF(OR($E54="",P$1=""),"",IF(TRIM(LEFT($E54,MIN(IFERROR(FIND("CDU",UPPER($E54)),999),IFERROR(FIND("BULK",UPPER($E54)),999),IFERROR(FIND("-",$E54),999),IFERROR(FIND("（",$E54),999))-1))=P$1,$F54,"")) | ... BU54: =IF(OR($E54="",BU$1=""),"",IF(TRIM(LEFT($E54,MIN(IFERROR(FIND("CDU",UPPER($E54)),999),IFERROR(FIND("BULK",UPPER($E54)),999),IFERROR(FIND("-",$E54),999),IFERROR(FIND("（",$E54),999))-1))=BU$1,$F54,"")) | BV54: 1.49 | BW54: =SUM(I54:BU54)*BV54 -> 7455.96 | BX54: =BW54*7.75 -> 57783.69 | BY54: =MID(E54,1,2) -> SR
A55: 45986 | B55: 46017 | C55: PL252362-01 | D55: PO00000043-UKCO | E55: SR103CDU-24 | F55: 30072 | G55: TOY客版 | H55: =IFERROR(VLOOKUP(E55,名称!A:E,4,0),"") -> 二代 | I55: =IF(OR($E55="",I$1=""),"",IF(TRIM(LEFT($E55,MIN(IFERROR(FIND("CDU",UPPER($E55)),999),IFERROR(FIND("BULK",UPPER($E55)),999),IFERROR(FIND("-",$E55),999),IFERROR(FIND("（",$E55),999))-1))=I$1,$F55,"")) | J55: =IF(OR($E55="",J$1=""),"",IF(TRIM(LEFT($E55,MIN(IFERROR(FIND("CDU",UPPER($E55)),999),IFERROR(FIND("BULK",UPPER($E55)),999),IFERROR(FIND("-",$E55),999),IFERROR(FIND("（",$E55),999))-1))=J$1,$F55,"")) | K55: =IF(OR($E55="",K$1=""),"",IF(TRIM(LEFT($E55,MIN(IFERROR(FIND("CDU",UPPER($E55)),999),IFERROR(FIND("BULK",UPPER($E55)),999),IFERROR(FIND("-",$E55),999),IFERROR(FIND("（",$E55),999))-1))=K$1,$F55,"")) | L55: =IF(OR($E55="",L$1=""),"",IF(TRIM(LEFT($E55,MIN(IFERROR(FIND("CDU",UPPER($E55)),999),IFERROR(FIND("BULK",UPPER($E55)),999),IFERROR(FIND("-",$E55),999),IFERROR(FIND("（",$E55),999))-1))=L$1,$F55,"")) | M55: =IF(OR($E55="",M$1=""),"",IF(TRIM(LEFT($E55,MIN(IFERROR(FIND("CDU",UPPER($E55)),999),IFERROR(FIND("BULK",UPPER($E55)),999),IFERROR(FIND("-",$E55),999),IFERROR(FIND("（",$E55),999))-1))=M$1,$F55,"")) -> 30072 | N55: =IF(OR($E55="",N$1=""),"",IF(TRIM(LEFT($E55,MIN(IFERROR(FIND("CDU",UPPER($E55)),999),IFERROR(FIND("BULK",UPPER($E55)),999),IFERROR(FIND("-",$E55),999),IFERROR(FIND("（",$E55),999))-1))=N$1,$F55,"")) | O55: =IF(OR($E55="",O$1=""),"",IF(TRIM(LEFT($E55,MIN(IFERROR(FIND("CDU",UPPER($E55)),999),IFERROR(FIND("BULK",UPPER($E55)),999),IFERROR(FIND("-",$E55),999),IFERROR(FIND("（",$E55),999))-1))=O$1,$F55,"")) | P55: =IF(OR($E55="",P$1=""),"",IF(TRIM(LEFT($E55,MIN(IFERROR(FIND("CDU",UPPER($E55)),999),IFERROR(FIND("BULK",UPPER($E55)),999),IFERROR(FIND("-",$E55),999),IFERROR(FIND("（",$E55),999))-1))=P$1,$F55,"")) | ... BU55: =IF(OR($E55="",BU$1=""),"",IF(TRIM(LEFT($E55,MIN(IFERROR(FIND("CDU",UPPER($E55)),999),IFERROR(FIND("BULK",UPPER($E55)),999),IFERROR(FIND("-",$E55),999),IFERROR(FIND("（",$E55),999))-1))=BU$1,$F55,"")) | BV55: 0.6 | BW55: =SUM(I55:BU55)*BV55 -> 18043.2 | BX55: =BW55*7.75 -> 139834.8 | BY55: =MID(E55,1,2) -> SR
A56: 45986 | B56: 46029 | C56: LOBLAWS POCA000212 | D56: PO00000044-CAJZ | E56: SR103CDU-24 | F56: 2400 | G56: Jazwares客版（2L） | H56: =IFERROR(VLOOKUP(E56,名称!A:E,4,0),"") -> 二代 | I56: =IF(OR($E56="",I$1=""),"",IF(TRIM(LEFT($E56,MIN(IFERROR(FIND("CDU",UPPER($E56)),999),IFERROR(FIND("BULK",UPPER($E56)),999),IFERROR(FIND("-",$E56),999),IFERROR(FIND("（",$E56),999))-1))=I$1,$F56,"")) | J56: =IF(OR($E56="",J$1=""),"",IF(TRIM(LEFT($E56,MIN(IFERROR(FIND("CDU",UPPER($E56)),999),IFERROR(FIND("BULK",UPPER($E56)),999),IFERROR(FIND("-",$E56),999),IFERROR(FIND("（",$E56),999))-1))=J$1,$F56,"")) | K56: =IF(OR($E56="",K$1=""),"",IF(TRIM(LEFT($E56,MIN(IFERROR(FIND("CDU",UPPER($E56)),999),IFERROR(FIND("BULK",UPPER($E56)),999),IFERROR(FIND("-",$E56),999),IFERROR(FIND("（",$E56),999))-1))=K$1,$F56,"")) | L56: =IF(OR($E56="",L$1=""),"",IF(TRIM(LEFT($E56,MIN(IFERROR(FIND("CDU",UPPER($E56)),999),IFERROR(FIND("BULK",UPPER($E56)),999),IFERROR(FIND("-",$E56),999),IFERROR(FIND("（",$E56),999))-1))=L$1,$F56,"")) | M56: =IF(OR($E56="",M$1=""),"",IF(TRIM(LEFT($E56,MIN(IFERROR(FIND("CDU",UPPER($E56)),999),IFERROR(FIND("BULK",UPPER($E56)),999),IFERROR(FIND("-",$E56),999),IFERROR(FIND("（",$E56),999))-1))=M$1,$F56,"")) -> 2400 | N56: =IF(OR($E56="",N$1=""),"",IF(TRIM(LEFT($E56,MIN(IFERROR(FIND("CDU",UPPER($E56)),999),IFERROR(FIND("BULK",UPPER($E56)),999),IFERROR(FIND("-",$E56),999),IFERROR(FIND("（",$E56),999))-1))=N$1,$F56,"")) | O56: =IF(OR($E56="",O$1=""),"",IF(TRIM(LEFT($E56,MIN(IFERROR(FIND("CDU",UPPER($E56)),999),IFERROR(FIND("BULK",UPPER($E56)),999),IFERROR(FIND("-",$E56),999),IFERROR(FIND("（",$E56),999))-1))=O$1,$F56,"")) | P56: =IF(OR($E56="",P$1=""),"",IF(TRIM(LEFT($E56,MIN(IFERROR(FIND("CDU",UPPER($E56)),999),IFERROR(FIND("BULK",UPPER($E56)),999),IFERROR(FIND("-",$E56),999),IFERROR(FIND("（",$E56),999))-1))=P$1,$F56,"")) | ... BU56: =IF(OR($E56="",BU$1=""),"",IF(TRIM(LEFT($E56,MIN(IFERROR(FIND("CDU",UPPER($E56)),999),IFERROR(FIND("BULK",UPPER($E56)),999),IFERROR(FIND("-",$E56),999),IFERROR(FIND("（",$E56),999))-1))=BU$1,$F56,"")) | BV56: 0.61 | BW56: =SUM(I56:BU56)*BV56 -> 1464 | BX56: =BW56*7.75 -> 11346 | BY56: =MID(E56,1,2) -> SR
A57: 45992 | B57: 46044 | D57: PO0000047-MGBS | E57: SR102 | F57: 960 | G57: 第二代美文版 | H57: =IFERROR(VLOOKUP(E57,名称!A:E,4,0),"") -> 二代 | I57: =IF(OR($E57="",I$1=""),"",IF(TRIM(LEFT($E57,MIN(IFERROR(FIND("CDU",UPPER($E57)),999),IFERROR(FIND("BULK",UPPER($E57)),999),IFERROR(FIND("-",$E57),999),IFERROR(FIND("（",$E57),999))-1))=I$1,$F57,"")) | J57: =IF(OR($E57="",J$1=""),"",IF(TRIM(LEFT($E57,MIN(IFERROR(FIND("CDU",UPPER($E57)),999),IFERROR(FIND("BULK",UPPER($E57)),999),IFERROR(FIND("-",$E57),999),IFERROR(FIND("（",$E57),999))-1))=J$1,$F57,"")) | K57: =IF(OR($E57="",K$1=""),"",IF(TRIM(LEFT($E57,MIN(IFERROR(FIND("CDU",UPPER($E57)),999),IFERROR(FIND("BULK",UPPER($E57)),999),IFERROR(FIND("-",$E57),999),IFERROR(FIND("（",$E57),999))-1))=K$1,$F57,"")) -> 960 | L57: =IF(OR($E57="",L$1=""),"",IF(TRIM(LEFT($E57,MIN(IFERROR(FIND("CDU",UPPER($E57)),999),IFERROR(FIND("BULK",UPPER($E57)),999),IFERROR(FIND("-",$E57),999),IFERROR(FIND("（",$E57),999))-1))=L$1,$F57,"")) | M57: =IF(OR($E57="",M$1=""),"",IF(TRIM(LEFT($E57,MIN(IFERROR(FIND("CDU",UPPER($E57)),999),IFERROR(FIND("BULK",UPPER($E57)),999),IFERROR(FIND("-",$E57),999),IFERROR(FIND("（",$E57),999))-1))=M$1,$F57,"")) | N57: =IF(OR($E57="",N$1=""),"",IF(TRIM(LEFT($E57,MIN(IFERROR(FIND("CDU",UPPER($E57)),999),IFERROR(FIND("BULK",UPPER($E57)),999),IFERROR(FIND("-",$E57),999),IFERROR(FIND("（",$E57),999))-1))=N$1,$F57,"")) | O57: =IF(OR($E57="",O$1=""),"",IF(TRIM(LEFT($E57,MIN(IFERROR(FIND("CDU",UPPER($E57)),999),IFERROR(FIND("BULK",UPPER($E57)),999),IFERROR(FIND("-",$E57),999),IFERROR(FIND("（",$E57),999))-1))=O$1,$F57,"")) | P57: =IF(OR($E57="",P$1=""),"",IF(TRIM(LEFT($E57,MIN(IFERROR(FIND("CDU",UPPER($E57)),999),IFERROR(FIND("BULK",UPPER($E57)),999),IFERROR(FIND("-",$E57),999),IFERROR(FIND("（",$E57),999))-1))=P$1,$F57,"")) | ... BU57: =IF(OR($E57="",BU$1=""),"",IF(TRIM(LEFT($E57,MIN(IFERROR(FIND("CDU",UPPER($E57)),999),IFERROR(FIND("BULK",UPPER($E57)),999),IFERROR(FIND("-",$E57),999),IFERROR(FIND("（",$E57),999))-1))=BU$1,$F57,"")) | BV57: 0.79 | BW57: =SUM(I57:BU57)*BV57 -> 758.4 | BX57: =BW57*7.75 -> 5877.6 | BY57: =MID(E57,1,2) -> SR
A58: 45992 | B58: 46044 | D58: PO0000047-MGBS | E58: SR102CDU-16 | F58: 960 | G58: 第二代美文版 | H58: =IFERROR(VLOOKUP(E58,名称!A:E,4,0),"") -> 二代 | I58: =IF(OR($E58="",I$1=""),"",IF(TRIM(LEFT($E58,MIN(IFERROR(FIND("CDU",UPPER($E58)),999),IFERROR(FIND("BULK",UPPER($E58)),999),IFERROR(FIND("-",$E58),999),IFERROR(FIND("（",$E58),999))-1))=I$1,$F58,"")) | J58: =IF(OR($E58="",J$1=""),"",IF(TRIM(LEFT($E58,MIN(IFERROR(FIND("CDU",UPPER($E58)),999),IFERROR(FIND("BULK",UPPER($E58)),999),IFERROR(FIND("-",$E58),999),IFERROR(FIND("（",$E58),999))-1))=J$1,$F58,"")) | K58: =IF(OR($E58="",K$1=""),"",IF(TRIM(LEFT($E58,MIN(IFERROR(FIND("CDU",UPPER($E58)),999),IFERROR(FIND("BULK",UPPER($E58)),999),IFERROR(FIND("-",$E58),999),IFERROR(FIND("（",$E58),999))-1))=K$1,$F58,"")) -> 960 | L58: =IF(OR($E58="",L$1=""),"",IF(TRIM(LEFT($E58,MIN(IFERROR(FIND("CDU",UPPER($E58)),999),IFERROR(FIND("BULK",UPPER($E58)),999),IFERROR(FIND("-",$E58),999),IFERROR(FIND("（",$E58),999))-1))=L$1,$F58,"")) | M58: =IF(OR($E58="",M$1=""),"",IF(TRIM(LEFT($E58,MIN(IFERROR(FIND("CDU",UPPER($E58)),999),IFERROR(FIND("BULK",UPPER($E58)),999),IFERROR(FIND("-",$E58),999),IFERROR(FIND("（",$E58),999))-1))=M$1,$F58,"")) | N58: =IF(OR($E58="",N$1=""),"",IF(TRIM(LEFT($E58,MIN(IFERROR(FIND("CDU",UPPER($E58)),999),IFERROR(FIND("BULK",UPPER($E58)),999),IFERROR(FIND("-",$E58),999),IFERROR(FIND("（",$E58),999))-1))=N$1,$F58,"")) | O58: =IF(OR($E58="",O$1=""),"",IF(TRIM(LEFT($E58,MIN(IFERROR(FIND("CDU",UPPER($E58)),999),IFERROR(FIND("BULK",UPPER($E58)),999),IFERROR(FIND("-",$E58),999),IFERROR(FIND("（",$E58),999))-1))=O$1,$F58,"")) | P58: =IF(OR($E58="",P$1=""),"",IF(TRIM(LEFT($E58,MIN(IFERROR(FIND("CDU",UPPER($E58)),999),IFERROR(FIND("BULK",UPPER($E58)),999),IFERROR(FIND("-",$E58),999),IFERROR(FIND("（",$E58),999))-1))=P$1,$F58,"")) | ... BU58: =IF(OR($E58="",BU$1=""),"",IF(TRIM(LEFT($E58,MIN(IFERROR(FIND("CDU",UPPER($E58)),999),IFERROR(FIND("BULK",UPPER($E58)),999),IFERROR(FIND("-",$E58),999),IFERROR(FIND("（",$E58),999))-1))=BU$1,$F58,"")) | BV58: 0.91 | BW58: =SUM(I58:BU58)*BV58 -> 873.6 | BX58: =BW58*7.75 -> 6770.4 | BY58: =MID(E58,1,2) -> SR
A59: 45992 | B59: 46044 | D59: PO0000047-MGBS | E59: SR103CDU-24 | F59: 1512 | G59: 第二代美文版 | H59: =IFERROR(VLOOKUP(E59,名称!A:E,4,0),"") -> 二代 | I59: =IF(OR($E59="",I$1=""),"",IF(TRIM(LEFT($E59,MIN(IFERROR(FIND("CDU",UPPER($E59)),999),IFERROR(FIND("BULK",UPPER($E59)),999),IFERROR(FIND("-",$E59),999),IFERROR(FIND("（",$E59),999))-1))=I$1,$F59,"")) | J59: =IF(OR($E59="",J$1=""),"",IF(TRIM(LEFT($E59,MIN(IFERROR(FIND("CDU",UPPER($E59)),999),IFERROR(FIND("BULK",UPPER($E59)),999),IFERROR(FIND("-",$E59),999),IFERROR(FIND("（",$E59),999))-1))=J$1,$F59,"")) | K59: =IF(OR($E59="",K$1=""),"",IF(TRIM(LEFT($E59,MIN(IFERROR(FIND("CDU",UPPER($E59)),999),IFERROR(FIND("BULK",UPPER($E59)),999),IFERROR(FIND("-",$E59),999),IFERROR(FIND("（",$E59),999))-1))=K$1,$F59,"")) | L59: =IF(OR($E59="",L$1=""),"",IF(TRIM(LEFT($E59,MIN(IFERROR(FIND("CDU",UPPER($E59)),999),IFERROR(FIND("BULK",UPPER($E59)),999),IFERROR(FIND("-",$E59),999),IFERROR(FIND("（",$E59),999))-1))=L$1,$F59,"")) | M59: =IF(OR($E59="",M$1=""),"",IF(TRIM(LEFT($E59,MIN(IFERROR(FIND("CDU",UPPER($E59)),999),IFERROR(FIND("BULK",UPPER($E59)),999),IFERROR(FIND("-",$E59),999),IFERROR(FIND("（",$E59),999))-1))=M$1,$F59,"")) -> 1512 | N59: =IF(OR($E59="",N$1=""),"",IF(TRIM(LEFT($E59,MIN(IFERROR(FIND("CDU",UPPER($E59)),999),IFERROR(FIND("BULK",UPPER($E59)),999),IFERROR(FIND("-",$E59),999),IFERROR(FIND("（",$E59),999))-1))=N$1,$F59,"")) | O59: =IF(OR($E59="",O$1=""),"",IF(TRIM(LEFT($E59,MIN(IFERROR(FIND("CDU",UPPER($E59)),999),IFERROR(FIND("BULK",UPPER($E59)),999),IFERROR(FIND("-",$E59),999),IFERROR(FIND("（",$E59),999))-1))=O$1,$F59,"")) | P59: =IF(OR($E59="",P$1=""),"",IF(TRIM(LEFT($E59,MIN(IFERROR(FIND("CDU",UPPER($E59)),999),IFERROR(FIND("BULK",UPPER($E59)),999),IFERROR(FIND("-",$E59),999),IFERROR(FIND("（",$E59),999))-1))=P$1,$F59,"")) | ... BU59: =IF(OR($E59="",BU$1=""),"",IF(TRIM(LEFT($E59,MIN(IFERROR(FIND("CDU",UPPER($E59)),999),IFERROR(FIND("BULK",UPPER($E59)),999),IFERROR(FIND("-",$E59),999),IFERROR(FIND("（",$E59),999))-1))=BU$1,$F59,"")) | BV59: 0.65 | BW59: =SUM(I59:BU59)*BV59 -> 982.8 | BX59: =BW59*7.75 -> 7616.7 | BY59: =MID(E59,1,2) -> SR
A60: 45992 | B60: 46044 | D60: PO0000047-MGBS | E60: SR201 | F60: 978 | G60: 第二代美文版 | H60: =IFERROR(VLOOKUP(E60,名称!A:E,4,0),"") -> 二代 | I60: =IF(OR($E60="",I$1=""),"",IF(TRIM(LEFT($E60,MIN(IFERROR(FIND("CDU",UPPER($E60)),999),IFERROR(FIND("BULK",UPPER($E60)),999),IFERROR(FIND("-",$E60),999),IFERROR(FIND("（",$E60),999))-1))=I$1,$F60,"")) | J60: =IF(OR($E60="",J$1=""),"",IF(TRIM(LEFT($E60,MIN(IFERROR(FIND("CDU",UPPER($E60)),999),IFERROR(FIND("BULK",UPPER($E60)),999),IFERROR(FIND("-",$E60),999),IFERROR(FIND("（",$E60),999))-1))=J$1,$F60,"")) | K60: =IF(OR($E60="",K$1=""),"",IF(TRIM(LEFT($E60,MIN(IFERROR(FIND("CDU",UPPER($E60)),999),IFERROR(FIND("BULK",UPPER($E60)),999),IFERROR(FIND("-",$E60),999),IFERROR(FIND("（",$E60),999))-1))=K$1,$F60,"")) | L60: =IF(OR($E60="",L$1=""),"",IF(TRIM(LEFT($E60,MIN(IFERROR(FIND("CDU",UPPER($E60)),999),IFERROR(FIND("BULK",UPPER($E60)),999),IFERROR(FIND("-",$E60),999),IFERROR(FIND("（",$E60),999))-1))=L$1,$F60,"")) | M60: =IF(OR($E60="",M$1=""),"",IF(TRIM(LEFT($E60,MIN(IFERROR(FIND("CDU",UPPER($E60)),999),IFERROR(FIND("BULK",UPPER($E60)),999),IFERROR(FIND("-",$E60),999),IFERROR(FIND("（",$E60),999))-1))=M$1,$F60,"")) | N60: =IF(OR($E60="",N$1=""),"",IF(TRIM(LEFT($E60,MIN(IFERROR(FIND("CDU",UPPER($E60)),999),IFERROR(FIND("BULK",UPPER($E60)),999),IFERROR(FIND("-",$E60),999),IFERROR(FIND("（",$E60),999))-1))=N$1,$F60,"")) | O60: =IF(OR($E60="",O$1=""),"",IF(TRIM(LEFT($E60,MIN(IFERROR(FIND("CDU",UPPER($E60)),999),IFERROR(FIND("BULK",UPPER($E60)),999),IFERROR(FIND("-",$E60),999),IFERROR(FIND("（",$E60),999))-1))=O$1,$F60,"")) | P60: =IF(OR($E60="",P$1=""),"",IF(TRIM(LEFT($E60,MIN(IFERROR(FIND("CDU",UPPER($E60)),999),IFERROR(FIND("BULK",UPPER($E60)),999),IFERROR(FIND("-",$E60),999),IFERROR(FIND("（",$E60),999))-1))=P$1,$F60,"")) | ... BU60: =IF(OR($E60="",BU$1=""),"",IF(TRIM(LEFT($E60,MIN(IFERROR(FIND("CDU",UPPER($E60)),999),IFERROR(FIND("BULK",UPPER($E60)),999),IFERROR(FIND("-",$E60),999),IFERROR(FIND("（",$E60),999))-1))=BU$1,$F60,"")) | BV60: 2.09 | BW60: =SUM(I60:BU60)*BV60 -> 2044.02 | BX60: =BW60*7.75 -> 15841.16 | BY60: =MID(E60,1,2) -> SR
A61: 45992 | B61: 46044 | D61: PO0000047-MGBS | E61: SR301 | F61: 480 | G61: 第二代美文版 | H61: =IFERROR(VLOOKUP(E61,名称!A:E,4,0),"") -> 二代 | I61: =IF(OR($E61="",I$1=""),"",IF(TRIM(LEFT($E61,MIN(IFERROR(FIND("CDU",UPPER($E61)),999),IFERROR(FIND("BULK",UPPER($E61)),999),IFERROR(FIND("-",$E61),999),IFERROR(FIND("（",$E61),999))-1))=I$1,$F61,"")) | J61: =IF(OR($E61="",J$1=""),"",IF(TRIM(LEFT($E61,MIN(IFERROR(FIND("CDU",UPPER($E61)),999),IFERROR(FIND("BULK",UPPER($E61)),999),IFERROR(FIND("-",$E61),999),IFERROR(FIND("（",$E61),999))-1))=J$1,$F61,"")) | K61: =IF(OR($E61="",K$1=""),"",IF(TRIM(LEFT($E61,MIN(IFERROR(FIND("CDU",UPPER($E61)),999),IFERROR(FIND("BULK",UPPER($E61)),999),IFERROR(FIND("-",$E61),999),IFERROR(FIND("（",$E61),999))-1))=K$1,$F61,"")) | L61: =IF(OR($E61="",L$1=""),"",IF(TRIM(LEFT($E61,MIN(IFERROR(FIND("CDU",UPPER($E61)),999),IFERROR(FIND("BULK",UPPER($E61)),999),IFERROR(FIND("-",$E61),999),IFERROR(FIND("（",$E61),999))-1))=L$1,$F61,"")) | M61: =IF(OR($E61="",M$1=""),"",IF(TRIM(LEFT($E61,MIN(IFERROR(FIND("CDU",UPPER($E61)),999),IFERROR(FIND("BULK",UPPER($E61)),999),IFERROR(FIND("-",$E61),999),IFERROR(FIND("（",$E61),999))-1))=M$1,$F61,"")) | N61: =IF(OR($E61="",N$1=""),"",IF(TRIM(LEFT($E61,MIN(IFERROR(FIND("CDU",UPPER($E61)),999),IFERROR(FIND("BULK",UPPER($E61)),999),IFERROR(FIND("-",$E61),999),IFERROR(FIND("（",$E61),999))-1))=N$1,$F61,"")) | O61: =IF(OR($E61="",O$1=""),"",IF(TRIM(LEFT($E61,MIN(IFERROR(FIND("CDU",UPPER($E61)),999),IFERROR(FIND("BULK",UPPER($E61)),999),IFERROR(FIND("-",$E61),999),IFERROR(FIND("（",$E61),999))-1))=O$1,$F61,"")) | P61: =IF(OR($E61="",P$1=""),"",IF(TRIM(LEFT($E61,MIN(IFERROR(FIND("CDU",UPPER($E61)),999),IFERROR(FIND("BULK",UPPER($E61)),999),IFERROR(FIND("-",$E61),999),IFERROR(FIND("（",$E61),999))-1))=P$1,$F61,"")) | ... BU61: =IF(OR($E61="",BU$1=""),"",IF(TRIM(LEFT($E61,MIN(IFERROR(FIND("CDU",UPPER($E61)),999),IFERROR(FIND("BULK",UPPER($E61)),999),IFERROR(FIND("-",$E61),999),IFERROR(FIND("（",$E61),999))-1))=BU$1,$F61,"")) | BV61: 3.23 | BW61: =SUM(I61:BU61)*BV61 -> 1550.4 | BX61: =BW61*7.75 -> 12015.6 | BY61: =MID(E61,1,2) -> SR
A62: 45992 | B62: 46044 | D62: PO0000047-MGBS | E62: SR400CDU-12 | F62: 480 | G62: 第二代美文版 | H62: =IFERROR(VLOOKUP(E62,名称!A:E,4,0),"") -> 二代 | I62: =IF(OR($E62="",I$1=""),"",IF(TRIM(LEFT($E62,MIN(IFERROR(FIND("CDU",UPPER($E62)),999),IFERROR(FIND("BULK",UPPER($E62)),999),IFERROR(FIND("-",$E62),999),IFERROR(FIND("（",$E62),999))-1))=I$1,$F62,"")) | J62: =IF(OR($E62="",J$1=""),"",IF(TRIM(LEFT($E62,MIN(IFERROR(FIND("CDU",UPPER($E62)),999),IFERROR(FIND("BULK",UPPER($E62)),999),IFERROR(FIND("-",$E62),999),IFERROR(FIND("（",$E62),999))-1))=J$1,$F62,"")) | K62: =IF(OR($E62="",K$1=""),"",IF(TRIM(LEFT($E62,MIN(IFERROR(FIND("CDU",UPPER($E62)),999),IFERROR(FIND("BULK",UPPER($E62)),999),IFERROR(FIND("-",$E62),999),IFERROR(FIND("（",$E62),999))-1))=K$1,$F62,"")) | L62: =IF(OR($E62="",L$1=""),"",IF(TRIM(LEFT($E62,MIN(IFERROR(FIND("CDU",UPPER($E62)),999),IFERROR(FIND("BULK",UPPER($E62)),999),IFERROR(FIND("-",$E62),999),IFERROR(FIND("（",$E62),999))-1))=L$1,$F62,"")) | M62: =IF(OR($E62="",M$1=""),"",IF(TRIM(LEFT($E62,MIN(IFERROR(FIND("CDU",UPPER($E62)),999),IFERROR(FIND("BULK",UPPER($E62)),999),IFERROR(FIND("-",$E62),999),IFERROR(FIND("（",$E62),999))-1))=M$1,$F62,"")) | N62: =IF(OR($E62="",N$1=""),"",IF(TRIM(LEFT($E62,MIN(IFERROR(FIND("CDU",UPPER($E62)),999),IFERROR(FIND("BULK",UPPER($E62)),999),IFERROR(FIND("-",$E62),999),IFERROR(FIND("（",$E62),999))-1))=N$1,$F62,"")) | O62: =IF(OR($E62="",O$1=""),"",IF(TRIM(LEFT($E62,MIN(IFERROR(FIND("CDU",UPPER($E62)),999),IFERROR(FIND("BULK",UPPER($E62)),999),IFERROR(FIND("-",$E62),999),IFERROR(FIND("（",$E62),999))-1))=O$1,$F62,"")) | P62: =IF(OR($E62="",P$1=""),"",IF(TRIM(LEFT($E62,MIN(IFERROR(FIND("CDU",UPPER($E62)),999),IFERROR(FIND("BULK",UPPER($E62)),999),IFERROR(FIND("-",$E62),999),IFERROR(FIND("（",$E62),999))-1))=P$1,$F62,"")) | ... BU62: =IF(OR($E62="",BU$1=""),"",IF(TRIM(LEFT($E62,MIN(IFERROR(FIND("CDU",UPPER($E62)),999),IFERROR(FIND("BULK",UPPER($E62)),999),IFERROR(FIND("-",$E62),999),IFERROR(FIND("（",$E62),999))-1))=BU$1,$F62,"")) | BV62: 1.65 | BW62: =SUM(I62:BU62)*BV62 -> 792 | BX62: =BW62*7.75 -> 6138 | BY62: =MID(E62,1,2) -> SR
A63: 45992 | B63: 46044 | D63: PO0000047-MGBS | E63: SR320（蓝绿版） | F63: 100 | G63: 第二代美文版 | H63: =IFERROR(VLOOKUP(E63,名称!A:E,4,0),"") -> 二代 | I63: =IF(OR($E63="",I$1=""),"",IF(TRIM(LEFT($E63,MIN(IFERROR(FIND("CDU",UPPER($E63)),999),IFERROR(FIND("BULK",UPPER($E63)),999),IFERROR(FIND("-",$E63),999),IFERROR(FIND("（",$E63),999))-1))=I$1,$F63,"")) | J63: =IF(OR($E63="",J$1=""),"",IF(TRIM(LEFT($E63,MIN(IFERROR(FIND("CDU",UPPER($E63)),999),IFERROR(FIND("BULK",UPPER($E63)),999),IFERROR(FIND("-",$E63),999),IFERROR(FIND("（",$E63),999))-1))=J$1,$F63,"")) | K63: =IF(OR($E63="",K$1=""),"",IF(TRIM(LEFT($E63,MIN(IFERROR(FIND("CDU",UPPER($E63)),999),IFERROR(FIND("BULK",UPPER($E63)),999),IFERROR(FIND("-",$E63),999),IFERROR(FIND("（",$E63),999))-1))=K$1,$F63,"")) | L63: =IF(OR($E63="",L$1=""),"",IF(TRIM(LEFT($E63,MIN(IFERROR(FIND("CDU",UPPER($E63)),999),IFERROR(FIND("BULK",UPPER($E63)),999),IFERROR(FIND("-",$E63),999),IFERROR(FIND("（",$E63),999))-1))=L$1,$F63,"")) | M63: =IF(OR($E63="",M$1=""),"",IF(TRIM(LEFT($E63,MIN(IFERROR(FIND("CDU",UPPER($E63)),999),IFERROR(FIND("BULK",UPPER($E63)),999),IFERROR(FIND("-",$E63),999),IFERROR(FIND("（",$E63),999))-1))=M$1,$F63,"")) | N63: =IF(OR($E63="",N$1=""),"",IF(TRIM(LEFT($E63,MIN(IFERROR(FIND("CDU",UPPER($E63)),999),IFERROR(FIND("BULK",UPPER($E63)),999),IFERROR(FIND("-",$E63),999),IFERROR(FIND("（",$E63),999))-1))=N$1,$F63,"")) | O63: =IF(OR($E63="",O$1=""),"",IF(TRIM(LEFT($E63,MIN(IFERROR(FIND("CDU",UPPER($E63)),999),IFERROR(FIND("BULK",UPPER($E63)),999),IFERROR(FIND("-",$E63),999),IFERROR(FIND("（",$E63),999))-1))=O$1,$F63,"")) | P63: =IF(OR($E63="",P$1=""),"",IF(TRIM(LEFT($E63,MIN(IFERROR(FIND("CDU",UPPER($E63)),999),IFERROR(FIND("BULK",UPPER($E63)),999),IFERROR(FIND("-",$E63),999),IFERROR(FIND("（",$E63),999))-1))=P$1,$F63,"")) | ... BU63: =IF(OR($E63="",BU$1=""),"",IF(TRIM(LEFT($E63,MIN(IFERROR(FIND("CDU",UPPER($E63)),999),IFERROR(FIND("BULK",UPPER($E63)),999),IFERROR(FIND("-",$E63),999),IFERROR(FIND("（",$E63),999))-1))=BU$1,$F63,"")) | BV63: 9.98 | BW63: =SUM(I63:BU63)*BV63 -> 998 | BX63: =BW63*7.75 -> 7734.5 | BY63: =MID(E63,1,2) -> SR
A64: 45992 | B64: 46044 | D64: PO0000047-MGBS | E64: SR180CDU-24 | F64: 480 | G64: 第二代美文版 | H64: =IFERROR(VLOOKUP(E64,名称!A:E,4,0),"") -> 二代 | I64: =IF(OR($E64="",I$1=""),"",IF(TRIM(LEFT($E64,MIN(IFERROR(FIND("CDU",UPPER($E64)),999),IFERROR(FIND("BULK",UPPER($E64)),999),IFERROR(FIND("-",$E64),999),IFERROR(FIND("（",$E64),999))-1))=I$1,$F64,"")) | J64: =IF(OR($E64="",J$1=""),"",IF(TRIM(LEFT($E64,MIN(IFERROR(FIND("CDU",UPPER($E64)),999),IFERROR(FIND("BULK",UPPER($E64)),999),IFERROR(FIND("-",$E64),999),IFERROR(FIND("（",$E64),999))-1))=J$1,$F64,"")) | K64: =IF(OR($E64="",K$1=""),"",IF(TRIM(LEFT($E64,MIN(IFERROR(FIND("CDU",UPPER($E64)),999),IFERROR(FIND("BULK",UPPER($E64)),999),IFERROR(FIND("-",$E64),999),IFERROR(FIND("（",$E64),999))-1))=K$1,$F64,"")) | L64: =IF(OR($E64="",L$1=""),"",IF(TRIM(LEFT($E64,MIN(IFERROR(FIND("CDU",UPPER($E64)),999),IFERROR(FIND("BULK",UPPER($E64)),999),IFERROR(FIND("-",$E64),999),IFERROR(FIND("（",$E64),999))-1))=L$1,$F64,"")) | M64: =IF(OR($E64="",M$1=""),"",IF(TRIM(LEFT($E64,MIN(IFERROR(FIND("CDU",UPPER($E64)),999),IFERROR(FIND("BULK",UPPER($E64)),999),IFERROR(FIND("-",$E64),999),IFERROR(FIND("（",$E64),999))-1))=M$1,$F64,"")) | N64: =IF(OR($E64="",N$1=""),"",IF(TRIM(LEFT($E64,MIN(IFERROR(FIND("CDU",UPPER($E64)),999),IFERROR(FIND("BULK",UPPER($E64)),999),IFERROR(FIND("-",$E64),999),IFERROR(FIND("（",$E64),999))-1))=N$1,$F64,"")) | O64: =IF(OR($E64="",O$1=""),"",IF(TRIM(LEFT($E64,MIN(IFERROR(FIND("CDU",UPPER($E64)),999),IFERROR(FIND("BULK",UPPER($E64)),999),IFERROR(FIND("-",$E64),999),IFERROR(FIND("（",$E64),999))-1))=O$1,$F64,"")) | P64: =IF(OR($E64="",P$1=""),"",IF(TRIM(LEFT($E64,MIN(IFERROR(FIND("CDU",UPPER($E64)),999),IFERROR(FIND("BULK",UPPER($E64)),999),IFERROR(FIND("-",$E64),999),IFERROR(FIND("（",$E64),999))-1))=P$1,$F64,"")) -> 480 | ... BU64: =IF(OR($E64="",BU$1=""),"",IF(TRIM(LEFT($E64,MIN(IFERROR(FIND("CDU",UPPER($E64)),999),IFERROR(FIND("BULK",UPPER($E64)),999),IFERROR(FIND("-",$E64),999),IFERROR(FIND("（",$E64),999))-1))=BU$1,$F64,"")) | BV64: 0.65 | BW64: =SUM(I64:BU64)*BV64 -> 312 | BX64: =BW64*7.75 -> 2418 | BY64: =MID(E64,1,2) -> SR
A65: 45992 | B65: 46044 | D65: PO0000047-MGBS | E65: SR430CDU-12 | F65: 120 | G65: 第二代美文版 | H65: =IFERROR(VLOOKUP(E65,名称!A:E,4,0),"") -> 二代 | I65: =IF(OR($E65="",I$1=""),"",IF(TRIM(LEFT($E65,MIN(IFERROR(FIND("CDU",UPPER($E65)),999),IFERROR(FIND("BULK",UPPER($E65)),999),IFERROR(FIND("-",$E65),999),IFERROR(FIND("（",$E65),999))-1))=I$1,$F65,"")) | J65: =IF(OR($E65="",J$1=""),"",IF(TRIM(LEFT($E65,MIN(IFERROR(FIND("CDU",UPPER($E65)),999),IFERROR(FIND("BULK",UPPER($E65)),999),IFERROR(FIND("-",$E65),999),IFERROR(FIND("（",$E65),999))-1))=J$1,$F65,"")) | K65: =IF(OR($E65="",K$1=""),"",IF(TRIM(LEFT($E65,MIN(IFERROR(FIND("CDU",UPPER($E65)),999),IFERROR(FIND("BULK",UPPER($E65)),999),IFERROR(FIND("-",$E65),999),IFERROR(FIND("（",$E65),999))-1))=K$1,$F65,"")) | L65: =IF(OR($E65="",L$1=""),"",IF(TRIM(LEFT($E65,MIN(IFERROR(FIND("CDU",UPPER($E65)),999),IFERROR(FIND("BULK",UPPER($E65)),999),IFERROR(FIND("-",$E65),999),IFERROR(FIND("（",$E65),999))-1))=L$1,$F65,"")) | M65: =IF(OR($E65="",M$1=""),"",IF(TRIM(LEFT($E65,MIN(IFERROR(FIND("CDU",UPPER($E65)),999),IFERROR(FIND("BULK",UPPER($E65)),999),IFERROR(FIND("-",$E65),999),IFERROR(FIND("（",$E65),999))-1))=M$1,$F65,"")) | N65: =IF(OR($E65="",N$1=""),"",IF(TRIM(LEFT($E65,MIN(IFERROR(FIND("CDU",UPPER($E65)),999),IFERROR(FIND("BULK",UPPER($E65)),999),IFERROR(FIND("-",$E65),999),IFERROR(FIND("（",$E65),999))-1))=N$1,$F65,"")) | O65: =IF(OR($E65="",O$1=""),"",IF(TRIM(LEFT($E65,MIN(IFERROR(FIND("CDU",UPPER($E65)),999),IFERROR(FIND("BULK",UPPER($E65)),999),IFERROR(FIND("-",$E65),999),IFERROR(FIND("（",$E65),999))-1))=O$1,$F65,"")) | P65: =IF(OR($E65="",P$1=""),"",IF(TRIM(LEFT($E65,MIN(IFERROR(FIND("CDU",UPPER($E65)),999),IFERROR(FIND("BULK",UPPER($E65)),999),IFERROR(FIND("-",$E65),999),IFERROR(FIND("（",$E65),999))-1))=P$1,$F65,"")) | ... BU65: =IF(OR($E65="",BU$1=""),"",IF(TRIM(LEFT($E65,MIN(IFERROR(FIND("CDU",UPPER($E65)),999),IFERROR(FIND("BULK",UPPER($E65)),999),IFERROR(FIND("-",$E65),999),IFERROR(FIND("（",$E65),999))-1))=BU$1,$F65,"")) | BV65: 1.65 | BW65: =SUM(I65:BU65)*BV65 -> 198 | BX65: =BW65*7.75 -> 1534.5 | BY65: =MID(E65,1,2) -> SR
A66: 45992 | B66: 46044 | D66: PO0000047-MGBS | E66: JS100CDU-24 | F66: 240 | G66: 第二代美文版 | H66: =IFERROR(VLOOKUP(E66,名称!A:E,4,0),"") -> 二代 | I66: =IF(OR($E66="",I$1=""),"",IF(TRIM(LEFT($E66,MIN(IFERROR(FIND("CDU",UPPER($E66)),999),IFERROR(FIND("BULK",UPPER($E66)),999),IFERROR(FIND("-",$E66),999),IFERROR(FIND("（",$E66),999))-1))=I$1,$F66,"")) | J66: =IF(OR($E66="",J$1=""),"",IF(TRIM(LEFT($E66,MIN(IFERROR(FIND("CDU",UPPER($E66)),999),IFERROR(FIND("BULK",UPPER($E66)),999),IFERROR(FIND("-",$E66),999),IFERROR(FIND("（",$E66),999))-1))=J$1,$F66,"")) | K66: =IF(OR($E66="",K$1=""),"",IF(TRIM(LEFT($E66,MIN(IFERROR(FIND("CDU",UPPER($E66)),999),IFERROR(FIND("BULK",UPPER($E66)),999),IFERROR(FIND("-",$E66),999),IFERROR(FIND("（",$E66),999))-1))=K$1,$F66,"")) | L66: =IF(OR($E66="",L$1=""),"",IF(TRIM(LEFT($E66,MIN(IFERROR(FIND("CDU",UPPER($E66)),999),IFERROR(FIND("BULK",UPPER($E66)),999),IFERROR(FIND("-",$E66),999),IFERROR(FIND("（",$E66),999))-1))=L$1,$F66,"")) | M66: =IF(OR($E66="",M$1=""),"",IF(TRIM(LEFT($E66,MIN(IFERROR(FIND("CDU",UPPER($E66)),999),IFERROR(FIND("BULK",UPPER($E66)),999),IFERROR(FIND("-",$E66),999),IFERROR(FIND("（",$E66),999))-1))=M$1,$F66,"")) | N66: =IF(OR($E66="",N$1=""),"",IF(TRIM(LEFT($E66,MIN(IFERROR(FIND("CDU",UPPER($E66)),999),IFERROR(FIND("BULK",UPPER($E66)),999),IFERROR(FIND("-",$E66),999),IFERROR(FIND("（",$E66),999))-1))=N$1,$F66,"")) | O66: =IF(OR($E66="",O$1=""),"",IF(TRIM(LEFT($E66,MIN(IFERROR(FIND("CDU",UPPER($E66)),999),IFERROR(FIND("BULK",UPPER($E66)),999),IFERROR(FIND("-",$E66),999),IFERROR(FIND("（",$E66),999))-1))=O$1,$F66,"")) | P66: =IF(OR($E66="",P$1=""),"",IF(TRIM(LEFT($E66,MIN(IFERROR(FIND("CDU",UPPER($E66)),999),IFERROR(FIND("BULK",UPPER($E66)),999),IFERROR(FIND("-",$E66),999),IFERROR(FIND("（",$E66),999))-1))=P$1,$F66,"")) | ... BU66: =IF(OR($E66="",BU$1=""),"",IF(TRIM(LEFT($E66,MIN(IFERROR(FIND("CDU",UPPER($E66)),999),IFERROR(FIND("BULK",UPPER($E66)),999),IFERROR(FIND("-",$E66),999),IFERROR(FIND("（",$E66),999))-1))=BU$1,$F66,"")) | BV66: 0.64 | BW66: =SUM(I66:BU66)*BV66 -> 153.6 | BX66: =BW66*7.75 -> 1190.4 | BY66: =MID(E66,1,2) -> JS
A67: 45992 | B67: 46044 | D67: PO0000047-MGBS | E67: SR130CDU-24 | F67: 120 | G67: 第二代美文版 | H67: =IFERROR(VLOOKUP(E67,名称!A:E,4,0),"") -> 二代 | I67: =IF(OR($E67="",I$1=""),"",IF(TRIM(LEFT($E67,MIN(IFERROR(FIND("CDU",UPPER($E67)),999),IFERROR(FIND("BULK",UPPER($E67)),999),IFERROR(FIND("-",$E67),999),IFERROR(FIND("（",$E67),999))-1))=I$1,$F67,"")) | J67: =IF(OR($E67="",J$1=""),"",IF(TRIM(LEFT($E67,MIN(IFERROR(FIND("CDU",UPPER($E67)),999),IFERROR(FIND("BULK",UPPER($E67)),999),IFERROR(FIND("-",$E67),999),IFERROR(FIND("（",$E67),999))-1))=J$1,$F67,"")) | K67: =IF(OR($E67="",K$1=""),"",IF(TRIM(LEFT($E67,MIN(IFERROR(FIND("CDU",UPPER($E67)),999),IFERROR(FIND("BULK",UPPER($E67)),999),IFERROR(FIND("-",$E67),999),IFERROR(FIND("（",$E67),999))-1))=K$1,$F67,"")) | L67: =IF(OR($E67="",L$1=""),"",IF(TRIM(LEFT($E67,MIN(IFERROR(FIND("CDU",UPPER($E67)),999),IFERROR(FIND("BULK",UPPER($E67)),999),IFERROR(FIND("-",$E67),999),IFERROR(FIND("（",$E67),999))-1))=L$1,$F67,"")) | M67: =IF(OR($E67="",M$1=""),"",IF(TRIM(LEFT($E67,MIN(IFERROR(FIND("CDU",UPPER($E67)),999),IFERROR(FIND("BULK",UPPER($E67)),999),IFERROR(FIND("-",$E67),999),IFERROR(FIND("（",$E67),999))-1))=M$1,$F67,"")) | N67: =IF(OR($E67="",N$1=""),"",IF(TRIM(LEFT($E67,MIN(IFERROR(FIND("CDU",UPPER($E67)),999),IFERROR(FIND("BULK",UPPER($E67)),999),IFERROR(FIND("-",$E67),999),IFERROR(FIND("（",$E67),999))-1))=N$1,$F67,"")) -> 120 | O67: =IF(OR($E67="",O$1=""),"",IF(TRIM(LEFT($E67,MIN(IFERROR(FIND("CDU",UPPER($E67)),999),IFERROR(FIND("BULK",UPPER($E67)),999),IFERROR(FIND("-",$E67),999),IFERROR(FIND("（",$E67),999))-1))=O$1,$F67,"")) | P67: =IF(OR($E67="",P$1=""),"",IF(TRIM(LEFT($E67,MIN(IFERROR(FIND("CDU",UPPER($E67)),999),IFERROR(FIND("BULK",UPPER($E67)),999),IFERROR(FIND("-",$E67),999),IFERROR(FIND("（",$E67),999))-1))=P$1,$F67,"")) | ... BU67: =IF(OR($E67="",BU$1=""),"",IF(TRIM(LEFT($E67,MIN(IFERROR(FIND("CDU",UPPER($E67)),999),IFERROR(FIND("BULK",UPPER($E67)),999),IFERROR(FIND("-",$E67),999),IFERROR(FIND("（",$E67),999))-1))=BU$1,$F67,"")) | BV67: 0.65 | BW67: =SUM(I67:BU67)*BV67 -> 78 | BX67: =BW67*7.75 -> 604.5 | BY67: =MID(E67,1,2) -> SR
A68: 45995 | B68: 46045 | C68: PL252474-01 | D68: PO0000049-UKCO | E68: JS100CDU-9 | F68: 6003 | G68: TOY客版 | H68: =IFERROR(VLOOKUP(E68,名称!A:E,4,0),"") -> 二代 | I68: =IF(OR($E68="",I$1=""),"",IF(TRIM(LEFT($E68,MIN(IFERROR(FIND("CDU",UPPER($E68)),999),IFERROR(FIND("BULK",UPPER($E68)),999),IFERROR(FIND("-",$E68),999),IFERROR(FIND("（",$E68),999))-1))=I$1,$F68,"")) | J68: =IF(OR($E68="",J$1=""),"",IF(TRIM(LEFT($E68,MIN(IFERROR(FIND("CDU",UPPER($E68)),999),IFERROR(FIND("BULK",UPPER($E68)),999),IFERROR(FIND("-",$E68),999),IFERROR(FIND("（",$E68),999))-1))=J$1,$F68,"")) | K68: =IF(OR($E68="",K$1=""),"",IF(TRIM(LEFT($E68,MIN(IFERROR(FIND("CDU",UPPER($E68)),999),IFERROR(FIND("BULK",UPPER($E68)),999),IFERROR(FIND("-",$E68),999),IFERROR(FIND("（",$E68),999))-1))=K$1,$F68,"")) | L68: =IF(OR($E68="",L$1=""),"",IF(TRIM(LEFT($E68,MIN(IFERROR(FIND("CDU",UPPER($E68)),999),IFERROR(FIND("BULK",UPPER($E68)),999),IFERROR(FIND("-",$E68),999),IFERROR(FIND("（",$E68),999))-1))=L$1,$F68,"")) | M68: =IF(OR($E68="",M$1=""),"",IF(TRIM(LEFT($E68,MIN(IFERROR(FIND("CDU",UPPER($E68)),999),IFERROR(FIND("BULK",UPPER($E68)),999),IFERROR(FIND("-",$E68),999),IFERROR(FIND("（",$E68),999))-1))=M$1,$F68,"")) | N68: =IF(OR($E68="",N$1=""),"",IF(TRIM(LEFT($E68,MIN(IFERROR(FIND("CDU",UPPER($E68)),999),IFERROR(FIND("BULK",UPPER($E68)),999),IFERROR(FIND("-",$E68),999),IFERROR(FIND("（",$E68),999))-1))=N$1,$F68,"")) | O68: =IF(OR($E68="",O$1=""),"",IF(TRIM(LEFT($E68,MIN(IFERROR(FIND("CDU",UPPER($E68)),999),IFERROR(FIND("BULK",UPPER($E68)),999),IFERROR(FIND("-",$E68),999),IFERROR(FIND("（",$E68),999))-1))=O$1,$F68,"")) | P68: =IF(OR($E68="",P$1=""),"",IF(TRIM(LEFT($E68,MIN(IFERROR(FIND("CDU",UPPER($E68)),999),IFERROR(FIND("BULK",UPPER($E68)),999),IFERROR(FIND("-",$E68),999),IFERROR(FIND("（",$E68),999))-1))=P$1,$F68,"")) | ... BU68: =IF(OR($E68="",BU$1=""),"",IF(TRIM(LEFT($E68,MIN(IFERROR(FIND("CDU",UPPER($E68)),999),IFERROR(FIND("BULK",UPPER($E68)),999),IFERROR(FIND("-",$E68),999),IFERROR(FIND("（",$E68),999))-1))=BU$1,$F68,"")) | BV68: 0.6 | BW68: =SUM(I68:BU68)*BV68 -> 3601.8 | BX68: =BW68*7.75 -> 27913.95 | BY68: =MID(E68,1,2) -> JS
A69: 45995 | B69: 46045 | C69: PL252474-01 | D69: PO0000049-UKCO | E69: SR102CDU-24 | F69: 18000 | G69: TOY客版 | H69: =IFERROR(VLOOKUP(E69,名称!A:E,4,0),"") -> 二代 | I69: =IF(OR($E69="",I$1=""),"",IF(TRIM(LEFT($E69,MIN(IFERROR(FIND("CDU",UPPER($E69)),999),IFERROR(FIND("BULK",UPPER($E69)),999),IFERROR(FIND("-",$E69),999),IFERROR(FIND("（",$E69),999))-1))=I$1,$F69,"")) | J69: =IF(OR($E69="",J$1=""),"",IF(TRIM(LEFT($E69,MIN(IFERROR(FIND("CDU",UPPER($E69)),999),IFERROR(FIND("BULK",UPPER($E69)),999),IFERROR(FIND("-",$E69),999),IFERROR(FIND("（",$E69),999))-1))=J$1,$F69,"")) | K69: =IF(OR($E69="",K$1=""),"",IF(TRIM(LEFT($E69,MIN(IFERROR(FIND("CDU",UPPER($E69)),999),IFERROR(FIND("BULK",UPPER($E69)),999),IFERROR(FIND("-",$E69),999),IFERROR(FIND("（",$E69),999))-1))=K$1,$F69,"")) -> 18000 | L69: =IF(OR($E69="",L$1=""),"",IF(TRIM(LEFT($E69,MIN(IFERROR(FIND("CDU",UPPER($E69)),999),IFERROR(FIND("BULK",UPPER($E69)),999),IFERROR(FIND("-",$E69),999),IFERROR(FIND("（",$E69),999))-1))=L$1,$F69,"")) | M69: =IF(OR($E69="",M$1=""),"",IF(TRIM(LEFT($E69,MIN(IFERROR(FIND("CDU",UPPER($E69)),999),IFERROR(FIND("BULK",UPPER($E69)),999),IFERROR(FIND("-",$E69),999),IFERROR(FIND("（",$E69),999))-1))=M$1,$F69,"")) | N69: =IF(OR($E69="",N$1=""),"",IF(TRIM(LEFT($E69,MIN(IFERROR(FIND("CDU",UPPER($E69)),999),IFERROR(FIND("BULK",UPPER($E69)),999),IFERROR(FIND("-",$E69),999),IFERROR(FIND("（",$E69),999))-1))=N$1,$F69,"")) | O69: =IF(OR($E69="",O$1=""),"",IF(TRIM(LEFT($E69,MIN(IFERROR(FIND("CDU",UPPER($E69)),999),IFERROR(FIND("BULK",UPPER($E69)),999),IFERROR(FIND("-",$E69),999),IFERROR(FIND("（",$E69),999))-1))=O$1,$F69,"")) | P69: =IF(OR($E69="",P$1=""),"",IF(TRIM(LEFT($E69,MIN(IFERROR(FIND("CDU",UPPER($E69)),999),IFERROR(FIND("BULK",UPPER($E69)),999),IFERROR(FIND("-",$E69),999),IFERROR(FIND("（",$E69),999))-1))=P$1,$F69,"")) | ... BU69: =IF(OR($E69="",BU$1=""),"",IF(TRIM(LEFT($E69,MIN(IFERROR(FIND("CDU",UPPER($E69)),999),IFERROR(FIND("BULK",UPPER($E69)),999),IFERROR(FIND("-",$E69),999),IFERROR(FIND("（",$E69),999))-1))=BU$1,$F69,"")) | BV69: 0.85 | BW69: =SUM(I69:BU69)*BV69 -> 15300 | BX69: =BW69*7.75 -> 118575 | BY69: =MID(E69,1,2) -> SR
A70: 45995 | B70: 46045 | C70: PL252474-01 | D70: PO0000049-UKCO | E70: SR201 | F70: 18000 | G70: TOY客版 | H70: =IFERROR(VLOOKUP(E70,名称!A:E,4,0),"") -> 二代 | I70: =IF(OR($E70="",I$1=""),"",IF(TRIM(LEFT($E70,MIN(IFERROR(FIND("CDU",UPPER($E70)),999),IFERROR(FIND("BULK",UPPER($E70)),999),IFERROR(FIND("-",$E70),999),IFERROR(FIND("（",$E70),999))-1))=I$1,$F70,"")) | J70: =IF(OR($E70="",J$1=""),"",IF(TRIM(LEFT($E70,MIN(IFERROR(FIND("CDU",UPPER($E70)),999),IFERROR(FIND("BULK",UPPER($E70)),999),IFERROR(FIND("-",$E70),999),IFERROR(FIND("（",$E70),999))-1))=J$1,$F70,"")) | K70: =IF(OR($E70="",K$1=""),"",IF(TRIM(LEFT($E70,MIN(IFERROR(FIND("CDU",UPPER($E70)),999),IFERROR(FIND("BULK",UPPER($E70)),999),IFERROR(FIND("-",$E70),999),IFERROR(FIND("（",$E70),999))-1))=K$1,$F70,"")) | L70: =IF(OR($E70="",L$1=""),"",IF(TRIM(LEFT($E70,MIN(IFERROR(FIND("CDU",UPPER($E70)),999),IFERROR(FIND("BULK",UPPER($E70)),999),IFERROR(FIND("-",$E70),999),IFERROR(FIND("（",$E70),999))-1))=L$1,$F70,"")) | M70: =IF(OR($E70="",M$1=""),"",IF(TRIM(LEFT($E70,MIN(IFERROR(FIND("CDU",UPPER($E70)),999),IFERROR(FIND("BULK",UPPER($E70)),999),IFERROR(FIND("-",$E70),999),IFERROR(FIND("（",$E70),999))-1))=M$1,$F70,"")) | N70: =IF(OR($E70="",N$1=""),"",IF(TRIM(LEFT($E70,MIN(IFERROR(FIND("CDU",UPPER($E70)),999),IFERROR(FIND("BULK",UPPER($E70)),999),IFERROR(FIND("-",$E70),999),IFERROR(FIND("（",$E70),999))-1))=N$1,$F70,"")) | O70: =IF(OR($E70="",O$1=""),"",IF(TRIM(LEFT($E70,MIN(IFERROR(FIND("CDU",UPPER($E70)),999),IFERROR(FIND("BULK",UPPER($E70)),999),IFERROR(FIND("-",$E70),999),IFERROR(FIND("（",$E70),999))-1))=O$1,$F70,"")) | P70: =IF(OR($E70="",P$1=""),"",IF(TRIM(LEFT($E70,MIN(IFERROR(FIND("CDU",UPPER($E70)),999),IFERROR(FIND("BULK",UPPER($E70)),999),IFERROR(FIND("-",$E70),999),IFERROR(FIND("（",$E70),999))-1))=P$1,$F70,"")) | ... BU70: =IF(OR($E70="",BU$1=""),"",IF(TRIM(LEFT($E70,MIN(IFERROR(FIND("CDU",UPPER($E70)),999),IFERROR(FIND("BULK",UPPER($E70)),999),IFERROR(FIND("-",$E70),999),IFERROR(FIND("（",$E70),999))-1))=BU$1,$F70,"")) | BV70: 2.02 | BW70: =SUM(I70:BU70)*BV70 -> 36360 | BX70: =BW70*7.75 -> 281790 | BY70: =MID(E70,1,2) -> SR
A71: 45995 | B71: 46045 | C71: PL252474-01 | D71: PO0000049-UKCO | E71: SR301 | F71: 5000 | G71: TOY客版 | H71: =IFERROR(VLOOKUP(E71,名称!A:E,4,0),"") -> 二代 | I71: =IF(OR($E71="",I$1=""),"",IF(TRIM(LEFT($E71,MIN(IFERROR(FIND("CDU",UPPER($E71)),999),IFERROR(FIND("BULK",UPPER($E71)),999),IFERROR(FIND("-",$E71),999),IFERROR(FIND("（",$E71),999))-1))=I$1,$F71,"")) | J71: =IF(OR($E71="",J$1=""),"",IF(TRIM(LEFT($E71,MIN(IFERROR(FIND("CDU",UPPER($E71)),999),IFERROR(FIND("BULK",UPPER($E71)),999),IFERROR(FIND("-",$E71),999),IFERROR(FIND("（",$E71),999))-1))=J$1,$F71,"")) | K71: =IF(OR($E71="",K$1=""),"",IF(TRIM(LEFT($E71,MIN(IFERROR(FIND("CDU",UPPER($E71)),999),IFERROR(FIND("BULK",UPPER($E71)),999),IFERROR(FIND("-",$E71),999),IFERROR(FIND("（",$E71),999))-1))=K$1,$F71,"")) | L71: =IF(OR($E71="",L$1=""),"",IF(TRIM(LEFT($E71,MIN(IFERROR(FIND("CDU",UPPER($E71)),999),IFERROR(FIND("BULK",UPPER($E71)),999),IFERROR(FIND("-",$E71),999),IFERROR(FIND("（",$E71),999))-1))=L$1,$F71,"")) | M71: =IF(OR($E71="",M$1=""),"",IF(TRIM(LEFT($E71,MIN(IFERROR(FIND("CDU",UPPER($E71)),999),IFERROR(FIND("BULK",UPPER($E71)),999),IFERROR(FIND("-",$E71),999),IFERROR(FIND("（",$E71),999))-1))=M$1,$F71,"")) | N71: =IF(OR($E71="",N$1=""),"",IF(TRIM(LEFT($E71,MIN(IFERROR(FIND("CDU",UPPER($E71)),999),IFERROR(FIND("BULK",UPPER($E71)),999),IFERROR(FIND("-",$E71),999),IFERROR(FIND("（",$E71),999))-1))=N$1,$F71,"")) | O71: =IF(OR($E71="",O$1=""),"",IF(TRIM(LEFT($E71,MIN(IFERROR(FIND("CDU",UPPER($E71)),999),IFERROR(FIND("BULK",UPPER($E71)),999),IFERROR(FIND("-",$E71),999),IFERROR(FIND("（",$E71),999))-1))=O$1,$F71,"")) | P71: =IF(OR($E71="",P$1=""),"",IF(TRIM(LEFT($E71,MIN(IFERROR(FIND("CDU",UPPER($E71)),999),IFERROR(FIND("BULK",UPPER($E71)),999),IFERROR(FIND("-",$E71),999),IFERROR(FIND("（",$E71),999))-1))=P$1,$F71,"")) | ... BU71: =IF(OR($E71="",BU$1=""),"",IF(TRIM(LEFT($E71,MIN(IFERROR(FIND("CDU",UPPER($E71)),999),IFERROR(FIND("BULK",UPPER($E71)),999),IFERROR(FIND("-",$E71),999),IFERROR(FIND("（",$E71),999))-1))=BU$1,$F71,"")) | BV71: 3.09 | BW71: =SUM(I71:BU71)*BV71 -> 15450 | BX71: =BW71*7.75 -> 119737.5 | BY71: =MID(E71,1,2) -> SR
A72: 45995 | B72: 46045 | C72: PL252474-01 | D72: PO0000049-UKCO | E72: SR460CDU-6 | F72: 10002 | G72: TOY客版 | H72: =IFERROR(VLOOKUP(E72,名称!A:E,4,0),"") -> 二代 | I72: =IF(OR($E72="",I$1=""),"",IF(TRIM(LEFT($E72,MIN(IFERROR(FIND("CDU",UPPER($E72)),999),IFERROR(FIND("BULK",UPPER($E72)),999),IFERROR(FIND("-",$E72),999),IFERROR(FIND("（",$E72),999))-1))=I$1,$F72,"")) | J72: =IF(OR($E72="",J$1=""),"",IF(TRIM(LEFT($E72,MIN(IFERROR(FIND("CDU",UPPER($E72)),999),IFERROR(FIND("BULK",UPPER($E72)),999),IFERROR(FIND("-",$E72),999),IFERROR(FIND("（",$E72),999))-1))=J$1,$F72,"")) | K72: =IF(OR($E72="",K$1=""),"",IF(TRIM(LEFT($E72,MIN(IFERROR(FIND("CDU",UPPER($E72)),999),IFERROR(FIND("BULK",UPPER($E72)),999),IFERROR(FIND("-",$E72),999),IFERROR(FIND("（",$E72),999))-1))=K$1,$F72,"")) | L72: =IF(OR($E72="",L$1=""),"",IF(TRIM(LEFT($E72,MIN(IFERROR(FIND("CDU",UPPER($E72)),999),IFERROR(FIND("BULK",UPPER($E72)),999),IFERROR(FIND("-",$E72),999),IFERROR(FIND("（",$E72),999))-1))=L$1,$F72,"")) | M72: =IF(OR($E72="",M$1=""),"",IF(TRIM(LEFT($E72,MIN(IFERROR(FIND("CDU",UPPER($E72)),999),IFERROR(FIND("BULK",UPPER($E72)),999),IFERROR(FIND("-",$E72),999),IFERROR(FIND("（",$E72),999))-1))=M$1,$F72,"")) | N72: =IF(OR($E72="",N$1=""),"",IF(TRIM(LEFT($E72,MIN(IFERROR(FIND("CDU",UPPER($E72)),999),IFERROR(FIND("BULK",UPPER($E72)),999),IFERROR(FIND("-",$E72),999),IFERROR(FIND("（",$E72),999))-1))=N$1,$F72,"")) | O72: =IF(OR($E72="",O$1=""),"",IF(TRIM(LEFT($E72,MIN(IFERROR(FIND("CDU",UPPER($E72)),999),IFERROR(FIND("BULK",UPPER($E72)),999),IFERROR(FIND("-",$E72),999),IFERROR(FIND("（",$E72),999))-1))=O$1,$F72,"")) | P72: =IF(OR($E72="",P$1=""),"",IF(TRIM(LEFT($E72,MIN(IFERROR(FIND("CDU",UPPER($E72)),999),IFERROR(FIND("BULK",UPPER($E72)),999),IFERROR(FIND("-",$E72),999),IFERROR(FIND("（",$E72),999))-1))=P$1,$F72,"")) | ... BU72: =IF(OR($E72="",BU$1=""),"",IF(TRIM(LEFT($E72,MIN(IFERROR(FIND("CDU",UPPER($E72)),999),IFERROR(FIND("BULK",UPPER($E72)),999),IFERROR(FIND("-",$E72),999),IFERROR(FIND("（",$E72),999))-1))=BU$1,$F72,"")) | BV72: 1.52 | BW72: =SUM(I72:BU72)*BV72 -> 15203.04 | BX72: =BW72*7.75 -> 117823.56 | BY72: =MID(E72,1,2) -> SR
A73: 45995 | B73: 46045 | C73: PL252474-01 | D73: PO0000049-UKCO | E73: SR600CDU-6 | F73: 9000 | G73: TOY客版 | H73: =IFERROR(VLOOKUP(E73,名称!A:E,4,0),"") -> 二代 | I73: =IF(OR($E73="",I$1=""),"",IF(TRIM(LEFT($E73,MIN(IFERROR(FIND("CDU",UPPER($E73)),999),IFERROR(FIND("BULK",UPPER($E73)),999),IFERROR(FIND("-",$E73),999),IFERROR(FIND("（",$E73),999))-1))=I$1,$F73,"")) | J73: =IF(OR($E73="",J$1=""),"",IF(TRIM(LEFT($E73,MIN(IFERROR(FIND("CDU",UPPER($E73)),999),IFERROR(FIND("BULK",UPPER($E73)),999),IFERROR(FIND("-",$E73),999),IFERROR(FIND("（",$E73),999))-1))=J$1,$F73,"")) | K73: =IF(OR($E73="",K$1=""),"",IF(TRIM(LEFT($E73,MIN(IFERROR(FIND("CDU",UPPER($E73)),999),IFERROR(FIND("BULK",UPPER($E73)),999),IFERROR(FIND("-",$E73),999),IFERROR(FIND("（",$E73),999))-1))=K$1,$F73,"")) | L73: =IF(OR($E73="",L$1=""),"",IF(TRIM(LEFT($E73,MIN(IFERROR(FIND("CDU",UPPER($E73)),999),IFERROR(FIND("BULK",UPPER($E73)),999),IFERROR(FIND("-",$E73),999),IFERROR(FIND("（",$E73),999))-1))=L$1,$F73,"")) | M73: =IF(OR($E73="",M$1=""),"",IF(TRIM(LEFT($E73,MIN(IFERROR(FIND("CDU",UPPER($E73)),999),IFERROR(FIND("BULK",UPPER($E73)),999),IFERROR(FIND("-",$E73),999),IFERROR(FIND("（",$E73),999))-1))=M$1,$F73,"")) | N73: =IF(OR($E73="",N$1=""),"",IF(TRIM(LEFT($E73,MIN(IFERROR(FIND("CDU",UPPER($E73)),999),IFERROR(FIND("BULK",UPPER($E73)),999),IFERROR(FIND("-",$E73),999),IFERROR(FIND("（",$E73),999))-1))=N$1,$F73,"")) | O73: =IF(OR($E73="",O$1=""),"",IF(TRIM(LEFT($E73,MIN(IFERROR(FIND("CDU",UPPER($E73)),999),IFERROR(FIND("BULK",UPPER($E73)),999),IFERROR(FIND("-",$E73),999),IFERROR(FIND("（",$E73),999))-1))=O$1,$F73,"")) | P73: =IF(OR($E73="",P$1=""),"",IF(TRIM(LEFT($E73,MIN(IFERROR(FIND("CDU",UPPER($E73)),999),IFERROR(FIND("BULK",UPPER($E73)),999),IFERROR(FIND("-",$E73),999),IFERROR(FIND("（",$E73),999))-1))=P$1,$F73,"")) | ... BU73: =IF(OR($E73="",BU$1=""),"",IF(TRIM(LEFT($E73,MIN(IFERROR(FIND("CDU",UPPER($E73)),999),IFERROR(FIND("BULK",UPPER($E73)),999),IFERROR(FIND("-",$E73),999),IFERROR(FIND("（",$E73),999))-1))=BU$1,$F73,"")) | BV73: 1.49 | BW73: =SUM(I73:BU73)*BV73 -> 13410 | BX73: =BW73*7.75 -> 103927.5 | BY73: =MID(E73,1,2) -> SR
A74: 45996 | B74: 46045 | D74: PO-USSC045 | E74: SR102-F-EC | F74: 3312 | G74: 密封盒彩盒包装 | H74: =IFERROR(VLOOKUP(E74,名称!A:E,4,0),"") -> 二代 | I74: =IF(OR($E74="",I$1=""),"",IF(TRIM(LEFT($E74,MIN(IFERROR(FIND("CDU",UPPER($E74)),999),IFERROR(FIND("BULK",UPPER($E74)),999),IFERROR(FIND("-",$E74),999),IFERROR(FIND("（",$E74),999))-1))=I$1,$F74,"")) | J74: =IF(OR($E74="",J$1=""),"",IF(TRIM(LEFT($E74,MIN(IFERROR(FIND("CDU",UPPER($E74)),999),IFERROR(FIND("BULK",UPPER($E74)),999),IFERROR(FIND("-",$E74),999),IFERROR(FIND("（",$E74),999))-1))=J$1,$F74,"")) | K74: =IF(OR($E74="",K$1=""),"",IF(TRIM(LEFT($E74,MIN(IFERROR(FIND("CDU",UPPER($E74)),999),IFERROR(FIND("BULK",UPPER($E74)),999),IFERROR(FIND("-",$E74),999),IFERROR(FIND("（",$E74),999))-1))=K$1,$F74,"")) -> 3312 | L74: =IF(OR($E74="",L$1=""),"",IF(TRIM(LEFT($E74,MIN(IFERROR(FIND("CDU",UPPER($E74)),999),IFERROR(FIND("BULK",UPPER($E74)),999),IFERROR(FIND("-",$E74),999),IFERROR(FIND("（",$E74),999))-1))=L$1,$F74,"")) | M74: =IF(OR($E74="",M$1=""),"",IF(TRIM(LEFT($E74,MIN(IFERROR(FIND("CDU",UPPER($E74)),999),IFERROR(FIND("BULK",UPPER($E74)),999),IFERROR(FIND("-",$E74),999),IFERROR(FIND("（",$E74),999))-1))=M$1,$F74,"")) | N74: =IF(OR($E74="",N$1=""),"",IF(TRIM(LEFT($E74,MIN(IFERROR(FIND("CDU",UPPER($E74)),999),IFERROR(FIND("BULK",UPPER($E74)),999),IFERROR(FIND("-",$E74),999),IFERROR(FIND("（",$E74),999))-1))=N$1,$F74,"")) | O74: =IF(OR($E74="",O$1=""),"",IF(TRIM(LEFT($E74,MIN(IFERROR(FIND("CDU",UPPER($E74)),999),IFERROR(FIND("BULK",UPPER($E74)),999),IFERROR(FIND("-",$E74),999),IFERROR(FIND("（",$E74),999))-1))=O$1,$F74,"")) | P74: =IF(OR($E74="",P$1=""),"",IF(TRIM(LEFT($E74,MIN(IFERROR(FIND("CDU",UPPER($E74)),999),IFERROR(FIND("BULK",UPPER($E74)),999),IFERROR(FIND("-",$E74),999),IFERROR(FIND("（",$E74),999))-1))=P$1,$F74,"")) | ... BU74: =IF(OR($E74="",BU$1=""),"",IF(TRIM(LEFT($E74,MIN(IFERROR(FIND("CDU",UPPER($E74)),999),IFERROR(FIND("BULK",UPPER($E74)),999),IFERROR(FIND("-",$E74),999),IFERROR(FIND("（",$E74),999))-1))=BU$1,$F74,"")) | BV74: 0.63 | BW74: =SUM(I74:BU74)*BV74 -> 2086.56 | BX74: =BW74*7.75 -> 16170.84 | BY74: =MID(E74,1,2) -> SR
A75: 45996 | B75: 46045 | D75: PO-USSC045 | E75: SR430-ECOMM-C1 | F75: 4416 | G75: 密封盒彩盒包装 | H75: =IFERROR(VLOOKUP(E75,名称!A:E,4,0),"") -> 二代 | I75: =IF(OR($E75="",I$1=""),"",IF(TRIM(LEFT($E75,MIN(IFERROR(FIND("CDU",UPPER($E75)),999),IFERROR(FIND("BULK",UPPER($E75)),999),IFERROR(FIND("-",$E75),999),IFERROR(FIND("（",$E75),999))-1))=I$1,$F75,"")) | J75: =IF(OR($E75="",J$1=""),"",IF(TRIM(LEFT($E75,MIN(IFERROR(FIND("CDU",UPPER($E75)),999),IFERROR(FIND("BULK",UPPER($E75)),999),IFERROR(FIND("-",$E75),999),IFERROR(FIND("（",$E75),999))-1))=J$1,$F75,"")) | K75: =IF(OR($E75="",K$1=""),"",IF(TRIM(LEFT($E75,MIN(IFERROR(FIND("CDU",UPPER($E75)),999),IFERROR(FIND("BULK",UPPER($E75)),999),IFERROR(FIND("-",$E75),999),IFERROR(FIND("（",$E75),999))-1))=K$1,$F75,"")) | L75: =IF(OR($E75="",L$1=""),"",IF(TRIM(LEFT($E75,MIN(IFERROR(FIND("CDU",UPPER($E75)),999),IFERROR(FIND("BULK",UPPER($E75)),999),IFERROR(FIND("-",$E75),999),IFERROR(FIND("（",$E75),999))-1))=L$1,$F75,"")) | M75: =IF(OR($E75="",M$1=""),"",IF(TRIM(LEFT($E75,MIN(IFERROR(FIND("CDU",UPPER($E75)),999),IFERROR(FIND("BULK",UPPER($E75)),999),IFERROR(FIND("-",$E75),999),IFERROR(FIND("（",$E75),999))-1))=M$1,$F75,"")) | N75: =IF(OR($E75="",N$1=""),"",IF(TRIM(LEFT($E75,MIN(IFERROR(FIND("CDU",UPPER($E75)),999),IFERROR(FIND("BULK",UPPER($E75)),999),IFERROR(FIND("-",$E75),999),IFERROR(FIND("（",$E75),999))-1))=N$1,$F75,"")) | O75: =IF(OR($E75="",O$1=""),"",IF(TRIM(LEFT($E75,MIN(IFERROR(FIND("CDU",UPPER($E75)),999),IFERROR(FIND("BULK",UPPER($E75)),999),IFERROR(FIND("-",$E75),999),IFERROR(FIND("（",$E75),999))-1))=O$1,$F75,"")) | P75: =IF(OR($E75="",P$1=""),"",IF(TRIM(LEFT($E75,MIN(IFERROR(FIND("CDU",UPPER($E75)),999),IFERROR(FIND("BULK",UPPER($E75)),999),IFERROR(FIND("-",$E75),999),IFERROR(FIND("（",$E75),999))-1))=P$1,$F75,"")) | ... BU75: =IF(OR($E75="",BU$1=""),"",IF(TRIM(LEFT($E75,MIN(IFERROR(FIND("CDU",UPPER($E75)),999),IFERROR(FIND("BULK",UPPER($E75)),999),IFERROR(FIND("-",$E75),999),IFERROR(FIND("（",$E75),999))-1))=BU$1,$F75,"")) | BV75: 1.27 | BW75: =SUM(I75:BU75)*BV75 -> 5608.32 | BX75: =BW75*7.75 -> 43464.48 | BY75: =MID(E75,1,2) -> SR
A76: 45996 | B76: 46045 | D76: PO-USSC045 | E76: SR430-ECOMM-C2 | F76: 3360 | G76: 密封盒彩盒包装 | H76: =IFERROR(VLOOKUP(E76,名称!A:E,4,0),"") -> 二代 | I76: =IF(OR($E76="",I$1=""),"",IF(TRIM(LEFT($E76,MIN(IFERROR(FIND("CDU",UPPER($E76)),999),IFERROR(FIND("BULK",UPPER($E76)),999),IFERROR(FIND("-",$E76),999),IFERROR(FIND("（",$E76),999))-1))=I$1,$F76,"")) | J76: =IF(OR($E76="",J$1=""),"",IF(TRIM(LEFT($E76,MIN(IFERROR(FIND("CDU",UPPER($E76)),999),IFERROR(FIND("BULK",UPPER($E76)),999),IFERROR(FIND("-",$E76),999),IFERROR(FIND("（",$E76),999))-1))=J$1,$F76,"")) | K76: =IF(OR($E76="",K$1=""),"",IF(TRIM(LEFT($E76,MIN(IFERROR(FIND("CDU",UPPER($E76)),999),IFERROR(FIND("BULK",UPPER($E76)),999),IFERROR(FIND("-",$E76),999),IFERROR(FIND("（",$E76),999))-1))=K$1,$F76,"")) | L76: =IF(OR($E76="",L$1=""),"",IF(TRIM(LEFT($E76,MIN(IFERROR(FIND("CDU",UPPER($E76)),999),IFERROR(FIND("BULK",UPPER($E76)),999),IFERROR(FIND("-",$E76),999),IFERROR(FIND("（",$E76),999))-1))=L$1,$F76,"")) | M76: =IF(OR($E76="",M$1=""),"",IF(TRIM(LEFT($E76,MIN(IFERROR(FIND("CDU",UPPER($E76)),999),IFERROR(FIND("BULK",UPPER($E76)),999),IFERROR(FIND("-",$E76),999),IFERROR(FIND("（",$E76),999))-1))=M$1,$F76,"")) | N76: =IF(OR($E76="",N$1=""),"",IF(TRIM(LEFT($E76,MIN(IFERROR(FIND("CDU",UPPER($E76)),999),IFERROR(FIND("BULK",UPPER($E76)),999),IFERROR(FIND("-",$E76),999),IFERROR(FIND("（",$E76),999))-1))=N$1,$F76,"")) | O76: =IF(OR($E76="",O$1=""),"",IF(TRIM(LEFT($E76,MIN(IFERROR(FIND("CDU",UPPER($E76)),999),IFERROR(FIND("BULK",UPPER($E76)),999),IFERROR(FIND("-",$E76),999),IFERROR(FIND("（",$E76),999))-1))=O$1,$F76,"")) | P76: =IF(OR($E76="",P$1=""),"",IF(TRIM(LEFT($E76,MIN(IFERROR(FIND("CDU",UPPER($E76)),999),IFERROR(FIND("BULK",UPPER($E76)),999),IFERROR(FIND("-",$E76),999),IFERROR(FIND("（",$E76),999))-1))=P$1,$F76,"")) | ... BU76: =IF(OR($E76="",BU$1=""),"",IF(TRIM(LEFT($E76,MIN(IFERROR(FIND("CDU",UPPER($E76)),999),IFERROR(FIND("BULK",UPPER($E76)),999),IFERROR(FIND("-",$E76),999),IFERROR(FIND("（",$E76),999))-1))=BU$1,$F76,"")) | BV76: 1.27 | BW76: =SUM(I76:BU76)*BV76 -> 4267.2 | BX76: =BW76*7.75 -> 33070.8 | BY76: =MID(E76,1,2) -> SR
A77: 45996 | B77: 46045 | D77: PO-USSC045 | E77: SR430-ECOMM-C3 | F77: 3360 | G77: 密封盒彩盒包装 | H77: =IFERROR(VLOOKUP(E77,名称!A:E,4,0),"") -> 二代 | I77: =IF(OR($E77="",I$1=""),"",IF(TRIM(LEFT($E77,MIN(IFERROR(FIND("CDU",UPPER($E77)),999),IFERROR(FIND("BULK",UPPER($E77)),999),IFERROR(FIND("-",$E77),999),IFERROR(FIND("（",$E77),999))-1))=I$1,$F77,"")) | J77: =IF(OR($E77="",J$1=""),"",IF(TRIM(LEFT($E77,MIN(IFERROR(FIND("CDU",UPPER($E77)),999),IFERROR(FIND("BULK",UPPER($E77)),999),IFERROR(FIND("-",$E77),999),IFERROR(FIND("（",$E77),999))-1))=J$1,$F77,"")) | K77: =IF(OR($E77="",K$1=""),"",IF(TRIM(LEFT($E77,MIN(IFERROR(FIND("CDU",UPPER($E77)),999),IFERROR(FIND("BULK",UPPER($E77)),999),IFERROR(FIND("-",$E77),999),IFERROR(FIND("（",$E77),999))-1))=K$1,$F77,"")) | L77: =IF(OR($E77="",L$1=""),"",IF(TRIM(LEFT($E77,MIN(IFERROR(FIND("CDU",UPPER($E77)),999),IFERROR(FIND("BULK",UPPER($E77)),999),IFERROR(FIND("-",$E77),999),IFERROR(FIND("（",$E77),999))-1))=L$1,$F77,"")) | M77: =IF(OR($E77="",M$1=""),"",IF(TRIM(LEFT($E77,MIN(IFERROR(FIND("CDU",UPPER($E77)),999),IFERROR(FIND("BULK",UPPER($E77)),999),IFERROR(FIND("-",$E77),999),IFERROR(FIND("（",$E77),999))-1))=M$1,$F77,"")) | N77: =IF(OR($E77="",N$1=""),"",IF(TRIM(LEFT($E77,MIN(IFERROR(FIND("CDU",UPPER($E77)),999),IFERROR(FIND("BULK",UPPER($E77)),999),IFERROR(FIND("-",$E77),999),IFERROR(FIND("（",$E77),999))-1))=N$1,$F77,"")) | O77: =IF(OR($E77="",O$1=""),"",IF(TRIM(LEFT($E77,MIN(IFERROR(FIND("CDU",UPPER($E77)),999),IFERROR(FIND("BULK",UPPER($E77)),999),IFERROR(FIND("-",$E77),999),IFERROR(FIND("（",$E77),999))-1))=O$1,$F77,"")) | P77: =IF(OR($E77="",P$1=""),"",IF(TRIM(LEFT($E77,MIN(IFERROR(FIND("CDU",UPPER($E77)),999),IFERROR(FIND("BULK",UPPER($E77)),999),IFERROR(FIND("-",$E77),999),IFERROR(FIND("（",$E77),999))-1))=P$1,$F77,"")) | ... BU77: =IF(OR($E77="",BU$1=""),"",IF(TRIM(LEFT($E77,MIN(IFERROR(FIND("CDU",UPPER($E77)),999),IFERROR(FIND("BULK",UPPER($E77)),999),IFERROR(FIND("-",$E77),999),IFERROR(FIND("（",$E77),999))-1))=BU$1,$F77,"")) | BV77: 1.27 | BW77: =SUM(I77:BU77)*BV77 -> 4267.2 | BX77: =BW77*7.75 -> 33070.8 | BY77: =MID(E77,1,2) -> SR
A78: 45996 | B78: 46045 | D78: PO-USSC045 | E78: SR460-EC | F78: 4512 | G78: 密封盒彩盒包装 | H78: =IFERROR(VLOOKUP(E78,名称!A:E,4,0),"") -> 二代 | I78: =IF(OR($E78="",I$1=""),"",IF(TRIM(LEFT($E78,MIN(IFERROR(FIND("CDU",UPPER($E78)),999),IFERROR(FIND("BULK",UPPER($E78)),999),IFERROR(FIND("-",$E78),999),IFERROR(FIND("（",$E78),999))-1))=I$1,$F78,"")) | J78: =IF(OR($E78="",J$1=""),"",IF(TRIM(LEFT($E78,MIN(IFERROR(FIND("CDU",UPPER($E78)),999),IFERROR(FIND("BULK",UPPER($E78)),999),IFERROR(FIND("-",$E78),999),IFERROR(FIND("（",$E78),999))-1))=J$1,$F78,"")) | K78: =IF(OR($E78="",K$1=""),"",IF(TRIM(LEFT($E78,MIN(IFERROR(FIND("CDU",UPPER($E78)),999),IFERROR(FIND("BULK",UPPER($E78)),999),IFERROR(FIND("-",$E78),999),IFERROR(FIND("（",$E78),999))-1))=K$1,$F78,"")) | L78: =IF(OR($E78="",L$1=""),"",IF(TRIM(LEFT($E78,MIN(IFERROR(FIND("CDU",UPPER($E78)),999),IFERROR(FIND("BULK",UPPER($E78)),999),IFERROR(FIND("-",$E78),999),IFERROR(FIND("（",$E78),999))-1))=L$1,$F78,"")) | M78: =IF(OR($E78="",M$1=""),"",IF(TRIM(LEFT($E78,MIN(IFERROR(FIND("CDU",UPPER($E78)),999),IFERROR(FIND("BULK",UPPER($E78)),999),IFERROR(FIND("-",$E78),999),IFERROR(FIND("（",$E78),999))-1))=M$1,$F78,"")) | N78: =IF(OR($E78="",N$1=""),"",IF(TRIM(LEFT($E78,MIN(IFERROR(FIND("CDU",UPPER($E78)),999),IFERROR(FIND("BULK",UPPER($E78)),999),IFERROR(FIND("-",$E78),999),IFERROR(FIND("（",$E78),999))-1))=N$1,$F78,"")) | O78: =IF(OR($E78="",O$1=""),"",IF(TRIM(LEFT($E78,MIN(IFERROR(FIND("CDU",UPPER($E78)),999),IFERROR(FIND("BULK",UPPER($E78)),999),IFERROR(FIND("-",$E78),999),IFERROR(FIND("（",$E78),999))-1))=O$1,$F78,"")) | P78: =IF(OR($E78="",P$1=""),"",IF(TRIM(LEFT($E78,MIN(IFERROR(FIND("CDU",UPPER($E78)),999),IFERROR(FIND("BULK",UPPER($E78)),999),IFERROR(FIND("-",$E78),999),IFERROR(FIND("（",$E78),999))-1))=P$1,$F78,"")) | ... BU78: =IF(OR($E78="",BU$1=""),"",IF(TRIM(LEFT($E78,MIN(IFERROR(FIND("CDU",UPPER($E78)),999),IFERROR(FIND("BULK",UPPER($E78)),999),IFERROR(FIND("-",$E78),999),IFERROR(FIND("（",$E78),999))-1))=BU$1,$F78,"")) | BV78: 1.27 | BW78: =SUM(I78:BU78)*BV78 -> 5730.24 | BX78: =BW78*7.75 -> 44409.36 | BY78: =MID(E78,1,2) -> SR
A79: 46000 | B79: 46087 | C79: 8150975574 | D79: PO0000045-CAJZ | E79: SR201C-CDU-5 | F79: 3580 | G79: Jazwares客版（2L） | H79: =IFERROR(VLOOKUP(E79,名称!A:E,4,0),"") -> 二代 | I79: =IF(OR($E79="",I$1=""),"",IF(TRIM(LEFT($E79,MIN(IFERROR(FIND("CDU",UPPER($E79)),999),IFERROR(FIND("BULK",UPPER($E79)),999),IFERROR(FIND("-",$E79),999),IFERROR(FIND("（",$E79),999))-1))=I$1,$F79,"")) | J79: =IF(OR($E79="",J$1=""),"",IF(TRIM(LEFT($E79,MIN(IFERROR(FIND("CDU",UPPER($E79)),999),IFERROR(FIND("BULK",UPPER($E79)),999),IFERROR(FIND("-",$E79),999),IFERROR(FIND("（",$E79),999))-1))=J$1,$F79,"")) | K79: =IF(OR($E79="",K$1=""),"",IF(TRIM(LEFT($E79,MIN(IFERROR(FIND("CDU",UPPER($E79)),999),IFERROR(FIND("BULK",UPPER($E79)),999),IFERROR(FIND("-",$E79),999),IFERROR(FIND("（",$E79),999))-1))=K$1,$F79,"")) | L79: =IF(OR($E79="",L$1=""),"",IF(TRIM(LEFT($E79,MIN(IFERROR(FIND("CDU",UPPER($E79)),999),IFERROR(FIND("BULK",UPPER($E79)),999),IFERROR(FIND("-",$E79),999),IFERROR(FIND("（",$E79),999))-1))=L$1,$F79,"")) | M79: =IF(OR($E79="",M$1=""),"",IF(TRIM(LEFT($E79,MIN(IFERROR(FIND("CDU",UPPER($E79)),999),IFERROR(FIND("BULK",UPPER($E79)),999),IFERROR(FIND("-",$E79),999),IFERROR(FIND("（",$E79),999))-1))=M$1,$F79,"")) | N79: =IF(OR($E79="",N$1=""),"",IF(TRIM(LEFT($E79,MIN(IFERROR(FIND("CDU",UPPER($E79)),999),IFERROR(FIND("BULK",UPPER($E79)),999),IFERROR(FIND("-",$E79),999),IFERROR(FIND("（",$E79),999))-1))=N$1,$F79,"")) | O79: =IF(OR($E79="",O$1=""),"",IF(TRIM(LEFT($E79,MIN(IFERROR(FIND("CDU",UPPER($E79)),999),IFERROR(FIND("BULK",UPPER($E79)),999),IFERROR(FIND("-",$E79),999),IFERROR(FIND("（",$E79),999))-1))=O$1,$F79,"")) | P79: =IF(OR($E79="",P$1=""),"",IF(TRIM(LEFT($E79,MIN(IFERROR(FIND("CDU",UPPER($E79)),999),IFERROR(FIND("BULK",UPPER($E79)),999),IFERROR(FIND("-",$E79),999),IFERROR(FIND("（",$E79),999))-1))=P$1,$F79,"")) | ... BU79: =IF(OR($E79="",BU$1=""),"",IF(TRIM(LEFT($E79,MIN(IFERROR(FIND("CDU",UPPER($E79)),999),IFERROR(FIND("BULK",UPPER($E79)),999),IFERROR(FIND("-",$E79),999),IFERROR(FIND("（",$E79),999))-1))=BU$1,$F79,"")) | BV79: 2.29 | BW79: =SUM(I79:BU79)*BV79 -> 8198.2 | BX79: =BW79*7.75 -> 63536.05 | BY79: =MID(E79,1,2) -> SR
A80: 46000 | B80: 46087 | C80: 8150975575 | D80: PO0000052-CAJZ | E80: SR130CDU-12 | F80: 2616 | G80: Jazwares客版（2L） | H80: =IFERROR(VLOOKUP(E80,名称!A:E,4,0),"") -> 二代 | I80: =IF(OR($E80="",I$1=""),"",IF(TRIM(LEFT($E80,MIN(IFERROR(FIND("CDU",UPPER($E80)),999),IFERROR(FIND("BULK",UPPER($E80)),999),IFERROR(FIND("-",$E80),999),IFERROR(FIND("（",$E80),999))-1))=I$1,$F80,"")) | J80: =IF(OR($E80="",J$1=""),"",IF(TRIM(LEFT($E80,MIN(IFERROR(FIND("CDU",UPPER($E80)),999),IFERROR(FIND("BULK",UPPER($E80)),999),IFERROR(FIND("-",$E80),999),IFERROR(FIND("（",$E80),999))-1))=J$1,$F80,"")) | K80: =IF(OR($E80="",K$1=""),"",IF(TRIM(LEFT($E80,MIN(IFERROR(FIND("CDU",UPPER($E80)),999),IFERROR(FIND("BULK",UPPER($E80)),999),IFERROR(FIND("-",$E80),999),IFERROR(FIND("（",$E80),999))-1))=K$1,$F80,"")) | L80: =IF(OR($E80="",L$1=""),"",IF(TRIM(LEFT($E80,MIN(IFERROR(FIND("CDU",UPPER($E80)),999),IFERROR(FIND("BULK",UPPER($E80)),999),IFERROR(FIND("-",$E80),999),IFERROR(FIND("（",$E80),999))-1))=L$1,$F80,"")) | M80: =IF(OR($E80="",M$1=""),"",IF(TRIM(LEFT($E80,MIN(IFERROR(FIND("CDU",UPPER($E80)),999),IFERROR(FIND("BULK",UPPER($E80)),999),IFERROR(FIND("-",$E80),999),IFERROR(FIND("（",$E80),999))-1))=M$1,$F80,"")) | N80: =IF(OR($E80="",N$1=""),"",IF(TRIM(LEFT($E80,MIN(IFERROR(FIND("CDU",UPPER($E80)),999),IFERROR(FIND("BULK",UPPER($E80)),999),IFERROR(FIND("-",$E80),999),IFERROR(FIND("（",$E80),999))-1))=N$1,$F80,"")) -> 2616 | O80: =IF(OR($E80="",O$1=""),"",IF(TRIM(LEFT($E80,MIN(IFERROR(FIND("CDU",UPPER($E80)),999),IFERROR(FIND("BULK",UPPER($E80)),999),IFERROR(FIND("-",$E80),999),IFERROR(FIND("（",$E80),999))-1))=O$1,$F80,"")) | P80: =IF(OR($E80="",P$1=""),"",IF(TRIM(LEFT($E80,MIN(IFERROR(FIND("CDU",UPPER($E80)),999),IFERROR(FIND("BULK",UPPER($E80)),999),IFERROR(FIND("-",$E80),999),IFERROR(FIND("（",$E80),999))-1))=P$1,$F80,"")) | ... BU80: =IF(OR($E80="",BU$1=""),"",IF(TRIM(LEFT($E80,MIN(IFERROR(FIND("CDU",UPPER($E80)),999),IFERROR(FIND("BULK",UPPER($E80)),999),IFERROR(FIND("-",$E80),999),IFERROR(FIND("（",$E80),999))-1))=BU$1,$F80,"")) | BV80: 0.63 | BW80: =SUM(I80:BU80)*BV80 -> 1648.08 | BX80: =BW80*7.75 -> 12772.62 | BY80: =MID(E80,1,2) -> SR
A81: 45999 | B81: 46052 | C81: PK2025-3591R1 | D81: PO0000051-PHPP | E81: JS100CDU-24 | F81: 3120 | G81: 第二代美文版 | H81: =IFERROR(VLOOKUP(E81,名称!A:E,4,0),"") -> 二代 | I81: =IF(OR($E81="",I$1=""),"",IF(TRIM(LEFT($E81,MIN(IFERROR(FIND("CDU",UPPER($E81)),999),IFERROR(FIND("BULK",UPPER($E81)),999),IFERROR(FIND("-",$E81),999),IFERROR(FIND("（",$E81),999))-1))=I$1,$F81,"")) | J81: =IF(OR($E81="",J$1=""),"",IF(TRIM(LEFT($E81,MIN(IFERROR(FIND("CDU",UPPER($E81)),999),IFERROR(FIND("BULK",UPPER($E81)),999),IFERROR(FIND("-",$E81),999),IFERROR(FIND("（",$E81),999))-1))=J$1,$F81,"")) | K81: =IF(OR($E81="",K$1=""),"",IF(TRIM(LEFT($E81,MIN(IFERROR(FIND("CDU",UPPER($E81)),999),IFERROR(FIND("BULK",UPPER($E81)),999),IFERROR(FIND("-",$E81),999),IFERROR(FIND("（",$E81),999))-1))=K$1,$F81,"")) | L81: =IF(OR($E81="",L$1=""),"",IF(TRIM(LEFT($E81,MIN(IFERROR(FIND("CDU",UPPER($E81)),999),IFERROR(FIND("BULK",UPPER($E81)),999),IFERROR(FIND("-",$E81),999),IFERROR(FIND("（",$E81),999))-1))=L$1,$F81,"")) | M81: =IF(OR($E81="",M$1=""),"",IF(TRIM(LEFT($E81,MIN(IFERROR(FIND("CDU",UPPER($E81)),999),IFERROR(FIND("BULK",UPPER($E81)),999),IFERROR(FIND("-",$E81),999),IFERROR(FIND("（",$E81),999))-1))=M$1,$F81,"")) | N81: =IF(OR($E81="",N$1=""),"",IF(TRIM(LEFT($E81,MIN(IFERROR(FIND("CDU",UPPER($E81)),999),IFERROR(FIND("BULK",UPPER($E81)),999),IFERROR(FIND("-",$E81),999),IFERROR(FIND("（",$E81),999))-1))=N$1,$F81,"")) | O81: =IF(OR($E81="",O$1=""),"",IF(TRIM(LEFT($E81,MIN(IFERROR(FIND("CDU",UPPER($E81)),999),IFERROR(FIND("BULK",UPPER($E81)),999),IFERROR(FIND("-",$E81),999),IFERROR(FIND("（",$E81),999))-1))=O$1,$F81,"")) | P81: =IF(OR($E81="",P$1=""),"",IF(TRIM(LEFT($E81,MIN(IFERROR(FIND("CDU",UPPER($E81)),999),IFERROR(FIND("BULK",UPPER($E81)),999),IFERROR(FIND("-",$E81),999),IFERROR(FIND("（",$E81),999))-1))=P$1,$F81,"")) | ... BU81: =IF(OR($E81="",BU$1=""),"",IF(TRIM(LEFT($E81,MIN(IFERROR(FIND("CDU",UPPER($E81)),999),IFERROR(FIND("BULK",UPPER($E81)),999),IFERROR(FIND("-",$E81),999),IFERROR(FIND("（",$E81),999))-1))=BU$1,$F81,"")) | BV81: 0.61 | BW81: =SUM(I81:BU81)*BV81 -> 1903.2 | BX81: =BW81*7.75 -> 14749.8 | BY81: =MID(E81,1,2) -> JS
A82: 45999 | B82: 46052 | C82: PK2025-3591R1 | D82: PO0000051-PHPP | E82: JS300 | F82: 1560 | G82: 第二代美文版 | H82: =IFERROR(VLOOKUP(E82,名称!A:E,4,0),"") -> 二代 | I82: =IF(OR($E82="",I$1=""),"",IF(TRIM(LEFT($E82,MIN(IFERROR(FIND("CDU",UPPER($E82)),999),IFERROR(FIND("BULK",UPPER($E82)),999),IFERROR(FIND("-",$E82),999),IFERROR(FIND("（",$E82),999))-1))=I$1,$F82,"")) | J82: =IF(OR($E82="",J$1=""),"",IF(TRIM(LEFT($E82,MIN(IFERROR(FIND("CDU",UPPER($E82)),999),IFERROR(FIND("BULK",UPPER($E82)),999),IFERROR(FIND("-",$E82),999),IFERROR(FIND("（",$E82),999))-1))=J$1,$F82,"")) | K82: =IF(OR($E82="",K$1=""),"",IF(TRIM(LEFT($E82,MIN(IFERROR(FIND("CDU",UPPER($E82)),999),IFERROR(FIND("BULK",UPPER($E82)),999),IFERROR(FIND("-",$E82),999),IFERROR(FIND("（",$E82),999))-1))=K$1,$F82,"")) | L82: =IF(OR($E82="",L$1=""),"",IF(TRIM(LEFT($E82,MIN(IFERROR(FIND("CDU",UPPER($E82)),999),IFERROR(FIND("BULK",UPPER($E82)),999),IFERROR(FIND("-",$E82),999),IFERROR(FIND("（",$E82),999))-1))=L$1,$F82,"")) | M82: =IF(OR($E82="",M$1=""),"",IF(TRIM(LEFT($E82,MIN(IFERROR(FIND("CDU",UPPER($E82)),999),IFERROR(FIND("BULK",UPPER($E82)),999),IFERROR(FIND("-",$E82),999),IFERROR(FIND("（",$E82),999))-1))=M$1,$F82,"")) | N82: =IF(OR($E82="",N$1=""),"",IF(TRIM(LEFT($E82,MIN(IFERROR(FIND("CDU",UPPER($E82)),999),IFERROR(FIND("BULK",UPPER($E82)),999),IFERROR(FIND("-",$E82),999),IFERROR(FIND("（",$E82),999))-1))=N$1,$F82,"")) | O82: =IF(OR($E82="",O$1=""),"",IF(TRIM(LEFT($E82,MIN(IFERROR(FIND("CDU",UPPER($E82)),999),IFERROR(FIND("BULK",UPPER($E82)),999),IFERROR(FIND("-",$E82),999),IFERROR(FIND("（",$E82),999))-1))=O$1,$F82,"")) | P82: =IF(OR($E82="",P$1=""),"",IF(TRIM(LEFT($E82,MIN(IFERROR(FIND("CDU",UPPER($E82)),999),IFERROR(FIND("BULK",UPPER($E82)),999),IFERROR(FIND("-",$E82),999),IFERROR(FIND("（",$E82),999))-1))=P$1,$F82,"")) | ... BU82: =IF(OR($E82="",BU$1=""),"",IF(TRIM(LEFT($E82,MIN(IFERROR(FIND("CDU",UPPER($E82)),999),IFERROR(FIND("BULK",UPPER($E82)),999),IFERROR(FIND("-",$E82),999),IFERROR(FIND("（",$E82),999))-1))=BU$1,$F82,"")) | BV82: 1.27 | BW82: =SUM(I82:BU82)*BV82 -> 1981.2 | BX82: =BW82*7.75 -> 15354.3 | BY82: =MID(E82,1,2) -> JS
A83: 45999 | B83: 46052 | C83: PK2025-3599 | D83: PO0000050-PHPP | E83: SR102CDU-24 | F83: 6120 | G83: 第二代美文版 | H83: =IFERROR(VLOOKUP(E83,名称!A:E,4,0),"") -> 二代 | I83: =IF(OR($E83="",I$1=""),"",IF(TRIM(LEFT($E83,MIN(IFERROR(FIND("CDU",UPPER($E83)),999),IFERROR(FIND("BULK",UPPER($E83)),999),IFERROR(FIND("-",$E83),999),IFERROR(FIND("（",$E83),999))-1))=I$1,$F83,"")) | J83: =IF(OR($E83="",J$1=""),"",IF(TRIM(LEFT($E83,MIN(IFERROR(FIND("CDU",UPPER($E83)),999),IFERROR(FIND("BULK",UPPER($E83)),999),IFERROR(FIND("-",$E83),999),IFERROR(FIND("（",$E83),999))-1))=J$1,$F83,"")) | K83: =IF(OR($E83="",K$1=""),"",IF(TRIM(LEFT($E83,MIN(IFERROR(FIND("CDU",UPPER($E83)),999),IFERROR(FIND("BULK",UPPER($E83)),999),IFERROR(FIND("-",$E83),999),IFERROR(FIND("（",$E83),999))-1))=K$1,$F83,"")) -> 6120 | L83: =IF(OR($E83="",L$1=""),"",IF(TRIM(LEFT($E83,MIN(IFERROR(FIND("CDU",UPPER($E83)),999),IFERROR(FIND("BULK",UPPER($E83)),999),IFERROR(FIND("-",$E83),999),IFERROR(FIND("（",$E83),999))-1))=L$1,$F83,"")) | M83: =IF(OR($E83="",M$1=""),"",IF(TRIM(LEFT($E83,MIN(IFERROR(FIND("CDU",UPPER($E83)),999),IFERROR(FIND("BULK",UPPER($E83)),999),IFERROR(FIND("-",$E83),999),IFERROR(FIND("（",$E83),999))-1))=M$1,$F83,"")) | N83: =IF(OR($E83="",N$1=""),"",IF(TRIM(LEFT($E83,MIN(IFERROR(FIND("CDU",UPPER($E83)),999),IFERROR(FIND("BULK",UPPER($E83)),999),IFERROR(FIND("-",$E83),999),IFERROR(FIND("（",$E83),999))-1))=N$1,$F83,"")) | O83: =IF(OR($E83="",O$1=""),"",IF(TRIM(LEFT($E83,MIN(IFERROR(FIND("CDU",UPPER($E83)),999),IFERROR(FIND("BULK",UPPER($E83)),999),IFERROR(FIND("-",$E83),999),IFERROR(FIND("（",$E83),999))-1))=O$1,$F83,"")) | P83: =IF(OR($E83="",P$1=""),"",IF(TRIM(LEFT($E83,MIN(IFERROR(FIND("CDU",UPPER($E83)),999),IFERROR(FIND("BULK",UPPER($E83)),999),IFERROR(FIND("-",$E83),999),IFERROR(FIND("（",$E83),999))-1))=P$1,$F83,"")) | ... BU83: =IF(OR($E83="",BU$1=""),"",IF(TRIM(LEFT($E83,MIN(IFERROR(FIND("CDU",UPPER($E83)),999),IFERROR(FIND("BULK",UPPER($E83)),999),IFERROR(FIND("-",$E83),999),IFERROR(FIND("（",$E83),999))-1))=BU$1,$F83,"")) | BV83: 0.87 | BW83: =SUM(I83:BU83)*BV83 -> 5324.4 | BX83: =BW83*7.75 -> 41264.1 | BY83: =MID(E83,1,2) -> SR
A84: 45999 | B84: 46052 | C84: PK2025-3599 | D84: PO0000050-PHPP | E84: SR103CDU-24 | F84: 6120 | G84: 第二代美文版 | H84: =IFERROR(VLOOKUP(E84,名称!A:E,4,0),"") -> 二代 | I84: =IF(OR($E84="",I$1=""),"",IF(TRIM(LEFT($E84,MIN(IFERROR(FIND("CDU",UPPER($E84)),999),IFERROR(FIND("BULK",UPPER($E84)),999),IFERROR(FIND("-",$E84),999),IFERROR(FIND("（",$E84),999))-1))=I$1,$F84,"")) | J84: =IF(OR($E84="",J$1=""),"",IF(TRIM(LEFT($E84,MIN(IFERROR(FIND("CDU",UPPER($E84)),999),IFERROR(FIND("BULK",UPPER($E84)),999),IFERROR(FIND("-",$E84),999),IFERROR(FIND("（",$E84),999))-1))=J$1,$F84,"")) | K84: =IF(OR($E84="",K$1=""),"",IF(TRIM(LEFT($E84,MIN(IFERROR(FIND("CDU",UPPER($E84)),999),IFERROR(FIND("BULK",UPPER($E84)),999),IFERROR(FIND("-",$E84),999),IFERROR(FIND("（",$E84),999))-1))=K$1,$F84,"")) | L84: =IF(OR($E84="",L$1=""),"",IF(TRIM(LEFT($E84,MIN(IFERROR(FIND("CDU",UPPER($E84)),999),IFERROR(FIND("BULK",UPPER($E84)),999),IFERROR(FIND("-",$E84),999),IFERROR(FIND("（",$E84),999))-1))=L$1,$F84,"")) | M84: =IF(OR($E84="",M$1=""),"",IF(TRIM(LEFT($E84,MIN(IFERROR(FIND("CDU",UPPER($E84)),999),IFERROR(FIND("BULK",UPPER($E84)),999),IFERROR(FIND("-",$E84),999),IFERROR(FIND("（",$E84),999))-1))=M$1,$F84,"")) -> 6120 | N84: =IF(OR($E84="",N$1=""),"",IF(TRIM(LEFT($E84,MIN(IFERROR(FIND("CDU",UPPER($E84)),999),IFERROR(FIND("BULK",UPPER($E84)),999),IFERROR(FIND("-",$E84),999),IFERROR(FIND("（",$E84),999))-1))=N$1,$F84,"")) | O84: =IF(OR($E84="",O$1=""),"",IF(TRIM(LEFT($E84,MIN(IFERROR(FIND("CDU",UPPER($E84)),999),IFERROR(FIND("BULK",UPPER($E84)),999),IFERROR(FIND("-",$E84),999),IFERROR(FIND("（",$E84),999))-1))=O$1,$F84,"")) | P84: =IF(OR($E84="",P$1=""),"",IF(TRIM(LEFT($E84,MIN(IFERROR(FIND("CDU",UPPER($E84)),999),IFERROR(FIND("BULK",UPPER($E84)),999),IFERROR(FIND("-",$E84),999),IFERROR(FIND("（",$E84),999))-1))=P$1,$F84,"")) | ... BU84: =IF(OR($E84="",BU$1=""),"",IF(TRIM(LEFT($E84,MIN(IFERROR(FIND("CDU",UPPER($E84)),999),IFERROR(FIND("BULK",UPPER($E84)),999),IFERROR(FIND("-",$E84),999),IFERROR(FIND("（",$E84),999))-1))=BU$1,$F84,"")) | BV84: 0.63 | BW84: =SUM(I84:BU84)*BV84 -> 3855.6 | BX84: =BW84*7.75 -> 29880.9 | BY84: =MID(E84,1,2) -> SR
A85: 45999 | B85: 46052 | C85: PK2025-3599 | D85: PO0000050-PHPP | E85: SR301 | F85: 1320 | G85: 第二代美文版 | H85: =IFERROR(VLOOKUP(E85,名称!A:E,4,0),"") -> 二代 | I85: =IF(OR($E85="",I$1=""),"",IF(TRIM(LEFT($E85,MIN(IFERROR(FIND("CDU",UPPER($E85)),999),IFERROR(FIND("BULK",UPPER($E85)),999),IFERROR(FIND("-",$E85),999),IFERROR(FIND("（",$E85),999))-1))=I$1,$F85,"")) | J85: =IF(OR($E85="",J$1=""),"",IF(TRIM(LEFT($E85,MIN(IFERROR(FIND("CDU",UPPER($E85)),999),IFERROR(FIND("BULK",UPPER($E85)),999),IFERROR(FIND("-",$E85),999),IFERROR(FIND("（",$E85),999))-1))=J$1,$F85,"")) | K85: =IF(OR($E85="",K$1=""),"",IF(TRIM(LEFT($E85,MIN(IFERROR(FIND("CDU",UPPER($E85)),999),IFERROR(FIND("BULK",UPPER($E85)),999),IFERROR(FIND("-",$E85),999),IFERROR(FIND("（",$E85),999))-1))=K$1,$F85,"")) | L85: =IF(OR($E85="",L$1=""),"",IF(TRIM(LEFT($E85,MIN(IFERROR(FIND("CDU",UPPER($E85)),999),IFERROR(FIND("BULK",UPPER($E85)),999),IFERROR(FIND("-",$E85),999),IFERROR(FIND("（",$E85),999))-1))=L$1,$F85,"")) | M85: =IF(OR($E85="",M$1=""),"",IF(TRIM(LEFT($E85,MIN(IFERROR(FIND("CDU",UPPER($E85)),999),IFERROR(FIND("BULK",UPPER($E85)),999),IFERROR(FIND("-",$E85),999),IFERROR(FIND("（",$E85),999))-1))=M$1,$F85,"")) | N85: =IF(OR($E85="",N$1=""),"",IF(TRIM(LEFT($E85,MIN(IFERROR(FIND("CDU",UPPER($E85)),999),IFERROR(FIND("BULK",UPPER($E85)),999),IFERROR(FIND("-",$E85),999),IFERROR(FIND("（",$E85),999))-1))=N$1,$F85,"")) | O85: =IF(OR($E85="",O$1=""),"",IF(TRIM(LEFT($E85,MIN(IFERROR(FIND("CDU",UPPER($E85)),999),IFERROR(FIND("BULK",UPPER($E85)),999),IFERROR(FIND("-",$E85),999),IFERROR(FIND("（",$E85),999))-1))=O$1,$F85,"")) | P85: =IF(OR($E85="",P$1=""),"",IF(TRIM(LEFT($E85,MIN(IFERROR(FIND("CDU",UPPER($E85)),999),IFERROR(FIND("BULK",UPPER($E85)),999),IFERROR(FIND("-",$E85),999),IFERROR(FIND("（",$E85),999))-1))=P$1,$F85,"")) | ... BU85: =IF(OR($E85="",BU$1=""),"",IF(TRIM(LEFT($E85,MIN(IFERROR(FIND("CDU",UPPER($E85)),999),IFERROR(FIND("BULK",UPPER($E85)),999),IFERROR(FIND("-",$E85),999),IFERROR(FIND("（",$E85),999))-1))=BU$1,$F85,"")) | BV85: 3.12 | BW85: =SUM(I85:BU85)*BV85 -> 4118.4 | BX85: =BW85*7.75 -> 31917.6 | BY85: =MID(E85,1,2) -> SR
A86: 45999 | B86: 46052 | C86: PK2025-3599 | D86: PO0000050-PHPP | E86: SR400 | F86: 840 | G86: 第二代美文版 | H86: =IFERROR(VLOOKUP(E86,名称!A:E,4,0),"") -> 二代 | I86: =IF(OR($E86="",I$1=""),"",IF(TRIM(LEFT($E86,MIN(IFERROR(FIND("CDU",UPPER($E86)),999),IFERROR(FIND("BULK",UPPER($E86)),999),IFERROR(FIND("-",$E86),999),IFERROR(FIND("（",$E86),999))-1))=I$1,$F86,"")) | J86: =IF(OR($E86="",J$1=""),"",IF(TRIM(LEFT($E86,MIN(IFERROR(FIND("CDU",UPPER($E86)),999),IFERROR(FIND("BULK",UPPER($E86)),999),IFERROR(FIND("-",$E86),999),IFERROR(FIND("（",$E86),999))-1))=J$1,$F86,"")) | K86: =IF(OR($E86="",K$1=""),"",IF(TRIM(LEFT($E86,MIN(IFERROR(FIND("CDU",UPPER($E86)),999),IFERROR(FIND("BULK",UPPER($E86)),999),IFERROR(FIND("-",$E86),999),IFERROR(FIND("（",$E86),999))-1))=K$1,$F86,"")) | L86: =IF(OR($E86="",L$1=""),"",IF(TRIM(LEFT($E86,MIN(IFERROR(FIND("CDU",UPPER($E86)),999),IFERROR(FIND("BULK",UPPER($E86)),999),IFERROR(FIND("-",$E86),999),IFERROR(FIND("（",$E86),999))-1))=L$1,$F86,"")) | M86: =IF(OR($E86="",M$1=""),"",IF(TRIM(LEFT($E86,MIN(IFERROR(FIND("CDU",UPPER($E86)),999),IFERROR(FIND("BULK",UPPER($E86)),999),IFERROR(FIND("-",$E86),999),IFERROR(FIND("（",$E86),999))-1))=M$1,$F86,"")) | N86: =IF(OR($E86="",N$1=""),"",IF(TRIM(LEFT($E86,MIN(IFERROR(FIND("CDU",UPPER($E86)),999),IFERROR(FIND("BULK",UPPER($E86)),999),IFERROR(FIND("-",$E86),999),IFERROR(FIND("（",$E86),999))-1))=N$1,$F86,"")) | O86: =IF(OR($E86="",O$1=""),"",IF(TRIM(LEFT($E86,MIN(IFERROR(FIND("CDU",UPPER($E86)),999),IFERROR(FIND("BULK",UPPER($E86)),999),IFERROR(FIND("-",$E86),999),IFERROR(FIND("（",$E86),999))-1))=O$1,$F86,"")) | P86: =IF(OR($E86="",P$1=""),"",IF(TRIM(LEFT($E86,MIN(IFERROR(FIND("CDU",UPPER($E86)),999),IFERROR(FIND("BULK",UPPER($E86)),999),IFERROR(FIND("-",$E86),999),IFERROR(FIND("（",$E86),999))-1))=P$1,$F86,"")) | ... BU86: =IF(OR($E86="",BU$1=""),"",IF(TRIM(LEFT($E86,MIN(IFERROR(FIND("CDU",UPPER($E86)),999),IFERROR(FIND("BULK",UPPER($E86)),999),IFERROR(FIND("-",$E86),999),IFERROR(FIND("（",$E86),999))-1))=BU$1,$F86,"")) | BV86: 1.49 | BW86: =SUM(I86:BU86)*BV86 -> 1251.6 | BX86: =BW86*7.75 -> 9699.9 | BY86: =MID(E86,1,2) -> SR
A87: 45999 | B87: 46052 | C87: PK2025-3599 | D87: PO0000050-PHPP | E87: SR430 | F87: 1284 | G87: 第二代美文版 | H87: =IFERROR(VLOOKUP(E87,名称!A:E,4,0),"") -> 二代 | I87: =IF(OR($E87="",I$1=""),"",IF(TRIM(LEFT($E87,MIN(IFERROR(FIND("CDU",UPPER($E87)),999),IFERROR(FIND("BULK",UPPER($E87)),999),IFERROR(FIND("-",$E87),999),IFERROR(FIND("（",$E87),999))-1))=I$1,$F87,"")) | J87: =IF(OR($E87="",J$1=""),"",IF(TRIM(LEFT($E87,MIN(IFERROR(FIND("CDU",UPPER($E87)),999),IFERROR(FIND("BULK",UPPER($E87)),999),IFERROR(FIND("-",$E87),999),IFERROR(FIND("（",$E87),999))-1))=J$1,$F87,"")) | K87: =IF(OR($E87="",K$1=""),"",IF(TRIM(LEFT($E87,MIN(IFERROR(FIND("CDU",UPPER($E87)),999),IFERROR(FIND("BULK",UPPER($E87)),999),IFERROR(FIND("-",$E87),999),IFERROR(FIND("（",$E87),999))-1))=K$1,$F87,"")) | L87: =IF(OR($E87="",L$1=""),"",IF(TRIM(LEFT($E87,MIN(IFERROR(FIND("CDU",UPPER($E87)),999),IFERROR(FIND("BULK",UPPER($E87)),999),IFERROR(FIND("-",$E87),999),IFERROR(FIND("（",$E87),999))-1))=L$1,$F87,"")) | M87: =IF(OR($E87="",M$1=""),"",IF(TRIM(LEFT($E87,MIN(IFERROR(FIND("CDU",UPPER($E87)),999),IFERROR(FIND("BULK",UPPER($E87)),999),IFERROR(FIND("-",$E87),999),IFERROR(FIND("（",$E87),999))-1))=M$1,$F87,"")) | N87: =IF(OR($E87="",N$1=""),"",IF(TRIM(LEFT($E87,MIN(IFERROR(FIND("CDU",UPPER($E87)),999),IFERROR(FIND("BULK",UPPER($E87)),999),IFERROR(FIND("-",$E87),999),IFERROR(FIND("（",$E87),999))-1))=N$1,$F87,"")) | O87: =IF(OR($E87="",O$1=""),"",IF(TRIM(LEFT($E87,MIN(IFERROR(FIND("CDU",UPPER($E87)),999),IFERROR(FIND("BULK",UPPER($E87)),999),IFERROR(FIND("-",$E87),999),IFERROR(FIND("（",$E87),999))-1))=O$1,$F87,"")) | P87: =IF(OR($E87="",P$1=""),"",IF(TRIM(LEFT($E87,MIN(IFERROR(FIND("CDU",UPPER($E87)),999),IFERROR(FIND("BULK",UPPER($E87)),999),IFERROR(FIND("-",$E87),999),IFERROR(FIND("（",$E87),999))-1))=P$1,$F87,"")) | ... BU87: =IF(OR($E87="",BU$1=""),"",IF(TRIM(LEFT($E87,MIN(IFERROR(FIND("CDU",UPPER($E87)),999),IFERROR(FIND("BULK",UPPER($E87)),999),IFERROR(FIND("-",$E87),999),IFERROR(FIND("（",$E87),999))-1))=BU$1,$F87,"")) | BV87: 1.49 | BW87: =SUM(I87:BU87)*BV87 -> 1913.16 | BX87: =BW87*7.75 -> 14826.99 | BY87: =MID(E87,1,2) -> SR
A88: 46000 | B88: 46053 | C88: 21011533 | D88: PO0000053-AUBA | E88: SR301 | F88: =3840+160 -> 4000 | G88: 第二代美文版 | H88: =IFERROR(VLOOKUP(E88,名称!A:E,4,0),"") -> 二代 | I88: =IF(OR($E88="",I$1=""),"",IF(TRIM(LEFT($E88,MIN(IFERROR(FIND("CDU",UPPER($E88)),999),IFERROR(FIND("BULK",UPPER($E88)),999),IFERROR(FIND("-",$E88),999),IFERROR(FIND("（",$E88),999))-1))=I$1,$F88,"")) | J88: =IF(OR($E88="",J$1=""),"",IF(TRIM(LEFT($E88,MIN(IFERROR(FIND("CDU",UPPER($E88)),999),IFERROR(FIND("BULK",UPPER($E88)),999),IFERROR(FIND("-",$E88),999),IFERROR(FIND("（",$E88),999))-1))=J$1,$F88,"")) | K88: =IF(OR($E88="",K$1=""),"",IF(TRIM(LEFT($E88,MIN(IFERROR(FIND("CDU",UPPER($E88)),999),IFERROR(FIND("BULK",UPPER($E88)),999),IFERROR(FIND("-",$E88),999),IFERROR(FIND("（",$E88),999))-1))=K$1,$F88,"")) | L88: =IF(OR($E88="",L$1=""),"",IF(TRIM(LEFT($E88,MIN(IFERROR(FIND("CDU",UPPER($E88)),999),IFERROR(FIND("BULK",UPPER($E88)),999),IFERROR(FIND("-",$E88),999),IFERROR(FIND("（",$E88),999))-1))=L$1,$F88,"")) | M88: =IF(OR($E88="",M$1=""),"",IF(TRIM(LEFT($E88,MIN(IFERROR(FIND("CDU",UPPER($E88)),999),IFERROR(FIND("BULK",UPPER($E88)),999),IFERROR(FIND("-",$E88),999),IFERROR(FIND("（",$E88),999))-1))=M$1,$F88,"")) | N88: =IF(OR($E88="",N$1=""),"",IF(TRIM(LEFT($E88,MIN(IFERROR(FIND("CDU",UPPER($E88)),999),IFERROR(FIND("BULK",UPPER($E88)),999),IFERROR(FIND("-",$E88),999),IFERROR(FIND("（",$E88),999))-1))=N$1,$F88,"")) | O88: =IF(OR($E88="",O$1=""),"",IF(TRIM(LEFT($E88,MIN(IFERROR(FIND("CDU",UPPER($E88)),999),IFERROR(FIND("BULK",UPPER($E88)),999),IFERROR(FIND("-",$E88),999),IFERROR(FIND("（",$E88),999))-1))=O$1,$F88,"")) | P88: =IF(OR($E88="",P$1=""),"",IF(TRIM(LEFT($E88,MIN(IFERROR(FIND("CDU",UPPER($E88)),999),IFERROR(FIND("BULK",UPPER($E88)),999),IFERROR(FIND("-",$E88),999),IFERROR(FIND("（",$E88),999))-1))=P$1,$F88,"")) | ... BU88: =IF(OR($E88="",BU$1=""),"",IF(TRIM(LEFT($E88,MIN(IFERROR(FIND("CDU",UPPER($E88)),999),IFERROR(FIND("BULK",UPPER($E88)),999),IFERROR(FIND("-",$E88),999),IFERROR(FIND("（",$E88),999))-1))=BU$1,$F88,"")) | BV88: 3.23 | BW88: =SUM(I88:BU88)*BV88 -> 12920 | BX88: =BW88*7.75 -> 100130 | BY88: =MID(E88,1,2) -> SR
A89: 46000 | B89: 46053 | C89: 21011533 | D89: PO0000053-AUBA | E89: JS100CDU-24 | F89: 12000 | G89: 第二代美文版 | H89: =IFERROR(VLOOKUP(E89,名称!A:E,4,0),"") -> 二代 | I89: =IF(OR($E89="",I$1=""),"",IF(TRIM(LEFT($E89,MIN(IFERROR(FIND("CDU",UPPER($E89)),999),IFERROR(FIND("BULK",UPPER($E89)),999),IFERROR(FIND("-",$E89),999),IFERROR(FIND("（",$E89),999))-1))=I$1,$F89,"")) | J89: =IF(OR($E89="",J$1=""),"",IF(TRIM(LEFT($E89,MIN(IFERROR(FIND("CDU",UPPER($E89)),999),IFERROR(FIND("BULK",UPPER($E89)),999),IFERROR(FIND("-",$E89),999),IFERROR(FIND("（",$E89),999))-1))=J$1,$F89,"")) | K89: =IF(OR($E89="",K$1=""),"",IF(TRIM(LEFT($E89,MIN(IFERROR(FIND("CDU",UPPER($E89)),999),IFERROR(FIND("BULK",UPPER($E89)),999),IFERROR(FIND("-",$E89),999),IFERROR(FIND("（",$E89),999))-1))=K$1,$F89,"")) | L89: =IF(OR($E89="",L$1=""),"",IF(TRIM(LEFT($E89,MIN(IFERROR(FIND("CDU",UPPER($E89)),999),IFERROR(FIND("BULK",UPPER($E89)),999),IFERROR(FIND("-",$E89),999),IFERROR(FIND("（",$E89),999))-1))=L$1,$F89,"")) | M89: =IF(OR($E89="",M$1=""),"",IF(TRIM(LEFT($E89,MIN(IFERROR(FIND("CDU",UPPER($E89)),999),IFERROR(FIND("BULK",UPPER($E89)),999),IFERROR(FIND("-",$E89),999),IFERROR(FIND("（",$E89),999))-1))=M$1,$F89,"")) | N89: =IF(OR($E89="",N$1=""),"",IF(TRIM(LEFT($E89,MIN(IFERROR(FIND("CDU",UPPER($E89)),999),IFERROR(FIND("BULK",UPPER($E89)),999),IFERROR(FIND("-",$E89),999),IFERROR(FIND("（",$E89),999))-1))=N$1,$F89,"")) | O89: =IF(OR($E89="",O$1=""),"",IF(TRIM(LEFT($E89,MIN(IFERROR(FIND("CDU",UPPER($E89)),999),IFERROR(FIND("BULK",UPPER($E89)),999),IFERROR(FIND("-",$E89),999),IFERROR(FIND("（",$E89),999))-1))=O$1,$F89,"")) | P89: =IF(OR($E89="",P$1=""),"",IF(TRIM(LEFT($E89,MIN(IFERROR(FIND("CDU",UPPER($E89)),999),IFERROR(FIND("BULK",UPPER($E89)),999),IFERROR(FIND("-",$E89),999),IFERROR(FIND("（",$E89),999))-1))=P$1,$F89,"")) | ... BU89: =IF(OR($E89="",BU$1=""),"",IF(TRIM(LEFT($E89,MIN(IFERROR(FIND("CDU",UPPER($E89)),999),IFERROR(FIND("BULK",UPPER($E89)),999),IFERROR(FIND("-",$E89),999),IFERROR(FIND("（",$E89),999))-1))=BU$1,$F89,"")) | BV89: 0.64 | BW89: =SUM(I89:BU89)*BV89 -> 7680 | BX89: =BW89*7.75 -> 59520 | BY89: =MID(E89,1,2) -> JS
A90: 46000 | B90: 46053 | C90: 21011533 | D90: PO0000053-AUBA | E90: SR102CDU-24 | F90: 8016 | G90: 第二代美文版 | H90: =IFERROR(VLOOKUP(E90,名称!A:E,4,0),"") -> 二代 | I90: =IF(OR($E90="",I$1=""),"",IF(TRIM(LEFT($E90,MIN(IFERROR(FIND("CDU",UPPER($E90)),999),IFERROR(FIND("BULK",UPPER($E90)),999),IFERROR(FIND("-",$E90),999),IFERROR(FIND("（",$E90),999))-1))=I$1,$F90,"")) | J90: =IF(OR($E90="",J$1=""),"",IF(TRIM(LEFT($E90,MIN(IFERROR(FIND("CDU",UPPER($E90)),999),IFERROR(FIND("BULK",UPPER($E90)),999),IFERROR(FIND("-",$E90),999),IFERROR(FIND("（",$E90),999))-1))=J$1,$F90,"")) | K90: =IF(OR($E90="",K$1=""),"",IF(TRIM(LEFT($E90,MIN(IFERROR(FIND("CDU",UPPER($E90)),999),IFERROR(FIND("BULK",UPPER($E90)),999),IFERROR(FIND("-",$E90),999),IFERROR(FIND("（",$E90),999))-1))=K$1,$F90,"")) -> 8016 | L90: =IF(OR($E90="",L$1=""),"",IF(TRIM(LEFT($E90,MIN(IFERROR(FIND("CDU",UPPER($E90)),999),IFERROR(FIND("BULK",UPPER($E90)),999),IFERROR(FIND("-",$E90),999),IFERROR(FIND("（",$E90),999))-1))=L$1,$F90,"")) | M90: =IF(OR($E90="",M$1=""),"",IF(TRIM(LEFT($E90,MIN(IFERROR(FIND("CDU",UPPER($E90)),999),IFERROR(FIND("BULK",UPPER($E90)),999),IFERROR(FIND("-",$E90),999),IFERROR(FIND("（",$E90),999))-1))=M$1,$F90,"")) | N90: =IF(OR($E90="",N$1=""),"",IF(TRIM(LEFT($E90,MIN(IFERROR(FIND("CDU",UPPER($E90)),999),IFERROR(FIND("BULK",UPPER($E90)),999),IFERROR(FIND("-",$E90),999),IFERROR(FIND("（",$E90),999))-1))=N$1,$F90,"")) | O90: =IF(OR($E90="",O$1=""),"",IF(TRIM(LEFT($E90,MIN(IFERROR(FIND("CDU",UPPER($E90)),999),IFERROR(FIND("BULK",UPPER($E90)),999),IFERROR(FIND("-",$E90),999),IFERROR(FIND("（",$E90),999))-1))=O$1,$F90,"")) | P90: =IF(OR($E90="",P$1=""),"",IF(TRIM(LEFT($E90,MIN(IFERROR(FIND("CDU",UPPER($E90)),999),IFERROR(FIND("BULK",UPPER($E90)),999),IFERROR(FIND("-",$E90),999),IFERROR(FIND("（",$E90),999))-1))=P$1,$F90,"")) | ... BU90: =IF(OR($E90="",BU$1=""),"",IF(TRIM(LEFT($E90,MIN(IFERROR(FIND("CDU",UPPER($E90)),999),IFERROR(FIND("BULK",UPPER($E90)),999),IFERROR(FIND("-",$E90),999),IFERROR(FIND("（",$E90),999))-1))=BU$1,$F90,"")) | BV90: 0.9 | BW90: =SUM(I90:BU90)*BV90 -> 7214.4 | BX90: =BW90*7.75 -> 55911.6 | BY90: =MID(E90,1,2) -> SR
A91: 46002 | B91: 46055 | D91: PO0000054-VNVT | E91: SR301 | F91: 660 | G91: 第二代美文版 | H91: =IFERROR(VLOOKUP(E91,名称!A:E,4,0),"") -> 二代 | I91: =IF(OR($E91="",I$1=""),"",IF(TRIM(LEFT($E91,MIN(IFERROR(FIND("CDU",UPPER($E91)),999),IFERROR(FIND("BULK",UPPER($E91)),999),IFERROR(FIND("-",$E91),999),IFERROR(FIND("（",$E91),999))-1))=I$1,$F91,"")) | J91: =IF(OR($E91="",J$1=""),"",IF(TRIM(LEFT($E91,MIN(IFERROR(FIND("CDU",UPPER($E91)),999),IFERROR(FIND("BULK",UPPER($E91)),999),IFERROR(FIND("-",$E91),999),IFERROR(FIND("（",$E91),999))-1))=J$1,$F91,"")) | K91: =IF(OR($E91="",K$1=""),"",IF(TRIM(LEFT($E91,MIN(IFERROR(FIND("CDU",UPPER($E91)),999),IFERROR(FIND("BULK",UPPER($E91)),999),IFERROR(FIND("-",$E91),999),IFERROR(FIND("（",$E91),999))-1))=K$1,$F91,"")) | L91: =IF(OR($E91="",L$1=""),"",IF(TRIM(LEFT($E91,MIN(IFERROR(FIND("CDU",UPPER($E91)),999),IFERROR(FIND("BULK",UPPER($E91)),999),IFERROR(FIND("-",$E91),999),IFERROR(FIND("（",$E91),999))-1))=L$1,$F91,"")) | M91: =IF(OR($E91="",M$1=""),"",IF(TRIM(LEFT($E91,MIN(IFERROR(FIND("CDU",UPPER($E91)),999),IFERROR(FIND("BULK",UPPER($E91)),999),IFERROR(FIND("-",$E91),999),IFERROR(FIND("（",$E91),999))-1))=M$1,$F91,"")) | N91: =IF(OR($E91="",N$1=""),"",IF(TRIM(LEFT($E91,MIN(IFERROR(FIND("CDU",UPPER($E91)),999),IFERROR(FIND("BULK",UPPER($E91)),999),IFERROR(FIND("-",$E91),999),IFERROR(FIND("（",$E91),999))-1))=N$1,$F91,"")) | O91: =IF(OR($E91="",O$1=""),"",IF(TRIM(LEFT($E91,MIN(IFERROR(FIND("CDU",UPPER($E91)),999),IFERROR(FIND("BULK",UPPER($E91)),999),IFERROR(FIND("-",$E91),999),IFERROR(FIND("（",$E91),999))-1))=O$1,$F91,"")) | P91: =IF(OR($E91="",P$1=""),"",IF(TRIM(LEFT($E91,MIN(IFERROR(FIND("CDU",UPPER($E91)),999),IFERROR(FIND("BULK",UPPER($E91)),999),IFERROR(FIND("-",$E91),999),IFERROR(FIND("（",$E91),999))-1))=P$1,$F91,"")) | ... BU91: =IF(OR($E91="",BU$1=""),"",IF(TRIM(LEFT($E91,MIN(IFERROR(FIND("CDU",UPPER($E91)),999),IFERROR(FIND("BULK",UPPER($E91)),999),IFERROR(FIND("-",$E91),999),IFERROR(FIND("（",$E91),999))-1))=BU$1,$F91,"")) | BV91: 3.23 | BW91: =SUM(I91:BU91)*BV91 -> 2131.8 | BX91: =BW91*7.75 -> 16521.45 | BY91: =MID(E91,1,2) -> SR
A92: 46002 | B92: 46055 | D92: PO0000054-VNVT | E92: SR201 | F92: 720 | G92: 第二代美文版 | H92: =IFERROR(VLOOKUP(E92,名称!A:E,4,0),"") -> 二代 | I92: =IF(OR($E92="",I$1=""),"",IF(TRIM(LEFT($E92,MIN(IFERROR(FIND("CDU",UPPER($E92)),999),IFERROR(FIND("BULK",UPPER($E92)),999),IFERROR(FIND("-",$E92),999),IFERROR(FIND("（",$E92),999))-1))=I$1,$F92,"")) | J92: =IF(OR($E92="",J$1=""),"",IF(TRIM(LEFT($E92,MIN(IFERROR(FIND("CDU",UPPER($E92)),999),IFERROR(FIND("BULK",UPPER($E92)),999),IFERROR(FIND("-",$E92),999),IFERROR(FIND("（",$E92),999))-1))=J$1,$F92,"")) | K92: =IF(OR($E92="",K$1=""),"",IF(TRIM(LEFT($E92,MIN(IFERROR(FIND("CDU",UPPER($E92)),999),IFERROR(FIND("BULK",UPPER($E92)),999),IFERROR(FIND("-",$E92),999),IFERROR(FIND("（",$E92),999))-1))=K$1,$F92,"")) | L92: =IF(OR($E92="",L$1=""),"",IF(TRIM(LEFT($E92,MIN(IFERROR(FIND("CDU",UPPER($E92)),999),IFERROR(FIND("BULK",UPPER($E92)),999),IFERROR(FIND("-",$E92),999),IFERROR(FIND("（",$E92),999))-1))=L$1,$F92,"")) | M92: =IF(OR($E92="",M$1=""),"",IF(TRIM(LEFT($E92,MIN(IFERROR(FIND("CDU",UPPER($E92)),999),IFERROR(FIND("BULK",UPPER($E92)),999),IFERROR(FIND("-",$E92),999),IFERROR(FIND("（",$E92),999))-1))=M$1,$F92,"")) | N92: =IF(OR($E92="",N$1=""),"",IF(TRIM(LEFT($E92,MIN(IFERROR(FIND("CDU",UPPER($E92)),999),IFERROR(FIND("BULK",UPPER($E92)),999),IFERROR(FIND("-",$E92),999),IFERROR(FIND("（",$E92),999))-1))=N$1,$F92,"")) | O92: =IF(OR($E92="",O$1=""),"",IF(TRIM(LEFT($E92,MIN(IFERROR(FIND("CDU",UPPER($E92)),999),IFERROR(FIND("BULK",UPPER($E92)),999),IFERROR(FIND("-",$E92),999),IFERROR(FIND("（",$E92),999))-1))=O$1,$F92,"")) | P92: =IF(OR($E92="",P$1=""),"",IF(TRIM(LEFT($E92,MIN(IFERROR(FIND("CDU",UPPER($E92)),999),IFERROR(FIND("BULK",UPPER($E92)),999),IFERROR(FIND("-",$E92),999),IFERROR(FIND("（",$E92),999))-1))=P$1,$F92,"")) | ... BU92: =IF(OR($E92="",BU$1=""),"",IF(TRIM(LEFT($E92,MIN(IFERROR(FIND("CDU",UPPER($E92)),999),IFERROR(FIND("BULK",UPPER($E92)),999),IFERROR(FIND("-",$E92),999),IFERROR(FIND("（",$E92),999))-1))=BU$1,$F92,"")) | BV92: 2.09 | BW92: =SUM(I92:BU92)*BV92 -> 1504.8 | BX92: =BW92*7.75 -> 11662.2 | BY92: =MID(E92,1,2) -> SR
A93: 46002 | B93: 46055 | D93: PO0000054-VNVT | E93: SR181CDU-24 | F93: 3240 | G93: 第二代美文版 | H93: =IFERROR(VLOOKUP(E93,名称!A:E,4,0),"") -> 二代 | I93: =IF(OR($E93="",I$1=""),"",IF(TRIM(LEFT($E93,MIN(IFERROR(FIND("CDU",UPPER($E93)),999),IFERROR(FIND("BULK",UPPER($E93)),999),IFERROR(FIND("-",$E93),999),IFERROR(FIND("（",$E93),999))-1))=I$1,$F93,"")) | J93: =IF(OR($E93="",J$1=""),"",IF(TRIM(LEFT($E93,MIN(IFERROR(FIND("CDU",UPPER($E93)),999),IFERROR(FIND("BULK",UPPER($E93)),999),IFERROR(FIND("-",$E93),999),IFERROR(FIND("（",$E93),999))-1))=J$1,$F93,"")) | K93: =IF(OR($E93="",K$1=""),"",IF(TRIM(LEFT($E93,MIN(IFERROR(FIND("CDU",UPPER($E93)),999),IFERROR(FIND("BULK",UPPER($E93)),999),IFERROR(FIND("-",$E93),999),IFERROR(FIND("（",$E93),999))-1))=K$1,$F93,"")) | L93: =IF(OR($E93="",L$1=""),"",IF(TRIM(LEFT($E93,MIN(IFERROR(FIND("CDU",UPPER($E93)),999),IFERROR(FIND("BULK",UPPER($E93)),999),IFERROR(FIND("-",$E93),999),IFERROR(FIND("（",$E93),999))-1))=L$1,$F93,"")) | M93: =IF(OR($E93="",M$1=""),"",IF(TRIM(LEFT($E93,MIN(IFERROR(FIND("CDU",UPPER($E93)),999),IFERROR(FIND("BULK",UPPER($E93)),999),IFERROR(FIND("-",$E93),999),IFERROR(FIND("（",$E93),999))-1))=M$1,$F93,"")) | N93: =IF(OR($E93="",N$1=""),"",IF(TRIM(LEFT($E93,MIN(IFERROR(FIND("CDU",UPPER($E93)),999),IFERROR(FIND("BULK",UPPER($E93)),999),IFERROR(FIND("-",$E93),999),IFERROR(FIND("（",$E93),999))-1))=N$1,$F93,"")) | O93: =IF(OR($E93="",O$1=""),"",IF(TRIM(LEFT($E93,MIN(IFERROR(FIND("CDU",UPPER($E93)),999),IFERROR(FIND("BULK",UPPER($E93)),999),IFERROR(FIND("-",$E93),999),IFERROR(FIND("（",$E93),999))-1))=O$1,$F93,"")) | P93: =IF(OR($E93="",P$1=""),"",IF(TRIM(LEFT($E93,MIN(IFERROR(FIND("CDU",UPPER($E93)),999),IFERROR(FIND("BULK",UPPER($E93)),999),IFERROR(FIND("-",$E93),999),IFERROR(FIND("（",$E93),999))-1))=P$1,$F93,"")) | ... BU93: =IF(OR($E93="",BU$1=""),"",IF(TRIM(LEFT($E93,MIN(IFERROR(FIND("CDU",UPPER($E93)),999),IFERROR(FIND("BULK",UPPER($E93)),999),IFERROR(FIND("-",$E93),999),IFERROR(FIND("（",$E93),999))-1))=BU$1,$F93,"")) | BV93: 0.65 | BW93: =SUM(I93:BU93)*BV93 -> 2106 | BX93: =BW93*7.75 -> 16321.5 | BY93: =MID(E93,1,2) -> SR
A94: 46003 | B94: 46052 | C94: PR250252-01 (KO-3629) | D94: PO0000064-NOPR | E94: SR301 | F94: 1500 | G94: 第二代美文版 | H94: =IFERROR(VLOOKUP(E94,名称!A:E,4,0),"") -> 二代 | I94: =IF(OR($E94="",I$1=""),"",IF(TRIM(LEFT($E94,MIN(IFERROR(FIND("CDU",UPPER($E94)),999),IFERROR(FIND("BULK",UPPER($E94)),999),IFERROR(FIND("-",$E94),999),IFERROR(FIND("（",$E94),999))-1))=I$1,$F94,"")) | J94: =IF(OR($E94="",J$1=""),"",IF(TRIM(LEFT($E94,MIN(IFERROR(FIND("CDU",UPPER($E94)),999),IFERROR(FIND("BULK",UPPER($E94)),999),IFERROR(FIND("-",$E94),999),IFERROR(FIND("（",$E94),999))-1))=J$1,$F94,"")) | K94: =IF(OR($E94="",K$1=""),"",IF(TRIM(LEFT($E94,MIN(IFERROR(FIND("CDU",UPPER($E94)),999),IFERROR(FIND("BULK",UPPER($E94)),999),IFERROR(FIND("-",$E94),999),IFERROR(FIND("（",$E94),999))-1))=K$1,$F94,"")) | L94: =IF(OR($E94="",L$1=""),"",IF(TRIM(LEFT($E94,MIN(IFERROR(FIND("CDU",UPPER($E94)),999),IFERROR(FIND("BULK",UPPER($E94)),999),IFERROR(FIND("-",$E94),999),IFERROR(FIND("（",$E94),999))-1))=L$1,$F94,"")) | M94: =IF(OR($E94="",M$1=""),"",IF(TRIM(LEFT($E94,MIN(IFERROR(FIND("CDU",UPPER($E94)),999),IFERROR(FIND("BULK",UPPER($E94)),999),IFERROR(FIND("-",$E94),999),IFERROR(FIND("（",$E94),999))-1))=M$1,$F94,"")) | N94: =IF(OR($E94="",N$1=""),"",IF(TRIM(LEFT($E94,MIN(IFERROR(FIND("CDU",UPPER($E94)),999),IFERROR(FIND("BULK",UPPER($E94)),999),IFERROR(FIND("-",$E94),999),IFERROR(FIND("（",$E94),999))-1))=N$1,$F94,"")) | O94: =IF(OR($E94="",O$1=""),"",IF(TRIM(LEFT($E94,MIN(IFERROR(FIND("CDU",UPPER($E94)),999),IFERROR(FIND("BULK",UPPER($E94)),999),IFERROR(FIND("-",$E94),999),IFERROR(FIND("（",$E94),999))-1))=O$1,$F94,"")) | P94: =IF(OR($E94="",P$1=""),"",IF(TRIM(LEFT($E94,MIN(IFERROR(FIND("CDU",UPPER($E94)),999),IFERROR(FIND("BULK",UPPER($E94)),999),IFERROR(FIND("-",$E94),999),IFERROR(FIND("（",$E94),999))-1))=P$1,$F94,"")) | ... BU94: =IF(OR($E94="",BU$1=""),"",IF(TRIM(LEFT($E94,MIN(IFERROR(FIND("CDU",UPPER($E94)),999),IFERROR(FIND("BULK",UPPER($E94)),999),IFERROR(FIND("-",$E94),999),IFERROR(FIND("（",$E94),999))-1))=BU$1,$F94,"")) | BV94: 3.23 | BW94: =SUM(I94:BU94)*BV94 -> 4845 | BX94: =BW94*7.75 -> 37548.75 | BY94: =MID(E94,1,2) -> SR
A95: 46003 | B95: 46052 | C95: PR250252-01 (KO-3629) | D95: PO0000064-NOPR | E95: SR201 | F95: 2004 | G95: 第二代美文版 | H95: =IFERROR(VLOOKUP(E95,名称!A:E,4,0),"") -> 二代 | I95: =IF(OR($E95="",I$1=""),"",IF(TRIM(LEFT($E95,MIN(IFERROR(FIND("CDU",UPPER($E95)),999),IFERROR(FIND("BULK",UPPER($E95)),999),IFERROR(FIND("-",$E95),999),IFERROR(FIND("（",$E95),999))-1))=I$1,$F95,"")) | J95: =IF(OR($E95="",J$1=""),"",IF(TRIM(LEFT($E95,MIN(IFERROR(FIND("CDU",UPPER($E95)),999),IFERROR(FIND("BULK",UPPER($E95)),999),IFERROR(FIND("-",$E95),999),IFERROR(FIND("（",$E95),999))-1))=J$1,$F95,"")) | K95: =IF(OR($E95="",K$1=""),"",IF(TRIM(LEFT($E95,MIN(IFERROR(FIND("CDU",UPPER($E95)),999),IFERROR(FIND("BULK",UPPER($E95)),999),IFERROR(FIND("-",$E95),999),IFERROR(FIND("（",$E95),999))-1))=K$1,$F95,"")) | L95: =IF(OR($E95="",L$1=""),"",IF(TRIM(LEFT($E95,MIN(IFERROR(FIND("CDU",UPPER($E95)),999),IFERROR(FIND("BULK",UPPER($E95)),999),IFERROR(FIND("-",$E95),999),IFERROR(FIND("（",$E95),999))-1))=L$1,$F95,"")) | M95: =IF(OR($E95="",M$1=""),"",IF(TRIM(LEFT($E95,MIN(IFERROR(FIND("CDU",UPPER($E95)),999),IFERROR(FIND("BULK",UPPER($E95)),999),IFERROR(FIND("-",$E95),999),IFERROR(FIND("（",$E95),999))-1))=M$1,$F95,"")) | N95: =IF(OR($E95="",N$1=""),"",IF(TRIM(LEFT($E95,MIN(IFERROR(FIND("CDU",UPPER($E95)),999),IFERROR(FIND("BULK",UPPER($E95)),999),IFERROR(FIND("-",$E95),999),IFERROR(FIND("（",$E95),999))-1))=N$1,$F95,"")) | O95: =IF(OR($E95="",O$1=""),"",IF(TRIM(LEFT($E95,MIN(IFERROR(FIND("CDU",UPPER($E95)),999),IFERROR(FIND("BULK",UPPER($E95)),999),IFERROR(FIND("-",$E95),999),IFERROR(FIND("（",$E95),999))-1))=O$1,$F95,"")) | P95: =IF(OR($E95="",P$1=""),"",IF(TRIM(LEFT($E95,MIN(IFERROR(FIND("CDU",UPPER($E95)),999),IFERROR(FIND("BULK",UPPER($E95)),999),IFERROR(FIND("-",$E95),999),IFERROR(FIND("（",$E95),999))-1))=P$1,$F95,"")) | ... BU95: =IF(OR($E95="",BU$1=""),"",IF(TRIM(LEFT($E95,MIN(IFERROR(FIND("CDU",UPPER($E95)),999),IFERROR(FIND("BULK",UPPER($E95)),999),IFERROR(FIND("-",$E95),999),IFERROR(FIND("（",$E95),999))-1))=BU$1,$F95,"")) | BV95: 2.09 | BW95: =SUM(I95:BU95)*BV95 -> 4188.36 | BX95: =BW95*7.75 -> 32459.79 | BY95: =MID(E95,1,2) -> SR
A96: 46003 | B96: 46052 | C96: PR250252-01 (KO-3629) | D96: PO0000064-NOPR | E96: SR160CDU-24 | F96: 3000 | G96: 第二代美文版 | H96: =IFERROR(VLOOKUP(E96,名称!A:E,4,0),"") -> 二代 | I96: =IF(OR($E96="",I$1=""),"",IF(TRIM(LEFT($E96,MIN(IFERROR(FIND("CDU",UPPER($E96)),999),IFERROR(FIND("BULK",UPPER($E96)),999),IFERROR(FIND("-",$E96),999),IFERROR(FIND("（",$E96),999))-1))=I$1,$F96,"")) | J96: =IF(OR($E96="",J$1=""),"",IF(TRIM(LEFT($E96,MIN(IFERROR(FIND("CDU",UPPER($E96)),999),IFERROR(FIND("BULK",UPPER($E96)),999),IFERROR(FIND("-",$E96),999),IFERROR(FIND("（",$E96),999))-1))=J$1,$F96,"")) | K96: =IF(OR($E96="",K$1=""),"",IF(TRIM(LEFT($E96,MIN(IFERROR(FIND("CDU",UPPER($E96)),999),IFERROR(FIND("BULK",UPPER($E96)),999),IFERROR(FIND("-",$E96),999),IFERROR(FIND("（",$E96),999))-1))=K$1,$F96,"")) | L96: =IF(OR($E96="",L$1=""),"",IF(TRIM(LEFT($E96,MIN(IFERROR(FIND("CDU",UPPER($E96)),999),IFERROR(FIND("BULK",UPPER($E96)),999),IFERROR(FIND("-",$E96),999),IFERROR(FIND("（",$E96),999))-1))=L$1,$F96,"")) | M96: =IF(OR($E96="",M$1=""),"",IF(TRIM(LEFT($E96,MIN(IFERROR(FIND("CDU",UPPER($E96)),999),IFERROR(FIND("BULK",UPPER($E96)),999),IFERROR(FIND("-",$E96),999),IFERROR(FIND("（",$E96),999))-1))=M$1,$F96,"")) | N96: =IF(OR($E96="",N$1=""),"",IF(TRIM(LEFT($E96,MIN(IFERROR(FIND("CDU",UPPER($E96)),999),IFERROR(FIND("BULK",UPPER($E96)),999),IFERROR(FIND("-",$E96),999),IFERROR(FIND("（",$E96),999))-1))=N$1,$F96,"")) | O96: =IF(OR($E96="",O$1=""),"",IF(TRIM(LEFT($E96,MIN(IFERROR(FIND("CDU",UPPER($E96)),999),IFERROR(FIND("BULK",UPPER($E96)),999),IFERROR(FIND("-",$E96),999),IFERROR(FIND("（",$E96),999))-1))=O$1,$F96,"")) -> 3000 | P96: =IF(OR($E96="",P$1=""),"",IF(TRIM(LEFT($E96,MIN(IFERROR(FIND("CDU",UPPER($E96)),999),IFERROR(FIND("BULK",UPPER($E96)),999),IFERROR(FIND("-",$E96),999),IFERROR(FIND("（",$E96),999))-1))=P$1,$F96,"")) | ... BU96: =IF(OR($E96="",BU$1=""),"",IF(TRIM(LEFT($E96,MIN(IFERROR(FIND("CDU",UPPER($E96)),999),IFERROR(FIND("BULK",UPPER($E96)),999),IFERROR(FIND("-",$E96),999),IFERROR(FIND("（",$E96),999))-1))=BU$1,$F96,"")) | BV96: 0.65 | BW96: =SUM(I96:BU96)*BV96 -> 1950 | BX96: =BW96*7.75 -> 15112.5 | BY96: =MID(E96,1,2) -> SR
A97: 46003 | B97: 46052 | C97: PR250252-01 (KO-3629) | D97: PO0000064-NOPR | E97: SR103CDU-24 | F97: 4008 | G97: 第二代美文版 | H97: =IFERROR(VLOOKUP(E97,名称!A:E,4,0),"") -> 二代 | I97: =IF(OR($E97="",I$1=""),"",IF(TRIM(LEFT($E97,MIN(IFERROR(FIND("CDU",UPPER($E97)),999),IFERROR(FIND("BULK",UPPER($E97)),999),IFERROR(FIND("-",$E97),999),IFERROR(FIND("（",$E97),999))-1))=I$1,$F97,"")) | J97: =IF(OR($E97="",J$1=""),"",IF(TRIM(LEFT($E97,MIN(IFERROR(FIND("CDU",UPPER($E97)),999),IFERROR(FIND("BULK",UPPER($E97)),999),IFERROR(FIND("-",$E97),999),IFERROR(FIND("（",$E97),999))-1))=J$1,$F97,"")) | K97: =IF(OR($E97="",K$1=""),"",IF(TRIM(LEFT($E97,MIN(IFERROR(FIND("CDU",UPPER($E97)),999),IFERROR(FIND("BULK",UPPER($E97)),999),IFERROR(FIND("-",$E97),999),IFERROR(FIND("（",$E97),999))-1))=K$1,$F97,"")) | L97: =IF(OR($E97="",L$1=""),"",IF(TRIM(LEFT($E97,MIN(IFERROR(FIND("CDU",UPPER($E97)),999),IFERROR(FIND("BULK",UPPER($E97)),999),IFERROR(FIND("-",$E97),999),IFERROR(FIND("（",$E97),999))-1))=L$1,$F97,"")) | M97: =IF(OR($E97="",M$1=""),"",IF(TRIM(LEFT($E97,MIN(IFERROR(FIND("CDU",UPPER($E97)),999),IFERROR(FIND("BULK",UPPER($E97)),999),IFERROR(FIND("-",$E97),999),IFERROR(FIND("（",$E97),999))-1))=M$1,$F97,"")) -> 4008 | N97: =IF(OR($E97="",N$1=""),"",IF(TRIM(LEFT($E97,MIN(IFERROR(FIND("CDU",UPPER($E97)),999),IFERROR(FIND("BULK",UPPER($E97)),999),IFERROR(FIND("-",$E97),999),IFERROR(FIND("（",$E97),999))-1))=N$1,$F97,"")) | O97: =IF(OR($E97="",O$1=""),"",IF(TRIM(LEFT($E97,MIN(IFERROR(FIND("CDU",UPPER($E97)),999),IFERROR(FIND("BULK",UPPER($E97)),999),IFERROR(FIND("-",$E97),999),IFERROR(FIND("（",$E97),999))-1))=O$1,$F97,"")) | P97: =IF(OR($E97="",P$1=""),"",IF(TRIM(LEFT($E97,MIN(IFERROR(FIND("CDU",UPPER($E97)),999),IFERROR(FIND("BULK",UPPER($E97)),999),IFERROR(FIND("-",$E97),999),IFERROR(FIND("（",$E97),999))-1))=P$1,$F97,"")) | ... BU97: =IF(OR($E97="",BU$1=""),"",IF(TRIM(LEFT($E97,MIN(IFERROR(FIND("CDU",UPPER($E97)),999),IFERROR(FIND("BULK",UPPER($E97)),999),IFERROR(FIND("-",$E97),999),IFERROR(FIND("（",$E97),999))-1))=BU$1,$F97,"")) | BV97: 0.65 | BW97: =SUM(I97:BU97)*BV97 -> 2605.2 | BX97: =BW97*7.75 -> 20190.3 | BY97: =MID(E97,1,2) -> SR
A98: 46003 | B98: 46052 | C98: PR250252-01 (KO-3629) | D98: PO0000064-NOPR | E98: SR102 | F98: 3000 | G98: 第二代美文版 | H98: =IFERROR(VLOOKUP(E98,名称!A:E,4,0),"") -> 二代 | I98: =IF(OR($E98="",I$1=""),"",IF(TRIM(LEFT($E98,MIN(IFERROR(FIND("CDU",UPPER($E98)),999),IFERROR(FIND("BULK",UPPER($E98)),999),IFERROR(FIND("-",$E98),999),IFERROR(FIND("（",$E98),999))-1))=I$1,$F98,"")) | J98: =IF(OR($E98="",J$1=""),"",IF(TRIM(LEFT($E98,MIN(IFERROR(FIND("CDU",UPPER($E98)),999),IFERROR(FIND("BULK",UPPER($E98)),999),IFERROR(FIND("-",$E98),999),IFERROR(FIND("（",$E98),999))-1))=J$1,$F98,"")) | K98: =IF(OR($E98="",K$1=""),"",IF(TRIM(LEFT($E98,MIN(IFERROR(FIND("CDU",UPPER($E98)),999),IFERROR(FIND("BULK",UPPER($E98)),999),IFERROR(FIND("-",$E98),999),IFERROR(FIND("（",$E98),999))-1))=K$1,$F98,"")) -> 3000 | L98: =IF(OR($E98="",L$1=""),"",IF(TRIM(LEFT($E98,MIN(IFERROR(FIND("CDU",UPPER($E98)),999),IFERROR(FIND("BULK",UPPER($E98)),999),IFERROR(FIND("-",$E98),999),IFERROR(FIND("（",$E98),999))-1))=L$1,$F98,"")) | M98: =IF(OR($E98="",M$1=""),"",IF(TRIM(LEFT($E98,MIN(IFERROR(FIND("CDU",UPPER($E98)),999),IFERROR(FIND("BULK",UPPER($E98)),999),IFERROR(FIND("-",$E98),999),IFERROR(FIND("（",$E98),999))-1))=M$1,$F98,"")) | N98: =IF(OR($E98="",N$1=""),"",IF(TRIM(LEFT($E98,MIN(IFERROR(FIND("CDU",UPPER($E98)),999),IFERROR(FIND("BULK",UPPER($E98)),999),IFERROR(FIND("-",$E98),999),IFERROR(FIND("（",$E98),999))-1))=N$1,$F98,"")) | O98: =IF(OR($E98="",O$1=""),"",IF(TRIM(LEFT($E98,MIN(IFERROR(FIND("CDU",UPPER($E98)),999),IFERROR(FIND("BULK",UPPER($E98)),999),IFERROR(FIND("-",$E98),999),IFERROR(FIND("（",$E98),999))-1))=O$1,$F98,"")) | P98: =IF(OR($E98="",P$1=""),"",IF(TRIM(LEFT($E98,MIN(IFERROR(FIND("CDU",UPPER($E98)),999),IFERROR(FIND("BULK",UPPER($E98)),999),IFERROR(FIND("-",$E98),999),IFERROR(FIND("（",$E98),999))-1))=P$1,$F98,"")) | ... BU98: =IF(OR($E98="",BU$1=""),"",IF(TRIM(LEFT($E98,MIN(IFERROR(FIND("CDU",UPPER($E98)),999),IFERROR(FIND("BULK",UPPER($E98)),999),IFERROR(FIND("-",$E98),999),IFERROR(FIND("（",$E98),999))-1))=BU$1,$F98,"")) | BV98: 0.79 | BW98: =SUM(I98:BU98)*BV98 -> 2370 | BX98: =BW98*7.75 -> 18367.5 | BY98: =MID(E98,1,2) -> SR
A99: 46009 | B99: 46052 | C99: PO-FK-DXB-211125 | D99: PO0000044-GCKL | E99: SR102 | F99: 2400 | G99: 第二代美文版 | H99: =IFERROR(VLOOKUP(E99,名称!A:E,4,0),"") -> 二代 | I99: =IF(OR($E99="",I$1=""),"",IF(TRIM(LEFT($E99,MIN(IFERROR(FIND("CDU",UPPER($E99)),999),IFERROR(FIND("BULK",UPPER($E99)),999),IFERROR(FIND("-",$E99),999),IFERROR(FIND("（",$E99),999))-1))=I$1,$F99,"")) | J99: =IF(OR($E99="",J$1=""),"",IF(TRIM(LEFT($E99,MIN(IFERROR(FIND("CDU",UPPER($E99)),999),IFERROR(FIND("BULK",UPPER($E99)),999),IFERROR(FIND("-",$E99),999),IFERROR(FIND("（",$E99),999))-1))=J$1,$F99,"")) | K99: =IF(OR($E99="",K$1=""),"",IF(TRIM(LEFT($E99,MIN(IFERROR(FIND("CDU",UPPER($E99)),999),IFERROR(FIND("BULK",UPPER($E99)),999),IFERROR(FIND("-",$E99),999),IFERROR(FIND("（",$E99),999))-1))=K$1,$F99,"")) -> 2400 | L99: =IF(OR($E99="",L$1=""),"",IF(TRIM(LEFT($E99,MIN(IFERROR(FIND("CDU",UPPER($E99)),999),IFERROR(FIND("BULK",UPPER($E99)),999),IFERROR(FIND("-",$E99),999),IFERROR(FIND("（",$E99),999))-1))=L$1,$F99,"")) | M99: =IF(OR($E99="",M$1=""),"",IF(TRIM(LEFT($E99,MIN(IFERROR(FIND("CDU",UPPER($E99)),999),IFERROR(FIND("BULK",UPPER($E99)),999),IFERROR(FIND("-",$E99),999),IFERROR(FIND("（",$E99),999))-1))=M$1,$F99,"")) | N99: =IF(OR($E99="",N$1=""),"",IF(TRIM(LEFT($E99,MIN(IFERROR(FIND("CDU",UPPER($E99)),999),IFERROR(FIND("BULK",UPPER($E99)),999),IFERROR(FIND("-",$E99),999),IFERROR(FIND("（",$E99),999))-1))=N$1,$F99,"")) | O99: =IF(OR($E99="",O$1=""),"",IF(TRIM(LEFT($E99,MIN(IFERROR(FIND("CDU",UPPER($E99)),999),IFERROR(FIND("BULK",UPPER($E99)),999),IFERROR(FIND("-",$E99),999),IFERROR(FIND("（",$E99),999))-1))=O$1,$F99,"")) | P99: =IF(OR($E99="",P$1=""),"",IF(TRIM(LEFT($E99,MIN(IFERROR(FIND("CDU",UPPER($E99)),999),IFERROR(FIND("BULK",UPPER($E99)),999),IFERROR(FIND("-",$E99),999),IFERROR(FIND("（",$E99),999))-1))=P$1,$F99,"")) | ... BU99: =IF(OR($E99="",BU$1=""),"",IF(TRIM(LEFT($E99,MIN(IFERROR(FIND("CDU",UPPER($E99)),999),IFERROR(FIND("BULK",UPPER($E99)),999),IFERROR(FIND("-",$E99),999),IFERROR(FIND("（",$E99),999))-1))=BU$1,$F99,"")) | BV99: 0.78 | BW99: =SUM(I99:BU99)*BV99 -> 1872 | BX99: =BW99*7.75 -> 14508 | BY99: =MID(E99,1,2) -> SR
A100: 46009 | B100: 46052 | C100: PO-FK-DXB-211125 | D100: PO0000044-GCKL | E100: SR103CDU-24 | F100: 1920 | G100: 第二代美文版 | H100: =IFERROR(VLOOKUP(E100,名称!A:E,4,0),"") -> 二代 | I100: =IF(OR($E100="",I$1=""),"",IF(TRIM(LEFT($E100,MIN(IFERROR(FIND("CDU",UPPER($E100)),999),IFERROR(FIND("BULK",UPPER($E100)),999),IFERROR(FIND("-",$E100),999),IFERROR(FIND("（",$E100),999))-1))=I$1,$F100,"")) | J100: =IF(OR($E100="",J$1=""),"",IF(TRIM(LEFT($E100,MIN(IFERROR(FIND("CDU",UPPER($E100)),999),IFERROR(FIND("BULK",UPPER($E100)),999),IFERROR(FIND("-",$E100),999),IFERROR(FIND("（",$E100),999))-1))=J$1,$F100,"")) | K100: =IF(OR($E100="",K$1=""),"",IF(TRIM(LEFT($E100,MIN(IFERROR(FIND("CDU",UPPER($E100)),999),IFERROR(FIND("BULK",UPPER($E100)),999),IFERROR(FIND("-",$E100),999),IFERROR(FIND("（",$E100),999))-1))=K$1,$F100,"")) | L100: =IF(OR($E100="",L$1=""),"",IF(TRIM(LEFT($E100,MIN(IFERROR(FIND("CDU",UPPER($E100)),999),IFERROR(FIND("BULK",UPPER($E100)),999),IFERROR(FIND("-",$E100),999),IFERROR(FIND("（",$E100),999))-1))=L$1,$F100,"")) | M100: =IF(OR($E100="",M$1=""),"",IF(TRIM(LEFT($E100,MIN(IFERROR(FIND("CDU",UPPER($E100)),999),IFERROR(FIND("BULK",UPPER($E100)),999),IFERROR(FIND("-",$E100),999),IFERROR(FIND("（",$E100),999))-1))=M$1,$F100,"")) -> 1920 | N100: =IF(OR($E100="",N$1=""),"",IF(TRIM(LEFT($E100,MIN(IFERROR(FIND("CDU",UPPER($E100)),999),IFERROR(FIND("BULK",UPPER($E100)),999),IFERROR(FIND("-",$E100),999),IFERROR(FIND("（",$E100),999))-1))=N$1,$F100,"")) | O100: =IF(OR($E100="",O$1=""),"",IF(TRIM(LEFT($E100,MIN(IFERROR(FIND("CDU",UPPER($E100)),999),IFERROR(FIND("BULK",UPPER($E100)),999),IFERROR(FIND("-",$E100),999),IFERROR(FIND("（",$E100),999))-1))=O$1,$F100,"")) | P100: =IF(OR($E100="",P$1=""),"",IF(TRIM(LEFT($E100,MIN(IFERROR(FIND("CDU",UPPER($E100)),999),IFERROR(FIND("BULK",UPPER($E100)),999),IFERROR(FIND("-",$E100),999),IFERROR(FIND("（",$E100),999))-1))=P$1,$F100,"")) | ... BU100: =IF(OR($E100="",BU$1=""),"",IF(TRIM(LEFT($E100,MIN(IFERROR(FIND("CDU",UPPER($E100)),999),IFERROR(FIND("BULK",UPPER($E100)),999),IFERROR(FIND("-",$E100),999),IFERROR(FIND("（",$E100),999))-1))=BU$1,$F100,"")) | BV100: 0.61 | BW100: =SUM(I100:BU100)*BV100 -> 1171.2 | BX100: =BW100*7.75 -> 9076.8 | BY100: =MID(E100,1,2) -> SR
A101: 46009 | B101: 46052 | C101: PO-FK-DXB-211125 | D101: PO0000044-GCKL | E101: SR201 | F101: 1440 | G101: 第二代美文版 | H101: =IFERROR(VLOOKUP(E101,名称!A:E,4,0),"") -> 二代 | I101: =IF(OR($E101="",I$1=""),"",IF(TRIM(LEFT($E101,MIN(IFERROR(FIND("CDU",UPPER($E101)),999),IFERROR(FIND("BULK",UPPER($E101)),999),IFERROR(FIND("-",$E101),999),IFERROR(FIND("（",$E101),999))-1))=I$1,$F101,"")) | J101: =IF(OR($E101="",J$1=""),"",IF(TRIM(LEFT($E101,MIN(IFERROR(FIND("CDU",UPPER($E101)),999),IFERROR(FIND("BULK",UPPER($E101)),999),IFERROR(FIND("-",$E101),999),IFERROR(FIND("（",$E101),999))-1))=J$1,$F101,"")) | K101: =IF(OR($E101="",K$1=""),"",IF(TRIM(LEFT($E101,MIN(IFERROR(FIND("CDU",UPPER($E101)),999),IFERROR(FIND("BULK",UPPER($E101)),999),IFERROR(FIND("-",$E101),999),IFERROR(FIND("（",$E101),999))-1))=K$1,$F101,"")) | L101: =IF(OR($E101="",L$1=""),"",IF(TRIM(LEFT($E101,MIN(IFERROR(FIND("CDU",UPPER($E101)),999),IFERROR(FIND("BULK",UPPER($E101)),999),IFERROR(FIND("-",$E101),999),IFERROR(FIND("（",$E101),999))-1))=L$1,$F101,"")) | M101: =IF(OR($E101="",M$1=""),"",IF(TRIM(LEFT($E101,MIN(IFERROR(FIND("CDU",UPPER($E101)),999),IFERROR(FIND("BULK",UPPER($E101)),999),IFERROR(FIND("-",$E101),999),IFERROR(FIND("（",$E101),999))-1))=M$1,$F101,"")) | N101: =IF(OR($E101="",N$1=""),"",IF(TRIM(LEFT($E101,MIN(IFERROR(FIND("CDU",UPPER($E101)),999),IFERROR(FIND("BULK",UPPER($E101)),999),IFERROR(FIND("-",$E101),999),IFERROR(FIND("（",$E101),999))-1))=N$1,$F101,"")) | O101: =IF(OR($E101="",O$1=""),"",IF(TRIM(LEFT($E101,MIN(IFERROR(FIND("CDU",UPPER($E101)),999),IFERROR(FIND("BULK",UPPER($E101)),999),IFERROR(FIND("-",$E101),999),IFERROR(FIND("（",$E101),999))-1))=O$1,$F101,"")) | P101: =IF(OR($E101="",P$1=""),"",IF(TRIM(LEFT($E101,MIN(IFERROR(FIND("CDU",UPPER($E101)),999),IFERROR(FIND("BULK",UPPER($E101)),999),IFERROR(FIND("-",$E101),999),IFERROR(FIND("（",$E101),999))-1))=P$1,$F101,"")) | ... BU101: =IF(OR($E101="",BU$1=""),"",IF(TRIM(LEFT($E101,MIN(IFERROR(FIND("CDU",UPPER($E101)),999),IFERROR(FIND("BULK",UPPER($E101)),999),IFERROR(FIND("-",$E101),999),IFERROR(FIND("（",$E101),999))-1))=BU$1,$F101,"")) | BV101: 2.02 | BW101: =SUM(I101:BU101)*BV101 -> 2908.8 | BX101: =BW101*7.75 -> 22543.2 | BY101: =MID(E101,1,2) -> SR
A102: 46009 | B102: 46052 | C102: PO-FK-DXB-211125 | D102: PO0000044-GCKL | E102: SR301 | F102: 1008 | G102: 第二代美文版 | H102: =IFERROR(VLOOKUP(E102,名称!A:E,4,0),"") -> 二代 | I102: =IF(OR($E102="",I$1=""),"",IF(TRIM(LEFT($E102,MIN(IFERROR(FIND("CDU",UPPER($E102)),999),IFERROR(FIND("BULK",UPPER($E102)),999),IFERROR(FIND("-",$E102),999),IFERROR(FIND("（",$E102),999))-1))=I$1,$F102,"")) | J102: =IF(OR($E102="",J$1=""),"",IF(TRIM(LEFT($E102,MIN(IFERROR(FIND("CDU",UPPER($E102)),999),IFERROR(FIND("BULK",UPPER($E102)),999),IFERROR(FIND("-",$E102),999),IFERROR(FIND("（",$E102),999))-1))=J$1,$F102,"")) | K102: =IF(OR($E102="",K$1=""),"",IF(TRIM(LEFT($E102,MIN(IFERROR(FIND("CDU",UPPER($E102)),999),IFERROR(FIND("BULK",UPPER($E102)),999),IFERROR(FIND("-",$E102),999),IFERROR(FIND("（",$E102),999))-1))=K$1,$F102,"")) | L102: =IF(OR($E102="",L$1=""),"",IF(TRIM(LEFT($E102,MIN(IFERROR(FIND("CDU",UPPER($E102)),999),IFERROR(FIND("BULK",UPPER($E102)),999),IFERROR(FIND("-",$E102),999),IFERROR(FIND("（",$E102),999))-1))=L$1,$F102,"")) | M102: =IF(OR($E102="",M$1=""),"",IF(TRIM(LEFT($E102,MIN(IFERROR(FIND("CDU",UPPER($E102)),999),IFERROR(FIND("BULK",UPPER($E102)),999),IFERROR(FIND("-",$E102),999),IFERROR(FIND("（",$E102),999))-1))=M$1,$F102,"")) | N102: =IF(OR($E102="",N$1=""),"",IF(TRIM(LEFT($E102,MIN(IFERROR(FIND("CDU",UPPER($E102)),999),IFERROR(FIND("BULK",UPPER($E102)),999),IFERROR(FIND("-",$E102),999),IFERROR(FIND("（",$E102),999))-1))=N$1,$F102,"")) | O102: =IF(OR($E102="",O$1=""),"",IF(TRIM(LEFT($E102,MIN(IFERROR(FIND("CDU",UPPER($E102)),999),IFERROR(FIND("BULK",UPPER($E102)),999),IFERROR(FIND("-",$E102),999),IFERROR(FIND("（",$E102),999))-1))=O$1,$F102,"")) | P102: =IF(OR($E102="",P$1=""),"",IF(TRIM(LEFT($E102,MIN(IFERROR(FIND("CDU",UPPER($E102)),999),IFERROR(FIND("BULK",UPPER($E102)),999),IFERROR(FIND("-",$E102),999),IFERROR(FIND("（",$E102),999))-1))=P$1,$F102,"")) | ... BU102: =IF(OR($E102="",BU$1=""),"",IF(TRIM(LEFT($E102,MIN(IFERROR(FIND("CDU",UPPER($E102)),999),IFERROR(FIND("BULK",UPPER($E102)),999),IFERROR(FIND("-",$E102),999),IFERROR(FIND("（",$E102),999))-1))=BU$1,$F102,"")) | BV102: 3.09 | BW102: =SUM(I102:BU102)*BV102 -> 3114.72 | BX102: =BW102*7.75 -> 24139.08 | BY102: =MID(E102,1,2) -> SR
A103: 46009 | B103: 46052 | C103: PO-FK-DXB-211125 | D103: PO0000044-GCKL | E103: SR181CDU-24 | F103: 2016 | G103: 第二代美文版 | H103: =IFERROR(VLOOKUP(E103,名称!A:E,4,0),"") -> 二代 | I103: =IF(OR($E103="",I$1=""),"",IF(TRIM(LEFT($E103,MIN(IFERROR(FIND("CDU",UPPER($E103)),999),IFERROR(FIND("BULK",UPPER($E103)),999),IFERROR(FIND("-",$E103),999),IFERROR(FIND("（",$E103),999))-1))=I$1,$F103,"")) | J103: =IF(OR($E103="",J$1=""),"",IF(TRIM(LEFT($E103,MIN(IFERROR(FIND("CDU",UPPER($E103)),999),IFERROR(FIND("BULK",UPPER($E103)),999),IFERROR(FIND("-",$E103),999),IFERROR(FIND("（",$E103),999))-1))=J$1,$F103,"")) | K103: =IF(OR($E103="",K$1=""),"",IF(TRIM(LEFT($E103,MIN(IFERROR(FIND("CDU",UPPER($E103)),999),IFERROR(FIND("BULK",UPPER($E103)),999),IFERROR(FIND("-",$E103),999),IFERROR(FIND("（",$E103),999))-1))=K$1,$F103,"")) | L103: =IF(OR($E103="",L$1=""),"",IF(TRIM(LEFT($E103,MIN(IFERROR(FIND("CDU",UPPER($E103)),999),IFERROR(FIND("BULK",UPPER($E103)),999),IFERROR(FIND("-",$E103),999),IFERROR(FIND("（",$E103),999))-1))=L$1,$F103,"")) | M103: =IF(OR($E103="",M$1=""),"",IF(TRIM(LEFT($E103,MIN(IFERROR(FIND("CDU",UPPER($E103)),999),IFERROR(FIND("BULK",UPPER($E103)),999),IFERROR(FIND("-",$E103),999),IFERROR(FIND("（",$E103),999))-1))=M$1,$F103,"")) | N103: =IF(OR($E103="",N$1=""),"",IF(TRIM(LEFT($E103,MIN(IFERROR(FIND("CDU",UPPER($E103)),999),IFERROR(FIND("BULK",UPPER($E103)),999),IFERROR(FIND("-",$E103),999),IFERROR(FIND("（",$E103),999))-1))=N$1,$F103,"")) | O103: =IF(OR($E103="",O$1=""),"",IF(TRIM(LEFT($E103,MIN(IFERROR(FIND("CDU",UPPER($E103)),999),IFERROR(FIND("BULK",UPPER($E103)),999),IFERROR(FIND("-",$E103),999),IFERROR(FIND("（",$E103),999))-1))=O$1,$F103,"")) | P103: =IF(OR($E103="",P$1=""),"",IF(TRIM(LEFT($E103,MIN(IFERROR(FIND("CDU",UPPER($E103)),999),IFERROR(FIND("BULK",UPPER($E103)),999),IFERROR(FIND("-",$E103),999),IFERROR(FIND("（",$E103),999))-1))=P$1,$F103,"")) | ... BU103: =IF(OR($E103="",BU$1=""),"",IF(TRIM(LEFT($E103,MIN(IFERROR(FIND("CDU",UPPER($E103)),999),IFERROR(FIND("BULK",UPPER($E103)),999),IFERROR(FIND("-",$E103),999),IFERROR(FIND("（",$E103),999))-1))=BU$1,$F103,"")) | BV103: 0.61 | BW103: =SUM(I103:BU103)*BV103 -> 1229.76 | BX103: =BW103*7.75 -> 9530.64 | BY103: =MID(E103,1,2) -> SR
A104: 46009 | B104: 46052 | C104: PO-FK-DXB-211125 | D104: PO0000044-GCKL | E104: SR180CDU-24 | F104: 2400 | G104: 第二代美文版 | H104: =IFERROR(VLOOKUP(E104,名称!A:E,4,0),"") -> 二代 | I104: =IF(OR($E104="",I$1=""),"",IF(TRIM(LEFT($E104,MIN(IFERROR(FIND("CDU",UPPER($E104)),999),IFERROR(FIND("BULK",UPPER($E104)),999),IFERROR(FIND("-",$E104),999),IFERROR(FIND("（",$E104),999))-1))=I$1,$F104,"")) | J104: =IF(OR($E104="",J$1=""),"",IF(TRIM(LEFT($E104,MIN(IFERROR(FIND("CDU",UPPER($E104)),999),IFERROR(FIND("BULK",UPPER($E104)),999),IFERROR(FIND("-",$E104),999),IFERROR(FIND("（",$E104),999))-1))=J$1,$F104,"")) | K104: =IF(OR($E104="",K$1=""),"",IF(TRIM(LEFT($E104,MIN(IFERROR(FIND("CDU",UPPER($E104)),999),IFERROR(FIND("BULK",UPPER($E104)),999),IFERROR(FIND("-",$E104),999),IFERROR(FIND("（",$E104),999))-1))=K$1,$F104,"")) | L104: =IF(OR($E104="",L$1=""),"",IF(TRIM(LEFT($E104,MIN(IFERROR(FIND("CDU",UPPER($E104)),999),IFERROR(FIND("BULK",UPPER($E104)),999),IFERROR(FIND("-",$E104),999),IFERROR(FIND("（",$E104),999))-1))=L$1,$F104,"")) | M104: =IF(OR($E104="",M$1=""),"",IF(TRIM(LEFT($E104,MIN(IFERROR(FIND("CDU",UPPER($E104)),999),IFERROR(FIND("BULK",UPPER($E104)),999),IFERROR(FIND("-",$E104),999),IFERROR(FIND("（",$E104),999))-1))=M$1,$F104,"")) | N104: =IF(OR($E104="",N$1=""),"",IF(TRIM(LEFT($E104,MIN(IFERROR(FIND("CDU",UPPER($E104)),999),IFERROR(FIND("BULK",UPPER($E104)),999),IFERROR(FIND("-",$E104),999),IFERROR(FIND("（",$E104),999))-1))=N$1,$F104,"")) | O104: =IF(OR($E104="",O$1=""),"",IF(TRIM(LEFT($E104,MIN(IFERROR(FIND("CDU",UPPER($E104)),999),IFERROR(FIND("BULK",UPPER($E104)),999),IFERROR(FIND("-",$E104),999),IFERROR(FIND("（",$E104),999))-1))=O$1,$F104,"")) | P104: =IF(OR($E104="",P$1=""),"",IF(TRIM(LEFT($E104,MIN(IFERROR(FIND("CDU",UPPER($E104)),999),IFERROR(FIND("BULK",UPPER($E104)),999),IFERROR(FIND("-",$E104),999),IFERROR(FIND("（",$E104),999))-1))=P$1,$F104,"")) -> 2400 | ... BU104: =IF(OR($E104="",BU$1=""),"",IF(TRIM(LEFT($E104,MIN(IFERROR(FIND("CDU",UPPER($E104)),999),IFERROR(FIND("BULK",UPPER($E104)),999),IFERROR(FIND("-",$E104),999),IFERROR(FIND("（",$E104),999))-1))=BU$1,$F104,"")) | BV104: 0.61 | BW104: =SUM(I104:BU104)*BV104 -> 1464 | BX104: =BW104*7.75 -> 11346 | BY104: =MID(E104,1,2) -> SR
A105: 46009 | B105: 46052 | C105: PO-FK-DXB-211125 | D105: PO0000044-GCKL | E105: SR160CDU-24 | F105: 2400 | G105: 第二代美文版 | H105: =IFERROR(VLOOKUP(E105,名称!A:E,4,0),"") -> 二代 | I105: =IF(OR($E105="",I$1=""),"",IF(TRIM(LEFT($E105,MIN(IFERROR(FIND("CDU",UPPER($E105)),999),IFERROR(FIND("BULK",UPPER($E105)),999),IFERROR(FIND("-",$E105),999),IFERROR(FIND("（",$E105),999))-1))=I$1,$F105,"")) | J105: =IF(OR($E105="",J$1=""),"",IF(TRIM(LEFT($E105,MIN(IFERROR(FIND("CDU",UPPER($E105)),999),IFERROR(FIND("BULK",UPPER($E105)),999),IFERROR(FIND("-",$E105),999),IFERROR(FIND("（",$E105),999))-1))=J$1,$F105,"")) | K105: =IF(OR($E105="",K$1=""),"",IF(TRIM(LEFT($E105,MIN(IFERROR(FIND("CDU",UPPER($E105)),999),IFERROR(FIND("BULK",UPPER($E105)),999),IFERROR(FIND("-",$E105),999),IFERROR(FIND("（",$E105),999))-1))=K$1,$F105,"")) | L105: =IF(OR($E105="",L$1=""),"",IF(TRIM(LEFT($E105,MIN(IFERROR(FIND("CDU",UPPER($E105)),999),IFERROR(FIND("BULK",UPPER($E105)),999),IFERROR(FIND("-",$E105),999),IFERROR(FIND("（",$E105),999))-1))=L$1,$F105,"")) | M105: =IF(OR($E105="",M$1=""),"",IF(TRIM(LEFT($E105,MIN(IFERROR(FIND("CDU",UPPER($E105)),999),IFERROR(FIND("BULK",UPPER($E105)),999),IFERROR(FIND("-",$E105),999),IFERROR(FIND("（",$E105),999))-1))=M$1,$F105,"")) | N105: =IF(OR($E105="",N$1=""),"",IF(TRIM(LEFT($E105,MIN(IFERROR(FIND("CDU",UPPER($E105)),999),IFERROR(FIND("BULK",UPPER($E105)),999),IFERROR(FIND("-",$E105),999),IFERROR(FIND("（",$E105),999))-1))=N$1,$F105,"")) | O105: =IF(OR($E105="",O$1=""),"",IF(TRIM(LEFT($E105,MIN(IFERROR(FIND("CDU",UPPER($E105)),999),IFERROR(FIND("BULK",UPPER($E105)),999),IFERROR(FIND("-",$E105),999),IFERROR(FIND("（",$E105),999))-1))=O$1,$F105,"")) -> 2400 | P105: =IF(OR($E105="",P$1=""),"",IF(TRIM(LEFT($E105,MIN(IFERROR(FIND("CDU",UPPER($E105)),999),IFERROR(FIND("BULK",UPPER($E105)),999),IFERROR(FIND("-",$E105),999),IFERROR(FIND("（",$E105),999))-1))=P$1,$F105,"")) | ... BU105: =IF(OR($E105="",BU$1=""),"",IF(TRIM(LEFT($E105,MIN(IFERROR(FIND("CDU",UPPER($E105)),999),IFERROR(FIND("BULK",UPPER($E105)),999),IFERROR(FIND("-",$E105),999),IFERROR(FIND("（",$E105),999))-1))=BU$1,$F105,"")) | BV105: 0.61 | BW105: =SUM(I105:BU105)*BV105 -> 1464 | BX105: =BW105*7.75 -> 11346 | BY105: =MID(E105,1,2) -> SR
... A107: 46009 | B107: 46052 | C107: PO-FK-DXB-211125 | D107: PO0000044-GCKL | E107: SR430CDU-12 | F107: 2400 | G107: 第二代美文版 | H107: =IFERROR(VLOOKUP(E107,名称!A:E,4,0),"") -> 二代 | I107: =IF(OR($E107="",I$1=""),"",IF(TRIM(LEFT($E107,MIN(IFERROR(FIND("CDU",UPPER($E107)),999),IFERROR(FIND("BULK",UPPER($E107)),999),IFERROR(FIND("-",$E107),999),IFERROR(FIND("（",$E107),999))-1))=I$1,$F107,"")) | J107: =IF(OR($E107="",J$1=""),"",IF(TRIM(LEFT($E107,MIN(IFERROR(FIND("CDU",UPPER($E107)),999),IFERROR(FIND("BULK",UPPER($E107)),999),IFERROR(FIND("-",$E107),999),IFERROR(FIND("（",$E107),999))-1))=J$1,$F107,"")) | K107: =IF(OR($E107="",K$1=""),"",IF(TRIM(LEFT($E107,MIN(IFERROR(FIND("CDU",UPPER($E107)),999),IFERROR(FIND("BULK",UPPER($E107)),999),IFERROR(FIND("-",$E107),999),IFERROR(FIND("（",$E107),999))-1))=K$1,$F107,"")) | L107: =IF(OR($E107="",L$1=""),"",IF(TRIM(LEFT($E107,MIN(IFERROR(FIND("CDU",UPPER($E107)),999),IFERROR(FIND("BULK",UPPER($E107)),999),IFERROR(FIND("-",$E107),999),IFERROR(FIND("（",$E107),999))-1))=L$1,$F107,"")) | M107: =IF(OR($E107="",M$1=""),"",IF(TRIM(LEFT($E107,MIN(IFERROR(FIND("CDU",UPPER($E107)),999),IFERROR(FIND("BULK",UPPER($E107)),999),IFERROR(FIND("-",$E107),999),IFERROR(FIND("（",$E107),999))-1))=M$1,$F107,"")) | N107: =IF(OR($E107="",N$1=""),"",IF(TRIM(LEFT($E107,MIN(IFERROR(FIND("CDU",UPPER($E107)),999),IFERROR(FIND("BULK",UPPER($E107)),999),IFERROR(FIND("-",$E107),999),IFERROR(FIND("（",$E107),999))-1))=N$1,$F107,"")) | O107: =IF(OR($E107="",O$1=""),"",IF(TRIM(LEFT($E107,MIN(IFERROR(FIND("CDU",UPPER($E107)),999),IFERROR(FIND("BULK",UPPER($E107)),999),IFERROR(FIND("-",$E107),999),IFERROR(FIND("（",$E107),999))-1))=O$1,$F107,"")) | P107: =IF(OR($E107="",P$1=""),"",IF(TRIM(LEFT($E107,MIN(IFERROR(FIND("CDU",UPPER($E107)),999),IFERROR(FIND("BULK",UPPER($E107)),999),IFERROR(FIND("-",$E107),999),IFERROR(FIND("（",$E107),999))-1))=P$1,$F107,"")) | ... BU107: =IF(OR($E107="",BU$1=""),"",IF(TRIM(LEFT($E107,MIN(IFERROR(FIND("CDU",UPPER($E107)),999),IFERROR(FIND("BULK",UPPER($E107)),999),IFERROR(FIND("-",$E107),999),IFERROR(FIND("（",$E107),999))-1))=BU$1,$F107,"")) | BV107: 1.58 | BW107: =SUM(I107:BU107)*BV107 -> 3792 | BX107: =BW107*7.75 -> 29388 | BY107: =MID(E107,1,2) -> SR
A108: 46011 | B108: 46036 | D108: PO-AUBA014 | E108: SR020 | F108: 27000 | G108: 第二代美文版 | H108: =IFERROR(VLOOKUP(E108,名称!A:E,4,0),"") -> 二代 | I108: =IF(OR($E108="",I$1=""),"",IF(TRIM(LEFT($E108,MIN(IFERROR(FIND("CDU",UPPER($E108)),999),IFERROR(FIND("BULK",UPPER($E108)),999),IFERROR(FIND("-",$E108),999),IFERROR(FIND("（",$E108),999))-1))=I$1,$F108,"")) | J108: =IF(OR($E108="",J$1=""),"",IF(TRIM(LEFT($E108,MIN(IFERROR(FIND("CDU",UPPER($E108)),999),IFERROR(FIND("BULK",UPPER($E108)),999),IFERROR(FIND("-",$E108),999),IFERROR(FIND("（",$E108),999))-1))=J$1,$F108,"")) -> 27000 | K108: =IF(OR($E108="",K$1=""),"",IF(TRIM(LEFT($E108,MIN(IFERROR(FIND("CDU",UPPER($E108)),999),IFERROR(FIND("BULK",UPPER($E108)),999),IFERROR(FIND("-",$E108),999),IFERROR(FIND("（",$E108),999))-1))=K$1,$F108,"")) | L108: =IF(OR($E108="",L$1=""),"",IF(TRIM(LEFT($E108,MIN(IFERROR(FIND("CDU",UPPER($E108)),999),IFERROR(FIND("BULK",UPPER($E108)),999),IFERROR(FIND("-",$E108),999),IFERROR(FIND("（",$E108),999))-1))=L$1,$F108,"")) | M108: =IF(OR($E108="",M$1=""),"",IF(TRIM(LEFT($E108,MIN(IFERROR(FIND("CDU",UPPER($E108)),999),IFERROR(FIND("BULK",UPPER($E108)),999),IFERROR(FIND("-",$E108),999),IFERROR(FIND("（",$E108),999))-1))=M$1,$F108,"")) | N108: =IF(OR($E108="",N$1=""),"",IF(TRIM(LEFT($E108,MIN(IFERROR(FIND("CDU",UPPER($E108)),999),IFERROR(FIND("BULK",UPPER($E108)),999),IFERROR(FIND("-",$E108),999),IFERROR(FIND("（",$E108),999))-1))=N$1,$F108,"")) | O108: =IF(OR($E108="",O$1=""),"",IF(TRIM(LEFT($E108,MIN(IFERROR(FIND("CDU",UPPER($E108)),999),IFERROR(FIND("BULK",UPPER($E108)),999),IFERROR(FIND("-",$E108),999),IFERROR(FIND("（",$E108),999))-1))=O$1,$F108,"")) | P108: =IF(OR($E108="",P$1=""),"",IF(TRIM(LEFT($E108,MIN(IFERROR(FIND("CDU",UPPER($E108)),999),IFERROR(FIND("BULK",UPPER($E108)),999),IFERROR(FIND("-",$E108),999),IFERROR(FIND("（",$E108),999))-1))=P$1,$F108,"")) | ... BU108: =IF(OR($E108="",BU$1=""),"",IF(TRIM(LEFT($E108,MIN(IFERROR(FIND("CDU",UPPER($E108)),999),IFERROR(FIND("BULK",UPPER($E108)),999),IFERROR(FIND("-",$E108),999),IFERROR(FIND("（",$E108),999))-1))=BU$1,$F108,"")) | BV108: 0.31 | BW108: =SUM(I108:BU108)*BV108 -> 8370 | BX108: =BW108*7.75 -> 64867.5 | BY108: =MID(E108,1,2) -> SR
A109: 46013 | B109: 46139 | C109: JAZ281815 | D109: PO0000066-USJZ | E109: SR103CDU-24 | F109: 2016 | G109: Jazwares客版（美文） | H109: =IFERROR(VLOOKUP(E109,名称!A:E,4,0),"") -> 二代 | I109: =IF(OR($E109="",I$1=""),"",IF(TRIM(LEFT($E109,MIN(IFERROR(FIND("CDU",UPPER($E109)),999),IFERROR(FIND("BULK",UPPER($E109)),999),IFERROR(FIND("-",$E109),999),IFERROR(FIND("（",$E109),999))-1))=I$1,$F109,"")) | J109: =IF(OR($E109="",J$1=""),"",IF(TRIM(LEFT($E109,MIN(IFERROR(FIND("CDU",UPPER($E109)),999),IFERROR(FIND("BULK",UPPER($E109)),999),IFERROR(FIND("-",$E109),999),IFERROR(FIND("（",$E109),999))-1))=J$1,$F109,"")) | K109: =IF(OR($E109="",K$1=""),"",IF(TRIM(LEFT($E109,MIN(IFERROR(FIND("CDU",UPPER($E109)),999),IFERROR(FIND("BULK",UPPER($E109)),999),IFERROR(FIND("-",$E109),999),IFERROR(FIND("（",$E109),999))-1))=K$1,$F109,"")) | L109: =IF(OR($E109="",L$1=""),"",IF(TRIM(LEFT($E109,MIN(IFERROR(FIND("CDU",UPPER($E109)),999),IFERROR(FIND("BULK",UPPER($E109)),999),IFERROR(FIND("-",$E109),999),IFERROR(FIND("（",$E109),999))-1))=L$1,$F109,"")) | M109: =IF(OR($E109="",M$1=""),"",IF(TRIM(LEFT($E109,MIN(IFERROR(FIND("CDU",UPPER($E109)),999),IFERROR(FIND("BULK",UPPER($E109)),999),IFERROR(FIND("-",$E109),999),IFERROR(FIND("（",$E109),999))-1))=M$1,$F109,"")) -> 2016 | N109: =IF(OR($E109="",N$1=""),"",IF(TRIM(LEFT($E109,MIN(IFERROR(FIND("CDU",UPPER($E109)),999),IFERROR(FIND("BULK",UPPER($E109)),999),IFERROR(FIND("-",$E109),999),IFERROR(FIND("（",$E109),999))-1))=N$1,$F109,"")) | O109: =IF(OR($E109="",O$1=""),"",IF(TRIM(LEFT($E109,MIN(IFERROR(FIND("CDU",UPPER($E109)),999),IFERROR(FIND("BULK",UPPER($E109)),999),IFERROR(FIND("-",$E109),999),IFERROR(FIND("（",$E109),999))-1))=O$1,$F109,"")) | P109: =IF(OR($E109="",P$1=""),"",IF(TRIM(LEFT($E109,MIN(IFERROR(FIND("CDU",UPPER($E109)),999),IFERROR(FIND("BULK",UPPER($E109)),999),IFERROR(FIND("-",$E109),999),IFERROR(FIND("（",$E109),999))-1))=P$1,$F109,"")) | ... BU109: =IF(OR($E109="",BU$1=""),"",IF(TRIM(LEFT($E109,MIN(IFERROR(FIND("CDU",UPPER($E109)),999),IFERROR(FIND("BULK",UPPER($E109)),999),IFERROR(FIND("-",$E109),999),IFERROR(FIND("（",$E109),999))-1))=BU$1,$F109,"")) | BV109: 0.61 | BW109: =SUM(I109:BU109)*BV109 -> 1229.76 | BX109: =BW109*7.75 -> 9530.64 | BY109: =MID(E109,1,2) -> SR
